Workbook

Sheet Dashboard
M1: =Settings!$C$5
B2: Batches and best before
B3: What to sell first, what to buy, and how much goes to waste.
B4: In stock | C4: Use soon | D4: Past its date | E4: Waste this month | G4: Made this month | H4: Cost of waste | I4: To buy | J4: Pantry going off
B5: =SUMIFS(Batches!$K$6:$K$505,Batches!$M$6:$M$505,"In stock")+SUMIFS(Batches!$K$6:$K$505,Batches!$M$6:$M$505,"Use soon") | C5: =SUMIFS(Batches!$K$6:$K$505,Batches!$M$6:$M$505,"Use soon") | D5: =SUMIFS(Batches!$K$6:$K$505,Batches!$M$6:$M$505,"Past its date") | E5: =IF(SUMIFS(Batches!$D$6:$D$505,Batches!$R$6:$R$505,(YEAR(TODAY())*100+MONTH(TODAY())))=0,"",SUMIFS(Batches!$G$6:$G$505,Batches!$R$6:$R$505,(YEAR(TODAY())*100+MONTH(TODAY())))/SUMIFS(Batches!$D$6:$D$505,Batches!$R$6:$R$505,(YEAR(TODAY())*100+MONTH(TODAY())))) | G5: =SUMIFS(Batches!$D$6:$D$505,Batches!$R$6:$R$505,(YEAR(TODAY())*100+MONTH(TODAY()))) | H5: =SUMIFS(Batches!$S$6:$S$505,Batches!$R$6:$R$505,(YEAR(TODAY())*100+MONTH(TODAY()))) | I5: =COUNTIF(Ingredients!$L$6:$L$105,"Buy more") | J5: =COUNTIF(Purchases!$K$6:$K$405,"Past its date")+COUNTIF(Purchases!$K$6:$K$405,"Use soon")
B7: Sell first | C7: Batch | D7: Left | E7: =Settings!$C$7 | G7: To buy | H7: Left | I7: Buy more at | J7: Unit
B8: =IF(N8="","",INDEX(Batches!$C$1:$C$505,MOD(N8,1000))) | C8: =IF(N8="","",INDEX(Batches!$I$1:$I$505,MOD(N8,1000))) | D8: =IF(N8="","",INDEX(Batches!$K$1:$K$505,MOD(N8,1000))) | E8: =IF(N8="","",INDEX(Batches!$J$1:$J$505,MOD(N8,1000))) | G8: =IF(O8="","",INDEX(Ingredients!$B$1:$B$105,O8)) | H8: =IF(O8="","",INDEX(Ingredients!$K$1:$K$105,O8)) | I8: =IF(O8="","",N(INDEX(Ingredients!$F$1:$F$105,O8))) | J8: =IF(O8="","",INDEX(Ingredients!$C$1:$C$105,O8)) | N8: =IFERROR(SMALL(Batches!$T$6:$T$505,1),"") | O8: =IFERROR(SMALL(Ingredients!$AR$6:$AR$105,1),"")
B9: =IF(N9="","",INDEX(Batches!$C$1:$C$505,MOD(N9,1000))) | C9: =IF(N9="","",INDEX(Batches!$I$1:$I$505,MOD(N9,1000))) | D9: =IF(N9="","",INDEX(Batches!$K$1:$K$505,MOD(N9,1000))) | E9: =IF(N9="","",INDEX(Batches!$J$1:$J$505,MOD(N9,1000))) | G9: =IF(O9="","",INDEX(Ingredients!$B$1:$B$105,O9)) | H9: =IF(O9="","",INDEX(Ingredients!$K$1:$K$105,O9)) | I9: =IF(O9="","",N(INDEX(Ingredients!$F$1:$F$105,O9))) | J9: =IF(O9="","",INDEX(Ingredients!$C$1:$C$105,O9)) | N9: =IFERROR(SMALL(Batches!$T$6:$T$505,2),"") | O9: =IFERROR(SMALL(Ingredients!$AR$6:$AR$105,2),"")
B10: =IF(N10="","",INDEX(Batches!$C$1:$C$505,MOD(N10,1000))) | C10: =IF(N10="","",INDEX(Batches!$I$1:$I$505,MOD(N10,1000))) | D10: =IF(N10="","",INDEX(Batches!$K$1:$K$505,MOD(N10,1000))) | E10: =IF(N10="","",INDEX(Batches!$J$1:$J$505,MOD(N10,1000))) | G10: =IF(O10="","",INDEX(Ingredients!$B$1:$B$105,O10)) | H10: =IF(O10="","",INDEX(Ingredients!$K$1:$K$105,O10)) | I10: =IF(O10="","",N(INDEX(Ingredients!$F$1:$F$105,O10))) | J10: =IF(O10="","",INDEX(Ingredients!$C$1:$C$105,O10)) | N10: =IFERROR(SMALL(Batches!$T$6:$T$505,3),"") | O10: =IFERROR(SMALL(Ingredients!$AR$6:$AR$105,3),"")
B11: =IF(N11="","",INDEX(Batches!$C$1:$C$505,MOD(N11,1000))) | C11: =IF(N11="","",INDEX(Batches!$I$1:$I$505,MOD(N11,1000))) | D11: =IF(N11="","",INDEX(Batches!$K$1:$K$505,MOD(N11,1000))) | E11: =IF(N11="","",INDEX(Batches!$J$1:$J$505,MOD(N11,1000))) | G11: =IF(O11="","",INDEX(Ingredients!$B$1:$B$105,O11)) | H11: =IF(O11="","",INDEX(Ingredients!$K$1:$K$105,O11)) | I11: =IF(O11="","",N(INDEX(Ingredients!$F$1:$F$105,O11))) | J11: =IF(O11="","",INDEX(Ingredients!$C$1:$C$105,O11)) | N11: =IFERROR(SMALL(Batches!$T$6:$T$505,4),"") | O11: =IFERROR(SMALL(Ingredients!$AR$6:$AR$105,4),"")
B12: =IF(N12="","",INDEX(Batches!$C$1:$C$505,MOD(N12,1000))) | C12: =IF(N12="","",INDEX(Batches!$I$1:$I$505,MOD(N12,1000))) | D12: =IF(N12="","",INDEX(Batches!$K$1:$K$505,MOD(N12,1000))) | E12: =IF(N12="","",INDEX(Batches!$J$1:$J$505,MOD(N12,1000))) | N12: =IFERROR(SMALL(Batches!$T$6:$T$505,5),"")
B13: =IF(N13="","",INDEX(Batches!$C$1:$C$505,MOD(N13,1000))) | C13: =IF(N13="","",INDEX(Batches!$I$1:$I$505,MOD(N13,1000))) | D13: =IF(N13="","",INDEX(Batches!$K$1:$K$505,MOD(N13,1000))) | E13: =IF(N13="","",INDEX(Batches!$J$1:$J$505,MOD(N13,1000))) | G13: Pantry | H13: Lot | I13: Date on pack | J13: Status | N13: =IFERROR(SMALL(Batches!$T$6:$T$505,6),"")
B14: =IF(N14="","",INDEX(Batches!$C$1:$C$505,MOD(N14,1000))) | C14: =IF(N14="","",INDEX(Batches!$I$1:$I$505,MOD(N14,1000))) | D14: =IF(N14="","",INDEX(Batches!$K$1:$K$505,MOD(N14,1000))) | E14: =IF(N14="","",INDEX(Batches!$J$1:$J$505,MOD(N14,1000))) | G14: =IF(O14="","",INDEX(Purchases!$C$1:$C$405,MOD(O14,1000))) | H14: =IF(O14="","",INDEX(Purchases!$G$1:$G$405,MOD(O14,1000))) | I14: =IF(O14="","",INDEX(Purchases!$H$1:$H$405,MOD(O14,1000))) | J14: =IF(O14="","",INDEX(Purchases!$K$1:$K$405,MOD(O14,1000))) | N14: =IFERROR(SMALL(Batches!$T$6:$T$505,7),"") | O14: =IFERROR(SMALL(Purchases!$L$6:$L$405,1),"")
B15: =IF(N15="","",INDEX(Batches!$C$1:$C$505,MOD(N15,1000))) | C15: =IF(N15="","",INDEX(Batches!$I$1:$I$505,MOD(N15,1000))) | D15: =IF(N15="","",INDEX(Batches!$K$1:$K$505,MOD(N15,1000))) | E15: =IF(N15="","",INDEX(Batches!$J$1:$J$505,MOD(N15,1000))) | G15: =IF(O15="","",INDEX(Purchases!$C$1:$C$405,MOD(O15,1000))) | H15: =IF(O15="","",INDEX(Purchases!$G$1:$G$405,MOD(O15,1000))) | I15: =IF(O15="","",INDEX(Purchases!$H$1:$H$405,MOD(O15,1000))) | J15: =IF(O15="","",INDEX(Purchases!$K$1:$K$405,MOD(O15,1000))) | N15: =IFERROR(SMALL(Batches!$T$6:$T$505,8),"") | O15: =IFERROR(SMALL(Purchases!$L$6:$L$405,2),"")
B16: =IF(N16="","",INDEX(Batches!$C$1:$C$505,MOD(N16,1000))) | C16: =IF(N16="","",INDEX(Batches!$I$1:$I$505,MOD(N16,1000))) | D16: =IF(N16="","",INDEX(Batches!$K$1:$K$505,MOD(N16,1000))) | E16: =IF(N16="","",INDEX(Batches!$J$1:$J$505,MOD(N16,1000))) | G16: =IF(O16="","",INDEX(Purchases!$C$1:$C$405,MOD(O16,1000))) | H16: =IF(O16="","",INDEX(Purchases!$G$1:$G$405,MOD(O16,1000))) | I16: =IF(O16="","",INDEX(Purchases!$H$1:$H$405,MOD(O16,1000))) | J16: =IF(O16="","",INDEX(Purchases!$K$1:$K$405,MOD(O16,1000))) | N16: =IFERROR(SMALL(Batches!$T$6:$T$505,9),"") | O16: =IFERROR(SMALL(Purchases!$L$6:$L$405,3),"")
B17: =IF(N17="","",INDEX(Batches!$C$1:$C$505,MOD(N17,1000))) | C17: =IF(N17="","",INDEX(Batches!$I$1:$I$505,MOD(N17,1000))) | D17: =IF(N17="","",INDEX(Batches!$K$1:$K$505,MOD(N17,1000))) | E17: =IF(N17="","",INDEX(Batches!$J$1:$J$505,MOD(N17,1000))) | G17: =IF(O17="","",INDEX(Purchases!$C$1:$C$405,MOD(O17,1000))) | H17: =IF(O17="","",INDEX(Purchases!$G$1:$G$405,MOD(O17,1000))) | I17: =IF(O17="","",INDEX(Purchases!$H$1:$H$405,MOD(O17,1000))) | J17: =IF(O17="","",INDEX(Purchases!$K$1:$K$405,MOD(O17,1000))) | N17: =IFERROR(SMALL(Batches!$T$6:$T$505,10),"") | O17: =IFERROR(SMALL(Purchases!$L$6:$L$405,4),"")
B19: Month made | C19: Made | D19: Wasted | E19: Waste
B20: =CHOOSE(MONTH(DATE(YEAR(TODAY()),MONTH(TODAY())-11,1)),"Jan","Feb","Mar","Apr","May","Jun","Jul","Aug","Sep","Oct","Nov","Dec")&" "&YEAR(DATE(YEAR(TODAY()),MONTH(TODAY())-11,1)) | C20: =SUMIFS(Batches!$D$6:$D$505,Batches!$R$6:$R$505,M20) | D20: =SUMIFS(Batches!$G$6:$G$505,Batches!$R$6:$R$505,M20) | E20: =IF(C20=0,"",D20/C20) | M20: =YEAR(DATE(YEAR(TODAY()),MONTH(TODAY())-11,1))*100+MONTH(DATE(YEAR(TODAY()),MONTH(TODAY())-11,1))
B21: =CHOOSE(MONTH(DATE(YEAR(TODAY()),MONTH(TODAY())-10,1)),"Jan","Feb","Mar","Apr","May","Jun","Jul","Aug","Sep","Oct","Nov","Dec")&" "&YEAR(DATE(YEAR(TODAY()),MONTH(TODAY())-10,1)) | C21: =SUMIFS(Batches!$D$6:$D$505,Batches!$R$6:$R$505,M21) | D21: =SUMIFS(Batches!$G$6:$G$505,Batches!$R$6:$R$505,M21) | E21: =IF(C21=0,"",D21/C21) | M21: =YEAR(DATE(YEAR(TODAY()),MONTH(TODAY())-10,1))*100+MONTH(DATE(YEAR(TODAY()),MONTH(TODAY())-10,1))
B22: =CHOOSE(MONTH(DATE(YEAR(TODAY()),MONTH(TODAY())-9,1)),"Jan","Feb","Mar","Apr","May","Jun","Jul","Aug","Sep","Oct","Nov","Dec")&" "&YEAR(DATE(YEAR(TODAY()),MONTH(TODAY())-9,1)) | C22: =SUMIFS(Batches!$D$6:$D$505,Batches!$R$6:$R$505,M22) | D22: =SUMIFS(Batches!$G$6:$G$505,Batches!$R$6:$R$505,M22) | E22: =IF(C22=0,"",D22/C22) | M22: =YEAR(DATE(YEAR(TODAY()),MONTH(TODAY())-9,1))*100+MONTH(DATE(YEAR(TODAY()),MONTH(TODAY())-9,1))
B23: =CHOOSE(MONTH(DATE(YEAR(TODAY()),MONTH(TODAY())-8,1)),"Jan","Feb","Mar","Apr","May","Jun","Jul","Aug","Sep","Oct","Nov","Dec")&" "&YEAR(DATE(YEAR(TODAY()),MONTH(TODAY())-8,1)) | C23: =SUMIFS(Batches!$D$6:$D$505,Batches!$R$6:$R$505,M23) | D23: =SUMIFS(Batches!$G$6:$G$505,Batches!$R$6:$R$505,M23) | E23: =IF(C23=0,"",D23/C23) | M23: =YEAR(DATE(YEAR(TODAY()),MONTH(TODAY())-8,1))*100+MONTH(DATE(YEAR(TODAY()),MONTH(TODAY())-8,1))
B24: =CHOOSE(MONTH(DATE(YEAR(TODAY()),MONTH(TODAY())-7,1)),"Jan","Feb","Mar","Apr","May","Jun","Jul","Aug","Sep","Oct","Nov","Dec")&" "&YEAR(DATE(YEAR(TODAY()),MONTH(TODAY())-7,1)) | C24: =SUMIFS(Batches!$D$6:$D$505,Batches!$R$6:$R$505,M24) | D24: =SUMIFS(Batches!$G$6:$G$505,Batches!$R$6:$R$505,M24) | E24: =IF(C24=0,"",D24/C24) | M24: =YEAR(DATE(YEAR(TODAY()),MONTH(TODAY())-7,1))*100+MONTH(DATE(YEAR(TODAY()),MONTH(TODAY())-7,1))
B25: =CHOOSE(MONTH(DATE(YEAR(TODAY()),MONTH(TODAY())-6,1)),"Jan","Feb","Mar","Apr","May","Jun","Jul","Aug","Sep","Oct","Nov","Dec")&" "&YEAR(DATE(YEAR(TODAY()),MONTH(TODAY())-6,1)) | C25: =SUMIFS(Batches!$D$6:$D$505,Batches!$R$6:$R$505,M25) | D25: =SUMIFS(Batches!$G$6:$G$505,Batches!$R$6:$R$505,M25) | E25: =IF(C25=0,"",D25/C25) | M25: =YEAR(DATE(YEAR(TODAY()),MONTH(TODAY())-6,1))*100+MONTH(DATE(YEAR(TODAY()),MONTH(TODAY())-6,1))
B26: =CHOOSE(MONTH(DATE(YEAR(TODAY()),MONTH(TODAY())-5,1)),"Jan","Feb","Mar","Apr","May","Jun","Jul","Aug","Sep","Oct","Nov","Dec")&" "&YEAR(DATE(YEAR(TODAY()),MONTH(TODAY())-5,1)) | C26: =SUMIFS(Batches!$D$6:$D$505,Batches!$R$6:$R$505,M26) | D26: =SUMIFS(Batches!$G$6:$G$505,Batches!$R$6:$R$505,M26) | E26: =IF(C26=0,"",D26/C26) | M26: =YEAR(DATE(YEAR(TODAY()),MONTH(TODAY())-5,1))*100+MONTH(DATE(YEAR(TODAY()),MONTH(TODAY())-5,1))
B27: =CHOOSE(MONTH(DATE(YEAR(TODAY()),MONTH(TODAY())-4,1)),"Jan","Feb","Mar","Apr","May","Jun","Jul","Aug","Sep","Oct","Nov","Dec")&" "&YEAR(DATE(YEAR(TODAY()),MONTH(TODAY())-4,1)) | C27: =SUMIFS(Batches!$D$6:$D$505,Batches!$R$6:$R$505,M27) | D27: =SUMIFS(Batches!$G$6:$G$505,Batches!$R$6:$R$505,M27) | E27: =IF(C27=0,"",D27/C27) | M27: =YEAR(DATE(YEAR(TODAY()),MONTH(TODAY())-4,1))*100+MONTH(DATE(YEAR(TODAY()),MONTH(TODAY())-4,1))
B28: =CHOOSE(MONTH(DATE(YEAR(TODAY()),MONTH(TODAY())-3,1)),"Jan","Feb","Mar","Apr","May","Jun","Jul","Aug","Sep","Oct","Nov","Dec")&" "&YEAR(DATE(YEAR(TODAY()),MONTH(TODAY())-3,1)) | C28: =SUMIFS(Batches!$D$6:$D$505,Batches!$R$6:$R$505,M28) | D28: =SUMIFS(Batches!$G$6:$G$505,Batches!$R$6:$R$505,M28) | E28: =IF(C28=0,"",D28/C28) | M28: =YEAR(DATE(YEAR(TODAY()),MONTH(TODAY())-3,1))*100+MONTH(DATE(YEAR(TODAY()),MONTH(TODAY())-3,1))
B29: =CHOOSE(MONTH(DATE(YEAR(TODAY()),MONTH(TODAY())-2,1)),"Jan","Feb","Mar","Apr","May","Jun","Jul","Aug","Sep","Oct","Nov","Dec")&" "&YEAR(DATE(YEAR(TODAY()),MONTH(TODAY())-2,1)) | C29: =SUMIFS(Batches!$D$6:$D$505,Batches!$R$6:$R$505,M29) | D29: =SUMIFS(Batches!$G$6:$G$505,Batches!$R$6:$R$505,M29) | E29: =IF(C29=0,"",D29/C29) | M29: =YEAR(DATE(YEAR(TODAY()),MONTH(TODAY())-2,1))*100+MONTH(DATE(YEAR(TODAY()),MONTH(TODAY())-2,1))
B30: =CHOOSE(MONTH(DATE(YEAR(TODAY()),MONTH(TODAY())-1,1)),"Jan","Feb","Mar","Apr","May","Jun","Jul","Aug","Sep","Oct","Nov","Dec")&" "&YEAR(DATE(YEAR(TODAY()),MONTH(TODAY())-1,1)) | C30: =SUMIFS(Batches!$D$6:$D$505,Batches!$R$6:$R$505,M30) | D30: =SUMIFS(Batches!$G$6:$G$505,Batches!$R$6:$R$505,M30) | E30: =IF(C30=0,"",D30/C30) | M30: =YEAR(DATE(YEAR(TODAY()),MONTH(TODAY())-1,1))*100+MONTH(DATE(YEAR(TODAY()),MONTH(TODAY())-1,1))
B31: =CHOOSE(MONTH(DATE(YEAR(TODAY()),MONTH(TODAY())-0,1)),"Jan","Feb","Mar","Apr","May","Jun","Jul","Aug","Sep","Oct","Nov","Dec")&" "&YEAR(DATE(YEAR(TODAY()),MONTH(TODAY())-0,1)) | C31: =SUMIFS(Batches!$D$6:$D$505,Batches!$R$6:$R$505,M31) | D31: =SUMIFS(Batches!$G$6:$G$505,Batches!$R$6:$R$505,M31) | E31: =IF(C31=0,"",D31/C31) | M31: =YEAR(DATE(YEAR(TODAY()),MONTH(TODAY())-0,1))*100+MONTH(DATE(YEAR(TODAY()),MONTH(TODAY())-0,1))

Sheet Batches
B2: Batches
B3: One line for each batch you make. Update what was sold, given away and thrown out.
B5: Made on | C5: Product | D5: Made | E5: Sold | F5: Given or used | G5: Wasted | H5: Notes | I5: Batch code | J5: =Settings!$C$7 | K5: Left | L5: Days left | M5: Status | N5: Cost
B6: 45990 | C6: Chocolate chip cookies | D6: 8 | E6: 8 | F6: 0 | G6: 0 | I6: =IF(OR(C6="",NOT(ISNUMBER(B6))),"",UPPER(IF(IFERROR(IF(INDEX(Products!$C$6:$C$45,MATCH(C6,Products!$B$6:$B$45,0))="","",INDEX(Products!$C$6:$C$45,MATCH(C6,Products!$B$6:$B$45,0))),"")="",LEFT(SUBSTITUTE(C6," ",""),3),IFERROR(IF(INDEX(Products!$C$6:$C$45,MATCH(C6,Products!$B$6:$B$45,0))="","",INDEX(Products!$C$6:$C$45,MATCH(C6,Products!$B$6:$B$45,0))),"")))&"-"&RIGHT(YEAR(B6),2)&RIGHT("0"&MONTH(B6),2)&RIGHT("0"&DAY(B6),2)&"-"&COUNTIFS(C$6:C6,C6,B$6:B6,B6)) | J6: =IF(OR(C6="",NOT(ISNUMBER(B6)),N(P6)=0),"",B6+P6) | K6: =IF(C6="","",N(D6)-N(E6)-N(F6)-N(G6)) | L6: =IF(OR(C6="",N(K6)<=0,NOT(ISNUMBER(J6))),"",J6-TODAY()) | M6: =IF(C6="","",IF(N(K6)<=0,"Sold out",IF(NOT(ISNUMBER(J6)),"In stock",IF(J6<TODAY(),"Past its date",IF(J6-TODAY()<=Settings!$C$5,"Use soon","In stock"))))) | N6: =IF(C6="","",N(D6)*Q6) | P6: =IF(C6="",0,IFERROR(N(INDEX(Products!$E$6:$E$45,MATCH(C6,Products!$B$6:$B$45,0))),0)) | Q6: =IF(C6="",0,IFERROR(N(INDEX(Products!$I$6:$I$45,MATCH(C6,Products!$B$6:$B$45,0))),0)) | R6: =IF(OR(C6="",NOT(ISNUMBER(B6))),"",YEAR(B6)*100+MONTH(B6)) | S6: =N(G6)*Q6 | T6: =IF(OR(M6="",M6="Sold out",NOT(ISNUMBER(J6))),"",J6*1000+ROW())
B7: 45995 | C7: Lemon drizzle loaf | D7: 4 | E7: 3 | F7: 0 | G7: 1 | I7: =IF(OR(C7="",NOT(ISNUMBER(B7))),"",UPPER(IF(IFERROR(IF(INDEX(Products!$C$6:$C$45,MATCH(C7,Products!$B$6:$B$45,0))="","",INDEX(Products!$C$6:$C$45,MATCH(C7,Products!$B$6:$B$45,0))),"")="",LEFT(SUBSTITUTE(C7," ",""),3),IFERROR(IF(INDEX(Products!$C$6:$C$45,MATCH(C7,Products!$B$6:$B$45,0))="","",INDEX(Products!$C$6:$C$45,MATCH(C7,Products!$B$6:$B$45,0))),"")))&"-"&RIGHT(YEAR(B7),2)&RIGHT("0"&MONTH(B7),2)&RIGHT("0"&DAY(B7),2)&"-"&COUNTIFS(C$6:C7,C7,B$6:B7,B7)) | J7: =IF(OR(C7="",NOT(ISNUMBER(B7)),N(P7)=0),"",B7+P7) | K7: =IF(C7="","",N(D7)-N(E7)-N(F7)-N(G7)) | L7: =IF(OR(C7="",N(K7)<=0,NOT(ISNUMBER(J7))),"",J7-TODAY()) | M7: =IF(C7="","",IF(N(K7)<=0,"Sold out",IF(NOT(ISNUMBER(J7)),"In stock",IF(J7<TODAY(),"Past its date",IF(J7-TODAY()<=Settings!$C$5,"Use soon","In stock"))))) | N7: =IF(C7="","",N(D7)*Q7) | P7: =IF(C7="",0,IFERROR(N(INDEX(Products!$E$6:$E$45,MATCH(C7,Products!$B$6:$B$45,0))),0)) | Q7: =IF(C7="",0,IFERROR(N(INDEX(Products!$I$6:$I$45,MATCH(C7,Products!$B$6:$B$45,0))),0)) | R7: =IF(OR(C7="",NOT(ISNUMBER(B7))),"",YEAR(B7)*100+MONTH(B7)) | S7: =N(G7)*Q7 | T7: =IF(OR(M7="",M7="Sold out",NOT(ISNUMBER(J7))),"",J7*1000+ROW())
B8: 46005 | C8: Sourdough loaf | D8: 4 | E8: 4 | F8: 0 | G8: 0 | I8: =IF(OR(C8="",NOT(ISNUMBER(B8))),"",UPPER(IF(IFERROR(IF(INDEX(Products!$C$6:$C$45,MATCH(C8,Products!$B$6:$B$45,0))="","",INDEX(Products!$C$6:$C$45,MATCH(C8,Products!$B$6:$B$45,0))),"")="",LEFT(SUBSTITUTE(C8," ",""),3),IFERROR(IF(INDEX(Products!$C$6:$C$45,MATCH(C8,Products!$B$6:$B$45,0))="","",INDEX(Products!$C$6:$C$45,MATCH(C8,Products!$B$6:$B$45,0))),"")))&"-"&RIGHT(YEAR(B8),2)&RIGHT("0"&MONTH(B8),2)&RIGHT("0"&DAY(B8),2)&"-"&COUNTIFS(C$6:C8,C8,B$6:B8,B8)) | J8: =IF(OR(C8="",NOT(ISNUMBER(B8)),N(P8)=0),"",B8+P8) | K8: =IF(C8="","",N(D8)-N(E8)-N(F8)-N(G8)) | L8: =IF(OR(C8="",N(K8)<=0,NOT(ISNUMBER(J8))),"",J8-TODAY()) | M8: =IF(C8="","",IF(N(K8)<=0,"Sold out",IF(NOT(ISNUMBER(J8)),"In stock",IF(J8<TODAY(),"Past its date",IF(J8-TODAY()<=Settings!$C$5,"Use soon","In stock"))))) | N8: =IF(C8="","",N(D8)*Q8) | P8: =IF(C8="",0,IFERROR(N(INDEX(Products!$E$6:$E$45,MATCH(C8,Products!$B$6:$B$45,0))),0)) | Q8: =IF(C8="",0,IFERROR(N(INDEX(Products!$I$6:$I$45,MATCH(C8,Products!$B$6:$B$45,0))),0)) | R8: =IF(OR(C8="",NOT(ISNUMBER(B8))),"",YEAR(B8)*100+MONTH(B8)) | S8: =N(G8)*Q8 | T8: =IF(OR(M8="",M8="Sold out",NOT(ISNUMBER(J8))),"",J8*1000+ROW())
B9: 46010 | C9: Cinnamon rolls | D9: 12 | E9: 9 | F9: 0 | G9: 3 | I9: =IF(OR(C9="",NOT(ISNUMBER(B9))),"",UPPER(IF(IFERROR(IF(INDEX(Products!$C$6:$C$45,MATCH(C9,Products!$B$6:$B$45,0))="","",INDEX(Products!$C$6:$C$45,MATCH(C9,Products!$B$6:$B$45,0))),"")="",LEFT(SUBSTITUTE(C9," ",""),3),IFERROR(IF(INDEX(Products!$C$6:$C$45,MATCH(C9,Products!$B$6:$B$45,0))="","",INDEX(Products!$C$6:$C$45,MATCH(C9,Products!$B$6:$B$45,0))),"")))&"-"&RIGHT(YEAR(B9),2)&RIGHT("0"&MONTH(B9),2)&RIGHT("0"&DAY(B9),2)&"-"&COUNTIFS(C$6:C9,C9,B$6:B9,B9)) | J9: =IF(OR(C9="",NOT(ISNUMBER(B9)),N(P9)=0),"",B9+P9) | K9: =IF(C9="","",N(D9)-N(E9)-N(F9)-N(G9)) | L9: =IF(OR(C9="",N(K9)<=0,NOT(ISNUMBER(J9))),"",J9-TODAY()) | M9: =IF(C9="","",IF(N(K9)<=0,"Sold out",IF(NOT(ISNUMBER(J9)),"In stock",IF(J9<TODAY(),"Past its date",IF(J9-TODAY()<=Settings!$C$5,"Use soon","In stock"))))) | N9: =IF(C9="","",N(D9)*Q9) | P9: =IF(C9="",0,IFERROR(N(INDEX(Products!$E$6:$E$45,MATCH(C9,Products!$B$6:$B$45,0))),0)) | Q9: =IF(C9="",0,IFERROR(N(INDEX(Products!$I$6:$I$45,MATCH(C9,Products!$B$6:$B$45,0))),0)) | R9: =IF(OR(C9="",NOT(ISNUMBER(B9))),"",YEAR(B9)*100+MONTH(B9)) | S9: =N(G9)*Q9 | T9: =IF(OR(M9="",M9="Sold out",NOT(ISNUMBER(J9))),"",J9*1000+ROW())
B10: 46013 | C10: Strawberry jam | D10: 12 | E10: 12 | F10: 0 | G10: 0 | I10: =IF(OR(C10="",NOT(ISNUMBER(B10))),"",UPPER(IF(IFERROR(IF(INDEX(Products!$C$6:$C$45,MATCH(C10,Products!$B$6:$B$45,0))="","",INDEX(Products!$C$6:$C$45,MATCH(C10,Products!$B$6:$B$45,0))),"")="",LEFT(SUBSTITUTE(C10," ",""),3),IFERROR(IF(INDEX(Products!$C$6:$C$45,MATCH(C10,Products!$B$6:$B$45,0))="","",INDEX(Products!$C$6:$C$45,MATCH(C10,Products!$B$6:$B$45,0))),"")))&"-"&RIGHT(YEAR(B10),2)&RIGHT("0"&MONTH(B10),2)&RIGHT("0"&DAY(B10),2)&"-"&COUNTIFS(C$6:C10,C10,B$6:B10,B10)) | J10: =IF(OR(C10="",NOT(ISNUMBER(B10)),N(P10)=0),"",B10+P10) | K10: =IF(C10="","",N(D10)-N(E10)-N(F10)-N(G10)) | L10: =IF(OR(C10="",N(K10)<=0,NOT(ISNUMBER(J10))),"",J10-TODAY()) | M10: =IF(C10="","",IF(N(K10)<=0,"Sold out",IF(NOT(ISNUMBER(J10)),"In stock",IF(J10<TODAY(),"Past its date",IF(J10-TODAY()<=Settings!$C$5,"Use soon","In stock"))))) | N10: =IF(C10="","",N(D10)*Q10) | P10: =IF(C10="",0,IFERROR(N(INDEX(Products!$E$6:$E$45,MATCH(C10,Products!$B$6:$B$45,0))),0)) | Q10: =IF(C10="",0,IFERROR(N(INDEX(Products!$I$6:$I$45,MATCH(C10,Products!$B$6:$B$45,0))),0)) | R10: =IF(OR(C10="",NOT(ISNUMBER(B10))),"",YEAR(B10)*100+MONTH(B10)) | S10: =N(G10)*Q10 | T10: =IF(OR(M10="",M10="Sold out",NOT(ISNUMBER(J10))),"",J10*1000+ROW())
B11: 46025 | C11: Lemon drizzle loaf | D11: 4 | E11: 3 | F11: 0 | G11: 1 | I11: =IF(OR(C11="",NOT(ISNUMBER(B11))),"",UPPER(IF(IFERROR(IF(INDEX(Products!$C$6:$C$45,MATCH(C11,Products!$B$6:$B$45,0))="","",INDEX(Products!$C$6:$C$45,MATCH(C11,Products!$B$6:$B$45,0))),"")="",LEFT(SUBSTITUTE(C11," ",""),3),IFERROR(IF(INDEX(Products!$C$6:$C$45,MATCH(C11,Products!$B$6:$B$45,0))="","",INDEX(Products!$C$6:$C$45,MATCH(C11,Products!$B$6:$B$45,0))),"")))&"-"&RIGHT(YEAR(B11),2)&RIGHT("0"&MONTH(B11),2)&RIGHT("0"&DAY(B11),2)&"-"&COUNTIFS(C$6:C11,C11,B$6:B11,B11)) | J11: =IF(OR(C11="",NOT(ISNUMBER(B11)),N(P11)=0),"",B11+P11) | K11: =IF(C11="","",N(D11)-N(E11)-N(F11)-N(G11)) | L11: =IF(OR(C11="",N(K11)<=0,NOT(ISNUMBER(J11))),"",J11-TODAY()) | M11: =IF(C11="","",IF(N(K11)<=0,"Sold out",IF(NOT(ISNUMBER(J11)),"In stock",IF(J11<TODAY(),"Past its date",IF(J11-TODAY()<=Settings!$C$5,"Use soon","In stock"))))) | N11: =IF(C11="","",N(D11)*Q11) | P11: =IF(C11="",0,IFERROR(N(INDEX(Products!$E$6:$E$45,MATCH(C11,Products!$B$6:$B$45,0))),0)) | Q11: =IF(C11="",0,IFERROR(N(INDEX(Products!$I$6:$I$45,MATCH(C11,Products!$B$6:$B$45,0))),0)) | R11: =IF(OR(C11="",NOT(ISNUMBER(B11))),"",YEAR(B11)*100+MONTH(B11)) | S11: =N(G11)*Q11 | T11: =IF(OR(M11="",M11="Sold out",NOT(ISNUMBER(J11))),"",J11*1000+ROW())
B12: 46030 | C12: Brownies | D12: 16 | E12: 14 | F12: 0 | G12: 2 | I12: =IF(OR(C12="",NOT(ISNUMBER(B12))),"",UPPER(IF(IFERROR(IF(INDEX(Products!$C$6:$C$45,MATCH(C12,Products!$B$6:$B$45,0))="","",INDEX(Products!$C$6:$C$45,MATCH(C12,Products!$B$6:$B$45,0))),"")="",LEFT(SUBSTITUTE(C12," ",""),3),IFERROR(IF(INDEX(Products!$C$6:$C$45,MATCH(C12,Products!$B$6:$B$45,0))="","",INDEX(Products!$C$6:$C$45,MATCH(C12,Products!$B$6:$B$45,0))),"")))&"-"&RIGHT(YEAR(B12),2)&RIGHT("0"&MONTH(B12),2)&RIGHT("0"&DAY(B12),2)&"-"&COUNTIFS(C$6:C12,C12,B$6:B12,B12)) | J12: =IF(OR(C12="",NOT(ISNUMBER(B12)),N(P12)=0),"",B12+P12) | K12: =IF(C12="","",N(D12)-N(E12)-N(F12)-N(G12)) | L12: =IF(OR(C12="",N(K12)<=0,NOT(ISNUMBER(J12))),"",J12-TODAY()) | M12: =IF(C12="","",IF(N(K12)<=0,"Sold out",IF(NOT(ISNUMBER(J12)),"In stock",IF(J12<TODAY(),"Past its date",IF(J12-TODAY()<=Settings!$C$5,"Use soon","In stock"))))) | N12: =IF(C12="","",N(D12)*Q12) | P12: =IF(C12="",0,IFERROR(N(INDEX(Products!$E$6:$E$45,MATCH(C12,Products!$B$6:$B$45,0))),0)) | Q12: =IF(C12="",0,IFERROR(N(INDEX(Products!$I$6:$I$45,MATCH(C12,Products!$B$6:$B$45,0))),0)) | R12: =IF(OR(C12="",NOT(ISNUMBER(B12))),"",YEAR(B12)*100+MONTH(B12)) | S12: =N(G12)*Q12 | T12: =IF(OR(M12="",M12="Sold out",NOT(ISNUMBER(J12))),"",J12*1000+ROW())
B13: 46040 | C13: Cinnamon rolls | D13: 12 | E13: 9 | F13: 0 | G13: 3 | I13: =IF(OR(C13="",NOT(ISNUMBER(B13))),"",UPPER(IF(IFERROR(IF(INDEX(Products!$C$6:$C$45,MATCH(C13,Products!$B$6:$B$45,0))="","",INDEX(Products!$C$6:$C$45,MATCH(C13,Products!$B$6:$B$45,0))),"")="",LEFT(SUBSTITUTE(C13," ",""),3),IFERROR(IF(INDEX(Products!$C$6:$C$45,MATCH(C13,Products!$B$6:$B$45,0))="","",INDEX(Products!$C$6:$C$45,MATCH(C13,Products!$B$6:$B$45,0))),"")))&"-"&RIGHT(YEAR(B13),2)&RIGHT("0"&MONTH(B13),2)&RIGHT("0"&DAY(B13),2)&"-"&COUNTIFS(C$6:C13,C13,B$6:B13,B13)) | J13: =IF(OR(C13="",NOT(ISNUMBER(B13)),N(P13)=0),"",B13+P13) | K13: =IF(C13="","",N(D13)-N(E13)-N(F13)-N(G13)) | L13: =IF(OR(C13="",N(K13)<=0,NOT(ISNUMBER(J13))),"",J13-TODAY()) | M13: =IF(C13="","",IF(N(K13)<=0,"Sold out",IF(NOT(ISNUMBER(J13)),"In stock",IF(J13<TODAY(),"Past its date",IF(J13-TODAY()<=Settings!$C$5,"Use soon","In stock"))))) | N13: =IF(C13="","",N(D13)*Q13) | P13: =IF(C13="",0,IFERROR(N(INDEX(Products!$E$6:$E$45,MATCH(C13,Products!$B$6:$B$45,0))),0)) | Q13: =IF(C13="",0,IFERROR(N(INDEX(Products!$I$6:$I$45,MATCH(C13,Products!$B$6:$B$45,0))),0)) | R13: =IF(OR(C13="",NOT(ISNUMBER(B13))),"",YEAR(B13)*100+MONTH(B13)) | S13: =N(G13)*Q13 | T13: =IF(OR(M13="",M13="Sold out",NOT(ISNUMBER(J13))),"",J13*1000+ROW())
B14: 46041 | C14: Granola | D14: 10 | E14: 9 | F14: 1 | G14: 0 | I14: =IF(OR(C14="",NOT(ISNUMBER(B14))),"",UPPER(IF(IFERROR(IF(INDEX(Products!$C$6:$C$45,MATCH(C14,Products!$B$6:$B$45,0))="","",INDEX(Products!$C$6:$C$45,MATCH(C14,Products!$B$6:$B$45,0))),"")="",LEFT(SUBSTITUTE(C14," ",""),3),IFERROR(IF(INDEX(Products!$C$6:$C$45,MATCH(C14,Products!$B$6:$B$45,0))="","",INDEX(Products!$C$6:$C$45,MATCH(C14,Products!$B$6:$B$45,0))),"")))&"-"&RIGHT(YEAR(B14),2)&RIGHT("0"&MONTH(B14),2)&RIGHT("0"&DAY(B14),2)&"-"&COUNTIFS(C$6:C14,C14,B$6:B14,B14)) | J14: =IF(OR(C14="",NOT(ISNUMBER(B14)),N(P14)=0),"",B14+P14) | K14: =IF(C14="","",N(D14)-N(E14)-N(F14)-N(G14)) | L14: =IF(OR(C14="",N(K14)<=0,NOT(ISNUMBER(J14))),"",J14-TODAY()) | M14: =IF(C14="","",IF(N(K14)<=0,"Sold out",IF(NOT(ISNUMBER(J14)),"In stock",IF(J14<TODAY(),"Past its date",IF(J14-TODAY()<=Settings!$C$5,"Use soon","In stock"))))) | N14: =IF(C14="","",N(D14)*Q14) | P14: =IF(C14="",0,IFERROR(N(INDEX(Products!$E$6:$E$45,MATCH(C14,Products!$B$6:$B$45,0))),0)) | Q14: =IF(C14="",0,IFERROR(N(INDEX(Products!$I$6:$I$45,MATCH(C14,Products!$B$6:$B$45,0))),0)) | R14: =IF(OR(C14="",NOT(ISNUMBER(B14))),"",YEAR(B14)*100+MONTH(B14)) | S14: =N(G14)*Q14 | T14: =IF(OR(M14="",M14="Sold out",NOT(ISNUMBER(J14))),"",J14*1000+ROW())
B15: 46050 | C15: Chocolate chip cookies | D15: 8 | E15: 8 | F15: 0 | G15: 0 | I15: =IF(OR(C15="",NOT(ISNUMBER(B15))),"",UPPER(IF(IFERROR(IF(INDEX(Products!$C$6:$C$45,MATCH(C15,Products!$B$6:$B$45,0))="","",INDEX(Products!$C$6:$C$45,MATCH(C15,Products!$B$6:$B$45,0))),"")="",LEFT(SUBSTITUTE(C15," ",""),3),IFERROR(IF(INDEX(Products!$C$6:$C$45,MATCH(C15,Products!$B$6:$B$45,0))="","",INDEX(Products!$C$6:$C$45,MATCH(C15,Products!$B$6:$B$45,0))),"")))&"-"&RIGHT(YEAR(B15),2)&RIGHT("0"&MONTH(B15),2)&RIGHT("0"&DAY(B15),2)&"-"&COUNTIFS(C$6:C15,C15,B$6:B15,B15)) | J15: =IF(OR(C15="",NOT(ISNUMBER(B15)),N(P15)=0),"",B15+P15) | K15: =IF(C15="","",N(D15)-N(E15)-N(F15)-N(G15)) | L15: =IF(OR(C15="",N(K15)<=0,NOT(ISNUMBER(J15))),"",J15-TODAY()) | M15: =IF(C15="","",IF(N(K15)<=0,"Sold out",IF(NOT(ISNUMBER(J15)),"In stock",IF(J15<TODAY(),"Past its date",IF(J15-TODAY()<=Settings!$C$5,"Use soon","In stock"))))) | N15: =IF(C15="","",N(D15)*Q15) | P15: =IF(C15="",0,IFERROR(N(INDEX(Products!$E$6:$E$45,MATCH(C15,Products!$B$6:$B$45,0))),0)) | Q15: =IF(C15="",0,IFERROR(N(INDEX(Products!$I$6:$I$45,MATCH(C15,Products!$B$6:$B$45,0))),0)) | R15: =IF(OR(C15="",NOT(ISNUMBER(B15))),"",YEAR(B15)*100+MONTH(B15)) | S15: =N(G15)*Q15 | T15: =IF(OR(M15="",M15="Sold out",NOT(ISNUMBER(J15))),"",J15*1000+ROW())
B16: 46060 | C16: Brownies | D16: 16 | E16: 15 | F16: 0 | G16: 1 | I16: =IF(OR(C16="",NOT(ISNUMBER(B16))),"",UPPER(IF(IFERROR(IF(INDEX(Products!$C$6:$C$45,MATCH(C16,Products!$B$6:$B$45,0))="","",INDEX(Products!$C$6:$C$45,MATCH(C16,Products!$B$6:$B$45,0))),"")="",LEFT(SUBSTITUTE(C16," ",""),3),IFERROR(IF(INDEX(Products!$C$6:$C$45,MATCH(C16,Products!$B$6:$B$45,0))="","",INDEX(Products!$C$6:$C$45,MATCH(C16,Products!$B$6:$B$45,0))),"")))&"-"&RIGHT(YEAR(B16),2)&RIGHT("0"&MONTH(B16),2)&RIGHT("0"&DAY(B16),2)&"-"&COUNTIFS(C$6:C16,C16,B$6:B16,B16)) | J16: =IF(OR(C16="",NOT(ISNUMBER(B16)),N(P16)=0),"",B16+P16) | K16: =IF(C16="","",N(D16)-N(E16)-N(F16)-N(G16)) | L16: =IF(OR(C16="",N(K16)<=0,NOT(ISNUMBER(J16))),"",J16-TODAY()) | M16: =IF(C16="","",IF(N(K16)<=0,"Sold out",IF(NOT(ISNUMBER(J16)),"In stock",IF(J16<TODAY(),"Past its date",IF(J16-TODAY()<=Settings!$C$5,"Use soon","In stock"))))) | N16: =IF(C16="","",N(D16)*Q16) | P16: =IF(C16="",0,IFERROR(N(INDEX(Products!$E$6:$E$45,MATCH(C16,Products!$B$6:$B$45,0))),0)) | Q16: =IF(C16="",0,IFERROR(N(INDEX(Products!$I$6:$I$45,MATCH(C16,Products!$B$6:$B$45,0))),0)) | R16: =IF(OR(C16="",NOT(ISNUMBER(B16))),"",YEAR(B16)*100+MONTH(B16)) | S16: =N(G16)*Q16 | T16: =IF(OR(M16="",M16="Sold out",NOT(ISNUMBER(J16))),"",J16*1000+ROW())
B17: 46065 | C17: Sourdough loaf | D17: 4 | E17: 4 | F17: 0 | G17: 0 | I17: =IF(OR(C17="",NOT(ISNUMBER(B17))),"",UPPER(IF(IFERROR(IF(INDEX(Products!$C$6:$C$45,MATCH(C17,Products!$B$6:$B$45,0))="","",INDEX(Products!$C$6:$C$45,MATCH(C17,Products!$B$6:$B$45,0))),"")="",LEFT(SUBSTITUTE(C17," ",""),3),IFERROR(IF(INDEX(Products!$C$6:$C$45,MATCH(C17,Products!$B$6:$B$45,0))="","",INDEX(Products!$C$6:$C$45,MATCH(C17,Products!$B$6:$B$45,0))),"")))&"-"&RIGHT(YEAR(B17),2)&RIGHT("0"&MONTH(B17),2)&RIGHT("0"&DAY(B17),2)&"-"&COUNTIFS(C$6:C17,C17,B$6:B17,B17)) | J17: =IF(OR(C17="",NOT(ISNUMBER(B17)),N(P17)=0),"",B17+P17) | K17: =IF(C17="","",N(D17)-N(E17)-N(F17)-N(G17)) | L17: =IF(OR(C17="",N(K17)<=0,NOT(ISNUMBER(J17))),"",J17-TODAY()) | M17: =IF(C17="","",IF(N(K17)<=0,"Sold out",IF(NOT(ISNUMBER(J17)),"In stock",IF(J17<TODAY(),"Past its date",IF(J17-TODAY()<=Settings!$C$5,"Use soon","In stock"))))) | N17: =IF(C17="","",N(D17)*Q17) | P17: =IF(C17="",0,IFERROR(N(INDEX(Products!$E$6:$E$45,MATCH(C17,Products!$B$6:$B$45,0))),0)) | Q17: =IF(C17="",0,IFERROR(N(INDEX(Products!$I$6:$I$45,MATCH(C17,Products!$B$6:$B$45,0))),0)) | R17: =IF(OR(C17="",NOT(ISNUMBER(B17))),"",YEAR(B17)*100+MONTH(B17)) | S17: =N(G17)*Q17 | T17: =IF(OR(M17="",M17="Sold out",NOT(ISNUMBER(J17))),"",J17*1000+ROW())
... B42: 46245 | C42: Sourdough loaf | D42: 4 | E42: 4 | F42: 0 | G42: 0 | I42: =IF(OR(C42="",NOT(ISNUMBER(B42))),"",UPPER(IF(IFERROR(IF(INDEX(Products!$C$6:$C$45,MATCH(C42,Products!$B$6:$B$45,0))="","",INDEX(Products!$C$6:$C$45,MATCH(C42,Products!$B$6:$B$45,0))),"")="",LEFT(SUBSTITUTE(C42," ",""),3),IFERROR(IF(INDEX(Products!$C$6:$C$45,MATCH(C42,Products!$B$6:$B$45,0))="","",INDEX(Products!$C$6:$C$45,MATCH(C42,Products!$B$6:$B$45,0))),"")))&"-"&RIGHT(YEAR(B42),2)&RIGHT("0"&MONTH(B42),2)&RIGHT("0"&DAY(B42),2)&"-"&COUNTIFS(C$6:C42,C42,B$6:B42,B42)) | J42: =IF(OR(C42="",NOT(ISNUMBER(B42)),N(P42)=0),"",B42+P42) | K42: =IF(C42="","",N(D42)-N(E42)-N(F42)-N(G42)) | L42: =IF(OR(C42="",N(K42)<=0,NOT(ISNUMBER(J42))),"",J42-TODAY()) | M42: =IF(C42="","",IF(N(K42)<=0,"Sold out",IF(NOT(ISNUMBER(J42)),"In stock",IF(J42<TODAY(),"Past its date",IF(J42-TODAY()<=Settings!$C$5,"Use soon","In stock"))))) | N42: =IF(C42="","",N(D42)*Q42) | P42: =IF(C42="",0,IFERROR(N(INDEX(Products!$E$6:$E$45,MATCH(C42,Products!$B$6:$B$45,0))),0)) | Q42: =IF(C42="",0,IFERROR(N(INDEX(Products!$I$6:$I$45,MATCH(C42,Products!$B$6:$B$45,0))),0)) | R42: =IF(OR(C42="",NOT(ISNUMBER(B42))),"",YEAR(B42)*100+MONTH(B42)) | S42: =N(G42)*Q42 | T42: =IF(OR(M42="",M42="Sold out",NOT(ISNUMBER(J42))),"",J42*1000+ROW())
B43: 46253 | C43: Strawberry jam | D43: 12 | E43: 7 | F43: 1 | G43: 0 | H43: Strawberries lot B-2207 | I43: =IF(OR(C43="",NOT(ISNUMBER(B43))),"",UPPER(IF(IFERROR(IF(INDEX(Products!$C$6:$C$45,MATCH(C43,Products!$B$6:$B$45,0))="","",INDEX(Products!$C$6:$C$45,MATCH(C43,Products!$B$6:$B$45,0))),"")="",LEFT(SUBSTITUTE(C43," ",""),3),IFERROR(IF(INDEX(Products!$C$6:$C$45,MATCH(C43,Products!$B$6:$B$45,0))="","",INDEX(Products!$C$6:$C$45,MATCH(C43,Products!$B$6:$B$45,0))),"")))&"-"&RIGHT(YEAR(B43),2)&RIGHT("0"&MONTH(B43),2)&RIGHT("0"&DAY(B43),2)&"-"&COUNTIFS(C$6:C43,C43,B$6:B43,B43)) | J43: =IF(OR(C43="",NOT(ISNUMBER(B43)),N(P43)=0),"",B43+P43) | K43: =IF(C43="","",N(D43)-N(E43)-N(F43)-N(G43)) | L43: =IF(OR(C43="",N(K43)<=0,NOT(ISNUMBER(J43))),"",J43-TODAY()) | M43: =IF(C43="","",IF(N(K43)<=0,"Sold out",IF(NOT(ISNUMBER(J43)),"In stock",IF(J43<TODAY(),"Past its date",IF(J43-TODAY()<=Settings!$C$5,"Use soon","In stock"))))) | N43: =IF(C43="","",N(D43)*Q43) | P43: =IF(C43="",0,IFERROR(N(INDEX(Products!$E$6:$E$45,MATCH(C43,Products!$B$6:$B$45,0))),0)) | Q43: =IF(C43="",0,IFERROR(N(INDEX(Products!$I$6:$I$45,MATCH(C43,Products!$B$6:$B$45,0))),0)) | R43: =IF(OR(C43="",NOT(ISNUMBER(B43))),"",YEAR(B43)*100+MONTH(B43)) | S43: =N(G43)*Q43 | T43: =IF(OR(M43="",M43="Sold out",NOT(ISNUMBER(J43))),"",J43*1000+ROW())
B44: 46258 | C44: Dog biscuits | D44: 10 | E44: 8 | F44: 0 | G44: 0 | I44: =IF(OR(C44="",NOT(ISNUMBER(B44))),"",UPPER(IF(IFERROR(IF(INDEX(Products!$C$6:$C$45,MATCH(C44,Products!$B$6:$B$45,0))="","",INDEX(Products!$C$6:$C$45,MATCH(C44,Products!$B$6:$B$45,0))),"")="",LEFT(SUBSTITUTE(C44," ",""),3),IFERROR(IF(INDEX(Products!$C$6:$C$45,MATCH(C44,Products!$B$6:$B$45,0))="","",INDEX(Products!$C$6:$C$45,MATCH(C44,Products!$B$6:$B$45,0))),"")))&"-"&RIGHT(YEAR(B44),2)&RIGHT("0"&MONTH(B44),2)&RIGHT("0"&DAY(B44),2)&"-"&COUNTIFS(C$6:C44,C44,B$6:B44,B44)) | J44: =IF(OR(C44="",NOT(ISNUMBER(B44)),N(P44)=0),"",B44+P44) | K44: =IF(C44="","",N(D44)-N(E44)-N(F44)-N(G44)) | L44: =IF(OR(C44="",N(K44)<=0,NOT(ISNUMBER(J44))),"",J44-TODAY()) | M44: =IF(C44="","",IF(N(K44)<=0,"Sold out",IF(NOT(ISNUMBER(J44)),"In stock",IF(J44<TODAY(),"Past its date",IF(J44-TODAY()<=Settings!$C$5,"Use soon","In stock"))))) | N44: =IF(C44="","",N(D44)*Q44) | P44: =IF(C44="",0,IFERROR(N(INDEX(Products!$E$6:$E$45,MATCH(C44,Products!$B$6:$B$45,0))),0)) | Q44: =IF(C44="",0,IFERROR(N(INDEX(Products!$I$6:$I$45,MATCH(C44,Products!$B$6:$B$45,0))),0)) | R44: =IF(OR(C44="",NOT(ISNUMBER(B44))),"",YEAR(B44)*100+MONTH(B44)) | S44: =N(G44)*Q44 | T44: =IF(OR(M44="",M44="Sold out",NOT(ISNUMBER(J44))),"",J44*1000+ROW())
B45: 46260 | C45: Chocolate chip cookies | D45: 8 | E45: 8 | F45: 0 | G45: 0 | I45: =IF(OR(C45="",NOT(ISNUMBER(B45))),"",UPPER(IF(IFERROR(IF(INDEX(Products!$C$6:$C$45,MATCH(C45,Products!$B$6:$B$45,0))="","",INDEX(Products!$C$6:$C$45,MATCH(C45,Products!$B$6:$B$45,0))),"")="",LEFT(SUBSTITUTE(C45," ",""),3),IFERROR(IF(INDEX(Products!$C$6:$C$45,MATCH(C45,Products!$B$6:$B$45,0))="","",INDEX(Products!$C$6:$C$45,MATCH(C45,Products!$B$6:$B$45,0))),"")))&"-"&RIGHT(YEAR(B45),2)&RIGHT("0"&MONTH(B45),2)&RIGHT("0"&DAY(B45),2)&"-"&COUNTIFS(C$6:C45,C45,B$6:B45,B45)) | J45: =IF(OR(C45="",NOT(ISNUMBER(B45)),N(P45)=0),"",B45+P45) | K45: =IF(C45="","",N(D45)-N(E45)-N(F45)-N(G45)) | L45: =IF(OR(C45="",N(K45)<=0,NOT(ISNUMBER(J45))),"",J45-TODAY()) | M45: =IF(C45="","",IF(N(K45)<=0,"Sold out",IF(NOT(ISNUMBER(J45)),"In stock",IF(J45<TODAY(),"Past its date",IF(J45-TODAY()<=Settings!$C$5,"Use soon","In stock"))))) | N45: =IF(C45="","",N(D45)*Q45) | P45: =IF(C45="",0,IFERROR(N(INDEX(Products!$E$6:$E$45,MATCH(C45,Products!$B$6:$B$45,0))),0)) | Q45: =IF(C45="",0,IFERROR(N(INDEX(Products!$I$6:$I$45,MATCH(C45,Products!$B$6:$B$45,0))),0)) | R45: =IF(OR(C45="",NOT(ISNUMBER(B45))),"",YEAR(B45)*100+MONTH(B45)) | S45: =N(G45)*Q45 | T45: =IF(OR(M45="",M45="Sold out",NOT(ISNUMBER(J45))),"",J45*1000+ROW())
B46: 46265 | C46: Lemon drizzle loaf | D46: 4 | E46: 3 | F46: 0 | G46: 1 | I46: =IF(OR(C46="",NOT(ISNUMBER(B46))),"",UPPER(IF(IFERROR(IF(INDEX(Products!$C$6:$C$45,MATCH(C46,Products!$B$6:$B$45,0))="","",INDEX(Products!$C$6:$C$45,MATCH(C46,Products!$B$6:$B$45,0))),"")="",LEFT(SUBSTITUTE(C46," ",""),3),IFERROR(IF(INDEX(Products!$C$6:$C$45,MATCH(C46,Products!$B$6:$B$45,0))="","",INDEX(Products!$C$6:$C$45,MATCH(C46,Products!$B$6:$B$45,0))),"")))&"-"&RIGHT(YEAR(B46),2)&RIGHT("0"&MONTH(B46),2)&RIGHT("0"&DAY(B46),2)&"-"&COUNTIFS(C$6:C46,C46,B$6:B46,B46)) | J46: =IF(OR(C46="",NOT(ISNUMBER(B46)),N(P46)=0),"",B46+P46) | K46: =IF(C46="","",N(D46)-N(E46)-N(F46)-N(G46)) | L46: =IF(OR(C46="",N(K46)<=0,NOT(ISNUMBER(J46))),"",J46-TODAY()) | M46: =IF(C46="","",IF(N(K46)<=0,"Sold out",IF(NOT(ISNUMBER(J46)),"In stock",IF(J46<TODAY(),"Past its date",IF(J46-TODAY()<=Settings!$C$5,"Use soon","In stock"))))) | N46: =IF(C46="","",N(D46)*Q46) | P46: =IF(C46="",0,IFERROR(N(INDEX(Products!$E$6:$E$45,MATCH(C46,Products!$B$6:$B$45,0))),0)) | Q46: =IF(C46="",0,IFERROR(N(INDEX(Products!$I$6:$I$45,MATCH(C46,Products!$B$6:$B$45,0))),0)) | R46: =IF(OR(C46="",NOT(ISNUMBER(B46))),"",YEAR(B46)*100+MONTH(B46)) | S46: =N(G46)*Q46 | T46: =IF(OR(M46="",M46="Sold out",NOT(ISNUMBER(J46))),"",J46*1000+ROW())
B47: 46273 | C47: Granola | D47: 10 | E47: 6 | F47: 0 | G47: 0 | I47: =IF(OR(C47="",NOT(ISNUMBER(B47))),"",UPPER(IF(IFERROR(IF(INDEX(Products!$C$6:$C$45,MATCH(C47,Products!$B$6:$B$45,0))="","",INDEX(Products!$C$6:$C$45,MATCH(C47,Products!$B$6:$B$45,0))),"")="",LEFT(SUBSTITUTE(C47," ",""),3),IFERROR(IF(INDEX(Products!$C$6:$C$45,MATCH(C47,Products!$B$6:$B$45,0))="","",INDEX(Products!$C$6:$C$45,MATCH(C47,Products!$B$6:$B$45,0))),"")))&"-"&RIGHT(YEAR(B47),2)&RIGHT("0"&MONTH(B47),2)&RIGHT("0"&DAY(B47),2)&"-"&COUNTIFS(C$6:C47,C47,B$6:B47,B47)) | J47: =IF(OR(C47="",NOT(ISNUMBER(B47)),N(P47)=0),"",B47+P47) | K47: =IF(C47="","",N(D47)-N(E47)-N(F47)-N(G47)) | L47: =IF(OR(C47="",N(K47)<=0,NOT(ISNUMBER(J47))),"",J47-TODAY()) | M47: =IF(C47="","",IF(N(K47)<=0,"Sold out",IF(NOT(ISNUMBER(J47)),"In stock",IF(J47<TODAY(),"Past its date",IF(J47-TODAY()<=Settings!$C$5,"Use soon","In stock"))))) | N47: =IF(C47="","",N(D47)*Q47) | P47: =IF(C47="",0,IFERROR(N(INDEX(Products!$E$6:$E$45,MATCH(C47,Products!$B$6:$B$45,0))),0)) | Q47: =IF(C47="",0,IFERROR(N(INDEX(Products!$I$6:$I$45,MATCH(C47,Products!$B$6:$B$45,0))),0)) | R47: =IF(OR(C47="",NOT(ISNUMBER(B47))),"",YEAR(B47)*100+MONTH(B47)) | S47: =N(G47)*Q47 | T47: =IF(OR(M47="",M47="Sold out",NOT(ISNUMBER(J47))),"",J47*1000+ROW())
B48: 46275 | C48: Sourdough loaf | D48: 4 | E48: 4 | F48: 0 | G48: 0 | I48: =IF(OR(C48="",NOT(ISNUMBER(B48))),"",UPPER(IF(IFERROR(IF(INDEX(Products!$C$6:$C$45,MATCH(C48,Products!$B$6:$B$45,0))="","",INDEX(Products!$C$6:$C$45,MATCH(C48,Products!$B$6:$B$45,0))),"")="",LEFT(SUBSTITUTE(C48," ",""),3),IFERROR(IF(INDEX(Products!$C$6:$C$45,MATCH(C48,Products!$B$6:$B$45,0))="","",INDEX(Products!$C$6:$C$45,MATCH(C48,Products!$B$6:$B$45,0))),"")))&"-"&RIGHT(YEAR(B48),2)&RIGHT("0"&MONTH(B48),2)&RIGHT("0"&DAY(B48),2)&"-"&COUNTIFS(C$6:C48,C48,B$6:B48,B48)) | J48: =IF(OR(C48="",NOT(ISNUMBER(B48)),N(P48)=0),"",B48+P48) | K48: =IF(C48="","",N(D48)-N(E48)-N(F48)-N(G48)) | L48: =IF(OR(C48="",N(K48)<=0,NOT(ISNUMBER(J48))),"",J48-TODAY()) | M48: =IF(C48="","",IF(N(K48)<=0,"Sold out",IF(NOT(ISNUMBER(J48)),"In stock",IF(J48<TODAY(),"Past its date",IF(J48-TODAY()<=Settings!$C$5,"Use soon","In stock"))))) | N48: =IF(C48="","",N(D48)*Q48) | P48: =IF(C48="",0,IFERROR(N(INDEX(Products!$E$6:$E$45,MATCH(C48,Products!$B$6:$B$45,0))),0)) | Q48: =IF(C48="",0,IFERROR(N(INDEX(Products!$I$6:$I$45,MATCH(C48,Products!$B$6:$B$45,0))),0)) | R48: =IF(OR(C48="",NOT(ISNUMBER(B48))),"",YEAR(B48)*100+MONTH(B48)) | S48: =N(G48)*Q48 | T48: =IF(OR(M48="",M48="Sold out",NOT(ISNUMBER(J48))),"",J48*1000+ROW())
B49: 46280 | C49: Cinnamon rolls | D49: 12 | E49: 9 | F49: 0 | G49: 3 | I49: =IF(OR(C49="",NOT(ISNUMBER(B49))),"",UPPER(IF(IFERROR(IF(INDEX(Products!$C$6:$C$45,MATCH(C49,Products!$B$6:$B$45,0))="","",INDEX(Products!$C$6:$C$45,MATCH(C49,Products!$B$6:$B$45,0))),"")="",LEFT(SUBSTITUTE(C49," ",""),3),IFERROR(IF(INDEX(Products!$C$6:$C$45,MATCH(C49,Products!$B$6:$B$45,0))="","",INDEX(Products!$C$6:$C$45,MATCH(C49,Products!$B$6:$B$45,0))),"")))&"-"&RIGHT(YEAR(B49),2)&RIGHT("0"&MONTH(B49),2)&RIGHT("0"&DAY(B49),2)&"-"&COUNTIFS(C$6:C49,C49,B$6:B49,B49)) | J49: =IF(OR(C49="",NOT(ISNUMBER(B49)),N(P49)=0),"",B49+P49) | K49: =IF(C49="","",N(D49)-N(E49)-N(F49)-N(G49)) | L49: =IF(OR(C49="",N(K49)<=0,NOT(ISNUMBER(J49))),"",J49-TODAY()) | M49: =IF(C49="","",IF(N(K49)<=0,"Sold out",IF(NOT(ISNUMBER(J49)),"In stock",IF(J49<TODAY(),"Past its date",IF(J49-TODAY()<=Settings!$C$5,"Use soon","In stock"))))) | N49: =IF(C49="","",N(D49)*Q49) | P49: =IF(C49="",0,IFERROR(N(INDEX(Products!$E$6:$E$45,MATCH(C49,Products!$B$6:$B$45,0))),0)) | Q49: =IF(C49="",0,IFERROR(N(INDEX(Products!$I$6:$I$45,MATCH(C49,Products!$B$6:$B$45,0))),0)) | R49: =IF(OR(C49="",NOT(ISNUMBER(B49))),"",YEAR(B49)*100+MONTH(B49)) | S49: =N(G49)*Q49 | T49: =IF(OR(M49="",M49="Sold out",NOT(ISNUMBER(J49))),"",J49*1000+ROW())
B50: 46285 | C50: Brownies | D50: 16 | E50: 13 | F50: 0 | G50: 3 | I50: =IF(OR(C50="",NOT(ISNUMBER(B50))),"",UPPER(IF(IFERROR(IF(INDEX(Products!$C$6:$C$45,MATCH(C50,Products!$B$6:$B$45,0))="","",INDEX(Products!$C$6:$C$45,MATCH(C50,Products!$B$6:$B$45,0))),"")="",LEFT(SUBSTITUTE(C50," ",""),3),IFERROR(IF(INDEX(Products!$C$6:$C$45,MATCH(C50,Products!$B$6:$B$45,0))="","",INDEX(Products!$C$6:$C$45,MATCH(C50,Products!$B$6:$B$45,0))),"")))&"-"&RIGHT(YEAR(B50),2)&RIGHT("0"&MONTH(B50),2)&RIGHT("0"&DAY(B50),2)&"-"&COUNTIFS(C$6:C50,C50,B$6:B50,B50)) | J50: =IF(OR(C50="",NOT(ISNUMBER(B50)),N(P50)=0),"",B50+P50) | K50: =IF(C50="","",N(D50)-N(E50)-N(F50)-N(G50)) | L50: =IF(OR(C50="",N(K50)<=0,NOT(ISNUMBER(J50))),"",J50-TODAY()) | M50: =IF(C50="","",IF(N(K50)<=0,"Sold out",IF(NOT(ISNUMBER(J50)),"In stock",IF(J50<TODAY(),"Past its date",IF(J50-TODAY()<=Settings!$C$5,"Use soon","In stock"))))) | N50: =IF(C50="","",N(D50)*Q50) | P50: =IF(C50="",0,IFERROR(N(INDEX(Products!$E$6:$E$45,MATCH(C50,Products!$B$6:$B$45,0))),0)) | Q50: =IF(C50="",0,IFERROR(N(INDEX(Products!$I$6:$I$45,MATCH(C50,Products!$B$6:$B$45,0))),0)) | R50: =IF(OR(C50="",NOT(ISNUMBER(B50))),"",YEAR(B50)*100+MONTH(B50)) | S50: =N(G50)*Q50 | T50: =IF(OR(M50="",M50="Sold out",NOT(ISNUMBER(J50))),"",J50*1000+ROW())
B51: 46289 | C51: Brownies | D51: 16 | E51: 10 | F51: 2 | G51: 0 | I51: =IF(OR(C51="",NOT(ISNUMBER(B51))),"",UPPER(IF(IFERROR(IF(INDEX(Products!$C$6:$C$45,MATCH(C51,Products!$B$6:$B$45,0))="","",INDEX(Products!$C$6:$C$45,MATCH(C51,Products!$B$6:$B$45,0))),"")="",LEFT(SUBSTITUTE(C51," ",""),3),IFERROR(IF(INDEX(Products!$C$6:$C$45,MATCH(C51,Products!$B$6:$B$45,0))="","",INDEX(Products!$C$6:$C$45,MATCH(C51,Products!$B$6:$B$45,0))),"")))&"-"&RIGHT(YEAR(B51),2)&RIGHT("0"&MONTH(B51),2)&RIGHT("0"&DAY(B51),2)&"-"&COUNTIFS(C$6:C51,C51,B$6:B51,B51)) | J51: =IF(OR(C51="",NOT(ISNUMBER(B51)),N(P51)=0),"",B51+P51) | K51: =IF(C51="","",N(D51)-N(E51)-N(F51)-N(G51)) | L51: =IF(OR(C51="",N(K51)<=0,NOT(ISNUMBER(J51))),"",J51-TODAY()) | M51: =IF(C51="","",IF(N(K51)<=0,"Sold out",IF(NOT(ISNUMBER(J51)),"In stock",IF(J51<TODAY(),"Past its date",IF(J51-TODAY()<=Settings!$C$5,"Use soon","In stock"))))) | N51: =IF(C51="","",N(D51)*Q51) | P51: =IF(C51="",0,IFERROR(N(INDEX(Products!$E$6:$E$45,MATCH(C51,Products!$B$6:$B$45,0))),0)) | Q51: =IF(C51="",0,IFERROR(N(INDEX(Products!$I$6:$I$45,MATCH(C51,Products!$B$6:$B$45,0))),0)) | R51: =IF(OR(C51="",NOT(ISNUMBER(B51))),"",YEAR(B51)*100+MONTH(B51)) | S51: =N(G51)*Q51 | T51: =IF(OR(M51="",M51="Sold out",NOT(ISNUMBER(J51))),"",J51*1000+ROW())
B52: 46290 | C52: Lemon drizzle loaf | D52: 4 | E52: 2 | F52: 0 | G52: 0 | I52: =IF(OR(C52="",NOT(ISNUMBER(B52))),"",UPPER(IF(IFERROR(IF(INDEX(Products!$C$6:$C$45,MATCH(C52,Products!$B$6:$B$45,0))="","",INDEX(Products!$C$6:$C$45,MATCH(C52,Products!$B$6:$B$45,0))),"")="",LEFT(SUBSTITUTE(C52," ",""),3),IFERROR(IF(INDEX(Products!$C$6:$C$45,MATCH(C52,Products!$B$6:$B$45,0))="","",INDEX(Products!$C$6:$C$45,MATCH(C52,Products!$B$6:$B$45,0))),"")))&"-"&RIGHT(YEAR(B52),2)&RIGHT("0"&MONTH(B52),2)&RIGHT("0"&DAY(B52),2)&"-"&COUNTIFS(C$6:C52,C52,B$6:B52,B52)) | J52: =IF(OR(C52="",NOT(ISNUMBER(B52)),N(P52)=0),"",B52+P52) | K52: =IF(C52="","",N(D52)-N(E52)-N(F52)-N(G52)) | L52: =IF(OR(C52="",N(K52)<=0,NOT(ISNUMBER(J52))),"",J52-TODAY()) | M52: =IF(C52="","",IF(N(K52)<=0,"Sold out",IF(NOT(ISNUMBER(J52)),"In stock",IF(J52<TODAY(),"Past its date",IF(J52-TODAY()<=Settings!$C$5,"Use soon","In stock"))))) | N52: =IF(C52="","",N(D52)*Q52) | P52: =IF(C52="",0,IFERROR(N(INDEX(Products!$E$6:$E$45,MATCH(C52,Products!$B$6:$B$45,0))),0)) | Q52: =IF(C52="",0,IFERROR(N(INDEX(Products!$I$6:$I$45,MATCH(C52,Products!$B$6:$B$45,0))),0)) | R52: =IF(OR(C52="",NOT(ISNUMBER(B52))),"",YEAR(B52)*100+MONTH(B52)) | S52: =N(G52)*Q52 | T52: =IF(OR(M52="",M52="Sold out",NOT(ISNUMBER(J52))),"",J52*1000+ROW())
B53: 46290 | C53: Cinnamon rolls | D53: 24 | E53: 20 | F53: 0 | G53: 4 | H53: Double batch for the market | I53: =IF(OR(C53="",NOT(ISNUMBER(B53))),"",UPPER(IF(IFERROR(IF(INDEX(Products!$C$6:$C$45,MATCH(C53,Products!$B$6:$B$45,0))="","",INDEX(Products!$C$6:$C$45,MATCH(C53,Products!$B$6:$B$45,0))),"")="",LEFT(SUBSTITUTE(C53," ",""),3),IFERROR(IF(INDEX(Products!$C$6:$C$45,MATCH(C53,Products!$B$6:$B$45,0))="","",INDEX(Products!$C$6:$C$45,MATCH(C53,Products!$B$6:$B$45,0))),"")))&"-"&RIGHT(YEAR(B53),2)&RIGHT("0"&MONTH(B53),2)&RIGHT("0"&DAY(B53),2)&"-"&COUNTIFS(C$6:C53,C53,B$6:B53,B53)) | J53: =IF(OR(C53="",NOT(ISNUMBER(B53)),N(P53)=0),"",B53+P53) | K53: =IF(C53="","",N(D53)-N(E53)-N(F53)-N(G53)) | L53: =IF(OR(C53="",N(K53)<=0,NOT(ISNUMBER(J53))),"",J53-TODAY()) | M53: =IF(C53="","",IF(N(K53)<=0,"Sold out",IF(NOT(ISNUMBER(J53)),"In stock",IF(J53<TODAY(),"Past its date",IF(J53-TODAY()<=Settings!$C$5,"Use soon","In stock"))))) | N53: =IF(C53="","",N(D53)*Q53) | P53: =IF(C53="",0,IFERROR(N(INDEX(Products!$E$6:$E$45,MATCH(C53,Products!$B$6:$B$45,0))),0)) | Q53: =IF(C53="",0,IFERROR(N(INDEX(Products!$I$6:$I$45,MATCH(C53,Products!$B$6:$B$45,0))),0)) | R53: =IF(OR(C53="",NOT(ISNUMBER(B53))),"",YEAR(B53)*100+MONTH(B53)) | S53: =N(G53)*Q53 | T53: =IF(OR(M53="",M53="Sold out",NOT(ISNUMBER(J53))),"",J53*1000+ROW())
B54: 46291 | C54: Chocolate chip cookies | D54: 8 | E54: 5 | F54: 0 | G54: 0 | I54: =IF(OR(C54="",NOT(ISNUMBER(B54))),"",UPPER(IF(IFERROR(IF(INDEX(Products!$C$6:$C$45,MATCH(C54,Products!$B$6:$B$45,0))="","",INDEX(Products!$C$6:$C$45,MATCH(C54,Products!$B$6:$B$45,0))),"")="",LEFT(SUBSTITUTE(C54," ",""),3),IFERROR(IF(INDEX(Products!$C$6:$C$45,MATCH(C54,Products!$B$6:$B$45,0))="","",INDEX(Products!$C$6:$C$45,MATCH(C54,Products!$B$6:$B$45,0))),"")))&"-"&RIGHT(YEAR(B54),2)&RIGHT("0"&MONTH(B54),2)&RIGHT("0"&DAY(B54),2)&"-"&COUNTIFS(C$6:C54,C54,B$6:B54,B54)) | J54: =IF(OR(C54="",NOT(ISNUMBER(B54)),N(P54)=0),"",B54+P54) | K54: =IF(C54="","",N(D54)-N(E54)-N(F54)-N(G54)) | L54: =IF(OR(C54="",N(K54)<=0,NOT(ISNUMBER(J54))),"",J54-TODAY()) | M54: =IF(C54="","",IF(N(K54)<=0,"Sold out",IF(NOT(ISNUMBER(J54)),"In stock",IF(J54<TODAY(),"Past its date",IF(J54-TODAY()<=Settings!$C$5,"Use soon","In stock"))))) | N54: =IF(C54="","",N(D54)*Q54) | P54: =IF(C54="",0,IFERROR(N(INDEX(Products!$E$6:$E$45,MATCH(C54,Products!$B$6:$B$45,0))),0)) | Q54: =IF(C54="",0,IFERROR(N(INDEX(Products!$I$6:$I$45,MATCH(C54,Products!$B$6:$B$45,0))),0)) | R54: =IF(OR(C54="",NOT(ISNUMBER(B54))),"",YEAR(B54)*100+MONTH(B54)) | S54: =N(G54)*Q54 | T54: =IF(OR(M54="",M54="Sold out",NOT(ISNUMBER(J54))),"",J54*1000+ROW())
B55: 46291 | C55: Cinnamon rolls | D55: 12 | E55: 9 | F55: 0 | G55: 0 | I55: =IF(OR(C55="",NOT(ISNUMBER(B55))),"",UPPER(IF(IFERROR(IF(INDEX(Products!$C$6:$C$45,MATCH(C55,Products!$B$6:$B$45,0))="","",INDEX(Products!$C$6:$C$45,MATCH(C55,Products!$B$6:$B$45,0))),"")="",LEFT(SUBSTITUTE(C55," ",""),3),IFERROR(IF(INDEX(Products!$C$6:$C$45,MATCH(C55,Products!$B$6:$B$45,0))="","",INDEX(Products!$C$6:$C$45,MATCH(C55,Products!$B$6:$B$45,0))),"")))&"-"&RIGHT(YEAR(B55),2)&RIGHT("0"&MONTH(B55),2)&RIGHT("0"&DAY(B55),2)&"-"&COUNTIFS(C$6:C55,C55,B$6:B55,B55)) | J55: =IF(OR(C55="",NOT(ISNUMBER(B55)),N(P55)=0),"",B55+P55) | K55: =IF(C55="","",N(D55)-N(E55)-N(F55)-N(G55)) | L55: =IF(OR(C55="",N(K55)<=0,NOT(ISNUMBER(J55))),"",J55-TODAY()) | M55: =IF(C55="","",IF(N(K55)<=0,"Sold out",IF(NOT(ISNUMBER(J55)),"In stock",IF(J55<TODAY(),"Past its date",IF(J55-TODAY()<=Settings!$C$5,"Use soon","In stock"))))) | N55: =IF(C55="","",N(D55)*Q55) | P55: =IF(C55="",0,IFERROR(N(INDEX(Products!$E$6:$E$45,MATCH(C55,Products!$B$6:$B$45,0))),0)) | Q55: =IF(C55="",0,IFERROR(N(INDEX(Products!$I$6:$I$45,MATCH(C55,Products!$B$6:$B$45,0))),0)) | R55: =IF(OR(C55="",NOT(ISNUMBER(B55))),"",YEAR(B55)*100+MONTH(B55)) | S55: =N(G55)*Q55 | T55: =IF(OR(M55="",M55="Sold out",NOT(ISNUMBER(J55))),"",J55*1000+ROW())
B56: 46292 | C56: Sourdough loaf | D56: 4 | E56: 3 | F56: 0 | G56: 0 | I56: =IF(OR(C56="",NOT(ISNUMBER(B56))),"",UPPER(IF(IFERROR(IF(INDEX(Products!$C$6:$C$45,MATCH(C56,Products!$B$6:$B$45,0))="","",INDEX(Products!$C$6:$C$45,MATCH(C56,Products!$B$6:$B$45,0))),"")="",LEFT(SUBSTITUTE(C56," ",""),3),IFERROR(IF(INDEX(Products!$C$6:$C$45,MATCH(C56,Products!$B$6:$B$45,0))="","",INDEX(Products!$C$6:$C$45,MATCH(C56,Products!$B$6:$B$45,0))),"")))&"-"&RIGHT(YEAR(B56),2)&RIGHT("0"&MONTH(B56),2)&RIGHT("0"&DAY(B56),2)&"-"&COUNTIFS(C$6:C56,C56,B$6:B56,B56)) | J56: =IF(OR(C56="",NOT(ISNUMBER(B56)),N(P56)=0),"",B56+P56) | K56: =IF(C56="","",N(D56)-N(E56)-N(F56)-N(G56)) | L56: =IF(OR(C56="",N(K56)<=0,NOT(ISNUMBER(J56))),"",J56-TODAY()) | M56: =IF(C56="","",IF(N(K56)<=0,"Sold out",IF(NOT(ISNUMBER(J56)),"In stock",IF(J56<TODAY(),"Past its date",IF(J56-TODAY()<=Settings!$C$5,"Use soon","In stock"))))) | N56: =IF(C56="","",N(D56)*Q56) | P56: =IF(C56="",0,IFERROR(N(INDEX(Products!$E$6:$E$45,MATCH(C56,Products!$B$6:$B$45,0))),0)) | Q56: =IF(C56="",0,IFERROR(N(INDEX(Products!$I$6:$I$45,MATCH(C56,Products!$B$6:$B$45,0))),0)) | R56: =IF(OR(C56="",NOT(ISNUMBER(B56))),"",YEAR(B56)*100+MONTH(B56)) | S56: =N(G56)*Q56 | T56: =IF(OR(M56="",M56="Sold out",NOT(ISNUMBER(J56))),"",J56*1000+ROW())
I57: =IF(OR(C57="",NOT(ISNUMBER(B57))),"",UPPER(IF(IFERROR(IF(INDEX(Products!$C$6:$C$45,MATCH(C57,Products!$B$6:$B$45,0))="","",INDEX(Products!$C$6:$C$45,MATCH(C57,Products!$B$6:$B$45,0))),"")="",LEFT(SUBSTITUTE(C57," ",""),3),IFERROR(IF(INDEX(Products!$C$6:$C$45,MATCH(C57,Products!$B$6:$B$45,0))="","",INDEX(Products!$C$6:$C$45,MATCH(C57,Products!$B$6:$B$45,0))),"")))&"-"&RIGHT(YEAR(B57),2)&RIGHT("0"&MONTH(B57),2)&RIGHT("0"&DAY(B57),2)&"-"&COUNTIFS(C$6:C57,C57,B$6:B57,B57)) | J57: =IF(OR(C57="",NOT(ISNUMBER(B57)),N(P57)=0),"",B57+P57) | K57: =IF(C57="","",N(D57)-N(E57)-N(F57)-N(G57)) | L57: =IF(OR(C57="",N(K57)<=0,NOT(ISNUMBER(J57))),"",J57-TODAY()) | M57: =IF(C57="","",IF(N(K57)<=0,"Sold out",IF(NOT(ISNUMBER(J57)),"In stock",IF(J57<TODAY(),"Past its date",IF(J57-TODAY()<=Settings!$C$5,"Use soon","In stock"))))) | N57: =IF(C57="","",N(D57)*Q57) | P57: =IF(C57="",0,IFERROR(N(INDEX(Products!$E$6:$E$45,MATCH(C57,Products!$B$6:$B$45,0))),0)) | Q57: =IF(C57="",0,IFERROR(N(INDEX(Products!$I$6:$I$45,MATCH(C57,Products!$B$6:$B$45,0))),0)) | R57: =IF(OR(C57="",NOT(ISNUMBER(B57))),"",YEAR(B57)*100+MONTH(B57)) | S57: =N(G57)*Q57 | T57: =IF(OR(M57="",M57="Sold out",NOT(ISNUMBER(J57))),"",J57*1000+ROW())
I58: =IF(OR(C58="",NOT(ISNUMBER(B58))),"",UPPER(IF(IFERROR(IF(INDEX(Products!$C$6:$C$45,MATCH(C58,Products!$B$6:$B$45,0))="","",INDEX(Products!$C$6:$C$45,MATCH(C58,Products!$B$6:$B$45,0))),"")="",LEFT(SUBSTITUTE(C58," ",""),3),IFERROR(IF(INDEX(Products!$C$6:$C$45,MATCH(C58,Products!$B$6:$B$45,0))="","",INDEX(Products!$C$6:$C$45,MATCH(C58,Products!$B$6:$B$45,0))),"")))&"-"&RIGHT(YEAR(B58),2)&RIGHT("0"&MONTH(B58),2)&RIGHT("0"&DAY(B58),2)&"-"&COUNTIFS(C$6:C58,C58,B$6:B58,B58)) | J58: =IF(OR(C58="",NOT(ISNUMBER(B58)),N(P58)=0),"",B58+P58) | K58: =IF(C58="","",N(D58)-N(E58)-N(F58)-N(G58)) | L58: =IF(OR(C58="",N(K58)<=0,NOT(ISNUMBER(J58))),"",J58-TODAY()) | M58: =IF(C58="","",IF(N(K58)<=0,"Sold out",IF(NOT(ISNUMBER(J58)),"In stock",IF(J58<TODAY(),"Past its date",IF(J58-TODAY()<=Settings!$C$5,"Use soon","In stock"))))) | N58: =IF(C58="","",N(D58)*Q58) | P58: =IF(C58="",0,IFERROR(N(INDEX(Products!$E$6:$E$45,MATCH(C58,Products!$B$6:$B$45,0))),0)) | Q58: =IF(C58="",0,IFERROR(N(INDEX(Products!$I$6:$I$45,MATCH(C58,Products!$B$6:$B$45,0))),0)) | R58: =IF(OR(C58="",NOT(ISNUMBER(B58))),"",YEAR(B58)*100+MONTH(B58)) | S58: =N(G58)*Q58 | T58: =IF(OR(M58="",M58="Sold out",NOT(ISNUMBER(J58))),"",J58*1000+ROW())
I59: =IF(OR(C59="",NOT(ISNUMBER(B59))),"",UPPER(IF(IFERROR(IF(INDEX(Products!$C$6:$C$45,MATCH(C59,Products!$B$6:$B$45,0))="","",INDEX(Products!$C$6:$C$45,MATCH(C59,Products!$B$6:$B$45,0))),"")="",LEFT(SUBSTITUTE(C59," ",""),3),IFERROR(IF(INDEX(Products!$C$6:$C$45,MATCH(C59,Products!$B$6:$B$45,0))="","",INDEX(Products!$C$6:$C$45,MATCH(C59,Products!$B$6:$B$45,0))),"")))&"-"&RIGHT(YEAR(B59),2)&RIGHT("0"&MONTH(B59),2)&RIGHT("0"&DAY(B59),2)&"-"&COUNTIFS(C$6:C59,C59,B$6:B59,B59)) | J59: =IF(OR(C59="",NOT(ISNUMBER(B59)),N(P59)=0),"",B59+P59) | K59: =IF(C59="","",N(D59)-N(E59)-N(F59)-N(G59)) | L59: =IF(OR(C59="",N(K59)<=0,NOT(ISNUMBER(J59))),"",J59-TODAY()) | M59: =IF(C59="","",IF(N(K59)<=0,"Sold out",IF(NOT(ISNUMBER(J59)),"In stock",IF(J59<TODAY(),"Past its date",IF(J59-TODAY()<=Settings!$C$5,"Use soon","In stock"))))) | N59: =IF(C59="","",N(D59)*Q59) | P59: =IF(C59="",0,IFERROR(N(INDEX(Products!$E$6:$E$45,MATCH(C59,Products!$B$6:$B$45,0))),0)) | Q59: =IF(C59="",0,IFERROR(N(INDEX(Products!$I$6:$I$45,MATCH(C59,Products!$B$6:$B$45,0))),0)) | R59: =IF(OR(C59="",NOT(ISNUMBER(B59))),"",YEAR(B59)*100+MONTH(B59)) | S59: =N(G59)*Q59 | T59: =IF(OR(M59="",M59="Sold out",NOT(ISNUMBER(J59))),"",J59*1000+ROW())
I60: =IF(OR(C60="",NOT(ISNUMBER(B60))),"",UPPER(IF(IFERROR(IF(INDEX(Products!$C$6:$C$45,MATCH(C60,Products!$B$6:$B$45,0))="","",INDEX(Products!$C$6:$C$45,MATCH(C60,Products!$B$6:$B$45,0))),"")="",LEFT(SUBSTITUTE(C60," ",""),3),IFERROR(IF(INDEX(Products!$C$6:$C$45,MATCH(C60,Products!$B$6:$B$45,0))="","",INDEX(Products!$C$6:$C$45,MATCH(C60,Products!$B$6:$B$45,0))),"")))&"-"&RIGHT(YEAR(B60),2)&RIGHT("0"&MONTH(B60),2)&RIGHT("0"&DAY(B60),2)&"-"&COUNTIFS(C$6:C60,C60,B$6:B60,B60)) | J60: =IF(OR(C60="",NOT(ISNUMBER(B60)),N(P60)=0),"",B60+P60) | K60: =IF(C60="","",N(D60)-N(E60)-N(F60)-N(G60)) | L60: =IF(OR(C60="",N(K60)<=0,NOT(ISNUMBER(J60))),"",J60-TODAY()) | M60: =IF(C60="","",IF(N(K60)<=0,"Sold out",IF(NOT(ISNUMBER(J60)),"In stock",IF(J60<TODAY(),"Past its date",IF(J60-TODAY()<=Settings!$C$5,"Use soon","In stock"))))) | N60: =IF(C60="","",N(D60)*Q60) | P60: =IF(C60="",0,IFERROR(N(INDEX(Products!$E$6:$E$45,MATCH(C60,Products!$B$6:$B$45,0))),0)) | Q60: =IF(C60="",0,IFERROR(N(INDEX(Products!$I$6:$I$45,MATCH(C60,Products!$B$6:$B$45,0))),0)) | R60: =IF(OR(C60="",NOT(ISNUMBER(B60))),"",YEAR(B60)*100+MONTH(B60)) | S60: =N(G60)*Q60 | T60: =IF(OR(M60="",M60="Sold out",NOT(ISNUMBER(J60))),"",J60*1000+ROW())
I61: =IF(OR(C61="",NOT(ISNUMBER(B61))),"",UPPER(IF(IFERROR(IF(INDEX(Products!$C$6:$C$45,MATCH(C61,Products!$B$6:$B$45,0))="","",INDEX(Products!$C$6:$C$45,MATCH(C61,Products!$B$6:$B$45,0))),"")="",LEFT(SUBSTITUTE(C61," ",""),3),IFERROR(IF(INDEX(Products!$C$6:$C$45,MATCH(C61,Products!$B$6:$B$45,0))="","",INDEX(Products!$C$6:$C$45,MATCH(C61,Products!$B$6:$B$45,0))),"")))&"-"&RIGHT(YEAR(B61),2)&RIGHT("0"&MONTH(B61),2)&RIGHT("0"&DAY(B61),2)&"-"&COUNTIFS(C$6:C61,C61,B$6:B61,B61)) | J61: =IF(OR(C61="",NOT(ISNUMBER(B61)),N(P61)=0),"",B61+P61) | K61: =IF(C61="","",N(D61)-N(E61)-N(F61)-N(G61)) | L61: =IF(OR(C61="",N(K61)<=0,NOT(ISNUMBER(J61))),"",J61-TODAY()) | M61: =IF(C61="","",IF(N(K61)<=0,"Sold out",IF(NOT(ISNUMBER(J61)),"In stock",IF(J61<TODAY(),"Past its date",IF(J61-TODAY()<=Settings!$C$5,"Use soon","In stock"))))) | N61: =IF(C61="","",N(D61)*Q61) | P61: =IF(C61="",0,IFERROR(N(INDEX(Products!$E$6:$E$45,MATCH(C61,Products!$B$6:$B$45,0))),0)) | Q61: =IF(C61="",0,IFERROR(N(INDEX(Products!$I$6:$I$45,MATCH(C61,Products!$B$6:$B$45,0))),0)) | R61: =IF(OR(C61="",NOT(ISNUMBER(B61))),"",YEAR(B61)*100+MONTH(B61)) | S61: =N(G61)*Q61 | T61: =IF(OR(M61="",M61="Sold out",NOT(ISNUMBER(J61))),"",J61*1000+ROW())
I62: =IF(OR(C62="",NOT(ISNUMBER(B62))),"",UPPER(IF(IFERROR(IF(INDEX(Products!$C$6:$C$45,MATCH(C62,Products!$B$6:$B$45,0))="","",INDEX(Products!$C$6:$C$45,MATCH(C62,Products!$B$6:$B$45,0))),"")="",LEFT(SUBSTITUTE(C62," ",""),3),IFERROR(IF(INDEX(Products!$C$6:$C$45,MATCH(C62,Products!$B$6:$B$45,0))="","",INDEX(Products!$C$6:$C$45,MATCH(C62,Products!$B$6:$B$45,0))),"")))&"-"&RIGHT(YEAR(B62),2)&RIGHT("0"&MONTH(B62),2)&RIGHT("0"&DAY(B62),2)&"-"&COUNTIFS(C$6:C62,C62,B$6:B62,B62)) | J62: =IF(OR(C62="",NOT(ISNUMBER(B62)),N(P62)=0),"",B62+P62) | K62: =IF(C62="","",N(D62)-N(E62)-N(F62)-N(G62)) | L62: =IF(OR(C62="",N(K62)<=0,NOT(ISNUMBER(J62))),"",J62-TODAY()) | M62: =IF(C62="","",IF(N(K62)<=0,"Sold out",IF(NOT(ISNUMBER(J62)),"In stock",IF(J62<TODAY(),"Past its date",IF(J62-TODAY()<=Settings!$C$5,"Use soon","In stock"))))) | N62: =IF(C62="","",N(D62)*Q62) | P62: =IF(C62="",0,IFERROR(N(INDEX(Products!$E$6:$E$45,MATCH(C62,Products!$B$6:$B$45,0))),0)) | Q62: =IF(C62="",0,IFERROR(N(INDEX(Products!$I$6:$I$45,MATCH(C62,Products!$B$6:$B$45,0))),0)) | R62: =IF(OR(C62="",NOT(ISNUMBER(B62))),"",YEAR(B62)*100+MONTH(B62)) | S62: =N(G62)*Q62 | T62: =IF(OR(M62="",M62="Sold out",NOT(ISNUMBER(J62))),"",J62*1000+ROW())
I63: =IF(OR(C63="",NOT(ISNUMBER(B63))),"",UPPER(IF(IFERROR(IF(INDEX(Products!$C$6:$C$45,MATCH(C63,Products!$B$6:$B$45,0))="","",INDEX(Products!$C$6:$C$45,MATCH(C63,Products!$B$6:$B$45,0))),"")="",LEFT(SUBSTITUTE(C63," ",""),3),IFERROR(IF(INDEX(Products!$C$6:$C$45,MATCH(C63,Products!$B$6:$B$45,0))="","",INDEX(Products!$C$6:$C$45,MATCH(C63,Products!$B$6:$B$45,0))),"")))&"-"&RIGHT(YEAR(B63),2)&RIGHT("0"&MONTH(B63),2)&RIGHT("0"&DAY(B63),2)&"-"&COUNTIFS(C$6:C63,C63,B$6:B63,B63)) | J63: =IF(OR(C63="",NOT(ISNUMBER(B63)),N(P63)=0),"",B63+P63) | K63: =IF(C63="","",N(D63)-N(E63)-N(F63)-N(G63)) | L63: =IF(OR(C63="",N(K63)<=0,NOT(ISNUMBER(J63))),"",J63-TODAY()) | M63: =IF(C63="","",IF(N(K63)<=0,"Sold out",IF(NOT(ISNUMBER(J63)),"In stock",IF(J63<TODAY(),"Past its date",IF(J63-TODAY()<=Settings!$C$5,"Use soon","In stock"))))) | N63: =IF(C63="","",N(D63)*Q63) | P63: =IF(C63="",0,IFERROR(N(INDEX(Products!$E$6:$E$45,MATCH(C63,Products!$B$6:$B$45,0))),0)) | Q63: =IF(C63="",0,IFERROR(N(INDEX(Products!$I$6:$I$45,MATCH(C63,Products!$B$6:$B$45,0))),0)) | R63: =IF(OR(C63="",NOT(ISNUMBER(B63))),"",YEAR(B63)*100+MONTH(B63)) | S63: =N(G63)*Q63 | T63: =IF(OR(M63="",M63="Sold out",NOT(ISNUMBER(J63))),"",J63*1000+ROW())
I64: =IF(OR(C64="",NOT(ISNUMBER(B64))),"",UPPER(IF(IFERROR(IF(INDEX(Products!$C$6:$C$45,MATCH(C64,Products!$B$6:$B$45,0))="","",INDEX(Products!$C$6:$C$45,MATCH(C64,Products!$B$6:$B$45,0))),"")="",LEFT(SUBSTITUTE(C64," ",""),3),IFERROR(IF(INDEX(Products!$C$6:$C$45,MATCH(C64,Products!$B$6:$B$45,0))="","",INDEX(Products!$C$6:$C$45,MATCH(C64,Products!$B$6:$B$45,0))),"")))&"-"&RIGHT(YEAR(B64),2)&RIGHT("0"&MONTH(B64),2)&RIGHT("0"&DAY(B64),2)&"-"&COUNTIFS(C$6:C64,C64,B$6:B64,B64)) | J64: =IF(OR(C64="",NOT(ISNUMBER(B64)),N(P64)=0),"",B64+P64) | K64: =IF(C64="","",N(D64)-N(E64)-N(F64)-N(G64)) | L64: =IF(OR(C64="",N(K64)<=0,NOT(ISNUMBER(J64))),"",J64-TODAY()) | M64: =IF(C64="","",IF(N(K64)<=0,"Sold out",IF(NOT(ISNUMBER(J64)),"In stock",IF(J64<TODAY(),"Past its date",IF(J64-TODAY()<=Settings!$C$5,"Use soon","In stock"))))) | N64: =IF(C64="","",N(D64)*Q64) | P64: =IF(C64="",0,IFERROR(N(INDEX(Products!$E$6:$E$45,MATCH(C64,Products!$B$6:$B$45,0))),0)) | Q64: =IF(C64="",0,IFERROR(N(INDEX(Products!$I$6:$I$45,MATCH(C64,Products!$B$6:$B$45,0))),0)) | R64: =IF(OR(C64="",NOT(ISNUMBER(B64))),"",YEAR(B64)*100+MONTH(B64)) | S64: =N(G64)*Q64 | T64: =IF(OR(M64="",M64="Sold out",NOT(ISNUMBER(J64))),"",J64*1000+ROW())
I65: =IF(OR(C65="",NOT(ISNUMBER(B65))),"",UPPER(IF(IFERROR(IF(INDEX(Products!$C$6:$C$45,MATCH(C65,Products!$B$6:$B$45,0))="","",INDEX(Products!$C$6:$C$45,MATCH(C65,Products!$B$6:$B$45,0))),"")="",LEFT(SUBSTITUTE(C65," ",""),3),IFERROR(IF(INDEX(Products!$C$6:$C$45,MATCH(C65,Products!$B$6:$B$45,0))="","",INDEX(Products!$C$6:$C$45,MATCH(C65,Products!$B$6:$B$45,0))),"")))&"-"&RIGHT(YEAR(B65),2)&RIGHT("0"&MONTH(B65),2)&RIGHT("0"&DAY(B65),2)&"-"&COUNTIFS(C$6:C65,C65,B$6:B65,B65)) | J65: =IF(OR(C65="",NOT(ISNUMBER(B65)),N(P65)=0),"",B65+P65) | K65: =IF(C65="","",N(D65)-N(E65)-N(F65)-N(G65)) | L65: =IF(OR(C65="",N(K65)<=0,NOT(ISNUMBER(J65))),"",J65-TODAY()) | M65: =IF(C65="","",IF(N(K65)<=0,"Sold out",IF(NOT(ISNUMBER(J65)),"In stock",IF(J65<TODAY(),"Past its date",IF(J65-TODAY()<=Settings!$C$5,"Use soon","In stock"))))) | N65: =IF(C65="","",N(D65)*Q65) | P65: =IF(C65="",0,IFERROR(N(INDEX(Products!$E$6:$E$45,MATCH(C65,Products!$B$6:$B$45,0))),0)) | Q65: =IF(C65="",0,IFERROR(N(INDEX(Products!$I$6:$I$45,MATCH(C65,Products!$B$6:$B$45,0))),0)) | R65: =IF(OR(C65="",NOT(ISNUMBER(B65))),"",YEAR(B65)*100+MONTH(B65)) | S65: =N(G65)*Q65 | T65: =IF(OR(M65="",M65="Sold out",NOT(ISNUMBER(J65))),"",J65*1000+ROW())
I66: =IF(OR(C66="",NOT(ISNUMBER(B66))),"",UPPER(IF(IFERROR(IF(INDEX(Products!$C$6:$C$45,MATCH(C66,Products!$B$6:$B$45,0))="","",INDEX(Products!$C$6:$C$45,MATCH(C66,Products!$B$6:$B$45,0))),"")="",LEFT(SUBSTITUTE(C66," ",""),3),IFERROR(IF(INDEX(Products!$C$6:$C$45,MATCH(C66,Products!$B$6:$B$45,0))="","",INDEX(Products!$C$6:$C$45,MATCH(C66,Products!$B$6:$B$45,0))),"")))&"-"&RIGHT(YEAR(B66),2)&RIGHT("0"&MONTH(B66),2)&RIGHT("0"&DAY(B66),2)&"-"&COUNTIFS(C$6:C66,C66,B$6:B66,B66)) | J66: =IF(OR(C66="",NOT(ISNUMBER(B66)),N(P66)=0),"",B66+P66) | K66: =IF(C66="","",N(D66)-N(E66)-N(F66)-N(G66)) | L66: =IF(OR(C66="",N(K66)<=0,NOT(ISNUMBER(J66))),"",J66-TODAY()) | M66: =IF(C66="","",IF(N(K66)<=0,"Sold out",IF(NOT(ISNUMBER(J66)),"In stock",IF(J66<TODAY(),"Past its date",IF(J66-TODAY()<=Settings!$C$5,"Use soon","In stock"))))) | N66: =IF(C66="","",N(D66)*Q66) | P66: =IF(C66="",0,IFERROR(N(INDEX(Products!$E$6:$E$45,MATCH(C66,Products!$B$6:$B$45,0))),0)) | Q66: =IF(C66="",0,IFERROR(N(INDEX(Products!$I$6:$I$45,MATCH(C66,Products!$B$6:$B$45,0))),0)) | R66: =IF(OR(C66="",NOT(ISNUMBER(B66))),"",YEAR(B66)*100+MONTH(B66)) | S66: =N(G66)*Q66 | T66: =IF(OR(M66="",M66="Sold out",NOT(ISNUMBER(J66))),"",J66*1000+ROW())
I67: =IF(OR(C67="",NOT(ISNUMBER(B67))),"",UPPER(IF(IFERROR(IF(INDEX(Products!$C$6:$C$45,MATCH(C67,Products!$B$6:$B$45,0))="","",INDEX(Products!$C$6:$C$45,MATCH(C67,Products!$B$6:$B$45,0))),"")="",LEFT(SUBSTITUTE(C67," ",""),3),IFERROR(IF(INDEX(Products!$C$6:$C$45,MATCH(C67,Products!$B$6:$B$45,0))="","",INDEX(Products!$C$6:$C$45,MATCH(C67,Products!$B$6:$B$45,0))),"")))&"-"&RIGHT(YEAR(B67),2)&RIGHT("0"&MONTH(B67),2)&RIGHT("0"&DAY(B67),2)&"-"&COUNTIFS(C$6:C67,C67,B$6:B67,B67)) | J67: =IF(OR(C67="",NOT(ISNUMBER(B67)),N(P67)=0),"",B67+P67) | K67: =IF(C67="","",N(D67)-N(E67)-N(F67)-N(G67)) | L67: =IF(OR(C67="",N(K67)<=0,NOT(ISNUMBER(J67))),"",J67-TODAY()) | M67: =IF(C67="","",IF(N(K67)<=0,"Sold out",IF(NOT(ISNUMBER(J67)),"In stock",IF(J67<TODAY(),"Past its date",IF(J67-TODAY()<=Settings!$C$5,"Use soon","In stock"))))) | N67: =IF(C67="","",N(D67)*Q67) | P67: =IF(C67="",0,IFERROR(N(INDEX(Products!$E$6:$E$45,MATCH(C67,Products!$B$6:$B$45,0))),0)) | Q67: =IF(C67="",0,IFERROR(N(INDEX(Products!$I$6:$I$45,MATCH(C67,Products!$B$6:$B$45,0))),0)) | R67: =IF(OR(C67="",NOT(ISNUMBER(B67))),"",YEAR(B67)*100+MONTH(B67)) | S67: =N(G67)*Q67 | T67: =IF(OR(M67="",M67="Sold out",NOT(ISNUMBER(J67))),"",J67*1000+ROW())
I68: =IF(OR(C68="",NOT(ISNUMBER(B68))),"",UPPER(IF(IFERROR(IF(INDEX(Products!$C$6:$C$45,MATCH(C68,Products!$B$6:$B$45,0))="","",INDEX(Products!$C$6:$C$45,MATCH(C68,Products!$B$6:$B$45,0))),"")="",LEFT(SUBSTITUTE(C68," ",""),3),IFERROR(IF(INDEX(Products!$C$6:$C$45,MATCH(C68,Products!$B$6:$B$45,0))="","",INDEX(Products!$C$6:$C$45,MATCH(C68,Products!$B$6:$B$45,0))),"")))&"-"&RIGHT(YEAR(B68),2)&RIGHT("0"&MONTH(B68),2)&RIGHT("0"&DAY(B68),2)&"-"&COUNTIFS(C$6:C68,C68,B$6:B68,B68)) | J68: =IF(OR(C68="",NOT(ISNUMBER(B68)),N(P68)=0),"",B68+P68) | K68: =IF(C68="","",N(D68)-N(E68)-N(F68)-N(G68)) | L68: =IF(OR(C68="",N(K68)<=0,NOT(ISNUMBER(J68))),"",J68-TODAY()) | M68: =IF(C68="","",IF(N(K68)<=0,"Sold out",IF(NOT(ISNUMBER(J68)),"In stock",IF(J68<TODAY(),"Past its date",IF(J68-TODAY()<=Settings!$C$5,"Use soon","In stock"))))) | N68: =IF(C68="","",N(D68)*Q68) | P68: =IF(C68="",0,IFERROR(N(INDEX(Products!$E$6:$E$45,MATCH(C68,Products!$B$6:$B$45,0))),0)) | Q68: =IF(C68="",0,IFERROR(N(INDEX(Products!$I$6:$I$45,MATCH(C68,Products!$B$6:$B$45,0))),0)) | R68: =IF(OR(C68="",NOT(ISNUMBER(B68))),"",YEAR(B68)*100+MONTH(B68)) | S68: =N(G68)*Q68 | T68: =IF(OR(M68="",M68="Sold out",NOT(ISNUMBER(J68))),"",J68*1000+ROW())
... I505: =IF(OR(C505="",NOT(ISNUMBER(B505))),"",UPPER(IF(IFERROR(IF(INDEX(Products!$C$6:$C$45,MATCH(C505,Products!$B$6:$B$45,0))="","",INDEX(Products!$C$6:$C$45,MATCH(C505,Products!$B$6:$B$45,0))),"")="",LEFT(SUBSTITUTE(C505," ",""),3),IFERROR(IF(INDEX(Products!$C$6:$C$45,MATCH(C505,Products!$B$6:$B$45,0))="","",INDEX(Products!$C$6:$C$45,MATCH(C505,Products!$B$6:$B$45,0))),"")))&"-"&RIGHT(YEAR(B505),2)&RIGHT("0"&MONTH(B505),2)&RIGHT("0"&DAY(B505),2)&"-"&COUNTIFS(C$6:C505,C505,B$6:B505,B505)) | J505: =IF(OR(C505="",NOT(ISNUMBER(B505)),N(P505)=0),"",B505+P505) | K505: =IF(C505="","",N(D505)-N(E505)-N(F505)-N(G505)) | L505: =IF(OR(C505="",N(K505)<=0,NOT(ISNUMBER(J505))),"",J505-TODAY()) | M505: =IF(C505="","",IF(N(K505)<=0,"Sold out",IF(NOT(ISNUMBER(J505)),"In stock",IF(J505<TODAY(),"Past its date",IF(J505-TODAY()<=Settings!$C$5,"Use soon","In stock"))))) | N505: =IF(C505="","",N(D505)*Q505) | P505: =IF(C505="",0,IFERROR(N(INDEX(Products!$E$6:$E$45,MATCH(C505,Products!$B$6:$B$45,0))),0)) | Q505: =IF(C505="",0,IFERROR(N(INDEX(Products!$I$6:$I$45,MATCH(C505,Products!$B$6:$B$45,0))),0)) | R505: =IF(OR(C505="",NOT(ISNUMBER(B505))),"",YEAR(B505)*100+MONTH(B505)) | S505: =N(G505)*Q505 | T505: =IF(OR(M505="",M505="Sold out",NOT(ISNUMBER(J505))),"",J505*1000+ROW())

Sheet Label
B2: Labels for batch | D2: CCC-260926-1 | H2: =IFERROR(MATCH(D2,Batches!$I$6:$I$505,0)+5,"")
B3: Pick a batch in the yellow box, then print and cut along the lines. | H3: =IF(H2="","",INDEX(Batches!$C$1:$C$505,H2))
H4: =IF(H2="","",INDEX(Batches!$B$1:$B$505,H2))
B5: =IF($H$3="","",$H$3) | D5: =IF($H$3="","",$H$3) | H5: =IF(H2="","",INDEX(Batches!$J$1:$J$505,H2))
B6: =$H$31 | D6: =$H$31 | H6: =IF(H3="","",IFERROR(IF(INDEX(Products!$G$6:$G$45,MATCH(H3,Products!$B$6:$B$45,0))="","",INDEX(Products!$G$6:$G$45,MATCH(H3,Products!$B$6:$B$45,0))),""))
B7: =IF($H$7="","","Contains: "&$H$7&".") | D7: =IF($H$7="","","Contains: "&$H$7&".") | H7: =IF(H3="","",IFERROR(IF(INDEX(Products!$L$6:$L$45,MATCH(H3,Products!$B$6:$B$45,0))="","",INDEX(Products!$L$6:$L$45,MATCH(H3,Products!$B$6:$B$45,0))),""))
B8: =IF($H$3="","",IF($H$6="","","Net weight: "&$H$6&" ")&"Batch: "&$H$8) | D8: =IF($H$3="","",IF($H$6="","","Net weight: "&$H$6&" ")&"Batch: "&$H$8) | H8: =IF(H2="","",INDEX(Batches!$I$1:$I$505,H2))
B9: =IF($H$3="","","Made: "&DAY($H$4)&" "&CHOOSE(MONTH($H$4),"Jan","Feb","Mar","Apr","May","Jun","Jul","Aug","Sep","Oct","Nov","Dec")&" "&YEAR($H$4)&IF(ISNUMBER($H$5)," "&Settings!$C$7&": "&DAY($H$5)&" "&CHOOSE(MONTH($H$5),"Jan","Feb","Mar","Apr","May","Jun","Jul","Aug","Sep","Oct","Nov","Dec")&" "&YEAR($H$5),"")) | D9: =IF($H$3="","","Made: "&DAY($H$4)&" "&CHOOSE(MONTH($H$4),"Jan","Feb","Mar","Apr","May","Jun","Jul","Aug","Sep","Oct","Nov","Dec")&" "&YEAR($H$4)&IF(ISNUMBER($H$5)," "&Settings!$C$7&": "&DAY($H$5)&" "&CHOOSE(MONTH($H$5),"Jan","Feb","Mar","Apr","May","Jun","Jul","Aug","Sep","Oct","Nov","Dec")&" "&YEAR($H$5),"")) | H9: =IF(I9="","",INDEX(Recipes!$C$1:$C$405,100000-MOD(I9,100000))) | I9: =IFERROR(LARGE(Recipes!$I$6:$I$405,1),"")
B10: =IF(Settings!$C$8="","",Settings!$C$8&IF(Settings!$C$9="","",", "&Settings!$C$9)) | D10: =IF(Settings!$C$8="","",Settings!$C$8&IF(Settings!$C$9="","",", "&Settings!$C$9)) | H10: =IF(I10="","",INDEX(Recipes!$C$1:$C$405,100000-MOD(I10,100000))) | I10: =IFERROR(LARGE(Recipes!$I$6:$I$405,2),"")
B11: =IF(Settings!$C$10="","",Settings!$C$10) | D11: =IF(Settings!$C$10="","",Settings!$C$10) | H11: =IF(I11="","",INDEX(Recipes!$C$1:$C$405,100000-MOD(I11,100000))) | I11: =IFERROR(LARGE(Recipes!$I$6:$I$405,3),"")
H12: =IF(I12="","",INDEX(Recipes!$C$1:$C$405,100000-MOD(I12,100000))) | I12: =IFERROR(LARGE(Recipes!$I$6:$I$405,4),"")
H13: =IF(I13="","",INDEX(Recipes!$C$1:$C$405,100000-MOD(I13,100000))) | I13: =IFERROR(LARGE(Recipes!$I$6:$I$405,5),"")
B14: =IF($H$3="","",$H$3) | D14: =IF($H$3="","",$H$3) | H14: =IF(I14="","",INDEX(Recipes!$C$1:$C$405,100000-MOD(I14,100000))) | I14: =IFERROR(LARGE(Recipes!$I$6:$I$405,6),"")
B15: =$H$31 | D15: =$H$31 | H15: =IF(I15="","",INDEX(Recipes!$C$1:$C$405,100000-MOD(I15,100000))) | I15: =IFERROR(LARGE(Recipes!$I$6:$I$405,7),"")
B16: =IF($H$7="","","Contains: "&$H$7&".") | D16: =IF($H$7="","","Contains: "&$H$7&".") | H16: =IF(I16="","",INDEX(Recipes!$C$1:$C$405,100000-MOD(I16,100000))) | I16: =IFERROR(LARGE(Recipes!$I$6:$I$405,8),"")
B17: =IF($H$3="","",IF($H$6="","","Net weight: "&$H$6&" ")&"Batch: "&$H$8) | D17: =IF($H$3="","",IF($H$6="","","Net weight: "&$H$6&" ")&"Batch: "&$H$8) | H17: =IF(I17="","",INDEX(Recipes!$C$1:$C$405,100000-MOD(I17,100000))) | I17: =IFERROR(LARGE(Recipes!$I$6:$I$405,9),"")
B18: =IF($H$3="","","Made: "&DAY($H$4)&" "&CHOOSE(MONTH($H$4),"Jan","Feb","Mar","Apr","May","Jun","Jul","Aug","Sep","Oct","Nov","Dec")&" "&YEAR($H$4)&IF(ISNUMBER($H$5)," "&Settings!$C$7&": "&DAY($H$5)&" "&CHOOSE(MONTH($H$5),"Jan","Feb","Mar","Apr","May","Jun","Jul","Aug","Sep","Oct","Nov","Dec")&" "&YEAR($H$5),"")) | D18: =IF($H$3="","","Made: "&DAY($H$4)&" "&CHOOSE(MONTH($H$4),"Jan","Feb","Mar","Apr","May","Jun","Jul","Aug","Sep","Oct","Nov","Dec")&" "&YEAR($H$4)&IF(ISNUMBER($H$5)," "&Settings!$C$7&": "&DAY($H$5)&" "&CHOOSE(MONTH($H$5),"Jan","Feb","Mar","Apr","May","Jun","Jul","Aug","Sep","Oct","Nov","Dec")&" "&YEAR($H$5),"")) | H18: =IF(I18="","",INDEX(Recipes!$C$1:$C$405,100000-MOD(I18,100000))) | I18: =IFERROR(LARGE(Recipes!$I$6:$I$405,10),"")
B19: =IF(Settings!$C$8="","",Settings!$C$8&IF(Settings!$C$9="","",", "&Settings!$C$9)) | D19: =IF(Settings!$C$8="","",Settings!$C$8&IF(Settings!$C$9="","",", "&Settings!$C$9)) | H19: =IF(I19="","",INDEX(Recipes!$C$1:$C$405,100000-MOD(I19,100000))) | I19: =IFERROR(LARGE(Recipes!$I$6:$I$405,11),"")
B20: =IF(Settings!$C$10="","",Settings!$C$10) | D20: =IF(Settings!$C$10="","",Settings!$C$10) | H20: =IF(I20="","",INDEX(Recipes!$C$1:$C$405,100000-MOD(I20,100000))) | I20: =IFERROR(LARGE(Recipes!$I$6:$I$405,12),"")
H21: =IF(I21="","",INDEX(Recipes!$C$1:$C$405,100000-MOD(I21,100000))) | I21: =IFERROR(LARGE(Recipes!$I$6:$I$405,13),"")
H22: =IF(I22="","",INDEX(Recipes!$C$1:$C$405,100000-MOD(I22,100000))) | I22: =IFERROR(LARGE(Recipes!$I$6:$I$405,14),"")
B23: =IF($H$3="","",$H$3) | D23: =IF($H$3="","",$H$3) | H23: =IF(I23="","",INDEX(Recipes!$C$1:$C$405,100000-MOD(I23,100000))) | I23: =IFERROR(LARGE(Recipes!$I$6:$I$405,15),"")
B24: =$H$31 | D24: =$H$31 | H24: =IF(I24="","",INDEX(Recipes!$C$1:$C$405,100000-MOD(I24,100000))) | I24: =IFERROR(LARGE(Recipes!$I$6:$I$405,16),"")
B25: =IF($H$7="","","Contains: "&$H$7&".") | D25: =IF($H$7="","","Contains: "&$H$7&".") | H25: =IF(I25="","",INDEX(Recipes!$C$1:$C$405,100000-MOD(I25,100000))) | I25: =IFERROR(LARGE(Recipes!$I$6:$I$405,17),"")
B26: =IF($H$3="","",IF($H$6="","","Net weight: "&$H$6&" ")&"Batch: "&$H$8) | D26: =IF($H$3="","",IF($H$6="","","Net weight: "&$H$6&" ")&"Batch: "&$H$8) | H26: =IF(I26="","",INDEX(Recipes!$C$1:$C$405,100000-MOD(I26,100000))) | I26: =IFERROR(LARGE(Recipes!$I$6:$I$405,18),"")
B27: =IF($H$3="","","Made: "&DAY($H$4)&" "&CHOOSE(MONTH($H$4),"Jan","Feb","Mar","Apr","May","Jun","Jul","Aug","Sep","Oct","Nov","Dec")&" "&YEAR($H$4)&IF(ISNUMBER($H$5)," "&Settings!$C$7&": "&DAY($H$5)&" "&CHOOSE(MONTH($H$5),"Jan","Feb","Mar","Apr","May","Jun","Jul","Aug","Sep","Oct","Nov","Dec")&" "&YEAR($H$5),"")) | D27: =IF($H$3="","","Made: "&DAY($H$4)&" "&CHOOSE(MONTH($H$4),"Jan","Feb","Mar","Apr","May","Jun","Jul","Aug","Sep","Oct","Nov","Dec")&" "&YEAR($H$4)&IF(ISNUMBER($H$5)," "&Settings!$C$7&": "&DAY($H$5)&" "&CHOOSE(MONTH($H$5),"Jan","Feb","Mar","Apr","May","Jun","Jul","Aug","Sep","Oct","Nov","Dec")&" "&YEAR($H$5),"")) | H27: =IF(I27="","",INDEX(Recipes!$C$1:$C$405,100000-MOD(I27,100000))) | I27: =IFERROR(LARGE(Recipes!$I$6:$I$405,19),"")
B28: =IF(Settings!$C$8="","",Settings!$C$8&IF(Settings!$C$9="","",", "&Settings!$C$9)) | D28: =IF(Settings!$C$8="","",Settings!$C$8&IF(Settings!$C$9="","",", "&Settings!$C$9)) | H28: =IF(I28="","",INDEX(Recipes!$C$1:$C$405,100000-MOD(I28,100000))) | I28: =IFERROR(LARGE(Recipes!$I$6:$I$405,20),"")
B29: =IF(Settings!$C$10="","",Settings!$C$10) | D29: =IF(Settings!$C$10="","",Settings!$C$10) | H29: =H9&IF(H10="","",", "&H10)&IF(H11="","",", "&H11)&IF(H12="","",", "&H12)&IF(H13="","",", "&H13)&IF(H14="","",", "&H14)&IF(H15="","",", "&H15)&IF(H16="","",", "&H16)&IF(H17="","",", "&H17)&IF(H18="","",", "&H18)&IF(H19="","",", "&H19)&IF(H20="","",", "&H20)&IF(H21="","",", "&H21)&IF(H22="","",", "&H22)&IF(H23="","",", "&H23)&IF(H24="","",", "&H24)&IF(H25="","",", "&H25)&IF(H26="","",", "&H26)&IF(H27="","",", "&H27)&IF(H28="","",", "&H28)
H30: =COUNT(Recipes!$I$6:$I$405)
H31: =IF(H30=0,"",IF(H30>20,"Too many ingredients for one label: "&H30&". Keep it to 20.",IF(LEN(H29)>240,"The ingredient list is too long for this label. Shorten the names on Ingredients.","Ingredients: "&H29&".")))

Sheet Products
B2: Products
B3: Each thing you sell: how many one batch makes, how long it keeps, and its price.
B5: Product | C5: Code | D5: Items a batch | E5: Keeps (days) | F5: Price | G5: Net weight | H5: Cost a batch | I5: Cost an item | J5: Profit an item | K5: Margin | L5: Contains | M5: In stock | N5: Waste
B6: Lemon drizzle loaf | C6: LEM | D6: 2 | E6: 5 | F6: 9 | G6: 450 g | H6: =IF(B6="","",SUMIFS(Recipes!$F$6:$F$405,Recipes!$B$6:$B$405,B6)) | I6: =IF(OR(B6="",N(D6)=0),"",H6/D6) | J6: =IF(OR(NOT(ISNUMBER(I6)),N(F6)=0),"",F6-I6) | K6: =IF(NOT(ISNUMBER(J6)),"",J6/F6) | L6: =IF(OR(B6="",AE6=""),"",LEFT(AE6,LEN(AE6)-2)) | M6: =IF(B6="","",SUMIFS(Batches!$K$6:$K$505,Batches!$C$6:$C$505,B6,Batches!$M$6:$M$505,"In stock")+SUMIFS(Batches!$K$6:$K$505,Batches!$C$6:$C$505,B6,Batches!$M$6:$M$505,"Use soon")) | N6: =IF(B6="","",IF(SUMIFS(Batches!$D$6:$D$505,Batches!$C$6:$C$505,B6)=0,"",SUMIFS(Batches!$G$6:$G$505,Batches!$C$6:$C$505,B6)/SUMIFS(Batches!$D$6:$D$505,Batches!$C$6:$C$505,B6))) | P6: =IF(B6="",0,SUMIFS(Recipes!$J$6:$J$405,Recipes!$B$6:$B$405,B6)) | Q6: =IF(B6="",0,SUMIFS(Recipes!$K$6:$K$405,Recipes!$B$6:$B$405,B6)) | R6: =IF(B6="",0,SUMIFS(Recipes!$L$6:$L$405,Recipes!$B$6:$B$405,B6)) | S6: =IF(B6="",0,SUMIFS(Recipes!$M$6:$M$405,Recipes!$B$6:$B$405,B6)) | T6: =IF(B6="",0,SUMIFS(Recipes!$N$6:$N$405,Recipes!$B$6:$B$405,B6)) | U6: =IF(B6="",0,SUMIFS(Recipes!$O$6:$O$405,Recipes!$B$6:$B$405,B6)) | V6: =IF(B6="",0,SUMIFS(Recipes!$P$6:$P$405,Recipes!$B$6:$B$405,B6)) | W6: =IF(B6="",0,SUMIFS(Recipes!$Q$6:$Q$405,Recipes!$B$6:$B$405,B6)) | X6: =IF(B6="",0,SUMIFS(Recipes!$R$6:$R$405,Recipes!$B$6:$B$405,B6)) | Y6: =IF(B6="",0,SUMIFS(Recipes!$S$6:$S$405,Recipes!$B$6:$B$405,B6)) | Z6: =IF(B6="",0,SUMIFS(Recipes!$T$6:$T$405,Recipes!$B$6:$B$405,B6)) | AA6: =IF(B6="",0,SUMIFS(Recipes!$U$6:$U$405,Recipes!$B$6:$B$405,B6)) | AB6: =IF(B6="",0,SUMIFS(Recipes!$V$6:$V$405,Recipes!$B$6:$B$405,B6)) | AC6: =IF(B6="",0,SUMIFS(Recipes!$W$6:$W$405,Recipes!$B$6:$B$405,B6)) | AD6: =IF(B6="",0,SUMIFS(Recipes!$X$6:$X$405,Recipes!$B$6:$B$405,B6)) | AE6: =IF(AND(P6>0,Settings!$C$13<>""),Settings!$C$13&", ","")&IF(AND(Q6>0,Settings!$C$14<>""),Settings!$C$14&", ","")&IF(AND(R6>0,Settings!$C$15<>""),Settings!$C$15&", ","")&IF(AND(S6>0,Settings!$C$16<>""),Settings!$C$16&", ","")&IF(AND(T6>0,Settings!$C$17<>""),Settings!$C$17&", ","")&IF(AND(U6>0,Settings!$C$18<>""),Settings!$C$18&", ","")&IF(AND(V6>0,Settings!$C$19<>""),Settings!$C$19&", ","")&IF(AND(W6>0,Settings!$C$20<>""),Settings!$C$20&", ","")&IF(AND(X6>0,Settings!$C$21<>""),Settings!$C$21&", ","")&IF(AND(Y6>0,Settings!$C$22<>""),Settings!$C$22&", ","")&IF(AND(Z6>0,Settings!$C$23<>""),Settings!$C$23&", ","")&IF(AND(AA6>0,Settings!$C$24<>""),Settings!$C$24&", ","")&IF(AND(AB6>0,Settings!$C$25<>""),Settings!$C$25&", ","")&IF(AND(AC6>0,Settings!$C$26<>""),Settings!$C$26&", ","")&IF(AND(AD6>0,Settings!$C$27<>""),Settings!$C$27&", ","")
B7: Chocolate chip cookies | C7: CCC | D7: 4 | E7: 7 | F7: 5 | G7: 6 cookies, 240 g | H7: =IF(B7="","",SUMIFS(Recipes!$F$6:$F$405,Recipes!$B$6:$B$405,B7)) | I7: =IF(OR(B7="",N(D7)=0),"",H7/D7) | J7: =IF(OR(NOT(ISNUMBER(I7)),N(F7)=0),"",F7-I7) | K7: =IF(NOT(ISNUMBER(J7)),"",J7/F7) | L7: =IF(OR(B7="",AE7=""),"",LEFT(AE7,LEN(AE7)-2)) | M7: =IF(B7="","",SUMIFS(Batches!$K$6:$K$505,Batches!$C$6:$C$505,B7,Batches!$M$6:$M$505,"In stock")+SUMIFS(Batches!$K$6:$K$505,Batches!$C$6:$C$505,B7,Batches!$M$6:$M$505,"Use soon")) | N7: =IF(B7="","",IF(SUMIFS(Batches!$D$6:$D$505,Batches!$C$6:$C$505,B7)=0,"",SUMIFS(Batches!$G$6:$G$505,Batches!$C$6:$C$505,B7)/SUMIFS(Batches!$D$6:$D$505,Batches!$C$6:$C$505,B7))) | P7: =IF(B7="",0,SUMIFS(Recipes!$J$6:$J$405,Recipes!$B$6:$B$405,B7)) | Q7: =IF(B7="",0,SUMIFS(Recipes!$K$6:$K$405,Recipes!$B$6:$B$405,B7)) | R7: =IF(B7="",0,SUMIFS(Recipes!$L$6:$L$405,Recipes!$B$6:$B$405,B7)) | S7: =IF(B7="",0,SUMIFS(Recipes!$M$6:$M$405,Recipes!$B$6:$B$405,B7)) | T7: =IF(B7="",0,SUMIFS(Recipes!$N$6:$N$405,Recipes!$B$6:$B$405,B7)) | U7: =IF(B7="",0,SUMIFS(Recipes!$O$6:$O$405,Recipes!$B$6:$B$405,B7)) | V7: =IF(B7="",0,SUMIFS(Recipes!$P$6:$P$405,Recipes!$B$6:$B$405,B7)) | W7: =IF(B7="",0,SUMIFS(Recipes!$Q$6:$Q$405,Recipes!$B$6:$B$405,B7)) | X7: =IF(B7="",0,SUMIFS(Recipes!$R$6:$R$405,Recipes!$B$6:$B$405,B7)) | Y7: =IF(B7="",0,SUMIFS(Recipes!$S$6:$S$405,Recipes!$B$6:$B$405,B7)) | Z7: =IF(B7="",0,SUMIFS(Recipes!$T$6:$T$405,Recipes!$B$6:$B$405,B7)) | AA7: =IF(B7="",0,SUMIFS(Recipes!$U$6:$U$405,Recipes!$B$6:$B$405,B7)) | AB7: =IF(B7="",0,SUMIFS(Recipes!$V$6:$V$405,Recipes!$B$6:$B$405,B7)) | AC7: =IF(B7="",0,SUMIFS(Recipes!$W$6:$W$405,Recipes!$B$6:$B$405,B7)) | AD7: =IF(B7="",0,SUMIFS(Recipes!$X$6:$X$405,Recipes!$B$6:$B$405,B7)) | AE7: =IF(AND(P7>0,Settings!$C$13<>""),Settings!$C$13&", ","")&IF(AND(Q7>0,Settings!$C$14<>""),Settings!$C$14&", ","")&IF(AND(R7>0,Settings!$C$15<>""),Settings!$C$15&", ","")&IF(AND(S7>0,Settings!$C$16<>""),Settings!$C$16&", ","")&IF(AND(T7>0,Settings!$C$17<>""),Settings!$C$17&", ","")&IF(AND(U7>0,Settings!$C$18<>""),Settings!$C$18&", ","")&IF(AND(V7>0,Settings!$C$19<>""),Settings!$C$19&", ","")&IF(AND(W7>0,Settings!$C$20<>""),Settings!$C$20&", ","")&IF(AND(X7>0,Settings!$C$21<>""),Settings!$C$21&", ","")&IF(AND(Y7>0,Settings!$C$22<>""),Settings!$C$22&", ","")&IF(AND(Z7>0,Settings!$C$23<>""),Settings!$C$23&", ","")&IF(AND(AA7>0,Settings!$C$24<>""),Settings!$C$24&", ","")&IF(AND(AB7>0,Settings!$C$25<>""),Settings!$C$25&", ","")&IF(AND(AC7>0,Settings!$C$26<>""),Settings!$C$26&", ","")&IF(AND(AD7>0,Settings!$C$27<>""),Settings!$C$27&", ","")
B8: Sourdough loaf | C8: SDL | D8: 2 | E8: 3 | F8: 7.5 | G8: 800 g | H8: =IF(B8="","",SUMIFS(Recipes!$F$6:$F$405,Recipes!$B$6:$B$405,B8)) | I8: =IF(OR(B8="",N(D8)=0),"",H8/D8) | J8: =IF(OR(NOT(ISNUMBER(I8)),N(F8)=0),"",F8-I8) | K8: =IF(NOT(ISNUMBER(J8)),"",J8/F8) | L8: =IF(OR(B8="",AE8=""),"",LEFT(AE8,LEN(AE8)-2)) | M8: =IF(B8="","",SUMIFS(Batches!$K$6:$K$505,Batches!$C$6:$C$505,B8,Batches!$M$6:$M$505,"In stock")+SUMIFS(Batches!$K$6:$K$505,Batches!$C$6:$C$505,B8,Batches!$M$6:$M$505,"Use soon")) | N8: =IF(B8="","",IF(SUMIFS(Batches!$D$6:$D$505,Batches!$C$6:$C$505,B8)=0,"",SUMIFS(Batches!$G$6:$G$505,Batches!$C$6:$C$505,B8)/SUMIFS(Batches!$D$6:$D$505,Batches!$C$6:$C$505,B8))) | P8: =IF(B8="",0,SUMIFS(Recipes!$J$6:$J$405,Recipes!$B$6:$B$405,B8)) | Q8: =IF(B8="",0,SUMIFS(Recipes!$K$6:$K$405,Recipes!$B$6:$B$405,B8)) | R8: =IF(B8="",0,SUMIFS(Recipes!$L$6:$L$405,Recipes!$B$6:$B$405,B8)) | S8: =IF(B8="",0,SUMIFS(Recipes!$M$6:$M$405,Recipes!$B$6:$B$405,B8)) | T8: =IF(B8="",0,SUMIFS(Recipes!$N$6:$N$405,Recipes!$B$6:$B$405,B8)) | U8: =IF(B8="",0,SUMIFS(Recipes!$O$6:$O$405,Recipes!$B$6:$B$405,B8)) | V8: =IF(B8="",0,SUMIFS(Recipes!$P$6:$P$405,Recipes!$B$6:$B$405,B8)) | W8: =IF(B8="",0,SUMIFS(Recipes!$Q$6:$Q$405,Recipes!$B$6:$B$405,B8)) | X8: =IF(B8="",0,SUMIFS(Recipes!$R$6:$R$405,Recipes!$B$6:$B$405,B8)) | Y8: =IF(B8="",0,SUMIFS(Recipes!$S$6:$S$405,Recipes!$B$6:$B$405,B8)) | Z8: =IF(B8="",0,SUMIFS(Recipes!$T$6:$T$405,Recipes!$B$6:$B$405,B8)) | AA8: =IF(B8="",0,SUMIFS(Recipes!$U$6:$U$405,Recipes!$B$6:$B$405,B8)) | AB8: =IF(B8="",0,SUMIFS(Recipes!$V$6:$V$405,Recipes!$B$6:$B$405,B8)) | AC8: =IF(B8="",0,SUMIFS(Recipes!$W$6:$W$405,Recipes!$B$6:$B$405,B8)) | AD8: =IF(B8="",0,SUMIFS(Recipes!$X$6:$X$405,Recipes!$B$6:$B$405,B8)) | AE8: =IF(AND(P8>0,Settings!$C$13<>""),Settings!$C$13&", ","")&IF(AND(Q8>0,Settings!$C$14<>""),Settings!$C$14&", ","")&IF(AND(R8>0,Settings!$C$15<>""),Settings!$C$15&", ","")&IF(AND(S8>0,Settings!$C$16<>""),Settings!$C$16&", ","")&IF(AND(T8>0,Settings!$C$17<>""),Settings!$C$17&", ","")&IF(AND(U8>0,Settings!$C$18<>""),Settings!$C$18&", ","")&IF(AND(V8>0,Settings!$C$19<>""),Settings!$C$19&", ","")&IF(AND(W8>0,Settings!$C$20<>""),Settings!$C$20&", ","")&IF(AND(X8>0,Settings!$C$21<>""),Settings!$C$21&", ","")&IF(AND(Y8>0,Settings!$C$22<>""),Settings!$C$22&", ","")&IF(AND(Z8>0,Settings!$C$23<>""),Settings!$C$23&", ","")&IF(AND(AA8>0,Settings!$C$24<>""),Settings!$C$24&", ","")&IF(AND(AB8>0,Settings!$C$25<>""),Settings!$C$25&", ","")&IF(AND(AC8>0,Settings!$C$26<>""),Settings!$C$26&", ","")&IF(AND(AD8>0,Settings!$C$27<>""),Settings!$C$27&", ","")
B9: Strawberry jam | C9: JAM | D9: 6 | E9: 180 | F9: 6.5 | G9: 340 g | H9: =IF(B9="","",SUMIFS(Recipes!$F$6:$F$405,Recipes!$B$6:$B$405,B9)) | I9: =IF(OR(B9="",N(D9)=0),"",H9/D9) | J9: =IF(OR(NOT(ISNUMBER(I9)),N(F9)=0),"",F9-I9) | K9: =IF(NOT(ISNUMBER(J9)),"",J9/F9) | L9: =IF(OR(B9="",AE9=""),"",LEFT(AE9,LEN(AE9)-2)) | M9: =IF(B9="","",SUMIFS(Batches!$K$6:$K$505,Batches!$C$6:$C$505,B9,Batches!$M$6:$M$505,"In stock")+SUMIFS(Batches!$K$6:$K$505,Batches!$C$6:$C$505,B9,Batches!$M$6:$M$505,"Use soon")) | N9: =IF(B9="","",IF(SUMIFS(Batches!$D$6:$D$505,Batches!$C$6:$C$505,B9)=0,"",SUMIFS(Batches!$G$6:$G$505,Batches!$C$6:$C$505,B9)/SUMIFS(Batches!$D$6:$D$505,Batches!$C$6:$C$505,B9))) | P9: =IF(B9="",0,SUMIFS(Recipes!$J$6:$J$405,Recipes!$B$6:$B$405,B9)) | Q9: =IF(B9="",0,SUMIFS(Recipes!$K$6:$K$405,Recipes!$B$6:$B$405,B9)) | R9: =IF(B9="",0,SUMIFS(Recipes!$L$6:$L$405,Recipes!$B$6:$B$405,B9)) | S9: =IF(B9="",0,SUMIFS(Recipes!$M$6:$M$405,Recipes!$B$6:$B$405,B9)) | T9: =IF(B9="",0,SUMIFS(Recipes!$N$6:$N$405,Recipes!$B$6:$B$405,B9)) | U9: =IF(B9="",0,SUMIFS(Recipes!$O$6:$O$405,Recipes!$B$6:$B$405,B9)) | V9: =IF(B9="",0,SUMIFS(Recipes!$P$6:$P$405,Recipes!$B$6:$B$405,B9)) | W9: =IF(B9="",0,SUMIFS(Recipes!$Q$6:$Q$405,Recipes!$B$6:$B$405,B9)) | X9: =IF(B9="",0,SUMIFS(Recipes!$R$6:$R$405,Recipes!$B$6:$B$405,B9)) | Y9: =IF(B9="",0,SUMIFS(Recipes!$S$6:$S$405,Recipes!$B$6:$B$405,B9)) | Z9: =IF(B9="",0,SUMIFS(Recipes!$T$6:$T$405,Recipes!$B$6:$B$405,B9)) | AA9: =IF(B9="",0,SUMIFS(Recipes!$U$6:$U$405,Recipes!$B$6:$B$405,B9)) | AB9: =IF(B9="",0,SUMIFS(Recipes!$V$6:$V$405,Recipes!$B$6:$B$405,B9)) | AC9: =IF(B9="",0,SUMIFS(Recipes!$W$6:$W$405,Recipes!$B$6:$B$405,B9)) | AD9: =IF(B9="",0,SUMIFS(Recipes!$X$6:$X$405,Recipes!$B$6:$B$405,B9)) | AE9: =IF(AND(P9>0,Settings!$C$13<>""),Settings!$C$13&", ","")&IF(AND(Q9>0,Settings!$C$14<>""),Settings!$C$14&", ","")&IF(AND(R9>0,Settings!$C$15<>""),Settings!$C$15&", ","")&IF(AND(S9>0,Settings!$C$16<>""),Settings!$C$16&", ","")&IF(AND(T9>0,Settings!$C$17<>""),Settings!$C$17&", ","")&IF(AND(U9>0,Settings!$C$18<>""),Settings!$C$18&", ","")&IF(AND(V9>0,Settings!$C$19<>""),Settings!$C$19&", ","")&IF(AND(W9>0,Settings!$C$20<>""),Settings!$C$20&", ","")&IF(AND(X9>0,Settings!$C$21<>""),Settings!$C$21&", ","")&IF(AND(Y9>0,Settings!$C$22<>""),Settings!$C$22&", ","")&IF(AND(Z9>0,Settings!$C$23<>""),Settings!$C$23&", ","")&IF(AND(AA9>0,Settings!$C$24<>""),Settings!$C$24&", ","")&IF(AND(AB9>0,Settings!$C$25<>""),Settings!$C$25&", ","")&IF(AND(AC9>0,Settings!$C$26<>""),Settings!$C$26&", ","")&IF(AND(AD9>0,Settings!$C$27<>""),Settings!$C$27&", ","")
B10: Granola | C10: GRA | D10: 5 | E10: 60 | F10: 8 | G10: 400 g | H10: =IF(B10="","",SUMIFS(Recipes!$F$6:$F$405,Recipes!$B$6:$B$405,B10)) | I10: =IF(OR(B10="",N(D10)=0),"",H10/D10) | J10: =IF(OR(NOT(ISNUMBER(I10)),N(F10)=0),"",F10-I10) | K10: =IF(NOT(ISNUMBER(J10)),"",J10/F10) | L10: =IF(OR(B10="",AE10=""),"",LEFT(AE10,LEN(AE10)-2)) | M10: =IF(B10="","",SUMIFS(Batches!$K$6:$K$505,Batches!$C$6:$C$505,B10,Batches!$M$6:$M$505,"In stock")+SUMIFS(Batches!$K$6:$K$505,Batches!$C$6:$C$505,B10,Batches!$M$6:$M$505,"Use soon")) | N10: =IF(B10="","",IF(SUMIFS(Batches!$D$6:$D$505,Batches!$C$6:$C$505,B10)=0,"",SUMIFS(Batches!$G$6:$G$505,Batches!$C$6:$C$505,B10)/SUMIFS(Batches!$D$6:$D$505,Batches!$C$6:$C$505,B10))) | P10: =IF(B10="",0,SUMIFS(Recipes!$J$6:$J$405,Recipes!$B$6:$B$405,B10)) | Q10: =IF(B10="",0,SUMIFS(Recipes!$K$6:$K$405,Recipes!$B$6:$B$405,B10)) | R10: =IF(B10="",0,SUMIFS(Recipes!$L$6:$L$405,Recipes!$B$6:$B$405,B10)) | S10: =IF(B10="",0,SUMIFS(Recipes!$M$6:$M$405,Recipes!$B$6:$B$405,B10)) | T10: =IF(B10="",0,SUMIFS(Recipes!$N$6:$N$405,Recipes!$B$6:$B$405,B10)) | U10: =IF(B10="",0,SUMIFS(Recipes!$O$6:$O$405,Recipes!$B$6:$B$405,B10)) | V10: =IF(B10="",0,SUMIFS(Recipes!$P$6:$P$405,Recipes!$B$6:$B$405,B10)) | W10: =IF(B10="",0,SUMIFS(Recipes!$Q$6:$Q$405,Recipes!$B$6:$B$405,B10)) | X10: =IF(B10="",0,SUMIFS(Recipes!$R$6:$R$405,Recipes!$B$6:$B$405,B10)) | Y10: =IF(B10="",0,SUMIFS(Recipes!$S$6:$S$405,Recipes!$B$6:$B$405,B10)) | Z10: =IF(B10="",0,SUMIFS(Recipes!$T$6:$T$405,Recipes!$B$6:$B$405,B10)) | AA10: =IF(B10="",0,SUMIFS(Recipes!$U$6:$U$405,Recipes!$B$6:$B$405,B10)) | AB10: =IF(B10="",0,SUMIFS(Recipes!$V$6:$V$405,Recipes!$B$6:$B$405,B10)) | AC10: =IF(B10="",0,SUMIFS(Recipes!$W$6:$W$405,Recipes!$B$6:$B$405,B10)) | AD10: =IF(B10="",0,SUMIFS(Recipes!$X$6:$X$405,Recipes!$B$6:$B$405,B10)) | AE10: =IF(AND(P10>0,Settings!$C$13<>""),Settings!$C$13&", ","")&IF(AND(Q10>0,Settings!$C$14<>""),Settings!$C$14&", ","")&IF(AND(R10>0,Settings!$C$15<>""),Settings!$C$15&", ","")&IF(AND(S10>0,Settings!$C$16<>""),Settings!$C$16&", ","")&IF(AND(T10>0,Settings!$C$17<>""),Settings!$C$17&", ","")&IF(AND(U10>0,Settings!$C$18<>""),Settings!$C$18&", ","")&IF(AND(V10>0,Settings!$C$19<>""),Settings!$C$19&", ","")&IF(AND(W10>0,Settings!$C$20<>""),Settings!$C$20&", ","")&IF(AND(X10>0,Settings!$C$21<>""),Settings!$C$21&", ","")&IF(AND(Y10>0,Settings!$C$22<>""),Settings!$C$22&", ","")&IF(AND(Z10>0,Settings!$C$23<>""),Settings!$C$23&", ","")&IF(AND(AA10>0,Settings!$C$24<>""),Settings!$C$24&", ","")&IF(AND(AB10>0,Settings!$C$25<>""),Settings!$C$25&", ","")&IF(AND(AC10>0,Settings!$C$26<>""),Settings!$C$26&", ","")&IF(AND(AD10>0,Settings!$C$27<>""),Settings!$C$27&", ","")
B11: Cinnamon rolls | C11: CIN | D11: 12 | E11: 2 | F11: 3 | G11: 1 roll, 110 g | H11: =IF(B11="","",SUMIFS(Recipes!$F$6:$F$405,Recipes!$B$6:$B$405,B11)) | I11: =IF(OR(B11="",N(D11)=0),"",H11/D11) | J11: =IF(OR(NOT(ISNUMBER(I11)),N(F11)=0),"",F11-I11) | K11: =IF(NOT(ISNUMBER(J11)),"",J11/F11) | L11: =IF(OR(B11="",AE11=""),"",LEFT(AE11,LEN(AE11)-2)) | M11: =IF(B11="","",SUMIFS(Batches!$K$6:$K$505,Batches!$C$6:$C$505,B11,Batches!$M$6:$M$505,"In stock")+SUMIFS(Batches!$K$6:$K$505,Batches!$C$6:$C$505,B11,Batches!$M$6:$M$505,"Use soon")) | N11: =IF(B11="","",IF(SUMIFS(Batches!$D$6:$D$505,Batches!$C$6:$C$505,B11)=0,"",SUMIFS(Batches!$G$6:$G$505,Batches!$C$6:$C$505,B11)/SUMIFS(Batches!$D$6:$D$505,Batches!$C$6:$C$505,B11))) | P11: =IF(B11="",0,SUMIFS(Recipes!$J$6:$J$405,Recipes!$B$6:$B$405,B11)) | Q11: =IF(B11="",0,SUMIFS(Recipes!$K$6:$K$405,Recipes!$B$6:$B$405,B11)) | R11: =IF(B11="",0,SUMIFS(Recipes!$L$6:$L$405,Recipes!$B$6:$B$405,B11)) | S11: =IF(B11="",0,SUMIFS(Recipes!$M$6:$M$405,Recipes!$B$6:$B$405,B11)) | T11: =IF(B11="",0,SUMIFS(Recipes!$N$6:$N$405,Recipes!$B$6:$B$405,B11)) | U11: =IF(B11="",0,SUMIFS(Recipes!$O$6:$O$405,Recipes!$B$6:$B$405,B11)) | V11: =IF(B11="",0,SUMIFS(Recipes!$P$6:$P$405,Recipes!$B$6:$B$405,B11)) | W11: =IF(B11="",0,SUMIFS(Recipes!$Q$6:$Q$405,Recipes!$B$6:$B$405,B11)) | X11: =IF(B11="",0,SUMIFS(Recipes!$R$6:$R$405,Recipes!$B$6:$B$405,B11)) | Y11: =IF(B11="",0,SUMIFS(Recipes!$S$6:$S$405,Recipes!$B$6:$B$405,B11)) | Z11: =IF(B11="",0,SUMIFS(Recipes!$T$6:$T$405,Recipes!$B$6:$B$405,B11)) | AA11: =IF(B11="",0,SUMIFS(Recipes!$U$6:$U$405,Recipes!$B$6:$B$405,B11)) | AB11: =IF(B11="",0,SUMIFS(Recipes!$V$6:$V$405,Recipes!$B$6:$B$405,B11)) | AC11: =IF(B11="",0,SUMIFS(Recipes!$W$6:$W$405,Recipes!$B$6:$B$405,B11)) | AD11: =IF(B11="",0,SUMIFS(Recipes!$X$6:$X$405,Recipes!$B$6:$B$405,B11)) | AE11: =IF(AND(P11>0,Settings!$C$13<>""),Settings!$C$13&", ","")&IF(AND(Q11>0,Settings!$C$14<>""),Settings!$C$14&", ","")&IF(AND(R11>0,Settings!$C$15<>""),Settings!$C$15&", ","")&IF(AND(S11>0,Settings!$C$16<>""),Settings!$C$16&", ","")&IF(AND(T11>0,Settings!$C$17<>""),Settings!$C$17&", ","")&IF(AND(U11>0,Settings!$C$18<>""),Settings!$C$18&", ","")&IF(AND(V11>0,Settings!$C$19<>""),Settings!$C$19&", ","")&IF(AND(W11>0,Settings!$C$20<>""),Settings!$C$20&", ","")&IF(AND(X11>0,Settings!$C$21<>""),Settings!$C$21&", ","")&IF(AND(Y11>0,Settings!$C$22<>""),Settings!$C$22&", ","")&IF(AND(Z11>0,Settings!$C$23<>""),Settings!$C$23&", ","")&IF(AND(AA11>0,Settings!$C$24<>""),Settings!$C$24&", ","")&IF(AND(AB11>0,Settings!$C$25<>""),Settings!$C$25&", ","")&IF(AND(AC11>0,Settings!$C$26<>""),Settings!$C$26&", ","")&IF(AND(AD11>0,Settings!$C$27<>""),Settings!$C$27&", ","")
B12: Dog biscuits | C12: DOG | D12: 10 | E12: 30 | F12: 5.5 | G12: 200 g | H12: =IF(B12="","",SUMIFS(Recipes!$F$6:$F$405,Recipes!$B$6:$B$405,B12)) | I12: =IF(OR(B12="",N(D12)=0),"",H12/D12) | J12: =IF(OR(NOT(ISNUMBER(I12)),N(F12)=0),"",F12-I12) | K12: =IF(NOT(ISNUMBER(J12)),"",J12/F12) | L12: =IF(OR(B12="",AE12=""),"",LEFT(AE12,LEN(AE12)-2)) | M12: =IF(B12="","",SUMIFS(Batches!$K$6:$K$505,Batches!$C$6:$C$505,B12,Batches!$M$6:$M$505,"In stock")+SUMIFS(Batches!$K$6:$K$505,Batches!$C$6:$C$505,B12,Batches!$M$6:$M$505,"Use soon")) | N12: =IF(B12="","",IF(SUMIFS(Batches!$D$6:$D$505,Batches!$C$6:$C$505,B12)=0,"",SUMIFS(Batches!$G$6:$G$505,Batches!$C$6:$C$505,B12)/SUMIFS(Batches!$D$6:$D$505,Batches!$C$6:$C$505,B12))) | P12: =IF(B12="",0,SUMIFS(Recipes!$J$6:$J$405,Recipes!$B$6:$B$405,B12)) | Q12: =IF(B12="",0,SUMIFS(Recipes!$K$6:$K$405,Recipes!$B$6:$B$405,B12)) | R12: =IF(B12="",0,SUMIFS(Recipes!$L$6:$L$405,Recipes!$B$6:$B$405,B12)) | S12: =IF(B12="",0,SUMIFS(Recipes!$M$6:$M$405,Recipes!$B$6:$B$405,B12)) | T12: =IF(B12="",0,SUMIFS(Recipes!$N$6:$N$405,Recipes!$B$6:$B$405,B12)) | U12: =IF(B12="",0,SUMIFS(Recipes!$O$6:$O$405,Recipes!$B$6:$B$405,B12)) | V12: =IF(B12="",0,SUMIFS(Recipes!$P$6:$P$405,Recipes!$B$6:$B$405,B12)) | W12: =IF(B12="",0,SUMIFS(Recipes!$Q$6:$Q$405,Recipes!$B$6:$B$405,B12)) | X12: =IF(B12="",0,SUMIFS(Recipes!$R$6:$R$405,Recipes!$B$6:$B$405,B12)) | Y12: =IF(B12="",0,SUMIFS(Recipes!$S$6:$S$405,Recipes!$B$6:$B$405,B12)) | Z12: =IF(B12="",0,SUMIFS(Recipes!$T$6:$T$405,Recipes!$B$6:$B$405,B12)) | AA12: =IF(B12="",0,SUMIFS(Recipes!$U$6:$U$405,Recipes!$B$6:$B$405,B12)) | AB12: =IF(B12="",0,SUMIFS(Recipes!$V$6:$V$405,Recipes!$B$6:$B$405,B12)) | AC12: =IF(B12="",0,SUMIFS(Recipes!$W$6:$W$405,Recipes!$B$6:$B$405,B12)) | AD12: =IF(B12="",0,SUMIFS(Recipes!$X$6:$X$405,Recipes!$B$6:$B$405,B12)) | AE12: =IF(AND(P12>0,Settings!$C$13<>""),Settings!$C$13&", ","")&IF(AND(Q12>0,Settings!$C$14<>""),Settings!$C$14&", ","")&IF(AND(R12>0,Settings!$C$15<>""),Settings!$C$15&", ","")&IF(AND(S12>0,Settings!$C$16<>""),Settings!$C$16&", ","")&IF(AND(T12>0,Settings!$C$17<>""),Settings!$C$17&", ","")&IF(AND(U12>0,Settings!$C$18<>""),Settings!$C$18&", ","")&IF(AND(V12>0,Settings!$C$19<>""),Settings!$C$19&", ","")&IF(AND(W12>0,Settings!$C$20<>""),Settings!$C$20&", ","")&IF(AND(X12>0,Settings!$C$21<>""),Settings!$C$21&", ","")&IF(AND(Y12>0,Settings!$C$22<>""),Settings!$C$22&", ","")&IF(AND(Z12>0,Settings!$C$23<>""),Settings!$C$23&", ","")&IF(AND(AA12>0,Settings!$C$24<>""),Settings!$C$24&", ","")&IF(AND(AB12>0,Settings!$C$25<>""),Settings!$C$25&", ","")&IF(AND(AC12>0,Settings!$C$26<>""),Settings!$C$26&", ","")&IF(AND(AD12>0,Settings!$C$27<>""),Settings!$C$27&", ","")
B13: Brownies | C13: BRW | D13: 16 | E13: 5 | F13: 2.5 | G13: 1 piece, 70 g | H13: =IF(B13="","",SUMIFS(Recipes!$F$6:$F$405,Recipes!$B$6:$B$405,B13)) | I13: =IF(OR(B13="",N(D13)=0),"",H13/D13) | J13: =IF(OR(NOT(ISNUMBER(I13)),N(F13)=0),"",F13-I13) | K13: =IF(NOT(ISNUMBER(J13)),"",J13/F13) | L13: =IF(OR(B13="",AE13=""),"",LEFT(AE13,LEN(AE13)-2)) | M13: =IF(B13="","",SUMIFS(Batches!$K$6:$K$505,Batches!$C$6:$C$505,B13,Batches!$M$6:$M$505,"In stock")+SUMIFS(Batches!$K$6:$K$505,Batches!$C$6:$C$505,B13,Batches!$M$6:$M$505,"Use soon")) | N13: =IF(B13="","",IF(SUMIFS(Batches!$D$6:$D$505,Batches!$C$6:$C$505,B13)=0,"",SUMIFS(Batches!$G$6:$G$505,Batches!$C$6:$C$505,B13)/SUMIFS(Batches!$D$6:$D$505,Batches!$C$6:$C$505,B13))) | P13: =IF(B13="",0,SUMIFS(Recipes!$J$6:$J$405,Recipes!$B$6:$B$405,B13)) | Q13: =IF(B13="",0,SUMIFS(Recipes!$K$6:$K$405,Recipes!$B$6:$B$405,B13)) | R13: =IF(B13="",0,SUMIFS(Recipes!$L$6:$L$405,Recipes!$B$6:$B$405,B13)) | S13: =IF(B13="",0,SUMIFS(Recipes!$M$6:$M$405,Recipes!$B$6:$B$405,B13)) | T13: =IF(B13="",0,SUMIFS(Recipes!$N$6:$N$405,Recipes!$B$6:$B$405,B13)) | U13: =IF(B13="",0,SUMIFS(Recipes!$O$6:$O$405,Recipes!$B$6:$B$405,B13)) | V13: =IF(B13="",0,SUMIFS(Recipes!$P$6:$P$405,Recipes!$B$6:$B$405,B13)) | W13: =IF(B13="",0,SUMIFS(Recipes!$Q$6:$Q$405,Recipes!$B$6:$B$405,B13)) | X13: =IF(B13="",0,SUMIFS(Recipes!$R$6:$R$405,Recipes!$B$6:$B$405,B13)) | Y13: =IF(B13="",0,SUMIFS(Recipes!$S$6:$S$405,Recipes!$B$6:$B$405,B13)) | Z13: =IF(B13="",0,SUMIFS(Recipes!$T$6:$T$405,Recipes!$B$6:$B$405,B13)) | AA13: =IF(B13="",0,SUMIFS(Recipes!$U$6:$U$405,Recipes!$B$6:$B$405,B13)) | AB13: =IF(B13="",0,SUMIFS(Recipes!$V$6:$V$405,Recipes!$B$6:$B$405,B13)) | AC13: =IF(B13="",0,SUMIFS(Recipes!$W$6:$W$405,Recipes!$B$6:$B$405,B13)) | AD13: =IF(B13="",0,SUMIFS(Recipes!$X$6:$X$405,Recipes!$B$6:$B$405,B13)) | AE13: =IF(AND(P13>0,Settings!$C$13<>""),Settings!$C$13&", ","")&IF(AND(Q13>0,Settings!$C$14<>""),Settings!$C$14&", ","")&IF(AND(R13>0,Settings!$C$15<>""),Settings!$C$15&", ","")&IF(AND(S13>0,Settings!$C$16<>""),Settings!$C$16&", ","")&IF(AND(T13>0,Settings!$C$17<>""),Settings!$C$17&", ","")&IF(AND(U13>0,Settings!$C$18<>""),Settings!$C$18&", ","")&IF(AND(V13>0,Settings!$C$19<>""),Settings!$C$19&", ","")&IF(AND(W13>0,Settings!$C$20<>""),Settings!$C$20&", ","")&IF(AND(X13>0,Settings!$C$21<>""),Settings!$C$21&", ","")&IF(AND(Y13>0,Settings!$C$22<>""),Settings!$C$22&", ","")&IF(AND(Z13>0,Settings!$C$23<>""),Settings!$C$23&", ","")&IF(AND(AA13>0,Settings!$C$24<>""),Settings!$C$24&", ","")&IF(AND(AB13>0,Settings!$C$25<>""),Settings!$C$25&", ","")&IF(AND(AC13>0,Settings!$C$26<>""),Settings!$C$26&", ","")&IF(AND(AD13>0,Settings!$C$27<>""),Settings!$C$27&", ","")
H14: =IF(B14="","",SUMIFS(Recipes!$F$6:$F$405,Recipes!$B$6:$B$405,B14)) | I14: =IF(OR(B14="",N(D14)=0),"",H14/D14) | J14: =IF(OR(NOT(ISNUMBER(I14)),N(F14)=0),"",F14-I14) | K14: =IF(NOT(ISNUMBER(J14)),"",J14/F14) | L14: =IF(OR(B14="",AE14=""),"",LEFT(AE14,LEN(AE14)-2)) | M14: =IF(B14="","",SUMIFS(Batches!$K$6:$K$505,Batches!$C$6:$C$505,B14,Batches!$M$6:$M$505,"In stock")+SUMIFS(Batches!$K$6:$K$505,Batches!$C$6:$C$505,B14,Batches!$M$6:$M$505,"Use soon")) | N14: =IF(B14="","",IF(SUMIFS(Batches!$D$6:$D$505,Batches!$C$6:$C$505,B14)=0,"",SUMIFS(Batches!$G$6:$G$505,Batches!$C$6:$C$505,B14)/SUMIFS(Batches!$D$6:$D$505,Batches!$C$6:$C$505,B14))) | P14: =IF(B14="",0,SUMIFS(Recipes!$J$6:$J$405,Recipes!$B$6:$B$405,B14)) | Q14: =IF(B14="",0,SUMIFS(Recipes!$K$6:$K$405,Recipes!$B$6:$B$405,B14)) | R14: =IF(B14="",0,SUMIFS(Recipes!$L$6:$L$405,Recipes!$B$6:$B$405,B14)) | S14: =IF(B14="",0,SUMIFS(Recipes!$M$6:$M$405,Recipes!$B$6:$B$405,B14)) | T14: =IF(B14="",0,SUMIFS(Recipes!$N$6:$N$405,Recipes!$B$6:$B$405,B14)) | U14: =IF(B14="",0,SUMIFS(Recipes!$O$6:$O$405,Recipes!$B$6:$B$405,B14)) | V14: =IF(B14="",0,SUMIFS(Recipes!$P$6:$P$405,Recipes!$B$6:$B$405,B14)) | W14: =IF(B14="",0,SUMIFS(Recipes!$Q$6:$Q$405,Recipes!$B$6:$B$405,B14)) | X14: =IF(B14="",0,SUMIFS(Recipes!$R$6:$R$405,Recipes!$B$6:$B$405,B14)) | Y14: =IF(B14="",0,SUMIFS(Recipes!$S$6:$S$405,Recipes!$B$6:$B$405,B14)) | Z14: =IF(B14="",0,SUMIFS(Recipes!$T$6:$T$405,Recipes!$B$6:$B$405,B14)) | AA14: =IF(B14="",0,SUMIFS(Recipes!$U$6:$U$405,Recipes!$B$6:$B$405,B14)) | AB14: =IF(B14="",0,SUMIFS(Recipes!$V$6:$V$405,Recipes!$B$6:$B$405,B14)) | AC14: =IF(B14="",0,SUMIFS(Recipes!$W$6:$W$405,Recipes!$B$6:$B$405,B14)) | AD14: =IF(B14="",0,SUMIFS(Recipes!$X$6:$X$405,Recipes!$B$6:$B$405,B14)) | AE14: =IF(AND(P14>0,Settings!$C$13<>""),Settings!$C$13&", ","")&IF(AND(Q14>0,Settings!$C$14<>""),Settings!$C$14&", ","")&IF(AND(R14>0,Settings!$C$15<>""),Settings!$C$15&", ","")&IF(AND(S14>0,Settings!$C$16<>""),Settings!$C$16&", ","")&IF(AND(T14>0,Settings!$C$17<>""),Settings!$C$17&", ","")&IF(AND(U14>0,Settings!$C$18<>""),Settings!$C$18&", ","")&IF(AND(V14>0,Settings!$C$19<>""),Settings!$C$19&", ","")&IF(AND(W14>0,Settings!$C$20<>""),Settings!$C$20&", ","")&IF(AND(X14>0,Settings!$C$21<>""),Settings!$C$21&", ","")&IF(AND(Y14>0,Settings!$C$22<>""),Settings!$C$22&", ","")&IF(AND(Z14>0,Settings!$C$23<>""),Settings!$C$23&", ","")&IF(AND(AA14>0,Settings!$C$24<>""),Settings!$C$24&", ","")&IF(AND(AB14>0,Settings!$C$25<>""),Settings!$C$25&", ","")&IF(AND(AC14>0,Settings!$C$26<>""),Settings!$C$26&", ","")&IF(AND(AD14>0,Settings!$C$27<>""),Settings!$C$27&", ","")
H15: =IF(B15="","",SUMIFS(Recipes!$F$6:$F$405,Recipes!$B$6:$B$405,B15)) | I15: =IF(OR(B15="",N(D15)=0),"",H15/D15) | J15: =IF(OR(NOT(ISNUMBER(I15)),N(F15)=0),"",F15-I15) | K15: =IF(NOT(ISNUMBER(J15)),"",J15/F15) | L15: =IF(OR(B15="",AE15=""),"",LEFT(AE15,LEN(AE15)-2)) | M15: =IF(B15="","",SUMIFS(Batches!$K$6:$K$505,Batches!$C$6:$C$505,B15,Batches!$M$6:$M$505,"In stock")+SUMIFS(Batches!$K$6:$K$505,Batches!$C$6:$C$505,B15,Batches!$M$6:$M$505,"Use soon")) | N15: =IF(B15="","",IF(SUMIFS(Batches!$D$6:$D$505,Batches!$C$6:$C$505,B15)=0,"",SUMIFS(Batches!$G$6:$G$505,Batches!$C$6:$C$505,B15)/SUMIFS(Batches!$D$6:$D$505,Batches!$C$6:$C$505,B15))) | P15: =IF(B15="",0,SUMIFS(Recipes!$J$6:$J$405,Recipes!$B$6:$B$405,B15)) | Q15: =IF(B15="",0,SUMIFS(Recipes!$K$6:$K$405,Recipes!$B$6:$B$405,B15)) | R15: =IF(B15="",0,SUMIFS(Recipes!$L$6:$L$405,Recipes!$B$6:$B$405,B15)) | S15: =IF(B15="",0,SUMIFS(Recipes!$M$6:$M$405,Recipes!$B$6:$B$405,B15)) | T15: =IF(B15="",0,SUMIFS(Recipes!$N$6:$N$405,Recipes!$B$6:$B$405,B15)) | U15: =IF(B15="",0,SUMIFS(Recipes!$O$6:$O$405,Recipes!$B$6:$B$405,B15)) | V15: =IF(B15="",0,SUMIFS(Recipes!$P$6:$P$405,Recipes!$B$6:$B$405,B15)) | W15: =IF(B15="",0,SUMIFS(Recipes!$Q$6:$Q$405,Recipes!$B$6:$B$405,B15)) | X15: =IF(B15="",0,SUMIFS(Recipes!$R$6:$R$405,Recipes!$B$6:$B$405,B15)) | Y15: =IF(B15="",0,SUMIFS(Recipes!$S$6:$S$405,Recipes!$B$6:$B$405,B15)) | Z15: =IF(B15="",0,SUMIFS(Recipes!$T$6:$T$405,Recipes!$B$6:$B$405,B15)) | AA15: =IF(B15="",0,SUMIFS(Recipes!$U$6:$U$405,Recipes!$B$6:$B$405,B15)) | AB15: =IF(B15="",0,SUMIFS(Recipes!$V$6:$V$405,Recipes!$B$6:$B$405,B15)) | AC15: =IF(B15="",0,SUMIFS(Recipes!$W$6:$W$405,Recipes!$B$6:$B$405,B15)) | AD15: =IF(B15="",0,SUMIFS(Recipes!$X$6:$X$405,Recipes!$B$6:$B$405,B15)) | AE15: =IF(AND(P15>0,Settings!$C$13<>""),Settings!$C$13&", ","")&IF(AND(Q15>0,Settings!$C$14<>""),Settings!$C$14&", ","")&IF(AND(R15>0,Settings!$C$15<>""),Settings!$C$15&", ","")&IF(AND(S15>0,Settings!$C$16<>""),Settings!$C$16&", ","")&IF(AND(T15>0,Settings!$C$17<>""),Settings!$C$17&", ","")&IF(AND(U15>0,Settings!$C$18<>""),Settings!$C$18&", ","")&IF(AND(V15>0,Settings!$C$19<>""),Settings!$C$19&", ","")&IF(AND(W15>0,Settings!$C$20<>""),Settings!$C$20&", ","")&IF(AND(X15>0,Settings!$C$21<>""),Settings!$C$21&", ","")&IF(AND(Y15>0,Settings!$C$22<>""),Settings!$C$22&", ","")&IF(AND(Z15>0,Settings!$C$23<>""),Settings!$C$23&", ","")&IF(AND(AA15>0,Settings!$C$24<>""),Settings!$C$24&", ","")&IF(AND(AB15>0,Settings!$C$25<>""),Settings!$C$25&", ","")&IF(AND(AC15>0,Settings!$C$26<>""),Settings!$C$26&", ","")&IF(AND(AD15>0,Settings!$C$27<>""),Settings!$C$27&", ","")
H16: =IF(B16="","",SUMIFS(Recipes!$F$6:$F$405,Recipes!$B$6:$B$405,B16)) | I16: =IF(OR(B16="",N(D16)=0),"",H16/D16) | J16: =IF(OR(NOT(ISNUMBER(I16)),N(F16)=0),"",F16-I16) | K16: =IF(NOT(ISNUMBER(J16)),"",J16/F16) | L16: =IF(OR(B16="",AE16=""),"",LEFT(AE16,LEN(AE16)-2)) | M16: =IF(B16="","",SUMIFS(Batches!$K$6:$K$505,Batches!$C$6:$C$505,B16,Batches!$M$6:$M$505,"In stock")+SUMIFS(Batches!$K$6:$K$505,Batches!$C$6:$C$505,B16,Batches!$M$6:$M$505,"Use soon")) | N16: =IF(B16="","",IF(SUMIFS(Batches!$D$6:$D$505,Batches!$C$6:$C$505,B16)=0,"",SUMIFS(Batches!$G$6:$G$505,Batches!$C$6:$C$505,B16)/SUMIFS(Batches!$D$6:$D$505,Batches!$C$6:$C$505,B16))) | P16: =IF(B16="",0,SUMIFS(Recipes!$J$6:$J$405,Recipes!$B$6:$B$405,B16)) | Q16: =IF(B16="",0,SUMIFS(Recipes!$K$6:$K$405,Recipes!$B$6:$B$405,B16)) | R16: =IF(B16="",0,SUMIFS(Recipes!$L$6:$L$405,Recipes!$B$6:$B$405,B16)) | S16: =IF(B16="",0,SUMIFS(Recipes!$M$6:$M$405,Recipes!$B$6:$B$405,B16)) | T16: =IF(B16="",0,SUMIFS(Recipes!$N$6:$N$405,Recipes!$B$6:$B$405,B16)) | U16: =IF(B16="",0,SUMIFS(Recipes!$O$6:$O$405,Recipes!$B$6:$B$405,B16)) | V16: =IF(B16="",0,SUMIFS(Recipes!$P$6:$P$405,Recipes!$B$6:$B$405,B16)) | W16: =IF(B16="",0,SUMIFS(Recipes!$Q$6:$Q$405,Recipes!$B$6:$B$405,B16)) | X16: =IF(B16="",0,SUMIFS(Recipes!$R$6:$R$405,Recipes!$B$6:$B$405,B16)) | Y16: =IF(B16="",0,SUMIFS(Recipes!$S$6:$S$405,Recipes!$B$6:$B$405,B16)) | Z16: =IF(B16="",0,SUMIFS(Recipes!$T$6:$T$405,Recipes!$B$6:$B$405,B16)) | AA16: =IF(B16="",0,SUMIFS(Recipes!$U$6:$U$405,Recipes!$B$6:$B$405,B16)) | AB16: =IF(B16="",0,SUMIFS(Recipes!$V$6:$V$405,Recipes!$B$6:$B$405,B16)) | AC16: =IF(B16="",0,SUMIFS(Recipes!$W$6:$W$405,Recipes!$B$6:$B$405,B16)) | AD16: =IF(B16="",0,SUMIFS(Recipes!$X$6:$X$405,Recipes!$B$6:$B$405,B16)) | AE16: =IF(AND(P16>0,Settings!$C$13<>""),Settings!$C$13&", ","")&IF(AND(Q16>0,Settings!$C$14<>""),Settings!$C$14&", ","")&IF(AND(R16>0,Settings!$C$15<>""),Settings!$C$15&", ","")&IF(AND(S16>0,Settings!$C$16<>""),Settings!$C$16&", ","")&IF(AND(T16>0,Settings!$C$17<>""),Settings!$C$17&", ","")&IF(AND(U16>0,Settings!$C$18<>""),Settings!$C$18&", ","")&IF(AND(V16>0,Settings!$C$19<>""),Settings!$C$19&", ","")&IF(AND(W16>0,Settings!$C$20<>""),Settings!$C$20&", ","")&IF(AND(X16>0,Settings!$C$21<>""),Settings!$C$21&", ","")&IF(AND(Y16>0,Settings!$C$22<>""),Settings!$C$22&", ","")&IF(AND(Z16>0,Settings!$C$23<>""),Settings!$C$23&", ","")&IF(AND(AA16>0,Settings!$C$24<>""),Settings!$C$24&", ","")&IF(AND(AB16>0,Settings!$C$25<>""),Settings!$C$25&", ","")&IF(AND(AC16>0,Settings!$C$26<>""),Settings!$C$26&", ","")&IF(AND(AD16>0,Settings!$C$27<>""),Settings!$C$27&", ","")
H17: =IF(B17="","",SUMIFS(Recipes!$F$6:$F$405,Recipes!$B$6:$B$405,B17)) | I17: =IF(OR(B17="",N(D17)=0),"",H17/D17) | J17: =IF(OR(NOT(ISNUMBER(I17)),N(F17)=0),"",F17-I17) | K17: =IF(NOT(ISNUMBER(J17)),"",J17/F17) | L17: =IF(OR(B17="",AE17=""),"",LEFT(AE17,LEN(AE17)-2)) | M17: =IF(B17="","",SUMIFS(Batches!$K$6:$K$505,Batches!$C$6:$C$505,B17,Batches!$M$6:$M$505,"In stock")+SUMIFS(Batches!$K$6:$K$505,Batches!$C$6:$C$505,B17,Batches!$M$6:$M$505,"Use soon")) | N17: =IF(B17="","",IF(SUMIFS(Batches!$D$6:$D$505,Batches!$C$6:$C$505,B17)=0,"",SUMIFS(Batches!$G$6:$G$505,Batches!$C$6:$C$505,B17)/SUMIFS(Batches!$D$6:$D$505,Batches!$C$6:$C$505,B17))) | P17: =IF(B17="",0,SUMIFS(Recipes!$J$6:$J$405,Recipes!$B$6:$B$405,B17)) | Q17: =IF(B17="",0,SUMIFS(Recipes!$K$6:$K$405,Recipes!$B$6:$B$405,B17)) | R17: =IF(B17="",0,SUMIFS(Recipes!$L$6:$L$405,Recipes!$B$6:$B$405,B17)) | S17: =IF(B17="",0,SUMIFS(Recipes!$M$6:$M$405,Recipes!$B$6:$B$405,B17)) | T17: =IF(B17="",0,SUMIFS(Recipes!$N$6:$N$405,Recipes!$B$6:$B$405,B17)) | U17: =IF(B17="",0,SUMIFS(Recipes!$O$6:$O$405,Recipes!$B$6:$B$405,B17)) | V17: =IF(B17="",0,SUMIFS(Recipes!$P$6:$P$405,Recipes!$B$6:$B$405,B17)) | W17: =IF(B17="",0,SUMIFS(Recipes!$Q$6:$Q$405,Recipes!$B$6:$B$405,B17)) | X17: =IF(B17="",0,SUMIFS(Recipes!$R$6:$R$405,Recipes!$B$6:$B$405,B17)) | Y17: =IF(B17="",0,SUMIFS(Recipes!$S$6:$S$405,Recipes!$B$6:$B$405,B17)) | Z17: =IF(B17="",0,SUMIFS(Recipes!$T$6:$T$405,Recipes!$B$6:$B$405,B17)) | AA17: =IF(B17="",0,SUMIFS(Recipes!$U$6:$U$405,Recipes!$B$6:$B$405,B17)) | AB17: =IF(B17="",0,SUMIFS(Recipes!$V$6:$V$405,Recipes!$B$6:$B$405,B17)) | AC17: =IF(B17="",0,SUMIFS(Recipes!$W$6:$W$405,Recipes!$B$6:$B$405,B17)) | AD17: =IF(B17="",0,SUMIFS(Recipes!$X$6:$X$405,Recipes!$B$6:$B$405,B17)) | AE17: =IF(AND(P17>0,Settings!$C$13<>""),Settings!$C$13&", ","")&IF(AND(Q17>0,Settings!$C$14<>""),Settings!$C$14&", ","")&IF(AND(R17>0,Settings!$C$15<>""),Settings!$C$15&", ","")&IF(AND(S17>0,Settings!$C$16<>""),Settings!$C$16&", ","")&IF(AND(T17>0,Settings!$C$17<>""),Settings!$C$17&", ","")&IF(AND(U17>0,Settings!$C$18<>""),Settings!$C$18&", ","")&IF(AND(V17>0,Settings!$C$19<>""),Settings!$C$19&", ","")&IF(AND(W17>0,Settings!$C$20<>""),Settings!$C$20&", ","")&IF(AND(X17>0,Settings!$C$21<>""),Settings!$C$21&", ","")&IF(AND(Y17>0,Settings!$C$22<>""),Settings!$C$22&", ","")&IF(AND(Z17>0,Settings!$C$23<>""),Settings!$C$23&", ","")&IF(AND(AA17>0,Settings!$C$24<>""),Settings!$C$24&", ","")&IF(AND(AB17>0,Settings!$C$25<>""),Settings!$C$25&", ","")&IF(AND(AC17>0,Settings!$C$26<>""),Settings!$C$26&", ","")&IF(AND(AD17>0,Settings!$C$27<>""),Settings!$C$27&", ","")
H18: =IF(B18="","",SUMIFS(Recipes!$F$6:$F$405,Recipes!$B$6:$B$405,B18)) | I18: =IF(OR(B18="",N(D18)=0),"",H18/D18) | J18: =IF(OR(NOT(ISNUMBER(I18)),N(F18)=0),"",F18-I18) | K18: =IF(NOT(ISNUMBER(J18)),"",J18/F18) | L18: =IF(OR(B18="",AE18=""),"",LEFT(AE18,LEN(AE18)-2)) | M18: =IF(B18="","",SUMIFS(Batches!$K$6:$K$505,Batches!$C$6:$C$505,B18,Batches!$M$6:$M$505,"In stock")+SUMIFS(Batches!$K$6:$K$505,Batches!$C$6:$C$505,B18,Batches!$M$6:$M$505,"Use soon")) | N18: =IF(B18="","",IF(SUMIFS(Batches!$D$6:$D$505,Batches!$C$6:$C$505,B18)=0,"",SUMIFS(Batches!$G$6:$G$505,Batches!$C$6:$C$505,B18)/SUMIFS(Batches!$D$6:$D$505,Batches!$C$6:$C$505,B18))) | P18: =IF(B18="",0,SUMIFS(Recipes!$J$6:$J$405,Recipes!$B$6:$B$405,B18)) | Q18: =IF(B18="",0,SUMIFS(Recipes!$K$6:$K$405,Recipes!$B$6:$B$405,B18)) | R18: =IF(B18="",0,SUMIFS(Recipes!$L$6:$L$405,Recipes!$B$6:$B$405,B18)) | S18: =IF(B18="",0,SUMIFS(Recipes!$M$6:$M$405,Recipes!$B$6:$B$405,B18)) | T18: =IF(B18="",0,SUMIFS(Recipes!$N$6:$N$405,Recipes!$B$6:$B$405,B18)) | U18: =IF(B18="",0,SUMIFS(Recipes!$O$6:$O$405,Recipes!$B$6:$B$405,B18)) | V18: =IF(B18="",0,SUMIFS(Recipes!$P$6:$P$405,Recipes!$B$6:$B$405,B18)) | W18: =IF(B18="",0,SUMIFS(Recipes!$Q$6:$Q$405,Recipes!$B$6:$B$405,B18)) | X18: =IF(B18="",0,SUMIFS(Recipes!$R$6:$R$405,Recipes!$B$6:$B$405,B18)) | Y18: =IF(B18="",0,SUMIFS(Recipes!$S$6:$S$405,Recipes!$B$6:$B$405,B18)) | Z18: =IF(B18="",0,SUMIFS(Recipes!$T$6:$T$405,Recipes!$B$6:$B$405,B18)) | AA18: =IF(B18="",0,SUMIFS(Recipes!$U$6:$U$405,Recipes!$B$6:$B$405,B18)) | AB18: =IF(B18="",0,SUMIFS(Recipes!$V$6:$V$405,Recipes!$B$6:$B$405,B18)) | AC18: =IF(B18="",0,SUMIFS(Recipes!$W$6:$W$405,Recipes!$B$6:$B$405,B18)) | AD18: =IF(B18="",0,SUMIFS(Recipes!$X$6:$X$405,Recipes!$B$6:$B$405,B18)) | AE18: =IF(AND(P18>0,Settings!$C$13<>""),Settings!$C$13&", ","")&IF(AND(Q18>0,Settings!$C$14<>""),Settings!$C$14&", ","")&IF(AND(R18>0,Settings!$C$15<>""),Settings!$C$15&", ","")&IF(AND(S18>0,Settings!$C$16<>""),Settings!$C$16&", ","")&IF(AND(T18>0,Settings!$C$17<>""),Settings!$C$17&", ","")&IF(AND(U18>0,Settings!$C$18<>""),Settings!$C$18&", ","")&IF(AND(V18>0,Settings!$C$19<>""),Settings!$C$19&", ","")&IF(AND(W18>0,Settings!$C$20<>""),Settings!$C$20&", ","")&IF(AND(X18>0,Settings!$C$21<>""),Settings!$C$21&", ","")&IF(AND(Y18>0,Settings!$C$22<>""),Settings!$C$22&", ","")&IF(AND(Z18>0,Settings!$C$23<>""),Settings!$C$23&", ","")&IF(AND(AA18>0,Settings!$C$24<>""),Settings!$C$24&", ","")&IF(AND(AB18>0,Settings!$C$25<>""),Settings!$C$25&", ","")&IF(AND(AC18>0,Settings!$C$26<>""),Settings!$C$26&", ","")&IF(AND(AD18>0,Settings!$C$27<>""),Settings!$C$27&", ","")
H19: =IF(B19="","",SUMIFS(Recipes!$F$6:$F$405,Recipes!$B$6:$B$405,B19)) | I19: =IF(OR(B19="",N(D19)=0),"",H19/D19) | J19: =IF(OR(NOT(ISNUMBER(I19)),N(F19)=0),"",F19-I19) | K19: =IF(NOT(ISNUMBER(J19)),"",J19/F19) | L19: =IF(OR(B19="",AE19=""),"",LEFT(AE19,LEN(AE19)-2)) | M19: =IF(B19="","",SUMIFS(Batches!$K$6:$K$505,Batches!$C$6:$C$505,B19,Batches!$M$6:$M$505,"In stock")+SUMIFS(Batches!$K$6:$K$505,Batches!$C$6:$C$505,B19,Batches!$M$6:$M$505,"Use soon")) | N19: =IF(B19="","",IF(SUMIFS(Batches!$D$6:$D$505,Batches!$C$6:$C$505,B19)=0,"",SUMIFS(Batches!$G$6:$G$505,Batches!$C$6:$C$505,B19)/SUMIFS(Batches!$D$6:$D$505,Batches!$C$6:$C$505,B19))) | P19: =IF(B19="",0,SUMIFS(Recipes!$J$6:$J$405,Recipes!$B$6:$B$405,B19)) | Q19: =IF(B19="",0,SUMIFS(Recipes!$K$6:$K$405,Recipes!$B$6:$B$405,B19)) | R19: =IF(B19="",0,SUMIFS(Recipes!$L$6:$L$405,Recipes!$B$6:$B$405,B19)) | S19: =IF(B19="",0,SUMIFS(Recipes!$M$6:$M$405,Recipes!$B$6:$B$405,B19)) | T19: =IF(B19="",0,SUMIFS(Recipes!$N$6:$N$405,Recipes!$B$6:$B$405,B19)) | U19: =IF(B19="",0,SUMIFS(Recipes!$O$6:$O$405,Recipes!$B$6:$B$405,B19)) | V19: =IF(B19="",0,SUMIFS(Recipes!$P$6:$P$405,Recipes!$B$6:$B$405,B19)) | W19: =IF(B19="",0,SUMIFS(Recipes!$Q$6:$Q$405,Recipes!$B$6:$B$405,B19)) | X19: =IF(B19="",0,SUMIFS(Recipes!$R$6:$R$405,Recipes!$B$6:$B$405,B19)) | Y19: =IF(B19="",0,SUMIFS(Recipes!$S$6:$S$405,Recipes!$B$6:$B$405,B19)) | Z19: =IF(B19="",0,SUMIFS(Recipes!$T$6:$T$405,Recipes!$B$6:$B$405,B19)) | AA19: =IF(B19="",0,SUMIFS(Recipes!$U$6:$U$405,Recipes!$B$6:$B$405,B19)) | AB19: =IF(B19="",0,SUMIFS(Recipes!$V$6:$V$405,Recipes!$B$6:$B$405,B19)) | AC19: =IF(B19="",0,SUMIFS(Recipes!$W$6:$W$405,Recipes!$B$6:$B$405,B19)) | AD19: =IF(B19="",0,SUMIFS(Recipes!$X$6:$X$405,Recipes!$B$6:$B$405,B19)) | AE19: =IF(AND(P19>0,Settings!$C$13<>""),Settings!$C$13&", ","")&IF(AND(Q19>0,Settings!$C$14<>""),Settings!$C$14&", ","")&IF(AND(R19>0,Settings!$C$15<>""),Settings!$C$15&", ","")&IF(AND(S19>0,Settings!$C$16<>""),Settings!$C$16&", ","")&IF(AND(T19>0,Settings!$C$17<>""),Settings!$C$17&", ","")&IF(AND(U19>0,Settings!$C$18<>""),Settings!$C$18&", ","")&IF(AND(V19>0,Settings!$C$19<>""),Settings!$C$19&", ","")&IF(AND(W19>0,Settings!$C$20<>""),Settings!$C$20&", ","")&IF(AND(X19>0,Settings!$C$21<>""),Settings!$C$21&", ","")&IF(AND(Y19>0,Settings!$C$22<>""),Settings!$C$22&", ","")&IF(AND(Z19>0,Settings!$C$23<>""),Settings!$C$23&", ","")&IF(AND(AA19>0,Settings!$C$24<>""),Settings!$C$24&", ","")&IF(AND(AB19>0,Settings!$C$25<>""),Settings!$C$25&", ","")&IF(AND(AC19>0,Settings!$C$26<>""),Settings!$C$26&", ","")&IF(AND(AD19>0,Settings!$C$27<>""),Settings!$C$27&", ","")
H20: =IF(B20="","",SUMIFS(Recipes!$F$6:$F$405,Recipes!$B$6:$B$405,B20)) | I20: =IF(OR(B20="",N(D20)=0),"",H20/D20) | J20: =IF(OR(NOT(ISNUMBER(I20)),N(F20)=0),"",F20-I20) | K20: =IF(NOT(ISNUMBER(J20)),"",J20/F20) | L20: =IF(OR(B20="",AE20=""),"",LEFT(AE20,LEN(AE20)-2)) | M20: =IF(B20="","",SUMIFS(Batches!$K$6:$K$505,Batches!$C$6:$C$505,B20,Batches!$M$6:$M$505,"In stock")+SUMIFS(Batches!$K$6:$K$505,Batches!$C$6:$C$505,B20,Batches!$M$6:$M$505,"Use soon")) | N20: =IF(B20="","",IF(SUMIFS(Batches!$D$6:$D$505,Batches!$C$6:$C$505,B20)=0,"",SUMIFS(Batches!$G$6:$G$505,Batches!$C$6:$C$505,B20)/SUMIFS(Batches!$D$6:$D$505,Batches!$C$6:$C$505,B20))) | P20: =IF(B20="",0,SUMIFS(Recipes!$J$6:$J$405,Recipes!$B$6:$B$405,B20)) | Q20: =IF(B20="",0,SUMIFS(Recipes!$K$6:$K$405,Recipes!$B$6:$B$405,B20)) | R20: =IF(B20="",0,SUMIFS(Recipes!$L$6:$L$405,Recipes!$B$6:$B$405,B20)) | S20: =IF(B20="",0,SUMIFS(Recipes!$M$6:$M$405,Recipes!$B$6:$B$405,B20)) | T20: =IF(B20="",0,SUMIFS(Recipes!$N$6:$N$405,Recipes!$B$6:$B$405,B20)) | U20: =IF(B20="",0,SUMIFS(Recipes!$O$6:$O$405,Recipes!$B$6:$B$405,B20)) | V20: =IF(B20="",0,SUMIFS(Recipes!$P$6:$P$405,Recipes!$B$6:$B$405,B20)) | W20: =IF(B20="",0,SUMIFS(Recipes!$Q$6:$Q$405,Recipes!$B$6:$B$405,B20)) | X20: =IF(B20="",0,SUMIFS(Recipes!$R$6:$R$405,Recipes!$B$6:$B$405,B20)) | Y20: =IF(B20="",0,SUMIFS(Recipes!$S$6:$S$405,Recipes!$B$6:$B$405,B20)) | Z20: =IF(B20="",0,SUMIFS(Recipes!$T$6:$T$405,Recipes!$B$6:$B$405,B20)) | AA20: =IF(B20="",0,SUMIFS(Recipes!$U$6:$U$405,Recipes!$B$6:$B$405,B20)) | AB20: =IF(B20="",0,SUMIFS(Recipes!$V$6:$V$405,Recipes!$B$6:$B$405,B20)) | AC20: =IF(B20="",0,SUMIFS(Recipes!$W$6:$W$405,Recipes!$B$6:$B$405,B20)) | AD20: =IF(B20="",0,SUMIFS(Recipes!$X$6:$X$405,Recipes!$B$6:$B$405,B20)) | AE20: =IF(AND(P20>0,Settings!$C$13<>""),Settings!$C$13&", ","")&IF(AND(Q20>0,Settings!$C$14<>""),Settings!$C$14&", ","")&IF(AND(R20>0,Settings!$C$15<>""),Settings!$C$15&", ","")&IF(AND(S20>0,Settings!$C$16<>""),Settings!$C$16&", ","")&IF(AND(T20>0,Settings!$C$17<>""),Settings!$C$17&", ","")&IF(AND(U20>0,Settings!$C$18<>""),Settings!$C$18&", ","")&IF(AND(V20>0,Settings!$C$19<>""),Settings!$C$19&", ","")&IF(AND(W20>0,Settings!$C$20<>""),Settings!$C$20&", ","")&IF(AND(X20>0,Settings!$C$21<>""),Settings!$C$21&", ","")&IF(AND(Y20>0,Settings!$C$22<>""),Settings!$C$22&", ","")&IF(AND(Z20>0,Settings!$C$23<>""),Settings!$C$23&", ","")&IF(AND(AA20>0,Settings!$C$24<>""),Settings!$C$24&", ","")&IF(AND(AB20>0,Settings!$C$25<>""),Settings!$C$25&", ","")&IF(AND(AC20>0,Settings!$C$26<>""),Settings!$C$26&", ","")&IF(AND(AD20>0,Settings!$C$27<>""),Settings!$C$27&", ","")
H21: =IF(B21="","",SUMIFS(Recipes!$F$6:$F$405,Recipes!$B$6:$B$405,B21)) | I21: =IF(OR(B21="",N(D21)=0),"",H21/D21) | J21: =IF(OR(NOT(ISNUMBER(I21)),N(F21)=0),"",F21-I21) | K21: =IF(NOT(ISNUMBER(J21)),"",J21/F21) | L21: =IF(OR(B21="",AE21=""),"",LEFT(AE21,LEN(AE21)-2)) | M21: =IF(B21="","",SUMIFS(Batches!$K$6:$K$505,Batches!$C$6:$C$505,B21,Batches!$M$6:$M$505,"In stock")+SUMIFS(Batches!$K$6:$K$505,Batches!$C$6:$C$505,B21,Batches!$M$6:$M$505,"Use soon")) | N21: =IF(B21="","",IF(SUMIFS(Batches!$D$6:$D$505,Batches!$C$6:$C$505,B21)=0,"",SUMIFS(Batches!$G$6:$G$505,Batches!$C$6:$C$505,B21)/SUMIFS(Batches!$D$6:$D$505,Batches!$C$6:$C$505,B21))) | P21: =IF(B21="",0,SUMIFS(Recipes!$J$6:$J$405,Recipes!$B$6:$B$405,B21)) | Q21: =IF(B21="",0,SUMIFS(Recipes!$K$6:$K$405,Recipes!$B$6:$B$405,B21)) | R21: =IF(B21="",0,SUMIFS(Recipes!$L$6:$L$405,Recipes!$B$6:$B$405,B21)) | S21: =IF(B21="",0,SUMIFS(Recipes!$M$6:$M$405,Recipes!$B$6:$B$405,B21)) | T21: =IF(B21="",0,SUMIFS(Recipes!$N$6:$N$405,Recipes!$B$6:$B$405,B21)) | U21: =IF(B21="",0,SUMIFS(Recipes!$O$6:$O$405,Recipes!$B$6:$B$405,B21)) | V21: =IF(B21="",0,SUMIFS(Recipes!$P$6:$P$405,Recipes!$B$6:$B$405,B21)) | W21: =IF(B21="",0,SUMIFS(Recipes!$Q$6:$Q$405,Recipes!$B$6:$B$405,B21)) | X21: =IF(B21="",0,SUMIFS(Recipes!$R$6:$R$405,Recipes!$B$6:$B$405,B21)) | Y21: =IF(B21="",0,SUMIFS(Recipes!$S$6:$S$405,Recipes!$B$6:$B$405,B21)) | Z21: =IF(B21="",0,SUMIFS(Recipes!$T$6:$T$405,Recipes!$B$6:$B$405,B21)) | AA21: =IF(B21="",0,SUMIFS(Recipes!$U$6:$U$405,Recipes!$B$6:$B$405,B21)) | AB21: =IF(B21="",0,SUMIFS(Recipes!$V$6:$V$405,Recipes!$B$6:$B$405,B21)) | AC21: =IF(B21="",0,SUMIFS(Recipes!$W$6:$W$405,Recipes!$B$6:$B$405,B21)) | AD21: =IF(B21="",0,SUMIFS(Recipes!$X$6:$X$405,Recipes!$B$6:$B$405,B21)) | AE21: =IF(AND(P21>0,Settings!$C$13<>""),Settings!$C$13&", ","")&IF(AND(Q21>0,Settings!$C$14<>""),Settings!$C$14&", ","")&IF(AND(R21>0,Settings!$C$15<>""),Settings!$C$15&", ","")&IF(AND(S21>0,Settings!$C$16<>""),Settings!$C$16&", ","")&IF(AND(T21>0,Settings!$C$17<>""),Settings!$C$17&", ","")&IF(AND(U21>0,Settings!$C$18<>""),Settings!$C$18&", ","")&IF(AND(V21>0,Settings!$C$19<>""),Settings!$C$19&", ","")&IF(AND(W21>0,Settings!$C$20<>""),Settings!$C$20&", ","")&IF(AND(X21>0,Settings!$C$21<>""),Settings!$C$21&", ","")&IF(AND(Y21>0,Settings!$C$22<>""),Settings!$C$22&", ","")&IF(AND(Z21>0,Settings!$C$23<>""),Settings!$C$23&", ","")&IF(AND(AA21>0,Settings!$C$24<>""),Settings!$C$24&", ","")&IF(AND(AB21>0,Settings!$C$25<>""),Settings!$C$25&", ","")&IF(AND(AC21>0,Settings!$C$26<>""),Settings!$C$26&", ","")&IF(AND(AD21>0,Settings!$C$27<>""),Settings!$C$27&", ","")
H22: =IF(B22="","",SUMIFS(Recipes!$F$6:$F$405,Recipes!$B$6:$B$405,B22)) | I22: =IF(OR(B22="",N(D22)=0),"",H22/D22) | J22: =IF(OR(NOT(ISNUMBER(I22)),N(F22)=0),"",F22-I22) | K22: =IF(NOT(ISNUMBER(J22)),"",J22/F22) | L22: =IF(OR(B22="",AE22=""),"",LEFT(AE22,LEN(AE22)-2)) | M22: =IF(B22="","",SUMIFS(Batches!$K$6:$K$505,Batches!$C$6:$C$505,B22,Batches!$M$6:$M$505,"In stock")+SUMIFS(Batches!$K$6:$K$505,Batches!$C$6:$C$505,B22,Batches!$M$6:$M$505,"Use soon")) | N22: =IF(B22="","",IF(SUMIFS(Batches!$D$6:$D$505,Batches!$C$6:$C$505,B22)=0,"",SUMIFS(Batches!$G$6:$G$505,Batches!$C$6:$C$505,B22)/SUMIFS(Batches!$D$6:$D$505,Batches!$C$6:$C$505,B22))) | P22: =IF(B22="",0,SUMIFS(Recipes!$J$6:$J$405,Recipes!$B$6:$B$405,B22)) | Q22: =IF(B22="",0,SUMIFS(Recipes!$K$6:$K$405,Recipes!$B$6:$B$405,B22)) | R22: =IF(B22="",0,SUMIFS(Recipes!$L$6:$L$405,Recipes!$B$6:$B$405,B22)) | S22: =IF(B22="",0,SUMIFS(Recipes!$M$6:$M$405,Recipes!$B$6:$B$405,B22)) | T22: =IF(B22="",0,SUMIFS(Recipes!$N$6:$N$405,Recipes!$B$6:$B$405,B22)) | U22: =IF(B22="",0,SUMIFS(Recipes!$O$6:$O$405,Recipes!$B$6:$B$405,B22)) | V22: =IF(B22="",0,SUMIFS(Recipes!$P$6:$P$405,Recipes!$B$6:$B$405,B22)) | W22: =IF(B22="",0,SUMIFS(Recipes!$Q$6:$Q$405,Recipes!$B$6:$B$405,B22)) | X22: =IF(B22="",0,SUMIFS(Recipes!$R$6:$R$405,Recipes!$B$6:$B$405,B22)) | Y22: =IF(B22="",0,SUMIFS(Recipes!$S$6:$S$405,Recipes!$B$6:$B$405,B22)) | Z22: =IF(B22="",0,SUMIFS(Recipes!$T$6:$T$405,Recipes!$B$6:$B$405,B22)) | AA22: =IF(B22="",0,SUMIFS(Recipes!$U$6:$U$405,Recipes!$B$6:$B$405,B22)) | AB22: =IF(B22="",0,SUMIFS(Recipes!$V$6:$V$405,Recipes!$B$6:$B$405,B22)) | AC22: =IF(B22="",0,SUMIFS(Recipes!$W$6:$W$405,Recipes!$B$6:$B$405,B22)) | AD22: =IF(B22="",0,SUMIFS(Recipes!$X$6:$X$405,Recipes!$B$6:$B$405,B22)) | AE22: =IF(AND(P22>0,Settings!$C$13<>""),Settings!$C$13&", ","")&IF(AND(Q22>0,Settings!$C$14<>""),Settings!$C$14&", ","")&IF(AND(R22>0,Settings!$C$15<>""),Settings!$C$15&", ","")&IF(AND(S22>0,Settings!$C$16<>""),Settings!$C$16&", ","")&IF(AND(T22>0,Settings!$C$17<>""),Settings!$C$17&", ","")&IF(AND(U22>0,Settings!$C$18<>""),Settings!$C$18&", ","")&IF(AND(V22>0,Settings!$C$19<>""),Settings!$C$19&", ","")&IF(AND(W22>0,Settings!$C$20<>""),Settings!$C$20&", ","")&IF(AND(X22>0,Settings!$C$21<>""),Settings!$C$21&", ","")&IF(AND(Y22>0,Settings!$C$22<>""),Settings!$C$22&", ","")&IF(AND(Z22>0,Settings!$C$23<>""),Settings!$C$23&", ","")&IF(AND(AA22>0,Settings!$C$24<>""),Settings!$C$24&", ","")&IF(AND(AB22>0,Settings!$C$25<>""),Settings!$C$25&", ","")&IF(AND(AC22>0,Settings!$C$26<>""),Settings!$C$26&", ","")&IF(AND(AD22>0,Settings!$C$27<>""),Settings!$C$27&", ","")
H23: =IF(B23="","",SUMIFS(Recipes!$F$6:$F$405,Recipes!$B$6:$B$405,B23)) | I23: =IF(OR(B23="",N(D23)=0),"",H23/D23) | J23: =IF(OR(NOT(ISNUMBER(I23)),N(F23)=0),"",F23-I23) | K23: =IF(NOT(ISNUMBER(J23)),"",J23/F23) | L23: =IF(OR(B23="",AE23=""),"",LEFT(AE23,LEN(AE23)-2)) | M23: =IF(B23="","",SUMIFS(Batches!$K$6:$K$505,Batches!$C$6:$C$505,B23,Batches!$M$6:$M$505,"In stock")+SUMIFS(Batches!$K$6:$K$505,Batches!$C$6:$C$505,B23,Batches!$M$6:$M$505,"Use soon")) | N23: =IF(B23="","",IF(SUMIFS(Batches!$D$6:$D$505,Batches!$C$6:$C$505,B23)=0,"",SUMIFS(Batches!$G$6:$G$505,Batches!$C$6:$C$505,B23)/SUMIFS(Batches!$D$6:$D$505,Batches!$C$6:$C$505,B23))) | P23: =IF(B23="",0,SUMIFS(Recipes!$J$6:$J$405,Recipes!$B$6:$B$405,B23)) | Q23: =IF(B23="",0,SUMIFS(Recipes!$K$6:$K$405,Recipes!$B$6:$B$405,B23)) | R23: =IF(B23="",0,SUMIFS(Recipes!$L$6:$L$405,Recipes!$B$6:$B$405,B23)) | S23: =IF(B23="",0,SUMIFS(Recipes!$M$6:$M$405,Recipes!$B$6:$B$405,B23)) | T23: =IF(B23="",0,SUMIFS(Recipes!$N$6:$N$405,Recipes!$B$6:$B$405,B23)) | U23: =IF(B23="",0,SUMIFS(Recipes!$O$6:$O$405,Recipes!$B$6:$B$405,B23)) | V23: =IF(B23="",0,SUMIFS(Recipes!$P$6:$P$405,Recipes!$B$6:$B$405,B23)) | W23: =IF(B23="",0,SUMIFS(Recipes!$Q$6:$Q$405,Recipes!$B$6:$B$405,B23)) | X23: =IF(B23="",0,SUMIFS(Recipes!$R$6:$R$405,Recipes!$B$6:$B$405,B23)) | Y23: =IF(B23="",0,SUMIFS(Recipes!$S$6:$S$405,Recipes!$B$6:$B$405,B23)) | Z23: =IF(B23="",0,SUMIFS(Recipes!$T$6:$T$405,Recipes!$B$6:$B$405,B23)) | AA23: =IF(B23="",0,SUMIFS(Recipes!$U$6:$U$405,Recipes!$B$6:$B$405,B23)) | AB23: =IF(B23="",0,SUMIFS(Recipes!$V$6:$V$405,Recipes!$B$6:$B$405,B23)) | AC23: =IF(B23="",0,SUMIFS(Recipes!$W$6:$W$405,Recipes!$B$6:$B$405,B23)) | AD23: =IF(B23="",0,SUMIFS(Recipes!$X$6:$X$405,Recipes!$B$6:$B$405,B23)) | AE23: =IF(AND(P23>0,Settings!$C$13<>""),Settings!$C$13&", ","")&IF(AND(Q23>0,Settings!$C$14<>""),Settings!$C$14&", ","")&IF(AND(R23>0,Settings!$C$15<>""),Settings!$C$15&", ","")&IF(AND(S23>0,Settings!$C$16<>""),Settings!$C$16&", ","")&IF(AND(T23>0,Settings!$C$17<>""),Settings!$C$17&", ","")&IF(AND(U23>0,Settings!$C$18<>""),Settings!$C$18&", ","")&IF(AND(V23>0,Settings!$C$19<>""),Settings!$C$19&", ","")&IF(AND(W23>0,Settings!$C$20<>""),Settings!$C$20&", ","")&IF(AND(X23>0,Settings!$C$21<>""),Settings!$C$21&", ","")&IF(AND(Y23>0,Settings!$C$22<>""),Settings!$C$22&", ","")&IF(AND(Z23>0,Settings!$C$23<>""),Settings!$C$23&", ","")&IF(AND(AA23>0,Settings!$C$24<>""),Settings!$C$24&", ","")&IF(AND(AB23>0,Settings!$C$25<>""),Settings!$C$25&", ","")&IF(AND(AC23>0,Settings!$C$26<>""),Settings!$C$26&", ","")&IF(AND(AD23>0,Settings!$C$27<>""),Settings!$C$27&", ","")
H24: =IF(B24="","",SUMIFS(Recipes!$F$6:$F$405,Recipes!$B$6:$B$405,B24)) | I24: =IF(OR(B24="",N(D24)=0),"",H24/D24) | J24: =IF(OR(NOT(ISNUMBER(I24)),N(F24)=0),"",F24-I24) | K24: =IF(NOT(ISNUMBER(J24)),"",J24/F24) | L24: =IF(OR(B24="",AE24=""),"",LEFT(AE24,LEN(AE24)-2)) | M24: =IF(B24="","",SUMIFS(Batches!$K$6:$K$505,Batches!$C$6:$C$505,B24,Batches!$M$6:$M$505,"In stock")+SUMIFS(Batches!$K$6:$K$505,Batches!$C$6:$C$505,B24,Batches!$M$6:$M$505,"Use soon")) | N24: =IF(B24="","",IF(SUMIFS(Batches!$D$6:$D$505,Batches!$C$6:$C$505,B24)=0,"",SUMIFS(Batches!$G$6:$G$505,Batches!$C$6:$C$505,B24)/SUMIFS(Batches!$D$6:$D$505,Batches!$C$6:$C$505,B24))) | P24: =IF(B24="",0,SUMIFS(Recipes!$J$6:$J$405,Recipes!$B$6:$B$405,B24)) | Q24: =IF(B24="",0,SUMIFS(Recipes!$K$6:$K$405,Recipes!$B$6:$B$405,B24)) | R24: =IF(B24="",0,SUMIFS(Recipes!$L$6:$L$405,Recipes!$B$6:$B$405,B24)) | S24: =IF(B24="",0,SUMIFS(Recipes!$M$6:$M$405,Recipes!$B$6:$B$405,B24)) | T24: =IF(B24="",0,SUMIFS(Recipes!$N$6:$N$405,Recipes!$B$6:$B$405,B24)) | U24: =IF(B24="",0,SUMIFS(Recipes!$O$6:$O$405,Recipes!$B$6:$B$405,B24)) | V24: =IF(B24="",0,SUMIFS(Recipes!$P$6:$P$405,Recipes!$B$6:$B$405,B24)) | W24: =IF(B24="",0,SUMIFS(Recipes!$Q$6:$Q$405,Recipes!$B$6:$B$405,B24)) | X24: =IF(B24="",0,SUMIFS(Recipes!$R$6:$R$405,Recipes!$B$6:$B$405,B24)) | Y24: =IF(B24="",0,SUMIFS(Recipes!$S$6:$S$405,Recipes!$B$6:$B$405,B24)) | Z24: =IF(B24="",0,SUMIFS(Recipes!$T$6:$T$405,Recipes!$B$6:$B$405,B24)) | AA24: =IF(B24="",0,SUMIFS(Recipes!$U$6:$U$405,Recipes!$B$6:$B$405,B24)) | AB24: =IF(B24="",0,SUMIFS(Recipes!$V$6:$V$405,Recipes!$B$6:$B$405,B24)) | AC24: =IF(B24="",0,SUMIFS(Recipes!$W$6:$W$405,Recipes!$B$6:$B$405,B24)) | AD24: =IF(B24="",0,SUMIFS(Recipes!$X$6:$X$405,Recipes!$B$6:$B$405,B24)) | AE24: =IF(AND(P24>0,Settings!$C$13<>""),Settings!$C$13&", ","")&IF(AND(Q24>0,Settings!$C$14<>""),Settings!$C$14&", ","")&IF(AND(R24>0,Settings!$C$15<>""),Settings!$C$15&", ","")&IF(AND(S24>0,Settings!$C$16<>""),Settings!$C$16&", ","")&IF(AND(T24>0,Settings!$C$17<>""),Settings!$C$17&", ","")&IF(AND(U24>0,Settings!$C$18<>""),Settings!$C$18&", ","")&IF(AND(V24>0,Settings!$C$19<>""),Settings!$C$19&", ","")&IF(AND(W24>0,Settings!$C$20<>""),Settings!$C$20&", ","")&IF(AND(X24>0,Settings!$C$21<>""),Settings!$C$21&", ","")&IF(AND(Y24>0,Settings!$C$22<>""),Settings!$C$22&", ","")&IF(AND(Z24>0,Settings!$C$23<>""),Settings!$C$23&", ","")&IF(AND(AA24>0,Settings!$C$24<>""),Settings!$C$24&", ","")&IF(AND(AB24>0,Settings!$C$25<>""),Settings!$C$25&", ","")&IF(AND(AC24>0,Settings!$C$26<>""),Settings!$C$26&", ","")&IF(AND(AD24>0,Settings!$C$27<>""),Settings!$C$27&", ","")
H25: =IF(B25="","",SUMIFS(Recipes!$F$6:$F$405,Recipes!$B$6:$B$405,B25)) | I25: =IF(OR(B25="",N(D25)=0),"",H25/D25) | J25: =IF(OR(NOT(ISNUMBER(I25)),N(F25)=0),"",F25-I25) | K25: =IF(NOT(ISNUMBER(J25)),"",J25/F25) | L25: =IF(OR(B25="",AE25=""),"",LEFT(AE25,LEN(AE25)-2)) | M25: =IF(B25="","",SUMIFS(Batches!$K$6:$K$505,Batches!$C$6:$C$505,B25,Batches!$M$6:$M$505,"In stock")+SUMIFS(Batches!$K$6:$K$505,Batches!$C$6:$C$505,B25,Batches!$M$6:$M$505,"Use soon")) | N25: =IF(B25="","",IF(SUMIFS(Batches!$D$6:$D$505,Batches!$C$6:$C$505,B25)=0,"",SUMIFS(Batches!$G$6:$G$505,Batches!$C$6:$C$505,B25)/SUMIFS(Batches!$D$6:$D$505,Batches!$C$6:$C$505,B25))) | P25: =IF(B25="",0,SUMIFS(Recipes!$J$6:$J$405,Recipes!$B$6:$B$405,B25)) | Q25: =IF(B25="",0,SUMIFS(Recipes!$K$6:$K$405,Recipes!$B$6:$B$405,B25)) | R25: =IF(B25="",0,SUMIFS(Recipes!$L$6:$L$405,Recipes!$B$6:$B$405,B25)) | S25: =IF(B25="",0,SUMIFS(Recipes!$M$6:$M$405,Recipes!$B$6:$B$405,B25)) | T25: =IF(B25="",0,SUMIFS(Recipes!$N$6:$N$405,Recipes!$B$6:$B$405,B25)) | U25: =IF(B25="",0,SUMIFS(Recipes!$O$6:$O$405,Recipes!$B$6:$B$405,B25)) | V25: =IF(B25="",0,SUMIFS(Recipes!$P$6:$P$405,Recipes!$B$6:$B$405,B25)) | W25: =IF(B25="",0,SUMIFS(Recipes!$Q$6:$Q$405,Recipes!$B$6:$B$405,B25)) | X25: =IF(B25="",0,SUMIFS(Recipes!$R$6:$R$405,Recipes!$B$6:$B$405,B25)) | Y25: =IF(B25="",0,SUMIFS(Recipes!$S$6:$S$405,Recipes!$B$6:$B$405,B25)) | Z25: =IF(B25="",0,SUMIFS(Recipes!$T$6:$T$405,Recipes!$B$6:$B$405,B25)) | AA25: =IF(B25="",0,SUMIFS(Recipes!$U$6:$U$405,Recipes!$B$6:$B$405,B25)) | AB25: =IF(B25="",0,SUMIFS(Recipes!$V$6:$V$405,Recipes!$B$6:$B$405,B25)) | AC25: =IF(B25="",0,SUMIFS(Recipes!$W$6:$W$405,Recipes!$B$6:$B$405,B25)) | AD25: =IF(B25="",0,SUMIFS(Recipes!$X$6:$X$405,Recipes!$B$6:$B$405,B25)) | AE25: =IF(AND(P25>0,Settings!$C$13<>""),Settings!$C$13&", ","")&IF(AND(Q25>0,Settings!$C$14<>""),Settings!$C$14&", ","")&IF(AND(R25>0,Settings!$C$15<>""),Settings!$C$15&", ","")&IF(AND(S25>0,Settings!$C$16<>""),Settings!$C$16&", ","")&IF(AND(T25>0,Settings!$C$17<>""),Settings!$C$17&", ","")&IF(AND(U25>0,Settings!$C$18<>""),Settings!$C$18&", ","")&IF(AND(V25>0,Settings!$C$19<>""),Settings!$C$19&", ","")&IF(AND(W25>0,Settings!$C$20<>""),Settings!$C$20&", ","")&IF(AND(X25>0,Settings!$C$21<>""),Settings!$C$21&", ","")&IF(AND(Y25>0,Settings!$C$22<>""),Settings!$C$22&", ","")&IF(AND(Z25>0,Settings!$C$23<>""),Settings!$C$23&", ","")&IF(AND(AA25>0,Settings!$C$24<>""),Settings!$C$24&", ","")&IF(AND(AB25>0,Settings!$C$25<>""),Settings!$C$25&", ","")&IF(AND(AC25>0,Settings!$C$26<>""),Settings!$C$26&", ","")&IF(AND(AD25>0,Settings!$C$27<>""),Settings!$C$27&", ","")
... H45: =IF(B45="","",SUMIFS(Recipes!$F$6:$F$405,Recipes!$B$6:$B$405,B45)) | I45: =IF(OR(B45="",N(D45)=0),"",H45/D45) | J45: =IF(OR(NOT(ISNUMBER(I45)),N(F45)=0),"",F45-I45) | K45: =IF(NOT(ISNUMBER(J45)),"",J45/F45) | L45: =IF(OR(B45="",AE45=""),"",LEFT(AE45,LEN(AE45)-2)) | M45: =IF(B45="","",SUMIFS(Batches!$K$6:$K$505,Batches!$C$6:$C$505,B45,Batches!$M$6:$M$505,"In stock")+SUMIFS(Batches!$K$6:$K$505,Batches!$C$6:$C$505,B45,Batches!$M$6:$M$505,"Use soon")) | N45: =IF(B45="","",IF(SUMIFS(Batches!$D$6:$D$505,Batches!$C$6:$C$505,B45)=0,"",SUMIFS(Batches!$G$6:$G$505,Batches!$C$6:$C$505,B45)/SUMIFS(Batches!$D$6:$D$505,Batches!$C$6:$C$505,B45))) | P45: =IF(B45="",0,SUMIFS(Recipes!$J$6:$J$405,Recipes!$B$6:$B$405,B45)) | Q45: =IF(B45="",0,SUMIFS(Recipes!$K$6:$K$405,Recipes!$B$6:$B$405,B45)) | R45: =IF(B45="",0,SUMIFS(Recipes!$L$6:$L$405,Recipes!$B$6:$B$405,B45)) | S45: =IF(B45="",0,SUMIFS(Recipes!$M$6:$M$405,Recipes!$B$6:$B$405,B45)) | T45: =IF(B45="",0,SUMIFS(Recipes!$N$6:$N$405,Recipes!$B$6:$B$405,B45)) | U45: =IF(B45="",0,SUMIFS(Recipes!$O$6:$O$405,Recipes!$B$6:$B$405,B45)) | V45: =IF(B45="",0,SUMIFS(Recipes!$P$6:$P$405,Recipes!$B$6:$B$405,B45)) | W45: =IF(B45="",0,SUMIFS(Recipes!$Q$6:$Q$405,Recipes!$B$6:$B$405,B45)) | X45: =IF(B45="",0,SUMIFS(Recipes!$R$6:$R$405,Recipes!$B$6:$B$405,B45)) | Y45: =IF(B45="",0,SUMIFS(Recipes!$S$6:$S$405,Recipes!$B$6:$B$405,B45)) | Z45: =IF(B45="",0,SUMIFS(Recipes!$T$6:$T$405,Recipes!$B$6:$B$405,B45)) | AA45: =IF(B45="",0,SUMIFS(Recipes!$U$6:$U$405,Recipes!$B$6:$B$405,B45)) | AB45: =IF(B45="",0,SUMIFS(Recipes!$V$6:$V$405,Recipes!$B$6:$B$405,B45)) | AC45: =IF(B45="",0,SUMIFS(Recipes!$W$6:$W$405,Recipes!$B$6:$B$405,B45)) | AD45: =IF(B45="",0,SUMIFS(Recipes!$X$6:$X$405,Recipes!$B$6:$B$405,B45)) | AE45: =IF(AND(P45>0,Settings!$C$13<>""),Settings!$C$13&", ","")&IF(AND(Q45>0,Settings!$C$14<>""),Settings!$C$14&", ","")&IF(AND(R45>0,Settings!$C$15<>""),Settings!$C$15&", ","")&IF(AND(S45>0,Settings!$C$16<>""),Settings!$C$16&", ","")&IF(AND(T45>0,Settings!$C$17<>""),Settings!$C$17&", ","")&IF(AND(U45>0,Settings!$C$18<>""),Settings!$C$18&", ","")&IF(AND(V45>0,Settings!$C$19<>""),Settings!$C$19&", ","")&IF(AND(W45>0,Settings!$C$20<>""),Settings!$C$20&", ","")&IF(AND(X45>0,Settings!$C$21<>""),Settings!$C$21&", ","")&IF(AND(Y45>0,Settings!$C$22<>""),Settings!$C$22&", ","")&IF(AND(Z45>0,Settings!$C$23<>""),Settings!$C$23&", ","")&IF(AND(AA45>0,Settings!$C$24<>""),Settings!$C$24&", ","")&IF(AND(AB45>0,Settings!$C$25<>""),Settings!$C$25&", ","")&IF(AND(AC45>0,Settings!$C$26<>""),Settings!$C$26&", ","")&IF(AND(AD45>0,Settings!$C$27<>""),Settings!$C$27&", ","")

Sheet Recipes
B2: Recipes
B3: What goes into one batch of each product. Packaging too, so the cost is right.
B5: Product | C5: Ingredient | D5: Amount a batch | E5: Unit | F5: Cost
B6: Lemon drizzle loaf | C6: Plain flour | D6: 450 | E6: =IF(C6="","",IF(ISNA(MATCH(C6,Ingredients!$B$6:$B$105,0)),"Not on Ingredients",IFERROR(IF(INDEX(Ingredients!$C$6:$C$105,MATCH(C6,Ingredients!$B$6:$B$105,0))="","",INDEX(Ingredients!$C$6:$C$105,MATCH(C6,Ingredients!$B$6:$B$105,0))),""))) | F6: =IF(OR(B6="",C6=""),"",N(D6)*IFERROR(N(INDEX(Ingredients!$H$6:$H$105,MATCH(C6,Ingredients!$B$6:$B$105,0))),0)) | G6: =IF(OR(B6="",C6=""),0,IFERROR(N(INDEX(Products!$D$6:$D$45,MATCH(B6,Products!$B$6:$B$45,0))),0)) | H6: =IF(N(G6)=0,0,N(D6)*SUMIFS(Batches!$D$6:$D$505,Batches!$C$6:$C$505,B6)/G6) | I6: =IF(OR(B6="",C6=""),"",IF(B6<>Label!$H$3,"",IF(IFERROR(N(INDEX(Ingredients!$AS$6:$AS$105,MATCH(C6,Ingredients!$B$6:$B$105,0))),0)=1,"",ROUND(N(D6)*1000,0)*100000+100000-ROW()))) | J6: =IF(OR(B6="",C6=""),0,IFERROR(N(INDEX(Ingredients!$AC$6:$AC$105,MATCH(C6,Ingredients!$B$6:$B$105,0))),0)) | K6: =IF(OR(B6="",C6=""),0,IFERROR(N(INDEX(Ingredients!$AD$6:$AD$105,MATCH(C6,Ingredients!$B$6:$B$105,0))),0)) | L6: =IF(OR(B6="",C6=""),0,IFERROR(N(INDEX(Ingredients!$AE$6:$AE$105,MATCH(C6,Ingredients!$B$6:$B$105,0))),0)) | M6: =IF(OR(B6="",C6=""),0,IFERROR(N(INDEX(Ingredients!$AF$6:$AF$105,MATCH(C6,Ingredients!$B$6:$B$105,0))),0)) | N6: =IF(OR(B6="",C6=""),0,IFERROR(N(INDEX(Ingredients!$AG$6:$AG$105,MATCH(C6,Ingredients!$B$6:$B$105,0))),0)) | O6: =IF(OR(B6="",C6=""),0,IFERROR(N(INDEX(Ingredients!$AH$6:$AH$105,MATCH(C6,Ingredients!$B$6:$B$105,0))),0)) | P6: =IF(OR(B6="",C6=""),0,IFERROR(N(INDEX(Ingredients!$AI$6:$AI$105,MATCH(C6,Ingredients!$B$6:$B$105,0))),0)) | Q6: =IF(OR(B6="",C6=""),0,IFERROR(N(INDEX(Ingredients!$AJ$6:$AJ$105,MATCH(C6,Ingredients!$B$6:$B$105,0))),0)) | R6: =IF(OR(B6="",C6=""),0,IFERROR(N(INDEX(Ingredients!$AK$6:$AK$105,MATCH(C6,Ingredients!$B$6:$B$105,0))),0)) | S6: =IF(OR(B6="",C6=""),0,IFERROR(N(INDEX(Ingredients!$AL$6:$AL$105,MATCH(C6,Ingredients!$B$6:$B$105,0))),0)) | T6: =IF(OR(B6="",C6=""),0,IFERROR(N(INDEX(Ingredients!$AM$6:$AM$105,MATCH(C6,Ingredients!$B$6:$B$105,0))),0)) | U6: =IF(OR(B6="",C6=""),0,IFERROR(N(INDEX(Ingredients!$AN$6:$AN$105,MATCH(C6,Ingredients!$B$6:$B$105,0))),0)) | V6: =IF(OR(B6="",C6=""),0,IFERROR(N(INDEX(Ingredients!$AO$6:$AO$105,MATCH(C6,Ingredients!$B$6:$B$105,0))),0)) | W6: =IF(OR(B6="",C6=""),0,IFERROR(N(INDEX(Ingredients!$AP$6:$AP$105,MATCH(C6,Ingredients!$B$6:$B$105,0))),0)) | X6: =IF(OR(B6="",C6=""),0,IFERROR(N(INDEX(Ingredients!$AQ$6:$AQ$105,MATCH(C6,Ingredients!$B$6:$B$105,0))),0))
B7: Lemon drizzle loaf | C7: Caster sugar | D7: 450 | E7: =IF(C7="","",IF(ISNA(MATCH(C7,Ingredients!$B$6:$B$105,0)),"Not on Ingredients",IFERROR(IF(INDEX(Ingredients!$C$6:$C$105,MATCH(C7,Ingredients!$B$6:$B$105,0))="","",INDEX(Ingredients!$C$6:$C$105,MATCH(C7,Ingredients!$B$6:$B$105,0))),""))) | F7: =IF(OR(B7="",C7=""),"",N(D7)*IFERROR(N(INDEX(Ingredients!$H$6:$H$105,MATCH(C7,Ingredients!$B$6:$B$105,0))),0)) | G7: =IF(OR(B7="",C7=""),0,IFERROR(N(INDEX(Products!$D$6:$D$45,MATCH(B7,Products!$B$6:$B$45,0))),0)) | H7: =IF(N(G7)=0,0,N(D7)*SUMIFS(Batches!$D$6:$D$505,Batches!$C$6:$C$505,B7)/G7) | I7: =IF(OR(B7="",C7=""),"",IF(B7<>Label!$H$3,"",IF(IFERROR(N(INDEX(Ingredients!$AS$6:$AS$105,MATCH(C7,Ingredients!$B$6:$B$105,0))),0)=1,"",ROUND(N(D7)*1000,0)*100000+100000-ROW()))) | J7: =IF(OR(B7="",C7=""),0,IFERROR(N(INDEX(Ingredients!$AC$6:$AC$105,MATCH(C7,Ingredients!$B$6:$B$105,0))),0)) | K7: =IF(OR(B7="",C7=""),0,IFERROR(N(INDEX(Ingredients!$AD$6:$AD$105,MATCH(C7,Ingredients!$B$6:$B$105,0))),0)) | L7: =IF(OR(B7="",C7=""),0,IFERROR(N(INDEX(Ingredients!$AE$6:$AE$105,MATCH(C7,Ingredients!$B$6:$B$105,0))),0)) | M7: =IF(OR(B7="",C7=""),0,IFERROR(N(INDEX(Ingredients!$AF$6:$AF$105,MATCH(C7,Ingredients!$B$6:$B$105,0))),0)) | N7: =IF(OR(B7="",C7=""),0,IFERROR(N(INDEX(Ingredients!$AG$6:$AG$105,MATCH(C7,Ingredients!$B$6:$B$105,0))),0)) | O7: =IF(OR(B7="",C7=""),0,IFERROR(N(INDEX(Ingredients!$AH$6:$AH$105,MATCH(C7,Ingredients!$B$6:$B$105,0))),0)) | P7: =IF(OR(B7="",C7=""),0,IFERROR(N(INDEX(Ingredients!$AI$6:$AI$105,MATCH(C7,Ingredients!$B$6:$B$105,0))),0)) | Q7: =IF(OR(B7="",C7=""),0,IFERROR(N(INDEX(Ingredients!$AJ$6:$AJ$105,MATCH(C7,Ingredients!$B$6:$B$105,0))),0)) | R7: =IF(OR(B7="",C7=""),0,IFERROR(N(INDEX(Ingredients!$AK$6:$AK$105,MATCH(C7,Ingredients!$B$6:$B$105,0))),0)) | S7: =IF(OR(B7="",C7=""),0,IFERROR(N(INDEX(Ingredients!$AL$6:$AL$105,MATCH(C7,Ingredients!$B$6:$B$105,0))),0)) | T7: =IF(OR(B7="",C7=""),0,IFERROR(N(INDEX(Ingredients!$AM$6:$AM$105,MATCH(C7,Ingredients!$B$6:$B$105,0))),0)) | U7: =IF(OR(B7="",C7=""),0,IFERROR(N(INDEX(Ingredients!$AN$6:$AN$105,MATCH(C7,Ingredients!$B$6:$B$105,0))),0)) | V7: =IF(OR(B7="",C7=""),0,IFERROR(N(INDEX(Ingredients!$AO$6:$AO$105,MATCH(C7,Ingredients!$B$6:$B$105,0))),0)) | W7: =IF(OR(B7="",C7=""),0,IFERROR(N(INDEX(Ingredients!$AP$6:$AP$105,MATCH(C7,Ingredients!$B$6:$B$105,0))),0)) | X7: =IF(OR(B7="",C7=""),0,IFERROR(N(INDEX(Ingredients!$AQ$6:$AQ$105,MATCH(C7,Ingredients!$B$6:$B$105,0))),0))
B8: Lemon drizzle loaf | C8: Butter | D8: 450 | E8: =IF(C8="","",IF(ISNA(MATCH(C8,Ingredients!$B$6:$B$105,0)),"Not on Ingredients",IFERROR(IF(INDEX(Ingredients!$C$6:$C$105,MATCH(C8,Ingredients!$B$6:$B$105,0))="","",INDEX(Ingredients!$C$6:$C$105,MATCH(C8,Ingredients!$B$6:$B$105,0))),""))) | F8: =IF(OR(B8="",C8=""),"",N(D8)*IFERROR(N(INDEX(Ingredients!$H$6:$H$105,MATCH(C8,Ingredients!$B$6:$B$105,0))),0)) | G8: =IF(OR(B8="",C8=""),0,IFERROR(N(INDEX(Products!$D$6:$D$45,MATCH(B8,Products!$B$6:$B$45,0))),0)) | H8: =IF(N(G8)=0,0,N(D8)*SUMIFS(Batches!$D$6:$D$505,Batches!$C$6:$C$505,B8)/G8) | I8: =IF(OR(B8="",C8=""),"",IF(B8<>Label!$H$3,"",IF(IFERROR(N(INDEX(Ingredients!$AS$6:$AS$105,MATCH(C8,Ingredients!$B$6:$B$105,0))),0)=1,"",ROUND(N(D8)*1000,0)*100000+100000-ROW()))) | J8: =IF(OR(B8="",C8=""),0,IFERROR(N(INDEX(Ingredients!$AC$6:$AC$105,MATCH(C8,Ingredients!$B$6:$B$105,0))),0)) | K8: =IF(OR(B8="",C8=""),0,IFERROR(N(INDEX(Ingredients!$AD$6:$AD$105,MATCH(C8,Ingredients!$B$6:$B$105,0))),0)) | L8: =IF(OR(B8="",C8=""),0,IFERROR(N(INDEX(Ingredients!$AE$6:$AE$105,MATCH(C8,Ingredients!$B$6:$B$105,0))),0)) | M8: =IF(OR(B8="",C8=""),0,IFERROR(N(INDEX(Ingredients!$AF$6:$AF$105,MATCH(C8,Ingredients!$B$6:$B$105,0))),0)) | N8: =IF(OR(B8="",C8=""),0,IFERROR(N(INDEX(Ingredients!$AG$6:$AG$105,MATCH(C8,Ingredients!$B$6:$B$105,0))),0)) | O8: =IF(OR(B8="",C8=""),0,IFERROR(N(INDEX(Ingredients!$AH$6:$AH$105,MATCH(C8,Ingredients!$B$6:$B$105,0))),0)) | P8: =IF(OR(B8="",C8=""),0,IFERROR(N(INDEX(Ingredients!$AI$6:$AI$105,MATCH(C8,Ingredients!$B$6:$B$105,0))),0)) | Q8: =IF(OR(B8="",C8=""),0,IFERROR(N(INDEX(Ingredients!$AJ$6:$AJ$105,MATCH(C8,Ingredients!$B$6:$B$105,0))),0)) | R8: =IF(OR(B8="",C8=""),0,IFERROR(N(INDEX(Ingredients!$AK$6:$AK$105,MATCH(C8,Ingredients!$B$6:$B$105,0))),0)) | S8: =IF(OR(B8="",C8=""),0,IFERROR(N(INDEX(Ingredients!$AL$6:$AL$105,MATCH(C8,Ingredients!$B$6:$B$105,0))),0)) | T8: =IF(OR(B8="",C8=""),0,IFERROR(N(INDEX(Ingredients!$AM$6:$AM$105,MATCH(C8,Ingredients!$B$6:$B$105,0))),0)) | U8: =IF(OR(B8="",C8=""),0,IFERROR(N(INDEX(Ingredients!$AN$6:$AN$105,MATCH(C8,Ingredients!$B$6:$B$105,0))),0)) | V8: =IF(OR(B8="",C8=""),0,IFERROR(N(INDEX(Ingredients!$AO$6:$AO$105,MATCH(C8,Ingredients!$B$6:$B$105,0))),0)) | W8: =IF(OR(B8="",C8=""),0,IFERROR(N(INDEX(Ingredients!$AP$6:$AP$105,MATCH(C8,Ingredients!$B$6:$B$105,0))),0)) | X8: =IF(OR(B8="",C8=""),0,IFERROR(N(INDEX(Ingredients!$AQ$6:$AQ$105,MATCH(C8,Ingredients!$B$6:$B$105,0))),0))
B9: Lemon drizzle loaf | C9: Eggs | D9: 400 | E9: =IF(C9="","",IF(ISNA(MATCH(C9,Ingredients!$B$6:$B$105,0)),"Not on Ingredients",IFERROR(IF(INDEX(Ingredients!$C$6:$C$105,MATCH(C9,Ingredients!$B$6:$B$105,0))="","",INDEX(Ingredients!$C$6:$C$105,MATCH(C9,Ingredients!$B$6:$B$105,0))),""))) | F9: =IF(OR(B9="",C9=""),"",N(D9)*IFERROR(N(INDEX(Ingredients!$H$6:$H$105,MATCH(C9,Ingredients!$B$6:$B$105,0))),0)) | G9: =IF(OR(B9="",C9=""),0,IFERROR(N(INDEX(Products!$D$6:$D$45,MATCH(B9,Products!$B$6:$B$45,0))),0)) | H9: =IF(N(G9)=0,0,N(D9)*SUMIFS(Batches!$D$6:$D$505,Batches!$C$6:$C$505,B9)/G9) | I9: =IF(OR(B9="",C9=""),"",IF(B9<>Label!$H$3,"",IF(IFERROR(N(INDEX(Ingredients!$AS$6:$AS$105,MATCH(C9,Ingredients!$B$6:$B$105,0))),0)=1,"",ROUND(N(D9)*1000,0)*100000+100000-ROW()))) | J9: =IF(OR(B9="",C9=""),0,IFERROR(N(INDEX(Ingredients!$AC$6:$AC$105,MATCH(C9,Ingredients!$B$6:$B$105,0))),0)) | K9: =IF(OR(B9="",C9=""),0,IFERROR(N(INDEX(Ingredients!$AD$6:$AD$105,MATCH(C9,Ingredients!$B$6:$B$105,0))),0)) | L9: =IF(OR(B9="",C9=""),0,IFERROR(N(INDEX(Ingredients!$AE$6:$AE$105,MATCH(C9,Ingredients!$B$6:$B$105,0))),0)) | M9: =IF(OR(B9="",C9=""),0,IFERROR(N(INDEX(Ingredients!$AF$6:$AF$105,MATCH(C9,Ingredients!$B$6:$B$105,0))),0)) | N9: =IF(OR(B9="",C9=""),0,IFERROR(N(INDEX(Ingredients!$AG$6:$AG$105,MATCH(C9,Ingredients!$B$6:$B$105,0))),0)) | O9: =IF(OR(B9="",C9=""),0,IFERROR(N(INDEX(Ingredients!$AH$6:$AH$105,MATCH(C9,Ingredients!$B$6:$B$105,0))),0)) | P9: =IF(OR(B9="",C9=""),0,IFERROR(N(INDEX(Ingredients!$AI$6:$AI$105,MATCH(C9,Ingredients!$B$6:$B$105,0))),0)) | Q9: =IF(OR(B9="",C9=""),0,IFERROR(N(INDEX(Ingredients!$AJ$6:$AJ$105,MATCH(C9,Ingredients!$B$6:$B$105,0))),0)) | R9: =IF(OR(B9="",C9=""),0,IFERROR(N(INDEX(Ingredients!$AK$6:$AK$105,MATCH(C9,Ingredients!$B$6:$B$105,0))),0)) | S9: =IF(OR(B9="",C9=""),0,IFERROR(N(INDEX(Ingredients!$AL$6:$AL$105,MATCH(C9,Ingredients!$B$6:$B$105,0))),0)) | T9: =IF(OR(B9="",C9=""),0,IFERROR(N(INDEX(Ingredients!$AM$6:$AM$105,MATCH(C9,Ingredients!$B$6:$B$105,0))),0)) | U9: =IF(OR(B9="",C9=""),0,IFERROR(N(INDEX(Ingredients!$AN$6:$AN$105,MATCH(C9,Ingredients!$B$6:$B$105,0))),0)) | V9: =IF(OR(B9="",C9=""),0,IFERROR(N(INDEX(Ingredients!$AO$6:$AO$105,MATCH(C9,Ingredients!$B$6:$B$105,0))),0)) | W9: =IF(OR(B9="",C9=""),0,IFERROR(N(INDEX(Ingredients!$AP$6:$AP$105,MATCH(C9,Ingredients!$B$6:$B$105,0))),0)) | X9: =IF(OR(B9="",C9=""),0,IFERROR(N(INDEX(Ingredients!$AQ$6:$AQ$105,MATCH(C9,Ingredients!$B$6:$B$105,0))),0))
B10: Lemon drizzle loaf | C10: Lemons | D10: 3 | E10: =IF(C10="","",IF(ISNA(MATCH(C10,Ingredients!$B$6:$B$105,0)),"Not on Ingredients",IFERROR(IF(INDEX(Ingredients!$C$6:$C$105,MATCH(C10,Ingredients!$B$6:$B$105,0))="","",INDEX(Ingredients!$C$6:$C$105,MATCH(C10,Ingredients!$B$6:$B$105,0))),""))) | F10: =IF(OR(B10="",C10=""),"",N(D10)*IFERROR(N(INDEX(Ingredients!$H$6:$H$105,MATCH(C10,Ingredients!$B$6:$B$105,0))),0)) | G10: =IF(OR(B10="",C10=""),0,IFERROR(N(INDEX(Products!$D$6:$D$45,MATCH(B10,Products!$B$6:$B$45,0))),0)) | H10: =IF(N(G10)=0,0,N(D10)*SUMIFS(Batches!$D$6:$D$505,Batches!$C$6:$C$505,B10)/G10) | I10: =IF(OR(B10="",C10=""),"",IF(B10<>Label!$H$3,"",IF(IFERROR(N(INDEX(Ingredients!$AS$6:$AS$105,MATCH(C10,Ingredients!$B$6:$B$105,0))),0)=1,"",ROUND(N(D10)*1000,0)*100000+100000-ROW()))) | J10: =IF(OR(B10="",C10=""),0,IFERROR(N(INDEX(Ingredients!$AC$6:$AC$105,MATCH(C10,Ingredients!$B$6:$B$105,0))),0)) | K10: =IF(OR(B10="",C10=""),0,IFERROR(N(INDEX(Ingredients!$AD$6:$AD$105,MATCH(C10,Ingredients!$B$6:$B$105,0))),0)) | L10: =IF(OR(B10="",C10=""),0,IFERROR(N(INDEX(Ingredients!$AE$6:$AE$105,MATCH(C10,Ingredients!$B$6:$B$105,0))),0)) | M10: =IF(OR(B10="",C10=""),0,IFERROR(N(INDEX(Ingredients!$AF$6:$AF$105,MATCH(C10,Ingredients!$B$6:$B$105,0))),0)) | N10: =IF(OR(B10="",C10=""),0,IFERROR(N(INDEX(Ingredients!$AG$6:$AG$105,MATCH(C10,Ingredients!$B$6:$B$105,0))),0)) | O10: =IF(OR(B10="",C10=""),0,IFERROR(N(INDEX(Ingredients!$AH$6:$AH$105,MATCH(C10,Ingredients!$B$6:$B$105,0))),0)) | P10: =IF(OR(B10="",C10=""),0,IFERROR(N(INDEX(Ingredients!$AI$6:$AI$105,MATCH(C10,Ingredients!$B$6:$B$105,0))),0)) | Q10: =IF(OR(B10="",C10=""),0,IFERROR(N(INDEX(Ingredients!$AJ$6:$AJ$105,MATCH(C10,Ingredients!$B$6:$B$105,0))),0)) | R10: =IF(OR(B10="",C10=""),0,IFERROR(N(INDEX(Ingredients!$AK$6:$AK$105,MATCH(C10,Ingredients!$B$6:$B$105,0))),0)) | S10: =IF(OR(B10="",C10=""),0,IFERROR(N(INDEX(Ingredients!$AL$6:$AL$105,MATCH(C10,Ingredients!$B$6:$B$105,0))),0)) | T10: =IF(OR(B10="",C10=""),0,IFERROR(N(INDEX(Ingredients!$AM$6:$AM$105,MATCH(C10,Ingredients!$B$6:$B$105,0))),0)) | U10: =IF(OR(B10="",C10=""),0,IFERROR(N(INDEX(Ingredients!$AN$6:$AN$105,MATCH(C10,Ingredients!$B$6:$B$105,0))),0)) | V10: =IF(OR(B10="",C10=""),0,IFERROR(N(INDEX(Ingredients!$AO$6:$AO$105,MATCH(C10,Ingredients!$B$6:$B$105,0))),0)) | W10: =IF(OR(B10="",C10=""),0,IFERROR(N(INDEX(Ingredients!$AP$6:$AP$105,MATCH(C10,Ingredients!$B$6:$B$105,0))),0)) | X10: =IF(OR(B10="",C10=""),0,IFERROR(N(INDEX(Ingredients!$AQ$6:$AQ$105,MATCH(C10,Ingredients!$B$6:$B$105,0))),0))
B11: Lemon drizzle loaf | C11: Cake boxes | D11: 2 | E11: =IF(C11="","",IF(ISNA(MATCH(C11,Ingredients!$B$6:$B$105,0)),"Not on Ingredients",IFERROR(IF(INDEX(Ingredients!$C$6:$C$105,MATCH(C11,Ingredients!$B$6:$B$105,0))="","",INDEX(Ingredients!$C$6:$C$105,MATCH(C11,Ingredients!$B$6:$B$105,0))),""))) | F11: =IF(OR(B11="",C11=""),"",N(D11)*IFERROR(N(INDEX(Ingredients!$H$6:$H$105,MATCH(C11,Ingredients!$B$6:$B$105,0))),0)) | G11: =IF(OR(B11="",C11=""),0,IFERROR(N(INDEX(Products!$D$6:$D$45,MATCH(B11,Products!$B$6:$B$45,0))),0)) | H11: =IF(N(G11)=0,0,N(D11)*SUMIFS(Batches!$D$6:$D$505,Batches!$C$6:$C$505,B11)/G11) | I11: =IF(OR(B11="",C11=""),"",IF(B11<>Label!$H$3,"",IF(IFERROR(N(INDEX(Ingredients!$AS$6:$AS$105,MATCH(C11,Ingredients!$B$6:$B$105,0))),0)=1,"",ROUND(N(D11)*1000,0)*100000+100000-ROW()))) | J11: =IF(OR(B11="",C11=""),0,IFERROR(N(INDEX(Ingredients!$AC$6:$AC$105,MATCH(C11,Ingredients!$B$6:$B$105,0))),0)) | K11: =IF(OR(B11="",C11=""),0,IFERROR(N(INDEX(Ingredients!$AD$6:$AD$105,MATCH(C11,Ingredients!$B$6:$B$105,0))),0)) | L11: =IF(OR(B11="",C11=""),0,IFERROR(N(INDEX(Ingredients!$AE$6:$AE$105,MATCH(C11,Ingredients!$B$6:$B$105,0))),0)) | M11: =IF(OR(B11="",C11=""),0,IFERROR(N(INDEX(Ingredients!$AF$6:$AF$105,MATCH(C11,Ingredients!$B$6:$B$105,0))),0)) | N11: =IF(OR(B11="",C11=""),0,IFERROR(N(INDEX(Ingredients!$AG$6:$AG$105,MATCH(C11,Ingredients!$B$6:$B$105,0))),0)) | O11: =IF(OR(B11="",C11=""),0,IFERROR(N(INDEX(Ingredients!$AH$6:$AH$105,MATCH(C11,Ingredients!$B$6:$B$105,0))),0)) | P11: =IF(OR(B11="",C11=""),0,IFERROR(N(INDEX(Ingredients!$AI$6:$AI$105,MATCH(C11,Ingredients!$B$6:$B$105,0))),0)) | Q11: =IF(OR(B11="",C11=""),0,IFERROR(N(INDEX(Ingredients!$AJ$6:$AJ$105,MATCH(C11,Ingredients!$B$6:$B$105,0))),0)) | R11: =IF(OR(B11="",C11=""),0,IFERROR(N(INDEX(Ingredients!$AK$6:$AK$105,MATCH(C11,Ingredients!$B$6:$B$105,0))),0)) | S11: =IF(OR(B11="",C11=""),0,IFERROR(N(INDEX(Ingredients!$AL$6:$AL$105,MATCH(C11,Ingredients!$B$6:$B$105,0))),0)) | T11: =IF(OR(B11="",C11=""),0,IFERROR(N(INDEX(Ingredients!$AM$6:$AM$105,MATCH(C11,Ingredients!$B$6:$B$105,0))),0)) | U11: =IF(OR(B11="",C11=""),0,IFERROR(N(INDEX(Ingredients!$AN$6:$AN$105,MATCH(C11,Ingredients!$B$6:$B$105,0))),0)) | V11: =IF(OR(B11="",C11=""),0,IFERROR(N(INDEX(Ingredients!$AO$6:$AO$105,MATCH(C11,Ingredients!$B$6:$B$105,0))),0)) | W11: =IF(OR(B11="",C11=""),0,IFERROR(N(INDEX(Ingredients!$AP$6:$AP$105,MATCH(C11,Ingredients!$B$6:$B$105,0))),0)) | X11: =IF(OR(B11="",C11=""),0,IFERROR(N(INDEX(Ingredients!$AQ$6:$AQ$105,MATCH(C11,Ingredients!$B$6:$B$105,0))),0))
B12: Chocolate chip cookies | C12: Plain flour | D12: 375 | E12: =IF(C12="","",IF(ISNA(MATCH(C12,Ingredients!$B$6:$B$105,0)),"Not on Ingredients",IFERROR(IF(INDEX(Ingredients!$C$6:$C$105,MATCH(C12,Ingredients!$B$6:$B$105,0))="","",INDEX(Ingredients!$C$6:$C$105,MATCH(C12,Ingredients!$B$6:$B$105,0))),""))) | F12: =IF(OR(B12="",C12=""),"",N(D12)*IFERROR(N(INDEX(Ingredients!$H$6:$H$105,MATCH(C12,Ingredients!$B$6:$B$105,0))),0)) | G12: =IF(OR(B12="",C12=""),0,IFERROR(N(INDEX(Products!$D$6:$D$45,MATCH(B12,Products!$B$6:$B$45,0))),0)) | H12: =IF(N(G12)=0,0,N(D12)*SUMIFS(Batches!$D$6:$D$505,Batches!$C$6:$C$505,B12)/G12) | I12: =IF(OR(B12="",C12=""),"",IF(B12<>Label!$H$3,"",IF(IFERROR(N(INDEX(Ingredients!$AS$6:$AS$105,MATCH(C12,Ingredients!$B$6:$B$105,0))),0)=1,"",ROUND(N(D12)*1000,0)*100000+100000-ROW()))) | J12: =IF(OR(B12="",C12=""),0,IFERROR(N(INDEX(Ingredients!$AC$6:$AC$105,MATCH(C12,Ingredients!$B$6:$B$105,0))),0)) | K12: =IF(OR(B12="",C12=""),0,IFERROR(N(INDEX(Ingredients!$AD$6:$AD$105,MATCH(C12,Ingredients!$B$6:$B$105,0))),0)) | L12: =IF(OR(B12="",C12=""),0,IFERROR(N(INDEX(Ingredients!$AE$6:$AE$105,MATCH(C12,Ingredients!$B$6:$B$105,0))),0)) | M12: =IF(OR(B12="",C12=""),0,IFERROR(N(INDEX(Ingredients!$AF$6:$AF$105,MATCH(C12,Ingredients!$B$6:$B$105,0))),0)) | N12: =IF(OR(B12="",C12=""),0,IFERROR(N(INDEX(Ingredients!$AG$6:$AG$105,MATCH(C12,Ingredients!$B$6:$B$105,0))),0)) | O12: =IF(OR(B12="",C12=""),0,IFERROR(N(INDEX(Ingredients!$AH$6:$AH$105,MATCH(C12,Ingredients!$B$6:$B$105,0))),0)) | P12: =IF(OR(B12="",C12=""),0,IFERROR(N(INDEX(Ingredients!$AI$6:$AI$105,MATCH(C12,Ingredients!$B$6:$B$105,0))),0)) | Q12: =IF(OR(B12="",C12=""),0,IFERROR(N(INDEX(Ingredients!$AJ$6:$AJ$105,MATCH(C12,Ingredients!$B$6:$B$105,0))),0)) | R12: =IF(OR(B12="",C12=""),0,IFERROR(N(INDEX(Ingredients!$AK$6:$AK$105,MATCH(C12,Ingredients!$B$6:$B$105,0))),0)) | S12: =IF(OR(B12="",C12=""),0,IFERROR(N(INDEX(Ingredients!$AL$6:$AL$105,MATCH(C12,Ingredients!$B$6:$B$105,0))),0)) | T12: =IF(OR(B12="",C12=""),0,IFERROR(N(INDEX(Ingredients!$AM$6:$AM$105,MATCH(C12,Ingredients!$B$6:$B$105,0))),0)) | U12: =IF(OR(B12="",C12=""),0,IFERROR(N(INDEX(Ingredients!$AN$6:$AN$105,MATCH(C12,Ingredients!$B$6:$B$105,0))),0)) | V12: =IF(OR(B12="",C12=""),0,IFERROR(N(INDEX(Ingredients!$AO$6:$AO$105,MATCH(C12,Ingredients!$B$6:$B$105,0))),0)) | W12: =IF(OR(B12="",C12=""),0,IFERROR(N(INDEX(Ingredients!$AP$6:$AP$105,MATCH(C12,Ingredients!$B$6:$B$105,0))),0)) | X12: =IF(OR(B12="",C12=""),0,IFERROR(N(INDEX(Ingredients!$AQ$6:$AQ$105,MATCH(C12,Ingredients!$B$6:$B$105,0))),0))
B13: Chocolate chip cookies | C13: Dark chocolate chips | D13: 340 | E13: =IF(C13="","",IF(ISNA(MATCH(C13,Ingredients!$B$6:$B$105,0)),"Not on Ingredients",IFERROR(IF(INDEX(Ingredients!$C$6:$C$105,MATCH(C13,Ingredients!$B$6:$B$105,0))="","",INDEX(Ingredients!$C$6:$C$105,MATCH(C13,Ingredients!$B$6:$B$105,0))),""))) | F13: =IF(OR(B13="",C13=""),"",N(D13)*IFERROR(N(INDEX(Ingredients!$H$6:$H$105,MATCH(C13,Ingredients!$B$6:$B$105,0))),0)) | G13: =IF(OR(B13="",C13=""),0,IFERROR(N(INDEX(Products!$D$6:$D$45,MATCH(B13,Products!$B$6:$B$45,0))),0)) | H13: =IF(N(G13)=0,0,N(D13)*SUMIFS(Batches!$D$6:$D$505,Batches!$C$6:$C$505,B13)/G13) | I13: =IF(OR(B13="",C13=""),"",IF(B13<>Label!$H$3,"",IF(IFERROR(N(INDEX(Ingredients!$AS$6:$AS$105,MATCH(C13,Ingredients!$B$6:$B$105,0))),0)=1,"",ROUND(N(D13)*1000,0)*100000+100000-ROW()))) | J13: =IF(OR(B13="",C13=""),0,IFERROR(N(INDEX(Ingredients!$AC$6:$AC$105,MATCH(C13,Ingredients!$B$6:$B$105,0))),0)) | K13: =IF(OR(B13="",C13=""),0,IFERROR(N(INDEX(Ingredients!$AD$6:$AD$105,MATCH(C13,Ingredients!$B$6:$B$105,0))),0)) | L13: =IF(OR(B13="",C13=""),0,IFERROR(N(INDEX(Ingredients!$AE$6:$AE$105,MATCH(C13,Ingredients!$B$6:$B$105,0))),0)) | M13: =IF(OR(B13="",C13=""),0,IFERROR(N(INDEX(Ingredients!$AF$6:$AF$105,MATCH(C13,Ingredients!$B$6:$B$105,0))),0)) | N13: =IF(OR(B13="",C13=""),0,IFERROR(N(INDEX(Ingredients!$AG$6:$AG$105,MATCH(C13,Ingredients!$B$6:$B$105,0))),0)) | O13: =IF(OR(B13="",C13=""),0,IFERROR(N(INDEX(Ingredients!$AH$6:$AH$105,MATCH(C13,Ingredients!$B$6:$B$105,0))),0)) | P13: =IF(OR(B13="",C13=""),0,IFERROR(N(INDEX(Ingredients!$AI$6:$AI$105,MATCH(C13,Ingredients!$B$6:$B$105,0))),0)) | Q13: =IF(OR(B13="",C13=""),0,IFERROR(N(INDEX(Ingredients!$AJ$6:$AJ$105,MATCH(C13,Ingredients!$B$6:$B$105,0))),0)) | R13: =IF(OR(B13="",C13=""),0,IFERROR(N(INDEX(Ingredients!$AK$6:$AK$105,MATCH(C13,Ingredients!$B$6:$B$105,0))),0)) | S13: =IF(OR(B13="",C13=""),0,IFERROR(N(INDEX(Ingredients!$AL$6:$AL$105,MATCH(C13,Ingredients!$B$6:$B$105,0))),0)) | T13: =IF(OR(B13="",C13=""),0,IFERROR(N(INDEX(Ingredients!$AM$6:$AM$105,MATCH(C13,Ingredients!$B$6:$B$105,0))),0)) | U13: =IF(OR(B13="",C13=""),0,IFERROR(N(INDEX(Ingredients!$AN$6:$AN$105,MATCH(C13,Ingredients!$B$6:$B$105,0))),0)) | V13: =IF(OR(B13="",C13=""),0,IFERROR(N(INDEX(Ingredients!$AO$6:$AO$105,MATCH(C13,Ingredients!$B$6:$B$105,0))),0)) | W13: =IF(OR(B13="",C13=""),0,IFERROR(N(INDEX(Ingredients!$AP$6:$AP$105,MATCH(C13,Ingredients!$B$6:$B$105,0))),0)) | X13: =IF(OR(B13="",C13=""),0,IFERROR(N(INDEX(Ingredients!$AQ$6:$AQ$105,MATCH(C13,Ingredients!$B$6:$B$105,0))),0))
B14: Chocolate chip cookies | C14: Caster sugar | D14: 300 | E14: =IF(C14="","",IF(ISNA(MATCH(C14,Ingredients!$B$6:$B$105,0)),"Not on Ingredients",IFERROR(IF(INDEX(Ingredients!$C$6:$C$105,MATCH(C14,Ingredients!$B$6:$B$105,0))="","",INDEX(Ingredients!$C$6:$C$105,MATCH(C14,Ingredients!$B$6:$B$105,0))),""))) | F14: =IF(OR(B14="",C14=""),"",N(D14)*IFERROR(N(INDEX(Ingredients!$H$6:$H$105,MATCH(C14,Ingredients!$B$6:$B$105,0))),0)) | G14: =IF(OR(B14="",C14=""),0,IFERROR(N(INDEX(Products!$D$6:$D$45,MATCH(B14,Products!$B$6:$B$45,0))),0)) | H14: =IF(N(G14)=0,0,N(D14)*SUMIFS(Batches!$D$6:$D$505,Batches!$C$6:$C$505,B14)/G14) | I14: =IF(OR(B14="",C14=""),"",IF(B14<>Label!$H$3,"",IF(IFERROR(N(INDEX(Ingredients!$AS$6:$AS$105,MATCH(C14,Ingredients!$B$6:$B$105,0))),0)=1,"",ROUND(N(D14)*1000,0)*100000+100000-ROW()))) | J14: =IF(OR(B14="",C14=""),0,IFERROR(N(INDEX(Ingredients!$AC$6:$AC$105,MATCH(C14,Ingredients!$B$6:$B$105,0))),0)) | K14: =IF(OR(B14="",C14=""),0,IFERROR(N(INDEX(Ingredients!$AD$6:$AD$105,MATCH(C14,Ingredients!$B$6:$B$105,0))),0)) | L14: =IF(OR(B14="",C14=""),0,IFERROR(N(INDEX(Ingredients!$AE$6:$AE$105,MATCH(C14,Ingredients!$B$6:$B$105,0))),0)) | M14: =IF(OR(B14="",C14=""),0,IFERROR(N(INDEX(Ingredients!$AF$6:$AF$105,MATCH(C14,Ingredients!$B$6:$B$105,0))),0)) | N14: =IF(OR(B14="",C14=""),0,IFERROR(N(INDEX(Ingredients!$AG$6:$AG$105,MATCH(C14,Ingredients!$B$6:$B$105,0))),0)) | O14: =IF(OR(B14="",C14=""),0,IFERROR(N(INDEX(Ingredients!$AH$6:$AH$105,MATCH(C14,Ingredients!$B$6:$B$105,0))),0)) | P14: =IF(OR(B14="",C14=""),0,IFERROR(N(INDEX(Ingredients!$AI$6:$AI$105,MATCH(C14,Ingredients!$B$6:$B$105,0))),0)) | Q14: =IF(OR(B14="",C14=""),0,IFERROR(N(INDEX(Ingredients!$AJ$6:$AJ$105,MATCH(C14,Ingredients!$B$6:$B$105,0))),0)) | R14: =IF(OR(B14="",C14=""),0,IFERROR(N(INDEX(Ingredients!$AK$6:$AK$105,MATCH(C14,Ingredients!$B$6:$B$105,0))),0)) | S14: =IF(OR(B14="",C14=""),0,IFERROR(N(INDEX(Ingredients!$AL$6:$AL$105,MATCH(C14,Ingredients!$B$6:$B$105,0))),0)) | T14: =IF(OR(B14="",C14=""),0,IFERROR(N(INDEX(Ingredients!$AM$6:$AM$105,MATCH(C14,Ingredients!$B$6:$B$105,0))),0)) | U14: =IF(OR(B14="",C14=""),0,IFERROR(N(INDEX(Ingredients!$AN$6:$AN$105,MATCH(C14,Ingredients!$B$6:$B$105,0))),0)) | V14: =IF(OR(B14="",C14=""),0,IFERROR(N(INDEX(Ingredients!$AO$6:$AO$105,MATCH(C14,Ingredients!$B$6:$B$105,0))),0)) | W14: =IF(OR(B14="",C14=""),0,IFERROR(N(INDEX(Ingredients!$AP$6:$AP$105,MATCH(C14,Ingredients!$B$6:$B$105,0))),0)) | X14: =IF(OR(B14="",C14=""),0,IFERROR(N(INDEX(Ingredients!$AQ$6:$AQ$105,MATCH(C14,Ingredients!$B$6:$B$105,0))),0))
B15: Chocolate chip cookies | C15: Butter | D15: 225 | E15: =IF(C15="","",IF(ISNA(MATCH(C15,Ingredients!$B$6:$B$105,0)),"Not on Ingredients",IFERROR(IF(INDEX(Ingredients!$C$6:$C$105,MATCH(C15,Ingredients!$B$6:$B$105,0))="","",INDEX(Ingredients!$C$6:$C$105,MATCH(C15,Ingredients!$B$6:$B$105,0))),""))) | F15: =IF(OR(B15="",C15=""),"",N(D15)*IFERROR(N(INDEX(Ingredients!$H$6:$H$105,MATCH(C15,Ingredients!$B$6:$B$105,0))),0)) | G15: =IF(OR(B15="",C15=""),0,IFERROR(N(INDEX(Products!$D$6:$D$45,MATCH(B15,Products!$B$6:$B$45,0))),0)) | H15: =IF(N(G15)=0,0,N(D15)*SUMIFS(Batches!$D$6:$D$505,Batches!$C$6:$C$505,B15)/G15) | I15: =IF(OR(B15="",C15=""),"",IF(B15<>Label!$H$3,"",IF(IFERROR(N(INDEX(Ingredients!$AS$6:$AS$105,MATCH(C15,Ingredients!$B$6:$B$105,0))),0)=1,"",ROUND(N(D15)*1000,0)*100000+100000-ROW()))) | J15: =IF(OR(B15="",C15=""),0,IFERROR(N(INDEX(Ingredients!$AC$6:$AC$105,MATCH(C15,Ingredients!$B$6:$B$105,0))),0)) | K15: =IF(OR(B15="",C15=""),0,IFERROR(N(INDEX(Ingredients!$AD$6:$AD$105,MATCH(C15,Ingredients!$B$6:$B$105,0))),0)) | L15: =IF(OR(B15="",C15=""),0,IFERROR(N(INDEX(Ingredients!$AE$6:$AE$105,MATCH(C15,Ingredients!$B$6:$B$105,0))),0)) | M15: =IF(OR(B15="",C15=""),0,IFERROR(N(INDEX(Ingredients!$AF$6:$AF$105,MATCH(C15,Ingredients!$B$6:$B$105,0))),0)) | N15: =IF(OR(B15="",C15=""),0,IFERROR(N(INDEX(Ingredients!$AG$6:$AG$105,MATCH(C15,Ingredients!$B$6:$B$105,0))),0)) | O15: =IF(OR(B15="",C15=""),0,IFERROR(N(INDEX(Ingredients!$AH$6:$AH$105,MATCH(C15,Ingredients!$B$6:$B$105,0))),0)) | P15: =IF(OR(B15="",C15=""),0,IFERROR(N(INDEX(Ingredients!$AI$6:$AI$105,MATCH(C15,Ingredients!$B$6:$B$105,0))),0)) | Q15: =IF(OR(B15="",C15=""),0,IFERROR(N(INDEX(Ingredients!$AJ$6:$AJ$105,MATCH(C15,Ingredients!$B$6:$B$105,0))),0)) | R15: =IF(OR(B15="",C15=""),0,IFERROR(N(INDEX(Ingredients!$AK$6:$AK$105,MATCH(C15,Ingredients!$B$6:$B$105,0))),0)) | S15: =IF(OR(B15="",C15=""),0,IFERROR(N(INDEX(Ingredients!$AL$6:$AL$105,MATCH(C15,Ingredients!$B$6:$B$105,0))),0)) | T15: =IF(OR(B15="",C15=""),0,IFERROR(N(INDEX(Ingredients!$AM$6:$AM$105,MATCH(C15,Ingredients!$B$6:$B$105,0))),0)) | U15: =IF(OR(B15="",C15=""),0,IFERROR(N(INDEX(Ingredients!$AN$6:$AN$105,MATCH(C15,Ingredients!$B$6:$B$105,0))),0)) | V15: =IF(OR(B15="",C15=""),0,IFERROR(N(INDEX(Ingredients!$AO$6:$AO$105,MATCH(C15,Ingredients!$B$6:$B$105,0))),0)) | W15: =IF(OR(B15="",C15=""),0,IFERROR(N(INDEX(Ingredients!$AP$6:$AP$105,MATCH(C15,Ingredients!$B$6:$B$105,0))),0)) | X15: =IF(OR(B15="",C15=""),0,IFERROR(N(INDEX(Ingredients!$AQ$6:$AQ$105,MATCH(C15,Ingredients!$B$6:$B$105,0))),0))
B16: Chocolate chip cookies | C16: Eggs | D16: 100 | E16: =IF(C16="","",IF(ISNA(MATCH(C16,Ingredients!$B$6:$B$105,0)),"Not on Ingredients",IFERROR(IF(INDEX(Ingredients!$C$6:$C$105,MATCH(C16,Ingredients!$B$6:$B$105,0))="","",INDEX(Ingredients!$C$6:$C$105,MATCH(C16,Ingredients!$B$6:$B$105,0))),""))) | F16: =IF(OR(B16="",C16=""),"",N(D16)*IFERROR(N(INDEX(Ingredients!$H$6:$H$105,MATCH(C16,Ingredients!$B$6:$B$105,0))),0)) | G16: =IF(OR(B16="",C16=""),0,IFERROR(N(INDEX(Products!$D$6:$D$45,MATCH(B16,Products!$B$6:$B$45,0))),0)) | H16: =IF(N(G16)=0,0,N(D16)*SUMIFS(Batches!$D$6:$D$505,Batches!$C$6:$C$505,B16)/G16) | I16: =IF(OR(B16="",C16=""),"",IF(B16<>Label!$H$3,"",IF(IFERROR(N(INDEX(Ingredients!$AS$6:$AS$105,MATCH(C16,Ingredients!$B$6:$B$105,0))),0)=1,"",ROUND(N(D16)*1000,0)*100000+100000-ROW()))) | J16: =IF(OR(B16="",C16=""),0,IFERROR(N(INDEX(Ingredients!$AC$6:$AC$105,MATCH(C16,Ingredients!$B$6:$B$105,0))),0)) | K16: =IF(OR(B16="",C16=""),0,IFERROR(N(INDEX(Ingredients!$AD$6:$AD$105,MATCH(C16,Ingredients!$B$6:$B$105,0))),0)) | L16: =IF(OR(B16="",C16=""),0,IFERROR(N(INDEX(Ingredients!$AE$6:$AE$105,MATCH(C16,Ingredients!$B$6:$B$105,0))),0)) | M16: =IF(OR(B16="",C16=""),0,IFERROR(N(INDEX(Ingredients!$AF$6:$AF$105,MATCH(C16,Ingredients!$B$6:$B$105,0))),0)) | N16: =IF(OR(B16="",C16=""),0,IFERROR(N(INDEX(Ingredients!$AG$6:$AG$105,MATCH(C16,Ingredients!$B$6:$B$105,0))),0)) | O16: =IF(OR(B16="",C16=""),0,IFERROR(N(INDEX(Ingredients!$AH$6:$AH$105,MATCH(C16,Ingredients!$B$6:$B$105,0))),0)) | P16: =IF(OR(B16="",C16=""),0,IFERROR(N(INDEX(Ingredients!$AI$6:$AI$105,MATCH(C16,Ingredients!$B$6:$B$105,0))),0)) | Q16: =IF(OR(B16="",C16=""),0,IFERROR(N(INDEX(Ingredients!$AJ$6:$AJ$105,MATCH(C16,Ingredients!$B$6:$B$105,0))),0)) | R16: =IF(OR(B16="",C16=""),0,IFERROR(N(INDEX(Ingredients!$AK$6:$AK$105,MATCH(C16,Ingredients!$B$6:$B$105,0))),0)) | S16: =IF(OR(B16="",C16=""),0,IFERROR(N(INDEX(Ingredients!$AL$6:$AL$105,MATCH(C16,Ingredients!$B$6:$B$105,0))),0)) | T16: =IF(OR(B16="",C16=""),0,IFERROR(N(INDEX(Ingredients!$AM$6:$AM$105,MATCH(C16,Ingredients!$B$6:$B$105,0))),0)) | U16: =IF(OR(B16="",C16=""),0,IFERROR(N(INDEX(Ingredients!$AN$6:$AN$105,MATCH(C16,Ingredients!$B$6:$B$105,0))),0)) | V16: =IF(OR(B16="",C16=""),0,IFERROR(N(INDEX(Ingredients!$AO$6:$AO$105,MATCH(C16,Ingredients!$B$6:$B$105,0))),0)) | W16: =IF(OR(B16="",C16=""),0,IFERROR(N(INDEX(Ingredients!$AP$6:$AP$105,MATCH(C16,Ingredients!$B$6:$B$105,0))),0)) | X16: =IF(OR(B16="",C16=""),0,IFERROR(N(INDEX(Ingredients!$AQ$6:$AQ$105,MATCH(C16,Ingredients!$B$6:$B$105,0))),0))
B17: Chocolate chip cookies | C17: Vanilla extract | D17: 5 | E17: =IF(C17="","",IF(ISNA(MATCH(C17,Ingredients!$B$6:$B$105,0)),"Not on Ingredients",IFERROR(IF(INDEX(Ingredients!$C$6:$C$105,MATCH(C17,Ingredients!$B$6:$B$105,0))="","",INDEX(Ingredients!$C$6:$C$105,MATCH(C17,Ingredients!$B$6:$B$105,0))),""))) | F17: =IF(OR(B17="",C17=""),"",N(D17)*IFERROR(N(INDEX(Ingredients!$H$6:$H$105,MATCH(C17,Ingredients!$B$6:$B$105,0))),0)) | G17: =IF(OR(B17="",C17=""),0,IFERROR(N(INDEX(Products!$D$6:$D$45,MATCH(B17,Products!$B$6:$B$45,0))),0)) | H17: =IF(N(G17)=0,0,N(D17)*SUMIFS(Batches!$D$6:$D$505,Batches!$C$6:$C$505,B17)/G17) | I17: =IF(OR(B17="",C17=""),"",IF(B17<>Label!$H$3,"",IF(IFERROR(N(INDEX(Ingredients!$AS$6:$AS$105,MATCH(C17,Ingredients!$B$6:$B$105,0))),0)=1,"",ROUND(N(D17)*1000,0)*100000+100000-ROW()))) | J17: =IF(OR(B17="",C17=""),0,IFERROR(N(INDEX(Ingredients!$AC$6:$AC$105,MATCH(C17,Ingredients!$B$6:$B$105,0))),0)) | K17: =IF(OR(B17="",C17=""),0,IFERROR(N(INDEX(Ingredients!$AD$6:$AD$105,MATCH(C17,Ingredients!$B$6:$B$105,0))),0)) | L17: =IF(OR(B17="",C17=""),0,IFERROR(N(INDEX(Ingredients!$AE$6:$AE$105,MATCH(C17,Ingredients!$B$6:$B$105,0))),0)) | M17: =IF(OR(B17="",C17=""),0,IFERROR(N(INDEX(Ingredients!$AF$6:$AF$105,MATCH(C17,Ingredients!$B$6:$B$105,0))),0)) | N17: =IF(OR(B17="",C17=""),0,IFERROR(N(INDEX(Ingredients!$AG$6:$AG$105,MATCH(C17,Ingredients!$B$6:$B$105,0))),0)) | O17: =IF(OR(B17="",C17=""),0,IFERROR(N(INDEX(Ingredients!$AH$6:$AH$105,MATCH(C17,Ingredients!$B$6:$B$105,0))),0)) | P17: =IF(OR(B17="",C17=""),0,IFERROR(N(INDEX(Ingredients!$AI$6:$AI$105,MATCH(C17,Ingredients!$B$6:$B$105,0))),0)) | Q17: =IF(OR(B17="",C17=""),0,IFERROR(N(INDEX(Ingredients!$AJ$6:$AJ$105,MATCH(C17,Ingredients!$B$6:$B$105,0))),0)) | R17: =IF(OR(B17="",C17=""),0,IFERROR(N(INDEX(Ingredients!$AK$6:$AK$105,MATCH(C17,Ingredients!$B$6:$B$105,0))),0)) | S17: =IF(OR(B17="",C17=""),0,IFERROR(N(INDEX(Ingredients!$AL$6:$AL$105,MATCH(C17,Ingredients!$B$6:$B$105,0))),0)) | T17: =IF(OR(B17="",C17=""),0,IFERROR(N(INDEX(Ingredients!$AM$6:$AM$105,MATCH(C17,Ingredients!$B$6:$B$105,0))),0)) | U17: =IF(OR(B17="",C17=""),0,IFERROR(N(INDEX(Ingredients!$AN$6:$AN$105,MATCH(C17,Ingredients!$B$6:$B$105,0))),0)) | V17: =IF(OR(B17="",C17=""),0,IFERROR(N(INDEX(Ingredients!$AO$6:$AO$105,MATCH(C17,Ingredients!$B$6:$B$105,0))),0)) | W17: =IF(OR(B17="",C17=""),0,IFERROR(N(INDEX(Ingredients!$AP$6:$AP$105,MATCH(C17,Ingredients!$B$6:$B$105,0))),0)) | X17: =IF(OR(B17="",C17=""),0,IFERROR(N(INDEX(Ingredients!$AQ$6:$AQ$105,MATCH(C17,Ingredients!$B$6:$B$105,0))),0))
... B53: Brownies | C53: Cake boxes | D53: 2 | E53: =IF(C53="","",IF(ISNA(MATCH(C53,Ingredients!$B$6:$B$105,0)),"Not on Ingredients",IFERROR(IF(INDEX(Ingredients!$C$6:$C$105,MATCH(C53,Ingredients!$B$6:$B$105,0))="","",INDEX(Ingredients!$C$6:$C$105,MATCH(C53,Ingredients!$B$6:$B$105,0))),""))) | F53: =IF(OR(B53="",C53=""),"",N(D53)*IFERROR(N(INDEX(Ingredients!$H$6:$H$105,MATCH(C53,Ingredients!$B$6:$B$105,0))),0)) | G53: =IF(OR(B53="",C53=""),0,IFERROR(N(INDEX(Products!$D$6:$D$45,MATCH(B53,Products!$B$6:$B$45,0))),0)) | H53: =IF(N(G53)=0,0,N(D53)*SUMIFS(Batches!$D$6:$D$505,Batches!$C$6:$C$505,B53)/G53) | I53: =IF(OR(B53="",C53=""),"",IF(B53<>Label!$H$3,"",IF(IFERROR(N(INDEX(Ingredients!$AS$6:$AS$105,MATCH(C53,Ingredients!$B$6:$B$105,0))),0)=1,"",ROUND(N(D53)*1000,0)*100000+100000-ROW()))) | J53: =IF(OR(B53="",C53=""),0,IFERROR(N(INDEX(Ingredients!$AC$6:$AC$105,MATCH(C53,Ingredients!$B$6:$B$105,0))),0)) | K53: =IF(OR(B53="",C53=""),0,IFERROR(N(INDEX(Ingredients!$AD$6:$AD$105,MATCH(C53,Ingredients!$B$6:$B$105,0))),0)) | L53: =IF(OR(B53="",C53=""),0,IFERROR(N(INDEX(Ingredients!$AE$6:$AE$105,MATCH(C53,Ingredients!$B$6:$B$105,0))),0)) | M53: =IF(OR(B53="",C53=""),0,IFERROR(N(INDEX(Ingredients!$AF$6:$AF$105,MATCH(C53,Ingredients!$B$6:$B$105,0))),0)) | N53: =IF(OR(B53="",C53=""),0,IFERROR(N(INDEX(Ingredients!$AG$6:$AG$105,MATCH(C53,Ingredients!$B$6:$B$105,0))),0)) | O53: =IF(OR(B53="",C53=""),0,IFERROR(N(INDEX(Ingredients!$AH$6:$AH$105,MATCH(C53,Ingredients!$B$6:$B$105,0))),0)) | P53: =IF(OR(B53="",C53=""),0,IFERROR(N(INDEX(Ingredients!$AI$6:$AI$105,MATCH(C53,Ingredients!$B$6:$B$105,0))),0)) | Q53: =IF(OR(B53="",C53=""),0,IFERROR(N(INDEX(Ingredients!$AJ$6:$AJ$105,MATCH(C53,Ingredients!$B$6:$B$105,0))),0)) | R53: =IF(OR(B53="",C53=""),0,IFERROR(N(INDEX(Ingredients!$AK$6:$AK$105,MATCH(C53,Ingredients!$B$6:$B$105,0))),0)) | S53: =IF(OR(B53="",C53=""),0,IFERROR(N(INDEX(Ingredients!$AL$6:$AL$105,MATCH(C53,Ingredients!$B$6:$B$105,0))),0)) | T53: =IF(OR(B53="",C53=""),0,IFERROR(N(INDEX(Ingredients!$AM$6:$AM$105,MATCH(C53,Ingredients!$B$6:$B$105,0))),0)) | U53: =IF(OR(B53="",C53=""),0,IFERROR(N(INDEX(Ingredients!$AN$6:$AN$105,MATCH(C53,Ingredients!$B$6:$B$105,0))),0)) | V53: =IF(OR(B53="",C53=""),0,IFERROR(N(INDEX(Ingredients!$AO$6:$AO$105,MATCH(C53,Ingredients!$B$6:$B$105,0))),0)) | W53: =IF(OR(B53="",C53=""),0,IFERROR(N(INDEX(Ingredients!$AP$6:$AP$105,MATCH(C53,Ingredients!$B$6:$B$105,0))),0)) | X53: =IF(OR(B53="",C53=""),0,IFERROR(N(INDEX(Ingredients!$AQ$6:$AQ$105,MATCH(C53,Ingredients!$B$6:$B$105,0))),0))
E54: =IF(C54="","",IF(ISNA(MATCH(C54,Ingredients!$B$6:$B$105,0)),"Not on Ingredients",IFERROR(IF(INDEX(Ingredients!$C$6:$C$105,MATCH(C54,Ingredients!$B$6:$B$105,0))="","",INDEX(Ingredients!$C$6:$C$105,MATCH(C54,Ingredients!$B$6:$B$105,0))),""))) | F54: =IF(OR(B54="",C54=""),"",N(D54)*IFERROR(N(INDEX(Ingredients!$H$6:$H$105,MATCH(C54,Ingredients!$B$6:$B$105,0))),0)) | G54: =IF(OR(B54="",C54=""),0,IFERROR(N(INDEX(Products!$D$6:$D$45,MATCH(B54,Products!$B$6:$B$45,0))),0)) | H54: =IF(N(G54)=0,0,N(D54)*SUMIFS(Batches!$D$6:$D$505,Batches!$C$6:$C$505,B54)/G54) | I54: =IF(OR(B54="",C54=""),"",IF(B54<>Label!$H$3,"",IF(IFERROR(N(INDEX(Ingredients!$AS$6:$AS$105,MATCH(C54,Ingredients!$B$6:$B$105,0))),0)=1,"",ROUND(N(D54)*1000,0)*100000+100000-ROW()))) | J54: =IF(OR(B54="",C54=""),0,IFERROR(N(INDEX(Ingredients!$AC$6:$AC$105,MATCH(C54,Ingredients!$B$6:$B$105,0))),0)) | K54: =IF(OR(B54="",C54=""),0,IFERROR(N(INDEX(Ingredients!$AD$6:$AD$105,MATCH(C54,Ingredients!$B$6:$B$105,0))),0)) | L54: =IF(OR(B54="",C54=""),0,IFERROR(N(INDEX(Ingredients!$AE$6:$AE$105,MATCH(C54,Ingredients!$B$6:$B$105,0))),0)) | M54: =IF(OR(B54="",C54=""),0,IFERROR(N(INDEX(Ingredients!$AF$6:$AF$105,MATCH(C54,Ingredients!$B$6:$B$105,0))),0)) | N54: =IF(OR(B54="",C54=""),0,IFERROR(N(INDEX(Ingredients!$AG$6:$AG$105,MATCH(C54,Ingredients!$B$6:$B$105,0))),0)) | O54: =IF(OR(B54="",C54=""),0,IFERROR(N(INDEX(Ingredients!$AH$6:$AH$105,MATCH(C54,Ingredients!$B$6:$B$105,0))),0)) | P54: =IF(OR(B54="",C54=""),0,IFERROR(N(INDEX(Ingredients!$AI$6:$AI$105,MATCH(C54,Ingredients!$B$6:$B$105,0))),0)) | Q54: =IF(OR(B54="",C54=""),0,IFERROR(N(INDEX(Ingredients!$AJ$6:$AJ$105,MATCH(C54,Ingredients!$B$6:$B$105,0))),0)) | R54: =IF(OR(B54="",C54=""),0,IFERROR(N(INDEX(Ingredients!$AK$6:$AK$105,MATCH(C54,Ingredients!$B$6:$B$105,0))),0)) | S54: =IF(OR(B54="",C54=""),0,IFERROR(N(INDEX(Ingredients!$AL$6:$AL$105,MATCH(C54,Ingredients!$B$6:$B$105,0))),0)) | T54: =IF(OR(B54="",C54=""),0,IFERROR(N(INDEX(Ingredients!$AM$6:$AM$105,MATCH(C54,Ingredients!$B$6:$B$105,0))),0)) | U54: =IF(OR(B54="",C54=""),0,IFERROR(N(INDEX(Ingredients!$AN$6:$AN$105,MATCH(C54,Ingredients!$B$6:$B$105,0))),0)) | V54: =IF(OR(B54="",C54=""),0,IFERROR(N(INDEX(Ingredients!$AO$6:$AO$105,MATCH(C54,Ingredients!$B$6:$B$105,0))),0)) | W54: =IF(OR(B54="",C54=""),0,IFERROR(N(INDEX(Ingredients!$AP$6:$AP$105,MATCH(C54,Ingredients!$B$6:$B$105,0))),0)) | X54: =IF(OR(B54="",C54=""),0,IFERROR(N(INDEX(Ingredients!$AQ$6:$AQ$105,MATCH(C54,Ingredients!$B$6:$B$105,0))),0))
E55: =IF(C55="","",IF(ISNA(MATCH(C55,Ingredients!$B$6:$B$105,0)),"Not on Ingredients",IFERROR(IF(INDEX(Ingredients!$C$6:$C$105,MATCH(C55,Ingredients!$B$6:$B$105,0))="","",INDEX(Ingredients!$C$6:$C$105,MATCH(C55,Ingredients!$B$6:$B$105,0))),""))) | F55: =IF(OR(B55="",C55=""),"",N(D55)*IFERROR(N(INDEX(Ingredients!$H$6:$H$105,MATCH(C55,Ingredients!$B$6:$B$105,0))),0)) | G55: =IF(OR(B55="",C55=""),0,IFERROR(N(INDEX(Products!$D$6:$D$45,MATCH(B55,Products!$B$6:$B$45,0))),0)) | H55: =IF(N(G55)=0,0,N(D55)*SUMIFS(Batches!$D$6:$D$505,Batches!$C$6:$C$505,B55)/G55) | I55: =IF(OR(B55="",C55=""),"",IF(B55<>Label!$H$3,"",IF(IFERROR(N(INDEX(Ingredients!$AS$6:$AS$105,MATCH(C55,Ingredients!$B$6:$B$105,0))),0)=1,"",ROUND(N(D55)*1000,0)*100000+100000-ROW()))) | J55: =IF(OR(B55="",C55=""),0,IFERROR(N(INDEX(Ingredients!$AC$6:$AC$105,MATCH(C55,Ingredients!$B$6:$B$105,0))),0)) | K55: =IF(OR(B55="",C55=""),0,IFERROR(N(INDEX(Ingredients!$AD$6:$AD$105,MATCH(C55,Ingredients!$B$6:$B$105,0))),0)) | L55: =IF(OR(B55="",C55=""),0,IFERROR(N(INDEX(Ingredients!$AE$6:$AE$105,MATCH(C55,Ingredients!$B$6:$B$105,0))),0)) | M55: =IF(OR(B55="",C55=""),0,IFERROR(N(INDEX(Ingredients!$AF$6:$AF$105,MATCH(C55,Ingredients!$B$6:$B$105,0))),0)) | N55: =IF(OR(B55="",C55=""),0,IFERROR(N(INDEX(Ingredients!$AG$6:$AG$105,MATCH(C55,Ingredients!$B$6:$B$105,0))),0)) | O55: =IF(OR(B55="",C55=""),0,IFERROR(N(INDEX(Ingredients!$AH$6:$AH$105,MATCH(C55,Ingredients!$B$6:$B$105,0))),0)) | P55: =IF(OR(B55="",C55=""),0,IFERROR(N(INDEX(Ingredients!$AI$6:$AI$105,MATCH(C55,Ingredients!$B$6:$B$105,0))),0)) | Q55: =IF(OR(B55="",C55=""),0,IFERROR(N(INDEX(Ingredients!$AJ$6:$AJ$105,MATCH(C55,Ingredients!$B$6:$B$105,0))),0)) | R55: =IF(OR(B55="",C55=""),0,IFERROR(N(INDEX(Ingredients!$AK$6:$AK$105,MATCH(C55,Ingredients!$B$6:$B$105,0))),0)) | S55: =IF(OR(B55="",C55=""),0,IFERROR(N(INDEX(Ingredients!$AL$6:$AL$105,MATCH(C55,Ingredients!$B$6:$B$105,0))),0)) | T55: =IF(OR(B55="",C55=""),0,IFERROR(N(INDEX(Ingredients!$AM$6:$AM$105,MATCH(C55,Ingredients!$B$6:$B$105,0))),0)) | U55: =IF(OR(B55="",C55=""),0,IFERROR(N(INDEX(Ingredients!$AN$6:$AN$105,MATCH(C55,Ingredients!$B$6:$B$105,0))),0)) | V55: =IF(OR(B55="",C55=""),0,IFERROR(N(INDEX(Ingredients!$AO$6:$AO$105,MATCH(C55,Ingredients!$B$6:$B$105,0))),0)) | W55: =IF(OR(B55="",C55=""),0,IFERROR(N(INDEX(Ingredients!$AP$6:$AP$105,MATCH(C55,Ingredients!$B$6:$B$105,0))),0)) | X55: =IF(OR(B55="",C55=""),0,IFERROR(N(INDEX(Ingredients!$AQ$6:$AQ$105,MATCH(C55,Ingredients!$B$6:$B$105,0))),0))
E56: =IF(C56="","",IF(ISNA(MATCH(C56,Ingredients!$B$6:$B$105,0)),"Not on Ingredients",IFERROR(IF(INDEX(Ingredients!$C$6:$C$105,MATCH(C56,Ingredients!$B$6:$B$105,0))="","",INDEX(Ingredients!$C$6:$C$105,MATCH(C56,Ingredients!$B$6:$B$105,0))),""))) | F56: =IF(OR(B56="",C56=""),"",N(D56)*IFERROR(N(INDEX(Ingredients!$H$6:$H$105,MATCH(C56,Ingredients!$B$6:$B$105,0))),0)) | G56: =IF(OR(B56="",C56=""),0,IFERROR(N(INDEX(Products!$D$6:$D$45,MATCH(B56,Products!$B$6:$B$45,0))),0)) | H56: =IF(N(G56)=0,0,N(D56)*SUMIFS(Batches!$D$6:$D$505,Batches!$C$6:$C$505,B56)/G56) | I56: =IF(OR(B56="",C56=""),"",IF(B56<>Label!$H$3,"",IF(IFERROR(N(INDEX(Ingredients!$AS$6:$AS$105,MATCH(C56,Ingredients!$B$6:$B$105,0))),0)=1,"",ROUND(N(D56)*1000,0)*100000+100000-ROW()))) | J56: =IF(OR(B56="",C56=""),0,IFERROR(N(INDEX(Ingredients!$AC$6:$AC$105,MATCH(C56,Ingredients!$B$6:$B$105,0))),0)) | K56: =IF(OR(B56="",C56=""),0,IFERROR(N(INDEX(Ingredients!$AD$6:$AD$105,MATCH(C56,Ingredients!$B$6:$B$105,0))),0)) | L56: =IF(OR(B56="",C56=""),0,IFERROR(N(INDEX(Ingredients!$AE$6:$AE$105,MATCH(C56,Ingredients!$B$6:$B$105,0))),0)) | M56: =IF(OR(B56="",C56=""),0,IFERROR(N(INDEX(Ingredients!$AF$6:$AF$105,MATCH(C56,Ingredients!$B$6:$B$105,0))),0)) | N56: =IF(OR(B56="",C56=""),0,IFERROR(N(INDEX(Ingredients!$AG$6:$AG$105,MATCH(C56,Ingredients!$B$6:$B$105,0))),0)) | O56: =IF(OR(B56="",C56=""),0,IFERROR(N(INDEX(Ingredients!$AH$6:$AH$105,MATCH(C56,Ingredients!$B$6:$B$105,0))),0)) | P56: =IF(OR(B56="",C56=""),0,IFERROR(N(INDEX(Ingredients!$AI$6:$AI$105,MATCH(C56,Ingredients!$B$6:$B$105,0))),0)) | Q56: =IF(OR(B56="",C56=""),0,IFERROR(N(INDEX(Ingredients!$AJ$6:$AJ$105,MATCH(C56,Ingredients!$B$6:$B$105,0))),0)) | R56: =IF(OR(B56="",C56=""),0,IFERROR(N(INDEX(Ingredients!$AK$6:$AK$105,MATCH(C56,Ingredients!$B$6:$B$105,0))),0)) | S56: =IF(OR(B56="",C56=""),0,IFERROR(N(INDEX(Ingredients!$AL$6:$AL$105,MATCH(C56,Ingredients!$B$6:$B$105,0))),0)) | T56: =IF(OR(B56="",C56=""),0,IFERROR(N(INDEX(Ingredients!$AM$6:$AM$105,MATCH(C56,Ingredients!$B$6:$B$105,0))),0)) | U56: =IF(OR(B56="",C56=""),0,IFERROR(N(INDEX(Ingredients!$AN$6:$AN$105,MATCH(C56,Ingredients!$B$6:$B$105,0))),0)) | V56: =IF(OR(B56="",C56=""),0,IFERROR(N(INDEX(Ingredients!$AO$6:$AO$105,MATCH(C56,Ingredients!$B$6:$B$105,0))),0)) | W56: =IF(OR(B56="",C56=""),0,IFERROR(N(INDEX(Ingredients!$AP$6:$AP$105,MATCH(C56,Ingredients!$B$6:$B$105,0))),0)) | X56: =IF(OR(B56="",C56=""),0,IFERROR(N(INDEX(Ingredients!$AQ$6:$AQ$105,MATCH(C56,Ingredients!$B$6:$B$105,0))),0))
E57: =IF(C57="","",IF(ISNA(MATCH(C57,Ingredients!$B$6:$B$105,0)),"Not on Ingredients",IFERROR(IF(INDEX(Ingredients!$C$6:$C$105,MATCH(C57,Ingredients!$B$6:$B$105,0))="","",INDEX(Ingredients!$C$6:$C$105,MATCH(C57,Ingredients!$B$6:$B$105,0))),""))) | F57: =IF(OR(B57="",C57=""),"",N(D57)*IFERROR(N(INDEX(Ingredients!$H$6:$H$105,MATCH(C57,Ingredients!$B$6:$B$105,0))),0)) | G57: =IF(OR(B57="",C57=""),0,IFERROR(N(INDEX(Products!$D$6:$D$45,MATCH(B57,Products!$B$6:$B$45,0))),0)) | H57: =IF(N(G57)=0,0,N(D57)*SUMIFS(Batches!$D$6:$D$505,Batches!$C$6:$C$505,B57)/G57) | I57: =IF(OR(B57="",C57=""),"",IF(B57<>Label!$H$3,"",IF(IFERROR(N(INDEX(Ingredients!$AS$6:$AS$105,MATCH(C57,Ingredients!$B$6:$B$105,0))),0)=1,"",ROUND(N(D57)*1000,0)*100000+100000-ROW()))) | J57: =IF(OR(B57="",C57=""),0,IFERROR(N(INDEX(Ingredients!$AC$6:$AC$105,MATCH(C57,Ingredients!$B$6:$B$105,0))),0)) | K57: =IF(OR(B57="",C57=""),0,IFERROR(N(INDEX(Ingredients!$AD$6:$AD$105,MATCH(C57,Ingredients!$B$6:$B$105,0))),0)) | L57: =IF(OR(B57="",C57=""),0,IFERROR(N(INDEX(Ingredients!$AE$6:$AE$105,MATCH(C57,Ingredients!$B$6:$B$105,0))),0)) | M57: =IF(OR(B57="",C57=""),0,IFERROR(N(INDEX(Ingredients!$AF$6:$AF$105,MATCH(C57,Ingredients!$B$6:$B$105,0))),0)) | N57: =IF(OR(B57="",C57=""),0,IFERROR(N(INDEX(Ingredients!$AG$6:$AG$105,MATCH(C57,Ingredients!$B$6:$B$105,0))),0)) | O57: =IF(OR(B57="",C57=""),0,IFERROR(N(INDEX(Ingredients!$AH$6:$AH$105,MATCH(C57,Ingredients!$B$6:$B$105,0))),0)) | P57: =IF(OR(B57="",C57=""),0,IFERROR(N(INDEX(Ingredients!$AI$6:$AI$105,MATCH(C57,Ingredients!$B$6:$B$105,0))),0)) | Q57: =IF(OR(B57="",C57=""),0,IFERROR(N(INDEX(Ingredients!$AJ$6:$AJ$105,MATCH(C57,Ingredients!$B$6:$B$105,0))),0)) | R57: =IF(OR(B57="",C57=""),0,IFERROR(N(INDEX(Ingredients!$AK$6:$AK$105,MATCH(C57,Ingredients!$B$6:$B$105,0))),0)) | S57: =IF(OR(B57="",C57=""),0,IFERROR(N(INDEX(Ingredients!$AL$6:$AL$105,MATCH(C57,Ingredients!$B$6:$B$105,0))),0)) | T57: =IF(OR(B57="",C57=""),0,IFERROR(N(INDEX(Ingredients!$AM$6:$AM$105,MATCH(C57,Ingredients!$B$6:$B$105,0))),0)) | U57: =IF(OR(B57="",C57=""),0,IFERROR(N(INDEX(Ingredients!$AN$6:$AN$105,MATCH(C57,Ingredients!$B$6:$B$105,0))),0)) | V57: =IF(OR(B57="",C57=""),0,IFERROR(N(INDEX(Ingredients!$AO$6:$AO$105,MATCH(C57,Ingredients!$B$6:$B$105,0))),0)) | W57: =IF(OR(B57="",C57=""),0,IFERROR(N(INDEX(Ingredients!$AP$6:$AP$105,MATCH(C57,Ingredients!$B$6:$B$105,0))),0)) | X57: =IF(OR(B57="",C57=""),0,IFERROR(N(INDEX(Ingredients!$AQ$6:$AQ$105,MATCH(C57,Ingredients!$B$6:$B$105,0))),0))
E58: =IF(C58="","",IF(ISNA(MATCH(C58,Ingredients!$B$6:$B$105,0)),"Not on Ingredients",IFERROR(IF(INDEX(Ingredients!$C$6:$C$105,MATCH(C58,Ingredients!$B$6:$B$105,0))="","",INDEX(Ingredients!$C$6:$C$105,MATCH(C58,Ingredients!$B$6:$B$105,0))),""))) | F58: =IF(OR(B58="",C58=""),"",N(D58)*IFERROR(N(INDEX(Ingredients!$H$6:$H$105,MATCH(C58,Ingredients!$B$6:$B$105,0))),0)) | G58: =IF(OR(B58="",C58=""),0,IFERROR(N(INDEX(Products!$D$6:$D$45,MATCH(B58,Products!$B$6:$B$45,0))),0)) | H58: =IF(N(G58)=0,0,N(D58)*SUMIFS(Batches!$D$6:$D$505,Batches!$C$6:$C$505,B58)/G58) | I58: =IF(OR(B58="",C58=""),"",IF(B58<>Label!$H$3,"",IF(IFERROR(N(INDEX(Ingredients!$AS$6:$AS$105,MATCH(C58,Ingredients!$B$6:$B$105,0))),0)=1,"",ROUND(N(D58)*1000,0)*100000+100000-ROW()))) | J58: =IF(OR(B58="",C58=""),0,IFERROR(N(INDEX(Ingredients!$AC$6:$AC$105,MATCH(C58,Ingredients!$B$6:$B$105,0))),0)) | K58: =IF(OR(B58="",C58=""),0,IFERROR(N(INDEX(Ingredients!$AD$6:$AD$105,MATCH(C58,Ingredients!$B$6:$B$105,0))),0)) | L58: =IF(OR(B58="",C58=""),0,IFERROR(N(INDEX(Ingredients!$AE$6:$AE$105,MATCH(C58,Ingredients!$B$6:$B$105,0))),0)) | M58: =IF(OR(B58="",C58=""),0,IFERROR(N(INDEX(Ingredients!$AF$6:$AF$105,MATCH(C58,Ingredients!$B$6:$B$105,0))),0)) | N58: =IF(OR(B58="",C58=""),0,IFERROR(N(INDEX(Ingredients!$AG$6:$AG$105,MATCH(C58,Ingredients!$B$6:$B$105,0))),0)) | O58: =IF(OR(B58="",C58=""),0,IFERROR(N(INDEX(Ingredients!$AH$6:$AH$105,MATCH(C58,Ingredients!$B$6:$B$105,0))),0)) | P58: =IF(OR(B58="",C58=""),0,IFERROR(N(INDEX(Ingredients!$AI$6:$AI$105,MATCH(C58,Ingredients!$B$6:$B$105,0))),0)) | Q58: =IF(OR(B58="",C58=""),0,IFERROR(N(INDEX(Ingredients!$AJ$6:$AJ$105,MATCH(C58,Ingredients!$B$6:$B$105,0))),0)) | R58: =IF(OR(B58="",C58=""),0,IFERROR(N(INDEX(Ingredients!$AK$6:$AK$105,MATCH(C58,Ingredients!$B$6:$B$105,0))),0)) | S58: =IF(OR(B58="",C58=""),0,IFERROR(N(INDEX(Ingredients!$AL$6:$AL$105,MATCH(C58,Ingredients!$B$6:$B$105,0))),0)) | T58: =IF(OR(B58="",C58=""),0,IFERROR(N(INDEX(Ingredients!$AM$6:$AM$105,MATCH(C58,Ingredients!$B$6:$B$105,0))),0)) | U58: =IF(OR(B58="",C58=""),0,IFERROR(N(INDEX(Ingredients!$AN$6:$AN$105,MATCH(C58,Ingredients!$B$6:$B$105,0))),0)) | V58: =IF(OR(B58="",C58=""),0,IFERROR(N(INDEX(Ingredients!$AO$6:$AO$105,MATCH(C58,Ingredients!$B$6:$B$105,0))),0)) | W58: =IF(OR(B58="",C58=""),0,IFERROR(N(INDEX(Ingredients!$AP$6:$AP$105,MATCH(C58,Ingredients!$B$6:$B$105,0))),0)) | X58: =IF(OR(B58="",C58=""),0,IFERROR(N(INDEX(Ingredients!$AQ$6:$AQ$105,MATCH(C58,Ingredients!$B$6:$B$105,0))),0))
E59: =IF(C59="","",IF(ISNA(MATCH(C59,Ingredients!$B$6:$B$105,0)),"Not on Ingredients",IFERROR(IF(INDEX(Ingredients!$C$6:$C$105,MATCH(C59,Ingredients!$B$6:$B$105,0))="","",INDEX(Ingredients!$C$6:$C$105,MATCH(C59,Ingredients!$B$6:$B$105,0))),""))) | F59: =IF(OR(B59="",C59=""),"",N(D59)*IFERROR(N(INDEX(Ingredients!$H$6:$H$105,MATCH(C59,Ingredients!$B$6:$B$105,0))),0)) | G59: =IF(OR(B59="",C59=""),0,IFERROR(N(INDEX(Products!$D$6:$D$45,MATCH(B59,Products!$B$6:$B$45,0))),0)) | H59: =IF(N(G59)=0,0,N(D59)*SUMIFS(Batches!$D$6:$D$505,Batches!$C$6:$C$505,B59)/G59) | I59: =IF(OR(B59="",C59=""),"",IF(B59<>Label!$H$3,"",IF(IFERROR(N(INDEX(Ingredients!$AS$6:$AS$105,MATCH(C59,Ingredients!$B$6:$B$105,0))),0)=1,"",ROUND(N(D59)*1000,0)*100000+100000-ROW()))) | J59: =IF(OR(B59="",C59=""),0,IFERROR(N(INDEX(Ingredients!$AC$6:$AC$105,MATCH(C59,Ingredients!$B$6:$B$105,0))),0)) | K59: =IF(OR(B59="",C59=""),0,IFERROR(N(INDEX(Ingredients!$AD$6:$AD$105,MATCH(C59,Ingredients!$B$6:$B$105,0))),0)) | L59: =IF(OR(B59="",C59=""),0,IFERROR(N(INDEX(Ingredients!$AE$6:$AE$105,MATCH(C59,Ingredients!$B$6:$B$105,0))),0)) | M59: =IF(OR(B59="",C59=""),0,IFERROR(N(INDEX(Ingredients!$AF$6:$AF$105,MATCH(C59,Ingredients!$B$6:$B$105,0))),0)) | N59: =IF(OR(B59="",C59=""),0,IFERROR(N(INDEX(Ingredients!$AG$6:$AG$105,MATCH(C59,Ingredients!$B$6:$B$105,0))),0)) | O59: =IF(OR(B59="",C59=""),0,IFERROR(N(INDEX(Ingredients!$AH$6:$AH$105,MATCH(C59,Ingredients!$B$6:$B$105,0))),0)) | P59: =IF(OR(B59="",C59=""),0,IFERROR(N(INDEX(Ingredients!$AI$6:$AI$105,MATCH(C59,Ingredients!$B$6:$B$105,0))),0)) | Q59: =IF(OR(B59="",C59=""),0,IFERROR(N(INDEX(Ingredients!$AJ$6:$AJ$105,MATCH(C59,Ingredients!$B$6:$B$105,0))),0)) | R59: =IF(OR(B59="",C59=""),0,IFERROR(N(INDEX(Ingredients!$AK$6:$AK$105,MATCH(C59,Ingredients!$B$6:$B$105,0))),0)) | S59: =IF(OR(B59="",C59=""),0,IFERROR(N(INDEX(Ingredients!$AL$6:$AL$105,MATCH(C59,Ingredients!$B$6:$B$105,0))),0)) | T59: =IF(OR(B59="",C59=""),0,IFERROR(N(INDEX(Ingredients!$AM$6:$AM$105,MATCH(C59,Ingredients!$B$6:$B$105,0))),0)) | U59: =IF(OR(B59="",C59=""),0,IFERROR(N(INDEX(Ingredients!$AN$6:$AN$105,MATCH(C59,Ingredients!$B$6:$B$105,0))),0)) | V59: =IF(OR(B59="",C59=""),0,IFERROR(N(INDEX(Ingredients!$AO$6:$AO$105,MATCH(C59,Ingredients!$B$6:$B$105,0))),0)) | W59: =IF(OR(B59="",C59=""),0,IFERROR(N(INDEX(Ingredients!$AP$6:$AP$105,MATCH(C59,Ingredients!$B$6:$B$105,0))),0)) | X59: =IF(OR(B59="",C59=""),0,IFERROR(N(INDEX(Ingredients!$AQ$6:$AQ$105,MATCH(C59,Ingredients!$B$6:$B$105,0))),0))
E60: =IF(C60="","",IF(ISNA(MATCH(C60,Ingredients!$B$6:$B$105,0)),"Not on Ingredients",IFERROR(IF(INDEX(Ingredients!$C$6:$C$105,MATCH(C60,Ingredients!$B$6:$B$105,0))="","",INDEX(Ingredients!$C$6:$C$105,MATCH(C60,Ingredients!$B$6:$B$105,0))),""))) | F60: =IF(OR(B60="",C60=""),"",N(D60)*IFERROR(N(INDEX(Ingredients!$H$6:$H$105,MATCH(C60,Ingredients!$B$6:$B$105,0))),0)) | G60: =IF(OR(B60="",C60=""),0,IFERROR(N(INDEX(Products!$D$6:$D$45,MATCH(B60,Products!$B$6:$B$45,0))),0)) | H60: =IF(N(G60)=0,0,N(D60)*SUMIFS(Batches!$D$6:$D$505,Batches!$C$6:$C$505,B60)/G60) | I60: =IF(OR(B60="",C60=""),"",IF(B60<>Label!$H$3,"",IF(IFERROR(N(INDEX(Ingredients!$AS$6:$AS$105,MATCH(C60,Ingredients!$B$6:$B$105,0))),0)=1,"",ROUND(N(D60)*1000,0)*100000+100000-ROW()))) | J60: =IF(OR(B60="",C60=""),0,IFERROR(N(INDEX(Ingredients!$AC$6:$AC$105,MATCH(C60,Ingredients!$B$6:$B$105,0))),0)) | K60: =IF(OR(B60="",C60=""),0,IFERROR(N(INDEX(Ingredients!$AD$6:$AD$105,MATCH(C60,Ingredients!$B$6:$B$105,0))),0)) | L60: =IF(OR(B60="",C60=""),0,IFERROR(N(INDEX(Ingredients!$AE$6:$AE$105,MATCH(C60,Ingredients!$B$6:$B$105,0))),0)) | M60: =IF(OR(B60="",C60=""),0,IFERROR(N(INDEX(Ingredients!$AF$6:$AF$105,MATCH(C60,Ingredients!$B$6:$B$105,0))),0)) | N60: =IF(OR(B60="",C60=""),0,IFERROR(N(INDEX(Ingredients!$AG$6:$AG$105,MATCH(C60,Ingredients!$B$6:$B$105,0))),0)) | O60: =IF(OR(B60="",C60=""),0,IFERROR(N(INDEX(Ingredients!$AH$6:$AH$105,MATCH(C60,Ingredients!$B$6:$B$105,0))),0)) | P60: =IF(OR(B60="",C60=""),0,IFERROR(N(INDEX(Ingredients!$AI$6:$AI$105,MATCH(C60,Ingredients!$B$6:$B$105,0))),0)) | Q60: =IF(OR(B60="",C60=""),0,IFERROR(N(INDEX(Ingredients!$AJ$6:$AJ$105,MATCH(C60,Ingredients!$B$6:$B$105,0))),0)) | R60: =IF(OR(B60="",C60=""),0,IFERROR(N(INDEX(Ingredients!$AK$6:$AK$105,MATCH(C60,Ingredients!$B$6:$B$105,0))),0)) | S60: =IF(OR(B60="",C60=""),0,IFERROR(N(INDEX(Ingredients!$AL$6:$AL$105,MATCH(C60,Ingredients!$B$6:$B$105,0))),0)) | T60: =IF(OR(B60="",C60=""),0,IFERROR(N(INDEX(Ingredients!$AM$6:$AM$105,MATCH(C60,Ingredients!$B$6:$B$105,0))),0)) | U60: =IF(OR(B60="",C60=""),0,IFERROR(N(INDEX(Ingredients!$AN$6:$AN$105,MATCH(C60,Ingredients!$B$6:$B$105,0))),0)) | V60: =IF(OR(B60="",C60=""),0,IFERROR(N(INDEX(Ingredients!$AO$6:$AO$105,MATCH(C60,Ingredients!$B$6:$B$105,0))),0)) | W60: =IF(OR(B60="",C60=""),0,IFERROR(N(INDEX(Ingredients!$AP$6:$AP$105,MATCH(C60,Ingredients!$B$6:$B$105,0))),0)) | X60: =IF(OR(B60="",C60=""),0,IFERROR(N(INDEX(Ingredients!$AQ$6:$AQ$105,MATCH(C60,Ingredients!$B$6:$B$105,0))),0))
E61: =IF(C61="","",IF(ISNA(MATCH(C61,Ingredients!$B$6:$B$105,0)),"Not on Ingredients",IFERROR(IF(INDEX(Ingredients!$C$6:$C$105,MATCH(C61,Ingredients!$B$6:$B$105,0))="","",INDEX(Ingredients!$C$6:$C$105,MATCH(C61,Ingredients!$B$6:$B$105,0))),""))) | F61: =IF(OR(B61="",C61=""),"",N(D61)*IFERROR(N(INDEX(Ingredients!$H$6:$H$105,MATCH(C61,Ingredients!$B$6:$B$105,0))),0)) | G61: =IF(OR(B61="",C61=""),0,IFERROR(N(INDEX(Products!$D$6:$D$45,MATCH(B61,Products!$B$6:$B$45,0))),0)) | H61: =IF(N(G61)=0,0,N(D61)*SUMIFS(Batches!$D$6:$D$505,Batches!$C$6:$C$505,B61)/G61) | I61: =IF(OR(B61="",C61=""),"",IF(B61<>Label!$H$3,"",IF(IFERROR(N(INDEX(Ingredients!$AS$6:$AS$105,MATCH(C61,Ingredients!$B$6:$B$105,0))),0)=1,"",ROUND(N(D61)*1000,0)*100000+100000-ROW()))) | J61: =IF(OR(B61="",C61=""),0,IFERROR(N(INDEX(Ingredients!$AC$6:$AC$105,MATCH(C61,Ingredients!$B$6:$B$105,0))),0)) | K61: =IF(OR(B61="",C61=""),0,IFERROR(N(INDEX(Ingredients!$AD$6:$AD$105,MATCH(C61,Ingredients!$B$6:$B$105,0))),0)) | L61: =IF(OR(B61="",C61=""),0,IFERROR(N(INDEX(Ingredients!$AE$6:$AE$105,MATCH(C61,Ingredients!$B$6:$B$105,0))),0)) | M61: =IF(OR(B61="",C61=""),0,IFERROR(N(INDEX(Ingredients!$AF$6:$AF$105,MATCH(C61,Ingredients!$B$6:$B$105,0))),0)) | N61: =IF(OR(B61="",C61=""),0,IFERROR(N(INDEX(Ingredients!$AG$6:$AG$105,MATCH(C61,Ingredients!$B$6:$B$105,0))),0)) | O61: =IF(OR(B61="",C61=""),0,IFERROR(N(INDEX(Ingredients!$AH$6:$AH$105,MATCH(C61,Ingredients!$B$6:$B$105,0))),0)) | P61: =IF(OR(B61="",C61=""),0,IFERROR(N(INDEX(Ingredients!$AI$6:$AI$105,MATCH(C61,Ingredients!$B$6:$B$105,0))),0)) | Q61: =IF(OR(B61="",C61=""),0,IFERROR(N(INDEX(Ingredients!$AJ$6:$AJ$105,MATCH(C61,Ingredients!$B$6:$B$105,0))),0)) | R61: =IF(OR(B61="",C61=""),0,IFERROR(N(INDEX(Ingredients!$AK$6:$AK$105,MATCH(C61,Ingredients!$B$6:$B$105,0))),0)) | S61: =IF(OR(B61="",C61=""),0,IFERROR(N(INDEX(Ingredients!$AL$6:$AL$105,MATCH(C61,Ingredients!$B$6:$B$105,0))),0)) | T61: =IF(OR(B61="",C61=""),0,IFERROR(N(INDEX(Ingredients!$AM$6:$AM$105,MATCH(C61,Ingredients!$B$6:$B$105,0))),0)) | U61: =IF(OR(B61="",C61=""),0,IFERROR(N(INDEX(Ingredients!$AN$6:$AN$105,MATCH(C61,Ingredients!$B$6:$B$105,0))),0)) | V61: =IF(OR(B61="",C61=""),0,IFERROR(N(INDEX(Ingredients!$AO$6:$AO$105,MATCH(C61,Ingredients!$B$6:$B$105,0))),0)) | W61: =IF(OR(B61="",C61=""),0,IFERROR(N(INDEX(Ingredients!$AP$6:$AP$105,MATCH(C61,Ingredients!$B$6:$B$105,0))),0)) | X61: =IF(OR(B61="",C61=""),0,IFERROR(N(INDEX(Ingredients!$AQ$6:$AQ$105,MATCH(C61,Ingredients!$B$6:$B$105,0))),0))
E62: =IF(C62="","",IF(ISNA(MATCH(C62,Ingredients!$B$6:$B$105,0)),"Not on Ingredients",IFERROR(IF(INDEX(Ingredients!$C$6:$C$105,MATCH(C62,Ingredients!$B$6:$B$105,0))="","",INDEX(Ingredients!$C$6:$C$105,MATCH(C62,Ingredients!$B$6:$B$105,0))),""))) | F62: =IF(OR(B62="",C62=""),"",N(D62)*IFERROR(N(INDEX(Ingredients!$H$6:$H$105,MATCH(C62,Ingredients!$B$6:$B$105,0))),0)) | G62: =IF(OR(B62="",C62=""),0,IFERROR(N(INDEX(Products!$D$6:$D$45,MATCH(B62,Products!$B$6:$B$45,0))),0)) | H62: =IF(N(G62)=0,0,N(D62)*SUMIFS(Batches!$D$6:$D$505,Batches!$C$6:$C$505,B62)/G62) | I62: =IF(OR(B62="",C62=""),"",IF(B62<>Label!$H$3,"",IF(IFERROR(N(INDEX(Ingredients!$AS$6:$AS$105,MATCH(C62,Ingredients!$B$6:$B$105,0))),0)=1,"",ROUND(N(D62)*1000,0)*100000+100000-ROW()))) | J62: =IF(OR(B62="",C62=""),0,IFERROR(N(INDEX(Ingredients!$AC$6:$AC$105,MATCH(C62,Ingredients!$B$6:$B$105,0))),0)) | K62: =IF(OR(B62="",C62=""),0,IFERROR(N(INDEX(Ingredients!$AD$6:$AD$105,MATCH(C62,Ingredients!$B$6:$B$105,0))),0)) | L62: =IF(OR(B62="",C62=""),0,IFERROR(N(INDEX(Ingredients!$AE$6:$AE$105,MATCH(C62,Ingredients!$B$6:$B$105,0))),0)) | M62: =IF(OR(B62="",C62=""),0,IFERROR(N(INDEX(Ingredients!$AF$6:$AF$105,MATCH(C62,Ingredients!$B$6:$B$105,0))),0)) | N62: =IF(OR(B62="",C62=""),0,IFERROR(N(INDEX(Ingredients!$AG$6:$AG$105,MATCH(C62,Ingredients!$B$6:$B$105,0))),0)) | O62: =IF(OR(B62="",C62=""),0,IFERROR(N(INDEX(Ingredients!$AH$6:$AH$105,MATCH(C62,Ingredients!$B$6:$B$105,0))),0)) | P62: =IF(OR(B62="",C62=""),0,IFERROR(N(INDEX(Ingredients!$AI$6:$AI$105,MATCH(C62,Ingredients!$B$6:$B$105,0))),0)) | Q62: =IF(OR(B62="",C62=""),0,IFERROR(N(INDEX(Ingredients!$AJ$6:$AJ$105,MATCH(C62,Ingredients!$B$6:$B$105,0))),0)) | R62: =IF(OR(B62="",C62=""),0,IFERROR(N(INDEX(Ingredients!$AK$6:$AK$105,MATCH(C62,Ingredients!$B$6:$B$105,0))),0)) | S62: =IF(OR(B62="",C62=""),0,IFERROR(N(INDEX(Ingredients!$AL$6:$AL$105,MATCH(C62,Ingredients!$B$6:$B$105,0))),0)) | T62: =IF(OR(B62="",C62=""),0,IFERROR(N(INDEX(Ingredients!$AM$6:$AM$105,MATCH(C62,Ingredients!$B$6:$B$105,0))),0)) | U62: =IF(OR(B62="",C62=""),0,IFERROR(N(INDEX(Ingredients!$AN$6:$AN$105,MATCH(C62,Ingredients!$B$6:$B$105,0))),0)) | V62: =IF(OR(B62="",C62=""),0,IFERROR(N(INDEX(Ingredients!$AO$6:$AO$105,MATCH(C62,Ingredients!$B$6:$B$105,0))),0)) | W62: =IF(OR(B62="",C62=""),0,IFERROR(N(INDEX(Ingredients!$AP$6:$AP$105,MATCH(C62,Ingredients!$B$6:$B$105,0))),0)) | X62: =IF(OR(B62="",C62=""),0,IFERROR(N(INDEX(Ingredients!$AQ$6:$AQ$105,MATCH(C62,Ingredients!$B$6:$B$105,0))),0))
E63: =IF(C63="","",IF(ISNA(MATCH(C63,Ingredients!$B$6:$B$105,0)),"Not on Ingredients",IFERROR(IF(INDEX(Ingredients!$C$6:$C$105,MATCH(C63,Ingredients!$B$6:$B$105,0))="","",INDEX(Ingredients!$C$6:$C$105,MATCH(C63,Ingredients!$B$6:$B$105,0))),""))) | F63: =IF(OR(B63="",C63=""),"",N(D63)*IFERROR(N(INDEX(Ingredients!$H$6:$H$105,MATCH(C63,Ingredients!$B$6:$B$105,0))),0)) | G63: =IF(OR(B63="",C63=""),0,IFERROR(N(INDEX(Products!$D$6:$D$45,MATCH(B63,Products!$B$6:$B$45,0))),0)) | H63: =IF(N(G63)=0,0,N(D63)*SUMIFS(Batches!$D$6:$D$505,Batches!$C$6:$C$505,B63)/G63) | I63: =IF(OR(B63="",C63=""),"",IF(B63<>Label!$H$3,"",IF(IFERROR(N(INDEX(Ingredients!$AS$6:$AS$105,MATCH(C63,Ingredients!$B$6:$B$105,0))),0)=1,"",ROUND(N(D63)*1000,0)*100000+100000-ROW()))) | J63: =IF(OR(B63="",C63=""),0,IFERROR(N(INDEX(Ingredients!$AC$6:$AC$105,MATCH(C63,Ingredients!$B$6:$B$105,0))),0)) | K63: =IF(OR(B63="",C63=""),0,IFERROR(N(INDEX(Ingredients!$AD$6:$AD$105,MATCH(C63,Ingredients!$B$6:$B$105,0))),0)) | L63: =IF(OR(B63="",C63=""),0,IFERROR(N(INDEX(Ingredients!$AE$6:$AE$105,MATCH(C63,Ingredients!$B$6:$B$105,0))),0)) | M63: =IF(OR(B63="",C63=""),0,IFERROR(N(INDEX(Ingredients!$AF$6:$AF$105,MATCH(C63,Ingredients!$B$6:$B$105,0))),0)) | N63: =IF(OR(B63="",C63=""),0,IFERROR(N(INDEX(Ingredients!$AG$6:$AG$105,MATCH(C63,Ingredients!$B$6:$B$105,0))),0)) | O63: =IF(OR(B63="",C63=""),0,IFERROR(N(INDEX(Ingredients!$AH$6:$AH$105,MATCH(C63,Ingredients!$B$6:$B$105,0))),0)) | P63: =IF(OR(B63="",C63=""),0,IFERROR(N(INDEX(Ingredients!$AI$6:$AI$105,MATCH(C63,Ingredients!$B$6:$B$105,0))),0)) | Q63: =IF(OR(B63="",C63=""),0,IFERROR(N(INDEX(Ingredients!$AJ$6:$AJ$105,MATCH(C63,Ingredients!$B$6:$B$105,0))),0)) | R63: =IF(OR(B63="",C63=""),0,IFERROR(N(INDEX(Ingredients!$AK$6:$AK$105,MATCH(C63,Ingredients!$B$6:$B$105,0))),0)) | S63: =IF(OR(B63="",C63=""),0,IFERROR(N(INDEX(Ingredients!$AL$6:$AL$105,MATCH(C63,Ingredients!$B$6:$B$105,0))),0)) | T63: =IF(OR(B63="",C63=""),0,IFERROR(N(INDEX(Ingredients!$AM$6:$AM$105,MATCH(C63,Ingredients!$B$6:$B$105,0))),0)) | U63: =IF(OR(B63="",C63=""),0,IFERROR(N(INDEX(Ingredients!$AN$6:$AN$105,MATCH(C63,Ingredients!$B$6:$B$105,0))),0)) | V63: =IF(OR(B63="",C63=""),0,IFERROR(N(INDEX(Ingredients!$AO$6:$AO$105,MATCH(C63,Ingredients!$B$6:$B$105,0))),0)) | W63: =IF(OR(B63="",C63=""),0,IFERROR(N(INDEX(Ingredients!$AP$6:$AP$105,MATCH(C63,Ingredients!$B$6:$B$105,0))),0)) | X63: =IF(OR(B63="",C63=""),0,IFERROR(N(INDEX(Ingredients!$AQ$6:$AQ$105,MATCH(C63,Ingredients!$B$6:$B$105,0))),0))
E64: =IF(C64="","",IF(ISNA(MATCH(C64,Ingredients!$B$6:$B$105,0)),"Not on Ingredients",IFERROR(IF(INDEX(Ingredients!$C$6:$C$105,MATCH(C64,Ingredients!$B$6:$B$105,0))="","",INDEX(Ingredients!$C$6:$C$105,MATCH(C64,Ingredients!$B$6:$B$105,0))),""))) | F64: =IF(OR(B64="",C64=""),"",N(D64)*IFERROR(N(INDEX(Ingredients!$H$6:$H$105,MATCH(C64,Ingredients!$B$6:$B$105,0))),0)) | G64: =IF(OR(B64="",C64=""),0,IFERROR(N(INDEX(Products!$D$6:$D$45,MATCH(B64,Products!$B$6:$B$45,0))),0)) | H64: =IF(N(G64)=0,0,N(D64)*SUMIFS(Batches!$D$6:$D$505,Batches!$C$6:$C$505,B64)/G64) | I64: =IF(OR(B64="",C64=""),"",IF(B64<>Label!$H$3,"",IF(IFERROR(N(INDEX(Ingredients!$AS$6:$AS$105,MATCH(C64,Ingredients!$B$6:$B$105,0))),0)=1,"",ROUND(N(D64)*1000,0)*100000+100000-ROW()))) | J64: =IF(OR(B64="",C64=""),0,IFERROR(N(INDEX(Ingredients!$AC$6:$AC$105,MATCH(C64,Ingredients!$B$6:$B$105,0))),0)) | K64: =IF(OR(B64="",C64=""),0,IFERROR(N(INDEX(Ingredients!$AD$6:$AD$105,MATCH(C64,Ingredients!$B$6:$B$105,0))),0)) | L64: =IF(OR(B64="",C64=""),0,IFERROR(N(INDEX(Ingredients!$AE$6:$AE$105,MATCH(C64,Ingredients!$B$6:$B$105,0))),0)) | M64: =IF(OR(B64="",C64=""),0,IFERROR(N(INDEX(Ingredients!$AF$6:$AF$105,MATCH(C64,Ingredients!$B$6:$B$105,0))),0)) | N64: =IF(OR(B64="",C64=""),0,IFERROR(N(INDEX(Ingredients!$AG$6:$AG$105,MATCH(C64,Ingredients!$B$6:$B$105,0))),0)) | O64: =IF(OR(B64="",C64=""),0,IFERROR(N(INDEX(Ingredients!$AH$6:$AH$105,MATCH(C64,Ingredients!$B$6:$B$105,0))),0)) | P64: =IF(OR(B64="",C64=""),0,IFERROR(N(INDEX(Ingredients!$AI$6:$AI$105,MATCH(C64,Ingredients!$B$6:$B$105,0))),0)) | Q64: =IF(OR(B64="",C64=""),0,IFERROR(N(INDEX(Ingredients!$AJ$6:$AJ$105,MATCH(C64,Ingredients!$B$6:$B$105,0))),0)) | R64: =IF(OR(B64="",C64=""),0,IFERROR(N(INDEX(Ingredients!$AK$6:$AK$105,MATCH(C64,Ingredients!$B$6:$B$105,0))),0)) | S64: =IF(OR(B64="",C64=""),0,IFERROR(N(INDEX(Ingredients!$AL$6:$AL$105,MATCH(C64,Ingredients!$B$6:$B$105,0))),0)) | T64: =IF(OR(B64="",C64=""),0,IFERROR(N(INDEX(Ingredients!$AM$6:$AM$105,MATCH(C64,Ingredients!$B$6:$B$105,0))),0)) | U64: =IF(OR(B64="",C64=""),0,IFERROR(N(INDEX(Ingredients!$AN$6:$AN$105,MATCH(C64,Ingredients!$B$6:$B$105,0))),0)) | V64: =IF(OR(B64="",C64=""),0,IFERROR(N(INDEX(Ingredients!$AO$6:$AO$105,MATCH(C64,Ingredients!$B$6:$B$105,0))),0)) | W64: =IF(OR(B64="",C64=""),0,IFERROR(N(INDEX(Ingredients!$AP$6:$AP$105,MATCH(C64,Ingredients!$B$6:$B$105,0))),0)) | X64: =IF(OR(B64="",C64=""),0,IFERROR(N(INDEX(Ingredients!$AQ$6:$AQ$105,MATCH(C64,Ingredients!$B$6:$B$105,0))),0))
E65: =IF(C65="","",IF(ISNA(MATCH(C65,Ingredients!$B$6:$B$105,0)),"Not on Ingredients",IFERROR(IF(INDEX(Ingredients!$C$6:$C$105,MATCH(C65,Ingredients!$B$6:$B$105,0))="","",INDEX(Ingredients!$C$6:$C$105,MATCH(C65,Ingredients!$B$6:$B$105,0))),""))) | F65: =IF(OR(B65="",C65=""),"",N(D65)*IFERROR(N(INDEX(Ingredients!$H$6:$H$105,MATCH(C65,Ingredients!$B$6:$B$105,0))),0)) | G65: =IF(OR(B65="",C65=""),0,IFERROR(N(INDEX(Products!$D$6:$D$45,MATCH(B65,Products!$B$6:$B$45,0))),0)) | H65: =IF(N(G65)=0,0,N(D65)*SUMIFS(Batches!$D$6:$D$505,Batches!$C$6:$C$505,B65)/G65) | I65: =IF(OR(B65="",C65=""),"",IF(B65<>Label!$H$3,"",IF(IFERROR(N(INDEX(Ingredients!$AS$6:$AS$105,MATCH(C65,Ingredients!$B$6:$B$105,0))),0)=1,"",ROUND(N(D65)*1000,0)*100000+100000-ROW()))) | J65: =IF(OR(B65="",C65=""),0,IFERROR(N(INDEX(Ingredients!$AC$6:$AC$105,MATCH(C65,Ingredients!$B$6:$B$105,0))),0)) | K65: =IF(OR(B65="",C65=""),0,IFERROR(N(INDEX(Ingredients!$AD$6:$AD$105,MATCH(C65,Ingredients!$B$6:$B$105,0))),0)) | L65: =IF(OR(B65="",C65=""),0,IFERROR(N(INDEX(Ingredients!$AE$6:$AE$105,MATCH(C65,Ingredients!$B$6:$B$105,0))),0)) | M65: =IF(OR(B65="",C65=""),0,IFERROR(N(INDEX(Ingredients!$AF$6:$AF$105,MATCH(C65,Ingredients!$B$6:$B$105,0))),0)) | N65: =IF(OR(B65="",C65=""),0,IFERROR(N(INDEX(Ingredients!$AG$6:$AG$105,MATCH(C65,Ingredients!$B$6:$B$105,0))),0)) | O65: =IF(OR(B65="",C65=""),0,IFERROR(N(INDEX(Ingredients!$AH$6:$AH$105,MATCH(C65,Ingredients!$B$6:$B$105,0))),0)) | P65: =IF(OR(B65="",C65=""),0,IFERROR(N(INDEX(Ingredients!$AI$6:$AI$105,MATCH(C65,Ingredients!$B$6:$B$105,0))),0)) | Q65: =IF(OR(B65="",C65=""),0,IFERROR(N(INDEX(Ingredients!$AJ$6:$AJ$105,MATCH(C65,Ingredients!$B$6:$B$105,0))),0)) | R65: =IF(OR(B65="",C65=""),0,IFERROR(N(INDEX(Ingredients!$AK$6:$AK$105,MATCH(C65,Ingredients!$B$6:$B$105,0))),0)) | S65: =IF(OR(B65="",C65=""),0,IFERROR(N(INDEX(Ingredients!$AL$6:$AL$105,MATCH(C65,Ingredients!$B$6:$B$105,0))),0)) | T65: =IF(OR(B65="",C65=""),0,IFERROR(N(INDEX(Ingredients!$AM$6:$AM$105,MATCH(C65,Ingredients!$B$6:$B$105,0))),0)) | U65: =IF(OR(B65="",C65=""),0,IFERROR(N(INDEX(Ingredients!$AN$6:$AN$105,MATCH(C65,Ingredients!$B$6:$B$105,0))),0)) | V65: =IF(OR(B65="",C65=""),0,IFERROR(N(INDEX(Ingredients!$AO$6:$AO$105,MATCH(C65,Ingredients!$B$6:$B$105,0))),0)) | W65: =IF(OR(B65="",C65=""),0,IFERROR(N(INDEX(Ingredients!$AP$6:$AP$105,MATCH(C65,Ingredients!$B$6:$B$105,0))),0)) | X65: =IF(OR(B65="",C65=""),0,IFERROR(N(INDEX(Ingredients!$AQ$6:$AQ$105,MATCH(C65,Ingredients!$B$6:$B$105,0))),0))
... E405: =IF(C405="","",IF(ISNA(MATCH(C405,Ingredients!$B$6:$B$105,0)),"Not on Ingredients",IFERROR(IF(INDEX(Ingredients!$C$6:$C$105,MATCH(C405,Ingredients!$B$6:$B$105,0))="","",INDEX(Ingredients!$C$6:$C$105,MATCH(C405,Ingredients!$B$6:$B$105,0))),""))) | F405: =IF(OR(B405="",C405=""),"",N(D405)*IFERROR(N(INDEX(Ingredients!$H$6:$H$105,MATCH(C405,Ingredients!$B$6:$B$105,0))),0)) | G405: =IF(OR(B405="",C405=""),0,IFERROR(N(INDEX(Products!$D$6:$D$45,MATCH(B405,Products!$B$6:$B$45,0))),0)) | H405: =IF(N(G405)=0,0,N(D405)*SUMIFS(Batches!$D$6:$D$505,Batches!$C$6:$C$505,B405)/G405) | I405: =IF(OR(B405="",C405=""),"",IF(B405<>Label!$H$3,"",IF(IFERROR(N(INDEX(Ingredients!$AS$6:$AS$105,MATCH(C405,Ingredients!$B$6:$B$105,0))),0)=1,"",ROUND(N(D405)*1000,0)*100000+100000-ROW()))) | J405: =IF(OR(B405="",C405=""),0,IFERROR(N(INDEX(Ingredients!$AC$6:$AC$105,MATCH(C405,Ingredients!$B$6:$B$105,0))),0)) | K405: =IF(OR(B405="",C405=""),0,IFERROR(N(INDEX(Ingredients!$AD$6:$AD$105,MATCH(C405,Ingredients!$B$6:$B$105,0))),0)) | L405: =IF(OR(B405="",C405=""),0,IFERROR(N(INDEX(Ingredients!$AE$6:$AE$105,MATCH(C405,Ingredients!$B$6:$B$105,0))),0)) | M405: =IF(OR(B405="",C405=""),0,IFERROR(N(INDEX(Ingredients!$AF$6:$AF$105,MATCH(C405,Ingredients!$B$6:$B$105,0))),0)) | N405: =IF(OR(B405="",C405=""),0,IFERROR(N(INDEX(Ingredients!$AG$6:$AG$105,MATCH(C405,Ingredients!$B$6:$B$105,0))),0)) | O405: =IF(OR(B405="",C405=""),0,IFERROR(N(INDEX(Ingredients!$AH$6:$AH$105,MATCH(C405,Ingredients!$B$6:$B$105,0))),0)) | P405: =IF(OR(B405="",C405=""),0,IFERROR(N(INDEX(Ingredients!$AI$6:$AI$105,MATCH(C405,Ingredients!$B$6:$B$105,0))),0)) | Q405: =IF(OR(B405="",C405=""),0,IFERROR(N(INDEX(Ingredients!$AJ$6:$AJ$105,MATCH(C405,Ingredients!$B$6:$B$105,0))),0)) | R405: =IF(OR(B405="",C405=""),0,IFERROR(N(INDEX(Ingredients!$AK$6:$AK$105,MATCH(C405,Ingredients!$B$6:$B$105,0))),0)) | S405: =IF(OR(B405="",C405=""),0,IFERROR(N(INDEX(Ingredients!$AL$6:$AL$105,MATCH(C405,Ingredients!$B$6:$B$105,0))),0)) | T405: =IF(OR(B405="",C405=""),0,IFERROR(N(INDEX(Ingredients!$AM$6:$AM$105,MATCH(C405,Ingredients!$B$6:$B$105,0))),0)) | U405: =IF(OR(B405="",C405=""),0,IFERROR(N(INDEX(Ingredients!$AN$6:$AN$105,MATCH(C405,Ingredients!$B$6:$B$105,0))),0)) | V405: =IF(OR(B405="",C405=""),0,IFERROR(N(INDEX(Ingredients!$AO$6:$AO$105,MATCH(C405,Ingredients!$B$6:$B$105,0))),0)) | W405: =IF(OR(B405="",C405=""),0,IFERROR(N(INDEX(Ingredients!$AP$6:$AP$105,MATCH(C405,Ingredients!$B$6:$B$105,0))),0)) | X405: =IF(OR(B405="",C405=""),0,IFERROR(N(INDEX(Ingredients!$AQ$6:$AQ$105,MATCH(C405,Ingredients!$B$6:$B$105,0))),0))

Sheet Ingredients
B2: Ingredients
B3: Each ingredient and packaging item once, with its pack price. An x under each allergen it contains.
B5: Ingredient | C5: Unit | D5: Pack size | E5: Pack price | F5: Buy more at | G5: Not on label | H5: Cost per unit | I5: Bought | J5: Used | K5: Left | L5: Status | M5: =Settings!$C$13 | N5: =Settings!$C$14 | O5: =Settings!$C$15 | P5: =Settings!$C$16 | Q5: =Settings!$C$17 | R5: =Settings!$C$18 | S5: =Settings!$C$19 | T5: =Settings!$C$20 | U5: =Settings!$C$21 | V5: =Settings!$C$22 | W5: =Settings!$C$23 | X5: =Settings!$C$24 | Y5: =Settings!$C$25 | Z5: =Settings!$C$26 | AA5: =Settings!$C$27
B6: Plain flour | C6: g | D6: 2000 | E6: 2.4 | F6: 1500 | H6: =IF(OR(B6="",N(D6)=0),"",N(E6)/D6) | I6: =IF(B6="","",SUMIFS(Purchases!$J$6:$J$405,Purchases!$C$6:$C$405,B6)) | J6: =IF(B6="","",SUMIFS(Recipes!$H$6:$H$405,Recipes!$C$6:$C$405,B6)) | K6: =IF(OR(B6="",N(I6)=0),"",I6-J6) | L6: =IF(OR(B6="",F6="",NOT(ISNUMBER(K6))),"",IF(K6<=N(F6),"Buy more","")) | M6: x | AC6: =IF(M6="",0,1) | AD6: =IF(N6="",0,1) | AE6: =IF(O6="",0,1) | AF6: =IF(P6="",0,1) | AG6: =IF(Q6="",0,1) | AH6: =IF(R6="",0,1) | AI6: =IF(S6="",0,1) | AJ6: =IF(T6="",0,1) | ... AQ6: =IF(AA6="",0,1) | AR6: =IF(L6="Buy more",ROW(),"") | AS6: =IF(G6="",0,1)
B7: Bread flour | C7: g | D7: 2000 | E7: 3.2 | F7: 1500 | H7: =IF(OR(B7="",N(D7)=0),"",N(E7)/D7) | I7: =IF(B7="","",SUMIFS(Purchases!$J$6:$J$405,Purchases!$C$6:$C$405,B7)) | J7: =IF(B7="","",SUMIFS(Recipes!$H$6:$H$405,Recipes!$C$6:$C$405,B7)) | K7: =IF(OR(B7="",N(I7)=0),"",I7-J7) | L7: =IF(OR(B7="",F7="",NOT(ISNUMBER(K7))),"",IF(K7<=N(F7),"Buy more","")) | M7: x | AC7: =IF(M7="",0,1) | AD7: =IF(N7="",0,1) | AE7: =IF(O7="",0,1) | AF7: =IF(P7="",0,1) | AG7: =IF(Q7="",0,1) | AH7: =IF(R7="",0,1) | AI7: =IF(S7="",0,1) | AJ7: =IF(T7="",0,1) | ... AQ7: =IF(AA7="",0,1) | AR7: =IF(L7="Buy more",ROW(),"") | AS7: =IF(G7="",0,1)
B8: Rye flour | C8: g | D8: 1000 | E8: 2.8 | F8: 500 | H8: =IF(OR(B8="",N(D8)=0),"",N(E8)/D8) | I8: =IF(B8="","",SUMIFS(Purchases!$J$6:$J$405,Purchases!$C$6:$C$405,B8)) | J8: =IF(B8="","",SUMIFS(Recipes!$H$6:$H$405,Recipes!$C$6:$C$405,B8)) | K8: =IF(OR(B8="",N(I8)=0),"",I8-J8) | L8: =IF(OR(B8="",F8="",NOT(ISNUMBER(K8))),"",IF(K8<=N(F8),"Buy more","")) | N8: x | AC8: =IF(M8="",0,1) | AD8: =IF(N8="",0,1) | AE8: =IF(O8="",0,1) | AF8: =IF(P8="",0,1) | AG8: =IF(Q8="",0,1) | AH8: =IF(R8="",0,1) | AI8: =IF(S8="",0,1) | AJ8: =IF(T8="",0,1) | ... AQ8: =IF(AA8="",0,1) | AR8: =IF(L8="Buy more",ROW(),"") | AS8: =IF(G8="",0,1)
B9: Caster sugar | C9: g | D9: 1000 | E9: 1.9 | F9: 800 | H9: =IF(OR(B9="",N(D9)=0),"",N(E9)/D9) | I9: =IF(B9="","",SUMIFS(Purchases!$J$6:$J$405,Purchases!$C$6:$C$405,B9)) | J9: =IF(B9="","",SUMIFS(Recipes!$H$6:$H$405,Recipes!$C$6:$C$405,B9)) | K9: =IF(OR(B9="",N(I9)=0),"",I9-J9) | L9: =IF(OR(B9="",F9="",NOT(ISNUMBER(K9))),"",IF(K9<=N(F9),"Buy more","")) | AC9: =IF(M9="",0,1) | AD9: =IF(N9="",0,1) | AE9: =IF(O9="",0,1) | AF9: =IF(P9="",0,1) | AG9: =IF(Q9="",0,1) | AH9: =IF(R9="",0,1) | AI9: =IF(S9="",0,1) | AJ9: =IF(T9="",0,1) | ... AQ9: =IF(AA9="",0,1) | AR9: =IF(L9="Buy more",ROW(),"") | AS9: =IF(G9="",0,1)
B10: Butter | C10: g | D10: 250 | E10: 2.6 | F10: 500 | H10: =IF(OR(B10="",N(D10)=0),"",N(E10)/D10) | I10: =IF(B10="","",SUMIFS(Purchases!$J$6:$J$405,Purchases!$C$6:$C$405,B10)) | J10: =IF(B10="","",SUMIFS(Recipes!$H$6:$H$405,Recipes!$C$6:$C$405,B10)) | K10: =IF(OR(B10="",N(I10)=0),"",I10-J10) | L10: =IF(OR(B10="",F10="",NOT(ISNUMBER(K10))),"",IF(K10<=N(F10),"Buy more","")) | O10: x | AC10: =IF(M10="",0,1) | AD10: =IF(N10="",0,1) | AE10: =IF(O10="",0,1) | AF10: =IF(P10="",0,1) | AG10: =IF(Q10="",0,1) | AH10: =IF(R10="",0,1) | AI10: =IF(S10="",0,1) | AJ10: =IF(T10="",0,1) | ... AQ10: =IF(AA10="",0,1) | AR10: =IF(L10="Buy more",ROW(),"") | AS10: =IF(G10="",0,1)
B11: Eggs | C11: g | D11: 600 | E11: 4.2 | F11: 600 | H11: =IF(OR(B11="",N(D11)=0),"",N(E11)/D11) | I11: =IF(B11="","",SUMIFS(Purchases!$J$6:$J$405,Purchases!$C$6:$C$405,B11)) | J11: =IF(B11="","",SUMIFS(Recipes!$H$6:$H$405,Recipes!$C$6:$C$405,B11)) | K11: =IF(OR(B11="",N(I11)=0),"",I11-J11) | L11: =IF(OR(B11="",F11="",NOT(ISNUMBER(K11))),"",IF(K11<=N(F11),"Buy more","")) | P11: x | AC11: =IF(M11="",0,1) | AD11: =IF(N11="",0,1) | AE11: =IF(O11="",0,1) | AF11: =IF(P11="",0,1) | AG11: =IF(Q11="",0,1) | AH11: =IF(R11="",0,1) | AI11: =IF(S11="",0,1) | AJ11: =IF(T11="",0,1) | ... AQ11: =IF(AA11="",0,1) | AR11: =IF(L11="Buy more",ROW(),"") | AS11: =IF(G11="",0,1)
B12: Lemons | C12: each | D12: 4 | E12: 2 | F12: 4 | H12: =IF(OR(B12="",N(D12)=0),"",N(E12)/D12) | I12: =IF(B12="","",SUMIFS(Purchases!$J$6:$J$405,Purchases!$C$6:$C$405,B12)) | J12: =IF(B12="","",SUMIFS(Recipes!$H$6:$H$405,Recipes!$C$6:$C$405,B12)) | K12: =IF(OR(B12="",N(I12)=0),"",I12-J12) | L12: =IF(OR(B12="",F12="",NOT(ISNUMBER(K12))),"",IF(K12<=N(F12),"Buy more","")) | AC12: =IF(M12="",0,1) | AD12: =IF(N12="",0,1) | AE12: =IF(O12="",0,1) | AF12: =IF(P12="",0,1) | AG12: =IF(Q12="",0,1) | AH12: =IF(R12="",0,1) | AI12: =IF(S12="",0,1) | AJ12: =IF(T12="",0,1) | ... AQ12: =IF(AA12="",0,1) | AR12: =IF(L12="Buy more",ROW(),"") | AS12: =IF(G12="",0,1)
B13: Dark chocolate chips | C13: g | D13: 500 | E13: 5.5 | F13: 300 | H13: =IF(OR(B13="",N(D13)=0),"",N(E13)/D13) | I13: =IF(B13="","",SUMIFS(Purchases!$J$6:$J$405,Purchases!$C$6:$C$405,B13)) | J13: =IF(B13="","",SUMIFS(Recipes!$H$6:$H$405,Recipes!$C$6:$C$405,B13)) | K13: =IF(OR(B13="",N(I13)=0),"",I13-J13) | L13: =IF(OR(B13="",F13="",NOT(ISNUMBER(K13))),"",IF(K13<=N(F13),"Buy more","")) | O13: x | Q13: x | AC13: =IF(M13="",0,1) | AD13: =IF(N13="",0,1) | AE13: =IF(O13="",0,1) | AF13: =IF(P13="",0,1) | AG13: =IF(Q13="",0,1) | AH13: =IF(R13="",0,1) | AI13: =IF(S13="",0,1) | AJ13: =IF(T13="",0,1) | ... AQ13: =IF(AA13="",0,1) | AR13: =IF(L13="Buy more",ROW(),"") | AS13: =IF(G13="",0,1)
B14: Cocoa powder | C14: g | D14: 250 | E14: 3.8 | F14: 100 | H14: =IF(OR(B14="",N(D14)=0),"",N(E14)/D14) | I14: =IF(B14="","",SUMIFS(Purchases!$J$6:$J$405,Purchases!$C$6:$C$405,B14)) | J14: =IF(B14="","",SUMIFS(Recipes!$H$6:$H$405,Recipes!$C$6:$C$405,B14)) | K14: =IF(OR(B14="",N(I14)=0),"",I14-J14) | L14: =IF(OR(B14="",F14="",NOT(ISNUMBER(K14))),"",IF(K14<=N(F14),"Buy more","")) | AC14: =IF(M14="",0,1) | AD14: =IF(N14="",0,1) | AE14: =IF(O14="",0,1) | AF14: =IF(P14="",0,1) | AG14: =IF(Q14="",0,1) | AH14: =IF(R14="",0,1) | AI14: =IF(S14="",0,1) | AJ14: =IF(T14="",0,1) | ... AQ14: =IF(AA14="",0,1) | AR14: =IF(L14="Buy more",ROW(),"") | AS14: =IF(G14="",0,1)
B15: Strawberries | C15: g | D15: 1000 | E15: 6 | H15: =IF(OR(B15="",N(D15)=0),"",N(E15)/D15) | I15: =IF(B15="","",SUMIFS(Purchases!$J$6:$J$405,Purchases!$C$6:$C$405,B15)) | J15: =IF(B15="","",SUMIFS(Recipes!$H$6:$H$405,Recipes!$C$6:$C$405,B15)) | K15: =IF(OR(B15="",N(I15)=0),"",I15-J15) | L15: =IF(OR(B15="",F15="",NOT(ISNUMBER(K15))),"",IF(K15<=N(F15),"Buy more","")) | AC15: =IF(M15="",0,1) | AD15: =IF(N15="",0,1) | AE15: =IF(O15="",0,1) | AF15: =IF(P15="",0,1) | AG15: =IF(Q15="",0,1) | AH15: =IF(R15="",0,1) | AI15: =IF(S15="",0,1) | AJ15: =IF(T15="",0,1) | ... AQ15: =IF(AA15="",0,1) | AR15: =IF(L15="Buy more",ROW(),"") | AS15: =IF(G15="",0,1)
B16: Jam sugar | C16: g | D16: 1000 | E16: 2.5 | F16: 500 | H16: =IF(OR(B16="",N(D16)=0),"",N(E16)/D16) | I16: =IF(B16="","",SUMIFS(Purchases!$J$6:$J$405,Purchases!$C$6:$C$405,B16)) | J16: =IF(B16="","",SUMIFS(Recipes!$H$6:$H$405,Recipes!$C$6:$C$405,B16)) | K16: =IF(OR(B16="",N(I16)=0),"",I16-J16) | L16: =IF(OR(B16="",F16="",NOT(ISNUMBER(K16))),"",IF(K16<=N(F16),"Buy more","")) | AC16: =IF(M16="",0,1) | AD16: =IF(N16="",0,1) | AE16: =IF(O16="",0,1) | AF16: =IF(P16="",0,1) | AG16: =IF(Q16="",0,1) | AH16: =IF(R16="",0,1) | AI16: =IF(S16="",0,1) | AJ16: =IF(T16="",0,1) | ... AQ16: =IF(AA16="",0,1) | AR16: =IF(L16="Buy more",ROW(),"") | AS16: =IF(G16="",0,1)
B17: Rolled oats | C17: g | D17: 1000 | E17: 2.2 | F17: 500 | H17: =IF(OR(B17="",N(D17)=0),"",N(E17)/D17) | I17: =IF(B17="","",SUMIFS(Purchases!$J$6:$J$405,Purchases!$C$6:$C$405,B17)) | J17: =IF(B17="","",SUMIFS(Recipes!$H$6:$H$405,Recipes!$C$6:$C$405,B17)) | K17: =IF(OR(B17="",N(I17)=0),"",I17-J17) | L17: =IF(OR(B17="",F17="",NOT(ISNUMBER(K17))),"",IF(K17<=N(F17),"Buy more","")) | N17: x | AC17: =IF(M17="",0,1) | AD17: =IF(N17="",0,1) | AE17: =IF(O17="",0,1) | AF17: =IF(P17="",0,1) | AG17: =IF(Q17="",0,1) | AH17: =IF(R17="",0,1) | AI17: =IF(S17="",0,1) | AJ17: =IF(T17="",0,1) | ... AQ17: =IF(AA17="",0,1) | AR17: =IF(L17="Buy more",ROW(),"") | AS17: =IF(G17="",0,1)
B18: Honey | C18: g | D18: 340 | E18: 4.5 | F18: 340 | H18: =IF(OR(B18="",N(D18)=0),"",N(E18)/D18) | I18: =IF(B18="","",SUMIFS(Purchases!$J$6:$J$405,Purchases!$C$6:$C$405,B18)) | J18: =IF(B18="","",SUMIFS(Recipes!$H$6:$H$405,Recipes!$C$6:$C$405,B18)) | K18: =IF(OR(B18="",N(I18)=0),"",I18-J18) | L18: =IF(OR(B18="",F18="",NOT(ISNUMBER(K18))),"",IF(K18<=N(F18),"Buy more","")) | AC18: =IF(M18="",0,1) | AD18: =IF(N18="",0,1) | AE18: =IF(O18="",0,1) | AF18: =IF(P18="",0,1) | AG18: =IF(Q18="",0,1) | AH18: =IF(R18="",0,1) | AI18: =IF(S18="",0,1) | AJ18: =IF(T18="",0,1) | ... AQ18: =IF(AA18="",0,1) | AR18: =IF(L18="Buy more",ROW(),"") | AS18: =IF(G18="",0,1)
