Workbook

Sheet Dashboard
J1: =MATCH(C4,{"Jan","Feb","Mar","Apr","May","Jun","Jul","Aug","Sep","Oct","Nov","Dec"},0)
B2: Shop dashboard | J2: =DATE(E4,J1,1)
B3: Pick a month and a year. Stock figures are always as of today. | J3: =EOMONTH(J2,0)
B4: Month | C4: Sep | D4: Year | E4: 2026
B6: Sales this month | C6: Gross profit | D6: Units sold | E6: Stock value (cost) | F6: Stock value (price) | H6: To reorder now
B7: =SUMIFS('Stock Moves'!$G$6:$G$2005,'Stock Moves'!$B$6:$B$2005,">="&$J$2,'Stock Moves'!$B$6:$B$2005,"<="&$J$3) | C7: =B7-SUMIFS('Stock Moves'!$H$6:$H$2005,'Stock Moves'!$B$6:$B$2005,">="&$J$2,'Stock Moves'!$B$6:$B$2005,"<="&$J$3) | D7: =SUMIFS('Stock Moves'!$E$6:$E$2005,'Stock Moves'!$D$6:$D$2005,"Sale",'Stock Moves'!$B$6:$B$2005,">="&$J$2,'Stock Moves'!$B$6:$B$2005,"<="&$J$3) | E7: =SUMPRODUCT(Products!$E$6:$E$205,Products!$K$6:$K$205) | F7: =SUMPRODUCT(Products!$F$6:$F$205,Products!$K$6:$K$205) | H7: =COUNTIFS(Products!$M$6:$M$205,"Reorder now")+COUNTIFS(Products!$M$6:$M$205,"Out of stock")
B9: Month | C9: Sales | D9: Units | E9: Gross profit | H9: Heads-up
B10: Jan | C10: =SUMIFS('Stock Moves'!$G$6:$G$2005,'Stock Moves'!$B$6:$B$2005,">="&DATE($E$4,1,1),'Stock Moves'!$B$6:$B$2005,"<="&EOMONTH(DATE($E$4,1,1),0)) | D10: =SUMIFS('Stock Moves'!$E$6:$E$2005,'Stock Moves'!$D$6:$D$2005,"Sale",'Stock Moves'!$B$6:$B$2005,">="&DATE($E$4,1,1),'Stock Moves'!$B$6:$B$2005,"<="&EOMONTH(DATE($E$4,1,1),0)) | E10: =C10-SUMIFS('Stock Moves'!$H$6:$H$2005,'Stock Moves'!$B$6:$B$2005,">="&DATE($E$4,1,1),'Stock Moves'!$B$6:$B$2005,"<="&EOMONTH(DATE($E$4,1,1),0)) | H10: =IF(COUNTIFS(Products!$M$6:$M$205,"Out of stock")=0,"Nothing is out of stock",IF(COUNTIFS(Products!$M$6:$M$205,"Out of stock")=1,"1 product is out of stock",COUNTIFS(Products!$M$6:$M$205,"Out of stock")&" products are out of stock"))
B11: Feb | C11: =SUMIFS('Stock Moves'!$G$6:$G$2005,'Stock Moves'!$B$6:$B$2005,">="&DATE($E$4,2,1),'Stock Moves'!$B$6:$B$2005,"<="&EOMONTH(DATE($E$4,2,1),0)) | D11: =SUMIFS('Stock Moves'!$E$6:$E$2005,'Stock Moves'!$D$6:$D$2005,"Sale",'Stock Moves'!$B$6:$B$2005,">="&DATE($E$4,2,1),'Stock Moves'!$B$6:$B$2005,"<="&EOMONTH(DATE($E$4,2,1),0)) | E11: =C11-SUMIFS('Stock Moves'!$H$6:$H$2005,'Stock Moves'!$B$6:$B$2005,">="&DATE($E$4,2,1),'Stock Moves'!$B$6:$B$2005,"<="&EOMONTH(DATE($E$4,2,1),0)) | H11: =IF(COUNTIFS(Products!$M$6:$M$205,"Reorder now")=0,"No product is at its reorder level",IF(COUNTIFS(Products!$M$6:$M$205,"Reorder now")=1,"1 product is at its reorder level",COUNTIFS(Products!$M$6:$M$205,"Reorder now")&" products are at their reorder level"))
B12: Mar | C12: =SUMIFS('Stock Moves'!$G$6:$G$2005,'Stock Moves'!$B$6:$B$2005,">="&DATE($E$4,3,1),'Stock Moves'!$B$6:$B$2005,"<="&EOMONTH(DATE($E$4,3,1),0)) | D12: =SUMIFS('Stock Moves'!$E$6:$E$2005,'Stock Moves'!$D$6:$D$2005,"Sale",'Stock Moves'!$B$6:$B$2005,">="&DATE($E$4,3,1),'Stock Moves'!$B$6:$B$2005,"<="&EOMONTH(DATE($E$4,3,1),0)) | E12: =C12-SUMIFS('Stock Moves'!$H$6:$H$2005,'Stock Moves'!$B$6:$B$2005,">="&DATE($E$4,3,1),'Stock Moves'!$B$6:$B$2005,"<="&EOMONTH(DATE($E$4,3,1),0)) | H12: ="Best seller so far: "&IFERROR(INDEX(Products!$C$6:$C$205,MATCH(MAX(Products!$J$6:$J$205),Products!$J$6:$J$205,0)),"none yet")
B13: Apr | C13: =SUMIFS('Stock Moves'!$G$6:$G$2005,'Stock Moves'!$B$6:$B$2005,">="&DATE($E$4,4,1),'Stock Moves'!$B$6:$B$2005,"<="&EOMONTH(DATE($E$4,4,1),0)) | D13: =SUMIFS('Stock Moves'!$E$6:$E$2005,'Stock Moves'!$D$6:$D$2005,"Sale",'Stock Moves'!$B$6:$B$2005,">="&DATE($E$4,4,1),'Stock Moves'!$B$6:$B$2005,"<="&EOMONTH(DATE($E$4,4,1),0)) | E13: =C13-SUMIFS('Stock Moves'!$H$6:$H$2005,'Stock Moves'!$B$6:$B$2005,">="&DATE($E$4,4,1),'Stock Moves'!$B$6:$B$2005,"<="&EOMONTH(DATE($E$4,4,1),0)) | H13: ="Average margin: "&IFERROR(FIXED(AVERAGE(Products!$L$6:$L$205)*100,0)&"%","n/a")
B14: May | C14: =SUMIFS('Stock Moves'!$G$6:$G$2005,'Stock Moves'!$B$6:$B$2005,">="&DATE($E$4,5,1),'Stock Moves'!$B$6:$B$2005,"<="&EOMONTH(DATE($E$4,5,1),0)) | D14: =SUMIFS('Stock Moves'!$E$6:$E$2005,'Stock Moves'!$D$6:$D$2005,"Sale",'Stock Moves'!$B$6:$B$2005,">="&DATE($E$4,5,1),'Stock Moves'!$B$6:$B$2005,"<="&EOMONTH(DATE($E$4,5,1),0)) | E14: =C14-SUMIFS('Stock Moves'!$H$6:$H$2005,'Stock Moves'!$B$6:$B$2005,">="&DATE($E$4,5,1),'Stock Moves'!$B$6:$B$2005,"<="&EOMONTH(DATE($E$4,5,1),0))
B15: Jun | C15: =SUMIFS('Stock Moves'!$G$6:$G$2005,'Stock Moves'!$B$6:$B$2005,">="&DATE($E$4,6,1),'Stock Moves'!$B$6:$B$2005,"<="&EOMONTH(DATE($E$4,6,1),0)) | D15: =SUMIFS('Stock Moves'!$E$6:$E$2005,'Stock Moves'!$D$6:$D$2005,"Sale",'Stock Moves'!$B$6:$B$2005,">="&DATE($E$4,6,1),'Stock Moves'!$B$6:$B$2005,"<="&EOMONTH(DATE($E$4,6,1),0)) | E15: =C15-SUMIFS('Stock Moves'!$H$6:$H$2005,'Stock Moves'!$B$6:$B$2005,">="&DATE($E$4,6,1),'Stock Moves'!$B$6:$B$2005,"<="&EOMONTH(DATE($E$4,6,1),0))
B16: Jul | C16: =SUMIFS('Stock Moves'!$G$6:$G$2005,'Stock Moves'!$B$6:$B$2005,">="&DATE($E$4,7,1),'Stock Moves'!$B$6:$B$2005,"<="&EOMONTH(DATE($E$4,7,1),0)) | D16: =SUMIFS('Stock Moves'!$E$6:$E$2005,'Stock Moves'!$D$6:$D$2005,"Sale",'Stock Moves'!$B$6:$B$2005,">="&DATE($E$4,7,1),'Stock Moves'!$B$6:$B$2005,"<="&EOMONTH(DATE($E$4,7,1),0)) | E16: =C16-SUMIFS('Stock Moves'!$H$6:$H$2005,'Stock Moves'!$B$6:$B$2005,">="&DATE($E$4,7,1),'Stock Moves'!$B$6:$B$2005,"<="&EOMONTH(DATE($E$4,7,1),0))
B17: Aug | C17: =SUMIFS('Stock Moves'!$G$6:$G$2005,'Stock Moves'!$B$6:$B$2005,">="&DATE($E$4,8,1),'Stock Moves'!$B$6:$B$2005,"<="&EOMONTH(DATE($E$4,8,1),0)) | D17: =SUMIFS('Stock Moves'!$E$6:$E$2005,'Stock Moves'!$D$6:$D$2005,"Sale",'Stock Moves'!$B$6:$B$2005,">="&DATE($E$4,8,1),'Stock Moves'!$B$6:$B$2005,"<="&EOMONTH(DATE($E$4,8,1),0)) | E17: =C17-SUMIFS('Stock Moves'!$H$6:$H$2005,'Stock Moves'!$B$6:$B$2005,">="&DATE($E$4,8,1),'Stock Moves'!$B$6:$B$2005,"<="&EOMONTH(DATE($E$4,8,1),0))
B18: Sep | C18: =SUMIFS('Stock Moves'!$G$6:$G$2005,'Stock Moves'!$B$6:$B$2005,">="&DATE($E$4,9,1),'Stock Moves'!$B$6:$B$2005,"<="&EOMONTH(DATE($E$4,9,1),0)) | D18: =SUMIFS('Stock Moves'!$E$6:$E$2005,'Stock Moves'!$D$6:$D$2005,"Sale",'Stock Moves'!$B$6:$B$2005,">="&DATE($E$4,9,1),'Stock Moves'!$B$6:$B$2005,"<="&EOMONTH(DATE($E$4,9,1),0)) | E18: =C18-SUMIFS('Stock Moves'!$H$6:$H$2005,'Stock Moves'!$B$6:$B$2005,">="&DATE($E$4,9,1),'Stock Moves'!$B$6:$B$2005,"<="&EOMONTH(DATE($E$4,9,1),0))
B19: Oct | C19: =SUMIFS('Stock Moves'!$G$6:$G$2005,'Stock Moves'!$B$6:$B$2005,">="&DATE($E$4,10,1),'Stock Moves'!$B$6:$B$2005,"<="&EOMONTH(DATE($E$4,10,1),0)) | D19: =SUMIFS('Stock Moves'!$E$6:$E$2005,'Stock Moves'!$D$6:$D$2005,"Sale",'Stock Moves'!$B$6:$B$2005,">="&DATE($E$4,10,1),'Stock Moves'!$B$6:$B$2005,"<="&EOMONTH(DATE($E$4,10,1),0)) | E19: =C19-SUMIFS('Stock Moves'!$H$6:$H$2005,'Stock Moves'!$B$6:$B$2005,">="&DATE($E$4,10,1),'Stock Moves'!$B$6:$B$2005,"<="&EOMONTH(DATE($E$4,10,1),0))
B20: Nov | C20: =SUMIFS('Stock Moves'!$G$6:$G$2005,'Stock Moves'!$B$6:$B$2005,">="&DATE($E$4,11,1),'Stock Moves'!$B$6:$B$2005,"<="&EOMONTH(DATE($E$4,11,1),0)) | D20: =SUMIFS('Stock Moves'!$E$6:$E$2005,'Stock Moves'!$D$6:$D$2005,"Sale",'Stock Moves'!$B$6:$B$2005,">="&DATE($E$4,11,1),'Stock Moves'!$B$6:$B$2005,"<="&EOMONTH(DATE($E$4,11,1),0)) | E20: =C20-SUMIFS('Stock Moves'!$H$6:$H$2005,'Stock Moves'!$B$6:$B$2005,">="&DATE($E$4,11,1),'Stock Moves'!$B$6:$B$2005,"<="&EOMONTH(DATE($E$4,11,1),0))
B21: Dec | C21: =SUMIFS('Stock Moves'!$G$6:$G$2005,'Stock Moves'!$B$6:$B$2005,">="&DATE($E$4,12,1),'Stock Moves'!$B$6:$B$2005,"<="&EOMONTH(DATE($E$4,12,1),0)) | D21: =SUMIFS('Stock Moves'!$E$6:$E$2005,'Stock Moves'!$D$6:$D$2005,"Sale",'Stock Moves'!$B$6:$B$2005,">="&DATE($E$4,12,1),'Stock Moves'!$B$6:$B$2005,"<="&EOMONTH(DATE($E$4,12,1),0)) | E21: =C21-SUMIFS('Stock Moves'!$H$6:$H$2005,'Stock Moves'!$B$6:$B$2005,">="&DATE($E$4,12,1),'Stock Moves'!$B$6:$B$2005,"<="&EOMONTH(DATE($E$4,12,1),0))

Sheet Products
B2: Products
B3: One line per product. Stock and status update from Stock Moves.
B5: SKU | C5: Product | D5: Category | E5: Unit cost | F5: Price | G5: Start stock | H5: Reorder at | I5: In | J5: Out | K5: Stock now | L5: Margin | M5: Status
B6: CAN-01 | C6: Soy candle, lavender | D6: Candles | E6: 4.2 | F6: 18 | G6: 20 | H6: 8 | I6: =IF(B6="","",SUMIFS('Stock Moves'!$E$6:$E$2005,'Stock Moves'!$C$6:$C$2005,B6,'Stock Moves'!$D$6:$D$2005,"Purchase")+SUMIFS('Stock Moves'!$E$6:$E$2005,'Stock Moves'!$C$6:$C$2005,B6,'Stock Moves'!$D$6:$D$2005,"Return")+SUMIFS('Stock Moves'!$E$6:$E$2005,'Stock Moves'!$C$6:$C$2005,B6,'Stock Moves'!$D$6:$D$2005,"Adjustment")) | J6: =IF(B6="","",SUMIFS('Stock Moves'!$E$6:$E$2005,'Stock Moves'!$C$6:$C$2005,B6,'Stock Moves'!$D$6:$D$2005,"Sale")) | K6: =IF(B6="","",G6+I6-J6) | L6: =IF(OR(B6="",N(F6)=0),"",(F6-E6)/F6) | M6: =IF(B6="","",IF(K6<=0,"Out of stock",IF(K6<=H6,"Reorder now","OK")))
B7: CAN-02 | C7: Soy candle, cedar | D7: Candles | E7: 4.2 | F7: 18 | G7: 15 | H7: 8 | I7: =IF(B7="","",SUMIFS('Stock Moves'!$E$6:$E$2005,'Stock Moves'!$C$6:$C$2005,B7,'Stock Moves'!$D$6:$D$2005,"Purchase")+SUMIFS('Stock Moves'!$E$6:$E$2005,'Stock Moves'!$C$6:$C$2005,B7,'Stock Moves'!$D$6:$D$2005,"Return")+SUMIFS('Stock Moves'!$E$6:$E$2005,'Stock Moves'!$C$6:$C$2005,B7,'Stock Moves'!$D$6:$D$2005,"Adjustment")) | J7: =IF(B7="","",SUMIFS('Stock Moves'!$E$6:$E$2005,'Stock Moves'!$C$6:$C$2005,B7,'Stock Moves'!$D$6:$D$2005,"Sale")) | K7: =IF(B7="","",G7+I7-J7) | L7: =IF(OR(B7="",N(F7)=0),"",(F7-E7)/F7) | M7: =IF(B7="","",IF(K7<=0,"Out of stock",IF(K7<=H7,"Reorder now","OK")))
B8: MUG-01 | C8: Hand-painted mug | D8: Ceramics | E8: 7.5 | F8: 28 | G8: 12 | H8: 5 | I8: =IF(B8="","",SUMIFS('Stock Moves'!$E$6:$E$2005,'Stock Moves'!$C$6:$C$2005,B8,'Stock Moves'!$D$6:$D$2005,"Purchase")+SUMIFS('Stock Moves'!$E$6:$E$2005,'Stock Moves'!$C$6:$C$2005,B8,'Stock Moves'!$D$6:$D$2005,"Return")+SUMIFS('Stock Moves'!$E$6:$E$2005,'Stock Moves'!$C$6:$C$2005,B8,'Stock Moves'!$D$6:$D$2005,"Adjustment")) | J8: =IF(B8="","",SUMIFS('Stock Moves'!$E$6:$E$2005,'Stock Moves'!$C$6:$C$2005,B8,'Stock Moves'!$D$6:$D$2005,"Sale")) | K8: =IF(B8="","",G8+I8-J8) | L8: =IF(OR(B8="",N(F8)=0),"",(F8-E8)/F8) | M8: =IF(B8="","",IF(K8<=0,"Out of stock",IF(K8<=H8,"Reorder now","OK")))
B9: EAR-01 | C9: Brass earrings | D9: Jewelry | E9: 3.1 | F9: 22 | G9: 30 | H9: 6 | I9: =IF(B9="","",SUMIFS('Stock Moves'!$E$6:$E$2005,'Stock Moves'!$C$6:$C$2005,B9,'Stock Moves'!$D$6:$D$2005,"Purchase")+SUMIFS('Stock Moves'!$E$6:$E$2005,'Stock Moves'!$C$6:$C$2005,B9,'Stock Moves'!$D$6:$D$2005,"Return")+SUMIFS('Stock Moves'!$E$6:$E$2005,'Stock Moves'!$C$6:$C$2005,B9,'Stock Moves'!$D$6:$D$2005,"Adjustment")) | J9: =IF(B9="","",SUMIFS('Stock Moves'!$E$6:$E$2005,'Stock Moves'!$C$6:$C$2005,B9,'Stock Moves'!$D$6:$D$2005,"Sale")) | K9: =IF(B9="","",G9+I9-J9) | L9: =IF(OR(B9="",N(F9)=0),"",(F9-E9)/F9) | M9: =IF(B9="","",IF(K9<=0,"Out of stock",IF(K9<=H9,"Reorder now","OK")))
B10: CRD-01 | C10: Greeting card set | D10: Paper | E10: 1.4 | F10: 9 | G10: 40 | H10: 10 | I10: =IF(B10="","",SUMIFS('Stock Moves'!$E$6:$E$2005,'Stock Moves'!$C$6:$C$2005,B10,'Stock Moves'!$D$6:$D$2005,"Purchase")+SUMIFS('Stock Moves'!$E$6:$E$2005,'Stock Moves'!$C$6:$C$2005,B10,'Stock Moves'!$D$6:$D$2005,"Return")+SUMIFS('Stock Moves'!$E$6:$E$2005,'Stock Moves'!$C$6:$C$2005,B10,'Stock Moves'!$D$6:$D$2005,"Adjustment")) | J10: =IF(B10="","",SUMIFS('Stock Moves'!$E$6:$E$2005,'Stock Moves'!$C$6:$C$2005,B10,'Stock Moves'!$D$6:$D$2005,"Sale")) | K10: =IF(B10="","",G10+I10-J10) | L10: =IF(OR(B10="",N(F10)=0),"",(F10-E10)/F10) | M10: =IF(B10="","",IF(K10<=0,"Out of stock",IF(K10<=H10,"Reorder now","OK")))
B11: BAG-01 | C11: Linen tote bag | D11: Textile | E11: 6.8 | F11: 24 | G11: 10 | H11: 4 | I11: =IF(B11="","",SUMIFS('Stock Moves'!$E$6:$E$2005,'Stock Moves'!$C$6:$C$2005,B11,'Stock Moves'!$D$6:$D$2005,"Purchase")+SUMIFS('Stock Moves'!$E$6:$E$2005,'Stock Moves'!$C$6:$C$2005,B11,'Stock Moves'!$D$6:$D$2005,"Return")+SUMIFS('Stock Moves'!$E$6:$E$2005,'Stock Moves'!$C$6:$C$2005,B11,'Stock Moves'!$D$6:$D$2005,"Adjustment")) | J11: =IF(B11="","",SUMIFS('Stock Moves'!$E$6:$E$2005,'Stock Moves'!$C$6:$C$2005,B11,'Stock Moves'!$D$6:$D$2005,"Sale")) | K11: =IF(B11="","",G11+I11-J11) | L11: =IF(OR(B11="",N(F11)=0),"",(F11-E11)/F11) | M11: =IF(B11="","",IF(K11<=0,"Out of stock",IF(K11<=H11,"Reorder now","OK")))
I12: =IF(B12="","",SUMIFS('Stock Moves'!$E$6:$E$2005,'Stock Moves'!$C$6:$C$2005,B12,'Stock Moves'!$D$6:$D$2005,"Purchase")+SUMIFS('Stock Moves'!$E$6:$E$2005,'Stock Moves'!$C$6:$C$2005,B12,'Stock Moves'!$D$6:$D$2005,"Return")+SUMIFS('Stock Moves'!$E$6:$E$2005,'Stock Moves'!$C$6:$C$2005,B12,'Stock Moves'!$D$6:$D$2005,"Adjustment")) | J12: =IF(B12="","",SUMIFS('Stock Moves'!$E$6:$E$2005,'Stock Moves'!$C$6:$C$2005,B12,'Stock Moves'!$D$6:$D$2005,"Sale")) | K12: =IF(B12="","",G12+I12-J12) | L12: =IF(OR(B12="",N(F12)=0),"",(F12-E12)/F12) | M12: =IF(B12="","",IF(K12<=0,"Out of stock",IF(K12<=H12,"Reorder now","OK")))
I13: =IF(B13="","",SUMIFS('Stock Moves'!$E$6:$E$2005,'Stock Moves'!$C$6:$C$2005,B13,'Stock Moves'!$D$6:$D$2005,"Purchase")+SUMIFS('Stock Moves'!$E$6:$E$2005,'Stock Moves'!$C$6:$C$2005,B13,'Stock Moves'!$D$6:$D$2005,"Return")+SUMIFS('Stock Moves'!$E$6:$E$2005,'Stock Moves'!$C$6:$C$2005,B13,'Stock Moves'!$D$6:$D$2005,"Adjustment")) | J13: =IF(B13="","",SUMIFS('Stock Moves'!$E$6:$E$2005,'Stock Moves'!$C$6:$C$2005,B13,'Stock Moves'!$D$6:$D$2005,"Sale")) | K13: =IF(B13="","",G13+I13-J13) | L13: =IF(OR(B13="",N(F13)=0),"",(F13-E13)/F13) | M13: =IF(B13="","",IF(K13<=0,"Out of stock",IF(K13<=H13,"Reorder now","OK")))
I14: =IF(B14="","",SUMIFS('Stock Moves'!$E$6:$E$2005,'Stock Moves'!$C$6:$C$2005,B14,'Stock Moves'!$D$6:$D$2005,"Purchase")+SUMIFS('Stock Moves'!$E$6:$E$2005,'Stock Moves'!$C$6:$C$2005,B14,'Stock Moves'!$D$6:$D$2005,"Return")+SUMIFS('Stock Moves'!$E$6:$E$2005,'Stock Moves'!$C$6:$C$2005,B14,'Stock Moves'!$D$6:$D$2005,"Adjustment")) | J14: =IF(B14="","",SUMIFS('Stock Moves'!$E$6:$E$2005,'Stock Moves'!$C$6:$C$2005,B14,'Stock Moves'!$D$6:$D$2005,"Sale")) | K14: =IF(B14="","",G14+I14-J14) | L14: =IF(OR(B14="",N(F14)=0),"",(F14-E14)/F14) | M14: =IF(B14="","",IF(K14<=0,"Out of stock",IF(K14<=H14,"Reorder now","OK")))
I15: =IF(B15="","",SUMIFS('Stock Moves'!$E$6:$E$2005,'Stock Moves'!$C$6:$C$2005,B15,'Stock Moves'!$D$6:$D$2005,"Purchase")+SUMIFS('Stock Moves'!$E$6:$E$2005,'Stock Moves'!$C$6:$C$2005,B15,'Stock Moves'!$D$6:$D$2005,"Return")+SUMIFS('Stock Moves'!$E$6:$E$2005,'Stock Moves'!$C$6:$C$2005,B15,'Stock Moves'!$D$6:$D$2005,"Adjustment")) | J15: =IF(B15="","",SUMIFS('Stock Moves'!$E$6:$E$2005,'Stock Moves'!$C$6:$C$2005,B15,'Stock Moves'!$D$6:$D$2005,"Sale")) | K15: =IF(B15="","",G15+I15-J15) | L15: =IF(OR(B15="",N(F15)=0),"",(F15-E15)/F15) | M15: =IF(B15="","",IF(K15<=0,"Out of stock",IF(K15<=H15,"Reorder now","OK")))
I16: =IF(B16="","",SUMIFS('Stock Moves'!$E$6:$E$2005,'Stock Moves'!$C$6:$C$2005,B16,'Stock Moves'!$D$6:$D$2005,"Purchase")+SUMIFS('Stock Moves'!$E$6:$E$2005,'Stock Moves'!$C$6:$C$2005,B16,'Stock Moves'!$D$6:$D$2005,"Return")+SUMIFS('Stock Moves'!$E$6:$E$2005,'Stock Moves'!$C$6:$C$2005,B16,'Stock Moves'!$D$6:$D$2005,"Adjustment")) | J16: =IF(B16="","",SUMIFS('Stock Moves'!$E$6:$E$2005,'Stock Moves'!$C$6:$C$2005,B16,'Stock Moves'!$D$6:$D$2005,"Sale")) | K16: =IF(B16="","",G16+I16-J16) | L16: =IF(OR(B16="",N(F16)=0),"",(F16-E16)/F16) | M16: =IF(B16="","",IF(K16<=0,"Out of stock",IF(K16<=H16,"Reorder now","OK")))
I17: =IF(B17="","",SUMIFS('Stock Moves'!$E$6:$E$2005,'Stock Moves'!$C$6:$C$2005,B17,'Stock Moves'!$D$6:$D$2005,"Purchase")+SUMIFS('Stock Moves'!$E$6:$E$2005,'Stock Moves'!$C$6:$C$2005,B17,'Stock Moves'!$D$6:$D$2005,"Return")+SUMIFS('Stock Moves'!$E$6:$E$2005,'Stock Moves'!$C$6:$C$2005,B17,'Stock Moves'!$D$6:$D$2005,"Adjustment")) | J17: =IF(B17="","",SUMIFS('Stock Moves'!$E$6:$E$2005,'Stock Moves'!$C$6:$C$2005,B17,'Stock Moves'!$D$6:$D$2005,"Sale")) | K17: =IF(B17="","",G17+I17-J17) | L17: =IF(OR(B17="",N(F17)=0),"",(F17-E17)/F17) | M17: =IF(B17="","",IF(K17<=0,"Out of stock",IF(K17<=H17,"Reorder now","OK")))
I18: =IF(B18="","",SUMIFS('Stock Moves'!$E$6:$E$2005,'Stock Moves'!$C$6:$C$2005,B18,'Stock Moves'!$D$6:$D$2005,"Purchase")+SUMIFS('Stock Moves'!$E$6:$E$2005,'Stock Moves'!$C$6:$C$2005,B18,'Stock Moves'!$D$6:$D$2005,"Return")+SUMIFS('Stock Moves'!$E$6:$E$2005,'Stock Moves'!$C$6:$C$2005,B18,'Stock Moves'!$D$6:$D$2005,"Adjustment")) | J18: =IF(B18="","",SUMIFS('Stock Moves'!$E$6:$E$2005,'Stock Moves'!$C$6:$C$2005,B18,'Stock Moves'!$D$6:$D$2005,"Sale")) | K18: =IF(B18="","",G18+I18-J18) | L18: =IF(OR(B18="",N(F18)=0),"",(F18-E18)/F18) | M18: =IF(B18="","",IF(K18<=0,"Out of stock",IF(K18<=H18,"Reorder now","OK")))
I19: =IF(B19="","",SUMIFS('Stock Moves'!$E$6:$E$2005,'Stock Moves'!$C$6:$C$2005,B19,'Stock Moves'!$D$6:$D$2005,"Purchase")+SUMIFS('Stock Moves'!$E$6:$E$2005,'Stock Moves'!$C$6:$C$2005,B19,'Stock Moves'!$D$6:$D$2005,"Return")+SUMIFS('Stock Moves'!$E$6:$E$2005,'Stock Moves'!$C$6:$C$2005,B19,'Stock Moves'!$D$6:$D$2005,"Adjustment")) | J19: =IF(B19="","",SUMIFS('Stock Moves'!$E$6:$E$2005,'Stock Moves'!$C$6:$C$2005,B19,'Stock Moves'!$D$6:$D$2005,"Sale")) | K19: =IF(B19="","",G19+I19-J19) | L19: =IF(OR(B19="",N(F19)=0),"",(F19-E19)/F19) | M19: =IF(B19="","",IF(K19<=0,"Out of stock",IF(K19<=H19,"Reorder now","OK")))
I20: =IF(B20="","",SUMIFS('Stock Moves'!$E$6:$E$2005,'Stock Moves'!$C$6:$C$2005,B20,'Stock Moves'!$D$6:$D$2005,"Purchase")+SUMIFS('Stock Moves'!$E$6:$E$2005,'Stock Moves'!$C$6:$C$2005,B20,'Stock Moves'!$D$6:$D$2005,"Return")+SUMIFS('Stock Moves'!$E$6:$E$2005,'Stock Moves'!$C$6:$C$2005,B20,'Stock Moves'!$D$6:$D$2005,"Adjustment")) | J20: =IF(B20="","",SUMIFS('Stock Moves'!$E$6:$E$2005,'Stock Moves'!$C$6:$C$2005,B20,'Stock Moves'!$D$6:$D$2005,"Sale")) | K20: =IF(B20="","",G20+I20-J20) | L20: =IF(OR(B20="",N(F20)=0),"",(F20-E20)/F20) | M20: =IF(B20="","",IF(K20<=0,"Out of stock",IF(K20<=H20,"Reorder now","OK")))
I21: =IF(B21="","",SUMIFS('Stock Moves'!$E$6:$E$2005,'Stock Moves'!$C$6:$C$2005,B21,'Stock Moves'!$D$6:$D$2005,"Purchase")+SUMIFS('Stock Moves'!$E$6:$E$2005,'Stock Moves'!$C$6:$C$2005,B21,'Stock Moves'!$D$6:$D$2005,"Return")+SUMIFS('Stock Moves'!$E$6:$E$2005,'Stock Moves'!$C$6:$C$2005,B21,'Stock Moves'!$D$6:$D$2005,"Adjustment")) | J21: =IF(B21="","",SUMIFS('Stock Moves'!$E$6:$E$2005,'Stock Moves'!$C$6:$C$2005,B21,'Stock Moves'!$D$6:$D$2005,"Sale")) | K21: =IF(B21="","",G21+I21-J21) | L21: =IF(OR(B21="",N(F21)=0),"",(F21-E21)/F21) | M21: =IF(B21="","",IF(K21<=0,"Out of stock",IF(K21<=H21,"Reorder now","OK")))
I22: =IF(B22="","",SUMIFS('Stock Moves'!$E$6:$E$2005,'Stock Moves'!$C$6:$C$2005,B22,'Stock Moves'!$D$6:$D$2005,"Purchase")+SUMIFS('Stock Moves'!$E$6:$E$2005,'Stock Moves'!$C$6:$C$2005,B22,'Stock Moves'!$D$6:$D$2005,"Return")+SUMIFS('Stock Moves'!$E$6:$E$2005,'Stock Moves'!$C$6:$C$2005,B22,'Stock Moves'!$D$6:$D$2005,"Adjustment")) | J22: =IF(B22="","",SUMIFS('Stock Moves'!$E$6:$E$2005,'Stock Moves'!$C$6:$C$2005,B22,'Stock Moves'!$D$6:$D$2005,"Sale")) | K22: =IF(B22="","",G22+I22-J22) | L22: =IF(OR(B22="",N(F22)=0),"",(F22-E22)/F22) | M22: =IF(B22="","",IF(K22<=0,"Out of stock",IF(K22<=H22,"Reorder now","OK")))
I23: =IF(B23="","",SUMIFS('Stock Moves'!$E$6:$E$2005,'Stock Moves'!$C$6:$C$2005,B23,'Stock Moves'!$D$6:$D$2005,"Purchase")+SUMIFS('Stock Moves'!$E$6:$E$2005,'Stock Moves'!$C$6:$C$2005,B23,'Stock Moves'!$D$6:$D$2005,"Return")+SUMIFS('Stock Moves'!$E$6:$E$2005,'Stock Moves'!$C$6:$C$2005,B23,'Stock Moves'!$D$6:$D$2005,"Adjustment")) | J23: =IF(B23="","",SUMIFS('Stock Moves'!$E$6:$E$2005,'Stock Moves'!$C$6:$C$2005,B23,'Stock Moves'!$D$6:$D$2005,"Sale")) | K23: =IF(B23="","",G23+I23-J23) | L23: =IF(OR(B23="",N(F23)=0),"",(F23-E23)/F23) | M23: =IF(B23="","",IF(K23<=0,"Out of stock",IF(K23<=H23,"Reorder now","OK")))
... I205: =IF(B205="","",SUMIFS('Stock Moves'!$E$6:$E$2005,'Stock Moves'!$C$6:$C$2005,B205,'Stock Moves'!$D$6:$D$2005,"Purchase")+SUMIFS('Stock Moves'!$E$6:$E$2005,'Stock Moves'!$C$6:$C$2005,B205,'Stock Moves'!$D$6:$D$2005,"Return")+SUMIFS('Stock Moves'!$E$6:$E$2005,'Stock Moves'!$C$6:$C$2005,B205,'Stock Moves'!$D$6:$D$2005,"Adjustment")) | J205: =IF(B205="","",SUMIFS('Stock Moves'!$E$6:$E$2005,'Stock Moves'!$C$6:$C$2005,B205,'Stock Moves'!$D$6:$D$2005,"Sale")) | K205: =IF(B205="","",G205+I205-J205) | L205: =IF(OR(B205="",N(F205)=0),"",(F205-E205)/F205) | M205: =IF(B205="","",IF(K205<=0,"Out of stock",IF(K205<=H205,"Reorder now","OK")))

Sheet Stock Moves
B2: Stock moves
B3: One line per purchase, sale, return or adjustment (negative number = stock removed).
B5: Date | C5: SKU | D5: Type | E5: Qty | F5: Unit price | G5: Sale total | H5: Cost of sale | I5: Note
B6: 46223 | C6: CAN-01 | D6: Purchase | E6: 30 | F6: 4.2 | G6: =IF(D6="Sale",E6*F6,IF(D6="Return",-E6*F6,"")) | H6: =IFERROR(IF(D6="Sale",E6*INDEX(Products!$E$6:$E$205,MATCH(C6,Products!$B$6:$B$205,0)),IF(D6="Return",-E6*INDEX(Products!$E$6:$E$205,MATCH(C6,Products!$B$6:$B$205,0)),"")),"")
B7: 46223 | C7: CAN-02 | D7: Purchase | E7: 20 | F7: 4.2 | G7: =IF(D7="Sale",E7*F7,IF(D7="Return",-E7*F7,"")) | H7: =IFERROR(IF(D7="Sale",E7*INDEX(Products!$E$6:$E$205,MATCH(C7,Products!$B$6:$B$205,0)),IF(D7="Return",-E7*INDEX(Products!$E$6:$E$205,MATCH(C7,Products!$B$6:$B$205,0)),"")),"")
B8: 46228 | C8: MUG-01 | D8: Purchase | E8: 10 | F8: 7.5 | G8: =IF(D8="Sale",E8*F8,IF(D8="Return",-E8*F8,"")) | H8: =IFERROR(IF(D8="Sale",E8*INDEX(Products!$E$6:$E$205,MATCH(C8,Products!$B$6:$B$205,0)),IF(D8="Return",-E8*INDEX(Products!$E$6:$E$205,MATCH(C8,Products!$B$6:$B$205,0)),"")),"")
B9: 46233 | C9: CAN-01 | D9: Sale | E9: 12 | F9: 18 | G9: =IF(D9="Sale",E9*F9,IF(D9="Return",-E9*F9,"")) | H9: =IFERROR(IF(D9="Sale",E9*INDEX(Products!$E$6:$E$205,MATCH(C9,Products!$B$6:$B$205,0)),IF(D9="Return",-E9*INDEX(Products!$E$6:$E$205,MATCH(C9,Products!$B$6:$B$205,0)),"")),"")
B10: 46238 | C10: EAR-01 | D10: Sale | E10: 9 | F10: 22 | G10: =IF(D10="Sale",E10*F10,IF(D10="Return",-E10*F10,"")) | H10: =IFERROR(IF(D10="Sale",E10*INDEX(Products!$E$6:$E$205,MATCH(C10,Products!$B$6:$B$205,0)),IF(D10="Return",-E10*INDEX(Products!$E$6:$E$205,MATCH(C10,Products!$B$6:$B$205,0)),"")),"")
B11: 46243 | C11: CRD-01 | D11: Sale | E11: 14 | F11: 9 | G11: =IF(D11="Sale",E11*F11,IF(D11="Return",-E11*F11,"")) | H11: =IFERROR(IF(D11="Sale",E11*INDEX(Products!$E$6:$E$205,MATCH(C11,Products!$B$6:$B$205,0)),IF(D11="Return",-E11*INDEX(Products!$E$6:$E$205,MATCH(C11,Products!$B$6:$B$205,0)),"")),"")
B12: 46253 | C12: MUG-01 | D12: Sale | E12: 8 | F12: 28 | G12: =IF(D12="Sale",E12*F12,IF(D12="Return",-E12*F12,"")) | H12: =IFERROR(IF(D12="Sale",E12*INDEX(Products!$E$6:$E$205,MATCH(C12,Products!$B$6:$B$205,0)),IF(D12="Return",-E12*INDEX(Products!$E$6:$E$205,MATCH(C12,Products!$B$6:$B$205,0)),"")),"")
B13: 46260 | C13: CAN-02 | D13: Sale | E13: 19 | F13: 18 | G13: =IF(D13="Sale",E13*F13,IF(D13="Return",-E13*F13,"")) | H13: =IFERROR(IF(D13="Sale",E13*INDEX(Products!$E$6:$E$205,MATCH(C13,Products!$B$6:$B$205,0)),IF(D13="Return",-E13*INDEX(Products!$E$6:$E$205,MATCH(C13,Products!$B$6:$B$205,0)),"")),"")
B14: 46263 | C14: BAG-01 | D14: Sale | E14: 3 | F14: 24 | G14: =IF(D14="Sale",E14*F14,IF(D14="Return",-E14*F14,"")) | H14: =IFERROR(IF(D14="Sale",E14*INDEX(Products!$E$6:$E$205,MATCH(C14,Products!$B$6:$B$205,0)),IF(D14="Return",-E14*INDEX(Products!$E$6:$E$205,MATCH(C14,Products!$B$6:$B$205,0)),"")),"")
B15: 46267 | C15: CAN-01 | D15: Sale | E15: 16 | F15: 18 | G15: =IF(D15="Sale",E15*F15,IF(D15="Return",-E15*F15,"")) | H15: =IFERROR(IF(D15="Sale",E15*INDEX(Products!$E$6:$E$205,MATCH(C15,Products!$B$6:$B$205,0)),IF(D15="Return",-E15*INDEX(Products!$E$6:$E$205,MATCH(C15,Products!$B$6:$B$205,0)),"")),"")
B16: 46273 | C16: EAR-01 | D16: Sale | E16: 12 | F16: 22 | G16: =IF(D16="Sale",E16*F16,IF(D16="Return",-E16*F16,"")) | H16: =IFERROR(IF(D16="Sale",E16*INDEX(Products!$E$6:$E$205,MATCH(C16,Products!$B$6:$B$205,0)),IF(D16="Return",-E16*INDEX(Products!$E$6:$E$205,MATCH(C16,Products!$B$6:$B$205,0)),"")),"")
B17: 46275 | C17: MUG-01 | D17: Sale | E17: 7 | F17: 28 | G17: =IF(D17="Sale",E17*F17,IF(D17="Return",-E17*F17,"")) | H17: =IFERROR(IF(D17="Sale",E17*INDEX(Products!$E$6:$E$205,MATCH(C17,Products!$B$6:$B$205,0)),IF(D17="Return",-E17*INDEX(Products!$E$6:$E$205,MATCH(C17,Products!$B$6:$B$205,0)),"")),"")
... B24: 46292 | C24: MUG-01 | D24: Sale | E24: 3 | F24: 28 | G24: =IF(D24="Sale",E24*F24,IF(D24="Return",-E24*F24,"")) | H24: =IFERROR(IF(D24="Sale",E24*INDEX(Products!$E$6:$E$205,MATCH(C24,Products!$B$6:$B$205,0)),IF(D24="Return",-E24*INDEX(Products!$E$6:$E$205,MATCH(C24,Products!$B$6:$B$205,0)),"")),"")
G25: =IF(D25="Sale",E25*F25,IF(D25="Return",-E25*F25,"")) | H25: =IFERROR(IF(D25="Sale",E25*INDEX(Products!$E$6:$E$205,MATCH(C25,Products!$B$6:$B$205,0)),IF(D25="Return",-E25*INDEX(Products!$E$6:$E$205,MATCH(C25,Products!$B$6:$B$205,0)),"")),"")
G26: =IF(D26="Sale",E26*F26,IF(D26="Return",-E26*F26,"")) | H26: =IFERROR(IF(D26="Sale",E26*INDEX(Products!$E$6:$E$205,MATCH(C26,Products!$B$6:$B$205,0)),IF(D26="Return",-E26*INDEX(Products!$E$6:$E$205,MATCH(C26,Products!$B$6:$B$205,0)),"")),"")
G27: =IF(D27="Sale",E27*F27,IF(D27="Return",-E27*F27,"")) | H27: =IFERROR(IF(D27="Sale",E27*INDEX(Products!$E$6:$E$205,MATCH(C27,Products!$B$6:$B$205,0)),IF(D27="Return",-E27*INDEX(Products!$E$6:$E$205,MATCH(C27,Products!$B$6:$B$205,0)),"")),"")
G28: =IF(D28="Sale",E28*F28,IF(D28="Return",-E28*F28,"")) | H28: =IFERROR(IF(D28="Sale",E28*INDEX(Products!$E$6:$E$205,MATCH(C28,Products!$B$6:$B$205,0)),IF(D28="Return",-E28*INDEX(Products!$E$6:$E$205,MATCH(C28,Products!$B$6:$B$205,0)),"")),"")
G29: =IF(D29="Sale",E29*F29,IF(D29="Return",-E29*F29,"")) | H29: =IFERROR(IF(D29="Sale",E29*INDEX(Products!$E$6:$E$205,MATCH(C29,Products!$B$6:$B$205,0)),IF(D29="Return",-E29*INDEX(Products!$E$6:$E$205,MATCH(C29,Products!$B$6:$B$205,0)),"")),"")
G30: =IF(D30="Sale",E30*F30,IF(D30="Return",-E30*F30,"")) | H30: =IFERROR(IF(D30="Sale",E30*INDEX(Products!$E$6:$E$205,MATCH(C30,Products!$B$6:$B$205,0)),IF(D30="Return",-E30*INDEX(Products!$E$6:$E$205,MATCH(C30,Products!$B$6:$B$205,0)),"")),"")
G31: =IF(D31="Sale",E31*F31,IF(D31="Return",-E31*F31,"")) | H31: =IFERROR(IF(D31="Sale",E31*INDEX(Products!$E$6:$E$205,MATCH(C31,Products!$B$6:$B$205,0)),IF(D31="Return",-E31*INDEX(Products!$E$6:$E$205,MATCH(C31,Products!$B$6:$B$205,0)),"")),"")
G32: =IF(D32="Sale",E32*F32,IF(D32="Return",-E32*F32,"")) | H32: =IFERROR(IF(D32="Sale",E32*INDEX(Products!$E$6:$E$205,MATCH(C32,Products!$B$6:$B$205,0)),IF(D32="Return",-E32*INDEX(Products!$E$6:$E$205,MATCH(C32,Products!$B$6:$B$205,0)),"")),"")
G33: =IF(D33="Sale",E33*F33,IF(D33="Return",-E33*F33,"")) | H33: =IFERROR(IF(D33="Sale",E33*INDEX(Products!$E$6:$E$205,MATCH(C33,Products!$B$6:$B$205,0)),IF(D33="Return",-E33*INDEX(Products!$E$6:$E$205,MATCH(C33,Products!$B$6:$B$205,0)),"")),"")
G34: =IF(D34="Sale",E34*F34,IF(D34="Return",-E34*F34,"")) | H34: =IFERROR(IF(D34="Sale",E34*INDEX(Products!$E$6:$E$205,MATCH(C34,Products!$B$6:$B$205,0)),IF(D34="Return",-E34*INDEX(Products!$E$6:$E$205,MATCH(C34,Products!$B$6:$B$205,0)),"")),"")
G35: =IF(D35="Sale",E35*F35,IF(D35="Return",-E35*F35,"")) | H35: =IFERROR(IF(D35="Sale",E35*INDEX(Products!$E$6:$E$205,MATCH(C35,Products!$B$6:$B$205,0)),IF(D35="Return",-E35*INDEX(Products!$E$6:$E$205,MATCH(C35,Products!$B$6:$B$205,0)),"")),"")
G36: =IF(D36="Sale",E36*F36,IF(D36="Return",-E36*F36,"")) | H36: =IFERROR(IF(D36="Sale",E36*INDEX(Products!$E$6:$E$205,MATCH(C36,Products!$B$6:$B$205,0)),IF(D36="Return",-E36*INDEX(Products!$E$6:$E$205,MATCH(C36,Products!$B$6:$B$205,0)),"")),"")
... G2005: =IF(D2005="Sale",E2005*F2005,IF(D2005="Return",-E2005*F2005,"")) | H2005: =IFERROR(IF(D2005="Sale",E2005*INDEX(Products!$E$6:$E$205,MATCH(C2005,Products!$B$6:$B$205,0)),IF(D2005="Return",-E2005*INDEX(Products!$E$6:$E$205,MATCH(C2005,Products!$B$6:$B$205,0)),"")),"")

Sheet Start Here
B2: Start here
B3: Type only in the yellow cells. Everything else is calculated.
B5: 1 | C5: Products: add each product once, with its code, cost, price, stock today and reorder level.
B7: 2 | C7: Stock Moves: add a line each time stock changes (Purchase, Sale, Return or Adjustment).
B9: 3 | C9: Broken, lost or gifted items: add an Adjustment with a negative quantity.
B11: 4 | C11: Products then shows the stock you have. Orange means reorder, red means sold out.
B13: 5 | C13: Dashboard: sales, profit and units for the month you pick, and the value of your stock.
C17: The example products and moves show how it works. Delete them and add your own.
C19: Works in Google Sheets and Microsoft Excel, in any currency.
