Workbook

Sheet Dashboard
B2: ="Christmas "&Settings!$C$4
B3: Gifts and plans on the left, the money on the right.
B4: Days to Christmas | C4: Gifts bought | D4: Wrapped | E4: Cards sent | G4: Budget | H4: Spent | I4: Still to pay | J4: Left
B5: =IF(TODAY()=DATE(Settings!$C$4,12,25),"Today",MAX(0,DATE(Settings!$C$4,12,25)-TODAY())) | C5: =SUM(Gifts!$M$6:$M$305)&" of "&COUNT(Gifts!$M$6:$M$305) | D5: =COUNTIF(Gifts!$K$6:$K$305,"Wrapped")&" of "&COUNT(Gifts!$M$6:$M$305) | E5: =COUNTIF(Cards!$H$6:$H$305,"Sent")&" of "&(COUNTIF(Cards!$H$6:$H$305,"Sent")+COUNTIF(Cards!$H$6:$H$305,"To send")) | G5: =Budget!C22 | H5: =Budget!D22 | I5: =Budget!E22 | J5: =Budget!F22
B8: Still to buy for | C8: Status | D8: Budget | E8: Left | G8: Category | H8: Budget | I8: Spent | J8: To pay
B9: =IF(O9="","Every gift is bought",INDEX(People!$B$6:$B$65,O9-5)) | C9: =IF(O9="","",INDEX(People!$J$6:$J$65,O9-5)) | D9: =IF(O9="","",IF(INDEX(People!$D$6:$D$65,O9-5)="","",INDEX(People!$D$6:$D$65,O9-5))) | E9: =IF(O9="","",INDEX(People!$I$6:$I$65,O9-5)) | G9: =IF(P9="","",INDEX(Budget!$B$6:$B$21,P9-5)) | H9: =IF(P9="","",N(INDEX(Budget!$C$6:$C$21,P9-5))) | I9: =IF(P9="","",N(INDEX(Budget!$D$6:$D$21,P9-5))) | J9: =IF(P9="","",N(INDEX(Budget!$E$6:$E$21,P9-5))) | O9: =IFERROR(SMALL(People!$L$6:$L$65,1),"") | P9: =IFERROR(SMALL(Budget!$I$6:$I$21,1),"")
B10: =IF(O10="","",INDEX(People!$B$6:$B$65,O10-5)) | C10: =IF(O10="","",INDEX(People!$J$6:$J$65,O10-5)) | D10: =IF(O10="","",IF(INDEX(People!$D$6:$D$65,O10-5)="","",INDEX(People!$D$6:$D$65,O10-5))) | E10: =IF(O10="","",INDEX(People!$I$6:$I$65,O10-5)) | G10: =IF(P10="","",INDEX(Budget!$B$6:$B$21,P10-5)) | H10: =IF(P10="","",N(INDEX(Budget!$C$6:$C$21,P10-5))) | I10: =IF(P10="","",N(INDEX(Budget!$D$6:$D$21,P10-5))) | J10: =IF(P10="","",N(INDEX(Budget!$E$6:$E$21,P10-5))) | O10: =IFERROR(SMALL(People!$L$6:$L$65,2),"") | P10: =IFERROR(SMALL(Budget!$I$6:$I$21,2),"")
B11: =IF(O11="","",INDEX(People!$B$6:$B$65,O11-5)) | C11: =IF(O11="","",INDEX(People!$J$6:$J$65,O11-5)) | D11: =IF(O11="","",IF(INDEX(People!$D$6:$D$65,O11-5)="","",INDEX(People!$D$6:$D$65,O11-5))) | E11: =IF(O11="","",INDEX(People!$I$6:$I$65,O11-5)) | G11: =IF(P11="","",INDEX(Budget!$B$6:$B$21,P11-5)) | H11: =IF(P11="","",N(INDEX(Budget!$C$6:$C$21,P11-5))) | I11: =IF(P11="","",N(INDEX(Budget!$D$6:$D$21,P11-5))) | J11: =IF(P11="","",N(INDEX(Budget!$E$6:$E$21,P11-5))) | O11: =IFERROR(SMALL(People!$L$6:$L$65,3),"") | P11: =IFERROR(SMALL(Budget!$I$6:$I$21,3),"")
B12: =IF(O12="","",INDEX(People!$B$6:$B$65,O12-5)) | C12: =IF(O12="","",INDEX(People!$J$6:$J$65,O12-5)) | D12: =IF(O12="","",IF(INDEX(People!$D$6:$D$65,O12-5)="","",INDEX(People!$D$6:$D$65,O12-5))) | E12: =IF(O12="","",INDEX(People!$I$6:$I$65,O12-5)) | G12: =IF(P12="","",INDEX(Budget!$B$6:$B$21,P12-5)) | H12: =IF(P12="","",N(INDEX(Budget!$C$6:$C$21,P12-5))) | I12: =IF(P12="","",N(INDEX(Budget!$D$6:$D$21,P12-5))) | J12: =IF(P12="","",N(INDEX(Budget!$E$6:$E$21,P12-5))) | O12: =IFERROR(SMALL(People!$L$6:$L$65,4),"") | P12: =IFERROR(SMALL(Budget!$I$6:$I$21,4),"")
B13: =IF(O13="","",INDEX(People!$B$6:$B$65,O13-5)) | C13: =IF(O13="","",INDEX(People!$J$6:$J$65,O13-5)) | D13: =IF(O13="","",IF(INDEX(People!$D$6:$D$65,O13-5)="","",INDEX(People!$D$6:$D$65,O13-5))) | E13: =IF(O13="","",INDEX(People!$I$6:$I$65,O13-5)) | G13: =IF(P13="","",INDEX(Budget!$B$6:$B$21,P13-5)) | H13: =IF(P13="","",N(INDEX(Budget!$C$6:$C$21,P13-5))) | I13: =IF(P13="","",N(INDEX(Budget!$D$6:$D$21,P13-5))) | J13: =IF(P13="","",N(INDEX(Budget!$E$6:$E$21,P13-5))) | O13: =IFERROR(SMALL(People!$L$6:$L$65,5),"") | P13: =IFERROR(SMALL(Budget!$I$6:$I$21,5),"")
B14: =IF(O14="","",INDEX(People!$B$6:$B$65,O14-5)) | C14: =IF(O14="","",INDEX(People!$J$6:$J$65,O14-5)) | D14: =IF(O14="","",IF(INDEX(People!$D$6:$D$65,O14-5)="","",INDEX(People!$D$6:$D$65,O14-5))) | E14: =IF(O14="","",INDEX(People!$I$6:$I$65,O14-5)) | G14: =IF(P14="","",INDEX(Budget!$B$6:$B$21,P14-5)) | H14: =IF(P14="","",N(INDEX(Budget!$C$6:$C$21,P14-5))) | I14: =IF(P14="","",N(INDEX(Budget!$D$6:$D$21,P14-5))) | J14: =IF(P14="","",N(INDEX(Budget!$E$6:$E$21,P14-5))) | O14: =IFERROR(SMALL(People!$L$6:$L$65,6),"") | P14: =IFERROR(SMALL(Budget!$I$6:$I$21,6),"")
B15: =IF(O15="","",INDEX(People!$B$6:$B$65,O15-5)) | C15: =IF(O15="","",INDEX(People!$J$6:$J$65,O15-5)) | D15: =IF(O15="","",IF(INDEX(People!$D$6:$D$65,O15-5)="","",INDEX(People!$D$6:$D$65,O15-5))) | E15: =IF(O15="","",INDEX(People!$I$6:$I$65,O15-5)) | G15: =IF(P15="","",INDEX(Budget!$B$6:$B$21,P15-5)) | H15: =IF(P15="","",N(INDEX(Budget!$C$6:$C$21,P15-5))) | I15: =IF(P15="","",N(INDEX(Budget!$D$6:$D$21,P15-5))) | J15: =IF(P15="","",N(INDEX(Budget!$E$6:$E$21,P15-5))) | O15: =IFERROR(SMALL(People!$L$6:$L$65,7),"") | P15: =IFERROR(SMALL(Budget!$I$6:$I$21,7),"")
B16: =IF(O16="","",INDEX(People!$B$6:$B$65,O16-5)) | C16: =IF(O16="","",INDEX(People!$J$6:$J$65,O16-5)) | D16: =IF(O16="","",IF(INDEX(People!$D$6:$D$65,O16-5)="","",INDEX(People!$D$6:$D$65,O16-5))) | E16: =IF(O16="","",INDEX(People!$I$6:$I$65,O16-5)) | G16: =IF(P16="","",INDEX(Budget!$B$6:$B$21,P16-5)) | H16: =IF(P16="","",N(INDEX(Budget!$C$6:$C$21,P16-5))) | I16: =IF(P16="","",N(INDEX(Budget!$D$6:$D$21,P16-5))) | J16: =IF(P16="","",N(INDEX(Budget!$E$6:$E$21,P16-5))) | O16: =IFERROR(SMALL(People!$L$6:$L$65,8),"") | P16: =IFERROR(SMALL(Budget!$I$6:$I$21,8),"")
B19: Orders on the way | C19: For | D19: Arrives by | E19: Status | G19: Coming up | H19: Time | I19: What
B20: =IF(O20="","No orders on the way",INDEX(Gifts!$C$6:$C$305,MATCH(O20,Gifts!$P$6:$P$305,0))) | C20: =IF(O20="","",INDEX(Gifts!$B$6:$B$305,MATCH(O20,Gifts!$P$6:$P$305,0))) | D20: =IF(O20="","",INT(O20)) | E20: =IF(O20="","",INDEX(Gifts!$K$6:$K$305,MATCH(O20,Gifts!$P$6:$P$305,0))) | G20: =IF(P20="","Nothing planned yet",INT(P20)) | H20: =IF(P20="","",IF(INDEX(Plans!$C$6:$C$155,MATCH(P20,Plans!$H$6:$H$155,0))="","",INDEX(Plans!$C$6:$C$155,MATCH(P20,Plans!$H$6:$H$155,0)))) | I20: =IF(P20="","",INDEX(Plans!$D$6:$D$155,MATCH(P20,Plans!$H$6:$H$155,0))&IF(INDEX(Plans!$E$6:$E$155,MATCH(P20,Plans!$H$6:$H$155,0))="","",", "&INDEX(Plans!$E$6:$E$155,MATCH(P20,Plans!$H$6:$H$155,0)))) | O20: =IFERROR(SMALL(Gifts!$P$6:$P$305,1),"") | P20: =IFERROR(SMALL(Plans!$H$6:$H$155,COUNTIF(Plans!$H$6:$H$155,"<"&TODAY())+1),"")
B21: =IF(O21="","",INDEX(Gifts!$C$6:$C$305,MATCH(O21,Gifts!$P$6:$P$305,0))) | C21: =IF(O21="","",INDEX(Gifts!$B$6:$B$305,MATCH(O21,Gifts!$P$6:$P$305,0))) | D21: =IF(O21="","",INT(O21)) | E21: =IF(O21="","",INDEX(Gifts!$K$6:$K$305,MATCH(O21,Gifts!$P$6:$P$305,0))) | G21: =IF(P21="","",INT(P21)) | H21: =IF(P21="","",IF(INDEX(Plans!$C$6:$C$155,MATCH(P21,Plans!$H$6:$H$155,0))="","",INDEX(Plans!$C$6:$C$155,MATCH(P21,Plans!$H$6:$H$155,0)))) | I21: =IF(P21="","",INDEX(Plans!$D$6:$D$155,MATCH(P21,Plans!$H$6:$H$155,0))&IF(INDEX(Plans!$E$6:$E$155,MATCH(P21,Plans!$H$6:$H$155,0))="","",", "&INDEX(Plans!$E$6:$E$155,MATCH(P21,Plans!$H$6:$H$155,0)))) | O21: =IFERROR(SMALL(Gifts!$P$6:$P$305,2),"") | P21: =IFERROR(SMALL(Plans!$H$6:$H$155,COUNTIF(Plans!$H$6:$H$155,"<"&TODAY())+2),"")
B22: =IF(O22="","",INDEX(Gifts!$C$6:$C$305,MATCH(O22,Gifts!$P$6:$P$305,0))) | C22: =IF(O22="","",INDEX(Gifts!$B$6:$B$305,MATCH(O22,Gifts!$P$6:$P$305,0))) | D22: =IF(O22="","",INT(O22)) | E22: =IF(O22="","",INDEX(Gifts!$K$6:$K$305,MATCH(O22,Gifts!$P$6:$P$305,0))) | G22: =IF(P22="","",INT(P22)) | H22: =IF(P22="","",IF(INDEX(Plans!$C$6:$C$155,MATCH(P22,Plans!$H$6:$H$155,0))="","",INDEX(Plans!$C$6:$C$155,MATCH(P22,Plans!$H$6:$H$155,0)))) | I22: =IF(P22="","",INDEX(Plans!$D$6:$D$155,MATCH(P22,Plans!$H$6:$H$155,0))&IF(INDEX(Plans!$E$6:$E$155,MATCH(P22,Plans!$H$6:$H$155,0))="","",", "&INDEX(Plans!$E$6:$E$155,MATCH(P22,Plans!$H$6:$H$155,0)))) | O22: =IFERROR(SMALL(Gifts!$P$6:$P$305,3),"") | P22: =IFERROR(SMALL(Plans!$H$6:$H$155,COUNTIF(Plans!$H$6:$H$155,"<"&TODAY())+3),"")
B23: =IF(O23="","",INDEX(Gifts!$C$6:$C$305,MATCH(O23,Gifts!$P$6:$P$305,0))) | C23: =IF(O23="","",INDEX(Gifts!$B$6:$B$305,MATCH(O23,Gifts!$P$6:$P$305,0))) | D23: =IF(O23="","",INT(O23)) | E23: =IF(O23="","",INDEX(Gifts!$K$6:$K$305,MATCH(O23,Gifts!$P$6:$P$305,0))) | G23: =IF(P23="","",INT(P23)) | H23: =IF(P23="","",IF(INDEX(Plans!$C$6:$C$155,MATCH(P23,Plans!$H$6:$H$155,0))="","",INDEX(Plans!$C$6:$C$155,MATCH(P23,Plans!$H$6:$H$155,0)))) | I23: =IF(P23="","",INDEX(Plans!$D$6:$D$155,MATCH(P23,Plans!$H$6:$H$155,0))&IF(INDEX(Plans!$E$6:$E$155,MATCH(P23,Plans!$H$6:$H$155,0))="","",", "&INDEX(Plans!$E$6:$E$155,MATCH(P23,Plans!$H$6:$H$155,0)))) | O23: =IFERROR(SMALL(Gifts!$P$6:$P$305,4),"") | P23: =IFERROR(SMALL(Plans!$H$6:$H$155,COUNTIF(Plans!$H$6:$H$155,"<"&TODAY())+4),"")
B24: =IF(O24="","",INDEX(Gifts!$C$6:$C$305,MATCH(O24,Gifts!$P$6:$P$305,0))) | C24: =IF(O24="","",INDEX(Gifts!$B$6:$B$305,MATCH(O24,Gifts!$P$6:$P$305,0))) | D24: =IF(O24="","",INT(O24)) | E24: =IF(O24="","",INDEX(Gifts!$K$6:$K$305,MATCH(O24,Gifts!$P$6:$P$305,0))) | G24: =IF(P24="","",INT(P24)) | H24: =IF(P24="","",IF(INDEX(Plans!$C$6:$C$155,MATCH(P24,Plans!$H$6:$H$155,0))="","",INDEX(Plans!$C$6:$C$155,MATCH(P24,Plans!$H$6:$H$155,0)))) | I24: =IF(P24="","",INDEX(Plans!$D$6:$D$155,MATCH(P24,Plans!$H$6:$H$155,0))&IF(INDEX(Plans!$E$6:$E$155,MATCH(P24,Plans!$H$6:$H$155,0))="","",", "&INDEX(Plans!$E$6:$E$155,MATCH(P24,Plans!$H$6:$H$155,0)))) | O24: =IFERROR(SMALL(Gifts!$P$6:$P$305,5),"") | P24: =IFERROR(SMALL(Plans!$H$6:$H$155,COUNTIF(Plans!$H$6:$H$155,"<"&TODAY())+5),"")
B25: =IF(O25="","",INDEX(Gifts!$C$6:$C$305,MATCH(O25,Gifts!$P$6:$P$305,0))) | C25: =IF(O25="","",INDEX(Gifts!$B$6:$B$305,MATCH(O25,Gifts!$P$6:$P$305,0))) | D25: =IF(O25="","",INT(O25)) | E25: =IF(O25="","",INDEX(Gifts!$K$6:$K$305,MATCH(O25,Gifts!$P$6:$P$305,0))) | G25: =IF(P25="","",INT(P25)) | H25: =IF(P25="","",IF(INDEX(Plans!$C$6:$C$155,MATCH(P25,Plans!$H$6:$H$155,0))="","",INDEX(Plans!$C$6:$C$155,MATCH(P25,Plans!$H$6:$H$155,0)))) | I25: =IF(P25="","",INDEX(Plans!$D$6:$D$155,MATCH(P25,Plans!$H$6:$H$155,0))&IF(INDEX(Plans!$E$6:$E$155,MATCH(P25,Plans!$H$6:$H$155,0))="","",", "&INDEX(Plans!$E$6:$E$155,MATCH(P25,Plans!$H$6:$H$155,0)))) | O25: =IFERROR(SMALL(Gifts!$P$6:$P$305,6),"") | P25: =IFERROR(SMALL(Plans!$H$6:$H$155,COUNTIF(Plans!$H$6:$H$155,"<"&TODAY())+6),"")
B26: =IF(O26="","",INDEX(Gifts!$C$6:$C$305,MATCH(O26,Gifts!$P$6:$P$305,0))) | C26: =IF(O26="","",INDEX(Gifts!$B$6:$B$305,MATCH(O26,Gifts!$P$6:$P$305,0))) | D26: =IF(O26="","",INT(O26)) | E26: =IF(O26="","",INDEX(Gifts!$K$6:$K$305,MATCH(O26,Gifts!$P$6:$P$305,0))) | G26: =IF(P26="","",INT(P26)) | H26: =IF(P26="","",IF(INDEX(Plans!$C$6:$C$155,MATCH(P26,Plans!$H$6:$H$155,0))="","",INDEX(Plans!$C$6:$C$155,MATCH(P26,Plans!$H$6:$H$155,0)))) | I26: =IF(P26="","",INDEX(Plans!$D$6:$D$155,MATCH(P26,Plans!$H$6:$H$155,0))&IF(INDEX(Plans!$E$6:$E$155,MATCH(P26,Plans!$H$6:$H$155,0))="","",", "&INDEX(Plans!$E$6:$E$155,MATCH(P26,Plans!$H$6:$H$155,0)))) | O26: =IFERROR(SMALL(Gifts!$P$6:$P$305,7),"") | P26: =IFERROR(SMALL(Plans!$H$6:$H$155,COUNTIF(Plans!$H$6:$H$155,"<"&TODAY())+7),"")
B27: =IF(O27="","",INDEX(Gifts!$C$6:$C$305,MATCH(O27,Gifts!$P$6:$P$305,0))) | C27: =IF(O27="","",INDEX(Gifts!$B$6:$B$305,MATCH(O27,Gifts!$P$6:$P$305,0))) | D27: =IF(O27="","",INT(O27)) | E27: =IF(O27="","",INDEX(Gifts!$K$6:$K$305,MATCH(O27,Gifts!$P$6:$P$305,0))) | G27: =IF(P27="","",INT(P27)) | H27: =IF(P27="","",IF(INDEX(Plans!$C$6:$C$155,MATCH(P27,Plans!$H$6:$H$155,0))="","",INDEX(Plans!$C$6:$C$155,MATCH(P27,Plans!$H$6:$H$155,0)))) | I27: =IF(P27="","",INDEX(Plans!$D$6:$D$155,MATCH(P27,Plans!$H$6:$H$155,0))&IF(INDEX(Plans!$E$6:$E$155,MATCH(P27,Plans!$H$6:$H$155,0))="","",", "&INDEX(Plans!$E$6:$E$155,MATCH(P27,Plans!$H$6:$H$155,0)))) | O27: =IFERROR(SMALL(Gifts!$P$6:$P$305,8),"") | P27: =IFERROR(SMALL(Plans!$H$6:$H$155,COUNTIF(Plans!$H$6:$H$155,"<"&TODAY())+8),"")

Sheet Gifts
B2: Gifts
B3: One line per gift. An x when you buy it, the day an order should arrive, an x when it is here and when it is wrapped.
B5: For | C5: Gift | D5: Shop or link | E5: Price | F5: Paid | G5: Bought | H5: Arrives by | I5: Here | J5: Wrapped | K5: Status
B6: Mum | C6: Cashmere scarf | D6: Department store | E6: 65 | F6: 59 | G6: x | J6: x | K6: =IF(AND(B6="",C6=""),"",IF(J6<>"","Wrapped",IF(I6<>"","To wrap",IF(AND(G6="",F6=""),"Idea",IF(H6="","To wrap",IF(H6<TODAY(),"Late","On the way")))))) | M6: =IF(AND(B6="",C6=""),"",IF(OR(F6<>"",G6<>"",I6<>"",J6<>""),1,0)) | N6: =IF(M6="","",IF(M6=1,IF(F6<>"",N(F6),N(E6)),0)) | O6: =IF(M6="","",IF(M6=1,0,N(E6))) | P6: =IF(OR(K6="On the way",K6="Late"),H6+ROW()/10000000,"")
B7: Mum | C7: Cookbook | D7: Local bookshop | E7: 28 | F7: 28 | G7: x | K7: =IF(AND(B7="",C7=""),"",IF(J7<>"","Wrapped",IF(I7<>"","To wrap",IF(AND(G7="",F7=""),"Idea",IF(H7="","To wrap",IF(H7<TODAY(),"Late","On the way")))))) | M7: =IF(AND(B7="",C7=""),"",IF(OR(F7<>"",G7<>"",I7<>"",J7<>""),1,0)) | N7: =IF(M7="","",IF(M7=1,IF(F7<>"",N(F7),N(E7)),0)) | O7: =IF(M7="","",IF(M7=1,0,N(E7))) | P7: =IF(OR(K7="On the way",K7="Late"),H7+ROW()/10000000,"")
B8: Mum | C8: Bath set | D8: Online | E8: 25 | K8: =IF(AND(B8="",C8=""),"",IF(J8<>"","Wrapped",IF(I8<>"","To wrap",IF(AND(G8="",F8=""),"Idea",IF(H8="","To wrap",IF(H8<TODAY(),"Late","On the way")))))) | M8: =IF(AND(B8="",C8=""),"",IF(OR(F8<>"",G8<>"",I8<>"",J8<>""),1,0)) | N8: =IF(M8="","",IF(M8=1,IF(F8<>"",N(F8),N(E8)),0)) | O8: =IF(M8="","",IF(M8=1,0,N(E8))) | P8: =IF(OR(K8="On the way",K8="Late"),H8+ROW()/10000000,"")
B9: Dad | C9: Wireless headphones | D9: Online | E9: 90 | F9: 84 | G9: x | H9: 46298 | K9: =IF(AND(B9="",C9=""),"",IF(J9<>"","Wrapped",IF(I9<>"","To wrap",IF(AND(G9="",F9=""),"Idea",IF(H9="","To wrap",IF(H9<TODAY(),"Late","On the way")))))) | M9: =IF(AND(B9="",C9=""),"",IF(OR(F9<>"",G9<>"",I9<>"",J9<>""),1,0)) | N9: =IF(M9="","",IF(M9=1,IF(F9<>"",N(F9),N(E9)),0)) | O9: =IF(M9="","",IF(M9=1,0,N(E9))) | P9: =IF(OR(K9="On the way",K9="Late"),H9+ROW()/10000000,"")
B10: Dad | C10: Coffee sampler | D10: Craft market | E10: 18 | K10: =IF(AND(B10="",C10=""),"",IF(J10<>"","Wrapped",IF(I10<>"","To wrap",IF(AND(G10="",F10=""),"Idea",IF(H10="","To wrap",IF(H10<TODAY(),"Late","On the way")))))) | M10: =IF(AND(B10="",C10=""),"",IF(OR(F10<>"",G10<>"",I10<>"",J10<>""),1,0)) | N10: =IF(M10="","",IF(M10=1,IF(F10<>"",N(F10),N(E10)),0)) | O10: =IF(M10="","",IF(M10=1,0,N(E10))) | P10: =IF(OR(K10="On the way",K10="Late"),H10+ROW()/10000000,"")
B11: Grandma | C11: Photo calendar | D11: Online | E11: 35 | F11: 32 | G11: x | H11: 46291 | K11: =IF(AND(B11="",C11=""),"",IF(J11<>"","Wrapped",IF(I11<>"","To wrap",IF(AND(G11="",F11=""),"Idea",IF(H11="","To wrap",IF(H11<TODAY(),"Late","On the way")))))) | M11: =IF(AND(B11="",C11=""),"",IF(OR(F11<>"",G11<>"",I11<>"",J11<>""),1,0)) | N11: =IF(M11="","",IF(M11=1,IF(F11<>"",N(F11),N(E11)),0)) | O11: =IF(M11="","",IF(M11=1,0,N(E11))) | P11: =IF(OR(K11="On the way",K11="Late"),H11+ROW()/10000000,"")
B12: Grandma | C12: Warm slippers | D12: Department store | E12: 25 | K12: =IF(AND(B12="",C12=""),"",IF(J12<>"","Wrapped",IF(I12<>"","To wrap",IF(AND(G12="",F12=""),"Idea",IF(H12="","To wrap",IF(H12<TODAY(),"Late","On the way")))))) | M12: =IF(AND(B12="",C12=""),"",IF(OR(F12<>"",G12<>"",I12<>"",J12<>""),1,0)) | N12: =IF(M12="","",IF(M12=1,IF(F12<>"",N(F12),N(E12)),0)) | O12: =IF(M12="","",IF(M12=1,0,N(E12))) | P12: =IF(OR(K12="On the way",K12="Late"),H12+ROW()/10000000,"")
B13: Sam | C13: Board game | D13: Toy shop | E13: 45 | F13: 42 | G13: x | I13: x | J13: x | K13: =IF(AND(B13="",C13=""),"",IF(J13<>"","Wrapped",IF(I13<>"","To wrap",IF(AND(G13="",F13=""),"Idea",IF(H13="","To wrap",IF(H13<TODAY(),"Late","On the way")))))) | M13: =IF(AND(B13="",C13=""),"",IF(OR(F13<>"",G13<>"",I13<>"",J13<>""),1,0)) | N13: =IF(M13="","",IF(M13=1,IF(F13<>"",N(F13),N(E13)),0)) | O13: =IF(M13="","",IF(M13=1,0,N(E13))) | P13: =IF(OR(K13="On the way",K13="Late"),H13+ROW()/10000000,"")
B14: Sam | C14: Beanie hat | E14: 20 | K14: =IF(AND(B14="",C14=""),"",IF(J14<>"","Wrapped",IF(I14<>"","To wrap",IF(AND(G14="",F14=""),"Idea",IF(H14="","To wrap",IF(H14<TODAY(),"Late","On the way")))))) | M14: =IF(AND(B14="",C14=""),"",IF(OR(F14<>"",G14<>"",I14<>"",J14<>""),1,0)) | N14: =IF(M14="","",IF(M14=1,IF(F14<>"",N(F14),N(E14)),0)) | O14: =IF(M14="","",IF(M14=1,0,N(E14))) | P14: =IF(OR(K14="On the way",K14="Late"),H14+ROW()/10000000,"")
B15: Lily | C15: Art set | D15: Craft shop | E15: 35 | F15: 35 | G15: x | J15: x | K15: =IF(AND(B15="",C15=""),"",IF(J15<>"","Wrapped",IF(I15<>"","To wrap",IF(AND(G15="",F15=""),"Idea",IF(H15="","To wrap",IF(H15<TODAY(),"Late","On the way")))))) | M15: =IF(AND(B15="",C15=""),"",IF(OR(F15<>"",G15<>"",I15<>"",J15<>""),1,0)) | N15: =IF(M15="","",IF(M15=1,IF(F15<>"",N(F15),N(E15)),0)) | O15: =IF(M15="","",IF(M15=1,0,N(E15))) | P15: =IF(OR(K15="On the way",K15="Late"),H15+ROW()/10000000,"")
B16: Lily | C16: Storybook | D16: Local bookshop | E16: 15 | F16: 15 | G16: x | K16: =IF(AND(B16="",C16=""),"",IF(J16<>"","Wrapped",IF(I16<>"","To wrap",IF(AND(G16="",F16=""),"Idea",IF(H16="","To wrap",IF(H16<TODAY(),"Late","On the way")))))) | M16: =IF(AND(B16="",C16=""),"",IF(OR(F16<>"",G16<>"",I16<>"",J16<>""),1,0)) | N16: =IF(M16="","",IF(M16=1,IF(F16<>"",N(F16),N(E16)),0)) | O16: =IF(M16="","",IF(M16=1,0,N(E16))) | P16: =IF(OR(K16="On the way",K16="Late"),H16+ROW()/10000000,"")
B17: Lily | C17: Pyjamas | E17: 20 | K17: =IF(AND(B17="",C17=""),"",IF(J17<>"","Wrapped",IF(I17<>"","To wrap",IF(AND(G17="",F17=""),"Idea",IF(H17="","To wrap",IF(H17<TODAY(),"Late","On the way")))))) | M17: =IF(AND(B17="",C17=""),"",IF(OR(F17<>"",G17<>"",I17<>"",J17<>""),1,0)) | N17: =IF(M17="","",IF(M17=1,IF(F17<>"",N(F17),N(E17)),0)) | O17: =IF(M17="","",IF(M17=1,0,N(E17))) | P17: =IF(OR(K17="On the way",K17="Late"),H17+ROW()/10000000,"")
B18: Noah | C18: Building blocks | D18: Toy shop | E18: 55 | F18: 49 | G18: x | H18: 46305 | K18: =IF(AND(B18="",C18=""),"",IF(J18<>"","Wrapped",IF(I18<>"","To wrap",IF(AND(G18="",F18=""),"Idea",IF(H18="","To wrap",IF(H18<TODAY(),"Late","On the way")))))) | M18: =IF(AND(B18="",C18=""),"",IF(OR(F18<>"",G18<>"",I18<>"",J18<>""),1,0)) | N18: =IF(M18="","",IF(M18=1,IF(F18<>"",N(F18),N(E18)),0)) | O18: =IF(M18="","",IF(M18=1,0,N(E18))) | P18: =IF(OR(K18="On the way",K18="Late"),H18+ROW()/10000000,"")
B19: Noah | C19: Football | D19: Sports shop | E19: 15 | K19: =IF(AND(B19="",C19=""),"",IF(J19<>"","Wrapped",IF(I19<>"","To wrap",IF(AND(G19="",F19=""),"Idea",IF(H19="","To wrap",IF(H19<TODAY(),"Late","On the way")))))) | M19: =IF(AND(B19="",C19=""),"",IF(OR(F19<>"",G19<>"",I19<>"",J19<>""),1,0)) | N19: =IF(M19="","",IF(M19=1,IF(F19<>"",N(F19),N(E19)),0)) | O19: =IF(M19="","",IF(M19=1,0,N(E19))) | P19: =IF(OR(K19="On the way",K19="Late"),H19+ROW()/10000000,"")
B20: Aunt Rose | C20: Scented candle | D20: Craft market | E20: 22 | F20: 22 | G20: x | K20: =IF(AND(B20="",C20=""),"",IF(J20<>"","Wrapped",IF(I20<>"","To wrap",IF(AND(G20="",F20=""),"Idea",IF(H20="","To wrap",IF(H20<TODAY(),"Late","On the way")))))) | M20: =IF(AND(B20="",C20=""),"",IF(OR(F20<>"",G20<>"",I20<>"",J20<>""),1,0)) | N20: =IF(M20="","",IF(M20=1,IF(F20<>"",N(F20),N(E20)),0)) | O20: =IF(M20="","",IF(M20=1,0,N(E20))) | P20: =IF(OR(K20="On the way",K20="Late"),H20+ROW()/10000000,"")
B21: Priya | C21: Plant and pot | D21: Garden centre | E21: 30 | K21: =IF(AND(B21="",C21=""),"",IF(J21<>"","Wrapped",IF(I21<>"","To wrap",IF(AND(G21="",F21=""),"Idea",IF(H21="","To wrap",IF(H21<TODAY(),"Late","On the way")))))) | M21: =IF(AND(B21="",C21=""),"",IF(OR(F21<>"",G21<>"",I21<>"",J21<>""),1,0)) | N21: =IF(M21="","",IF(M21=1,IF(F21<>"",N(F21),N(E21)),0)) | O21: =IF(M21="","",IF(M21=1,0,N(E21))) | P21: =IF(OR(K21="On the way",K21="Late"),H21+ROW()/10000000,"")
B22: Tom | C22: Hot sauce set | D22: Online | E22: 28 | F22: 26 | G22: x | H22: 46296 | K22: =IF(AND(B22="",C22=""),"",IF(J22<>"","Wrapped",IF(I22<>"","To wrap",IF(AND(G22="",F22=""),"Idea",IF(H22="","To wrap",IF(H22<TODAY(),"Late","On the way")))))) | M22: =IF(AND(B22="",C22=""),"",IF(OR(F22<>"",G22<>"",I22<>"",J22<>""),1,0)) | N22: =IF(M22="","",IF(M22=1,IF(F22<>"",N(F22),N(E22)),0)) | O22: =IF(M22="","",IF(M22=1,0,N(E22))) | P22: =IF(OR(K22="On the way",K22="Late"),H22+ROW()/10000000,"")
B23: Secret Santa | C23: Mug and cocoa | E23: 15 | K23: =IF(AND(B23="",C23=""),"",IF(J23<>"","Wrapped",IF(I23<>"","To wrap",IF(AND(G23="",F23=""),"Idea",IF(H23="","To wrap",IF(H23<TODAY(),"Late","On the way")))))) | M23: =IF(AND(B23="",C23=""),"",IF(OR(F23<>"",G23<>"",I23<>"",J23<>""),1,0)) | N23: =IF(M23="","",IF(M23=1,IF(F23<>"",N(F23),N(E23)),0)) | O23: =IF(M23="","",IF(M23=1,0,N(E23))) | P23: =IF(OR(K23="On the way",K23="Late"),H23+ROW()/10000000,"")
B24: Lily's teacher | C24: Card and chocolates | E24: 12 | K24: =IF(AND(B24="",C24=""),"",IF(J24<>"","Wrapped",IF(I24<>"","To wrap",IF(AND(G24="",F24=""),"Idea",IF(H24="","To wrap",IF(H24<TODAY(),"Late","On the way")))))) | M24: =IF(AND(B24="",C24=""),"",IF(OR(F24<>"",G24<>"",I24<>"",J24<>""),1,0)) | N24: =IF(M24="","",IF(M24=1,IF(F24<>"",N(F24),N(E24)),0)) | O24: =IF(M24="","",IF(M24=1,0,N(E24))) | P24: =IF(OR(K24="On the way",K24="Late"),H24+ROW()/10000000,"")
B25: Neighbours | C25: Mince pies | D25: Bakery | E25: 10 | K25: =IF(AND(B25="",C25=""),"",IF(J25<>"","Wrapped",IF(I25<>"","To wrap",IF(AND(G25="",F25=""),"Idea",IF(H25="","To wrap",IF(H25<TODAY(),"Late","On the way")))))) | M25: =IF(AND(B25="",C25=""),"",IF(OR(F25<>"",G25<>"",I25<>"",J25<>""),1,0)) | N25: =IF(M25="","",IF(M25=1,IF(F25<>"",N(F25),N(E25)),0)) | O25: =IF(M25="","",IF(M25=1,0,N(E25))) | P25: =IF(OR(K25="On the way",K25="Late"),H25+ROW()/10000000,"")
K26: =IF(AND(B26="",C26=""),"",IF(J26<>"","Wrapped",IF(I26<>"","To wrap",IF(AND(G26="",F26=""),"Idea",IF(H26="","To wrap",IF(H26<TODAY(),"Late","On the way")))))) | M26: =IF(AND(B26="",C26=""),"",IF(OR(F26<>"",G26<>"",I26<>"",J26<>""),1,0)) | N26: =IF(M26="","",IF(M26=1,IF(F26<>"",N(F26),N(E26)),0)) | O26: =IF(M26="","",IF(M26=1,0,N(E26))) | P26: =IF(OR(K26="On the way",K26="Late"),H26+ROW()/10000000,"")
K27: =IF(AND(B27="",C27=""),"",IF(J27<>"","Wrapped",IF(I27<>"","To wrap",IF(AND(G27="",F27=""),"Idea",IF(H27="","To wrap",IF(H27<TODAY(),"Late","On the way")))))) | M27: =IF(AND(B27="",C27=""),"",IF(OR(F27<>"",G27<>"",I27<>"",J27<>""),1,0)) | N27: =IF(M27="","",IF(M27=1,IF(F27<>"",N(F27),N(E27)),0)) | O27: =IF(M27="","",IF(M27=1,0,N(E27))) | P27: =IF(OR(K27="On the way",K27="Late"),H27+ROW()/10000000,"")
K28: =IF(AND(B28="",C28=""),"",IF(J28<>"","Wrapped",IF(I28<>"","To wrap",IF(AND(G28="",F28=""),"Idea",IF(H28="","To wrap",IF(H28<TODAY(),"Late","On the way")))))) | M28: =IF(AND(B28="",C28=""),"",IF(OR(F28<>"",G28<>"",I28<>"",J28<>""),1,0)) | N28: =IF(M28="","",IF(M28=1,IF(F28<>"",N(F28),N(E28)),0)) | O28: =IF(M28="","",IF(M28=1,0,N(E28))) | P28: =IF(OR(K28="On the way",K28="Late"),H28+ROW()/10000000,"")
K29: =IF(AND(B29="",C29=""),"",IF(J29<>"","Wrapped",IF(I29<>"","To wrap",IF(AND(G29="",F29=""),"Idea",IF(H29="","To wrap",IF(H29<TODAY(),"Late","On the way")))))) | M29: =IF(AND(B29="",C29=""),"",IF(OR(F29<>"",G29<>"",I29<>"",J29<>""),1,0)) | N29: =IF(M29="","",IF(M29=1,IF(F29<>"",N(F29),N(E29)),0)) | O29: =IF(M29="","",IF(M29=1,0,N(E29))) | P29: =IF(OR(K29="On the way",K29="Late"),H29+ROW()/10000000,"")
K30: =IF(AND(B30="",C30=""),"",IF(J30<>"","Wrapped",IF(I30<>"","To wrap",IF(AND(G30="",F30=""),"Idea",IF(H30="","To wrap",IF(H30<TODAY(),"Late","On the way")))))) | M30: =IF(AND(B30="",C30=""),"",IF(OR(F30<>"",G30<>"",I30<>"",J30<>""),1,0)) | N30: =IF(M30="","",IF(M30=1,IF(F30<>"",N(F30),N(E30)),0)) | O30: =IF(M30="","",IF(M30=1,0,N(E30))) | P30: =IF(OR(K30="On the way",K30="Late"),H30+ROW()/10000000,"")
K31: =IF(AND(B31="",C31=""),"",IF(J31<>"","Wrapped",IF(I31<>"","To wrap",IF(AND(G31="",F31=""),"Idea",IF(H31="","To wrap",IF(H31<TODAY(),"Late","On the way")))))) | M31: =IF(AND(B31="",C31=""),"",IF(OR(F31<>"",G31<>"",I31<>"",J31<>""),1,0)) | N31: =IF(M31="","",IF(M31=1,IF(F31<>"",N(F31),N(E31)),0)) | O31: =IF(M31="","",IF(M31=1,0,N(E31))) | P31: =IF(OR(K31="On the way",K31="Late"),H31+ROW()/10000000,"")
K32: =IF(AND(B32="",C32=""),"",IF(J32<>"","Wrapped",IF(I32<>"","To wrap",IF(AND(G32="",F32=""),"Idea",IF(H32="","To wrap",IF(H32<TODAY(),"Late","On the way")))))) | M32: =IF(AND(B32="",C32=""),"",IF(OR(F32<>"",G32<>"",I32<>"",J32<>""),1,0)) | N32: =IF(M32="","",IF(M32=1,IF(F32<>"",N(F32),N(E32)),0)) | O32: =IF(M32="","",IF(M32=1,0,N(E32))) | P32: =IF(OR(K32="On the way",K32="Late"),H32+ROW()/10000000,"")
K33: =IF(AND(B33="",C33=""),"",IF(J33<>"","Wrapped",IF(I33<>"","To wrap",IF(AND(G33="",F33=""),"Idea",IF(H33="","To wrap",IF(H33<TODAY(),"Late","On the way")))))) | M33: =IF(AND(B33="",C33=""),"",IF(OR(F33<>"",G33<>"",I33<>"",J33<>""),1,0)) | N33: =IF(M33="","",IF(M33=1,IF(F33<>"",N(F33),N(E33)),0)) | O33: =IF(M33="","",IF(M33=1,0,N(E33))) | P33: =IF(OR(K33="On the way",K33="Late"),H33+ROW()/10000000,"")
K34: =IF(AND(B34="",C34=""),"",IF(J34<>"","Wrapped",IF(I34<>"","To wrap",IF(AND(G34="",F34=""),"Idea",IF(H34="","To wrap",IF(H34<TODAY(),"Late","On the way")))))) | M34: =IF(AND(B34="",C34=""),"",IF(OR(F34<>"",G34<>"",I34<>"",J34<>""),1,0)) | N34: =IF(M34="","",IF(M34=1,IF(F34<>"",N(F34),N(E34)),0)) | O34: =IF(M34="","",IF(M34=1,0,N(E34))) | P34: =IF(OR(K34="On the way",K34="Late"),H34+ROW()/10000000,"")
K35: =IF(AND(B35="",C35=""),"",IF(J35<>"","Wrapped",IF(I35<>"","To wrap",IF(AND(G35="",F35=""),"Idea",IF(H35="","To wrap",IF(H35<TODAY(),"Late","On the way")))))) | M35: =IF(AND(B35="",C35=""),"",IF(OR(F35<>"",G35<>"",I35<>"",J35<>""),1,0)) | N35: =IF(M35="","",IF(M35=1,IF(F35<>"",N(F35),N(E35)),0)) | O35: =IF(M35="","",IF(M35=1,0,N(E35))) | P35: =IF(OR(K35="On the way",K35="Late"),H35+ROW()/10000000,"")
K36: =IF(AND(B36="",C36=""),"",IF(J36<>"","Wrapped",IF(I36<>"","To wrap",IF(AND(G36="",F36=""),"Idea",IF(H36="","To wrap",IF(H36<TODAY(),"Late","On the way")))))) | M36: =IF(AND(B36="",C36=""),"",IF(OR(F36<>"",G36<>"",I36<>"",J36<>""),1,0)) | N36: =IF(M36="","",IF(M36=1,IF(F36<>"",N(F36),N(E36)),0)) | O36: =IF(M36="","",IF(M36=1,0,N(E36))) | P36: =IF(OR(K36="On the way",K36="Late"),H36+ROW()/10000000,"")
K37: =IF(AND(B37="",C37=""),"",IF(J37<>"","Wrapped",IF(I37<>"","To wrap",IF(AND(G37="",F37=""),"Idea",IF(H37="","To wrap",IF(H37<TODAY(),"Late","On the way")))))) | M37: =IF(AND(B37="",C37=""),"",IF(OR(F37<>"",G37<>"",I37<>"",J37<>""),1,0)) | N37: =IF(M37="","",IF(M37=1,IF(F37<>"",N(F37),N(E37)),0)) | O37: =IF(M37="","",IF(M37=1,0,N(E37))) | P37: =IF(OR(K37="On the way",K37="Late"),H37+ROW()/10000000,"")
... K305: =IF(AND(B305="",C305=""),"",IF(J305<>"","Wrapped",IF(I305<>"","To wrap",IF(AND(G305="",F305=""),"Idea",IF(H305="","To wrap",IF(H305<TODAY(),"Late","On the way")))))) | M305: =IF(AND(B305="",C305=""),"",IF(OR(F305<>"",G305<>"",I305<>"",J305<>""),1,0)) | N305: =IF(M305="","",IF(M305=1,IF(F305<>"",N(F305),N(E305)),0)) | O305: =IF(M305="","",IF(M305=1,0,N(E305))) | P305: =IF(OR(K305="On the way",K305="Late"),H305+ROW()/10000000,"")

Sheet People
B2: People
B3: Everyone you buy for, with a budget each. The rest comes from the Gifts tab.
B5: Name | C5: Group | D5: Budget | E5: Gifts | F5: Bought | G5: Spent | H5: To pay | I5: Left | J5: Status
B6: Mum | C6: Family | D6: 120 | E6: =IF(B6="","",COUNTIFS(Gifts!$B$6:$B$305,B6)) | F6: =IF(B6="","",SUMIFS(Gifts!$M$6:$M$305,Gifts!$B$6:$B$305,B6)) | G6: =IF(B6="","",SUMIFS(Gifts!$N$6:$N$305,Gifts!$B$6:$B$305,B6)) | H6: =IF(B6="","",SUMIFS(Gifts!$O$6:$O$305,Gifts!$B$6:$B$305,B6)) | I6: =IF(OR(B6="",D6=""),"",D6-G6-H6) | J6: =IF(B6="","",IF(E6=0,"No gift yet",IF(F6<E6,(E6-F6)&" to buy",IF(COUNTIFS(Gifts!$B$6:$B$305,B6,Gifts!$K$6:$K$305,"Wrapped")=E6,"All wrapped","All bought")))) | L6: =IF(B6="","",IF(OR(J6="All bought",J6="All wrapped"),"",ROW()))
B7: Dad | C7: Family | D7: 100 | E7: =IF(B7="","",COUNTIFS(Gifts!$B$6:$B$305,B7)) | F7: =IF(B7="","",SUMIFS(Gifts!$M$6:$M$305,Gifts!$B$6:$B$305,B7)) | G7: =IF(B7="","",SUMIFS(Gifts!$N$6:$N$305,Gifts!$B$6:$B$305,B7)) | H7: =IF(B7="","",SUMIFS(Gifts!$O$6:$O$305,Gifts!$B$6:$B$305,B7)) | I7: =IF(OR(B7="",D7=""),"",D7-G7-H7) | J7: =IF(B7="","",IF(E7=0,"No gift yet",IF(F7<E7,(E7-F7)&" to buy",IF(COUNTIFS(Gifts!$B$6:$B$305,B7,Gifts!$K$6:$K$305,"Wrapped")=E7,"All wrapped","All bought")))) | L7: =IF(B7="","",IF(OR(J7="All bought",J7="All wrapped"),"",ROW()))
B8: Grandma | C8: Family | D8: 60 | E8: =IF(B8="","",COUNTIFS(Gifts!$B$6:$B$305,B8)) | F8: =IF(B8="","",SUMIFS(Gifts!$M$6:$M$305,Gifts!$B$6:$B$305,B8)) | G8: =IF(B8="","",SUMIFS(Gifts!$N$6:$N$305,Gifts!$B$6:$B$305,B8)) | H8: =IF(B8="","",SUMIFS(Gifts!$O$6:$O$305,Gifts!$B$6:$B$305,B8)) | I8: =IF(OR(B8="",D8=""),"",D8-G8-H8) | J8: =IF(B8="","",IF(E8=0,"No gift yet",IF(F8<E8,(E8-F8)&" to buy",IF(COUNTIFS(Gifts!$B$6:$B$305,B8,Gifts!$K$6:$K$305,"Wrapped")=E8,"All wrapped","All bought")))) | L8: =IF(B8="","",IF(OR(J8="All bought",J8="All wrapped"),"",ROW()))
B9: Sam | C9: Family | D9: 80 | E9: =IF(B9="","",COUNTIFS(Gifts!$B$6:$B$305,B9)) | F9: =IF(B9="","",SUMIFS(Gifts!$M$6:$M$305,Gifts!$B$6:$B$305,B9)) | G9: =IF(B9="","",SUMIFS(Gifts!$N$6:$N$305,Gifts!$B$6:$B$305,B9)) | H9: =IF(B9="","",SUMIFS(Gifts!$O$6:$O$305,Gifts!$B$6:$B$305,B9)) | I9: =IF(OR(B9="",D9=""),"",D9-G9-H9) | J9: =IF(B9="","",IF(E9=0,"No gift yet",IF(F9<E9,(E9-F9)&" to buy",IF(COUNTIFS(Gifts!$B$6:$B$305,B9,Gifts!$K$6:$K$305,"Wrapped")=E9,"All wrapped","All bought")))) | L9: =IF(B9="","",IF(OR(J9="All bought",J9="All wrapped"),"",ROW()))
B10: Lily | C10: Kids | D10: 70 | E10: =IF(B10="","",COUNTIFS(Gifts!$B$6:$B$305,B10)) | F10: =IF(B10="","",SUMIFS(Gifts!$M$6:$M$305,Gifts!$B$6:$B$305,B10)) | G10: =IF(B10="","",SUMIFS(Gifts!$N$6:$N$305,Gifts!$B$6:$B$305,B10)) | H10: =IF(B10="","",SUMIFS(Gifts!$O$6:$O$305,Gifts!$B$6:$B$305,B10)) | I10: =IF(OR(B10="",D10=""),"",D10-G10-H10) | J10: =IF(B10="","",IF(E10=0,"No gift yet",IF(F10<E10,(E10-F10)&" to buy",IF(COUNTIFS(Gifts!$B$6:$B$305,B10,Gifts!$K$6:$K$305,"Wrapped")=E10,"All wrapped","All bought")))) | L10: =IF(B10="","",IF(OR(J10="All bought",J10="All wrapped"),"",ROW()))
B11: Noah | C11: Kids | D11: 70 | E11: =IF(B11="","",COUNTIFS(Gifts!$B$6:$B$305,B11)) | F11: =IF(B11="","",SUMIFS(Gifts!$M$6:$M$305,Gifts!$B$6:$B$305,B11)) | G11: =IF(B11="","",SUMIFS(Gifts!$N$6:$N$305,Gifts!$B$6:$B$305,B11)) | H11: =IF(B11="","",SUMIFS(Gifts!$O$6:$O$305,Gifts!$B$6:$B$305,B11)) | I11: =IF(OR(B11="",D11=""),"",D11-G11-H11) | J11: =IF(B11="","",IF(E11=0,"No gift yet",IF(F11<E11,(E11-F11)&" to buy",IF(COUNTIFS(Gifts!$B$6:$B$305,B11,Gifts!$K$6:$K$305,"Wrapped")=E11,"All wrapped","All bought")))) | L11: =IF(B11="","",IF(OR(J11="All bought",J11="All wrapped"),"",ROW()))
B12: Aunt Rose | C12: Family | D12: 40 | E12: =IF(B12="","",COUNTIFS(Gifts!$B$6:$B$305,B12)) | F12: =IF(B12="","",SUMIFS(Gifts!$M$6:$M$305,Gifts!$B$6:$B$305,B12)) | G12: =IF(B12="","",SUMIFS(Gifts!$N$6:$N$305,Gifts!$B$6:$B$305,B12)) | H12: =IF(B12="","",SUMIFS(Gifts!$O$6:$O$305,Gifts!$B$6:$B$305,B12)) | I12: =IF(OR(B12="",D12=""),"",D12-G12-H12) | J12: =IF(B12="","",IF(E12=0,"No gift yet",IF(F12<E12,(E12-F12)&" to buy",IF(COUNTIFS(Gifts!$B$6:$B$305,B12,Gifts!$K$6:$K$305,"Wrapped")=E12,"All wrapped","All bought")))) | L12: =IF(B12="","",IF(OR(J12="All bought",J12="All wrapped"),"",ROW()))
B13: Priya | C13: Friends | D13: 40 | E13: =IF(B13="","",COUNTIFS(Gifts!$B$6:$B$305,B13)) | F13: =IF(B13="","",SUMIFS(Gifts!$M$6:$M$305,Gifts!$B$6:$B$305,B13)) | G13: =IF(B13="","",SUMIFS(Gifts!$N$6:$N$305,Gifts!$B$6:$B$305,B13)) | H13: =IF(B13="","",SUMIFS(Gifts!$O$6:$O$305,Gifts!$B$6:$B$305,B13)) | I13: =IF(OR(B13="",D13=""),"",D13-G13-H13) | J13: =IF(B13="","",IF(E13=0,"No gift yet",IF(F13<E13,(E13-F13)&" to buy",IF(COUNTIFS(Gifts!$B$6:$B$305,B13,Gifts!$K$6:$K$305,"Wrapped")=E13,"All wrapped","All bought")))) | L13: =IF(B13="","",IF(OR(J13="All bought",J13="All wrapped"),"",ROW()))
B14: Tom | C14: Friends | D14: 40 | E14: =IF(B14="","",COUNTIFS(Gifts!$B$6:$B$305,B14)) | F14: =IF(B14="","",SUMIFS(Gifts!$M$6:$M$305,Gifts!$B$6:$B$305,B14)) | G14: =IF(B14="","",SUMIFS(Gifts!$N$6:$N$305,Gifts!$B$6:$B$305,B14)) | H14: =IF(B14="","",SUMIFS(Gifts!$O$6:$O$305,Gifts!$B$6:$B$305,B14)) | I14: =IF(OR(B14="",D14=""),"",D14-G14-H14) | J14: =IF(B14="","",IF(E14=0,"No gift yet",IF(F14<E14,(E14-F14)&" to buy",IF(COUNTIFS(Gifts!$B$6:$B$305,B14,Gifts!$K$6:$K$305,"Wrapped")=E14,"All wrapped","All bought")))) | L14: =IF(B14="","",IF(OR(J14="All bought",J14="All wrapped"),"",ROW()))
B15: Secret Santa | C15: Work | D15: 25 | E15: =IF(B15="","",COUNTIFS(Gifts!$B$6:$B$305,B15)) | F15: =IF(B15="","",SUMIFS(Gifts!$M$6:$M$305,Gifts!$B$6:$B$305,B15)) | G15: =IF(B15="","",SUMIFS(Gifts!$N$6:$N$305,Gifts!$B$6:$B$305,B15)) | H15: =IF(B15="","",SUMIFS(Gifts!$O$6:$O$305,Gifts!$B$6:$B$305,B15)) | I15: =IF(OR(B15="",D15=""),"",D15-G15-H15) | J15: =IF(B15="","",IF(E15=0,"No gift yet",IF(F15<E15,(E15-F15)&" to buy",IF(COUNTIFS(Gifts!$B$6:$B$305,B15,Gifts!$K$6:$K$305,"Wrapped")=E15,"All wrapped","All bought")))) | L15: =IF(B15="","",IF(OR(J15="All bought",J15="All wrapped"),"",ROW()))
B16: Lily's teacher | C16: Kids | D16: 15 | E16: =IF(B16="","",COUNTIFS(Gifts!$B$6:$B$305,B16)) | F16: =IF(B16="","",SUMIFS(Gifts!$M$6:$M$305,Gifts!$B$6:$B$305,B16)) | G16: =IF(B16="","",SUMIFS(Gifts!$N$6:$N$305,Gifts!$B$6:$B$305,B16)) | H16: =IF(B16="","",SUMIFS(Gifts!$O$6:$O$305,Gifts!$B$6:$B$305,B16)) | I16: =IF(OR(B16="",D16=""),"",D16-G16-H16) | J16: =IF(B16="","",IF(E16=0,"No gift yet",IF(F16<E16,(E16-F16)&" to buy",IF(COUNTIFS(Gifts!$B$6:$B$305,B16,Gifts!$K$6:$K$305,"Wrapped")=E16,"All wrapped","All bought")))) | L16: =IF(B16="","",IF(OR(J16="All bought",J16="All wrapped"),"",ROW()))
B17: Neighbours | C17: Neighbours | D17: 20 | E17: =IF(B17="","",COUNTIFS(Gifts!$B$6:$B$305,B17)) | F17: =IF(B17="","",SUMIFS(Gifts!$M$6:$M$305,Gifts!$B$6:$B$305,B17)) | G17: =IF(B17="","",SUMIFS(Gifts!$N$6:$N$305,Gifts!$B$6:$B$305,B17)) | H17: =IF(B17="","",SUMIFS(Gifts!$O$6:$O$305,Gifts!$B$6:$B$305,B17)) | I17: =IF(OR(B17="",D17=""),"",D17-G17-H17) | J17: =IF(B17="","",IF(E17=0,"No gift yet",IF(F17<E17,(E17-F17)&" to buy",IF(COUNTIFS(Gifts!$B$6:$B$305,B17,Gifts!$K$6:$K$305,"Wrapped")=E17,"All wrapped","All bought")))) | L17: =IF(B17="","",IF(OR(J17="All bought",J17="All wrapped"),"",ROW()))
B18: Mia | C18: Friends | D18: 30 | E18: =IF(B18="","",COUNTIFS(Gifts!$B$6:$B$305,B18)) | F18: =IF(B18="","",SUMIFS(Gifts!$M$6:$M$305,Gifts!$B$6:$B$305,B18)) | G18: =IF(B18="","",SUMIFS(Gifts!$N$6:$N$305,Gifts!$B$6:$B$305,B18)) | H18: =IF(B18="","",SUMIFS(Gifts!$O$6:$O$305,Gifts!$B$6:$B$305,B18)) | I18: =IF(OR(B18="",D18=""),"",D18-G18-H18) | J18: =IF(B18="","",IF(E18=0,"No gift yet",IF(F18<E18,(E18-F18)&" to buy",IF(COUNTIFS(Gifts!$B$6:$B$305,B18,Gifts!$K$6:$K$305,"Wrapped")=E18,"All wrapped","All bought")))) | L18: =IF(B18="","",IF(OR(J18="All bought",J18="All wrapped"),"",ROW()))
E19: =IF(B19="","",COUNTIFS(Gifts!$B$6:$B$305,B19)) | F19: =IF(B19="","",SUMIFS(Gifts!$M$6:$M$305,Gifts!$B$6:$B$305,B19)) | G19: =IF(B19="","",SUMIFS(Gifts!$N$6:$N$305,Gifts!$B$6:$B$305,B19)) | H19: =IF(B19="","",SUMIFS(Gifts!$O$6:$O$305,Gifts!$B$6:$B$305,B19)) | I19: =IF(OR(B19="",D19=""),"",D19-G19-H19) | J19: =IF(B19="","",IF(E19=0,"No gift yet",IF(F19<E19,(E19-F19)&" to buy",IF(COUNTIFS(Gifts!$B$6:$B$305,B19,Gifts!$K$6:$K$305,"Wrapped")=E19,"All wrapped","All bought")))) | L19: =IF(B19="","",IF(OR(J19="All bought",J19="All wrapped"),"",ROW()))
E20: =IF(B20="","",COUNTIFS(Gifts!$B$6:$B$305,B20)) | F20: =IF(B20="","",SUMIFS(Gifts!$M$6:$M$305,Gifts!$B$6:$B$305,B20)) | G20: =IF(B20="","",SUMIFS(Gifts!$N$6:$N$305,Gifts!$B$6:$B$305,B20)) | H20: =IF(B20="","",SUMIFS(Gifts!$O$6:$O$305,Gifts!$B$6:$B$305,B20)) | I20: =IF(OR(B20="",D20=""),"",D20-G20-H20) | J20: =IF(B20="","",IF(E20=0,"No gift yet",IF(F20<E20,(E20-F20)&" to buy",IF(COUNTIFS(Gifts!$B$6:$B$305,B20,Gifts!$K$6:$K$305,"Wrapped")=E20,"All wrapped","All bought")))) | L20: =IF(B20="","",IF(OR(J20="All bought",J20="All wrapped"),"",ROW()))
E21: =IF(B21="","",COUNTIFS(Gifts!$B$6:$B$305,B21)) | F21: =IF(B21="","",SUMIFS(Gifts!$M$6:$M$305,Gifts!$B$6:$B$305,B21)) | G21: =IF(B21="","",SUMIFS(Gifts!$N$6:$N$305,Gifts!$B$6:$B$305,B21)) | H21: =IF(B21="","",SUMIFS(Gifts!$O$6:$O$305,Gifts!$B$6:$B$305,B21)) | I21: =IF(OR(B21="",D21=""),"",D21-G21-H21) | J21: =IF(B21="","",IF(E21=0,"No gift yet",IF(F21<E21,(E21-F21)&" to buy",IF(COUNTIFS(Gifts!$B$6:$B$305,B21,Gifts!$K$6:$K$305,"Wrapped")=E21,"All wrapped","All bought")))) | L21: =IF(B21="","",IF(OR(J21="All bought",J21="All wrapped"),"",ROW()))
E22: =IF(B22="","",COUNTIFS(Gifts!$B$6:$B$305,B22)) | F22: =IF(B22="","",SUMIFS(Gifts!$M$6:$M$305,Gifts!$B$6:$B$305,B22)) | G22: =IF(B22="","",SUMIFS(Gifts!$N$6:$N$305,Gifts!$B$6:$B$305,B22)) | H22: =IF(B22="","",SUMIFS(Gifts!$O$6:$O$305,Gifts!$B$6:$B$305,B22)) | I22: =IF(OR(B22="",D22=""),"",D22-G22-H22) | J22: =IF(B22="","",IF(E22=0,"No gift yet",IF(F22<E22,(E22-F22)&" to buy",IF(COUNTIFS(Gifts!$B$6:$B$305,B22,Gifts!$K$6:$K$305,"Wrapped")=E22,"All wrapped","All bought")))) | L22: =IF(B22="","",IF(OR(J22="All bought",J22="All wrapped"),"",ROW()))
E23: =IF(B23="","",COUNTIFS(Gifts!$B$6:$B$305,B23)) | F23: =IF(B23="","",SUMIFS(Gifts!$M$6:$M$305,Gifts!$B$6:$B$305,B23)) | G23: =IF(B23="","",SUMIFS(Gifts!$N$6:$N$305,Gifts!$B$6:$B$305,B23)) | H23: =IF(B23="","",SUMIFS(Gifts!$O$6:$O$305,Gifts!$B$6:$B$305,B23)) | I23: =IF(OR(B23="",D23=""),"",D23-G23-H23) | J23: =IF(B23="","",IF(E23=0,"No gift yet",IF(F23<E23,(E23-F23)&" to buy",IF(COUNTIFS(Gifts!$B$6:$B$305,B23,Gifts!$K$6:$K$305,"Wrapped")=E23,"All wrapped","All bought")))) | L23: =IF(B23="","",IF(OR(J23="All bought",J23="All wrapped"),"",ROW()))
E24: =IF(B24="","",COUNTIFS(Gifts!$B$6:$B$305,B24)) | F24: =IF(B24="","",SUMIFS(Gifts!$M$6:$M$305,Gifts!$B$6:$B$305,B24)) | G24: =IF(B24="","",SUMIFS(Gifts!$N$6:$N$305,Gifts!$B$6:$B$305,B24)) | H24: =IF(B24="","",SUMIFS(Gifts!$O$6:$O$305,Gifts!$B$6:$B$305,B24)) | I24: =IF(OR(B24="",D24=""),"",D24-G24-H24) | J24: =IF(B24="","",IF(E24=0,"No gift yet",IF(F24<E24,(E24-F24)&" to buy",IF(COUNTIFS(Gifts!$B$6:$B$305,B24,Gifts!$K$6:$K$305,"Wrapped")=E24,"All wrapped","All bought")))) | L24: =IF(B24="","",IF(OR(J24="All bought",J24="All wrapped"),"",ROW()))
E25: =IF(B25="","",COUNTIFS(Gifts!$B$6:$B$305,B25)) | F25: =IF(B25="","",SUMIFS(Gifts!$M$6:$M$305,Gifts!$B$6:$B$305,B25)) | G25: =IF(B25="","",SUMIFS(Gifts!$N$6:$N$305,Gifts!$B$6:$B$305,B25)) | H25: =IF(B25="","",SUMIFS(Gifts!$O$6:$O$305,Gifts!$B$6:$B$305,B25)) | I25: =IF(OR(B25="",D25=""),"",D25-G25-H25) | J25: =IF(B25="","",IF(E25=0,"No gift yet",IF(F25<E25,(E25-F25)&" to buy",IF(COUNTIFS(Gifts!$B$6:$B$305,B25,Gifts!$K$6:$K$305,"Wrapped")=E25,"All wrapped","All bought")))) | L25: =IF(B25="","",IF(OR(J25="All bought",J25="All wrapped"),"",ROW()))
E26: =IF(B26="","",COUNTIFS(Gifts!$B$6:$B$305,B26)) | F26: =IF(B26="","",SUMIFS(Gifts!$M$6:$M$305,Gifts!$B$6:$B$305,B26)) | G26: =IF(B26="","",SUMIFS(Gifts!$N$6:$N$305,Gifts!$B$6:$B$305,B26)) | H26: =IF(B26="","",SUMIFS(Gifts!$O$6:$O$305,Gifts!$B$6:$B$305,B26)) | I26: =IF(OR(B26="",D26=""),"",D26-G26-H26) | J26: =IF(B26="","",IF(E26=0,"No gift yet",IF(F26<E26,(E26-F26)&" to buy",IF(COUNTIFS(Gifts!$B$6:$B$305,B26,Gifts!$K$6:$K$305,"Wrapped")=E26,"All wrapped","All bought")))) | L26: =IF(B26="","",IF(OR(J26="All bought",J26="All wrapped"),"",ROW()))
E27: =IF(B27="","",COUNTIFS(Gifts!$B$6:$B$305,B27)) | F27: =IF(B27="","",SUMIFS(Gifts!$M$6:$M$305,Gifts!$B$6:$B$305,B27)) | G27: =IF(B27="","",SUMIFS(Gifts!$N$6:$N$305,Gifts!$B$6:$B$305,B27)) | H27: =IF(B27="","",SUMIFS(Gifts!$O$6:$O$305,Gifts!$B$6:$B$305,B27)) | I27: =IF(OR(B27="",D27=""),"",D27-G27-H27) | J27: =IF(B27="","",IF(E27=0,"No gift yet",IF(F27<E27,(E27-F27)&" to buy",IF(COUNTIFS(Gifts!$B$6:$B$305,B27,Gifts!$K$6:$K$305,"Wrapped")=E27,"All wrapped","All bought")))) | L27: =IF(B27="","",IF(OR(J27="All bought",J27="All wrapped"),"",ROW()))
E28: =IF(B28="","",COUNTIFS(Gifts!$B$6:$B$305,B28)) | F28: =IF(B28="","",SUMIFS(Gifts!$M$6:$M$305,Gifts!$B$6:$B$305,B28)) | G28: =IF(B28="","",SUMIFS(Gifts!$N$6:$N$305,Gifts!$B$6:$B$305,B28)) | H28: =IF(B28="","",SUMIFS(Gifts!$O$6:$O$305,Gifts!$B$6:$B$305,B28)) | I28: =IF(OR(B28="",D28=""),"",D28-G28-H28) | J28: =IF(B28="","",IF(E28=0,"No gift yet",IF(F28<E28,(E28-F28)&" to buy",IF(COUNTIFS(Gifts!$B$6:$B$305,B28,Gifts!$K$6:$K$305,"Wrapped")=E28,"All wrapped","All bought")))) | L28: =IF(B28="","",IF(OR(J28="All bought",J28="All wrapped"),"",ROW()))
E29: =IF(B29="","",COUNTIFS(Gifts!$B$6:$B$305,B29)) | F29: =IF(B29="","",SUMIFS(Gifts!$M$6:$M$305,Gifts!$B$6:$B$305,B29)) | G29: =IF(B29="","",SUMIFS(Gifts!$N$6:$N$305,Gifts!$B$6:$B$305,B29)) | H29: =IF(B29="","",SUMIFS(Gifts!$O$6:$O$305,Gifts!$B$6:$B$305,B29)) | I29: =IF(OR(B29="",D29=""),"",D29-G29-H29) | J29: =IF(B29="","",IF(E29=0,"No gift yet",IF(F29<E29,(E29-F29)&" to buy",IF(COUNTIFS(Gifts!$B$6:$B$305,B29,Gifts!$K$6:$K$305,"Wrapped")=E29,"All wrapped","All bought")))) | L29: =IF(B29="","",IF(OR(J29="All bought",J29="All wrapped"),"",ROW()))
E30: =IF(B30="","",COUNTIFS(Gifts!$B$6:$B$305,B30)) | F30: =IF(B30="","",SUMIFS(Gifts!$M$6:$M$305,Gifts!$B$6:$B$305,B30)) | G30: =IF(B30="","",SUMIFS(Gifts!$N$6:$N$305,Gifts!$B$6:$B$305,B30)) | H30: =IF(B30="","",SUMIFS(Gifts!$O$6:$O$305,Gifts!$B$6:$B$305,B30)) | I30: =IF(OR(B30="",D30=""),"",D30-G30-H30) | J30: =IF(B30="","",IF(E30=0,"No gift yet",IF(F30<E30,(E30-F30)&" to buy",IF(COUNTIFS(Gifts!$B$6:$B$305,B30,Gifts!$K$6:$K$305,"Wrapped")=E30,"All wrapped","All bought")))) | L30: =IF(B30="","",IF(OR(J30="All bought",J30="All wrapped"),"",ROW()))
... E65: =IF(B65="","",COUNTIFS(Gifts!$B$6:$B$305,B65)) | F65: =IF(B65="","",SUMIFS(Gifts!$M$6:$M$305,Gifts!$B$6:$B$305,B65)) | G65: =IF(B65="","",SUMIFS(Gifts!$N$6:$N$305,Gifts!$B$6:$B$305,B65)) | H65: =IF(B65="","",SUMIFS(Gifts!$O$6:$O$305,Gifts!$B$6:$B$305,B65)) | I65: =IF(OR(B65="",D65=""),"",D65-G65-H65) | J65: =IF(B65="","",IF(E65=0,"No gift yet",IF(F65<E65,(E65-F65)&" to buy",IF(COUNTIFS(Gifts!$B$6:$B$305,B65,Gifts!$K$6:$K$305,"Wrapped")=E65,"All wrapped","All bought")))) | L65: =IF(B65="","",IF(OR(J65="All bought",J65="All wrapped"),"",ROW()))

Sheet Budget
B2: Budget
B3: The gifts add up the people's budgets. Type a budget for everything else. Left takes off what is still to pay.
B5: Category | C5: Budget | D5: Spent | E5: To pay | F5: Left | G5: Used
B6: Gifts | C6: =SUM(People!$D$6:$D$65) | D6: =SUM(Gifts!$N$6:$N$305)+SUMIFS(Costs!$H$6:$H$305,Costs!$C$6:$C$305,"Gifts") | E6: =SUM(Gifts!$O$6:$O$305)+SUMIFS(Costs!$I$6:$I$305,Costs!$C$6:$C$305,"Gifts") | F6: =IF(OR(B6="",C6=""),"",N(C6)-D6-E6) | G6: =IF(OR(B6="",N(C6)=0),"",REPT("█",MIN(16,MAX(0,ROUND(((D6+E6)/C6)*16,0))))&REPT("░",16-MIN(16,MAX(0,ROUND(((D6+E6)/C6)*16,0))))) | I6: =IF(AND(B6<>"",OR(N(C6)>0,N(D6)+N(E6)>0)),ROW(),"")
B7: Food and drink | C7: 350 | D7: =IF(B7="","",SUMIFS(Costs!$H$6:$H$305,Costs!$C$6:$C$305,B7)) | E7: =IF(B7="","",SUMIFS(Costs!$I$6:$I$305,Costs!$C$6:$C$305,B7)) | F7: =IF(OR(B7="",C7=""),"",N(C7)-D7-E7) | G7: =IF(OR(B7="",N(C7)=0),"",REPT("█",MIN(16,MAX(0,ROUND(((D7+E7)/C7)*16,0))))&REPT("░",16-MIN(16,MAX(0,ROUND(((D7+E7)/C7)*16,0))))) | I7: =IF(AND(B7<>"",OR(N(C7)>0,N(D7)+N(E7)>0)),ROW(),"")
B8: Decorations | C8: 120 | D8: =IF(B8="","",SUMIFS(Costs!$H$6:$H$305,Costs!$C$6:$C$305,B8)) | E8: =IF(B8="","",SUMIFS(Costs!$I$6:$I$305,Costs!$C$6:$C$305,B8)) | F8: =IF(OR(B8="",C8=""),"",N(C8)-D8-E8) | G8: =IF(OR(B8="",N(C8)=0),"",REPT("█",MIN(16,MAX(0,ROUND(((D8+E8)/C8)*16,0))))&REPT("░",16-MIN(16,MAX(0,ROUND(((D8+E8)/C8)*16,0))))) | I8: =IF(AND(B8<>"",OR(N(C8)>0,N(D8)+N(E8)>0)),ROW(),"")
B9: Cards and wrapping | C9: 80 | D9: =IF(B9="","",SUMIFS(Costs!$H$6:$H$305,Costs!$C$6:$C$305,B9)) | E9: =IF(B9="","",SUMIFS(Costs!$I$6:$I$305,Costs!$C$6:$C$305,B9)) | F9: =IF(OR(B9="",C9=""),"",N(C9)-D9-E9) | G9: =IF(OR(B9="",N(C9)=0),"",REPT("█",MIN(16,MAX(0,ROUND(((D9+E9)/C9)*16,0))))&REPT("░",16-MIN(16,MAX(0,ROUND(((D9+E9)/C9)*16,0))))) | I9: =IF(AND(B9<>"",OR(N(C9)>0,N(D9)+N(E9)>0)),ROW(),"")
B10: Travel | C10: 150 | D10: =IF(B10="","",SUMIFS(Costs!$H$6:$H$305,Costs!$C$6:$C$305,B10)) | E10: =IF(B10="","",SUMIFS(Costs!$I$6:$I$305,Costs!$C$6:$C$305,B10)) | F10: =IF(OR(B10="",C10=""),"",N(C10)-D10-E10) | G10: =IF(OR(B10="",N(C10)=0),"",REPT("█",MIN(16,MAX(0,ROUND(((D10+E10)/C10)*16,0))))&REPT("░",16-MIN(16,MAX(0,ROUND(((D10+E10)/C10)*16,0))))) | I10: =IF(AND(B10<>"",OR(N(C10)>0,N(D10)+N(E10)>0)),ROW(),"")
B11: Outings | C11: 150 | D11: =IF(B11="","",SUMIFS(Costs!$H$6:$H$305,Costs!$C$6:$C$305,B11)) | E11: =IF(B11="","",SUMIFS(Costs!$I$6:$I$305,Costs!$C$6:$C$305,B11)) | F11: =IF(OR(B11="",C11=""),"",N(C11)-D11-E11) | G11: =IF(OR(B11="",N(C11)=0),"",REPT("█",MIN(16,MAX(0,ROUND(((D11+E11)/C11)*16,0))))&REPT("░",16-MIN(16,MAX(0,ROUND(((D11+E11)/C11)*16,0))))) | I11: =IF(AND(B11<>"",OR(N(C11)>0,N(D11)+N(E11)>0)),ROW(),"")
B12: Clothes | C12: 60 | D12: =IF(B12="","",SUMIFS(Costs!$H$6:$H$305,Costs!$C$6:$C$305,B12)) | E12: =IF(B12="","",SUMIFS(Costs!$I$6:$I$305,Costs!$C$6:$C$305,B12)) | F12: =IF(OR(B12="",C12=""),"",N(C12)-D12-E12) | G12: =IF(OR(B12="",N(C12)=0),"",REPT("█",MIN(16,MAX(0,ROUND(((D12+E12)/C12)*16,0))))&REPT("░",16-MIN(16,MAX(0,ROUND(((D12+E12)/C12)*16,0))))) | I12: =IF(AND(B12<>"",OR(N(C12)>0,N(D12)+N(E12)>0)),ROW(),"")
B13: Charity | C13: 50 | D13: =IF(B13="","",SUMIFS(Costs!$H$6:$H$305,Costs!$C$6:$C$305,B13)) | E13: =IF(B13="","",SUMIFS(Costs!$I$6:$I$305,Costs!$C$6:$C$305,B13)) | F13: =IF(OR(B13="",C13=""),"",N(C13)-D13-E13) | G13: =IF(OR(B13="",N(C13)=0),"",REPT("█",MIN(16,MAX(0,ROUND(((D13+E13)/C13)*16,0))))&REPT("░",16-MIN(16,MAX(0,ROUND(((D13+E13)/C13)*16,0))))) | I13: =IF(AND(B13<>"",OR(N(C13)>0,N(D13)+N(E13)>0)),ROW(),"")
D14: =IF(B14="","",SUMIFS(Costs!$H$6:$H$305,Costs!$C$6:$C$305,B14)) | E14: =IF(B14="","",SUMIFS(Costs!$I$6:$I$305,Costs!$C$6:$C$305,B14)) | F14: =IF(OR(B14="",C14=""),"",N(C14)-D14-E14) | G14: =IF(OR(B14="",N(C14)=0),"",REPT("█",MIN(16,MAX(0,ROUND(((D14+E14)/C14)*16,0))))&REPT("░",16-MIN(16,MAX(0,ROUND(((D14+E14)/C14)*16,0))))) | I14: =IF(AND(B14<>"",OR(N(C14)>0,N(D14)+N(E14)>0)),ROW(),"")
D15: =IF(B15="","",SUMIFS(Costs!$H$6:$H$305,Costs!$C$6:$C$305,B15)) | E15: =IF(B15="","",SUMIFS(Costs!$I$6:$I$305,Costs!$C$6:$C$305,B15)) | F15: =IF(OR(B15="",C15=""),"",N(C15)-D15-E15) | G15: =IF(OR(B15="",N(C15)=0),"",REPT("█",MIN(16,MAX(0,ROUND(((D15+E15)/C15)*16,0))))&REPT("░",16-MIN(16,MAX(0,ROUND(((D15+E15)/C15)*16,0))))) | I15: =IF(AND(B15<>"",OR(N(C15)>0,N(D15)+N(E15)>0)),ROW(),"")
D16: =IF(B16="","",SUMIFS(Costs!$H$6:$H$305,Costs!$C$6:$C$305,B16)) | E16: =IF(B16="","",SUMIFS(Costs!$I$6:$I$305,Costs!$C$6:$C$305,B16)) | F16: =IF(OR(B16="",C16=""),"",N(C16)-D16-E16) | G16: =IF(OR(B16="",N(C16)=0),"",REPT("█",MIN(16,MAX(0,ROUND(((D16+E16)/C16)*16,0))))&REPT("░",16-MIN(16,MAX(0,ROUND(((D16+E16)/C16)*16,0))))) | I16: =IF(AND(B16<>"",OR(N(C16)>0,N(D16)+N(E16)>0)),ROW(),"")
D17: =IF(B17="","",SUMIFS(Costs!$H$6:$H$305,Costs!$C$6:$C$305,B17)) | E17: =IF(B17="","",SUMIFS(Costs!$I$6:$I$305,Costs!$C$6:$C$305,B17)) | F17: =IF(OR(B17="",C17=""),"",N(C17)-D17-E17) | G17: =IF(OR(B17="",N(C17)=0),"",REPT("█",MIN(16,MAX(0,ROUND(((D17+E17)/C17)*16,0))))&REPT("░",16-MIN(16,MAX(0,ROUND(((D17+E17)/C17)*16,0))))) | I17: =IF(AND(B17<>"",OR(N(C17)>0,N(D17)+N(E17)>0)),ROW(),"")
D18: =IF(B18="","",SUMIFS(Costs!$H$6:$H$305,Costs!$C$6:$C$305,B18)) | E18: =IF(B18="","",SUMIFS(Costs!$I$6:$I$305,Costs!$C$6:$C$305,B18)) | F18: =IF(OR(B18="",C18=""),"",N(C18)-D18-E18) | G18: =IF(OR(B18="",N(C18)=0),"",REPT("█",MIN(16,MAX(0,ROUND(((D18+E18)/C18)*16,0))))&REPT("░",16-MIN(16,MAX(0,ROUND(((D18+E18)/C18)*16,0))))) | I18: =IF(AND(B18<>"",OR(N(C18)>0,N(D18)+N(E18)>0)),ROW(),"")
D19: =IF(B19="","",SUMIFS(Costs!$H$6:$H$305,Costs!$C$6:$C$305,B19)) | E19: =IF(B19="","",SUMIFS(Costs!$I$6:$I$305,Costs!$C$6:$C$305,B19)) | F19: =IF(OR(B19="",C19=""),"",N(C19)-D19-E19) | G19: =IF(OR(B19="",N(C19)=0),"",REPT("█",MIN(16,MAX(0,ROUND(((D19+E19)/C19)*16,0))))&REPT("░",16-MIN(16,MAX(0,ROUND(((D19+E19)/C19)*16,0))))) | I19: =IF(AND(B19<>"",OR(N(C19)>0,N(D19)+N(E19)>0)),ROW(),"")
D20: =IF(B20="","",SUMIFS(Costs!$H$6:$H$305,Costs!$C$6:$C$305,B20)) | E20: =IF(B20="","",SUMIFS(Costs!$I$6:$I$305,Costs!$C$6:$C$305,B20)) | F20: =IF(OR(B20="",C20=""),"",N(C20)-D20-E20) | G20: =IF(OR(B20="",N(C20)=0),"",REPT("█",MIN(16,MAX(0,ROUND(((D20+E20)/C20)*16,0))))&REPT("░",16-MIN(16,MAX(0,ROUND(((D20+E20)/C20)*16,0))))) | I20: =IF(AND(B20<>"",OR(N(C20)>0,N(D20)+N(E20)>0)),ROW(),"")
B21: =IF(AND(D21=0,E21=0),"","Not on this list") | D21: =SUM(Costs!$H$6:$H$305)-SUMIFS(Costs!$H$6:$H$305,Costs!$C$6:$C$305,"Gifts")-SUM(D7:D20) | E21: =SUM(Costs!$I$6:$I$305)-SUMIFS(Costs!$I$6:$I$305,Costs!$C$6:$C$305,"Gifts")-SUM(E7:E20) | F21: =IF(OR(B21="",C21=""),"",N(C21)-D21-E21) | G21: =IF(OR(B21="",N(C21)=0),"",REPT("█",MIN(16,MAX(0,ROUND(((D21+E21)/C21)*16,0))))&REPT("░",16-MIN(16,MAX(0,ROUND(((D21+E21)/C21)*16,0))))) | I21: =IF(AND(B21<>"",OR(N(C21)>0,N(D21)+N(E21)>0)),ROW(),"")
B22: Total | C22: =SUM(C6:C20) | D22: =SUM(D6:D21) | E22: =SUM(E6:E21) | F22: =C22-D22-E22 | G22: =IF(N(C22)=0,"",REPT("█",MIN(16,MAX(0,ROUND(((D22+E22)/C22)*16,0))))&REPT("░",16-MIN(16,MAX(0,ROUND(((D22+E22)/C22)*16,0)))))

Sheet Costs
B2: Costs
B3: Everything else Christmas costs: what you plan to spend, and what you paid.
B5: Date | C5: Category | D5: What | E5: Planned | F5: Paid
B6: 46285 | C6: Decorations | D6: Advent calendars | E6: 24 | F6: 24 | H6: =N(F6) | I6: =IF(F6="",N(E6),0)
B7: 46290 | C7: Cards and wrapping | D7: Box of 30 cards | E7: 15 | F7: 15 | H7: =N(F7) | I7: =IF(F7="",N(E7),0)
B8: 46290 | C8: Cards and wrapping | D8: Wrapping paper and tags | E8: 20 | F8: 18 | H8: =N(F8) | I8: =IF(F8="",N(E8),0)
B9: 46357 | C9: Cards and wrapping | D9: Stamps | E9: 25 | H9: =N(F9) | I9: =IF(F9="",N(E9),0)
B10: 46361 | C10: Decorations | D10: Real tree | E10: 60 | H10: =N(F10) | I10: =IF(F10="",N(E10),0)
B11: 46361 | C11: Decorations | D11: New lights | E11: 30 | H11: =N(F11) | I11: =IF(F11="",N(E11),0)
B12: 46281 | C12: Travel | D12: Train tickets to Grandma's | E12: 90 | F12: 86 | H12: =N(F12) | I12: =IF(F12="",N(E12),0)
B13: 46376 | C13: Travel | D13: Fuel | E13: 40 | H13: =N(F13) | I13: =IF(F13="",N(E13),0)
B14: 46288 | C14: Outings | D14: Pantomime tickets | E14: 96 | F14: 96 | H14: =N(F14) | I14: =IF(F14="",N(E14),0)
B15: 46375 | C15: Outings | D15: Christmas market | E15: 40 | H15: =N(F15) | I15: =IF(F15="",N(E15),0)
B16: 46378 | C16: Food and drink | D16: Turkey | E16: 60 | H16: =N(F16) | I16: =IF(F16="",N(E16),0)
B17: 46379 | C17: Food and drink | D17: Big food shop | E17: 180 | H17: =N(F17) | I17: =IF(F17="",N(E17),0)
B18: 46292 | C18: Food and drink | D18: Drinks | E18: 70 | F18: 64 | H18: =N(F18) | I18: =IF(F18="",N(E18),0)
B19: 46366 | C19: Clothes | D19: Christmas jumpers | E19: 45 | H19: =N(F19) | I19: =IF(F19="",N(E19),0)
B20: 46371 | C20: Charity | D20: Food bank donation | E20: 50 | H20: =N(F20) | I20: =IF(F20="",N(E20),0)
H21: =N(F21) | I21: =IF(F21="",N(E21),0)
H22: =N(F22) | I22: =IF(F22="",N(E22),0)
H23: =N(F23) | I23: =IF(F23="",N(E23),0)
H24: =N(F24) | I24: =IF(F24="",N(E24),0)
H25: =N(F25) | I25: =IF(F25="",N(E25),0)
H26: =N(F26) | I26: =IF(F26="",N(E26),0)
H27: =N(F27) | I27: =IF(F27="",N(E27),0)
H28: =N(F28) | I28: =IF(F28="",N(E28),0)
H29: =N(F29) | I29: =IF(F29="",N(E29),0)
H30: =N(F30) | I30: =IF(F30="",N(E30),0)
H31: =N(F31) | I31: =IF(F31="",N(E31),0)
H32: =N(F32) | I32: =IF(F32="",N(E32),0)
... H305: =N(F305) | I305: =IF(F305="",N(E305),0)

Sheet Cards
B2: Cards
B3: Who gets a card, the address, an x when it is posted and when one comes from them.
B5: Name | C5: Address | D5: Town and postcode | E5: Sent | F5: From them | G5: Notes | H5: Status
B6: Aunt Rose | C6: 3 Ivy Lane | D6: Riverton | E6: x | H6: =IF(B6="","",IF(E6<>"","Sent","To send"))
B7: Uncle Ben and Jo | C7: 8 Holly Road | D7: Eastbridge | E7: x | F7: x | H7: =IF(B7="","",IF(E7<>"","Sent","To send"))
B8: The Parkers | C8: 21 Mill Street | D8: Riverton | E8: x | H8: =IF(B8="","",IF(E8<>"","Sent","To send"))
B9: Grandma | C9: 5 Rose Court | D9: Westford | E9: x | H9: =IF(B9="","",IF(E9<>"","Sent","To send"))
B10: Priya and Dev | E10: x | H10: =IF(B10="","",IF(E10<>"","Sent","To send"))
B11: Tom | H11: =IF(B11="","",IF(E11<>"","Sent","To send"))
B12: Mia | H12: =IF(B12="","",IF(E12<>"","Sent","To send"))
B13: The Lees | C13: 40 Oak Avenue | D13: Riverton | F13: x | H13: =IF(B13="","",IF(E13<>"","Sent","To send"))
B14: Mr and Mrs Grant | C14: 2 Station Road | D14: Northam | H14: =IF(B14="","",IF(E14<>"","Sent","To send"))
B15: Lily's teacher | H15: =IF(B15="","",IF(E15<>"","Sent","To send"))
B16: Noah's coach | H16: =IF(B16="","",IF(E16<>"","Sent","To send"))
B17: Cousin Ella | C17: 17 Bay View | D17: Seaford | H17: =IF(B17="","",IF(E17<>"","Sent","To send"))
B18: Cousin Max | H18: =IF(B18="","",IF(E18<>"","Sent","To send"))
B19: Next door at 12 | H19: =IF(B19="","",IF(E19<>"","Sent","To send"))
B20: Next door at 16 | H20: =IF(B20="","",IF(E20<>"","Sent","To send"))
B21: Old friends from school | H21: =IF(B21="","",IF(E21<>"","Sent","To send"))
B22: Work team | H22: =IF(B22="","",IF(E22<>"","Sent","To send"))
B23: Sam and Kate | C23: 9 Elm Close | D23: Eastbridge | H23: =IF(B23="","",IF(E23<>"","Sent","To send"))
H24: =IF(B24="","",IF(E24<>"","Sent","To send"))
H25: =IF(B25="","",IF(E25<>"","Sent","To send"))
H26: =IF(B26="","",IF(E26<>"","Sent","To send"))
H27: =IF(B27="","",IF(E27<>"","Sent","To send"))
H28: =IF(B28="","",IF(E28<>"","Sent","To send"))
H29: =IF(B29="","",IF(E29<>"","Sent","To send"))
H30: =IF(B30="","",IF(E30<>"","Sent","To send"))
H31: =IF(B31="","",IF(E31<>"","Sent","To send"))
H32: =IF(B32="","",IF(E32<>"","Sent","To send"))
H33: =IF(B33="","",IF(E33<>"","Sent","To send"))
H34: =IF(B34="","",IF(E34<>"","Sent","To send"))
H35: =IF(B35="","",IF(E35<>"","Sent","To send"))
... H305: =IF(B305="","",IF(E305<>"","Sent","To send"))

Sheet Dinner
B2: Christmas dinner
B3: The menu, who makes what, and when to start each dish so it is all ready together.
B4: Dinner on | C4: =DATE(Settings!$C$4,12,25) | E4: Ready by: leave it empty for the time you sit down, or type a time, or a date and time.
B5: Sit down at | C5: 0.625 | E5: Minutes: prep before it cooks, cooking, and resting after.
B6: Guests coming | C6: =SUMPRODUCT(($B$32:$B$51<>"")*($C$32:$C$51<>""))
B8: Dish | C8: Course | D8: Who makes it | E8: Ready by | F8: Prep (min) | G8: Cook (min) | H8: Rest (min) | I8: Start | J8: Done | L8: When | M8: What to do
B9: Prawn cocktail | C9: Starter | D9: Priya | F9: 20 | I9: =IF(OR(B9="",(N(F9)+N(G9)+N(H9))=0),"",ROUND((IF(E9="",$C$4+$C$5,IF(E9>=1,E9,$C$4+E9))-(N(F9)+N(G9)+N(H9))/1440)*1440,0)/1440) | L9: =IF(O9="","",ROUND(O9*1440,0)/1440) | M9: =IF(O9="","",IF(O9=$R$29,"Sit down to eat",IF(ISNUMBER(MATCH(O9,$R$9:$R$28,0)),"Prepare: "&INDEX($B$9:$B$28,MATCH(O9,$R$9:$R$28,0)),IF(ISNUMBER(MATCH(O9,$S$9:$S$28,0)),"Cook: "&INDEX($B$9:$B$28,MATCH(O9,$S$9:$S$28,0)),"Rest: "&INDEX($B$9:$B$28,MATCH(O9,$T$9:$T$28,0)))))) | O9: =IF(1<=COUNT($R$9:$T$29),SMALL($R$9:$T$29,1),"") | R9: =IF(OR(B9="",N(F9)=0),"",IF(E9="",$C$4+$C$5,IF(E9>=1,E9,$C$4+E9))-(N(F9)+N(G9)+N(H9))/1440+(100+ROW())/10000000) | S9: =IF(OR(B9="",N(G9)=0),"",IF(E9="",$C$4+$C$5,IF(E9>=1,E9,$C$4+E9))-(N(G9)+N(H9))/1440+(200+ROW())/10000000) | T9: =IF(OR(B9="",N(H9)=0),"",IF(E9="",$C$4+$C$5,IF(E9>=1,E9,$C$4+E9))-N(H9)/1440+(300+ROW())/10000000)
B10: Roast turkey | C10: Main | D10: Me | F10: 30 | G10: 210 | H10: 45 | I10: =IF(OR(B10="",(N(F10)+N(G10)+N(H10))=0),"",ROUND((IF(E10="",$C$4+$C$5,IF(E10>=1,E10,$C$4+E10))-(N(F10)+N(G10)+N(H10))/1440)*1440,0)/1440) | L10: =IF(O10="","",ROUND(O10*1440,0)/1440) | M10: =IF(O10="","",IF(O10=$R$29,"Sit down to eat",IF(ISNUMBER(MATCH(O10,$R$9:$R$28,0)),"Prepare: "&INDEX($B$9:$B$28,MATCH(O10,$R$9:$R$28,0)),IF(ISNUMBER(MATCH(O10,$S$9:$S$28,0)),"Cook: "&INDEX($B$9:$B$28,MATCH(O10,$S$9:$S$28,0)),"Rest: "&INDEX($B$9:$B$28,MATCH(O10,$T$9:$T$28,0)))))) | O10: =IF(2<=COUNT($R$9:$T$29),SMALL($R$9:$T$29,2),"") | R10: =IF(OR(B10="",N(F10)=0),"",IF(E10="",$C$4+$C$5,IF(E10>=1,E10,$C$4+E10))-(N(F10)+N(G10)+N(H10))/1440+(100+ROW())/10000000) | S10: =IF(OR(B10="",N(G10)=0),"",IF(E10="",$C$4+$C$5,IF(E10>=1,E10,$C$4+E10))-(N(G10)+N(H10))/1440+(200+ROW())/10000000) | T10: =IF(OR(B10="",N(H10)=0),"",IF(E10="",$C$4+$C$5,IF(E10>=1,E10,$C$4+E10))-N(H10)/1440+(300+ROW())/10000000)
B11: Roast potatoes | C11: Side | D11: Me | F11: 20 | G11: 60 | I11: =IF(OR(B11="",(N(F11)+N(G11)+N(H11))=0),"",ROUND((IF(E11="",$C$4+$C$5,IF(E11>=1,E11,$C$4+E11))-(N(F11)+N(G11)+N(H11))/1440)*1440,0)/1440) | L11: =IF(O11="","",ROUND(O11*1440,0)/1440) | M11: =IF(O11="","",IF(O11=$R$29,"Sit down to eat",IF(ISNUMBER(MATCH(O11,$R$9:$R$28,0)),"Prepare: "&INDEX($B$9:$B$28,MATCH(O11,$R$9:$R$28,0)),IF(ISNUMBER(MATCH(O11,$S$9:$S$28,0)),"Cook: "&INDEX($B$9:$B$28,MATCH(O11,$S$9:$S$28,0)),"Rest: "&INDEX($B$9:$B$28,MATCH(O11,$T$9:$T$28,0)))))) | O11: =IF(3<=COUNT($R$9:$T$29),SMALL($R$9:$T$29,3),"") | R11: =IF(OR(B11="",N(F11)=0),"",IF(E11="",$C$4+$C$5,IF(E11>=1,E11,$C$4+E11))-(N(F11)+N(G11)+N(H11))/1440+(100+ROW())/10000000) | S11: =IF(OR(B11="",N(G11)=0),"",IF(E11="",$C$4+$C$5,IF(E11>=1,E11,$C$4+E11))-(N(G11)+N(H11))/1440+(200+ROW())/10000000) | T11: =IF(OR(B11="",N(H11)=0),"",IF(E11="",$C$4+$C$5,IF(E11>=1,E11,$C$4+E11))-N(H11)/1440+(300+ROW())/10000000)
B12: Stuffing | C12: Side | D12: Me | F12: 15 | G12: 45 | I12: =IF(OR(B12="",(N(F12)+N(G12)+N(H12))=0),"",ROUND((IF(E12="",$C$4+$C$5,IF(E12>=1,E12,$C$4+E12))-(N(F12)+N(G12)+N(H12))/1440)*1440,0)/1440) | L12: =IF(O12="","",ROUND(O12*1440,0)/1440) | M12: =IF(O12="","",IF(O12=$R$29,"Sit down to eat",IF(ISNUMBER(MATCH(O12,$R$9:$R$28,0)),"Prepare: "&INDEX($B$9:$B$28,MATCH(O12,$R$9:$R$28,0)),IF(ISNUMBER(MATCH(O12,$S$9:$S$28,0)),"Cook: "&INDEX($B$9:$B$28,MATCH(O12,$S$9:$S$28,0)),"Rest: "&INDEX($B$9:$B$28,MATCH(O12,$T$9:$T$28,0)))))) | O12: =IF(4<=COUNT($R$9:$T$29),SMALL($R$9:$T$29,4),"") | R12: =IF(OR(B12="",N(F12)=0),"",IF(E12="",$C$4+$C$5,IF(E12>=1,E12,$C$4+E12))-(N(F12)+N(G12)+N(H12))/1440+(100+ROW())/10000000) | S12: =IF(OR(B12="",N(G12)=0),"",IF(E12="",$C$4+$C$5,IF(E12>=1,E12,$C$4+E12))-(N(G12)+N(H12))/1440+(200+ROW())/10000000) | T12: =IF(OR(B12="",N(H12)=0),"",IF(E12="",$C$4+$C$5,IF(E12>=1,E12,$C$4+E12))-N(H12)/1440+(300+ROW())/10000000)
B13: Glazed carrots | C13: Side | D13: Sam | F13: 10 | G13: 30 | I13: =IF(OR(B13="",(N(F13)+N(G13)+N(H13))=0),"",ROUND((IF(E13="",$C$4+$C$5,IF(E13>=1,E13,$C$4+E13))-(N(F13)+N(G13)+N(H13))/1440)*1440,0)/1440) | L13: =IF(O13="","",ROUND(O13*1440,0)/1440) | M13: =IF(O13="","",IF(O13=$R$29,"Sit down to eat",IF(ISNUMBER(MATCH(O13,$R$9:$R$28,0)),"Prepare: "&INDEX($B$9:$B$28,MATCH(O13,$R$9:$R$28,0)),IF(ISNUMBER(MATCH(O13,$S$9:$S$28,0)),"Cook: "&INDEX($B$9:$B$28,MATCH(O13,$S$9:$S$28,0)),"Rest: "&INDEX($B$9:$B$28,MATCH(O13,$T$9:$T$28,0)))))) | O13: =IF(5<=COUNT($R$9:$T$29),SMALL($R$9:$T$29,5),"") | R13: =IF(OR(B13="",N(F13)=0),"",IF(E13="",$C$4+$C$5,IF(E13>=1,E13,$C$4+E13))-(N(F13)+N(G13)+N(H13))/1440+(100+ROW())/10000000) | S13: =IF(OR(B13="",N(G13)=0),"",IF(E13="",$C$4+$C$5,IF(E13>=1,E13,$C$4+E13))-(N(G13)+N(H13))/1440+(200+ROW())/10000000) | T13: =IF(OR(B13="",N(H13)=0),"",IF(E13="",$C$4+$C$5,IF(E13>=1,E13,$C$4+E13))-N(H13)/1440+(300+ROW())/10000000)
B14: Green beans | C14: Side | D14: Me | F14: 10 | G14: 10 | I14: =IF(OR(B14="",(N(F14)+N(G14)+N(H14))=0),"",ROUND((IF(E14="",$C$4+$C$5,IF(E14>=1,E14,$C$4+E14))-(N(F14)+N(G14)+N(H14))/1440)*1440,0)/1440) | L14: =IF(O14="","",ROUND(O14*1440,0)/1440) | M14: =IF(O14="","",IF(O14=$R$29,"Sit down to eat",IF(ISNUMBER(MATCH(O14,$R$9:$R$28,0)),"Prepare: "&INDEX($B$9:$B$28,MATCH(O14,$R$9:$R$28,0)),IF(ISNUMBER(MATCH(O14,$S$9:$S$28,0)),"Cook: "&INDEX($B$9:$B$28,MATCH(O14,$S$9:$S$28,0)),"Rest: "&INDEX($B$9:$B$28,MATCH(O14,$T$9:$T$28,0)))))) | O14: =IF(6<=COUNT($R$9:$T$29),SMALL($R$9:$T$29,6),"") | R14: =IF(OR(B14="",N(F14)=0),"",IF(E14="",$C$4+$C$5,IF(E14>=1,E14,$C$4+E14))-(N(F14)+N(G14)+N(H14))/1440+(100+ROW())/10000000) | S14: =IF(OR(B14="",N(G14)=0),"",IF(E14="",$C$4+$C$5,IF(E14>=1,E14,$C$4+E14))-(N(G14)+N(H14))/1440+(200+ROW())/10000000) | T14: =IF(OR(B14="",N(H14)=0),"",IF(E14="",$C$4+$C$5,IF(E14>=1,E14,$C$4+E14))-N(H14)/1440+(300+ROW())/10000000)
B15: Gravy | C15: Side | D15: Me | F15: 5 | G15: 15 | I15: =IF(OR(B15="",(N(F15)+N(G15)+N(H15))=0),"",ROUND((IF(E15="",$C$4+$C$5,IF(E15>=1,E15,$C$4+E15))-(N(F15)+N(G15)+N(H15))/1440)*1440,0)/1440) | L15: =IF(O15="","",ROUND(O15*1440,0)/1440) | M15: =IF(O15="","",IF(O15=$R$29,"Sit down to eat",IF(ISNUMBER(MATCH(O15,$R$9:$R$28,0)),"Prepare: "&INDEX($B$9:$B$28,MATCH(O15,$R$9:$R$28,0)),IF(ISNUMBER(MATCH(O15,$S$9:$S$28,0)),"Cook: "&INDEX($B$9:$B$28,MATCH(O15,$S$9:$S$28,0)),"Rest: "&INDEX($B$9:$B$28,MATCH(O15,$T$9:$T$28,0)))))) | O15: =IF(7<=COUNT($R$9:$T$29),SMALL($R$9:$T$29,7),"") | R15: =IF(OR(B15="",N(F15)=0),"",IF(E15="",$C$4+$C$5,IF(E15>=1,E15,$C$4+E15))-(N(F15)+N(G15)+N(H15))/1440+(100+ROW())/10000000) | S15: =IF(OR(B15="",N(G15)=0),"",IF(E15="",$C$4+$C$5,IF(E15>=1,E15,$C$4+E15))-(N(G15)+N(H15))/1440+(200+ROW())/10000000) | T15: =IF(OR(B15="",N(H15)=0),"",IF(E15="",$C$4+$C$5,IF(E15>=1,E15,$C$4+E15))-N(H15)/1440+(300+ROW())/10000000)
B16: Cranberry sauce | C16: Side | D16: Grandma | I16: =IF(OR(B16="",(N(F16)+N(G16)+N(H16))=0),"",ROUND((IF(E16="",$C$4+$C$5,IF(E16>=1,E16,$C$4+E16))-(N(F16)+N(G16)+N(H16))/1440)*1440,0)/1440) | L16: =IF(O16="","",ROUND(O16*1440,0)/1440) | M16: =IF(O16="","",IF(O16=$R$29,"Sit down to eat",IF(ISNUMBER(MATCH(O16,$R$9:$R$28,0)),"Prepare: "&INDEX($B$9:$B$28,MATCH(O16,$R$9:$R$28,0)),IF(ISNUMBER(MATCH(O16,$S$9:$S$28,0)),"Cook: "&INDEX($B$9:$B$28,MATCH(O16,$S$9:$S$28,0)),"Rest: "&INDEX($B$9:$B$28,MATCH(O16,$T$9:$T$28,0)))))) | O16: =IF(8<=COUNT($R$9:$T$29),SMALL($R$9:$T$29,8),"") | R16: =IF(OR(B16="",N(F16)=0),"",IF(E16="",$C$4+$C$5,IF(E16>=1,E16,$C$4+E16))-(N(F16)+N(G16)+N(H16))/1440+(100+ROW())/10000000) | S16: =IF(OR(B16="",N(G16)=0),"",IF(E16="",$C$4+$C$5,IF(E16>=1,E16,$C$4+E16))-(N(G16)+N(H16))/1440+(200+ROW())/10000000) | T16: =IF(OR(B16="",N(H16)=0),"",IF(E16="",$C$4+$C$5,IF(E16>=1,E16,$C$4+E16))-N(H16)/1440+(300+ROW())/10000000)
B17: Christmas pudding | C17: Dessert | D17: Grandma | E17: 0.66666667 | G17: 120 | I17: =IF(OR(B17="",(N(F17)+N(G17)+N(H17))=0),"",ROUND((IF(E17="",$C$4+$C$5,IF(E17>=1,E17,$C$4+E17))-(N(F17)+N(G17)+N(H17))/1440)*1440,0)/1440) | L17: =IF(O17="","",ROUND(O17*1440,0)/1440) | M17: =IF(O17="","",IF(O17=$R$29,"Sit down to eat",IF(ISNUMBER(MATCH(O17,$R$9:$R$28,0)),"Prepare: "&INDEX($B$9:$B$28,MATCH(O17,$R$9:$R$28,0)),IF(ISNUMBER(MATCH(O17,$S$9:$S$28,0)),"Cook: "&INDEX($B$9:$B$28,MATCH(O17,$S$9:$S$28,0)),"Rest: "&INDEX($B$9:$B$28,MATCH(O17,$T$9:$T$28,0)))))) | O17: =IF(9<=COUNT($R$9:$T$29),SMALL($R$9:$T$29,9),"") | R17: =IF(OR(B17="",N(F17)=0),"",IF(E17="",$C$4+$C$5,IF(E17>=1,E17,$C$4+E17))-(N(F17)+N(G17)+N(H17))/1440+(100+ROW())/10000000) | S17: =IF(OR(B17="",N(G17)=0),"",IF(E17="",$C$4+$C$5,IF(E17>=1,E17,$C$4+E17))-(N(G17)+N(H17))/1440+(200+ROW())/10000000) | T17: =IF(OR(B17="",N(H17)=0),"",IF(E17="",$C$4+$C$5,IF(E17>=1,E17,$C$4+E17))-N(H17)/1440+(300+ROW())/10000000)
B18: Trifle | C18: Dessert | D18: Me | E18: 46380.833 | F18: 40 | I18: =IF(OR(B18="",(N(F18)+N(G18)+N(H18))=0),"",ROUND((IF(E18="",$C$4+$C$5,IF(E18>=1,E18,$C$4+E18))-(N(F18)+N(G18)+N(H18))/1440)*1440,0)/1440) | L18: =IF(O18="","",ROUND(O18*1440,0)/1440) | M18: =IF(O18="","",IF(O18=$R$29,"Sit down to eat",IF(ISNUMBER(MATCH(O18,$R$9:$R$28,0)),"Prepare: "&INDEX($B$9:$B$28,MATCH(O18,$R$9:$R$28,0)),IF(ISNUMBER(MATCH(O18,$S$9:$S$28,0)),"Cook: "&INDEX($B$9:$B$28,MATCH(O18,$S$9:$S$28,0)),"Rest: "&INDEX($B$9:$B$28,MATCH(O18,$T$9:$T$28,0)))))) | O18: =IF(10<=COUNT($R$9:$T$29),SMALL($R$9:$T$29,10),"") | R18: =IF(OR(B18="",N(F18)=0),"",IF(E18="",$C$4+$C$5,IF(E18>=1,E18,$C$4+E18))-(N(F18)+N(G18)+N(H18))/1440+(100+ROW())/10000000) | S18: =IF(OR(B18="",N(G18)=0),"",IF(E18="",$C$4+$C$5,IF(E18>=1,E18,$C$4+E18))-(N(G18)+N(H18))/1440+(200+ROW())/10000000) | T18: =IF(OR(B18="",N(H18)=0),"",IF(E18="",$C$4+$C$5,IF(E18>=1,E18,$C$4+E18))-N(H18)/1440+(300+ROW())/10000000)
B19: Mulled wine | C19: Drinks | D19: Tom | E19: 0.60416667 | F19: 5 | G19: 20 | I19: =IF(OR(B19="",(N(F19)+N(G19)+N(H19))=0),"",ROUND((IF(E19="",$C$4+$C$5,IF(E19>=1,E19,$C$4+E19))-(N(F19)+N(G19)+N(H19))/1440)*1440,0)/1440) | L19: =IF(O19="","",ROUND(O19*1440,0)/1440) | M19: =IF(O19="","",IF(O19=$R$29,"Sit down to eat",IF(ISNUMBER(MATCH(O19,$R$9:$R$28,0)),"Prepare: "&INDEX($B$9:$B$28,MATCH(O19,$R$9:$R$28,0)),IF(ISNUMBER(MATCH(O19,$S$9:$S$28,0)),"Cook: "&INDEX($B$9:$B$28,MATCH(O19,$S$9:$S$28,0)),"Rest: "&INDEX($B$9:$B$28,MATCH(O19,$T$9:$T$28,0)))))) | O19: =IF(11<=COUNT($R$9:$T$29),SMALL($R$9:$T$29,11),"") | R19: =IF(OR(B19="",N(F19)=0),"",IF(E19="",$C$4+$C$5,IF(E19>=1,E19,$C$4+E19))-(N(F19)+N(G19)+N(H19))/1440+(100+ROW())/10000000) | S19: =IF(OR(B19="",N(G19)=0),"",IF(E19="",$C$4+$C$5,IF(E19>=1,E19,$C$4+E19))-(N(G19)+N(H19))/1440+(200+ROW())/10000000) | T19: =IF(OR(B19="",N(H19)=0),"",IF(E19="",$C$4+$C$5,IF(E19>=1,E19,$C$4+E19))-N(H19)/1440+(300+ROW())/10000000)
I20: =IF(OR(B20="",(N(F20)+N(G20)+N(H20))=0),"",ROUND((IF(E20="",$C$4+$C$5,IF(E20>=1,E20,$C$4+E20))-(N(F20)+N(G20)+N(H20))/1440)*1440,0)/1440) | L20: =IF(O20="","",ROUND(O20*1440,0)/1440) | M20: =IF(O20="","",IF(O20=$R$29,"Sit down to eat",IF(ISNUMBER(MATCH(O20,$R$9:$R$28,0)),"Prepare: "&INDEX($B$9:$B$28,MATCH(O20,$R$9:$R$28,0)),IF(ISNUMBER(MATCH(O20,$S$9:$S$28,0)),"Cook: "&INDEX($B$9:$B$28,MATCH(O20,$S$9:$S$28,0)),"Rest: "&INDEX($B$9:$B$28,MATCH(O20,$T$9:$T$28,0)))))) | O20: =IF(12<=COUNT($R$9:$T$29),SMALL($R$9:$T$29,12),"") | R20: =IF(OR(B20="",N(F20)=0),"",IF(E20="",$C$4+$C$5,IF(E20>=1,E20,$C$4+E20))-(N(F20)+N(G20)+N(H20))/1440+(100+ROW())/10000000) | S20: =IF(OR(B20="",N(G20)=0),"",IF(E20="",$C$4+$C$5,IF(E20>=1,E20,$C$4+E20))-(N(G20)+N(H20))/1440+(200+ROW())/10000000) | T20: =IF(OR(B20="",N(H20)=0),"",IF(E20="",$C$4+$C$5,IF(E20>=1,E20,$C$4+E20))-N(H20)/1440+(300+ROW())/10000000)
I21: =IF(OR(B21="",(N(F21)+N(G21)+N(H21))=0),"",ROUND((IF(E21="",$C$4+$C$5,IF(E21>=1,E21,$C$4+E21))-(N(F21)+N(G21)+N(H21))/1440)*1440,0)/1440) | L21: =IF(O21="","",ROUND(O21*1440,0)/1440) | M21: =IF(O21="","",IF(O21=$R$29,"Sit down to eat",IF(ISNUMBER(MATCH(O21,$R$9:$R$28,0)),"Prepare: "&INDEX($B$9:$B$28,MATCH(O21,$R$9:$R$28,0)),IF(ISNUMBER(MATCH(O21,$S$9:$S$28,0)),"Cook: "&INDEX($B$9:$B$28,MATCH(O21,$S$9:$S$28,0)),"Rest: "&INDEX($B$9:$B$28,MATCH(O21,$T$9:$T$28,0)))))) | O21: =IF(13<=COUNT($R$9:$T$29),SMALL($R$9:$T$29,13),"") | R21: =IF(OR(B21="",N(F21)=0),"",IF(E21="",$C$4+$C$5,IF(E21>=1,E21,$C$4+E21))-(N(F21)+N(G21)+N(H21))/1440+(100+ROW())/10000000) | S21: =IF(OR(B21="",N(G21)=0),"",IF(E21="",$C$4+$C$5,IF(E21>=1,E21,$C$4+E21))-(N(G21)+N(H21))/1440+(200+ROW())/10000000) | T21: =IF(OR(B21="",N(H21)=0),"",IF(E21="",$C$4+$C$5,IF(E21>=1,E21,$C$4+E21))-N(H21)/1440+(300+ROW())/10000000)
I22: =IF(OR(B22="",(N(F22)+N(G22)+N(H22))=0),"",ROUND((IF(E22="",$C$4+$C$5,IF(E22>=1,E22,$C$4+E22))-(N(F22)+N(G22)+N(H22))/1440)*1440,0)/1440) | L22: =IF(O22="","",ROUND(O22*1440,0)/1440) | M22: =IF(O22="","",IF(O22=$R$29,"Sit down to eat",IF(ISNUMBER(MATCH(O22,$R$9:$R$28,0)),"Prepare: "&INDEX($B$9:$B$28,MATCH(O22,$R$9:$R$28,0)),IF(ISNUMBER(MATCH(O22,$S$9:$S$28,0)),"Cook: "&INDEX($B$9:$B$28,MATCH(O22,$S$9:$S$28,0)),"Rest: "&INDEX($B$9:$B$28,MATCH(O22,$T$9:$T$28,0)))))) | O22: =IF(14<=COUNT($R$9:$T$29),SMALL($R$9:$T$29,14),"") | R22: =IF(OR(B22="",N(F22)=0),"",IF(E22="",$C$4+$C$5,IF(E22>=1,E22,$C$4+E22))-(N(F22)+N(G22)+N(H22))/1440+(100+ROW())/10000000) | S22: =IF(OR(B22="",N(G22)=0),"",IF(E22="",$C$4+$C$5,IF(E22>=1,E22,$C$4+E22))-(N(G22)+N(H22))/1440+(200+ROW())/10000000) | T22: =IF(OR(B22="",N(H22)=0),"",IF(E22="",$C$4+$C$5,IF(E22>=1,E22,$C$4+E22))-N(H22)/1440+(300+ROW())/10000000)
I23: =IF(OR(B23="",(N(F23)+N(G23)+N(H23))=0),"",ROUND((IF(E23="",$C$4+$C$5,IF(E23>=1,E23,$C$4+E23))-(N(F23)+N(G23)+N(H23))/1440)*1440,0)/1440) | L23: =IF(O23="","",ROUND(O23*1440,0)/1440) | M23: =IF(O23="","",IF(O23=$R$29,"Sit down to eat",IF(ISNUMBER(MATCH(O23,$R$9:$R$28,0)),"Prepare: "&INDEX($B$9:$B$28,MATCH(O23,$R$9:$R$28,0)),IF(ISNUMBER(MATCH(O23,$S$9:$S$28,0)),"Cook: "&INDEX($B$9:$B$28,MATCH(O23,$S$9:$S$28,0)),"Rest: "&INDEX($B$9:$B$28,MATCH(O23,$T$9:$T$28,0)))))) | O23: =IF(15<=COUNT($R$9:$T$29),SMALL($R$9:$T$29,15),"") | R23: =IF(OR(B23="",N(F23)=0),"",IF(E23="",$C$4+$C$5,IF(E23>=1,E23,$C$4+E23))-(N(F23)+N(G23)+N(H23))/1440+(100+ROW())/10000000) | S23: =IF(OR(B23="",N(G23)=0),"",IF(E23="",$C$4+$C$5,IF(E23>=1,E23,$C$4+E23))-(N(G23)+N(H23))/1440+(200+ROW())/10000000) | T23: =IF(OR(B23="",N(H23)=0),"",IF(E23="",$C$4+$C$5,IF(E23>=1,E23,$C$4+E23))-N(H23)/1440+(300+ROW())/10000000)
I24: =IF(OR(B24="",(N(F24)+N(G24)+N(H24))=0),"",ROUND((IF(E24="",$C$4+$C$5,IF(E24>=1,E24,$C$4+E24))-(N(F24)+N(G24)+N(H24))/1440)*1440,0)/1440) | L24: =IF(O24="","",ROUND(O24*1440,0)/1440) | M24: =IF(O24="","",IF(O24=$R$29,"Sit down to eat",IF(ISNUMBER(MATCH(O24,$R$9:$R$28,0)),"Prepare: "&INDEX($B$9:$B$28,MATCH(O24,$R$9:$R$28,0)),IF(ISNUMBER(MATCH(O24,$S$9:$S$28,0)),"Cook: "&INDEX($B$9:$B$28,MATCH(O24,$S$9:$S$28,0)),"Rest: "&INDEX($B$9:$B$28,MATCH(O24,$T$9:$T$28,0)))))) | O24: =IF(16<=COUNT($R$9:$T$29),SMALL($R$9:$T$29,16),"") | R24: =IF(OR(B24="",N(F24)=0),"",IF(E24="",$C$4+$C$5,IF(E24>=1,E24,$C$4+E24))-(N(F24)+N(G24)+N(H24))/1440+(100+ROW())/10000000) | S24: =IF(OR(B24="",N(G24)=0),"",IF(E24="",$C$4+$C$5,IF(E24>=1,E24,$C$4+E24))-(N(G24)+N(H24))/1440+(200+ROW())/10000000) | T24: =IF(OR(B24="",N(H24)=0),"",IF(E24="",$C$4+$C$5,IF(E24>=1,E24,$C$4+E24))-N(H24)/1440+(300+ROW())/10000000)
I25: =IF(OR(B25="",(N(F25)+N(G25)+N(H25))=0),"",ROUND((IF(E25="",$C$4+$C$5,IF(E25>=1,E25,$C$4+E25))-(N(F25)+N(G25)+N(H25))/1440)*1440,0)/1440) | L25: =IF(O25="","",ROUND(O25*1440,0)/1440) | M25: =IF(O25="","",IF(O25=$R$29,"Sit down to eat",IF(ISNUMBER(MATCH(O25,$R$9:$R$28,0)),"Prepare: "&INDEX($B$9:$B$28,MATCH(O25,$R$9:$R$28,0)),IF(ISNUMBER(MATCH(O25,$S$9:$S$28,0)),"Cook: "&INDEX($B$9:$B$28,MATCH(O25,$S$9:$S$28,0)),"Rest: "&INDEX($B$9:$B$28,MATCH(O25,$T$9:$T$28,0)))))) | O25: =IF(17<=COUNT($R$9:$T$29),SMALL($R$9:$T$29,17),"") | R25: =IF(OR(B25="",N(F25)=0),"",IF(E25="",$C$4+$C$5,IF(E25>=1,E25,$C$4+E25))-(N(F25)+N(G25)+N(H25))/1440+(100+ROW())/10000000) | S25: =IF(OR(B25="",N(G25)=0),"",IF(E25="",$C$4+$C$5,IF(E25>=1,E25,$C$4+E25))-(N(G25)+N(H25))/1440+(200+ROW())/10000000) | T25: =IF(OR(B25="",N(H25)=0),"",IF(E25="",$C$4+$C$5,IF(E25>=1,E25,$C$4+E25))-N(H25)/1440+(300+ROW())/10000000)
I26: =IF(OR(B26="",(N(F26)+N(G26)+N(H26))=0),"",ROUND((IF(E26="",$C$4+$C$5,IF(E26>=1,E26,$C$4+E26))-(N(F26)+N(G26)+N(H26))/1440)*1440,0)/1440) | L26: =IF(O26="","",ROUND(O26*1440,0)/1440) | M26: =IF(O26="","",IF(O26=$R$29,"Sit down to eat",IF(ISNUMBER(MATCH(O26,$R$9:$R$28,0)),"Prepare: "&INDEX($B$9:$B$28,MATCH(O26,$R$9:$R$28,0)),IF(ISNUMBER(MATCH(O26,$S$9:$S$28,0)),"Cook: "&INDEX($B$9:$B$28,MATCH(O26,$S$9:$S$28,0)),"Rest: "&INDEX($B$9:$B$28,MATCH(O26,$T$9:$T$28,0)))))) | O26: =IF(18<=COUNT($R$9:$T$29),SMALL($R$9:$T$29,18),"") | R26: =IF(OR(B26="",N(F26)=0),"",IF(E26="",$C$4+$C$5,IF(E26>=1,E26,$C$4+E26))-(N(F26)+N(G26)+N(H26))/1440+(100+ROW())/10000000) | S26: =IF(OR(B26="",N(G26)=0),"",IF(E26="",$C$4+$C$5,IF(E26>=1,E26,$C$4+E26))-(N(G26)+N(H26))/1440+(200+ROW())/10000000) | T26: =IF(OR(B26="",N(H26)=0),"",IF(E26="",$C$4+$C$5,IF(E26>=1,E26,$C$4+E26))-N(H26)/1440+(300+ROW())/10000000)
I27: =IF(OR(B27="",(N(F27)+N(G27)+N(H27))=0),"",ROUND((IF(E27="",$C$4+$C$5,IF(E27>=1,E27,$C$4+E27))-(N(F27)+N(G27)+N(H27))/1440)*1440,0)/1440) | L27: =IF(O27="","",ROUND(O27*1440,0)/1440) | M27: =IF(O27="","",IF(O27=$R$29,"Sit down to eat",IF(ISNUMBER(MATCH(O27,$R$9:$R$28,0)),"Prepare: "&INDEX($B$9:$B$28,MATCH(O27,$R$9:$R$28,0)),IF(ISNUMBER(MATCH(O27,$S$9:$S$28,0)),"Cook: "&INDEX($B$9:$B$28,MATCH(O27,$S$9:$S$28,0)),"Rest: "&INDEX($B$9:$B$28,MATCH(O27,$T$9:$T$28,0)))))) | O27: =IF(19<=COUNT($R$9:$T$29),SMALL($R$9:$T$29,19),"") | R27: =IF(OR(B27="",N(F27)=0),"",IF(E27="",$C$4+$C$5,IF(E27>=1,E27,$C$4+E27))-(N(F27)+N(G27)+N(H27))/1440+(100+ROW())/10000000) | S27: =IF(OR(B27="",N(G27)=0),"",IF(E27="",$C$4+$C$5,IF(E27>=1,E27,$C$4+E27))-(N(G27)+N(H27))/1440+(200+ROW())/10000000) | T27: =IF(OR(B27="",N(H27)=0),"",IF(E27="",$C$4+$C$5,IF(E27>=1,E27,$C$4+E27))-N(H27)/1440+(300+ROW())/10000000)
I28: =IF(OR(B28="",(N(F28)+N(G28)+N(H28))=0),"",ROUND((IF(E28="",$C$4+$C$5,IF(E28>=1,E28,$C$4+E28))-(N(F28)+N(G28)+N(H28))/1440)*1440,0)/1440) | L28: =IF(O28="","",ROUND(O28*1440,0)/1440) | M28: =IF(O28="","",IF(O28=$R$29,"Sit down to eat",IF(ISNUMBER(MATCH(O28,$R$9:$R$28,0)),"Prepare: "&INDEX($B$9:$B$28,MATCH(O28,$R$9:$R$28,0)),IF(ISNUMBER(MATCH(O28,$S$9:$S$28,0)),"Cook: "&INDEX($B$9:$B$28,MATCH(O28,$S$9:$S$28,0)),"Rest: "&INDEX($B$9:$B$28,MATCH(O28,$T$9:$T$28,0)))))) | O28: =IF(20<=COUNT($R$9:$T$29),SMALL($R$9:$T$29,20),"") | R28: =IF(OR(B28="",N(F28)=0),"",IF(E28="",$C$4+$C$5,IF(E28>=1,E28,$C$4+E28))-(N(F28)+N(G28)+N(H28))/1440+(100+ROW())/10000000) | S28: =IF(OR(B28="",N(G28)=0),"",IF(E28="",$C$4+$C$5,IF(E28>=1,E28,$C$4+E28))-(N(G28)+N(H28))/1440+(200+ROW())/10000000) | T28: =IF(OR(B28="",N(H28)=0),"",IF(E28="",$C$4+$C$5,IF(E28>=1,E28,$C$4+E28))-N(H28)/1440+(300+ROW())/10000000)
L29: =IF(O29="","",ROUND(O29*1440,0)/1440) | M29: =IF(O29="","",IF(O29=$R$29,"Sit down to eat",IF(ISNUMBER(MATCH(O29,$R$9:$R$28,0)),"Prepare: "&INDEX($B$9:$B$28,MATCH(O29,$R$9:$R$28,0)),IF(ISNUMBER(MATCH(O29,$S$9:$S$28,0)),"Cook: "&INDEX($B$9:$B$28,MATCH(O29,$S$9:$S$28,0)),"Rest: "&INDEX($B$9:$B$28,MATCH(O29,$T$9:$T$28,0)))))) | O29: =IF(21<=COUNT($R$9:$T$29),SMALL($R$9:$T$29,21),"") | R29: =$C$4+$C$5+999/10000000
L30: =IF(O30="","",ROUND(O30*1440,0)/1440) | M30: =IF(O30="","",IF(O30=$R$29,"Sit down to eat",IF(ISNUMBER(MATCH(O30,$R$9:$R$28,0)),"Prepare: "&INDEX($B$9:$B$28,MATCH(O30,$R$9:$R$28,0)),IF(ISNUMBER(MATCH(O30,$S$9:$S$28,0)),"Cook: "&INDEX($B$9:$B$28,MATCH(O30,$S$9:$S$28,0)),"Rest: "&INDEX($B$9:$B$28,MATCH(O30,$T$9:$T$28,0)))))) | O30: =IF(22<=COUNT($R$9:$T$29),SMALL($R$9:$T$29,22),"")
B31: Guest | C31: Coming | D31: Diet or allergies | L31: =IF(O31="","",ROUND(O31*1440,0)/1440) | M31: =IF(O31="","",IF(O31=$R$29,"Sit down to eat",IF(ISNUMBER(MATCH(O31,$R$9:$R$28,0)),"Prepare: "&INDEX($B$9:$B$28,MATCH(O31,$R$9:$R$28,0)),IF(ISNUMBER(MATCH(O31,$S$9:$S$28,0)),"Cook: "&INDEX($B$9:$B$28,MATCH(O31,$S$9:$S$28,0)),"Rest: "&INDEX($B$9:$B$28,MATCH(O31,$T$9:$T$28,0)))))) | O31: =IF(23<=COUNT($R$9:$T$29),SMALL($R$9:$T$29,23),"")
B32: Me | C32: x | L32: =IF(O32="","",ROUND(O32*1440,0)/1440) | M32: =IF(O32="","",IF(O32=$R$29,"Sit down to eat",IF(ISNUMBER(MATCH(O32,$R$9:$R$28,0)),"Prepare: "&INDEX($B$9:$B$28,MATCH(O32,$R$9:$R$28,0)),IF(ISNUMBER(MATCH(O32,$S$9:$S$28,0)),"Cook: "&INDEX($B$9:$B$28,MATCH(O32,$S$9:$S$28,0)),"Rest: "&INDEX($B$9:$B$28,MATCH(O32,$T$9:$T$28,0)))))) | O32: =IF(24<=COUNT($R$9:$T$29),SMALL($R$9:$T$29,24),"")
B33: Sam | C33: x | D33: Vegetarian | L33: =IF(O33="","",ROUND(O33*1440,0)/1440) | M33: =IF(O33="","",IF(O33=$R$29,"Sit down to eat",IF(ISNUMBER(MATCH(O33,$R$9:$R$28,0)),"Prepare: "&INDEX($B$9:$B$28,MATCH(O33,$R$9:$R$28,0)),IF(ISNUMBER(MATCH(O33,$S$9:$S$28,0)),"Cook: "&INDEX($B$9:$B$28,MATCH(O33,$S$9:$S$28,0)),"Rest: "&INDEX($B$9:$B$28,MATCH(O33,$T$9:$T$28,0)))))) | O33: =IF(25<=COUNT($R$9:$T$29),SMALL($R$9:$T$29,25),"")
B34: Kate | C34: x | L34: =IF(O34="","",ROUND(O34*1440,0)/1440) | M34: =IF(O34="","",IF(O34=$R$29,"Sit down to eat",IF(ISNUMBER(MATCH(O34,$R$9:$R$28,0)),"Prepare: "&INDEX($B$9:$B$28,MATCH(O34,$R$9:$R$28,0)),IF(ISNUMBER(MATCH(O34,$S$9:$S$28,0)),"Cook: "&INDEX($B$9:$B$28,MATCH(O34,$S$9:$S$28,0)),"Rest: "&INDEX($B$9:$B$28,MATCH(O34,$T$9:$T$28,0)))))) | O34: =IF(26<=COUNT($R$9:$T$29),SMALL($R$9:$T$29,26),"")
B35: Grandma | C35: x | D35: Soft food | L35: =IF(O35="","",ROUND(O35*1440,0)/1440) | M35: =IF(O35="","",IF(O35=$R$29,"Sit down to eat",IF(ISNUMBER(MATCH(O35,$R$9:$R$28,0)),"Prepare: "&INDEX($B$9:$B$28,MATCH(O35,$R$9:$R$28,0)),IF(ISNUMBER(MATCH(O35,$S$9:$S$28,0)),"Cook: "&INDEX($B$9:$B$28,MATCH(O35,$S$9:$S$28,0)),"Rest: "&INDEX($B$9:$B$28,MATCH(O35,$T$9:$T$28,0)))))) | O35: =IF(27<=COUNT($R$9:$T$29),SMALL($R$9:$T$29,27),"")
B36: Mum | C36: x | L36: =IF(O36="","",ROUND(O36*1440,0)/1440) | M36: =IF(O36="","",IF(O36=$R$29,"Sit down to eat",IF(ISNUMBER(MATCH(O36,$R$9:$R$28,0)),"Prepare: "&INDEX($B$9:$B$28,MATCH(O36,$R$9:$R$28,0)),IF(ISNUMBER(MATCH(O36,$S$9:$S$28,0)),"Cook: "&INDEX($B$9:$B$28,MATCH(O36,$S$9:$S$28,0)),"Rest: "&INDEX($B$9:$B$28,MATCH(O36,$T$9:$T$28,0)))))) | O36: =IF(28<=COUNT($R$9:$T$29),SMALL($R$9:$T$29,28),"")
B37: Dad | C37: x | D37: No nuts | L37: =IF(O37="","",ROUND(O37*1440,0)/1440) | M37: =IF(O37="","",IF(O37=$R$29,"Sit down to eat",IF(ISNUMBER(MATCH(O37,$R$9:$R$28,0)),"Prepare: "&INDEX($B$9:$B$28,MATCH(O37,$R$9:$R$28,0)),IF(ISNUMBER(MATCH(O37,$S$9:$S$28,0)),"Cook: "&INDEX($B$9:$B$28,MATCH(O37,$S$9:$S$28,0)),"Rest: "&INDEX($B$9:$B$28,MATCH(O37,$T$9:$T$28,0)))))) | O37: =IF(29<=COUNT($R$9:$T$29),SMALL($R$9:$T$29,29),"")
B38: Priya | C38: x | D38: Gluten free | L38: =IF(O38="","",ROUND(O38*1440,0)/1440) | M38: =IF(O38="","",IF(O38=$R$29,"Sit down to eat",IF(ISNUMBER(MATCH(O38,$R$9:$R$28,0)),"Prepare: "&INDEX($B$9:$B$28,MATCH(O38,$R$9:$R$28,0)),IF(ISNUMBER(MATCH(O38,$S$9:$S$28,0)),"Cook: "&INDEX($B$9:$B$28,MATCH(O38,$S$9:$S$28,0)),"Rest: "&INDEX($B$9:$B$28,MATCH(O38,$T$9:$T$28,0)))))) | O38: =IF(30<=COUNT($R$9:$T$29),SMALL($R$9:$T$29,30),"")
B39: Tom | C39: x | L39: =IF(O39="","",ROUND(O39*1440,0)/1440) | M39: =IF(O39="","",IF(O39=$R$29,"Sit down to eat",IF(ISNUMBER(MATCH(O39,$R$9:$R$28,0)),"Prepare: "&INDEX($B$9:$B$28,MATCH(O39,$R$9:$R$28,0)),IF(ISNUMBER(MATCH(O39,$S$9:$S$28,0)),"Cook: "&INDEX($B$9:$B$28,MATCH(O39,$S$9:$S$28,0)),"Rest: "&INDEX($B$9:$B$28,MATCH(O39,$T$9:$T$28,0)))))) | O39: =IF(31<=COUNT($R$9:$T$29),SMALL($R$9:$T$29,31),"")
B40: Aunt Rose | D40: Not sure yet | L40: =IF(O40="","",ROUND(O40*1440,0)/1440) | M40: =IF(O40="","",IF(O40=$R$29,"Sit down to eat",IF(ISNUMBER(MATCH(O40,$R$9:$R$28,0)),"Prepare: "&INDEX($B$9:$B$28,MATCH(O40,$R$9:$R$28,0)),IF(ISNUMBER(MATCH(O40,$S$9:$S$28,0)),"Cook: "&INDEX($B$9:$B$28,MATCH(O40,$S$9:$S$28,0)),"Rest: "&INDEX($B$9:$B$28,MATCH(O40,$T$9:$T$28,0)))))) | O40: =IF(32<=COUNT($R$9:$T$29),SMALL($R$9:$T$29,32),"")
L41: =IF(O41="","",ROUND(O41*1440,0)/1440) | M41: =IF(O41="","",IF(O41=$R$29,"Sit down to eat",IF(ISNUMBER(MATCH(O41,$R$9:$R$28,0)),"Prepare: "&INDEX($B$9:$B$28,MATCH(O41,$R$9:$R$28,0)),IF(ISNUMBER(MATCH(O41,$S$9:$S$28,0)),"Cook: "&INDEX($B$9:$B$28,MATCH(O41,$S$9:$S$28,0)),"Rest: "&INDEX($B$9:$B$28,MATCH(O41,$T$9:$T$28,0)))))) | O41: =IF(33<=COUNT($R$9:$T$29),SMALL($R$9:$T$29,33),"")
L42: =IF(O42="","",ROUND(O42*1440,0)/1440) | M42: =IF(O42="","",IF(O42=$R$29,"Sit down to eat",IF(ISNUMBER(MATCH(O42,$R$9:$R$28,0)),"Prepare: "&INDEX($B$9:$B$28,MATCH(O42,$R$9:$R$28,0)),IF(ISNUMBER(MATCH(O42,$S$9:$S$28,0)),"Cook: "&INDEX($B$9:$B$28,MATCH(O42,$S$9:$S$28,0)),"Rest: "&INDEX($B$9:$B$28,MATCH(O42,$T$9:$T$28,0)))))) | O42: =IF(34<=COUNT($R$9:$T$29),SMALL($R$9:$T$29,34),"")
L43: =IF(O43="","",ROUND(O43*1440,0)/1440) | M43: =IF(O43="","",IF(O43=$R$29,"Sit down to eat",IF(ISNUMBER(MATCH(O43,$R$9:$R$28,0)),"Prepare: "&INDEX($B$9:$B$28,MATCH(O43,$R$9:$R$28,0)),IF(ISNUMBER(MATCH(O43,$S$9:$S$28,0)),"Cook: "&INDEX($B$9:$B$28,MATCH(O43,$S$9:$S$28,0)),"Rest: "&INDEX($B$9:$B$28,MATCH(O43,$T$9:$T$28,0)))))) | O43: =IF(35<=COUNT($R$9:$T$29),SMALL($R$9:$T$29,35),"")
L44: =IF(O44="","",ROUND(O44*1440,0)/1440) | M44: =IF(O44="","",IF(O44=$R$29,"Sit down to eat",IF(ISNUMBER(MATCH(O44,$R$9:$R$28,0)),"Prepare: "&INDEX($B$9:$B$28,MATCH(O44,$R$9:$R$28,0)),IF(ISNUMBER(MATCH(O44,$S$9:$S$28,0)),"Cook: "&INDEX($B$9:$B$28,MATCH(O44,$S$9:$S$28,0)),"Rest: "&INDEX($B$9:$B$28,MATCH(O44,$T$9:$T$28,0)))))) | O44: =IF(36<=COUNT($R$9:$T$29),SMALL($R$9:$T$29,36),"")
L45: =IF(O45="","",ROUND(O45*1440,0)/1440) | M45: =IF(O45="","",IF(O45=$R$29,"Sit down to eat",IF(ISNUMBER(MATCH(O45,$R$9:$R$28,0)),"Prepare: "&INDEX($B$9:$B$28,MATCH(O45,$R$9:$R$28,0)),IF(ISNUMBER(MATCH(O45,$S$9:$S$28,0)),"Cook: "&INDEX($B$9:$B$28,MATCH(O45,$S$9:$S$28,0)),"Rest: "&INDEX($B$9:$B$28,MATCH(O45,$T$9:$T$28,0)))))) | O45: =IF(37<=COUNT($R$9:$T$29),SMALL($R$9:$T$29,37),"")
L46: =IF(O46="","",ROUND(O46*1440,0)/1440) | M46: =IF(O46="","",IF(O46=$R$29,"Sit down to eat",IF(ISNUMBER(MATCH(O46,$R$9:$R$28,0)),"Prepare: "&INDEX($B$9:$B$28,MATCH(O46,$R$9:$R$28,0)),IF(ISNUMBER(MATCH(O46,$S$9:$S$28,0)),"Cook: "&INDEX($B$9:$B$28,MATCH(O46,$S$9:$S$28,0)),"Rest: "&INDEX($B$9:$B$28,MATCH(O46,$T$9:$T$28,0)))))) | O46: =IF(38<=COUNT($R$9:$T$29),SMALL($R$9:$T$29,38),"")
L47: =IF(O47="","",ROUND(O47*1440,0)/1440) | M47: =IF(O47="","",IF(O47=$R$29,"Sit down to eat",IF(ISNUMBER(MATCH(O47,$R$9:$R$28,0)),"Prepare: "&INDEX($B$9:$B$28,MATCH(O47,$R$9:$R$28,0)),IF(ISNUMBER(MATCH(O47,$S$9:$S$28,0)),"Cook: "&INDEX($B$9:$B$28,MATCH(O47,$S$9:$S$28,0)),"Rest: "&INDEX($B$9:$B$28,MATCH(O47,$T$9:$T$28,0)))))) | O47: =IF(39<=COUNT($R$9:$T$29),SMALL($R$9:$T$29,39),"")
L48: =IF(O48="","",ROUND(O48*1440,0)/1440) | M48: =IF(O48="","",IF(O48=$R$29,"Sit down to eat",IF(ISNUMBER(MATCH(O48,$R$9:$R$28,0)),"Prepare: "&INDEX($B$9:$B$28,MATCH(O48,$R$9:$R$28,0)),IF(ISNUMBER(MATCH(O48,$S$9:$S$28,0)),"Cook: "&INDEX($B$9:$B$28,MATCH(O48,$S$9:$S$28,0)),"Rest: "&INDEX($B$9:$B$28,MATCH(O48,$T$9:$T$28,0)))))) | O48: =IF(40<=COUNT($R$9:$T$29),SMALL($R$9:$T$29,40),"")
L49: =IF(COUNT($R$9:$T$29)>40,"More steps than fit here.","")

Sheet Plans
B2: Plans
B3: Parties, school events, travel and the days to get things done. The December tab puts them on a calendar.
B5: Date | C5: Time | D5: What | E5: Where | F5: Notes
B6: 46340 | D6: Order the turkey | E6: Butcher | H6: =IF(B6="","",B6+MOD(N(C6),1)+ROW()/10000000)
B7: 46353 | C7: 0.41666667 | D7: Gift shopping day | E7: Town centre | H7: =IF(B7="","",B7+MOD(N(C7),1)+ROW()/10000000)
B8: 46357 | D8: Advent calendars start | E8: Home | H8: =IF(B8="","",B8+MOD(N(C8),1)+ROW()/10000000)
B9: 46361 | C9: 0.58333333 | D9: Tree up and decorating | E9: Home | H9: =IF(B9="","",B9+MOD(N(C9),1)+ROW()/10000000)
B10: 46364 | C10: 0.79166667 | D10: Office party | E10: The Old Mill | H10: =IF(B10="","",B10+MOD(N(C10),1)+ROW()/10000000)
B11: 46367 | C11: 0.60416667 | D11: School concert | E11: School hall | H11: =IF(B11="","",B11+MOD(N(C11),1)+ROW()/10000000)
B12: 46368 | C12: 0.41666667 | D12: Post the cards | E12: Post office | H12: =IF(B12="","",B12+MOD(N(C12),1)+ROW()/10000000)
B13: 46369 | C13: 0.625 | D13: Pantomime | E13: Theatre | H13: =IF(B13="","",B13+MOD(N(C13),1)+ROW()/10000000)
B14: 46375 | C14: 0.45833333 | D14: Christmas market | E14: Market square | H14: =IF(B14="","",B14+MOD(N(C14),1)+ROW()/10000000)
B15: 46375 | C15: 0.75 | D15: Drinks with Priya and Tom | H15: =IF(B15="","",B15+MOD(N(C15),1)+ROW()/10000000)
B16: 46376 | C16: 0.70833333 | D16: Carol singing | E16: Church | H16: =IF(B16="","",B16+MOD(N(C16),1)+ROW()/10000000)
B17: 46378 | C17: 0.5 | D17: Pick up the turkey | E17: Butcher | H17: =IF(B17="","",B17+MOD(N(C17),1)+ROW()/10000000)
B18: 46379 | C18: 0.375 | D18: Big food shop | E18: Supermarket | H18: =IF(B18="","",B18+MOD(N(C18),1)+ROW()/10000000)
B19: 46380 | C19: 0.75 | D19: Christmas Eve at Grandma's | E19: Westford | H19: =IF(B19="","",B19+MOD(N(C19),1)+ROW()/10000000)
B20: 46381 | C20: 0.625 | D20: Christmas dinner | E20: Home | H20: =IF(B20="","",B20+MOD(N(C20),1)+ROW()/10000000)
B21: 46382 | C21: 0.45833333 | D21: Boxing Day walk | E21: The river | H21: =IF(B21="","",B21+MOD(N(C21),1)+ROW()/10000000)
B22: 46387 | C22: 0.83333333 | D22: New Year's Eve party | E22: Sam and Kate's | H22: =IF(B22="","",B22+MOD(N(C22),1)+ROW()/10000000)
H23: =IF(B23="","",B23+MOD(N(C23),1)+ROW()/10000000)
H24: =IF(B24="","",B24+MOD(N(C24),1)+ROW()/10000000)
H25: =IF(B25="","",B25+MOD(N(C25),1)+ROW()/10000000)
H26: =IF(B26="","",B26+MOD(N(C26),1)+ROW()/10000000)
H27: =IF(B27="","",B27+MOD(N(C27),1)+ROW()/10000000)
H28: =IF(B28="","",B28+MOD(N(C28),1)+ROW()/10000000)
H29: =IF(B29="","",B29+MOD(N(C29),1)+ROW()/10000000)
H30: =IF(B30="","",B30+MOD(N(C30),1)+ROW()/10000000)
H31: =IF(B31="","",B31+MOD(N(C31),1)+ROW()/10000000)
H32: =IF(B32="","",B32+MOD(N(C32),1)+ROW()/10000000)
H33: =IF(B33="","",B33+MOD(N(C33),1)+ROW()/10000000)
H34: =IF(B34="","",B34+MOD(N(C34),1)+ROW()/10000000)
... H155: =IF(B155="","",B155+MOD(N(C155),1)+ROW()/10000000)

Sheet December
B2: ="December "&Settings!$C$4
B3: Everything on the Plans tab, day by day. Up to two plans a day are shown.
B5: Monday | C5: Tuesday | D5: Wednesday | E5: Thursday | F5: Friday | G5: Saturday | H5: Sunday
B6: =IF(MONTH(((DATE(Settings!$C$4,12,1)-WEEKDAY(DATE(Settings!$C$4,12,1),3))+0))=12,DAY(((DATE(Settings!$C$4,12,1)-WEEKDAY(DATE(Settings!$C$4,12,1),3))+0)),"") | C6: =IF(MONTH(((DATE(Settings!$C$4,12,1)-WEEKDAY(DATE(Settings!$C$4,12,1),3))+1))=12,DAY(((DATE(Settings!$C$4,12,1)-WEEKDAY(DATE(Settings!$C$4,12,1),3))+1)),"") | D6: =IF(MONTH(((DATE(Settings!$C$4,12,1)-WEEKDAY(DATE(Settings!$C$4,12,1),3))+2))=12,DAY(((DATE(Settings!$C$4,12,1)-WEEKDAY(DATE(Settings!$C$4,12,1),3))+2)),"") | E6: =IF(MONTH(((DATE(Settings!$C$4,12,1)-WEEKDAY(DATE(Settings!$C$4,12,1),3))+3))=12,DAY(((DATE(Settings!$C$4,12,1)-WEEKDAY(DATE(Settings!$C$4,12,1),3))+3)),"") | F6: =IF(MONTH(((DATE(Settings!$C$4,12,1)-WEEKDAY(DATE(Settings!$C$4,12,1),3))+4))=12,DAY(((DATE(Settings!$C$4,12,1)-WEEKDAY(DATE(Settings!$C$4,12,1),3))+4)),"") | G6: =IF(MONTH(((DATE(Settings!$C$4,12,1)-WEEKDAY(DATE(Settings!$C$4,12,1),3))+5))=12,DAY(((DATE(Settings!$C$4,12,1)-WEEKDAY(DATE(Settings!$C$4,12,1),3))+5)),"") | H6: =IF(MONTH(((DATE(Settings!$C$4,12,1)-WEEKDAY(DATE(Settings!$C$4,12,1),3))+6))=12,DAY(((DATE(Settings!$C$4,12,1)-WEEKDAY(DATE(Settings!$C$4,12,1),3))+6)),"")
B7: =IF(OR(MONTH(((DATE(Settings!$C$4,12,1)-WEEKDAY(DATE(Settings!$C$4,12,1),3))+0))<>12,COUNTIFS(Plans!$H$6:$H$155,">="&((DATE(Settings!$C$4,12,1)-WEEKDAY(DATE(Settings!$C$4,12,1),3))+0),Plans!$H$6:$H$155,"<"&(((DATE(Settings!$C$4,12,1)-WEEKDAY(DATE(Settings!$C$4,12,1),3))+0)+1))=0),"",INDEX(Plans!$D$6:$D$155,MATCH(SMALL(Plans!$H$6:$H$155,COUNTIF(Plans!$H$6:$H$155,"<"&((DATE(Settings!$C$4,12,1)-WEEKDAY(DATE(Settings!$C$4,12,1),3))+0))+1),Plans!$H$6:$H$155,0))&IF(COUNTIFS(Plans!$H$6:$H$155,">="&((DATE(Settings!$C$4,12,1)-WEEKDAY(DATE(Settings!$C$4,12,1),3))+0),Plans!$H$6:$H$155,"<"&(((DATE(Settings!$C$4,12,1)-WEEKDAY(DATE(Settings!$C$4,12,1),3))+0)+1))>1,CHAR(10)&INDEX(Plans!$D$6:$D$155,MATCH(SMALL(Plans!$H$6:$H$155,COUNTIF(Plans!$H$6:$H$155,"<"&((DATE(Settings!$C$4,12,1)-WEEKDAY(DATE(Settings!$C$4,12,1),3))+0))+2),Plans!$H$6:$H$155,0)),"")&IF(COUNTIFS(Plans!$H$6:$H$155,">="&((DATE(Settings!$C$4,12,1)-WEEKDAY(DATE(Settings!$C$4,12,1),3))+0),Plans!$H$6:$H$155,"<"&(((DATE(Settings!$C$4,12,1)-WEEKDAY(DATE(Settings!$C$4,12,1),3))+0)+1))>2,CHAR(10)&"+"&(COUNTIFS(Plans!$H$6:$H$155,">="&((DATE(Settings!$C$4,12,1)-WEEKDAY(DATE(Settings!$C$4,12,1),3))+0),Plans!$H$6:$H$155,"<"&(((DATE(Settings!$C$4,12,1)-WEEKDAY(DATE(Settings!$C$4,12,1),3))+0)+1))-2)&" more","")) | C7: =IF(OR(MONTH(((DATE(Settings!$C$4,12,1)-WEEKDAY(DATE(Settings!$C$4,12,1),3))+1))<>12,COUNTIFS(Plans!$H$6:$H$155,">="&((DATE(Settings!$C$4,12,1)-WEEKDAY(DATE(Settings!$C$4,12,1),3))+1),Plans!$H$6:$H$155,"<"&(((DATE(Settings!$C$4,12,1)-WEEKDAY(DATE(Settings!$C$4,12,1),3))+1)+1))=0),"",INDEX(Plans!$D$6:$D$155,MATCH(SMALL(Plans!$H$6:$H$155,COUNTIF(Plans!$H$6:$H$155,"<"&((DATE(Settings!$C$4,12,1)-WEEKDAY(DATE(Settings!$C$4,12,1),3))+1))+1),Plans!$H$6:$H$155,0))&IF(COUNTIFS(Plans!$H$6:$H$155,">="&((DATE(Settings!$C$4,12,1)-WEEKDAY(DATE(Settings!$C$4,12,1),3))+1),Plans!$H$6:$H$155,"<"&(((DATE(Settings!$C$4,12,1)-WEEKDAY(DATE(Settings!$C$4,12,1),3))+1)+1))>1,CHAR(10)&INDEX(Plans!$D$6:$D$155,MATCH(SMALL(Plans!$H$6:$H$155,COUNTIF(Plans!$H$6:$H$155,"<"&((DATE(Settings!$C$4,12,1)-WEEKDAY(DATE(Settings!$C$4,12,1),3))+1))+2),Plans!$H$6:$H$155,0)),"")&IF(COUNTIFS(Plans!$H$6:$H$155,">="&((DATE(Settings!$C$4,12,1)-WEEKDAY(DATE(Settings!$C$4,12,1),3))+1),Plans!$H$6:$H$155,"<"&(((DATE(Settings!$C$4,12,1)-WEEKDAY(DATE(Settings!$C$4,12,1),3))+1)+1))>2,CHAR(10)&"+"&(COUNTIFS(Plans!$H$6:$H$155,">="&((DATE(Settings!$C$4,12,1)-WEEKDAY(DATE(Settings!$C$4,12,1),3))+1),Plans!$H$6:$H$155,"<"&(((DATE(Settings!$C$4,12,1)-WEEKDAY(DATE(Settings!$C$4,12,1),3))+1)+1))-2)&" more","")) | D7: =IF(OR(MONTH(((DATE(Settings!$C$4,12,1)-WEEKDAY(DATE(Settings!$C$4,12,1),3))+2))<>12,COUNTIFS(Plans!$H$6:$H$155,">="&((DATE(Settings!$C$4,12,1)-WEEKDAY(DATE(Settings!$C$4,12,1),3))+2),Plans!$H$6:$H$155,"<"&(((DATE(Settings!$C$4,12,1)-WEEKDAY(DATE(Settings!$C$4,12,1),3))+2)+1))=0),"",INDEX(Plans!$D$6:$D$155,MATCH(SMALL(Plans!$H$6:$H$155,COUNTIF(Plans!$H$6:$H$155,"<"&((DATE(Settings!$C$4,12,1)-WEEKDAY(DATE(Settings!$C$4,12,1),3))+2))+1),Plans!$H$6:$H$155,0))&IF(COUNTIFS(Plans!$H$6:$H$155,">="&((DATE(Settings!$C$4,12,1)-WEEKDAY(DATE(Settings!$C$4,12,1),3))+2),Plans!$H$6:$H$155,"<"&(((DATE(Settings!$C$4,12,1)-WEEKDAY(DATE(Settings!$C$4,12,1),3))+2)+1))>1,CHAR(10)&INDEX(Plans!$D$6:$D$155,MATCH(SMALL(Plans!$H$6:$H$155,COUNTIF(Plans!$H$6:$H$155,"<"&((DATE(Settings!$C$4,12,1)-WEEKDAY(DATE(Settings!$C$4,12,1),3))+2))+2),Plans!$H$6:$H$155,0)),"")&IF(COUNTIFS(Plans!$H$6:$H$155,">="&((DATE(Settings!$C$4,12,1)-WEEKDAY(DATE(Settings!$C$4,12,1),3))+2),Plans!$H$6:$H$155,"<"&(((DATE(Settings!$C$4,12,1)-WEEKDAY(DATE(Settings!$C$4,12,1),3))+2)+1))>2,CHAR(10)&"+"&(COUNTIFS(Plans!$H$6:$H$155,">="&((DATE(Settings!$C$4,12,1)-WEEKDAY(DATE(Settings!$C$4,12,1),3))+2),Plans!$H$6:$H$155,"<"&(((DATE(Settings!$C$4,12,1)-WEEKDAY(DATE(Settings!$C$4,12,1),3))+2)+1))-2)&" more","")) | E7: =IF(OR(MONTH(((DATE(Settings!$C$4,12,1)-WEEKDAY(DATE(Settings!$C$4,12,1),3))+3))<>12,COUNTIFS(Plans!$H$6:$H$155,">="&((DATE(Settings!$C$4,12,1)-WEEKDAY(DATE(Settings!$C$4,12,1),3))+3),Plans!$H$6:$H$155,"<"&(((DATE(Settings!$C$4,12,1)-WEEKDAY(DATE(Settings!$C$4,12,1),3))+3)+1))=0),"",INDEX(Plans!$D$6:$D$155,MATCH(SMALL(Plans!$H$6:$H$155,COUNTIF(Plans!$H$6:$H$155,"<"&((DATE(Settings!$C$4,12,1)-WEEKDAY(DATE(Settings!$C$4,12,1),3))+3))+1),Plans!$H$6:$H$155,0))&IF(COUNTIFS(Plans!$H$6:$H$155,">="&((DATE(Settings!$C$4,12,1)-WEEKDAY(DATE(Settings!$C$4,12,1),3))+3),Plans!$H$6:$H$155,"<"&(((DATE(Settings!$C$4,12,1)-WEEKDAY(DATE(Settings!$C$4,12,1),3))+3)+1))>1,CHAR(10)&INDEX(Plans!$D$6:$D$155,MATCH(SMALL(Plans!$H$6:$H$155,COUNTIF(Plans!$H$6:$H$155,"<"&((DATE(Settings!$C$4,12,1)-WEEKDAY(DATE(Settings!$C$4,12,1),3))+3))+2),Plans!$H$6:$H$155,0)),"")&IF(COUNTIFS(Plans!$H$6:$H$155,">="&((DATE(Settings!$C$4,12,1)-WEEKDAY(DATE(Settings!$C$4,12,1),3))+3),Plans!$H$6:$H$155,"<"&(((DATE(Settings!$C$4,12,1)-WEEKDAY(DATE(Settings!$C$4,12,1),3))+3)+1))>2,CHAR(10)&"+"&(COUNTIFS(Plans!$H$6:$H$155,">="&((DATE(Settings!$C$4,12,1)-WEEKDAY(DATE(Settings!$C$4,12,1),3))+3),Plans!$H$6:$H$155,"<"&(((DATE(Settings!$C$4,12,1)-WEEKDAY(DATE(Settings!$C$4,12,1),3))+3)+1))-2)&" more","")) | F7: =IF(OR(MONTH(((DATE(Settings!$C$4,12,1)-WEEKDAY(DATE(Settings!$C$4,12,1),3))+4))<>12,COUNTIFS(Plans!$H$6:$H$155,">="&((DATE(Settings!$C$4,12,1)-WEEKDAY(DATE(Settings!$C$4,12,1),3))+4),Plans!$H$6:$H$155,"<"&(((DATE(Settings!$C$4,12,1)-WEEKDAY(DATE(Settings!$C$4,12,1),3))+4)+1))=0),"",INDEX(Plans!$D$6:$D$155,MATCH(SMALL(Plans!$H$6:$H$155,COUNTIF(Plans!$H$6:$H$155,"<"&((DATE(Settings!$C$4,12,1)-WEEKDAY(DATE(Settings!$C$4,12,1),3))+4))+1),Plans!$H$6:$H$155,0))&IF(COUNTIFS(Plans!$H$6:$H$155,">="&((DATE(Settings!$C$4,12,1)-WEEKDAY(DATE(Settings!$C$4,12,1),3))+4),Plans!$H$6:$H$155,"<"&(((DATE(Settings!$C$4,12,1)-WEEKDAY(DATE(Settings!$C$4,12,1),3))+4)+1))>1,CHAR(10)&INDEX(Plans!$D$6:$D$155,MATCH(SMALL(Plans!$H$6:$H$155,COUNTIF(Plans!$H$6:$H$155,"<"&((DATE(Settings!$C$4,12,1)-WEEKDAY(DATE(Settings!$C$4,12,1),3))+4))+2),Plans!$H$6:$H$155,0)),"")&IF(COUNTIFS(Plans!$H$6:$H$155,">="&((DATE(Settings!$C$4,12,1)-WEEKDAY(DATE(Settings!$C$4,12,1),3))+4),Plans!$H$6:$H$155,"<"&(((DATE(Settings!$C$4,12,1)-WEEKDAY(DATE(Settings!$C$4,12,1),3))+4)+1))>2,CHAR(10)&"+"&(COUNTIFS(Plans!$H$6:$H$155,">="&((DATE(Settings!$C$4,12,1)-WEEKDAY(DATE(Settings!$C$4,12,1),3))+4),Plans!$H$6:$H$155,"<"&(((DATE(Settings!$C$4,12,1)-WEEKDAY(DATE(Settings!$C$4,12,1),3))+4)+1))-2)&" more","")) | G7: =IF(OR(MONTH(((DATE(Settings!$C$4,12,1)-WEEKDAY(DATE(Settings!$C$4,12,1),3))+5))<>12,COUNTIFS(Plans!$H$6:$H$155,">="&((DATE(Settings!$C$4,12,1)-WEEKDAY(DATE(Settings!$C$4,12,1),3))+5),Plans!$H$6:$H$155,"<"&(((DATE(Settings!$C$4,12,1)-WEEKDAY(DATE(Settings!$C$4,12,1),3))+5)+1))=0),"",INDEX(Plans!$D$6:$D$155,MATCH(SMALL(Plans!$H$6:$H$155,COUNTIF(Plans!$H$6:$H$155,"<"&((DATE(Settings!$C$4,12,1)-WEEKDAY(DATE(Settings!$C$4,12,1),3))+5))+1),Plans!$H$6:$H$155,0))&IF(COUNTIFS(Plans!$H$6:$H$155,">="&((DATE(Settings!$C$4,12,1)-WEEKDAY(DATE(Settings!$C$4,12,1),3))+5),Plans!$H$6:$H$155,"<"&(((DATE(Settings!$C$4,12,1)-WEEKDAY(DATE(Settings!$C$4,12,1),3))+5)+1))>1,CHAR(10)&INDEX(Plans!$D$6:$D$155,MATCH(SMALL(Plans!$H$6:$H$155,COUNTIF(Plans!$H$6:$H$155,"<"&((DATE(Settings!$C$4,12,1)-WEEKDAY(DATE(Settings!$C$4,12,1),3))+5))+2),Plans!$H$6:$H$155,0)),"")&IF(COUNTIFS(Plans!$H$6:$H$155,">="&((DATE(Settings!$C$4,12,1)-WEEKDAY(DATE(Settings!$C$4,12,1),3))+5),Plans!$H$6:$H$155,"<"&(((DATE(Settings!$C$4,12,1)-WEEKDAY(DATE(Settings!$C$4,12,1),3))+5)+1))>2,CHAR(10)&"+"&(COUNTIFS(Plans!$H$6:$H$155,">="&((DATE(Settings!$C$4,12,1)-WEEKDAY(DATE(Settings!$C$4,12,1),3))+5),Plans!$H$6:$H$155,"<"&(((DATE(Settings!$C$4,12,1)-WEEKDAY(DATE(Settings!$C$4,12,1),3))+5)+1))-2)&" more","")) | H7: =IF(OR(MONTH(((DATE(Settings!$C$4,12,1)-WEEKDAY(DATE(Settings!$C$4,12,1),3))+6))<>12,COUNTIFS(Plans!$H$6:$H$155,">="&((DATE(Settings!$C$4,12,1)-WEEKDAY(DATE(Settings!$C$4,12,1),3))+6),Plans!$H$6:$H$155,"<"&(((DATE(Settings!$C$4,12,1)-WEEKDAY(DATE(Settings!$C$4,12,1),3))+6)+1))=0),"",INDEX(Plans!$D$6:$D$155,MATCH(SMALL(Plans!$H$6:$H$155,COUNTIF(Plans!$H$6:$H$155,"<"&((DATE(Settings!$C$4,12,1)-WEEKDAY(DATE(Settings!$C$4,12,1),3))+6))+1),Plans!$H$6:$H$155,0))&IF(COUNTIFS(Plans!$H$6:$H$155,">="&((DATE(Settings!$C$4,12,1)-WEEKDAY(DATE(Settings!$C$4,12,1),3))+6),Plans!$H$6:$H$155,"<"&(((DATE(Settings!$C$4,12,1)-WEEKDAY(DATE(Settings!$C$4,12,1),3))+6)+1))>1,CHAR(10)&INDEX(Plans!$D$6:$D$155,MATCH(SMALL(Plans!$H$6:$H$155,COUNTIF(Plans!$H$6:$H$155,"<"&((DATE(Settings!$C$4,12,1)-WEEKDAY(DATE(Settings!$C$4,12,1),3))+6))+2),Plans!$H$6:$H$155,0)),"")&IF(COUNTIFS(Plans!$H$6:$H$155,">="&((DATE(Settings!$C$4,12,1)-WEEKDAY(DATE(Settings!$C$4,12,1),3))+6),Plans!$H$6:$H$155,"<"&(((DATE(Settings!$C$4,12,1)-WEEKDAY(DATE(Settings!$C$4,12,1),3))+6)+1))>2,CHAR(10)&"+"&(COUNTIFS(Plans!$H$6:$H$155,">="&((DATE(Settings!$C$4,12,1)-WEEKDAY(DATE(Settings!$C$4,12,1),3))+6),Plans!$H$6:$H$155,"<"&(((DATE(Settings!$C$4,12,1)-WEEKDAY(DATE(Settings!$C$4,12,1),3))+6)+1))-2)&" more",""))
B8: =IF(MONTH(((DATE(Settings!$C$4,12,1)-WEEKDAY(DATE(Settings!$C$4,12,1),3))+7))=12,DAY(((DATE(Settings!$C$4,12,1)-WEEKDAY(DATE(Settings!$C$4,12,1),3))+7)),"") | C8: =IF(MONTH(((DATE(Settings!$C$4,12,1)-WEEKDAY(DATE(Settings!$C$4,12,1),3))+8))=12,DAY(((DATE(Settings!$C$4,12,1)-WEEKDAY(DATE(Settings!$C$4,12,1),3))+8)),"") | D8: =IF(MONTH(((DATE(Settings!$C$4,12,1)-WEEKDAY(DATE(Settings!$C$4,12,1),3))+9))=12,DAY(((DATE(Settings!$C$4,12,1)-WEEKDAY(DATE(Settings!$C$4,12,1),3))+9)),"") | E8: =IF(MONTH(((DATE(Settings!$C$4,12,1)-WEEKDAY(DATE(Settings!$C$4,12,1),3))+10))=12,DAY(((DATE(Settings!$C$4,12,1)-WEEKDAY(DATE(Settings!$C$4,12,1),3))+10)),"") | F8: =IF(MONTH(((DATE(Settings!$C$4,12,1)-WEEKDAY(DATE(Settings!$C$4,12,1),3))+11))=12,DAY(((DATE(Settings!$C$4,12,1)-WEEKDAY(DATE(Settings!$C$4,12,1),3))+11)),"") | G8: =IF(MONTH(((DATE(Settings!$C$4,12,1)-WEEKDAY(DATE(Settings!$C$4,12,1),3))+12))=12,DAY(((DATE(Settings!$C$4,12,1)-WEEKDAY(DATE(Settings!$C$4,12,1),3))+12)),"") | H8: =IF(MONTH(((DATE(Settings!$C$4,12,1)-WEEKDAY(DATE(Settings!$C$4,12,1),3))+13))=12,DAY(((DATE(Settings!$C$4,12,1)-WEEKDAY(DATE(Settings!$C$4,12,1),3))+13)),"")
B9: =IF(OR(MONTH(((DATE(Settings!$C$4,12,1)-WEEKDAY(DATE(Settings!$C$4,12,1),3))+7))<>12,COUNTIFS(Plans!$H$6:$H$155,">="&((DATE(Settings!$C$4,12,1)-WEEKDAY(DATE(Settings!$C$4,12,1),3))+7),Plans!$H$6:$H$155,"<"&(((DATE(Settings!$C$4,12,1)-WEEKDAY(DATE(Settings!$C$4,12,1),3))+7)+1))=0),"",INDEX(Plans!$D$6:$D$155,MATCH(SMALL(Plans!$H$6:$H$155,COUNTIF(Plans!$H$6:$H$155,"<"&((DATE(Settings!$C$4,12,1)-WEEKDAY(DATE(Settings!$C$4,12,1),3))+7))+1),Plans!$H$6:$H$155,0))&IF(COUNTIFS(Plans!$H$6:$H$155,">="&((DATE(Settings!$C$4,12,1)-WEEKDAY(DATE(Settings!$C$4,12,1),3))+7),Plans!$H$6:$H$155,"<"&(((DATE(Settings!$C$4,12,1)-WEEKDAY(DATE(Settings!$C$4,12,1),3))+7)+1))>1,CHAR(10)&INDEX(Plans!$D$6:$D$155,MATCH(SMALL(Plans!$H$6:$H$155,COUNTIF(Plans!$H$6:$H$155,"<"&((DATE(Settings!$C$4,12,1)-WEEKDAY(DATE(Settings!$C$4,12,1),3))+7))+2),Plans!$H$6:$H$155,0)),"")&IF(COUNTIFS(Plans!$H$6:$H$155,">="&((DATE(Settings!$C$4,12,1)-WEEKDAY(DATE(Settings!$C$4,12,1),3))+7),Plans!$H$6:$H$155,"<"&(((DATE(Settings!$C$4,12,1)-WEEKDAY(DATE(Settings!$C$4,12,1),3))+7)+1))>2,CHAR(10)&"+"&(COUNTIFS(Plans!$H$6:$H$155,">="&((DATE(Settings!$C$4,12,1)-WEEKDAY(DATE(Settings!$C$4,12,1),3))+7),Plans!$H$6:$H$155,"<"&(((DATE(Settings!$C$4,12,1)-WEEKDAY(DATE(Settings!$C$4,12,1),3))+7)+1))-2)&" more","")) | C9: =IF(OR(MONTH(((DATE(Settings!$C$4,12,1)-WEEKDAY(DATE(Settings!$C$4,12,1),3))+8))<>12,COUNTIFS(Plans!$H$6:$H$155,">="&((DATE(Settings!$C$4,12,1)-WEEKDAY(DATE(Settings!$C$4,12,1),3))+8),Plans!$H$6:$H$155,"<"&(((DATE(Settings!$C$4,12,1)-WEEKDAY(DATE(Settings!$C$4,12,1),3))+8)+1))=0),"",INDEX(Plans!$D$6:$D$155,MATCH(SMALL(Plans!$H$6:$H$155,COUNTIF(Plans!$H$6:$H$155,"<"&((DATE(Settings!$C$4,12,1)-WEEKDAY(DATE(Settings!$C$4,12,1),3))+8))+1),Plans!$H$6:$H$155,0))&IF(COUNTIFS(Plans!$H$6:$H$155,">="&((DATE(Settings!$C$4,12,1)-WEEKDAY(DATE(Settings!$C$4,12,1),3))+8),Plans!$H$6:$H$155,"<"&(((DATE(Settings!$C$4,12,1)-WEEKDAY(DATE(Settings!$C$4,12,1),3))+8)+1))>1,CHAR(10)&INDEX(Plans!$D$6:$D$155,MATCH(SMALL(Plans!$H$6:$H$155,COUNTIF(Plans!$H$6:$H$155,"<"&((DATE(Settings!$C$4,12,1)-WEEKDAY(DATE(Settings!$C$4,12,1),3))+8))+2),Plans!$H$6:$H$155,0)),"")&IF(COUNTIFS(Plans!$H$6:$H$155,">="&((DATE(Settings!$C$4,12,1)-WEEKDAY(DATE(Settings!$C$4,12,1),3))+8),Plans!$H$6:$H$155,"<"&(((DATE(Settings!$C$4,12,1)-WEEKDAY(DATE(Settings!$C$4,12,1),3))+8)+1))>2,CHAR(10)&"+"&(COUNTIFS(Plans!$H$6:$H$155,">="&((DATE(Settings!$C$4,12,1)-WEEKDAY(DATE(Settings!$C$4,12,1),3))+8),Plans!$H$6:$H$155,"<"&(((DATE(Settings!$C$4,12,1)-WEEKDAY(DATE(Settings!$C$4,12,1),3))+8)+1))-2)&" more","")) | D9: =IF(OR(MONTH(((DATE(Settings!$C$4,12,1)-WEEKDAY(DATE(Settings!$C$4,12,1),3))+9))<>12,COUNTIFS(Plans!$H$6:$H$155,">="&((DATE(Settings!$C$4,12,1)-WEEKDAY(DATE(Settings!$C$4,12,1),3))+9),Plans!$H$6:$H$155,"<"&(((DATE(Settings!$C$4,12,1)-WEEKDAY(DATE(Settings!$C$4,12,1),3))+9)+1))=0),"",INDEX(Plans!$D$6:$D$155,MATCH(SMALL(Plans!$H$6:$H$155,COUNTIF(Plans!$H$6:$H$155,"<"&((DATE(Settings!$C$4,12,1)-WEEKDAY(DATE(Settings!$C$4,12,1),3))+9))+1),Plans!$H$6:$H$155,0))&IF(COUNTIFS(Plans!$H$6:$H$155,">="&((DATE(Settings!$C$4,12,1)-WEEKDAY(DATE(Settings!$C$4,12,1),3))+9),Plans!$H$6:$H$155,"<"&(((DATE(Settings!$C$4,12,1)-WEEKDAY(DATE(Settings!$C$4,12,1),3))+9)+1))>1,CHAR(10)&INDEX(Plans!$D$6:$D$155,MATCH(SMALL(Plans!$H$6:$H$155,COUNTIF(Plans!$H$6:$H$155,"<"&((DATE(Settings!$C$4,12,1)-WEEKDAY(DATE(Settings!$C$4,12,1),3))+9))+2),Plans!$H$6:$H$155,0)),"")&IF(COUNTIFS(Plans!$H$6:$H$155,">="&((DATE(Settings!$C$4,12,1)-WEEKDAY(DATE(Settings!$C$4,12,1),3))+9),Plans!$H$6:$H$155,"<"&(((DATE(Settings!$C$4,12,1)-WEEKDAY(DATE(Settings!$C$4,12,1),3))+9)+1))>2,CHAR(10)&"+"&(COUNTIFS(Plans!$H$6:$H$155,">="&((DATE(Settings!$C$4,12,1)-WEEKDAY(DATE(Settings!$C$4,12,1),3))+9),Plans!$H$6:$H$155,"<"&(((DATE(Settings!$C$4,12,1)-WEEKDAY(DATE(Settings!$C$4,12,1),3))+9)+1))-2)&" more","")) | E9: =IF(OR(MONTH(((DATE(Settings!$C$4,12,1)-WEEKDAY(DATE(Settings!$C$4,12,1),3))+10))<>12,COUNTIFS(Plans!$H$6:$H$155,">="&((DATE(Settings!$C$4,12,1)-WEEKDAY(DATE(Settings!$C$4,12,1),3))+10),Plans!$H$6:$H$155,"<"&(((DATE(Settings!$C$4,12,1)-WEEKDAY(DATE(Settings!$C$4,12,1),3))+10)+1))=0),"",INDEX(Plans!$D$6:$D$155,MATCH(SMALL(Plans!$H$6:$H$155,COUNTIF(Plans!$H$6:$H$155,"<"&((DATE(Settings!$C$4,12,1)-WEEKDAY(DATE(Settings!$C$4,12,1),3))+10))+1),Plans!$H$6:$H$155,0))&IF(COUNTIFS(Plans!$H$6:$H$155,">="&((DATE(Settings!$C$4,12,1)-WEEKDAY(DATE(Settings!$C$4,12,1),3))+10),Plans!$H$6:$H$155,"<"&(((DATE(Settings!$C$4,12,1)-WEEKDAY(DATE(Settings!$C$4,12,1),3))+10)+1))>1,CHAR(10)&INDEX(Plans!$D$6:$D$155,MATCH(SMALL(Plans!$H$6:$H$155,COUNTIF(Plans!$H$6:$H$155,"<"&((DATE(Settings!$C$4,12,1)-WEEKDAY(DATE(Settings!$C$4,12,1),3))+10))+2),Plans!$H$6:$H$155,0)),"")&IF(COUNTIFS(Plans!$H$6:$H$155,">="&((DATE(Settings!$C$4,12,1)-WEEKDAY(DATE(Settings!$C$4,12,1),3))+10),Plans!$H$6:$H$155,"<"&(((DATE(Settings!$C$4,12,1)-WEEKDAY(DATE(Settings!$C$4,12,1),3))+10)+1))>2,CHAR(10)&"+"&(COUNTIFS(Plans!$H$6:$H$155,">="&((DATE(Settings!$C$4,12,1)-WEEKDAY(DATE(Settings!$C$4,12,1),3))+10),Plans!$H$6:$H$155,"<"&(((DATE(Settings!$C$4,12,1)-WEEKDAY(DATE(Settings!$C$4,12,1),3))+10)+1))-2)&" more","")) | F9: =IF(OR(MONTH(((DATE(Settings!$C$4,12,1)-WEEKDAY(DATE(Settings!$C$4,12,1),3))+11))<>12,COUNTIFS(Plans!$H$6:$H$155,">="&((DATE(Settings!$C$4,12,1)-WEEKDAY(DATE(Settings!$C$4,12,1),3))+11),Plans!$H$6:$H$155,"<"&(((DATE(Settings!$C$4,12,1)-WEEKDAY(DATE(Settings!$C$4,12,1),3))+11)+1))=0),"",INDEX(Plans!$D$6:$D$155,MATCH(SMALL(Plans!$H$6:$H$155,COUNTIF(Plans!$H$6:$H$155,"<"&((DATE(Settings!$C$4,12,1)-WEEKDAY(DATE(Settings!$C$4,12,1),3))+11))+1),Plans!$H$6:$H$155,0))&IF(COUNTIFS(Plans!$H$6:$H$155,">="&((DATE(Settings!$C$4,12,1)-WEEKDAY(DATE(Settings!$C$4,12,1),3))+11),Plans!$H$6:$H$155,"<"&(((DATE(Settings!$C$4,12,1)-WEEKDAY(DATE(Settings!$C$4,12,1),3))+11)+1))>1,CHAR(10)&INDEX(Plans!$D$6:$D$155,MATCH(SMALL(Plans!$H$6:$H$155,COUNTIF(Plans!$H$6:$H$155,"<"&((DATE(Settings!$C$4,12,1)-WEEKDAY(DATE(Settings!$C$4,12,1),3))+11))+2),Plans!$H$6:$H$155,0)),"")&IF(COUNTIFS(Plans!$H$6:$H$155,">="&((DATE(Settings!$C$4,12,1)-WEEKDAY(DATE(Settings!$C$4,12,1),3))+11),Plans!$H$6:$H$155,"<"&(((DATE(Settings!$C$4,12,1)-WEEKDAY(DATE(Settings!$C$4,12,1),3))+11)+1))>2,CHAR(10)&"+"&(COUNTIFS(Plans!$H$6:$H$155,">="&((DATE(Settings!$C$4,12,1)-WEEKDAY(DATE(Settings!$C$4,12,1),3))+11),Plans!$H$6:$H$155,"<"&(((DATE(Settings!$C$4,12,1)-WEEKDAY(DATE(Settings!$C$4,12,1),3))+11)+1))-2)&" more","")) | G9: =IF(OR(MONTH(((DATE(Settings!$C$4,12,1)-WEEKDAY(DATE(Settings!$C$4,12,1),3))+12))<>12,COUNTIFS(Plans!$H$6:$H$155,">="&((DATE(Settings!$C$4,12,1)-WEEKDAY(DATE(Settings!$C$4,12,1),3))+12),Plans!$H$6:$H$155,"<"&(((DATE(Settings!$C$4,12,1)-WEEKDAY(DATE(Settings!$C$4,12,1),3))+12)+1))=0),"",INDEX(Plans!$D$6:$D$155,MATCH(SMALL(Plans!$H$6:$H$155,COUNTIF(Plans!$H$6:$H$155,"<"&((DATE(Settings!$C$4,12,1)-WEEKDAY(DATE(Settings!$C$4,12,1),3))+12))+1),Plans!$H$6:$H$155,0))&IF(COUNTIFS(Plans!$H$6:$H$155,">="&((DATE(Settings!$C$4,12,1)-WEEKDAY(DATE(Settings!$C$4,12,1),3))+12),Plans!$H$6:$H$155,"<"&(((DATE(Settings!$C$4,12,1)-WEEKDAY(DATE(Settings!$C$4,12,1),3))+12)+1))>1,CHAR(10)&INDEX(Plans!$D$6:$D$155,MATCH(SMALL(Plans!$H$6:$H$155,COUNTIF(Plans!$H$6:$H$155,"<"&((DATE(Settings!$C$4,12,1)-WEEKDAY(DATE(Settings!$C$4,12,1),3))+12))+2),Plans!$H$6:$H$155,0)),"")&IF(COUNTIFS(Plans!$H$6:$H$155,">="&((DATE(Settings!$C$4,12,1)-WEEKDAY(DATE(Settings!$C$4,12,1),3))+12),Plans!$H$6:$H$155,"<"&(((DATE(Settings!$C$4,12,1)-WEEKDAY(DATE(Settings!$C$4,12,1),3))+12)+1))>2,CHAR(10)&"+"&(COUNTIFS(Plans!$H$6:$H$155,">="&((DATE(Settings!$C$4,12,1)-WEEKDAY(DATE(Settings!$C$4,12,1),3))+12),Plans!$H$6:$H$155,"<"&(((DATE(Settings!$C$4,12,1)-WEEKDAY(DATE(Settings!$C$4,12,1),3))+12)+1))-2)&" more","")) | H9: =IF(OR(MONTH(((DATE(Settings!$C$4,12,1)-WEEKDAY(DATE(Settings!$C$4,12,1),3))+13))<>12,COUNTIFS(Plans!$H$6:$H$155,">="&((DATE(Settings!$C$4,12,1)-WEEKDAY(DATE(Settings!$C$4,12,1),3))+13),Plans!$H$6:$H$155,"<"&(((DATE(Settings!$C$4,12,1)-WEEKDAY(DATE(Settings!$C$4,12,1),3))+13)+1))=0),"",INDEX(Plans!$D$6:$D$155,MATCH(SMALL(Plans!$H$6:$H$155,COUNTIF(Plans!$H$6:$H$155,"<"&((DATE(Settings!$C$4,12,1)-WEEKDAY(DATE(Settings!$C$4,12,1),3))+13))+1),Plans!$H$6:$H$155,0))&IF(COUNTIFS(Plans!$H$6:$H$155,">="&((DATE(Settings!$C$4,12,1)-WEEKDAY(DATE(Settings!$C$4,12,1),3))+13),Plans!$H$6:$H$155,"<"&(((DATE(Settings!$C$4,12,1)-WEEKDAY(DATE(Settings!$C$4,12,1),3))+13)+1))>1,CHAR(10)&INDEX(Plans!$D$6:$D$155,MATCH(SMALL(Plans!$H$6:$H$155,COUNTIF(Plans!$H$6:$H$155,"<"&((DATE(Settings!$C$4,12,1)-WEEKDAY(DATE(Settings!$C$4,12,1),3))+13))+2),Plans!$H$6:$H$155,0)),"")&IF(COUNTIFS(Plans!$H$6:$H$155,">="&((DATE(Settings!$C$4,12,1)-WEEKDAY(DATE(Settings!$C$4,12,1),3))+13),Plans!$H$6:$H$155,"<"&(((DATE(Settings!$C$4,12,1)-WEEKDAY(DATE(Settings!$C$4,12,1),3))+13)+1))>2,CHAR(10)&"+"&(COUNTIFS(Plans!$H$6:$H$155,">="&((DATE(Settings!$C$4,12,1)-WEEKDAY(DATE(Settings!$C$4,12,1),3))+13),Plans!$H$6:$H$155,"<"&(((DATE(Settings!$C$4,12,1)-WEEKDAY(DATE(Settings!$C$4,12,1),3))+13)+1))-2)&" more",""))
B10: =IF(MONTH(((DATE(Settings!$C$4,12,1)-WEEKDAY(DATE(Settings!$C$4,12,1),3))+14))=12,DAY(((DATE(Settings!$C$4,12,1)-WEEKDAY(DATE(Settings!$C$4,12,1),3))+14)),"") | C10: =IF(MONTH(((DATE(Settings!$C$4,12,1)-WEEKDAY(DATE(Settings!$C$4,12,1),3))+15))=12,DAY(((DATE(Settings!$C$4,12,1)-WEEKDAY(DATE(Settings!$C$4,12,1),3))+15)),"") | D10: =IF(MONTH(((DATE(Settings!$C$4,12,1)-WEEKDAY(DATE(Settings!$C$4,12,1),3))+16))=12,DAY(((DATE(Settings!$C$4,12,1)-WEEKDAY(DATE(Settings!$C$4,12,1),3))+16)),"") | E10: =IF(MONTH(((DATE(Settings!$C$4,12,1)-WEEKDAY(DATE(Settings!$C$4,12,1),3))+17))=12,DAY(((DATE(Settings!$C$4,12,1)-WEEKDAY(DATE(Settings!$C$4,12,1),3))+17)),"") | F10: =IF(MONTH(((DATE(Settings!$C$4,12,1)-WEEKDAY(DATE(Settings!$C$4,12,1),3))+18))=12,DAY(((DATE(Settings!$C$4,12,1)-WEEKDAY(DATE(Settings!$C$4,12,1),3))+18)),"") | G10: =IF(MONTH(((DATE(Settings!$C$4,12,1)-WEEKDAY(DATE(Settings!$C$4,12,1),3))+19))=12,DAY(((DATE(Settings!$C$4,12,1)-WEEKDAY(DATE(Settings!$C$4,12,1),3))+19)),"") | H10: =IF(MONTH(((DATE(Settings!$C$4,12,1)-WEEKDAY(DATE(Settings!$C$4,12,1),3))+20))=12,DAY(((DATE(Settings!$C$4,12,1)-WEEKDAY(DATE(Settings!$C$4,12,1),3))+20)),"")
B11: =IF(OR(MONTH(((DATE(Settings!$C$4,12,1)-WEEKDAY(DATE(Settings!$C$4,12,1),3))+14))<>12,COUNTIFS(Plans!$H$6:$H$155,">="&((DATE(Settings!$C$4,12,1)-WEEKDAY(DATE(Settings!$C$4,12,1),3))+14),Plans!$H$6:$H$155,"<"&(((DATE(Settings!$C$4,12,1)-WEEKDAY(DATE(Settings!$C$4,12,1),3))+14)+1))=0),"",INDEX(Plans!$D$6:$D$155,MATCH(SMALL(Plans!$H$6:$H$155,COUNTIF(Plans!$H$6:$H$155,"<"&((DATE(Settings!$C$4,12,1)-WEEKDAY(DATE(Settings!$C$4,12,1),3))+14))+1),Plans!$H$6:$H$155,0))&IF(COUNTIFS(Plans!$H$6:$H$155,">="&((DATE(Settings!$C$4,12,1)-WEEKDAY(DATE(Settings!$C$4,12,1),3))+14),Plans!$H$6:$H$155,"<"&(((DATE(Settings!$C$4,12,1)-WEEKDAY(DATE(Settings!$C$4,12,1),3))+14)+1))>1,CHAR(10)&INDEX(Plans!$D$6:$D$155,MATCH(SMALL(Plans!$H$6:$H$155,COUNTIF(Plans!$H$6:$H$155,"<"&((DATE(Settings!$C$4,12,1)-WEEKDAY(DATE(Settings!$C$4,12,1),3))+14))+2),Plans!$H$6:$H$155,0)),"")&IF(COUNTIFS(Plans!$H$6:$H$155,">="&((DATE(Settings!$C$4,12,1)-WEEKDAY(DATE(Settings!$C$4,12,1),3))+14),Plans!$H$6:$H$155,"<"&(((DATE(Settings!$C$4,12,1)-WEEKDAY(DATE(Settings!$C$4,12,1),3))+14)+1))>2,CHAR(10)&"+"&(COUNTIFS(Plans!$H$6:$H$155,">="&((DATE(Settings!$C$4,12,1)-WEEKDAY(DATE(Settings!$C$4,12,1),3))+14),Plans!$H$6:$H$155,"<"&(((DATE(Settings!$C$4,12,1)-WEEKDAY(DATE(Settings!$C$4,12,1),3))+14)+1))-2)&" more","")) | C11: =IF(OR(MONTH(((DATE(Settings!$C$4,12,1)-WEEKDAY(DATE(Settings!$C$4,12,1),3))+15))<>12,COUNTIFS(Plans!$H$6:$H$155,">="&((DATE(Settings!$C$4,12,1)-WEEKDAY(DATE(Settings!$C$4,12,1),3))+15),Plans!$H$6:$H$155,"<"&(((DATE(Settings!$C$4,12,1)-WEEKDAY(DATE(Settings!$C$4,12,1),3))+15)+1))=0),"",INDEX(Plans!$D$6:$D$155,MATCH(SMALL(Plans!$H$6:$H$155,COUNTIF(Plans!$H$6:$H$155,"<"&((DATE(Settings!$C$4,12,1)-WEEKDAY(DATE(Settings!$C$4,12,1),3))+15))+1),Plans!$H$6:$H$155,0))&IF(COUNTIFS(Plans!$H$6:$H$155,">="&((DATE(Settings!$C$4,12,1)-WEEKDAY(DATE(Settings!$C$4,12,1),3))+15),Plans!$H$6:$H$155,"<"&(((DATE(Settings!$C$4,12,1)-WEEKDAY(DATE(Settings!$C$4,12,1),3))+15)+1))>1,CHAR(10)&INDEX(Plans!$D$6:$D$155,MATCH(SMALL(Plans!$H$6:$H$155,COUNTIF(Plans!$H$6:$H$155,"<"&((DATE(Settings!$C$4,12,1)-WEEKDAY(DATE(Settings!$C$4,12,1),3))+15))+2),Plans!$H$6:$H$155,0)),"")&IF(COUNTIFS(Plans!$H$6:$H$155,">="&((DATE(Settings!$C$4,12,1)-WEEKDAY(DATE(Settings!$C$4,12,1),3))+15),Plans!$H$6:$H$155,"<"&(((DATE(Settings!$C$4,12,1)-WEEKDAY(DATE(Settings!$C$4,12,1),3))+15)+1))>2,CHAR(10)&"+"&(COUNTIFS(Plans!$H$6:$H$155,">="&((DATE(Settings!$C$4,12,1)-WEEKDAY(DATE(Settings!$C$4,12,1),3))+15),Plans!$H$6:$H$155,"<"&(((DATE(Settings!$C$4,12,1)-WEEKDAY(DATE(Settings!$C$4,12,1),3))+15)+1))-2)&" more","")) | D11: =IF(OR(MONTH(((DATE(Settings!$C$4,12,1)-WEEKDAY(DATE(Settings!$C$4,12,1),3))+16))<>12,COUNTIFS(Plans!$H$6:$H$155,">="&((DATE(Settings!$C$4,12,1)-WEEKDAY(DATE(Settings!$C$4,12,1),3))+16),Plans!$H$6:$H$155,"<"&(((DATE(Settings!$C$4,12,1)-WEEKDAY(DATE(Settings!$C$4,12,1),3))+16)+1))=0),"",INDEX(Plans!$D$6:$D$155,MATCH(SMALL(Plans!$H$6:$H$155,COUNTIF(Plans!$H$6:$H$155,"<"&((DATE(Settings!$C$4,12,1)-WEEKDAY(DATE(Settings!$C$4,12,1),3))+16))+1),Plans!$H$6:$H$155,0))&IF(COUNTIFS(Plans!$H$6:$H$155,">="&((DATE(Settings!$C$4,12,1)-WEEKDAY(DATE(Settings!$C$4,12,1),3))+16),Plans!$H$6:$H$155,"<"&(((DATE(Settings!$C$4,12,1)-WEEKDAY(DATE(Settings!$C$4,12,1),3))+16)+1))>1,CHAR(10)&INDEX(Plans!$D$6:$D$155,MATCH(SMALL(Plans!$H$6:$H$155,COUNTIF(Plans!$H$6:$H$155,"<"&((DATE(Settings!$C$4,12,1)-WEEKDAY(DATE(Settings!$C$4,12,1),3))+16))+2),Plans!$H$6:$H$155,0)),"")&IF(COUNTIFS(Plans!$H$6:$H$155,">="&((DATE(Settings!$C$4,12,1)-WEEKDAY(DATE(Settings!$C$4,12,1),3))+16),Plans!$H$6:$H$155,"<"&(((DATE(Settings!$C$4,12,1)-WEEKDAY(DATE(Settings!$C$4,12,1),3))+16)+1))>2,CHAR(10)&"+"&(COUNTIFS(Plans!$H$6:$H$155,">="&((DATE(Settings!$C$4,12,1)-WEEKDAY(DATE(Settings!$C$4,12,1),3))+16),Plans!$H$6:$H$155,"<"&(((DATE(Settings!$C$4,12,1)-WEEKDAY(DATE(Settings!$C$4,12,1),3))+16)+1))-2)&" more","")) | E11: =IF(OR(MONTH(((DATE(Settings!$C$4,12,1)-WEEKDAY(DATE(Settings!$C$4,12,1),3))+17))<>12,COUNTIFS(Plans!$H$6:$H$155,">="&((DATE(Settings!$C$4,12,1)-WEEKDAY(DATE(Settings!$C$4,12,1),3))+17),Plans!$H$6:$H$155,"<"&(((DATE(Settings!$C$4,12,1)-WEEKDAY(DATE(Settings!$C$4,12,1),3))+17)+1))=0),"",INDEX(Plans!$D$6:$D$155,MATCH(SMALL(Plans!$H$6:$H$155,COUNTIF(Plans!$H$6:$H$155,"<"&((DATE(Settings!$C$4,12,1)-WEEKDAY(DATE(Settings!$C$4,12,1),3))+17))+1),Plans!$H$6:$H$155,0))&IF(COUNTIFS(Plans!$H$6:$H$155,">="&((DATE(Settings!$C$4,12,1)-WEEKDAY(DATE(Settings!$C$4,12,1),3))+17),Plans!$H$6:$H$155,"<"&(((DATE(Settings!$C$4,12,1)-WEEKDAY(DATE(Settings!$C$4,12,1),3))+17)+1))>1,CHAR(10)&INDEX(Plans!$D$6:$D$155,MATCH(SMALL(Plans!$H$6:$H$155,COUNTIF(Plans!$H$6:$H$155,"<"&((DATE(Settings!$C$4,12,1)-WEEKDAY(DATE(Settings!$C$4,12,1),3))+17))+2),Plans!$H$6:$H$155,0)),"")&IF(COUNTIFS(Plans!$H$6:$H$155,">="&((DATE(Settings!$C$4,12,1)-WEEKDAY(DATE(Settings!$C$4,12,1),3))+17),Plans!$H$6:$H$155,"<"&(((DATE(Settings!$C$4,12,1)-WEEKDAY(DATE(Settings!$C$4,12,1),3))+17)+1))>2,CHAR(10)&"+"&(COUNTIFS(Plans!$H$6:$H$155,">="&((DATE(Settings!$C$4,12,1)-WEEKDAY(DATE(Settings!$C$4,12,1),3))+17),Plans!$H$6:$H$155,"<"&(((DATE(Settings!$C$4,12,1)-WEEKDAY(DATE(Settings!$C$4,12,1),3))+17)+1))-2)&" more","")) | F11: =IF(OR(MONTH(((DATE(Settings!$C$4,12,1)-WEEKDAY(DATE(Settings!$C$4,12,1),3))+18))<>12,COUNTIFS(Plans!$H$6:$H$155,">="&((DATE(Settings!$C$4,12,1)-WEEKDAY(DATE(Settings!$C$4,12,1),3))+18),Plans!$H$6:$H$155,"<"&(((DATE(Settings!$C$4,12,1)-WEEKDAY(DATE(Settings!$C$4,12,1),3))+18)+1))=0),"",INDEX(Plans!$D$6:$D$155,MATCH(SMALL(Plans!$H$6:$H$155,COUNTIF(Plans!$H$6:$H$155,"<"&((DATE(Settings!$C$4,12,1)-WEEKDAY(DATE(Settings!$C$4,12,1),3))+18))+1),Plans!$H$6:$H$155,0))&IF(COUNTIFS(Plans!$H$6:$H$155,">="&((DATE(Settings!$C$4,12,1)-WEEKDAY(DATE(Settings!$C$4,12,1),3))+18),Plans!$H$6:$H$155,"<"&(((DATE(Settings!$C$4,12,1)-WEEKDAY(DATE(Settings!$C$4,12,1),3))+18)+1))>1,CHAR(10)&INDEX(Plans!$D$6:$D$155,MATCH(SMALL(Plans!$H$6:$H$155,COUNTIF(Plans!$H$6:$H$155,"<"&((DATE(Settings!$C$4,12,1)-WEEKDAY(DATE(Settings!$C$4,12,1),3))+18))+2),Plans!$H$6:$H$155,0)),"")&IF(COUNTIFS(Plans!$H$6:$H$155,">="&((DATE(Settings!$C$4,12,1)-WEEKDAY(DATE(Settings!$C$4,12,1),3))+18),Plans!$H$6:$H$155,"<"&(((DATE(Settings!$C$4,12,1)-WEEKDAY(DATE(Settings!$C$4,12,1),3))+18)+1))>2,CHAR(10)&"+"&(COUNTIFS(Plans!$H$6:$H$155,">="&((DATE(Settings!$C$4,12,1)-WEEKDAY(DATE(Settings!$C$4,12,1),3))+18),Plans!$H$6:$H$155,"<"&(((DATE(Settings!$C$4,12,1)-WEEKDAY(DATE(Settings!$C$4,12,1),3))+18)+1))-2)&" more","")) | G11: =IF(OR(MONTH(((DATE(Settings!$C$4,12,1)-WEEKDAY(DATE(Settings!$C$4,12,1),3))+19))<>12,COUNTIFS(Plans!$H$6:$H$155,">="&((DATE(Settings!$C$4,12,1)-WEEKDAY(DATE(Settings!$C$4,12,1),3))+19),Plans!$H$6:$H$155,"<"&(((DATE(Settings!$C$4,12,1)-WEEKDAY(DATE(Settings!$C$4,12,1),3))+19)+1))=0),"",INDEX(Plans!$D$6:$D$155,MATCH(SMALL(Plans!$H$6:$H$155,COUNTIF(Plans!$H$6:$H$155,"<"&((DATE(Settings!$C$4,12,1)-WEEKDAY(DATE(Settings!$C$4,12,1),3))+19))+1),Plans!$H$6:$H$155,0))&IF(COUNTIFS(Plans!$H$6:$H$155,">="&((DATE(Settings!$C$4,12,1)-WEEKDAY(DATE(Settings!$C$4,12,1),3))+19),Plans!$H$6:$H$155,"<"&(((DATE(Settings!$C$4,12,1)-WEEKDAY(DATE(Settings!$C$4,12,1),3))+19)+1))>1,CHAR(10)&INDEX(Plans!$D$6:$D$155,MATCH(SMALL(Plans!$H$6:$H$155,COUNTIF(Plans!$H$6:$H$155,"<"&((DATE(Settings!$C$4,12,1)-WEEKDAY(DATE(Settings!$C$4,12,1),3))+19))+2),Plans!$H$6:$H$155,0)),"")&IF(COUNTIFS(Plans!$H$6:$H$155,">="&((DATE(Settings!$C$4,12,1)-WEEKDAY(DATE(Settings!$C$4,12,1),3))+19),Plans!$H$6:$H$155,"<"&(((DATE(Settings!$C$4,12,1)-WEEKDAY(DATE(Settings!$C$4,12,1),3))+19)+1))>2,CHAR(10)&"+"&(COUNTIFS(Plans!$H$6:$H$155,">="&((DATE(Settings!$C$4,12,1)-WEEKDAY(DATE(Settings!$C$4,12,1),3))+19),Plans!$H$6:$H$155,"<"&(((DATE(Settings!$C$4,12,1)-WEEKDAY(DATE(Settings!$C$4,12,1),3))+19)+1))-2)&" more","")) | H11: =IF(OR(MONTH(((DATE(Settings!$C$4,12,1)-WEEKDAY(DATE(Settings!$C$4,12,1),3))+20))<>12,COUNTIFS(Plans!$H$6:$H$155,">="&((DATE(Settings!$C$4,12,1)-WEEKDAY(DATE(Settings!$C$4,12,1),3))+20),Plans!$H$6:$H$155,"<"&(((DATE(Settings!$C$4,12,1)-WEEKDAY(DATE(Settings!$C$4,12,1),3))+20)+1))=0),"",INDEX(Plans!$D$6:$D$155,MATCH(SMALL(Plans!$H$6:$H$155,COUNTIF(Plans!$H$6:$H$155,"<"&((DATE(Settings!$C$4,12,1)-WEEKDAY(DATE(Settings!$C$4,12,1),3))+20))+1),Plans!$H$6:$H$155,0))&IF(COUNTIFS(Plans!$H$6:$H$155,">="&((DATE(Settings!$C$4,12,1)-WEEKDAY(DATE(Settings!$C$4,12,1),3))+20),Plans!$H$6:$H$155,"<"&(((DATE(Settings!$C$4,12,1)-WEEKDAY(DATE(Settings!$C$4,12,1),3))+20)+1))>1,CHAR(10)&INDEX(Plans!$D$6:$D$155,MATCH(SMALL(Plans!$H$6:$H$155,COUNTIF(Plans!$H$6:$H$155,"<"&((DATE(Settings!$C$4,12,1)-WEEKDAY(DATE(Settings!$C$4,12,1),3))+20))+2),Plans!$H$6:$H$155,0)),"")&IF(COUNTIFS(Plans!$H$6:$H$155,">="&((DATE(Settings!$C$4,12,1)-WEEKDAY(DATE(Settings!$C$4,12,1),3))+20),Plans!$H$6:$H$155,"<"&(((DATE(Settings!$C$4,12,1)-WEEKDAY(DATE(Settings!$C$4,12,1),3))+20)+1))>2,CHAR(10)&"+"&(COUNTIFS(Plans!$H$6:$H$155,">="&((DATE(Settings!$C$4,12,1)-WEEKDAY(DATE(Settings!$C$4,12,1),3))+20),Plans!$H$6:$H$155,"<"&(((DATE(Settings!$C$4,12,1)-WEEKDAY(DATE(Settings!$C$4,12,1),3))+20)+1))-2)&" more",""))
B12: =IF(MONTH(((DATE(Settings!$C$4,12,1)-WEEKDAY(DATE(Settings!$C$4,12,1),3))+21))=12,DAY(((DATE(Settings!$C$4,12,1)-WEEKDAY(DATE(Settings!$C$4,12,1),3))+21)),"") | C12: =IF(MONTH(((DATE(Settings!$C$4,12,1)-WEEKDAY(DATE(Settings!$C$4,12,1),3))+22))=12,DAY(((DATE(Settings!$C$4,12,1)-WEEKDAY(DATE(Settings!$C$4,12,1),3))+22)),"") | D12: =IF(MONTH(((DATE(Settings!$C$4,12,1)-WEEKDAY(DATE(Settings!$C$4,12,1),3))+23))=12,DAY(((DATE(Settings!$C$4,12,1)-WEEKDAY(DATE(Settings!$C$4,12,1),3))+23)),"") | E12: =IF(MONTH(((DATE(Settings!$C$4,12,1)-WEEKDAY(DATE(Settings!$C$4,12,1),3))+24))=12,DAY(((DATE(Settings!$C$4,12,1)-WEEKDAY(DATE(Settings!$C$4,12,1),3))+24)),"") | F12: =IF(MONTH(((DATE(Settings!$C$4,12,1)-WEEKDAY(DATE(Settings!$C$4,12,1),3))+25))=12,DAY(((DATE(Settings!$C$4,12,1)-WEEKDAY(DATE(Settings!$C$4,12,1),3))+25)),"") | G12: =IF(MONTH(((DATE(Settings!$C$4,12,1)-WEEKDAY(DATE(Settings!$C$4,12,1),3))+26))=12,DAY(((DATE(Settings!$C$4,12,1)-WEEKDAY(DATE(Settings!$C$4,12,1),3))+26)),"") | H12: =IF(MONTH(((DATE(Settings!$C$4,12,1)-WEEKDAY(DATE(Settings!$C$4,12,1),3))+27))=12,DAY(((DATE(Settings!$C$4,12,1)-WEEKDAY(DATE(Settings!$C$4,12,1),3))+27)),"")
B13: =IF(OR(MONTH(((DATE(Settings!$C$4,12,1)-WEEKDAY(DATE(Settings!$C$4,12,1),3))+21))<>12,COUNTIFS(Plans!$H$6:$H$155,">="&((DATE(Settings!$C$4,12,1)-WEEKDAY(DATE(Settings!$C$4,12,1),3))+21),Plans!$H$6:$H$155,"<"&(((DATE(Settings!$C$4,12,1)-WEEKDAY(DATE(Settings!$C$4,12,1),3))+21)+1))=0),"",INDEX(Plans!$D$6:$D$155,MATCH(SMALL(Plans!$H$6:$H$155,COUNTIF(Plans!$H$6:$H$155,"<"&((DATE(Settings!$C$4,12,1)-WEEKDAY(DATE(Settings!$C$4,12,1),3))+21))+1),Plans!$H$6:$H$155,0))&IF(COUNTIFS(Plans!$H$6:$H$155,">="&((DATE(Settings!$C$4,12,1)-WEEKDAY(DATE(Settings!$C$4,12,1),3))+21),Plans!$H$6:$H$155,"<"&(((DATE(Settings!$C$4,12,1)-WEEKDAY(DATE(Settings!$C$4,12,1),3))+21)+1))>1,CHAR(10)&INDEX(Plans!$D$6:$D$155,MATCH(SMALL(Plans!$H$6:$H$155,COUNTIF(Plans!$H$6:$H$155,"<"&((DATE(Settings!$C$4,12,1)-WEEKDAY(DATE(Settings!$C$4,12,1),3))+21))+2),Plans!$H$6:$H$155,0)),"")&IF(COUNTIFS(Plans!$H$6:$H$155,">="&((DATE(Settings!$C$4,12,1)-WEEKDAY(DATE(Settings!$C$4,12,1),3))+21),Plans!$H$6:$H$155,"<"&(((DATE(Settings!$C$4,12,1)-WEEKDAY(DATE(Settings!$C$4,12,1),3))+21)+1))>2,CHAR(10)&"+"&(COUNTIFS(Plans!$H$6:$H$155,">="&((DATE(Settings!$C$4,12,1)-WEEKDAY(DATE(Settings!$C$4,12,1),3))+21),Plans!$H$6:$H$155,"<"&(((DATE(Settings!$C$4,12,1)-WEEKDAY(DATE(Settings!$C$4,12,1),3))+21)+1))-2)&" more","")) | C13: =IF(OR(MONTH(((DATE(Settings!$C$4,12,1)-WEEKDAY(DATE(Settings!$C$4,12,1),3))+22))<>12,COUNTIFS(Plans!$H$6:$H$155,">="&((DATE(Settings!$C$4,12,1)-WEEKDAY(DATE(Settings!$C$4,12,1),3))+22),Plans!$H$6:$H$155,"<"&(((DATE(Settings!$C$4,12,1)-WEEKDAY(DATE(Settings!$C$4,12,1),3))+22)+1))=0),"",INDEX(Plans!$D$6:$D$155,MATCH(SMALL(Plans!$H$6:$H$155,COUNTIF(Plans!$H$6:$H$155,"<"&((DATE(Settings!$C$4,12,1)-WEEKDAY(DATE(Settings!$C$4,12,1),3))+22))+1),Plans!$H$6:$H$155,0))&IF(COUNTIFS(Plans!$H$6:$H$155,">="&((DATE(Settings!$C$4,12,1)-WEEKDAY(DATE(Settings!$C$4,12,1),3))+22),Plans!$H$6:$H$155,"<"&(((DATE(Settings!$C$4,12,1)-WEEKDAY(DATE(Settings!$C$4,12,1),3))+22)+1))>1,CHAR(10)&INDEX(Plans!$D$6:$D$155,MATCH(SMALL(Plans!$H$6:$H$155,COUNTIF(Plans!$H$6:$H$155,"<"&((DATE(Settings!$C$4,12,1)-WEEKDAY(DATE(Settings!$C$4,12,1),3))+22))+2),Plans!$H$6:$H$155,0)),"")&IF(COUNTIFS(Plans!$H$6:$H$155,">="&((DATE(Settings!$C$4,12,1)-WEEKDAY(DATE(Settings!$C$4,12,1),3))+22),Plans!$H$6:$H$155,"<"&(((DATE(Settings!$C$4,12,1)-WEEKDAY(DATE(Settings!$C$4,12,1),3))+22)+1))>2,CHAR(10)&"+"&(COUNTIFS(Plans!$H$6:$H$155,">="&((DATE(Settings!$C$4,12,1)-WEEKDAY(DATE(Settings!$C$4,12,1),3))+22),Plans!$H$6:$H$155,"<"&(((DATE(Settings!$C$4,12,1)-WEEKDAY(DATE(Settings!$C$4,12,1),3))+22)+1))-2)&" more","")) | D13: =IF(OR(MONTH(((DATE(Settings!$C$4,12,1)-WEEKDAY(DATE(Settings!$C$4,12,1),3))+23))<>12,COUNTIFS(Plans!$H$6:$H$155,">="&((DATE(Settings!$C$4,12,1)-WEEKDAY(DATE(Settings!$C$4,12,1),3))+23),Plans!$H$6:$H$155,"<"&(((DATE(Settings!$C$4,12,1)-WEEKDAY(DATE(Settings!$C$4,12,1),3))+23)+1))=0),"",INDEX(Plans!$D$6:$D$155,MATCH(SMALL(Plans!$H$6:$H$155,COUNTIF(Plans!$H$6:$H$155,"<"&((DATE(Settings!$C$4,12,1)-WEEKDAY(DATE(Settings!$C$4,12,1),3))+23))+1),Plans!$H$6:$H$155,0))&IF(COUNTIFS(Plans!$H$6:$H$155,">="&((DATE(Settings!$C$4,12,1)-WEEKDAY(DATE(Settings!$C$4,12,1),3))+23),Plans!$H$6:$H$155,"<"&(((DATE(Settings!$C$4,12,1)-WEEKDAY(DATE(Settings!$C$4,12,1),3))+23)+1))>1,CHAR(10)&INDEX(Plans!$D$6:$D$155,MATCH(SMALL(Plans!$H$6:$H$155,COUNTIF(Plans!$H$6:$H$155,"<"&((DATE(Settings!$C$4,12,1)-WEEKDAY(DATE(Settings!$C$4,12,1),3))+23))+2),Plans!$H$6:$H$155,0)),"")&IF(COUNTIFS(Plans!$H$6:$H$155,">="&((DATE(Settings!$C$4,12,1)-WEEKDAY(DATE(Settings!$C$4,12,1),3))+23),Plans!$H$6:$H$155,"<"&(((DATE(Settings!$C$4,12,1)-WEEKDAY(DATE(Settings!$C$4,12,1),3))+23)+1))>2,CHAR(10)&"+"&(COUNTIFS(Plans!$H$6:$H$155,">="&((DATE(Settings!$C$4,12,1)-WEEKDAY(DATE(Settings!$C$4,12,1),3))+23),Plans!$H$6:$H$155,"<"&(((DATE(Settings!$C$4,12,1)-WEEKDAY(DATE(Settings!$C$4,12,1),3))+23)+1))-2)&" more","")) | E13: =IF(OR(MONTH(((DATE(Settings!$C$4,12,1)-WEEKDAY(DATE(Settings!$C$4,12,1),3))+24))<>12,COUNTIFS(Plans!$H$6:$H$155,">="&((DATE(Settings!$C$4,12,1)-WEEKDAY(DATE(Settings!$C$4,12,1),3))+24),Plans!$H$6:$H$155,"<"&(((DATE(Settings!$C$4,12,1)-WEEKDAY(DATE(Settings!$C$4,12,1),3))+24)+1))=0),"",INDEX(Plans!$D$6:$D$155,MATCH(SMALL(Plans!$H$6:$H$155,COUNTIF(Plans!$H$6:$H$155,"<"&((DATE(Settings!$C$4,12,1)-WEEKDAY(DATE(Settings!$C$4,12,1),3))+24))+1),Plans!$H$6:$H$155,0))&IF(COUNTIFS(Plans!$H$6:$H$155,">="&((DATE(Settings!$C$4,12,1)-WEEKDAY(DATE(Settings!$C$4,12,1),3))+24),Plans!$H$6:$H$155,"<"&(((DATE(Settings!$C$4,12,1)-WEEKDAY(DATE(Settings!$C$4,12,1),3))+24)+1))>1,CHAR(10)&INDEX(Plans!$D$6:$D$155,MATCH(SMALL(Plans!$H$6:$H$155,COUNTIF(Plans!$H$6:$H$155,"<"&((DATE(Settings!$C$4,12,1)-WEEKDAY(DATE(Settings!$C$4,12,1),3))+24))+2),Plans!$H$6:$H$155,0)),"")&IF(COUNTIFS(Plans!$H$6:$H$155,">="&((DATE(Settings!$C$4,12,1)-WEEKDAY(DATE(Settings!$C$4,12,1),3))+24),Plans!$H$6:$H$155,"<"&(((DATE(Settings!$C$4,12,1)-WEEKDAY(DATE(Settings!$C$4,12,1),3))+24)+1))>2,CHAR(10)&"+"&(COUNTIFS(Plans!$H$6:$H$155,">="&((DATE(Settings!$C$4,12,1)-WEEKDAY(DATE(Settings!$C$4,12,1),3))+24),Plans!$H$6:$H$155,"<"&(((DATE(Settings!$C$4,12,1)-WEEKDAY(DATE(Settings!$C$4,12,1),3))+24)+1))-2)&" more","")) | F13: =IF(OR(MONTH(((DATE(Settings!$C$4,12,1)-WEEKDAY(DATE(Settings!$C$4,12,1),3))+25))<>12,COUNTIFS(Plans!$H$6:$H$155,">="&((DATE(Settings!$C$4,12,1)-WEEKDAY(DATE(Settings!$C$4,12,1),3))+25),Plans!$H$6:$H$155,"<"&(((DATE(Settings!$C$4,12,1)-WEEKDAY(DATE(Settings!$C$4,12,1),3))+25)+1))=0),"",INDEX(Plans!$D$6:$D$155,MATCH(SMALL(Plans!$H$6:$H$155,COUNTIF(Plans!$H$6:$H$155,"<"&((DATE(Settings!$C$4,12,1)-WEEKDAY(DATE(Settings!$C$4,12,1),3))+25))+1),Plans!$H$6:$H$155,0))&IF(COUNTIFS(Plans!$H$6:$H$155,">="&((DATE(Settings!$C$4,12,1)-WEEKDAY(DATE(Settings!$C$4,12,1),3))+25),Plans!$H$6:$H$155,"<"&(((DATE(Settings!$C$4,12,1)-WEEKDAY(DATE(Settings!$C$4,12,1),3))+25)+1))>1,CHAR(10)&INDEX(Plans!$D$6:$D$155,MATCH(SMALL(Plans!$H$6:$H$155,COUNTIF(Plans!$H$6:$H$155,"<"&((DATE(Settings!$C$4,12,1)-WEEKDAY(DATE(Settings!$C$4,12,1),3))+25))+2),Plans!$H$6:$H$155,0)),"")&IF(COUNTIFS(Plans!$H$6:$H$155,">="&((DATE(Settings!$C$4,12,1)-WEEKDAY(DATE(Settings!$C$4,12,1),3))+25),Plans!$H$6:$H$155,"<"&(((DATE(Settings!$C$4,12,1)-WEEKDAY(DATE(Settings!$C$4,12,1),3))+25)+1))>2,CHAR(10)&"+"&(COUNTIFS(Plans!$H$6:$H$155,">="&((DATE(Settings!$C$4,12,1)-WEEKDAY(DATE(Settings!$C$4,12,1),3))+25),Plans!$H$6:$H$155,"<"&(((DATE(Settings!$C$4,12,1)-WEEKDAY(DATE(Settings!$C$4,12,1),3))+25)+1))-2)&" more","")) | G13: =IF(OR(MONTH(((DATE(Settings!$C$4,12,1)-WEEKDAY(DATE(Settings!$C$4,12,1),3))+26))<>12,COUNTIFS(Plans!$H$6:$H$155,">="&((DATE(Settings!$C$4,12,1)-WEEKDAY(DATE(Settings!$C$4,12,1),3))+26),Plans!$H$6:$H$155,"<"&(((DATE(Settings!$C$4,12,1)-WEEKDAY(DATE(Settings!$C$4,12,1),3))+26)+1))=0),"",INDEX(Plans!$D$6:$D$155,MATCH(SMALL(Plans!$H$6:$H$155,COUNTIF(Plans!$H$6:$H$155,"<"&((DATE(Settings!$C$4,12,1)-WEEKDAY(DATE(Settings!$C$4,12,1),3))+26))+1),Plans!$H$6:$H$155,0))&IF(COUNTIFS(Plans!$H$6:$H$155,">="&((DATE(Settings!$C$4,12,1)-WEEKDAY(DATE(Settings!$C$4,12,1),3))+26),Plans!$H$6:$H$155,"<"&(((DATE(Settings!$C$4,12,1)-WEEKDAY(DATE(Settings!$C$4,12,1),3))+26)+1))>1,CHAR(10)&INDEX(Plans!$D$6:$D$155,MATCH(SMALL(Plans!$H$6:$H$155,COUNTIF(Plans!$H$6:$H$155,"<"&((DATE(Settings!$C$4,12,1)-WEEKDAY(DATE(Settings!$C$4,12,1),3))+26))+2),Plans!$H$6:$H$155,0)),"")&IF(COUNTIFS(Plans!$H$6:$H$155,">="&((DATE(Settings!$C$4,12,1)-WEEKDAY(DATE(Settings!$C$4,12,1),3))+26),Plans!$H$6:$H$155,"<"&(((DATE(Settings!$C$4,12,1)-WEEKDAY(DATE(Settings!$C$4,12,1),3))+26)+1))>2,CHAR(10)&"+"&(COUNTIFS(Plans!$H$6:$H$155,">="&((DATE(Settings!$C$4,12,1)-WEEKDAY(DATE(Settings!$C$4,12,1),3))+26),Plans!$H$6:$H$155,"<"&(((DATE(Settings!$C$4,12,1)-WEEKDAY(DATE(Settings!$C$4,12,1),3))+26)+1))-2)&" more","")) | H13: =IF(OR(MONTH(((DATE(Settings!$C$4,12,1)-WEEKDAY(DATE(Settings!$C$4,12,1),3))+27))<>12,COUNTIFS(Plans!$H$6:$H$155,">="&((DATE(Settings!$C$4,12,1)-WEEKDAY(DATE(Settings!$C$4,12,1),3))+27),Plans!$H$6:$H$155,"<"&(((DATE(Settings!$C$4,12,1)-WEEKDAY(DATE(Settings!$C$4,12,1),3))+27)+1))=0),"",INDEX(Plans!$D$6:$D$155,MATCH(SMALL(Plans!$H$6:$H$155,COUNTIF(Plans!$H$6:$H$155,"<"&((DATE(Settings!$C$4,12,1)-WEEKDAY(DATE(Settings!$C$4,12,1),3))+27))+1),Plans!$H$6:$H$155,0))&IF(COUNTIFS(Plans!$H$6:$H$155,">="&((DATE(Settings!$C$4,12,1)-WEEKDAY(DATE(Settings!$C$4,12,1),3))+27),Plans!$H$6:$H$155,"<"&(((DATE(Settings!$C$4,12,1)-WEEKDAY(DATE(Settings!$C$4,12,1),3))+27)+1))>1,CHAR(10)&INDEX(Plans!$D$6:$D$155,MATCH(SMALL(Plans!$H$6:$H$155,COUNTIF(Plans!$H$6:$H$155,"<"&((DATE(Settings!$C$4,12,1)-WEEKDAY(DATE(Settings!$C$4,12,1),3))+27))+2),Plans!$H$6:$H$155,0)),"")&IF(COUNTIFS(Plans!$H$6:$H$155,">="&((DATE(Settings!$C$4,12,1)-WEEKDAY(DATE(Settings!$C$4,12,1),3))+27),Plans!$H$6:$H$155,"<"&(((DATE(Settings!$C$4,12,1)-WEEKDAY(DATE(Settings!$C$4,12,1),3))+27)+1))>2,CHAR(10)&"+"&(COUNTIFS(Plans!$H$6:$H$155,">="&((DATE(Settings!$C$4,12,1)-WEEKDAY(DATE(Settings!$C$4,12,1),3))+27),Plans!$H$6:$H$155,"<"&(((DATE(Settings!$C$4,12,1)-WEEKDAY(DATE(Settings!$C$4,12,1),3))+27)+1))-2)&" more",""))
B14: =IF(MONTH(((DATE(Settings!$C$4,12,1)-WEEKDAY(DATE(Settings!$C$4,12,1),3))+28))=12,DAY(((DATE(Settings!$C$4,12,1)-WEEKDAY(DATE(Settings!$C$4,12,1),3))+28)),"") | C14: =IF(MONTH(((DATE(Settings!$C$4,12,1)-WEEKDAY(DATE(Settings!$C$4,12,1),3))+29))=12,DAY(((DATE(Settings!$C$4,12,1)-WEEKDAY(DATE(Settings!$C$4,12,1),3))+29)),"") | D14: =IF(MONTH(((DATE(Settings!$C$4,12,1)-WEEKDAY(DATE(Settings!$C$4,12,1),3))+30))=12,DAY(((DATE(Settings!$C$4,12,1)-WEEKDAY(DATE(Settings!$C$4,12,1),3))+30)),"") | E14: =IF(MONTH(((DATE(Settings!$C$4,12,1)-WEEKDAY(DATE(Settings!$C$4,12,1),3))+31))=12,DAY(((DATE(Settings!$C$4,12,1)-WEEKDAY(DATE(Settings!$C$4,12,1),3))+31)),"") | F14: =IF(MONTH(((DATE(Settings!$C$4,12,1)-WEEKDAY(DATE(Settings!$C$4,12,1),3))+32))=12,DAY(((DATE(Settings!$C$4,12,1)-WEEKDAY(DATE(Settings!$C$4,12,1),3))+32)),"") | G14: =IF(MONTH(((DATE(Settings!$C$4,12,1)-WEEKDAY(DATE(Settings!$C$4,12,1),3))+33))=12,DAY(((DATE(Settings!$C$4,12,1)-WEEKDAY(DATE(Settings!$C$4,12,1),3))+33)),"") | H14: =IF(MONTH(((DATE(Settings!$C$4,12,1)-WEEKDAY(DATE(Settings!$C$4,12,1),3))+34))=12,DAY(((DATE(Settings!$C$4,12,1)-WEEKDAY(DATE(Settings!$C$4,12,1),3))+34)),"")
B15: =IF(OR(MONTH(((DATE(Settings!$C$4,12,1)-WEEKDAY(DATE(Settings!$C$4,12,1),3))+28))<>12,COUNTIFS(Plans!$H$6:$H$155,">="&((DATE(Settings!$C$4,12,1)-WEEKDAY(DATE(Settings!$C$4,12,1),3))+28),Plans!$H$6:$H$155,"<"&(((DATE(Settings!$C$4,12,1)-WEEKDAY(DATE(Settings!$C$4,12,1),3))+28)+1))=0),"",INDEX(Plans!$D$6:$D$155,MATCH(SMALL(Plans!$H$6:$H$155,COUNTIF(Plans!$H$6:$H$155,"<"&((DATE(Settings!$C$4,12,1)-WEEKDAY(DATE(Settings!$C$4,12,1),3))+28))+1),Plans!$H$6:$H$155,0))&IF(COUNTIFS(Plans!$H$6:$H$155,">="&((DATE(Settings!$C$4,12,1)-WEEKDAY(DATE(Settings!$C$4,12,1),3))+28),Plans!$H$6:$H$155,"<"&(((DATE(Settings!$C$4,12,1)-WEEKDAY(DATE(Settings!$C$4,12,1),3))+28)+1))>1,CHAR(10)&INDEX(Plans!$D$6:$D$155,MATCH(SMALL(Plans!$H$6:$H$155,COUNTIF(Plans!$H$6:$H$155,"<"&((DATE(Settings!$C$4,12,1)-WEEKDAY(DATE(Settings!$C$4,12,1),3))+28))+2),Plans!$H$6:$H$155,0)),"")&IF(COUNTIFS(Plans!$H$6:$H$155,">="&((DATE(Settings!$C$4,12,1)-WEEKDAY(DATE(Settings!$C$4,12,1),3))+28),Plans!$H$6:$H$155,"<"&(((DATE(Settings!$C$4,12,1)-WEEKDAY(DATE(Settings!$C$4,12,1),3))+28)+1))>2,CHAR(10)&"+"&(COUNTIFS(Plans!$H$6:$H$155,">="&((DATE(Settings!$C$4,12,1)-WEEKDAY(DATE(Settings!$C$4,12,1),3))+28),Plans!$H$6:$H$155,"<"&(((DATE(Settings!$C$4,12,1)-WEEKDAY(DATE(Settings!$C$4,12,1),3))+28)+1))-2)&" more","")) | C15: =IF(OR(MONTH(((DATE(Settings!$C$4,12,1)-WEEKDAY(DATE(Settings!$C$4,12,1),3))+29))<>12,COUNTIFS(Plans!$H$6:$H$155,">="&((DATE(Settings!$C$4,12,1)-WEEKDAY(DATE(Settings!$C$4,12,1),3))+29),Plans!$H$6:$H$155,"<"&(((DATE(Settings!$C$4,12,1)-WEEKDAY(DATE(Settings!$C$4,12,1),3))+29)+1))=0),"",INDEX(Plans!$D$6:$D$155,MATCH(SMALL(Plans!$H$6:$H$155,COUNTIF(Plans!$H$6:$H$155,"<"&((DATE(Settings!$C$4,12,1)-WEEKDAY(DATE(Settings!$C$4,12,1),3))+29))+1),Plans!$H$6:$H$155,0))&IF(COUNTIFS(Plans!$H$6:$H$155,">="&((DATE(Settings!$C$4,12,1)-WEEKDAY(DATE(Settings!$C$4,12,1),3))+29),Plans!$H$6:$H$155,"<"&(((DATE(Settings!$C$4,12,1)-WEEKDAY(DATE(Settings!$C$4,12,1),3))+29)+1))>1,CHAR(10)&INDEX(Plans!$D$6:$D$155,MATCH(SMALL(Plans!$H$6:$H$155,COUNTIF(Plans!$H$6:$H$155,"<"&((DATE(Settings!$C$4,12,1)-WEEKDAY(DATE(Settings!$C$4,12,1),3))+29))+2),Plans!$H$6:$H$155,0)),"")&IF(COUNTIFS(Plans!$H$6:$H$155,">="&((DATE(Settings!$C$4,12,1)-WEEKDAY(DATE(Settings!$C$4,12,1),3))+29),Plans!$H$6:$H$155,"<"&(((DATE(Settings!$C$4,12,1)-WEEKDAY(DATE(Settings!$C$4,12,1),3))+29)+1))>2,CHAR(10)&"+"&(COUNTIFS(Plans!$H$6:$H$155,">="&((DATE(Settings!$C$4,12,1)-WEEKDAY(DATE(Settings!$C$4,12,1),3))+29),Plans!$H$6:$H$155,"<"&(((DATE(Settings!$C$4,12,1)-WEEKDAY(DATE(Settings!$C$4,12,1),3))+29)+1))-2)&" more","")) | D15: =IF(OR(MONTH(((DATE(Settings!$C$4,12,1)-WEEKDAY(DATE(Settings!$C$4,12,1),3))+30))<>12,COUNTIFS(Plans!$H$6:$H$155,">="&((DATE(Settings!$C$4,12,1)-WEEKDAY(DATE(Settings!$C$4,12,1),3))+30),Plans!$H$6:$H$155,"<"&(((DATE(Settings!$C$4,12,1)-WEEKDAY(DATE(Settings!$C$4,12,1),3))+30)+1))=0),"",INDEX(Plans!$D$6:$D$155,MATCH(SMALL(Plans!$H$6:$H$155,COUNTIF(Plans!$H$6:$H$155,"<"&((DATE(Settings!$C$4,12,1)-WEEKDAY(DATE(Settings!$C$4,12,1),3))+30))+1),Plans!$H$6:$H$155,0))&IF(COUNTIFS(Plans!$H$6:$H$155,">="&((DATE(Settings!$C$4,12,1)-WEEKDAY(DATE(Settings!$C$4,12,1),3))+30),Plans!$H$6:$H$155,"<"&(((DATE(Settings!$C$4,12,1)-WEEKDAY(DATE(Settings!$C$4,12,1),3))+30)+1))>1,CHAR(10)&INDEX(Plans!$D$6:$D$155,MATCH(SMALL(Plans!$H$6:$H$155,COUNTIF(Plans!$H$6:$H$155,"<"&((DATE(Settings!$C$4,12,1)-WEEKDAY(DATE(Settings!$C$4,12,1),3))+30))+2),Plans!$H$6:$H$155,0)),"")&IF(COUNTIFS(Plans!$H$6:$H$155,">="&((DATE(Settings!$C$4,12,1)-WEEKDAY(DATE(Settings!$C$4,12,1),3))+30),Plans!$H$6:$H$155,"<"&(((DATE(Settings!$C$4,12,1)-WEEKDAY(DATE(Settings!$C$4,12,1),3))+30)+1))>2,CHAR(10)&"+"&(COUNTIFS(Plans!$H$6:$H$155,">="&((DATE(Settings!$C$4,12,1)-WEEKDAY(DATE(Settings!$C$4,12,1),3))+30),Plans!$H$6:$H$155,"<"&(((DATE(Settings!$C$4,12,1)-WEEKDAY(DATE(Settings!$C$4,12,1),3))+30)+1))-2)&" more","")) | E15: =IF(OR(MONTH(((DATE(Settings!$C$4,12,1)-WEEKDAY(DATE(Settings!$C$4,12,1),3))+31))<>12,COUNTIFS(Plans!$H$6:$H$155,">="&((DATE(Settings!$C$4,12,1)-WEEKDAY(DATE(Settings!$C$4,12,1),3))+31),Plans!$H$6:$H$155,"<"&(((DATE(Settings!$C$4,12,1)-WEEKDAY(DATE(Settings!$C$4,12,1),3))+31)+1))=0),"",INDEX(Plans!$D$6:$D$155,MATCH(SMALL(Plans!$H$6:$H$155,COUNTIF(Plans!$H$6:$H$155,"<"&((DATE(Settings!$C$4,12,1)-WEEKDAY(DATE(Settings!$C$4,12,1),3))+31))+1),Plans!$H$6:$H$155,0))&IF(COUNTIFS(Plans!$H$6:$H$155,">="&((DATE(Settings!$C$4,12,1)-WEEKDAY(DATE(Settings!$C$4,12,1),3))+31),Plans!$H$6:$H$155,"<"&(((DATE(Settings!$C$4,12,1)-WEEKDAY(DATE(Settings!$C$4,12,1),3))+31)+1))>1,CHAR(10)&INDEX(Plans!$D$6:$D$155,MATCH(SMALL(Plans!$H$6:$H$155,COUNTIF(Plans!$H$6:$H$155,"<"&((DATE(Settings!$C$4,12,1)-WEEKDAY(DATE(Settings!$C$4,12,1),3))+31))+2),Plans!$H$6:$H$155,0)),"")&IF(COUNTIFS(Plans!$H$6:$H$155,">="&((DATE(Settings!$C$4,12,1)-WEEKDAY(DATE(Settings!$C$4,12,1),3))+31),Plans!$H$6:$H$155,"<"&(((DATE(Settings!$C$4,12,1)-WEEKDAY(DATE(Settings!$C$4,12,1),3))+31)+1))>2,CHAR(10)&"+"&(COUNTIFS(Plans!$H$6:$H$155,">="&((DATE(Settings!$C$4,12,1)-WEEKDAY(DATE(Settings!$C$4,12,1),3))+31),Plans!$H$6:$H$155,"<"&(((DATE(Settings!$C$4,12,1)-WEEKDAY(DATE(Settings!$C$4,12,1),3))+31)+1))-2)&" more","")) | F15: =IF(OR(MONTH(((DATE(Settings!$C$4,12,1)-WEEKDAY(DATE(Settings!$C$4,12,1),3))+32))<>12,COUNTIFS(Plans!$H$6:$H$155,">="&((DATE(Settings!$C$4,12,1)-WEEKDAY(DATE(Settings!$C$4,12,1),3))+32),Plans!$H$6:$H$155,"<"&(((DATE(Settings!$C$4,12,1)-WEEKDAY(DATE(Settings!$C$4,12,1),3))+32)+1))=0),"",INDEX(Plans!$D$6:$D$155,MATCH(SMALL(Plans!$H$6:$H$155,COUNTIF(Plans!$H$6:$H$155,"<"&((DATE(Settings!$C$4,12,1)-WEEKDAY(DATE(Settings!$C$4,12,1),3))+32))+1),Plans!$H$6:$H$155,0))&IF(COUNTIFS(Plans!$H$6:$H$155,">="&((DATE(Settings!$C$4,12,1)-WEEKDAY(DATE(Settings!$C$4,12,1),3))+32),Plans!$H$6:$H$155,"<"&(((DATE(Settings!$C$4,12,1)-WEEKDAY(DATE(Settings!$C$4,12,1),3))+32)+1))>1,CHAR(10)&INDEX(Plans!$D$6:$D$155,MATCH(SMALL(Plans!$H$6:$H$155,COUNTIF(Plans!$H$6:$H$155,"<"&((DATE(Settings!$C$4,12,1)-WEEKDAY(DATE(Settings!$C$4,12,1),3))+32))+2),Plans!$H$6:$H$155,0)),"")&IF(COUNTIFS(Plans!$H$6:$H$155,">="&((DATE(Settings!$C$4,12,1)-WEEKDAY(DATE(Settings!$C$4,12,1),3))+32),Plans!$H$6:$H$155,"<"&(((DATE(Settings!$C$4,12,1)-WEEKDAY(DATE(Settings!$C$4,12,1),3))+32)+1))>2,CHAR(10)&"+"&(COUNTIFS(Plans!$H$6:$H$155,">="&((DATE(Settings!$C$4,12,1)-WEEKDAY(DATE(Settings!$C$4,12,1),3))+32),Plans!$H$6:$H$155,"<"&(((DATE(Settings!$C$4,12,1)-WEEKDAY(DATE(Settings!$C$4,12,1),3))+32)+1))-2)&" more","")) | G15: =IF(OR(MONTH(((DATE(Settings!$C$4,12,1)-WEEKDAY(DATE(Settings!$C$4,12,1),3))+33))<>12,COUNTIFS(Plans!$H$6:$H$155,">="&((DATE(Settings!$C$4,12,1)-WEEKDAY(DATE(Settings!$C$4,12,1),3))+33),Plans!$H$6:$H$155,"<"&(((DATE(Settings!$C$4,12,1)-WEEKDAY(DATE(Settings!$C$4,12,1),3))+33)+1))=0),"",INDEX(Plans!$D$6:$D$155,MATCH(SMALL(Plans!$H$6:$H$155,COUNTIF(Plans!$H$6:$H$155,"<"&((DATE(Settings!$C$4,12,1)-WEEKDAY(DATE(Settings!$C$4,12,1),3))+33))+1),Plans!$H$6:$H$155,0))&IF(COUNTIFS(Plans!$H$6:$H$155,">="&((DATE(Settings!$C$4,12,1)-WEEKDAY(DATE(Settings!$C$4,12,1),3))+33),Plans!$H$6:$H$155,"<"&(((DATE(Settings!$C$4,12,1)-WEEKDAY(DATE(Settings!$C$4,12,1),3))+33)+1))>1,CHAR(10)&INDEX(Plans!$D$6:$D$155,MATCH(SMALL(Plans!$H$6:$H$155,COUNTIF(Plans!$H$6:$H$155,"<"&((DATE(Settings!$C$4,12,1)-WEEKDAY(DATE(Settings!$C$4,12,1),3))+33))+2),Plans!$H$6:$H$155,0)),"")&IF(COUNTIFS(Plans!$H$6:$H$155,">="&((DATE(Settings!$C$4,12,1)-WEEKDAY(DATE(Settings!$C$4,12,1),3))+33),Plans!$H$6:$H$155,"<"&(((DATE(Settings!$C$4,12,1)-WEEKDAY(DATE(Settings!$C$4,12,1),3))+33)+1))>2,CHAR(10)&"+"&(COUNTIFS(Plans!$H$6:$H$155,">="&((DATE(Settings!$C$4,12,1)-WEEKDAY(DATE(Settings!$C$4,12,1),3))+33),Plans!$H$6:$H$155,"<"&(((DATE(Settings!$C$4,12,1)-WEEKDAY(DATE(Settings!$C$4,12,1),3))+33)+1))-2)&" more","")) | H15: =IF(OR(MONTH(((DATE(Settings!$C$4,12,1)-WEEKDAY(DATE(Settings!$C$4,12,1),3))+34))<>12,COUNTIFS(Plans!$H$6:$H$155,">="&((DATE(Settings!$C$4,12,1)-WEEKDAY(DATE(Settings!$C$4,12,1),3))+34),Plans!$H$6:$H$155,"<"&(((DATE(Settings!$C$4,12,1)-WEEKDAY(DATE(Settings!$C$4,12,1),3))+34)+1))=0),"",INDEX(Plans!$D$6:$D$155,MATCH(SMALL(Plans!$H$6:$H$155,COUNTIF(Plans!$H$6:$H$155,"<"&((DATE(Settings!$C$4,12,1)-WEEKDAY(DATE(Settings!$C$4,12,1),3))+34))+1),Plans!$H$6:$H$155,0))&IF(COUNTIFS(Plans!$H$6:$H$155,">="&((DATE(Settings!$C$4,12,1)-WEEKDAY(DATE(Settings!$C$4,12,1),3))+34),Plans!$H$6:$H$155,"<"&(((DATE(Settings!$C$4,12,1)-WEEKDAY(DATE(Settings!$C$4,12,1),3))+34)+1))>1,CHAR(10)&INDEX(Plans!$D$6:$D$155,MATCH(SMALL(Plans!$H$6:$H$155,COUNTIF(Plans!$H$6:$H$155,"<"&((DATE(Settings!$C$4,12,1)-WEEKDAY(DATE(Settings!$C$4,12,1),3))+34))+2),Plans!$H$6:$H$155,0)),"")&IF(COUNTIFS(Plans!$H$6:$H$155,">="&((DATE(Settings!$C$4,12,1)-WEEKDAY(DATE(Settings!$C$4,12,1),3))+34),Plans!$H$6:$H$155,"<"&(((DATE(Settings!$C$4,12,1)-WEEKDAY(DATE(Settings!$C$4,12,1),3))+34)+1))>2,CHAR(10)&"+"&(COUNTIFS(Plans!$H$6:$H$155,">="&((DATE(Settings!$C$4,12,1)-WEEKDAY(DATE(Settings!$C$4,12,1),3))+34),Plans!$H$6:$H$155,"<"&(((DATE(Settings!$C$4,12,1)-WEEKDAY(DATE(Settings!$C$4,12,1),3))+34)+1))-2)&" more",""))
B16: =IF(MONTH(((DATE(Settings!$C$4,12,1)-WEEKDAY(DATE(Settings!$C$4,12,1),3))+35))=12,DAY(((DATE(Settings!$C$4,12,1)-WEEKDAY(DATE(Settings!$C$4,12,1),3))+35)),"") | C16: =IF(MONTH(((DATE(Settings!$C$4,12,1)-WEEKDAY(DATE(Settings!$C$4,12,1),3))+36))=12,DAY(((DATE(Settings!$C$4,12,1)-WEEKDAY(DATE(Settings!$C$4,12,1),3))+36)),"") | D16: =IF(MONTH(((DATE(Settings!$C$4,12,1)-WEEKDAY(DATE(Settings!$C$4,12,1),3))+37))=12,DAY(((DATE(Settings!$C$4,12,1)-WEEKDAY(DATE(Settings!$C$4,12,1),3))+37)),"") | E16: =IF(MONTH(((DATE(Settings!$C$4,12,1)-WEEKDAY(DATE(Settings!$C$4,12,1),3))+38))=12,DAY(((DATE(Settings!$C$4,12,1)-WEEKDAY(DATE(Settings!$C$4,12,1),3))+38)),"") | F16: =IF(MONTH(((DATE(Settings!$C$4,12,1)-WEEKDAY(DATE(Settings!$C$4,12,1),3))+39))=12,DAY(((DATE(Settings!$C$4,12,1)-WEEKDAY(DATE(Settings!$C$4,12,1),3))+39)),"") | G16: =IF(MONTH(((DATE(Settings!$C$4,12,1)-WEEKDAY(DATE(Settings!$C$4,12,1),3))+40))=12,DAY(((DATE(Settings!$C$4,12,1)-WEEKDAY(DATE(Settings!$C$4,12,1),3))+40)),"") | H16: =IF(MONTH(((DATE(Settings!$C$4,12,1)-WEEKDAY(DATE(Settings!$C$4,12,1),3))+41))=12,DAY(((DATE(Settings!$C$4,12,1)-WEEKDAY(DATE(Settings!$C$4,12,1),3))+41)),"")
B17: =IF(OR(MONTH(((DATE(Settings!$C$4,12,1)-WEEKDAY(DATE(Settings!$C$4,12,1),3))+35))<>12,COUNTIFS(Plans!$H$6:$H$155,">="&((DATE(Settings!$C$4,12,1)-WEEKDAY(DATE(Settings!$C$4,12,1),3))+35),Plans!$H$6:$H$155,"<"&(((DATE(Settings!$C$4,12,1)-WEEKDAY(DATE(Settings!$C$4,12,1),3))+35)+1))=0),"",INDEX(Plans!$D$6:$D$155,MATCH(SMALL(Plans!$H$6:$H$155,COUNTIF(Plans!$H$6:$H$155,"<"&((DATE(Settings!$C$4,12,1)-WEEKDAY(DATE(Settings!$C$4,12,1),3))+35))+1),Plans!$H$6:$H$155,0))&IF(COUNTIFS(Plans!$H$6:$H$155,">="&((DATE(Settings!$C$4,12,1)-WEEKDAY(DATE(Settings!$C$4,12,1),3))+35),Plans!$H$6:$H$155,"<"&(((DATE(Settings!$C$4,12,1)-WEEKDAY(DATE(Settings!$C$4,12,1),3))+35)+1))>1,CHAR(10)&INDEX(Plans!$D$6:$D$155,MATCH(SMALL(Plans!$H$6:$H$155,COUNTIF(Plans!$H$6:$H$155,"<"&((DATE(Settings!$C$4,12,1)-WEEKDAY(DATE(Settings!$C$4,12,1),3))+35))+2),Plans!$H$6:$H$155,0)),"")&IF(COUNTIFS(Plans!$H$6:$H$155,">="&((DATE(Settings!$C$4,12,1)-WEEKDAY(DATE(Settings!$C$4,12,1),3))+35),Plans!$H$6:$H$155,"<"&(((DATE(Settings!$C$4,12,1)-WEEKDAY(DATE(Settings!$C$4,12,1),3))+35)+1))>2,CHAR(10)&"+"&(COUNTIFS(Plans!$H$6:$H$155,">="&((DATE(Settings!$C$4,12,1)-WEEKDAY(DATE(Settings!$C$4,12,1),3))+35),Plans!$H$6:$H$155,"<"&(((DATE(Settings!$C$4,12,1)-WEEKDAY(DATE(Settings!$C$4,12,1),3))+35)+1))-2)&" more","")) | C17: =IF(OR(MONTH(((DATE(Settings!$C$4,12,1)-WEEKDAY(DATE(Settings!$C$4,12,1),3))+36))<>12,COUNTIFS(Plans!$H$6:$H$155,">="&((DATE(Settings!$C$4,12,1)-WEEKDAY(DATE(Settings!$C$4,12,1),3))+36),Plans!$H$6:$H$155,"<"&(((DATE(Settings!$C$4,12,1)-WEEKDAY(DATE(Settings!$C$4,12,1),3))+36)+1))=0),"",INDEX(Plans!$D$6:$D$155,MATCH(SMALL(Plans!$H$6:$H$155,COUNTIF(Plans!$H$6:$H$155,"<"&((DATE(Settings!$C$4,12,1)-WEEKDAY(DATE(Settings!$C$4,12,1),3))+36))+1),Plans!$H$6:$H$155,0))&IF(COUNTIFS(Plans!$H$6:$H$155,">="&((DATE(Settings!$C$4,12,1)-WEEKDAY(DATE(Settings!$C$4,12,1),3))+36),Plans!$H$6:$H$155,"<"&(((DATE(Settings!$C$4,12,1)-WEEKDAY(DATE(Settings!$C$4,12,1),3))+36)+1))>1,CHAR(10)&INDEX(Plans!$D$6:$D$155,MATCH(SMALL(Plans!$H$6:$H$155,COUNTIF(Plans!$H$6:$H$155,"<"&((DATE(Settings!$C$4,12,1)-WEEKDAY(DATE(Settings!$C$4,12,1),3))+36))+2),Plans!$H$6:$H$155,0)),"")&IF(COUNTIFS(Plans!$H$6:$H$155,">="&((DATE(Settings!$C$4,12,1)-WEEKDAY(DATE(Settings!$C$4,12,1),3))+36),Plans!$H$6:$H$155,"<"&(((DATE(Settings!$C$4,12,1)-WEEKDAY(DATE(Settings!$C$4,12,1),3))+36)+1))>2,CHAR(10)&"+"&(COUNTIFS(Plans!$H$6:$H$155,">="&((DATE(Settings!$C$4,12,1)-WEEKDAY(DATE(Settings!$C$4,12,1),3))+36),Plans!$H$6:$H$155,"<"&(((DATE(Settings!$C$4,12,1)-WEEKDAY(DATE(Settings!$C$4,12,1),3))+36)+1))-2)&" more","")) | D17: =IF(OR(MONTH(((DATE(Settings!$C$4,12,1)-WEEKDAY(DATE(Settings!$C$4,12,1),3))+37))<>12,COUNTIFS(Plans!$H$6:$H$155,">="&((DATE(Settings!$C$4,12,1)-WEEKDAY(DATE(Settings!$C$4,12,1),3))+37),Plans!$H$6:$H$155,"<"&(((DATE(Settings!$C$4,12,1)-WEEKDAY(DATE(Settings!$C$4,12,1),3))+37)+1))=0),"",INDEX(Plans!$D$6:$D$155,MATCH(SMALL(Plans!$H$6:$H$155,COUNTIF(Plans!$H$6:$H$155,"<"&((DATE(Settings!$C$4,12,1)-WEEKDAY(DATE(Settings!$C$4,12,1),3))+37))+1),Plans!$H$6:$H$155,0))&IF(COUNTIFS(Plans!$H$6:$H$155,">="&((DATE(Settings!$C$4,12,1)-WEEKDAY(DATE(Settings!$C$4,12,1),3))+37),Plans!$H$6:$H$155,"<"&(((DATE(Settings!$C$4,12,1)-WEEKDAY(DATE(Settings!$C$4,12,1),3))+37)+1))>1,CHAR(10)&INDEX(Plans!$D$6:$D$155,MATCH(SMALL(Plans!$H$6:$H$155,COUNTIF(Plans!$H$6:$H$155,"<"&((DATE(Settings!$C$4,12,1)-WEEKDAY(DATE(Settings!$C$4,12,1),3))+37))+2),Plans!$H$6:$H$155,0)),"")&IF(COUNTIFS(Plans!$H$6:$H$155,">="&((DATE(Settings!$C$4,12,1)-WEEKDAY(DATE(Settings!$C$4,12,1),3))+37),Plans!$H$6:$H$155,"<"&(((DATE(Settings!$C$4,12,1)-WEEKDAY(DATE(Settings!$C$4,12,1),3))+37)+1))>2,CHAR(10)&"+"&(COUNTIFS(Plans!$H$6:$H$155,">="&((DATE(Settings!$C$4,12,1)-WEEKDAY(DATE(Settings!$C$4,12,1),3))+37),Plans!$H$6:$H$155,"<"&(((DATE(Settings!$C$4,12,1)-WEEKDAY(DATE(Settings!$C$4,12,1),3))+37)+1))-2)&" more","")) | E17: =IF(OR(MONTH(((DATE(Settings!$C$4,12,1)-WEEKDAY(DATE(Settings!$C$4,12,1),3))+38))<>12,COUNTIFS(Plans!$H$6:$H$155,">="&((DATE(Settings!$C$4,12,1)-WEEKDAY(DATE(Settings!$C$4,12,1),3))+38),Plans!$H$6:$H$155,"<"&(((DATE(Settings!$C$4,12,1)-WEEKDAY(DATE(Settings!$C$4,12,1),3))+38)+1))=0),"",INDEX(Plans!$D$6:$D$155,MATCH(SMALL(Plans!$H$6:$H$155,COUNTIF(Plans!$H$6:$H$155,"<"&((DATE(Settings!$C$4,12,1)-WEEKDAY(DATE(Settings!$C$4,12,1),3))+38))+1),Plans!$H$6:$H$155,0))&IF(COUNTIFS(Plans!$H$6:$H$155,">="&((DATE(Settings!$C$4,12,1)-WEEKDAY(DATE(Settings!$C$4,12,1),3))+38),Plans!$H$6:$H$155,"<"&(((DATE(Settings!$C$4,12,1)-WEEKDAY(DATE(Settings!$C$4,12,1),3))+38)+1))>1,CHAR(10)&INDEX(Plans!$D$6:$D$155,MATCH(SMALL(Plans!$H$6:$H$155,COUNTIF(Plans!$H$6:$H$155,"<"&((DATE(Settings!$C$4,12,1)-WEEKDAY(DATE(Settings!$C$4,12,1),3))+38))+2),Plans!$H$6:$H$155,0)),"")&IF(COUNTIFS(Plans!$H$6:$H$155,">="&((DATE(Settings!$C$4,12,1)-WEEKDAY(DATE(Settings!$C$4,12,1),3))+38),Plans!$H$6:$H$155,"<"&(((DATE(Settings!$C$4,12,1)-WEEKDAY(DATE(Settings!$C$4,12,1),3))+38)+1))>2,CHAR(10)&"+"&(COUNTIFS(Plans!$H$6:$H$155,">="&((DATE(Settings!$C$4,12,1)-WEEKDAY(DATE(Settings!$C$4,12,1),3))+38),Plans!$H$6:$H$155,"<"&(((DATE(Settings!$C$4,12,1)-WEEKDAY(DATE(Settings!$C$4,12,1),3))+38)+1))-2)&" more","")) | F17: =IF(OR(MONTH(((DATE(Settings!$C$4,12,1)-WEEKDAY(DATE(Settings!$C$4,12,1),3))+39))<>12,COUNTIFS(Plans!$H$6:$H$155,">="&((DATE(Settings!$C$4,12,1)-WEEKDAY(DATE(Settings!$C$4,12,1),3))+39),Plans!$H$6:$H$155,"<"&(((DATE(Settings!$C$4,12,1)-WEEKDAY(DATE(Settings!$C$4,12,1),3))+39)+1))=0),"",INDEX(Plans!$D$6:$D$155,MATCH(SMALL(Plans!$H$6:$H$155,COUNTIF(Plans!$H$6:$H$155,"<"&((DATE(Settings!$C$4,12,1)-WEEKDAY(DATE(Settings!$C$4,12,1),3))+39))+1),Plans!$H$6:$H$155,0))&IF(COUNTIFS(Plans!$H$6:$H$155,">="&((DATE(Settings!$C$4,12,1)-WEEKDAY(DATE(Settings!$C$4,12,1),3))+39),Plans!$H$6:$H$155,"<"&(((DATE(Settings!$C$4,12,1)-WEEKDAY(DATE(Settings!$C$4,12,1),3))+39)+1))>1,CHAR(10)&INDEX(Plans!$D$6:$D$155,MATCH(SMALL(Plans!$H$6:$H$155,COUNTIF(Plans!$H$6:$H$155,"<"&((DATE(Settings!$C$4,12,1)-WEEKDAY(DATE(Settings!$C$4,12,1),3))+39))+2),Plans!$H$6:$H$155,0)),"")&IF(COUNTIFS(Plans!$H$6:$H$155,">="&((DATE(Settings!$C$4,12,1)-WEEKDAY(DATE(Settings!$C$4,12,1),3))+39),Plans!$H$6:$H$155,"<"&(((DATE(Settings!$C$4,12,1)-WEEKDAY(DATE(Settings!$C$4,12,1),3))+39)+1))>2,CHAR(10)&"+"&(COUNTIFS(Plans!$H$6:$H$155,">="&((DATE(Settings!$C$4,12,1)-WEEKDAY(DATE(Settings!$C$4,12,1),3))+39),Plans!$H$6:$H$155,"<"&(((DATE(Settings!$C$4,12,1)-WEEKDAY(DATE(Settings!$C$4,12,1),3))+39)+1))-2)&" more","")) | G17: =IF(OR(MONTH(((DATE(Settings!$C$4,12,1)-WEEKDAY(DATE(Settings!$C$4,12,1),3))+40))<>12,COUNTIFS(Plans!$H$6:$H$155,">="&((DATE(Settings!$C$4,12,1)-WEEKDAY(DATE(Settings!$C$4,12,1),3))+40),Plans!$H$6:$H$155,"<"&(((DATE(Settings!$C$4,12,1)-WEEKDAY(DATE(Settings!$C$4,12,1),3))+40)+1))=0),"",INDEX(Plans!$D$6:$D$155,MATCH(SMALL(Plans!$H$6:$H$155,COUNTIF(Plans!$H$6:$H$155,"<"&((DATE(Settings!$C$4,12,1)-WEEKDAY(DATE(Settings!$C$4,12,1),3))+40))+1),Plans!$H$6:$H$155,0))&IF(COUNTIFS(Plans!$H$6:$H$155,">="&((DATE(Settings!$C$4,12,1)-WEEKDAY(DATE(Settings!$C$4,12,1),3))+40),Plans!$H$6:$H$155,"<"&(((DATE(Settings!$C$4,12,1)-WEEKDAY(DATE(Settings!$C$4,12,1),3))+40)+1))>1,CHAR(10)&INDEX(Plans!$D$6:$D$155,MATCH(SMALL(Plans!$H$6:$H$155,COUNTIF(Plans!$H$6:$H$155,"<"&((DATE(Settings!$C$4,12,1)-WEEKDAY(DATE(Settings!$C$4,12,1),3))+40))+2),Plans!$H$6:$H$155,0)),"")&IF(COUNTIFS(Plans!$H$6:$H$155,">="&((DATE(Settings!$C$4,12,1)-WEEKDAY(DATE(Settings!$C$4,12,1),3))+40),Plans!$H$6:$H$155,"<"&(((DATE(Settings!$C$4,12,1)-WEEKDAY(DATE(Settings!$C$4,12,1),3))+40)+1))>2,CHAR(10)&"+"&(COUNTIFS(Plans!$H$6:$H$155,">="&((DATE(Settings!$C$4,12,1)-WEEKDAY(DATE(Settings!$C$4,12,1),3))+40),Plans!$H$6:$H$155,"<"&(((DATE(Settings!$C$4,12,1)-WEEKDAY(DATE(Settings!$C$4,12,1),3))+40)+1))-2)&" more","")) | H17: =IF(OR(MONTH(((DATE(Settings!$C$4,12,1)-WEEKDAY(DATE(Settings!$C$4,12,1),3))+41))<>12,COUNTIFS(Plans!$H$6:$H$155,">="&((DATE(Settings!$C$4,12,1)-WEEKDAY(DATE(Settings!$C$4,12,1),3))+41),Plans!$H$6:$H$155,"<"&(((DATE(Settings!$C$4,12,1)-WEEKDAY(DATE(Settings!$C$4,12,1),3))+41)+1))=0),"",INDEX(Plans!$D$6:$D$155,MATCH(SMALL(Plans!$H$6:$H$155,COUNTIF(Plans!$H$6:$H$155,"<"&((DATE(Settings!$C$4,12,1)-WEEKDAY(DATE(Settings!$C$4,12,1),3))+41))+1),Plans!$H$6:$H$155,0))&IF(COUNTIFS(Plans!$H$6:$H$155,">="&((DATE(Settings!$C$4,12,1)-WEEKDAY(DATE(Settings!$C$4,12,1),3))+41),Plans!$H$6:$H$155,"<"&(((DATE(Settings!$C$4,12,1)-WEEKDAY(DATE(Settings!$C$4,12,1),3))+41)+1))>1,CHAR(10)&INDEX(Plans!$D$6:$D$155,MATCH(SMALL(Plans!$H$6:$H$155,COUNTIF(Plans!$H$6:$H$155,"<"&((DATE(Settings!$C$4,12,1)-WEEKDAY(DATE(Settings!$C$4,12,1),3))+41))+2),Plans!$H$6:$H$155,0)),"")&IF(COUNTIFS(Plans!$H$6:$H$155,">="&((DATE(Settings!$C$4,12,1)-WEEKDAY(DATE(Settings!$C$4,12,1),3))+41),Plans!$H$6:$H$155,"<"&(((DATE(Settings!$C$4,12,1)-WEEKDAY(DATE(Settings!$C$4,12,1),3))+41)+1))>2,CHAR(10)&"+"&(COUNTIFS(Plans!$H$6:$H$155,">="&((DATE(Settings!$C$4,12,1)-WEEKDAY(DATE(Settings!$C$4,12,1),3))+41),Plans!$H$6:$H$155,"<"&(((DATE(Settings!$C$4,12,1)-WEEKDAY(DATE(Settings!$C$4,12,1),3))+41)+1))-2)&" more",""))

Sheet Settings
B2: Settings
B3: The year and the currency. Everything else is on its own tab.
B4: Christmas of | C4: 2026 | E4: Next year, change the year: the countdown, the calendar and the dinner day follow it.
B5: Currency | C5: USD | E5: Amounts have no currency sign, so any currency works.

Sheet Start Here
B2: Start here
B3: Type only in the yellow cells. Everything else is calculated.
B5: 1 | C5: People: everyone you buy for, with a budget each. Settings has the year and the currency.
B7: 2 | C7: Gifts: one line per gift with its price. An x when you buy it, the day an order should arrive, then Here and Wrapped.
B9: 3 | C9: Budget and Costs: a budget for food, decorations, travel and the rest, and one line per cost.
B11: 4 | C11: Cards: who gets one, and an x when it is posted.
B13: 5 | C13: Dinner, Plans and December: the menu with a cooking plan, the guests, and your dates on a calendar.
C16: The example family, their gifts and plans are made up. Delete them and add your own.
C18: An order turns Late when its day has passed and it is not marked Here.
C20: Works in Google Sheets and Microsoft Excel, in any currency.
