Workbook

Sheet Dashboard
B2: Order dashboard
B3: What is due, what you are owed, and what each month earned.
B5: Open orders | C5: Due in 7 days | D5: Late | F5: Owed to you | I5: Sales this month | J5: Profit this month | L5: Orders this month
B6: =COUNT(Orders!$T$6:$T$1005) | C6: =COUNTIFS(Orders!$T$6:$T$1005,">="&TODAY(),Orders!$T$6:$T$1005,"<"&(TODAY()+8)) | D6: =COUNTIFS(Orders!$T$6:$T$1005,"<"&TODAY()) | F6: =SUM(Orders!$J$6:$J$1005) | I6: =SUMIFS(Orders!$H$6:$H$1005,Orders!$B$6:$B$1005,">="&DATE(YEAR(TODAY()),MONTH(TODAY()),1),Orders!$B$6:$B$1005,"<="&EOMONTH(TODAY(),0),Orders!$L$6:$L$1005,"<>Cancelled") | J6: =SUMIFS(Orders!$Q$6:$Q$1005,Orders!$B$6:$B$1005,">="&DATE(YEAR(TODAY()),MONTH(TODAY()),1),Orders!$B$6:$B$1005,"<="&EOMONTH(TODAY(),0),Orders!$L$6:$L$1005,"<>Cancelled") | L6: =COUNTIFS(Orders!$B$6:$B$1005,">="&DATE(YEAR(TODAY()),MONTH(TODAY()),1),Orders!$B$6:$B$1005,"<="&EOMONTH(TODAY(),0),Orders!$L$6:$L$1005,"<>Cancelled")
B8: Due | C8: Customer | D8: Product | E8: Qty | F8: Status | G8: When | I8: Needs attention
B9: =IF(O9="","",INT(O9)) | C9: =IF(O9="","",INDEX(Orders!$C$6:$C$1005,MATCH(O9,Orders!$T$6:$T$1005,0))) | D9: =IF(O9="","",INDEX(Orders!$D$6:$D$1005,MATCH(O9,Orders!$T$6:$T$1005,0))) | E9: =IF(O9="","",INDEX(Orders!$E$6:$E$1005,MATCH(O9,Orders!$T$6:$T$1005,0))) | F9: =IF(O9="","",INDEX(Orders!$L$6:$L$1005,MATCH(O9,Orders!$T$6:$T$1005,0))) | G9: =IF(O9="","",INDEX(Orders!$R$6:$R$1005,MATCH(O9,Orders!$T$6:$T$1005,0))) | I9: =IF(COUNTIFS(Orders!$T$6:$T$1005,"<"&TODAY())=0,"No order is late",IF(COUNTIFS(Orders!$T$6:$T$1005,"<"&TODAY())=1,"1 order is",COUNTIFS(Orders!$T$6:$T$1005,"<"&TODAY())&" orders are")&" past its due date") | O9: =IFERROR(SMALL(Orders!$T$6:$T$1005,1),"")
B10: =IF(O10="","",INT(O10)) | C10: =IF(O10="","",INDEX(Orders!$C$6:$C$1005,MATCH(O10,Orders!$T$6:$T$1005,0))) | D10: =IF(O10="","",INDEX(Orders!$D$6:$D$1005,MATCH(O10,Orders!$T$6:$T$1005,0))) | E10: =IF(O10="","",INDEX(Orders!$E$6:$E$1005,MATCH(O10,Orders!$T$6:$T$1005,0))) | F10: =IF(O10="","",INDEX(Orders!$L$6:$L$1005,MATCH(O10,Orders!$T$6:$T$1005,0))) | G10: =IF(O10="","",INDEX(Orders!$R$6:$R$1005,MATCH(O10,Orders!$T$6:$T$1005,0))) | I10: =IF(COUNTIFS(Orders!$J$6:$J$1005,">0")=0,"Every order is paid",IF(COUNTIFS(Orders!$J$6:$J$1005,">0")=1,"1 order has",COUNTIFS(Orders!$J$6:$J$1005,">0")&" orders have")&" a balance to collect: "&FIXED(SUM(Orders!$J$6:$J$1005),2)) | O10: =IFERROR(SMALL(Orders!$T$6:$T$1005,2),"")
B11: =IF(O11="","",INT(O11)) | C11: =IF(O11="","",INDEX(Orders!$C$6:$C$1005,MATCH(O11,Orders!$T$6:$T$1005,0))) | D11: =IF(O11="","",INDEX(Orders!$D$6:$D$1005,MATCH(O11,Orders!$T$6:$T$1005,0))) | E11: =IF(O11="","",INDEX(Orders!$E$6:$E$1005,MATCH(O11,Orders!$T$6:$T$1005,0))) | F11: =IF(O11="","",INDEX(Orders!$L$6:$L$1005,MATCH(O11,Orders!$T$6:$T$1005,0))) | G11: =IF(O11="","",INDEX(Orders!$R$6:$R$1005,MATCH(O11,Orders!$T$6:$T$1005,0))) | I11: =IF(COUNTIFS(Materials!$I$6:$I$205,">0")=0,"You have the materials for every open order",IF(COUNTIFS(Materials!$I$6:$I$205,">0")=1,"1 material is",COUNTIFS(Materials!$I$6:$I$205,">0")&" materials are")&" short for the open orders") | O11: =IFERROR(SMALL(Orders!$T$6:$T$1005,3),"")
B12: =IF(O12="","",INT(O12)) | C12: =IF(O12="","",INDEX(Orders!$C$6:$C$1005,MATCH(O12,Orders!$T$6:$T$1005,0))) | D12: =IF(O12="","",INDEX(Orders!$D$6:$D$1005,MATCH(O12,Orders!$T$6:$T$1005,0))) | E12: =IF(O12="","",INDEX(Orders!$E$6:$E$1005,MATCH(O12,Orders!$T$6:$T$1005,0))) | F12: =IF(O12="","",INDEX(Orders!$L$6:$L$1005,MATCH(O12,Orders!$T$6:$T$1005,0))) | G12: =IF(O12="","",INDEX(Orders!$R$6:$R$1005,MATCH(O12,Orders!$T$6:$T$1005,0))) | I12: =IF(COUNTIFS('Product materials'!$E$6:$E$505,"Add it to Materials")=0,"Every product has its cost",IF(COUNTIFS('Product materials'!$E$6:$E$505,"Add it to Materials")=1,"1 material line is",COUNTIFS('Product materials'!$E$6:$E$505,"Add it to Materials")&" material lines are")&" missing from Materials") | O12: =IFERROR(SMALL(Orders!$T$6:$T$1005,4),"")
B13: =IF(O13="","",INT(O13)) | C13: =IF(O13="","",INDEX(Orders!$C$6:$C$1005,MATCH(O13,Orders!$T$6:$T$1005,0))) | D13: =IF(O13="","",INDEX(Orders!$D$6:$D$1005,MATCH(O13,Orders!$T$6:$T$1005,0))) | E13: =IF(O13="","",INDEX(Orders!$E$6:$E$1005,MATCH(O13,Orders!$T$6:$T$1005,0))) | F13: =IF(O13="","",INDEX(Orders!$L$6:$L$1005,MATCH(O13,Orders!$T$6:$T$1005,0))) | G13: =IF(O13="","",INDEX(Orders!$R$6:$R$1005,MATCH(O13,Orders!$T$6:$T$1005,0))) | O13: =IFERROR(SMALL(Orders!$T$6:$T$1005,5),"")
B14: =IF(O14="","",INT(O14)) | C14: =IF(O14="","",INDEX(Orders!$C$6:$C$1005,MATCH(O14,Orders!$T$6:$T$1005,0))) | D14: =IF(O14="","",INDEX(Orders!$D$6:$D$1005,MATCH(O14,Orders!$T$6:$T$1005,0))) | E14: =IF(O14="","",INDEX(Orders!$E$6:$E$1005,MATCH(O14,Orders!$T$6:$T$1005,0))) | F14: =IF(O14="","",INDEX(Orders!$L$6:$L$1005,MATCH(O14,Orders!$T$6:$T$1005,0))) | G14: =IF(O14="","",INDEX(Orders!$R$6:$R$1005,MATCH(O14,Orders!$T$6:$T$1005,0))) | I14: Channel this year | J14: Orders | K14: Sales | L14: Profit | O14: =IFERROR(SMALL(Orders!$T$6:$T$1005,6),"")
B15: =IF(O15="","",INT(O15)) | C15: =IF(O15="","",INDEX(Orders!$C$6:$C$1005,MATCH(O15,Orders!$T$6:$T$1005,0))) | D15: =IF(O15="","",INDEX(Orders!$D$6:$D$1005,MATCH(O15,Orders!$T$6:$T$1005,0))) | E15: =IF(O15="","",INDEX(Orders!$E$6:$E$1005,MATCH(O15,Orders!$T$6:$T$1005,0))) | F15: =IF(O15="","",INDEX(Orders!$L$6:$L$1005,MATCH(O15,Orders!$T$6:$T$1005,0))) | G15: =IF(O15="","",INDEX(Orders!$R$6:$R$1005,MATCH(O15,Orders!$T$6:$T$1005,0))) | I15: =IF(Settings!B6="","",Settings!B6) | J15: =IF(I15="","",COUNTIFS(Orders!$M$6:$M$1005,I15,Orders!$L$6:$L$1005,"<>Cancelled",Orders!$B$6:$B$1005,">="&DATE(YEAR(TODAY()),1,1))) | K15: =IF(I15="","",SUMIFS(Orders!$H$6:$H$1005,Orders!$M$6:$M$1005,I15,Orders!$L$6:$L$1005,"<>Cancelled",Orders!$B$6:$B$1005,">="&DATE(YEAR(TODAY()),1,1))) | L15: =IF(I15="","",SUMIFS(Orders!$Q$6:$Q$1005,Orders!$M$6:$M$1005,I15,Orders!$L$6:$L$1005,"<>Cancelled",Orders!$B$6:$B$1005,">="&DATE(YEAR(TODAY()),1,1))) | O15: =IFERROR(SMALL(Orders!$T$6:$T$1005,7),"")
B16: =IF(O16="","",INT(O16)) | C16: =IF(O16="","",INDEX(Orders!$C$6:$C$1005,MATCH(O16,Orders!$T$6:$T$1005,0))) | D16: =IF(O16="","",INDEX(Orders!$D$6:$D$1005,MATCH(O16,Orders!$T$6:$T$1005,0))) | E16: =IF(O16="","",INDEX(Orders!$E$6:$E$1005,MATCH(O16,Orders!$T$6:$T$1005,0))) | F16: =IF(O16="","",INDEX(Orders!$L$6:$L$1005,MATCH(O16,Orders!$T$6:$T$1005,0))) | G16: =IF(O16="","",INDEX(Orders!$R$6:$R$1005,MATCH(O16,Orders!$T$6:$T$1005,0))) | I16: =IF(Settings!B7="","",Settings!B7) | J16: =IF(I16="","",COUNTIFS(Orders!$M$6:$M$1005,I16,Orders!$L$6:$L$1005,"<>Cancelled",Orders!$B$6:$B$1005,">="&DATE(YEAR(TODAY()),1,1))) | K16: =IF(I16="","",SUMIFS(Orders!$H$6:$H$1005,Orders!$M$6:$M$1005,I16,Orders!$L$6:$L$1005,"<>Cancelled",Orders!$B$6:$B$1005,">="&DATE(YEAR(TODAY()),1,1))) | L16: =IF(I16="","",SUMIFS(Orders!$Q$6:$Q$1005,Orders!$M$6:$M$1005,I16,Orders!$L$6:$L$1005,"<>Cancelled",Orders!$B$6:$B$1005,">="&DATE(YEAR(TODAY()),1,1))) | O16: =IFERROR(SMALL(Orders!$T$6:$T$1005,8),"")
B17: =IF(O17="","",INT(O17)) | C17: =IF(O17="","",INDEX(Orders!$C$6:$C$1005,MATCH(O17,Orders!$T$6:$T$1005,0))) | D17: =IF(O17="","",INDEX(Orders!$D$6:$D$1005,MATCH(O17,Orders!$T$6:$T$1005,0))) | E17: =IF(O17="","",INDEX(Orders!$E$6:$E$1005,MATCH(O17,Orders!$T$6:$T$1005,0))) | F17: =IF(O17="","",INDEX(Orders!$L$6:$L$1005,MATCH(O17,Orders!$T$6:$T$1005,0))) | G17: =IF(O17="","",INDEX(Orders!$R$6:$R$1005,MATCH(O17,Orders!$T$6:$T$1005,0))) | I17: =IF(Settings!B8="","",Settings!B8) | J17: =IF(I17="","",COUNTIFS(Orders!$M$6:$M$1005,I17,Orders!$L$6:$L$1005,"<>Cancelled",Orders!$B$6:$B$1005,">="&DATE(YEAR(TODAY()),1,1))) | K17: =IF(I17="","",SUMIFS(Orders!$H$6:$H$1005,Orders!$M$6:$M$1005,I17,Orders!$L$6:$L$1005,"<>Cancelled",Orders!$B$6:$B$1005,">="&DATE(YEAR(TODAY()),1,1))) | L17: =IF(I17="","",SUMIFS(Orders!$Q$6:$Q$1005,Orders!$M$6:$M$1005,I17,Orders!$L$6:$L$1005,"<>Cancelled",Orders!$B$6:$B$1005,">="&DATE(YEAR(TODAY()),1,1))) | O17: =IFERROR(SMALL(Orders!$T$6:$T$1005,9),"")
B18: =IF(O18="","",INT(O18)) | C18: =IF(O18="","",INDEX(Orders!$C$6:$C$1005,MATCH(O18,Orders!$T$6:$T$1005,0))) | D18: =IF(O18="","",INDEX(Orders!$D$6:$D$1005,MATCH(O18,Orders!$T$6:$T$1005,0))) | E18: =IF(O18="","",INDEX(Orders!$E$6:$E$1005,MATCH(O18,Orders!$T$6:$T$1005,0))) | F18: =IF(O18="","",INDEX(Orders!$L$6:$L$1005,MATCH(O18,Orders!$T$6:$T$1005,0))) | G18: =IF(O18="","",INDEX(Orders!$R$6:$R$1005,MATCH(O18,Orders!$T$6:$T$1005,0))) | I18: =IF(Settings!B9="","",Settings!B9) | J18: =IF(I18="","",COUNTIFS(Orders!$M$6:$M$1005,I18,Orders!$L$6:$L$1005,"<>Cancelled",Orders!$B$6:$B$1005,">="&DATE(YEAR(TODAY()),1,1))) | K18: =IF(I18="","",SUMIFS(Orders!$H$6:$H$1005,Orders!$M$6:$M$1005,I18,Orders!$L$6:$L$1005,"<>Cancelled",Orders!$B$6:$B$1005,">="&DATE(YEAR(TODAY()),1,1))) | L18: =IF(I18="","",SUMIFS(Orders!$Q$6:$Q$1005,Orders!$M$6:$M$1005,I18,Orders!$L$6:$L$1005,"<>Cancelled",Orders!$B$6:$B$1005,">="&DATE(YEAR(TODAY()),1,1))) | O18: =IFERROR(SMALL(Orders!$T$6:$T$1005,10),"")
B19: Open orders, the soonest due first. Late orders come first. | I19: =IF(Settings!B10="","",Settings!B10) | J19: =IF(I19="","",COUNTIFS(Orders!$M$6:$M$1005,I19,Orders!$L$6:$L$1005,"<>Cancelled",Orders!$B$6:$B$1005,">="&DATE(YEAR(TODAY()),1,1))) | K19: =IF(I19="","",SUMIFS(Orders!$H$6:$H$1005,Orders!$M$6:$M$1005,I19,Orders!$L$6:$L$1005,"<>Cancelled",Orders!$B$6:$B$1005,">="&DATE(YEAR(TODAY()),1,1))) | L19: =IF(I19="","",SUMIFS(Orders!$Q$6:$Q$1005,Orders!$M$6:$M$1005,I19,Orders!$L$6:$L$1005,"<>Cancelled",Orders!$B$6:$B$1005,">="&DATE(YEAR(TODAY()),1,1)))
B21: Year | C21: 2026
B23: Month | C23: Orders | D23: Sales | F23: Materials | G23: Fees and postage | H23: Profit
B24: Jan | C24: =COUNTIFS(Orders!$B$6:$B$1005,">="&DATE($C$21,1,1),Orders!$B$6:$B$1005,"<="&EOMONTH(DATE($C$21,1,1),0),Orders!$L$6:$L$1005,"<>Cancelled") | D24: =SUMIFS(Orders!$H$6:$H$1005,Orders!$B$6:$B$1005,">="&DATE($C$21,1,1),Orders!$B$6:$B$1005,"<="&EOMONTH(DATE($C$21,1,1),0),Orders!$L$6:$L$1005,"<>Cancelled") | F24: =SUMIFS(Orders!$N$6:$N$1005,Orders!$B$6:$B$1005,">="&DATE($C$21,1,1),Orders!$B$6:$B$1005,"<="&EOMONTH(DATE($C$21,1,1),0),Orders!$L$6:$L$1005,"<>Cancelled") | G24: =SUMIFS(Orders!$O$6:$O$1005,Orders!$B$6:$B$1005,">="&DATE($C$21,1,1),Orders!$B$6:$B$1005,"<="&EOMONTH(DATE($C$21,1,1),0),Orders!$L$6:$L$1005,"<>Cancelled")+SUMIFS(Orders!$P$6:$P$1005,Orders!$B$6:$B$1005,">="&DATE($C$21,1,1),Orders!$B$6:$B$1005,"<="&EOMONTH(DATE($C$21,1,1),0),Orders!$L$6:$L$1005,"<>Cancelled") | H24: =D24-F24-G24
B25: Feb | C25: =COUNTIFS(Orders!$B$6:$B$1005,">="&DATE($C$21,2,1),Orders!$B$6:$B$1005,"<="&EOMONTH(DATE($C$21,2,1),0),Orders!$L$6:$L$1005,"<>Cancelled") | D25: =SUMIFS(Orders!$H$6:$H$1005,Orders!$B$6:$B$1005,">="&DATE($C$21,2,1),Orders!$B$6:$B$1005,"<="&EOMONTH(DATE($C$21,2,1),0),Orders!$L$6:$L$1005,"<>Cancelled") | F25: =SUMIFS(Orders!$N$6:$N$1005,Orders!$B$6:$B$1005,">="&DATE($C$21,2,1),Orders!$B$6:$B$1005,"<="&EOMONTH(DATE($C$21,2,1),0),Orders!$L$6:$L$1005,"<>Cancelled") | G25: =SUMIFS(Orders!$O$6:$O$1005,Orders!$B$6:$B$1005,">="&DATE($C$21,2,1),Orders!$B$6:$B$1005,"<="&EOMONTH(DATE($C$21,2,1),0),Orders!$L$6:$L$1005,"<>Cancelled")+SUMIFS(Orders!$P$6:$P$1005,Orders!$B$6:$B$1005,">="&DATE($C$21,2,1),Orders!$B$6:$B$1005,"<="&EOMONTH(DATE($C$21,2,1),0),Orders!$L$6:$L$1005,"<>Cancelled") | H25: =D25-F25-G25
B26: Mar | C26: =COUNTIFS(Orders!$B$6:$B$1005,">="&DATE($C$21,3,1),Orders!$B$6:$B$1005,"<="&EOMONTH(DATE($C$21,3,1),0),Orders!$L$6:$L$1005,"<>Cancelled") | D26: =SUMIFS(Orders!$H$6:$H$1005,Orders!$B$6:$B$1005,">="&DATE($C$21,3,1),Orders!$B$6:$B$1005,"<="&EOMONTH(DATE($C$21,3,1),0),Orders!$L$6:$L$1005,"<>Cancelled") | F26: =SUMIFS(Orders!$N$6:$N$1005,Orders!$B$6:$B$1005,">="&DATE($C$21,3,1),Orders!$B$6:$B$1005,"<="&EOMONTH(DATE($C$21,3,1),0),Orders!$L$6:$L$1005,"<>Cancelled") | G26: =SUMIFS(Orders!$O$6:$O$1005,Orders!$B$6:$B$1005,">="&DATE($C$21,3,1),Orders!$B$6:$B$1005,"<="&EOMONTH(DATE($C$21,3,1),0),Orders!$L$6:$L$1005,"<>Cancelled")+SUMIFS(Orders!$P$6:$P$1005,Orders!$B$6:$B$1005,">="&DATE($C$21,3,1),Orders!$B$6:$B$1005,"<="&EOMONTH(DATE($C$21,3,1),0),Orders!$L$6:$L$1005,"<>Cancelled") | H26: =D26-F26-G26
B27: Apr | C27: =COUNTIFS(Orders!$B$6:$B$1005,">="&DATE($C$21,4,1),Orders!$B$6:$B$1005,"<="&EOMONTH(DATE($C$21,4,1),0),Orders!$L$6:$L$1005,"<>Cancelled") | D27: =SUMIFS(Orders!$H$6:$H$1005,Orders!$B$6:$B$1005,">="&DATE($C$21,4,1),Orders!$B$6:$B$1005,"<="&EOMONTH(DATE($C$21,4,1),0),Orders!$L$6:$L$1005,"<>Cancelled") | F27: =SUMIFS(Orders!$N$6:$N$1005,Orders!$B$6:$B$1005,">="&DATE($C$21,4,1),Orders!$B$6:$B$1005,"<="&EOMONTH(DATE($C$21,4,1),0),Orders!$L$6:$L$1005,"<>Cancelled") | G27: =SUMIFS(Orders!$O$6:$O$1005,Orders!$B$6:$B$1005,">="&DATE($C$21,4,1),Orders!$B$6:$B$1005,"<="&EOMONTH(DATE($C$21,4,1),0),Orders!$L$6:$L$1005,"<>Cancelled")+SUMIFS(Orders!$P$6:$P$1005,Orders!$B$6:$B$1005,">="&DATE($C$21,4,1),Orders!$B$6:$B$1005,"<="&EOMONTH(DATE($C$21,4,1),0),Orders!$L$6:$L$1005,"<>Cancelled") | H27: =D27-F27-G27
B28: May | C28: =COUNTIFS(Orders!$B$6:$B$1005,">="&DATE($C$21,5,1),Orders!$B$6:$B$1005,"<="&EOMONTH(DATE($C$21,5,1),0),Orders!$L$6:$L$1005,"<>Cancelled") | D28: =SUMIFS(Orders!$H$6:$H$1005,Orders!$B$6:$B$1005,">="&DATE($C$21,5,1),Orders!$B$6:$B$1005,"<="&EOMONTH(DATE($C$21,5,1),0),Orders!$L$6:$L$1005,"<>Cancelled") | F28: =SUMIFS(Orders!$N$6:$N$1005,Orders!$B$6:$B$1005,">="&DATE($C$21,5,1),Orders!$B$6:$B$1005,"<="&EOMONTH(DATE($C$21,5,1),0),Orders!$L$6:$L$1005,"<>Cancelled") | G28: =SUMIFS(Orders!$O$6:$O$1005,Orders!$B$6:$B$1005,">="&DATE($C$21,5,1),Orders!$B$6:$B$1005,"<="&EOMONTH(DATE($C$21,5,1),0),Orders!$L$6:$L$1005,"<>Cancelled")+SUMIFS(Orders!$P$6:$P$1005,Orders!$B$6:$B$1005,">="&DATE($C$21,5,1),Orders!$B$6:$B$1005,"<="&EOMONTH(DATE($C$21,5,1),0),Orders!$L$6:$L$1005,"<>Cancelled") | H28: =D28-F28-G28
B29: Jun | C29: =COUNTIFS(Orders!$B$6:$B$1005,">="&DATE($C$21,6,1),Orders!$B$6:$B$1005,"<="&EOMONTH(DATE($C$21,6,1),0),Orders!$L$6:$L$1005,"<>Cancelled") | D29: =SUMIFS(Orders!$H$6:$H$1005,Orders!$B$6:$B$1005,">="&DATE($C$21,6,1),Orders!$B$6:$B$1005,"<="&EOMONTH(DATE($C$21,6,1),0),Orders!$L$6:$L$1005,"<>Cancelled") | F29: =SUMIFS(Orders!$N$6:$N$1005,Orders!$B$6:$B$1005,">="&DATE($C$21,6,1),Orders!$B$6:$B$1005,"<="&EOMONTH(DATE($C$21,6,1),0),Orders!$L$6:$L$1005,"<>Cancelled") | G29: =SUMIFS(Orders!$O$6:$O$1005,Orders!$B$6:$B$1005,">="&DATE($C$21,6,1),Orders!$B$6:$B$1005,"<="&EOMONTH(DATE($C$21,6,1),0),Orders!$L$6:$L$1005,"<>Cancelled")+SUMIFS(Orders!$P$6:$P$1005,Orders!$B$6:$B$1005,">="&DATE($C$21,6,1),Orders!$B$6:$B$1005,"<="&EOMONTH(DATE($C$21,6,1),0),Orders!$L$6:$L$1005,"<>Cancelled") | H29: =D29-F29-G29
B30: Jul | C30: =COUNTIFS(Orders!$B$6:$B$1005,">="&DATE($C$21,7,1),Orders!$B$6:$B$1005,"<="&EOMONTH(DATE($C$21,7,1),0),Orders!$L$6:$L$1005,"<>Cancelled") | D30: =SUMIFS(Orders!$H$6:$H$1005,Orders!$B$6:$B$1005,">="&DATE($C$21,7,1),Orders!$B$6:$B$1005,"<="&EOMONTH(DATE($C$21,7,1),0),Orders!$L$6:$L$1005,"<>Cancelled") | F30: =SUMIFS(Orders!$N$6:$N$1005,Orders!$B$6:$B$1005,">="&DATE($C$21,7,1),Orders!$B$6:$B$1005,"<="&EOMONTH(DATE($C$21,7,1),0),Orders!$L$6:$L$1005,"<>Cancelled") | G30: =SUMIFS(Orders!$O$6:$O$1005,Orders!$B$6:$B$1005,">="&DATE($C$21,7,1),Orders!$B$6:$B$1005,"<="&EOMONTH(DATE($C$21,7,1),0),Orders!$L$6:$L$1005,"<>Cancelled")+SUMIFS(Orders!$P$6:$P$1005,Orders!$B$6:$B$1005,">="&DATE($C$21,7,1),Orders!$B$6:$B$1005,"<="&EOMONTH(DATE($C$21,7,1),0),Orders!$L$6:$L$1005,"<>Cancelled") | H30: =D30-F30-G30
B31: Aug | C31: =COUNTIFS(Orders!$B$6:$B$1005,">="&DATE($C$21,8,1),Orders!$B$6:$B$1005,"<="&EOMONTH(DATE($C$21,8,1),0),Orders!$L$6:$L$1005,"<>Cancelled") | D31: =SUMIFS(Orders!$H$6:$H$1005,Orders!$B$6:$B$1005,">="&DATE($C$21,8,1),Orders!$B$6:$B$1005,"<="&EOMONTH(DATE($C$21,8,1),0),Orders!$L$6:$L$1005,"<>Cancelled") | F31: =SUMIFS(Orders!$N$6:$N$1005,Orders!$B$6:$B$1005,">="&DATE($C$21,8,1),Orders!$B$6:$B$1005,"<="&EOMONTH(DATE($C$21,8,1),0),Orders!$L$6:$L$1005,"<>Cancelled") | G31: =SUMIFS(Orders!$O$6:$O$1005,Orders!$B$6:$B$1005,">="&DATE($C$21,8,1),Orders!$B$6:$B$1005,"<="&EOMONTH(DATE($C$21,8,1),0),Orders!$L$6:$L$1005,"<>Cancelled")+SUMIFS(Orders!$P$6:$P$1005,Orders!$B$6:$B$1005,">="&DATE($C$21,8,1),Orders!$B$6:$B$1005,"<="&EOMONTH(DATE($C$21,8,1),0),Orders!$L$6:$L$1005,"<>Cancelled") | H31: =D31-F31-G31
B32: Sep | C32: =COUNTIFS(Orders!$B$6:$B$1005,">="&DATE($C$21,9,1),Orders!$B$6:$B$1005,"<="&EOMONTH(DATE($C$21,9,1),0),Orders!$L$6:$L$1005,"<>Cancelled") | D32: =SUMIFS(Orders!$H$6:$H$1005,Orders!$B$6:$B$1005,">="&DATE($C$21,9,1),Orders!$B$6:$B$1005,"<="&EOMONTH(DATE($C$21,9,1),0),Orders!$L$6:$L$1005,"<>Cancelled") | F32: =SUMIFS(Orders!$N$6:$N$1005,Orders!$B$6:$B$1005,">="&DATE($C$21,9,1),Orders!$B$6:$B$1005,"<="&EOMONTH(DATE($C$21,9,1),0),Orders!$L$6:$L$1005,"<>Cancelled") | G32: =SUMIFS(Orders!$O$6:$O$1005,Orders!$B$6:$B$1005,">="&DATE($C$21,9,1),Orders!$B$6:$B$1005,"<="&EOMONTH(DATE($C$21,9,1),0),Orders!$L$6:$L$1005,"<>Cancelled")+SUMIFS(Orders!$P$6:$P$1005,Orders!$B$6:$B$1005,">="&DATE($C$21,9,1),Orders!$B$6:$B$1005,"<="&EOMONTH(DATE($C$21,9,1),0),Orders!$L$6:$L$1005,"<>Cancelled") | H32: =D32-F32-G32
B33: Oct | C33: =COUNTIFS(Orders!$B$6:$B$1005,">="&DATE($C$21,10,1),Orders!$B$6:$B$1005,"<="&EOMONTH(DATE($C$21,10,1),0),Orders!$L$6:$L$1005,"<>Cancelled") | D33: =SUMIFS(Orders!$H$6:$H$1005,Orders!$B$6:$B$1005,">="&DATE($C$21,10,1),Orders!$B$6:$B$1005,"<="&EOMONTH(DATE($C$21,10,1),0),Orders!$L$6:$L$1005,"<>Cancelled") | F33: =SUMIFS(Orders!$N$6:$N$1005,Orders!$B$6:$B$1005,">="&DATE($C$21,10,1),Orders!$B$6:$B$1005,"<="&EOMONTH(DATE($C$21,10,1),0),Orders!$L$6:$L$1005,"<>Cancelled") | G33: =SUMIFS(Orders!$O$6:$O$1005,Orders!$B$6:$B$1005,">="&DATE($C$21,10,1),Orders!$B$6:$B$1005,"<="&EOMONTH(DATE($C$21,10,1),0),Orders!$L$6:$L$1005,"<>Cancelled")+SUMIFS(Orders!$P$6:$P$1005,Orders!$B$6:$B$1005,">="&DATE($C$21,10,1),Orders!$B$6:$B$1005,"<="&EOMONTH(DATE($C$21,10,1),0),Orders!$L$6:$L$1005,"<>Cancelled") | H33: =D33-F33-G33
B34: Nov | C34: =COUNTIFS(Orders!$B$6:$B$1005,">="&DATE($C$21,11,1),Orders!$B$6:$B$1005,"<="&EOMONTH(DATE($C$21,11,1),0),Orders!$L$6:$L$1005,"<>Cancelled") | D34: =SUMIFS(Orders!$H$6:$H$1005,Orders!$B$6:$B$1005,">="&DATE($C$21,11,1),Orders!$B$6:$B$1005,"<="&EOMONTH(DATE($C$21,11,1),0),Orders!$L$6:$L$1005,"<>Cancelled") | F34: =SUMIFS(Orders!$N$6:$N$1005,Orders!$B$6:$B$1005,">="&DATE($C$21,11,1),Orders!$B$6:$B$1005,"<="&EOMONTH(DATE($C$21,11,1),0),Orders!$L$6:$L$1005,"<>Cancelled") | G34: =SUMIFS(Orders!$O$6:$O$1005,Orders!$B$6:$B$1005,">="&DATE($C$21,11,1),Orders!$B$6:$B$1005,"<="&EOMONTH(DATE($C$21,11,1),0),Orders!$L$6:$L$1005,"<>Cancelled")+SUMIFS(Orders!$P$6:$P$1005,Orders!$B$6:$B$1005,">="&DATE($C$21,11,1),Orders!$B$6:$B$1005,"<="&EOMONTH(DATE($C$21,11,1),0),Orders!$L$6:$L$1005,"<>Cancelled") | H34: =D34-F34-G34
B35: Dec | C35: =COUNTIFS(Orders!$B$6:$B$1005,">="&DATE($C$21,12,1),Orders!$B$6:$B$1005,"<="&EOMONTH(DATE($C$21,12,1),0),Orders!$L$6:$L$1005,"<>Cancelled") | D35: =SUMIFS(Orders!$H$6:$H$1005,Orders!$B$6:$B$1005,">="&DATE($C$21,12,1),Orders!$B$6:$B$1005,"<="&EOMONTH(DATE($C$21,12,1),0),Orders!$L$6:$L$1005,"<>Cancelled") | F35: =SUMIFS(Orders!$N$6:$N$1005,Orders!$B$6:$B$1005,">="&DATE($C$21,12,1),Orders!$B$6:$B$1005,"<="&EOMONTH(DATE($C$21,12,1),0),Orders!$L$6:$L$1005,"<>Cancelled") | G35: =SUMIFS(Orders!$O$6:$O$1005,Orders!$B$6:$B$1005,">="&DATE($C$21,12,1),Orders!$B$6:$B$1005,"<="&EOMONTH(DATE($C$21,12,1),0),Orders!$L$6:$L$1005,"<>Cancelled")+SUMIFS(Orders!$P$6:$P$1005,Orders!$B$6:$B$1005,">="&DATE($C$21,12,1),Orders!$B$6:$B$1005,"<="&EOMONTH(DATE($C$21,12,1),0),Orders!$L$6:$L$1005,"<>Cancelled") | H35: =D35-F35-G35
B36: Year | C36: =SUM(C24:C35) | D36: =SUM(D24:D35) | F36: =SUM(F24:F35) | G36: =SUM(G24:G35) | H36: =SUM(H24:H35)

Sheet Orders
B2: Orders
B3: One line per order. The total, costs, fees and profit fill in from your products and channels.
B5: Order date | C5: Customer | D5: Product | E5: Qty | F5: Extras | G5: Shipping charged | H5: Total | I5: Paid so far | J5: Balance | K5: Due date | L5: Status | M5: Channel | N5: Materials | O5: Postage | P5: Fees | Q5: Profit | R5: Due | S5: Note
B6: 46028 | C6: Dan King | D6: Soy candle 8 oz | E6: 1 | G6: 6.95 | H6: =IF(OR(B6="",D6=""),"",IF(N(E6)=0,1,E6)*IFERROR(INDEX(Products!$C$6:$C$105,MATCH(D6,Products!$B$6:$B$105,0)),0)+N(F6)+N(G6)) | I6: 28.95 | J6: =IF(OR(H6="",L6="Cancelled"),"",IF(H6-N(I6)>0.005,H6-N(I6),"")) | K6: 46036 | L6: Sent | M6: Etsy | N6: =IF(OR(H6="",L6="Cancelled"),"",IF(N(E6)=0,1,E6)*IFERROR(INDEX(Products!$E$6:$E$105,MATCH(D6,Products!$B$6:$B$105,0)),0)) | O6: 6.6 | P6: =IF(OR(H6="",L6="Cancelled"),"",ROUND(IFERROR(H6*INDEX(Settings!$C$6:$C$15,MATCH(M6,Settings!$B$6:$B$15,0))+INDEX(Settings!$D$6:$D$15,MATCH(M6,Settings!$B$6:$B$15,0)),0),2)) | Q6: =IF(OR(H6="",L6="Cancelled"),"",H6-N(N6)-N(O6)-N(P6)) | R6: =IF(OR(B6="",K6=""),"",IF(OR(L6="Sent",L6="Picked up"),"Done",IF(L6="Cancelled","Cancelled",IF(K6<TODAY(),"Late by "&(TODAY()-K6)&IF((TODAY()-K6)=1," day"," days"),IF(K6=TODAY(),"Due today","Due in "&(K6-TODAY())&IF((K6-TODAY())=1," day"," days")))))) | T6: =IF(AND(B6<>"",K6<>"",L6<>"Sent",L6<>"Picked up",L6<>"Cancelled"),K6+ROW()/10000000,"") | U6: =IF(OR(B6="",C6=""),"",B6+ROW()/10000000) | V6: =IF(U6="","",IF(COUNTIFS(Orders!$C$6:$C$1005,C6,Orders!$U$6:$U$1005,">"&U6)=0,1,0)) | W6: =IF(AND(B6<>"",K6<>"",L6<>"Sent",L6<>"Picked up",L6<>"Cancelled"),IF(N(E6)=0,1,E6),0) | X6: =IF(OR(B6="",D6=""),"",IF(N(E6)=0,1,E6))
B7: 46028 | C7: Ava Adams | D7: Soy candle 8 oz | E7: 1 | G7: 6.95 | H7: =IF(OR(B7="",D7=""),"",IF(N(E7)=0,1,E7)*IFERROR(INDEX(Products!$C$6:$C$105,MATCH(D7,Products!$B$6:$B$105,0)),0)+N(F7)+N(G7)) | I7: 28.95 | J7: =IF(OR(H7="",L7="Cancelled"),"",IF(H7-N(I7)>0.005,H7-N(I7),"")) | K7: 46038 | L7: Sent | M7: Own website | N7: =IF(OR(H7="",L7="Cancelled"),"",IF(N(E7)=0,1,E7)*IFERROR(INDEX(Products!$E$6:$E$105,MATCH(D7,Products!$B$6:$B$105,0)),0)) | O7: 7.13 | P7: =IF(OR(H7="",L7="Cancelled"),"",ROUND(IFERROR(H7*INDEX(Settings!$C$6:$C$15,MATCH(M7,Settings!$B$6:$B$15,0))+INDEX(Settings!$D$6:$D$15,MATCH(M7,Settings!$B$6:$B$15,0)),0),2)) | Q7: =IF(OR(H7="",L7="Cancelled"),"",H7-N(N7)-N(O7)-N(P7)) | R7: =IF(OR(B7="",K7=""),"",IF(OR(L7="Sent",L7="Picked up"),"Done",IF(L7="Cancelled","Cancelled",IF(K7<TODAY(),"Late by "&(TODAY()-K7)&IF((TODAY()-K7)=1," day"," days"),IF(K7=TODAY(),"Due today","Due in "&(K7-TODAY())&IF((K7-TODAY())=1," day"," days")))))) | T7: =IF(AND(B7<>"",K7<>"",L7<>"Sent",L7<>"Picked up",L7<>"Cancelled"),K7+ROW()/10000000,"") | U7: =IF(OR(B7="",C7=""),"",B7+ROW()/10000000) | V7: =IF(U7="","",IF(COUNTIFS(Orders!$C$6:$C$1005,C7,Orders!$U$6:$U$1005,">"&U7)=0,1,0)) | W7: =IF(AND(B7<>"",K7<>"",L7<>"Sent",L7<>"Picked up",L7<>"Cancelled"),IF(N(E7)=0,1,E7),0) | X7: =IF(OR(B7="",D7=""),"",IF(N(E7)=0,1,E7))
B8: 46032 | C8: Nora Lewis | D8: Soy candle 16 oz | E8: 4 | G8: 6.95 | H8: =IF(OR(B8="",D8=""),"",IF(N(E8)=0,1,E8)*IFERROR(INDEX(Products!$C$6:$C$105,MATCH(D8,Products!$B$6:$B$105,0)),0)+N(F8)+N(G8)) | I8: 142.95 | J8: =IF(OR(H8="",L8="Cancelled"),"",IF(H8-N(I8)>0.005,H8-N(I8),"")) | K8: 46040 | L8: Sent | M8: Etsy | N8: =IF(OR(H8="",L8="Cancelled"),"",IF(N(E8)=0,1,E8)*IFERROR(INDEX(Products!$E$6:$E$105,MATCH(D8,Products!$B$6:$B$105,0)),0)) | O8: 6.77 | P8: =IF(OR(H8="",L8="Cancelled"),"",ROUND(IFERROR(H8*INDEX(Settings!$C$6:$C$15,MATCH(M8,Settings!$B$6:$B$15,0))+INDEX(Settings!$D$6:$D$15,MATCH(M8,Settings!$B$6:$B$15,0)),0),2)) | Q8: =IF(OR(H8="",L8="Cancelled"),"",H8-N(N8)-N(O8)-N(P8)) | R8: =IF(OR(B8="",K8=""),"",IF(OR(L8="Sent",L8="Picked up"),"Done",IF(L8="Cancelled","Cancelled",IF(K8<TODAY(),"Late by "&(TODAY()-K8)&IF((TODAY()-K8)=1," day"," days"),IF(K8=TODAY(),"Due today","Due in "&(K8-TODAY())&IF((K8-TODAY())=1," day"," days")))))) | T8: =IF(AND(B8<>"",K8<>"",L8<>"Sent",L8<>"Picked up",L8<>"Cancelled"),K8+ROW()/10000000,"") | U8: =IF(OR(B8="",C8=""),"",B8+ROW()/10000000) | V8: =IF(U8="","",IF(COUNTIFS(Orders!$C$6:$C$1005,C8,Orders!$U$6:$U$1005,">"&U8)=0,1,0)) | W8: =IF(AND(B8<>"",K8<>"",L8<>"Sent",L8<>"Picked up",L8<>"Cancelled"),IF(N(E8)=0,1,E8),0) | X8: =IF(OR(B8="",D8=""),"",IF(N(E8)=0,1,E8))
B9: 46032 | C9: George Hill | D9: Soap bar | E9: 1 | G9: 6.95 | H9: =IF(OR(B9="",D9=""),"",IF(N(E9)=0,1,E9)*IFERROR(INDEX(Products!$C$6:$C$105,MATCH(D9,Products!$B$6:$B$105,0)),0)+N(F9)+N(G9)) | I9: 14.95 | J9: =IF(OR(H9="",L9="Cancelled"),"",IF(H9-N(I9)>0.005,H9-N(I9),"")) | K9: 46044 | L9: Sent | M9: Etsy | N9: =IF(OR(H9="",L9="Cancelled"),"",IF(N(E9)=0,1,E9)*IFERROR(INDEX(Products!$E$6:$E$105,MATCH(D9,Products!$B$6:$B$105,0)),0)) | O9: 6.69 | P9: =IF(OR(H9="",L9="Cancelled"),"",ROUND(IFERROR(H9*INDEX(Settings!$C$6:$C$15,MATCH(M9,Settings!$B$6:$B$15,0))+INDEX(Settings!$D$6:$D$15,MATCH(M9,Settings!$B$6:$B$15,0)),0),2)) | Q9: =IF(OR(H9="",L9="Cancelled"),"",H9-N(N9)-N(O9)-N(P9)) | R9: =IF(OR(B9="",K9=""),"",IF(OR(L9="Sent",L9="Picked up"),"Done",IF(L9="Cancelled","Cancelled",IF(K9<TODAY(),"Late by "&(TODAY()-K9)&IF((TODAY()-K9)=1," day"," days"),IF(K9=TODAY(),"Due today","Due in "&(K9-TODAY())&IF((K9-TODAY())=1," day"," days")))))) | T9: =IF(AND(B9<>"",K9<>"",L9<>"Sent",L9<>"Picked up",L9<>"Cancelled"),K9+ROW()/10000000,"") | U9: =IF(OR(B9="",C9=""),"",B9+ROW()/10000000) | V9: =IF(U9="","",IF(COUNTIFS(Orders!$C$6:$C$1005,C9,Orders!$U$6:$U$1005,">"&U9)=0,1,0)) | W9: =IF(AND(B9<>"",K9<>"",L9<>"Sent",L9<>"Picked up",L9<>"Cancelled"),IF(N(E9)=0,1,E9),0) | X9: =IF(OR(B9="",D9=""),"",IF(N(E9)=0,1,E9))
B10: 46034 | C10: Clara Mason | D10: Wedding favours, 10 tins | E10: 8 | G10: 6.95 | H10: =IF(OR(B10="",D10=""),"",IF(N(E10)=0,1,E10)*IFERROR(INDEX(Products!$C$6:$C$105,MATCH(D10,Products!$B$6:$B$105,0)),0)+N(F10)+N(G10)) | I10: 486.95 | J10: =IF(OR(H10="",L10="Cancelled"),"",IF(H10-N(I10)>0.005,H10-N(I10),"")) | K10: 46078 | L10: Sent | M10: Etsy | N10: =IF(OR(H10="",L10="Cancelled"),"",IF(N(E10)=0,1,E10)*IFERROR(INDEX(Products!$E$6:$E$105,MATCH(D10,Products!$B$6:$B$105,0)),0)) | O10: 7.74 | P10: =IF(OR(H10="",L10="Cancelled"),"",ROUND(IFERROR(H10*INDEX(Settings!$C$6:$C$15,MATCH(M10,Settings!$B$6:$B$15,0))+INDEX(Settings!$D$6:$D$15,MATCH(M10,Settings!$B$6:$B$15,0)),0),2)) | Q10: =IF(OR(H10="",L10="Cancelled"),"",H10-N(N10)-N(O10)-N(P10)) | R10: =IF(OR(B10="",K10=""),"",IF(OR(L10="Sent",L10="Picked up"),"Done",IF(L10="Cancelled","Cancelled",IF(K10<TODAY(),"Late by "&(TODAY()-K10)&IF((TODAY()-K10)=1," day"," days"),IF(K10=TODAY(),"Due today","Due in "&(K10-TODAY())&IF((K10-TODAY())=1," day"," days")))))) | T10: =IF(AND(B10<>"",K10<>"",L10<>"Sent",L10<>"Picked up",L10<>"Cancelled"),K10+ROW()/10000000,"") | U10: =IF(OR(B10="",C10=""),"",B10+ROW()/10000000) | V10: =IF(U10="","",IF(COUNTIFS(Orders!$C$6:$C$1005,C10,Orders!$U$6:$U$1005,">"&U10)=0,1,0)) | W10: =IF(AND(B10<>"",K10<>"",L10<>"Sent",L10<>"Picked up",L10<>"Cancelled"),IF(N(E10)=0,1,E10),0) | X10: =IF(OR(B10="",D10=""),"",IF(N(E10)=0,1,E10))
B11: 46035 | C11: Adam Cox | D11: Soy candle 8 oz | E11: 3 | F11: 15 | H11: =IF(OR(B11="",D11=""),"",IF(N(E11)=0,1,E11)*IFERROR(INDEX(Products!$C$6:$C$105,MATCH(D11,Products!$B$6:$B$105,0)),0)+N(F11)+N(G11)) | I11: 81 | J11: =IF(OR(H11="",L11="Cancelled"),"",IF(H11-N(I11)>0.005,H11-N(I11),"")) | K11: 46046 | L11: Picked up | M11: Instagram | N11: =IF(OR(H11="",L11="Cancelled"),"",IF(N(E11)=0,1,E11)*IFERROR(INDEX(Products!$E$6:$E$105,MATCH(D11,Products!$B$6:$B$105,0)),0)) | P11: =IF(OR(H11="",L11="Cancelled"),"",ROUND(IFERROR(H11*INDEX(Settings!$C$6:$C$15,MATCH(M11,Settings!$B$6:$B$15,0))+INDEX(Settings!$D$6:$D$15,MATCH(M11,Settings!$B$6:$B$15,0)),0),2)) | Q11: =IF(OR(H11="",L11="Cancelled"),"",H11-N(N11)-N(O11)-N(P11)) | R11: =IF(OR(B11="",K11=""),"",IF(OR(L11="Sent",L11="Picked up"),"Done",IF(L11="Cancelled","Cancelled",IF(K11<TODAY(),"Late by "&(TODAY()-K11)&IF((TODAY()-K11)=1," day"," days"),IF(K11=TODAY(),"Due today","Due in "&(K11-TODAY())&IF((K11-TODAY())=1," day"," days")))))) | S11: Custom label | T11: =IF(AND(B11<>"",K11<>"",L11<>"Sent",L11<>"Picked up",L11<>"Cancelled"),K11+ROW()/10000000,"") | U11: =IF(OR(B11="",C11=""),"",B11+ROW()/10000000) | V11: =IF(U11="","",IF(COUNTIFS(Orders!$C$6:$C$1005,C11,Orders!$U$6:$U$1005,">"&U11)=0,1,0)) | W11: =IF(AND(B11<>"",K11<>"",L11<>"Sent",L11<>"Picked up",L11<>"Cancelled"),IF(N(E11)=0,1,E11),0) | X11: =IF(OR(B11="",D11=""),"",IF(N(E11)=0,1,E11))
B12: 46037 | C12: Rita Price | D12: Soy candle 16 oz | E12: 1 | F12: 5 | G12: 6.95 | H12: =IF(OR(B12="",D12=""),"",IF(N(E12)=0,1,E12)*IFERROR(INDEX(Products!$C$6:$C$105,MATCH(D12,Products!$B$6:$B$105,0)),0)+N(F12)+N(G12)) | I12: 45.95 | J12: =IF(OR(H12="",L12="Cancelled"),"",IF(H12-N(I12)>0.005,H12-N(I12),"")) | K12: 46047 | L12: Sent | M12: Own website | N12: =IF(OR(H12="",L12="Cancelled"),"",IF(N(E12)=0,1,E12)*IFERROR(INDEX(Products!$E$6:$E$105,MATCH(D12,Products!$B$6:$B$105,0)),0)) | O12: 5.92 | P12: =IF(OR(H12="",L12="Cancelled"),"",ROUND(IFERROR(H12*INDEX(Settings!$C$6:$C$15,MATCH(M12,Settings!$B$6:$B$15,0))+INDEX(Settings!$D$6:$D$15,MATCH(M12,Settings!$B$6:$B$15,0)),0),2)) | Q12: =IF(OR(H12="",L12="Cancelled"),"",H12-N(N12)-N(O12)-N(P12)) | R12: =IF(OR(B12="",K12=""),"",IF(OR(L12="Sent",L12="Picked up"),"Done",IF(L12="Cancelled","Cancelled",IF(K12<TODAY(),"Late by "&(TODAY()-K12)&IF((TODAY()-K12)=1," day"," days"),IF(K12=TODAY(),"Due today","Due in "&(K12-TODAY())&IF((K12-TODAY())=1," day"," days")))))) | S12: Custom label | T12: =IF(AND(B12<>"",K12<>"",L12<>"Sent",L12<>"Picked up",L12<>"Cancelled"),K12+ROW()/10000000,"") | U12: =IF(OR(B12="",C12=""),"",B12+ROW()/10000000) | V12: =IF(U12="","",IF(COUNTIFS(Orders!$C$6:$C$1005,C12,Orders!$U$6:$U$1005,">"&U12)=0,1,0)) | W12: =IF(AND(B12<>"",K12<>"",L12<>"Sent",L12<>"Picked up",L12<>"Cancelled"),IF(N(E12)=0,1,E12),0) | X12: =IF(OR(B12="",D12=""),"",IF(N(E12)=0,1,E12))
B13: 46037 | C13: Jade Reed | D13: Wax melts, 6 pack | E13: 2 | G13: 6.95 | H13: =IF(OR(B13="",D13=""),"",IF(N(E13)=0,1,E13)*IFERROR(INDEX(Products!$C$6:$C$105,MATCH(D13,Products!$B$6:$B$105,0)),0)+N(F13)+N(G13)) | I13: 24.95 | J13: =IF(OR(H13="",L13="Cancelled"),"",IF(H13-N(I13)>0.005,H13-N(I13),"")) | K13: 46048 | L13: Sent | M13: Etsy | N13: =IF(OR(H13="",L13="Cancelled"),"",IF(N(E13)=0,1,E13)*IFERROR(INDEX(Products!$E$6:$E$105,MATCH(D13,Products!$B$6:$B$105,0)),0)) | O13: 7.58 | P13: =IF(OR(H13="",L13="Cancelled"),"",ROUND(IFERROR(H13*INDEX(Settings!$C$6:$C$15,MATCH(M13,Settings!$B$6:$B$15,0))+INDEX(Settings!$D$6:$D$15,MATCH(M13,Settings!$B$6:$B$15,0)),0),2)) | Q13: =IF(OR(H13="",L13="Cancelled"),"",H13-N(N13)-N(O13)-N(P13)) | R13: =IF(OR(B13="",K13=""),"",IF(OR(L13="Sent",L13="Picked up"),"Done",IF(L13="Cancelled","Cancelled",IF(K13<TODAY(),"Late by "&(TODAY()-K13)&IF((TODAY()-K13)=1," day"," days"),IF(K13=TODAY(),"Due today","Due in "&(K13-TODAY())&IF((K13-TODAY())=1," day"," days")))))) | T13: =IF(AND(B13<>"",K13<>"",L13<>"Sent",L13<>"Picked up",L13<>"Cancelled"),K13+ROW()/10000000,"") | U13: =IF(OR(B13="",C13=""),"",B13+ROW()/10000000) | V13: =IF(U13="","",IF(COUNTIFS(Orders!$C$6:$C$1005,C13,Orders!$U$6:$U$1005,">"&U13)=0,1,0)) | W13: =IF(AND(B13<>"",K13<>"",L13<>"Sent",L13<>"Picked up",L13<>"Cancelled"),IF(N(E13)=0,1,E13),0) | X13: =IF(OR(B13="",D13=""),"",IF(N(E13)=0,1,E13))
B14: 46040 | C14: Helen Kelly | D14: Soy candle 8 oz | E14: 4 | G14: 6.95 | H14: =IF(OR(B14="",D14=""),"",IF(N(E14)=0,1,E14)*IFERROR(INDEX(Products!$C$6:$C$105,MATCH(D14,Products!$B$6:$B$105,0)),0)+N(F14)+N(G14)) | I14: 94.95 | J14: =IF(OR(H14="",L14="Cancelled"),"",IF(H14-N(I14)>0.005,H14-N(I14),"")) | K14: 46048 | L14: Sent | M14: Etsy | N14: =IF(OR(H14="",L14="Cancelled"),"",IF(N(E14)=0,1,E14)*IFERROR(INDEX(Products!$E$6:$E$105,MATCH(D14,Products!$B$6:$B$105,0)),0)) | O14: 7.58 | P14: =IF(OR(H14="",L14="Cancelled"),"",ROUND(IFERROR(H14*INDEX(Settings!$C$6:$C$15,MATCH(M14,Settings!$B$6:$B$15,0))+INDEX(Settings!$D$6:$D$15,MATCH(M14,Settings!$B$6:$B$15,0)),0),2)) | Q14: =IF(OR(H14="",L14="Cancelled"),"",H14-N(N14)-N(O14)-N(P14)) | R14: =IF(OR(B14="",K14=""),"",IF(OR(L14="Sent",L14="Picked up"),"Done",IF(L14="Cancelled","Cancelled",IF(K14<TODAY(),"Late by "&(TODAY()-K14)&IF((TODAY()-K14)=1," day"," days"),IF(K14=TODAY(),"Due today","Due in "&(K14-TODAY())&IF((K14-TODAY())=1," day"," days")))))) | T14: =IF(AND(B14<>"",K14<>"",L14<>"Sent",L14<>"Picked up",L14<>"Cancelled"),K14+ROW()/10000000,"") | U14: =IF(OR(B14="",C14=""),"",B14+ROW()/10000000) | V14: =IF(U14="","",IF(COUNTIFS(Orders!$C$6:$C$1005,C14,Orders!$U$6:$U$1005,">"&U14)=0,1,0)) | W14: =IF(AND(B14<>"",K14<>"",L14<>"Sent",L14<>"Picked up",L14<>"Cancelled"),IF(N(E14)=0,1,E14),0) | X14: =IF(OR(B14="",D14=""),"",IF(N(E14)=0,1,E14))
B15: 46040 | C15: Leah Hughes | D15: Soy candle 16 oz | E15: 1 | H15: =IF(OR(B15="",D15=""),"",IF(N(E15)=0,1,E15)*IFERROR(INDEX(Products!$C$6:$C$105,MATCH(D15,Products!$B$6:$B$105,0)),0)+N(F15)+N(G15)) | I15: 34 | J15: =IF(OR(H15="",L15="Cancelled"),"",IF(H15-N(I15)>0.005,H15-N(I15),"")) | K15: 46048 | L15: Picked up | M15: Instagram | N15: =IF(OR(H15="",L15="Cancelled"),"",IF(N(E15)=0,1,E15)*IFERROR(INDEX(Products!$E$6:$E$105,MATCH(D15,Products!$B$6:$B$105,0)),0)) | P15: =IF(OR(H15="",L15="Cancelled"),"",ROUND(IFERROR(H15*INDEX(Settings!$C$6:$C$15,MATCH(M15,Settings!$B$6:$B$15,0))+INDEX(Settings!$D$6:$D$15,MATCH(M15,Settings!$B$6:$B$15,0)),0),2)) | Q15: =IF(OR(H15="",L15="Cancelled"),"",H15-N(N15)-N(O15)-N(P15)) | R15: =IF(OR(B15="",K15=""),"",IF(OR(L15="Sent",L15="Picked up"),"Done",IF(L15="Cancelled","Cancelled",IF(K15<TODAY(),"Late by "&(TODAY()-K15)&IF((TODAY()-K15)=1," day"," days"),IF(K15=TODAY(),"Due today","Due in "&(K15-TODAY())&IF((K15-TODAY())=1," day"," days")))))) | T15: =IF(AND(B15<>"",K15<>"",L15<>"Sent",L15<>"Picked up",L15<>"Cancelled"),K15+ROW()/10000000,"") | U15: =IF(OR(B15="",C15=""),"",B15+ROW()/10000000) | V15: =IF(U15="","",IF(COUNTIFS(Orders!$C$6:$C$1005,C15,Orders!$U$6:$U$1005,">"&U15)=0,1,0)) | W15: =IF(AND(B15<>"",K15<>"",L15<>"Sent",L15<>"Picked up",L15<>"Cancelled"),IF(N(E15)=0,1,E15),0) | X15: =IF(OR(B15="",D15=""),"",IF(N(E15)=0,1,E15))
B16: 46041 | C16: Adam Baker | D16: Soy candle 8 oz | E16: 3 | G16: 6.95 | H16: =IF(OR(B16="",D16=""),"",IF(N(E16)=0,1,E16)*IFERROR(INDEX(Products!$C$6:$C$105,MATCH(D16,Products!$B$6:$B$105,0)),0)+N(F16)+N(G16)) | I16: 72.95 | J16: =IF(OR(H16="",L16="Cancelled"),"",IF(H16-N(I16)>0.005,H16-N(I16),"")) | K16: 46046 | L16: Sent | M16: Etsy | N16: =IF(OR(H16="",L16="Cancelled"),"",IF(N(E16)=0,1,E16)*IFERROR(INDEX(Products!$E$6:$E$105,MATCH(D16,Products!$B$6:$B$105,0)),0)) | O16: 5.63 | P16: =IF(OR(H16="",L16="Cancelled"),"",ROUND(IFERROR(H16*INDEX(Settings!$C$6:$C$15,MATCH(M16,Settings!$B$6:$B$15,0))+INDEX(Settings!$D$6:$D$15,MATCH(M16,Settings!$B$6:$B$15,0)),0),2)) | Q16: =IF(OR(H16="",L16="Cancelled"),"",H16-N(N16)-N(O16)-N(P16)) | R16: =IF(OR(B16="",K16=""),"",IF(OR(L16="Sent",L16="Picked up"),"Done",IF(L16="Cancelled","Cancelled",IF(K16<TODAY(),"Late by "&(TODAY()-K16)&IF((TODAY()-K16)=1," day"," days"),IF(K16=TODAY(),"Due today","Due in "&(K16-TODAY())&IF((K16-TODAY())=1," day"," days")))))) | T16: =IF(AND(B16<>"",K16<>"",L16<>"Sent",L16<>"Picked up",L16<>"Cancelled"),K16+ROW()/10000000,"") | U16: =IF(OR(B16="",C16=""),"",B16+ROW()/10000000) | V16: =IF(U16="","",IF(COUNTIFS(Orders!$C$6:$C$1005,C16,Orders!$U$6:$U$1005,">"&U16)=0,1,0)) | W16: =IF(AND(B16<>"",K16<>"",L16<>"Sent",L16<>"Picked up",L16<>"Cancelled"),IF(N(E16)=0,1,E16),0) | X16: =IF(OR(B16="",D16=""),"",IF(N(E16)=0,1,E16))
B17: 46042 | C17: Iris Cole | D17: Soy candle 8 oz | E17: 1 | F17: 5 | G17: 6.95 | H17: =IF(OR(B17="",D17=""),"",IF(N(E17)=0,1,E17)*IFERROR(INDEX(Products!$C$6:$C$105,MATCH(D17,Products!$B$6:$B$105,0)),0)+N(F17)+N(G17)) | I17: 33.95 | J17: =IF(OR(H17="",L17="Cancelled"),"",IF(H17-N(I17)>0.005,H17-N(I17),"")) | K17: 46046 | L17: Sent | M17: Etsy | N17: =IF(OR(H17="",L17="Cancelled"),"",IF(N(E17)=0,1,E17)*IFERROR(INDEX(Products!$E$6:$E$105,MATCH(D17,Products!$B$6:$B$105,0)),0)) | O17: 5.86 | P17: =IF(OR(H17="",L17="Cancelled"),"",ROUND(IFERROR(H17*INDEX(Settings!$C$6:$C$15,MATCH(M17,Settings!$B$6:$B$15,0))+INDEX(Settings!$D$6:$D$15,MATCH(M17,Settings!$B$6:$B$15,0)),0),2)) | Q17: =IF(OR(H17="",L17="Cancelled"),"",H17-N(N17)-N(O17)-N(P17)) | R17: =IF(OR(B17="",K17=""),"",IF(OR(L17="Sent",L17="Picked up"),"Done",IF(L17="Cancelled","Cancelled",IF(K17<TODAY(),"Late by "&(TODAY()-K17)&IF((TODAY()-K17)=1," day"," days"),IF(K17=TODAY(),"Due today","Due in "&(K17-TODAY())&IF((K17-TODAY())=1," day"," days")))))) | S17: Custom label | T17: =IF(AND(B17<>"",K17<>"",L17<>"Sent",L17<>"Picked up",L17<>"Cancelled"),K17+ROW()/10000000,"") | U17: =IF(OR(B17="",C17=""),"",B17+ROW()/10000000) | V17: =IF(U17="","",IF(COUNTIFS(Orders!$C$6:$C$1005,C17,Orders!$U$6:$U$1005,">"&U17)=0,1,0)) | W17: =IF(AND(B17<>"",K17<>"",L17<>"Sent",L17<>"Picked up",L17<>"Cancelled"),IF(N(E17)=0,1,E17),0) | X17: =IF(OR(B17="",D17=""),"",IF(N(E17)=0,1,E17))
B18: 46042 | C18: Paula Fox | D18: Soap bar | E18: 1 | G18: 6.95 | H18: =IF(OR(B18="",D18=""),"",IF(N(E18)=0,1,E18)*IFERROR(INDEX(Products!$C$6:$C$105,MATCH(D18,Products!$B$6:$B$105,0)),0)+N(F18)+N(G18)) | I18: 14.95 | J18: =IF(OR(H18="",L18="Cancelled"),"",IF(H18-N(I18)>0.005,H18-N(I18),"")) | K18: 46050 | L18: Sent | M18: Etsy | N18: =IF(OR(H18="",L18="Cancelled"),"",IF(N(E18)=0,1,E18)*IFERROR(INDEX(Products!$E$6:$E$105,MATCH(D18,Products!$B$6:$B$105,0)),0)) | O18: 5.61 | P18: =IF(OR(H18="",L18="Cancelled"),"",ROUND(IFERROR(H18*INDEX(Settings!$C$6:$C$15,MATCH(M18,Settings!$B$6:$B$15,0))+INDEX(Settings!$D$6:$D$15,MATCH(M18,Settings!$B$6:$B$15,0)),0),2)) | Q18: =IF(OR(H18="",L18="Cancelled"),"",H18-N(N18)-N(O18)-N(P18)) | R18: =IF(OR(B18="",K18=""),"",IF(OR(L18="Sent",L18="Picked up"),"Done",IF(L18="Cancelled","Cancelled",IF(K18<TODAY(),"Late by "&(TODAY()-K18)&IF((TODAY()-K18)=1," day"," days"),IF(K18=TODAY(),"Due today","Due in "&(K18-TODAY())&IF((K18-TODAY())=1," day"," days")))))) | T18: =IF(AND(B18<>"",K18<>"",L18<>"Sent",L18<>"Picked up",L18<>"Cancelled"),K18+ROW()/10000000,"") | U18: =IF(OR(B18="",C18=""),"",B18+ROW()/10000000) | V18: =IF(U18="","",IF(COUNTIFS(Orders!$C$6:$C$1005,C18,Orders!$U$6:$U$1005,">"&U18)=0,1,0)) | W18: =IF(AND(B18<>"",K18<>"",L18<>"Sent",L18<>"Picked up",L18<>"Cancelled"),IF(N(E18)=0,1,E18),0) | X18: =IF(OR(B18="",D18=""),"",IF(N(E18)=0,1,E18))
B19: 46043 | C19: Leah Morgan | D19: Soy candle 16 oz | E19: 3 | G19: 6.95 | H19: =IF(OR(B19="",D19=""),"",IF(N(E19)=0,1,E19)*IFERROR(INDEX(Products!$C$6:$C$105,MATCH(D19,Products!$B$6:$B$105,0)),0)+N(F19)+N(G19)) | I19: 108.95 | J19: =IF(OR(H19="",L19="Cancelled"),"",IF(H19-N(I19)>0.005,H19-N(I19),"")) | K19: 46053 | L19: Sent | M19: Etsy | N19: =IF(OR(H19="",L19="Cancelled"),"",IF(N(E19)=0,1,E19)*IFERROR(INDEX(Products!$E$6:$E$105,MATCH(D19,Products!$B$6:$B$105,0)),0)) | O19: 5.46 | P19: =IF(OR(H19="",L19="Cancelled"),"",ROUND(IFERROR(H19*INDEX(Settings!$C$6:$C$15,MATCH(M19,Settings!$B$6:$B$15,0))+INDEX(Settings!$D$6:$D$15,MATCH(M19,Settings!$B$6:$B$15,0)),0),2)) | Q19: =IF(OR(H19="",L19="Cancelled"),"",H19-N(N19)-N(O19)-N(P19)) | R19: =IF(OR(B19="",K19=""),"",IF(OR(L19="Sent",L19="Picked up"),"Done",IF(L19="Cancelled","Cancelled",IF(K19<TODAY(),"Late by "&(TODAY()-K19)&IF((TODAY()-K19)=1," day"," days"),IF(K19=TODAY(),"Due today","Due in "&(K19-TODAY())&IF((K19-TODAY())=1," day"," days")))))) | T19: =IF(AND(B19<>"",K19<>"",L19<>"Sent",L19<>"Picked up",L19<>"Cancelled"),K19+ROW()/10000000,"") | U19: =IF(OR(B19="",C19=""),"",B19+ROW()/10000000) | V19: =IF(U19="","",IF(COUNTIFS(Orders!$C$6:$C$1005,C19,Orders!$U$6:$U$1005,">"&U19)=0,1,0)) | W19: =IF(AND(B19<>"",K19<>"",L19<>"Sent",L19<>"Picked up",L19<>"Cancelled"),IF(N(E19)=0,1,E19),0) | X19: =IF(OR(B19="",D19=""),"",IF(N(E19)=0,1,E19))
B20: 46043 | C20: Holly Cox | D20: Wedding favours, 10 tins | E20: 8 | G20: 6.95 | H20: =IF(OR(B20="",D20=""),"",IF(N(E20)=0,1,E20)*IFERROR(INDEX(Products!$C$6:$C$105,MATCH(D20,Products!$B$6:$B$105,0)),0)+N(F20)+N(G20)) | I20: 486.95 | J20: =IF(OR(H20="",L20="Cancelled"),"",IF(H20-N(I20)>0.005,H20-N(I20),"")) | K20: 46070 | L20: Sent | M20: Etsy | N20: =IF(OR(H20="",L20="Cancelled"),"",IF(N(E20)=0,1,E20)*IFERROR(INDEX(Products!$E$6:$E$105,MATCH(D20,Products!$B$6:$B$105,0)),0)) | O20: 5.3 | P20: =IF(OR(H20="",L20="Cancelled"),"",ROUND(IFERROR(H20*INDEX(Settings!$C$6:$C$15,MATCH(M20,Settings!$B$6:$B$15,0))+INDEX(Settings!$D$6:$D$15,MATCH(M20,Settings!$B$6:$B$15,0)),0),2)) | Q20: =IF(OR(H20="",L20="Cancelled"),"",H20-N(N20)-N(O20)-N(P20)) | R20: =IF(OR(B20="",K20=""),"",IF(OR(L20="Sent",L20="Picked up"),"Done",IF(L20="Cancelled","Cancelled",IF(K20<TODAY(),"Late by "&(TODAY()-K20)&IF((TODAY()-K20)=1," day"," days"),IF(K20=TODAY(),"Due today","Due in "&(K20-TODAY())&IF((K20-TODAY())=1," day"," days")))))) | T20: =IF(AND(B20<>"",K20<>"",L20<>"Sent",L20<>"Picked up",L20<>"Cancelled"),K20+ROW()/10000000,"") | U20: =IF(OR(B20="",C20=""),"",B20+ROW()/10000000) | V20: =IF(U20="","",IF(COUNTIFS(Orders!$C$6:$C$1005,C20,Orders!$U$6:$U$1005,">"&U20)=0,1,0)) | W20: =IF(AND(B20<>"",K20<>"",L20<>"Sent",L20<>"Picked up",L20<>"Cancelled"),IF(N(E20)=0,1,E20),0) | X20: =IF(OR(B20="",D20=""),"",IF(N(E20)=0,1,E20))
B21: 46044 | C21: Nina Kelly | D21: Soap bar | E21: 1 | G21: 6.95 | H21: =IF(OR(B21="",D21=""),"",IF(N(E21)=0,1,E21)*IFERROR(INDEX(Products!$C$6:$C$105,MATCH(D21,Products!$B$6:$B$105,0)),0)+N(F21)+N(G21)) | I21: 14.95 | J21: =IF(OR(H21="",L21="Cancelled"),"",IF(H21-N(I21)>0.005,H21-N(I21),"")) | K21: 46052 | L21: Sent | M21: Etsy | N21: =IF(OR(H21="",L21="Cancelled"),"",IF(N(E21)=0,1,E21)*IFERROR(INDEX(Products!$E$6:$E$105,MATCH(D21,Products!$B$6:$B$105,0)),0)) | O21: 6.16 | P21: =IF(OR(H21="",L21="Cancelled"),"",ROUND(IFERROR(H21*INDEX(Settings!$C$6:$C$15,MATCH(M21,Settings!$B$6:$B$15,0))+INDEX(Settings!$D$6:$D$15,MATCH(M21,Settings!$B$6:$B$15,0)),0),2)) | Q21: =IF(OR(H21="",L21="Cancelled"),"",H21-N(N21)-N(O21)-N(P21)) | R21: =IF(OR(B21="",K21=""),"",IF(OR(L21="Sent",L21="Picked up"),"Done",IF(L21="Cancelled","Cancelled",IF(K21<TODAY(),"Late by "&(TODAY()-K21)&IF((TODAY()-K21)=1," day"," days"),IF(K21=TODAY(),"Due today","Due in "&(K21-TODAY())&IF((K21-TODAY())=1," day"," days")))))) | T21: =IF(AND(B21<>"",K21<>"",L21<>"Sent",L21<>"Picked up",L21<>"Cancelled"),K21+ROW()/10000000,"") | U21: =IF(OR(B21="",C21=""),"",B21+ROW()/10000000) | V21: =IF(U21="","",IF(COUNTIFS(Orders!$C$6:$C$1005,C21,Orders!$U$6:$U$1005,">"&U21)=0,1,0)) | W21: =IF(AND(B21<>"",K21<>"",L21<>"Sent",L21<>"Picked up",L21<>"Cancelled"),IF(N(E21)=0,1,E21),0) | X21: =IF(OR(B21="",D21=""),"",IF(N(E21)=0,1,E21))
B22: 46044 | C22: Dina Cole | D22: Soy candle 8 oz | E22: 2 | G22: 6.95 | H22: =IF(OR(B22="",D22=""),"",IF(N(E22)=0,1,E22)*IFERROR(INDEX(Products!$C$6:$C$105,MATCH(D22,Products!$B$6:$B$105,0)),0)+N(F22)+N(G22)) | I22: 50.95 | J22: =IF(OR(H22="",L22="Cancelled"),"",IF(H22-N(I22)>0.005,H22-N(I22),"")) | K22: 46052 | L22: Sent | M22: Etsy | N22: =IF(OR(H22="",L22="Cancelled"),"",IF(N(E22)=0,1,E22)*IFERROR(INDEX(Products!$E$6:$E$105,MATCH(D22,Products!$B$6:$B$105,0)),0)) | O22: 6.25 | P22: =IF(OR(H22="",L22="Cancelled"),"",ROUND(IFERROR(H22*INDEX(Settings!$C$6:$C$15,MATCH(M22,Settings!$B$6:$B$15,0))+INDEX(Settings!$D$6:$D$15,MATCH(M22,Settings!$B$6:$B$15,0)),0),2)) | Q22: =IF(OR(H22="",L22="Cancelled"),"",H22-N(N22)-N(O22)-N(P22)) | R22: =IF(OR(B22="",K22=""),"",IF(OR(L22="Sent",L22="Picked up"),"Done",IF(L22="Cancelled","Cancelled",IF(K22<TODAY(),"Late by "&(TODAY()-K22)&IF((TODAY()-K22)=1," day"," days"),IF(K22=TODAY(),"Due today","Due in "&(K22-TODAY())&IF((K22-TODAY())=1," day"," days")))))) | T22: =IF(AND(B22<>"",K22<>"",L22<>"Sent",L22<>"Picked up",L22<>"Cancelled"),K22+ROW()/10000000,"") | U22: =IF(OR(B22="",C22=""),"",B22+ROW()/10000000) | V22: =IF(U22="","",IF(COUNTIFS(Orders!$C$6:$C$1005,C22,Orders!$U$6:$U$1005,">"&U22)=0,1,0)) | W22: =IF(AND(B22<>"",K22<>"",L22<>"Sent",L22<>"Picked up",L22<>"Cancelled"),IF(N(E22)=0,1,E22),0) | X22: =IF(OR(B22="",D22=""),"",IF(N(E22)=0,1,E22))
B23: 46045 | C23: Jon Reed | D23: Soy candle 8 oz | E23: 4 | F23: 20 | H23: =IF(OR(B23="",D23=""),"",IF(N(E23)=0,1,E23)*IFERROR(INDEX(Products!$C$6:$C$105,MATCH(D23,Products!$B$6:$B$105,0)),0)+N(F23)+N(G23)) | I23: 108 | J23: =IF(OR(H23="",L23="Cancelled"),"",IF(H23-N(I23)>0.005,H23-N(I23),"")) | K23: 46050 | L23: Picked up | M23: Craft market | N23: =IF(OR(H23="",L23="Cancelled"),"",IF(N(E23)=0,1,E23)*IFERROR(INDEX(Products!$E$6:$E$105,MATCH(D23,Products!$B$6:$B$105,0)),0)) | P23: =IF(OR(H23="",L23="Cancelled"),"",ROUND(IFERROR(H23*INDEX(Settings!$C$6:$C$15,MATCH(M23,Settings!$B$6:$B$15,0))+INDEX(Settings!$D$6:$D$15,MATCH(M23,Settings!$B$6:$B$15,0)),0),2)) | Q23: =IF(OR(H23="",L23="Cancelled"),"",H23-N(N23)-N(O23)-N(P23)) | R23: =IF(OR(B23="",K23=""),"",IF(OR(L23="Sent",L23="Picked up"),"Done",IF(L23="Cancelled","Cancelled",IF(K23<TODAY(),"Late by "&(TODAY()-K23)&IF((TODAY()-K23)=1," day"," days"),IF(K23=TODAY(),"Due today","Due in "&(K23-TODAY())&IF((K23-TODAY())=1," day"," days")))))) | S23: Custom label | T23: =IF(AND(B23<>"",K23<>"",L23<>"Sent",L23<>"Picked up",L23<>"Cancelled"),K23+ROW()/10000000,"") | U23: =IF(OR(B23="",C23=""),"",B23+ROW()/10000000) | V23: =IF(U23="","",IF(COUNTIFS(Orders!$C$6:$C$1005,C23,Orders!$U$6:$U$1005,">"&U23)=0,1,0)) | W23: =IF(AND(B23<>"",K23<>"",L23<>"Sent",L23<>"Picked up",L23<>"Cancelled"),IF(N(E23)=0,1,E23),0) | X23: =IF(OR(B23="",D23=""),"",IF(N(E23)=0,1,E23))
B24: 46046 | C24: Nina Reed | D24: Soy candle 8 oz | E24: 2 | G24: 6.95 | H24: =IF(OR(B24="",D24=""),"",IF(N(E24)=0,1,E24)*IFERROR(INDEX(Products!$C$6:$C$105,MATCH(D24,Products!$B$6:$B$105,0)),0)+N(F24)+N(G24)) | I24: 50.95 | J24: =IF(OR(H24="",L24="Cancelled"),"",IF(H24-N(I24)>0.005,H24-N(I24),"")) | K24: 46055 | L24: Sent | M24: Own website | N24: =IF(OR(H24="",L24="Cancelled"),"",IF(N(E24)=0,1,E24)*IFERROR(INDEX(Products!$E$6:$E$105,MATCH(D24,Products!$B$6:$B$105,0)),0)) | O24: 5.6 | P24: =IF(OR(H24="",L24="Cancelled"),"",ROUND(IFERROR(H24*INDEX(Settings!$C$6:$C$15,MATCH(M24,Settings!$B$6:$B$15,0))+INDEX(Settings!$D$6:$D$15,MATCH(M24,Settings!$B$6:$B$15,0)),0),2)) | Q24: =IF(OR(H24="",L24="Cancelled"),"",H24-N(N24)-N(O24)-N(P24)) | R24: =IF(OR(B24="",K24=""),"",IF(OR(L24="Sent",L24="Picked up"),"Done",IF(L24="Cancelled","Cancelled",IF(K24<TODAY(),"Late by "&(TODAY()-K24)&IF((TODAY()-K24)=1," day"," days"),IF(K24=TODAY(),"Due today","Due in "&(K24-TODAY())&IF((K24-TODAY())=1," day"," days")))))) | T24: =IF(AND(B24<>"",K24<>"",L24<>"Sent",L24<>"Picked up",L24<>"Cancelled"),K24+ROW()/10000000,"") | U24: =IF(OR(B24="",C24=""),"",B24+ROW()/10000000) | V24: =IF(U24="","",IF(COUNTIFS(Orders!$C$6:$C$1005,C24,Orders!$U$6:$U$1005,">"&U24)=0,1,0)) | W24: =IF(AND(B24<>"",K24<>"",L24<>"Sent",L24<>"Picked up",L24<>"Cancelled"),IF(N(E24)=0,1,E24),0) | X24: =IF(OR(B24="",D24=""),"",IF(N(E24)=0,1,E24))
B25: 46047 | C25: Rita Price | D25: Soy candle 8 oz | E25: 3 | F25: 15 | H25: =IF(OR(B25="",D25=""),"",IF(N(E25)=0,1,E25)*IFERROR(INDEX(Products!$C$6:$C$105,MATCH(D25,Products!$B$6:$B$105,0)),0)+N(F25)+N(G25)) | I25: 81 | J25: =IF(OR(H25="",L25="Cancelled"),"",IF(H25-N(I25)>0.005,H25-N(I25),"")) | K25: 46059 | L25: Picked up | M25: Instagram | N25: =IF(OR(H25="",L25="Cancelled"),"",IF(N(E25)=0,1,E25)*IFERROR(INDEX(Products!$E$6:$E$105,MATCH(D25,Products!$B$6:$B$105,0)),0)) | P25: =IF(OR(H25="",L25="Cancelled"),"",ROUND(IFERROR(H25*INDEX(Settings!$C$6:$C$15,MATCH(M25,Settings!$B$6:$B$15,0))+INDEX(Settings!$D$6:$D$15,MATCH(M25,Settings!$B$6:$B$15,0)),0),2)) | Q25: =IF(OR(H25="",L25="Cancelled"),"",H25-N(N25)-N(O25)-N(P25)) | R25: =IF(OR(B25="",K25=""),"",IF(OR(L25="Sent",L25="Picked up"),"Done",IF(L25="Cancelled","Cancelled",IF(K25<TODAY(),"Late by "&(TODAY()-K25)&IF((TODAY()-K25)=1," day"," days"),IF(K25=TODAY(),"Due today","Due in "&(K25-TODAY())&IF((K25-TODAY())=1," day"," days")))))) | S25: Custom label | T25: =IF(AND(B25<>"",K25<>"",L25<>"Sent",L25<>"Picked up",L25<>"Cancelled"),K25+ROW()/10000000,"") | U25: =IF(OR(B25="",C25=""),"",B25+ROW()/10000000) | V25: =IF(U25="","",IF(COUNTIFS(Orders!$C$6:$C$1005,C25,Orders!$U$6:$U$1005,">"&U25)=0,1,0)) | W25: =IF(AND(B25<>"",K25<>"",L25<>"Sent",L25<>"Picked up",L25<>"Cancelled"),IF(N(E25)=0,1,E25),0) | X25: =IF(OR(B25="",D25=""),"",IF(N(E25)=0,1,E25))
B26: 46048 | C26: Megan Murphy | D26: Soy candle 16 oz | E26: 2 | G26: 6.95 | H26: =IF(OR(B26="",D26=""),"",IF(N(E26)=0,1,E26)*IFERROR(INDEX(Products!$C$6:$C$105,MATCH(D26,Products!$B$6:$B$105,0)),0)+N(F26)+N(G26)) | I26: 74.95 | J26: =IF(OR(H26="",L26="Cancelled"),"",IF(H26-N(I26)>0.005,H26-N(I26),"")) | K26: 46058 | L26: Sent | M26: Etsy | N26: =IF(OR(H26="",L26="Cancelled"),"",IF(N(E26)=0,1,E26)*IFERROR(INDEX(Products!$E$6:$E$105,MATCH(D26,Products!$B$6:$B$105,0)),0)) | O26: 5.47 | P26: =IF(OR(H26="",L26="Cancelled"),"",ROUND(IFERROR(H26*INDEX(Settings!$C$6:$C$15,MATCH(M26,Settings!$B$6:$B$15,0))+INDEX(Settings!$D$6:$D$15,MATCH(M26,Settings!$B$6:$B$15,0)),0),2)) | Q26: =IF(OR(H26="",L26="Cancelled"),"",H26-N(N26)-N(O26)-N(P26)) | R26: =IF(OR(B26="",K26=""),"",IF(OR(L26="Sent",L26="Picked up"),"Done",IF(L26="Cancelled","Cancelled",IF(K26<TODAY(),"Late by "&(TODAY()-K26)&IF((TODAY()-K26)=1," day"," days"),IF(K26=TODAY(),"Due today","Due in "&(K26-TODAY())&IF((K26-TODAY())=1," day"," days")))))) | T26: =IF(AND(B26<>"",K26<>"",L26<>"Sent",L26<>"Picked up",L26<>"Cancelled"),K26+ROW()/10000000,"") | U26: =IF(OR(B26="",C26=""),"",B26+ROW()/10000000) | V26: =IF(U26="","",IF(COUNTIFS(Orders!$C$6:$C$1005,C26,Orders!$U$6:$U$1005,">"&U26)=0,1,0)) | W26: =IF(AND(B26<>"",K26<>"",L26<>"Sent",L26<>"Picked up",L26<>"Cancelled"),IF(N(E26)=0,1,E26),0) | X26: =IF(OR(B26="",D26=""),"",IF(N(E26)=0,1,E26))
B27: 46049 | C27: Clara Mason | D27: Soy candle 16 oz | E27: 2 | F27: 10 | G27: 6.95 | H27: =IF(OR(B27="",D27=""),"",IF(N(E27)=0,1,E27)*IFERROR(INDEX(Products!$C$6:$C$105,MATCH(D27,Products!$B$6:$B$105,0)),0)+N(F27)+N(G27)) | I27: 84.95 | J27: =IF(OR(H27="",L27="Cancelled"),"",IF(H27-N(I27)>0.005,H27-N(I27),"")) | K27: 46056 | L27: Sent | M27: Etsy | N27: =IF(OR(H27="",L27="Cancelled"),"",IF(N(E27)=0,1,E27)*IFERROR(INDEX(Products!$E$6:$E$105,MATCH(D27,Products!$B$6:$B$105,0)),0)) | O27: 5.31 | P27: =IF(OR(H27="",L27="Cancelled"),"",ROUND(IFERROR(H27*INDEX(Settings!$C$6:$C$15,MATCH(M27,Settings!$B$6:$B$15,0))+INDEX(Settings!$D$6:$D$15,MATCH(M27,Settings!$B$6:$B$15,0)),0),2)) | Q27: =IF(OR(H27="",L27="Cancelled"),"",H27-N(N27)-N(O27)-N(P27)) | R27: =IF(OR(B27="",K27=""),"",IF(OR(L27="Sent",L27="Picked up"),"Done",IF(L27="Cancelled","Cancelled",IF(K27<TODAY(),"Late by "&(TODAY()-K27)&IF((TODAY()-K27)=1," day"," days"),IF(K27=TODAY(),"Due today","Due in "&(K27-TODAY())&IF((K27-TODAY())=1," day"," days")))))) | S27: Custom label | T27: =IF(AND(B27<>"",K27<>"",L27<>"Sent",L27<>"Picked up",L27<>"Cancelled"),K27+ROW()/10000000,"") | U27: =IF(OR(B27="",C27=""),"",B27+ROW()/10000000) | V27: =IF(U27="","",IF(COUNTIFS(Orders!$C$6:$C$1005,C27,Orders!$U$6:$U$1005,">"&U27)=0,1,0)) | W27: =IF(AND(B27<>"",K27<>"",L27<>"Sent",L27<>"Picked up",L27<>"Cancelled"),IF(N(E27)=0,1,E27),0) | X27: =IF(OR(B27="",D27=""),"",IF(N(E27)=0,1,E27))
B28: 46050 | C28: Adam Cox | D28: Wax melts, 6 pack | E28: 3 | H28: =IF(OR(B28="",D28=""),"",IF(N(E28)=0,1,E28)*IFERROR(INDEX(Products!$C$6:$C$105,MATCH(D28,Products!$B$6:$B$105,0)),0)+N(F28)+N(G28)) | I28: 27 | J28: =IF(OR(H28="",L28="Cancelled"),"",IF(H28-N(I28)>0.005,H28-N(I28),"")) | K28: 46061 | L28: Picked up | M28: Instagram | N28: =IF(OR(H28="",L28="Cancelled"),"",IF(N(E28)=0,1,E28)*IFERROR(INDEX(Products!$E$6:$E$105,MATCH(D28,Products!$B$6:$B$105,0)),0)) | P28: =IF(OR(H28="",L28="Cancelled"),"",ROUND(IFERROR(H28*INDEX(Settings!$C$6:$C$15,MATCH(M28,Settings!$B$6:$B$15,0))+INDEX(Settings!$D$6:$D$15,MATCH(M28,Settings!$B$6:$B$15,0)),0),2)) | Q28: =IF(OR(H28="",L28="Cancelled"),"",H28-N(N28)-N(O28)-N(P28)) | R28: =IF(OR(B28="",K28=""),"",IF(OR(L28="Sent",L28="Picked up"),"Done",IF(L28="Cancelled","Cancelled",IF(K28<TODAY(),"Late by "&(TODAY()-K28)&IF((TODAY()-K28)=1," day"," days"),IF(K28=TODAY(),"Due today","Due in "&(K28-TODAY())&IF((K28-TODAY())=1," day"," days")))))) | T28: =IF(AND(B28<>"",K28<>"",L28<>"Sent",L28<>"Picked up",L28<>"Cancelled"),K28+ROW()/10000000,"") | U28: =IF(OR(B28="",C28=""),"",B28+ROW()/10000000) | V28: =IF(U28="","",IF(COUNTIFS(Orders!$C$6:$C$1005,C28,Orders!$U$6:$U$1005,">"&U28)=0,1,0)) | W28: =IF(AND(B28<>"",K28<>"",L28<>"Sent",L28<>"Picked up",L28<>"Cancelled"),IF(N(E28)=0,1,E28),0) | X28: =IF(OR(B28="",D28=""),"",IF(N(E28)=0,1,E28))
B29: 46051 | C29: Helen Kelly | D29: Soap bar | E29: 3 | H29: =IF(OR(B29="",D29=""),"",IF(N(E29)=0,1,E29)*IFERROR(INDEX(Products!$C$6:$C$105,MATCH(D29,Products!$B$6:$B$105,0)),0)+N(F29)+N(G29)) | I29: 24 | J29: =IF(OR(H29="",L29="Cancelled"),"",IF(H29-N(I29)>0.005,H29-N(I29),"")) | K29: 46063 | L29: Picked up | M29: Friends and family | N29: =IF(OR(H29="",L29="Cancelled"),"",IF(N(E29)=0,1,E29)*IFERROR(INDEX(Products!$E$6:$E$105,MATCH(D29,Products!$B$6:$B$105,0)),0)) | P29: =IF(OR(H29="",L29="Cancelled"),"",ROUND(IFERROR(H29*INDEX(Settings!$C$6:$C$15,MATCH(M29,Settings!$B$6:$B$15,0))+INDEX(Settings!$D$6:$D$15,MATCH(M29,Settings!$B$6:$B$15,0)),0),2)) | Q29: =IF(OR(H29="",L29="Cancelled"),"",H29-N(N29)-N(O29)-N(P29)) | R29: =IF(OR(B29="",K29=""),"",IF(OR(L29="Sent",L29="Picked up"),"Done",IF(L29="Cancelled","Cancelled",IF(K29<TODAY(),"Late by "&(TODAY()-K29)&IF((TODAY()-K29)=1," day"," days"),IF(K29=TODAY(),"Due today","Due in "&(K29-TODAY())&IF((K29-TODAY())=1," day"," days")))))) | T29: =IF(AND(B29<>"",K29<>"",L29<>"Sent",L29<>"Picked up",L29<>"Cancelled"),K29+ROW()/10000000,"") | U29: =IF(OR(B29="",C29=""),"",B29+ROW()/10000000) | V29: =IF(U29="","",IF(COUNTIFS(Orders!$C$6:$C$1005,C29,Orders!$U$6:$U$1005,">"&U29)=0,1,0)) | W29: =IF(AND(B29<>"",K29<>"",L29<>"Sent",L29<>"Picked up",L29<>"Cancelled"),IF(N(E29)=0,1,E29),0) | X29: =IF(OR(B29="",D29=""),"",IF(N(E29)=0,1,E29))
B30: 46051 | C30: Ruby Brooks | D30: Soy candle 8 oz | E30: 3 | G30: 6.95 | H30: =IF(OR(B30="",D30=""),"",IF(N(E30)=0,1,E30)*IFERROR(INDEX(Products!$C$6:$C$105,MATCH(D30,Products!$B$6:$B$105,0)),0)+N(F30)+N(G30)) | I30: 72.95 | J30: =IF(OR(H30="",L30="Cancelled"),"",IF(H30-N(I30)>0.005,H30-N(I30),"")) | K30: 46055 | L30: Sent | M30: Etsy | N30: =IF(OR(H30="",L30="Cancelled"),"",IF(N(E30)=0,1,E30)*IFERROR(INDEX(Products!$E$6:$E$105,MATCH(D30,Products!$B$6:$B$105,0)),0)) | O30: 5.65 | P30: =IF(OR(H30="",L30="Cancelled"),"",ROUND(IFERROR(H30*INDEX(Settings!$C$6:$C$15,MATCH(M30,Settings!$B$6:$B$15,0))+INDEX(Settings!$D$6:$D$15,MATCH(M30,Settings!$B$6:$B$15,0)),0),2)) | Q30: =IF(OR(H30="",L30="Cancelled"),"",H30-N(N30)-N(O30)-N(P30)) | R30: =IF(OR(B30="",K30=""),"",IF(OR(L30="Sent",L30="Picked up"),"Done",IF(L30="Cancelled","Cancelled",IF(K30<TODAY(),"Late by "&(TODAY()-K30)&IF((TODAY()-K30)=1," day"," days"),IF(K30=TODAY(),"Due today","Due in "&(K30-TODAY())&IF((K30-TODAY())=1," day"," days")))))) | T30: =IF(AND(B30<>"",K30<>"",L30<>"Sent",L30<>"Picked up",L30<>"Cancelled"),K30+ROW()/10000000,"") | U30: =IF(OR(B30="",C30=""),"",B30+ROW()/10000000) | V30: =IF(U30="","",IF(COUNTIFS(Orders!$C$6:$C$1005,C30,Orders!$U$6:$U$1005,">"&U30)=0,1,0)) | W30: =IF(AND(B30<>"",K30<>"",L30<>"Sent",L30<>"Picked up",L30<>"Cancelled"),IF(N(E30)=0,1,E30),0) | X30: =IF(OR(B30="",D30=""),"",IF(N(E30)=0,1,E30))
B31: 46052 | C31: Holly Cox | D31: Wax melts, 6 pack | E31: 1 | H31: =IF(OR(B31="",D31=""),"",IF(N(E31)=0,1,E31)*IFERROR(INDEX(Products!$C$6:$C$105,MATCH(D31,Products!$B$6:$B$105,0)),0)+N(F31)+N(G31)) | I31: 9 | J31: =IF(OR(H31="",L31="Cancelled"),"",IF(H31-N(I31)>0.005,H31-N(I31),"")) | K31: 46064 | L31: Picked up | M31: Craft market | N31: =IF(OR(H31="",L31="Cancelled"),"",IF(N(E31)=0,1,E31)*IFERROR(INDEX(Products!$E$6:$E$105,MATCH(D31,Products!$B$6:$B$105,0)),0)) | P31: =IF(OR(H31="",L31="Cancelled"),"",ROUND(IFERROR(H31*INDEX(Settings!$C$6:$C$15,MATCH(M31,Settings!$B$6:$B$15,0))+INDEX(Settings!$D$6:$D$15,MATCH(M31,Settings!$B$6:$B$15,0)),0),2)) | Q31: =IF(OR(H31="",L31="Cancelled"),"",H31-N(N31)-N(O31)-N(P31)) | R31: =IF(OR(B31="",K31=""),"",IF(OR(L31="Sent",L31="Picked up"),"Done",IF(L31="Cancelled","Cancelled",IF(K31<TODAY(),"Late by "&(TODAY()-K31)&IF((TODAY()-K31)=1," day"," days"),IF(K31=TODAY(),"Due today","Due in "&(K31-TODAY())&IF((K31-TODAY())=1," day"," days")))))) | T31: =IF(AND(B31<>"",K31<>"",L31<>"Sent",L31<>"Picked up",L31<>"Cancelled"),K31+ROW()/10000000,"") | U31: =IF(OR(B31="",C31=""),"",B31+ROW()/10000000) | V31: =IF(U31="","",IF(COUNTIFS(Orders!$C$6:$C$1005,C31,Orders!$U$6:$U$1005,">"&U31)=0,1,0)) | W31: =IF(AND(B31<>"",K31<>"",L31<>"Sent",L31<>"Picked up",L31<>"Cancelled"),IF(N(E31)=0,1,E31),0) | X31: =IF(OR(B31="",D31=""),"",IF(N(E31)=0,1,E31))
B32: 46053 | C32: Mia Cox | D32: Soy candle 8 oz | E32: 3 | H32: =IF(OR(B32="",D32=""),"",IF(N(E32)=0,1,E32)*IFERROR(INDEX(Products!$C$6:$C$105,MATCH(D32,Products!$B$6:$B$105,0)),0)+N(F32)+N(G32)) | I32: 66 | J32: =IF(OR(H32="",L32="Cancelled"),"",IF(H32-N(I32)>0.005,H32-N(I32),"")) | K32: 46062 | L32: Picked up | M32: Friends and family | N32: =IF(OR(H32="",L32="Cancelled"),"",IF(N(E32)=0,1,E32)*IFERROR(INDEX(Products!$E$6:$E$105,MATCH(D32,Products!$B$6:$B$105,0)),0)) | P32: =IF(OR(H32="",L32="Cancelled"),"",ROUND(IFERROR(H32*INDEX(Settings!$C$6:$C$15,MATCH(M32,Settings!$B$6:$B$15,0))+INDEX(Settings!$D$6:$D$15,MATCH(M32,Settings!$B$6:$B$15,0)),0),2)) | Q32: =IF(OR(H32="",L32="Cancelled"),"",H32-N(N32)-N(O32)-N(P32)) | R32: =IF(OR(B32="",K32=""),"",IF(OR(L32="Sent",L32="Picked up"),"Done",IF(L32="Cancelled","Cancelled",IF(K32<TODAY(),"Late by "&(TODAY()-K32)&IF((TODAY()-K32)=1," day"," days"),IF(K32=TODAY(),"Due today","Due in "&(K32-TODAY())&IF((K32-TODAY())=1," day"," days")))))) | T32: =IF(AND(B32<>"",K32<>"",L32<>"Sent",L32<>"Picked up",L32<>"Cancelled"),K32+ROW()/10000000,"") | U32: =IF(OR(B32="",C32=""),"",B32+ROW()/10000000) | V32: =IF(U32="","",IF(COUNTIFS(Orders!$C$6:$C$1005,C32,Orders!$U$6:$U$1005,">"&U32)=0,1,0)) | W32: =IF(AND(B32<>"",K32<>"",L32<>"Sent",L32<>"Picked up",L32<>"Cancelled"),IF(N(E32)=0,1,E32),0) | X32: =IF(OR(B32="",D32=""),"",IF(N(E32)=0,1,E32))
B33: 46053 | C33: Ian Price | D33: Soy candle 8 oz | E33: 4 | G33: 6.95 | H33: =IF(OR(B33="",D33=""),"",IF(N(E33)=0,1,E33)*IFERROR(INDEX(Products!$C$6:$C$105,MATCH(D33,Products!$B$6:$B$105,0)),0)+N(F33)+N(G33)) | I33: 94.95 | J33: =IF(OR(H33="",L33="Cancelled"),"",IF(H33-N(I33)>0.005,H33-N(I33),"")) | K33: 46059 | L33: Sent | M33: Own website | N33: =IF(OR(H33="",L33="Cancelled"),"",IF(N(E33)=0,1,E33)*IFERROR(INDEX(Products!$E$6:$E$105,MATCH(D33,Products!$B$6:$B$105,0)),0)) | O33: 7.57 | P33: =IF(OR(H33="",L33="Cancelled"),"",ROUND(IFERROR(H33*INDEX(Settings!$C$6:$C$15,MATCH(M33,Settings!$B$6:$B$15,0))+INDEX(Settings!$D$6:$D$15,MATCH(M33,Settings!$B$6:$B$15,0)),0),2)) | Q33: =IF(OR(H33="",L33="Cancelled"),"",H33-N(N33)-N(O33)-N(P33)) | R33: =IF(OR(B33="",K33=""),"",IF(OR(L33="Sent",L33="Picked up"),"Done",IF(L33="Cancelled","Cancelled",IF(K33<TODAY(),"Late by "&(TODAY()-K33)&IF((TODAY()-K33)=1," day"," days"),IF(K33=TODAY(),"Due today","Due in "&(K33-TODAY())&IF((K33-TODAY())=1," day"," days")))))) | T33: =IF(AND(B33<>"",K33<>"",L33<>"Sent",L33<>"Picked up",L33<>"Cancelled"),K33+ROW()/10000000,"") | U33: =IF(OR(B33="",C33=""),"",B33+ROW()/10000000) | V33: =IF(U33="","",IF(COUNTIFS(Orders!$C$6:$C$1005,C33,Orders!$U$6:$U$1005,">"&U33)=0,1,0)) | W33: =IF(AND(B33<>"",K33<>"",L33<>"Sent",L33<>"Picked up",L33<>"Cancelled"),IF(N(E33)=0,1,E33),0) | X33: =IF(OR(B33="",D33=""),"",IF(N(E33)=0,1,E33))
B34: 46055 | C34: Paula Reed | D34: Soap bar | E34: 2 | G34: 6.95 | H34: =IF(OR(B34="",D34=""),"",IF(N(E34)=0,1,E34)*IFERROR(INDEX(Products!$C$6:$C$105,MATCH(D34,Products!$B$6:$B$105,0)),0)+N(F34)+N(G34)) | I34: 22.95 | J34: =IF(OR(H34="",L34="Cancelled"),"",IF(H34-N(I34)>0.005,H34-N(I34),"")) | K34: 46061 | L34: Sent | M34: Etsy | N34: =IF(OR(H34="",L34="Cancelled"),"",IF(N(E34)=0,1,E34)*IFERROR(INDEX(Products!$E$6:$E$105,MATCH(D34,Products!$B$6:$B$105,0)),0)) | O34: 6.3 | P34: =IF(OR(H34="",L34="Cancelled"),"",ROUND(IFERROR(H34*INDEX(Settings!$C$6:$C$15,MATCH(M34,Settings!$B$6:$B$15,0))+INDEX(Settings!$D$6:$D$15,MATCH(M34,Settings!$B$6:$B$15,0)),0),2)) | Q34: =IF(OR(H34="",L34="Cancelled"),"",H34-N(N34)-N(O34)-N(P34)) | R34: =IF(OR(B34="",K34=""),"",IF(OR(L34="Sent",L34="Picked up"),"Done",IF(L34="Cancelled","Cancelled",IF(K34<TODAY(),"Late by "&(TODAY()-K34)&IF((TODAY()-K34)=1," day"," days"),IF(K34=TODAY(),"Due today","Due in "&(K34-TODAY())&IF((K34-TODAY())=1," day"," days")))))) | T34: =IF(AND(B34<>"",K34<>"",L34<>"Sent",L34<>"Picked up",L34<>"Cancelled"),K34+ROW()/10000000,"") | U34: =IF(OR(B34="",C34=""),"",B34+ROW()/10000000) | V34: =IF(U34="","",IF(COUNTIFS(Orders!$C$6:$C$1005,C34,Orders!$U$6:$U$1005,">"&U34)=0,1,0)) | W34: =IF(AND(B34<>"",K34<>"",L34<>"Sent",L34<>"Picked up",L34<>"Cancelled"),IF(N(E34)=0,1,E34),0) | X34: =IF(OR(B34="",D34=""),"",IF(N(E34)=0,1,E34))
B35: 46056 | C35: Eli Davies | D35: Soap bar | E35: 1 | H35: =IF(OR(B35="",D35=""),"",IF(N(E35)=0,1,E35)*IFERROR(INDEX(Products!$C$6:$C$105,MATCH(D35,Products!$B$6:$B$105,0)),0)+N(F35)+N(G35)) | I35: 8 | J35: =IF(OR(H35="",L35="Cancelled"),"",IF(H35-N(I35)>0.005,H35-N(I35),"")) | K35: 46066 | L35: Picked up | M35: Craft market | N35: =IF(OR(H35="",L35="Cancelled"),"",IF(N(E35)=0,1,E35)*IFERROR(INDEX(Products!$E$6:$E$105,MATCH(D35,Products!$B$6:$B$105,0)),0)) | P35: =IF(OR(H35="",L35="Cancelled"),"",ROUND(IFERROR(H35*INDEX(Settings!$C$6:$C$15,MATCH(M35,Settings!$B$6:$B$15,0))+INDEX(Settings!$D$6:$D$15,MATCH(M35,Settings!$B$6:$B$15,0)),0),2)) | Q35: =IF(OR(H35="",L35="Cancelled"),"",H35-N(N35)-N(O35)-N(P35)) | R35: =IF(OR(B35="",K35=""),"",IF(OR(L35="Sent",L35="Picked up"),"Done",IF(L35="Cancelled","Cancelled",IF(K35<TODAY(),"Late by "&(TODAY()-K35)&IF((TODAY()-K35)=1," day"," days"),IF(K35=TODAY(),"Due today","Due in "&(K35-TODAY())&IF((K35-TODAY())=1," day"," days")))))) | T35: =IF(AND(B35<>"",K35<>"",L35<>"Sent",L35<>"Picked up",L35<>"Cancelled"),K35+ROW()/10000000,"") | U35: =IF(OR(B35="",C35=""),"",B35+ROW()/10000000) | V35: =IF(U35="","",IF(COUNTIFS(Orders!$C$6:$C$1005,C35,Orders!$U$6:$U$1005,">"&U35)=0,1,0)) | W35: =IF(AND(B35<>"",K35<>"",L35<>"Sent",L35<>"Picked up",L35<>"Cancelled"),IF(N(E35)=0,1,E35),0) | X35: =IF(OR(B35="",D35=""),"",IF(N(E35)=0,1,E35))
B36: 46056 | C36: Sara King | D36: Soy candle 16 oz | E36: 1 | G36: 6.95 | H36: =IF(OR(B36="",D36=""),"",IF(N(E36)=0,1,E36)*IFERROR(INDEX(Products!$C$6:$C$105,MATCH(D36,Products!$B$6:$B$105,0)),0)+N(F36)+N(G36)) | I36: 40.95 | J36: =IF(OR(H36="",L36="Cancelled"),"",IF(H36-N(I36)>0.005,H36-N(I36),"")) | K36: 46065 | L36: Sent | M36: Etsy | N36: =IF(OR(H36="",L36="Cancelled"),"",IF(N(E36)=0,1,E36)*IFERROR(INDEX(Products!$E$6:$E$105,MATCH(D36,Products!$B$6:$B$105,0)),0)) | O36: 7.29 | P36: =IF(OR(H36="",L36="Cancelled"),"",ROUND(IFERROR(H36*INDEX(Settings!$C$6:$C$15,MATCH(M36,Settings!$B$6:$B$15,0))+INDEX(Settings!$D$6:$D$15,MATCH(M36,Settings!$B$6:$B$15,0)),0),2)) | Q36: =IF(OR(H36="",L36="Cancelled"),"",H36-N(N36)-N(O36)-N(P36)) | R36: =IF(OR(B36="",K36=""),"",IF(OR(L36="Sent",L36="Picked up"),"Done",IF(L36="Cancelled","Cancelled",IF(K36<TODAY(),"Late by "&(TODAY()-K36)&IF((TODAY()-K36)=1," day"," days"),IF(K36=TODAY(),"Due today","Due in "&(K36-TODAY())&IF((K36-TODAY())=1," day"," days")))))) | T36: =IF(AND(B36<>"",K36<>"",L36<>"Sent",L36<>"Picked up",L36<>"Cancelled"),K36+ROW()/10000000,"") | U36: =IF(OR(B36="",C36=""),"",B36+ROW()/10000000) | V36: =IF(U36="","",IF(COUNTIFS(Orders!$C$6:$C$1005,C36,Orders!$U$6:$U$1005,">"&U36)=0,1,0)) | W36: =IF(AND(B36<>"",K36<>"",L36<>"Sent",L36<>"Picked up",L36<>"Cancelled"),IF(N(E36)=0,1,E36),0) | X36: =IF(OR(B36="",D36=""),"",IF(N(E36)=0,1,E36))
B37: 46057 | C37: Chris Owens | D37: Soap bar | E37: 1 | H37: =IF(OR(B37="",D37=""),"",IF(N(E37)=0,1,E37)*IFERROR(INDEX(Products!$C$6:$C$105,MATCH(D37,Products!$B$6:$B$105,0)),0)+N(F37)+N(G37)) | I37: 8 | J37: =IF(OR(H37="",L37="Cancelled"),"",IF(H37-N(I37)>0.005,H37-N(I37),"")) | K37: 46065 | L37: Picked up | M37: Friends and family | N37: =IF(OR(H37="",L37="Cancelled"),"",IF(N(E37)=0,1,E37)*IFERROR(INDEX(Products!$E$6:$E$105,MATCH(D37,Products!$B$6:$B$105,0)),0)) | P37: =IF(OR(H37="",L37="Cancelled"),"",ROUND(IFERROR(H37*INDEX(Settings!$C$6:$C$15,MATCH(M37,Settings!$B$6:$B$15,0))+INDEX(Settings!$D$6:$D$15,MATCH(M37,Settings!$B$6:$B$15,0)),0),2)) | Q37: =IF(OR(H37="",L37="Cancelled"),"",H37-N(N37)-N(O37)-N(P37)) | R37: =IF(OR(B37="",K37=""),"",IF(OR(L37="Sent",L37="Picked up"),"Done",IF(L37="Cancelled","Cancelled",IF(K37<TODAY(),"Late by "&(TODAY()-K37)&IF((TODAY()-K37)=1," day"," days"),IF(K37=TODAY(),"Due today","Due in "&(K37-TODAY())&IF((K37-TODAY())=1," day"," days")))))) | T37: =IF(AND(B37<>"",K37<>"",L37<>"Sent",L37<>"Picked up",L37<>"Cancelled"),K37+ROW()/10000000,"") | U37: =IF(OR(B37="",C37=""),"",B37+ROW()/10000000) | V37: =IF(U37="","",IF(COUNTIFS(Orders!$C$6:$C$1005,C37,Orders!$U$6:$U$1005,">"&U37)=0,1,0)) | W37: =IF(AND(B37<>"",K37<>"",L37<>"Sent",L37<>"Picked up",L37<>"Cancelled"),IF(N(E37)=0,1,E37),0) | X37: =IF(OR(B37="",D37=""),"",IF(N(E37)=0,1,E37))
B38: 46058 | C38: Adam Fox | D38: Soy candle 8 oz | E38: 3 | F38: 15 | G38: 6.95 | H38: =IF(OR(B38="",D38=""),"",IF(N(E38)=0,1,E38)*IFERROR(INDEX(Products!$C$6:$C$105,MATCH(D38,Products!$B$6:$B$105,0)),0)+N(F38)+N(G38)) | I38: 87.95 | J38: =IF(OR(H38="",L38="Cancelled"),"",IF(H38-N(I38)>0.005,H38-N(I38),"")) | K38: 46067 | L38: Sent | M38: Etsy | N38: =IF(OR(H38="",L38="Cancelled"),"",IF(N(E38)=0,1,E38)*IFERROR(INDEX(Products!$E$6:$E$105,MATCH(D38,Products!$B$6:$B$105,0)),0)) | O38: 5.54 | P38: =IF(OR(H38="",L38="Cancelled"),"",ROUND(IFERROR(H38*INDEX(Settings!$C$6:$C$15,MATCH(M38,Settings!$B$6:$B$15,0))+INDEX(Settings!$D$6:$D$15,MATCH(M38,Settings!$B$6:$B$15,0)),0),2)) | Q38: =IF(OR(H38="",L38="Cancelled"),"",H38-N(N38)-N(O38)-N(P38)) | R38: =IF(OR(B38="",K38=""),"",IF(OR(L38="Sent",L38="Picked up"),"Done",IF(L38="Cancelled","Cancelled",IF(K38<TODAY(),"Late by "&(TODAY()-K38)&IF((TODAY()-K38)=1," day"," days"),IF(K38=TODAY(),"Due today","Due in "&(K38-TODAY())&IF((K38-TODAY())=1," day"," days")))))) | S38: Custom label | T38: =IF(AND(B38<>"",K38<>"",L38<>"Sent",L38<>"Picked up",L38<>"Cancelled"),K38+ROW()/10000000,"") | U38: =IF(OR(B38="",C38=""),"",B38+ROW()/10000000) | V38: =IF(U38="","",IF(COUNTIFS(Orders!$C$6:$C$1005,C38,Orders!$U$6:$U$1005,">"&U38)=0,1,0)) | W38: =IF(AND(B38<>"",K38<>"",L38<>"Sent",L38<>"Picked up",L38<>"Cancelled"),IF(N(E38)=0,1,E38),0) | X38: =IF(OR(B38="",D38=""),"",IF(N(E38)=0,1,E38))
B39: 46058 | C39: Mia Cox | D39: Soy candle 8 oz | E39: 2 | G39: 6.95 | H39: =IF(OR(B39="",D39=""),"",IF(N(E39)=0,1,E39)*IFERROR(INDEX(Products!$C$6:$C$105,MATCH(D39,Products!$B$6:$B$105,0)),0)+N(F39)+N(G39)) | I39: 50.95 | J39: =IF(OR(H39="",L39="Cancelled"),"",IF(H39-N(I39)>0.005,H39-N(I39),"")) | K39: 46063 | L39: Sent | M39: Etsy | N39: =IF(OR(H39="",L39="Cancelled"),"",IF(N(E39)=0,1,E39)*IFERROR(INDEX(Products!$E$6:$E$105,MATCH(D39,Products!$B$6:$B$105,0)),0)) | O39: 7.15 | P39: =IF(OR(H39="",L39="Cancelled"),"",ROUND(IFERROR(H39*INDEX(Settings!$C$6:$C$15,MATCH(M39,Settings!$B$6:$B$15,0))+INDEX(Settings!$D$6:$D$15,MATCH(M39,Settings!$B$6:$B$15,0)),0),2)) | Q39: =IF(OR(H39="",L39="Cancelled"),"",H39-N(N39)-N(O39)-N(P39)) | R39: =IF(OR(B39="",K39=""),"",IF(OR(L39="Sent",L39="Picked up"),"Done",IF(L39="Cancelled","Cancelled",IF(K39<TODAY(),"Late by "&(TODAY()-K39)&IF((TODAY()-K39)=1," day"," days"),IF(K39=TODAY(),"Due today","Due in "&(K39-TODAY())&IF((K39-TODAY())=1," day"," days")))))) | T39: =IF(AND(B39<>"",K39<>"",L39<>"Sent",L39<>"Picked up",L39<>"Cancelled"),K39+ROW()/10000000,"") | U39: =IF(OR(B39="",C39=""),"",B39+ROW()/10000000) | V39: =IF(U39="","",IF(COUNTIFS(Orders!$C$6:$C$1005,C39,Orders!$U$6:$U$1005,">"&U39)=0,1,0)) | W39: =IF(AND(B39<>"",K39<>"",L39<>"Sent",L39<>"Picked up",L39<>"Cancelled"),IF(N(E39)=0,1,E39),0) | X39: =IF(OR(B39="",D39=""),"",IF(N(E39)=0,1,E39))
B40: 46059 | C40: Adam King | D40: Wax melts, 6 pack | E40: 1 | H40: =IF(OR(B40="",D40=""),"",IF(N(E40)=0,1,E40)*IFERROR(INDEX(Products!$C$6:$C$105,MATCH(D40,Products!$B$6:$B$105,0)),0)+N(F40)+N(G40)) | I40: 9 | J40: =IF(OR(H40="",L40="Cancelled"),"",IF(H40-N(I40)>0.005,H40-N(I40),"")) | K40: 46068 | L40: Picked up | M40: Instagram | N40: =IF(OR(H40="",L40="Cancelled"),"",IF(N(E40)=0,1,E40)*IFERROR(INDEX(Products!$E$6:$E$105,MATCH(D40,Products!$B$6:$B$105,0)),0)) | P40: =IF(OR(H40="",L40="Cancelled"),"",ROUND(IFERROR(H40*INDEX(Settings!$C$6:$C$15,MATCH(M40,Settings!$B$6:$B$15,0))+INDEX(Settings!$D$6:$D$15,MATCH(M40,Settings!$B$6:$B$15,0)),0),2)) | Q40: =IF(OR(H40="",L40="Cancelled"),"",H40-N(N40)-N(O40)-N(P40)) | R40: =IF(OR(B40="",K40=""),"",IF(OR(L40="Sent",L40="Picked up"),"Done",IF(L40="Cancelled","Cancelled",IF(K40<TODAY(),"Late by "&(TODAY()-K40)&IF((TODAY()-K40)=1," day"," days"),IF(K40=TODAY(),"Due today","Due in "&(K40-TODAY())&IF((K40-TODAY())=1," day"," days")))))) | T40: =IF(AND(B40<>"",K40<>"",L40<>"Sent",L40<>"Picked up",L40<>"Cancelled"),K40+ROW()/10000000,"") | U40: =IF(OR(B40="",C40=""),"",B40+ROW()/10000000) | V40: =IF(U40="","",IF(COUNTIFS(Orders!$C$6:$C$1005,C40,Orders!$U$6:$U$1005,">"&U40)=0,1,0)) | W40: =IF(AND(B40<>"",K40<>"",L40<>"Sent",L40<>"Picked up",L40<>"Cancelled"),IF(N(E40)=0,1,E40),0) | X40: =IF(OR(B40="",D40=""),"",IF(N(E40)=0,1,E40))
B41: 46061 | C41: Jon Gray | D41: Soy candle 8 oz | E41: 1 | G41: 6.95 | H41: =IF(OR(B41="",D41=""),"",IF(N(E41)=0,1,E41)*IFERROR(INDEX(Products!$C$6:$C$105,MATCH(D41,Products!$B$6:$B$105,0)),0)+N(F41)+N(G41)) | I41: 28.95 | J41: =IF(OR(H41="",L41="Cancelled"),"",IF(H41-N(I41)>0.005,H41-N(I41),"")) | K41: 46069 | L41: Sent | M41: Etsy | N41: =IF(OR(H41="",L41="Cancelled"),"",IF(N(E41)=0,1,E41)*IFERROR(INDEX(Products!$E$6:$E$105,MATCH(D41,Products!$B$6:$B$105,0)),0)) | O41: 6.54 | P41: =IF(OR(H41="",L41="Cancelled"),"",ROUND(IFERROR(H41*INDEX(Settings!$C$6:$C$15,MATCH(M41,Settings!$B$6:$B$15,0))+INDEX(Settings!$D$6:$D$15,MATCH(M41,Settings!$B$6:$B$15,0)),0),2)) | Q41: =IF(OR(H41="",L41="Cancelled"),"",H41-N(N41)-N(O41)-N(P41)) | R41: =IF(OR(B41="",K41=""),"",IF(OR(L41="Sent",L41="Picked up"),"Done",IF(L41="Cancelled","Cancelled",IF(K41<TODAY(),"Late by "&(TODAY()-K41)&IF((TODAY()-K41)=1," day"," days"),IF(K41=TODAY(),"Due today","Due in "&(K41-TODAY())&IF((K41-TODAY())=1," day"," days")))))) | T41: =IF(AND(B41<>"",K41<>"",L41<>"Sent",L41<>"Picked up",L41<>"Cancelled"),K41+ROW()/10000000,"") | U41: =IF(OR(B41="",C41=""),"",B41+ROW()/10000000) | V41: =IF(U41="","",IF(COUNTIFS(Orders!$C$6:$C$1005,C41,Orders!$U$6:$U$1005,">"&U41)=0,1,0)) | W41: =IF(AND(B41<>"",K41<>"",L41<>"Sent",L41<>"Picked up",L41<>"Cancelled"),IF(N(E41)=0,1,E41),0) | X41: =IF(OR(B41="",D41=""),"",IF(N(E41)=0,1,E41))
B42: 46062 | C42: Ian Price | D42: Soy candle 16 oz | E42: 1 | H42: =IF(OR(B42="",D42=""),"",IF(N(E42)=0,1,E42)*IFERROR(INDEX(Products!$C$6:$C$105,MATCH(D42,Products!$B$6:$B$105,0)),0)+N(F42)+N(G42)) | I42: 34 | J42: =IF(OR(H42="",L42="Cancelled"),"",IF(H42-N(I42)>0.005,H42-N(I42),"")) | K42: 46074 | L42: Picked up | M42: Instagram | N42: =IF(OR(H42="",L42="Cancelled"),"",IF(N(E42)=0,1,E42)*IFERROR(INDEX(Products!$E$6:$E$105,MATCH(D42,Products!$B$6:$B$105,0)),0)) | P42: =IF(OR(H42="",L42="Cancelled"),"",ROUND(IFERROR(H42*INDEX(Settings!$C$6:$C$15,MATCH(M42,Settings!$B$6:$B$15,0))+INDEX(Settings!$D$6:$D$15,MATCH(M42,Settings!$B$6:$B$15,0)),0),2)) | Q42: =IF(OR(H42="",L42="Cancelled"),"",H42-N(N42)-N(O42)-N(P42)) | R42: =IF(OR(B42="",K42=""),"",IF(OR(L42="Sent",L42="Picked up"),"Done",IF(L42="Cancelled","Cancelled",IF(K42<TODAY(),"Late by "&(TODAY()-K42)&IF((TODAY()-K42)=1," day"," days"),IF(K42=TODAY(),"Due today","Due in "&(K42-TODAY())&IF((K42-TODAY())=1," day"," days")))))) | T42: =IF(AND(B42<>"",K42<>"",L42<>"Sent",L42<>"Picked up",L42<>"Cancelled"),K42+ROW()/10000000,"") | U42: =IF(OR(B42="",C42=""),"",B42+ROW()/10000000) | V42: =IF(U42="","",IF(COUNTIFS(Orders!$C$6:$C$1005,C42,Orders!$U$6:$U$1005,">"&U42)=0,1,0)) | W42: =IF(AND(B42<>"",K42<>"",L42<>"Sent",L42<>"Picked up",L42<>"Cancelled"),IF(N(E42)=0,1,E42),0) | X42: =IF(OR(B42="",D42=""),"",IF(N(E42)=0,1,E42))
B43: 46063 | C43: Kara Adams | D43: Soap bar | E43: 1 | G43: 6.95 | H43: =IF(OR(B43="",D43=""),"",IF(N(E43)=0,1,E43)*IFERROR(INDEX(Products!$C$6:$C$105,MATCH(D43,Products!$B$6:$B$105,0)),0)+N(F43)+N(G43)) | I43: 14.95 | J43: =IF(OR(H43="",L43="Cancelled"),"",IF(H43-N(I43)>0.005,H43-N(I43),"")) | K43: 46075 | L43: Sent | M43: Etsy | N43: =IF(OR(H43="",L43="Cancelled"),"",IF(N(E43)=0,1,E43)*IFERROR(INDEX(Products!$E$6:$E$105,MATCH(D43,Products!$B$6:$B$105,0)),0)) | O43: 7.08 | P43: =IF(OR(H43="",L43="Cancelled"),"",ROUND(IFERROR(H43*INDEX(Settings!$C$6:$C$15,MATCH(M43,Settings!$B$6:$B$15,0))+INDEX(Settings!$D$6:$D$15,MATCH(M43,Settings!$B$6:$B$15,0)),0),2)) | Q43: =IF(OR(H43="",L43="Cancelled"),"",H43-N(N43)-N(O43)-N(P43)) | R43: =IF(OR(B43="",K43=""),"",IF(OR(L43="Sent",L43="Picked up"),"Done",IF(L43="Cancelled","Cancelled",IF(K43<TODAY(),"Late by "&(TODAY()-K43)&IF((TODAY()-K43)=1," day"," days"),IF(K43=TODAY(),"Due today","Due in "&(K43-TODAY())&IF((K43-TODAY())=1," day"," days")))))) | T43: =IF(AND(B43<>"",K43<>"",L43<>"Sent",L43<>"Picked up",L43<>"Cancelled"),K43+ROW()/10000000,"") | U43: =IF(OR(B43="",C43=""),"",B43+ROW()/10000000) | V43: =IF(U43="","",IF(COUNTIFS(Orders!$C$6:$C$1005,C43,Orders!$U$6:$U$1005,">"&U43)=0,1,0)) | W43: =IF(AND(B43<>"",K43<>"",L43<>"Sent",L43<>"Picked up",L43<>"Cancelled"),IF(N(E43)=0,1,E43),0) | X43: =IF(OR(B43="",D43=""),"",IF(N(E43)=0,1,E43))
B44: 46064 | C44: Dina Cole | D44: Soy candle 16 oz | E44: 3 | F44: 15 | G44: 6.95 | H44: =IF(OR(B44="",D44=""),"",IF(N(E44)=0,1,E44)*IFERROR(INDEX(Products!$C$6:$C$105,MATCH(D44,Products!$B$6:$B$105,0)),0)+N(F44)+N(G44)) | I44: 123.95 | J44: =IF(OR(H44="",L44="Cancelled"),"",IF(H44-N(I44)>0.005,H44-N(I44),"")) | K44: 46073 | L44: Sent | M44: Own website | N44: =IF(OR(H44="",L44="Cancelled"),"",IF(N(E44)=0,1,E44)*IFERROR(INDEX(Products!$E$6:$E$105,MATCH(D44,Products!$B$6:$B$105,0)),0)) | O44: 6.24 | P44: =IF(OR(H44="",L44="Cancelled"),"",ROUND(IFERROR(H44*INDEX(Settings!$C$6:$C$15,MATCH(M44,Settings!$B$6:$B$15,0))+INDEX(Settings!$D$6:$D$15,MATCH(M44,Settings!$B$6:$B$15,0)),0),2)) | Q44: =IF(OR(H44="",L44="Cancelled"),"",H44-N(N44)-N(O44)-N(P44)) | R44: =IF(OR(B44="",K44=""),"",IF(OR(L44="Sent",L44="Picked up"),"Done",IF(L44="Cancelled","Cancelled",IF(K44<TODAY(),"Late by "&(TODAY()-K44)&IF((TODAY()-K44)=1," day"," days"),IF(K44=TODAY(),"Due today","Due in "&(K44-TODAY())&IF((K44-TODAY())=1," day"," days")))))) | S44: Custom label | T44: =IF(AND(B44<>"",K44<>"",L44<>"Sent",L44<>"Picked up",L44<>"Cancelled"),K44+ROW()/10000000,"") | U44: =IF(OR(B44="",C44=""),"",B44+ROW()/10000000) | V44: =IF(U44="","",IF(COUNTIFS(Orders!$C$6:$C$1005,C44,Orders!$U$6:$U$1005,">"&U44)=0,1,0)) | W44: =IF(AND(B44<>"",K44<>"",L44<>"Sent",L44<>"Picked up",L44<>"Cancelled"),IF(N(E44)=0,1,E44),0) | X44: =IF(OR(B44="",D44=""),"",IF(N(E44)=0,1,E44))
B45: 46064 | C45: Eva Adams | D45: Soy candle 16 oz | E45: 2 | H45: =IF(OR(B45="",D45=""),"",IF(N(E45)=0,1,E45)*IFERROR(INDEX(Products!$C$6:$C$105,MATCH(D45,Products!$B$6:$B$105,0)),0)+N(F45)+N(G45)) | I45: 68 | J45: =IF(OR(H45="",L45="Cancelled"),"",IF(H45-N(I45)>0.005,H45-N(I45),"")) | K45: 46068 | L45: Picked up | M45: Instagram | N45: =IF(OR(H45="",L45="Cancelled"),"",IF(N(E45)=0,1,E45)*IFERROR(INDEX(Products!$E$6:$E$105,MATCH(D45,Products!$B$6:$B$105,0)),0)) | P45: =IF(OR(H45="",L45="Cancelled"),"",ROUND(IFERROR(H45*INDEX(Settings!$C$6:$C$15,MATCH(M45,Settings!$B$6:$B$15,0))+INDEX(Settings!$D$6:$D$15,MATCH(M45,Settings!$B$6:$B$15,0)),0),2)) | Q45: =IF(OR(H45="",L45="Cancelled"),"",H45-N(N45)-N(O45)-N(P45)) | R45: =IF(OR(B45="",K45=""),"",IF(OR(L45="Sent",L45="Picked up"),"Done",IF(L45="Cancelled","Cancelled",IF(K45<TODAY(),"Late by "&(TODAY()-K45)&IF((TODAY()-K45)=1," day"," days"),IF(K45=TODAY(),"Due today","Due in "&(K45-TODAY())&IF((K45-TODAY())=1," day"," days")))))) | T45: =IF(AND(B45<>"",K45<>"",L45<>"Sent",L45<>"Picked up",L45<>"Cancelled"),K45+ROW()/10000000,"") | U45: =IF(OR(B45="",C45=""),"",B45+ROW()/10000000) | V45: =IF(U45="","",IF(COUNTIFS(Orders!$C$6:$C$1005,C45,Orders!$U$6:$U$1005,">"&U45)=0,1,0)) | W45: =IF(AND(B45<>"",K45<>"",L45<>"Sent",L45<>"Picked up",L45<>"Cancelled"),IF(N(E45)=0,1,E45),0) | X45: =IF(OR(B45="",D45=""),"",IF(N(E45)=0,1,E45))
B46: 46065 | C46: Lily Gray | D46: Soap bar | E46: 1 | H46: =IF(OR(B46="",D46=""),"",IF(N(E46)=0,1,E46)*IFERROR(INDEX(Products!$C$6:$C$105,MATCH(D46,Products!$B$6:$B$105,0)),0)+N(F46)+N(G46)) | I46: 8 | J46: =IF(OR(H46="",L46="Cancelled"),"",IF(H46-N(I46)>0.005,H46-N(I46),"")) | K46: 46071 | L46: Cancelled | M46: Craft market | N46: =IF(OR(H46="",L46="Cancelled"),"",IF(N(E46)=0,1,E46)*IFERROR(INDEX(Products!$E$6:$E$105,MATCH(D46,Products!$B$6:$B$105,0)),0)) | P46: =IF(OR(H46="",L46="Cancelled"),"",ROUND(IFERROR(H46*INDEX(Settings!$C$6:$C$15,MATCH(M46,Settings!$B$6:$B$15,0))+INDEX(Settings!$D$6:$D$15,MATCH(M46,Settings!$B$6:$B$15,0)),0),2)) | Q46: =IF(OR(H46="",L46="Cancelled"),"",H46-N(N46)-N(O46)-N(P46)) | R46: =IF(OR(B46="",K46=""),"",IF(OR(L46="Sent",L46="Picked up"),"Done",IF(L46="Cancelled","Cancelled",IF(K46<TODAY(),"Late by "&(TODAY()-K46)&IF((TODAY()-K46)=1," day"," days"),IF(K46=TODAY(),"Due today","Due in "&(K46-TODAY())&IF((K46-TODAY())=1," day"," days")))))) | T46: =IF(AND(B46<>"",K46<>"",L46<>"Sent",L46<>"Picked up",L46<>"Cancelled"),K46+ROW()/10000000,"") | U46: =IF(OR(B46="",C46=""),"",B46+ROW()/10000000) | V46: =IF(U46="","",IF(COUNTIFS(Orders!$C$6:$C$1005,C46,Orders!$U$6:$U$1005,">"&U46)=0,1,0)) | W46: =IF(AND(B46<>"",K46<>"",L46<>"Sent",L46<>"Picked up",L46<>"Cancelled"),IF(N(E46)=0,1,E46),0) | X46: =IF(OR(B46="",D46=""),"",IF(N(E46)=0,1,E46))
B47: 46065 | C47: Paula Morgan | D47: Soy candle 8 oz | E47: 2 | H47: =IF(OR(B47="",D47=""),"",IF(N(E47)=0,1,E47)*IFERROR(INDEX(Products!$C$6:$C$105,MATCH(D47,Products!$B$6:$B$105,0)),0)+N(F47)+N(G47)) | I47: 44 | J47: =IF(OR(H47="",L47="Cancelled"),"",IF(H47-N(I47)>0.005,H47-N(I47),"")) | K47: 46071 | L47: Cancelled | M47: Instagram | N47: =IF(OR(H47="",L47="Cancelled"),"",IF(N(E47)=0,1,E47)*IFERROR(INDEX(Products!$E$6:$E$105,MATCH(D47,Products!$B$6:$B$105,0)),0)) | P47: =IF(OR(H47="",L47="Cancelled"),"",ROUND(IFERROR(H47*INDEX(Settings!$C$6:$C$15,MATCH(M47,Settings!$B$6:$B$15,0))+INDEX(Settings!$D$6:$D$15,MATCH(M47,Settings!$B$6:$B$15,0)),0),2)) | Q47: =IF(OR(H47="",L47="Cancelled"),"",H47-N(N47)-N(O47)-N(P47)) | R47: =IF(OR(B47="",K47=""),"",IF(OR(L47="Sent",L47="Picked up"),"Done",IF(L47="Cancelled","Cancelled",IF(K47<TODAY(),"Late by "&(TODAY()-K47)&IF((TODAY()-K47)=1," day"," days"),IF(K47=TODAY(),"Due today","Due in "&(K47-TODAY())&IF((K47-TODAY())=1," day"," days")))))) | T47: =IF(AND(B47<>"",K47<>"",L47<>"Sent",L47<>"Picked up",L47<>"Cancelled"),K47+ROW()/10000000,"") | U47: =IF(OR(B47="",C47=""),"",B47+ROW()/10000000) | V47: =IF(U47="","",IF(COUNTIFS(Orders!$C$6:$C$1005,C47,Orders!$U$6:$U$1005,">"&U47)=0,1,0)) | W47: =IF(AND(B47<>"",K47<>"",L47<>"Sent",L47<>"Picked up",L47<>"Cancelled"),IF(N(E47)=0,1,E47),0) | X47: =IF(OR(B47="",D47=""),"",IF(N(E47)=0,1,E47))
B48: 46066 | C48: Nina Kelly | D48: Soap bar | E48: 3 | G48: 6.95 | H48: =IF(OR(B48="",D48=""),"",IF(N(E48)=0,1,E48)*IFERROR(INDEX(Products!$C$6:$C$105,MATCH(D48,Products!$B$6:$B$105,0)),0)+N(F48)+N(G48)) | I48: 30.95 | J48: =IF(OR(H48="",L48="Cancelled"),"",IF(H48-N(I48)>0.005,H48-N(I48),"")) | K48: 46076 | L48: Sent | M48: Etsy | N48: =IF(OR(H48="",L48="Cancelled"),"",IF(N(E48)=0,1,E48)*IFERROR(INDEX(Products!$E$6:$E$105,MATCH(D48,Products!$B$6:$B$105,0)),0)) | O48: 5.52 | P48: =IF(OR(H48="",L48="Cancelled"),"",ROUND(IFERROR(H48*INDEX(Settings!$C$6:$C$15,MATCH(M48,Settings!$B$6:$B$15,0))+INDEX(Settings!$D$6:$D$15,MATCH(M48,Settings!$B$6:$B$15,0)),0),2)) | Q48: =IF(OR(H48="",L48="Cancelled"),"",H48-N(N48)-N(O48)-N(P48)) | R48: =IF(OR(B48="",K48=""),"",IF(OR(L48="Sent",L48="Picked up"),"Done",IF(L48="Cancelled","Cancelled",IF(K48<TODAY(),"Late by "&(TODAY()-K48)&IF((TODAY()-K48)=1," day"," days"),IF(K48=TODAY(),"Due today","Due in "&(K48-TODAY())&IF((K48-TODAY())=1," day"," days")))))) | T48: =IF(AND(B48<>"",K48<>"",L48<>"Sent",L48<>"Picked up",L48<>"Cancelled"),K48+ROW()/10000000,"") | U48: =IF(OR(B48="",C48=""),"",B48+ROW()/10000000) | V48: =IF(U48="","",IF(COUNTIFS(Orders!$C$6:$C$1005,C48,Orders!$U$6:$U$1005,">"&U48)=0,1,0)) | W48: =IF(AND(B48<>"",K48<>"",L48<>"Sent",L48<>"Picked up",L48<>"Cancelled"),IF(N(E48)=0,1,E48),0) | X48: =IF(OR(B48="",D48=""),"",IF(N(E48)=0,1,E48))
B49: 46067 | C49: Adam Davies | D49: Soy candle 16 oz | E49: 2 | F49: 10 | G49: 6.95 | H49: =IF(OR(B49="",D49=""),"",IF(N(E49)=0,1,E49)*IFERROR(INDEX(Products!$C$6:$C$105,MATCH(D49,Products!$B$6:$B$105,0)),0)+N(F49)+N(G49)) | I49: 84.95 | J49: =IF(OR(H49="",L49="Cancelled"),"",IF(H49-N(I49)>0.005,H49-N(I49),"")) | K49: 46074 | L49: Sent | M49: Etsy | N49: =IF(OR(H49="",L49="Cancelled"),"",IF(N(E49)=0,1,E49)*IFERROR(INDEX(Products!$E$6:$E$105,MATCH(D49,Products!$B$6:$B$105,0)),0)) | O49: 7.25 | P49: =IF(OR(H49="",L49="Cancelled"),"",ROUND(IFERROR(H49*INDEX(Settings!$C$6:$C$15,MATCH(M49,Settings!$B$6:$B$15,0))+INDEX(Settings!$D$6:$D$15,MATCH(M49,Settings!$B$6:$B$15,0)),0),2)) | Q49: =IF(OR(H49="",L49="Cancelled"),"",H49-N(N49)-N(O49)-N(P49)) | R49: =IF(OR(B49="",K49=""),"",IF(OR(L49="Sent",L49="Picked up"),"Done",IF(L49="Cancelled","Cancelled",IF(K49<TODAY(),"Late by "&(TODAY()-K49)&IF((TODAY()-K49)=1," day"," days"),IF(K49=TODAY(),"Due today","Due in "&(K49-TODAY())&IF((K49-TODAY())=1," day"," days")))))) | S49: Custom label | T49: =IF(AND(B49<>"",K49<>"",L49<>"Sent",L49<>"Picked up",L49<>"Cancelled"),K49+ROW()/10000000,"") | U49: =IF(OR(B49="",C49=""),"",B49+ROW()/10000000) | V49: =IF(U49="","",IF(COUNTIFS(Orders!$C$6:$C$1005,C49,Orders!$U$6:$U$1005,">"&U49)=0,1,0)) | W49: =IF(AND(B49<>"",K49<>"",L49<>"Sent",L49<>"Picked up",L49<>"Cancelled"),IF(N(E49)=0,1,E49),0) | X49: =IF(OR(B49="",D49=""),"",IF(N(E49)=0,1,E49))
B50: 46069 | C50: Clara Davies | D50: Soy candle 8 oz | E50: 4 | G50: 6.95 | H50: =IF(OR(B50="",D50=""),"",IF(N(E50)=0,1,E50)*IFERROR(INDEX(Products!$C$6:$C$105,MATCH(D50,Products!$B$6:$B$105,0)),0)+N(F50)+N(G50)) | I50: 94.95 | J50: =IF(OR(H50="",L50="Cancelled"),"",IF(H50-N(I50)>0.005,H50-N(I50),"")) | K50: 46080 | L50: Sent | M50: Etsy | N50: =IF(OR(H50="",L50="Cancelled"),"",IF(N(E50)=0,1,E50)*IFERROR(INDEX(Products!$E$6:$E$105,MATCH(D50,Products!$B$6:$B$105,0)),0)) | O50: 6.25 | P50: =IF(OR(H50="",L50="Cancelled"),"",ROUND(IFERROR(H50*INDEX(Settings!$C$6:$C$15,MATCH(M50,Settings!$B$6:$B$15,0))+INDEX(Settings!$D$6:$D$15,MATCH(M50,Settings!$B$6:$B$15,0)),0),2)) | Q50: =IF(OR(H50="",L50="Cancelled"),"",H50-N(N50)-N(O50)-N(P50)) | R50: =IF(OR(B50="",K50=""),"",IF(OR(L50="Sent",L50="Picked up"),"Done",IF(L50="Cancelled","Cancelled",IF(K50<TODAY(),"Late by "&(TODAY()-K50)&IF((TODAY()-K50)=1," day"," days"),IF(K50=TODAY(),"Due today","Due in "&(K50-TODAY())&IF((K50-TODAY())=1," day"," days")))))) | T50: =IF(AND(B50<>"",K50<>"",L50<>"Sent",L50<>"Picked up",L50<>"Cancelled"),K50+ROW()/10000000,"") | U50: =IF(OR(B50="",C50=""),"",B50+ROW()/10000000) | V50: =IF(U50="","",IF(COUNTIFS(Orders!$C$6:$C$1005,C50,Orders!$U$6:$U$1005,">"&U50)=0,1,0)) | W50: =IF(AND(B50<>"",K50<>"",L50<>"Sent",L50<>"Picked up",L50<>"Cancelled"),IF(N(E50)=0,1,E50),0) | X50: =IF(OR(B50="",D50=""),"",IF(N(E50)=0,1,E50))
B51: 46069 | C51: Holly Cox | D51: Soap bar | E51: 1 | G51: 6.95 | H51: =IF(OR(B51="",D51=""),"",IF(N(E51)=0,1,E51)*IFERROR(INDEX(Products!$C$6:$C$105,MATCH(D51,Products!$B$6:$B$105,0)),0)+N(F51)+N(G51)) | I51: 14.95 | J51: =IF(OR(H51="",L51="Cancelled"),"",IF(H51-N(I51)>0.005,H51-N(I51),"")) | K51: 46077 | L51: Sent | M51: Own website | N51: =IF(OR(H51="",L51="Cancelled"),"",IF(N(E51)=0,1,E51)*IFERROR(INDEX(Products!$E$6:$E$105,MATCH(D51,Products!$B$6:$B$105,0)),0)) | O51: 7.07 | P51: =IF(OR(H51="",L51="Cancelled"),"",ROUND(IFERROR(H51*INDEX(Settings!$C$6:$C$15,MATCH(M51,Settings!$B$6:$B$15,0))+INDEX(Settings!$D$6:$D$15,MATCH(M51,Settings!$B$6:$B$15,0)),0),2)) | Q51: =IF(OR(H51="",L51="Cancelled"),"",H51-N(N51)-N(O51)-N(P51)) | R51: =IF(OR(B51="",K51=""),"",IF(OR(L51="Sent",L51="Picked up"),"Done",IF(L51="Cancelled","Cancelled",IF(K51<TODAY(),"Late by "&(TODAY()-K51)&IF((TODAY()-K51)=1," day"," days"),IF(K51=TODAY(),"Due today","Due in "&(K51-TODAY())&IF((K51-TODAY())=1," day"," days")))))) | T51: =IF(AND(B51<>"",K51<>"",L51<>"Sent",L51<>"Picked up",L51<>"Cancelled"),K51+ROW()/10000000,"") | U51: =IF(OR(B51="",C51=""),"",B51+ROW()/10000000) | V51: =IF(U51="","",IF(COUNTIFS(Orders!$C$6:$C$1005,C51,Orders!$U$6:$U$1005,">"&U51)=0,1,0)) | W51: =IF(AND(B51<>"",K51<>"",L51<>"Sent",L51<>"Picked up",L51<>"Cancelled"),IF(N(E51)=0,1,E51),0) | X51: =IF(OR(B51="",D51=""),"",IF(N(E51)=0,1,E51))
B52: 46070 | C52: Beth Owens | D52: Soy candle 8 oz | E52: 2 | G52: 6.95 | H52: =IF(OR(B52="",D52=""),"",IF(N(E52)=0,1,E52)*IFERROR(INDEX(Products!$C$6:$C$105,MATCH(D52,Products!$B$6:$B$105,0)),0)+N(F52)+N(G52)) | I52: 50.95 | J52: =IF(OR(H52="",L52="Cancelled"),"",IF(H52-N(I52)>0.005,H52-N(I52),"")) | K52: 46078 | L52: Sent | M52: Etsy | N52: =IF(OR(H52="",L52="Cancelled"),"",IF(N(E52)=0,1,E52)*IFERROR(INDEX(Products!$E$6:$E$105,MATCH(D52,Products!$B$6:$B$105,0)),0)) | O52: 5.95 | P52: =IF(OR(H52="",L52="Cancelled"),"",ROUND(IFERROR(H52*INDEX(Settings!$C$6:$C$15,MATCH(M52,Settings!$B$6:$B$15,0))+INDEX(Settings!$D$6:$D$15,MATCH(M52,Settings!$B$6:$B$15,0)),0),2)) | Q52: =IF(OR(H52="",L52="Cancelled"),"",H52-N(N52)-N(O52)-N(P52)) | R52: =IF(OR(B52="",K52=""),"",IF(OR(L52="Sent",L52="Picked up"),"Done",IF(L52="Cancelled","Cancelled",IF(K52<TODAY(),"Late by "&(TODAY()-K52)&IF((TODAY()-K52)=1," day"," days"),IF(K52=TODAY(),"Due today","Due in "&(K52-TODAY())&IF((K52-TODAY())=1," day"," days")))))) | T52: =IF(AND(B52<>"",K52<>"",L52<>"Sent",L52<>"Picked up",L52<>"Cancelled"),K52+ROW()/10000000,"") | U52: =IF(OR(B52="",C52=""),"",B52+ROW()/10000000) | V52: =IF(U52="","",IF(COUNTIFS(Orders!$C$6:$C$1005,C52,Orders!$U$6:$U$1005,">"&U52)=0,1,0)) | W52: =IF(AND(B52<>"",K52<>"",L52<>"Sent",L52<>"Picked up",L52<>"Cancelled"),IF(N(E52)=0,1,E52),0) | X52: =IF(OR(B52="",D52=""),"",IF(N(E52)=0,1,E52))
B53: 46072 | C53: Adam Davies | D53: Soy candle 8 oz | E53: 1 | H53: =IF(OR(B53="",D53=""),"",IF(N(E53)=0,1,E53)*IFERROR(INDEX(Products!$C$6:$C$105,MATCH(D53,Products!$B$6:$B$105,0)),0)+N(F53)+N(G53)) | I53: 22 | J53: =IF(OR(H53="",L53="Cancelled"),"",IF(H53-N(I53)>0.005,H53-N(I53),"")) | K53: 46077 | L53: Picked up | M53: Craft market | N53: =IF(OR(H53="",L53="Cancelled"),"",IF(N(E53)=0,1,E53)*IFERROR(INDEX(Products!$E$6:$E$105,MATCH(D53,Products!$B$6:$B$105,0)),0)) | P53: =IF(OR(H53="",L53="Cancelled"),"",ROUND(IFERROR(H53*INDEX(Settings!$C$6:$C$15,MATCH(M53,Settings!$B$6:$B$15,0))+INDEX(Settings!$D$6:$D$15,MATCH(M53,Settings!$B$6:$B$15,0)),0),2)) | Q53: =IF(OR(H53="",L53="Cancelled"),"",H53-N(N53)-N(O53)-N(P53)) | R53: =IF(OR(B53="",K53=""),"",IF(OR(L53="Sent",L53="Picked up"),"Done",IF(L53="Cancelled","Cancelled",IF(K53<TODAY(),"Late by "&(TODAY()-K53)&IF((TODAY()-K53)=1," day"," days"),IF(K53=TODAY(),"Due today","Due in "&(K53-TODAY())&IF((K53-TODAY())=1," day"," days")))))) | T53: =IF(AND(B53<>"",K53<>"",L53<>"Sent",L53<>"Picked up",L53<>"Cancelled"),K53+ROW()/10000000,"") | U53: =IF(OR(B53="",C53=""),"",B53+ROW()/10000000) | V53: =IF(U53="","",IF(COUNTIFS(Orders!$C$6:$C$1005,C53,Orders!$U$6:$U$1005,">"&U53)=0,1,0)) | W53: =IF(AND(B53<>"",K53<>"",L53<>"Sent",L53<>"Picked up",L53<>"Cancelled"),IF(N(E53)=0,1,E53),0) | X53: =IF(OR(B53="",D53=""),"",IF(N(E53)=0,1,E53))
B54: 46072 | C54: George Hill | D54: Wax melts, 6 pack | E54: 4 | H54: =IF(OR(B54="",D54=""),"",IF(N(E54)=0,1,E54)*IFERROR(INDEX(Products!$C$6:$C$105,MATCH(D54,Products!$B$6:$B$105,0)),0)+N(F54)+N(G54)) | I54: 36 | J54: =IF(OR(H54="",L54="Cancelled"),"",IF(H54-N(I54)>0.005,H54-N(I54),"")) | K54: 46084 | L54: Picked up | M54: Friends and family | N54: =IF(OR(H54="",L54="Cancelled"),"",IF(N(E54)=0,1,E54)*IFERROR(INDEX(Products!$E$6:$E$105,MATCH(D54,Products!$B$6:$B$105,0)),0)) | P54: =IF(OR(H54="",L54="Cancelled"),"",ROUND(IFERROR(H54*INDEX(Settings!$C$6:$C$15,MATCH(M54,Settings!$B$6:$B$15,0))+INDEX(Settings!$D$6:$D$15,MATCH(M54,Settings!$B$6:$B$15,0)),0),2)) | Q54: =IF(OR(H54="",L54="Cancelled"),"",H54-N(N54)-N(O54)-N(P54)) | R54: =IF(OR(B54="",K54=""),"",IF(OR(L54="Sent",L54="Picked up"),"Done",IF(L54="Cancelled","Cancelled",IF(K54<TODAY(),"Late by "&(TODAY()-K54)&IF((TODAY()-K54)=1," day"," days"),IF(K54=TODAY(),"Due today","Due in "&(K54-TODAY())&IF((K54-TODAY())=1," day"," days")))))) | T54: =IF(AND(B54<>"",K54<>"",L54<>"Sent",L54<>"Picked up",L54<>"Cancelled"),K54+ROW()/10000000,"") | U54: =IF(OR(B54="",C54=""),"",B54+ROW()/10000000) | V54: =IF(U54="","",IF(COUNTIFS(Orders!$C$6:$C$1005,C54,Orders!$U$6:$U$1005,">"&U54)=0,1,0)) | W54: =IF(AND(B54<>"",K54<>"",L54<>"Sent",L54<>"Picked up",L54<>"Cancelled"),IF(N(E54)=0,1,E54),0) | X54: =IF(OR(B54="",D54=""),"",IF(N(E54)=0,1,E54))
B55: 46073 | C55: Ava Adams | D55: Soy candle 8 oz | E55: 2 | H55: =IF(OR(B55="",D55=""),"",IF(N(E55)=0,1,E55)*IFERROR(INDEX(Products!$C$6:$C$105,MATCH(D55,Products!$B$6:$B$105,0)),0)+N(F55)+N(G55)) | I55: 44 | J55: =IF(OR(H55="",L55="Cancelled"),"",IF(H55-N(I55)>0.005,H55-N(I55),"")) | K55: 46082 | L55: Picked up | M55: Craft market | N55: =IF(OR(H55="",L55="Cancelled"),"",IF(N(E55)=0,1,E55)*IFERROR(INDEX(Products!$E$6:$E$105,MATCH(D55,Products!$B$6:$B$105,0)),0)) | P55: =IF(OR(H55="",L55="Cancelled"),"",ROUND(IFERROR(H55*INDEX(Settings!$C$6:$C$15,MATCH(M55,Settings!$B$6:$B$15,0))+INDEX(Settings!$D$6:$D$15,MATCH(M55,Settings!$B$6:$B$15,0)),0),2)) | Q55: =IF(OR(H55="",L55="Cancelled"),"",H55-N(N55)-N(O55)-N(P55)) | R55: =IF(OR(B55="",K55=""),"",IF(OR(L55="Sent",L55="Picked up"),"Done",IF(L55="Cancelled","Cancelled",IF(K55<TODAY(),"Late by "&(TODAY()-K55)&IF((TODAY()-K55)=1," day"," days"),IF(K55=TODAY(),"Due today","Due in "&(K55-TODAY())&IF((K55-TODAY())=1," day"," days")))))) | T55: =IF(AND(B55<>"",K55<>"",L55<>"Sent",L55<>"Picked up",L55<>"Cancelled"),K55+ROW()/10000000,"") | U55: =IF(OR(B55="",C55=""),"",B55+ROW()/10000000) | V55: =IF(U55="","",IF(COUNTIFS(Orders!$C$6:$C$1005,C55,Orders!$U$6:$U$1005,">"&U55)=0,1,0)) | W55: =IF(AND(B55<>"",K55<>"",L55<>"Sent",L55<>"Picked up",L55<>"Cancelled"),IF(N(E55)=0,1,E55),0) | X55: =IF(OR(B55="",D55=""),"",IF(N(E55)=0,1,E55))
B56: 46073 | C56: Holly Cox | D56: Soap bar | E56: 1 | G56: 6.95 | H56: =IF(OR(B56="",D56=""),"",IF(N(E56)=0,1,E56)*IFERROR(INDEX(Products!$C$6:$C$105,MATCH(D56,Products!$B$6:$B$105,0)),0)+N(F56)+N(G56)) | I56: 14.95 | J56: =IF(OR(H56="",L56="Cancelled"),"",IF(H56-N(I56)>0.005,H56-N(I56),"")) | K56: 46079 | L56: Sent | M56: Etsy | N56: =IF(OR(H56="",L56="Cancelled"),"",IF(N(E56)=0,1,E56)*IFERROR(INDEX(Products!$E$6:$E$105,MATCH(D56,Products!$B$6:$B$105,0)),0)) | O56: 6.08 | P56: =IF(OR(H56="",L56="Cancelled"),"",ROUND(IFERROR(H56*INDEX(Settings!$C$6:$C$15,MATCH(M56,Settings!$B$6:$B$15,0))+INDEX(Settings!$D$6:$D$15,MATCH(M56,Settings!$B$6:$B$15,0)),0),2)) | Q56: =IF(OR(H56="",L56="Cancelled"),"",H56-N(N56)-N(O56)-N(P56)) | R56: =IF(OR(B56="",K56=""),"",IF(OR(L56="Sent",L56="Picked up"),"Done",IF(L56="Cancelled","Cancelled",IF(K56<TODAY(),"Late by "&(TODAY()-K56)&IF((TODAY()-K56)=1," day"," days"),IF(K56=TODAY(),"Due today","Due in "&(K56-TODAY())&IF((K56-TODAY())=1," day"," days")))))) | T56: =IF(AND(B56<>"",K56<>"",L56<>"Sent",L56<>"Picked up",L56<>"Cancelled"),K56+ROW()/10000000,"") | U56: =IF(OR(B56="",C56=""),"",B56+ROW()/10000000) | V56: =IF(U56="","",IF(COUNTIFS(Orders!$C$6:$C$1005,C56,Orders!$U$6:$U$1005,">"&U56)=0,1,0)) | W56: =IF(AND(B56<>"",K56<>"",L56<>"Sent",L56<>"Picked up",L56<>"Cancelled"),IF(N(E56)=0,1,E56),0) | X56: =IF(OR(B56="",D56=""),"",IF(N(E56)=0,1,E56))
B57: 46074 | C57: Lily Gray | D57: Gift box | E57: 2 | H57: =IF(OR(B57="",D57=""),"",IF(N(E57)=0,1,E57)*IFERROR(INDEX(Products!$C$6:$C$105,MATCH(D57,Products!$B$6:$B$105,0)),0)+N(F57)+N(G57)) | I57: 90 | J57: =IF(OR(H57="",L57="Cancelled"),"",IF(H57-N(I57)>0.005,H57-N(I57),"")) | K57: 46081 | L57: Picked up | M57: Friends and family | N57: =IF(OR(H57="",L57="Cancelled"),"",IF(N(E57)=0,1,E57)*IFERROR(INDEX(Products!$E$6:$E$105,MATCH(D57,Products!$B$6:$B$105,0)),0)) | P57: =IF(OR(H57="",L57="Cancelled"),"",ROUND(IFERROR(H57*INDEX(Settings!$C$6:$C$15,MATCH(M57,Settings!$B$6:$B$15,0))+INDEX(Settings!$D$6:$D$15,MATCH(M57,Settings!$B$6:$B$15,0)),0),2)) | Q57: =IF(OR(H57="",L57="Cancelled"),"",H57-N(N57)-N(O57)-N(P57)) | R57: =IF(OR(B57="",K57=""),"",IF(OR(L57="Sent",L57="Picked up"),"Done",IF(L57="Cancelled","Cancelled",IF(K57<TODAY(),"Late by "&(TODAY()-K57)&IF((TODAY()-K57)=1," day"," days"),IF(K57=TODAY(),"Due today","Due in "&(K57-TODAY())&IF((K57-TODAY())=1," day"," days")))))) | T57: =IF(AND(B57<>"",K57<>"",L57<>"Sent",L57<>"Picked up",L57<>"Cancelled"),K57+ROW()/10000000,"") | U57: =IF(OR(B57="",C57=""),"",B57+ROW()/10000000) | V57: =IF(U57="","",IF(COUNTIFS(Orders!$C$6:$C$1005,C57,Orders!$U$6:$U$1005,">"&U57)=0,1,0)) | W57: =IF(AND(B57<>"",K57<>"",L57<>"Sent",L57<>"Picked up",L57<>"Cancelled"),IF(N(E57)=0,1,E57),0) | X57: =IF(OR(B57="",D57=""),"",IF(N(E57)=0,1,E57))
B58: 46075 | C58: Holly Cox | D58: Wax melts, 6 pack | E58: 1 | G58: 6.95 | H58: =IF(OR(B58="",D58=""),"",IF(N(E58)=0,1,E58)*IFERROR(INDEX(Products!$C$6:$C$105,MATCH(D58,Products!$B$6:$B$105,0)),0)+N(F58)+N(G58)) | I58: 15.95 | J58: =IF(OR(H58="",L58="Cancelled"),"",IF(H58-N(I58)>0.005,H58-N(I58),"")) | K58: 46080 | L58: Sent | M58: Own website | N58: =IF(OR(H58="",L58="Cancelled"),"",IF(N(E58)=0,1,E58)*IFERROR(INDEX(Products!$E$6:$E$105,MATCH(D58,Products!$B$6:$B$105,0)),0)) | O58: 5.84 | P58: =IF(OR(H58="",L58="Cancelled"),"",ROUND(IFERROR(H58*INDEX(Settings!$C$6:$C$15,MATCH(M58,Settings!$B$6:$B$15,0))+INDEX(Settings!$D$6:$D$15,MATCH(M58,Settings!$B$6:$B$15,0)),0),2)) | Q58: =IF(OR(H58="",L58="Cancelled"),"",H58-N(N58)-N(O58)-N(P58)) | R58: =IF(OR(B58="",K58=""),"",IF(OR(L58="Sent",L58="Picked up"),"Done",IF(L58="Cancelled","Cancelled",IF(K58<TODAY(),"Late by "&(TODAY()-K58)&IF((TODAY()-K58)=1," day"," days"),IF(K58=TODAY(),"Due today","Due in "&(K58-TODAY())&IF((K58-TODAY())=1," day"," days")))))) | T58: =IF(AND(B58<>"",K58<>"",L58<>"Sent",L58<>"Picked up",L58<>"Cancelled"),K58+ROW()/10000000,"") | U58: =IF(OR(B58="",C58=""),"",B58+ROW()/10000000) | V58: =IF(U58="","",IF(COUNTIFS(Orders!$C$6:$C$1005,C58,Orders!$U$6:$U$1005,">"&U58)=0,1,0)) | W58: =IF(AND(B58<>"",K58<>"",L58<>"Sent",L58<>"Picked up",L58<>"Cancelled"),IF(N(E58)=0,1,E58),0) | X58: =IF(OR(B58="",D58=""),"",IF(N(E58)=0,1,E58))
B59: 46076 | C59: Ian Price | D59: Soy candle 8 oz | E59: 3 | G59: 6.95 | H59: =IF(OR(B59="",D59=""),"",IF(N(E59)=0,1,E59)*IFERROR(INDEX(Products!$C$6:$C$105,MATCH(D59,Products!$B$6:$B$105,0)),0)+N(F59)+N(G59)) | I59: 72.95 | J59: =IF(OR(H59="",L59="Cancelled"),"",IF(H59-N(I59)>0.005,H59-N(I59),"")) | K59: 46084 | L59: Sent | M59: Etsy | N59: =IF(OR(H59="",L59="Cancelled"),"",IF(N(E59)=0,1,E59)*IFERROR(INDEX(Products!$E$6:$E$105,MATCH(D59,Products!$B$6:$B$105,0)),0)) | O59: 5.75 | P59: =IF(OR(H59="",L59="Cancelled"),"",ROUND(IFERROR(H59*INDEX(Settings!$C$6:$C$15,MATCH(M59,Settings!$B$6:$B$15,0))+INDEX(Settings!$D$6:$D$15,MATCH(M59,Settings!$B$6:$B$15,0)),0),2)) | Q59: =IF(OR(H59="",L59="Cancelled"),"",H59-N(N59)-N(O59)-N(P59)) | R59: =IF(OR(B59="",K59=""),"",IF(OR(L59="Sent",L59="Picked up"),"Done",IF(L59="Cancelled","Cancelled",IF(K59<TODAY(),"Late by "&(TODAY()-K59)&IF((TODAY()-K59)=1," day"," days"),IF(K59=TODAY(),"Due today","Due in "&(K59-TODAY())&IF((K59-TODAY())=1," day"," days")))))) | T59: =IF(AND(B59<>"",K59<>"",L59<>"Sent",L59<>"Picked up",L59<>"Cancelled"),K59+ROW()/10000000,"") | U59: =IF(OR(B59="",C59=""),"",B59+ROW()/10000000) | V59: =IF(U59="","",IF(COUNTIFS(Orders!$C$6:$C$1005,C59,Orders!$U$6:$U$1005,">"&U59)=0,1,0)) | W59: =IF(AND(B59<>"",K59<>"",L59<>"Sent",L59<>"Picked up",L59<>"Cancelled"),IF(N(E59)=0,1,E59),0) | X59: =IF(OR(B59="",D59=""),"",IF(N(E59)=0,1,E59))
B60: 46077 | C60: Adam Baker | D60: Soap bar | E60: 1 | H60: =IF(OR(B60="",D60=""),"",IF(N(E60)=0,1,E60)*IFERROR(INDEX(Products!$C$6:$C$105,MATCH(D60,Products!$B$6:$B$105,0)),0)+N(F60)+N(G60)) | I60: 8 | J60: =IF(OR(H60="",L60="Cancelled"),"",IF(H60-N(I60)>0.005,H60-N(I60),"")) | K60: 46089 | L60: Picked up | M60: Craft market | N60: =IF(OR(H60="",L60="Cancelled"),"",IF(N(E60)=0,1,E60)*IFERROR(INDEX(Products!$E$6:$E$105,MATCH(D60,Products!$B$6:$B$105,0)),0)) | P60: =IF(OR(H60="",L60="Cancelled"),"",ROUND(IFERROR(H60*INDEX(Settings!$C$6:$C$15,MATCH(M60,Settings!$B$6:$B$15,0))+INDEX(Settings!$D$6:$D$15,MATCH(M60,Settings!$B$6:$B$15,0)),0),2)) | Q60: =IF(OR(H60="",L60="Cancelled"),"",H60-N(N60)-N(O60)-N(P60)) | R60: =IF(OR(B60="",K60=""),"",IF(OR(L60="Sent",L60="Picked up"),"Done",IF(L60="Cancelled","Cancelled",IF(K60<TODAY(),"Late by "&(TODAY()-K60)&IF((TODAY()-K60)=1," day"," days"),IF(K60=TODAY(),"Due today","Due in "&(K60-TODAY())&IF((K60-TODAY())=1," day"," days")))))) | T60: =IF(AND(B60<>"",K60<>"",L60<>"Sent",L60<>"Picked up",L60<>"Cancelled"),K60+ROW()/10000000,"") | U60: =IF(OR(B60="",C60=""),"",B60+ROW()/10000000) | V60: =IF(U60="","",IF(COUNTIFS(Orders!$C$6:$C$1005,C60,Orders!$U$6:$U$1005,">"&U60)=0,1,0)) | W60: =IF(AND(B60<>"",K60<>"",L60<>"Sent",L60<>"Picked up",L60<>"Cancelled"),IF(N(E60)=0,1,E60),0) | X60: =IF(OR(B60="",D60=""),"",IF(N(E60)=0,1,E60))
B61: 46078 | C61: Jon Fox | D61: Wax melts, 6 pack | E61: 4 | G61: 6.95 | H61: =IF(OR(B61="",D61=""),"",IF(N(E61)=0,1,E61)*IFERROR(INDEX(Products!$C$6:$C$105,MATCH(D61,Products!$B$6:$B$105,0)),0)+N(F61)+N(G61)) | I61: 42.95 | J61: =IF(OR(H61="",L61="Cancelled"),"",IF(H61-N(I61)>0.005,H61-N(I61),"")) | K61: 46088 | L61: Sent | M61: Etsy | N61: =IF(OR(H61="",L61="Cancelled"),"",IF(N(E61)=0,1,E61)*IFERROR(INDEX(Products!$E$6:$E$105,MATCH(D61,Products!$B$6:$B$105,0)),0)) | O61: 7.05 | P61: =IF(OR(H61="",L61="Cancelled"),"",ROUND(IFERROR(H61*INDEX(Settings!$C$6:$C$15,MATCH(M61,Settings!$B$6:$B$15,0))+INDEX(Settings!$D$6:$D$15,MATCH(M61,Settings!$B$6:$B$15,0)),0),2)) | Q61: =IF(OR(H61="",L61="Cancelled"),"",H61-N(N61)-N(O61)-N(P61)) | R61: =IF(OR(B61="",K61=""),"",IF(OR(L61="Sent",L61="Picked up"),"Done",IF(L61="Cancelled","Cancelled",IF(K61<TODAY(),"Late by "&(TODAY()-K61)&IF((TODAY()-K61)=1," day"," days"),IF(K61=TODAY(),"Due today","Due in "&(K61-TODAY())&IF((K61-TODAY())=1," day"," days")))))) | T61: =IF(AND(B61<>"",K61<>"",L61<>"Sent",L61<>"Picked up",L61<>"Cancelled"),K61+ROW()/10000000,"") | U61: =IF(OR(B61="",C61=""),"",B61+ROW()/10000000) | V61: =IF(U61="","",IF(COUNTIFS(Orders!$C$6:$C$1005,C61,Orders!$U$6:$U$1005,">"&U61)=0,1,0)) | W61: =IF(AND(B61<>"",K61<>"",L61<>"Sent",L61<>"Picked up",L61<>"Cancelled"),IF(N(E61)=0,1,E61),0) | X61: =IF(OR(B61="",D61=""),"",IF(N(E61)=0,1,E61))
B62: 46080 | C62: Holly Cox | D62: Soy candle 16 oz | E62: 1 | H62: =IF(OR(B62="",D62=""),"",IF(N(E62)=0,1,E62)*IFERROR(INDEX(Products!$C$6:$C$105,MATCH(D62,Products!$B$6:$B$105,0)),0)+N(F62)+N(G62)) | I62: 34 | J62: =IF(OR(H62="",L62="Cancelled"),"",IF(H62-N(I62)>0.005,H62-N(I62),"")) | K62: 46092 | L62: Picked up | M62: Craft market | N62: =IF(OR(H62="",L62="Cancelled"),"",IF(N(E62)=0,1,E62)*IFERROR(INDEX(Products!$E$6:$E$105,MATCH(D62,Products!$B$6:$B$105,0)),0)) | P62: =IF(OR(H62="",L62="Cancelled"),"",ROUND(IFERROR(H62*INDEX(Settings!$C$6:$C$15,MATCH(M62,Settings!$B$6:$B$15,0))+INDEX(Settings!$D$6:$D$15,MATCH(M62,Settings!$B$6:$B$15,0)),0),2)) | Q62: =IF(OR(H62="",L62="Cancelled"),"",H62-N(N62)-N(O62)-N(P62)) | R62: =IF(OR(B62="",K62=""),"",IF(OR(L62="Sent",L62="Picked up"),"Done",IF(L62="Cancelled","Cancelled",IF(K62<TODAY(),"Late by "&(TODAY()-K62)&IF((TODAY()-K62)=1," day"," days"),IF(K62=TODAY(),"Due today","Due in "&(K62-TODAY())&IF((K62-TODAY())=1," day"," days")))))) | T62: =IF(AND(B62<>"",K62<>"",L62<>"Sent",L62<>"Picked up",L62<>"Cancelled"),K62+ROW()/10000000,"") | U62: =IF(OR(B62="",C62=""),"",B62+ROW()/10000000) | V62: =IF(U62="","",IF(COUNTIFS(Orders!$C$6:$C$1005,C62,Orders!$U$6:$U$1005,">"&U62)=0,1,0)) | W62: =IF(AND(B62<>"",K62<>"",L62<>"Sent",L62<>"Picked up",L62<>"Cancelled"),IF(N(E62)=0,1,E62),0) | X62: =IF(OR(B62="",D62=""),"",IF(N(E62)=0,1,E62))
B63: 46081 | C63: Ruby Brooks | D63: Gift box | E63: 1 | G63: 6.95 | H63: =IF(OR(B63="",D63=""),"",IF(N(E63)=0,1,E63)*IFERROR(INDEX(Products!$C$6:$C$105,MATCH(D63,Products!$B$6:$B$105,0)),0)+N(F63)+N(G63)) | I63: 51.95 | J63: =IF(OR(H63="",L63="Cancelled"),"",IF(H63-N(I63)>0.005,H63-N(I63),"")) | K63: 46091 | L63: Sent | M63: Etsy | N63: =IF(OR(H63="",L63="Cancelled"),"",IF(N(E63)=0,1,E63)*IFERROR(INDEX(Products!$E$6:$E$105,MATCH(D63,Products!$B$6:$B$105,0)),0)) | O63: 7.75 | P63: =IF(OR(H63="",L63="Cancelled"),"",ROUND(IFERROR(H63*INDEX(Settings!$C$6:$C$15,MATCH(M63,Settings!$B$6:$B$15,0))+INDEX(Settings!$D$6:$D$15,MATCH(M63,Settings!$B$6:$B$15,0)),0),2)) | Q63: =IF(OR(H63="",L63="Cancelled"),"",H63-N(N63)-N(O63)-N(P63)) | R63: =IF(OR(B63="",K63=""),"",IF(OR(L63="Sent",L63="Picked up"),"Done",IF(L63="Cancelled","Cancelled",IF(K63<TODAY(),"Late by "&(TODAY()-K63)&IF((TODAY()-K63)=1," day"," days"),IF(K63=TODAY(),"Due today","Due in "&(K63-TODAY())&IF((K63-TODAY())=1," day"," days")))))) | T63: =IF(AND(B63<>"",K63<>"",L63<>"Sent",L63<>"Picked up",L63<>"Cancelled"),K63+ROW()/10000000,"") | U63: =IF(OR(B63="",C63=""),"",B63+ROW()/10000000) | V63: =IF(U63="","",IF(COUNTIFS(Orders!$C$6:$C$1005,C63,Orders!$U$6:$U$1005,">"&U63)=0,1,0)) | W63: =IF(AND(B63<>"",K63<>"",L63<>"Sent",L63<>"Picked up",L63<>"Cancelled"),IF(N(E63)=0,1,E63),0) | X63: =IF(OR(B63="",D63=""),"",IF(N(E63)=0,1,E63))
B64: 46081 | C64: Nora Lewis | D64: Soy candle 8 oz | E64: 1 | H64: =IF(OR(B64="",D64=""),"",IF(N(E64)=0,1,E64)*IFERROR(INDEX(Products!$C$6:$C$105,MATCH(D64,Products!$B$6:$B$105,0)),0)+N(F64)+N(G64)) | I64: 22 | J64: =IF(OR(H64="",L64="Cancelled"),"",IF(H64-N(I64)>0.005,H64-N(I64),"")) | K64: 46087 | L64: Picked up | M64: Instagram | N64: =IF(OR(H64="",L64="Cancelled"),"",IF(N(E64)=0,1,E64)*IFERROR(INDEX(Products!$E$6:$E$105,MATCH(D64,Products!$B$6:$B$105,0)),0)) | P64: =IF(OR(H64="",L64="Cancelled"),"",ROUND(IFERROR(H64*INDEX(Settings!$C$6:$C$15,MATCH(M64,Settings!$B$6:$B$15,0))+INDEX(Settings!$D$6:$D$15,MATCH(M64,Settings!$B$6:$B$15,0)),0),2)) | Q64: =IF(OR(H64="",L64="Cancelled"),"",H64-N(N64)-N(O64)-N(P64)) | R64: =IF(OR(B64="",K64=""),"",IF(OR(L64="Sent",L64="Picked up"),"Done",IF(L64="Cancelled","Cancelled",IF(K64<TODAY(),"Late by "&(TODAY()-K64)&IF((TODAY()-K64)=1," day"," days"),IF(K64=TODAY(),"Due today","Due in "&(K64-TODAY())&IF((K64-TODAY())=1," day"," days")))))) | T64: =IF(AND(B64<>"",K64<>"",L64<>"Sent",L64<>"Picked up",L64<>"Cancelled"),K64+ROW()/10000000,"") | U64: =IF(OR(B64="",C64=""),"",B64+ROW()/10000000) | V64: =IF(U64="","",IF(COUNTIFS(Orders!$C$6:$C$1005,C64,Orders!$U$6:$U$1005,">"&U64)=0,1,0)) | W64: =IF(AND(B64<>"",K64<>"",L64<>"Sent",L64<>"Picked up",L64<>"Cancelled"),IF(N(E64)=0,1,E64),0) | X64: =IF(OR(B64="",D64=""),"",IF(N(E64)=0,1,E64))
B65: 46082 | C65: Ava Adams | D65: Soy candle 8 oz | E65: 1 | G65: 6.95 | H65: =IF(OR(B65="",D65=""),"",IF(N(E65)=0,1,E65)*IFERROR(INDEX(Products!$C$6:$C$105,MATCH(D65,Products!$B$6:$B$105,0)),0)+N(F65)+N(G65)) | I65: 28.95 | J65: =IF(OR(H65="",L65="Cancelled"),"",IF(H65-N(I65)>0.005,H65-N(I65),"")) | K65: 46086 | L65: Sent | M65: Etsy | N65: =IF(OR(H65="",L65="Cancelled"),"",IF(N(E65)=0,1,E65)*IFERROR(INDEX(Products!$E$6:$E$105,MATCH(D65,Products!$B$6:$B$105,0)),0)) | O65: 6.1 | P65: =IF(OR(H65="",L65="Cancelled"),"",ROUND(IFERROR(H65*INDEX(Settings!$C$6:$C$15,MATCH(M65,Settings!$B$6:$B$15,0))+INDEX(Settings!$D$6:$D$15,MATCH(M65,Settings!$B$6:$B$15,0)),0),2)) | Q65: =IF(OR(H65="",L65="Cancelled"),"",H65-N(N65)-N(O65)-N(P65)) | R65: =IF(OR(B65="",K65=""),"",IF(OR(L65="Sent",L65="Picked up"),"Done",IF(L65="Cancelled","Cancelled",IF(K65<TODAY(),"Late by "&(TODAY()-K65)&IF((TODAY()-K65)=1," day"," days"),IF(K65=TODAY(),"Due today","Due in "&(K65-TODAY())&IF((K65-TODAY())=1," day"," days")))))) | T65: =IF(AND(B65<>"",K65<>"",L65<>"Sent",L65<>"Picked up",L65<>"Cancelled"),K65+ROW()/10000000,"") | U65: =IF(OR(B65="",C65=""),"",B65+ROW()/10000000) | V65: =IF(U65="","",IF(COUNTIFS(Orders!$C$6:$C$1005,C65,Orders!$U$6:$U$1005,">"&U65)=0,1,0)) | W65: =IF(AND(B65<>"",K65<>"",L65<>"Sent",L65<>"Picked up",L65<>"Cancelled"),IF(N(E65)=0,1,E65),0) | X65: =IF(OR(B65="",D65=""),"",IF(N(E65)=0,1,E65))
B66: 46083 | C66: Paula Mills | D66: Soy candle 16 oz | E66: 2 | G66: 6.95 | H66: =IF(OR(B66="",D66=""),"",IF(N(E66)=0,1,E66)*IFERROR(INDEX(Products!$C$6:$C$105,MATCH(D66,Products!$B$6:$B$105,0)),0)+N(F66)+N(G66)) | I66: 74.95 | J66: =IF(OR(H66="",L66="Cancelled"),"",IF(H66-N(I66)>0.005,H66-N(I66),"")) | K66: 46090 | L66: Sent | M66: Etsy | N66: =IF(OR(H66="",L66="Cancelled"),"",IF(N(E66)=0,1,E66)*IFERROR(INDEX(Products!$E$6:$E$105,MATCH(D66,Products!$B$6:$B$105,0)),0)) | O66: 7.4 | P66: =IF(OR(H66="",L66="Cancelled"),"",ROUND(IFERROR(H66*INDEX(Settings!$C$6:$C$15,MATCH(M66,Settings!$B$6:$B$15,0))+INDEX(Settings!$D$6:$D$15,MATCH(M66,Settings!$B$6:$B$15,0)),0),2)) | Q66: =IF(OR(H66="",L66="Cancelled"),"",H66-N(N66)-N(O66)-N(P66)) | R66: =IF(OR(B66="",K66=""),"",IF(OR(L66="Sent",L66="Picked up"),"Done",IF(L66="Cancelled","Cancelled",IF(K66<TODAY(),"Late by "&(TODAY()-K66)&IF((TODAY()-K66)=1," day"," days"),IF(K66=TODAY(),"Due today","Due in "&(K66-TODAY())&IF((K66-TODAY())=1," day"," days")))))) | T66: =IF(AND(B66<>"",K66<>"",L66<>"Sent",L66<>"Picked up",L66<>"Cancelled"),K66+ROW()/10000000,"") | U66: =IF(OR(B66="",C66=""),"",B66+ROW()/10000000) | V66: =IF(U66="","",IF(COUNTIFS(Orders!$C$6:$C$1005,C66,Orders!$U$6:$U$1005,">"&U66)=0,1,0)) | W66: =IF(AND(B66<>"",K66<>"",L66<>"Sent",L66<>"Picked up",L66<>"Cancelled"),IF(N(E66)=0,1,E66),0) | X66: =IF(OR(B66="",D66=""),"",IF(N(E66)=0,1,E66))
B67: 46084 | C67: George Hill | D67: Wax melts, 6 pack | E67: 1 | G67: 6.95 | H67: =IF(OR(B67="",D67=""),"",IF(N(E67)=0,1,E67)*IFERROR(INDEX(Products!$C$6:$C$105,MATCH(D67,Products!$B$6:$B$105,0)),0)+N(F67)+N(G67)) | I67: 15.95 | J67: =IF(OR(H67="",L67="Cancelled"),"",IF(H67-N(I67)>0.005,H67-N(I67),"")) | K67: 46093 | L67: Sent | M67: Etsy | N67: =IF(OR(H67="",L67="Cancelled"),"",IF(N(E67)=0,1,E67)*IFERROR(INDEX(Products!$E$6:$E$105,MATCH(D67,Products!$B$6:$B$105,0)),0)) | O67: 6.23 | P67: =IF(OR(H67="",L67="Cancelled"),"",ROUND(IFERROR(H67*INDEX(Settings!$C$6:$C$15,MATCH(M67,Settings!$B$6:$B$15,0))+INDEX(Settings!$D$6:$D$15,MATCH(M67,Settings!$B$6:$B$15,0)),0),2)) | Q67: =IF(OR(H67="",L67="Cancelled"),"",H67-N(N67)-N(O67)-N(P67)) | R67: =IF(OR(B67="",K67=""),"",IF(OR(L67="Sent",L67="Picked up"),"Done",IF(L67="Cancelled","Cancelled",IF(K67<TODAY(),"Late by "&(TODAY()-K67)&IF((TODAY()-K67)=1," day"," days"),IF(K67=TODAY(),"Due today","Due in "&(K67-TODAY())&IF((K67-TODAY())=1," day"," days")))))) | T67: =IF(AND(B67<>"",K67<>"",L67<>"Sent",L67<>"Picked up",L67<>"Cancelled"),K67+ROW()/10000000,"") | U67: =IF(OR(B67="",C67=""),"",B67+ROW()/10000000) | V67: =IF(U67="","",IF(COUNTIFS(Orders!$C$6:$C$1005,C67,Orders!$U$6:$U$1005,">"&U67)=0,1,0)) | W67: =IF(AND(B67<>"",K67<>"",L67<>"Sent",L67<>"Picked up",L67<>"Cancelled"),IF(N(E67)=0,1,E67),0) | X67: =IF(OR(B67="",D67=""),"",IF(N(E67)=0,1,E67))
B68: 46085 | C68: Paula Mills | D68: Soap bar | E68: 1 | H68: =IF(OR(B68="",D68=""),"",IF(N(E68)=0,1,E68)*IFERROR(INDEX(Products!$C$6:$C$105,MATCH(D68,Products!$B$6:$B$105,0)),0)+N(F68)+N(G68)) | I68: 8 | J68: =IF(OR(H68="",L68="Cancelled"),"",IF(H68-N(I68)>0.005,H68-N(I68),"")) | K68: 46095 | L68: Picked up | M68: Instagram | N68: =IF(OR(H68="",L68="Cancelled"),"",IF(N(E68)=0,1,E68)*IFERROR(INDEX(Products!$E$6:$E$105,MATCH(D68,Products!$B$6:$B$105,0)),0)) | P68: =IF(OR(H68="",L68="Cancelled"),"",ROUND(IFERROR(H68*INDEX(Settings!$C$6:$C$15,MATCH(M68,Settings!$B$6:$B$15,0))+INDEX(Settings!$D$6:$D$15,MATCH(M68,Settings!$B$6:$B$15,0)),0),2)) | Q68: =IF(OR(H68="",L68="Cancelled"),"",H68-N(N68)-N(O68)-N(P68)) | R68: =IF(OR(B68="",K68=""),"",IF(OR(L68="Sent",L68="Picked up"),"Done",IF(L68="Cancelled","Cancelled",IF(K68<TODAY(),"Late by "&(TODAY()-K68)&IF((TODAY()-K68)=1," day"," days"),IF(K68=TODAY(),"Due today","Due in "&(K68-TODAY())&IF((K68-TODAY())=1," day"," days")))))) | T68: =IF(AND(B68<>"",K68<>"",L68<>"Sent",L68<>"Picked up",L68<>"Cancelled"),K68+ROW()/10000000,"") | U68: =IF(OR(B68="",C68=""),"",B68+ROW()/10000000) | V68: =IF(U68="","",IF(COUNTIFS(Orders!$C$6:$C$1005,C68,Orders!$U$6:$U$1005,">"&U68)=0,1,0)) | W68: =IF(AND(B68<>"",K68<>"",L68<>"Sent",L68<>"Picked up",L68<>"Cancelled"),IF(N(E68)=0,1,E68),0) | X68: =IF(OR(B68="",D68=""),"",IF(N(E68)=0,1,E68))
B69: 46086 | C69: Jon Reed | D69: Wedding favours, 10 tins | E69: 6 | G69: 6.95 | H69: =IF(OR(B69="",D69=""),"",IF(N(E69)=0,1,E69)*IFERROR(INDEX(Products!$C$6:$C$105,MATCH(D69,Products!$B$6:$B$105,0)),0)+N(F69)+N(G69)) | I69: 366.95 | J69: =IF(OR(H69="",L69="Cancelled"),"",IF(H69-N(I69)>0.005,H69-N(I69),"")) | K69: 46116 | L69: Sent | M69: Etsy | N69: =IF(OR(H69="",L69="Cancelled"),"",IF(N(E69)=0,1,E69)*IFERROR(INDEX(Products!$E$6:$E$105,MATCH(D69,Products!$B$6:$B$105,0)),0)) | O69: 6.8 | P69: =IF(OR(H69="",L69="Cancelled"),"",ROUND(IFERROR(H69*INDEX(Settings!$C$6:$C$15,MATCH(M69,Settings!$B$6:$B$15,0))+INDEX(Settings!$D$6:$D$15,MATCH(M69,Settings!$B$6:$B$15,0)),0),2)) | Q69: =IF(OR(H69="",L69="Cancelled"),"",H69-N(N69)-N(O69)-N(P69)) | R69: =IF(OR(B69="",K69=""),"",IF(OR(L69="Sent",L69="Picked up"),"Done",IF(L69="Cancelled","Cancelled",IF(K69<TODAY(),"Late by "&(TODAY()-K69)&IF((TODAY()-K69)=1," day"," days"),IF(K69=TODAY(),"Due today","Due in "&(K69-TODAY())&IF((K69-TODAY())=1," day"," days")))))) | T69: =IF(AND(B69<>"",K69<>"",L69<>"Sent",L69<>"Picked up",L69<>"Cancelled"),K69+ROW()/10000000,"") | U69: =IF(OR(B69="",C69=""),"",B69+ROW()/10000000) | V69: =IF(U69="","",IF(COUNTIFS(Orders!$C$6:$C$1005,C69,Orders!$U$6:$U$1005,">"&U69)=0,1,0)) | W69: =IF(AND(B69<>"",K69<>"",L69<>"Sent",L69<>"Picked up",L69<>"Cancelled"),IF(N(E69)=0,1,E69),0) | X69: =IF(OR(B69="",D69=""),"",IF(N(E69)=0,1,E69))
B70: 46088 | C70: Finn Mason | D70: Gift box | E70: 1 | G70: 6.95 | H70: =IF(OR(B70="",D70=""),"",IF(N(E70)=0,1,E70)*IFERROR(INDEX(Products!$C$6:$C$105,MATCH(D70,Products!$B$6:$B$105,0)),0)+N(F70)+N(G70)) | I70: 51.95 | J70: =IF(OR(H70="",L70="Cancelled"),"",IF(H70-N(I70)>0.005,H70-N(I70),"")) | K70: 46093 | L70: Sent | M70: Etsy | N70: =IF(OR(H70="",L70="Cancelled"),"",IF(N(E70)=0,1,E70)*IFERROR(INDEX(Products!$E$6:$E$105,MATCH(D70,Products!$B$6:$B$105,0)),0)) | O70: 5.22 | P70: =IF(OR(H70="",L70="Cancelled"),"",ROUND(IFERROR(H70*INDEX(Settings!$C$6:$C$15,MATCH(M70,Settings!$B$6:$B$15,0))+INDEX(Settings!$D$6:$D$15,MATCH(M70,Settings!$B$6:$B$15,0)),0),2)) | Q70: =IF(OR(H70="",L70="Cancelled"),"",H70-N(N70)-N(O70)-N(P70)) | R70: =IF(OR(B70="",K70=""),"",IF(OR(L70="Sent",L70="Picked up"),"Done",IF(L70="Cancelled","Cancelled",IF(K70<TODAY(),"Late by "&(TODAY()-K70)&IF((TODAY()-K70)=1," day"," days"),IF(K70=TODAY(),"Due today","Due in "&(K70-TODAY())&IF((K70-TODAY())=1," day"," days")))))) | T70: =IF(AND(B70<>"",K70<>"",L70<>"Sent",L70<>"Picked up",L70<>"Cancelled"),K70+ROW()/10000000,"") | U70: =IF(OR(B70="",C70=""),"",B70+ROW()/10000000) | V70: =IF(U70="","",IF(COUNTIFS(Orders!$C$6:$C$1005,C70,Orders!$U$6:$U$1005,">"&U70)=0,1,0)) | W70: =IF(AND(B70<>"",K70<>"",L70<>"Sent",L70<>"Picked up",L70<>"Cancelled"),IF(N(E70)=0,1,E70),0) | X70: =IF(OR(B70="",D70=""),"",IF(N(E70)=0,1,E70))
B71: 46088 | C71: Leah Hughes | D71: Soap bar | E71: 3 | H71: =IF(OR(B71="",D71=""),"",IF(N(E71)=0,1,E71)*IFERROR(INDEX(Products!$C$6:$C$105,MATCH(D71,Products!$B$6:$B$105,0)),0)+N(F71)+N(G71)) | I71: 24 | J71: =IF(OR(H71="",L71="Cancelled"),"",IF(H71-N(I71)>0.005,H71-N(I71),"")) | K71: 46099 | L71: Picked up | M71: Friends and family | N71: =IF(OR(H71="",L71="Cancelled"),"",IF(N(E71)=0,1,E71)*IFERROR(INDEX(Products!$E$6:$E$105,MATCH(D71,Products!$B$6:$B$105,0)),0)) | P71: =IF(OR(H71="",L71="Cancelled"),"",ROUND(IFERROR(H71*INDEX(Settings!$C$6:$C$15,MATCH(M71,Settings!$B$6:$B$15,0))+INDEX(Settings!$D$6:$D$15,MATCH(M71,Settings!$B$6:$B$15,0)),0),2)) | Q71: =IF(OR(H71="",L71="Cancelled"),"",H71-N(N71)-N(O71)-N(P71)) | R71: =IF(OR(B71="",K71=""),"",IF(OR(L71="Sent",L71="Picked up"),"Done",IF(L71="Cancelled","Cancelled",IF(K71<TODAY(),"Late by "&(TODAY()-K71)&IF((TODAY()-K71)=1," day"," days"),IF(K71=TODAY(),"Due today","Due in "&(K71-TODAY())&IF((K71-TODAY())=1," day"," days")))))) | T71: =IF(AND(B71<>"",K71<>"",L71<>"Sent",L71<>"Picked up",L71<>"Cancelled"),K71+ROW()/10000000,"") | U71: =IF(OR(B71="",C71=""),"",B71+ROW()/10000000) | V71: =IF(U71="","",IF(COUNTIFS(Orders!$C$6:$C$1005,C71,Orders!$U$6:$U$1005,">"&U71)=0,1,0)) | W71: =IF(AND(B71<>"",K71<>"",L71<>"Sent",L71<>"Picked up",L71<>"Cancelled"),IF(N(E71)=0,1,E71),0) | X71: =IF(OR(B71="",D71=""),"",IF(N(E71)=0,1,E71))
B72: 46089 | C72: Ruby Brooks | D72: Soy candle 16 oz | E72: 2 | H72: =IF(OR(B72="",D72=""),"",IF(N(E72)=0,1,E72)*IFERROR(INDEX(Products!$C$6:$C$105,MATCH(D72,Products!$B$6:$B$105,0)),0)+N(F72)+N(G72)) | I72: 68 | J72: =IF(OR(H72="",L72="Cancelled"),"",IF(H72-N(I72)>0.005,H72-N(I72),"")) | K72: 46095 | L72: Picked up | M72: Instagram | N72: =IF(OR(H72="",L72="Cancelled"),"",IF(N(E72)=0,1,E72)*IFERROR(INDEX(Products!$E$6:$E$105,MATCH(D72,Products!$B$6:$B$105,0)),0)) | P72: =IF(OR(H72="",L72="Cancelled"),"",ROUND(IFERROR(H72*INDEX(Settings!$C$6:$C$15,MATCH(M72,Settings!$B$6:$B$15,0))+INDEX(Settings!$D$6:$D$15,MATCH(M72,Settings!$B$6:$B$15,0)),0),2)) | Q72: =IF(OR(H72="",L72="Cancelled"),"",H72-N(N72)-N(O72)-N(P72)) | R72: =IF(OR(B72="",K72=""),"",IF(OR(L72="Sent",L72="Picked up"),"Done",IF(L72="Cancelled","Cancelled",IF(K72<TODAY(),"Late by "&(TODAY()-K72)&IF((TODAY()-K72)=1," day"," days"),IF(K72=TODAY(),"Due today","Due in "&(K72-TODAY())&IF((K72-TODAY())=1," day"," days")))))) | T72: =IF(AND(B72<>"",K72<>"",L72<>"Sent",L72<>"Picked up",L72<>"Cancelled"),K72+ROW()/10000000,"") | U72: =IF(OR(B72="",C72=""),"",B72+ROW()/10000000) | V72: =IF(U72="","",IF(COUNTIFS(Orders!$C$6:$C$1005,C72,Orders!$U$6:$U$1005,">"&U72)=0,1,0)) | W72: =IF(AND(B72<>"",K72<>"",L72<>"Sent",L72<>"Picked up",L72<>"Cancelled"),IF(N(E72)=0,1,E72),0) | X72: =IF(OR(B72="",D72=""),"",IF(N(E72)=0,1,E72))
B73: 46089 | C73: Dan King | D73: Wax melts, 6 pack | E73: 1 | H73: =IF(OR(B73="",D73=""),"",IF(N(E73)=0,1,E73)*IFERROR(INDEX(Products!$C$6:$C$105,MATCH(D73,Products!$B$6:$B$105,0)),0)+N(F73)+N(G73)) | I73: 9 | J73: =IF(OR(H73="",L73="Cancelled"),"",IF(H73-N(I73)>0.005,H73-N(I73),"")) | K73: 46098 | L73: Picked up | M73: Friends and family | N73: =IF(OR(H73="",L73="Cancelled"),"",IF(N(E73)=0,1,E73)*IFERROR(INDEX(Products!$E$6:$E$105,MATCH(D73,Products!$B$6:$B$105,0)),0)) | P73: =IF(OR(H73="",L73="Cancelled"),"",ROUND(IFERROR(H73*INDEX(Settings!$C$6:$C$15,MATCH(M73,Settings!$B$6:$B$15,0))+INDEX(Settings!$D$6:$D$15,MATCH(M73,Settings!$B$6:$B$15,0)),0),2)) | Q73: =IF(OR(H73="",L73="Cancelled"),"",H73-N(N73)-N(O73)-N(P73)) | R73: =IF(OR(B73="",K73=""),"",IF(OR(L73="Sent",L73="Picked up"),"Done",IF(L73="Cancelled","Cancelled",IF(K73<TODAY(),"Late by "&(TODAY()-K73)&IF((TODAY()-K73)=1," day"," days"),IF(K73=TODAY(),"Due today","Due in "&(K73-TODAY())&IF((K73-TODAY())=1," day"," days")))))) | T73: =IF(AND(B73<>"",K73<>"",L73<>"Sent",L73<>"Picked up",L73<>"Cancelled"),K73+ROW()/10000000,"") | U73: =IF(OR(B73="",C73=""),"",B73+ROW()/10000000) | V73: =IF(U73="","",IF(COUNTIFS(Orders!$C$6:$C$1005,C73,Orders!$U$6:$U$1005,">"&U73)=0,1,0)) | W73: =IF(AND(B73<>"",K73<>"",L73<>"Sent",L73<>"Picked up",L73<>"Cancelled"),IF(N(E73)=0,1,E73),0) | X73: =IF(OR(B73="",D73=""),"",IF(N(E73)=0,1,E73))
B74: 46090 | C74: George Price | D74: Soy candle 16 oz | E74: 1 | H74: =IF(OR(B74="",D74=""),"",IF(N(E74)=0,1,E74)*IFERROR(INDEX(Products!$C$6:$C$105,MATCH(D74,Products!$B$6:$B$105,0)),0)+N(F74)+N(G74)) | I74: 34 | J74: =IF(OR(H74="",L74="Cancelled"),"",IF(H74-N(I74)>0.005,H74-N(I74),"")) | K74: 46097 | L74: Picked up | M74: Instagram | N74: =IF(OR(H74="",L74="Cancelled"),"",IF(N(E74)=0,1,E74)*IFERROR(INDEX(Products!$E$6:$E$105,MATCH(D74,Products!$B$6:$B$105,0)),0)) | P74: =IF(OR(H74="",L74="Cancelled"),"",ROUND(IFERROR(H74*INDEX(Settings!$C$6:$C$15,MATCH(M74,Settings!$B$6:$B$15,0))+INDEX(Settings!$D$6:$D$15,MATCH(M74,Settings!$B$6:$B$15,0)),0),2)) | Q74: =IF(OR(H74="",L74="Cancelled"),"",H74-N(N74)-N(O74)-N(P74)) | R74: =IF(OR(B74="",K74=""),"",IF(OR(L74="Sent",L74="Picked up"),"Done",IF(L74="Cancelled","Cancelled",IF(K74<TODAY(),"Late by "&(TODAY()-K74)&IF((TODAY()-K74)=1," day"," days"),IF(K74=TODAY(),"Due today","Due in "&(K74-TODAY())&IF((K74-TODAY())=1," day"," days")))))) | T74: =IF(AND(B74<>"",K74<>"",L74<>"Sent",L74<>"Picked up",L74<>"Cancelled"),K74+ROW()/10000000,"") | U74: =IF(OR(B74="",C74=""),"",B74+ROW()/10000000) | V74: =IF(U74="","",IF(COUNTIFS(Orders!$C$6:$C$1005,C74,Orders!$U$6:$U$1005,">"&U74)=0,1,0)) | W74: =IF(AND(B74<>"",K74<>"",L74<>"Sent",L74<>"Picked up",L74<>"Cancelled"),IF(N(E74)=0,1,E74),0) | X74: =IF(OR(B74="",D74=""),"",IF(N(E74)=0,1,E74))
B75: 46091 | C75: Chris Mason | D75: Soy candle 8 oz | E75: 1 | G75: 6.95 | H75: =IF(OR(B75="",D75=""),"",IF(N(E75)=0,1,E75)*IFERROR(INDEX(Products!$C$6:$C$105,MATCH(D75,Products!$B$6:$B$105,0)),0)+N(F75)+N(G75)) | I75: 28.95 | J75: =IF(OR(H75="",L75="Cancelled"),"",IF(H75-N(I75)>0.005,H75-N(I75),"")) | K75: 46100 | L75: Sent | M75: Etsy | N75: =IF(OR(H75="",L75="Cancelled"),"",IF(N(E75)=0,1,E75)*IFERROR(INDEX(Products!$E$6:$E$105,MATCH(D75,Products!$B$6:$B$105,0)),0)) | O75: 6.73 | P75: =IF(OR(H75="",L75="Cancelled"),"",ROUND(IFERROR(H75*INDEX(Settings!$C$6:$C$15,MATCH(M75,Settings!$B$6:$B$15,0))+INDEX(Settings!$D$6:$D$15,MATCH(M75,Settings!$B$6:$B$15,0)),0),2)) | Q75: =IF(OR(H75="",L75="Cancelled"),"",H75-N(N75)-N(O75)-N(P75)) | R75: =IF(OR(B75="",K75=""),"",IF(OR(L75="Sent",L75="Picked up"),"Done",IF(L75="Cancelled","Cancelled",IF(K75<TODAY(),"Late by "&(TODAY()-K75)&IF((TODAY()-K75)=1," day"," days"),IF(K75=TODAY(),"Due today","Due in "&(K75-TODAY())&IF((K75-TODAY())=1," day"," days")))))) | T75: =IF(AND(B75<>"",K75<>"",L75<>"Sent",L75<>"Picked up",L75<>"Cancelled"),K75+ROW()/10000000,"") | U75: =IF(OR(B75="",C75=""),"",B75+ROW()/10000000) | V75: =IF(U75="","",IF(COUNTIFS(Orders!$C$6:$C$1005,C75,Orders!$U$6:$U$1005,">"&U75)=0,1,0)) | W75: =IF(AND(B75<>"",K75<>"",L75<>"Sent",L75<>"Picked up",L75<>"Cancelled"),IF(N(E75)=0,1,E75),0) | X75: =IF(OR(B75="",D75=""),"",IF(N(E75)=0,1,E75))
B76: 46091 | C76: Beth Owens | D76: Soy candle 16 oz | E76: 1 | G76: 6.95 | H76: =IF(OR(B76="",D76=""),"",IF(N(E76)=0,1,E76)*IFERROR(INDEX(Products!$C$6:$C$105,MATCH(D76,Products!$B$6:$B$105,0)),0)+N(F76)+N(G76)) | I76: 40.95 | J76: =IF(OR(H76="",L76="Cancelled"),"",IF(H76-N(I76)>0.005,H76-N(I76),"")) | K76: 46103 | L76: Sent | M76: Etsy | N76: =IF(OR(H76="",L76="Cancelled"),"",IF(N(E76)=0,1,E76)*IFERROR(INDEX(Products!$E$6:$E$105,MATCH(D76,Products!$B$6:$B$105,0)),0)) | O76: 7.55 | P76: =IF(OR(H76="",L76="Cancelled"),"",ROUND(IFERROR(H76*INDEX(Settings!$C$6:$C$15,MATCH(M76,Settings!$B$6:$B$15,0))+INDEX(Settings!$D$6:$D$15,MATCH(M76,Settings!$B$6:$B$15,0)),0),2)) | Q76: =IF(OR(H76="",L76="Cancelled"),"",H76-N(N76)-N(O76)-N(P76)) | R76: =IF(OR(B76="",K76=""),"",IF(OR(L76="Sent",L76="Picked up"),"Done",IF(L76="Cancelled","Cancelled",IF(K76<TODAY(),"Late by "&(TODAY()-K76)&IF((TODAY()-K76)=1," day"," days"),IF(K76=TODAY(),"Due today","Due in "&(K76-TODAY())&IF((K76-TODAY())=1," day"," days")))))) | T76: =IF(AND(B76<>"",K76<>"",L76<>"Sent",L76<>"Picked up",L76<>"Cancelled"),K76+ROW()/10000000,"") | U76: =IF(OR(B76="",C76=""),"",B76+ROW()/10000000) | V76: =IF(U76="","",IF(COUNTIFS(Orders!$C$6:$C$1005,C76,Orders!$U$6:$U$1005,">"&U76)=0,1,0)) | W76: =IF(AND(B76<>"",K76<>"",L76<>"Sent",L76<>"Picked up",L76<>"Cancelled"),IF(N(E76)=0,1,E76),0) | X76: =IF(OR(B76="",D76=""),"",IF(N(E76)=0,1,E76))
B77: 46093 | C77: Nina Kelly | D77: Soy candle 8 oz | E77: 1 | H77: =IF(OR(B77="",D77=""),"",IF(N(E77)=0,1,E77)*IFERROR(INDEX(Products!$C$6:$C$105,MATCH(D77,Products!$B$6:$B$105,0)),0)+N(F77)+N(G77)) | I77: 22 | J77: =IF(OR(H77="",L77="Cancelled"),"",IF(H77-N(I77)>0.005,H77-N(I77),"")) | K77: 46101 | L77: Picked up | M77: Craft market | N77: =IF(OR(H77="",L77="Cancelled"),"",IF(N(E77)=0,1,E77)*IFERROR(INDEX(Products!$E$6:$E$105,MATCH(D77,Products!$B$6:$B$105,0)),0)) | P77: =IF(OR(H77="",L77="Cancelled"),"",ROUND(IFERROR(H77*INDEX(Settings!$C$6:$C$15,MATCH(M77,Settings!$B$6:$B$15,0))+INDEX(Settings!$D$6:$D$15,MATCH(M77,Settings!$B$6:$B$15,0)),0),2)) | Q77: =IF(OR(H77="",L77="Cancelled"),"",H77-N(N77)-N(O77)-N(P77)) | R77: =IF(OR(B77="",K77=""),"",IF(OR(L77="Sent",L77="Picked up"),"Done",IF(L77="Cancelled","Cancelled",IF(K77<TODAY(),"Late by "&(TODAY()-K77)&IF((TODAY()-K77)=1," day"," days"),IF(K77=TODAY(),"Due today","Due in "&(K77-TODAY())&IF((K77-TODAY())=1," day"," days")))))) | T77: =IF(AND(B77<>"",K77<>"",L77<>"Sent",L77<>"Picked up",L77<>"Cancelled"),K77+ROW()/10000000,"") | U77: =IF(OR(B77="",C77=""),"",B77+ROW()/10000000) | V77: =IF(U77="","",IF(COUNTIFS(Orders!$C$6:$C$1005,C77,Orders!$U$6:$U$1005,">"&U77)=0,1,0)) | W77: =IF(AND(B77<>"",K77<>"",L77<>"Sent",L77<>"Picked up",L77<>"Cancelled"),IF(N(E77)=0,1,E77),0) | X77: =IF(OR(B77="",D77=""),"",IF(N(E77)=0,1,E77))
B78: 46095 | C78: Ian Price | D78: Wax melts, 6 pack | E78: 3 | G78: 6.95 | H78: =IF(OR(B78="",D78=""),"",IF(N(E78)=0,1,E78)*IFERROR(INDEX(Products!$C$6:$C$105,MATCH(D78,Products!$B$6:$B$105,0)),0)+N(F78)+N(G78)) | I78: 33.95 | J78: =IF(OR(H78="",L78="Cancelled"),"",IF(H78-N(I78)>0.005,H78-N(I78),"")) | K78: 46107 | L78: Sent | M78: Etsy | N78: =IF(OR(H78="",L78="Cancelled"),"",IF(N(E78)=0,1,E78)*IFERROR(INDEX(Products!$E$6:$E$105,MATCH(D78,Products!$B$6:$B$105,0)),0)) | O78: 7.27 | P78: =IF(OR(H78="",L78="Cancelled"),"",ROUND(IFERROR(H78*INDEX(Settings!$C$6:$C$15,MATCH(M78,Settings!$B$6:$B$15,0))+INDEX(Settings!$D$6:$D$15,MATCH(M78,Settings!$B$6:$B$15,0)),0),2)) | Q78: =IF(OR(H78="",L78="Cancelled"),"",H78-N(N78)-N(O78)-N(P78)) | R78: =IF(OR(B78="",K78=""),"",IF(OR(L78="Sent",L78="Picked up"),"Done",IF(L78="Cancelled","Cancelled",IF(K78<TODAY(),"Late by "&(TODAY()-K78)&IF((TODAY()-K78)=1," day"," days"),IF(K78=TODAY(),"Due today","Due in "&(K78-TODAY())&IF((K78-TODAY())=1," day"," days")))))) | T78: =IF(AND(B78<>"",K78<>"",L78<>"Sent",L78<>"Picked up",L78<>"Cancelled"),K78+ROW()/10000000,"") | U78: =IF(OR(B78="",C78=""),"",B78+ROW()/10000000) | V78: =IF(U78="","",IF(COUNTIFS(Orders!$C$6:$C$1005,C78,Orders!$U$6:$U$1005,">"&U78)=0,1,0)) | W78: =IF(AND(B78<>"",K78<>"",L78<>"Sent",L78<>"Picked up",L78<>"Cancelled"),IF(N(E78)=0,1,E78),0) | X78: =IF(OR(B78="",D78=""),"",IF(N(E78)=0,1,E78))
B79: 46096 | C79: Dina Murphy | D79: Wax melts, 6 pack | E79: 1 | H79: =IF(OR(B79="",D79=""),"",IF(N(E79)=0,1,E79)*IFERROR(INDEX(Products!$C$6:$C$105,MATCH(D79,Products!$B$6:$B$105,0)),0)+N(F79)+N(G79)) | I79: 9 | J79: =IF(OR(H79="",L79="Cancelled"),"",IF(H79-N(I79)>0.005,H79-N(I79),"")) | K79: 46102 | L79: Picked up | M79: Instagram | N79: =IF(OR(H79="",L79="Cancelled"),"",IF(N(E79)=0,1,E79)*IFERROR(INDEX(Products!$E$6:$E$105,MATCH(D79,Products!$B$6:$B$105,0)),0)) | P79: =IF(OR(H79="",L79="Cancelled"),"",ROUND(IFERROR(H79*INDEX(Settings!$C$6:$C$15,MATCH(M79,Settings!$B$6:$B$15,0))+INDEX(Settings!$D$6:$D$15,MATCH(M79,Settings!$B$6:$B$15,0)),0),2)) | Q79: =IF(OR(H79="",L79="Cancelled"),"",H79-N(N79)-N(O79)-N(P79)) | R79: =IF(OR(B79="",K79=""),"",IF(OR(L79="Sent",L79="Picked up"),"Done",IF(L79="Cancelled","Cancelled",IF(K79<TODAY(),"Late by "&(TODAY()-K79)&IF((TODAY()-K79)=1," day"," days"),IF(K79=TODAY(),"Due today","Due in "&(K79-TODAY())&IF((K79-TODAY())=1," day"," days")))))) | T79: =IF(AND(B79<>"",K79<>"",L79<>"Sent",L79<>"Picked up",L79<>"Cancelled"),K79+ROW()/10000000,"") | U79: =IF(OR(B79="",C79=""),"",B79+ROW()/10000000) | V79: =IF(U79="","",IF(COUNTIFS(Orders!$C$6:$C$1005,C79,Orders!$U$6:$U$1005,">"&U79)=0,1,0)) | W79: =IF(AND(B79<>"",K79<>"",L79<>"Sent",L79<>"Picked up",L79<>"Cancelled"),IF(N(E79)=0,1,E79),0) | X79: =IF(OR(B79="",D79=""),"",IF(N(E79)=0,1,E79))
B80: 46098 | C80: Jon Gray | D80: Wedding favours, 10 tins | E80: 8 | G80: 6.95 | H80: =IF(OR(B80="",D80=""),"",IF(N(E80)=0,1,E80)*IFERROR(INDEX(Products!$C$6:$C$105,MATCH(D80,Products!$B$6:$B$105,0)),0)+N(F80)+N(G80)) | I80: 486.95 | J80: =IF(OR(H80="",L80="Cancelled"),"",IF(H80-N(I80)>0.005,H80-N(I80),"")) | K80: 46135 | L80: Sent | M80: Etsy | N80: =IF(OR(H80="",L80="Cancelled"),"",IF(N(E80)=0,1,E80)*IFERROR(INDEX(Products!$E$6:$E$105,MATCH(D80,Products!$B$6:$B$105,0)),0)) | O80: 6.73 | P80: =IF(OR(H80="",L80="Cancelled"),"",ROUND(IFERROR(H80*INDEX(Settings!$C$6:$C$15,MATCH(M80,Settings!$B$6:$B$15,0))+INDEX(Settings!$D$6:$D$15,MATCH(M80,Settings!$B$6:$B$15,0)),0),2)) | Q80: =IF(OR(H80="",L80="Cancelled"),"",H80-N(N80)-N(O80)-N(P80)) | R80: =IF(OR(B80="",K80=""),"",IF(OR(L80="Sent",L80="Picked up"),"Done",IF(L80="Cancelled","Cancelled",IF(K80<TODAY(),"Late by "&(TODAY()-K80)&IF((TODAY()-K80)=1," day"," days"),IF(K80=TODAY(),"Due today","Due in "&(K80-TODAY())&IF((K80-TODAY())=1," day"," days")))))) | T80: =IF(AND(B80<>"",K80<>"",L80<>"Sent",L80<>"Picked up",L80<>"Cancelled"),K80+ROW()/10000000,"") | U80: =IF(OR(B80="",C80=""),"",B80+ROW()/10000000) | V80: =IF(U80="","",IF(COUNTIFS(Orders!$C$6:$C$1005,C80,Orders!$U$6:$U$1005,">"&U80)=0,1,0)) | W80: =IF(AND(B80<>"",K80<>"",L80<>"Sent",L80<>"Picked up",L80<>"Cancelled"),IF(N(E80)=0,1,E80),0) | X80: =IF(OR(B80="",D80=""),"",IF(N(E80)=0,1,E80))
B81: 46099 | C81: Paula Mills | D81: Soy candle 8 oz | E81: 2 | G81: 6.95 | H81: =IF(OR(B81="",D81=""),"",IF(N(E81)=0,1,E81)*IFERROR(INDEX(Products!$C$6:$C$105,MATCH(D81,Products!$B$6:$B$105,0)),0)+N(F81)+N(G81)) | I81: 50.95 | J81: =IF(OR(H81="",L81="Cancelled"),"",IF(H81-N(I81)>0.005,H81-N(I81),"")) | K81: 46103 | L81: Sent | M81: Etsy | N81: =IF(OR(H81="",L81="Cancelled"),"",IF(N(E81)=0,1,E81)*IFERROR(INDEX(Products!$E$6:$E$105,MATCH(D81,Products!$B$6:$B$105,0)),0)) | O81: 5.62 | P81: =IF(OR(H81="",L81="Cancelled"),"",ROUND(IFERROR(H81*INDEX(Settings!$C$6:$C$15,MATCH(M81,Settings!$B$6:$B$15,0))+INDEX(Settings!$D$6:$D$15,MATCH(M81,Settings!$B$6:$B$15,0)),0),2)) | Q81: =IF(OR(H81="",L81="Cancelled"),"",H81-N(N81)-N(O81)-N(P81)) | R81: =IF(OR(B81="",K81=""),"",IF(OR(L81="Sent",L81="Picked up"),"Done",IF(L81="Cancelled","Cancelled",IF(K81<TODAY(),"Late by "&(TODAY()-K81)&IF((TODAY()-K81)=1," day"," days"),IF(K81=TODAY(),"Due today","Due in "&(K81-TODAY())&IF((K81-TODAY())=1," day"," days")))))) | T81: =IF(AND(B81<>"",K81<>"",L81<>"Sent",L81<>"Picked up",L81<>"Cancelled"),K81+ROW()/10000000,"") | U81: =IF(OR(B81="",C81=""),"",B81+ROW()/10000000) | V81: =IF(U81="","",IF(COUNTIFS(Orders!$C$6:$C$1005,C81,Orders!$U$6:$U$1005,">"&U81)=0,1,0)) | W81: =IF(AND(B81<>"",K81<>"",L81<>"Sent",L81<>"Picked up",L81<>"Cancelled"),IF(N(E81)=0,1,E81),0) | X81: =IF(OR(B81="",D81=""),"",IF(N(E81)=0,1,E81))
B82: 46100 | C82: Eva Adams | D82: Gift box | E82: 1 | G82: 6.95 | H82: =IF(OR(B82="",D82=""),"",IF(N(E82)=0,1,E82)*IFERROR(INDEX(Products!$C$6:$C$105,MATCH(D82,Products!$B$6:$B$105,0)),0)+N(F82)+N(G82)) | I82: 51.95 | J82: =IF(OR(H82="",L82="Cancelled"),"",IF(H82-N(I82)>0.005,H82-N(I82),"")) | K82: 46106 | L82: Sent | M82: Etsy | N82: =IF(OR(H82="",L82="Cancelled"),"",IF(N(E82)=0,1,E82)*IFERROR(INDEX(Products!$E$6:$E$105,MATCH(D82,Products!$B$6:$B$105,0)),0)) | O82: 6.57 | P82: =IF(OR(H82="",L82="Cancelled"),"",ROUND(IFERROR(H82*INDEX(Settings!$C$6:$C$15,MATCH(M82,Settings!$B$6:$B$15,0))+INDEX(Settings!$D$6:$D$15,MATCH(M82,Settings!$B$6:$B$15,0)),0),2)) | Q82: =IF(OR(H82="",L82="Cancelled"),"",H82-N(N82)-N(O82)-N(P82)) | R82: =IF(OR(B82="",K82=""),"",IF(OR(L82="Sent",L82="Picked up"),"Done",IF(L82="Cancelled","Cancelled",IF(K82<TODAY(),"Late by "&(TODAY()-K82)&IF((TODAY()-K82)=1," day"," days"),IF(K82=TODAY(),"Due today","Due in "&(K82-TODAY())&IF((K82-TODAY())=1," day"," days")))))) | T82: =IF(AND(B82<>"",K82<>"",L82<>"Sent",L82<>"Picked up",L82<>"Cancelled"),K82+ROW()/10000000,"") | U82: =IF(OR(B82="",C82=""),"",B82+ROW()/10000000) | V82: =IF(U82="","",IF(COUNTIFS(Orders!$C$6:$C$1005,C82,Orders!$U$6:$U$1005,">"&U82)=0,1,0)) | W82: =IF(AND(B82<>"",K82<>"",L82<>"Sent",L82<>"Picked up",L82<>"Cancelled"),IF(N(E82)=0,1,E82),0) | X82: =IF(OR(B82="",D82=""),"",IF(N(E82)=0,1,E82))
B83: 46104 | C83: Chris Owens | D83: Soap bar | E83: 2 | G83: 6.95 | H83: =IF(OR(B83="",D83=""),"",IF(N(E83)=0,1,E83)*IFERROR(INDEX(Products!$C$6:$C$105,MATCH(D83,Products!$B$6:$B$105,0)),0)+N(F83)+N(G83)) | I83: 22.95 | J83: =IF(OR(H83="",L83="Cancelled"),"",IF(H83-N(I83)>0.005,H83-N(I83),"")) | K83: 46115 | L83: Sent | M83: Own website | N83: =IF(OR(H83="",L83="Cancelled"),"",IF(N(E83)=0,1,E83)*IFERROR(INDEX(Products!$E$6:$E$105,MATCH(D83,Products!$B$6:$B$105,0)),0)) | O83: 7.75 | P83: =IF(OR(H83="",L83="Cancelled"),"",ROUND(IFERROR(H83*INDEX(Settings!$C$6:$C$15,MATCH(M83,Settings!$B$6:$B$15,0))+INDEX(Settings!$D$6:$D$15,MATCH(M83,Settings!$B$6:$B$15,0)),0),2)) | Q83: =IF(OR(H83="",L83="Cancelled"),"",H83-N(N83)-N(O83)-N(P83)) | R83: =IF(OR(B83="",K83=""),"",IF(OR(L83="Sent",L83="Picked up"),"Done",IF(L83="Cancelled","Cancelled",IF(K83<TODAY(),"Late by "&(TODAY()-K83)&IF((TODAY()-K83)=1," day"," days"),IF(K83=TODAY(),"Due today","Due in "&(K83-TODAY())&IF((K83-TODAY())=1," day"," days")))))) | T83: =IF(AND(B83<>"",K83<>"",L83<>"Sent",L83<>"Picked up",L83<>"Cancelled"),K83+ROW()/10000000,"") | U83: =IF(OR(B83="",C83=""),"",B83+ROW()/10000000) | V83: =IF(U83="","",IF(COUNTIFS(Orders!$C$6:$C$1005,C83,Orders!$U$6:$U$1005,">"&U83)=0,1,0)) | W83: =IF(AND(B83<>"",K83<>"",L83<>"Sent",L83<>"Picked up",L83<>"Cancelled"),IF(N(E83)=0,1,E83),0) | X83: =IF(OR(B83="",D83=""),"",IF(N(E83)=0,1,E83))
B84: 46104 | C84: Holly Cox | D84: Soy candle 8 oz | E84: 2 | H84: =IF(OR(B84="",D84=""),"",IF(N(E84)=0,1,E84)*IFERROR(INDEX(Products!$C$6:$C$105,MATCH(D84,Products!$B$6:$B$105,0)),0)+N(F84)+N(G84)) | I84: 44 | J84: =IF(OR(H84="",L84="Cancelled"),"",IF(H84-N(I84)>0.005,H84-N(I84),"")) | K84: 46114 | L84: Picked up | M84: Friends and family | N84: =IF(OR(H84="",L84="Cancelled"),"",IF(N(E84)=0,1,E84)*IFERROR(INDEX(Products!$E$6:$E$105,MATCH(D84,Products!$B$6:$B$105,0)),0)) | P84: =IF(OR(H84="",L84="Cancelled"),"",ROUND(IFERROR(H84*INDEX(Settings!$C$6:$C$15,MATCH(M84,Settings!$B$6:$B$15,0))+INDEX(Settings!$D$6:$D$15,MATCH(M84,Settings!$B$6:$B$15,0)),0),2)) | Q84: =IF(OR(H84="",L84="Cancelled"),"",H84-N(N84)-N(O84)-N(P84)) | R84: =IF(OR(B84="",K84=""),"",IF(OR(L84="Sent",L84="Picked up"),"Done",IF(L84="Cancelled","Cancelled",IF(K84<TODAY(),"Late by "&(TODAY()-K84)&IF((TODAY()-K84)=1," day"," days"),IF(K84=TODAY(),"Due today","Due in "&(K84-TODAY())&IF((K84-TODAY())=1," day"," days")))))) | T84: =IF(AND(B84<>"",K84<>"",L84<>"Sent",L84<>"Picked up",L84<>"Cancelled"),K84+ROW()/10000000,"") | U84: =IF(OR(B84="",C84=""),"",B84+ROW()/10000000) | V84: =IF(U84="","",IF(COUNTIFS(Orders!$C$6:$C$1005,C84,Orders!$U$6:$U$1005,">"&U84)=0,1,0)) | W84: =IF(AND(B84<>"",K84<>"",L84<>"Sent",L84<>"Picked up",L84<>"Cancelled"),IF(N(E84)=0,1,E84),0) | X84: =IF(OR(B84="",D84=""),"",IF(N(E84)=0,1,E84))
B85: 46105 | C85: Paula Mills | D85: Wax melts, 6 pack | E85: 1 | H85: =IF(OR(B85="",D85=""),"",IF(N(E85)=0,1,E85)*IFERROR(INDEX(Products!$C$6:$C$105,MATCH(D85,Products!$B$6:$B$105,0)),0)+N(F85)+N(G85)) | I85: 9 | J85: =IF(OR(H85="",L85="Cancelled"),"",IF(H85-N(I85)>0.005,H85-N(I85),"")) | K85: 46115 | L85: Picked up | M85: Craft market | N85: =IF(OR(H85="",L85="Cancelled"),"",IF(N(E85)=0,1,E85)*IFERROR(INDEX(Products!$E$6:$E$105,MATCH(D85,Products!$B$6:$B$105,0)),0)) | P85: =IF(OR(H85="",L85="Cancelled"),"",ROUND(IFERROR(H85*INDEX(Settings!$C$6:$C$15,MATCH(M85,Settings!$B$6:$B$15,0))+INDEX(Settings!$D$6:$D$15,MATCH(M85,Settings!$B$6:$B$15,0)),0),2)) | Q85: =IF(OR(H85="",L85="Cancelled"),"",H85-N(N85)-N(O85)-N(P85)) | R85: =IF(OR(B85="",K85=""),"",IF(OR(L85="Sent",L85="Picked up"),"Done",IF(L85="Cancelled","Cancelled",IF(K85<TODAY(),"Late by "&(TODAY()-K85)&IF((TODAY()-K85)=1," day"," days"),IF(K85=TODAY(),"Due today","Due in "&(K85-TODAY())&IF((K85-TODAY())=1," day"," days")))))) | T85: =IF(AND(B85<>"",K85<>"",L85<>"Sent",L85<>"Picked up",L85<>"Cancelled"),K85+ROW()/10000000,"") | U85: =IF(OR(B85="",C85=""),"",B85+ROW()/10000000) | V85: =IF(U85="","",IF(COUNTIFS(Orders!$C$6:$C$1005,C85,Orders!$U$6:$U$1005,">"&U85)=0,1,0)) | W85: =IF(AND(B85<>"",K85<>"",L85<>"Sent",L85<>"Picked up",L85<>"Cancelled"),IF(N(E85)=0,1,E85),0) | X85: =IF(OR(B85="",D85=""),"",IF(N(E85)=0,1,E85))
B86: 46106 | C86: Adam Cox | D86: Soy candle 16 oz | E86: 4 | H86: =IF(OR(B86="",D86=""),"",IF(N(E86)=0,1,E86)*IFERROR(INDEX(Products!$C$6:$C$105,MATCH(D86,Products!$B$6:$B$105,0)),0)+N(F86)+N(G86)) | I86: 136 | J86: =IF(OR(H86="",L86="Cancelled"),"",IF(H86-N(I86)>0.005,H86-N(I86),"")) | K86: 46116 | L86: Picked up | M86: Craft market | N86: =IF(OR(H86="",L86="Cancelled"),"",IF(N(E86)=0,1,E86)*IFERROR(INDEX(Products!$E$6:$E$105,MATCH(D86,Products!$B$6:$B$105,0)),0)) | P86: =IF(OR(H86="",L86="Cancelled"),"",ROUND(IFERROR(H86*INDEX(Settings!$C$6:$C$15,MATCH(M86,Settings!$B$6:$B$15,0))+INDEX(Settings!$D$6:$D$15,MATCH(M86,Settings!$B$6:$B$15,0)),0),2)) | Q86: =IF(OR(H86="",L86="Cancelled"),"",H86-N(N86)-N(O86)-N(P86)) | R86: =IF(OR(B86="",K86=""),"",IF(OR(L86="Sent",L86="Picked up"),"Done",IF(L86="Cancelled","Cancelled",IF(K86<TODAY(),"Late by "&(TODAY()-K86)&IF((TODAY()-K86)=1," day"," days"),IF(K86=TODAY(),"Due today","Due in "&(K86-TODAY())&IF((K86-TODAY())=1," day"," days")))))) | T86: =IF(AND(B86<>"",K86<>"",L86<>"Sent",L86<>"Picked up",L86<>"Cancelled"),K86+ROW()/10000000,"") | U86: =IF(OR(B86="",C86=""),"",B86+ROW()/10000000) | V86: =IF(U86="","",IF(COUNTIFS(Orders!$C$6:$C$1005,C86,Orders!$U$6:$U$1005,">"&U86)=0,1,0)) | W86: =IF(AND(B86<>"",K86<>"",L86<>"Sent",L86<>"Picked up",L86<>"Cancelled"),IF(N(E86)=0,1,E86),0) | X86: =IF(OR(B86="",D86=""),"",IF(N(E86)=0,1,E86))
B87: 46107 | C87: Adam King | D87: Soy candle 8 oz | E87: 2 | G87: 6.95 | H87: =IF(OR(B87="",D87=""),"",IF(N(E87)=0,1,E87)*IFERROR(INDEX(Products!$C$6:$C$105,MATCH(D87,Products!$B$6:$B$105,0)),0)+N(F87)+N(G87)) | I87: 50.95 | J87: =IF(OR(H87="",L87="Cancelled"),"",IF(H87-N(I87)>0.005,H87-N(I87),"")) | K87: 46118 | L87: Sent | M87: Own website | N87: =IF(OR(H87="",L87="Cancelled"),"",IF(N(E87)=0,1,E87)*IFERROR(INDEX(Products!$E$6:$E$105,MATCH(D87,Products!$B$6:$B$105,0)),0)) | O87: 7.18 | P87: =IF(OR(H87="",L87="Cancelled"),"",ROUND(IFERROR(H87*INDEX(Settings!$C$6:$C$15,MATCH(M87,Settings!$B$6:$B$15,0))+INDEX(Settings!$D$6:$D$15,MATCH(M87,Settings!$B$6:$B$15,0)),0),2)) | Q87: =IF(OR(H87="",L87="Cancelled"),"",H87-N(N87)-N(O87)-N(P87)) | R87: =IF(OR(B87="",K87=""),"",IF(OR(L87="Sent",L87="Picked up"),"Done",IF(L87="Cancelled","Cancelled",IF(K87<TODAY(),"Late by "&(TODAY()-K87)&IF((TODAY()-K87)=1," day"," days"),IF(K87=TODAY(),"Due today","Due in "&(K87-TODAY())&IF((K87-TODAY())=1," day"," days")))))) | T87: =IF(AND(B87<>"",K87<>"",L87<>"Sent",L87<>"Picked up",L87<>"Cancelled"),K87+ROW()/10000000,"") | U87: =IF(OR(B87="",C87=""),"",B87+ROW()/10000000) | V87: =IF(U87="","",IF(COUNTIFS(Orders!$C$6:$C$1005,C87,Orders!$U$6:$U$1005,">"&U87)=0,1,0)) | W87: =IF(AND(B87<>"",K87<>"",L87<>"Sent",L87<>"Picked up",L87<>"Cancelled"),IF(N(E87)=0,1,E87),0) | X87: =IF(OR(B87="",D87=""),"",IF(N(E87)=0,1,E87))
B88: 46109 | C88: Jon Gray | D88: Soy candle 8 oz | E88: 1 | H88: =IF(OR(B88="",D88=""),"",IF(N(E88)=0,1,E88)*IFERROR(INDEX(Products!$C$6:$C$105,MATCH(D88,Products!$B$6:$B$105,0)),0)+N(F88)+N(G88)) | I88: 22 | J88: =IF(OR(H88="",L88="Cancelled"),"",IF(H88-N(I88)>0.005,H88-N(I88),"")) | K88: 46117 | L88: Picked up | M88: Friends and family | N88: =IF(OR(H88="",L88="Cancelled"),"",IF(N(E88)=0,1,E88)*IFERROR(INDEX(Products!$E$6:$E$105,MATCH(D88,Products!$B$6:$B$105,0)),0)) | P88: =IF(OR(H88="",L88="Cancelled"),"",ROUND(IFERROR(H88*INDEX(Settings!$C$6:$C$15,MATCH(M88,Settings!$B$6:$B$15,0))+INDEX(Settings!$D$6:$D$15,MATCH(M88,Settings!$B$6:$B$15,0)),0),2)) | Q88: =IF(OR(H88="",L88="Cancelled"),"",H88-N(N88)-N(O88)-N(P88)) | R88: =IF(OR(B88="",K88=""),"",IF(OR(L88="Sent",L88="Picked up"),"Done",IF(L88="Cancelled","Cancelled",IF(K88<TODAY(),"Late by "&(TODAY()-K88)&IF((TODAY()-K88)=1," day"," days"),IF(K88=TODAY(),"Due today","Due in "&(K88-TODAY())&IF((K88-TODAY())=1," day"," days")))))) | T88: =IF(AND(B88<>"",K88<>"",L88<>"Sent",L88<>"Picked up",L88<>"Cancelled"),K88+ROW()/10000000,"") | U88: =IF(OR(B88="",C88=""),"",B88+ROW()/10000000) | V88: =IF(U88="","",IF(COUNTIFS(Orders!$C$6:$C$1005,C88,Orders!$U$6:$U$1005,">"&U88)=0,1,0)) | W88: =IF(AND(B88<>"",K88<>"",L88<>"Sent",L88<>"Picked up",L88<>"Cancelled"),IF(N(E88)=0,1,E88),0) | X88: =IF(OR(B88="",D88=""),"",IF(N(E88)=0,1,E88))
B89: 46109 | C89: Dina Cole | D89: Wax melts, 6 pack | E89: 2 | G89: 6.95 | H89: =IF(OR(B89="",D89=""),"",IF(N(E89)=0,1,E89)*IFERROR(INDEX(Products!$C$6:$C$105,MATCH(D89,Products!$B$6:$B$105,0)),0)+N(F89)+N(G89)) | I89: 24.95 | J89: =IF(OR(H89="",L89="Cancelled"),"",IF(H89-N(I89)>0.005,H89-N(I89),"")) | K89: 46116 | L89: Sent | M89: Etsy | N89: =IF(OR(H89="",L89="Cancelled"),"",IF(N(E89)=0,1,E89)*IFERROR(INDEX(Products!$E$6:$E$105,MATCH(D89,Products!$B$6:$B$105,0)),0)) | O89: 7.39 | P89: =IF(OR(H89="",L89="Cancelled"),"",ROUND(IFERROR(H89*INDEX(Settings!$C$6:$C$15,MATCH(M89,Settings!$B$6:$B$15,0))+INDEX(Settings!$D$6:$D$15,MATCH(M89,Settings!$B$6:$B$15,0)),0),2)) | Q89: =IF(OR(H89="",L89="Cancelled"),"",H89-N(N89)-N(O89)-N(P89)) | R89: =IF(OR(B89="",K89=""),"",IF(OR(L89="Sent",L89="Picked up"),"Done",IF(L89="Cancelled","Cancelled",IF(K89<TODAY(),"Late by "&(TODAY()-K89)&IF((TODAY()-K89)=1," day"," days"),IF(K89=TODAY(),"Due today","Due in "&(K89-TODAY())&IF((K89-TODAY())=1," day"," days")))))) | T89: =IF(AND(B89<>"",K89<>"",L89<>"Sent",L89<>"Picked up",L89<>"Cancelled"),K89+ROW()/10000000,"") | U89: =IF(OR(B89="",C89=""),"",B89+ROW()/10000000) | V89: =IF(U89="","",IF(COUNTIFS(Orders!$C$6:$C$1005,C89,Orders!$U$6:$U$1005,">"&U89)=0,1,0)) | W89: =IF(AND(B89<>"",K89<>"",L89<>"Sent",L89<>"Picked up",L89<>"Cancelled"),IF(N(E89)=0,1,E89),0) | X89: =IF(OR(B89="",D89=""),"",IF(N(E89)=0,1,E89))
B90: 46110 | C90: Holly Cox | D90: Soap bar | E90: 1 | G90: 6.95 | H90: =IF(OR(B90="",D90=""),"",IF(N(E90)=0,1,E90)*IFERROR(INDEX(Products!$C$6:$C$105,MATCH(D90,Products!$B$6:$B$105,0)),0)+N(F90)+N(G90)) | I90: 14.95 | J90: =IF(OR(H90="",L90="Cancelled"),"",IF(H90-N(I90)>0.005,H90-N(I90),"")) | K90: 46115 | L90: Sent | M90: Etsy | N90: =IF(OR(H90="",L90="Cancelled"),"",IF(N(E90)=0,1,E90)*IFERROR(INDEX(Products!$E$6:$E$105,MATCH(D90,Products!$B$6:$B$105,0)),0)) | O90: 7.56 | P90: =IF(OR(H90="",L90="Cancelled"),"",ROUND(IFERROR(H90*INDEX(Settings!$C$6:$C$15,MATCH(M90,Settings!$B$6:$B$15,0))+INDEX(Settings!$D$6:$D$15,MATCH(M90,Settings!$B$6:$B$15,0)),0),2)) | Q90: =IF(OR(H90="",L90="Cancelled"),"",H90-N(N90)-N(O90)-N(P90)) | R90: =IF(OR(B90="",K90=""),"",IF(OR(L90="Sent",L90="Picked up"),"Done",IF(L90="Cancelled","Cancelled",IF(K90<TODAY(),"Late by "&(TODAY()-K90)&IF((TODAY()-K90)=1," day"," days"),IF(K90=TODAY(),"Due today","Due in "&(K90-TODAY())&IF((K90-TODAY())=1," day"," days")))))) | T90: =IF(AND(B90<>"",K90<>"",L90<>"Sent",L90<>"Picked up",L90<>"Cancelled"),K90+ROW()/10000000,"") | U90: =IF(OR(B90="",C90=""),"",B90+ROW()/10000000) | V90: =IF(U90="","",IF(COUNTIFS(Orders!$C$6:$C$1005,C90,Orders!$U$6:$U$1005,">"&U90)=0,1,0)) | W90: =IF(AND(B90<>"",K90<>"",L90<>"Sent",L90<>"Picked up",L90<>"Cancelled"),IF(N(E90)=0,1,E90),0) | X90: =IF(OR(B90="",D90=""),"",IF(N(E90)=0,1,E90))
B91: 46111 | C91: Chris Owens | D91: Soy candle 8 oz | E91: 1 | H91: =IF(OR(B91="",D91=""),"",IF(N(E91)=0,1,E91)*IFERROR(INDEX(Products!$C$6:$C$105,MATCH(D91,Products!$B$6:$B$105,0)),0)+N(F91)+N(G91)) | I91: 22 | J91: =IF(OR(H91="",L91="Cancelled"),"",IF(H91-N(I91)>0.005,H91-N(I91),"")) | K91: 46116 | L91: Picked up | M91: Craft market | N91: =IF(OR(H91="",L91="Cancelled"),"",IF(N(E91)=0,1,E91)*IFERROR(INDEX(Products!$E$6:$E$105,MATCH(D91,Products!$B$6:$B$105,0)),0)) | P91: =IF(OR(H91="",L91="Cancelled"),"",ROUND(IFERROR(H91*INDEX(Settings!$C$6:$C$15,MATCH(M91,Settings!$B$6:$B$15,0))+INDEX(Settings!$D$6:$D$15,MATCH(M91,Settings!$B$6:$B$15,0)),0),2)) | Q91: =IF(OR(H91="",L91="Cancelled"),"",H91-N(N91)-N(O91)-N(P91)) | R91: =IF(OR(B91="",K91=""),"",IF(OR(L91="Sent",L91="Picked up"),"Done",IF(L91="Cancelled","Cancelled",IF(K91<TODAY(),"Late by "&(TODAY()-K91)&IF((TODAY()-K91)=1," day"," days"),IF(K91=TODAY(),"Due today","Due in "&(K91-TODAY())&IF((K91-TODAY())=1," day"," days")))))) | T91: =IF(AND(B91<>"",K91<>"",L91<>"Sent",L91<>"Picked up",L91<>"Cancelled"),K91+ROW()/10000000,"") | U91: =IF(OR(B91="",C91=""),"",B91+ROW()/10000000) | V91: =IF(U91="","",IF(COUNTIFS(Orders!$C$6:$C$1005,C91,Orders!$U$6:$U$1005,">"&U91)=0,1,0)) | W91: =IF(AND(B91<>"",K91<>"",L91<>"Sent",L91<>"Picked up",L91<>"Cancelled"),IF(N(E91)=0,1,E91),0) | X91: =IF(OR(B91="",D91=""),"",IF(N(E91)=0,1,E91))
B92: 46111 | C92: Paula Fox | D92: Soy candle 8 oz | E92: 1 | G92: 6.95 | H92: =IF(OR(B92="",D92=""),"",IF(N(E92)=0,1,E92)*IFERROR(INDEX(Products!$C$6:$C$105,MATCH(D92,Products!$B$6:$B$105,0)),0)+N(F92)+N(G92)) | I92: 28.95 | J92: =IF(OR(H92="",L92="Cancelled"),"",IF(H92-N(I92)>0.005,H92-N(I92),"")) | K92: 46123 | L92: Sent | M92: Own website | N92: =IF(OR(H92="",L92="Cancelled"),"",IF(N(E92)=0,1,E92)*IFERROR(INDEX(Products!$E$6:$E$105,MATCH(D92,Products!$B$6:$B$105,0)),0)) | O92: 7.66 | P92: =IF(OR(H92="",L92="Cancelled"),"",ROUND(IFERROR(H92*INDEX(Settings!$C$6:$C$15,MATCH(M92,Settings!$B$6:$B$15,0))+INDEX(Settings!$D$6:$D$15,MATCH(M92,Settings!$B$6:$B$15,0)),0),2)) | Q92: =IF(OR(H92="",L92="Cancelled"),"",H92-N(N92)-N(O92)-N(P92)) | R92: =IF(OR(B92="",K92=""),"",IF(OR(L92="Sent",L92="Picked up"),"Done",IF(L92="Cancelled","Cancelled",IF(K92<TODAY(),"Late by "&(TODAY()-K92)&IF((TODAY()-K92)=1," day"," days"),IF(K92=TODAY(),"Due today","Due in "&(K92-TODAY())&IF((K92-TODAY())=1," day"," days")))))) | T92: =IF(AND(B92<>"",K92<>"",L92<>"Sent",L92<>"Picked up",L92<>"Cancelled"),K92+ROW()/10000000,"") | U92: =IF(OR(B92="",C92=""),"",B92+ROW()/10000000) | V92: =IF(U92="","",IF(COUNTIFS(Orders!$C$6:$C$1005,C92,Orders!$U$6:$U$1005,">"&U92)=0,1,0)) | W92: =IF(AND(B92<>"",K92<>"",L92<>"Sent",L92<>"Picked up",L92<>"Cancelled"),IF(N(E92)=0,1,E92),0) | X92: =IF(OR(B92="",D92=""),"",IF(N(E92)=0,1,E92))
B93: 46112 | C93: Megan Murphy | D93: Soy candle 16 oz | E93: 1 | H93: =IF(OR(B93="",D93=""),"",IF(N(E93)=0,1,E93)*IFERROR(INDEX(Products!$C$6:$C$105,MATCH(D93,Products!$B$6:$B$105,0)),0)+N(F93)+N(G93)) | I93: 34 | J93: =IF(OR(H93="",L93="Cancelled"),"",IF(H93-N(I93)>0.005,H93-N(I93),"")) | K93: 46122 | L93: Picked up | M93: Friends and family | N93: =IF(OR(H93="",L93="Cancelled"),"",IF(N(E93)=0,1,E93)*IFERROR(INDEX(Products!$E$6:$E$105,MATCH(D93,Products!$B$6:$B$105,0)),0)) | P93: =IF(OR(H93="",L93="Cancelled"),"",ROUND(IFERROR(H93*INDEX(Settings!$C$6:$C$15,MATCH(M93,Settings!$B$6:$B$15,0))+INDEX(Settings!$D$6:$D$15,MATCH(M93,Settings!$B$6:$B$15,0)),0),2)) | Q93: =IF(OR(H93="",L93="Cancelled"),"",H93-N(N93)-N(O93)-N(P93)) | R93: =IF(OR(B93="",K93=""),"",IF(OR(L93="Sent",L93="Picked up"),"Done",IF(L93="Cancelled","Cancelled",IF(K93<TODAY(),"Late by "&(TODAY()-K93)&IF((TODAY()-K93)=1," day"," days"),IF(K93=TODAY(),"Due today","Due in "&(K93-TODAY())&IF((K93-TODAY())=1," day"," days")))))) | T93: =IF(AND(B93<>"",K93<>"",L93<>"Sent",L93<>"Picked up",L93<>"Cancelled"),K93+ROW()/10000000,"") | U93: =IF(OR(B93="",C93=""),"",B93+ROW()/10000000) | V93: =IF(U93="","",IF(COUNTIFS(Orders!$C$6:$C$1005,C93,Orders!$U$6:$U$1005,">"&U93)=0,1,0)) | W93: =IF(AND(B93<>"",K93<>"",L93<>"Sent",L93<>"Picked up",L93<>"Cancelled"),IF(N(E93)=0,1,E93),0) | X93: =IF(OR(B93="",D93=""),"",IF(N(E93)=0,1,E93))
B94: 46112 | C94: Jade Reed | D94: Soap bar | E94: 1 | H94: =IF(OR(B94="",D94=""),"",IF(N(E94)=0,1,E94)*IFERROR(INDEX(Products!$C$6:$C$105,MATCH(D94,Products!$B$6:$B$105,0)),0)+N(F94)+N(G94)) | I94: 8 | J94: =IF(OR(H94="",L94="Cancelled"),"",IF(H94-N(I94)>0.005,H94-N(I94),"")) | K94: 46119 | L94: Cancelled | M94: Friends and family | N94: =IF(OR(H94="",L94="Cancelled"),"",IF(N(E94)=0,1,E94)*IFERROR(INDEX(Products!$E$6:$E$105,MATCH(D94,Products!$B$6:$B$105,0)),0)) | P94: =IF(OR(H94="",L94="Cancelled"),"",ROUND(IFERROR(H94*INDEX(Settings!$C$6:$C$15,MATCH(M94,Settings!$B$6:$B$15,0))+INDEX(Settings!$D$6:$D$15,MATCH(M94,Settings!$B$6:$B$15,0)),0),2)) | Q94: =IF(OR(H94="",L94="Cancelled"),"",H94-N(N94)-N(O94)-N(P94)) | R94: =IF(OR(B94="",K94=""),"",IF(OR(L94="Sent",L94="Picked up"),"Done",IF(L94="Cancelled","Cancelled",IF(K94<TODAY(),"Late by "&(TODAY()-K94)&IF((TODAY()-K94)=1," day"," days"),IF(K94=TODAY(),"Due today","Due in "&(K94-TODAY())&IF((K94-TODAY())=1," day"," days")))))) | T94: =IF(AND(B94<>"",K94<>"",L94<>"Sent",L94<>"Picked up",L94<>"Cancelled"),K94+ROW()/10000000,"") | U94: =IF(OR(B94="",C94=""),"",B94+ROW()/10000000) | V94: =IF(U94="","",IF(COUNTIFS(Orders!$C$6:$C$1005,C94,Orders!$U$6:$U$1005,">"&U94)=0,1,0)) | W94: =IF(AND(B94<>"",K94<>"",L94<>"Sent",L94<>"Picked up",L94<>"Cancelled"),IF(N(E94)=0,1,E94),0) | X94: =IF(OR(B94="",D94=""),"",IF(N(E94)=0,1,E94))
B95: 46113 | C95: Paula Fox | D95: Soy candle 8 oz | E95: 2 | G95: 6.95 | H95: =IF(OR(B95="",D95=""),"",IF(N(E95)=0,1,E95)*IFERROR(INDEX(Products!$C$6:$C$105,MATCH(D95,Products!$B$6:$B$105,0)),0)+N(F95)+N(G95)) | I95: 50.95 | J95: =IF(OR(H95="",L95="Cancelled"),"",IF(H95-N(I95)>0.005,H95-N(I95),"")) | K95: 46123 | L95: Sent | M95: Own website | N95: =IF(OR(H95="",L95="Cancelled"),"",IF(N(E95)=0,1,E95)*IFERROR(INDEX(Products!$E$6:$E$105,MATCH(D95,Products!$B$6:$B$105,0)),0)) | O95: 5.44 | P95: =IF(OR(H95="",L95="Cancelled"),"",ROUND(IFERROR(H95*INDEX(Settings!$C$6:$C$15,MATCH(M95,Settings!$B$6:$B$15,0))+INDEX(Settings!$D$6:$D$15,MATCH(M95,Settings!$B$6:$B$15,0)),0),2)) | Q95: =IF(OR(H95="",L95="Cancelled"),"",H95-N(N95)-N(O95)-N(P95)) | R95: =IF(OR(B95="",K95=""),"",IF(OR(L95="Sent",L95="Picked up"),"Done",IF(L95="Cancelled","Cancelled",IF(K95<TODAY(),"Late by "&(TODAY()-K95)&IF((TODAY()-K95)=1," day"," days"),IF(K95=TODAY(),"Due today","Due in "&(K95-TODAY())&IF((K95-TODAY())=1," day"," days")))))) | T95: =IF(AND(B95<>"",K95<>"",L95<>"Sent",L95<>"Picked up",L95<>"Cancelled"),K95+ROW()/10000000,"") | U95: =IF(OR(B95="",C95=""),"",B95+ROW()/10000000) | V95: =IF(U95="","",IF(COUNTIFS(Orders!$C$6:$C$1005,C95,Orders!$U$6:$U$1005,">"&U95)=0,1,0)) | W95: =IF(AND(B95<>"",K95<>"",L95<>"Sent",L95<>"Picked up",L95<>"Cancelled"),IF(N(E95)=0,1,E95),0) | X95: =IF(OR(B95="",D95=""),"",IF(N(E95)=0,1,E95))
B96: 46114 | C96: Iris Cole | D96: Gift box | E96: 4 | H96: =IF(OR(B96="",D96=""),"",IF(N(E96)=0,1,E96)*IFERROR(INDEX(Products!$C$6:$C$105,MATCH(D96,Products!$B$6:$B$105,0)),0)+N(F96)+N(G96)) | I96: 180 | J96: =IF(OR(H96="",L96="Cancelled"),"",IF(H96-N(I96)>0.005,H96-N(I96),"")) | K96: 46125 | L96: Picked up | M96: Craft market | N96: =IF(OR(H96="",L96="Cancelled"),"",IF(N(E96)=0,1,E96)*IFERROR(INDEX(Products!$E$6:$E$105,MATCH(D96,Products!$B$6:$B$105,0)),0)) | P96: =IF(OR(H96="",L96="Cancelled"),"",ROUND(IFERROR(H96*INDEX(Settings!$C$6:$C$15,MATCH(M96,Settings!$B$6:$B$15,0))+INDEX(Settings!$D$6:$D$15,MATCH(M96,Settings!$B$6:$B$15,0)),0),2)) | Q96: =IF(OR(H96="",L96="Cancelled"),"",H96-N(N96)-N(O96)-N(P96)) | R96: =IF(OR(B96="",K96=""),"",IF(OR(L96="Sent",L96="Picked up"),"Done",IF(L96="Cancelled","Cancelled",IF(K96<TODAY(),"Late by "&(TODAY()-K96)&IF((TODAY()-K96)=1," day"," days"),IF(K96=TODAY(),"Due today","Due in "&(K96-TODAY())&IF((K96-TODAY())=1," day"," days")))))) | T96: =IF(AND(B96<>"",K96<>"",L96<>"Sent",L96<>"Picked up",L96<>"Cancelled"),K96+ROW()/10000000,"") | U96: =IF(OR(B96="",C96=""),"",B96+ROW()/10000000) | V96: =IF(U96="","",IF(COUNTIFS(Orders!$C$6:$C$1005,C96,Orders!$U$6:$U$1005,">"&U96)=0,1,0)) | W96: =IF(AND(B96<>"",K96<>"",L96<>"Sent",L96<>"Picked up",L96<>"Cancelled"),IF(N(E96)=0,1,E96),0) | X96: =IF(OR(B96="",D96=""),"",IF(N(E96)=0,1,E96))
B97: 46115 | C97: Holly Cox | D97: Soy candle 8 oz | E97: 1 | F97: 5 | G97: 6.95 | H97: =IF(OR(B97="",D97=""),"",IF(N(E97)=0,1,E97)*IFERROR(INDEX(Products!$C$6:$C$105,MATCH(D97,Products!$B$6:$B$105,0)),0)+N(F97)+N(G97)) | I97: 33.95 | J97: =IF(OR(H97="",L97="Cancelled"),"",IF(H97-N(I97)>0.005,H97-N(I97),"")) | K97: 46127 | L97: Sent | M97: Etsy | N97: =IF(OR(H97="",L97="Cancelled"),"",IF(N(E97)=0,1,E97)*IFERROR(INDEX(Products!$E$6:$E$105,MATCH(D97,Products!$B$6:$B$105,0)),0)) | O97: 5.29 | P97: =IF(OR(H97="",L97="Cancelled"),"",ROUND(IFERROR(H97*INDEX(Settings!$C$6:$C$15,MATCH(M97,Settings!$B$6:$B$15,0))+INDEX(Settings!$D$6:$D$15,MATCH(M97,Settings!$B$6:$B$15,0)),0),2)) | Q97: =IF(OR(H97="",L97="Cancelled"),"",H97-N(N97)-N(O97)-N(P97)) | R97: =IF(OR(B97="",K97=""),"",IF(OR(L97="Sent",L97="Picked up"),"Done",IF(L97="Cancelled","Cancelled",IF(K97<TODAY(),"Late by "&(TODAY()-K97)&IF((TODAY()-K97)=1," day"," days"),IF(K97=TODAY(),"Due today","Due in "&(K97-TODAY())&IF((K97-TODAY())=1," day"," days")))))) | S97: Custom label | T97: =IF(AND(B97<>"",K97<>"",L97<>"Sent",L97<>"Picked up",L97<>"Cancelled"),K97+ROW()/10000000,"") | U97: =IF(OR(B97="",C97=""),"",B97+ROW()/10000000) | V97: =IF(U97="","",IF(COUNTIFS(Orders!$C$6:$C$1005,C97,Orders!$U$6:$U$1005,">"&U97)=0,1,0)) | W97: =IF(AND(B97<>"",K97<>"",L97<>"Sent",L97<>"Picked up",L97<>"Cancelled"),IF(N(E97)=0,1,E97),0) | X97: =IF(OR(B97="",D97=""),"",IF(N(E97)=0,1,E97))
B98: 46115 | C98: Nora Lewis | D98: Soy candle 16 oz | E98: 2 | H98: =IF(OR(B98="",D98=""),"",IF(N(E98)=0,1,E98)*IFERROR(INDEX(Products!$C$6:$C$105,MATCH(D98,Products!$B$6:$B$105,0)),0)+N(F98)+N(G98)) | I98: 68 | J98: =IF(OR(H98="",L98="Cancelled"),"",IF(H98-N(I98)>0.005,H98-N(I98),"")) | K98: 46120 | L98: Picked up | M98: Friends and family | N98: =IF(OR(H98="",L98="Cancelled"),"",IF(N(E98)=0,1,E98)*IFERROR(INDEX(Products!$E$6:$E$105,MATCH(D98,Products!$B$6:$B$105,0)),0)) | P98: =IF(OR(H98="",L98="Cancelled"),"",ROUND(IFERROR(H98*INDEX(Settings!$C$6:$C$15,MATCH(M98,Settings!$B$6:$B$15,0))+INDEX(Settings!$D$6:$D$15,MATCH(M98,Settings!$B$6:$B$15,0)),0),2)) | Q98: =IF(OR(H98="",L98="Cancelled"),"",H98-N(N98)-N(O98)-N(P98)) | R98: =IF(OR(B98="",K98=""),"",IF(OR(L98="Sent",L98="Picked up"),"Done",IF(L98="Cancelled","Cancelled",IF(K98<TODAY(),"Late by "&(TODAY()-K98)&IF((TODAY()-K98)=1," day"," days"),IF(K98=TODAY(),"Due today","Due in "&(K98-TODAY())&IF((K98-TODAY())=1," day"," days")))))) | T98: =IF(AND(B98<>"",K98<>"",L98<>"Sent",L98<>"Picked up",L98<>"Cancelled"),K98+ROW()/10000000,"") | U98: =IF(OR(B98="",C98=""),"",B98+ROW()/10000000) | V98: =IF(U98="","",IF(COUNTIFS(Orders!$C$6:$C$1005,C98,Orders!$U$6:$U$1005,">"&U98)=0,1,0)) | W98: =IF(AND(B98<>"",K98<>"",L98<>"Sent",L98<>"Picked up",L98<>"Cancelled"),IF(N(E98)=0,1,E98),0) | X98: =IF(OR(B98="",D98=""),"",IF(N(E98)=0,1,E98))
B99: 46116 | C99: Paula Mills | D99: Soap bar | E99: 1 | H99: =IF(OR(B99="",D99=""),"",IF(N(E99)=0,1,E99)*IFERROR(INDEX(Products!$C$6:$C$105,MATCH(D99,Products!$B$6:$B$105,0)),0)+N(F99)+N(G99)) | I99: 8 | J99: =IF(OR(H99="",L99="Cancelled"),"",IF(H99-N(I99)>0.005,H99-N(I99),"")) | K99: 46120 | L99: Picked up | M99: Instagram | N99: =IF(OR(H99="",L99="Cancelled"),"",IF(N(E99)=0,1,E99)*IFERROR(INDEX(Products!$E$6:$E$105,MATCH(D99,Products!$B$6:$B$105,0)),0)) | P99: =IF(OR(H99="",L99="Cancelled"),"",ROUND(IFERROR(H99*INDEX(Settings!$C$6:$C$15,MATCH(M99,Settings!$B$6:$B$15,0))+INDEX(Settings!$D$6:$D$15,MATCH(M99,Settings!$B$6:$B$15,0)),0),2)) | Q99: =IF(OR(H99="",L99="Cancelled"),"",H99-N(N99)-N(O99)-N(P99)) | R99: =IF(OR(B99="",K99=""),"",IF(OR(L99="Sent",L99="Picked up"),"Done",IF(L99="Cancelled","Cancelled",IF(K99<TODAY(),"Late by "&(TODAY()-K99)&IF((TODAY()-K99)=1," day"," days"),IF(K99=TODAY(),"Due today","Due in "&(K99-TODAY())&IF((K99-TODAY())=1," day"," days")))))) | T99: =IF(AND(B99<>"",K99<>"",L99<>"Sent",L99<>"Picked up",L99<>"Cancelled"),K99+ROW()/10000000,"") | U99: =IF(OR(B99="",C99=""),"",B99+ROW()/10000000) | V99: =IF(U99="","",IF(COUNTIFS(Orders!$C$6:$C$1005,C99,Orders!$U$6:$U$1005,">"&U99)=0,1,0)) | W99: =IF(AND(B99<>"",K99<>"",L99<>"Sent",L99<>"Picked up",L99<>"Cancelled"),IF(N(E99)=0,1,E99),0) | X99: =IF(OR(B99="",D99=""),"",IF(N(E99)=0,1,E99))
B100: 46117 | C100: Holly Cox | D100: Wax melts, 6 pack | E100: 2 | H100: =IF(OR(B100="",D100=""),"",IF(N(E100)=0,1,E100)*IFERROR(INDEX(Products!$C$6:$C$105,MATCH(D100,Products!$B$6:$B$105,0)),0)+N(F100)+N(G100)) | I100: 18 | J100: =IF(OR(H100="",L100="Cancelled"),"",IF(H100-N(I100)>0.005,H100-N(I100),"")) | K100: 46124 | L100: Picked up | M100: Craft market | N100: =IF(OR(H100="",L100="Cancelled"),"",IF(N(E100)=0,1,E100)*IFERROR(INDEX(Products!$E$6:$E$105,MATCH(D100,Products!$B$6:$B$105,0)),0)) | P100: =IF(OR(H100="",L100="Cancelled"),"",ROUND(IFERROR(H100*INDEX(Settings!$C$6:$C$15,MATCH(M100,Settings!$B$6:$B$15,0))+INDEX(Settings!$D$6:$D$15,MATCH(M100,Settings!$B$6:$B$15,0)),0),2)) | Q100: =IF(OR(H100="",L100="Cancelled"),"",H100-N(N100)-N(O100)-N(P100)) | R100: =IF(OR(B100="",K100=""),"",IF(OR(L100="Sent",L100="Picked up"),"Done",IF(L100="Cancelled","Cancelled",IF(K100<TODAY(),"Late by "&(TODAY()-K100)&IF((TODAY()-K100)=1," day"," days"),IF(K100=TODAY(),"Due today","Due in "&(K100-TODAY())&IF((K100-TODAY())=1," day"," days")))))) | T100: =IF(AND(B100<>"",K100<>"",L100<>"Sent",L100<>"Picked up",L100<>"Cancelled"),K100+ROW()/10000000,"") | U100: =IF(OR(B100="",C100=""),"",B100+ROW()/10000000) | V100: =IF(U100="","",IF(COUNTIFS(Orders!$C$6:$C$1005,C100,Orders!$U$6:$U$1005,">"&U100)=0,1,0)) | W100: =IF(AND(B100<>"",K100<>"",L100<>"Sent",L100<>"Picked up",L100<>"Cancelled"),IF(N(E100)=0,1,E100),0) | X100: =IF(OR(B100="",D100=""),"",IF(N(E100)=0,1,E100))
B101: 46119 | C101: George Price | D101: Soy candle 16 oz | E101: 1 | H101: =IF(OR(B101="",D101=""),"",IF(N(E101)=0,1,E101)*IFERROR(INDEX(Products!$C$6:$C$105,MATCH(D101,Products!$B$6:$B$105,0)),0)+N(F101)+N(G101)) | I101: 34 | J101: =IF(OR(H101="",L101="Cancelled"),"",IF(H101-N(I101)>0.005,H101-N(I101),"")) | K101: 46130 | L101: Picked up | M101: Instagram | N101: =IF(OR(H101="",L101="Cancelled"),"",IF(N(E101)=0,1,E101)*IFERROR(INDEX(Products!$E$6:$E$105,MATCH(D101,Products!$B$6:$B$105,0)),0)) | P101: =IF(OR(H101="",L101="Cancelled"),"",ROUND(IFERROR(H101*INDEX(Settings!$C$6:$C$15,MATCH(M101,Settings!$B$6:$B$15,0))+INDEX(Settings!$D$6:$D$15,MATCH(M101,Settings!$B$6:$B$15,0)),0),2)) | Q101: =IF(OR(H101="",L101="Cancelled"),"",H101-N(N101)-N(O101)-N(P101)) | R101: =IF(OR(B101="",K101=""),"",IF(OR(L101="Sent",L101="Picked up"),"Done",IF(L101="Cancelled","Cancelled",IF(K101<TODAY(),"Late by "&(TODAY()-K101)&IF((TODAY()-K101)=1," day"," days"),IF(K101=TODAY(),"Due today","Due in "&(K101-TODAY())&IF((K101-TODAY())=1," day"," days")))))) | T101: =IF(AND(B101<>"",K101<>"",L101<>"Sent",L101<>"Picked up",L101<>"Cancelled"),K101+ROW()/10000000,"") | U101: =IF(OR(B101="",C101=""),"",B101+ROW()/10000000) | V101: =IF(U101="","",IF(COUNTIFS(Orders!$C$6:$C$1005,C101,Orders!$U$6:$U$1005,">"&U101)=0,1,0)) | W101: =IF(AND(B101<>"",K101<>"",L101<>"Sent",L101<>"Picked up",L101<>"Cancelled"),IF(N(E101)=0,1,E101),0) | X101: =IF(OR(B101="",D101=""),"",IF(N(E101)=0,1,E101))
B102: 46120 | C102: Ian Adams | D102: Soy candle 8 oz | E102: 1 | H102: =IF(OR(B102="",D102=""),"",IF(N(E102)=0,1,E102)*IFERROR(INDEX(Products!$C$6:$C$105,MATCH(D102,Products!$B$6:$B$105,0)),0)+N(F102)+N(G102)) | I102: 22 | J102: =IF(OR(H102="",L102="Cancelled"),"",IF(H102-N(I102)>0.005,H102-N(I102),"")) | K102: 46129 | L102: Picked up | M102: Friends and family | N102: =IF(OR(H102="",L102="Cancelled"),"",IF(N(E102)=0,1,E102)*IFERROR(INDEX(Products!$E$6:$E$105,MATCH(D102,Products!$B$6:$B$105,0)),0)) | P102: =IF(OR(H102="",L102="Cancelled"),"",ROUND(IFERROR(H102*INDEX(Settings!$C$6:$C$15,MATCH(M102,Settings!$B$6:$B$15,0))+INDEX(Settings!$D$6:$D$15,MATCH(M102,Settings!$B$6:$B$15,0)),0),2)) | Q102: =IF(OR(H102="",L102="Cancelled"),"",H102-N(N102)-N(O102)-N(P102)) | R102: =IF(OR(B102="",K102=""),"",IF(OR(L102="Sent",L102="Picked up"),"Done",IF(L102="Cancelled","Cancelled",IF(K102<TODAY(),"Late by "&(TODAY()-K102)&IF((TODAY()-K102)=1," day"," days"),IF(K102=TODAY(),"Due today","Due in "&(K102-TODAY())&IF((K102-TODAY())=1," day"," days")))))) | T102: =IF(AND(B102<>"",K102<>"",L102<>"Sent",L102<>"Picked up",L102<>"Cancelled"),K102+ROW()/10000000,"") | U102: =IF(OR(B102="",C102=""),"",B102+ROW()/10000000) | V102: =IF(U102="","",IF(COUNTIFS(Orders!$C$6:$C$1005,C102,Orders!$U$6:$U$1005,">"&U102)=0,1,0)) | W102: =IF(AND(B102<>"",K102<>"",L102<>"Sent",L102<>"Picked up",L102<>"Cancelled"),IF(N(E102)=0,1,E102),0) | X102: =IF(OR(B102="",D102=""),"",IF(N(E102)=0,1,E102))
...

Sheet Products
B2: Products
B3: What you sell and its price. The cost comes from the Product materials tab.
B5: Product | C5: Price | D5: Minutes to make | E5: Materials cost | F5: Profit per item | G5: Margin | H5: Sold this year | I5: Sales this year | J5: In open orders
B6: Soy candle 8 oz | C6: 22 | D6: 20 | E6: =IF(B6="","",SUMIFS('Product materials'!$F$6:$F$505,'Product materials'!$B$6:$B$505,B6)) | F6: =IF(B6="","",N(C6)-E6) | G6: =IF(OR(B6="",N(C6)=0),"",F6/C6) | H6: =IF(B6="","",SUMIFS(Orders!$X$6:$X$1005,Orders!$D$6:$D$1005,B6,Orders!$L$6:$L$1005,"Sent",Orders!$B$6:$B$1005,">="&DATE(YEAR(TODAY()),1,1))+SUMIFS(Orders!$X$6:$X$1005,Orders!$D$6:$D$1005,B6,Orders!$L$6:$L$1005,"Picked up",Orders!$B$6:$B$1005,">="&DATE(YEAR(TODAY()),1,1))) | I6: =IF(B6="","",SUMIFS(Orders!$H$6:$H$1005,Orders!$D$6:$D$1005,B6,Orders!$L$6:$L$1005,"<>Cancelled",Orders!$B$6:$B$1005,">="&DATE(YEAR(TODAY()),1,1))) | J6: =IF(B6="","",SUMIFS(Orders!$W$6:$W$1005,Orders!$D$6:$D$1005,B6))
B7: Soy candle 16 oz | C7: 34 | D7: 25 | E7: =IF(B7="","",SUMIFS('Product materials'!$F$6:$F$505,'Product materials'!$B$6:$B$505,B7)) | F7: =IF(B7="","",N(C7)-E7) | G7: =IF(OR(B7="",N(C7)=0),"",F7/C7) | H7: =IF(B7="","",SUMIFS(Orders!$X$6:$X$1005,Orders!$D$6:$D$1005,B7,Orders!$L$6:$L$1005,"Sent",Orders!$B$6:$B$1005,">="&DATE(YEAR(TODAY()),1,1))+SUMIFS(Orders!$X$6:$X$1005,Orders!$D$6:$D$1005,B7,Orders!$L$6:$L$1005,"Picked up",Orders!$B$6:$B$1005,">="&DATE(YEAR(TODAY()),1,1))) | I7: =IF(B7="","",SUMIFS(Orders!$H$6:$H$1005,Orders!$D$6:$D$1005,B7,Orders!$L$6:$L$1005,"<>Cancelled",Orders!$B$6:$B$1005,">="&DATE(YEAR(TODAY()),1,1))) | J7: =IF(B7="","",SUMIFS(Orders!$W$6:$W$1005,Orders!$D$6:$D$1005,B7))
B8: Wax melts, 6 pack | C8: 9 | D8: 10 | E8: =IF(B8="","",SUMIFS('Product materials'!$F$6:$F$505,'Product materials'!$B$6:$B$505,B8)) | F8: =IF(B8="","",N(C8)-E8) | G8: =IF(OR(B8="",N(C8)=0),"",F8/C8) | H8: =IF(B8="","",SUMIFS(Orders!$X$6:$X$1005,Orders!$D$6:$D$1005,B8,Orders!$L$6:$L$1005,"Sent",Orders!$B$6:$B$1005,">="&DATE(YEAR(TODAY()),1,1))+SUMIFS(Orders!$X$6:$X$1005,Orders!$D$6:$D$1005,B8,Orders!$L$6:$L$1005,"Picked up",Orders!$B$6:$B$1005,">="&DATE(YEAR(TODAY()),1,1))) | I8: =IF(B8="","",SUMIFS(Orders!$H$6:$H$1005,Orders!$D$6:$D$1005,B8,Orders!$L$6:$L$1005,"<>Cancelled",Orders!$B$6:$B$1005,">="&DATE(YEAR(TODAY()),1,1))) | J8: =IF(B8="","",SUMIFS(Orders!$W$6:$W$1005,Orders!$D$6:$D$1005,B8))
B9: Soap bar | C9: 8 | D9: 10 | E9: =IF(B9="","",SUMIFS('Product materials'!$F$6:$F$505,'Product materials'!$B$6:$B$505,B9)) | F9: =IF(B9="","",N(C9)-E9) | G9: =IF(OR(B9="",N(C9)=0),"",F9/C9) | H9: =IF(B9="","",SUMIFS(Orders!$X$6:$X$1005,Orders!$D$6:$D$1005,B9,Orders!$L$6:$L$1005,"Sent",Orders!$B$6:$B$1005,">="&DATE(YEAR(TODAY()),1,1))+SUMIFS(Orders!$X$6:$X$1005,Orders!$D$6:$D$1005,B9,Orders!$L$6:$L$1005,"Picked up",Orders!$B$6:$B$1005,">="&DATE(YEAR(TODAY()),1,1))) | I9: =IF(B9="","",SUMIFS(Orders!$H$6:$H$1005,Orders!$D$6:$D$1005,B9,Orders!$L$6:$L$1005,"<>Cancelled",Orders!$B$6:$B$1005,">="&DATE(YEAR(TODAY()),1,1))) | J9: =IF(B9="","",SUMIFS(Orders!$W$6:$W$1005,Orders!$D$6:$D$1005,B9))
B10: Gift box | C10: 45 | D10: 35 | E10: =IF(B10="","",SUMIFS('Product materials'!$F$6:$F$505,'Product materials'!$B$6:$B$505,B10)) | F10: =IF(B10="","",N(C10)-E10) | G10: =IF(OR(B10="",N(C10)=0),"",F10/C10) | H10: =IF(B10="","",SUMIFS(Orders!$X$6:$X$1005,Orders!$D$6:$D$1005,B10,Orders!$L$6:$L$1005,"Sent",Orders!$B$6:$B$1005,">="&DATE(YEAR(TODAY()),1,1))+SUMIFS(Orders!$X$6:$X$1005,Orders!$D$6:$D$1005,B10,Orders!$L$6:$L$1005,"Picked up",Orders!$B$6:$B$1005,">="&DATE(YEAR(TODAY()),1,1))) | I10: =IF(B10="","",SUMIFS(Orders!$H$6:$H$1005,Orders!$D$6:$D$1005,B10,Orders!$L$6:$L$1005,"<>Cancelled",Orders!$B$6:$B$1005,">="&DATE(YEAR(TODAY()),1,1))) | J10: =IF(B10="","",SUMIFS(Orders!$W$6:$W$1005,Orders!$D$6:$D$1005,B10))
B11: Wedding favours, 10 tins | C11: 60 | D11: 60 | E11: =IF(B11="","",SUMIFS('Product materials'!$F$6:$F$505,'Product materials'!$B$6:$B$505,B11)) | F11: =IF(B11="","",N(C11)-E11) | G11: =IF(OR(B11="",N(C11)=0),"",F11/C11) | H11: =IF(B11="","",SUMIFS(Orders!$X$6:$X$1005,Orders!$D$6:$D$1005,B11,Orders!$L$6:$L$1005,"Sent",Orders!$B$6:$B$1005,">="&DATE(YEAR(TODAY()),1,1))+SUMIFS(Orders!$X$6:$X$1005,Orders!$D$6:$D$1005,B11,Orders!$L$6:$L$1005,"Picked up",Orders!$B$6:$B$1005,">="&DATE(YEAR(TODAY()),1,1))) | I11: =IF(B11="","",SUMIFS(Orders!$H$6:$H$1005,Orders!$D$6:$D$1005,B11,Orders!$L$6:$L$1005,"<>Cancelled",Orders!$B$6:$B$1005,">="&DATE(YEAR(TODAY()),1,1))) | J11: =IF(B11="","",SUMIFS(Orders!$W$6:$W$1005,Orders!$D$6:$D$1005,B11))
E12: =IF(B12="","",SUMIFS('Product materials'!$F$6:$F$505,'Product materials'!$B$6:$B$505,B12)) | F12: =IF(B12="","",N(C12)-E12) | G12: =IF(OR(B12="",N(C12)=0),"",F12/C12) | H12: =IF(B12="","",SUMIFS(Orders!$X$6:$X$1005,Orders!$D$6:$D$1005,B12,Orders!$L$6:$L$1005,"Sent",Orders!$B$6:$B$1005,">="&DATE(YEAR(TODAY()),1,1))+SUMIFS(Orders!$X$6:$X$1005,Orders!$D$6:$D$1005,B12,Orders!$L$6:$L$1005,"Picked up",Orders!$B$6:$B$1005,">="&DATE(YEAR(TODAY()),1,1))) | I12: =IF(B12="","",SUMIFS(Orders!$H$6:$H$1005,Orders!$D$6:$D$1005,B12,Orders!$L$6:$L$1005,"<>Cancelled",Orders!$B$6:$B$1005,">="&DATE(YEAR(TODAY()),1,1))) | J12: =IF(B12="","",SUMIFS(Orders!$W$6:$W$1005,Orders!$D$6:$D$1005,B12))
E13: =IF(B13="","",SUMIFS('Product materials'!$F$6:$F$505,'Product materials'!$B$6:$B$505,B13)) | F13: =IF(B13="","",N(C13)-E13) | G13: =IF(OR(B13="",N(C13)=0),"",F13/C13) | H13: =IF(B13="","",SUMIFS(Orders!$X$6:$X$1005,Orders!$D$6:$D$1005,B13,Orders!$L$6:$L$1005,"Sent",Orders!$B$6:$B$1005,">="&DATE(YEAR(TODAY()),1,1))+SUMIFS(Orders!$X$6:$X$1005,Orders!$D$6:$D$1005,B13,Orders!$L$6:$L$1005,"Picked up",Orders!$B$6:$B$1005,">="&DATE(YEAR(TODAY()),1,1))) | I13: =IF(B13="","",SUMIFS(Orders!$H$6:$H$1005,Orders!$D$6:$D$1005,B13,Orders!$L$6:$L$1005,"<>Cancelled",Orders!$B$6:$B$1005,">="&DATE(YEAR(TODAY()),1,1))) | J13: =IF(B13="","",SUMIFS(Orders!$W$6:$W$1005,Orders!$D$6:$D$1005,B13))
E14: =IF(B14="","",SUMIFS('Product materials'!$F$6:$F$505,'Product materials'!$B$6:$B$505,B14)) | F14: =IF(B14="","",N(C14)-E14) | G14: =IF(OR(B14="",N(C14)=0),"",F14/C14) | H14: =IF(B14="","",SUMIFS(Orders!$X$6:$X$1005,Orders!$D$6:$D$1005,B14,Orders!$L$6:$L$1005,"Sent",Orders!$B$6:$B$1005,">="&DATE(YEAR(TODAY()),1,1))+SUMIFS(Orders!$X$6:$X$1005,Orders!$D$6:$D$1005,B14,Orders!$L$6:$L$1005,"Picked up",Orders!$B$6:$B$1005,">="&DATE(YEAR(TODAY()),1,1))) | I14: =IF(B14="","",SUMIFS(Orders!$H$6:$H$1005,Orders!$D$6:$D$1005,B14,Orders!$L$6:$L$1005,"<>Cancelled",Orders!$B$6:$B$1005,">="&DATE(YEAR(TODAY()),1,1))) | J14: =IF(B14="","",SUMIFS(Orders!$W$6:$W$1005,Orders!$D$6:$D$1005,B14))
E15: =IF(B15="","",SUMIFS('Product materials'!$F$6:$F$505,'Product materials'!$B$6:$B$505,B15)) | F15: =IF(B15="","",N(C15)-E15) | G15: =IF(OR(B15="",N(C15)=0),"",F15/C15) | H15: =IF(B15="","",SUMIFS(Orders!$X$6:$X$1005,Orders!$D$6:$D$1005,B15,Orders!$L$6:$L$1005,"Sent",Orders!$B$6:$B$1005,">="&DATE(YEAR(TODAY()),1,1))+SUMIFS(Orders!$X$6:$X$1005,Orders!$D$6:$D$1005,B15,Orders!$L$6:$L$1005,"Picked up",Orders!$B$6:$B$1005,">="&DATE(YEAR(TODAY()),1,1))) | I15: =IF(B15="","",SUMIFS(Orders!$H$6:$H$1005,Orders!$D$6:$D$1005,B15,Orders!$L$6:$L$1005,"<>Cancelled",Orders!$B$6:$B$1005,">="&DATE(YEAR(TODAY()),1,1))) | J15: =IF(B15="","",SUMIFS(Orders!$W$6:$W$1005,Orders!$D$6:$D$1005,B15))
E16: =IF(B16="","",SUMIFS('Product materials'!$F$6:$F$505,'Product materials'!$B$6:$B$505,B16)) | F16: =IF(B16="","",N(C16)-E16) | G16: =IF(OR(B16="",N(C16)=0),"",F16/C16) | H16: =IF(B16="","",SUMIFS(Orders!$X$6:$X$1005,Orders!$D$6:$D$1005,B16,Orders!$L$6:$L$1005,"Sent",Orders!$B$6:$B$1005,">="&DATE(YEAR(TODAY()),1,1))+SUMIFS(Orders!$X$6:$X$1005,Orders!$D$6:$D$1005,B16,Orders!$L$6:$L$1005,"Picked up",Orders!$B$6:$B$1005,">="&DATE(YEAR(TODAY()),1,1))) | I16: =IF(B16="","",SUMIFS(Orders!$H$6:$H$1005,Orders!$D$6:$D$1005,B16,Orders!$L$6:$L$1005,"<>Cancelled",Orders!$B$6:$B$1005,">="&DATE(YEAR(TODAY()),1,1))) | J16: =IF(B16="","",SUMIFS(Orders!$W$6:$W$1005,Orders!$D$6:$D$1005,B16))
E17: =IF(B17="","",SUMIFS('Product materials'!$F$6:$F$505,'Product materials'!$B$6:$B$505,B17)) | F17: =IF(B17="","",N(C17)-E17) | G17: =IF(OR(B17="",N(C17)=0),"",F17/C17) | H17: =IF(B17="","",SUMIFS(Orders!$X$6:$X$1005,Orders!$D$6:$D$1005,B17,Orders!$L$6:$L$1005,"Sent",Orders!$B$6:$B$1005,">="&DATE(YEAR(TODAY()),1,1))+SUMIFS(Orders!$X$6:$X$1005,Orders!$D$6:$D$1005,B17,Orders!$L$6:$L$1005,"Picked up",Orders!$B$6:$B$1005,">="&DATE(YEAR(TODAY()),1,1))) | I17: =IF(B17="","",SUMIFS(Orders!$H$6:$H$1005,Orders!$D$6:$D$1005,B17,Orders!$L$6:$L$1005,"<>Cancelled",Orders!$B$6:$B$1005,">="&DATE(YEAR(TODAY()),1,1))) | J17: =IF(B17="","",SUMIFS(Orders!$W$6:$W$1005,Orders!$D$6:$D$1005,B17))
E18: =IF(B18="","",SUMIFS('Product materials'!$F$6:$F$505,'Product materials'!$B$6:$B$505,B18)) | F18: =IF(B18="","",N(C18)-E18) | G18: =IF(OR(B18="",N(C18)=0),"",F18/C18) | H18: =IF(B18="","",SUMIFS(Orders!$X$6:$X$1005,Orders!$D$6:$D$1005,B18,Orders!$L$6:$L$1005,"Sent",Orders!$B$6:$B$1005,">="&DATE(YEAR(TODAY()),1,1))+SUMIFS(Orders!$X$6:$X$1005,Orders!$D$6:$D$1005,B18,Orders!$L$6:$L$1005,"Picked up",Orders!$B$6:$B$1005,">="&DATE(YEAR(TODAY()),1,1))) | I18: =IF(B18="","",SUMIFS(Orders!$H$6:$H$1005,Orders!$D$6:$D$1005,B18,Orders!$L$6:$L$1005,"<>Cancelled",Orders!$B$6:$B$1005,">="&DATE(YEAR(TODAY()),1,1))) | J18: =IF(B18="","",SUMIFS(Orders!$W$6:$W$1005,Orders!$D$6:$D$1005,B18))
E19: =IF(B19="","",SUMIFS('Product materials'!$F$6:$F$505,'Product materials'!$B$6:$B$505,B19)) | F19: =IF(B19="","",N(C19)-E19) | G19: =IF(OR(B19="",N(C19)=0),"",F19/C19) | H19: =IF(B19="","",SUMIFS(Orders!$X$6:$X$1005,Orders!$D$6:$D$1005,B19,Orders!$L$6:$L$1005,"Sent",Orders!$B$6:$B$1005,">="&DATE(YEAR(TODAY()),1,1))+SUMIFS(Orders!$X$6:$X$1005,Orders!$D$6:$D$1005,B19,Orders!$L$6:$L$1005,"Picked up",Orders!$B$6:$B$1005,">="&DATE(YEAR(TODAY()),1,1))) | I19: =IF(B19="","",SUMIFS(Orders!$H$6:$H$1005,Orders!$D$6:$D$1005,B19,Orders!$L$6:$L$1005,"<>Cancelled",Orders!$B$6:$B$1005,">="&DATE(YEAR(TODAY()),1,1))) | J19: =IF(B19="","",SUMIFS(Orders!$W$6:$W$1005,Orders!$D$6:$D$1005,B19))
E20: =IF(B20="","",SUMIFS('Product materials'!$F$6:$F$505,'Product materials'!$B$6:$B$505,B20)) | F20: =IF(B20="","",N(C20)-E20) | G20: =IF(OR(B20="",N(C20)=0),"",F20/C20) | H20: =IF(B20="","",SUMIFS(Orders!$X$6:$X$1005,Orders!$D$6:$D$1005,B20,Orders!$L$6:$L$1005,"Sent",Orders!$B$6:$B$1005,">="&DATE(YEAR(TODAY()),1,1))+SUMIFS(Orders!$X$6:$X$1005,Orders!$D$6:$D$1005,B20,Orders!$L$6:$L$1005,"Picked up",Orders!$B$6:$B$1005,">="&DATE(YEAR(TODAY()),1,1))) | I20: =IF(B20="","",SUMIFS(Orders!$H$6:$H$1005,Orders!$D$6:$D$1005,B20,Orders!$L$6:$L$1005,"<>Cancelled",Orders!$B$6:$B$1005,">="&DATE(YEAR(TODAY()),1,1))) | J20: =IF(B20="","",SUMIFS(Orders!$W$6:$W$1005,Orders!$D$6:$D$1005,B20))
E21: =IF(B21="","",SUMIFS('Product materials'!$F$6:$F$505,'Product materials'!$B$6:$B$505,B21)) | F21: =IF(B21="","",N(C21)-E21) | G21: =IF(OR(B21="",N(C21)=0),"",F21/C21) | H21: =IF(B21="","",SUMIFS(Orders!$X$6:$X$1005,Orders!$D$6:$D$1005,B21,Orders!$L$6:$L$1005,"Sent",Orders!$B$6:$B$1005,">="&DATE(YEAR(TODAY()),1,1))+SUMIFS(Orders!$X$6:$X$1005,Orders!$D$6:$D$1005,B21,Orders!$L$6:$L$1005,"Picked up",Orders!$B$6:$B$1005,">="&DATE(YEAR(TODAY()),1,1))) | I21: =IF(B21="","",SUMIFS(Orders!$H$6:$H$1005,Orders!$D$6:$D$1005,B21,Orders!$L$6:$L$1005,"<>Cancelled",Orders!$B$6:$B$1005,">="&DATE(YEAR(TODAY()),1,1))) | J21: =IF(B21="","",SUMIFS(Orders!$W$6:$W$1005,Orders!$D$6:$D$1005,B21))
E22: =IF(B22="","",SUMIFS('Product materials'!$F$6:$F$505,'Product materials'!$B$6:$B$505,B22)) | F22: =IF(B22="","",N(C22)-E22) | G22: =IF(OR(B22="",N(C22)=0),"",F22/C22) | H22: =IF(B22="","",SUMIFS(Orders!$X$6:$X$1005,Orders!$D$6:$D$1005,B22,Orders!$L$6:$L$1005,"Sent",Orders!$B$6:$B$1005,">="&DATE(YEAR(TODAY()),1,1))+SUMIFS(Orders!$X$6:$X$1005,Orders!$D$6:$D$1005,B22,Orders!$L$6:$L$1005,"Picked up",Orders!$B$6:$B$1005,">="&DATE(YEAR(TODAY()),1,1))) | I22: =IF(B22="","",SUMIFS(Orders!$H$6:$H$1005,Orders!$D$6:$D$1005,B22,Orders!$L$6:$L$1005,"<>Cancelled",Orders!$B$6:$B$1005,">="&DATE(YEAR(TODAY()),1,1))) | J22: =IF(B22="","",SUMIFS(Orders!$W$6:$W$1005,Orders!$D$6:$D$1005,B22))
E23: =IF(B23="","",SUMIFS('Product materials'!$F$6:$F$505,'Product materials'!$B$6:$B$505,B23)) | F23: =IF(B23="","",N(C23)-E23) | G23: =IF(OR(B23="",N(C23)=0),"",F23/C23) | H23: =IF(B23="","",SUMIFS(Orders!$X$6:$X$1005,Orders!$D$6:$D$1005,B23,Orders!$L$6:$L$1005,"Sent",Orders!$B$6:$B$1005,">="&DATE(YEAR(TODAY()),1,1))+SUMIFS(Orders!$X$6:$X$1005,Orders!$D$6:$D$1005,B23,Orders!$L$6:$L$1005,"Picked up",Orders!$B$6:$B$1005,">="&DATE(YEAR(TODAY()),1,1))) | I23: =IF(B23="","",SUMIFS(Orders!$H$6:$H$1005,Orders!$D$6:$D$1005,B23,Orders!$L$6:$L$1005,"<>Cancelled",Orders!$B$6:$B$1005,">="&DATE(YEAR(TODAY()),1,1))) | J23: =IF(B23="","",SUMIFS(Orders!$W$6:$W$1005,Orders!$D$6:$D$1005,B23))
... E105: =IF(B105="","",SUMIFS('Product materials'!$F$6:$F$505,'Product materials'!$B$6:$B$505,B105)) | F105: =IF(B105="","",N(C105)-E105) | G105: =IF(OR(B105="",N(C105)=0),"",F105/C105) | H105: =IF(B105="","",SUMIFS(Orders!$X$6:$X$1005,Orders!$D$6:$D$1005,B105,Orders!$L$6:$L$1005,"Sent",Orders!$B$6:$B$1005,">="&DATE(YEAR(TODAY()),1,1))+SUMIFS(Orders!$X$6:$X$1005,Orders!$D$6:$D$1005,B105,Orders!$L$6:$L$1005,"Picked up",Orders!$B$6:$B$1005,">="&DATE(YEAR(TODAY()),1,1))) | I105: =IF(B105="","",SUMIFS(Orders!$H$6:$H$1005,Orders!$D$6:$D$1005,B105,Orders!$L$6:$L$1005,"<>Cancelled",Orders!$B$6:$B$1005,">="&DATE(YEAR(TODAY()),1,1))) | J105: =IF(B105="","",SUMIFS(Orders!$W$6:$W$1005,Orders!$D$6:$D$1005,B105))
B107: Margin is the profit per item before fees and postage, as a share of the price.

Sheet Product materials
B2: Product materials
B3: One line per material in each product, with the amount one item uses.
B5: Product | C5: Material | D5: Amount per item | E5: Unit | F5: Cost per item | G5: For open orders
B6: Soy candle 8 oz | C6: Soy wax | D6: 0.5 | E6: =IF(C6="","",IFERROR(INDEX(Materials!$C$6:$C$205,MATCH(C6,Materials!$B$6:$B$205,0))&"","Add it to Materials")) | F6: =IF(OR(C6="",E6="Add it to Materials"),"",N(D6)*INDEX(Materials!$F$6:$F$205,MATCH(C6,Materials!$B$6:$B$205,0))) | G6: =IF(OR(B6="",C6=""),"",N(D6)*SUMIFS(Orders!$W$6:$W$1005,Orders!$D$6:$D$1005,B6))
B7: Soy candle 8 oz | C7: Cotton wick | D7: 1 | E7: =IF(C7="","",IFERROR(INDEX(Materials!$C$6:$C$205,MATCH(C7,Materials!$B$6:$B$205,0))&"","Add it to Materials")) | F7: =IF(OR(C7="",E7="Add it to Materials"),"",N(D7)*INDEX(Materials!$F$6:$F$205,MATCH(C7,Materials!$B$6:$B$205,0))) | G7: =IF(OR(B7="",C7=""),"",N(D7)*SUMIFS(Orders!$W$6:$W$1005,Orders!$D$6:$D$1005,B7))
B8: Soy candle 8 oz | C8: Jar 8 oz | D8: 1 | E8: =IF(C8="","",IFERROR(INDEX(Materials!$C$6:$C$205,MATCH(C8,Materials!$B$6:$B$205,0))&"","Add it to Materials")) | F8: =IF(OR(C8="",E8="Add it to Materials"),"",N(D8)*INDEX(Materials!$F$6:$F$205,MATCH(C8,Materials!$B$6:$B$205,0))) | G8: =IF(OR(B8="",C8=""),"",N(D8)*SUMIFS(Orders!$W$6:$W$1005,Orders!$D$6:$D$1005,B8))
B9: Soy candle 8 oz | C9: Fragrance oil | D9: 0.5 | E9: =IF(C9="","",IFERROR(INDEX(Materials!$C$6:$C$205,MATCH(C9,Materials!$B$6:$B$205,0))&"","Add it to Materials")) | F9: =IF(OR(C9="",E9="Add it to Materials"),"",N(D9)*INDEX(Materials!$F$6:$F$205,MATCH(C9,Materials!$B$6:$B$205,0))) | G9: =IF(OR(B9="",C9=""),"",N(D9)*SUMIFS(Orders!$W$6:$W$1005,Orders!$D$6:$D$1005,B9))
B10: Soy candle 8 oz | C10: Label | D10: 1 | E10: =IF(C10="","",IFERROR(INDEX(Materials!$C$6:$C$205,MATCH(C10,Materials!$B$6:$B$205,0))&"","Add it to Materials")) | F10: =IF(OR(C10="",E10="Add it to Materials"),"",N(D10)*INDEX(Materials!$F$6:$F$205,MATCH(C10,Materials!$B$6:$B$205,0))) | G10: =IF(OR(B10="",C10=""),"",N(D10)*SUMIFS(Orders!$W$6:$W$1005,Orders!$D$6:$D$1005,B10))
B11: Soy candle 16 oz | C11: Soy wax | D11: 1 | E11: =IF(C11="","",IFERROR(INDEX(Materials!$C$6:$C$205,MATCH(C11,Materials!$B$6:$B$205,0))&"","Add it to Materials")) | F11: =IF(OR(C11="",E11="Add it to Materials"),"",N(D11)*INDEX(Materials!$F$6:$F$205,MATCH(C11,Materials!$B$6:$B$205,0))) | G11: =IF(OR(B11="",C11=""),"",N(D11)*SUMIFS(Orders!$W$6:$W$1005,Orders!$D$6:$D$1005,B11))
B12: Soy candle 16 oz | C12: Cotton wick | D12: 2 | E12: =IF(C12="","",IFERROR(INDEX(Materials!$C$6:$C$205,MATCH(C12,Materials!$B$6:$B$205,0))&"","Add it to Materials")) | F12: =IF(OR(C12="",E12="Add it to Materials"),"",N(D12)*INDEX(Materials!$F$6:$F$205,MATCH(C12,Materials!$B$6:$B$205,0))) | G12: =IF(OR(B12="",C12=""),"",N(D12)*SUMIFS(Orders!$W$6:$W$1005,Orders!$D$6:$D$1005,B12))
B13: Soy candle 16 oz | C13: Jar 16 oz | D13: 1 | E13: =IF(C13="","",IFERROR(INDEX(Materials!$C$6:$C$205,MATCH(C13,Materials!$B$6:$B$205,0))&"","Add it to Materials")) | F13: =IF(OR(C13="",E13="Add it to Materials"),"",N(D13)*INDEX(Materials!$F$6:$F$205,MATCH(C13,Materials!$B$6:$B$205,0))) | G13: =IF(OR(B13="",C13=""),"",N(D13)*SUMIFS(Orders!$W$6:$W$1005,Orders!$D$6:$D$1005,B13))
B14: Soy candle 16 oz | C14: Fragrance oil | D14: 1 | E14: =IF(C14="","",IFERROR(INDEX(Materials!$C$6:$C$205,MATCH(C14,Materials!$B$6:$B$205,0))&"","Add it to Materials")) | F14: =IF(OR(C14="",E14="Add it to Materials"),"",N(D14)*INDEX(Materials!$F$6:$F$205,MATCH(C14,Materials!$B$6:$B$205,0))) | G14: =IF(OR(B14="",C14=""),"",N(D14)*SUMIFS(Orders!$W$6:$W$1005,Orders!$D$6:$D$1005,B14))
B15: Soy candle 16 oz | C15: Label | D15: 1 | E15: =IF(C15="","",IFERROR(INDEX(Materials!$C$6:$C$205,MATCH(C15,Materials!$B$6:$B$205,0))&"","Add it to Materials")) | F15: =IF(OR(C15="",E15="Add it to Materials"),"",N(D15)*INDEX(Materials!$F$6:$F$205,MATCH(C15,Materials!$B$6:$B$205,0))) | G15: =IF(OR(B15="",C15=""),"",N(D15)*SUMIFS(Orders!$W$6:$W$1005,Orders!$D$6:$D$1005,B15))
B16: Wax melts, 6 pack | C16: Soy wax | D16: 0.4 | E16: =IF(C16="","",IFERROR(INDEX(Materials!$C$6:$C$205,MATCH(C16,Materials!$B$6:$B$205,0))&"","Add it to Materials")) | F16: =IF(OR(C16="",E16="Add it to Materials"),"",N(D16)*INDEX(Materials!$F$6:$F$205,MATCH(C16,Materials!$B$6:$B$205,0))) | G16: =IF(OR(B16="",C16=""),"",N(D16)*SUMIFS(Orders!$W$6:$W$1005,Orders!$D$6:$D$1005,B16))
B17: Wax melts, 6 pack | C17: Fragrance oil | D17: 0.4 | E17: =IF(C17="","",IFERROR(INDEX(Materials!$C$6:$C$205,MATCH(C17,Materials!$B$6:$B$205,0))&"","Add it to Materials")) | F17: =IF(OR(C17="",E17="Add it to Materials"),"",N(D17)*INDEX(Materials!$F$6:$F$205,MATCH(C17,Materials!$B$6:$B$205,0))) | G17: =IF(OR(B17="",C17=""),"",N(D17)*SUMIFS(Orders!$W$6:$W$1005,Orders!$D$6:$D$1005,B17))
... B36: Wedding favours, 10 tins | C36: Label | D36: 10 | E36: =IF(C36="","",IFERROR(INDEX(Materials!$C$6:$C$205,MATCH(C36,Materials!$B$6:$B$205,0))&"","Add it to Materials")) | F36: =IF(OR(C36="",E36="Add it to Materials"),"",N(D36)*INDEX(Materials!$F$6:$F$205,MATCH(C36,Materials!$B$6:$B$205,0))) | G36: =IF(OR(B36="",C36=""),"",N(D36)*SUMIFS(Orders!$W$6:$W$1005,Orders!$D$6:$D$1005,B36))
E37: =IF(C37="","",IFERROR(INDEX(Materials!$C$6:$C$205,MATCH(C37,Materials!$B$6:$B$205,0))&"","Add it to Materials")) | F37: =IF(OR(C37="",E37="Add it to Materials"),"",N(D37)*INDEX(Materials!$F$6:$F$205,MATCH(C37,Materials!$B$6:$B$205,0))) | G37: =IF(OR(B37="",C37=""),"",N(D37)*SUMIFS(Orders!$W$6:$W$1005,Orders!$D$6:$D$1005,B37))
E38: =IF(C38="","",IFERROR(INDEX(Materials!$C$6:$C$205,MATCH(C38,Materials!$B$6:$B$205,0))&"","Add it to Materials")) | F38: =IF(OR(C38="",E38="Add it to Materials"),"",N(D38)*INDEX(Materials!$F$6:$F$205,MATCH(C38,Materials!$B$6:$B$205,0))) | G38: =IF(OR(B38="",C38=""),"",N(D38)*SUMIFS(Orders!$W$6:$W$1005,Orders!$D$6:$D$1005,B38))
E39: =IF(C39="","",IFERROR(INDEX(Materials!$C$6:$C$205,MATCH(C39,Materials!$B$6:$B$205,0))&"","Add it to Materials")) | F39: =IF(OR(C39="",E39="Add it to Materials"),"",N(D39)*INDEX(Materials!$F$6:$F$205,MATCH(C39,Materials!$B$6:$B$205,0))) | G39: =IF(OR(B39="",C39=""),"",N(D39)*SUMIFS(Orders!$W$6:$W$1005,Orders!$D$6:$D$1005,B39))
E40: =IF(C40="","",IFERROR(INDEX(Materials!$C$6:$C$205,MATCH(C40,Materials!$B$6:$B$205,0))&"","Add it to Materials")) | F40: =IF(OR(C40="",E40="Add it to Materials"),"",N(D40)*INDEX(Materials!$F$6:$F$205,MATCH(C40,Materials!$B$6:$B$205,0))) | G40: =IF(OR(B40="",C40=""),"",N(D40)*SUMIFS(Orders!$W$6:$W$1005,Orders!$D$6:$D$1005,B40))
E41: =IF(C41="","",IFERROR(INDEX(Materials!$C$6:$C$205,MATCH(C41,Materials!$B$6:$B$205,0))&"","Add it to Materials")) | F41: =IF(OR(C41="",E41="Add it to Materials"),"",N(D41)*INDEX(Materials!$F$6:$F$205,MATCH(C41,Materials!$B$6:$B$205,0))) | G41: =IF(OR(B41="",C41=""),"",N(D41)*SUMIFS(Orders!$W$6:$W$1005,Orders!$D$6:$D$1005,B41))
E42: =IF(C42="","",IFERROR(INDEX(Materials!$C$6:$C$205,MATCH(C42,Materials!$B$6:$B$205,0))&"","Add it to Materials")) | F42: =IF(OR(C42="",E42="Add it to Materials"),"",N(D42)*INDEX(Materials!$F$6:$F$205,MATCH(C42,Materials!$B$6:$B$205,0))) | G42: =IF(OR(B42="",C42=""),"",N(D42)*SUMIFS(Orders!$W$6:$W$1005,Orders!$D$6:$D$1005,B42))
E43: =IF(C43="","",IFERROR(INDEX(Materials!$C$6:$C$205,MATCH(C43,Materials!$B$6:$B$205,0))&"","Add it to Materials")) | F43: =IF(OR(C43="",E43="Add it to Materials"),"",N(D43)*INDEX(Materials!$F$6:$F$205,MATCH(C43,Materials!$B$6:$B$205,0))) | G43: =IF(OR(B43="",C43=""),"",N(D43)*SUMIFS(Orders!$W$6:$W$1005,Orders!$D$6:$D$1005,B43))
E44: =IF(C44="","",IFERROR(INDEX(Materials!$C$6:$C$205,MATCH(C44,Materials!$B$6:$B$205,0))&"","Add it to Materials")) | F44: =IF(OR(C44="",E44="Add it to Materials"),"",N(D44)*INDEX(Materials!$F$6:$F$205,MATCH(C44,Materials!$B$6:$B$205,0))) | G44: =IF(OR(B44="",C44=""),"",N(D44)*SUMIFS(Orders!$W$6:$W$1005,Orders!$D$6:$D$1005,B44))
E45: =IF(C45="","",IFERROR(INDEX(Materials!$C$6:$C$205,MATCH(C45,Materials!$B$6:$B$205,0))&"","Add it to Materials")) | F45: =IF(OR(C45="",E45="Add it to Materials"),"",N(D45)*INDEX(Materials!$F$6:$F$205,MATCH(C45,Materials!$B$6:$B$205,0))) | G45: =IF(OR(B45="",C45=""),"",N(D45)*SUMIFS(Orders!$W$6:$W$1005,Orders!$D$6:$D$1005,B45))
E46: =IF(C46="","",IFERROR(INDEX(Materials!$C$6:$C$205,MATCH(C46,Materials!$B$6:$B$205,0))&"","Add it to Materials")) | F46: =IF(OR(C46="",E46="Add it to Materials"),"",N(D46)*INDEX(Materials!$F$6:$F$205,MATCH(C46,Materials!$B$6:$B$205,0))) | G46: =IF(OR(B46="",C46=""),"",N(D46)*SUMIFS(Orders!$W$6:$W$1005,Orders!$D$6:$D$1005,B46))
E47: =IF(C47="","",IFERROR(INDEX(Materials!$C$6:$C$205,MATCH(C47,Materials!$B$6:$B$205,0))&"","Add it to Materials")) | F47: =IF(OR(C47="",E47="Add it to Materials"),"",N(D47)*INDEX(Materials!$F$6:$F$205,MATCH(C47,Materials!$B$6:$B$205,0))) | G47: =IF(OR(B47="",C47=""),"",N(D47)*SUMIFS(Orders!$W$6:$W$1005,Orders!$D$6:$D$1005,B47))
E48: =IF(C48="","",IFERROR(INDEX(Materials!$C$6:$C$205,MATCH(C48,Materials!$B$6:$B$205,0))&"","Add it to Materials")) | F48: =IF(OR(C48="",E48="Add it to Materials"),"",N(D48)*INDEX(Materials!$F$6:$F$205,MATCH(C48,Materials!$B$6:$B$205,0))) | G48: =IF(OR(B48="",C48=""),"",N(D48)*SUMIFS(Orders!$W$6:$W$1005,Orders!$D$6:$D$1005,B48))
... E505: =IF(C505="","",IFERROR(INDEX(Materials!$C$6:$C$205,MATCH(C505,Materials!$B$6:$B$205,0))&"","Add it to Materials")) | F505: =IF(OR(C505="",E505="Add it to Materials"),"",N(D505)*INDEX(Materials!$F$6:$F$205,MATCH(C505,Materials!$B$6:$B$205,0))) | G505: =IF(OR(B505="",C505=""),"",N(D505)*SUMIFS(Orders!$W$6:$W$1005,Orders!$D$6:$D$1005,B505))

Sheet Materials
B2: Materials
B3: What you buy to make your products, what you have, and what the open orders still need.
B5: Material | C5: Unit | D5: Pack size | E5: Pack price | F5: Cost per unit | G5: In stock | H5: For open orders | I5: Short by | J5: Note
B6: Soy wax | C6: lb | D6: 10 | E6: 32 | F6: =IF(B6="","",N(E6)/IF(N(D6)>0,D6,1)) | G6: 45 | H6: =IF(B6="","",SUMIFS('Product materials'!$G$6:$G$505,'Product materials'!$C$6:$C$505,B6)) | I6: =IF(B6="","",IF(H6-N(G6)>0,H6-N(G6),""))
B7: Cotton wick | C7: each | D7: 100 | E7: 9.5 | F7: =IF(B7="","",N(E7)/IF(N(D7)>0,D7,1)) | G7: 200 | H7: =IF(B7="","",SUMIFS('Product materials'!$G$6:$G$505,'Product materials'!$C$6:$C$505,B7)) | I7: =IF(B7="","",IF(H7-N(G7)>0,H7-N(G7),""))
B8: Jar 8 oz | C8: each | D8: 12 | E8: 18 | F8: =IF(B8="","",N(E8)/IF(N(D8)>0,D8,1)) | G8: 24 | H8: =IF(B8="","",SUMIFS('Product materials'!$G$6:$G$505,'Product materials'!$C$6:$C$505,B8)) | I8: =IF(B8="","",IF(H8-N(G8)>0,H8-N(G8),""))
B9: Jar 16 oz | C9: each | D9: 12 | E9: 26 | F9: =IF(B9="","",N(E9)/IF(N(D9)>0,D9,1)) | G9: 4 | H9: =IF(B9="","",SUMIFS('Product materials'!$G$6:$G$505,'Product materials'!$C$6:$C$505,B9)) | I9: =IF(B9="","",IF(H9-N(G9)>0,H9-N(G9),""))
B10: Fragrance oil | C10: oz | D10: 16 | E10: 21 | F10: =IF(B10="","",N(E10)/IF(N(D10)>0,D10,1)) | G10: 48 | H10: =IF(B10="","",SUMIFS('Product materials'!$G$6:$G$505,'Product materials'!$C$6:$C$505,B10)) | I10: =IF(B10="","",IF(H10-N(G10)>0,H10-N(G10),""))
B11: Label | C11: each | D11: 250 | E11: 25 | F11: =IF(B11="","",N(E11)/IF(N(D11)>0,D11,1)) | G11: 250 | H11: =IF(B11="","",SUMIFS('Product materials'!$G$6:$G$505,'Product materials'!$C$6:$C$505,B11)) | I11: =IF(B11="","",IF(H11-N(G11)>0,H11-N(G11),""))
B12: Clamshell | C12: each | D12: 50 | E12: 12 | F12: =IF(B12="","",N(E12)/IF(N(D12)>0,D12,1)) | G12: 30 | H12: =IF(B12="","",SUMIFS('Product materials'!$G$6:$G$505,'Product materials'!$C$6:$C$505,B12)) | I12: =IF(B12="","",IF(H12-N(G12)>0,H12-N(G12),""))
B13: Soap base | C13: lb | D13: 5 | E13: 22.5 | F13: =IF(B13="","",N(E13)/IF(N(D13)>0,D13,1)) | G13: 6 | H13: =IF(B13="","",SUMIFS('Product materials'!$G$6:$G$505,'Product materials'!$C$6:$C$505,B13)) | I13: =IF(B13="","",IF(H13-N(G13)>0,H13-N(G13),""))
B14: Kraft wrap | C14: each | D14: 100 | E14: 8 | F14: =IF(B14="","",N(E14)/IF(N(D14)>0,D14,1)) | G14: 70 | H14: =IF(B14="","",SUMIFS('Product materials'!$G$6:$G$505,'Product materials'!$C$6:$C$505,B14)) | I14: =IF(B14="","",IF(H14-N(G14)>0,H14-N(G14),""))
B15: Gift box | C15: each | D15: 25 | E15: 30 | F15: =IF(B15="","",N(E15)/IF(N(D15)>0,D15,1)) | G15: 3 | H15: =IF(B15="","",SUMIFS('Product materials'!$G$6:$G$505,'Product materials'!$C$6:$C$505,B15)) | I15: =IF(B15="","",IF(H15-N(G15)>0,H15-N(G15),""))
B16: Tissue paper | C16: sheet | D16: 100 | E16: 7 | F16: =IF(B16="","",N(E16)/IF(N(D16)>0,D16,1)) | G16: 40 | H16: =IF(B16="","",SUMIFS('Product materials'!$G$6:$G$505,'Product materials'!$C$6:$C$505,B16)) | I16: =IF(B16="","",IF(H16-N(G16)>0,H16-N(G16),""))
B17: Tin 4 oz | C17: each | D17: 24 | E17: 19 | F17: =IF(B17="","",N(E17)/IF(N(D17)>0,D17,1)) | G17: 12 | H17: =IF(B17="","",SUMIFS('Product materials'!$G$6:$G$505,'Product materials'!$C$6:$C$505,B17)) | I17: =IF(B17="","",IF(H17-N(G17)>0,H17-N(G17),""))
F18: =IF(B18="","",N(E18)/IF(N(D18)>0,D18,1)) | H18: =IF(B18="","",SUMIFS('Product materials'!$G$6:$G$505,'Product materials'!$C$6:$C$505,B18)) | I18: =IF(B18="","",IF(H18-N(G18)>0,H18-N(G18),""))
F19: =IF(B19="","",N(E19)/IF(N(D19)>0,D19,1)) | H19: =IF(B19="","",SUMIFS('Product materials'!$G$6:$G$505,'Product materials'!$C$6:$C$505,B19)) | I19: =IF(B19="","",IF(H19-N(G19)>0,H19-N(G19),""))
F20: =IF(B20="","",N(E20)/IF(N(D20)>0,D20,1)) | H20: =IF(B20="","",SUMIFS('Product materials'!$G$6:$G$505,'Product materials'!$C$6:$C$505,B20)) | I20: =IF(B20="","",IF(H20-N(G20)>0,H20-N(G20),""))
F21: =IF(B21="","",N(E21)/IF(N(D21)>0,D21,1)) | H21: =IF(B21="","",SUMIFS('Product materials'!$G$6:$G$505,'Product materials'!$C$6:$C$505,B21)) | I21: =IF(B21="","",IF(H21-N(G21)>0,H21-N(G21),""))
F22: =IF(B22="","",N(E22)/IF(N(D22)>0,D22,1)) | H22: =IF(B22="","",SUMIFS('Product materials'!$G$6:$G$505,'Product materials'!$C$6:$C$505,B22)) | I22: =IF(B22="","",IF(H22-N(G22)>0,H22-N(G22),""))
F23: =IF(B23="","",N(E23)/IF(N(D23)>0,D23,1)) | H23: =IF(B23="","",SUMIFS('Product materials'!$G$6:$G$505,'Product materials'!$C$6:$C$505,B23)) | I23: =IF(B23="","",IF(H23-N(G23)>0,H23-N(G23),""))
F24: =IF(B24="","",N(E24)/IF(N(D24)>0,D24,1)) | H24: =IF(B24="","",SUMIFS('Product materials'!$G$6:$G$505,'Product materials'!$C$6:$C$505,B24)) | I24: =IF(B24="","",IF(H24-N(G24)>0,H24-N(G24),""))
F25: =IF(B25="","",N(E25)/IF(N(D25)>0,D25,1)) | H25: =IF(B25="","",SUMIFS('Product materials'!$G$6:$G$505,'Product materials'!$C$6:$C$505,B25)) | I25: =IF(B25="","",IF(H25-N(G25)>0,H25-N(G25),""))
F26: =IF(B26="","",N(E26)/IF(N(D26)>0,D26,1)) | H26: =IF(B26="","",SUMIFS('Product materials'!$G$6:$G$505,'Product materials'!$C$6:$C$505,B26)) | I26: =IF(B26="","",IF(H26-N(G26)>0,H26-N(G26),""))
F27: =IF(B27="","",N(E27)/IF(N(D27)>0,D27,1)) | H27: =IF(B27="","",SUMIFS('Product materials'!$G$6:$G$505,'Product materials'!$C$6:$C$505,B27)) | I27: =IF(B27="","",IF(H27-N(G27)>0,H27-N(G27),""))
F28: =IF(B28="","",N(E28)/IF(N(D28)>0,D28,1)) | H28: =IF(B28="","",SUMIFS('Product materials'!$G$6:$G$505,'Product materials'!$C$6:$C$505,B28)) | I28: =IF(B28="","",IF(H28-N(G28)>0,H28-N(G28),""))
F29: =IF(B29="","",N(E29)/IF(N(D29)>0,D29,1)) | H29: =IF(B29="","",SUMIFS('Product materials'!$G$6:$G$505,'Product materials'!$C$6:$C$505,B29)) | I29: =IF(B29="","",IF(H29-N(G29)>0,H29-N(G29),""))
... F205: =IF(B205="","",N(E205)/IF(N(D205)>0,D205,1)) | H205: =IF(B205="","",SUMIFS('Product materials'!$G$6:$G$505,'Product materials'!$C$6:$C$505,B205)) | I205: =IF(B205="","",IF(H205-N(G205)>0,H205-N(G205),""))

Sheet Customers
B2: Customers
B3: One line per customer. Orders, spending and what they owe come from the Orders tab.
B5: Customer | C5: Email or phone | D5: City | E5: Notes | F5: Orders | G5: Spent | H5: Last order | I5: Owes
B6: Leah Hughes | C6: leah.h@example.com | D6: Local | E6: Wedding in October, 80 guests | F6: =IF(B6="","",COUNTIFS(Orders!$C$6:$C$1005,B6,Orders!$L$6:$L$1005,"<>Cancelled")) | G6: =IF(B6="","",SUMIFS(Orders!$H$6:$H$1005,Orders!$C$6:$C$1005,B6,Orders!$L$6:$L$1005,"<>Cancelled")) | H6: =IF(B6="","",IF(SUMIFS(Orders!$U$6:$U$1005,Orders!$C$6:$C$1005,B6,Orders!$V$6:$V$1005,1)=0,"",INT(SUMIFS(Orders!$U$6:$U$1005,Orders!$C$6:$C$1005,B6,Orders!$V$6:$V$1005,1)))) | I6: =IF(B6="","",IF(SUMIFS(Orders!$J$6:$J$1005,Orders!$C$6:$C$1005,B6)=0,"",SUMIFS(Orders!$J$6:$J$1005,Orders!$C$6:$C$1005,B6)))
B7: Paula Morgan | C7: paula.m@example.com | D7: Denver | F7: =IF(B7="","",COUNTIFS(Orders!$C$6:$C$1005,B7,Orders!$L$6:$L$1005,"<>Cancelled")) | G7: =IF(B7="","",SUMIFS(Orders!$H$6:$H$1005,Orders!$C$6:$C$1005,B7,Orders!$L$6:$L$1005,"<>Cancelled")) | H7: =IF(B7="","",IF(SUMIFS(Orders!$U$6:$U$1005,Orders!$C$6:$C$1005,B7,Orders!$V$6:$V$1005,1)=0,"",INT(SUMIFS(Orders!$U$6:$U$1005,Orders!$C$6:$C$1005,B7,Orders!$V$6:$V$1005,1)))) | I7: =IF(B7="","",IF(SUMIFS(Orders!$J$6:$J$1005,Orders!$C$6:$C$1005,B7)=0,"",SUMIFS(Orders!$J$6:$J$1005,Orders!$C$6:$C$1005,B7)))
B8: Adam Cox | C8: adam.c@example.com | D8: Local | F8: =IF(B8="","",COUNTIFS(Orders!$C$6:$C$1005,B8,Orders!$L$6:$L$1005,"<>Cancelled")) | G8: =IF(B8="","",SUMIFS(Orders!$H$6:$H$1005,Orders!$C$6:$C$1005,B8,Orders!$L$6:$L$1005,"<>Cancelled")) | H8: =IF(B8="","",IF(SUMIFS(Orders!$U$6:$U$1005,Orders!$C$6:$C$1005,B8,Orders!$V$6:$V$1005,1)=0,"",INT(SUMIFS(Orders!$U$6:$U$1005,Orders!$C$6:$C$1005,B8,Orders!$V$6:$V$1005,1)))) | I8: =IF(B8="","",IF(SUMIFS(Orders!$J$6:$J$1005,Orders!$C$6:$C$1005,B8)=0,"",SUMIFS(Orders!$J$6:$J$1005,Orders!$C$6:$C$1005,B8)))
B9: Adam King | C9: adam.k@example.com | D9: Seattle | F9: =IF(B9="","",COUNTIFS(Orders!$C$6:$C$1005,B9,Orders!$L$6:$L$1005,"<>Cancelled")) | G9: =IF(B9="","",SUMIFS(Orders!$H$6:$H$1005,Orders!$C$6:$C$1005,B9,Orders!$L$6:$L$1005,"<>Cancelled")) | H9: =IF(B9="","",IF(SUMIFS(Orders!$U$6:$U$1005,Orders!$C$6:$C$1005,B9,Orders!$V$6:$V$1005,1)=0,"",INT(SUMIFS(Orders!$U$6:$U$1005,Orders!$C$6:$C$1005,B9,Orders!$V$6:$V$1005,1)))) | I9: =IF(B9="","",IF(SUMIFS(Orders!$J$6:$J$1005,Orders!$C$6:$C$1005,B9)=0,"",SUMIFS(Orders!$J$6:$J$1005,Orders!$C$6:$C$1005,B9)))
B10: Dan King | C10: dan.k@example.com | D10: Seattle | F10: =IF(B10="","",COUNTIFS(Orders!$C$6:$C$1005,B10,Orders!$L$6:$L$1005,"<>Cancelled")) | G10: =IF(B10="","",SUMIFS(Orders!$H$6:$H$1005,Orders!$C$6:$C$1005,B10,Orders!$L$6:$L$1005,"<>Cancelled")) | H10: =IF(B10="","",IF(SUMIFS(Orders!$U$6:$U$1005,Orders!$C$6:$C$1005,B10,Orders!$V$6:$V$1005,1)=0,"",INT(SUMIFS(Orders!$U$6:$U$1005,Orders!$C$6:$C$1005,B10,Orders!$V$6:$V$1005,1)))) | I10: =IF(B10="","",IF(SUMIFS(Orders!$J$6:$J$1005,Orders!$C$6:$C$1005,B10)=0,"",SUMIFS(Orders!$J$6:$J$1005,Orders!$C$6:$C$1005,B10)))
B11: Ava Adams | C11: ava.a@example.com | D11: Denver | F11: =IF(B11="","",COUNTIFS(Orders!$C$6:$C$1005,B11,Orders!$L$6:$L$1005,"<>Cancelled")) | G11: =IF(B11="","",SUMIFS(Orders!$H$6:$H$1005,Orders!$C$6:$C$1005,B11,Orders!$L$6:$L$1005,"<>Cancelled")) | H11: =IF(B11="","",IF(SUMIFS(Orders!$U$6:$U$1005,Orders!$C$6:$C$1005,B11,Orders!$V$6:$V$1005,1)=0,"",INT(SUMIFS(Orders!$U$6:$U$1005,Orders!$C$6:$C$1005,B11,Orders!$V$6:$V$1005,1)))) | I11: =IF(B11="","",IF(SUMIFS(Orders!$J$6:$J$1005,Orders!$C$6:$C$1005,B11)=0,"",SUMIFS(Orders!$J$6:$J$1005,Orders!$C$6:$C$1005,B11)))
B12: Ian Hughes | C12: ian.h@example.com | D12: Portland | F12: =IF(B12="","",COUNTIFS(Orders!$C$6:$C$1005,B12,Orders!$L$6:$L$1005,"<>Cancelled")) | G12: =IF(B12="","",SUMIFS(Orders!$H$6:$H$1005,Orders!$C$6:$C$1005,B12,Orders!$L$6:$L$1005,"<>Cancelled")) | H12: =IF(B12="","",IF(SUMIFS(Orders!$U$6:$U$1005,Orders!$C$6:$C$1005,B12,Orders!$V$6:$V$1005,1)=0,"",INT(SUMIFS(Orders!$U$6:$U$1005,Orders!$C$6:$C$1005,B12,Orders!$V$6:$V$1005,1)))) | I12: =IF(B12="","",IF(SUMIFS(Orders!$J$6:$J$1005,Orders!$C$6:$C$1005,B12)=0,"",SUMIFS(Orders!$J$6:$J$1005,Orders!$C$6:$C$1005,B12)))
B13: Jade Reed | C13: jade.r@example.com | D13: Seattle | F13: =IF(B13="","",COUNTIFS(Orders!$C$6:$C$1005,B13,Orders!$L$6:$L$1005,"<>Cancelled")) | G13: =IF(B13="","",SUMIFS(Orders!$H$6:$H$1005,Orders!$C$6:$C$1005,B13,Orders!$L$6:$L$1005,"<>Cancelled")) | H13: =IF(B13="","",IF(SUMIFS(Orders!$U$6:$U$1005,Orders!$C$6:$C$1005,B13,Orders!$V$6:$V$1005,1)=0,"",INT(SUMIFS(Orders!$U$6:$U$1005,Orders!$C$6:$C$1005,B13,Orders!$V$6:$V$1005,1)))) | I13: =IF(B13="","",IF(SUMIFS(Orders!$J$6:$J$1005,Orders!$C$6:$C$1005,B13)=0,"",SUMIFS(Orders!$J$6:$J$1005,Orders!$C$6:$C$1005,B13)))
B14: Beth Owens | C14: beth.o@example.com | D14: Portland | F14: =IF(B14="","",COUNTIFS(Orders!$C$6:$C$1005,B14,Orders!$L$6:$L$1005,"<>Cancelled")) | G14: =IF(B14="","",SUMIFS(Orders!$H$6:$H$1005,Orders!$C$6:$C$1005,B14,Orders!$L$6:$L$1005,"<>Cancelled")) | H14: =IF(B14="","",IF(SUMIFS(Orders!$U$6:$U$1005,Orders!$C$6:$C$1005,B14,Orders!$V$6:$V$1005,1)=0,"",INT(SUMIFS(Orders!$U$6:$U$1005,Orders!$C$6:$C$1005,B14,Orders!$V$6:$V$1005,1)))) | I14: =IF(B14="","",IF(SUMIFS(Orders!$J$6:$J$1005,Orders!$C$6:$C$1005,B14)=0,"",SUMIFS(Orders!$J$6:$J$1005,Orders!$C$6:$C$1005,B14)))
B15: Rita Price | C15: rita.p@example.com | D15: Local | F15: =IF(B15="","",COUNTIFS(Orders!$C$6:$C$1005,B15,Orders!$L$6:$L$1005,"<>Cancelled")) | G15: =IF(B15="","",SUMIFS(Orders!$H$6:$H$1005,Orders!$C$6:$C$1005,B15,Orders!$L$6:$L$1005,"<>Cancelled")) | H15: =IF(B15="","",IF(SUMIFS(Orders!$U$6:$U$1005,Orders!$C$6:$C$1005,B15,Orders!$V$6:$V$1005,1)=0,"",INT(SUMIFS(Orders!$U$6:$U$1005,Orders!$C$6:$C$1005,B15,Orders!$V$6:$V$1005,1)))) | I15: =IF(B15="","",IF(SUMIFS(Orders!$J$6:$J$1005,Orders!$C$6:$C$1005,B15)=0,"",SUMIFS(Orders!$J$6:$J$1005,Orders!$C$6:$C$1005,B15)))
B16: Paula Mills | C16: paula.m@example.com | D16: Austin | F16: =IF(B16="","",COUNTIFS(Orders!$C$6:$C$1005,B16,Orders!$L$6:$L$1005,"<>Cancelled")) | G16: =IF(B16="","",SUMIFS(Orders!$H$6:$H$1005,Orders!$C$6:$C$1005,B16,Orders!$L$6:$L$1005,"<>Cancelled")) | H16: =IF(B16="","",IF(SUMIFS(Orders!$U$6:$U$1005,Orders!$C$6:$C$1005,B16,Orders!$V$6:$V$1005,1)=0,"",INT(SUMIFS(Orders!$U$6:$U$1005,Orders!$C$6:$C$1005,B16,Orders!$V$6:$V$1005,1)))) | I16: =IF(B16="","",IF(SUMIFS(Orders!$J$6:$J$1005,Orders!$C$6:$C$1005,B16)=0,"",SUMIFS(Orders!$J$6:$J$1005,Orders!$C$6:$C$1005,B16)))
B17: Lily Gray | C17: lily.g@example.com | D17: Boston | F17: =IF(B17="","",COUNTIFS(Orders!$C$6:$C$1005,B17,Orders!$L$6:$L$1005,"<>Cancelled")) | G17: =IF(B17="","",SUMIFS(Orders!$H$6:$H$1005,Orders!$C$6:$C$1005,B17,Orders!$L$6:$L$1005,"<>Cancelled")) | H17: =IF(B17="","",IF(SUMIFS(Orders!$U$6:$U$1005,Orders!$C$6:$C$1005,B17,Orders!$V$6:$V$1005,1)=0,"",INT(SUMIFS(Orders!$U$6:$U$1005,Orders!$C$6:$C$1005,B17,Orders!$V$6:$V$1005,1)))) | I17: =IF(B17="","",IF(SUMIFS(Orders!$J$6:$J$1005,Orders!$C$6:$C$1005,B17)=0,"",SUMIFS(Orders!$J$6:$J$1005,Orders!$C$6:$C$1005,B17)))
B18: Chris Owens | C18: chris.o@example.com | D18: Portland | F18: =IF(B18="","",COUNTIFS(Orders!$C$6:$C$1005,B18,Orders!$L$6:$L$1005,"<>Cancelled")) | G18: =IF(B18="","",SUMIFS(Orders!$H$6:$H$1005,Orders!$C$6:$C$1005,B18,Orders!$L$6:$L$1005,"<>Cancelled")) | H18: =IF(B18="","",IF(SUMIFS(Orders!$U$6:$U$1005,Orders!$C$6:$C$1005,B18,Orders!$V$6:$V$1005,1)=0,"",INT(SUMIFS(Orders!$U$6:$U$1005,Orders!$C$6:$C$1005,B18,Orders!$V$6:$V$1005,1)))) | I18: =IF(B18="","",IF(SUMIFS(Orders!$J$6:$J$1005,Orders!$C$6:$C$1005,B18)=0,"",SUMIFS(Orders!$J$6:$J$1005,Orders!$C$6:$C$1005,B18)))
... B75: Hannah Cole | C75: hannah.c@example.com | D75: Seattle | F75: =IF(B75="","",COUNTIFS(Orders!$C$6:$C$1005,B75,Orders!$L$6:$L$1005,"<>Cancelled")) | G75: =IF(B75="","",SUMIFS(Orders!$H$6:$H$1005,Orders!$C$6:$C$1005,B75,Orders!$L$6:$L$1005,"<>Cancelled")) | H75: =IF(B75="","",IF(SUMIFS(Orders!$U$6:$U$1005,Orders!$C$6:$C$1005,B75,Orders!$V$6:$V$1005,1)=0,"",INT(SUMIFS(Orders!$U$6:$U$1005,Orders!$C$6:$C$1005,B75,Orders!$V$6:$V$1005,1)))) | I75: =IF(B75="","",IF(SUMIFS(Orders!$J$6:$J$1005,Orders!$C$6:$C$1005,B75)=0,"",SUMIFS(Orders!$J$6:$J$1005,Orders!$C$6:$C$1005,B75)))
F76: =IF(B76="","",COUNTIFS(Orders!$C$6:$C$1005,B76,Orders!$L$6:$L$1005,"<>Cancelled")) | G76: =IF(B76="","",SUMIFS(Orders!$H$6:$H$1005,Orders!$C$6:$C$1005,B76,Orders!$L$6:$L$1005,"<>Cancelled")) | H76: =IF(B76="","",IF(SUMIFS(Orders!$U$6:$U$1005,Orders!$C$6:$C$1005,B76,Orders!$V$6:$V$1005,1)=0,"",INT(SUMIFS(Orders!$U$6:$U$1005,Orders!$C$6:$C$1005,B76,Orders!$V$6:$V$1005,1)))) | I76: =IF(B76="","",IF(SUMIFS(Orders!$J$6:$J$1005,Orders!$C$6:$C$1005,B76)=0,"",SUMIFS(Orders!$J$6:$J$1005,Orders!$C$6:$C$1005,B76)))
F77: =IF(B77="","",COUNTIFS(Orders!$C$6:$C$1005,B77,Orders!$L$6:$L$1005,"<>Cancelled")) | G77: =IF(B77="","",SUMIFS(Orders!$H$6:$H$1005,Orders!$C$6:$C$1005,B77,Orders!$L$6:$L$1005,"<>Cancelled")) | H77: =IF(B77="","",IF(SUMIFS(Orders!$U$6:$U$1005,Orders!$C$6:$C$1005,B77,Orders!$V$6:$V$1005,1)=0,"",INT(SUMIFS(Orders!$U$6:$U$1005,Orders!$C$6:$C$1005,B77,Orders!$V$6:$V$1005,1)))) | I77: =IF(B77="","",IF(SUMIFS(Orders!$J$6:$J$1005,Orders!$C$6:$C$1005,B77)=0,"",SUMIFS(Orders!$J$6:$J$1005,Orders!$C$6:$C$1005,B77)))
F78: =IF(B78="","",COUNTIFS(Orders!$C$6:$C$1005,B78,Orders!$L$6:$L$1005,"<>Cancelled")) | G78: =IF(B78="","",SUMIFS(Orders!$H$6:$H$1005,Orders!$C$6:$C$1005,B78,Orders!$L$6:$L$1005,"<>Cancelled")) | H78: =IF(B78="","",IF(SUMIFS(Orders!$U$6:$U$1005,Orders!$C$6:$C$1005,B78,Orders!$V$6:$V$1005,1)=0,"",INT(SUMIFS(Orders!$U$6:$U$1005,Orders!$C$6:$C$1005,B78,Orders!$V$6:$V$1005,1)))) | I78: =IF(B78="","",IF(SUMIFS(Orders!$J$6:$J$1005,Orders!$C$6:$C$1005,B78)=0,"",SUMIFS(Orders!$J$6:$J$1005,Orders!$C$6:$C$1005,B78)))
F79: =IF(B79="","",COUNTIFS(Orders!$C$6:$C$1005,B79,Orders!$L$6:$L$1005,"<>Cancelled")) | G79: =IF(B79="","",SUMIFS(Orders!$H$6:$H$1005,Orders!$C$6:$C$1005,B79,Orders!$L$6:$L$1005,"<>Cancelled")) | H79: =IF(B79="","",IF(SUMIFS(Orders!$U$6:$U$1005,Orders!$C$6:$C$1005,B79,Orders!$V$6:$V$1005,1)=0,"",INT(SUMIFS(Orders!$U$6:$U$1005,Orders!$C$6:$C$1005,B79,Orders!$V$6:$V$1005,1)))) | I79: =IF(B79="","",IF(SUMIFS(Orders!$J$6:$J$1005,Orders!$C$6:$C$1005,B79)=0,"",SUMIFS(Orders!$J$6:$J$1005,Orders!$C$6:$C$1005,B79)))
F80: =IF(B80="","",COUNTIFS(Orders!$C$6:$C$1005,B80,Orders!$L$6:$L$1005,"<>Cancelled")) | G80: =IF(B80="","",SUMIFS(Orders!$H$6:$H$1005,Orders!$C$6:$C$1005,B80,Orders!$L$6:$L$1005,"<>Cancelled")) | H80: =IF(B80="","",IF(SUMIFS(Orders!$U$6:$U$1005,Orders!$C$6:$C$1005,B80,Orders!$V$6:$V$1005,1)=0,"",INT(SUMIFS(Orders!$U$6:$U$1005,Orders!$C$6:$C$1005,B80,Orders!$V$6:$V$1005,1)))) | I80: =IF(B80="","",IF(SUMIFS(Orders!$J$6:$J$1005,Orders!$C$6:$C$1005,B80)=0,"",SUMIFS(Orders!$J$6:$J$1005,Orders!$C$6:$C$1005,B80)))
F81: =IF(B81="","",COUNTIFS(Orders!$C$6:$C$1005,B81,Orders!$L$6:$L$1005,"<>Cancelled")) | G81: =IF(B81="","",SUMIFS(Orders!$H$6:$H$1005,Orders!$C$6:$C$1005,B81,Orders!$L$6:$L$1005,"<>Cancelled")) | H81: =IF(B81="","",IF(SUMIFS(Orders!$U$6:$U$1005,Orders!$C$6:$C$1005,B81,Orders!$V$6:$V$1005,1)=0,"",INT(SUMIFS(Orders!$U$6:$U$1005,Orders!$C$6:$C$1005,B81,Orders!$V$6:$V$1005,1)))) | I81: =IF(B81="","",IF(SUMIFS(Orders!$J$6:$J$1005,Orders!$C$6:$C$1005,B81)=0,"",SUMIFS(Orders!$J$6:$J$1005,Orders!$C$6:$C$1005,B81)))
F82: =IF(B82="","",COUNTIFS(Orders!$C$6:$C$1005,B82,Orders!$L$6:$L$1005,"<>Cancelled")) | G82: =IF(B82="","",SUMIFS(Orders!$H$6:$H$1005,Orders!$C$6:$C$1005,B82,Orders!$L$6:$L$1005,"<>Cancelled")) | H82: =IF(B82="","",IF(SUMIFS(Orders!$U$6:$U$1005,Orders!$C$6:$C$1005,B82,Orders!$V$6:$V$1005,1)=0,"",INT(SUMIFS(Orders!$U$6:$U$1005,Orders!$C$6:$C$1005,B82,Orders!$V$6:$V$1005,1)))) | I82: =IF(B82="","",IF(SUMIFS(Orders!$J$6:$J$1005,Orders!$C$6:$C$1005,B82)=0,"",SUMIFS(Orders!$J$6:$J$1005,Orders!$C$6:$C$1005,B82)))
F83: =IF(B83="","",COUNTIFS(Orders!$C$6:$C$1005,B83,Orders!$L$6:$L$1005,"<>Cancelled")) | G83: =IF(B83="","",SUMIFS(Orders!$H$6:$H$1005,Orders!$C$6:$C$1005,B83,Orders!$L$6:$L$1005,"<>Cancelled")) | H83: =IF(B83="","",IF(SUMIFS(Orders!$U$6:$U$1005,Orders!$C$6:$C$1005,B83,Orders!$V$6:$V$1005,1)=0,"",INT(SUMIFS(Orders!$U$6:$U$1005,Orders!$C$6:$C$1005,B83,Orders!$V$6:$V$1005,1)))) | I83: =IF(B83="","",IF(SUMIFS(Orders!$J$6:$J$1005,Orders!$C$6:$C$1005,B83)=0,"",SUMIFS(Orders!$J$6:$J$1005,Orders!$C$6:$C$1005,B83)))
F84: =IF(B84="","",COUNTIFS(Orders!$C$6:$C$1005,B84,Orders!$L$6:$L$1005,"<>Cancelled")) | G84: =IF(B84="","",SUMIFS(Orders!$H$6:$H$1005,Orders!$C$6:$C$1005,B84,Orders!$L$6:$L$1005,"<>Cancelled")) | H84: =IF(B84="","",IF(SUMIFS(Orders!$U$6:$U$1005,Orders!$C$6:$C$1005,B84,Orders!$V$6:$V$1005,1)=0,"",INT(SUMIFS(Orders!$U$6:$U$1005,Orders!$C$6:$C$1005,B84,Orders!$V$6:$V$1005,1)))) | I84: =IF(B84="","",IF(SUMIFS(Orders!$J$6:$J$1005,Orders!$C$6:$C$1005,B84)=0,"",SUMIFS(Orders!$J$6:$J$1005,Orders!$C$6:$C$1005,B84)))
F85: =IF(B85="","",COUNTIFS(Orders!$C$6:$C$1005,B85,Orders!$L$6:$L$1005,"<>Cancelled")) | G85: =IF(B85="","",SUMIFS(Orders!$H$6:$H$1005,Orders!$C$6:$C$1005,B85,Orders!$L$6:$L$1005,"<>Cancelled")) | H85: =IF(B85="","",IF(SUMIFS(Orders!$U$6:$U$1005,Orders!$C$6:$C$1005,B85,Orders!$V$6:$V$1005,1)=0,"",INT(SUMIFS(Orders!$U$6:$U$1005,Orders!$C$6:$C$1005,B85,Orders!$V$6:$V$1005,1)))) | I85: =IF(B85="","",IF(SUMIFS(Orders!$J$6:$J$1005,Orders!$C$6:$C$1005,B85)=0,"",SUMIFS(Orders!$J$6:$J$1005,Orders!$C$6:$C$1005,B85)))
F86: =IF(B86="","",COUNTIFS(Orders!$C$6:$C$1005,B86,Orders!$L$6:$L$1005,"<>Cancelled")) | G86: =IF(B86="","",SUMIFS(Orders!$H$6:$H$1005,Orders!$C$6:$C$1005,B86,Orders!$L$6:$L$1005,"<>Cancelled")) | H86: =IF(B86="","",IF(SUMIFS(Orders!$U$6:$U$1005,Orders!$C$6:$C$1005,B86,Orders!$V$6:$V$1005,1)=0,"",INT(SUMIFS(Orders!$U$6:$U$1005,Orders!$C$6:$C$1005,B86,Orders!$V$6:$V$1005,1)))) | I86: =IF(B86="","",IF(SUMIFS(Orders!$J$6:$J$1005,Orders!$C$6:$C$1005,B86)=0,"",SUMIFS(Orders!$J$6:$J$1005,Orders!$C$6:$C$1005,B86)))
F87: =IF(B87="","",COUNTIFS(Orders!$C$6:$C$1005,B87,Orders!$L$6:$L$1005,"<>Cancelled")) | G87: =IF(B87="","",SUMIFS(Orders!$H$6:$H$1005,Orders!$C$6:$C$1005,B87,Orders!$L$6:$L$1005,"<>Cancelled")) | H87: =IF(B87="","",IF(SUMIFS(Orders!$U$6:$U$1005,Orders!$C$6:$C$1005,B87,Orders!$V$6:$V$1005,1)=0,"",INT(SUMIFS(Orders!$U$6:$U$1005,Orders!$C$6:$C$1005,B87,Orders!$V$6:$V$1005,1)))) | I87: =IF(B87="","",IF(SUMIFS(Orders!$J$6:$J$1005,Orders!$C$6:$C$1005,B87)=0,"",SUMIFS(Orders!$J$6:$J$1005,Orders!$C$6:$C$1005,B87)))
... F505: =IF(B505="","",COUNTIFS(Orders!$C$6:$C$1005,B505,Orders!$L$6:$L$1005,"<>Cancelled")) | G505: =IF(B505="","",SUMIFS(Orders!$H$6:$H$1005,Orders!$C$6:$C$1005,B505,Orders!$L$6:$L$1005,"<>Cancelled")) | H505: =IF(B505="","",IF(SUMIFS(Orders!$U$6:$U$1005,Orders!$C$6:$C$1005,B505,Orders!$V$6:$V$1005,1)=0,"",INT(SUMIFS(Orders!$U$6:$U$1005,Orders!$C$6:$C$1005,B505,Orders!$V$6:$V$1005,1)))) | I505: =IF(B505="","",IF(SUMIFS(Orders!$J$6:$J$1005,Orders!$C$6:$C$1005,B505)=0,"",SUMIFS(Orders!$J$6:$J$1005,Orders!$C$6:$C$1005,B505)))

Sheet Settings
B2: Settings
