Workbook

Sheet Dashboard
B2: Your freelance year at a glance
B3: Only the Settings year counts. Paid income only.
B6: Paid income | C6: Expenses | D6: Profit | E6: To put aside for tax | F6: Already put aside | H6: Still to put aside
B7: =SUMIFS(Income!$E$6:$E$305,Income!$F$6:$F$305,">="&DATE(Settings!$C$6,1,1),Income!$F$6:$F$305,"<="&DATE(Settings!$C$6,12,31)) | C7: =SUMIFS(Expenses!$E$6:$E$505,Expenses!$B$6:$B$505,">="&DATE(Settings!$C$6,1,1),Expenses!$B$6:$B$505,"<="&DATE(Settings!$C$6,12,31)) | D7: =B7-C7 | E7: =MAX(0,D7)*Settings!$C$8/100 | F7: =SUMIFS('Tax Savings'!$C$6:$C$105,'Tax Savings'!$B$6:$B$105,">="&DATE(Settings!$C$6,1,1),'Tax Savings'!$B$6:$B$105,"<="&DATE(Settings!$C$6,12,31)) | H7: =MAX(0,E7-F7)
B9: Quarter | C9: Paid income | D9: Expenses | E9: Profit | F9: Tax share | H9: Heads-up
B10: Q1 | C10: =SUMIFS(Income!$E$6:$E$305,Income!$F$6:$F$305,">="&DATE(Settings!$C$6,1,1),Income!$F$6:$F$305,"<="&EOMONTH(DATE(Settings!$C$6,3,1),0)) | D10: =SUMIFS(Expenses!$E$6:$E$505,Expenses!$B$6:$B$505,">="&DATE(Settings!$C$6,1,1),Expenses!$B$6:$B$505,"<="&EOMONTH(DATE(Settings!$C$6,3,1),0)) | E10: =C10-D10 | F10: =MAX(0,E10)*Settings!$C$8/100 | H10: =COUNTIFS(Income!$G$6:$G$305,"⚠*")&" overdue invoice(s): "&FIXED(SUMIFS(Income!$E$6:$E$305,Income!$G$6:$G$305,"⚠*"),2)
B11: Q2 | C11: =SUMIFS(Income!$E$6:$E$305,Income!$F$6:$F$305,">="&DATE(Settings!$C$6,4,1),Income!$F$6:$F$305,"<="&EOMONTH(DATE(Settings!$C$6,6,1),0)) | D11: =SUMIFS(Expenses!$E$6:$E$505,Expenses!$B$6:$B$505,">="&DATE(Settings!$C$6,4,1),Expenses!$B$6:$B$505,"<="&EOMONTH(DATE(Settings!$C$6,6,1),0)) | E11: =C11-D11 | F11: =MAX(0,E11)*Settings!$C$8/100 | H11: =COUNTIFS(Income!$G$6:$G$305,"Waiting*")&" invoice(s) waiting: "&FIXED(SUMIFS(Income!$E$6:$E$305,Income!$G$6:$G$305,"Waiting*"),2)
B12: Q3 | C12: =SUMIFS(Income!$E$6:$E$305,Income!$F$6:$F$305,">="&DATE(Settings!$C$6,7,1),Income!$F$6:$F$305,"<="&EOMONTH(DATE(Settings!$C$6,9,1),0)) | D12: =SUMIFS(Expenses!$E$6:$E$505,Expenses!$B$6:$B$505,">="&DATE(Settings!$C$6,7,1),Expenses!$B$6:$B$505,"<="&EOMONTH(DATE(Settings!$C$6,9,1),0)) | E12: =C12-D12 | F12: =MAX(0,E12)*Settings!$C$8/100 | H12: =COUNTIFS(Expenses!$B$6:$B$505,"<>",Expenses!$F$6:$F$505,"<>TRUE")&" expense(s) without a receipt"
B13: Q4 | C13: =SUMIFS(Income!$E$6:$E$305,Income!$F$6:$F$305,">="&DATE(Settings!$C$6,10,1),Income!$F$6:$F$305,"<="&EOMONTH(DATE(Settings!$C$6,12,1),0)) | D13: =SUMIFS(Expenses!$E$6:$E$505,Expenses!$B$6:$B$505,">="&DATE(Settings!$C$6,10,1),Expenses!$B$6:$B$505,"<="&EOMONTH(DATE(Settings!$C$6,12,1),0)) | E13: =C13-D13 | F13: =MAX(0,E13)*Settings!$C$8/100 | H13: ="Tax set-aside progress: "&IF(E7=0,"—",FIXED(MIN(1,F7/E7)*100,0)&"%")
B16: Expense category | C16: This year | D16: Share
B17: =Settings!B14 | C17: =SUMIFS(Expenses!$E$6:$E$505,Expenses!$D$6:$D$505,B17,Expenses!$B$6:$B$505,">="&DATE(Settings!$C$6,1,1),Expenses!$B$6:$B$505,"<="&DATE(Settings!$C$6,12,31)) | D17: =REPT("█",ROUND(IF($C$7=0,0,C17/$C$7)*15,0))&" "&TEXT(IF($C$7=0,0,C17/$C$7),"0%")
B18: =Settings!B15 | C18: =SUMIFS(Expenses!$E$6:$E$505,Expenses!$D$6:$D$505,B18,Expenses!$B$6:$B$505,">="&DATE(Settings!$C$6,1,1),Expenses!$B$6:$B$505,"<="&DATE(Settings!$C$6,12,31)) | D18: =REPT("█",ROUND(IF($C$7=0,0,C18/$C$7)*15,0))&" "&TEXT(IF($C$7=0,0,C18/$C$7),"0%")
B19: =Settings!B16 | C19: =SUMIFS(Expenses!$E$6:$E$505,Expenses!$D$6:$D$505,B19,Expenses!$B$6:$B$505,">="&DATE(Settings!$C$6,1,1),Expenses!$B$6:$B$505,"<="&DATE(Settings!$C$6,12,31)) | D19: =REPT("█",ROUND(IF($C$7=0,0,C19/$C$7)*15,0))&" "&TEXT(IF($C$7=0,0,C19/$C$7),"0%")
B20: =Settings!B17 | C20: =SUMIFS(Expenses!$E$6:$E$505,Expenses!$D$6:$D$505,B20,Expenses!$B$6:$B$505,">="&DATE(Settings!$C$6,1,1),Expenses!$B$6:$B$505,"<="&DATE(Settings!$C$6,12,31)) | D20: =REPT("█",ROUND(IF($C$7=0,0,C20/$C$7)*15,0))&" "&TEXT(IF($C$7=0,0,C20/$C$7),"0%")
B21: =Settings!B18 | C21: =SUMIFS(Expenses!$E$6:$E$505,Expenses!$D$6:$D$505,B21,Expenses!$B$6:$B$505,">="&DATE(Settings!$C$6,1,1),Expenses!$B$6:$B$505,"<="&DATE(Settings!$C$6,12,31)) | D21: =REPT("█",ROUND(IF($C$7=0,0,C21/$C$7)*15,0))&" "&TEXT(IF($C$7=0,0,C21/$C$7),"0%")
B22: =Settings!B19 | C22: =SUMIFS(Expenses!$E$6:$E$505,Expenses!$D$6:$D$505,B22,Expenses!$B$6:$B$505,">="&DATE(Settings!$C$6,1,1),Expenses!$B$6:$B$505,"<="&DATE(Settings!$C$6,12,31)) | D22: =REPT("█",ROUND(IF($C$7=0,0,C22/$C$7)*15,0))&" "&TEXT(IF($C$7=0,0,C22/$C$7),"0%")
B23: =Settings!B20 | C23: =SUMIFS(Expenses!$E$6:$E$505,Expenses!$D$6:$D$505,B23,Expenses!$B$6:$B$505,">="&DATE(Settings!$C$6,1,1),Expenses!$B$6:$B$505,"<="&DATE(Settings!$C$6,12,31)) | D23: =REPT("█",ROUND(IF($C$7=0,0,C23/$C$7)*15,0))&" "&TEXT(IF($C$7=0,0,C23/$C$7),"0%")
B24: =Settings!B21 | C24: =SUMIFS(Expenses!$E$6:$E$505,Expenses!$D$6:$D$505,B24,Expenses!$B$6:$B$505,">="&DATE(Settings!$C$6,1,1),Expenses!$B$6:$B$505,"<="&DATE(Settings!$C$6,12,31)) | D24: =REPT("█",ROUND(IF($C$7=0,0,C24/$C$7)*15,0))&" "&TEXT(IF($C$7=0,0,C24/$C$7),"0%")
B25: =Settings!B22 | C25: =SUMIFS(Expenses!$E$6:$E$505,Expenses!$D$6:$D$505,B25,Expenses!$B$6:$B$505,">="&DATE(Settings!$C$6,1,1),Expenses!$B$6:$B$505,"<="&DATE(Settings!$C$6,12,31)) | D25: =REPT("█",ROUND(IF($C$7=0,0,C25/$C$7)*15,0))&" "&TEXT(IF($C$7=0,0,C25/$C$7),"0%")

Sheet Settings
B2: Settings
B3: Set these once a year.
B6: Year | C6: 2026
B8: Share of profit to put aside for tax (%) | C8: 25 | E8: Ask your accountant or tax office for your rate; 25-30% is a common cautious choice.
B10: Invoice is overdue after (days) | C10: 30
B13: Expense categories
B14: Software & tools
B15: Equipment
B16: Travel
B17: Phone & internet
B18: Office & coworking
B19: Training
B20: Marketing
B21: Bank & fees
B22: Other

Sheet Income
B2: Income: one line per invoice
B3: Leave 'Paid on' empty until the money arrives.
B5: Invoice date | C5: Client | D5: Invoice # | E5: Amount | F5: Paid on | G5: Status
B6: 46093 | C6: Studio North | D6: 2026-009 | E6: 1600 | F6: 46108 | G6: =IF(OR(B6="",E6=""),"",IF(F6<>"","✓ Paid",IF(TODAY()-B6>Settings!$C$10,"⚠ Overdue "&(TODAY()-B6-Settings!$C$10)&" day(s)","Waiting "&(TODAY()-B6)&" day(s)")))
B7: 46143 | C7: Acme Co | D7: 2026-011 | E7: 2200 | F7: 46165 | G7: =IF(OR(B7="",E7=""),"",IF(F7<>"","✓ Paid",IF(TODAY()-B7>Settings!$C$10,"⚠ Overdue "&(TODAY()-B7-Settings!$C$10)&" day(s)","Waiting "&(TODAY()-B7)&" day(s)")))
B8: 46213 | C8: Studio North | D8: 2026-014 | E8: 1800 | F8: 46223 | G8: =IF(OR(B8="",E8=""),"",IF(F8<>"","✓ Paid",IF(TODAY()-B8>Settings!$C$10,"⚠ Overdue "&(TODAY()-B8-Settings!$C$10)&" day(s)","Waiting "&(TODAY()-B8)&" day(s)")))
B9: 46231 | C9: Acme Co | D9: 2026-015 | E9: 950 | F9: 46253 | G9: =IF(OR(B9="",E9=""),"",IF(F9<>"","✓ Paid",IF(TODAY()-B9>Settings!$C$10,"⚠ Overdue "&(TODAY()-B9-Settings!$C$10)&" day(s)","Waiting "&(TODAY()-B9)&" day(s)")))
B10: 46248 | C10: Lumen Agency | D10: 2026-016 | E10: 2400 | F10: 46273 | G10: =IF(OR(B10="",E10=""),"",IF(F10<>"","✓ Paid",IF(TODAY()-B10>Settings!$C$10,"⚠ Overdue "&(TODAY()-B10-Settings!$C$10)&" day(s)","Waiting "&(TODAY()-B10)&" day(s)")))
B11: 46255 | C11: Studio North | D11: 2026-017 | E11: 1200 | G11: =IF(OR(B11="",E11=""),"",IF(F11<>"","✓ Paid",IF(TODAY()-B11>Settings!$C$10,"⚠ Overdue "&(TODAY()-B11-Settings!$C$10)&" day(s)","Waiting "&(TODAY()-B11)&" day(s)")))
B12: 46281 | C12: Pixel & Co | D12: 2026-018 | E12: 640 | G12: =IF(OR(B12="",E12=""),"",IF(F12<>"","✓ Paid",IF(TODAY()-B12>Settings!$C$10,"⚠ Overdue "&(TODAY()-B12-Settings!$C$10)&" day(s)","Waiting "&(TODAY()-B12)&" day(s)")))
B13: 46290 | C13: Acme Co | D13: 2026-019 | E13: 1500 | G13: =IF(OR(B13="",E13=""),"",IF(F13<>"","✓ Paid",IF(TODAY()-B13>Settings!$C$10,"⚠ Overdue "&(TODAY()-B13-Settings!$C$10)&" day(s)","Waiting "&(TODAY()-B13)&" day(s)")))
G14: =IF(OR(B14="",E14=""),"",IF(F14<>"","✓ Paid",IF(TODAY()-B14>Settings!$C$10,"⚠ Overdue "&(TODAY()-B14-Settings!$C$10)&" day(s)","Waiting "&(TODAY()-B14)&" day(s)")))
G15: =IF(OR(B15="",E15=""),"",IF(F15<>"","✓ Paid",IF(TODAY()-B15>Settings!$C$10,"⚠ Overdue "&(TODAY()-B15-Settings!$C$10)&" day(s)","Waiting "&(TODAY()-B15)&" day(s)")))
G16: =IF(OR(B16="",E16=""),"",IF(F16<>"","✓ Paid",IF(TODAY()-B16>Settings!$C$10,"⚠ Overdue "&(TODAY()-B16-Settings!$C$10)&" day(s)","Waiting "&(TODAY()-B16)&" day(s)")))
G17: =IF(OR(B17="",E17=""),"",IF(F17<>"","✓ Paid",IF(TODAY()-B17>Settings!$C$10,"⚠ Overdue "&(TODAY()-B17-Settings!$C$10)&" day(s)","Waiting "&(TODAY()-B17)&" day(s)")))
G18: =IF(OR(B18="",E18=""),"",IF(F18<>"","✓ Paid",IF(TODAY()-B18>Settings!$C$10,"⚠ Overdue "&(TODAY()-B18-Settings!$C$10)&" day(s)","Waiting "&(TODAY()-B18)&" day(s)")))
G19: =IF(OR(B19="",E19=""),"",IF(F19<>"","✓ Paid",IF(TODAY()-B19>Settings!$C$10,"⚠ Overdue "&(TODAY()-B19-Settings!$C$10)&" day(s)","Waiting "&(TODAY()-B19)&" day(s)")))
G20: =IF(OR(B20="",E20=""),"",IF(F20<>"","✓ Paid",IF(TODAY()-B20>Settings!$C$10,"⚠ Overdue "&(TODAY()-B20-Settings!$C$10)&" day(s)","Waiting "&(TODAY()-B20)&" day(s)")))
G21: =IF(OR(B21="",E21=""),"",IF(F21<>"","✓ Paid",IF(TODAY()-B21>Settings!$C$10,"⚠ Overdue "&(TODAY()-B21-Settings!$C$10)&" day(s)","Waiting "&(TODAY()-B21)&" day(s)")))
G22: =IF(OR(B22="",E22=""),"",IF(F22<>"","✓ Paid",IF(TODAY()-B22>Settings!$C$10,"⚠ Overdue "&(TODAY()-B22-Settings!$C$10)&" day(s)","Waiting "&(TODAY()-B22)&" day(s)")))
G23: =IF(OR(B23="",E23=""),"",IF(F23<>"","✓ Paid",IF(TODAY()-B23>Settings!$C$10,"⚠ Overdue "&(TODAY()-B23-Settings!$C$10)&" day(s)","Waiting "&(TODAY()-B23)&" day(s)")))
G24: =IF(OR(B24="",E24=""),"",IF(F24<>"","✓ Paid",IF(TODAY()-B24>Settings!$C$10,"⚠ Overdue "&(TODAY()-B24-Settings!$C$10)&" day(s)","Waiting "&(TODAY()-B24)&" day(s)")))
G25: =IF(OR(B25="",E25=""),"",IF(F25<>"","✓ Paid",IF(TODAY()-B25>Settings!$C$10,"⚠ Overdue "&(TODAY()-B25-Settings!$C$10)&" day(s)","Waiting "&(TODAY()-B25)&" day(s)")))
... G305: =IF(OR(B305="",E305=""),"",IF(F305<>"","✓ Paid",IF(TODAY()-B305>Settings!$C$10,"⚠ Overdue "&(TODAY()-B305-Settings!$C$10)&" day(s)","Waiting "&(TODAY()-B305)&" day(s)")))

Sheet Expenses
B2: Expenses: one line per purchase
B3: Keep the receipt: tick 'Receipt?' when you have it.
B5: Date | C5: What | D5: Category | E5: Amount | F5: Receipt? | G5: Note
B6: 46103 | C6: Laptop repair | D6: Equipment | E6: 180 | F6: TRUE
B7: 46153 | C7: Accounting software | D7: Software & tools | E7: 96 | F7: TRUE | G7: yearly
B8: 46218 | C8: Design app yearly plan | D8: Software & tools | E8: 239 | F8: TRUE
B9: 46233 | C9: Train to client workshop | D9: Travel | E9: 86.4 | F9: TRUE
B10: 46252 | C10: Phone plan | D10: Phone & internet | E10: 19.99 | F10: TRUE | G10: monthly
B11: 46260 | C11: Monitor | D11: Equipment | E11: 329 | F11: FALSE | G11: find the invoice!
B12: 46273 | C12: Coworking day passes | D12: Office & coworking | E12: 75 | F12: TRUE
B13: 46284 | C13: Online course | D13: Training | E13: 120 | F13: TRUE

Sheet Tax Savings
B2: Money put aside for tax
B3: Each time you move money to your tax savings, add a line.
B5: Date | C5: Amount | D5: Note
B6: 46113 | C6: 400 | D6: Q1 set-aside
B7: 46173 | C7: 500 | D7: Q2 set-aside
B8: 46258 | C8: 600 | D8: from Acme + Lumen

Sheet Start Here
B2: Start here: 5 minutes
B3: Only type in YELLOW cells.
B5: 1 | C5: Settings: the year, and the share of profit you put aside for tax (ask your accountant; 25-30% is cautious).
B7: 2 | C7: Income: one line per invoice. Fill 'Paid on' when the money arrives. Late invoices turn red.
B9: 3 | C9: Expenses: one line per business purchase. Tick 'Receipt?' when you have the receipt.
B11: 4 | C11: Tax Savings: each time you move money aside for tax, add a line.
B13: ★ | C13: Dashboard: profit, what to put aside, what is still missing, quarter by quarter.
C17: This is a tracking tool, not tax advice. Tax rules differ by country: check your rate with an accountant.
C19: Works in Google Sheets and Microsoft Excel. Example lines show how it works: delete them and add yours.
