Workbook

Sheet Dashboard
B2: Giving and volunteering
B3: ="The year "&Settings!$C$7&", with the campaigns and the thank-you notes still to send."
B4: Given this year | C4: Gifts | D4: Average gift | E4: Donors | G4: New donors | H4: Lapsed | I4: To thank | J4: Volunteer hours
B5: =SUMIFS(Gifts!$D$6:$D$1005,Gifts!$K$6:$K$1005,Settings!$C$7,Gifts!$D$6:$D$1005,">0") | C5: =SUMIFS(Gifts!$Q$6:$Q$1005,Gifts!$K$6:$K$1005,Settings!$C$7) | D5: =IF(COUNTIFS(Gifts!$K$6:$K$1005,Settings!$C$7,Gifts!$D$6:$D$1005,">0")=0,"",B5/COUNTIFS(Gifts!$K$6:$K$1005,Settings!$C$7,Gifts!$D$6:$D$1005,">0")) | E5: =COUNTIF(Donors!$N$6:$N$305,">0") | G5: =COUNTIFS(Donors!$F$6:$F$305,">="&DATE(N(Settings!$C$7),1,1),Donors!$F$6:$F$305,"<"&DATE(N(Settings!$C$7)+1,1,1)) | H5: =COUNTIF(Donors!$K$6:$K$305,"Lapsed") | I5: =COUNT(Gifts!$O$6:$O$1005) | J5: =SUMIFS(Hours!$D$6:$D$1005,Hours!$I$6:$I$1005,Settings!$C$7,Hours!$D$6:$D$1005,">0")
B7: Campaign | C7: Goal | D7: Raised | E7: Of goal | G7: To thank | H7: Date | I7: Amount | J7: Campaign
B8: =IF(Campaigns!B6="","",Campaigns!B6) | C8: =IF(B8="","",IF(N(Campaigns!C6)=0,"",Campaigns!C6)) | D8: =IF(B8="","",Campaigns!F6) | E8: =IF(B8="","",Campaigns!G6) | G8: =IF(N8="","",INDEX(Gifts!$C$1:$C$1005,MOD(N8,10000))) | H8: =IF(N8="","",INDEX(Gifts!$B$1:$B$1005,MOD(N8,10000))) | I8: =IF(N8="","",IF(N(INDEX(Gifts!$D$1:$D$1005,MOD(N8,10000)))=0,"Goods",INDEX(Gifts!$D$1:$D$1005,MOD(N8,10000)))) | J8: =IF(N8="","",IF(INDEX(Gifts!$F$1:$F$1005,MOD(N8,10000))="","",INDEX(Gifts!$F$1:$F$1005,MOD(N8,10000)))) | N8: =IFERROR(SMALL(Gifts!$O$6:$O$1005,1),"")
B9: =IF(Campaigns!B7="","",Campaigns!B7) | C9: =IF(B9="","",IF(N(Campaigns!C7)=0,"",Campaigns!C7)) | D9: =IF(B9="","",Campaigns!F7) | E9: =IF(B9="","",Campaigns!G7) | G9: =IF(N9="","",INDEX(Gifts!$C$1:$C$1005,MOD(N9,10000))) | H9: =IF(N9="","",INDEX(Gifts!$B$1:$B$1005,MOD(N9,10000))) | I9: =IF(N9="","",IF(N(INDEX(Gifts!$D$1:$D$1005,MOD(N9,10000)))=0,"Goods",INDEX(Gifts!$D$1:$D$1005,MOD(N9,10000)))) | J9: =IF(N9="","",IF(INDEX(Gifts!$F$1:$F$1005,MOD(N9,10000))="","",INDEX(Gifts!$F$1:$F$1005,MOD(N9,10000)))) | N9: =IFERROR(SMALL(Gifts!$O$6:$O$1005,2),"")
B10: =IF(Campaigns!B8="","",Campaigns!B8) | C10: =IF(B10="","",IF(N(Campaigns!C8)=0,"",Campaigns!C8)) | D10: =IF(B10="","",Campaigns!F8) | E10: =IF(B10="","",Campaigns!G8) | G10: =IF(N10="","",INDEX(Gifts!$C$1:$C$1005,MOD(N10,10000))) | H10: =IF(N10="","",INDEX(Gifts!$B$1:$B$1005,MOD(N10,10000))) | I10: =IF(N10="","",IF(N(INDEX(Gifts!$D$1:$D$1005,MOD(N10,10000)))=0,"Goods",INDEX(Gifts!$D$1:$D$1005,MOD(N10,10000)))) | J10: =IF(N10="","",IF(INDEX(Gifts!$F$1:$F$1005,MOD(N10,10000))="","",INDEX(Gifts!$F$1:$F$1005,MOD(N10,10000)))) | N10: =IFERROR(SMALL(Gifts!$O$6:$O$1005,3),"")
B11: =IF(Campaigns!B9="","",Campaigns!B9) | C11: =IF(B11="","",IF(N(Campaigns!C9)=0,"",Campaigns!C9)) | D11: =IF(B11="","",Campaigns!F9) | E11: =IF(B11="","",Campaigns!G9) | G11: =IF(N11="","",INDEX(Gifts!$C$1:$C$1005,MOD(N11,10000))) | H11: =IF(N11="","",INDEX(Gifts!$B$1:$B$1005,MOD(N11,10000))) | I11: =IF(N11="","",IF(N(INDEX(Gifts!$D$1:$D$1005,MOD(N11,10000)))=0,"Goods",INDEX(Gifts!$D$1:$D$1005,MOD(N11,10000)))) | J11: =IF(N11="","",IF(INDEX(Gifts!$F$1:$F$1005,MOD(N11,10000))="","",INDEX(Gifts!$F$1:$F$1005,MOD(N11,10000)))) | N11: =IFERROR(SMALL(Gifts!$O$6:$O$1005,4),"")
B12: =IF(Campaigns!B10="","",Campaigns!B10) | C12: =IF(B12="","",IF(N(Campaigns!C10)=0,"",Campaigns!C10)) | D12: =IF(B12="","",Campaigns!F10) | E12: =IF(B12="","",Campaigns!G10) | G12: =IF(N12="","",INDEX(Gifts!$C$1:$C$1005,MOD(N12,10000))) | H12: =IF(N12="","",INDEX(Gifts!$B$1:$B$1005,MOD(N12,10000))) | I12: =IF(N12="","",IF(N(INDEX(Gifts!$D$1:$D$1005,MOD(N12,10000)))=0,"Goods",INDEX(Gifts!$D$1:$D$1005,MOD(N12,10000)))) | J12: =IF(N12="","",IF(INDEX(Gifts!$F$1:$F$1005,MOD(N12,10000))="","",INDEX(Gifts!$F$1:$F$1005,MOD(N12,10000)))) | N12: =IFERROR(SMALL(Gifts!$O$6:$O$1005,5),"")
B13: =IF(Campaigns!B11="","",Campaigns!B11) | C13: =IF(B13="","",IF(N(Campaigns!C11)=0,"",Campaigns!C11)) | D13: =IF(B13="","",Campaigns!F11) | E13: =IF(B13="","",Campaigns!G11) | G13: =IF(N13="","",INDEX(Gifts!$C$1:$C$1005,MOD(N13,10000))) | H13: =IF(N13="","",INDEX(Gifts!$B$1:$B$1005,MOD(N13,10000))) | I13: =IF(N13="","",IF(N(INDEX(Gifts!$D$1:$D$1005,MOD(N13,10000)))=0,"Goods",INDEX(Gifts!$D$1:$D$1005,MOD(N13,10000)))) | J13: =IF(N13="","",IF(INDEX(Gifts!$F$1:$F$1005,MOD(N13,10000))="","",INDEX(Gifts!$F$1:$F$1005,MOD(N13,10000)))) | N13: =IFERROR(SMALL(Gifts!$O$6:$O$1005,6),"")
B15: Month | C15: Given | D15: Gifts | E15: Hours | G15: Top donors | H15: This year | I15: Gifts | J15: Last gift
B16: Jan | C16: =SUMIFS(Gifts!$D$6:$D$1005,Gifts!$L$6:$L$1005,(Settings!$C$7*100+1),Gifts!$D$6:$D$1005,">0") | D16: =SUMIFS(Gifts!$Q$6:$Q$1005,Gifts!$L$6:$L$1005,(Settings!$C$7*100+1)) | E16: =SUMIFS(Hours!$D$6:$D$1005,Hours!$J$6:$J$1005,(Settings!$C$7*100+1),Hours!$D$6:$D$1005,">0") | G16: =IF(O16="","",INDEX(Donors!$B$1:$B$305,1000-MOD(O16,1000))) | H16: =IF(O16="","",INDEX(Donors!$H$1:$H$305,1000-MOD(O16,1000))) | I16: =IF(O16="","",INDEX(Donors!$N$1:$N$305,1000-MOD(O16,1000))) | J16: =IF(O16="","",INDEX(Donors!$G$1:$G$305,1000-MOD(O16,1000))) | O16: =IFERROR(LARGE(Donors!$M$6:$M$305,1),"")
B17: Feb | C17: =SUMIFS(Gifts!$D$6:$D$1005,Gifts!$L$6:$L$1005,(Settings!$C$7*100+2),Gifts!$D$6:$D$1005,">0") | D17: =SUMIFS(Gifts!$Q$6:$Q$1005,Gifts!$L$6:$L$1005,(Settings!$C$7*100+2)) | E17: =SUMIFS(Hours!$D$6:$D$1005,Hours!$J$6:$J$1005,(Settings!$C$7*100+2),Hours!$D$6:$D$1005,">0") | G17: =IF(O17="","",INDEX(Donors!$B$1:$B$305,1000-MOD(O17,1000))) | H17: =IF(O17="","",INDEX(Donors!$H$1:$H$305,1000-MOD(O17,1000))) | I17: =IF(O17="","",INDEX(Donors!$N$1:$N$305,1000-MOD(O17,1000))) | J17: =IF(O17="","",INDEX(Donors!$G$1:$G$305,1000-MOD(O17,1000))) | O17: =IFERROR(LARGE(Donors!$M$6:$M$305,2),"")
B18: Mar | C18: =SUMIFS(Gifts!$D$6:$D$1005,Gifts!$L$6:$L$1005,(Settings!$C$7*100+3),Gifts!$D$6:$D$1005,">0") | D18: =SUMIFS(Gifts!$Q$6:$Q$1005,Gifts!$L$6:$L$1005,(Settings!$C$7*100+3)) | E18: =SUMIFS(Hours!$D$6:$D$1005,Hours!$J$6:$J$1005,(Settings!$C$7*100+3),Hours!$D$6:$D$1005,">0") | G18: =IF(O18="","",INDEX(Donors!$B$1:$B$305,1000-MOD(O18,1000))) | H18: =IF(O18="","",INDEX(Donors!$H$1:$H$305,1000-MOD(O18,1000))) | I18: =IF(O18="","",INDEX(Donors!$N$1:$N$305,1000-MOD(O18,1000))) | J18: =IF(O18="","",INDEX(Donors!$G$1:$G$305,1000-MOD(O18,1000))) | O18: =IFERROR(LARGE(Donors!$M$6:$M$305,3),"")
B19: Apr | C19: =SUMIFS(Gifts!$D$6:$D$1005,Gifts!$L$6:$L$1005,(Settings!$C$7*100+4),Gifts!$D$6:$D$1005,">0") | D19: =SUMIFS(Gifts!$Q$6:$Q$1005,Gifts!$L$6:$L$1005,(Settings!$C$7*100+4)) | E19: =SUMIFS(Hours!$D$6:$D$1005,Hours!$J$6:$J$1005,(Settings!$C$7*100+4),Hours!$D$6:$D$1005,">0") | G19: =IF(O19="","",INDEX(Donors!$B$1:$B$305,1000-MOD(O19,1000))) | H19: =IF(O19="","",INDEX(Donors!$H$1:$H$305,1000-MOD(O19,1000))) | I19: =IF(O19="","",INDEX(Donors!$N$1:$N$305,1000-MOD(O19,1000))) | J19: =IF(O19="","",INDEX(Donors!$G$1:$G$305,1000-MOD(O19,1000))) | O19: =IFERROR(LARGE(Donors!$M$6:$M$305,4),"")
B20: May | C20: =SUMIFS(Gifts!$D$6:$D$1005,Gifts!$L$6:$L$1005,(Settings!$C$7*100+5),Gifts!$D$6:$D$1005,">0") | D20: =SUMIFS(Gifts!$Q$6:$Q$1005,Gifts!$L$6:$L$1005,(Settings!$C$7*100+5)) | E20: =SUMIFS(Hours!$D$6:$D$1005,Hours!$J$6:$J$1005,(Settings!$C$7*100+5),Hours!$D$6:$D$1005,">0") | G20: =IF(O20="","",INDEX(Donors!$B$1:$B$305,1000-MOD(O20,1000))) | H20: =IF(O20="","",INDEX(Donors!$H$1:$H$305,1000-MOD(O20,1000))) | I20: =IF(O20="","",INDEX(Donors!$N$1:$N$305,1000-MOD(O20,1000))) | J20: =IF(O20="","",INDEX(Donors!$G$1:$G$305,1000-MOD(O20,1000))) | O20: =IFERROR(LARGE(Donors!$M$6:$M$305,5),"")
B21: Jun | C21: =SUMIFS(Gifts!$D$6:$D$1005,Gifts!$L$6:$L$1005,(Settings!$C$7*100+6),Gifts!$D$6:$D$1005,">0") | D21: =SUMIFS(Gifts!$Q$6:$Q$1005,Gifts!$L$6:$L$1005,(Settings!$C$7*100+6)) | E21: =SUMIFS(Hours!$D$6:$D$1005,Hours!$J$6:$J$1005,(Settings!$C$7*100+6),Hours!$D$6:$D$1005,">0") | G21: =IF(O21="","",INDEX(Donors!$B$1:$B$305,1000-MOD(O21,1000))) | H21: =IF(O21="","",INDEX(Donors!$H$1:$H$305,1000-MOD(O21,1000))) | I21: =IF(O21="","",INDEX(Donors!$N$1:$N$305,1000-MOD(O21,1000))) | J21: =IF(O21="","",INDEX(Donors!$G$1:$G$305,1000-MOD(O21,1000))) | O21: =IFERROR(LARGE(Donors!$M$6:$M$305,6),"")
B22: Jul | C22: =SUMIFS(Gifts!$D$6:$D$1005,Gifts!$L$6:$L$1005,(Settings!$C$7*100+7),Gifts!$D$6:$D$1005,">0") | D22: =SUMIFS(Gifts!$Q$6:$Q$1005,Gifts!$L$6:$L$1005,(Settings!$C$7*100+7)) | E22: =SUMIFS(Hours!$D$6:$D$1005,Hours!$J$6:$J$1005,(Settings!$C$7*100+7),Hours!$D$6:$D$1005,">0") | G22: =IF(O22="","",INDEX(Donors!$B$1:$B$305,1000-MOD(O22,1000))) | H22: =IF(O22="","",INDEX(Donors!$H$1:$H$305,1000-MOD(O22,1000))) | I22: =IF(O22="","",INDEX(Donors!$N$1:$N$305,1000-MOD(O22,1000))) | J22: =IF(O22="","",INDEX(Donors!$G$1:$G$305,1000-MOD(O22,1000))) | O22: =IFERROR(LARGE(Donors!$M$6:$M$305,7),"")
B23: Aug | C23: =SUMIFS(Gifts!$D$6:$D$1005,Gifts!$L$6:$L$1005,(Settings!$C$7*100+8),Gifts!$D$6:$D$1005,">0") | D23: =SUMIFS(Gifts!$Q$6:$Q$1005,Gifts!$L$6:$L$1005,(Settings!$C$7*100+8)) | E23: =SUMIFS(Hours!$D$6:$D$1005,Hours!$J$6:$J$1005,(Settings!$C$7*100+8),Hours!$D$6:$D$1005,">0") | G23: =IF(O23="","",INDEX(Donors!$B$1:$B$305,1000-MOD(O23,1000))) | H23: =IF(O23="","",INDEX(Donors!$H$1:$H$305,1000-MOD(O23,1000))) | I23: =IF(O23="","",INDEX(Donors!$N$1:$N$305,1000-MOD(O23,1000))) | J23: =IF(O23="","",INDEX(Donors!$G$1:$G$305,1000-MOD(O23,1000))) | O23: =IFERROR(LARGE(Donors!$M$6:$M$305,8),"")
B24: Sep | C24: =SUMIFS(Gifts!$D$6:$D$1005,Gifts!$L$6:$L$1005,(Settings!$C$7*100+9),Gifts!$D$6:$D$1005,">0") | D24: =SUMIFS(Gifts!$Q$6:$Q$1005,Gifts!$L$6:$L$1005,(Settings!$C$7*100+9)) | E24: =SUMIFS(Hours!$D$6:$D$1005,Hours!$J$6:$J$1005,(Settings!$C$7*100+9),Hours!$D$6:$D$1005,">0")
B25: Oct | C25: =SUMIFS(Gifts!$D$6:$D$1005,Gifts!$L$6:$L$1005,(Settings!$C$7*100+10),Gifts!$D$6:$D$1005,">0") | D25: =SUMIFS(Gifts!$Q$6:$Q$1005,Gifts!$L$6:$L$1005,(Settings!$C$7*100+10)) | E25: =SUMIFS(Hours!$D$6:$D$1005,Hours!$J$6:$J$1005,(Settings!$C$7*100+10),Hours!$D$6:$D$1005,">0")
B26: Nov | C26: =SUMIFS(Gifts!$D$6:$D$1005,Gifts!$L$6:$L$1005,(Settings!$C$7*100+11),Gifts!$D$6:$D$1005,">0") | D26: =SUMIFS(Gifts!$Q$6:$Q$1005,Gifts!$L$6:$L$1005,(Settings!$C$7*100+11)) | E26: =SUMIFS(Hours!$D$6:$D$1005,Hours!$J$6:$J$1005,(Settings!$C$7*100+11),Hours!$D$6:$D$1005,">0")
B27: Dec | C27: =SUMIFS(Gifts!$D$6:$D$1005,Gifts!$L$6:$L$1005,(Settings!$C$7*100+12),Gifts!$D$6:$D$1005,">0") | D27: =SUMIFS(Gifts!$Q$6:$Q$1005,Gifts!$L$6:$L$1005,(Settings!$C$7*100+12)) | E27: =SUMIFS(Hours!$D$6:$D$1005,Hours!$J$6:$J$1005,(Settings!$C$7*100+12),Hours!$D$6:$D$1005,">0")

Sheet Gifts
B2: Gifts
B3: Every gift, with its campaign. For goods, leave the amount empty and say what was given. An x once the donor has been thanked.
B5: Date | C5: Donor | D5: Amount | E5: How | F5: Campaign | G5: Goods given | H5: Thanked | I5: Note | J5: Check
B6: 45843 | C6: Grace Holloway | D6: 25 | E6: Bank transfer | F6: General fund | H6: x | I6: Monthly | J6: =IF(AND(C6="",D6="",G6=""),"",IF(NOT(ISNUMBER(B6)),"Needs a date",IF(AND(D6<>"",NOT(ISNUMBER(D6))),"Amount not a number",IF(N(D6)<0,"Amount below zero",IF(AND(N(D6)=0,G6=""),"Needs an amount or goods",IF(C6="","",IF(COUNTIF(Donors!$B$6:$B$305,C6)=0,"Not on Donors",""))))))) | K6: =IF(ISNUMBER(B6),YEAR(B6),"") | L6: =IF(ISNUMBER(B6),YEAR(B6)*100+MONTH(B6),"") | M6: =IF(ISNUMBER(B6),INT(B6),0) | N6: =IF(OR(C6="",F6="",Q6=0),0,IF(COUNTIFS(C$6:C6,C6,F$6:F6,F6,Q$6:Q6,1)=1,1,0)) | O6: =IF(OR(C6="",Q6=0,H6<>""),"",M6*10000+ROW()) | P6: =IF(OR(C6="",Q6=0),"",IF(AND(C6=Statement!$C$4,K6=Statement!$C$5),M6*10000+ROW(),"")) | Q6: =IF(AND(ISNUMBER(B6),OR(N(D6)>0,G6<>"")),1,0)
B7: 45846 | C7: Ravi Patel | D7: 20 | E7: Bank transfer | F7: General fund | H7: x | I7: Monthly | J7: =IF(AND(C7="",D7="",G7=""),"",IF(NOT(ISNUMBER(B7)),"Needs a date",IF(AND(D7<>"",NOT(ISNUMBER(D7))),"Amount not a number",IF(N(D7)<0,"Amount below zero",IF(AND(N(D7)=0,G7=""),"Needs an amount or goods",IF(C7="","",IF(COUNTIF(Donors!$B$6:$B$305,C7)=0,"Not on Donors",""))))))) | K7: =IF(ISNUMBER(B7),YEAR(B7),"") | L7: =IF(ISNUMBER(B7),YEAR(B7)*100+MONTH(B7),"") | M7: =IF(ISNUMBER(B7),INT(B7),0) | N7: =IF(OR(C7="",F7="",Q7=0),0,IF(COUNTIFS(C$6:C7,C7,F$6:F7,F7,Q$6:Q7,1)=1,1,0)) | O7: =IF(OR(C7="",Q7=0,H7<>""),"",M7*10000+ROW()) | P7: =IF(OR(C7="",Q7=0),"",IF(AND(C7=Statement!$C$4,K7=Statement!$C$5),M7*10000+ROW(),"")) | Q7: =IF(AND(ISNUMBER(B7),OR(N(D7)>0,G7<>"")),1,0)
B8: 45847 | C8: Helen Price | D8: 10 | E8: Bank transfer | F8: General fund | H8: x | I8: Monthly | J8: =IF(AND(C8="",D8="",G8=""),"",IF(NOT(ISNUMBER(B8)),"Needs a date",IF(AND(D8<>"",NOT(ISNUMBER(D8))),"Amount not a number",IF(N(D8)<0,"Amount below zero",IF(AND(N(D8)=0,G8=""),"Needs an amount or goods",IF(C8="","",IF(COUNTIF(Donors!$B$6:$B$305,C8)=0,"Not on Donors",""))))))) | K8: =IF(ISNUMBER(B8),YEAR(B8),"") | L8: =IF(ISNUMBER(B8),YEAR(B8)*100+MONTH(B8),"") | M8: =IF(ISNUMBER(B8),INT(B8),0) | N8: =IF(OR(C8="",F8="",Q8=0),0,IF(COUNTIFS(C$6:C8,C8,F$6:F8,F8,Q$6:Q8,1)=1,1,0)) | O8: =IF(OR(C8="",Q8=0,H8<>""),"",M8*10000+ROW()) | P8: =IF(OR(C8="",Q8=0),"",IF(AND(C8=Statement!$C$4,K8=Statement!$C$5),M8*10000+ROW(),"")) | Q8: =IF(AND(ISNUMBER(B8),OR(N(D8)>0,G8<>"")),1,0)
B9: 45847 | C9: Amina Yusuf | D9: 15 | E9: Bank transfer | F9: General fund | H9: x | I9: Monthly | J9: =IF(AND(C9="",D9="",G9=""),"",IF(NOT(ISNUMBER(B9)),"Needs a date",IF(AND(D9<>"",NOT(ISNUMBER(D9))),"Amount not a number",IF(N(D9)<0,"Amount below zero",IF(AND(N(D9)=0,G9=""),"Needs an amount or goods",IF(C9="","",IF(COUNTIF(Donors!$B$6:$B$305,C9)=0,"Not on Donors",""))))))) | K9: =IF(ISNUMBER(B9),YEAR(B9),"") | L9: =IF(ISNUMBER(B9),YEAR(B9)*100+MONTH(B9),"") | M9: =IF(ISNUMBER(B9),INT(B9),0) | N9: =IF(OR(C9="",F9="",Q9=0),0,IF(COUNTIFS(C$6:C9,C9,F$6:F9,F9,Q$6:Q9,1)=1,1,0)) | O9: =IF(OR(C9="",Q9=0,H9<>""),"",M9*10000+ROW()) | P9: =IF(OR(C9="",Q9=0),"",IF(AND(C9=Statement!$C$4,K9=Statement!$C$5),M9*10000+ROW(),"")) | Q9: =IF(AND(ISNUMBER(B9),OR(N(D9)>0,G9<>"")),1,0)
B10: 45874 | C10: Grace Holloway | D10: 25 | E10: Bank transfer | F10: General fund | H10: x | I10: Monthly | J10: =IF(AND(C10="",D10="",G10=""),"",IF(NOT(ISNUMBER(B10)),"Needs a date",IF(AND(D10<>"",NOT(ISNUMBER(D10))),"Amount not a number",IF(N(D10)<0,"Amount below zero",IF(AND(N(D10)=0,G10=""),"Needs an amount or goods",IF(C10="","",IF(COUNTIF(Donors!$B$6:$B$305,C10)=0,"Not on Donors",""))))))) | K10: =IF(ISNUMBER(B10),YEAR(B10),"") | L10: =IF(ISNUMBER(B10),YEAR(B10)*100+MONTH(B10),"") | M10: =IF(ISNUMBER(B10),INT(B10),0) | N10: =IF(OR(C10="",F10="",Q10=0),0,IF(COUNTIFS(C$6:C10,C10,F$6:F10,F10,Q$6:Q10,1)=1,1,0)) | O10: =IF(OR(C10="",Q10=0,H10<>""),"",M10*10000+ROW()) | P10: =IF(OR(C10="",Q10=0),"",IF(AND(C10=Statement!$C$4,K10=Statement!$C$5),M10*10000+ROW(),"")) | Q10: =IF(AND(ISNUMBER(B10),OR(N(D10)>0,G10<>"")),1,0)
B11: 45877 | C11: Ravi Patel | D11: 20 | E11: Bank transfer | F11: General fund | H11: x | I11: Monthly | J11: =IF(AND(C11="",D11="",G11=""),"",IF(NOT(ISNUMBER(B11)),"Needs a date",IF(AND(D11<>"",NOT(ISNUMBER(D11))),"Amount not a number",IF(N(D11)<0,"Amount below zero",IF(AND(N(D11)=0,G11=""),"Needs an amount or goods",IF(C11="","",IF(COUNTIF(Donors!$B$6:$B$305,C11)=0,"Not on Donors",""))))))) | K11: =IF(ISNUMBER(B11),YEAR(B11),"") | L11: =IF(ISNUMBER(B11),YEAR(B11)*100+MONTH(B11),"") | M11: =IF(ISNUMBER(B11),INT(B11),0) | N11: =IF(OR(C11="",F11="",Q11=0),0,IF(COUNTIFS(C$6:C11,C11,F$6:F11,F11,Q$6:Q11,1)=1,1,0)) | O11: =IF(OR(C11="",Q11=0,H11<>""),"",M11*10000+ROW()) | P11: =IF(OR(C11="",Q11=0),"",IF(AND(C11=Statement!$C$4,K11=Statement!$C$5),M11*10000+ROW(),"")) | Q11: =IF(AND(ISNUMBER(B11),OR(N(D11)>0,G11<>"")),1,0)
B12: 45878 | C12: Helen Price | D12: 10 | E12: Bank transfer | F12: General fund | H12: x | I12: Monthly | J12: =IF(AND(C12="",D12="",G12=""),"",IF(NOT(ISNUMBER(B12)),"Needs a date",IF(AND(D12<>"",NOT(ISNUMBER(D12))),"Amount not a number",IF(N(D12)<0,"Amount below zero",IF(AND(N(D12)=0,G12=""),"Needs an amount or goods",IF(C12="","",IF(COUNTIF(Donors!$B$6:$B$305,C12)=0,"Not on Donors",""))))))) | K12: =IF(ISNUMBER(B12),YEAR(B12),"") | L12: =IF(ISNUMBER(B12),YEAR(B12)*100+MONTH(B12),"") | M12: =IF(ISNUMBER(B12),INT(B12),0) | N12: =IF(OR(C12="",F12="",Q12=0),0,IF(COUNTIFS(C$6:C12,C12,F$6:F12,F12,Q$6:Q12,1)=1,1,0)) | O12: =IF(OR(C12="",Q12=0,H12<>""),"",M12*10000+ROW()) | P12: =IF(OR(C12="",Q12=0),"",IF(AND(C12=Statement!$C$4,K12=Statement!$C$5),M12*10000+ROW(),"")) | Q12: =IF(AND(ISNUMBER(B12),OR(N(D12)>0,G12<>"")),1,0)
B13: 45878 | C13: Amina Yusuf | D13: 15 | E13: Bank transfer | F13: General fund | H13: x | I13: Monthly | J13: =IF(AND(C13="",D13="",G13=""),"",IF(NOT(ISNUMBER(B13)),"Needs a date",IF(AND(D13<>"",NOT(ISNUMBER(D13))),"Amount not a number",IF(N(D13)<0,"Amount below zero",IF(AND(N(D13)=0,G13=""),"Needs an amount or goods",IF(C13="","",IF(COUNTIF(Donors!$B$6:$B$305,C13)=0,"Not on Donors",""))))))) | K13: =IF(ISNUMBER(B13),YEAR(B13),"") | L13: =IF(ISNUMBER(B13),YEAR(B13)*100+MONTH(B13),"") | M13: =IF(ISNUMBER(B13),INT(B13),0) | N13: =IF(OR(C13="",F13="",Q13=0),0,IF(COUNTIFS(C$6:C13,C13,F$6:F13,F13,Q$6:Q13,1)=1,1,0)) | O13: =IF(OR(C13="",Q13=0,H13<>""),"",M13*10000+ROW()) | P13: =IF(OR(C13="",Q13=0),"",IF(AND(C13=Statement!$C$4,K13=Statement!$C$5),M13*10000+ROW(),"")) | Q13: =IF(AND(ISNUMBER(B13),OR(N(D13)>0,G13<>"")),1,0)
B14: 45893 | C14: Riverton Hardware | D14: 400 | E14: Check | F14: General fund | H14: x | J14: =IF(AND(C14="",D14="",G14=""),"",IF(NOT(ISNUMBER(B14)),"Needs a date",IF(AND(D14<>"",NOT(ISNUMBER(D14))),"Amount not a number",IF(N(D14)<0,"Amount below zero",IF(AND(N(D14)=0,G14=""),"Needs an amount or goods",IF(C14="","",IF(COUNTIF(Donors!$B$6:$B$305,C14)=0,"Not on Donors",""))))))) | K14: =IF(ISNUMBER(B14),YEAR(B14),"") | L14: =IF(ISNUMBER(B14),YEAR(B14)*100+MONTH(B14),"") | M14: =IF(ISNUMBER(B14),INT(B14),0) | N14: =IF(OR(C14="",F14="",Q14=0),0,IF(COUNTIFS(C$6:C14,C14,F$6:F14,F14,Q$6:Q14,1)=1,1,0)) | O14: =IF(OR(C14="",Q14=0,H14<>""),"",M14*10000+ROW()) | P14: =IF(OR(C14="",Q14=0),"",IF(AND(C14=Statement!$C$4,K14=Statement!$C$5),M14*10000+ROW(),"")) | Q14: =IF(AND(ISNUMBER(B14),OR(N(D14)>0,G14<>"")),1,0)
B15: 45905 | C15: Grace Holloway | D15: 25 | E15: Bank transfer | F15: General fund | H15: x | I15: Monthly | J15: =IF(AND(C15="",D15="",G15=""),"",IF(NOT(ISNUMBER(B15)),"Needs a date",IF(AND(D15<>"",NOT(ISNUMBER(D15))),"Amount not a number",IF(N(D15)<0,"Amount below zero",IF(AND(N(D15)=0,G15=""),"Needs an amount or goods",IF(C15="","",IF(COUNTIF(Donors!$B$6:$B$305,C15)=0,"Not on Donors",""))))))) | K15: =IF(ISNUMBER(B15),YEAR(B15),"") | L15: =IF(ISNUMBER(B15),YEAR(B15)*100+MONTH(B15),"") | M15: =IF(ISNUMBER(B15),INT(B15),0) | N15: =IF(OR(C15="",F15="",Q15=0),0,IF(COUNTIFS(C$6:C15,C15,F$6:F15,F15,Q$6:Q15,1)=1,1,0)) | O15: =IF(OR(C15="",Q15=0,H15<>""),"",M15*10000+ROW()) | P15: =IF(OR(C15="",Q15=0),"",IF(AND(C15=Statement!$C$4,K15=Statement!$C$5),M15*10000+ROW(),"")) | Q15: =IF(AND(ISNUMBER(B15),OR(N(D15)>0,G15<>"")),1,0)
B16: 45908 | C16: Ravi Patel | D16: 20 | E16: Bank transfer | F16: General fund | H16: x | I16: Monthly | J16: =IF(AND(C16="",D16="",G16=""),"",IF(NOT(ISNUMBER(B16)),"Needs a date",IF(AND(D16<>"",NOT(ISNUMBER(D16))),"Amount not a number",IF(N(D16)<0,"Amount below zero",IF(AND(N(D16)=0,G16=""),"Needs an amount or goods",IF(C16="","",IF(COUNTIF(Donors!$B$6:$B$305,C16)=0,"Not on Donors",""))))))) | K16: =IF(ISNUMBER(B16),YEAR(B16),"") | L16: =IF(ISNUMBER(B16),YEAR(B16)*100+MONTH(B16),"") | M16: =IF(ISNUMBER(B16),INT(B16),0) | N16: =IF(OR(C16="",F16="",Q16=0),0,IF(COUNTIFS(C$6:C16,C16,F$6:F16,F16,Q$6:Q16,1)=1,1,0)) | O16: =IF(OR(C16="",Q16=0,H16<>""),"",M16*10000+ROW()) | P16: =IF(OR(C16="",Q16=0),"",IF(AND(C16=Statement!$C$4,K16=Statement!$C$5),M16*10000+ROW(),"")) | Q16: =IF(AND(ISNUMBER(B16),OR(N(D16)>0,G16<>"")),1,0)
B17: 45909 | C17: Amina Yusuf | D17: 15 | E17: Bank transfer | F17: General fund | H17: x | I17: Monthly | J17: =IF(AND(C17="",D17="",G17=""),"",IF(NOT(ISNUMBER(B17)),"Needs a date",IF(AND(D17<>"",NOT(ISNUMBER(D17))),"Amount not a number",IF(N(D17)<0,"Amount below zero",IF(AND(N(D17)=0,G17=""),"Needs an amount or goods",IF(C17="","",IF(COUNTIF(Donors!$B$6:$B$305,C17)=0,"Not on Donors",""))))))) | K17: =IF(ISNUMBER(B17),YEAR(B17),"") | L17: =IF(ISNUMBER(B17),YEAR(B17)*100+MONTH(B17),"") | M17: =IF(ISNUMBER(B17),INT(B17),0) | N17: =IF(OR(C17="",F17="",Q17=0),0,IF(COUNTIFS(C$6:C17,C17,F$6:F17,F17,Q$6:Q17,1)=1,1,0)) | O17: =IF(OR(C17="",Q17=0,H17<>""),"",M17*10000+ROW()) | P17: =IF(OR(C17="",Q17=0),"",IF(AND(C17=Statement!$C$4,K17=Statement!$C$5),M17*10000+ROW(),"")) | Q17: =IF(AND(ISNUMBER(B17),OR(N(D17)>0,G17<>"")),1,0)
B18: 45913 | C18: Old Mill Trust | D18: 2000 | E18: Bank transfer | F18: General fund | H18: x | I18: Yearly grant | J18: =IF(AND(C18="",D18="",G18=""),"",IF(NOT(ISNUMBER(B18)),"Needs a date",IF(AND(D18<>"",NOT(ISNUMBER(D18))),"Amount not a number",IF(N(D18)<0,"Amount below zero",IF(AND(N(D18)=0,G18=""),"Needs an amount or goods",IF(C18="","",IF(COUNTIF(Donors!$B$6:$B$305,C18)=0,"Not on Donors",""))))))) | K18: =IF(ISNUMBER(B18),YEAR(B18),"") | L18: =IF(ISNUMBER(B18),YEAR(B18)*100+MONTH(B18),"") | M18: =IF(ISNUMBER(B18),INT(B18),0) | N18: =IF(OR(C18="",F18="",Q18=0),0,IF(COUNTIFS(C$6:C18,C18,F$6:F18,F18,Q$6:Q18,1)=1,1,0)) | O18: =IF(OR(C18="",Q18=0,H18<>""),"",M18*10000+ROW()) | P18: =IF(OR(C18="",Q18=0),"",IF(AND(C18=Statement!$C$4,K18=Statement!$C$5),M18*10000+ROW(),"")) | Q18: =IF(AND(ISNUMBER(B18),OR(N(D18)>0,G18<>"")),1,0)
B19: 45935 | C19: Grace Holloway | D19: 25 | E19: Bank transfer | F19: General fund | H19: x | I19: Monthly | J19: =IF(AND(C19="",D19="",G19=""),"",IF(NOT(ISNUMBER(B19)),"Needs a date",IF(AND(D19<>"",NOT(ISNUMBER(D19))),"Amount not a number",IF(N(D19)<0,"Amount below zero",IF(AND(N(D19)=0,G19=""),"Needs an amount or goods",IF(C19="","",IF(COUNTIF(Donors!$B$6:$B$305,C19)=0,"Not on Donors",""))))))) | K19: =IF(ISNUMBER(B19),YEAR(B19),"") | L19: =IF(ISNUMBER(B19),YEAR(B19)*100+MONTH(B19),"") | M19: =IF(ISNUMBER(B19),INT(B19),0) | N19: =IF(OR(C19="",F19="",Q19=0),0,IF(COUNTIFS(C$6:C19,C19,F$6:F19,F19,Q$6:Q19,1)=1,1,0)) | O19: =IF(OR(C19="",Q19=0,H19<>""),"",M19*10000+ROW()) | P19: =IF(OR(C19="",Q19=0),"",IF(AND(C19=Statement!$C$4,K19=Statement!$C$5),M19*10000+ROW(),"")) | Q19: =IF(AND(ISNUMBER(B19),OR(N(D19)>0,G19<>"")),1,0)
B20: 45938 | C20: Ravi Patel | D20: 20 | E20: Bank transfer | F20: General fund | H20: x | I20: Monthly | J20: =IF(AND(C20="",D20="",G20=""),"",IF(NOT(ISNUMBER(B20)),"Needs a date",IF(AND(D20<>"",NOT(ISNUMBER(D20))),"Amount not a number",IF(N(D20)<0,"Amount below zero",IF(AND(N(D20)=0,G20=""),"Needs an amount or goods",IF(C20="","",IF(COUNTIF(Donors!$B$6:$B$305,C20)=0,"Not on Donors",""))))))) | K20: =IF(ISNUMBER(B20),YEAR(B20),"") | L20: =IF(ISNUMBER(B20),YEAR(B20)*100+MONTH(B20),"") | M20: =IF(ISNUMBER(B20),INT(B20),0) | N20: =IF(OR(C20="",F20="",Q20=0),0,IF(COUNTIFS(C$6:C20,C20,F$6:F20,F20,Q$6:Q20,1)=1,1,0)) | O20: =IF(OR(C20="",Q20=0,H20<>""),"",M20*10000+ROW()) | P20: =IF(OR(C20="",Q20=0),"",IF(AND(C20=Statement!$C$4,K20=Statement!$C$5),M20*10000+ROW(),"")) | Q20: =IF(AND(ISNUMBER(B20),OR(N(D20)>0,G20<>"")),1,0)
B21: 45939 | C21: Amina Yusuf | D21: 15 | E21: Bank transfer | F21: General fund | H21: x | I21: Monthly | J21: =IF(AND(C21="",D21="",G21=""),"",IF(NOT(ISNUMBER(B21)),"Needs a date",IF(AND(D21<>"",NOT(ISNUMBER(D21))),"Amount not a number",IF(N(D21)<0,"Amount below zero",IF(AND(N(D21)=0,G21=""),"Needs an amount or goods",IF(C21="","",IF(COUNTIF(Donors!$B$6:$B$305,C21)=0,"Not on Donors",""))))))) | K21: =IF(ISNUMBER(B21),YEAR(B21),"") | L21: =IF(ISNUMBER(B21),YEAR(B21)*100+MONTH(B21),"") | M21: =IF(ISNUMBER(B21),INT(B21),0) | N21: =IF(OR(C21="",F21="",Q21=0),0,IF(COUNTIFS(C$6:C21,C21,F$6:F21,F21,Q$6:Q21,1)=1,1,0)) | O21: =IF(OR(C21="",Q21=0,H21<>""),"",M21*10000+ROW()) | P21: =IF(OR(C21="",Q21=0),"",IF(AND(C21=Statement!$C$4,K21=Statement!$C$5),M21*10000+ROW(),"")) | Q21: =IF(AND(ISNUMBER(B21),OR(N(D21)>0,G21<>"")),1,0)
B22: 45963 | C22: Corner Bakery | D22: 120 | E22: Card | F22: General fund | H22: x | J22: =IF(AND(C22="",D22="",G22=""),"",IF(NOT(ISNUMBER(B22)),"Needs a date",IF(AND(D22<>"",NOT(ISNUMBER(D22))),"Amount not a number",IF(N(D22)<0,"Amount below zero",IF(AND(N(D22)=0,G22=""),"Needs an amount or goods",IF(C22="","",IF(COUNTIF(Donors!$B$6:$B$305,C22)=0,"Not on Donors",""))))))) | K22: =IF(ISNUMBER(B22),YEAR(B22),"") | L22: =IF(ISNUMBER(B22),YEAR(B22)*100+MONTH(B22),"") | M22: =IF(ISNUMBER(B22),INT(B22),0) | N22: =IF(OR(C22="",F22="",Q22=0),0,IF(COUNTIFS(C$6:C22,C22,F$6:F22,F22,Q$6:Q22,1)=1,1,0)) | O22: =IF(OR(C22="",Q22=0,H22<>""),"",M22*10000+ROW()) | P22: =IF(OR(C22="",Q22=0),"",IF(AND(C22=Statement!$C$4,K22=Statement!$C$5),M22*10000+ROW(),"")) | Q22: =IF(AND(ISNUMBER(B22),OR(N(D22)>0,G22<>"")),1,0)
B23: 45966 | C23: Grace Holloway | D23: 25 | E23: Bank transfer | F23: General fund | H23: x | I23: Monthly | J23: =IF(AND(C23="",D23="",G23=""),"",IF(NOT(ISNUMBER(B23)),"Needs a date",IF(AND(D23<>"",NOT(ISNUMBER(D23))),"Amount not a number",IF(N(D23)<0,"Amount below zero",IF(AND(N(D23)=0,G23=""),"Needs an amount or goods",IF(C23="","",IF(COUNTIF(Donors!$B$6:$B$305,C23)=0,"Not on Donors",""))))))) | K23: =IF(ISNUMBER(B23),YEAR(B23),"") | L23: =IF(ISNUMBER(B23),YEAR(B23)*100+MONTH(B23),"") | M23: =IF(ISNUMBER(B23),INT(B23),0) | N23: =IF(OR(C23="",F23="",Q23=0),0,IF(COUNTIFS(C$6:C23,C23,F$6:F23,F23,Q$6:Q23,1)=1,1,0)) | O23: =IF(OR(C23="",Q23=0,H23<>""),"",M23*10000+ROW()) | P23: =IF(OR(C23="",Q23=0),"",IF(AND(C23=Statement!$C$4,K23=Statement!$C$5),M23*10000+ROW(),"")) | Q23: =IF(AND(ISNUMBER(B23),OR(N(D23)>0,G23<>"")),1,0)
B24: 45969 | C24: Ravi Patel | D24: 20 | E24: Bank transfer | F24: General fund | H24: x | I24: Monthly | J24: =IF(AND(C24="",D24="",G24=""),"",IF(NOT(ISNUMBER(B24)),"Needs a date",IF(AND(D24<>"",NOT(ISNUMBER(D24))),"Amount not a number",IF(N(D24)<0,"Amount below zero",IF(AND(N(D24)=0,G24=""),"Needs an amount or goods",IF(C24="","",IF(COUNTIF(Donors!$B$6:$B$305,C24)=0,"Not on Donors",""))))))) | K24: =IF(ISNUMBER(B24),YEAR(B24),"") | L24: =IF(ISNUMBER(B24),YEAR(B24)*100+MONTH(B24),"") | M24: =IF(ISNUMBER(B24),INT(B24),0) | N24: =IF(OR(C24="",F24="",Q24=0),0,IF(COUNTIFS(C$6:C24,C24,F$6:F24,F24,Q$6:Q24,1)=1,1,0)) | O24: =IF(OR(C24="",Q24=0,H24<>""),"",M24*10000+ROW()) | P24: =IF(OR(C24="",Q24=0),"",IF(AND(C24=Statement!$C$4,K24=Statement!$C$5),M24*10000+ROW(),"")) | Q24: =IF(AND(ISNUMBER(B24),OR(N(D24)>0,G24<>"")),1,0)
B25: 45970 | C25: Amina Yusuf | D25: 15 | E25: Bank transfer | F25: General fund | H25: x | I25: Monthly | J25: =IF(AND(C25="",D25="",G25=""),"",IF(NOT(ISNUMBER(B25)),"Needs a date",IF(AND(D25<>"",NOT(ISNUMBER(D25))),"Amount not a number",IF(N(D25)<0,"Amount below zero",IF(AND(N(D25)=0,G25=""),"Needs an amount or goods",IF(C25="","",IF(COUNTIF(Donors!$B$6:$B$305,C25)=0,"Not on Donors",""))))))) | K25: =IF(ISNUMBER(B25),YEAR(B25),"") | L25: =IF(ISNUMBER(B25),YEAR(B25)*100+MONTH(B25),"") | M25: =IF(ISNUMBER(B25),INT(B25),0) | N25: =IF(OR(C25="",F25="",Q25=0),0,IF(COUNTIFS(C$6:C25,C25,F$6:F25,F25,Q$6:Q25,1)=1,1,0)) | O25: =IF(OR(C25="",Q25=0,H25<>""),"",M25*10000+ROW()) | P25: =IF(OR(C25="",Q25=0),"",IF(AND(C25=Statement!$C$4,K25=Statement!$C$5),M25*10000+ROW(),"")) | Q25: =IF(AND(ISNUMBER(B25),OR(N(D25)>0,G25<>"")),1,0)
B26: 45993 | C26: St Luke's Youth Group | D26: 260 | E26: Cash | F26: General fund | H26: x | I26: Carol singing | J26: =IF(AND(C26="",D26="",G26=""),"",IF(NOT(ISNUMBER(B26)),"Needs a date",IF(AND(D26<>"",NOT(ISNUMBER(D26))),"Amount not a number",IF(N(D26)<0,"Amount below zero",IF(AND(N(D26)=0,G26=""),"Needs an amount or goods",IF(C26="","",IF(COUNTIF(Donors!$B$6:$B$305,C26)=0,"Not on Donors",""))))))) | K26: =IF(ISNUMBER(B26),YEAR(B26),"") | L26: =IF(ISNUMBER(B26),YEAR(B26)*100+MONTH(B26),"") | M26: =IF(ISNUMBER(B26),INT(B26),0) | N26: =IF(OR(C26="",F26="",Q26=0),0,IF(COUNTIFS(C$6:C26,C26,F$6:F26,F26,Q$6:Q26,1)=1,1,0)) | O26: =IF(OR(C26="",Q26=0,H26<>""),"",M26*10000+ROW()) | P26: =IF(OR(C26="",Q26=0),"",IF(AND(C26=Statement!$C$4,K26=Statement!$C$5),M26*10000+ROW(),"")) | Q26: =IF(AND(ISNUMBER(B26),OR(N(D26)>0,G26<>"")),1,0)
B27: 45996 | C27: Grace Holloway | D27: 25 | E27: Bank transfer | F27: General fund | H27: x | I27: Monthly | J27: =IF(AND(C27="",D27="",G27=""),"",IF(NOT(ISNUMBER(B27)),"Needs a date",IF(AND(D27<>"",NOT(ISNUMBER(D27))),"Amount not a number",IF(N(D27)<0,"Amount below zero",IF(AND(N(D27)=0,G27=""),"Needs an amount or goods",IF(C27="","",IF(COUNTIF(Donors!$B$6:$B$305,C27)=0,"Not on Donors",""))))))) | K27: =IF(ISNUMBER(B27),YEAR(B27),"") | L27: =IF(ISNUMBER(B27),YEAR(B27)*100+MONTH(B27),"") | M27: =IF(ISNUMBER(B27),INT(B27),0) | N27: =IF(OR(C27="",F27="",Q27=0),0,IF(COUNTIFS(C$6:C27,C27,F$6:F27,F27,Q$6:Q27,1)=1,1,0)) | O27: =IF(OR(C27="",Q27=0,H27<>""),"",M27*10000+ROW()) | P27: =IF(OR(C27="",Q27=0),"",IF(AND(C27=Statement!$C$4,K27=Statement!$C$5),M27*10000+ROW(),"")) | Q27: =IF(AND(ISNUMBER(B27),OR(N(D27)>0,G27<>"")),1,0)
B28: 45999 | C28: Ravi Patel | D28: 20 | E28: Bank transfer | F28: General fund | H28: x | I28: Monthly | J28: =IF(AND(C28="",D28="",G28=""),"",IF(NOT(ISNUMBER(B28)),"Needs a date",IF(AND(D28<>"",NOT(ISNUMBER(D28))),"Amount not a number",IF(N(D28)<0,"Amount below zero",IF(AND(N(D28)=0,G28=""),"Needs an amount or goods",IF(C28="","",IF(COUNTIF(Donors!$B$6:$B$305,C28)=0,"Not on Donors",""))))))) | K28: =IF(ISNUMBER(B28),YEAR(B28),"") | L28: =IF(ISNUMBER(B28),YEAR(B28)*100+MONTH(B28),"") | M28: =IF(ISNUMBER(B28),INT(B28),0) | N28: =IF(OR(C28="",F28="",Q28=0),0,IF(COUNTIFS(C$6:C28,C28,F$6:F28,F28,Q$6:Q28,1)=1,1,0)) | O28: =IF(OR(C28="",Q28=0,H28<>""),"",M28*10000+ROW()) | P28: =IF(OR(C28="",Q28=0),"",IF(AND(C28=Statement!$C$4,K28=Statement!$C$5),M28*10000+ROW(),"")) | Q28: =IF(AND(ISNUMBER(B28),OR(N(D28)>0,G28<>"")),1,0)
B29: 46000 | C29: Amina Yusuf | D29: 15 | E29: Bank transfer | F29: General fund | H29: x | I29: Monthly | J29: =IF(AND(C29="",D29="",G29=""),"",IF(NOT(ISNUMBER(B29)),"Needs a date",IF(AND(D29<>"",NOT(ISNUMBER(D29))),"Amount not a number",IF(N(D29)<0,"Amount below zero",IF(AND(N(D29)=0,G29=""),"Needs an amount or goods",IF(C29="","",IF(COUNTIF(Donors!$B$6:$B$305,C29)=0,"Not on Donors",""))))))) | K29: =IF(ISNUMBER(B29),YEAR(B29),"") | L29: =IF(ISNUMBER(B29),YEAR(B29)*100+MONTH(B29),"") | M29: =IF(ISNUMBER(B29),INT(B29),0) | N29: =IF(OR(C29="",F29="",Q29=0),0,IF(COUNTIFS(C$6:C29,C29,F$6:F29,F29,Q$6:Q29,1)=1,1,0)) | O29: =IF(OR(C29="",Q29=0,H29<>""),"",M29*10000+ROW()) | P29: =IF(OR(C29="",Q29=0),"",IF(AND(C29=Statement!$C$4,K29=Statement!$C$5),M29*10000+ROW(),"")) | Q29: =IF(AND(ISNUMBER(B29),OR(N(D29)>0,G29<>"")),1,0)
B30: 46027 | C30: Grace Holloway | D30: 25 | E30: Bank transfer | F30: General fund | H30: x | I30: Monthly | J30: =IF(AND(C30="",D30="",G30=""),"",IF(NOT(ISNUMBER(B30)),"Needs a date",IF(AND(D30<>"",NOT(ISNUMBER(D30))),"Amount not a number",IF(N(D30)<0,"Amount below zero",IF(AND(N(D30)=0,G30=""),"Needs an amount or goods",IF(C30="","",IF(COUNTIF(Donors!$B$6:$B$305,C30)=0,"Not on Donors",""))))))) | K30: =IF(ISNUMBER(B30),YEAR(B30),"") | L30: =IF(ISNUMBER(B30),YEAR(B30)*100+MONTH(B30),"") | M30: =IF(ISNUMBER(B30),INT(B30),0) | N30: =IF(OR(C30="",F30="",Q30=0),0,IF(COUNTIFS(C$6:C30,C30,F$6:F30,F30,Q$6:Q30,1)=1,1,0)) | O30: =IF(OR(C30="",Q30=0,H30<>""),"",M30*10000+ROW()) | P30: =IF(OR(C30="",Q30=0),"",IF(AND(C30=Statement!$C$4,K30=Statement!$C$5),M30*10000+ROW(),"")) | Q30: =IF(AND(ISNUMBER(B30),OR(N(D30)>0,G30<>"")),1,0)
B31: 46030 | C31: Ravi Patel | D31: 20 | E31: Bank transfer | F31: General fund | H31: x | I31: Monthly | J31: =IF(AND(C31="",D31="",G31=""),"",IF(NOT(ISNUMBER(B31)),"Needs a date",IF(AND(D31<>"",NOT(ISNUMBER(D31))),"Amount not a number",IF(N(D31)<0,"Amount below zero",IF(AND(N(D31)=0,G31=""),"Needs an amount or goods",IF(C31="","",IF(COUNTIF(Donors!$B$6:$B$305,C31)=0,"Not on Donors",""))))))) | K31: =IF(ISNUMBER(B31),YEAR(B31),"") | L31: =IF(ISNUMBER(B31),YEAR(B31)*100+MONTH(B31),"") | M31: =IF(ISNUMBER(B31),INT(B31),0) | N31: =IF(OR(C31="",F31="",Q31=0),0,IF(COUNTIFS(C$6:C31,C31,F$6:F31,F31,Q$6:Q31,1)=1,1,0)) | O31: =IF(OR(C31="",Q31=0,H31<>""),"",M31*10000+ROW()) | P31: =IF(OR(C31="",Q31=0),"",IF(AND(C31=Statement!$C$4,K31=Statement!$C$5),M31*10000+ROW(),"")) | Q31: =IF(AND(ISNUMBER(B31),OR(N(D31)>0,G31<>"")),1,0)
B32: 46031 | C32: Amina Yusuf | D32: 15 | E32: Bank transfer | F32: General fund | H32: x | I32: Monthly | J32: =IF(AND(C32="",D32="",G32=""),"",IF(NOT(ISNUMBER(B32)),"Needs a date",IF(AND(D32<>"",NOT(ISNUMBER(D32))),"Amount not a number",IF(N(D32)<0,"Amount below zero",IF(AND(N(D32)=0,G32=""),"Needs an amount or goods",IF(C32="","",IF(COUNTIF(Donors!$B$6:$B$305,C32)=0,"Not on Donors",""))))))) | K32: =IF(ISNUMBER(B32),YEAR(B32),"") | L32: =IF(ISNUMBER(B32),YEAR(B32)*100+MONTH(B32),"") | M32: =IF(ISNUMBER(B32),INT(B32),0) | N32: =IF(OR(C32="",F32="",Q32=0),0,IF(COUNTIFS(C$6:C32,C32,F$6:F32,F32,Q$6:Q32,1)=1,1,0)) | O32: =IF(OR(C32="",Q32=0,H32<>""),"",M32*10000+ROW()) | P32: =IF(OR(C32="",Q32=0),"",IF(AND(C32=Statement!$C$4,K32=Statement!$C$5),M32*10000+ROW(),"")) | Q32: =IF(AND(ISNUMBER(B32),OR(N(D32)>0,G32<>"")),1,0)
B33: 46058 | C33: Grace Holloway | D33: 25 | E33: Bank transfer | F33: General fund | H33: x | I33: Monthly | J33: =IF(AND(C33="",D33="",G33=""),"",IF(NOT(ISNUMBER(B33)),"Needs a date",IF(AND(D33<>"",NOT(ISNUMBER(D33))),"Amount not a number",IF(N(D33)<0,"Amount below zero",IF(AND(N(D33)=0,G33=""),"Needs an amount or goods",IF(C33="","",IF(COUNTIF(Donors!$B$6:$B$305,C33)=0,"Not on Donors",""))))))) | K33: =IF(ISNUMBER(B33),YEAR(B33),"") | L33: =IF(ISNUMBER(B33),YEAR(B33)*100+MONTH(B33),"") | M33: =IF(ISNUMBER(B33),INT(B33),0) | N33: =IF(OR(C33="",F33="",Q33=0),0,IF(COUNTIFS(C$6:C33,C33,F$6:F33,F33,Q$6:Q33,1)=1,1,0)) | O33: =IF(OR(C33="",Q33=0,H33<>""),"",M33*10000+ROW()) | P33: =IF(OR(C33="",Q33=0),"",IF(AND(C33=Statement!$C$4,K33=Statement!$C$5),M33*10000+ROW(),"")) | Q33: =IF(AND(ISNUMBER(B33),OR(N(D33)>0,G33<>"")),1,0)
B34: 46061 | C34: Ravi Patel | D34: 20 | E34: Bank transfer | F34: General fund | H34: x | I34: Monthly | J34: =IF(AND(C34="",D34="",G34=""),"",IF(NOT(ISNUMBER(B34)),"Needs a date",IF(AND(D34<>"",NOT(ISNUMBER(D34))),"Amount not a number",IF(N(D34)<0,"Amount below zero",IF(AND(N(D34)=0,G34=""),"Needs an amount or goods",IF(C34="","",IF(COUNTIF(Donors!$B$6:$B$305,C34)=0,"Not on Donors",""))))))) | K34: =IF(ISNUMBER(B34),YEAR(B34),"") | L34: =IF(ISNUMBER(B34),YEAR(B34)*100+MONTH(B34),"") | M34: =IF(ISNUMBER(B34),INT(B34),0) | N34: =IF(OR(C34="",F34="",Q34=0),0,IF(COUNTIFS(C$6:C34,C34,F$6:F34,F34,Q$6:Q34,1)=1,1,0)) | O34: =IF(OR(C34="",Q34=0,H34<>""),"",M34*10000+ROW()) | P34: =IF(OR(C34="",Q34=0),"",IF(AND(C34=Statement!$C$4,K34=Statement!$C$5),M34*10000+ROW(),"")) | Q34: =IF(AND(ISNUMBER(B34),OR(N(D34)>0,G34<>"")),1,0)
... B44: 46151 | C44: Amina Yusuf | D44: 15 | E44: Bank transfer | F44: General fund | H44: x | I44: Monthly | J44: =IF(AND(C44="",D44="",G44=""),"",IF(NOT(ISNUMBER(B44)),"Needs a date",IF(AND(D44<>"",NOT(ISNUMBER(D44))),"Amount not a number",IF(N(D44)<0,"Amount below zero",IF(AND(N(D44)=0,G44=""),"Needs an amount or goods",IF(C44="","",IF(COUNTIF(Donors!$B$6:$B$305,C44)=0,"Not on Donors",""))))))) | K44: =IF(ISNUMBER(B44),YEAR(B44),"") | L44: =IF(ISNUMBER(B44),YEAR(B44)*100+MONTH(B44),"") | M44: =IF(ISNUMBER(B44),INT(B44),0) | N44: =IF(OR(C44="",F44="",Q44=0),0,IF(COUNTIFS(C$6:C44,C44,F$6:F44,F44,Q$6:Q44,1)=1,1,0)) | O44: =IF(OR(C44="",Q44=0,H44<>""),"",M44*10000+ROW()) | P44: =IF(OR(C44="",Q44=0),"",IF(AND(C44=Statement!$C$4,K44=Statement!$C$5),M44*10000+ROW(),"")) | Q44: =IF(AND(ISNUMBER(B44),OR(N(D44)>0,G44<>"")),1,0)
B45: 46153 | C45: Riverton Hardware | D45: 500 | E45: Check | F45: New freezer | H45: x | J45: =IF(AND(C45="",D45="",G45=""),"",IF(NOT(ISNUMBER(B45)),"Needs a date",IF(AND(D45<>"",NOT(ISNUMBER(D45))),"Amount not a number",IF(N(D45)<0,"Amount below zero",IF(AND(N(D45)=0,G45=""),"Needs an amount or goods",IF(C45="","",IF(COUNTIF(Donors!$B$6:$B$305,C45)=0,"Not on Donors",""))))))) | K45: =IF(ISNUMBER(B45),YEAR(B45),"") | L45: =IF(ISNUMBER(B45),YEAR(B45)*100+MONTH(B45),"") | M45: =IF(ISNUMBER(B45),INT(B45),0) | N45: =IF(OR(C45="",F45="",Q45=0),0,IF(COUNTIFS(C$6:C45,C45,F$6:F45,F45,Q$6:Q45,1)=1,1,0)) | O45: =IF(OR(C45="",Q45=0,H45<>""),"",M45*10000+ROW()) | P45: =IF(OR(C45="",Q45=0),"",IF(AND(C45=Statement!$C$4,K45=Statement!$C$5),M45*10000+ROW(),"")) | Q45: =IF(AND(ISNUMBER(B45),OR(N(D45)>0,G45<>"")),1,0)
B46: 46173 | C46: Old Mill Trust | D46: 2500 | E46: Bank transfer | F46: New freezer | H46: x | I46: Yearly grant | J46: =IF(AND(C46="",D46="",G46=""),"",IF(NOT(ISNUMBER(B46)),"Needs a date",IF(AND(D46<>"",NOT(ISNUMBER(D46))),"Amount not a number",IF(N(D46)<0,"Amount below zero",IF(AND(N(D46)=0,G46=""),"Needs an amount or goods",IF(C46="","",IF(COUNTIF(Donors!$B$6:$B$305,C46)=0,"Not on Donors",""))))))) | K46: =IF(ISNUMBER(B46),YEAR(B46),"") | L46: =IF(ISNUMBER(B46),YEAR(B46)*100+MONTH(B46),"") | M46: =IF(ISNUMBER(B46),INT(B46),0) | N46: =IF(OR(C46="",F46="",Q46=0),0,IF(COUNTIFS(C$6:C46,C46,F$6:F46,F46,Q$6:Q46,1)=1,1,0)) | O46: =IF(OR(C46="",Q46=0,H46<>""),"",M46*10000+ROW()) | P46: =IF(OR(C46="",Q46=0),"",IF(AND(C46=Statement!$C$4,K46=Statement!$C$5),M46*10000+ROW(),"")) | Q46: =IF(AND(ISNUMBER(B46),OR(N(D46)>0,G46<>"")),1,0)
B47: 46178 | C47: Grace Holloway | D47: 25 | E47: Bank transfer | F47: General fund | H47: x | I47: Monthly | J47: =IF(AND(C47="",D47="",G47=""),"",IF(NOT(ISNUMBER(B47)),"Needs a date",IF(AND(D47<>"",NOT(ISNUMBER(D47))),"Amount not a number",IF(N(D47)<0,"Amount below zero",IF(AND(N(D47)=0,G47=""),"Needs an amount or goods",IF(C47="","",IF(COUNTIF(Donors!$B$6:$B$305,C47)=0,"Not on Donors",""))))))) | K47: =IF(ISNUMBER(B47),YEAR(B47),"") | L47: =IF(ISNUMBER(B47),YEAR(B47)*100+MONTH(B47),"") | M47: =IF(ISNUMBER(B47),INT(B47),0) | N47: =IF(OR(C47="",F47="",Q47=0),0,IF(COUNTIFS(C$6:C47,C47,F$6:F47,F47,Q$6:Q47,1)=1,1,0)) | O47: =IF(OR(C47="",Q47=0,H47<>""),"",M47*10000+ROW()) | P47: =IF(OR(C47="",Q47=0),"",IF(AND(C47=Statement!$C$4,K47=Statement!$C$5),M47*10000+ROW(),"")) | Q47: =IF(AND(ISNUMBER(B47),OR(N(D47)>0,G47<>"")),1,0)
B48: 46181 | C48: Ravi Patel | D48: 20 | E48: Bank transfer | F48: General fund | H48: x | I48: Monthly | J48: =IF(AND(C48="",D48="",G48=""),"",IF(NOT(ISNUMBER(B48)),"Needs a date",IF(AND(D48<>"",NOT(ISNUMBER(D48))),"Amount not a number",IF(N(D48)<0,"Amount below zero",IF(AND(N(D48)=0,G48=""),"Needs an amount or goods",IF(C48="","",IF(COUNTIF(Donors!$B$6:$B$305,C48)=0,"Not on Donors",""))))))) | K48: =IF(ISNUMBER(B48),YEAR(B48),"") | L48: =IF(ISNUMBER(B48),YEAR(B48)*100+MONTH(B48),"") | M48: =IF(ISNUMBER(B48),INT(B48),0) | N48: =IF(OR(C48="",F48="",Q48=0),0,IF(COUNTIFS(C$6:C48,C48,F$6:F48,F48,Q$6:Q48,1)=1,1,0)) | O48: =IF(OR(C48="",Q48=0,H48<>""),"",M48*10000+ROW()) | P48: =IF(OR(C48="",Q48=0),"",IF(AND(C48=Statement!$C$4,K48=Statement!$C$5),M48*10000+ROW(),"")) | Q48: =IF(AND(ISNUMBER(B48),OR(N(D48)>0,G48<>"")),1,0)
B49: 46182 | C49: Amina Yusuf | D49: 15 | E49: Bank transfer | F49: General fund | H49: x | I49: Monthly | J49: =IF(AND(C49="",D49="",G49=""),"",IF(NOT(ISNUMBER(B49)),"Needs a date",IF(AND(D49<>"",NOT(ISNUMBER(D49))),"Amount not a number",IF(N(D49)<0,"Amount below zero",IF(AND(N(D49)=0,G49=""),"Needs an amount or goods",IF(C49="","",IF(COUNTIF(Donors!$B$6:$B$305,C49)=0,"Not on Donors",""))))))) | K49: =IF(ISNUMBER(B49),YEAR(B49),"") | L49: =IF(ISNUMBER(B49),YEAR(B49)*100+MONTH(B49),"") | M49: =IF(ISNUMBER(B49),INT(B49),0) | N49: =IF(OR(C49="",F49="",Q49=0),0,IF(COUNTIFS(C$6:C49,C49,F$6:F49,F49,Q$6:Q49,1)=1,1,0)) | O49: =IF(OR(C49="",Q49=0,H49<>""),"",M49*10000+ROW()) | P49: =IF(OR(C49="",Q49=0),"",IF(AND(C49=Statement!$C$4,K49=Statement!$C$5),M49*10000+ROW(),"")) | Q49: =IF(AND(ISNUMBER(B49),OR(N(D49)>0,G49<>"")),1,0)
B50: 46193 | C50: Corner Bakery | D50: 150 | E50: Card | F50: Back to school | H50: x | J50: =IF(AND(C50="",D50="",G50=""),"",IF(NOT(ISNUMBER(B50)),"Needs a date",IF(AND(D50<>"",NOT(ISNUMBER(D50))),"Amount not a number",IF(N(D50)<0,"Amount below zero",IF(AND(N(D50)=0,G50=""),"Needs an amount or goods",IF(C50="","",IF(COUNTIF(Donors!$B$6:$B$305,C50)=0,"Not on Donors",""))))))) | K50: =IF(ISNUMBER(B50),YEAR(B50),"") | L50: =IF(ISNUMBER(B50),YEAR(B50)*100+MONTH(B50),"") | M50: =IF(ISNUMBER(B50),INT(B50),0) | N50: =IF(OR(C50="",F50="",Q50=0),0,IF(COUNTIFS(C$6:C50,C50,F$6:F50,F50,Q$6:Q50,1)=1,1,0)) | O50: =IF(OR(C50="",Q50=0,H50<>""),"",M50*10000+ROW()) | P50: =IF(OR(C50="",Q50=0),"",IF(AND(C50=Statement!$C$4,K50=Statement!$C$5),M50*10000+ROW(),"")) | Q50: =IF(AND(ISNUMBER(B50),OR(N(D50)>0,G50<>"")),1,0)
B51: 46198 | C51: St Luke's Youth Group | D51: 320 | E51: Cash | F51: Back to school | H51: x | I51: Car wash | J51: =IF(AND(C51="",D51="",G51=""),"",IF(NOT(ISNUMBER(B51)),"Needs a date",IF(AND(D51<>"",NOT(ISNUMBER(D51))),"Amount not a number",IF(N(D51)<0,"Amount below zero",IF(AND(N(D51)=0,G51=""),"Needs an amount or goods",IF(C51="","",IF(COUNTIF(Donors!$B$6:$B$305,C51)=0,"Not on Donors",""))))))) | K51: =IF(ISNUMBER(B51),YEAR(B51),"") | L51: =IF(ISNUMBER(B51),YEAR(B51)*100+MONTH(B51),"") | M51: =IF(ISNUMBER(B51),INT(B51),0) | N51: =IF(OR(C51="",F51="",Q51=0),0,IF(COUNTIFS(C$6:C51,C51,F$6:F51,F51,Q$6:Q51,1)=1,1,0)) | O51: =IF(OR(C51="",Q51=0,H51<>""),"",M51*10000+ROW()) | P51: =IF(OR(C51="",Q51=0),"",IF(AND(C51=Statement!$C$4,K51=Statement!$C$5),M51*10000+ROW(),"")) | Q51: =IF(AND(ISNUMBER(B51),OR(N(D51)>0,G51<>"")),1,0)
B52: 46203 | C52: Tom and Jess Carter | D52: 100 | E52: Card | F52: Back to school | H52: x | J52: =IF(AND(C52="",D52="",G52=""),"",IF(NOT(ISNUMBER(B52)),"Needs a date",IF(AND(D52<>"",NOT(ISNUMBER(D52))),"Amount not a number",IF(N(D52)<0,"Amount below zero",IF(AND(N(D52)=0,G52=""),"Needs an amount or goods",IF(C52="","",IF(COUNTIF(Donors!$B$6:$B$305,C52)=0,"Not on Donors",""))))))) | K52: =IF(ISNUMBER(B52),YEAR(B52),"") | L52: =IF(ISNUMBER(B52),YEAR(B52)*100+MONTH(B52),"") | M52: =IF(ISNUMBER(B52),INT(B52),0) | N52: =IF(OR(C52="",F52="",Q52=0),0,IF(COUNTIFS(C$6:C52,C52,F$6:F52,F52,Q$6:Q52,1)=1,1,0)) | O52: =IF(OR(C52="",Q52=0,H52<>""),"",M52*10000+ROW()) | P52: =IF(OR(C52="",Q52=0),"",IF(AND(C52=Statement!$C$4,K52=Statement!$C$5),M52*10000+ROW(),"")) | Q52: =IF(AND(ISNUMBER(B52),OR(N(D52)>0,G52<>"")),1,0)
B53: 46208 | C53: Grace Holloway | D53: 25 | E53: Bank transfer | F53: General fund | H53: x | I53: Monthly | J53: =IF(AND(C53="",D53="",G53=""),"",IF(NOT(ISNUMBER(B53)),"Needs a date",IF(AND(D53<>"",NOT(ISNUMBER(D53))),"Amount not a number",IF(N(D53)<0,"Amount below zero",IF(AND(N(D53)=0,G53=""),"Needs an amount or goods",IF(C53="","",IF(COUNTIF(Donors!$B$6:$B$305,C53)=0,"Not on Donors",""))))))) | K53: =IF(ISNUMBER(B53),YEAR(B53),"") | L53: =IF(ISNUMBER(B53),YEAR(B53)*100+MONTH(B53),"") | M53: =IF(ISNUMBER(B53),INT(B53),0) | N53: =IF(OR(C53="",F53="",Q53=0),0,IF(COUNTIFS(C$6:C53,C53,F$6:F53,F53,Q$6:Q53,1)=1,1,0)) | O53: =IF(OR(C53="",Q53=0,H53<>""),"",M53*10000+ROW()) | P53: =IF(OR(C53="",Q53=0),"",IF(AND(C53=Statement!$C$4,K53=Statement!$C$5),M53*10000+ROW(),"")) | Q53: =IF(AND(ISNUMBER(B53),OR(N(D53)>0,G53<>"")),1,0)
B54: 46211 | C54: Ravi Patel | D54: 20 | E54: Bank transfer | F54: General fund | H54: x | I54: Monthly | J54: =IF(AND(C54="",D54="",G54=""),"",IF(NOT(ISNUMBER(B54)),"Needs a date",IF(AND(D54<>"",NOT(ISNUMBER(D54))),"Amount not a number",IF(N(D54)<0,"Amount below zero",IF(AND(N(D54)=0,G54=""),"Needs an amount or goods",IF(C54="","",IF(COUNTIF(Donors!$B$6:$B$305,C54)=0,"Not on Donors",""))))))) | K54: =IF(ISNUMBER(B54),YEAR(B54),"") | L54: =IF(ISNUMBER(B54),YEAR(B54)*100+MONTH(B54),"") | M54: =IF(ISNUMBER(B54),INT(B54),0) | N54: =IF(OR(C54="",F54="",Q54=0),0,IF(COUNTIFS(C$6:C54,C54,F$6:F54,F54,Q$6:Q54,1)=1,1,0)) | O54: =IF(OR(C54="",Q54=0,H54<>""),"",M54*10000+ROW()) | P54: =IF(OR(C54="",Q54=0),"",IF(AND(C54=Statement!$C$4,K54=Statement!$C$5),M54*10000+ROW(),"")) | Q54: =IF(AND(ISNUMBER(B54),OR(N(D54)>0,G54<>"")),1,0)
B55: 46212 | C55: Amina Yusuf | D55: 15 | E55: Bank transfer | F55: General fund | H55: x | I55: Monthly | J55: =IF(AND(C55="",D55="",G55=""),"",IF(NOT(ISNUMBER(B55)),"Needs a date",IF(AND(D55<>"",NOT(ISNUMBER(D55))),"Amount not a number",IF(N(D55)<0,"Amount below zero",IF(AND(N(D55)=0,G55=""),"Needs an amount or goods",IF(C55="","",IF(COUNTIF(Donors!$B$6:$B$305,C55)=0,"Not on Donors",""))))))) | K55: =IF(ISNUMBER(B55),YEAR(B55),"") | L55: =IF(ISNUMBER(B55),YEAR(B55)*100+MONTH(B55),"") | M55: =IF(ISNUMBER(B55),INT(B55),0) | N55: =IF(OR(C55="",F55="",Q55=0),0,IF(COUNTIFS(C$6:C55,C55,F$6:F55,F55,Q$6:Q55,1)=1,1,0)) | O55: =IF(OR(C55="",Q55=0,H55<>""),"",M55*10000+ROW()) | P55: =IF(OR(C55="",Q55=0),"",IF(AND(C55=Statement!$C$4,K55=Statement!$C$5),M55*10000+ROW(),"")) | Q55: =IF(AND(ISNUMBER(B55),OR(N(D55)>0,G55<>"")),1,0)
B56: 46218 | D56: 64 | E56: Cash | F56: General fund | I56: Collection box | J56: =IF(AND(C56="",D56="",G56=""),"",IF(NOT(ISNUMBER(B56)),"Needs a date",IF(AND(D56<>"",NOT(ISNUMBER(D56))),"Amount not a number",IF(N(D56)<0,"Amount below zero",IF(AND(N(D56)=0,G56=""),"Needs an amount or goods",IF(C56="","",IF(COUNTIF(Donors!$B$6:$B$305,C56)=0,"Not on Donors",""))))))) | K56: =IF(ISNUMBER(B56),YEAR(B56),"") | L56: =IF(ISNUMBER(B56),YEAR(B56)*100+MONTH(B56),"") | M56: =IF(ISNUMBER(B56),INT(B56),0) | N56: =IF(OR(C56="",F56="",Q56=0),0,IF(COUNTIFS(C$6:C56,C56,F$6:F56,F56,Q$6:Q56,1)=1,1,0)) | O56: =IF(OR(C56="",Q56=0,H56<>""),"",M56*10000+ROW()) | P56: =IF(OR(C56="",Q56=0),"",IF(AND(C56=Statement!$C$4,K56=Statement!$C$5),M56*10000+ROW(),"")) | Q56: =IF(AND(ISNUMBER(B56),OR(N(D56)>0,G56<>"")),1,0)
B57: 46233 | C57: Riverton Rotary | D57: 750 | E57: Check | F57: New freezer | H57: x | J57: =IF(AND(C57="",D57="",G57=""),"",IF(NOT(ISNUMBER(B57)),"Needs a date",IF(AND(D57<>"",NOT(ISNUMBER(D57))),"Amount not a number",IF(N(D57)<0,"Amount below zero",IF(AND(N(D57)=0,G57=""),"Needs an amount or goods",IF(C57="","",IF(COUNTIF(Donors!$B$6:$B$305,C57)=0,"Not on Donors",""))))))) | K57: =IF(ISNUMBER(B57),YEAR(B57),"") | L57: =IF(ISNUMBER(B57),YEAR(B57)*100+MONTH(B57),"") | M57: =IF(ISNUMBER(B57),INT(B57),0) | N57: =IF(OR(C57="",F57="",Q57=0),0,IF(COUNTIFS(C$6:C57,C57,F$6:F57,F57,Q$6:Q57,1)=1,1,0)) | O57: =IF(OR(C57="",Q57=0,H57<>""),"",M57*10000+ROW()) | P57: =IF(OR(C57="",Q57=0),"",IF(AND(C57=Statement!$C$4,K57=Statement!$C$5),M57*10000+ROW(),"")) | Q57: =IF(AND(ISNUMBER(B57),OR(N(D57)>0,G57<>"")),1,0)
B58: 46239 | C58: Grace Holloway | D58: 25 | E58: Bank transfer | F58: General fund | H58: x | I58: Monthly | J58: =IF(AND(C58="",D58="",G58=""),"",IF(NOT(ISNUMBER(B58)),"Needs a date",IF(AND(D58<>"",NOT(ISNUMBER(D58))),"Amount not a number",IF(N(D58)<0,"Amount below zero",IF(AND(N(D58)=0,G58=""),"Needs an amount or goods",IF(C58="","",IF(COUNTIF(Donors!$B$6:$B$305,C58)=0,"Not on Donors",""))))))) | K58: =IF(ISNUMBER(B58),YEAR(B58),"") | L58: =IF(ISNUMBER(B58),YEAR(B58)*100+MONTH(B58),"") | M58: =IF(ISNUMBER(B58),INT(B58),0) | N58: =IF(OR(C58="",F58="",Q58=0),0,IF(COUNTIFS(C$6:C58,C58,F$6:F58,F58,Q$6:Q58,1)=1,1,0)) | O58: =IF(OR(C58="",Q58=0,H58<>""),"",M58*10000+ROW()) | P58: =IF(OR(C58="",Q58=0),"",IF(AND(C58=Statement!$C$4,K58=Statement!$C$5),M58*10000+ROW(),"")) | Q58: =IF(AND(ISNUMBER(B58),OR(N(D58)>0,G58<>"")),1,0)
B59: 46242 | C59: Ravi Patel | D59: 20 | E59: Bank transfer | F59: General fund | H59: x | I59: Monthly | J59: =IF(AND(C59="",D59="",G59=""),"",IF(NOT(ISNUMBER(B59)),"Needs a date",IF(AND(D59<>"",NOT(ISNUMBER(D59))),"Amount not a number",IF(N(D59)<0,"Amount below zero",IF(AND(N(D59)=0,G59=""),"Needs an amount or goods",IF(C59="","",IF(COUNTIF(Donors!$B$6:$B$305,C59)=0,"Not on Donors",""))))))) | K59: =IF(ISNUMBER(B59),YEAR(B59),"") | L59: =IF(ISNUMBER(B59),YEAR(B59)*100+MONTH(B59),"") | M59: =IF(ISNUMBER(B59),INT(B59),0) | N59: =IF(OR(C59="",F59="",Q59=0),0,IF(COUNTIFS(C$6:C59,C59,F$6:F59,F59,Q$6:Q59,1)=1,1,0)) | O59: =IF(OR(C59="",Q59=0,H59<>""),"",M59*10000+ROW()) | P59: =IF(OR(C59="",Q59=0),"",IF(AND(C59=Statement!$C$4,K59=Statement!$C$5),M59*10000+ROW(),"")) | Q59: =IF(AND(ISNUMBER(B59),OR(N(D59)>0,G59<>"")),1,0)
B60: 46243 | C60: Amina Yusuf | D60: 15 | E60: Bank transfer | F60: General fund | H60: x | I60: Monthly | J60: =IF(AND(C60="",D60="",G60=""),"",IF(NOT(ISNUMBER(B60)),"Needs a date",IF(AND(D60<>"",NOT(ISNUMBER(D60))),"Amount not a number",IF(N(D60)<0,"Amount below zero",IF(AND(N(D60)=0,G60=""),"Needs an amount or goods",IF(C60="","",IF(COUNTIF(Donors!$B$6:$B$305,C60)=0,"Not on Donors",""))))))) | K60: =IF(ISNUMBER(B60),YEAR(B60),"") | L60: =IF(ISNUMBER(B60),YEAR(B60)*100+MONTH(B60),"") | M60: =IF(ISNUMBER(B60),INT(B60),0) | N60: =IF(OR(C60="",F60="",Q60=0),0,IF(COUNTIFS(C$6:C60,C60,F$6:F60,F60,Q$6:Q60,1)=1,1,0)) | O60: =IF(OR(C60="",Q60=0,H60<>""),"",M60*10000+ROW()) | P60: =IF(OR(C60="",Q60=0),"",IF(AND(C60=Statement!$C$4,K60=Statement!$C$5),M60*10000+ROW(),"")) | Q60: =IF(AND(ISNUMBER(B60),OR(N(D60)>0,G60<>"")),1,0)
B61: 46248 | C61: Daniel Mercer | D61: 60 | E61: Online | F61: Back to school | H61: x | J61: =IF(AND(C61="",D61="",G61=""),"",IF(NOT(ISNUMBER(B61)),"Needs a date",IF(AND(D61<>"",NOT(ISNUMBER(D61))),"Amount not a number",IF(N(D61)<0,"Amount below zero",IF(AND(N(D61)=0,G61=""),"Needs an amount or goods",IF(C61="","",IF(COUNTIF(Donors!$B$6:$B$305,C61)=0,"Not on Donors",""))))))) | K61: =IF(ISNUMBER(B61),YEAR(B61),"") | L61: =IF(ISNUMBER(B61),YEAR(B61)*100+MONTH(B61),"") | M61: =IF(ISNUMBER(B61),INT(B61),0) | N61: =IF(OR(C61="",F61="",Q61=0),0,IF(COUNTIFS(C$6:C61,C61,F$6:F61,F61,Q$6:Q61,1)=1,1,0)) | O61: =IF(OR(C61="",Q61=0,H61<>""),"",M61*10000+ROW()) | P61: =IF(OR(C61="",Q61=0),"",IF(AND(C61=Statement!$C$4,K61=Statement!$C$5),M61*10000+ROW(),"")) | Q61: =IF(AND(ISNUMBER(B61),OR(N(D61)>0,G61<>"")),1,0)
B62: 46258 | C62: Sofia Rossi | D62: 40 | E62: Online | F62: Winter coat drive | H62: x | J62: =IF(AND(C62="",D62="",G62=""),"",IF(NOT(ISNUMBER(B62)),"Needs a date",IF(AND(D62<>"",NOT(ISNUMBER(D62))),"Amount not a number",IF(N(D62)<0,"Amount below zero",IF(AND(N(D62)=0,G62=""),"Needs an amount or goods",IF(C62="","",IF(COUNTIF(Donors!$B$6:$B$305,C62)=0,"Not on Donors",""))))))) | K62: =IF(ISNUMBER(B62),YEAR(B62),"") | L62: =IF(ISNUMBER(B62),YEAR(B62)*100+MONTH(B62),"") | M62: =IF(ISNUMBER(B62),INT(B62),0) | N62: =IF(OR(C62="",F62="",Q62=0),0,IF(COUNTIFS(C$6:C62,C62,F$6:F62,F62,Q$6:Q62,1)=1,1,0)) | O62: =IF(OR(C62="",Q62=0,H62<>""),"",M62*10000+ROW()) | P62: =IF(OR(C62="",Q62=0),"",IF(AND(C62=Statement!$C$4,K62=Statement!$C$5),M62*10000+ROW(),"")) | Q62: =IF(AND(ISNUMBER(B62),OR(N(D62)>0,G62<>"")),1,0)
B63: 46263 | C63: Corner Bakery | D63: 200 | E63: Card | F63: Winter coat drive | H63: x | J63: =IF(AND(C63="",D63="",G63=""),"",IF(NOT(ISNUMBER(B63)),"Needs a date",IF(AND(D63<>"",NOT(ISNUMBER(D63))),"Amount not a number",IF(N(D63)<0,"Amount below zero",IF(AND(N(D63)=0,G63=""),"Needs an amount or goods",IF(C63="","",IF(COUNTIF(Donors!$B$6:$B$305,C63)=0,"Not on Donors",""))))))) | K63: =IF(ISNUMBER(B63),YEAR(B63),"") | L63: =IF(ISNUMBER(B63),YEAR(B63)*100+MONTH(B63),"") | M63: =IF(ISNUMBER(B63),INT(B63),0) | N63: =IF(OR(C63="",F63="",Q63=0),0,IF(COUNTIFS(C$6:C63,C63,F$6:F63,F63,Q$6:Q63,1)=1,1,0)) | O63: =IF(OR(C63="",Q63=0,H63<>""),"",M63*10000+ROW()) | P63: =IF(OR(C63="",Q63=0),"",IF(AND(C63=Statement!$C$4,K63=Statement!$C$5),M63*10000+ROW(),"")) | Q63: =IF(AND(ISNUMBER(B63),OR(N(D63)>0,G63<>"")),1,0)
B64: 46270 | C64: Grace Holloway | D64: 25 | E64: Bank transfer | F64: General fund | H64: x | I64: Monthly | J64: =IF(AND(C64="",D64="",G64=""),"",IF(NOT(ISNUMBER(B64)),"Needs a date",IF(AND(D64<>"",NOT(ISNUMBER(D64))),"Amount not a number",IF(N(D64)<0,"Amount below zero",IF(AND(N(D64)=0,G64=""),"Needs an amount or goods",IF(C64="","",IF(COUNTIF(Donors!$B$6:$B$305,C64)=0,"Not on Donors",""))))))) | K64: =IF(ISNUMBER(B64),YEAR(B64),"") | L64: =IF(ISNUMBER(B64),YEAR(B64)*100+MONTH(B64),"") | M64: =IF(ISNUMBER(B64),INT(B64),0) | N64: =IF(OR(C64="",F64="",Q64=0),0,IF(COUNTIFS(C$6:C64,C64,F$6:F64,F64,Q$6:Q64,1)=1,1,0)) | O64: =IF(OR(C64="",Q64=0,H64<>""),"",M64*10000+ROW()) | P64: =IF(OR(C64="",Q64=0),"",IF(AND(C64=Statement!$C$4,K64=Statement!$C$5),M64*10000+ROW(),"")) | Q64: =IF(AND(ISNUMBER(B64),OR(N(D64)>0,G64<>"")),1,0)
B65: 46272 | C65: Tom and Jess Carter | D65: 120 | E65: Online | F65: Winter coat drive | H65: x | J65: =IF(AND(C65="",D65="",G65=""),"",IF(NOT(ISNUMBER(B65)),"Needs a date",IF(AND(D65<>"",NOT(ISNUMBER(D65))),"Amount not a number",IF(N(D65)<0,"Amount below zero",IF(AND(N(D65)=0,G65=""),"Needs an amount or goods",IF(C65="","",IF(COUNTIF(Donors!$B$6:$B$305,C65)=0,"Not on Donors",""))))))) | K65: =IF(ISNUMBER(B65),YEAR(B65),"") | L65: =IF(ISNUMBER(B65),YEAR(B65)*100+MONTH(B65),"") | M65: =IF(ISNUMBER(B65),INT(B65),0) | N65: =IF(OR(C65="",F65="",Q65=0),0,IF(COUNTIFS(C$6:C65,C65,F$6:F65,F65,Q$6:Q65,1)=1,1,0)) | O65: =IF(OR(C65="",Q65=0,H65<>""),"",M65*10000+ROW()) | P65: =IF(OR(C65="",Q65=0),"",IF(AND(C65=Statement!$C$4,K65=Statement!$C$5),M65*10000+ROW(),"")) | Q65: =IF(AND(ISNUMBER(B65),OR(N(D65)>0,G65<>"")),1,0)
B66: 46273 | C66: Ravi Patel | D66: 20 | E66: Bank transfer | F66: General fund | H66: x | I66: Monthly | J66: =IF(AND(C66="",D66="",G66=""),"",IF(NOT(ISNUMBER(B66)),"Needs a date",IF(AND(D66<>"",NOT(ISNUMBER(D66))),"Amount not a number",IF(N(D66)<0,"Amount below zero",IF(AND(N(D66)=0,G66=""),"Needs an amount or goods",IF(C66="","",IF(COUNTIF(Donors!$B$6:$B$305,C66)=0,"Not on Donors",""))))))) | K66: =IF(ISNUMBER(B66),YEAR(B66),"") | L66: =IF(ISNUMBER(B66),YEAR(B66)*100+MONTH(B66),"") | M66: =IF(ISNUMBER(B66),INT(B66),0) | N66: =IF(OR(C66="",F66="",Q66=0),0,IF(COUNTIFS(C$6:C66,C66,F$6:F66,F66,Q$6:Q66,1)=1,1,0)) | O66: =IF(OR(C66="",Q66=0,H66<>""),"",M66*10000+ROW()) | P66: =IF(OR(C66="",Q66=0),"",IF(AND(C66=Statement!$C$4,K66=Statement!$C$5),M66*10000+ROW(),"")) | Q66: =IF(AND(ISNUMBER(B66),OR(N(D66)>0,G66<>"")),1,0)
B67: 46274 | C67: Amina Yusuf | D67: 15 | E67: Bank transfer | F67: General fund | H67: x | I67: Monthly | J67: =IF(AND(C67="",D67="",G67=""),"",IF(NOT(ISNUMBER(B67)),"Needs a date",IF(AND(D67<>"",NOT(ISNUMBER(D67))),"Amount not a number",IF(N(D67)<0,"Amount below zero",IF(AND(N(D67)=0,G67=""),"Needs an amount or goods",IF(C67="","",IF(COUNTIF(Donors!$B$6:$B$305,C67)=0,"Not on Donors",""))))))) | K67: =IF(ISNUMBER(B67),YEAR(B67),"") | L67: =IF(ISNUMBER(B67),YEAR(B67)*100+MONTH(B67),"") | M67: =IF(ISNUMBER(B67),INT(B67),0) | N67: =IF(OR(C67="",F67="",Q67=0),0,IF(COUNTIFS(C$6:C67,C67,F$6:F67,F67,Q$6:Q67,1)=1,1,0)) | O67: =IF(OR(C67="",Q67=0,H67<>""),"",M67*10000+ROW()) | P67: =IF(OR(C67="",Q67=0),"",IF(AND(C67=Statement!$C$4,K67=Statement!$C$5),M67*10000+ROW(),"")) | Q67: =IF(AND(ISNUMBER(B67),OR(N(D67)>0,G67<>"")),1,0)
B68: 46275 | C68: Riverton Hardware | E68: Goods | F68: Winter coat drive | G68: 12 boxes of gloves | H68: x | J68: =IF(AND(C68="",D68="",G68=""),"",IF(NOT(ISNUMBER(B68)),"Needs a date",IF(AND(D68<>"",NOT(ISNUMBER(D68))),"Amount not a number",IF(N(D68)<0,"Amount below zero",IF(AND(N(D68)=0,G68=""),"Needs an amount or goods",IF(C68="","",IF(COUNTIF(Donors!$B$6:$B$305,C68)=0,"Not on Donors",""))))))) | K68: =IF(ISNUMBER(B68),YEAR(B68),"") | L68: =IF(ISNUMBER(B68),YEAR(B68)*100+MONTH(B68),"") | M68: =IF(ISNUMBER(B68),INT(B68),0) | N68: =IF(OR(C68="",F68="",Q68=0),0,IF(COUNTIFS(C$6:C68,C68,F$6:F68,F68,Q$6:Q68,1)=1,1,0)) | O68: =IF(OR(C68="",Q68=0,H68<>""),"",M68*10000+ROW()) | P68: =IF(OR(C68="",Q68=0),"",IF(AND(C68=Statement!$C$4,K68=Statement!$C$5),M68*10000+ROW(),"")) | Q68: =IF(AND(ISNUMBER(B68),OR(N(D68)>0,G68<>"")),1,0)
B69: 46279 | C69: Riverton Hardware | D69: 300 | E69: Check | F69: Winter coat drive | H69: x | J69: =IF(AND(C69="",D69="",G69=""),"",IF(NOT(ISNUMBER(B69)),"Needs a date",IF(AND(D69<>"",NOT(ISNUMBER(D69))),"Amount not a number",IF(N(D69)<0,"Amount below zero",IF(AND(N(D69)=0,G69=""),"Needs an amount or goods",IF(C69="","",IF(COUNTIF(Donors!$B$6:$B$305,C69)=0,"Not on Donors",""))))))) | K69: =IF(ISNUMBER(B69),YEAR(B69),"") | L69: =IF(ISNUMBER(B69),YEAR(B69)*100+MONTH(B69),"") | M69: =IF(ISNUMBER(B69),INT(B69),0) | N69: =IF(OR(C69="",F69="",Q69=0),0,IF(COUNTIFS(C$6:C69,C69,F$6:F69,F69,Q$6:Q69,1)=1,1,0)) | O69: =IF(OR(C69="",Q69=0,H69<>""),"",M69*10000+ROW()) | P69: =IF(OR(C69="",Q69=0),"",IF(AND(C69=Statement!$C$4,K69=Statement!$C$5),M69*10000+ROW(),"")) | Q69: =IF(AND(ISNUMBER(B69),OR(N(D69)>0,G69<>"")),1,0)
B70: 46283 | C70: Daniel Mercer | D70: 80 | E70: Online | F70: Winter coat drive | J70: =IF(AND(C70="",D70="",G70=""),"",IF(NOT(ISNUMBER(B70)),"Needs a date",IF(AND(D70<>"",NOT(ISNUMBER(D70))),"Amount not a number",IF(N(D70)<0,"Amount below zero",IF(AND(N(D70)=0,G70=""),"Needs an amount or goods",IF(C70="","",IF(COUNTIF(Donors!$B$6:$B$305,C70)=0,"Not on Donors",""))))))) | K70: =IF(ISNUMBER(B70),YEAR(B70),"") | L70: =IF(ISNUMBER(B70),YEAR(B70)*100+MONTH(B70),"") | M70: =IF(ISNUMBER(B70),INT(B70),0) | N70: =IF(OR(C70="",F70="",Q70=0),0,IF(COUNTIFS(C$6:C70,C70,F$6:F70,F70,Q$6:Q70,1)=1,1,0)) | O70: =IF(OR(C70="",Q70=0,H70<>""),"",M70*10000+ROW()) | P70: =IF(OR(C70="",Q70=0),"",IF(AND(C70=Statement!$C$4,K70=Statement!$C$5),M70*10000+ROW(),"")) | Q70: =IF(AND(ISNUMBER(B70),OR(N(D70)>0,G70<>"")),1,0)
B71: 46285 | C71: Corner Bakery | E71: Goods | F71: General fund | G71: 40 loaves of bread | J71: =IF(AND(C71="",D71="",G71=""),"",IF(NOT(ISNUMBER(B71)),"Needs a date",IF(AND(D71<>"",NOT(ISNUMBER(D71))),"Amount not a number",IF(N(D71)<0,"Amount below zero",IF(AND(N(D71)=0,G71=""),"Needs an amount or goods",IF(C71="","",IF(COUNTIF(Donors!$B$6:$B$305,C71)=0,"Not on Donors",""))))))) | K71: =IF(ISNUMBER(B71),YEAR(B71),"") | L71: =IF(ISNUMBER(B71),YEAR(B71)*100+MONTH(B71),"") | M71: =IF(ISNUMBER(B71),INT(B71),0) | N71: =IF(OR(C71="",F71="",Q71=0),0,IF(COUNTIFS(C$6:C71,C71,F$6:F71,F71,Q$6:Q71,1)=1,1,0)) | O71: =IF(OR(C71="",Q71=0,H71<>""),"",M71*10000+ROW()) | P71: =IF(OR(C71="",Q71=0),"",IF(AND(C71=Statement!$C$4,K71=Statement!$C$5),M71*10000+ROW(),"")) | Q71: =IF(AND(ISNUMBER(B71),OR(N(D71)>0,G71<>"")),1,0)
B72: 46287 | C72: St Luke's Youth Group | D72: 185 | E72: Cash | F72: Winter coat drive | I72: Bake sale | J72: =IF(AND(C72="",D72="",G72=""),"",IF(NOT(ISNUMBER(B72)),"Needs a date",IF(AND(D72<>"",NOT(ISNUMBER(D72))),"Amount not a number",IF(N(D72)<0,"Amount below zero",IF(AND(N(D72)=0,G72=""),"Needs an amount or goods",IF(C72="","",IF(COUNTIF(Donors!$B$6:$B$305,C72)=0,"Not on Donors",""))))))) | K72: =IF(ISNUMBER(B72),YEAR(B72),"") | L72: =IF(ISNUMBER(B72),YEAR(B72)*100+MONTH(B72),"") | M72: =IF(ISNUMBER(B72),INT(B72),0) | N72: =IF(OR(C72="",F72="",Q72=0),0,IF(COUNTIFS(C$6:C72,C72,F$6:F72,F72,Q$6:Q72,1)=1,1,0)) | O72: =IF(OR(C72="",Q72=0,H72<>""),"",M72*10000+ROW()) | P72: =IF(OR(C72="",Q72=0),"",IF(AND(C72=Statement!$C$4,K72=Statement!$C$5),M72*10000+ROW(),"")) | Q72: =IF(AND(ISNUMBER(B72),OR(N(D72)>0,G72<>"")),1,0)
B73: 46289 | D73: 48 | E73: Cash | F73: General fund | I73: Collection box | J73: =IF(AND(C73="",D73="",G73=""),"",IF(NOT(ISNUMBER(B73)),"Needs a date",IF(AND(D73<>"",NOT(ISNUMBER(D73))),"Amount not a number",IF(N(D73)<0,"Amount below zero",IF(AND(N(D73)=0,G73=""),"Needs an amount or goods",IF(C73="","",IF(COUNTIF(Donors!$B$6:$B$305,C73)=0,"Not on Donors",""))))))) | K73: =IF(ISNUMBER(B73),YEAR(B73),"") | L73: =IF(ISNUMBER(B73),YEAR(B73)*100+MONTH(B73),"") | M73: =IF(ISNUMBER(B73),INT(B73),0) | N73: =IF(OR(C73="",F73="",Q73=0),0,IF(COUNTIFS(C$6:C73,C73,F$6:F73,F73,Q$6:Q73,1)=1,1,0)) | O73: =IF(OR(C73="",Q73=0,H73<>""),"",M73*10000+ROW()) | P73: =IF(OR(C73="",Q73=0),"",IF(AND(C73=Statement!$C$4,K73=Statement!$C$5),M73*10000+ROW(),"")) | Q73: =IF(AND(ISNUMBER(B73),OR(N(D73)>0,G73<>"")),1,0)
B74: 46290 | C74: Sofia Rossi | D74: 50 | E74: Online | F74: New freezer | J74: =IF(AND(C74="",D74="",G74=""),"",IF(NOT(ISNUMBER(B74)),"Needs a date",IF(AND(D74<>"",NOT(ISNUMBER(D74))),"Amount not a number",IF(N(D74)<0,"Amount below zero",IF(AND(N(D74)=0,G74=""),"Needs an amount or goods",IF(C74="","",IF(COUNTIF(Donors!$B$6:$B$305,C74)=0,"Not on Donors",""))))))) | K74: =IF(ISNUMBER(B74),YEAR(B74),"") | L74: =IF(ISNUMBER(B74),YEAR(B74)*100+MONTH(B74),"") | M74: =IF(ISNUMBER(B74),INT(B74),0) | N74: =IF(OR(C74="",F74="",Q74=0),0,IF(COUNTIFS(C$6:C74,C74,F$6:F74,F74,Q$6:Q74,1)=1,1,0)) | O74: =IF(OR(C74="",Q74=0,H74<>""),"",M74*10000+ROW()) | P74: =IF(OR(C74="",Q74=0),"",IF(AND(C74=Statement!$C$4,K74=Statement!$C$5),M74*10000+ROW(),"")) | Q74: =IF(AND(ISNUMBER(B74),OR(N(D74)>0,G74<>"")),1,0)
B75: 46291 | C75: Riverton Rotary | D75: 400 | E75: Check | F75: Winter coat drive | J75: =IF(AND(C75="",D75="",G75=""),"",IF(NOT(ISNUMBER(B75)),"Needs a date",IF(AND(D75<>"",NOT(ISNUMBER(D75))),"Amount not a number",IF(N(D75)<0,"Amount below zero",IF(AND(N(D75)=0,G75=""),"Needs an amount or goods",IF(C75="","",IF(COUNTIF(Donors!$B$6:$B$305,C75)=0,"Not on Donors",""))))))) | K75: =IF(ISNUMBER(B75),YEAR(B75),"") | L75: =IF(ISNUMBER(B75),YEAR(B75)*100+MONTH(B75),"") | M75: =IF(ISNUMBER(B75),INT(B75),0) | N75: =IF(OR(C75="",F75="",Q75=0),0,IF(COUNTIFS(C$6:C75,C75,F$6:F75,F75,Q$6:Q75,1)=1,1,0)) | O75: =IF(OR(C75="",Q75=0,H75<>""),"",M75*10000+ROW()) | P75: =IF(OR(C75="",Q75=0),"",IF(AND(C75=Statement!$C$4,K75=Statement!$C$5),M75*10000+ROW(),"")) | Q75: =IF(AND(ISNUMBER(B75),OR(N(D75)>0,G75<>"")),1,0)
B76: 46292 | C76: Lena Brooks | D76: 30 | E76: Online | F76: Winter coat drive | I76: First gift | J76: =IF(AND(C76="",D76="",G76=""),"",IF(NOT(ISNUMBER(B76)),"Needs a date",IF(AND(D76<>"",NOT(ISNUMBER(D76))),"Amount not a number",IF(N(D76)<0,"Amount below zero",IF(AND(N(D76)=0,G76=""),"Needs an amount or goods",IF(C76="","",IF(COUNTIF(Donors!$B$6:$B$305,C76)=0,"Not on Donors",""))))))) | K76: =IF(ISNUMBER(B76),YEAR(B76),"") | L76: =IF(ISNUMBER(B76),YEAR(B76)*100+MONTH(B76),"") | M76: =IF(ISNUMBER(B76),INT(B76),0) | N76: =IF(OR(C76="",F76="",Q76=0),0,IF(COUNTIFS(C$6:C76,C76,F$6:F76,F76,Q$6:Q76,1)=1,1,0)) | O76: =IF(OR(C76="",Q76=0,H76<>""),"",M76*10000+ROW()) | P76: =IF(OR(C76="",Q76=0),"",IF(AND(C76=Statement!$C$4,K76=Statement!$C$5),M76*10000+ROW(),"")) | Q76: =IF(AND(ISNUMBER(B76),OR(N(D76)>0,G76<>"")),1,0)
J77: =IF(AND(C77="",D77="",G77=""),"",IF(NOT(ISNUMBER(B77)),"Needs a date",IF(AND(D77<>"",NOT(ISNUMBER(D77))),"Amount not a number",IF(N(D77)<0,"Amount below zero",IF(AND(N(D77)=0,G77=""),"Needs an amount or goods",IF(C77="","",IF(COUNTIF(Donors!$B$6:$B$305,C77)=0,"Not on Donors",""))))))) | K77: =IF(ISNUMBER(B77),YEAR(B77),"") | L77: =IF(ISNUMBER(B77),YEAR(B77)*100+MONTH(B77),"") | M77: =IF(ISNUMBER(B77),INT(B77),0) | N77: =IF(OR(C77="",F77="",Q77=0),0,IF(COUNTIFS(C$6:C77,C77,F$6:F77,F77,Q$6:Q77,1)=1,1,0)) | O77: =IF(OR(C77="",Q77=0,H77<>""),"",M77*10000+ROW()) | P77: =IF(OR(C77="",Q77=0),"",IF(AND(C77=Statement!$C$4,K77=Statement!$C$5),M77*10000+ROW(),"")) | Q77: =IF(AND(ISNUMBER(B77),OR(N(D77)>0,G77<>"")),1,0)
J78: =IF(AND(C78="",D78="",G78=""),"",IF(NOT(ISNUMBER(B78)),"Needs a date",IF(AND(D78<>"",NOT(ISNUMBER(D78))),"Amount not a number",IF(N(D78)<0,"Amount below zero",IF(AND(N(D78)=0,G78=""),"Needs an amount or goods",IF(C78="","",IF(COUNTIF(Donors!$B$6:$B$305,C78)=0,"Not on Donors",""))))))) | K78: =IF(ISNUMBER(B78),YEAR(B78),"") | L78: =IF(ISNUMBER(B78),YEAR(B78)*100+MONTH(B78),"") | M78: =IF(ISNUMBER(B78),INT(B78),0) | N78: =IF(OR(C78="",F78="",Q78=0),0,IF(COUNTIFS(C$6:C78,C78,F$6:F78,F78,Q$6:Q78,1)=1,1,0)) | O78: =IF(OR(C78="",Q78=0,H78<>""),"",M78*10000+ROW()) | P78: =IF(OR(C78="",Q78=0),"",IF(AND(C78=Statement!$C$4,K78=Statement!$C$5),M78*10000+ROW(),"")) | Q78: =IF(AND(ISNUMBER(B78),OR(N(D78)>0,G78<>"")),1,0)
J79: =IF(AND(C79="",D79="",G79=""),"",IF(NOT(ISNUMBER(B79)),"Needs a date",IF(AND(D79<>"",NOT(ISNUMBER(D79))),"Amount not a number",IF(N(D79)<0,"Amount below zero",IF(AND(N(D79)=0,G79=""),"Needs an amount or goods",IF(C79="","",IF(COUNTIF(Donors!$B$6:$B$305,C79)=0,"Not on Donors",""))))))) | K79: =IF(ISNUMBER(B79),YEAR(B79),"") | L79: =IF(ISNUMBER(B79),YEAR(B79)*100+MONTH(B79),"") | M79: =IF(ISNUMBER(B79),INT(B79),0) | N79: =IF(OR(C79="",F79="",Q79=0),0,IF(COUNTIFS(C$6:C79,C79,F$6:F79,F79,Q$6:Q79,1)=1,1,0)) | O79: =IF(OR(C79="",Q79=0,H79<>""),"",M79*10000+ROW()) | P79: =IF(OR(C79="",Q79=0),"",IF(AND(C79=Statement!$C$4,K79=Statement!$C$5),M79*10000+ROW(),"")) | Q79: =IF(AND(ISNUMBER(B79),OR(N(D79)>0,G79<>"")),1,0)
J80: =IF(AND(C80="",D80="",G80=""),"",IF(NOT(ISNUMBER(B80)),"Needs a date",IF(AND(D80<>"",NOT(ISNUMBER(D80))),"Amount not a number",IF(N(D80)<0,"Amount below zero",IF(AND(N(D80)=0,G80=""),"Needs an amount or goods",IF(C80="","",IF(COUNTIF(Donors!$B$6:$B$305,C80)=0,"Not on Donors",""))))))) | K80: =IF(ISNUMBER(B80),YEAR(B80),"") | L80: =IF(ISNUMBER(B80),YEAR(B80)*100+MONTH(B80),"") | M80: =IF(ISNUMBER(B80),INT(B80),0) | N80: =IF(OR(C80="",F80="",Q80=0),0,IF(COUNTIFS(C$6:C80,C80,F$6:F80,F80,Q$6:Q80,1)=1,1,0)) | O80: =IF(OR(C80="",Q80=0,H80<>""),"",M80*10000+ROW()) | P80: =IF(OR(C80="",Q80=0),"",IF(AND(C80=Statement!$C$4,K80=Statement!$C$5),M80*10000+ROW(),"")) | Q80: =IF(AND(ISNUMBER(B80),OR(N(D80)>0,G80<>"")),1,0)
J81: =IF(AND(C81="",D81="",G81=""),"",IF(NOT(ISNUMBER(B81)),"Needs a date",IF(AND(D81<>"",NOT(ISNUMBER(D81))),"Amount not a number",IF(N(D81)<0,"Amount below zero",IF(AND(N(D81)=0,G81=""),"Needs an amount or goods",IF(C81="","",IF(COUNTIF(Donors!$B$6:$B$305,C81)=0,"Not on Donors",""))))))) | K81: =IF(ISNUMBER(B81),YEAR(B81),"") | L81: =IF(ISNUMBER(B81),YEAR(B81)*100+MONTH(B81),"") | M81: =IF(ISNUMBER(B81),INT(B81),0) | N81: =IF(OR(C81="",F81="",Q81=0),0,IF(COUNTIFS(C$6:C81,C81,F$6:F81,F81,Q$6:Q81,1)=1,1,0)) | O81: =IF(OR(C81="",Q81=0,H81<>""),"",M81*10000+ROW()) | P81: =IF(OR(C81="",Q81=0),"",IF(AND(C81=Statement!$C$4,K81=Statement!$C$5),M81*10000+ROW(),"")) | Q81: =IF(AND(ISNUMBER(B81),OR(N(D81)>0,G81<>"")),1,0)
J82: =IF(AND(C82="",D82="",G82=""),"",IF(NOT(ISNUMBER(B82)),"Needs a date",IF(AND(D82<>"",NOT(ISNUMBER(D82))),"Amount not a number",IF(N(D82)<0,"Amount below zero",IF(AND(N(D82)=0,G82=""),"Needs an amount or goods",IF(C82="","",IF(COUNTIF(Donors!$B$6:$B$305,C82)=0,"Not on Donors",""))))))) | K82: =IF(ISNUMBER(B82),YEAR(B82),"") | L82: =IF(ISNUMBER(B82),YEAR(B82)*100+MONTH(B82),"") | M82: =IF(ISNUMBER(B82),INT(B82),0) | N82: =IF(OR(C82="",F82="",Q82=0),0,IF(COUNTIFS(C$6:C82,C82,F$6:F82,F82,Q$6:Q82,1)=1,1,0)) | O82: =IF(OR(C82="",Q82=0,H82<>""),"",M82*10000+ROW()) | P82: =IF(OR(C82="",Q82=0),"",IF(AND(C82=Statement!$C$4,K82=Statement!$C$5),M82*10000+ROW(),"")) | Q82: =IF(AND(ISNUMBER(B82),OR(N(D82)>0,G82<>"")),1,0)
J83: =IF(AND(C83="",D83="",G83=""),"",IF(NOT(ISNUMBER(B83)),"Needs a date",IF(AND(D83<>"",NOT(ISNUMBER(D83))),"Amount not a number",IF(N(D83)<0,"Amount below zero",IF(AND(N(D83)=0,G83=""),"Needs an amount or goods",IF(C83="","",IF(COUNTIF(Donors!$B$6:$B$305,C83)=0,"Not on Donors",""))))))) | K83: =IF(ISNUMBER(B83),YEAR(B83),"") | L83: =IF(ISNUMBER(B83),YEAR(B83)*100+MONTH(B83),"") | M83: =IF(ISNUMBER(B83),INT(B83),0) | N83: =IF(OR(C83="",F83="",Q83=0),0,IF(COUNTIFS(C$6:C83,C83,F$6:F83,F83,Q$6:Q83,1)=1,1,0)) | O83: =IF(OR(C83="",Q83=0,H83<>""),"",M83*10000+ROW()) | P83: =IF(OR(C83="",Q83=0),"",IF(AND(C83=Statement!$C$4,K83=Statement!$C$5),M83*10000+ROW(),"")) | Q83: =IF(AND(ISNUMBER(B83),OR(N(D83)>0,G83<>"")),1,0)
J84: =IF(AND(C84="",D84="",G84=""),"",IF(NOT(ISNUMBER(B84)),"Needs a date",IF(AND(D84<>"",NOT(ISNUMBER(D84))),"Amount not a number",IF(N(D84)<0,"Amount below zero",IF(AND(N(D84)=0,G84=""),"Needs an amount or goods",IF(C84="","",IF(COUNTIF(Donors!$B$6:$B$305,C84)=0,"Not on Donors",""))))))) | K84: =IF(ISNUMBER(B84),YEAR(B84),"") | L84: =IF(ISNUMBER(B84),YEAR(B84)*100+MONTH(B84),"") | M84: =IF(ISNUMBER(B84),INT(B84),0) | N84: =IF(OR(C84="",F84="",Q84=0),0,IF(COUNTIFS(C$6:C84,C84,F$6:F84,F84,Q$6:Q84,1)=1,1,0)) | O84: =IF(OR(C84="",Q84=0,H84<>""),"",M84*10000+ROW()) | P84: =IF(OR(C84="",Q84=0),"",IF(AND(C84=Statement!$C$4,K84=Statement!$C$5),M84*10000+ROW(),"")) | Q84: =IF(AND(ISNUMBER(B84),OR(N(D84)>0,G84<>"")),1,0)
J85: =IF(AND(C85="",D85="",G85=""),"",IF(NOT(ISNUMBER(B85)),"Needs a date",IF(AND(D85<>"",NOT(ISNUMBER(D85))),"Amount not a number",IF(N(D85)<0,"Amount below zero",IF(AND(N(D85)=0,G85=""),"Needs an amount or goods",IF(C85="","",IF(COUNTIF(Donors!$B$6:$B$305,C85)=0,"Not on Donors",""))))))) | K85: =IF(ISNUMBER(B85),YEAR(B85),"") | L85: =IF(ISNUMBER(B85),YEAR(B85)*100+MONTH(B85),"") | M85: =IF(ISNUMBER(B85),INT(B85),0) | N85: =IF(OR(C85="",F85="",Q85=0),0,IF(COUNTIFS(C$6:C85,C85,F$6:F85,F85,Q$6:Q85,1)=1,1,0)) | O85: =IF(OR(C85="",Q85=0,H85<>""),"",M85*10000+ROW()) | P85: =IF(OR(C85="",Q85=0),"",IF(AND(C85=Statement!$C$4,K85=Statement!$C$5),M85*10000+ROW(),"")) | Q85: =IF(AND(ISNUMBER(B85),OR(N(D85)>0,G85<>"")),1,0)
J86: =IF(AND(C86="",D86="",G86=""),"",IF(NOT(ISNUMBER(B86)),"Needs a date",IF(AND(D86<>"",NOT(ISNUMBER(D86))),"Amount not a number",IF(N(D86)<0,"Amount below zero",IF(AND(N(D86)=0,G86=""),"Needs an amount or goods",IF(C86="","",IF(COUNTIF(Donors!$B$6:$B$305,C86)=0,"Not on Donors",""))))))) | K86: =IF(ISNUMBER(B86),YEAR(B86),"") | L86: =IF(ISNUMBER(B86),YEAR(B86)*100+MONTH(B86),"") | M86: =IF(ISNUMBER(B86),INT(B86),0) | N86: =IF(OR(C86="",F86="",Q86=0),0,IF(COUNTIFS(C$6:C86,C86,F$6:F86,F86,Q$6:Q86,1)=1,1,0)) | O86: =IF(OR(C86="",Q86=0,H86<>""),"",M86*10000+ROW()) | P86: =IF(OR(C86="",Q86=0),"",IF(AND(C86=Statement!$C$4,K86=Statement!$C$5),M86*10000+ROW(),"")) | Q86: =IF(AND(ISNUMBER(B86),OR(N(D86)>0,G86<>"")),1,0)
J87: =IF(AND(C87="",D87="",G87=""),"",IF(NOT(ISNUMBER(B87)),"Needs a date",IF(AND(D87<>"",NOT(ISNUMBER(D87))),"Amount not a number",IF(N(D87)<0,"Amount below zero",IF(AND(N(D87)=0,G87=""),"Needs an amount or goods",IF(C87="","",IF(COUNTIF(Donors!$B$6:$B$305,C87)=0,"Not on Donors",""))))))) | K87: =IF(ISNUMBER(B87),YEAR(B87),"") | L87: =IF(ISNUMBER(B87),YEAR(B87)*100+MONTH(B87),"") | M87: =IF(ISNUMBER(B87),INT(B87),0) | N87: =IF(OR(C87="",F87="",Q87=0),0,IF(COUNTIFS(C$6:C87,C87,F$6:F87,F87,Q$6:Q87,1)=1,1,0)) | O87: =IF(OR(C87="",Q87=0,H87<>""),"",M87*10000+ROW()) | P87: =IF(OR(C87="",Q87=0),"",IF(AND(C87=Statement!$C$4,K87=Statement!$C$5),M87*10000+ROW(),"")) | Q87: =IF(AND(ISNUMBER(B87),OR(N(D87)>0,G87<>"")),1,0)
J88: =IF(AND(C88="",D88="",G88=""),"",IF(NOT(ISNUMBER(B88)),"Needs a date",IF(AND(D88<>"",NOT(ISNUMBER(D88))),"Amount not a number",IF(N(D88)<0,"Amount below zero",IF(AND(N(D88)=0,G88=""),"Needs an amount or goods",IF(C88="","",IF(COUNTIF(Donors!$B$6:$B$305,C88)=0,"Not on Donors",""))))))) | K88: =IF(ISNUMBER(B88),YEAR(B88),"") | L88: =IF(ISNUMBER(B88),YEAR(B88)*100+MONTH(B88),"") | M88: =IF(ISNUMBER(B88),INT(B88),0) | N88: =IF(OR(C88="",F88="",Q88=0),0,IF(COUNTIFS(C$6:C88,C88,F$6:F88,F88,Q$6:Q88,1)=1,1,0)) | O88: =IF(OR(C88="",Q88=0,H88<>""),"",M88*10000+ROW()) | P88: =IF(OR(C88="",Q88=0),"",IF(AND(C88=Statement!$C$4,K88=Statement!$C$5),M88*10000+ROW(),"")) | Q88: =IF(AND(ISNUMBER(B88),OR(N(D88)>0,G88<>"")),1,0)
... J1005: =IF(AND(C1005="",D1005="",G1005=""),"",IF(NOT(ISNUMBER(B1005)),"Needs a date",IF(AND(D1005<>"",NOT(ISNUMBER(D1005))),"Amount not a number",IF(N(D1005)<0,"Amount below zero",IF(AND(N(D1005)=0,G1005=""),"Needs an amount or goods",IF(C1005="","",IF(COUNTIF(Donors!$B$6:$B$305,C1005)=0,"Not on Donors",""))))))) | K1005: =IF(ISNUMBER(B1005),YEAR(B1005),"") | L1005: =IF(ISNUMBER(B1005),YEAR(B1005)*100+MONTH(B1005),"") | M1005: =IF(ISNUMBER(B1005),INT(B1005),0) | N1005: =IF(OR(C1005="",F1005="",Q1005=0),0,IF(COUNTIFS(C$6:C1005,C1005,F$6:F1005,F1005,Q$6:Q1005,1)=1,1,0)) | O1005: =IF(OR(C1005="",Q1005=0,H1005<>""),"",M1005*10000+ROW()) | P1005: =IF(OR(C1005="",Q1005=0),"",IF(AND(C1005=Statement!$C$4,K1005=Statement!$C$5),M1005*10000+ROW(),"")) | Q1005: =IF(AND(ISNUMBER(B1005),OR(N(D1005)>0,G1005<>"")),1,0)

Sheet Donors
B2: Donors
B3: Each donor once. Their gifts add up from the Gifts tab.
B5: Donor | C5: Type | D5: Email | E5: Address | F5: First gift | G5: Last gift | H5: This year | I5: All time | J5: Gifts | K5: Status
B6: Grace Holloway | C6: Person | D6: grace@mail.example | E6: 12 Birch Road, Riverton | F6: =IF(OR(B6="",N(J6)=0),"",SUMPRODUCT(MIN((Gifts!$C$6:$C$1005=B6)*Gifts!$Q$6:$Q$1005*Gifts!$M$6:$M$1005+(1-(Gifts!$C$6:$C$1005=B6)*Gifts!$Q$6:$Q$1005)*1E9))) | G6: =IF(OR(B6="",N(J6)=0),"",SUMPRODUCT(MAX((Gifts!$C$6:$C$1005=B6)*Gifts!$Q$6:$Q$1005*Gifts!$M$6:$M$1005))) | H6: =IF(B6="","",SUMIFS(Gifts!$D$6:$D$1005,Gifts!$C$6:$C$1005,B6,Gifts!$K$6:$K$1005,Settings!$C$7,Gifts!$D$6:$D$1005,">0")) | I6: =IF(B6="","",SUMIFS(Gifts!$D$6:$D$1005,Gifts!$C$6:$C$1005,B6,Gifts!$D$6:$D$1005,">0",Gifts!$M$6:$M$1005,">0")) | J6: =IF(B6="","",SUMIFS(Gifts!$Q$6:$Q$1005,Gifts!$C$6:$C$1005,B6)) | K6: =IF(B6="","",IF(N(J6)=0,"No gifts yet",IF(AND(N(Settings!$C$9)>0,G6<EDATE(TODAY(),-N(Settings!$C$9))),"Lapsed",IF(YEAR(F6)=N(Settings!$C$7),"New","Active")))) | M6: =IF(OR(B6="",N(H6)<=0),"",ROUND(H6*100,0)*1000+1000-ROW()) | N6: =IF(B6="","",SUMIFS(Gifts!$Q$6:$Q$1005,Gifts!$C$6:$C$1005,B6,Gifts!$K$6:$K$1005,Settings!$C$7))
B7: Daniel Mercer | C7: Person | D7: dan.mercer@mail.example | E7: 4 Quay Street, Riverton | F7: =IF(OR(B7="",N(J7)=0),"",SUMPRODUCT(MIN((Gifts!$C$6:$C$1005=B7)*Gifts!$Q$6:$Q$1005*Gifts!$M$6:$M$1005+(1-(Gifts!$C$6:$C$1005=B7)*Gifts!$Q$6:$Q$1005)*1E9))) | G7: =IF(OR(B7="",N(J7)=0),"",SUMPRODUCT(MAX((Gifts!$C$6:$C$1005=B7)*Gifts!$Q$6:$Q$1005*Gifts!$M$6:$M$1005))) | H7: =IF(B7="","",SUMIFS(Gifts!$D$6:$D$1005,Gifts!$C$6:$C$1005,B7,Gifts!$K$6:$K$1005,Settings!$C$7,Gifts!$D$6:$D$1005,">0")) | I7: =IF(B7="","",SUMIFS(Gifts!$D$6:$D$1005,Gifts!$C$6:$C$1005,B7,Gifts!$D$6:$D$1005,">0",Gifts!$M$6:$M$1005,">0")) | J7: =IF(B7="","",SUMIFS(Gifts!$Q$6:$Q$1005,Gifts!$C$6:$C$1005,B7)) | K7: =IF(B7="","",IF(N(J7)=0,"No gifts yet",IF(AND(N(Settings!$C$9)>0,G7<EDATE(TODAY(),-N(Settings!$C$9))),"Lapsed",IF(YEAR(F7)=N(Settings!$C$7),"New","Active")))) | M7: =IF(OR(B7="",N(H7)<=0),"",ROUND(H7*100,0)*1000+1000-ROW()) | N7: =IF(B7="","",SUMIFS(Gifts!$Q$6:$Q$1005,Gifts!$C$6:$C$1005,B7,Gifts!$K$6:$K$1005,Settings!$C$7))
B8: Riverton Hardware | C8: Business | D8: shop@rivertonhardware.example | E8: 88 High Street, Riverton | F8: =IF(OR(B8="",N(J8)=0),"",SUMPRODUCT(MIN((Gifts!$C$6:$C$1005=B8)*Gifts!$Q$6:$Q$1005*Gifts!$M$6:$M$1005+(1-(Gifts!$C$6:$C$1005=B8)*Gifts!$Q$6:$Q$1005)*1E9))) | G8: =IF(OR(B8="",N(J8)=0),"",SUMPRODUCT(MAX((Gifts!$C$6:$C$1005=B8)*Gifts!$Q$6:$Q$1005*Gifts!$M$6:$M$1005))) | H8: =IF(B8="","",SUMIFS(Gifts!$D$6:$D$1005,Gifts!$C$6:$C$1005,B8,Gifts!$K$6:$K$1005,Settings!$C$7,Gifts!$D$6:$D$1005,">0")) | I8: =IF(B8="","",SUMIFS(Gifts!$D$6:$D$1005,Gifts!$C$6:$C$1005,B8,Gifts!$D$6:$D$1005,">0",Gifts!$M$6:$M$1005,">0")) | J8: =IF(B8="","",SUMIFS(Gifts!$Q$6:$Q$1005,Gifts!$C$6:$C$1005,B8)) | K8: =IF(B8="","",IF(N(J8)=0,"No gifts yet",IF(AND(N(Settings!$C$9)>0,G8<EDATE(TODAY(),-N(Settings!$C$9))),"Lapsed",IF(YEAR(F8)=N(Settings!$C$7),"New","Active")))) | M8: =IF(OR(B8="",N(H8)<=0),"",ROUND(H8*100,0)*1000+1000-ROW()) | N8: =IF(B8="","",SUMIFS(Gifts!$Q$6:$Q$1005,Gifts!$C$6:$C$1005,B8,Gifts!$K$6:$K$1005,Settings!$C$7))
B9: Amina Yusuf | C9: Person | D9: amina.y@mail.example | E9: 31 Elm Close, Riverton | F9: =IF(OR(B9="",N(J9)=0),"",SUMPRODUCT(MIN((Gifts!$C$6:$C$1005=B9)*Gifts!$Q$6:$Q$1005*Gifts!$M$6:$M$1005+(1-(Gifts!$C$6:$C$1005=B9)*Gifts!$Q$6:$Q$1005)*1E9))) | G9: =IF(OR(B9="",N(J9)=0),"",SUMPRODUCT(MAX((Gifts!$C$6:$C$1005=B9)*Gifts!$Q$6:$Q$1005*Gifts!$M$6:$M$1005))) | H9: =IF(B9="","",SUMIFS(Gifts!$D$6:$D$1005,Gifts!$C$6:$C$1005,B9,Gifts!$K$6:$K$1005,Settings!$C$7,Gifts!$D$6:$D$1005,">0")) | I9: =IF(B9="","",SUMIFS(Gifts!$D$6:$D$1005,Gifts!$C$6:$C$1005,B9,Gifts!$D$6:$D$1005,">0",Gifts!$M$6:$M$1005,">0")) | J9: =IF(B9="","",SUMIFS(Gifts!$Q$6:$Q$1005,Gifts!$C$6:$C$1005,B9)) | K9: =IF(B9="","",IF(N(J9)=0,"No gifts yet",IF(AND(N(Settings!$C$9)>0,G9<EDATE(TODAY(),-N(Settings!$C$9))),"Lapsed",IF(YEAR(F9)=N(Settings!$C$7),"New","Active")))) | M9: =IF(OR(B9="",N(H9)<=0),"",ROUND(H9*100,0)*1000+1000-ROW()) | N9: =IF(B9="","",SUMIFS(Gifts!$Q$6:$Q$1005,Gifts!$C$6:$C$1005,B9,Gifts!$K$6:$K$1005,Settings!$C$7))
B10: St Luke's Youth Group | C10: Group | E10: Church Lane, Riverton | F10: =IF(OR(B10="",N(J10)=0),"",SUMPRODUCT(MIN((Gifts!$C$6:$C$1005=B10)*Gifts!$Q$6:$Q$1005*Gifts!$M$6:$M$1005+(1-(Gifts!$C$6:$C$1005=B10)*Gifts!$Q$6:$Q$1005)*1E9))) | G10: =IF(OR(B10="",N(J10)=0),"",SUMPRODUCT(MAX((Gifts!$C$6:$C$1005=B10)*Gifts!$Q$6:$Q$1005*Gifts!$M$6:$M$1005))) | H10: =IF(B10="","",SUMIFS(Gifts!$D$6:$D$1005,Gifts!$C$6:$C$1005,B10,Gifts!$K$6:$K$1005,Settings!$C$7,Gifts!$D$6:$D$1005,">0")) | I10: =IF(B10="","",SUMIFS(Gifts!$D$6:$D$1005,Gifts!$C$6:$C$1005,B10,Gifts!$D$6:$D$1005,">0",Gifts!$M$6:$M$1005,">0")) | J10: =IF(B10="","",SUMIFS(Gifts!$Q$6:$Q$1005,Gifts!$C$6:$C$1005,B10)) | K10: =IF(B10="","",IF(N(J10)=0,"No gifts yet",IF(AND(N(Settings!$C$9)>0,G10<EDATE(TODAY(),-N(Settings!$C$9))),"Lapsed",IF(YEAR(F10)=N(Settings!$C$7),"New","Active")))) | M10: =IF(OR(B10="",N(H10)<=0),"",ROUND(H10*100,0)*1000+1000-ROW()) | N10: =IF(B10="","",SUMIFS(Gifts!$Q$6:$Q$1005,Gifts!$C$6:$C$1005,B10,Gifts!$K$6:$K$1005,Settings!$C$7))
B11: Tom and Jess Carter | C11: Person | D11: carters@mail.example | E11: 7 Mill Yard, Riverton | F11: =IF(OR(B11="",N(J11)=0),"",SUMPRODUCT(MIN((Gifts!$C$6:$C$1005=B11)*Gifts!$Q$6:$Q$1005*Gifts!$M$6:$M$1005+(1-(Gifts!$C$6:$C$1005=B11)*Gifts!$Q$6:$Q$1005)*1E9))) | G11: =IF(OR(B11="",N(J11)=0),"",SUMPRODUCT(MAX((Gifts!$C$6:$C$1005=B11)*Gifts!$Q$6:$Q$1005*Gifts!$M$6:$M$1005))) | H11: =IF(B11="","",SUMIFS(Gifts!$D$6:$D$1005,Gifts!$C$6:$C$1005,B11,Gifts!$K$6:$K$1005,Settings!$C$7,Gifts!$D$6:$D$1005,">0")) | I11: =IF(B11="","",SUMIFS(Gifts!$D$6:$D$1005,Gifts!$C$6:$C$1005,B11,Gifts!$D$6:$D$1005,">0",Gifts!$M$6:$M$1005,">0")) | J11: =IF(B11="","",SUMIFS(Gifts!$Q$6:$Q$1005,Gifts!$C$6:$C$1005,B11)) | K11: =IF(B11="","",IF(N(J11)=0,"No gifts yet",IF(AND(N(Settings!$C$9)>0,G11<EDATE(TODAY(),-N(Settings!$C$9))),"Lapsed",IF(YEAR(F11)=N(Settings!$C$7),"New","Active")))) | M11: =IF(OR(B11="",N(H11)<=0),"",ROUND(H11*100,0)*1000+1000-ROW()) | N11: =IF(B11="","",SUMIFS(Gifts!$Q$6:$Q$1005,Gifts!$C$6:$C$1005,B11,Gifts!$K$6:$K$1005,Settings!$C$7))
B12: Corner Bakery | C12: Business | D12: hello@cornerbakery.example | E12: 2 Market Square, Riverton | F12: =IF(OR(B12="",N(J12)=0),"",SUMPRODUCT(MIN((Gifts!$C$6:$C$1005=B12)*Gifts!$Q$6:$Q$1005*Gifts!$M$6:$M$1005+(1-(Gifts!$C$6:$C$1005=B12)*Gifts!$Q$6:$Q$1005)*1E9))) | G12: =IF(OR(B12="",N(J12)=0),"",SUMPRODUCT(MAX((Gifts!$C$6:$C$1005=B12)*Gifts!$Q$6:$Q$1005*Gifts!$M$6:$M$1005))) | H12: =IF(B12="","",SUMIFS(Gifts!$D$6:$D$1005,Gifts!$C$6:$C$1005,B12,Gifts!$K$6:$K$1005,Settings!$C$7,Gifts!$D$6:$D$1005,">0")) | I12: =IF(B12="","",SUMIFS(Gifts!$D$6:$D$1005,Gifts!$C$6:$C$1005,B12,Gifts!$D$6:$D$1005,">0",Gifts!$M$6:$M$1005,">0")) | J12: =IF(B12="","",SUMIFS(Gifts!$Q$6:$Q$1005,Gifts!$C$6:$C$1005,B12)) | K12: =IF(B12="","",IF(N(J12)=0,"No gifts yet",IF(AND(N(Settings!$C$9)>0,G12<EDATE(TODAY(),-N(Settings!$C$9))),"Lapsed",IF(YEAR(F12)=N(Settings!$C$7),"New","Active")))) | M12: =IF(OR(B12="",N(H12)<=0),"",ROUND(H12*100,0)*1000+1000-ROW()) | N12: =IF(B12="","",SUMIFS(Gifts!$Q$6:$Q$1005,Gifts!$C$6:$C$1005,B12,Gifts!$K$6:$K$1005,Settings!$C$7))
B13: Helen Price | C13: Person | E13: 19 Orchard Way, Riverton | F13: =IF(OR(B13="",N(J13)=0),"",SUMPRODUCT(MIN((Gifts!$C$6:$C$1005=B13)*Gifts!$Q$6:$Q$1005*Gifts!$M$6:$M$1005+(1-(Gifts!$C$6:$C$1005=B13)*Gifts!$Q$6:$Q$1005)*1E9))) | G13: =IF(OR(B13="",N(J13)=0),"",SUMPRODUCT(MAX((Gifts!$C$6:$C$1005=B13)*Gifts!$Q$6:$Q$1005*Gifts!$M$6:$M$1005))) | H13: =IF(B13="","",SUMIFS(Gifts!$D$6:$D$1005,Gifts!$C$6:$C$1005,B13,Gifts!$K$6:$K$1005,Settings!$C$7,Gifts!$D$6:$D$1005,">0")) | I13: =IF(B13="","",SUMIFS(Gifts!$D$6:$D$1005,Gifts!$C$6:$C$1005,B13,Gifts!$D$6:$D$1005,">0",Gifts!$M$6:$M$1005,">0")) | J13: =IF(B13="","",SUMIFS(Gifts!$Q$6:$Q$1005,Gifts!$C$6:$C$1005,B13)) | K13: =IF(B13="","",IF(N(J13)=0,"No gifts yet",IF(AND(N(Settings!$C$9)>0,G13<EDATE(TODAY(),-N(Settings!$C$9))),"Lapsed",IF(YEAR(F13)=N(Settings!$C$7),"New","Active")))) | M13: =IF(OR(B13="",N(H13)<=0),"",ROUND(H13*100,0)*1000+1000-ROW()) | N13: =IF(B13="","",SUMIFS(Gifts!$Q$6:$Q$1005,Gifts!$C$6:$C$1005,B13,Gifts!$K$6:$K$1005,Settings!$C$7))
B14: Ravi Patel | C14: Person | D14: ravi.patel@mail.example | E14: 5 Station Road, Riverton | F14: =IF(OR(B14="",N(J14)=0),"",SUMPRODUCT(MIN((Gifts!$C$6:$C$1005=B14)*Gifts!$Q$6:$Q$1005*Gifts!$M$6:$M$1005+(1-(Gifts!$C$6:$C$1005=B14)*Gifts!$Q$6:$Q$1005)*1E9))) | G14: =IF(OR(B14="",N(J14)=0),"",SUMPRODUCT(MAX((Gifts!$C$6:$C$1005=B14)*Gifts!$Q$6:$Q$1005*Gifts!$M$6:$M$1005))) | H14: =IF(B14="","",SUMIFS(Gifts!$D$6:$D$1005,Gifts!$C$6:$C$1005,B14,Gifts!$K$6:$K$1005,Settings!$C$7,Gifts!$D$6:$D$1005,">0")) | I14: =IF(B14="","",SUMIFS(Gifts!$D$6:$D$1005,Gifts!$C$6:$C$1005,B14,Gifts!$D$6:$D$1005,">0",Gifts!$M$6:$M$1005,">0")) | J14: =IF(B14="","",SUMIFS(Gifts!$Q$6:$Q$1005,Gifts!$C$6:$C$1005,B14)) | K14: =IF(B14="","",IF(N(J14)=0,"No gifts yet",IF(AND(N(Settings!$C$9)>0,G14<EDATE(TODAY(),-N(Settings!$C$9))),"Lapsed",IF(YEAR(F14)=N(Settings!$C$7),"New","Active")))) | M14: =IF(OR(B14="",N(H14)<=0),"",ROUND(H14*100,0)*1000+1000-ROW()) | N14: =IF(B14="","",SUMIFS(Gifts!$Q$6:$Q$1005,Gifts!$C$6:$C$1005,B14,Gifts!$K$6:$K$1005,Settings!$C$7))
B15: Riverton Rotary | C15: Group | D15: rotary@mail.example | F15: =IF(OR(B15="",N(J15)=0),"",SUMPRODUCT(MIN((Gifts!$C$6:$C$1005=B15)*Gifts!$Q$6:$Q$1005*Gifts!$M$6:$M$1005+(1-(Gifts!$C$6:$C$1005=B15)*Gifts!$Q$6:$Q$1005)*1E9))) | G15: =IF(OR(B15="",N(J15)=0),"",SUMPRODUCT(MAX((Gifts!$C$6:$C$1005=B15)*Gifts!$Q$6:$Q$1005*Gifts!$M$6:$M$1005))) | H15: =IF(B15="","",SUMIFS(Gifts!$D$6:$D$1005,Gifts!$C$6:$C$1005,B15,Gifts!$K$6:$K$1005,Settings!$C$7,Gifts!$D$6:$D$1005,">0")) | I15: =IF(B15="","",SUMIFS(Gifts!$D$6:$D$1005,Gifts!$C$6:$C$1005,B15,Gifts!$D$6:$D$1005,">0",Gifts!$M$6:$M$1005,">0")) | J15: =IF(B15="","",SUMIFS(Gifts!$Q$6:$Q$1005,Gifts!$C$6:$C$1005,B15)) | K15: =IF(B15="","",IF(N(J15)=0,"No gifts yet",IF(AND(N(Settings!$C$9)>0,G15<EDATE(TODAY(),-N(Settings!$C$9))),"Lapsed",IF(YEAR(F15)=N(Settings!$C$7),"New","Active")))) | M15: =IF(OR(B15="",N(H15)<=0),"",ROUND(H15*100,0)*1000+1000-ROW()) | N15: =IF(B15="","",SUMIFS(Gifts!$Q$6:$Q$1005,Gifts!$C$6:$C$1005,B15,Gifts!$K$6:$K$1005,Settings!$C$7))
B16: Sofia Rossi | C16: Person | D16: sofia.r@mail.example | E16: 40 Hill Street, Riverton | F16: =IF(OR(B16="",N(J16)=0),"",SUMPRODUCT(MIN((Gifts!$C$6:$C$1005=B16)*Gifts!$Q$6:$Q$1005*Gifts!$M$6:$M$1005+(1-(Gifts!$C$6:$C$1005=B16)*Gifts!$Q$6:$Q$1005)*1E9))) | G16: =IF(OR(B16="",N(J16)=0),"",SUMPRODUCT(MAX((Gifts!$C$6:$C$1005=B16)*Gifts!$Q$6:$Q$1005*Gifts!$M$6:$M$1005))) | H16: =IF(B16="","",SUMIFS(Gifts!$D$6:$D$1005,Gifts!$C$6:$C$1005,B16,Gifts!$K$6:$K$1005,Settings!$C$7,Gifts!$D$6:$D$1005,">0")) | I16: =IF(B16="","",SUMIFS(Gifts!$D$6:$D$1005,Gifts!$C$6:$C$1005,B16,Gifts!$D$6:$D$1005,">0",Gifts!$M$6:$M$1005,">0")) | J16: =IF(B16="","",SUMIFS(Gifts!$Q$6:$Q$1005,Gifts!$C$6:$C$1005,B16)) | K16: =IF(B16="","",IF(N(J16)=0,"No gifts yet",IF(AND(N(Settings!$C$9)>0,G16<EDATE(TODAY(),-N(Settings!$C$9))),"Lapsed",IF(YEAR(F16)=N(Settings!$C$7),"New","Active")))) | M16: =IF(OR(B16="",N(H16)<=0),"",ROUND(H16*100,0)*1000+1000-ROW()) | N16: =IF(B16="","",SUMIFS(Gifts!$Q$6:$Q$1005,Gifts!$C$6:$C$1005,B16,Gifts!$K$6:$K$1005,Settings!$C$7))
B17: Old Mill Trust | C17: Foundation | D17: grants@oldmill.example | E17: The Old Mill, Riverton | F17: =IF(OR(B17="",N(J17)=0),"",SUMPRODUCT(MIN((Gifts!$C$6:$C$1005=B17)*Gifts!$Q$6:$Q$1005*Gifts!$M$6:$M$1005+(1-(Gifts!$C$6:$C$1005=B17)*Gifts!$Q$6:$Q$1005)*1E9))) | G17: =IF(OR(B17="",N(J17)=0),"",SUMPRODUCT(MAX((Gifts!$C$6:$C$1005=B17)*Gifts!$Q$6:$Q$1005*Gifts!$M$6:$M$1005))) | H17: =IF(B17="","",SUMIFS(Gifts!$D$6:$D$1005,Gifts!$C$6:$C$1005,B17,Gifts!$K$6:$K$1005,Settings!$C$7,Gifts!$D$6:$D$1005,">0")) | I17: =IF(B17="","",SUMIFS(Gifts!$D$6:$D$1005,Gifts!$C$6:$C$1005,B17,Gifts!$D$6:$D$1005,">0",Gifts!$M$6:$M$1005,">0")) | J17: =IF(B17="","",SUMIFS(Gifts!$Q$6:$Q$1005,Gifts!$C$6:$C$1005,B17)) | K17: =IF(B17="","",IF(N(J17)=0,"No gifts yet",IF(AND(N(Settings!$C$9)>0,G17<EDATE(TODAY(),-N(Settings!$C$9))),"Lapsed",IF(YEAR(F17)=N(Settings!$C$7),"New","Active")))) | M17: =IF(OR(B17="",N(H17)<=0),"",ROUND(H17*100,0)*1000+1000-ROW()) | N17: =IF(B17="","",SUMIFS(Gifts!$Q$6:$Q$1005,Gifts!$C$6:$C$1005,B17,Gifts!$K$6:$K$1005,Settings!$C$7))
F18: =IF(OR(B18="",N(J18)=0),"",SUMPRODUCT(MIN((Gifts!$C$6:$C$1005=B18)*Gifts!$Q$6:$Q$1005*Gifts!$M$6:$M$1005+(1-(Gifts!$C$6:$C$1005=B18)*Gifts!$Q$6:$Q$1005)*1E9))) | G18: =IF(OR(B18="",N(J18)=0),"",SUMPRODUCT(MAX((Gifts!$C$6:$C$1005=B18)*Gifts!$Q$6:$Q$1005*Gifts!$M$6:$M$1005))) | H18: =IF(B18="","",SUMIFS(Gifts!$D$6:$D$1005,Gifts!$C$6:$C$1005,B18,Gifts!$K$6:$K$1005,Settings!$C$7,Gifts!$D$6:$D$1005,">0")) | I18: =IF(B18="","",SUMIFS(Gifts!$D$6:$D$1005,Gifts!$C$6:$C$1005,B18,Gifts!$D$6:$D$1005,">0",Gifts!$M$6:$M$1005,">0")) | J18: =IF(B18="","",SUMIFS(Gifts!$Q$6:$Q$1005,Gifts!$C$6:$C$1005,B18)) | K18: =IF(B18="","",IF(N(J18)=0,"No gifts yet",IF(AND(N(Settings!$C$9)>0,G18<EDATE(TODAY(),-N(Settings!$C$9))),"Lapsed",IF(YEAR(F18)=N(Settings!$C$7),"New","Active")))) | M18: =IF(OR(B18="",N(H18)<=0),"",ROUND(H18*100,0)*1000+1000-ROW()) | N18: =IF(B18="","",SUMIFS(Gifts!$Q$6:$Q$1005,Gifts!$C$6:$C$1005,B18,Gifts!$K$6:$K$1005,Settings!$C$7))
F19: =IF(OR(B19="",N(J19)=0),"",SUMPRODUCT(MIN((Gifts!$C$6:$C$1005=B19)*Gifts!$Q$6:$Q$1005*Gifts!$M$6:$M$1005+(1-(Gifts!$C$6:$C$1005=B19)*Gifts!$Q$6:$Q$1005)*1E9))) | G19: =IF(OR(B19="",N(J19)=0),"",SUMPRODUCT(MAX((Gifts!$C$6:$C$1005=B19)*Gifts!$Q$6:$Q$1005*Gifts!$M$6:$M$1005))) | H19: =IF(B19="","",SUMIFS(Gifts!$D$6:$D$1005,Gifts!$C$6:$C$1005,B19,Gifts!$K$6:$K$1005,Settings!$C$7,Gifts!$D$6:$D$1005,">0")) | I19: =IF(B19="","",SUMIFS(Gifts!$D$6:$D$1005,Gifts!$C$6:$C$1005,B19,Gifts!$D$6:$D$1005,">0",Gifts!$M$6:$M$1005,">0")) | J19: =IF(B19="","",SUMIFS(Gifts!$Q$6:$Q$1005,Gifts!$C$6:$C$1005,B19)) | K19: =IF(B19="","",IF(N(J19)=0,"No gifts yet",IF(AND(N(Settings!$C$9)>0,G19<EDATE(TODAY(),-N(Settings!$C$9))),"Lapsed",IF(YEAR(F19)=N(Settings!$C$7),"New","Active")))) | M19: =IF(OR(B19="",N(H19)<=0),"",ROUND(H19*100,0)*1000+1000-ROW()) | N19: =IF(B19="","",SUMIFS(Gifts!$Q$6:$Q$1005,Gifts!$C$6:$C$1005,B19,Gifts!$K$6:$K$1005,Settings!$C$7))
F20: =IF(OR(B20="",N(J20)=0),"",SUMPRODUCT(MIN((Gifts!$C$6:$C$1005=B20)*Gifts!$Q$6:$Q$1005*Gifts!$M$6:$M$1005+(1-(Gifts!$C$6:$C$1005=B20)*Gifts!$Q$6:$Q$1005)*1E9))) | G20: =IF(OR(B20="",N(J20)=0),"",SUMPRODUCT(MAX((Gifts!$C$6:$C$1005=B20)*Gifts!$Q$6:$Q$1005*Gifts!$M$6:$M$1005))) | H20: =IF(B20="","",SUMIFS(Gifts!$D$6:$D$1005,Gifts!$C$6:$C$1005,B20,Gifts!$K$6:$K$1005,Settings!$C$7,Gifts!$D$6:$D$1005,">0")) | I20: =IF(B20="","",SUMIFS(Gifts!$D$6:$D$1005,Gifts!$C$6:$C$1005,B20,Gifts!$D$6:$D$1005,">0",Gifts!$M$6:$M$1005,">0")) | J20: =IF(B20="","",SUMIFS(Gifts!$Q$6:$Q$1005,Gifts!$C$6:$C$1005,B20)) | K20: =IF(B20="","",IF(N(J20)=0,"No gifts yet",IF(AND(N(Settings!$C$9)>0,G20<EDATE(TODAY(),-N(Settings!$C$9))),"Lapsed",IF(YEAR(F20)=N(Settings!$C$7),"New","Active")))) | M20: =IF(OR(B20="",N(H20)<=0),"",ROUND(H20*100,0)*1000+1000-ROW()) | N20: =IF(B20="","",SUMIFS(Gifts!$Q$6:$Q$1005,Gifts!$C$6:$C$1005,B20,Gifts!$K$6:$K$1005,Settings!$C$7))
F21: =IF(OR(B21="",N(J21)=0),"",SUMPRODUCT(MIN((Gifts!$C$6:$C$1005=B21)*Gifts!$Q$6:$Q$1005*Gifts!$M$6:$M$1005+(1-(Gifts!$C$6:$C$1005=B21)*Gifts!$Q$6:$Q$1005)*1E9))) | G21: =IF(OR(B21="",N(J21)=0),"",SUMPRODUCT(MAX((Gifts!$C$6:$C$1005=B21)*Gifts!$Q$6:$Q$1005*Gifts!$M$6:$M$1005))) | H21: =IF(B21="","",SUMIFS(Gifts!$D$6:$D$1005,Gifts!$C$6:$C$1005,B21,Gifts!$K$6:$K$1005,Settings!$C$7,Gifts!$D$6:$D$1005,">0")) | I21: =IF(B21="","",SUMIFS(Gifts!$D$6:$D$1005,Gifts!$C$6:$C$1005,B21,Gifts!$D$6:$D$1005,">0",Gifts!$M$6:$M$1005,">0")) | J21: =IF(B21="","",SUMIFS(Gifts!$Q$6:$Q$1005,Gifts!$C$6:$C$1005,B21)) | K21: =IF(B21="","",IF(N(J21)=0,"No gifts yet",IF(AND(N(Settings!$C$9)>0,G21<EDATE(TODAY(),-N(Settings!$C$9))),"Lapsed",IF(YEAR(F21)=N(Settings!$C$7),"New","Active")))) | M21: =IF(OR(B21="",N(H21)<=0),"",ROUND(H21*100,0)*1000+1000-ROW()) | N21: =IF(B21="","",SUMIFS(Gifts!$Q$6:$Q$1005,Gifts!$C$6:$C$1005,B21,Gifts!$K$6:$K$1005,Settings!$C$7))
F22: =IF(OR(B22="",N(J22)=0),"",SUMPRODUCT(MIN((Gifts!$C$6:$C$1005=B22)*Gifts!$Q$6:$Q$1005*Gifts!$M$6:$M$1005+(1-(Gifts!$C$6:$C$1005=B22)*Gifts!$Q$6:$Q$1005)*1E9))) | G22: =IF(OR(B22="",N(J22)=0),"",SUMPRODUCT(MAX((Gifts!$C$6:$C$1005=B22)*Gifts!$Q$6:$Q$1005*Gifts!$M$6:$M$1005))) | H22: =IF(B22="","",SUMIFS(Gifts!$D$6:$D$1005,Gifts!$C$6:$C$1005,B22,Gifts!$K$6:$K$1005,Settings!$C$7,Gifts!$D$6:$D$1005,">0")) | I22: =IF(B22="","",SUMIFS(Gifts!$D$6:$D$1005,Gifts!$C$6:$C$1005,B22,Gifts!$D$6:$D$1005,">0",Gifts!$M$6:$M$1005,">0")) | J22: =IF(B22="","",SUMIFS(Gifts!$Q$6:$Q$1005,Gifts!$C$6:$C$1005,B22)) | K22: =IF(B22="","",IF(N(J22)=0,"No gifts yet",IF(AND(N(Settings!$C$9)>0,G22<EDATE(TODAY(),-N(Settings!$C$9))),"Lapsed",IF(YEAR(F22)=N(Settings!$C$7),"New","Active")))) | M22: =IF(OR(B22="",N(H22)<=0),"",ROUND(H22*100,0)*1000+1000-ROW()) | N22: =IF(B22="","",SUMIFS(Gifts!$Q$6:$Q$1005,Gifts!$C$6:$C$1005,B22,Gifts!$K$6:$K$1005,Settings!$C$7))
F23: =IF(OR(B23="",N(J23)=0),"",SUMPRODUCT(MIN((Gifts!$C$6:$C$1005=B23)*Gifts!$Q$6:$Q$1005*Gifts!$M$6:$M$1005+(1-(Gifts!$C$6:$C$1005=B23)*Gifts!$Q$6:$Q$1005)*1E9))) | G23: =IF(OR(B23="",N(J23)=0),"",SUMPRODUCT(MAX((Gifts!$C$6:$C$1005=B23)*Gifts!$Q$6:$Q$1005*Gifts!$M$6:$M$1005))) | H23: =IF(B23="","",SUMIFS(Gifts!$D$6:$D$1005,Gifts!$C$6:$C$1005,B23,Gifts!$K$6:$K$1005,Settings!$C$7,Gifts!$D$6:$D$1005,">0")) | I23: =IF(B23="","",SUMIFS(Gifts!$D$6:$D$1005,Gifts!$C$6:$C$1005,B23,Gifts!$D$6:$D$1005,">0",Gifts!$M$6:$M$1005,">0")) | J23: =IF(B23="","",SUMIFS(Gifts!$Q$6:$Q$1005,Gifts!$C$6:$C$1005,B23)) | K23: =IF(B23="","",IF(N(J23)=0,"No gifts yet",IF(AND(N(Settings!$C$9)>0,G23<EDATE(TODAY(),-N(Settings!$C$9))),"Lapsed",IF(YEAR(F23)=N(Settings!$C$7),"New","Active")))) | M23: =IF(OR(B23="",N(H23)<=0),"",ROUND(H23*100,0)*1000+1000-ROW()) | N23: =IF(B23="","",SUMIFS(Gifts!$Q$6:$Q$1005,Gifts!$C$6:$C$1005,B23,Gifts!$K$6:$K$1005,Settings!$C$7))
F24: =IF(OR(B24="",N(J24)=0),"",SUMPRODUCT(MIN((Gifts!$C$6:$C$1005=B24)*Gifts!$Q$6:$Q$1005*Gifts!$M$6:$M$1005+(1-(Gifts!$C$6:$C$1005=B24)*Gifts!$Q$6:$Q$1005)*1E9))) | G24: =IF(OR(B24="",N(J24)=0),"",SUMPRODUCT(MAX((Gifts!$C$6:$C$1005=B24)*Gifts!$Q$6:$Q$1005*Gifts!$M$6:$M$1005))) | H24: =IF(B24="","",SUMIFS(Gifts!$D$6:$D$1005,Gifts!$C$6:$C$1005,B24,Gifts!$K$6:$K$1005,Settings!$C$7,Gifts!$D$6:$D$1005,">0")) | I24: =IF(B24="","",SUMIFS(Gifts!$D$6:$D$1005,Gifts!$C$6:$C$1005,B24,Gifts!$D$6:$D$1005,">0",Gifts!$M$6:$M$1005,">0")) | J24: =IF(B24="","",SUMIFS(Gifts!$Q$6:$Q$1005,Gifts!$C$6:$C$1005,B24)) | K24: =IF(B24="","",IF(N(J24)=0,"No gifts yet",IF(AND(N(Settings!$C$9)>0,G24<EDATE(TODAY(),-N(Settings!$C$9))),"Lapsed",IF(YEAR(F24)=N(Settings!$C$7),"New","Active")))) | M24: =IF(OR(B24="",N(H24)<=0),"",ROUND(H24*100,0)*1000+1000-ROW()) | N24: =IF(B24="","",SUMIFS(Gifts!$Q$6:$Q$1005,Gifts!$C$6:$C$1005,B24,Gifts!$K$6:$K$1005,Settings!$C$7))
F25: =IF(OR(B25="",N(J25)=0),"",SUMPRODUCT(MIN((Gifts!$C$6:$C$1005=B25)*Gifts!$Q$6:$Q$1005*Gifts!$M$6:$M$1005+(1-(Gifts!$C$6:$C$1005=B25)*Gifts!$Q$6:$Q$1005)*1E9))) | G25: =IF(OR(B25="",N(J25)=0),"",SUMPRODUCT(MAX((Gifts!$C$6:$C$1005=B25)*Gifts!$Q$6:$Q$1005*Gifts!$M$6:$M$1005))) | H25: =IF(B25="","",SUMIFS(Gifts!$D$6:$D$1005,Gifts!$C$6:$C$1005,B25,Gifts!$K$6:$K$1005,Settings!$C$7,Gifts!$D$6:$D$1005,">0")) | I25: =IF(B25="","",SUMIFS(Gifts!$D$6:$D$1005,Gifts!$C$6:$C$1005,B25,Gifts!$D$6:$D$1005,">0",Gifts!$M$6:$M$1005,">0")) | J25: =IF(B25="","",SUMIFS(Gifts!$Q$6:$Q$1005,Gifts!$C$6:$C$1005,B25)) | K25: =IF(B25="","",IF(N(J25)=0,"No gifts yet",IF(AND(N(Settings!$C$9)>0,G25<EDATE(TODAY(),-N(Settings!$C$9))),"Lapsed",IF(YEAR(F25)=N(Settings!$C$7),"New","Active")))) | M25: =IF(OR(B25="",N(H25)<=0),"",ROUND(H25*100,0)*1000+1000-ROW()) | N25: =IF(B25="","",SUMIFS(Gifts!$Q$6:$Q$1005,Gifts!$C$6:$C$1005,B25,Gifts!$K$6:$K$1005,Settings!$C$7))
F26: =IF(OR(B26="",N(J26)=0),"",SUMPRODUCT(MIN((Gifts!$C$6:$C$1005=B26)*Gifts!$Q$6:$Q$1005*Gifts!$M$6:$M$1005+(1-(Gifts!$C$6:$C$1005=B26)*Gifts!$Q$6:$Q$1005)*1E9))) | G26: =IF(OR(B26="",N(J26)=0),"",SUMPRODUCT(MAX((Gifts!$C$6:$C$1005=B26)*Gifts!$Q$6:$Q$1005*Gifts!$M$6:$M$1005))) | H26: =IF(B26="","",SUMIFS(Gifts!$D$6:$D$1005,Gifts!$C$6:$C$1005,B26,Gifts!$K$6:$K$1005,Settings!$C$7,Gifts!$D$6:$D$1005,">0")) | I26: =IF(B26="","",SUMIFS(Gifts!$D$6:$D$1005,Gifts!$C$6:$C$1005,B26,Gifts!$D$6:$D$1005,">0",Gifts!$M$6:$M$1005,">0")) | J26: =IF(B26="","",SUMIFS(Gifts!$Q$6:$Q$1005,Gifts!$C$6:$C$1005,B26)) | K26: =IF(B26="","",IF(N(J26)=0,"No gifts yet",IF(AND(N(Settings!$C$9)>0,G26<EDATE(TODAY(),-N(Settings!$C$9))),"Lapsed",IF(YEAR(F26)=N(Settings!$C$7),"New","Active")))) | M26: =IF(OR(B26="",N(H26)<=0),"",ROUND(H26*100,0)*1000+1000-ROW()) | N26: =IF(B26="","",SUMIFS(Gifts!$Q$6:$Q$1005,Gifts!$C$6:$C$1005,B26,Gifts!$K$6:$K$1005,Settings!$C$7))
F27: =IF(OR(B27="",N(J27)=0),"",SUMPRODUCT(MIN((Gifts!$C$6:$C$1005=B27)*Gifts!$Q$6:$Q$1005*Gifts!$M$6:$M$1005+(1-(Gifts!$C$6:$C$1005=B27)*Gifts!$Q$6:$Q$1005)*1E9))) | G27: =IF(OR(B27="",N(J27)=0),"",SUMPRODUCT(MAX((Gifts!$C$6:$C$1005=B27)*Gifts!$Q$6:$Q$1005*Gifts!$M$6:$M$1005))) | H27: =IF(B27="","",SUMIFS(Gifts!$D$6:$D$1005,Gifts!$C$6:$C$1005,B27,Gifts!$K$6:$K$1005,Settings!$C$7,Gifts!$D$6:$D$1005,">0")) | I27: =IF(B27="","",SUMIFS(Gifts!$D$6:$D$1005,Gifts!$C$6:$C$1005,B27,Gifts!$D$6:$D$1005,">0",Gifts!$M$6:$M$1005,">0")) | J27: =IF(B27="","",SUMIFS(Gifts!$Q$6:$Q$1005,Gifts!$C$6:$C$1005,B27)) | K27: =IF(B27="","",IF(N(J27)=0,"No gifts yet",IF(AND(N(Settings!$C$9)>0,G27<EDATE(TODAY(),-N(Settings!$C$9))),"Lapsed",IF(YEAR(F27)=N(Settings!$C$7),"New","Active")))) | M27: =IF(OR(B27="",N(H27)<=0),"",ROUND(H27*100,0)*1000+1000-ROW()) | N27: =IF(B27="","",SUMIFS(Gifts!$Q$6:$Q$1005,Gifts!$C$6:$C$1005,B27,Gifts!$K$6:$K$1005,Settings!$C$7))
F28: =IF(OR(B28="",N(J28)=0),"",SUMPRODUCT(MIN((Gifts!$C$6:$C$1005=B28)*Gifts!$Q$6:$Q$1005*Gifts!$M$6:$M$1005+(1-(Gifts!$C$6:$C$1005=B28)*Gifts!$Q$6:$Q$1005)*1E9))) | G28: =IF(OR(B28="",N(J28)=0),"",SUMPRODUCT(MAX((Gifts!$C$6:$C$1005=B28)*Gifts!$Q$6:$Q$1005*Gifts!$M$6:$M$1005))) | H28: =IF(B28="","",SUMIFS(Gifts!$D$6:$D$1005,Gifts!$C$6:$C$1005,B28,Gifts!$K$6:$K$1005,Settings!$C$7,Gifts!$D$6:$D$1005,">0")) | I28: =IF(B28="","",SUMIFS(Gifts!$D$6:$D$1005,Gifts!$C$6:$C$1005,B28,Gifts!$D$6:$D$1005,">0",Gifts!$M$6:$M$1005,">0")) | J28: =IF(B28="","",SUMIFS(Gifts!$Q$6:$Q$1005,Gifts!$C$6:$C$1005,B28)) | K28: =IF(B28="","",IF(N(J28)=0,"No gifts yet",IF(AND(N(Settings!$C$9)>0,G28<EDATE(TODAY(),-N(Settings!$C$9))),"Lapsed",IF(YEAR(F28)=N(Settings!$C$7),"New","Active")))) | M28: =IF(OR(B28="",N(H28)<=0),"",ROUND(H28*100,0)*1000+1000-ROW()) | N28: =IF(B28="","",SUMIFS(Gifts!$Q$6:$Q$1005,Gifts!$C$6:$C$1005,B28,Gifts!$K$6:$K$1005,Settings!$C$7))
F29: =IF(OR(B29="",N(J29)=0),"",SUMPRODUCT(MIN((Gifts!$C$6:$C$1005=B29)*Gifts!$Q$6:$Q$1005*Gifts!$M$6:$M$1005+(1-(Gifts!$C$6:$C$1005=B29)*Gifts!$Q$6:$Q$1005)*1E9))) | G29: =IF(OR(B29="",N(J29)=0),"",SUMPRODUCT(MAX((Gifts!$C$6:$C$1005=B29)*Gifts!$Q$6:$Q$1005*Gifts!$M$6:$M$1005))) | H29: =IF(B29="","",SUMIFS(Gifts!$D$6:$D$1005,Gifts!$C$6:$C$1005,B29,Gifts!$K$6:$K$1005,Settings!$C$7,Gifts!$D$6:$D$1005,">0")) | I29: =IF(B29="","",SUMIFS(Gifts!$D$6:$D$1005,Gifts!$C$6:$C$1005,B29,Gifts!$D$6:$D$1005,">0",Gifts!$M$6:$M$1005,">0")) | J29: =IF(B29="","",SUMIFS(Gifts!$Q$6:$Q$1005,Gifts!$C$6:$C$1005,B29)) | K29: =IF(B29="","",IF(N(J29)=0,"No gifts yet",IF(AND(N(Settings!$C$9)>0,G29<EDATE(TODAY(),-N(Settings!$C$9))),"Lapsed",IF(YEAR(F29)=N(Settings!$C$7),"New","Active")))) | M29: =IF(OR(B29="",N(H29)<=0),"",ROUND(H29*100,0)*1000+1000-ROW()) | N29: =IF(B29="","",SUMIFS(Gifts!$Q$6:$Q$1005,Gifts!$C$6:$C$1005,B29,Gifts!$K$6:$K$1005,Settings!$C$7))
... F305: =IF(OR(B305="",N(J305)=0),"",SUMPRODUCT(MIN((Gifts!$C$6:$C$1005=B305)*Gifts!$Q$6:$Q$1005*Gifts!$M$6:$M$1005+(1-(Gifts!$C$6:$C$1005=B305)*Gifts!$Q$6:$Q$1005)*1E9))) | G305: =IF(OR(B305="",N(J305)=0),"",SUMPRODUCT(MAX((Gifts!$C$6:$C$1005=B305)*Gifts!$Q$6:$Q$1005*Gifts!$M$6:$M$1005))) | H305: =IF(B305="","",SUMIFS(Gifts!$D$6:$D$1005,Gifts!$C$6:$C$1005,B305,Gifts!$K$6:$K$1005,Settings!$C$7,Gifts!$D$6:$D$1005,">0")) | I305: =IF(B305="","",SUMIFS(Gifts!$D$6:$D$1005,Gifts!$C$6:$C$1005,B305,Gifts!$D$6:$D$1005,">0",Gifts!$M$6:$M$1005,">0")) | J305: =IF(B305="","",SUMIFS(Gifts!$Q$6:$Q$1005,Gifts!$C$6:$C$1005,B305)) | K305: =IF(B305="","",IF(N(J305)=0,"No gifts yet",IF(AND(N(Settings!$C$9)>0,G305<EDATE(TODAY(),-N(Settings!$C$9))),"Lapsed",IF(YEAR(F305)=N(Settings!$C$7),"New","Active")))) | M305: =IF(OR(B305="",N(H305)<=0),"",ROUND(H305*100,0)*1000+1000-ROW()) | N305: =IF(B305="","",SUMIFS(Gifts!$Q$6:$Q$1005,Gifts!$C$6:$C$1005,B305,Gifts!$K$6:$K$1005,Settings!$C$7))

Sheet Campaigns
B2: Campaigns
B3: What you raise money for, with a goal and dates if it has them.
B5: Campaign | C5: Goal | D5: Starts | E5: Ends | F5: Raised | G5: Of goal | I5: Donors | J5: Days left | K5: Status
B6: General fund | F6: =IF(B6="","",SUMIFS(Gifts!$D$6:$D$1005,Gifts!$F$6:$F$1005,B6,Gifts!$D$6:$D$1005,">0",Gifts!$M$6:$M$1005,">0")) | G6: =IF(OR(B6="",N(C6)<=0),"",F6/C6) | H6: =IF(G6="","",REPT("█",MIN(12,MAX(0,ROUND((G6)*12,0))))&REPT("░",12-MIN(12,MAX(0,ROUND((G6)*12,0))))) | I6: =IF(B6="","",SUMIFS(Gifts!$N$6:$N$1005,Gifts!$F$6:$F$1005,B6)) | J6: =IF(OR(B6="",NOT(ISNUMBER(E6))),"",MAX(0,E6-TODAY())) | K6: =IF(B6="","",IF(AND(N(C6)>0,F6>=N(C6)),"Reached",IF(AND(ISNUMBER(E6),E6<TODAY()),"Ended",IF(AND(ISNUMBER(D6),D6>TODAY()),"Not started","Running"))))
B7: Winter coat drive | C7: 3000 | D7: 46253 | E7: 46343 | F7: =IF(B7="","",SUMIFS(Gifts!$D$6:$D$1005,Gifts!$F$6:$F$1005,B7,Gifts!$D$6:$D$1005,">0",Gifts!$M$6:$M$1005,">0")) | G7: =IF(OR(B7="",N(C7)<=0),"",F7/C7) | H7: =IF(G7="","",REPT("█",MIN(12,MAX(0,ROUND((G7)*12,0))))&REPT("░",12-MIN(12,MAX(0,ROUND((G7)*12,0))))) | I7: =IF(B7="","",SUMIFS(Gifts!$N$6:$N$1005,Gifts!$F$6:$F$1005,B7)) | J7: =IF(OR(B7="",NOT(ISNUMBER(E7))),"",MAX(0,E7-TODAY())) | K7: =IF(B7="","",IF(AND(N(C7)>0,F7>=N(C7)),"Reached",IF(AND(ISNUMBER(E7),E7<TODAY()),"Ended",IF(AND(ISNUMBER(D7),D7>TODAY()),"Not started","Running"))))
B8: New freezer | C8: 5000 | D8: 46143 | E8: 46313 | F8: =IF(B8="","",SUMIFS(Gifts!$D$6:$D$1005,Gifts!$F$6:$F$1005,B8,Gifts!$D$6:$D$1005,">0",Gifts!$M$6:$M$1005,">0")) | G8: =IF(OR(B8="",N(C8)<=0),"",F8/C8) | H8: =IF(G8="","",REPT("█",MIN(12,MAX(0,ROUND((G8)*12,0))))&REPT("░",12-MIN(12,MAX(0,ROUND((G8)*12,0))))) | I8: =IF(B8="","",SUMIFS(Gifts!$N$6:$N$1005,Gifts!$F$6:$F$1005,B8)) | J8: =IF(OR(B8="",NOT(ISNUMBER(E8))),"",MAX(0,E8-TODAY())) | K8: =IF(B8="","",IF(AND(N(C8)>0,F8>=N(C8)),"Reached",IF(AND(ISNUMBER(E8),E8<TODAY()),"Ended",IF(AND(ISNUMBER(D8),D8>TODAY()),"Not started","Running"))))
B9: Back to school | C9: 600 | D9: 46173 | E9: 46263 | F9: =IF(B9="","",SUMIFS(Gifts!$D$6:$D$1005,Gifts!$F$6:$F$1005,B9,Gifts!$D$6:$D$1005,">0",Gifts!$M$6:$M$1005,">0")) | G9: =IF(OR(B9="",N(C9)<=0),"",F9/C9) | H9: =IF(G9="","",REPT("█",MIN(12,MAX(0,ROUND((G9)*12,0))))&REPT("░",12-MIN(12,MAX(0,ROUND((G9)*12,0))))) | I9: =IF(B9="","",SUMIFS(Gifts!$N$6:$N$1005,Gifts!$F$6:$F$1005,B9)) | J9: =IF(OR(B9="",NOT(ISNUMBER(E9))),"",MAX(0,E9-TODAY())) | K9: =IF(B9="","",IF(AND(N(C9)>0,F9>=N(C9)),"Reached",IF(AND(ISNUMBER(E9),E9<TODAY()),"Ended",IF(AND(ISNUMBER(D9),D9>TODAY()),"Not started","Running"))))
B10: Spring garden | C10: 800 | D10: 46323 | E10: 46413 | F10: =IF(B10="","",SUMIFS(Gifts!$D$6:$D$1005,Gifts!$F$6:$F$1005,B10,Gifts!$D$6:$D$1005,">0",Gifts!$M$6:$M$1005,">0")) | G10: =IF(OR(B10="",N(C10)<=0),"",F10/C10) | H10: =IF(G10="","",REPT("█",MIN(12,MAX(0,ROUND((G10)*12,0))))&REPT("░",12-MIN(12,MAX(0,ROUND((G10)*12,0))))) | I10: =IF(B10="","",SUMIFS(Gifts!$N$6:$N$1005,Gifts!$F$6:$F$1005,B10)) | J10: =IF(OR(B10="",NOT(ISNUMBER(E10))),"",MAX(0,E10-TODAY())) | K10: =IF(B10="","",IF(AND(N(C10)>0,F10>=N(C10)),"Reached",IF(AND(ISNUMBER(E10),E10<TODAY()),"Ended",IF(AND(ISNUMBER(D10),D10>TODAY()),"Not started","Running"))))
F11: =IF(B11="","",SUMIFS(Gifts!$D$6:$D$1005,Gifts!$F$6:$F$1005,B11,Gifts!$D$6:$D$1005,">0",Gifts!$M$6:$M$1005,">0")) | G11: =IF(OR(B11="",N(C11)<=0),"",F11/C11) | H11: =IF(G11="","",REPT("█",MIN(12,MAX(0,ROUND((G11)*12,0))))&REPT("░",12-MIN(12,MAX(0,ROUND((G11)*12,0))))) | I11: =IF(B11="","",SUMIFS(Gifts!$N$6:$N$1005,Gifts!$F$6:$F$1005,B11)) | J11: =IF(OR(B11="",NOT(ISNUMBER(E11))),"",MAX(0,E11-TODAY())) | K11: =IF(B11="","",IF(AND(N(C11)>0,F11>=N(C11)),"Reached",IF(AND(ISNUMBER(E11),E11<TODAY()),"Ended",IF(AND(ISNUMBER(D11),D11>TODAY()),"Not started","Running"))))
F12: =IF(B12="","",SUMIFS(Gifts!$D$6:$D$1005,Gifts!$F$6:$F$1005,B12,Gifts!$D$6:$D$1005,">0",Gifts!$M$6:$M$1005,">0")) | G12: =IF(OR(B12="",N(C12)<=0),"",F12/C12) | H12: =IF(G12="","",REPT("█",MIN(12,MAX(0,ROUND((G12)*12,0))))&REPT("░",12-MIN(12,MAX(0,ROUND((G12)*12,0))))) | I12: =IF(B12="","",SUMIFS(Gifts!$N$6:$N$1005,Gifts!$F$6:$F$1005,B12)) | J12: =IF(OR(B12="",NOT(ISNUMBER(E12))),"",MAX(0,E12-TODAY())) | K12: =IF(B12="","",IF(AND(N(C12)>0,F12>=N(C12)),"Reached",IF(AND(ISNUMBER(E12),E12<TODAY()),"Ended",IF(AND(ISNUMBER(D12),D12>TODAY()),"Not started","Running"))))
F13: =IF(B13="","",SUMIFS(Gifts!$D$6:$D$1005,Gifts!$F$6:$F$1005,B13,Gifts!$D$6:$D$1005,">0",Gifts!$M$6:$M$1005,">0")) | G13: =IF(OR(B13="",N(C13)<=0),"",F13/C13) | H13: =IF(G13="","",REPT("█",MIN(12,MAX(0,ROUND((G13)*12,0))))&REPT("░",12-MIN(12,MAX(0,ROUND((G13)*12,0))))) | I13: =IF(B13="","",SUMIFS(Gifts!$N$6:$N$1005,Gifts!$F$6:$F$1005,B13)) | J13: =IF(OR(B13="",NOT(ISNUMBER(E13))),"",MAX(0,E13-TODAY())) | K13: =IF(B13="","",IF(AND(N(C13)>0,F13>=N(C13)),"Reached",IF(AND(ISNUMBER(E13),E13<TODAY()),"Ended",IF(AND(ISNUMBER(D13),D13>TODAY()),"Not started","Running"))))
F14: =IF(B14="","",SUMIFS(Gifts!$D$6:$D$1005,Gifts!$F$6:$F$1005,B14,Gifts!$D$6:$D$1005,">0",Gifts!$M$6:$M$1005,">0")) | G14: =IF(OR(B14="",N(C14)<=0),"",F14/C14) | H14: =IF(G14="","",REPT("█",MIN(12,MAX(0,ROUND((G14)*12,0))))&REPT("░",12-MIN(12,MAX(0,ROUND((G14)*12,0))))) | I14: =IF(B14="","",SUMIFS(Gifts!$N$6:$N$1005,Gifts!$F$6:$F$1005,B14)) | J14: =IF(OR(B14="",NOT(ISNUMBER(E14))),"",MAX(0,E14-TODAY())) | K14: =IF(B14="","",IF(AND(N(C14)>0,F14>=N(C14)),"Reached",IF(AND(ISNUMBER(E14),E14<TODAY()),"Ended",IF(AND(ISNUMBER(D14),D14>TODAY()),"Not started","Running"))))
F15: =IF(B15="","",SUMIFS(Gifts!$D$6:$D$1005,Gifts!$F$6:$F$1005,B15,Gifts!$D$6:$D$1005,">0",Gifts!$M$6:$M$1005,">0")) | G15: =IF(OR(B15="",N(C15)<=0),"",F15/C15) | H15: =IF(G15="","",REPT("█",MIN(12,MAX(0,ROUND((G15)*12,0))))&REPT("░",12-MIN(12,MAX(0,ROUND((G15)*12,0))))) | I15: =IF(B15="","",SUMIFS(Gifts!$N$6:$N$1005,Gifts!$F$6:$F$1005,B15)) | J15: =IF(OR(B15="",NOT(ISNUMBER(E15))),"",MAX(0,E15-TODAY())) | K15: =IF(B15="","",IF(AND(N(C15)>0,F15>=N(C15)),"Reached",IF(AND(ISNUMBER(E15),E15<TODAY()),"Ended",IF(AND(ISNUMBER(D15),D15>TODAY()),"Not started","Running"))))
F16: =IF(B16="","",SUMIFS(Gifts!$D$6:$D$1005,Gifts!$F$6:$F$1005,B16,Gifts!$D$6:$D$1005,">0",Gifts!$M$6:$M$1005,">0")) | G16: =IF(OR(B16="",N(C16)<=0),"",F16/C16) | H16: =IF(G16="","",REPT("█",MIN(12,MAX(0,ROUND((G16)*12,0))))&REPT("░",12-MIN(12,MAX(0,ROUND((G16)*12,0))))) | I16: =IF(B16="","",SUMIFS(Gifts!$N$6:$N$1005,Gifts!$F$6:$F$1005,B16)) | J16: =IF(OR(B16="",NOT(ISNUMBER(E16))),"",MAX(0,E16-TODAY())) | K16: =IF(B16="","",IF(AND(N(C16)>0,F16>=N(C16)),"Reached",IF(AND(ISNUMBER(E16),E16<TODAY()),"Ended",IF(AND(ISNUMBER(D16),D16>TODAY()),"Not started","Running"))))
F17: =IF(B17="","",SUMIFS(Gifts!$D$6:$D$1005,Gifts!$F$6:$F$1005,B17,Gifts!$D$6:$D$1005,">0",Gifts!$M$6:$M$1005,">0")) | G17: =IF(OR(B17="",N(C17)<=0),"",F17/C17) | H17: =IF(G17="","",REPT("█",MIN(12,MAX(0,ROUND((G17)*12,0))))&REPT("░",12-MIN(12,MAX(0,ROUND((G17)*12,0))))) | I17: =IF(B17="","",SUMIFS(Gifts!$N$6:$N$1005,Gifts!$F$6:$F$1005,B17)) | J17: =IF(OR(B17="",NOT(ISNUMBER(E17))),"",MAX(0,E17-TODAY())) | K17: =IF(B17="","",IF(AND(N(C17)>0,F17>=N(C17)),"Reached",IF(AND(ISNUMBER(E17),E17<TODAY()),"Ended",IF(AND(ISNUMBER(D17),D17>TODAY()),"Not started","Running"))))
F18: =IF(B18="","",SUMIFS(Gifts!$D$6:$D$1005,Gifts!$F$6:$F$1005,B18,Gifts!$D$6:$D$1005,">0",Gifts!$M$6:$M$1005,">0")) | G18: =IF(OR(B18="",N(C18)<=0),"",F18/C18) | H18: =IF(G18="","",REPT("█",MIN(12,MAX(0,ROUND((G18)*12,0))))&REPT("░",12-MIN(12,MAX(0,ROUND((G18)*12,0))))) | I18: =IF(B18="","",SUMIFS(Gifts!$N$6:$N$1005,Gifts!$F$6:$F$1005,B18)) | J18: =IF(OR(B18="",NOT(ISNUMBER(E18))),"",MAX(0,E18-TODAY())) | K18: =IF(B18="","",IF(AND(N(C18)>0,F18>=N(C18)),"Reached",IF(AND(ISNUMBER(E18),E18<TODAY()),"Ended",IF(AND(ISNUMBER(D18),D18>TODAY()),"Not started","Running"))))
F19: =IF(B19="","",SUMIFS(Gifts!$D$6:$D$1005,Gifts!$F$6:$F$1005,B19,Gifts!$D$6:$D$1005,">0",Gifts!$M$6:$M$1005,">0")) | G19: =IF(OR(B19="",N(C19)<=0),"",F19/C19) | H19: =IF(G19="","",REPT("█",MIN(12,MAX(0,ROUND((G19)*12,0))))&REPT("░",12-MIN(12,MAX(0,ROUND((G19)*12,0))))) | I19: =IF(B19="","",SUMIFS(Gifts!$N$6:$N$1005,Gifts!$F$6:$F$1005,B19)) | J19: =IF(OR(B19="",NOT(ISNUMBER(E19))),"",MAX(0,E19-TODAY())) | K19: =IF(B19="","",IF(AND(N(C19)>0,F19>=N(C19)),"Reached",IF(AND(ISNUMBER(E19),E19<TODAY()),"Ended",IF(AND(ISNUMBER(D19),D19>TODAY()),"Not started","Running"))))
F20: =IF(B20="","",SUMIFS(Gifts!$D$6:$D$1005,Gifts!$F$6:$F$1005,B20,Gifts!$D$6:$D$1005,">0",Gifts!$M$6:$M$1005,">0")) | G20: =IF(OR(B20="",N(C20)<=0),"",F20/C20) | H20: =IF(G20="","",REPT("█",MIN(12,MAX(0,ROUND((G20)*12,0))))&REPT("░",12-MIN(12,MAX(0,ROUND((G20)*12,0))))) | I20: =IF(B20="","",SUMIFS(Gifts!$N$6:$N$1005,Gifts!$F$6:$F$1005,B20)) | J20: =IF(OR(B20="",NOT(ISNUMBER(E20))),"",MAX(0,E20-TODAY())) | K20: =IF(B20="","",IF(AND(N(C20)>0,F20>=N(C20)),"Reached",IF(AND(ISNUMBER(E20),E20<TODAY()),"Ended",IF(AND(ISNUMBER(D20),D20>TODAY()),"Not started","Running"))))
F21: =IF(B21="","",SUMIFS(Gifts!$D$6:$D$1005,Gifts!$F$6:$F$1005,B21,Gifts!$D$6:$D$1005,">0",Gifts!$M$6:$M$1005,">0")) | G21: =IF(OR(B21="",N(C21)<=0),"",F21/C21) | H21: =IF(G21="","",REPT("█",MIN(12,MAX(0,ROUND((G21)*12,0))))&REPT("░",12-MIN(12,MAX(0,ROUND((G21)*12,0))))) | I21: =IF(B21="","",SUMIFS(Gifts!$N$6:$N$1005,Gifts!$F$6:$F$1005,B21)) | J21: =IF(OR(B21="",NOT(ISNUMBER(E21))),"",MAX(0,E21-TODAY())) | K21: =IF(B21="","",IF(AND(N(C21)>0,F21>=N(C21)),"Reached",IF(AND(ISNUMBER(E21),E21<TODAY()),"Ended",IF(AND(ISNUMBER(D21),D21>TODAY()),"Not started","Running"))))
F22: =IF(B22="","",SUMIFS(Gifts!$D$6:$D$1005,Gifts!$F$6:$F$1005,B22,Gifts!$D$6:$D$1005,">0",Gifts!$M$6:$M$1005,">0")) | G22: =IF(OR(B22="",N(C22)<=0),"",F22/C22) | H22: =IF(G22="","",REPT("█",MIN(12,MAX(0,ROUND((G22)*12,0))))&REPT("░",12-MIN(12,MAX(0,ROUND((G22)*12,0))))) | I22: =IF(B22="","",SUMIFS(Gifts!$N$6:$N$1005,Gifts!$F$6:$F$1005,B22)) | J22: =IF(OR(B22="",NOT(ISNUMBER(E22))),"",MAX(0,E22-TODAY())) | K22: =IF(B22="","",IF(AND(N(C22)>0,F22>=N(C22)),"Reached",IF(AND(ISNUMBER(E22),E22<TODAY()),"Ended",IF(AND(ISNUMBER(D22),D22>TODAY()),"Not started","Running"))))
... F25: =IF(B25="","",SUMIFS(Gifts!$D$6:$D$1005,Gifts!$F$6:$F$1005,B25,Gifts!$D$6:$D$1005,">0",Gifts!$M$6:$M$1005,">0")) | G25: =IF(OR(B25="",N(C25)<=0),"",F25/C25) | H25: =IF(G25="","",REPT("█",MIN(12,MAX(0,ROUND((G25)*12,0))))&REPT("░",12-MIN(12,MAX(0,ROUND((G25)*12,0))))) | I25: =IF(B25="","",SUMIFS(Gifts!$N$6:$N$1005,Gifts!$F$6:$F$1005,B25)) | J25: =IF(OR(B25="",NOT(ISNUMBER(E25))),"",MAX(0,E25-TODAY())) | K25: =IF(B25="","",IF(AND(N(C25)>0,F25>=N(C25)),"Reached",IF(AND(ISNUMBER(E25),E25<TODAY()),"Ended",IF(AND(ISNUMBER(D25),D25>TODAY()),"Not started","Running"))))

Sheet Statement
B2: =IF(Settings!$C$4="","",Settings!$C$4)
B3: =IF(Settings!$C$5="","",Settings!$C$5)
B4: Donor | C4: Grace Holloway
B5: Year | C5: =Settings!$C$7
B7: =IF(C4="","","Statement of gifts for "&C5)
B8: =IF(C4="","",C4&IFERROR(IF(INDEX(Donors!$E$6:$E$305,MATCH(C4,Donors!$B$6:$B$305,0))="","",", "&INDEX(Donors!$E$6:$E$305,MATCH(C4,Donors!$B$6:$B$305,0))),""))
B9: ="Issued on "&DAY(TODAY())&" "&CHOOSE(MONTH(TODAY()),"Jan","Feb","Mar","Apr","May","Jun","Jul","Aug","Sep","Oct","Nov","Dec")&" "&YEAR(TODAY())
B11: Date | C11: Amount | D11: How | E11: Campaign | F11: Goods given
B12: =IF(H12="","",INDEX(Gifts!$B$1:$B$1005,MOD(H12,10000))) | C12: =IF(H12="","",IF(N(INDEX(Gifts!$D$1:$D$1005,MOD(H12,10000)))=0,"",INDEX(Gifts!$D$1:$D$1005,MOD(H12,10000)))) | D12: =IF(H12="","",IF(INDEX(Gifts!$E$1:$E$1005,MOD(H12,10000))="","",INDEX(Gifts!$E$1:$E$1005,MOD(H12,10000)))) | E12: =IF(H12="","",IF(INDEX(Gifts!$F$1:$F$1005,MOD(H12,10000))="","",INDEX(Gifts!$F$1:$F$1005,MOD(H12,10000)))) | F12: =IF(H12="","",IF(INDEX(Gifts!$G$1:$G$1005,MOD(H12,10000))="","",INDEX(Gifts!$G$1:$G$1005,MOD(H12,10000)))) | H12: =IFERROR(SMALL(Gifts!$P$6:$P$1005,1),"")
B13: =IF(H13="","",INDEX(Gifts!$B$1:$B$1005,MOD(H13,10000))) | C13: =IF(H13="","",IF(N(INDEX(Gifts!$D$1:$D$1005,MOD(H13,10000)))=0,"",INDEX(Gifts!$D$1:$D$1005,MOD(H13,10000)))) | D13: =IF(H13="","",IF(INDEX(Gifts!$E$1:$E$1005,MOD(H13,10000))="","",INDEX(Gifts!$E$1:$E$1005,MOD(H13,10000)))) | E13: =IF(H13="","",IF(INDEX(Gifts!$F$1:$F$1005,MOD(H13,10000))="","",INDEX(Gifts!$F$1:$F$1005,MOD(H13,10000)))) | F13: =IF(H13="","",IF(INDEX(Gifts!$G$1:$G$1005,MOD(H13,10000))="","",INDEX(Gifts!$G$1:$G$1005,MOD(H13,10000)))) | H13: =IFERROR(SMALL(Gifts!$P$6:$P$1005,2),"")
B14: =IF(H14="","",INDEX(Gifts!$B$1:$B$1005,MOD(H14,10000))) | C14: =IF(H14="","",IF(N(INDEX(Gifts!$D$1:$D$1005,MOD(H14,10000)))=0,"",INDEX(Gifts!$D$1:$D$1005,MOD(H14,10000)))) | D14: =IF(H14="","",IF(INDEX(Gifts!$E$1:$E$1005,MOD(H14,10000))="","",INDEX(Gifts!$E$1:$E$1005,MOD(H14,10000)))) | E14: =IF(H14="","",IF(INDEX(Gifts!$F$1:$F$1005,MOD(H14,10000))="","",INDEX(Gifts!$F$1:$F$1005,MOD(H14,10000)))) | F14: =IF(H14="","",IF(INDEX(Gifts!$G$1:$G$1005,MOD(H14,10000))="","",INDEX(Gifts!$G$1:$G$1005,MOD(H14,10000)))) | H14: =IFERROR(SMALL(Gifts!$P$6:$P$1005,3),"")
B15: =IF(H15="","",INDEX(Gifts!$B$1:$B$1005,MOD(H15,10000))) | C15: =IF(H15="","",IF(N(INDEX(Gifts!$D$1:$D$1005,MOD(H15,10000)))=0,"",INDEX(Gifts!$D$1:$D$1005,MOD(H15,10000)))) | D15: =IF(H15="","",IF(INDEX(Gifts!$E$1:$E$1005,MOD(H15,10000))="","",INDEX(Gifts!$E$1:$E$1005,MOD(H15,10000)))) | E15: =IF(H15="","",IF(INDEX(Gifts!$F$1:$F$1005,MOD(H15,10000))="","",INDEX(Gifts!$F$1:$F$1005,MOD(H15,10000)))) | F15: =IF(H15="","",IF(INDEX(Gifts!$G$1:$G$1005,MOD(H15,10000))="","",INDEX(Gifts!$G$1:$G$1005,MOD(H15,10000)))) | H15: =IFERROR(SMALL(Gifts!$P$6:$P$1005,4),"")
B16: =IF(H16="","",INDEX(Gifts!$B$1:$B$1005,MOD(H16,10000))) | C16: =IF(H16="","",IF(N(INDEX(Gifts!$D$1:$D$1005,MOD(H16,10000)))=0,"",INDEX(Gifts!$D$1:$D$1005,MOD(H16,10000)))) | D16: =IF(H16="","",IF(INDEX(Gifts!$E$1:$E$1005,MOD(H16,10000))="","",INDEX(Gifts!$E$1:$E$1005,MOD(H16,10000)))) | E16: =IF(H16="","",IF(INDEX(Gifts!$F$1:$F$1005,MOD(H16,10000))="","",INDEX(Gifts!$F$1:$F$1005,MOD(H16,10000)))) | F16: =IF(H16="","",IF(INDEX(Gifts!$G$1:$G$1005,MOD(H16,10000))="","",INDEX(Gifts!$G$1:$G$1005,MOD(H16,10000)))) | H16: =IFERROR(SMALL(Gifts!$P$6:$P$1005,5),"")
B17: =IF(H17="","",INDEX(Gifts!$B$1:$B$1005,MOD(H17,10000))) | C17: =IF(H17="","",IF(N(INDEX(Gifts!$D$1:$D$1005,MOD(H17,10000)))=0,"",INDEX(Gifts!$D$1:$D$1005,MOD(H17,10000)))) | D17: =IF(H17="","",IF(INDEX(Gifts!$E$1:$E$1005,MOD(H17,10000))="","",INDEX(Gifts!$E$1:$E$1005,MOD(H17,10000)))) | E17: =IF(H17="","",IF(INDEX(Gifts!$F$1:$F$1005,MOD(H17,10000))="","",INDEX(Gifts!$F$1:$F$1005,MOD(H17,10000)))) | F17: =IF(H17="","",IF(INDEX(Gifts!$G$1:$G$1005,MOD(H17,10000))="","",INDEX(Gifts!$G$1:$G$1005,MOD(H17,10000)))) | H17: =IFERROR(SMALL(Gifts!$P$6:$P$1005,6),"")
B18: =IF(H18="","",INDEX(Gifts!$B$1:$B$1005,MOD(H18,10000))) | C18: =IF(H18="","",IF(N(INDEX(Gifts!$D$1:$D$1005,MOD(H18,10000)))=0,"",INDEX(Gifts!$D$1:$D$1005,MOD(H18,10000)))) | D18: =IF(H18="","",IF(INDEX(Gifts!$E$1:$E$1005,MOD(H18,10000))="","",INDEX(Gifts!$E$1:$E$1005,MOD(H18,10000)))) | E18: =IF(H18="","",IF(INDEX(Gifts!$F$1:$F$1005,MOD(H18,10000))="","",INDEX(Gifts!$F$1:$F$1005,MOD(H18,10000)))) | F18: =IF(H18="","",IF(INDEX(Gifts!$G$1:$G$1005,MOD(H18,10000))="","",INDEX(Gifts!$G$1:$G$1005,MOD(H18,10000)))) | H18: =IFERROR(SMALL(Gifts!$P$6:$P$1005,7),"")
B19: =IF(H19="","",INDEX(Gifts!$B$1:$B$1005,MOD(H19,10000))) | C19: =IF(H19="","",IF(N(INDEX(Gifts!$D$1:$D$1005,MOD(H19,10000)))=0,"",INDEX(Gifts!$D$1:$D$1005,MOD(H19,10000)))) | D19: =IF(H19="","",IF(INDEX(Gifts!$E$1:$E$1005,MOD(H19,10000))="","",INDEX(Gifts!$E$1:$E$1005,MOD(H19,10000)))) | E19: =IF(H19="","",IF(INDEX(Gifts!$F$1:$F$1005,MOD(H19,10000))="","",INDEX(Gifts!$F$1:$F$1005,MOD(H19,10000)))) | F19: =IF(H19="","",IF(INDEX(Gifts!$G$1:$G$1005,MOD(H19,10000))="","",INDEX(Gifts!$G$1:$G$1005,MOD(H19,10000)))) | H19: =IFERROR(SMALL(Gifts!$P$6:$P$1005,8),"")
B20: =IF(H20="","",INDEX(Gifts!$B$1:$B$1005,MOD(H20,10000))) | C20: =IF(H20="","",IF(N(INDEX(Gifts!$D$1:$D$1005,MOD(H20,10000)))=0,"",INDEX(Gifts!$D$1:$D$1005,MOD(H20,10000)))) | D20: =IF(H20="","",IF(INDEX(Gifts!$E$1:$E$1005,MOD(H20,10000))="","",INDEX(Gifts!$E$1:$E$1005,MOD(H20,10000)))) | E20: =IF(H20="","",IF(INDEX(Gifts!$F$1:$F$1005,MOD(H20,10000))="","",INDEX(Gifts!$F$1:$F$1005,MOD(H20,10000)))) | F20: =IF(H20="","",IF(INDEX(Gifts!$G$1:$G$1005,MOD(H20,10000))="","",INDEX(Gifts!$G$1:$G$1005,MOD(H20,10000)))) | H20: =IFERROR(SMALL(Gifts!$P$6:$P$1005,9),"")
B21: =IF(H21="","",INDEX(Gifts!$B$1:$B$1005,MOD(H21,10000))) | C21: =IF(H21="","",IF(N(INDEX(Gifts!$D$1:$D$1005,MOD(H21,10000)))=0,"",INDEX(Gifts!$D$1:$D$1005,MOD(H21,10000)))) | D21: =IF(H21="","",IF(INDEX(Gifts!$E$1:$E$1005,MOD(H21,10000))="","",INDEX(Gifts!$E$1:$E$1005,MOD(H21,10000)))) | E21: =IF(H21="","",IF(INDEX(Gifts!$F$1:$F$1005,MOD(H21,10000))="","",INDEX(Gifts!$F$1:$F$1005,MOD(H21,10000)))) | F21: =IF(H21="","",IF(INDEX(Gifts!$G$1:$G$1005,MOD(H21,10000))="","",INDEX(Gifts!$G$1:$G$1005,MOD(H21,10000)))) | H21: =IFERROR(SMALL(Gifts!$P$6:$P$1005,10),"")
B22: =IF(H22="","",INDEX(Gifts!$B$1:$B$1005,MOD(H22,10000))) | C22: =IF(H22="","",IF(N(INDEX(Gifts!$D$1:$D$1005,MOD(H22,10000)))=0,"",INDEX(Gifts!$D$1:$D$1005,MOD(H22,10000)))) | D22: =IF(H22="","",IF(INDEX(Gifts!$E$1:$E$1005,MOD(H22,10000))="","",INDEX(Gifts!$E$1:$E$1005,MOD(H22,10000)))) | E22: =IF(H22="","",IF(INDEX(Gifts!$F$1:$F$1005,MOD(H22,10000))="","",INDEX(Gifts!$F$1:$F$1005,MOD(H22,10000)))) | F22: =IF(H22="","",IF(INDEX(Gifts!$G$1:$G$1005,MOD(H22,10000))="","",INDEX(Gifts!$G$1:$G$1005,MOD(H22,10000)))) | H22: =IFERROR(SMALL(Gifts!$P$6:$P$1005,11),"")
B23: =IF(H23="","",INDEX(Gifts!$B$1:$B$1005,MOD(H23,10000))) | C23: =IF(H23="","",IF(N(INDEX(Gifts!$D$1:$D$1005,MOD(H23,10000)))=0,"",INDEX(Gifts!$D$1:$D$1005,MOD(H23,10000)))) | D23: =IF(H23="","",IF(INDEX(Gifts!$E$1:$E$1005,MOD(H23,10000))="","",INDEX(Gifts!$E$1:$E$1005,MOD(H23,10000)))) | E23: =IF(H23="","",IF(INDEX(Gifts!$F$1:$F$1005,MOD(H23,10000))="","",INDEX(Gifts!$F$1:$F$1005,MOD(H23,10000)))) | F23: =IF(H23="","",IF(INDEX(Gifts!$G$1:$G$1005,MOD(H23,10000))="","",INDEX(Gifts!$G$1:$G$1005,MOD(H23,10000)))) | H23: =IFERROR(SMALL(Gifts!$P$6:$P$1005,12),"")
B24: =IF(H24="","",INDEX(Gifts!$B$1:$B$1005,MOD(H24,10000))) | C24: =IF(H24="","",IF(N(INDEX(Gifts!$D$1:$D$1005,MOD(H24,10000)))=0,"",INDEX(Gifts!$D$1:$D$1005,MOD(H24,10000)))) | D24: =IF(H24="","",IF(INDEX(Gifts!$E$1:$E$1005,MOD(H24,10000))="","",INDEX(Gifts!$E$1:$E$1005,MOD(H24,10000)))) | E24: =IF(H24="","",IF(INDEX(Gifts!$F$1:$F$1005,MOD(H24,10000))="","",INDEX(Gifts!$F$1:$F$1005,MOD(H24,10000)))) | F24: =IF(H24="","",IF(INDEX(Gifts!$G$1:$G$1005,MOD(H24,10000))="","",INDEX(Gifts!$G$1:$G$1005,MOD(H24,10000)))) | H24: =IFERROR(SMALL(Gifts!$P$6:$P$1005,13),"")
B25: =IF(H25="","",INDEX(Gifts!$B$1:$B$1005,MOD(H25,10000))) | C25: =IF(H25="","",IF(N(INDEX(Gifts!$D$1:$D$1005,MOD(H25,10000)))=0,"",INDEX(Gifts!$D$1:$D$1005,MOD(H25,10000)))) | D25: =IF(H25="","",IF(INDEX(Gifts!$E$1:$E$1005,MOD(H25,10000))="","",INDEX(Gifts!$E$1:$E$1005,MOD(H25,10000)))) | E25: =IF(H25="","",IF(INDEX(Gifts!$F$1:$F$1005,MOD(H25,10000))="","",INDEX(Gifts!$F$1:$F$1005,MOD(H25,10000)))) | F25: =IF(H25="","",IF(INDEX(Gifts!$G$1:$G$1005,MOD(H25,10000))="","",INDEX(Gifts!$G$1:$G$1005,MOD(H25,10000)))) | H25: =IFERROR(SMALL(Gifts!$P$6:$P$1005,14),"")
B26: =IF(H26="","",INDEX(Gifts!$B$1:$B$1005,MOD(H26,10000))) | C26: =IF(H26="","",IF(N(INDEX(Gifts!$D$1:$D$1005,MOD(H26,10000)))=0,"",INDEX(Gifts!$D$1:$D$1005,MOD(H26,10000)))) | D26: =IF(H26="","",IF(INDEX(Gifts!$E$1:$E$1005,MOD(H26,10000))="","",INDEX(Gifts!$E$1:$E$1005,MOD(H26,10000)))) | E26: =IF(H26="","",IF(INDEX(Gifts!$F$1:$F$1005,MOD(H26,10000))="","",INDEX(Gifts!$F$1:$F$1005,MOD(H26,10000)))) | F26: =IF(H26="","",IF(INDEX(Gifts!$G$1:$G$1005,MOD(H26,10000))="","",INDEX(Gifts!$G$1:$G$1005,MOD(H26,10000)))) | H26: =IFERROR(SMALL(Gifts!$P$6:$P$1005,15),"")
B27: =IF(H27="","",INDEX(Gifts!$B$1:$B$1005,MOD(H27,10000))) | C27: =IF(H27="","",IF(N(INDEX(Gifts!$D$1:$D$1005,MOD(H27,10000)))=0,"",INDEX(Gifts!$D$1:$D$1005,MOD(H27,10000)))) | D27: =IF(H27="","",IF(INDEX(Gifts!$E$1:$E$1005,MOD(H27,10000))="","",INDEX(Gifts!$E$1:$E$1005,MOD(H27,10000)))) | E27: =IF(H27="","",IF(INDEX(Gifts!$F$1:$F$1005,MOD(H27,10000))="","",INDEX(Gifts!$F$1:$F$1005,MOD(H27,10000)))) | F27: =IF(H27="","",IF(INDEX(Gifts!$G$1:$G$1005,MOD(H27,10000))="","",INDEX(Gifts!$G$1:$G$1005,MOD(H27,10000)))) | H27: =IFERROR(SMALL(Gifts!$P$6:$P$1005,16),"")
B28: =IF(H28="","",INDEX(Gifts!$B$1:$B$1005,MOD(H28,10000))) | C28: =IF(H28="","",IF(N(INDEX(Gifts!$D$1:$D$1005,MOD(H28,10000)))=0,"",INDEX(Gifts!$D$1:$D$1005,MOD(H28,10000)))) | D28: =IF(H28="","",IF(INDEX(Gifts!$E$1:$E$1005,MOD(H28,10000))="","",INDEX(Gifts!$E$1:$E$1005,MOD(H28,10000)))) | E28: =IF(H28="","",IF(INDEX(Gifts!$F$1:$F$1005,MOD(H28,10000))="","",INDEX(Gifts!$F$1:$F$1005,MOD(H28,10000)))) | F28: =IF(H28="","",IF(INDEX(Gifts!$G$1:$G$1005,MOD(H28,10000))="","",INDEX(Gifts!$G$1:$G$1005,MOD(H28,10000)))) | H28: =IFERROR(SMALL(Gifts!$P$6:$P$1005,17),"")
B29: =IF(H29="","",INDEX(Gifts!$B$1:$B$1005,MOD(H29,10000))) | C29: =IF(H29="","",IF(N(INDEX(Gifts!$D$1:$D$1005,MOD(H29,10000)))=0,"",INDEX(Gifts!$D$1:$D$1005,MOD(H29,10000)))) | D29: =IF(H29="","",IF(INDEX(Gifts!$E$1:$E$1005,MOD(H29,10000))="","",INDEX(Gifts!$E$1:$E$1005,MOD(H29,10000)))) | E29: =IF(H29="","",IF(INDEX(Gifts!$F$1:$F$1005,MOD(H29,10000))="","",INDEX(Gifts!$F$1:$F$1005,MOD(H29,10000)))) | F29: =IF(H29="","",IF(INDEX(Gifts!$G$1:$G$1005,MOD(H29,10000))="","",INDEX(Gifts!$G$1:$G$1005,MOD(H29,10000)))) | H29: =IFERROR(SMALL(Gifts!$P$6:$P$1005,18),"")
B30: =IF(H30="","",INDEX(Gifts!$B$1:$B$1005,MOD(H30,10000))) | C30: =IF(H30="","",IF(N(INDEX(Gifts!$D$1:$D$1005,MOD(H30,10000)))=0,"",INDEX(Gifts!$D$1:$D$1005,MOD(H30,10000)))) | D30: =IF(H30="","",IF(INDEX(Gifts!$E$1:$E$1005,MOD(H30,10000))="","",INDEX(Gifts!$E$1:$E$1005,MOD(H30,10000)))) | E30: =IF(H30="","",IF(INDEX(Gifts!$F$1:$F$1005,MOD(H30,10000))="","",INDEX(Gifts!$F$1:$F$1005,MOD(H30,10000)))) | F30: =IF(H30="","",IF(INDEX(Gifts!$G$1:$G$1005,MOD(H30,10000))="","",INDEX(Gifts!$G$1:$G$1005,MOD(H30,10000)))) | H30: =IFERROR(SMALL(Gifts!$P$6:$P$1005,19),"")
B31: =IF(H31="","",INDEX(Gifts!$B$1:$B$1005,MOD(H31,10000))) | C31: =IF(H31="","",IF(N(INDEX(Gifts!$D$1:$D$1005,MOD(H31,10000)))=0,"",INDEX(Gifts!$D$1:$D$1005,MOD(H31,10000)))) | D31: =IF(H31="","",IF(INDEX(Gifts!$E$1:$E$1005,MOD(H31,10000))="","",INDEX(Gifts!$E$1:$E$1005,MOD(H31,10000)))) | E31: =IF(H31="","",IF(INDEX(Gifts!$F$1:$F$1005,MOD(H31,10000))="","",INDEX(Gifts!$F$1:$F$1005,MOD(H31,10000)))) | F31: =IF(H31="","",IF(INDEX(Gifts!$G$1:$G$1005,MOD(H31,10000))="","",INDEX(Gifts!$G$1:$G$1005,MOD(H31,10000)))) | H31: =IFERROR(SMALL(Gifts!$P$6:$P$1005,20),"")
B32: =IF(H32="","",INDEX(Gifts!$B$1:$B$1005,MOD(H32,10000))) | C32: =IF(H32="","",IF(N(INDEX(Gifts!$D$1:$D$1005,MOD(H32,10000)))=0,"",INDEX(Gifts!$D$1:$D$1005,MOD(H32,10000)))) | D32: =IF(H32="","",IF(INDEX(Gifts!$E$1:$E$1005,MOD(H32,10000))="","",INDEX(Gifts!$E$1:$E$1005,MOD(H32,10000)))) | E32: =IF(H32="","",IF(INDEX(Gifts!$F$1:$F$1005,MOD(H32,10000))="","",INDEX(Gifts!$F$1:$F$1005,MOD(H32,10000)))) | F32: =IF(H32="","",IF(INDEX(Gifts!$G$1:$G$1005,MOD(H32,10000))="","",INDEX(Gifts!$G$1:$G$1005,MOD(H32,10000)))) | H32: =IFERROR(SMALL(Gifts!$P$6:$P$1005,21),"")
B33: =IF(H33="","",INDEX(Gifts!$B$1:$B$1005,MOD(H33,10000))) | C33: =IF(H33="","",IF(N(INDEX(Gifts!$D$1:$D$1005,MOD(H33,10000)))=0,"",INDEX(Gifts!$D$1:$D$1005,MOD(H33,10000)))) | D33: =IF(H33="","",IF(INDEX(Gifts!$E$1:$E$1005,MOD(H33,10000))="","",INDEX(Gifts!$E$1:$E$1005,MOD(H33,10000)))) | E33: =IF(H33="","",IF(INDEX(Gifts!$F$1:$F$1005,MOD(H33,10000))="","",INDEX(Gifts!$F$1:$F$1005,MOD(H33,10000)))) | F33: =IF(H33="","",IF(INDEX(Gifts!$G$1:$G$1005,MOD(H33,10000))="","",INDEX(Gifts!$G$1:$G$1005,MOD(H33,10000)))) | H33: =IFERROR(SMALL(Gifts!$P$6:$P$1005,22),"")
B34: =IF(H34="","",INDEX(Gifts!$B$1:$B$1005,MOD(H34,10000))) | C34: =IF(H34="","",IF(N(INDEX(Gifts!$D$1:$D$1005,MOD(H34,10000)))=0,"",INDEX(Gifts!$D$1:$D$1005,MOD(H34,10000)))) | D34: =IF(H34="","",IF(INDEX(Gifts!$E$1:$E$1005,MOD(H34,10000))="","",INDEX(Gifts!$E$1:$E$1005,MOD(H34,10000)))) | E34: =IF(H34="","",IF(INDEX(Gifts!$F$1:$F$1005,MOD(H34,10000))="","",INDEX(Gifts!$F$1:$F$1005,MOD(H34,10000)))) | F34: =IF(H34="","",IF(INDEX(Gifts!$G$1:$G$1005,MOD(H34,10000))="","",INDEX(Gifts!$G$1:$G$1005,MOD(H34,10000)))) | H34: =IFERROR(SMALL(Gifts!$P$6:$P$1005,23),"")
B35: =IF(H35="","",INDEX(Gifts!$B$1:$B$1005,MOD(H35,10000))) | C35: =IF(H35="","",IF(N(INDEX(Gifts!$D$1:$D$1005,MOD(H35,10000)))=0,"",INDEX(Gifts!$D$1:$D$1005,MOD(H35,10000)))) | D35: =IF(H35="","",IF(INDEX(Gifts!$E$1:$E$1005,MOD(H35,10000))="","",INDEX(Gifts!$E$1:$E$1005,MOD(H35,10000)))) | E35: =IF(H35="","",IF(INDEX(Gifts!$F$1:$F$1005,MOD(H35,10000))="","",INDEX(Gifts!$F$1:$F$1005,MOD(H35,10000)))) | F35: =IF(H35="","",IF(INDEX(Gifts!$G$1:$G$1005,MOD(H35,10000))="","",INDEX(Gifts!$G$1:$G$1005,MOD(H35,10000)))) | H35: =IFERROR(SMALL(Gifts!$P$6:$P$1005,24),"")
B36: =IF(COUNT(Gifts!$P$6:$P$1005)>24,"And "&(COUNT(Gifts!$P$6:$P$1005)-24)&" more gifts, in the total","")
B37: Total | C37: =IF(C4="","",SUMIFS(Gifts!$D$6:$D$1005,Gifts!$C$6:$C$1005,C4,Gifts!$K$6:$K$1005,C5,Gifts!$D$6:$D$1005,">0")) | D37: =IF(Settings!$C$8="","",Settings!$C$8)
B39: =IF(Settings!$C$6="","",Settings!$C$6)

Sheet Volunteers
B2: Volunteers
B3: Each volunteer once. Their hours add up from the Hours tab.
B5: Volunteer | C5: Phone or email | D5: Role | E5: This year | F5: All time | G5: Last time | H5: Times
B6: Mark Evans | C6: mark@mail.example | D6: Driver | E6: =IF(B6="","",SUMIFS(Hours!$D$6:$D$1005,Hours!$C$6:$C$1005,B6,Hours!$I$6:$I$1005,Settings!$C$7,Hours!$D$6:$D$1005,">0")) | F6: =IF(B6="","",SUMIFS(Hours!$D$6:$D$1005,Hours!$C$6:$C$1005,B6,Hours!$D$6:$D$1005,">0",Hours!$K$6:$K$1005,">0")) | G6: =IF(OR(B6="",N(F6)=0),"",SUMPRODUCT(MAX((Hours!$C$6:$C$1005=B6)*Hours!$L$6:$L$1005))) | H6: =IF(B6="","",COUNTIFS(Hours!$C$6:$C$1005,B6,Hours!$I$6:$I$1005,Settings!$C$7,Hours!$D$6:$D$1005,">0"))
B7: Lucy Chen | C7: lucy@mail.example | D7: Sorting | E7: =IF(B7="","",SUMIFS(Hours!$D$6:$D$1005,Hours!$C$6:$C$1005,B7,Hours!$I$6:$I$1005,Settings!$C$7,Hours!$D$6:$D$1005,">0")) | F7: =IF(B7="","",SUMIFS(Hours!$D$6:$D$1005,Hours!$C$6:$C$1005,B7,Hours!$D$6:$D$1005,">0",Hours!$K$6:$K$1005,">0")) | G7: =IF(OR(B7="",N(F7)=0),"",SUMPRODUCT(MAX((Hours!$C$6:$C$1005=B7)*Hours!$L$6:$L$1005))) | H7: =IF(B7="","",COUNTIFS(Hours!$C$6:$C$1005,B7,Hours!$I$6:$I$1005,Settings!$C$7,Hours!$D$6:$D$1005,">0"))
B8: Peter Olsen | C8: peter@mail.example | D8: Front desk | E8: =IF(B8="","",SUMIFS(Hours!$D$6:$D$1005,Hours!$C$6:$C$1005,B8,Hours!$I$6:$I$1005,Settings!$C$7,Hours!$D$6:$D$1005,">0")) | F8: =IF(B8="","",SUMIFS(Hours!$D$6:$D$1005,Hours!$C$6:$C$1005,B8,Hours!$D$6:$D$1005,">0",Hours!$K$6:$K$1005,">0")) | G8: =IF(OR(B8="",N(F8)=0),"",SUMPRODUCT(MAX((Hours!$C$6:$C$1005=B8)*Hours!$L$6:$L$1005))) | H8: =IF(B8="","",COUNTIFS(Hours!$C$6:$C$1005,B8,Hours!$I$6:$I$1005,Settings!$C$7,Hours!$D$6:$D$1005,">0"))
B9: Nadia Karim | C9: nadia@mail.example | D9: Sorting | E9: =IF(B9="","",SUMIFS(Hours!$D$6:$D$1005,Hours!$C$6:$C$1005,B9,Hours!$I$6:$I$1005,Settings!$C$7,Hours!$D$6:$D$1005,">0")) | F9: =IF(B9="","",SUMIFS(Hours!$D$6:$D$1005,Hours!$C$6:$C$1005,B9,Hours!$D$6:$D$1005,">0",Hours!$K$6:$K$1005,">0")) | G9: =IF(OR(B9="",N(F9)=0),"",SUMPRODUCT(MAX((Hours!$C$6:$C$1005=B9)*Hours!$L$6:$L$1005))) | H9: =IF(B9="","",COUNTIFS(Hours!$C$6:$C$1005,B9,Hours!$I$6:$I$1005,Settings!$C$7,Hours!$D$6:$D$1005,">0"))
B10: Joe Ward | C10: joe@mail.example | D10: Driver | E10: =IF(B10="","",SUMIFS(Hours!$D$6:$D$1005,Hours!$C$6:$C$1005,B10,Hours!$I$6:$I$1005,Settings!$C$7,Hours!$D$6:$D$1005,">0")) | F10: =IF(B10="","",SUMIFS(Hours!$D$6:$D$1005,Hours!$C$6:$C$1005,B10,Hours!$D$6:$D$1005,">0",Hours!$K$6:$K$1005,">0")) | G10: =IF(OR(B10="",N(F10)=0),"",SUMPRODUCT(MAX((Hours!$C$6:$C$1005=B10)*Hours!$L$6:$L$1005))) | H10: =IF(B10="","",COUNTIFS(Hours!$C$6:$C$1005,B10,Hours!$I$6:$I$1005,Settings!$C$7,Hours!$D$6:$D$1005,">0"))
B11: Beth Morgan | C11: beth@mail.example | D11: Front desk | E11: =IF(B11="","",SUMIFS(Hours!$D$6:$D$1005,Hours!$C$6:$C$1005,B11,Hours!$I$6:$I$1005,Settings!$C$7,Hours!$D$6:$D$1005,">0")) | F11: =IF(B11="","",SUMIFS(Hours!$D$6:$D$1005,Hours!$C$6:$C$1005,B11,Hours!$D$6:$D$1005,">0",Hours!$K$6:$K$1005,">0")) | G11: =IF(OR(B11="",N(F11)=0),"",SUMPRODUCT(MAX((Hours!$C$6:$C$1005=B11)*Hours!$L$6:$L$1005))) | H11: =IF(B11="","",COUNTIFS(Hours!$C$6:$C$1005,B11,Hours!$I$6:$I$1005,Settings!$C$7,Hours!$D$6:$D$1005,">0"))
B12: Sam Reid | C12: sam@mail.example | D12: Sorting | E12: =IF(B12="","",SUMIFS(Hours!$D$6:$D$1005,Hours!$C$6:$C$1005,B12,Hours!$I$6:$I$1005,Settings!$C$7,Hours!$D$6:$D$1005,">0")) | F12: =IF(B12="","",SUMIFS(Hours!$D$6:$D$1005,Hours!$C$6:$C$1005,B12,Hours!$D$6:$D$1005,">0",Hours!$K$6:$K$1005,">0")) | G12: =IF(OR(B12="",N(F12)=0),"",SUMPRODUCT(MAX((Hours!$C$6:$C$1005=B12)*Hours!$L$6:$L$1005))) | H12: =IF(B12="","",COUNTIFS(Hours!$C$6:$C$1005,B12,Hours!$I$6:$I$1005,Settings!$C$7,Hours!$D$6:$D$1005,">0"))
B13: Olga Novak | C13: olga@mail.example | D13: Kitchen | E13: =IF(B13="","",SUMIFS(Hours!$D$6:$D$1005,Hours!$C$6:$C$1005,B13,Hours!$I$6:$I$1005,Settings!$C$7,Hours!$D$6:$D$1005,">0")) | F13: =IF(B13="","",SUMIFS(Hours!$D$6:$D$1005,Hours!$C$6:$C$1005,B13,Hours!$D$6:$D$1005,">0",Hours!$K$6:$K$1005,">0")) | G13: =IF(OR(B13="",N(F13)=0),"",SUMPRODUCT(MAX((Hours!$C$6:$C$1005=B13)*Hours!$L$6:$L$1005))) | H13: =IF(B13="","",COUNTIFS(Hours!$C$6:$C$1005,B13,Hours!$I$6:$I$1005,Settings!$C$7,Hours!$D$6:$D$1005,">0"))
E14: =IF(B14="","",SUMIFS(Hours!$D$6:$D$1005,Hours!$C$6:$C$1005,B14,Hours!$I$6:$I$1005,Settings!$C$7,Hours!$D$6:$D$1005,">0")) | F14: =IF(B14="","",SUMIFS(Hours!$D$6:$D$1005,Hours!$C$6:$C$1005,B14,Hours!$D$6:$D$1005,">0",Hours!$K$6:$K$1005,">0")) | G14: =IF(OR(B14="",N(F14)=0),"",SUMPRODUCT(MAX((Hours!$C$6:$C$1005=B14)*Hours!$L$6:$L$1005))) | H14: =IF(B14="","",COUNTIFS(Hours!$C$6:$C$1005,B14,Hours!$I$6:$I$1005,Settings!$C$7,Hours!$D$6:$D$1005,">0"))
E15: =IF(B15="","",SUMIFS(Hours!$D$6:$D$1005,Hours!$C$6:$C$1005,B15,Hours!$I$6:$I$1005,Settings!$C$7,Hours!$D$6:$D$1005,">0")) | F15: =IF(B15="","",SUMIFS(Hours!$D$6:$D$1005,Hours!$C$6:$C$1005,B15,Hours!$D$6:$D$1005,">0",Hours!$K$6:$K$1005,">0")) | G15: =IF(OR(B15="",N(F15)=0),"",SUMPRODUCT(MAX((Hours!$C$6:$C$1005=B15)*Hours!$L$6:$L$1005))) | H15: =IF(B15="","",COUNTIFS(Hours!$C$6:$C$1005,B15,Hours!$I$6:$I$1005,Settings!$C$7,Hours!$D$6:$D$1005,">0"))
E16: =IF(B16="","",SUMIFS(Hours!$D$6:$D$1005,Hours!$C$6:$C$1005,B16,Hours!$I$6:$I$1005,Settings!$C$7,Hours!$D$6:$D$1005,">0")) | F16: =IF(B16="","",SUMIFS(Hours!$D$6:$D$1005,Hours!$C$6:$C$1005,B16,Hours!$D$6:$D$1005,">0",Hours!$K$6:$K$1005,">0")) | G16: =IF(OR(B16="",N(F16)=0),"",SUMPRODUCT(MAX((Hours!$C$6:$C$1005=B16)*Hours!$L$6:$L$1005))) | H16: =IF(B16="","",COUNTIFS(Hours!$C$6:$C$1005,B16,Hours!$I$6:$I$1005,Settings!$C$7,Hours!$D$6:$D$1005,">0"))
E17: =IF(B17="","",SUMIFS(Hours!$D$6:$D$1005,Hours!$C$6:$C$1005,B17,Hours!$I$6:$I$1005,Settings!$C$7,Hours!$D$6:$D$1005,">0")) | F17: =IF(B17="","",SUMIFS(Hours!$D$6:$D$1005,Hours!$C$6:$C$1005,B17,Hours!$D$6:$D$1005,">0",Hours!$K$6:$K$1005,">0")) | G17: =IF(OR(B17="",N(F17)=0),"",SUMPRODUCT(MAX((Hours!$C$6:$C$1005=B17)*Hours!$L$6:$L$1005))) | H17: =IF(B17="","",COUNTIFS(Hours!$C$6:$C$1005,B17,Hours!$I$6:$I$1005,Settings!$C$7,Hours!$D$6:$D$1005,">0"))
E18: =IF(B18="","",SUMIFS(Hours!$D$6:$D$1005,Hours!$C$6:$C$1005,B18,Hours!$I$6:$I$1005,Settings!$C$7,Hours!$D$6:$D$1005,">0")) | F18: =IF(B18="","",SUMIFS(Hours!$D$6:$D$1005,Hours!$C$6:$C$1005,B18,Hours!$D$6:$D$1005,">0",Hours!$K$6:$K$1005,">0")) | G18: =IF(OR(B18="",N(F18)=0),"",SUMPRODUCT(MAX((Hours!$C$6:$C$1005=B18)*Hours!$L$6:$L$1005))) | H18: =IF(B18="","",COUNTIFS(Hours!$C$6:$C$1005,B18,Hours!$I$6:$I$1005,Settings!$C$7,Hours!$D$6:$D$1005,">0"))
E19: =IF(B19="","",SUMIFS(Hours!$D$6:$D$1005,Hours!$C$6:$C$1005,B19,Hours!$I$6:$I$1005,Settings!$C$7,Hours!$D$6:$D$1005,">0")) | F19: =IF(B19="","",SUMIFS(Hours!$D$6:$D$1005,Hours!$C$6:$C$1005,B19,Hours!$D$6:$D$1005,">0",Hours!$K$6:$K$1005,">0")) | G19: =IF(OR(B19="",N(F19)=0),"",SUMPRODUCT(MAX((Hours!$C$6:$C$1005=B19)*Hours!$L$6:$L$1005))) | H19: =IF(B19="","",COUNTIFS(Hours!$C$6:$C$1005,B19,Hours!$I$6:$I$1005,Settings!$C$7,Hours!$D$6:$D$1005,">0"))
E20: =IF(B20="","",SUMIFS(Hours!$D$6:$D$1005,Hours!$C$6:$C$1005,B20,Hours!$I$6:$I$1005,Settings!$C$7,Hours!$D$6:$D$1005,">0")) | F20: =IF(B20="","",SUMIFS(Hours!$D$6:$D$1005,Hours!$C$6:$C$1005,B20,Hours!$D$6:$D$1005,">0",Hours!$K$6:$K$1005,">0")) | G20: =IF(OR(B20="",N(F20)=0),"",SUMPRODUCT(MAX((Hours!$C$6:$C$1005=B20)*Hours!$L$6:$L$1005))) | H20: =IF(B20="","",COUNTIFS(Hours!$C$6:$C$1005,B20,Hours!$I$6:$I$1005,Settings!$C$7,Hours!$D$6:$D$1005,">0"))
E21: =IF(B21="","",SUMIFS(Hours!$D$6:$D$1005,Hours!$C$6:$C$1005,B21,Hours!$I$6:$I$1005,Settings!$C$7,Hours!$D$6:$D$1005,">0")) | F21: =IF(B21="","",SUMIFS(Hours!$D$6:$D$1005,Hours!$C$6:$C$1005,B21,Hours!$D$6:$D$1005,">0",Hours!$K$6:$K$1005,">0")) | G21: =IF(OR(B21="",N(F21)=0),"",SUMPRODUCT(MAX((Hours!$C$6:$C$1005=B21)*Hours!$L$6:$L$1005))) | H21: =IF(B21="","",COUNTIFS(Hours!$C$6:$C$1005,B21,Hours!$I$6:$I$1005,Settings!$C$7,Hours!$D$6:$D$1005,">0"))
E22: =IF(B22="","",SUMIFS(Hours!$D$6:$D$1005,Hours!$C$6:$C$1005,B22,Hours!$I$6:$I$1005,Settings!$C$7,Hours!$D$6:$D$1005,">0")) | F22: =IF(B22="","",SUMIFS(Hours!$D$6:$D$1005,Hours!$C$6:$C$1005,B22,Hours!$D$6:$D$1005,">0",Hours!$K$6:$K$1005,">0")) | G22: =IF(OR(B22="",N(F22)=0),"",SUMPRODUCT(MAX((Hours!$C$6:$C$1005=B22)*Hours!$L$6:$L$1005))) | H22: =IF(B22="","",COUNTIFS(Hours!$C$6:$C$1005,B22,Hours!$I$6:$I$1005,Settings!$C$7,Hours!$D$6:$D$1005,">0"))
E23: =IF(B23="","",SUMIFS(Hours!$D$6:$D$1005,Hours!$C$6:$C$1005,B23,Hours!$I$6:$I$1005,Settings!$C$7,Hours!$D$6:$D$1005,">0")) | F23: =IF(B23="","",SUMIFS(Hours!$D$6:$D$1005,Hours!$C$6:$C$1005,B23,Hours!$D$6:$D$1005,">0",Hours!$K$6:$K$1005,">0")) | G23: =IF(OR(B23="",N(F23)=0),"",SUMPRODUCT(MAX((Hours!$C$6:$C$1005=B23)*Hours!$L$6:$L$1005))) | H23: =IF(B23="","",COUNTIFS(Hours!$C$6:$C$1005,B23,Hours!$I$6:$I$1005,Settings!$C$7,Hours!$D$6:$D$1005,">0"))
E24: =IF(B24="","",SUMIFS(Hours!$D$6:$D$1005,Hours!$C$6:$C$1005,B24,Hours!$I$6:$I$1005,Settings!$C$7,Hours!$D$6:$D$1005,">0")) | F24: =IF(B24="","",SUMIFS(Hours!$D$6:$D$1005,Hours!$C$6:$C$1005,B24,Hours!$D$6:$D$1005,">0",Hours!$K$6:$K$1005,">0")) | G24: =IF(OR(B24="",N(F24)=0),"",SUMPRODUCT(MAX((Hours!$C$6:$C$1005=B24)*Hours!$L$6:$L$1005))) | H24: =IF(B24="","",COUNTIFS(Hours!$C$6:$C$1005,B24,Hours!$I$6:$I$1005,Settings!$C$7,Hours!$D$6:$D$1005,">0"))
E25: =IF(B25="","",SUMIFS(Hours!$D$6:$D$1005,Hours!$C$6:$C$1005,B25,Hours!$I$6:$I$1005,Settings!$C$7,Hours!$D$6:$D$1005,">0")) | F25: =IF(B25="","",SUMIFS(Hours!$D$6:$D$1005,Hours!$C$6:$C$1005,B25,Hours!$D$6:$D$1005,">0",Hours!$K$6:$K$1005,">0")) | G25: =IF(OR(B25="",N(F25)=0),"",SUMPRODUCT(MAX((Hours!$C$6:$C$1005=B25)*Hours!$L$6:$L$1005))) | H25: =IF(B25="","",COUNTIFS(Hours!$C$6:$C$1005,B25,Hours!$I$6:$I$1005,Settings!$C$7,Hours!$D$6:$D$1005,">0"))
... E105: =IF(B105="","",SUMIFS(Hours!$D$6:$D$1005,Hours!$C$6:$C$1005,B105,Hours!$I$6:$I$1005,Settings!$C$7,Hours!$D$6:$D$1005,">0")) | F105: =IF(B105="","",SUMIFS(Hours!$D$6:$D$1005,Hours!$C$6:$C$1005,B105,Hours!$D$6:$D$1005,">0",Hours!$K$6:$K$1005,">0")) | G105: =IF(OR(B105="",N(F105)=0),"",SUMPRODUCT(MAX((Hours!$C$6:$C$1005=B105)*Hours!$L$6:$L$1005))) | H105: =IF(B105="","",COUNTIFS(Hours!$C$6:$C$1005,B105,Hours!$I$6:$I$1005,Settings!$C$7,Hours!$D$6:$D$1005,">0"))

Sheet Hours
B2: Hours
B3: Each time someone helps, with the hours as a number: 2.5 for two and a half.
B5: Date | C5: Volunteer | D5: Hours | E5: What | F5: Note | G5: Check
B6: 46018 | C6: Sam Reid | D6: 2.5 | E6: Front desk | G6: =IF(AND(C6="",D6=""),"",IF(NOT(ISNUMBER(B6)),"Needs a date",IF(AND(D6<>"",NOT(ISNUMBER(D6))),"Hours not a number",IF(N(D6)<=0,"Needs the hours",IF(C6="","Needs a name",IF(COUNTIF(Volunteers!$B$6:$B$105,C6)=0,"Not on Volunteers","")))))) | I6: =IF(ISNUMBER(B6),YEAR(B6),"") | J6: =IF(ISNUMBER(B6),YEAR(B6)*100+MONTH(B6),"") | K6: =IF(ISNUMBER(B6),INT(B6),0) | L6: =IF(AND(ISNUMBER(D6),N(D6)>0),K6,0)
B7: 46025 | C7: Peter Olsen | D7: 3 | E7: Front desk | G7: =IF(AND(C7="",D7=""),"",IF(NOT(ISNUMBER(B7)),"Needs a date",IF(AND(D7<>"",NOT(ISNUMBER(D7))),"Hours not a number",IF(N(D7)<=0,"Needs the hours",IF(C7="","Needs a name",IF(COUNTIF(Volunteers!$B$6:$B$105,C7)=0,"Not on Volunteers","")))))) | I7: =IF(ISNUMBER(B7),YEAR(B7),"") | J7: =IF(ISNUMBER(B7),YEAR(B7)*100+MONTH(B7),"") | K7: =IF(ISNUMBER(B7),INT(B7),0) | L7: =IF(AND(ISNUMBER(D7),N(D7)>0),K7,0)
B8: 46025 | C8: Beth Morgan | D8: 2.5 | E8: Deliveries | G8: =IF(AND(C8="",D8=""),"",IF(NOT(ISNUMBER(B8)),"Needs a date",IF(AND(D8<>"",NOT(ISNUMBER(D8))),"Hours not a number",IF(N(D8)<=0,"Needs the hours",IF(C8="","Needs a name",IF(COUNTIF(Volunteers!$B$6:$B$105,C8)=0,"Not on Volunteers","")))))) | I8: =IF(ISNUMBER(B8),YEAR(B8),"") | J8: =IF(ISNUMBER(B8),YEAR(B8)*100+MONTH(B8),"") | K8: =IF(ISNUMBER(B8),INT(B8),0) | L8: =IF(AND(ISNUMBER(D8),N(D8)>0),K8,0)
B9: 46025 | C9: Sam Reid | D9: 3 | E9: Sorting day | G9: =IF(AND(C9="",D9=""),"",IF(NOT(ISNUMBER(B9)),"Needs a date",IF(AND(D9<>"",NOT(ISNUMBER(D9))),"Hours not a number",IF(N(D9)<=0,"Needs the hours",IF(C9="","Needs a name",IF(COUNTIF(Volunteers!$B$6:$B$105,C9)=0,"Not on Volunteers","")))))) | I9: =IF(ISNUMBER(B9),YEAR(B9),"") | J9: =IF(ISNUMBER(B9),YEAR(B9)*100+MONTH(B9),"") | K9: =IF(ISNUMBER(B9),INT(B9),0) | L9: =IF(AND(ISNUMBER(D9),N(D9)>0),K9,0)
B10: 46025 | C10: Olga Novak | D10: 2 | E10: Sorting day | G10: =IF(AND(C10="",D10=""),"",IF(NOT(ISNUMBER(B10)),"Needs a date",IF(AND(D10<>"",NOT(ISNUMBER(D10))),"Hours not a number",IF(N(D10)<=0,"Needs the hours",IF(C10="","Needs a name",IF(COUNTIF(Volunteers!$B$6:$B$105,C10)=0,"Not on Volunteers","")))))) | I10: =IF(ISNUMBER(B10),YEAR(B10),"") | J10: =IF(ISNUMBER(B10),YEAR(B10)*100+MONTH(B10),"") | K10: =IF(ISNUMBER(B10),INT(B10),0) | L10: =IF(AND(ISNUMBER(D10),N(D10)>0),K10,0)
B11: 46032 | C11: Mark Evans | D11: 2.5 | E11: Saturday market | G11: =IF(AND(C11="",D11=""),"",IF(NOT(ISNUMBER(B11)),"Needs a date",IF(AND(D11<>"",NOT(ISNUMBER(D11))),"Hours not a number",IF(N(D11)<=0,"Needs the hours",IF(C11="","Needs a name",IF(COUNTIF(Volunteers!$B$6:$B$105,C11)=0,"Not on Volunteers","")))))) | I11: =IF(ISNUMBER(B11),YEAR(B11),"") | J11: =IF(ISNUMBER(B11),YEAR(B11)*100+MONTH(B11),"") | K11: =IF(ISNUMBER(B11),INT(B11),0) | L11: =IF(AND(ISNUMBER(D11),N(D11)>0),K11,0)
B12: 46032 | C12: Peter Olsen | D12: 3 | E12: Front desk | G12: =IF(AND(C12="",D12=""),"",IF(NOT(ISNUMBER(B12)),"Needs a date",IF(AND(D12<>"",NOT(ISNUMBER(D12))),"Hours not a number",IF(N(D12)<=0,"Needs the hours",IF(C12="","Needs a name",IF(COUNTIF(Volunteers!$B$6:$B$105,C12)=0,"Not on Volunteers","")))))) | I12: =IF(ISNUMBER(B12),YEAR(B12),"") | J12: =IF(ISNUMBER(B12),YEAR(B12)*100+MONTH(B12),"") | K12: =IF(ISNUMBER(B12),INT(B12),0) | L12: =IF(AND(ISNUMBER(D12),N(D12)>0),K12,0)
B13: 46032 | C13: Joe Ward | D13: 4 | E13: Saturday market | G13: =IF(AND(C13="",D13=""),"",IF(NOT(ISNUMBER(B13)),"Needs a date",IF(AND(D13<>"",NOT(ISNUMBER(D13))),"Hours not a number",IF(N(D13)<=0,"Needs the hours",IF(C13="","Needs a name",IF(COUNTIF(Volunteers!$B$6:$B$105,C13)=0,"Not on Volunteers","")))))) | I13: =IF(ISNUMBER(B13),YEAR(B13),"") | J13: =IF(ISNUMBER(B13),YEAR(B13)*100+MONTH(B13),"") | K13: =IF(ISNUMBER(B13),INT(B13),0) | L13: =IF(AND(ISNUMBER(D13),N(D13)>0),K13,0)
B14: 46032 | C14: Beth Morgan | D14: 2.5 | E14: Deliveries | G14: =IF(AND(C14="",D14=""),"",IF(NOT(ISNUMBER(B14)),"Needs a date",IF(AND(D14<>"",NOT(ISNUMBER(D14))),"Hours not a number",IF(N(D14)<=0,"Needs the hours",IF(C14="","Needs a name",IF(COUNTIF(Volunteers!$B$6:$B$105,C14)=0,"Not on Volunteers","")))))) | I14: =IF(ISNUMBER(B14),YEAR(B14),"") | J14: =IF(ISNUMBER(B14),YEAR(B14)*100+MONTH(B14),"") | K14: =IF(ISNUMBER(B14),INT(B14),0) | L14: =IF(AND(ISNUMBER(D14),N(D14)>0),K14,0)
B15: 46039 | C15: Lucy Chen | D15: 4 | E15: Sorting day | G15: =IF(AND(C15="",D15=""),"",IF(NOT(ISNUMBER(B15)),"Needs a date",IF(AND(D15<>"",NOT(ISNUMBER(D15))),"Hours not a number",IF(N(D15)<=0,"Needs the hours",IF(C15="","Needs a name",IF(COUNTIF(Volunteers!$B$6:$B$105,C15)=0,"Not on Volunteers","")))))) | I15: =IF(ISNUMBER(B15),YEAR(B15),"") | J15: =IF(ISNUMBER(B15),YEAR(B15)*100+MONTH(B15),"") | K15: =IF(ISNUMBER(B15),INT(B15),0) | L15: =IF(AND(ISNUMBER(D15),N(D15)>0),K15,0)
B16: 46039 | C16: Joe Ward | D16: 2 | E16: Sorting day | G16: =IF(AND(C16="",D16=""),"",IF(NOT(ISNUMBER(B16)),"Needs a date",IF(AND(D16<>"",NOT(ISNUMBER(D16))),"Hours not a number",IF(N(D16)<=0,"Needs the hours",IF(C16="","Needs a name",IF(COUNTIF(Volunteers!$B$6:$B$105,C16)=0,"Not on Volunteers","")))))) | I16: =IF(ISNUMBER(B16),YEAR(B16),"") | J16: =IF(ISNUMBER(B16),YEAR(B16)*100+MONTH(B16),"") | K16: =IF(ISNUMBER(B16),INT(B16),0) | L16: =IF(AND(ISNUMBER(D16),N(D16)>0),K16,0)
B17: 46039 | C17: Beth Morgan | D17: 2.5 | E17: Front desk | G17: =IF(AND(C17="",D17=""),"",IF(NOT(ISNUMBER(B17)),"Needs a date",IF(AND(D17<>"",NOT(ISNUMBER(D17))),"Hours not a number",IF(N(D17)<=0,"Needs the hours",IF(C17="","Needs a name",IF(COUNTIF(Volunteers!$B$6:$B$105,C17)=0,"Not on Volunteers","")))))) | I17: =IF(ISNUMBER(B17),YEAR(B17),"") | J17: =IF(ISNUMBER(B17),YEAR(B17)*100+MONTH(B17),"") | K17: =IF(ISNUMBER(B17),INT(B17),0) | L17: =IF(AND(ISNUMBER(D17),N(D17)>0),K17,0)
... B123: 46291 | C123: Lucy Chen | D123: 2.5 | E123: Front desk | G123: =IF(AND(C123="",D123=""),"",IF(NOT(ISNUMBER(B123)),"Needs a date",IF(AND(D123<>"",NOT(ISNUMBER(D123))),"Hours not a number",IF(N(D123)<=0,"Needs the hours",IF(C123="","Needs a name",IF(COUNTIF(Volunteers!$B$6:$B$105,C123)=0,"Not on Volunteers","")))))) | I123: =IF(ISNUMBER(B123),YEAR(B123),"") | J123: =IF(ISNUMBER(B123),YEAR(B123)*100+MONTH(B123),"") | K123: =IF(ISNUMBER(B123),INT(B123),0) | L123: =IF(AND(ISNUMBER(D123),N(D123)>0),K123,0)
G124: =IF(AND(C124="",D124=""),"",IF(NOT(ISNUMBER(B124)),"Needs a date",IF(AND(D124<>"",NOT(ISNUMBER(D124))),"Hours not a number",IF(N(D124)<=0,"Needs the hours",IF(C124="","Needs a name",IF(COUNTIF(Volunteers!$B$6:$B$105,C124)=0,"Not on Volunteers","")))))) | I124: =IF(ISNUMBER(B124),YEAR(B124),"") | J124: =IF(ISNUMBER(B124),YEAR(B124)*100+MONTH(B124),"") | K124: =IF(ISNUMBER(B124),INT(B124),0) | L124: =IF(AND(ISNUMBER(D124),N(D124)>0),K124,0)
G125: =IF(AND(C125="",D125=""),"",IF(NOT(ISNUMBER(B125)),"Needs a date",IF(AND(D125<>"",NOT(ISNUMBER(D125))),"Hours not a number",IF(N(D125)<=0,"Needs the hours",IF(C125="","Needs a name",IF(COUNTIF(Volunteers!$B$6:$B$105,C125)=0,"Not on Volunteers","")))))) | I125: =IF(ISNUMBER(B125),YEAR(B125),"") | J125: =IF(ISNUMBER(B125),YEAR(B125)*100+MONTH(B125),"") | K125: =IF(ISNUMBER(B125),INT(B125),0) | L125: =IF(AND(ISNUMBER(D125),N(D125)>0),K125,0)
G126: =IF(AND(C126="",D126=""),"",IF(NOT(ISNUMBER(B126)),"Needs a date",IF(AND(D126<>"",NOT(ISNUMBER(D126))),"Hours not a number",IF(N(D126)<=0,"Needs the hours",IF(C126="","Needs a name",IF(COUNTIF(Volunteers!$B$6:$B$105,C126)=0,"Not on Volunteers","")))))) | I126: =IF(ISNUMBER(B126),YEAR(B126),"") | J126: =IF(ISNUMBER(B126),YEAR(B126)*100+MONTH(B126),"") | K126: =IF(ISNUMBER(B126),INT(B126),0) | L126: =IF(AND(ISNUMBER(D126),N(D126)>0),K126,0)
G127: =IF(AND(C127="",D127=""),"",IF(NOT(ISNUMBER(B127)),"Needs a date",IF(AND(D127<>"",NOT(ISNUMBER(D127))),"Hours not a number",IF(N(D127)<=0,"Needs the hours",IF(C127="","Needs a name",IF(COUNTIF(Volunteers!$B$6:$B$105,C127)=0,"Not on Volunteers","")))))) | I127: =IF(ISNUMBER(B127),YEAR(B127),"") | J127: =IF(ISNUMBER(B127),YEAR(B127)*100+MONTH(B127),"") | K127: =IF(ISNUMBER(B127),INT(B127),0) | L127: =IF(AND(ISNUMBER(D127),N(D127)>0),K127,0)
G128: =IF(AND(C128="",D128=""),"",IF(NOT(ISNUMBER(B128)),"Needs a date",IF(AND(D128<>"",NOT(ISNUMBER(D128))),"Hours not a number",IF(N(D128)<=0,"Needs the hours",IF(C128="","Needs a name",IF(COUNTIF(Volunteers!$B$6:$B$105,C128)=0,"Not on Volunteers","")))))) | I128: =IF(ISNUMBER(B128),YEAR(B128),"") | J128: =IF(ISNUMBER(B128),YEAR(B128)*100+MONTH(B128),"") | K128: =IF(ISNUMBER(B128),INT(B128),0) | L128: =IF(AND(ISNUMBER(D128),N(D128)>0),K128,0)
G129: =IF(AND(C129="",D129=""),"",IF(NOT(ISNUMBER(B129)),"Needs a date",IF(AND(D129<>"",NOT(ISNUMBER(D129))),"Hours not a number",IF(N(D129)<=0,"Needs the hours",IF(C129="","Needs a name",IF(COUNTIF(Volunteers!$B$6:$B$105,C129)=0,"Not on Volunteers","")))))) | I129: =IF(ISNUMBER(B129),YEAR(B129),"") | J129: =IF(ISNUMBER(B129),YEAR(B129)*100+MONTH(B129),"") | K129: =IF(ISNUMBER(B129),INT(B129),0) | L129: =IF(AND(ISNUMBER(D129),N(D129)>0),K129,0)
G130: =IF(AND(C130="",D130=""),"",IF(NOT(ISNUMBER(B130)),"Needs a date",IF(AND(D130<>"",NOT(ISNUMBER(D130))),"Hours not a number",IF(N(D130)<=0,"Needs the hours",IF(C130="","Needs a name",IF(COUNTIF(Volunteers!$B$6:$B$105,C130)=0,"Not on Volunteers","")))))) | I130: =IF(ISNUMBER(B130),YEAR(B130),"") | J130: =IF(ISNUMBER(B130),YEAR(B130)*100+MONTH(B130),"") | K130: =IF(ISNUMBER(B130),INT(B130),0) | L130: =IF(AND(ISNUMBER(D130),N(D130)>0),K130,0)
G131: =IF(AND(C131="",D131=""),"",IF(NOT(ISNUMBER(B131)),"Needs a date",IF(AND(D131<>"",NOT(ISNUMBER(D131))),"Hours not a number",IF(N(D131)<=0,"Needs the hours",IF(C131="","Needs a name",IF(COUNTIF(Volunteers!$B$6:$B$105,C131)=0,"Not on Volunteers","")))))) | I131: =IF(ISNUMBER(B131),YEAR(B131),"") | J131: =IF(ISNUMBER(B131),YEAR(B131)*100+MONTH(B131),"") | K131: =IF(ISNUMBER(B131),INT(B131),0) | L131: =IF(AND(ISNUMBER(D131),N(D131)>0),K131,0)
G132: =IF(AND(C132="",D132=""),"",IF(NOT(ISNUMBER(B132)),"Needs a date",IF(AND(D132<>"",NOT(ISNUMBER(D132))),"Hours not a number",IF(N(D132)<=0,"Needs the hours",IF(C132="","Needs a name",IF(COUNTIF(Volunteers!$B$6:$B$105,C132)=0,"Not on Volunteers","")))))) | I132: =IF(ISNUMBER(B132),YEAR(B132),"") | J132: =IF(ISNUMBER(B132),YEAR(B132)*100+MONTH(B132),"") | K132: =IF(ISNUMBER(B132),INT(B132),0) | L132: =IF(AND(ISNUMBER(D132),N(D132)>0),K132,0)
G133: =IF(AND(C133="",D133=""),"",IF(NOT(ISNUMBER(B133)),"Needs a date",IF(AND(D133<>"",NOT(ISNUMBER(D133))),"Hours not a number",IF(N(D133)<=0,"Needs the hours",IF(C133="","Needs a name",IF(COUNTIF(Volunteers!$B$6:$B$105,C133)=0,"Not on Volunteers","")))))) | I133: =IF(ISNUMBER(B133),YEAR(B133),"") | J133: =IF(ISNUMBER(B133),YEAR(B133)*100+MONTH(B133),"") | K133: =IF(ISNUMBER(B133),INT(B133),0) | L133: =IF(AND(ISNUMBER(D133),N(D133)>0),K133,0)
G134: =IF(AND(C134="",D134=""),"",IF(NOT(ISNUMBER(B134)),"Needs a date",IF(AND(D134<>"",NOT(ISNUMBER(D134))),"Hours not a number",IF(N(D134)<=0,"Needs the hours",IF(C134="","Needs a name",IF(COUNTIF(Volunteers!$B$6:$B$105,C134)=0,"Not on Volunteers","")))))) | I134: =IF(ISNUMBER(B134),YEAR(B134),"") | J134: =IF(ISNUMBER(B134),YEAR(B134)*100+MONTH(B134),"") | K134: =IF(ISNUMBER(B134),INT(B134),0) | L134: =IF(AND(ISNUMBER(D134),N(D134)>0),K134,0)
G135: =IF(AND(C135="",D135=""),"",IF(NOT(ISNUMBER(B135)),"Needs a date",IF(AND(D135<>"",NOT(ISNUMBER(D135))),"Hours not a number",IF(N(D135)<=0,"Needs the hours",IF(C135="","Needs a name",IF(COUNTIF(Volunteers!$B$6:$B$105,C135)=0,"Not on Volunteers","")))))) | I135: =IF(ISNUMBER(B135),YEAR(B135),"") | J135: =IF(ISNUMBER(B135),YEAR(B135)*100+MONTH(B135),"") | K135: =IF(ISNUMBER(B135),INT(B135),0) | L135: =IF(AND(ISNUMBER(D135),N(D135)>0),K135,0)
... G1005: =IF(AND(C1005="",D1005=""),"",IF(NOT(ISNUMBER(B1005)),"Needs a date",IF(AND(D1005<>"",NOT(ISNUMBER(D1005))),"Hours not a number",IF(N(D1005)<=0,"Needs the hours",IF(C1005="","Needs a name",IF(COUNTIF(Volunteers!$B$6:$B$105,C1005)=0,"Not on Volunteers","")))))) | I1005: =IF(ISNUMBER(B1005),YEAR(B1005),"") | J1005: =IF(ISNUMBER(B1005),YEAR(B1005)*100+MONTH(B1005),"") | K1005: =IF(ISNUMBER(B1005),INT(B1005),0) | L1005: =IF(AND(ISNUMBER(D1005),N(D1005)>0),K1005,0)

Sheet Settings
B2: Settings
B3: Your organisation for the statements, the year shown, and when a donor counts as lapsed.
B4: Organisation | C4: Riverton Community Pantry | E4: At the top of each statement.
B5: Address | C5: 10 Church Lane, Riverton | E5: Under the name.
B6: Line at the end of each statement | C6: Thank you for your support. This statement lists the gifts we received from you. Please keep it for your records. | E6: Add your charity number or anything your rules ask for.
B7: Year | C7: =YEAR(TODAY()) | E7: The year on the Dashboard and the statements. Type another to look back.
B8: Currency | C8: USD | E8: Shown on the statements.
B9: Lapsed after (months) | C9: 12 | E9: A donor with no gift for this long counts as lapsed.

Sheet Start Here
B2: Start here
B3: Type only in the yellow cells.
B5: 1 | C5: Settings: your organisation's name and address, and the line at the end of each statement.
B7: 2 | C7: Donors and Campaigns: each donor once, and what you raise money for, with a goal if it has one.
B9: 3 | C9: Gifts: every gift with its donor and campaign. For goods, leave the amount empty and say what was given. An x under Thanked once you have said thank you.
B11: 4 | C11: Volunteers and Hours: each volunteer once, then each time they help, with the hours.
B13: 5 | C13: Statement: pick a donor and a year to print the list of their gifts.
C16: The example pantry, its donors and volunteers are made up. Delete them and add your own.
C18: The statement lists the gifts. Whether they can be claimed on taxes depends on the rules where you are.
C20: Works in Google Sheets and Microsoft Excel, in any currency.
