Workbook

Sheet Dashboard
M1: =MAX(Balances!E50:AN50)
B2: Net worth and passive income | M2: =IF(M1=0,"",EDATE(Settings!$C$5,M1-1))
B3: =IF(M1=0,"Type the balances on Balances.","Balances at the end of "&CHOOSE(MONTH(M2),"Jan","Feb","Mar","Apr","May","Jun","Jul","Aug","Sep","Oct","Nov","Dec")&" "&YEAR(M2)&"; income over the last 12 months.")
B4: Net worth | C4: On last month | D4: Assets | E4: Debts | G4: Income, 12 months | H4: A month on average | I4: Goal a month | J4: Of the goal
B5: =IF($M$1=0,"",IF(OR($M$1<1,$M$1>36),"",INDEX(Balances!$E$49:$AN$49,$M$1))) | C5: =IF($M$1<2,"",IF(OR(IF(OR($M$1-1<1,$M$1-1>36),"",INDEX(Balances!$E$49:$AN$49,$M$1-1))=""),"",IF(OR($M$1<1,$M$1>36),"",INDEX(Balances!$E$49:$AN$49,$M$1))-IF(OR($M$1-1<1,$M$1-1>36),"",INDEX(Balances!$E$49:$AN$49,$M$1-1)))) | D5: =IF($M$1=0,"",IF(OR($M$1<1,$M$1>36),"",INDEX(Balances!$E$47:$AN$47,$M$1))) | E5: =IF($M$1=0,"",IF(OR($M$1<1,$M$1>36),"",INDEX(Balances!$E$48:$AN$48,$M$1))) | G5: =SUM(J9:J20) | H5: =G5/12 | I5: =N(Settings!$C$6) | J5: =IF(N(Settings!$C$6)<=0,"",H5/Settings!$C$6)
B8: Month | C8: Assets | D8: Debts | E8: Net worth | G8: Month | H8: Dividends | I8: Other income | J8: Total
B9: =IF(N9="","",CHOOSE(MONTH(EDATE(Settings!$C$5,N9-1)),"Jan","Feb","Mar","Apr","May","Jun","Jul","Aug","Sep","Oct","Nov","Dec")&" "&YEAR(EDATE(Settings!$C$5,N9-1))) | C9: =IF(N9="","",IF(OR(N9<1,N9>36),"",INDEX(Balances!$E$47:$AN$47,N9))) | D9: =IF(N9="","",IF(OR(N9<1,N9>36),"",INDEX(Balances!$E$48:$AN$48,N9))) | E9: =IF(N9="","",IF(OR(N9<1,N9>36),"",INDEX(Balances!$E$49:$AN$49,N9))) | G9: =CHOOSE(MONTH(DATE(YEAR(TODAY()),MONTH(TODAY())-11,1)),"Jan","Feb","Mar","Apr","May","Jun","Jul","Aug","Sep","Oct","Nov","Dec")&" "&YEAR(DATE(YEAR(TODAY()),MONTH(TODAY())-11,1)) | H9: =SUMIFS(Income!$E$6:$E$1005,Income!$D$6:$D$1005,"Dividend",Income!$G$6:$G$1005,P9) | I9: =J9-H9 | J9: =SUMIFS(Income!$E$6:$E$1005,Income!$G$6:$G$1005,P9) | N9: =IF(OR($M$1=0,($M$1-11)<1),"",($M$1-11)) | O9: =IF(ISNUMBER(E9),E9,NA()) | P9: =YEAR(DATE(YEAR(TODAY()),MONTH(TODAY())-11,1))*100+MONTH(DATE(YEAR(TODAY()),MONTH(TODAY())-11,1))
B10: =IF(N10="","",CHOOSE(MONTH(EDATE(Settings!$C$5,N10-1)),"Jan","Feb","Mar","Apr","May","Jun","Jul","Aug","Sep","Oct","Nov","Dec")&" "&YEAR(EDATE(Settings!$C$5,N10-1))) | C10: =IF(N10="","",IF(OR(N10<1,N10>36),"",INDEX(Balances!$E$47:$AN$47,N10))) | D10: =IF(N10="","",IF(OR(N10<1,N10>36),"",INDEX(Balances!$E$48:$AN$48,N10))) | E10: =IF(N10="","",IF(OR(N10<1,N10>36),"",INDEX(Balances!$E$49:$AN$49,N10))) | G10: =CHOOSE(MONTH(DATE(YEAR(TODAY()),MONTH(TODAY())-10,1)),"Jan","Feb","Mar","Apr","May","Jun","Jul","Aug","Sep","Oct","Nov","Dec")&" "&YEAR(DATE(YEAR(TODAY()),MONTH(TODAY())-10,1)) | H10: =SUMIFS(Income!$E$6:$E$1005,Income!$D$6:$D$1005,"Dividend",Income!$G$6:$G$1005,P10) | I10: =J10-H10 | J10: =SUMIFS(Income!$E$6:$E$1005,Income!$G$6:$G$1005,P10) | N10: =IF(OR($M$1=0,($M$1-10)<1),"",($M$1-10)) | O10: =IF(ISNUMBER(E10),E10,NA()) | P10: =YEAR(DATE(YEAR(TODAY()),MONTH(TODAY())-10,1))*100+MONTH(DATE(YEAR(TODAY()),MONTH(TODAY())-10,1))
B11: =IF(N11="","",CHOOSE(MONTH(EDATE(Settings!$C$5,N11-1)),"Jan","Feb","Mar","Apr","May","Jun","Jul","Aug","Sep","Oct","Nov","Dec")&" "&YEAR(EDATE(Settings!$C$5,N11-1))) | C11: =IF(N11="","",IF(OR(N11<1,N11>36),"",INDEX(Balances!$E$47:$AN$47,N11))) | D11: =IF(N11="","",IF(OR(N11<1,N11>36),"",INDEX(Balances!$E$48:$AN$48,N11))) | E11: =IF(N11="","",IF(OR(N11<1,N11>36),"",INDEX(Balances!$E$49:$AN$49,N11))) | G11: =CHOOSE(MONTH(DATE(YEAR(TODAY()),MONTH(TODAY())-9,1)),"Jan","Feb","Mar","Apr","May","Jun","Jul","Aug","Sep","Oct","Nov","Dec")&" "&YEAR(DATE(YEAR(TODAY()),MONTH(TODAY())-9,1)) | H11: =SUMIFS(Income!$E$6:$E$1005,Income!$D$6:$D$1005,"Dividend",Income!$G$6:$G$1005,P11) | I11: =J11-H11 | J11: =SUMIFS(Income!$E$6:$E$1005,Income!$G$6:$G$1005,P11) | N11: =IF(OR($M$1=0,($M$1-9)<1),"",($M$1-9)) | O11: =IF(ISNUMBER(E11),E11,NA()) | P11: =YEAR(DATE(YEAR(TODAY()),MONTH(TODAY())-9,1))*100+MONTH(DATE(YEAR(TODAY()),MONTH(TODAY())-9,1))
B12: =IF(N12="","",CHOOSE(MONTH(EDATE(Settings!$C$5,N12-1)),"Jan","Feb","Mar","Apr","May","Jun","Jul","Aug","Sep","Oct","Nov","Dec")&" "&YEAR(EDATE(Settings!$C$5,N12-1))) | C12: =IF(N12="","",IF(OR(N12<1,N12>36),"",INDEX(Balances!$E$47:$AN$47,N12))) | D12: =IF(N12="","",IF(OR(N12<1,N12>36),"",INDEX(Balances!$E$48:$AN$48,N12))) | E12: =IF(N12="","",IF(OR(N12<1,N12>36),"",INDEX(Balances!$E$49:$AN$49,N12))) | G12: =CHOOSE(MONTH(DATE(YEAR(TODAY()),MONTH(TODAY())-8,1)),"Jan","Feb","Mar","Apr","May","Jun","Jul","Aug","Sep","Oct","Nov","Dec")&" "&YEAR(DATE(YEAR(TODAY()),MONTH(TODAY())-8,1)) | H12: =SUMIFS(Income!$E$6:$E$1005,Income!$D$6:$D$1005,"Dividend",Income!$G$6:$G$1005,P12) | I12: =J12-H12 | J12: =SUMIFS(Income!$E$6:$E$1005,Income!$G$6:$G$1005,P12) | N12: =IF(OR($M$1=0,($M$1-8)<1),"",($M$1-8)) | O12: =IF(ISNUMBER(E12),E12,NA()) | P12: =YEAR(DATE(YEAR(TODAY()),MONTH(TODAY())-8,1))*100+MONTH(DATE(YEAR(TODAY()),MONTH(TODAY())-8,1))
B13: =IF(N13="","",CHOOSE(MONTH(EDATE(Settings!$C$5,N13-1)),"Jan","Feb","Mar","Apr","May","Jun","Jul","Aug","Sep","Oct","Nov","Dec")&" "&YEAR(EDATE(Settings!$C$5,N13-1))) | C13: =IF(N13="","",IF(OR(N13<1,N13>36),"",INDEX(Balances!$E$47:$AN$47,N13))) | D13: =IF(N13="","",IF(OR(N13<1,N13>36),"",INDEX(Balances!$E$48:$AN$48,N13))) | E13: =IF(N13="","",IF(OR(N13<1,N13>36),"",INDEX(Balances!$E$49:$AN$49,N13))) | G13: =CHOOSE(MONTH(DATE(YEAR(TODAY()),MONTH(TODAY())-7,1)),"Jan","Feb","Mar","Apr","May","Jun","Jul","Aug","Sep","Oct","Nov","Dec")&" "&YEAR(DATE(YEAR(TODAY()),MONTH(TODAY())-7,1)) | H13: =SUMIFS(Income!$E$6:$E$1005,Income!$D$6:$D$1005,"Dividend",Income!$G$6:$G$1005,P13) | I13: =J13-H13 | J13: =SUMIFS(Income!$E$6:$E$1005,Income!$G$6:$G$1005,P13) | N13: =IF(OR($M$1=0,($M$1-7)<1),"",($M$1-7)) | O13: =IF(ISNUMBER(E13),E13,NA()) | P13: =YEAR(DATE(YEAR(TODAY()),MONTH(TODAY())-7,1))*100+MONTH(DATE(YEAR(TODAY()),MONTH(TODAY())-7,1))
B14: =IF(N14="","",CHOOSE(MONTH(EDATE(Settings!$C$5,N14-1)),"Jan","Feb","Mar","Apr","May","Jun","Jul","Aug","Sep","Oct","Nov","Dec")&" "&YEAR(EDATE(Settings!$C$5,N14-1))) | C14: =IF(N14="","",IF(OR(N14<1,N14>36),"",INDEX(Balances!$E$47:$AN$47,N14))) | D14: =IF(N14="","",IF(OR(N14<1,N14>36),"",INDEX(Balances!$E$48:$AN$48,N14))) | E14: =IF(N14="","",IF(OR(N14<1,N14>36),"",INDEX(Balances!$E$49:$AN$49,N14))) | G14: =CHOOSE(MONTH(DATE(YEAR(TODAY()),MONTH(TODAY())-6,1)),"Jan","Feb","Mar","Apr","May","Jun","Jul","Aug","Sep","Oct","Nov","Dec")&" "&YEAR(DATE(YEAR(TODAY()),MONTH(TODAY())-6,1)) | H14: =SUMIFS(Income!$E$6:$E$1005,Income!$D$6:$D$1005,"Dividend",Income!$G$6:$G$1005,P14) | I14: =J14-H14 | J14: =SUMIFS(Income!$E$6:$E$1005,Income!$G$6:$G$1005,P14) | N14: =IF(OR($M$1=0,($M$1-6)<1),"",($M$1-6)) | O14: =IF(ISNUMBER(E14),E14,NA()) | P14: =YEAR(DATE(YEAR(TODAY()),MONTH(TODAY())-6,1))*100+MONTH(DATE(YEAR(TODAY()),MONTH(TODAY())-6,1))
B15: =IF(N15="","",CHOOSE(MONTH(EDATE(Settings!$C$5,N15-1)),"Jan","Feb","Mar","Apr","May","Jun","Jul","Aug","Sep","Oct","Nov","Dec")&" "&YEAR(EDATE(Settings!$C$5,N15-1))) | C15: =IF(N15="","",IF(OR(N15<1,N15>36),"",INDEX(Balances!$E$47:$AN$47,N15))) | D15: =IF(N15="","",IF(OR(N15<1,N15>36),"",INDEX(Balances!$E$48:$AN$48,N15))) | E15: =IF(N15="","",IF(OR(N15<1,N15>36),"",INDEX(Balances!$E$49:$AN$49,N15))) | G15: =CHOOSE(MONTH(DATE(YEAR(TODAY()),MONTH(TODAY())-5,1)),"Jan","Feb","Mar","Apr","May","Jun","Jul","Aug","Sep","Oct","Nov","Dec")&" "&YEAR(DATE(YEAR(TODAY()),MONTH(TODAY())-5,1)) | H15: =SUMIFS(Income!$E$6:$E$1005,Income!$D$6:$D$1005,"Dividend",Income!$G$6:$G$1005,P15) | I15: =J15-H15 | J15: =SUMIFS(Income!$E$6:$E$1005,Income!$G$6:$G$1005,P15) | N15: =IF(OR($M$1=0,($M$1-5)<1),"",($M$1-5)) | O15: =IF(ISNUMBER(E15),E15,NA()) | P15: =YEAR(DATE(YEAR(TODAY()),MONTH(TODAY())-5,1))*100+MONTH(DATE(YEAR(TODAY()),MONTH(TODAY())-5,1))
B16: =IF(N16="","",CHOOSE(MONTH(EDATE(Settings!$C$5,N16-1)),"Jan","Feb","Mar","Apr","May","Jun","Jul","Aug","Sep","Oct","Nov","Dec")&" "&YEAR(EDATE(Settings!$C$5,N16-1))) | C16: =IF(N16="","",IF(OR(N16<1,N16>36),"",INDEX(Balances!$E$47:$AN$47,N16))) | D16: =IF(N16="","",IF(OR(N16<1,N16>36),"",INDEX(Balances!$E$48:$AN$48,N16))) | E16: =IF(N16="","",IF(OR(N16<1,N16>36),"",INDEX(Balances!$E$49:$AN$49,N16))) | G16: =CHOOSE(MONTH(DATE(YEAR(TODAY()),MONTH(TODAY())-4,1)),"Jan","Feb","Mar","Apr","May","Jun","Jul","Aug","Sep","Oct","Nov","Dec")&" "&YEAR(DATE(YEAR(TODAY()),MONTH(TODAY())-4,1)) | H16: =SUMIFS(Income!$E$6:$E$1005,Income!$D$6:$D$1005,"Dividend",Income!$G$6:$G$1005,P16) | I16: =J16-H16 | J16: =SUMIFS(Income!$E$6:$E$1005,Income!$G$6:$G$1005,P16) | N16: =IF(OR($M$1=0,($M$1-4)<1),"",($M$1-4)) | O16: =IF(ISNUMBER(E16),E16,NA()) | P16: =YEAR(DATE(YEAR(TODAY()),MONTH(TODAY())-4,1))*100+MONTH(DATE(YEAR(TODAY()),MONTH(TODAY())-4,1))
B17: =IF(N17="","",CHOOSE(MONTH(EDATE(Settings!$C$5,N17-1)),"Jan","Feb","Mar","Apr","May","Jun","Jul","Aug","Sep","Oct","Nov","Dec")&" "&YEAR(EDATE(Settings!$C$5,N17-1))) | C17: =IF(N17="","",IF(OR(N17<1,N17>36),"",INDEX(Balances!$E$47:$AN$47,N17))) | D17: =IF(N17="","",IF(OR(N17<1,N17>36),"",INDEX(Balances!$E$48:$AN$48,N17))) | E17: =IF(N17="","",IF(OR(N17<1,N17>36),"",INDEX(Balances!$E$49:$AN$49,N17))) | G17: =CHOOSE(MONTH(DATE(YEAR(TODAY()),MONTH(TODAY())-3,1)),"Jan","Feb","Mar","Apr","May","Jun","Jul","Aug","Sep","Oct","Nov","Dec")&" "&YEAR(DATE(YEAR(TODAY()),MONTH(TODAY())-3,1)) | H17: =SUMIFS(Income!$E$6:$E$1005,Income!$D$6:$D$1005,"Dividend",Income!$G$6:$G$1005,P17) | I17: =J17-H17 | J17: =SUMIFS(Income!$E$6:$E$1005,Income!$G$6:$G$1005,P17) | N17: =IF(OR($M$1=0,($M$1-3)<1),"",($M$1-3)) | O17: =IF(ISNUMBER(E17),E17,NA()) | P17: =YEAR(DATE(YEAR(TODAY()),MONTH(TODAY())-3,1))*100+MONTH(DATE(YEAR(TODAY()),MONTH(TODAY())-3,1))
B18: =IF(N18="","",CHOOSE(MONTH(EDATE(Settings!$C$5,N18-1)),"Jan","Feb","Mar","Apr","May","Jun","Jul","Aug","Sep","Oct","Nov","Dec")&" "&YEAR(EDATE(Settings!$C$5,N18-1))) | C18: =IF(N18="","",IF(OR(N18<1,N18>36),"",INDEX(Balances!$E$47:$AN$47,N18))) | D18: =IF(N18="","",IF(OR(N18<1,N18>36),"",INDEX(Balances!$E$48:$AN$48,N18))) | E18: =IF(N18="","",IF(OR(N18<1,N18>36),"",INDEX(Balances!$E$49:$AN$49,N18))) | G18: =CHOOSE(MONTH(DATE(YEAR(TODAY()),MONTH(TODAY())-2,1)),"Jan","Feb","Mar","Apr","May","Jun","Jul","Aug","Sep","Oct","Nov","Dec")&" "&YEAR(DATE(YEAR(TODAY()),MONTH(TODAY())-2,1)) | H18: =SUMIFS(Income!$E$6:$E$1005,Income!$D$6:$D$1005,"Dividend",Income!$G$6:$G$1005,P18) | I18: =J18-H18 | J18: =SUMIFS(Income!$E$6:$E$1005,Income!$G$6:$G$1005,P18) | N18: =IF(OR($M$1=0,($M$1-2)<1),"",($M$1-2)) | O18: =IF(ISNUMBER(E18),E18,NA()) | P18: =YEAR(DATE(YEAR(TODAY()),MONTH(TODAY())-2,1))*100+MONTH(DATE(YEAR(TODAY()),MONTH(TODAY())-2,1))
B19: =IF(N19="","",CHOOSE(MONTH(EDATE(Settings!$C$5,N19-1)),"Jan","Feb","Mar","Apr","May","Jun","Jul","Aug","Sep","Oct","Nov","Dec")&" "&YEAR(EDATE(Settings!$C$5,N19-1))) | C19: =IF(N19="","",IF(OR(N19<1,N19>36),"",INDEX(Balances!$E$47:$AN$47,N19))) | D19: =IF(N19="","",IF(OR(N19<1,N19>36),"",INDEX(Balances!$E$48:$AN$48,N19))) | E19: =IF(N19="","",IF(OR(N19<1,N19>36),"",INDEX(Balances!$E$49:$AN$49,N19))) | G19: =CHOOSE(MONTH(DATE(YEAR(TODAY()),MONTH(TODAY())-1,1)),"Jan","Feb","Mar","Apr","May","Jun","Jul","Aug","Sep","Oct","Nov","Dec")&" "&YEAR(DATE(YEAR(TODAY()),MONTH(TODAY())-1,1)) | H19: =SUMIFS(Income!$E$6:$E$1005,Income!$D$6:$D$1005,"Dividend",Income!$G$6:$G$1005,P19) | I19: =J19-H19 | J19: =SUMIFS(Income!$E$6:$E$1005,Income!$G$6:$G$1005,P19) | N19: =IF(OR($M$1=0,($M$1-1)<1),"",($M$1-1)) | O19: =IF(ISNUMBER(E19),E19,NA()) | P19: =YEAR(DATE(YEAR(TODAY()),MONTH(TODAY())-1,1))*100+MONTH(DATE(YEAR(TODAY()),MONTH(TODAY())-1,1))
B20: =IF(N20="","",CHOOSE(MONTH(EDATE(Settings!$C$5,N20-1)),"Jan","Feb","Mar","Apr","May","Jun","Jul","Aug","Sep","Oct","Nov","Dec")&" "&YEAR(EDATE(Settings!$C$5,N20-1))) | C20: =IF(N20="","",IF(OR(N20<1,N20>36),"",INDEX(Balances!$E$47:$AN$47,N20))) | D20: =IF(N20="","",IF(OR(N20<1,N20>36),"",INDEX(Balances!$E$48:$AN$48,N20))) | E20: =IF(N20="","",IF(OR(N20<1,N20>36),"",INDEX(Balances!$E$49:$AN$49,N20))) | G20: =CHOOSE(MONTH(DATE(YEAR(TODAY()),MONTH(TODAY())-0,1)),"Jan","Feb","Mar","Apr","May","Jun","Jul","Aug","Sep","Oct","Nov","Dec")&" "&YEAR(DATE(YEAR(TODAY()),MONTH(TODAY())-0,1)) | H20: =SUMIFS(Income!$E$6:$E$1005,Income!$D$6:$D$1005,"Dividend",Income!$G$6:$G$1005,P20) | I20: =J20-H20 | J20: =SUMIFS(Income!$E$6:$E$1005,Income!$G$6:$G$1005,P20) | N20: =IF(OR($M$1=0,($M$1-0)<1),"",($M$1-0)) | O20: =IF(ISNUMBER(E20),E20,NA()) | P20: =YEAR(DATE(YEAR(TODAY()),MONTH(TODAY())-0,1))*100+MONTH(DATE(YEAR(TODAY()),MONTH(TODAY())-0,1))
D23: Net worth
C24: =B9 | D24: =O9
C25: =B10 | D25: =O10
C26: =B11 | D26: =O11
C27: =B12 | D27: =O12
C28: =B13 | D28: =O13
C29: =B14 | D29: =O14
C30: =B15 | D30: =O15
C31: =B16 | D31: =O16
C32: =B17 | D32: =O17
C33: =B18 | D33: =O18
C34: =B19 | D34: =O19
C35: =B20 | D35: =O20
B38: Where it is | C38: Amount | D38: Share | G38: Top payers | H38: 12 months | I38: Yield | J38: A month
B39: Cash | C39: =IF($M$1=0,"",SUMIFS(INDEX(Balances!$E$6:$AN$45,0,$M$1),Balances!$C$6:$C$45,B39)) | D39: =IF(OR(C39="",N($D$5)<=0),"",C39/$D$5) | E39: =IF(D39="","",REPT("█",ROUND(D39*12,0))) | G39: =IF(Q39="","",INDEX(Holdings!$B$1:$B$105,1000-MOD(Q39,1000))) | H39: =IF(Q39="","",INDEX(Holdings!$E$1:$E$105,1000-MOD(Q39,1000))) | I39: =IF(Q39="","",IF(INDEX(Holdings!$G$1:$G$105,1000-MOD(Q39,1000))="","",INDEX(Holdings!$G$1:$G$105,1000-MOD(Q39,1000)))) | J39: =IF(Q39="","",INDEX(Holdings!$H$1:$H$105,1000-MOD(Q39,1000))) | Q39: =IFERROR(LARGE(Holdings!$J$6:$J$105,1),"")
B40: Savings | C40: =IF($M$1=0,"",SUMIFS(INDEX(Balances!$E$6:$AN$45,0,$M$1),Balances!$C$6:$C$45,B40)) | D40: =IF(OR(C40="",N($D$5)<=0),"",C40/$D$5) | E40: =IF(D40="","",REPT("█",ROUND(D40*12,0))) | G40: =IF(Q40="","",INDEX(Holdings!$B$1:$B$105,1000-MOD(Q40,1000))) | H40: =IF(Q40="","",INDEX(Holdings!$E$1:$E$105,1000-MOD(Q40,1000))) | I40: =IF(Q40="","",IF(INDEX(Holdings!$G$1:$G$105,1000-MOD(Q40,1000))="","",INDEX(Holdings!$G$1:$G$105,1000-MOD(Q40,1000)))) | J40: =IF(Q40="","",INDEX(Holdings!$H$1:$H$105,1000-MOD(Q40,1000))) | Q40: =IFERROR(LARGE(Holdings!$J$6:$J$105,2),"")
B41: Investments | C41: =IF($M$1=0,"",SUMIFS(INDEX(Balances!$E$6:$AN$45,0,$M$1),Balances!$C$6:$C$45,B41)) | D41: =IF(OR(C41="",N($D$5)<=0),"",C41/$D$5) | E41: =IF(D41="","",REPT("█",ROUND(D41*12,0))) | G41: =IF(Q41="","",INDEX(Holdings!$B$1:$B$105,1000-MOD(Q41,1000))) | H41: =IF(Q41="","",INDEX(Holdings!$E$1:$E$105,1000-MOD(Q41,1000))) | I41: =IF(Q41="","",IF(INDEX(Holdings!$G$1:$G$105,1000-MOD(Q41,1000))="","",INDEX(Holdings!$G$1:$G$105,1000-MOD(Q41,1000)))) | J41: =IF(Q41="","",INDEX(Holdings!$H$1:$H$105,1000-MOD(Q41,1000))) | Q41: =IFERROR(LARGE(Holdings!$J$6:$J$105,3),"")
B42: Retirement | C42: =IF($M$1=0,"",SUMIFS(INDEX(Balances!$E$6:$AN$45,0,$M$1),Balances!$C$6:$C$45,B42)) | D42: =IF(OR(C42="",N($D$5)<=0),"",C42/$D$5) | E42: =IF(D42="","",REPT("█",ROUND(D42*12,0))) | G42: =IF(Q42="","",INDEX(Holdings!$B$1:$B$105,1000-MOD(Q42,1000))) | H42: =IF(Q42="","",INDEX(Holdings!$E$1:$E$105,1000-MOD(Q42,1000))) | I42: =IF(Q42="","",IF(INDEX(Holdings!$G$1:$G$105,1000-MOD(Q42,1000))="","",INDEX(Holdings!$G$1:$G$105,1000-MOD(Q42,1000)))) | J42: =IF(Q42="","",INDEX(Holdings!$H$1:$H$105,1000-MOD(Q42,1000))) | Q42: =IFERROR(LARGE(Holdings!$J$6:$J$105,4),"")
B43: Property | C43: =IF($M$1=0,"",SUMIFS(INDEX(Balances!$E$6:$AN$45,0,$M$1),Balances!$C$6:$C$45,B43)) | D43: =IF(OR(C43="",N($D$5)<=0),"",C43/$D$5) | E43: =IF(D43="","",REPT("█",ROUND(D43*12,0))) | G43: =IF(Q43="","",INDEX(Holdings!$B$1:$B$105,1000-MOD(Q43,1000))) | H43: =IF(Q43="","",INDEX(Holdings!$E$1:$E$105,1000-MOD(Q43,1000))) | I43: =IF(Q43="","",IF(INDEX(Holdings!$G$1:$G$105,1000-MOD(Q43,1000))="","",INDEX(Holdings!$G$1:$G$105,1000-MOD(Q43,1000)))) | J43: =IF(Q43="","",INDEX(Holdings!$H$1:$H$105,1000-MOD(Q43,1000))) | Q43: =IFERROR(LARGE(Holdings!$J$6:$J$105,5),"")
B44: Vehicle | C44: =IF($M$1=0,"",SUMIFS(INDEX(Balances!$E$6:$AN$45,0,$M$1),Balances!$C$6:$C$45,B44)) | D44: =IF(OR(C44="",N($D$5)<=0),"",C44/$D$5) | E44: =IF(D44="","",REPT("█",ROUND(D44*12,0))) | G44: =IF(Q44="","",INDEX(Holdings!$B$1:$B$105,1000-MOD(Q44,1000))) | H44: =IF(Q44="","",INDEX(Holdings!$E$1:$E$105,1000-MOD(Q44,1000))) | I44: =IF(Q44="","",IF(INDEX(Holdings!$G$1:$G$105,1000-MOD(Q44,1000))="","",INDEX(Holdings!$G$1:$G$105,1000-MOD(Q44,1000)))) | J44: =IF(Q44="","",INDEX(Holdings!$H$1:$H$105,1000-MOD(Q44,1000))) | Q44: =IFERROR(LARGE(Holdings!$J$6:$J$105,6),"")
B45: Other asset | C45: =IF($M$1=0,"",SUMIFS(INDEX(Balances!$E$6:$AN$45,0,$M$1),Balances!$C$6:$C$45,B45)) | D45: =IF(OR(C45="",N($D$5)<=0),"",C45/$D$5) | E45: =IF(D45="","",REPT("█",ROUND(D45*12,0))) | G45: =IF(Q45="","",INDEX(Holdings!$B$1:$B$105,1000-MOD(Q45,1000))) | H45: =IF(Q45="","",INDEX(Holdings!$E$1:$E$105,1000-MOD(Q45,1000))) | I45: =IF(Q45="","",IF(INDEX(Holdings!$G$1:$G$105,1000-MOD(Q45,1000))="","",INDEX(Holdings!$G$1:$G$105,1000-MOD(Q45,1000)))) | J45: =IF(Q45="","",INDEX(Holdings!$H$1:$H$105,1000-MOD(Q45,1000))) | Q45: =IFERROR(LARGE(Holdings!$J$6:$J$105,7),"")

Sheet Balances
B2: Balances
B3: Each account once, with its balance at the end of each month. Debts as the amount owed.
B5: Account | C5: Type | D5: Kind | E5: =EDATE(Settings!$C$5,0) | F5: =EDATE(Settings!$C$5,1) | G5: =EDATE(Settings!$C$5,2) | H5: =EDATE(Settings!$C$5,3) | I5: =EDATE(Settings!$C$5,4) | J5: =EDATE(Settings!$C$5,5) | K5: =EDATE(Settings!$C$5,6) | L5: =EDATE(Settings!$C$5,7) | M5: =EDATE(Settings!$C$5,8) | N5: =EDATE(Settings!$C$5,9) | O5: =EDATE(Settings!$C$5,10) | P5: =EDATE(Settings!$C$5,11) | Q5: =EDATE(Settings!$C$5,12) | R5: =EDATE(Settings!$C$5,13) | S5: =EDATE(Settings!$C$5,14) | T5: =EDATE(Settings!$C$5,15) | U5: =EDATE(Settings!$C$5,16) | V5: =EDATE(Settings!$C$5,17) | W5: =EDATE(Settings!$C$5,18) | X5: =EDATE(Settings!$C$5,19) | Y5: =EDATE(Settings!$C$5,20) | Z5: =EDATE(Settings!$C$5,21) | AA5: =EDATE(Settings!$C$5,22) | AB5: =EDATE(Settings!$C$5,23) | AC5: =EDATE(Settings!$C$5,24) | AD5: =EDATE(Settings!$C$5,25) | AE5: =EDATE(Settings!$C$5,26) | AF5: =EDATE(Settings!$C$5,27) | AG5: =EDATE(Settings!$C$5,28) | AH5: =EDATE(Settings!$C$5,29) | AI5: =EDATE(Settings!$C$5,30) | AJ5: =EDATE(Settings!$C$5,31) | AK5: =EDATE(Settings!$C$5,32) | AL5: =EDATE(Settings!$C$5,33) | AM5: =EDATE(Settings!$C$5,34) | AN5: =EDATE(Settings!$C$5,35)
B6: Everyday account | C6: Cash | D6: =IF(B6="","",IF(OR(C6="Credit card",C6="Loan",C6="Mortgage",C6="Other debt"),"Debt","Asset")) | E6: 2100 | F6: 1900 | G6: 2060 | H6: 1940 | I6: 2130 | J6: 2290 | K6: 2380 | L6: 2090 | M6: 2200 | N6: 2090 | O6: 2620 | P6: 2400 | AP6: =IF(B6="",0,IF(OR(C6="Credit card",C6="Loan",C6="Mortgage",C6="Other debt"),-1,1))
B7: Emergency savings | C7: Savings | D7: =IF(B7="","",IF(OR(C7="Credit card",C7="Loan",C7="Mortgage",C7="Other debt"),"Debt","Asset")) | E7: 8000 | F7: 8300 | G7: 8600 | H7: 8900 | I7: 9200 | J7: 9500 | K7: 9800 | L7: 10100 | M7: 10400 | N7: 10700 | O7: 11000 | P7: 11300 | AP7: =IF(B7="",0,IF(OR(C7="Credit card",C7="Loan",C7="Mortgage",C7="Other debt"),-1,1))
B8: Brokerage | C8: Investments | D8: =IF(B8="","",IF(OR(C8="Credit card",C8="Loan",C8="Mortgage",C8="Other debt"),"Debt","Asset")) | E8: 24000 | F8: 25010 | G8: 25160 | H8: 25420 | I8: 26150 | J8: 26190 | K8: 28090 | L8: 27510 | M8: 28380 | N8: 29780 | O8: 30400 | P8: 30800 | AP8: =IF(B8="",0,IF(OR(C8="Credit card",C8="Loan",C8="Mortgage",C8="Other debt"),-1,1))
B9: Dividend portfolio | C9: Investments | D9: =IF(B9="","",IF(OR(C9="Credit card",C9="Loan",C9="Mortgage",C9="Other debt"),"Debt","Asset")) | E9: 18200 | F9: 18740 | G9: 19160 | H9: 19760 | I9: 20330 | J9: 20760 | K9: 20460 | L9: 20820 | M9: 20960 | N9: 21720 | O9: 21810 | P9: 22600 | AP9: =IF(B9="",0,IF(OR(C9="Credit card",C9="Loan",C9="Mortgage",C9="Other debt"),-1,1))
B10: Retirement plan | C10: Retirement | D10: =IF(B10="","",IF(OR(C10="Credit card",C10="Loan",C10="Mortgage",C10="Other debt"),"Debt","Asset")) | E10: 52000 | F10: 53900 | G10: 54320 | H10: 53930 | I10: 55880 | J10: 56750 | K10: 56170 | L10: 58720 | M10: 59400 | N10: 59620 | O10: 61610 | P10: 61400 | AP10: =IF(B10="",0,IF(OR(C10="Credit card",C10="Loan",C10="Mortgage",C10="Other debt"),-1,1))
B11: Home | C11: Property | D11: =IF(B11="","",IF(OR(C11="Credit card",C11="Loan",C11="Mortgage",C11="Other debt"),"Debt","Asset")) | E11: 320000 | F11: 320000 | G11: 320000 | H11: 320000 | I11: 320000 | J11: 320000 | K11: 330000 | L11: 330000 | M11: 330000 | N11: 330000 | O11: 330000 | P11: 330000 | AP11: =IF(B11="",0,IF(OR(C11="Credit card",C11="Loan",C11="Mortgage",C11="Other debt"),-1,1))
B12: Car | C12: Vehicle | D12: =IF(B12="","",IF(OR(C12="Credit card",C12="Loan",C12="Mortgage",C12="Other debt"),"Debt","Asset")) | E12: 14000 | F12: 13850 | G12: 13710 | H12: 13560 | I12: 13420 | J12: 13270 | K12: 13130 | L12: 12980 | M12: 12840 | N12: 12690 | O12: 12550 | P12: 12400 | AP12: =IF(B12="",0,IF(OR(C12="Credit card",C12="Loan",C12="Mortgage",C12="Other debt"),-1,1))
B13: Credit card | C13: Credit card | D13: =IF(B13="","",IF(OR(C13="Credit card",C13="Loan",C13="Mortgage",C13="Other debt"),"Debt","Asset")) | E13: 1200 | F13: 909.92 | G13: 848.93 | H13: 1300 | I13: 954.4 | J13: 1320 | K13: 1310 | L13: 824.09 | M13: 1110 | N13: 716.02 | O13: 882.58 | P13: 850 | AP13: =IF(B13="",0,IF(OR(C13="Credit card",C13="Loan",C13="Mortgage",C13="Other debt"),-1,1))
B14: Car loan | C14: Loan | D14: =IF(B14="","",IF(OR(C14="Credit card",C14="Loan",C14="Mortgage",C14="Other debt"),"Debt","Asset")) | E14: 9000 | F14: 8780 | G14: 8560 | H14: 8350 | I14: 8130 | J14: 7910 | K14: 7690 | L14: 7470 | M14: 7250 | N14: 7040 | O14: 6820 | P14: 6600 | AP14: =IF(B14="",0,IF(OR(C14="Credit card",C14="Loan",C14="Mortgage",C14="Other debt"),-1,1))
B15: Mortgage | C15: Mortgage | D15: =IF(B15="","",IF(OR(C15="Credit card",C15="Loan",C15="Mortgage",C15="Other debt"),"Debt","Asset")) | E15: 210000 | F15: 209530 | G15: 209050 | H15: 208580 | I15: 208110 | J15: 207640 | K15: 207160 | L15: 206690 | M15: 206220 | N15: 205750 | O15: 205270 | P15: 204800 | AP15: =IF(B15="",0,IF(OR(C15="Credit card",C15="Loan",C15="Mortgage",C15="Other debt"),-1,1))
D16: =IF(B16="","",IF(OR(C16="Credit card",C16="Loan",C16="Mortgage",C16="Other debt"),"Debt","Asset")) | AP16: =IF(B16="",0,IF(OR(C16="Credit card",C16="Loan",C16="Mortgage",C16="Other debt"),-1,1))
D17: =IF(B17="","",IF(OR(C17="Credit card",C17="Loan",C17="Mortgage",C17="Other debt"),"Debt","Asset")) | AP17: =IF(B17="",0,IF(OR(C17="Credit card",C17="Loan",C17="Mortgage",C17="Other debt"),-1,1))
D18: =IF(B18="","",IF(OR(C18="Credit card",C18="Loan",C18="Mortgage",C18="Other debt"),"Debt","Asset")) | AP18: =IF(B18="",0,IF(OR(C18="Credit card",C18="Loan",C18="Mortgage",C18="Other debt"),-1,1))
D19: =IF(B19="","",IF(OR(C19="Credit card",C19="Loan",C19="Mortgage",C19="Other debt"),"Debt","Asset")) | AP19: =IF(B19="",0,IF(OR(C19="Credit card",C19="Loan",C19="Mortgage",C19="Other debt"),-1,1))
D20: =IF(B20="","",IF(OR(C20="Credit card",C20="Loan",C20="Mortgage",C20="Other debt"),"Debt","Asset")) | AP20: =IF(B20="",0,IF(OR(C20="Credit card",C20="Loan",C20="Mortgage",C20="Other debt"),-1,1))
D21: =IF(B21="","",IF(OR(C21="Credit card",C21="Loan",C21="Mortgage",C21="Other debt"),"Debt","Asset")) | AP21: =IF(B21="",0,IF(OR(C21="Credit card",C21="Loan",C21="Mortgage",C21="Other debt"),-1,1))
D22: =IF(B22="","",IF(OR(C22="Credit card",C22="Loan",C22="Mortgage",C22="Other debt"),"Debt","Asset")) | AP22: =IF(B22="",0,IF(OR(C22="Credit card",C22="Loan",C22="Mortgage",C22="Other debt"),-1,1))
D23: =IF(B23="","",IF(OR(C23="Credit card",C23="Loan",C23="Mortgage",C23="Other debt"),"Debt","Asset")) | AP23: =IF(B23="",0,IF(OR(C23="Credit card",C23="Loan",C23="Mortgage",C23="Other debt"),-1,1))
D24: =IF(B24="","",IF(OR(C24="Credit card",C24="Loan",C24="Mortgage",C24="Other debt"),"Debt","Asset")) | AP24: =IF(B24="",0,IF(OR(C24="Credit card",C24="Loan",C24="Mortgage",C24="Other debt"),-1,1))
D25: =IF(B25="","",IF(OR(C25="Credit card",C25="Loan",C25="Mortgage",C25="Other debt"),"Debt","Asset")) | AP25: =IF(B25="",0,IF(OR(C25="Credit card",C25="Loan",C25="Mortgage",C25="Other debt"),-1,1))
D26: =IF(B26="","",IF(OR(C26="Credit card",C26="Loan",C26="Mortgage",C26="Other debt"),"Debt","Asset")) | AP26: =IF(B26="",0,IF(OR(C26="Credit card",C26="Loan",C26="Mortgage",C26="Other debt"),-1,1))
D27: =IF(B27="","",IF(OR(C27="Credit card",C27="Loan",C27="Mortgage",C27="Other debt"),"Debt","Asset")) | AP27: =IF(B27="",0,IF(OR(C27="Credit card",C27="Loan",C27="Mortgage",C27="Other debt"),-1,1))
... D45: =IF(B45="","",IF(OR(C45="Credit card",C45="Loan",C45="Mortgage",C45="Other debt"),"Debt","Asset")) | AP45: =IF(B45="",0,IF(OR(C45="Credit card",C45="Loan",C45="Mortgage",C45="Other debt"),-1,1))
B47: Assets | E47: =IF(COUNT(E6:E45)=0,"",SUMIFS(E6:E45,$AP$6:$AP$45,1)) | F47: =IF(COUNT(F6:F45)=0,"",SUMIFS(F6:F45,$AP$6:$AP$45,1)) | G47: =IF(COUNT(G6:G45)=0,"",SUMIFS(G6:G45,$AP$6:$AP$45,1)) | H47: =IF(COUNT(H6:H45)=0,"",SUMIFS(H6:H45,$AP$6:$AP$45,1)) | I47: =IF(COUNT(I6:I45)=0,"",SUMIFS(I6:I45,$AP$6:$AP$45,1)) | J47: =IF(COUNT(J6:J45)=0,"",SUMIFS(J6:J45,$AP$6:$AP$45,1)) | K47: =IF(COUNT(K6:K45)=0,"",SUMIFS(K6:K45,$AP$6:$AP$45,1)) | L47: =IF(COUNT(L6:L45)=0,"",SUMIFS(L6:L45,$AP$6:$AP$45,1)) | ... AN47: =IF(COUNT(AN6:AN45)=0,"",SUMIFS(AN6:AN45,$AP$6:$AP$45,1))
B48: Debts | E48: =IF(COUNT(E6:E45)=0,"",SUMIFS(E6:E45,$AP$6:$AP$45,-1)) | F48: =IF(COUNT(F6:F45)=0,"",SUMIFS(F6:F45,$AP$6:$AP$45,-1)) | G48: =IF(COUNT(G6:G45)=0,"",SUMIFS(G6:G45,$AP$6:$AP$45,-1)) | H48: =IF(COUNT(H6:H45)=0,"",SUMIFS(H6:H45,$AP$6:$AP$45,-1)) | I48: =IF(COUNT(I6:I45)=0,"",SUMIFS(I6:I45,$AP$6:$AP$45,-1)) | J48: =IF(COUNT(J6:J45)=0,"",SUMIFS(J6:J45,$AP$6:$AP$45,-1)) | K48: =IF(COUNT(K6:K45)=0,"",SUMIFS(K6:K45,$AP$6:$AP$45,-1)) | L48: =IF(COUNT(L6:L45)=0,"",SUMIFS(L6:L45,$AP$6:$AP$45,-1)) | ... AN48: =IF(COUNT(AN6:AN45)=0,"",SUMIFS(AN6:AN45,$AP$6:$AP$45,-1))
B49: Net worth | E49: =IF(COUNT(E6:E45)=0,"",E47-E48) | F49: =IF(COUNT(F6:F45)=0,"",F47-F48) | G49: =IF(COUNT(G6:G45)=0,"",G47-G48) | H49: =IF(COUNT(H6:H45)=0,"",H47-H48) | I49: =IF(COUNT(I6:I45)=0,"",I47-I48) | J49: =IF(COUNT(J6:J45)=0,"",J47-J48) | K49: =IF(COUNT(K6:K45)=0,"",K47-K48) | L49: =IF(COUNT(L6:L45)=0,"",L47-L48) | ... AN49: =IF(COUNT(AN6:AN45)=0,"",AN47-AN48)
E50: =IF(COUNT(E6:E45)>0,1,0) | F50: =IF(COUNT(F6:F45)>0,2,0) | G50: =IF(COUNT(G6:G45)>0,3,0) | H50: =IF(COUNT(H6:H45)>0,4,0) | I50: =IF(COUNT(I6:I45)>0,5,0) | J50: =IF(COUNT(J6:J45)>0,6,0) | K50: =IF(COUNT(K6:K45)>0,7,0) | L50: =IF(COUNT(L6:L45)>0,8,0) | M50: =IF(COUNT(M6:M45)>0,9,0) | N50: =IF(COUNT(N6:N45)>0,10,0) | O50: =IF(COUNT(O6:O45)>0,11,0) | P50: =IF(COUNT(P6:P45)>0,12,0) | Q50: =IF(COUNT(Q6:Q45)>0,13,0) | R50: =IF(COUNT(R6:R45)>0,14,0) | S50: =IF(COUNT(S6:S45)>0,15,0) | T50: =IF(COUNT(T6:T45)>0,16,0) | U50: =IF(COUNT(U6:U45)>0,17,0) | V50: =IF(COUNT(V6:V45)>0,18,0) | W50: =IF(COUNT(W6:W45)>0,19,0) | X50: =IF(COUNT(X6:X45)>0,20,0) | Y50: =IF(COUNT(Y6:Y45)>0,21,0) | Z50: =IF(COUNT(Z6:Z45)>0,22,0) | AA50: =IF(COUNT(AA6:AA45)>0,23,0) | AB50: =IF(COUNT(AB6:AB45)>0,24,0) | AC50: =IF(COUNT(AC6:AC45)>0,25,0) | AD50: =IF(COUNT(AD6:AD45)>0,26,0) | AE50: =IF(COUNT(AE6:AE45)>0,27,0) | AF50: =IF(COUNT(AF6:AF45)>0,28,0) | AG50: =IF(COUNT(AG6:AG45)>0,29,0) | AH50: =IF(COUNT(AH6:AH45)>0,30,0) | AI50: =IF(COUNT(AI6:AI45)>0,31,0) | AJ50: =IF(COUNT(AJ6:AJ45)>0,32,0) | AK50: =IF(COUNT(AK6:AK45)>0,33,0) | AL50: =IF(COUNT(AL6:AL45)>0,34,0) | AM50: =IF(COUNT(AM6:AM45)>0,35,0) | AN50: =IF(COUNT(AN6:AN45)>0,36,0)

Sheet Holdings
B2: Holdings
B3: What pays you: funds, shares, savings, a rented room. Its value now, for the yield.
B5: Holding | C5: Account | D5: Value now | E5: Last 12 months | F5: This year | G5: Yield | H5: A month
B6: Total market fund | C6: Brokerage | D6: 16400 | E6: =IF(B6="","",SUMIFS(Income!$E$6:$E$1005,Income!$C$6:$C$1005,B6,Income!$B$6:$B$1005,">="&DATE(YEAR(TODAY()),MONTH(TODAY())-11,1))) | F6: =IF(B6="","",SUMIFS(Income!$E$6:$E$1005,Income!$C$6:$C$1005,B6,Income!$B$6:$B$1005,">="&DATE(YEAR(TODAY()),1,1))) | G6: =IF(OR(B6="",N(D6)<=0),"",E6/D6) | H6: =IF(B6="","",E6/12) | J6: =IF(OR(B6="",N(E6)<=0),"",ROUND(E6*100,0)*1000+1000-ROW())
B7: Dividend fund | C7: Dividend portfolio | D7: 9800 | E7: =IF(B7="","",SUMIFS(Income!$E$6:$E$1005,Income!$C$6:$C$1005,B7,Income!$B$6:$B$1005,">="&DATE(YEAR(TODAY()),MONTH(TODAY())-11,1))) | F7: =IF(B7="","",SUMIFS(Income!$E$6:$E$1005,Income!$C$6:$C$1005,B7,Income!$B$6:$B$1005,">="&DATE(YEAR(TODAY()),1,1))) | G7: =IF(OR(B7="",N(D7)<=0),"",E7/D7) | H7: =IF(B7="","",E7/12) | J7: =IF(OR(B7="",N(E7)<=0),"",ROUND(E7*100,0)*1000+1000-ROW())
B8: Utility shares | C8: Dividend portfolio | D8: 5200 | E8: =IF(B8="","",SUMIFS(Income!$E$6:$E$1005,Income!$C$6:$C$1005,B8,Income!$B$6:$B$1005,">="&DATE(YEAR(TODAY()),MONTH(TODAY())-11,1))) | F8: =IF(B8="","",SUMIFS(Income!$E$6:$E$1005,Income!$C$6:$C$1005,B8,Income!$B$6:$B$1005,">="&DATE(YEAR(TODAY()),1,1))) | G8: =IF(OR(B8="",N(D8)<=0),"",E8/D8) | H8: =IF(B8="","",E8/12) | J8: =IF(OR(B8="",N(E8)<=0),"",ROUND(E8*100,0)*1000+1000-ROW())
B9: Bank shares | C9: Dividend portfolio | D9: 4100 | E9: =IF(B9="","",SUMIFS(Income!$E$6:$E$1005,Income!$C$6:$C$1005,B9,Income!$B$6:$B$1005,">="&DATE(YEAR(TODAY()),MONTH(TODAY())-11,1))) | F9: =IF(B9="","",SUMIFS(Income!$E$6:$E$1005,Income!$C$6:$C$1005,B9,Income!$B$6:$B$1005,">="&DATE(YEAR(TODAY()),1,1))) | G9: =IF(OR(B9="",N(D9)<=0),"",E9/D9) | H9: =IF(B9="","",E9/12) | J9: =IF(OR(B9="",N(E9)<=0),"",ROUND(E9*100,0)*1000+1000-ROW())
B10: Property fund | C10: Brokerage | D10: 6300 | E10: =IF(B10="","",SUMIFS(Income!$E$6:$E$1005,Income!$C$6:$C$1005,B10,Income!$B$6:$B$1005,">="&DATE(YEAR(TODAY()),MONTH(TODAY())-11,1))) | F10: =IF(B10="","",SUMIFS(Income!$E$6:$E$1005,Income!$C$6:$C$1005,B10,Income!$B$6:$B$1005,">="&DATE(YEAR(TODAY()),1,1))) | G10: =IF(OR(B10="",N(D10)<=0),"",E10/D10) | H10: =IF(B10="","",E10/12) | J10: =IF(OR(B10="",N(E10)<=0),"",ROUND(E10*100,0)*1000+1000-ROW())
B11: Bond fund | C11: Brokerage | D11: 8100 | E11: =IF(B11="","",SUMIFS(Income!$E$6:$E$1005,Income!$C$6:$C$1005,B11,Income!$B$6:$B$1005,">="&DATE(YEAR(TODAY()),MONTH(TODAY())-11,1))) | F11: =IF(B11="","",SUMIFS(Income!$E$6:$E$1005,Income!$C$6:$C$1005,B11,Income!$B$6:$B$1005,">="&DATE(YEAR(TODAY()),1,1))) | G11: =IF(OR(B11="",N(D11)<=0),"",E11/D11) | H11: =IF(B11="","",E11/12) | J11: =IF(OR(B11="",N(E11)<=0),"",ROUND(E11*100,0)*1000+1000-ROW())
B12: High yield savings | C12: Emergency savings | D12: 11300 | E12: =IF(B12="","",SUMIFS(Income!$E$6:$E$1005,Income!$C$6:$C$1005,B12,Income!$B$6:$B$1005,">="&DATE(YEAR(TODAY()),MONTH(TODAY())-11,1))) | F12: =IF(B12="","",SUMIFS(Income!$E$6:$E$1005,Income!$C$6:$C$1005,B12,Income!$B$6:$B$1005,">="&DATE(YEAR(TODAY()),1,1))) | G12: =IF(OR(B12="",N(D12)<=0),"",E12/D12) | H12: =IF(B12="","",E12/12) | J12: =IF(OR(B12="",N(E12)<=0),"",ROUND(E12*100,0)*1000+1000-ROW())
B13: Spare room | E13: =IF(B13="","",SUMIFS(Income!$E$6:$E$1005,Income!$C$6:$C$1005,B13,Income!$B$6:$B$1005,">="&DATE(YEAR(TODAY()),MONTH(TODAY())-11,1))) | F13: =IF(B13="","",SUMIFS(Income!$E$6:$E$1005,Income!$C$6:$C$1005,B13,Income!$B$6:$B$1005,">="&DATE(YEAR(TODAY()),1,1))) | G13: =IF(OR(B13="",N(D13)<=0),"",E13/D13) | H13: =IF(B13="","",E13/12) | J13: =IF(OR(B13="",N(E13)<=0),"",ROUND(E13*100,0)*1000+1000-ROW())
E14: =IF(B14="","",SUMIFS(Income!$E$6:$E$1005,Income!$C$6:$C$1005,B14,Income!$B$6:$B$1005,">="&DATE(YEAR(TODAY()),MONTH(TODAY())-11,1))) | F14: =IF(B14="","",SUMIFS(Income!$E$6:$E$1005,Income!$C$6:$C$1005,B14,Income!$B$6:$B$1005,">="&DATE(YEAR(TODAY()),1,1))) | G14: =IF(OR(B14="",N(D14)<=0),"",E14/D14) | H14: =IF(B14="","",E14/12) | J14: =IF(OR(B14="",N(E14)<=0),"",ROUND(E14*100,0)*1000+1000-ROW())
E15: =IF(B15="","",SUMIFS(Income!$E$6:$E$1005,Income!$C$6:$C$1005,B15,Income!$B$6:$B$1005,">="&DATE(YEAR(TODAY()),MONTH(TODAY())-11,1))) | F15: =IF(B15="","",SUMIFS(Income!$E$6:$E$1005,Income!$C$6:$C$1005,B15,Income!$B$6:$B$1005,">="&DATE(YEAR(TODAY()),1,1))) | G15: =IF(OR(B15="",N(D15)<=0),"",E15/D15) | H15: =IF(B15="","",E15/12) | J15: =IF(OR(B15="",N(E15)<=0),"",ROUND(E15*100,0)*1000+1000-ROW())
E16: =IF(B16="","",SUMIFS(Income!$E$6:$E$1005,Income!$C$6:$C$1005,B16,Income!$B$6:$B$1005,">="&DATE(YEAR(TODAY()),MONTH(TODAY())-11,1))) | F16: =IF(B16="","",SUMIFS(Income!$E$6:$E$1005,Income!$C$6:$C$1005,B16,Income!$B$6:$B$1005,">="&DATE(YEAR(TODAY()),1,1))) | G16: =IF(OR(B16="",N(D16)<=0),"",E16/D16) | H16: =IF(B16="","",E16/12) | J16: =IF(OR(B16="",N(E16)<=0),"",ROUND(E16*100,0)*1000+1000-ROW())
E17: =IF(B17="","",SUMIFS(Income!$E$6:$E$1005,Income!$C$6:$C$1005,B17,Income!$B$6:$B$1005,">="&DATE(YEAR(TODAY()),MONTH(TODAY())-11,1))) | F17: =IF(B17="","",SUMIFS(Income!$E$6:$E$1005,Income!$C$6:$C$1005,B17,Income!$B$6:$B$1005,">="&DATE(YEAR(TODAY()),1,1))) | G17: =IF(OR(B17="",N(D17)<=0),"",E17/D17) | H17: =IF(B17="","",E17/12) | J17: =IF(OR(B17="",N(E17)<=0),"",ROUND(E17*100,0)*1000+1000-ROW())
E18: =IF(B18="","",SUMIFS(Income!$E$6:$E$1005,Income!$C$6:$C$1005,B18,Income!$B$6:$B$1005,">="&DATE(YEAR(TODAY()),MONTH(TODAY())-11,1))) | F18: =IF(B18="","",SUMIFS(Income!$E$6:$E$1005,Income!$C$6:$C$1005,B18,Income!$B$6:$B$1005,">="&DATE(YEAR(TODAY()),1,1))) | G18: =IF(OR(B18="",N(D18)<=0),"",E18/D18) | H18: =IF(B18="","",E18/12) | J18: =IF(OR(B18="",N(E18)<=0),"",ROUND(E18*100,0)*1000+1000-ROW())
E19: =IF(B19="","",SUMIFS(Income!$E$6:$E$1005,Income!$C$6:$C$1005,B19,Income!$B$6:$B$1005,">="&DATE(YEAR(TODAY()),MONTH(TODAY())-11,1))) | F19: =IF(B19="","",SUMIFS(Income!$E$6:$E$1005,Income!$C$6:$C$1005,B19,Income!$B$6:$B$1005,">="&DATE(YEAR(TODAY()),1,1))) | G19: =IF(OR(B19="",N(D19)<=0),"",E19/D19) | H19: =IF(B19="","",E19/12) | J19: =IF(OR(B19="",N(E19)<=0),"",ROUND(E19*100,0)*1000+1000-ROW())
E20: =IF(B20="","",SUMIFS(Income!$E$6:$E$1005,Income!$C$6:$C$1005,B20,Income!$B$6:$B$1005,">="&DATE(YEAR(TODAY()),MONTH(TODAY())-11,1))) | F20: =IF(B20="","",SUMIFS(Income!$E$6:$E$1005,Income!$C$6:$C$1005,B20,Income!$B$6:$B$1005,">="&DATE(YEAR(TODAY()),1,1))) | G20: =IF(OR(B20="",N(D20)<=0),"",E20/D20) | H20: =IF(B20="","",E20/12) | J20: =IF(OR(B20="",N(E20)<=0),"",ROUND(E20*100,0)*1000+1000-ROW())
E21: =IF(B21="","",SUMIFS(Income!$E$6:$E$1005,Income!$C$6:$C$1005,B21,Income!$B$6:$B$1005,">="&DATE(YEAR(TODAY()),MONTH(TODAY())-11,1))) | F21: =IF(B21="","",SUMIFS(Income!$E$6:$E$1005,Income!$C$6:$C$1005,B21,Income!$B$6:$B$1005,">="&DATE(YEAR(TODAY()),1,1))) | G21: =IF(OR(B21="",N(D21)<=0),"",E21/D21) | H21: =IF(B21="","",E21/12) | J21: =IF(OR(B21="",N(E21)<=0),"",ROUND(E21*100,0)*1000+1000-ROW())
E22: =IF(B22="","",SUMIFS(Income!$E$6:$E$1005,Income!$C$6:$C$1005,B22,Income!$B$6:$B$1005,">="&DATE(YEAR(TODAY()),MONTH(TODAY())-11,1))) | F22: =IF(B22="","",SUMIFS(Income!$E$6:$E$1005,Income!$C$6:$C$1005,B22,Income!$B$6:$B$1005,">="&DATE(YEAR(TODAY()),1,1))) | G22: =IF(OR(B22="",N(D22)<=0),"",E22/D22) | H22: =IF(B22="","",E22/12) | J22: =IF(OR(B22="",N(E22)<=0),"",ROUND(E22*100,0)*1000+1000-ROW())
E23: =IF(B23="","",SUMIFS(Income!$E$6:$E$1005,Income!$C$6:$C$1005,B23,Income!$B$6:$B$1005,">="&DATE(YEAR(TODAY()),MONTH(TODAY())-11,1))) | F23: =IF(B23="","",SUMIFS(Income!$E$6:$E$1005,Income!$C$6:$C$1005,B23,Income!$B$6:$B$1005,">="&DATE(YEAR(TODAY()),1,1))) | G23: =IF(OR(B23="",N(D23)<=0),"",E23/D23) | H23: =IF(B23="","",E23/12) | J23: =IF(OR(B23="",N(E23)<=0),"",ROUND(E23*100,0)*1000+1000-ROW())
E24: =IF(B24="","",SUMIFS(Income!$E$6:$E$1005,Income!$C$6:$C$1005,B24,Income!$B$6:$B$1005,">="&DATE(YEAR(TODAY()),MONTH(TODAY())-11,1))) | F24: =IF(B24="","",SUMIFS(Income!$E$6:$E$1005,Income!$C$6:$C$1005,B24,Income!$B$6:$B$1005,">="&DATE(YEAR(TODAY()),1,1))) | G24: =IF(OR(B24="",N(D24)<=0),"",E24/D24) | H24: =IF(B24="","",E24/12) | J24: =IF(OR(B24="",N(E24)<=0),"",ROUND(E24*100,0)*1000+1000-ROW())
E25: =IF(B25="","",SUMIFS(Income!$E$6:$E$1005,Income!$C$6:$C$1005,B25,Income!$B$6:$B$1005,">="&DATE(YEAR(TODAY()),MONTH(TODAY())-11,1))) | F25: =IF(B25="","",SUMIFS(Income!$E$6:$E$1005,Income!$C$6:$C$1005,B25,Income!$B$6:$B$1005,">="&DATE(YEAR(TODAY()),1,1))) | G25: =IF(OR(B25="",N(D25)<=0),"",E25/D25) | H25: =IF(B25="","",E25/12) | J25: =IF(OR(B25="",N(E25)<=0),"",ROUND(E25*100,0)*1000+1000-ROW())
... E105: =IF(B105="","",SUMIFS(Income!$E$6:$E$1005,Income!$C$6:$C$1005,B105,Income!$B$6:$B$1005,">="&DATE(YEAR(TODAY()),MONTH(TODAY())-11,1))) | F105: =IF(B105="","",SUMIFS(Income!$E$6:$E$1005,Income!$C$6:$C$1005,B105,Income!$B$6:$B$1005,">="&DATE(YEAR(TODAY()),1,1))) | G105: =IF(OR(B105="",N(D105)<=0),"",E105/D105) | H105: =IF(B105="","",E105/12) | J105: =IF(OR(B105="",N(E105)<=0),"",ROUND(E105*100,0)*1000+1000-ROW())

Sheet Income
B2: Income
B3: Each dividend, interest payment or rent as it comes in.
B5: Date | C5: From | D5: Type | E5: Amount | F5: Note
B6: 45931 | C6: Spare room | D6: Rent | E6: 300 | G6: =IF(NOT(ISNUMBER(B6)),"",YEAR(B6)*100+MONTH(B6))
B7: 45935 | C7: Property fund | D7: Dividend | E7: 42 | G7: =IF(NOT(ISNUMBER(B7)),"",YEAR(B7)*100+MONTH(B7))
B8: 45958 | C8: Bond fund | D8: Dividend | E8: 55 | G8: =IF(NOT(ISNUMBER(B8)),"",YEAR(B8)*100+MONTH(B8))
B9: 45961 | C9: High yield savings | D9: Interest | E9: 33 | G9: =IF(NOT(ISNUMBER(B9)),"",YEAR(B9)*100+MONTH(B9))
B10: 45962 | C10: Spare room | D10: Rent | E10: 300 | G10: =IF(NOT(ISNUMBER(B10)),"",YEAR(B10)*100+MONTH(B10))
B11: 45966 | C11: Property fund | D11: Dividend | E11: 42 | G11: =IF(NOT(ISNUMBER(B11)),"",YEAR(B11)*100+MONTH(B11))
B12: 45989 | C12: Bond fund | D12: Dividend | E12: 55 | G12: =IF(NOT(ISNUMBER(B12)),"",YEAR(B12)*100+MONTH(B12))
B13: 45991 | C13: High yield savings | D13: Interest | E13: 33.4 | G13: =IF(NOT(ISNUMBER(B13)),"",YEAR(B13)*100+MONTH(B13))
B14: 45992 | C14: Spare room | D14: Rent | E14: 300 | G14: =IF(NOT(ISNUMBER(B14)),"",YEAR(B14)*100+MONTH(B14))
B15: 45996 | C15: Property fund | D15: Dividend | E15: 42 | G15: =IF(NOT(ISNUMBER(B15)),"",YEAR(B15)*100+MONTH(B15))
B16: 46006 | C16: Utility shares | D16: Dividend | E16: 95 | G16: =IF(NOT(ISNUMBER(B16)),"",YEAR(B16)*100+MONTH(B16))
B17: 46011 | C17: Dividend fund | D17: Dividend | E17: 175 | G17: =IF(NOT(ISNUMBER(B17)),"",YEAR(B17)*100+MONTH(B17))
... B66: 46293 | C66: Bond fund | D66: Dividend | E66: 55 | G66: =IF(NOT(ISNUMBER(B66)),"",YEAR(B66)*100+MONTH(B66))
G67: =IF(NOT(ISNUMBER(B67)),"",YEAR(B67)*100+MONTH(B67))
G68: =IF(NOT(ISNUMBER(B68)),"",YEAR(B68)*100+MONTH(B68))
G69: =IF(NOT(ISNUMBER(B69)),"",YEAR(B69)*100+MONTH(B69))
G70: =IF(NOT(ISNUMBER(B70)),"",YEAR(B70)*100+MONTH(B70))
G71: =IF(NOT(ISNUMBER(B71)),"",YEAR(B71)*100+MONTH(B71))
G72: =IF(NOT(ISNUMBER(B72)),"",YEAR(B72)*100+MONTH(B72))
G73: =IF(NOT(ISNUMBER(B73)),"",YEAR(B73)*100+MONTH(B73))
G74: =IF(NOT(ISNUMBER(B74)),"",YEAR(B74)*100+MONTH(B74))
G75: =IF(NOT(ISNUMBER(B75)),"",YEAR(B75)*100+MONTH(B75))
G76: =IF(NOT(ISNUMBER(B76)),"",YEAR(B76)*100+MONTH(B76))
G77: =IF(NOT(ISNUMBER(B77)),"",YEAR(B77)*100+MONTH(B77))
G78: =IF(NOT(ISNUMBER(B78)),"",YEAR(B78)*100+MONTH(B78))
... G1005: =IF(NOT(ISNUMBER(B1005)),"",YEAR(B1005)*100+MONTH(B1005))

Sheet Settings
B2: Settings
B3: The currency, the first month on Balances, and your passive income goal.
B4: Currency | C4: USD | E4: Amounts have no currency sign, so any currency works.
B5: First month on Balances | C5: 45931 | E5: Balances has 36 months from this one.
B6: Passive income goal a month | C6: 1000 | E6: Dividends, interest and rent together.

Sheet Start Here
B2: Start here
B3: Type only in the yellow cells.
B5: 1 | C5: Settings: the currency, the first month for Balances, and your passive income goal a month.
B7: 2 | C7: Balances: each account once with its type, then its balance at the end of every month.
B9: 3 | C9: Holdings: the funds, shares and accounts that pay you, with their value now.
B11: 4 | C11: Income: each dividend, interest payment or rent as it comes in.
B13: 5 | C13: Dashboard: your net worth month by month, and your passive income against the goal.
C16: The example accounts, holdings and amounts are made up. Delete them and add your own.
C18: Debts go in as the amount owed. Net worth is everything you own less everything you owe.
C20: Works in Google Sheets and Microsoft Excel, in any currency.
