Workbook

Sheet Dashboard
B2: Landlord dashboard
B3: Pick a year. Rent owed counts only rents whose due date and grace days have passed.
B4: Year | C4: 2026
B6: Rent received | C6: Rent owed now | D6: Expenses | E6: Net income | F6: Units let | G6: Deposits held
B7: =SUM('Rent roll'!$Q$6:$Q$25) | C7: =SUM('Rent roll'!$R$6:$R$25) | D7: =SUMIFS(Expenses!$E$6:$E$1005,Expenses!$B$6:$B$1005,">="&DATE($C$4,1,1),Expenses!$B$6:$B$1005,"<="&DATE($C$4,12,31)) | E7: =B7-D7 | F7: =COUNTIFS(Units!$K$6:$K$25,"Active")+COUNTIFS(Units!$K$6:$K$25,"Ends in*")&" of "&COUNTIFS(Units!$B$6:$B$25,"?*") | G7: =SUMIFS(Units!$J$6:$J$25,Units!$K$6:$K$25,"Active")+SUMIFS(Units!$J$6:$J$25,Units!$K$6:$K$25,"Ends in*")
B9: Month | C9: Rent due | D9: Received | E9: Expenses | F9: Net | I9: Needs attention
B10: Jan | C10: =SUM('Rent roll'!T6:T25) | D10: =SUM('Rent roll'!E6:E25) | E10: =SUMIFS(Expenses!$E$6:$E$1005,Expenses!$B$6:$B$1005,">="&DATE($C$4,1,1),Expenses!$B$6:$B$1005,"<="&EOMONTH(DATE($C$4,1,1),0)) | F10: =D10-E10 | I10: =IF(COUNTIFS('Rent roll'!$R$6:$R$25,">0")=0,"No rent is owed",IF(COUNTIFS('Rent roll'!$R$6:$R$25,">0")=1,"1 unit owes",COUNTIFS('Rent roll'!$R$6:$R$25,">0")&" units owe")&" rent: "&FIXED(SUM('Rent roll'!$R$6:$R$25),2))
B11: Feb | C11: =SUM('Rent roll'!U6:U25) | D11: =SUM('Rent roll'!F6:F25) | E11: =SUMIFS(Expenses!$E$6:$E$1005,Expenses!$B$6:$B$1005,">="&DATE($C$4,2,1),Expenses!$B$6:$B$1005,"<="&EOMONTH(DATE($C$4,2,1),0)) | F11: =D11-E11 | I11: =IF(COUNTIFS(Units!$K$6:$K$25,"Ends in*")=0,"No lease ends in the next 60 days",IF(COUNTIFS(Units!$K$6:$K$25,"Ends in*")=1,"1 lease ends",COUNTIFS(Units!$K$6:$K$25,"Ends in*")&" leases end")&" in the next 60 days")
B12: Mar | C12: =SUM('Rent roll'!V6:V25) | D12: =SUM('Rent roll'!G6:G25) | E12: =SUMIFS(Expenses!$E$6:$E$1005,Expenses!$B$6:$B$1005,">="&DATE($C$4,3,1),Expenses!$B$6:$B$1005,"<="&EOMONTH(DATE($C$4,3,1),0)) | F12: =D12-E12 | I12: =IF(COUNTIFS(Units!$K$6:$K$25,"Vacant")+COUNTIFS(Units!$K$6:$K$25,"Lease ended")=0,"Every unit is let",IF(COUNTIFS(Units!$K$6:$K$25,"Vacant")+COUNTIFS(Units!$K$6:$K$25,"Lease ended")=1,"1 unit is",COUNTIFS(Units!$K$6:$K$25,"Vacant")+COUNTIFS(Units!$K$6:$K$25,"Lease ended")&" units are")&" empty")
B13: Apr | C13: =SUM('Rent roll'!W6:W25) | D13: =SUM('Rent roll'!H6:H25) | E13: =SUMIFS(Expenses!$E$6:$E$1005,Expenses!$B$6:$B$1005,">="&DATE($C$4,4,1),Expenses!$B$6:$B$1005,"<="&EOMONTH(DATE($C$4,4,1),0)) | F13: =D13-E13 | I13: =IF(COUNTIFS('Rent roll'!$S$6:$S$25,"Part paid*")=0,"No part payments this month",IF(COUNTIFS('Rent roll'!$S$6:$S$25,"Part paid*")=1,"1 unit has",COUNTIFS('Rent roll'!$S$6:$S$25,"Part paid*")&" units have")&" paid part of this month")
B14: May | C14: =SUM('Rent roll'!X6:X25) | D14: =SUM('Rent roll'!I6:I25) | E14: =SUMIFS(Expenses!$E$6:$E$1005,Expenses!$B$6:$B$1005,">="&DATE($C$4,5,1),Expenses!$B$6:$B$1005,"<="&EOMONTH(DATE($C$4,5,1),0)) | F14: =D14-E14
B15: Jun | C15: =SUM('Rent roll'!Y6:Y25) | D15: =SUM('Rent roll'!J6:J25) | E15: =SUMIFS(Expenses!$E$6:$E$1005,Expenses!$B$6:$B$1005,">="&DATE($C$4,6,1),Expenses!$B$6:$B$1005,"<="&EOMONTH(DATE($C$4,6,1),0)) | F15: =D15-E15 | I15: Property | J15: Units | K15: Rent received | L15: Net
B16: Jul | C16: =SUM('Rent roll'!Z6:Z25) | D16: =SUM('Rent roll'!K6:K25) | E16: =SUMIFS(Expenses!$E$6:$E$1005,Expenses!$B$6:$B$1005,">="&DATE($C$4,7,1),Expenses!$B$6:$B$1005,"<="&EOMONTH(DATE($C$4,7,1),0)) | F16: =D16-E16 | I16: =IF(Settings!B6="","",Settings!B6) | J16: =IF(I16="","",COUNTIFS(Units!$C$6:$C$25,I16)) | K16: =IF(I16="","",SUMIFS('Rent roll'!$Q$6:$Q$25,'Rent roll'!$AR$6:$AR$25,I16)) | L16: =IF(I16="","",K16-SUMIFS(Expenses!$E$6:$E$1005,Expenses!$C$6:$C$1005,I16,Expenses!$B$6:$B$1005,">="&DATE($C$4,1,1),Expenses!$B$6:$B$1005,"<="&DATE($C$4,12,31)))
B17: Aug | C17: =SUM('Rent roll'!AA6:AA25) | D17: =SUM('Rent roll'!L6:L25) | E17: =SUMIFS(Expenses!$E$6:$E$1005,Expenses!$B$6:$B$1005,">="&DATE($C$4,8,1),Expenses!$B$6:$B$1005,"<="&EOMONTH(DATE($C$4,8,1),0)) | F17: =D17-E17 | I17: =IF(Settings!B7="","",Settings!B7) | J17: =IF(I17="","",COUNTIFS(Units!$C$6:$C$25,I17)) | K17: =IF(I17="","",SUMIFS('Rent roll'!$Q$6:$Q$25,'Rent roll'!$AR$6:$AR$25,I17)) | L17: =IF(I17="","",K17-SUMIFS(Expenses!$E$6:$E$1005,Expenses!$C$6:$C$1005,I17,Expenses!$B$6:$B$1005,">="&DATE($C$4,1,1),Expenses!$B$6:$B$1005,"<="&DATE($C$4,12,31)))
B18: Sep | C18: =SUM('Rent roll'!AB6:AB25) | D18: =SUM('Rent roll'!M6:M25) | E18: =SUMIFS(Expenses!$E$6:$E$1005,Expenses!$B$6:$B$1005,">="&DATE($C$4,9,1),Expenses!$B$6:$B$1005,"<="&EOMONTH(DATE($C$4,9,1),0)) | F18: =D18-E18 | I18: =IF(Settings!B8="","",Settings!B8) | J18: =IF(I18="","",COUNTIFS(Units!$C$6:$C$25,I18)) | K18: =IF(I18="","",SUMIFS('Rent roll'!$Q$6:$Q$25,'Rent roll'!$AR$6:$AR$25,I18)) | L18: =IF(I18="","",K18-SUMIFS(Expenses!$E$6:$E$1005,Expenses!$C$6:$C$1005,I18,Expenses!$B$6:$B$1005,">="&DATE($C$4,1,1),Expenses!$B$6:$B$1005,"<="&DATE($C$4,12,31)))
B19: Oct | C19: =SUM('Rent roll'!AC6:AC25) | D19: =SUM('Rent roll'!N6:N25) | E19: =SUMIFS(Expenses!$E$6:$E$1005,Expenses!$B$6:$B$1005,">="&DATE($C$4,10,1),Expenses!$B$6:$B$1005,"<="&EOMONTH(DATE($C$4,10,1),0)) | F19: =D19-E19 | I19: =IF(Settings!B9="","",Settings!B9) | J19: =IF(I19="","",COUNTIFS(Units!$C$6:$C$25,I19)) | K19: =IF(I19="","",SUMIFS('Rent roll'!$Q$6:$Q$25,'Rent roll'!$AR$6:$AR$25,I19)) | L19: =IF(I19="","",K19-SUMIFS(Expenses!$E$6:$E$1005,Expenses!$C$6:$C$1005,I19,Expenses!$B$6:$B$1005,">="&DATE($C$4,1,1),Expenses!$B$6:$B$1005,"<="&DATE($C$4,12,31)))
B20: Nov | C20: =SUM('Rent roll'!AD6:AD25) | D20: =SUM('Rent roll'!O6:O25) | E20: =SUMIFS(Expenses!$E$6:$E$1005,Expenses!$B$6:$B$1005,">="&DATE($C$4,11,1),Expenses!$B$6:$B$1005,"<="&EOMONTH(DATE($C$4,11,1),0)) | F20: =D20-E20 | I20: =IF(Settings!B10="","",Settings!B10) | J20: =IF(I20="","",COUNTIFS(Units!$C$6:$C$25,I20)) | K20: =IF(I20="","",SUMIFS('Rent roll'!$Q$6:$Q$25,'Rent roll'!$AR$6:$AR$25,I20)) | L20: =IF(I20="","",K20-SUMIFS(Expenses!$E$6:$E$1005,Expenses!$C$6:$C$1005,I20,Expenses!$B$6:$B$1005,">="&DATE($C$4,1,1),Expenses!$B$6:$B$1005,"<="&DATE($C$4,12,31)))
B21: Dec | C21: =SUM('Rent roll'!AE6:AE25) | D21: =SUM('Rent roll'!P6:P25) | E21: =SUMIFS(Expenses!$E$6:$E$1005,Expenses!$B$6:$B$1005,">="&DATE($C$4,12,1),Expenses!$B$6:$B$1005,"<="&EOMONTH(DATE($C$4,12,1),0)) | F21: =D21-E21 | I21: =IF(Settings!B11="","",Settings!B11) | J21: =IF(I21="","",COUNTIFS(Units!$C$6:$C$25,I21)) | K21: =IF(I21="","",SUMIFS('Rent roll'!$Q$6:$Q$25,'Rent roll'!$AR$6:$AR$25,I21)) | L21: =IF(I21="","",K21-SUMIFS(Expenses!$E$6:$E$1005,Expenses!$C$6:$C$1005,I21,Expenses!$B$6:$B$1005,">="&DATE($C$4,1,1),Expenses!$B$6:$B$1005,"<="&DATE($C$4,12,31)))
B22: Year | C22: =SUM(C10:C21) | D22: =SUM(D10:D21) | E22: =SUM(E10:E21) | F22: =SUM(F10:F21)
B23: Net is the rent received minus expenses. Rent due counts every month with an active lease.

Sheet Settings
B2: Settings
B3: Your properties and expense categories. The lists in the other tabs follow them.
B5: Properties (up to 6)
B6: 12 Oak Street | D6: A property can have several units. List the units on the Units tab.
B7: 8 River Road
B14: Expense categories
B15: Mortgage interest
B16: Insurance
B17: Property tax
B18: Repairs
B19: Maintenance
B20: Utilities
B21: HOA fees
B22: Management
B23: Legal and accounting
B24: Other

Sheet Units
B2: Units and leases
B3: One line per unit. The lease status updates by itself.
B5: Unit | C5: Property | D5: Tenant | E5: Rent | F5: Due day | G5: Grace days | H5: Lease start | I5: Lease end | J5: Deposit | K5: Lease status | L5: Note
B6: Oak Street, apt 1 | C6: 12 Oak Street | D6: Maria L. | E6: 1150 | F6: 1 | G6: 5 | H6: 45809 | I6: 46538 | J6: 1150 | K6: =IF(B6="","",IF(D6="","Vacant",IF(AND(I6<>"",I6<TODAY()),"Lease ended",IF(AND(I6<>"",(I6-TODAY())<=60),"Ends in "&(I6-TODAY())&IF((I6-TODAY())=1," day"," days"),"Active"))))
B7: Oak Street, apt 2 | C7: 12 Oak Street | D7: James T. | E7: 1200 | F7: 1 | G7: 5 | H7: 45962 | I7: 46326 | J7: 1200 | K7: =IF(B7="","",IF(D7="","Vacant",IF(AND(I7<>"",I7<TODAY()),"Lease ended",IF(AND(I7<>"",(I7-TODAY())<=60),"Ends in "&(I7-TODAY())&IF((I7-TODAY())=1," day"," days"),"Active"))))
B8: Oak Street, apt 3 | C8: 12 Oak Street | D8: Kevin P. | E8: 950 | F8: 1 | G8: 5 | H8: 45689 | I8: 46234 | J8: 950 | K8: =IF(B8="","",IF(D8="","Vacant",IF(AND(I8<>"",I8<TODAY()),"Lease ended",IF(AND(I8<>"",(I8-TODAY())<=60),"Ends in "&(I8-TODAY())&IF((I8-TODAY())=1," day"," days"),"Active"))))
B9: River Road house | C9: 8 River Road | D9: Priya S. | E9: 1800 | F9: 1 | G9: 5 | H9: 45536 | J9: 1800 | K9: =IF(B9="","",IF(D9="","Vacant",IF(AND(I9<>"",I9<TODAY()),"Lease ended",IF(AND(I9<>"",(I9-TODAY())<=60),"Ends in "&(I9-TODAY())&IF((I9-TODAY())=1," day"," days"),"Active"))))
K10: =IF(B10="","",IF(D10="","Vacant",IF(AND(I10<>"",I10<TODAY()),"Lease ended",IF(AND(I10<>"",(I10-TODAY())<=60),"Ends in "&(I10-TODAY())&IF((I10-TODAY())=1," day"," days"),"Active"))))
K11: =IF(B11="","",IF(D11="","Vacant",IF(AND(I11<>"",I11<TODAY()),"Lease ended",IF(AND(I11<>"",(I11-TODAY())<=60),"Ends in "&(I11-TODAY())&IF((I11-TODAY())=1," day"," days"),"Active"))))
K12: =IF(B12="","",IF(D12="","Vacant",IF(AND(I12<>"",I12<TODAY()),"Lease ended",IF(AND(I12<>"",(I12-TODAY())<=60),"Ends in "&(I12-TODAY())&IF((I12-TODAY())=1," day"," days"),"Active"))))
K13: =IF(B13="","",IF(D13="","Vacant",IF(AND(I13<>"",I13<TODAY()),"Lease ended",IF(AND(I13<>"",(I13-TODAY())<=60),"Ends in "&(I13-TODAY())&IF((I13-TODAY())=1," day"," days"),"Active"))))
K14: =IF(B14="","",IF(D14="","Vacant",IF(AND(I14<>"",I14<TODAY()),"Lease ended",IF(AND(I14<>"",(I14-TODAY())<=60),"Ends in "&(I14-TODAY())&IF((I14-TODAY())=1," day"," days"),"Active"))))
K15: =IF(B15="","",IF(D15="","Vacant",IF(AND(I15<>"",I15<TODAY()),"Lease ended",IF(AND(I15<>"",(I15-TODAY())<=60),"Ends in "&(I15-TODAY())&IF((I15-TODAY())=1," day"," days"),"Active"))))
K16: =IF(B16="","",IF(D16="","Vacant",IF(AND(I16<>"",I16<TODAY()),"Lease ended",IF(AND(I16<>"",(I16-TODAY())<=60),"Ends in "&(I16-TODAY())&IF((I16-TODAY())=1," day"," days"),"Active"))))
K17: =IF(B17="","",IF(D17="","Vacant",IF(AND(I17<>"",I17<TODAY()),"Lease ended",IF(AND(I17<>"",(I17-TODAY())<=60),"Ends in "&(I17-TODAY())&IF((I17-TODAY())=1," day"," days"),"Active"))))
K18: =IF(B18="","",IF(D18="","Vacant",IF(AND(I18<>"",I18<TODAY()),"Lease ended",IF(AND(I18<>"",(I18-TODAY())<=60),"Ends in "&(I18-TODAY())&IF((I18-TODAY())=1," day"," days"),"Active"))))
K19: =IF(B19="","",IF(D19="","Vacant",IF(AND(I19<>"",I19<TODAY()),"Lease ended",IF(AND(I19<>"",(I19-TODAY())<=60),"Ends in "&(I19-TODAY())&IF((I19-TODAY())=1," day"," days"),"Active"))))
K20: =IF(B20="","",IF(D20="","Vacant",IF(AND(I20<>"",I20<TODAY()),"Lease ended",IF(AND(I20<>"",(I20-TODAY())<=60),"Ends in "&(I20-TODAY())&IF((I20-TODAY())=1," day"," days"),"Active"))))
K21: =IF(B21="","",IF(D21="","Vacant",IF(AND(I21<>"",I21<TODAY()),"Lease ended",IF(AND(I21<>"",(I21-TODAY())<=60),"Ends in "&(I21-TODAY())&IF((I21-TODAY())=1," day"," days"),"Active"))))
... K25: =IF(B25="","",IF(D25="","Vacant",IF(AND(I25<>"",I25<TODAY()),"Lease ended",IF(AND(I25<>"",(I25-TODAY())<=60),"Ends in "&(I25-TODAY())&IF((I25-TODAY())=1," day"," days"),"Active"))))
B27: When a tenant leaves, keep the line and its lease end date so the past months stay right.

Sheet Rent log
B2: Rent received
B3: One line per payment. Leave 'For month' empty when it is for the month it arrives in.
B5: Date received | C5: Unit | D5: Amount | E5: For month | F5: Method | G5: Note
B6: 46023 | C6: Oak Street, apt 2 | D6: 1200 | F6: Bank transfer | H6: =IF(B6="","",IF(E6="",B6,E6))
B7: 46024 | C7: Oak Street, apt 1 | D7: 1150 | F7: Bank transfer | H7: =IF(B7="","",IF(E7="",B7,E7))
B8: 46025 | C8: Oak Street, apt 3 | D8: 950 | F8: Check | H8: =IF(B8="","",IF(E8="",B8,E8))
B9: 46026 | C9: River Road house | D9: 1800 | E9: 46023 | F9: App | H9: =IF(B9="","",IF(E9="",B9,E9))
B10: 46054 | C10: Oak Street, apt 2 | D10: 1200 | F10: Bank transfer | H10: =IF(B10="","",IF(E10="",B10,E10))
B11: 46055 | C11: Oak Street, apt 1 | D11: 1150 | F11: Bank transfer | H11: =IF(B11="","",IF(E11="",B11,E11))
B12: 46056 | C12: Oak Street, apt 3 | D12: 950 | F12: Check | H12: =IF(B12="","",IF(E12="",B12,E12))
B13: 46057 | C13: River Road house | D13: 1800 | E13: 46054 | F13: App | H13: =IF(B13="","",IF(E13="",B13,E13))
B14: 46082 | C14: Oak Street, apt 2 | D14: 1200 | F14: Bank transfer | H14: =IF(B14="","",IF(E14="",B14,E14))
B15: 46083 | C15: Oak Street, apt 1 | D15: 1150 | F15: Bank transfer | H15: =IF(B15="","",IF(E15="",B15,E15))
B16: 46084 | C16: Oak Street, apt 3 | D16: 950 | F16: Check | H16: =IF(B16="","",IF(E16="",B16,E16))
B17: 46085 | C17: River Road house | D17: 1800 | E17: 46082 | F17: App | H17: =IF(B17="","",IF(E17="",B17,E17))
B18: 46113 | C18: Oak Street, apt 2 | D18: 1200 | F18: Bank transfer | H18: =IF(B18="","",IF(E18="",B18,E18))
B19: 46114 | C19: Oak Street, apt 1 | D19: 1150 | F19: Bank transfer | H19: =IF(B19="","",IF(E19="",B19,E19))
B20: 46115 | C20: Oak Street, apt 3 | D20: 950 | F20: Check | H20: =IF(B20="","",IF(E20="",B20,E20))
B21: 46116 | C21: River Road house | D21: 1800 | E21: 46113 | F21: App | H21: =IF(B21="","",IF(E21="",B21,E21))
B22: 46143 | C22: Oak Street, apt 2 | D22: 1200 | F22: Bank transfer | H22: =IF(B22="","",IF(E22="",B22,E22))
B23: 46144 | C23: Oak Street, apt 1 | D23: 1150 | F23: Bank transfer | H23: =IF(B23="","",IF(E23="",B23,E23))
B24: 46145 | C24: Oak Street, apt 3 | D24: 950 | F24: Check | H24: =IF(B24="","",IF(E24="",B24,E24))
B25: 46146 | C25: River Road house | D25: 1800 | E25: 46143 | F25: App | H25: =IF(B25="","",IF(E25="",B25,E25))
B26: 46174 | C26: Oak Street, apt 2 | D26: 1200 | F26: Bank transfer | H26: =IF(B26="","",IF(E26="",B26,E26))
B27: 46175 | C27: Oak Street, apt 1 | D27: 1150 | F27: Bank transfer | H27: =IF(B27="","",IF(E27="",B27,E27))
B28: 46176 | C28: Oak Street, apt 3 | D28: 950 | F28: Check | H28: =IF(B28="","",IF(E28="",B28,E28))
B29: 46185 | C29: River Road house | D29: 1800 | E29: 46174 | F29: App | G29: Paid late | H29: =IF(B29="","",IF(E29="",B29,E29))
B30: 46204 | C30: Oak Street, apt 2 | D30: 1200 | F30: Bank transfer | H30: =IF(B30="","",IF(E30="",B30,E30))
B31: 46205 | C31: Oak Street, apt 1 | D31: 1150 | F31: Bank transfer | H31: =IF(B31="","",IF(E31="",B31,E31))
B32: 46206 | C32: Oak Street, apt 3 | D32: 950 | F32: Check | H32: =IF(B32="","",IF(E32="",B32,E32))
B33: 46207 | C33: River Road house | D33: 1800 | E33: 46204 | F33: App | H33: =IF(B33="","",IF(E33="",B33,E33))
B34: 46235 | C34: Oak Street, apt 2 | D34: 1200 | F34: Bank transfer | H34: =IF(B34="","",IF(E34="",B34,E34))
B35: 46236 | C35: Oak Street, apt 1 | D35: 1150 | F35: Bank transfer | H35: =IF(B35="","",IF(E35="",B35,E35))
B36: 46238 | C36: River Road house | D36: 1800 | E36: 46235 | F36: App | H36: =IF(B36="","",IF(E36="",B36,E36))
B37: 46266 | C37: Oak Street, apt 2 | D37: 600 | F37: Bank transfer | G37: Paid half, rest promised | H37: =IF(B37="","",IF(E37="",B37,E37))
B38: 46267 | C38: Oak Street, apt 1 | D38: 1150 | F38: Bank transfer | H38: =IF(B38="","",IF(E38="",B38,E38))
B39: 46269 | C39: River Road house | D39: 1800 | E39: 46266 | F39: App | H39: =IF(B39="","",IF(E39="",B39,E39))
H40: =IF(B40="","",IF(E40="",B40,E40))
H41: =IF(B41="","",IF(E41="",B41,E41))
H42: =IF(B42="","",IF(E42="",B42,E42))
H43: =IF(B43="","",IF(E43="",B43,E43))
H44: =IF(B44="","",IF(E44="",B44,E44))
H45: =IF(B45="","",IF(E45="",B45,E45))
H46: =IF(B46="","",IF(E46="",B46,E46))
H47: =IF(B47="","",IF(E47="",B47,E47))
H48: =IF(B48="","",IF(E48="",B48,E48))
H49: =IF(B49="","",IF(E49="",B49,E49))
H50: =IF(B50="","",IF(E50="",B50,E50))
H51: =IF(B51="","",IF(E51="",B51,E51))
... H1005: =IF(B1005="","",IF(E1005="",B1005,E1005))

Sheet Expenses
B2: Expenses
B3: One line per cost, with the property it belongs to.
B5: Date | C5: Property | D5: Category | E5: Amount | F5: Note
B6: 46027 | C6: 12 Oak Street | D6: Mortgage interest | E6: 1100
B7: 46027 | C7: 8 River Road | D7: Mortgage interest | E7: 650
B8: 46036 | C8: 12 Oak Street | D8: Repairs | E8: 480 | F8: Boiler repair
B9: 46058 | C9: 12 Oak Street | D9: Mortgage interest | E9: 1100
B10: 46058 | C10: 8 River Road | D10: Mortgage interest | E10: 650
B11: 46063 | C11: 12 Oak Street | D11: Insurance | E11: 1200 | F11: Building insurance, yearly
B12: 46086 | C12: 12 Oak Street | D12: Mortgage interest | E12: 1100
B13: 46086 | C13: 8 River Road | D13: Mortgage interest | E13: 650
B14: 46091 | C14: 8 River Road | D14: Insurance | E14: 900 | F14: Home insurance, yearly
B15: 46117 | C15: 12 Oak Street | D15: Mortgage interest | E15: 1100
B16: 46117 | C16: 8 River Road | D16: Mortgage interest | E16: 650
B17: 46127 | C17: 12 Oak Street | D17: Property tax | E17: 2400 | F17: First half
B18: 46134 | C18: 8 River Road | D18: Maintenance | E18: 150 | F18: Gutter cleaning
B19: 46147 | C19: 12 Oak Street | D19: Mortgage interest | E19: 1100
B20: 46147 | C20: 8 River Road | D20: Mortgage interest | E20: 650
B21: 46157 | C21: 8 River Road | D21: Property tax | E21: 1600 | F21: Yearly
B22: 46178 | C22: 12 Oak Street | D22: Mortgage interest | E22: 1100
B23: 46178 | C23: 8 River Road | D23: Mortgage interest | E23: 650
B24: 46208 | C24: 12 Oak Street | D24: Mortgage interest | E24: 1100
B25: 46208 | C25: 8 River Road | D25: Mortgage interest | E25: 650
B26: 46239 | C26: 12 Oak Street | D26: Mortgage interest | E26: 1100
B27: 46239 | C27: 8 River Road | D27: Mortgage interest | E27: 650
B28: 46252 | C28: 12 Oak Street | D28: Repairs | E28: 650 | F28: Paint apt 3 between tenants
B29: 46263 | C29: 12 Oak Street | D29: Legal and accounting | E29: 120 | F29: New lease template
B30: 46270 | C30: 12 Oak Street | D30: Mortgage interest | E30: 1100
B31: 46270 | C31: 8 River Road | D31: Mortgage interest | E31: 650

Sheet Rent roll
B2: Rent roll
B3: Rent received per unit and month for the year on the Dashboard.
B5: Unit | C5: Tenant | D5: Rent | E5: Jan | F5: Feb | G5: Mar | H5: Apr | I5: May | J5: Jun | K5: Jul | L5: Aug | M5: Sep | N5: Oct | O5: Nov | P5: Dec | Q5: Received | R5: Owed now | S5: This month
B6: =IF(Units!B6="","",Units!B6) | C6: =IF(B6="","",Units!D6) | D6: =IF(B6="","",Units!E6) | E6: =IF($B6="","",IF(AND(SUMIFS('Rent log'!$D$6:$D$1005,'Rent log'!$C$6:$C$1005,$B6,'Rent log'!$H$6:$H$1005,">="&DATE(Dashboard!$C$4,1,1),'Rent log'!$H$6:$H$1005,"<="&EOMONTH(DATE(Dashboard!$C$4,1,1),0))=0,DATE(Dashboard!$C$4,1,1)>TODAY()),"",SUMIFS('Rent log'!$D$6:$D$1005,'Rent log'!$C$6:$C$1005,$B6,'Rent log'!$H$6:$H$1005,">="&DATE(Dashboard!$C$4,1,1),'Rent log'!$H$6:$H$1005,"<="&EOMONTH(DATE(Dashboard!$C$4,1,1),0)))) | F6: =IF($B6="","",IF(AND(SUMIFS('Rent log'!$D$6:$D$1005,'Rent log'!$C$6:$C$1005,$B6,'Rent log'!$H$6:$H$1005,">="&DATE(Dashboard!$C$4,2,1),'Rent log'!$H$6:$H$1005,"<="&EOMONTH(DATE(Dashboard!$C$4,2,1),0))=0,DATE(Dashboard!$C$4,2,1)>TODAY()),"",SUMIFS('Rent log'!$D$6:$D$1005,'Rent log'!$C$6:$C$1005,$B6,'Rent log'!$H$6:$H$1005,">="&DATE(Dashboard!$C$4,2,1),'Rent log'!$H$6:$H$1005,"<="&EOMONTH(DATE(Dashboard!$C$4,2,1),0)))) | G6: =IF($B6="","",IF(AND(SUMIFS('Rent log'!$D$6:$D$1005,'Rent log'!$C$6:$C$1005,$B6,'Rent log'!$H$6:$H$1005,">="&DATE(Dashboard!$C$4,3,1),'Rent log'!$H$6:$H$1005,"<="&EOMONTH(DATE(Dashboard!$C$4,3,1),0))=0,DATE(Dashboard!$C$4,3,1)>TODAY()),"",SUMIFS('Rent log'!$D$6:$D$1005,'Rent log'!$C$6:$C$1005,$B6,'Rent log'!$H$6:$H$1005,">="&DATE(Dashboard!$C$4,3,1),'Rent log'!$H$6:$H$1005,"<="&EOMONTH(DATE(Dashboard!$C$4,3,1),0)))) | H6: =IF($B6="","",IF(AND(SUMIFS('Rent log'!$D$6:$D$1005,'Rent log'!$C$6:$C$1005,$B6,'Rent log'!$H$6:$H$1005,">="&DATE(Dashboard!$C$4,4,1),'Rent log'!$H$6:$H$1005,"<="&EOMONTH(DATE(Dashboard!$C$4,4,1),0))=0,DATE(Dashboard!$C$4,4,1)>TODAY()),"",SUMIFS('Rent log'!$D$6:$D$1005,'Rent log'!$C$6:$C$1005,$B6,'Rent log'!$H$6:$H$1005,">="&DATE(Dashboard!$C$4,4,1),'Rent log'!$H$6:$H$1005,"<="&EOMONTH(DATE(Dashboard!$C$4,4,1),0)))) | I6: =IF($B6="","",IF(AND(SUMIFS('Rent log'!$D$6:$D$1005,'Rent log'!$C$6:$C$1005,$B6,'Rent log'!$H$6:$H$1005,">="&DATE(Dashboard!$C$4,5,1),'Rent log'!$H$6:$H$1005,"<="&EOMONTH(DATE(Dashboard!$C$4,5,1),0))=0,DATE(Dashboard!$C$4,5,1)>TODAY()),"",SUMIFS('Rent log'!$D$6:$D$1005,'Rent log'!$C$6:$C$1005,$B6,'Rent log'!$H$6:$H$1005,">="&DATE(Dashboard!$C$4,5,1),'Rent log'!$H$6:$H$1005,"<="&EOMONTH(DATE(Dashboard!$C$4,5,1),0)))) | J6: =IF($B6="","",IF(AND(SUMIFS('Rent log'!$D$6:$D$1005,'Rent log'!$C$6:$C$1005,$B6,'Rent log'!$H$6:$H$1005,">="&DATE(Dashboard!$C$4,6,1),'Rent log'!$H$6:$H$1005,"<="&EOMONTH(DATE(Dashboard!$C$4,6,1),0))=0,DATE(Dashboard!$C$4,6,1)>TODAY()),"",SUMIFS('Rent log'!$D$6:$D$1005,'Rent log'!$C$6:$C$1005,$B6,'Rent log'!$H$6:$H$1005,">="&DATE(Dashboard!$C$4,6,1),'Rent log'!$H$6:$H$1005,"<="&EOMONTH(DATE(Dashboard!$C$4,6,1),0)))) | K6: =IF($B6="","",IF(AND(SUMIFS('Rent log'!$D$6:$D$1005,'Rent log'!$C$6:$C$1005,$B6,'Rent log'!$H$6:$H$1005,">="&DATE(Dashboard!$C$4,7,1),'Rent log'!$H$6:$H$1005,"<="&EOMONTH(DATE(Dashboard!$C$4,7,1),0))=0,DATE(Dashboard!$C$4,7,1)>TODAY()),"",SUMIFS('Rent log'!$D$6:$D$1005,'Rent log'!$C$6:$C$1005,$B6,'Rent log'!$H$6:$H$1005,">="&DATE(Dashboard!$C$4,7,1),'Rent log'!$H$6:$H$1005,"<="&EOMONTH(DATE(Dashboard!$C$4,7,1),0)))) | L6: =IF($B6="","",IF(AND(SUMIFS('Rent log'!$D$6:$D$1005,'Rent log'!$C$6:$C$1005,$B6,'Rent log'!$H$6:$H$1005,">="&DATE(Dashboard!$C$4,8,1),'Rent log'!$H$6:$H$1005,"<="&EOMONTH(DATE(Dashboard!$C$4,8,1),0))=0,DATE(Dashboard!$C$4,8,1)>TODAY()),"",SUMIFS('Rent log'!$D$6:$D$1005,'Rent log'!$C$6:$C$1005,$B6,'Rent log'!$H$6:$H$1005,">="&DATE(Dashboard!$C$4,8,1),'Rent log'!$H$6:$H$1005,"<="&EOMONTH(DATE(Dashboard!$C$4,8,1),0)))) | M6: =IF($B6="","",IF(AND(SUMIFS('Rent log'!$D$6:$D$1005,'Rent log'!$C$6:$C$1005,$B6,'Rent log'!$H$6:$H$1005,">="&DATE(Dashboard!$C$4,9,1),'Rent log'!$H$6:$H$1005,"<="&EOMONTH(DATE(Dashboard!$C$4,9,1),0))=0,DATE(Dashboard!$C$4,9,1)>TODAY()),"",SUMIFS('Rent log'!$D$6:$D$1005,'Rent log'!$C$6:$C$1005,$B6,'Rent log'!$H$6:$H$1005,">="&DATE(Dashboard!$C$4,9,1),'Rent log'!$H$6:$H$1005,"<="&EOMONTH(DATE(Dashboard!$C$4,9,1),0)))) | N6: =IF($B6="","",IF(AND(SUMIFS('Rent log'!$D$6:$D$1005,'Rent log'!$C$6:$C$1005,$B6,'Rent log'!$H$6:$H$1005,">="&DATE(Dashboard!$C$4,10,1),'Rent log'!$H$6:$H$1005,"<="&EOMONTH(DATE(Dashboard!$C$4,10,1),0))=0,DATE(Dashboard!$C$4,10,1)>TODAY()),"",SUMIFS('Rent log'!$D$6:$D$1005,'Rent log'!$C$6:$C$1005,$B6,'Rent log'!$H$6:$H$1005,">="&DATE(Dashboard!$C$4,10,1),'Rent log'!$H$6:$H$1005,"<="&EOMONTH(DATE(Dashboard!$C$4,10,1),0)))) | O6: =IF($B6="","",IF(AND(SUMIFS('Rent log'!$D$6:$D$1005,'Rent log'!$C$6:$C$1005,$B6,'Rent log'!$H$6:$H$1005,">="&DATE(Dashboard!$C$4,11,1),'Rent log'!$H$6:$H$1005,"<="&EOMONTH(DATE(Dashboard!$C$4,11,1),0))=0,DATE(Dashboard!$C$4,11,1)>TODAY()),"",SUMIFS('Rent log'!$D$6:$D$1005,'Rent log'!$C$6:$C$1005,$B6,'Rent log'!$H$6:$H$1005,">="&DATE(Dashboard!$C$4,11,1),'Rent log'!$H$6:$H$1005,"<="&EOMONTH(DATE(Dashboard!$C$4,11,1),0)))) | P6: =IF($B6="","",IF(AND(SUMIFS('Rent log'!$D$6:$D$1005,'Rent log'!$C$6:$C$1005,$B6,'Rent log'!$H$6:$H$1005,">="&DATE(Dashboard!$C$4,12,1),'Rent log'!$H$6:$H$1005,"<="&EOMONTH(DATE(Dashboard!$C$4,12,1),0))=0,DATE(Dashboard!$C$4,12,1)>TODAY()),"",SUMIFS('Rent log'!$D$6:$D$1005,'Rent log'!$C$6:$C$1005,$B6,'Rent log'!$H$6:$H$1005,">="&DATE(Dashboard!$C$4,12,1),'Rent log'!$H$6:$H$1005,"<="&EOMONTH(DATE(Dashboard!$C$4,12,1),0)))) | Q6: =IF(B6="","",SUM(E6:P6)) | R6: =IF(B6="","",SUM(AF6:AQ6)) | S6: =IF(B6="","",IF(Dashboard!$C$4<>YEAR(TODAY()),"",IF(INDEX(T6:AE6,MONTH(TODAY()))=0,"No rent due",IF(N(INDEX(E6:P6,MONTH(TODAY())))>=INDEX(T6:AE6,MONTH(TODAY())),"Paid",IF(TODAY()>DATE(YEAR(TODAY()),MONTH(TODAY()),MIN(N(Units!$F6)+(N(Units!$F6)=0),DAY(EOMONTH(TODAY(),0))))+N(Units!$G6),"Late: "&FIXED(INDEX(T6:AE6,MONTH(TODAY()))-N(INDEX(E6:P6,MONTH(TODAY()))),2)&" owed",IF(N(INDEX(E6:P6,MONTH(TODAY())))>0,"Part paid: "&FIXED(INDEX(T6:AE6,MONTH(TODAY()))-N(INDEX(E6:P6,MONTH(TODAY()))),2)&" left","Due on the "&MIN(N(Units!$F6)+(N(Units!$F6)=0),DAY(EOMONTH(TODAY(),0)))&IF(AND(MIN(N(Units!$F6)+(N(Units!$F6)=0),DAY(EOMONTH(TODAY(),0)))>=11,MIN(N(Units!$F6)+(N(Units!$F6)=0),DAY(EOMONTH(TODAY(),0)))<=13),"th",IF(MOD(MIN(N(Units!$F6)+(N(Units!$F6)=0),DAY(EOMONTH(TODAY(),0))),10)=1,"st",IF(MOD(MIN(N(Units!$F6)+(N(Units!$F6)=0),DAY(EOMONTH(TODAY(),0))),10)=2,"nd",IF(MOD(MIN(N(Units!$F6)+(N(Units!$F6)=0),DAY(EOMONTH(TODAY(),0))),10)=3,"rd","th")))))))))) | T6: =IF($B6="",0,IF(AND(OR(Units!$H6="",Units!$H6<=EOMONTH(DATE(Dashboard!$C$4,1,1),0)),OR(Units!$I6="",Units!$I6>=DATE(Dashboard!$C$4,1,1))),N(Units!$E6),0)) | U6: =IF($B6="",0,IF(AND(OR(Units!$H6="",Units!$H6<=EOMONTH(DATE(Dashboard!$C$4,2,1),0)),OR(Units!$I6="",Units!$I6>=DATE(Dashboard!$C$4,2,1))),N(Units!$E6),0)) | V6: =IF($B6="",0,IF(AND(OR(Units!$H6="",Units!$H6<=EOMONTH(DATE(Dashboard!$C$4,3,1),0)),OR(Units!$I6="",Units!$I6>=DATE(Dashboard!$C$4,3,1))),N(Units!$E6),0)) | W6: =IF($B6="",0,IF(AND(OR(Units!$H6="",Units!$H6<=EOMONTH(DATE(Dashboard!$C$4,4,1),0)),OR(Units!$I6="",Units!$I6>=DATE(Dashboard!$C$4,4,1))),N(Units!$E6),0)) | X6: =IF($B6="",0,IF(AND(OR(Units!$H6="",Units!$H6<=EOMONTH(DATE(Dashboard!$C$4,5,1),0)),OR(Units!$I6="",Units!$I6>=DATE(Dashboard!$C$4,5,1))),N(Units!$E6),0)) | Y6: =IF($B6="",0,IF(AND(OR(Units!$H6="",Units!$H6<=EOMONTH(DATE(Dashboard!$C$4,6,1),0)),OR(Units!$I6="",Units!$I6>=DATE(Dashboard!$C$4,6,1))),N(Units!$E6),0)) | Z6: =IF($B6="",0,IF(AND(OR(Units!$H6="",Units!$H6<=EOMONTH(DATE(Dashboard!$C$4,7,1),0)),OR(Units!$I6="",Units!$I6>=DATE(Dashboard!$C$4,7,1))),N(Units!$E6),0)) | AA6: =IF($B6="",0,IF(AND(OR(Units!$H6="",Units!$H6<=EOMONTH(DATE(Dashboard!$C$4,8,1),0)),OR(Units!$I6="",Units!$I6>=DATE(Dashboard!$C$4,8,1))),N(Units!$E6),0)) | AB6: =IF($B6="",0,IF(AND(OR(Units!$H6="",Units!$H6<=EOMONTH(DATE(Dashboard!$C$4,9,1),0)),OR(Units!$I6="",Units!$I6>=DATE(Dashboard!$C$4,9,1))),N(Units!$E6),0)) | AC6: =IF($B6="",0,IF(AND(OR(Units!$H6="",Units!$H6<=EOMONTH(DATE(Dashboard!$C$4,10,1),0)),OR(Units!$I6="",Units!$I6>=DATE(Dashboard!$C$4,10,1))),N(Units!$E6),0)) | AD6: =IF($B6="",0,IF(AND(OR(Units!$H6="",Units!$H6<=EOMONTH(DATE(Dashboard!$C$4,11,1),0)),OR(Units!$I6="",Units!$I6>=DATE(Dashboard!$C$4,11,1))),N(Units!$E6),0)) | AE6: =IF($B6="",0,IF(AND(OR(Units!$H6="",Units!$H6<=EOMONTH(DATE(Dashboard!$C$4,12,1),0)),OR(Units!$I6="",Units!$I6>=DATE(Dashboard!$C$4,12,1))),N(Units!$E6),0)) | AF6: =IF(AND(T6>0,DATE(Dashboard!$C$4,1,MIN(N(Units!$F6)+(N(Units!$F6)=0),DAY(EOMONTH(DATE(Dashboard!$C$4,1,1),0))))+N(Units!$G6)<TODAY()),MAX(0,T6-N(E6)),0) | AG6: =IF(AND(U6>0,DATE(Dashboard!$C$4,2,MIN(N(Units!$F6)+(N(Units!$F6)=0),DAY(EOMONTH(DATE(Dashboard!$C$4,2,1),0))))+N(Units!$G6)<TODAY()),MAX(0,U6-N(F6)),0) | AH6: =IF(AND(V6>0,DATE(Dashboard!$C$4,3,MIN(N(Units!$F6)+(N(Units!$F6)=0),DAY(EOMONTH(DATE(Dashboard!$C$4,3,1),0))))+N(Units!$G6)<TODAY()),MAX(0,V6-N(G6)),0) | AI6: =IF(AND(W6>0,DATE(Dashboard!$C$4,4,MIN(N(Units!$F6)+(N(Units!$F6)=0),DAY(EOMONTH(DATE(Dashboard!$C$4,4,1),0))))+N(Units!$G6)<TODAY()),MAX(0,W6-N(H6)),0) | AJ6: =IF(AND(X6>0,DATE(Dashboard!$C$4,5,MIN(N(Units!$F6)+(N(Units!$F6)=0),DAY(EOMONTH(DATE(Dashboard!$C$4,5,1),0))))+N(Units!$G6)<TODAY()),MAX(0,X6-N(I6)),0) | AK6: =IF(AND(Y6>0,DATE(Dashboard!$C$4,6,MIN(N(Units!$F6)+(N(Units!$F6)=0),DAY(EOMONTH(DATE(Dashboard!$C$4,6,1),0))))+N(Units!$G6)<TODAY()),MAX(0,Y6-N(J6)),0) | AL6: =IF(AND(Z6>0,DATE(Dashboard!$C$4,7,MIN(N(Units!$F6)+(N(Units!$F6)=0),DAY(EOMONTH(DATE(Dashboard!$C$4,7,1),0))))+N(Units!$G6)<TODAY()),MAX(0,Z6-N(K6)),0) | AM6: =IF(AND(AA6>0,DATE(Dashboard!$C$4,8,MIN(N(Units!$F6)+(N(Units!$F6)=0),DAY(EOMONTH(DATE(Dashboard!$C$4,8,1),0))))+N(Units!$G6)<TODAY()),MAX(0,AA6-N(L6)),0) | AN6: =IF(AND(AB6>0,DATE(Dashboard!$C$4,9,MIN(N(Units!$F6)+(N(Units!$F6)=0),DAY(EOMONTH(DATE(Dashboard!$C$4,9,1),0))))+N(Units!$G6)<TODAY()),MAX(0,AB6-N(M6)),0) | AO6: =IF(AND(AC6>0,DATE(Dashboard!$C$4,10,MIN(N(Units!$F6)+(N(Units!$F6)=0),DAY(EOMONTH(DATE(Dashboard!$C$4,10,1),0))))+N(Units!$G6)<TODAY()),MAX(0,AC6-N(N6)),0) | AP6: =IF(AND(AD6>0,DATE(Dashboard!$C$4,11,MIN(N(Units!$F6)+(N(Units!$F6)=0),DAY(EOMONTH(DATE(Dashboard!$C$4,11,1),0))))+N(Units!$G6)<TODAY()),MAX(0,AD6-N(O6)),0) | AQ6: =IF(AND(AE6>0,DATE(Dashboard!$C$4,12,MIN(N(Units!$F6)+(N(Units!$F6)=0),DAY(EOMONTH(DATE(Dashboard!$C$4,12,1),0))))+N(Units!$G6)<TODAY()),MAX(0,AE6-N(P6)),0) | AR6: =IF(B6="","",Units!C6)
B7: =IF(Units!B7="","",Units!B7) | C7: =IF(B7="","",Units!D7) | D7: =IF(B7="","",Units!E7) | E7: =IF($B7="","",IF(AND(SUMIFS('Rent log'!$D$6:$D$1005,'Rent log'!$C$6:$C$1005,$B7,'Rent log'!$H$6:$H$1005,">="&DATE(Dashboard!$C$4,1,1),'Rent log'!$H$6:$H$1005,"<="&EOMONTH(DATE(Dashboard!$C$4,1,1),0))=0,DATE(Dashboard!$C$4,1,1)>TODAY()),"",SUMIFS('Rent log'!$D$6:$D$1005,'Rent log'!$C$6:$C$1005,$B7,'Rent log'!$H$6:$H$1005,">="&DATE(Dashboard!$C$4,1,1),'Rent log'!$H$6:$H$1005,"<="&EOMONTH(DATE(Dashboard!$C$4,1,1),0)))) | F7: =IF($B7="","",IF(AND(SUMIFS('Rent log'!$D$6:$D$1005,'Rent log'!$C$6:$C$1005,$B7,'Rent log'!$H$6:$H$1005,">="&DATE(Dashboard!$C$4,2,1),'Rent log'!$H$6:$H$1005,"<="&EOMONTH(DATE(Dashboard!$C$4,2,1),0))=0,DATE(Dashboard!$C$4,2,1)>TODAY()),"",SUMIFS('Rent log'!$D$6:$D$1005,'Rent log'!$C$6:$C$1005,$B7,'Rent log'!$H$6:$H$1005,">="&DATE(Dashboard!$C$4,2,1),'Rent log'!$H$6:$H$1005,"<="&EOMONTH(DATE(Dashboard!$C$4,2,1),0)))) | G7: =IF($B7="","",IF(AND(SUMIFS('Rent log'!$D$6:$D$1005,'Rent log'!$C$6:$C$1005,$B7,'Rent log'!$H$6:$H$1005,">="&DATE(Dashboard!$C$4,3,1),'Rent log'!$H$6:$H$1005,"<="&EOMONTH(DATE(Dashboard!$C$4,3,1),0))=0,DATE(Dashboard!$C$4,3,1)>TODAY()),"",SUMIFS('Rent log'!$D$6:$D$1005,'Rent log'!$C$6:$C$1005,$B7,'Rent log'!$H$6:$H$1005,">="&DATE(Dashboard!$C$4,3,1),'Rent log'!$H$6:$H$1005,"<="&EOMONTH(DATE(Dashboard!$C$4,3,1),0)))) | H7: =IF($B7="","",IF(AND(SUMIFS('Rent log'!$D$6:$D$1005,'Rent log'!$C$6:$C$1005,$B7,'Rent log'!$H$6:$H$1005,">="&DATE(Dashboard!$C$4,4,1),'Rent log'!$H$6:$H$1005,"<="&EOMONTH(DATE(Dashboard!$C$4,4,1),0))=0,DATE(Dashboard!$C$4,4,1)>TODAY()),"",SUMIFS('Rent log'!$D$6:$D$1005,'Rent log'!$C$6:$C$1005,$B7,'Rent log'!$H$6:$H$1005,">="&DATE(Dashboard!$C$4,4,1),'Rent log'!$H$6:$H$1005,"<="&EOMONTH(DATE(Dashboard!$C$4,4,1),0)))) | I7: =IF($B7="","",IF(AND(SUMIFS('Rent log'!$D$6:$D$1005,'Rent log'!$C$6:$C$1005,$B7,'Rent log'!$H$6:$H$1005,">="&DATE(Dashboard!$C$4,5,1),'Rent log'!$H$6:$H$1005,"<="&EOMONTH(DATE(Dashboard!$C$4,5,1),0))=0,DATE(Dashboard!$C$4,5,1)>TODAY()),"",SUMIFS('Rent log'!$D$6:$D$1005,'Rent log'!$C$6:$C$1005,$B7,'Rent log'!$H$6:$H$1005,">="&DATE(Dashboard!$C$4,5,1),'Rent log'!$H$6:$H$1005,"<="&EOMONTH(DATE(Dashboard!$C$4,5,1),0)))) | J7: =IF($B7="","",IF(AND(SUMIFS('Rent log'!$D$6:$D$1005,'Rent log'!$C$6:$C$1005,$B7,'Rent log'!$H$6:$H$1005,">="&DATE(Dashboard!$C$4,6,1),'Rent log'!$H$6:$H$1005,"<="&EOMONTH(DATE(Dashboard!$C$4,6,1),0))=0,DATE(Dashboard!$C$4,6,1)>TODAY()),"",SUMIFS('Rent log'!$D$6:$D$1005,'Rent log'!$C$6:$C$1005,$B7,'Rent log'!$H$6:$H$1005,">="&DATE(Dashboard!$C$4,6,1),'Rent log'!$H$6:$H$1005,"<="&EOMONTH(DATE(Dashboard!$C$4,6,1),0)))) | K7: =IF($B7="","",IF(AND(SUMIFS('Rent log'!$D$6:$D$1005,'Rent log'!$C$6:$C$1005,$B7,'Rent log'!$H$6:$H$1005,">="&DATE(Dashboard!$C$4,7,1),'Rent log'!$H$6:$H$1005,"<="&EOMONTH(DATE(Dashboard!$C$4,7,1),0))=0,DATE(Dashboard!$C$4,7,1)>TODAY()),"",SUMIFS('Rent log'!$D$6:$D$1005,'Rent log'!$C$6:$C$1005,$B7,'Rent log'!$H$6:$H$1005,">="&DATE(Dashboard!$C$4,7,1),'Rent log'!$H$6:$H$1005,"<="&EOMONTH(DATE(Dashboard!$C$4,7,1),0)))) | L7: =IF($B7="","",IF(AND(SUMIFS('Rent log'!$D$6:$D$1005,'Rent log'!$C$6:$C$1005,$B7,'Rent log'!$H$6:$H$1005,">="&DATE(Dashboard!$C$4,8,1),'Rent log'!$H$6:$H$1005,"<="&EOMONTH(DATE(Dashboard!$C$4,8,1),0))=0,DATE(Dashboard!$C$4,8,1)>TODAY()),"",SUMIFS('Rent log'!$D$6:$D$1005,'Rent log'!$C$6:$C$1005,$B7,'Rent log'!$H$6:$H$1005,">="&DATE(Dashboard!$C$4,8,1),'Rent log'!$H$6:$H$1005,"<="&EOMONTH(DATE(Dashboard!$C$4,8,1),0)))) | M7: =IF($B7="","",IF(AND(SUMIFS('Rent log'!$D$6:$D$1005,'Rent log'!$C$6:$C$1005,$B7,'Rent log'!$H$6:$H$1005,">="&DATE(Dashboard!$C$4,9,1),'Rent log'!$H$6:$H$1005,"<="&EOMONTH(DATE(Dashboard!$C$4,9,1),0))=0,DATE(Dashboard!$C$4,9,1)>TODAY()),"",SUMIFS('Rent log'!$D$6:$D$1005,'Rent log'!$C$6:$C$1005,$B7,'Rent log'!$H$6:$H$1005,">="&DATE(Dashboard!$C$4,9,1),'Rent log'!$H$6:$H$1005,"<="&EOMONTH(DATE(Dashboard!$C$4,9,1),0)))) | N7: =IF($B7="","",IF(AND(SUMIFS('Rent log'!$D$6:$D$1005,'Rent log'!$C$6:$C$1005,$B7,'Rent log'!$H$6:$H$1005,">="&DATE(Dashboard!$C$4,10,1),'Rent log'!$H$6:$H$1005,"<="&EOMONTH(DATE(Dashboard!$C$4,10,1),0))=0,DATE(Dashboard!$C$4,10,1)>TODAY()),"",SUMIFS('Rent log'!$D$6:$D$1005,'Rent log'!$C$6:$C$1005,$B7,'Rent log'!$H$6:$H$1005,">="&DATE(Dashboard!$C$4,10,1),'Rent log'!$H$6:$H$1005,"<="&EOMONTH(DATE(Dashboard!$C$4,10,1),0)))) | O7: =IF($B7="","",IF(AND(SUMIFS('Rent log'!$D$6:$D$1005,'Rent log'!$C$6:$C$1005,$B7,'Rent log'!$H$6:$H$1005,">="&DATE(Dashboard!$C$4,11,1),'Rent log'!$H$6:$H$1005,"<="&EOMONTH(DATE(Dashboard!$C$4,11,1),0))=0,DATE(Dashboard!$C$4,11,1)>TODAY()),"",SUMIFS('Rent log'!$D$6:$D$1005,'Rent log'!$C$6:$C$1005,$B7,'Rent log'!$H$6:$H$1005,">="&DATE(Dashboard!$C$4,11,1),'Rent log'!$H$6:$H$1005,"<="&EOMONTH(DATE(Dashboard!$C$4,11,1),0)))) | P7: =IF($B7="","",IF(AND(SUMIFS('Rent log'!$D$6:$D$1005,'Rent log'!$C$6:$C$1005,$B7,'Rent log'!$H$6:$H$1005,">="&DATE(Dashboard!$C$4,12,1),'Rent log'!$H$6:$H$1005,"<="&EOMONTH(DATE(Dashboard!$C$4,12,1),0))=0,DATE(Dashboard!$C$4,12,1)>TODAY()),"",SUMIFS('Rent log'!$D$6:$D$1005,'Rent log'!$C$6:$C$1005,$B7,'Rent log'!$H$6:$H$1005,">="&DATE(Dashboard!$C$4,12,1),'Rent log'!$H$6:$H$1005,"<="&EOMONTH(DATE(Dashboard!$C$4,12,1),0)))) | Q7: =IF(B7="","",SUM(E7:P7)) | R7: =IF(B7="","",SUM(AF7:AQ7)) | S7: =IF(B7="","",IF(Dashboard!$C$4<>YEAR(TODAY()),"",IF(INDEX(T7:AE7,MONTH(TODAY()))=0,"No rent due",IF(N(INDEX(E7:P7,MONTH(TODAY())))>=INDEX(T7:AE7,MONTH(TODAY())),"Paid",IF(TODAY()>DATE(YEAR(TODAY()),MONTH(TODAY()),MIN(N(Units!$F7)+(N(Units!$F7)=0),DAY(EOMONTH(TODAY(),0))))+N(Units!$G7),"Late: "&FIXED(INDEX(T7:AE7,MONTH(TODAY()))-N(INDEX(E7:P7,MONTH(TODAY()))),2)&" owed",IF(N(INDEX(E7:P7,MONTH(TODAY())))>0,"Part paid: "&FIXED(INDEX(T7:AE7,MONTH(TODAY()))-N(INDEX(E7:P7,MONTH(TODAY()))),2)&" left","Due on the "&MIN(N(Units!$F7)+(N(Units!$F7)=0),DAY(EOMONTH(TODAY(),0)))&IF(AND(MIN(N(Units!$F7)+(N(Units!$F7)=0),DAY(EOMONTH(TODAY(),0)))>=11,MIN(N(Units!$F7)+(N(Units!$F7)=0),DAY(EOMONTH(TODAY(),0)))<=13),"th",IF(MOD(MIN(N(Units!$F7)+(N(Units!$F7)=0),DAY(EOMONTH(TODAY(),0))),10)=1,"st",IF(MOD(MIN(N(Units!$F7)+(N(Units!$F7)=0),DAY(EOMONTH(TODAY(),0))),10)=2,"nd",IF(MOD(MIN(N(Units!$F7)+(N(Units!$F7)=0),DAY(EOMONTH(TODAY(),0))),10)=3,"rd","th")))))))))) | T7: =IF($B7="",0,IF(AND(OR(Units!$H7="",Units!$H7<=EOMONTH(DATE(Dashboard!$C$4,1,1),0)),OR(Units!$I7="",Units!$I7>=DATE(Dashboard!$C$4,1,1))),N(Units!$E7),0)) | U7: =IF($B7="",0,IF(AND(OR(Units!$H7="",Units!$H7<=EOMONTH(DATE(Dashboard!$C$4,2,1),0)),OR(Units!$I7="",Units!$I7>=DATE(Dashboard!$C$4,2,1))),N(Units!$E7),0)) | V7: =IF($B7="",0,IF(AND(OR(Units!$H7="",Units!$H7<=EOMONTH(DATE(Dashboard!$C$4,3,1),0)),OR(Units!$I7="",Units!$I7>=DATE(Dashboard!$C$4,3,1))),N(Units!$E7),0)) | W7: =IF($B7="",0,IF(AND(OR(Units!$H7="",Units!$H7<=EOMONTH(DATE(Dashboard!$C$4,4,1),0)),OR(Units!$I7="",Units!$I7>=DATE(Dashboard!$C$4,4,1))),N(Units!$E7),0)) | X7: =IF($B7="",0,IF(AND(OR(Units!$H7="",Units!$H7<=EOMONTH(DATE(Dashboard!$C$4,5,1),0)),OR(Units!$I7="",Units!$I7>=DATE(Dashboard!$C$4,5,1))),N(Units!$E7),0)) | Y7: =IF($B7="",0,IF(AND(OR(Units!$H7="",Units!$H7<=EOMONTH(DATE(Dashboard!$C$4,6,1),0)),OR(Units!$I7="",Units!$I7>=DATE(Dashboard!$C$4,6,1))),N(Units!$E7),0)) | Z7: =IF($B7="",0,IF(AND(OR(Units!$H7="",Units!$H7<=EOMONTH(DATE(Dashboard!$C$4,7,1),0)),OR(Units!$I7="",Units!$I7>=DATE(Dashboard!$C$4,7,1))),N(Units!$E7),0)) | AA7: =IF($B7="",0,IF(AND(OR(Units!$H7="",Units!$H7<=EOMONTH(DATE(Dashboard!$C$4,8,1),0)),OR(Units!$I7="",Units!$I7>=DATE(Dashboard!$C$4,8,1))),N(Units!$E7),0)) | AB7: =IF($B7="",0,IF(AND(OR(Units!$H7="",Units!$H7<=EOMONTH(DATE(Dashboard!$C$4,9,1),0)),OR(Units!$I7="",Units!$I7>=DATE(Dashboard!$C$4,9,1))),N(Units!$E7),0)) | AC7: =IF($B7="",0,IF(AND(OR(Units!$H7="",Units!$H7<=EOMONTH(DATE(Dashboard!$C$4,10,1),0)),OR(Units!$I7="",Units!$I7>=DATE(Dashboard!$C$4,10,1))),N(Units!$E7),0)) | AD7: =IF($B7="",0,IF(AND(OR(Units!$H7="",Units!$H7<=EOMONTH(DATE(Dashboard!$C$4,11,1),0)),OR(Units!$I7="",Units!$I7>=DATE(Dashboard!$C$4,11,1))),N(Units!$E7),0)) | AE7: =IF($B7="",0,IF(AND(OR(Units!$H7="",Units!$H7<=EOMONTH(DATE(Dashboard!$C$4,12,1),0)),OR(Units!$I7="",Units!$I7>=DATE(Dashboard!$C$4,12,1))),N(Units!$E7),0)) | AF7: =IF(AND(T7>0,DATE(Dashboard!$C$4,1,MIN(N(Units!$F7)+(N(Units!$F7)=0),DAY(EOMONTH(DATE(Dashboard!$C$4,1,1),0))))+N(Units!$G7)<TODAY()),MAX(0,T7-N(E7)),0) | AG7: =IF(AND(U7>0,DATE(Dashboard!$C$4,2,MIN(N(Units!$F7)+(N(Units!$F7)=0),DAY(EOMONTH(DATE(Dashboard!$C$4,2,1),0))))+N(Units!$G7)<TODAY()),MAX(0,U7-N(F7)),0) | AH7: =IF(AND(V7>0,DATE(Dashboard!$C$4,3,MIN(N(Units!$F7)+(N(Units!$F7)=0),DAY(EOMONTH(DATE(Dashboard!$C$4,3,1),0))))+N(Units!$G7)<TODAY()),MAX(0,V7-N(G7)),0) | AI7: =IF(AND(W7>0,DATE(Dashboard!$C$4,4,MIN(N(Units!$F7)+(N(Units!$F7)=0),DAY(EOMONTH(DATE(Dashboard!$C$4,4,1),0))))+N(Units!$G7)<TODAY()),MAX(0,W7-N(H7)),0) | AJ7: =IF(AND(X7>0,DATE(Dashboard!$C$4,5,MIN(N(Units!$F7)+(N(Units!$F7)=0),DAY(EOMONTH(DATE(Dashboard!$C$4,5,1),0))))+N(Units!$G7)<TODAY()),MAX(0,X7-N(I7)),0) | AK7: =IF(AND(Y7>0,DATE(Dashboard!$C$4,6,MIN(N(Units!$F7)+(N(Units!$F7)=0),DAY(EOMONTH(DATE(Dashboard!$C$4,6,1),0))))+N(Units!$G7)<TODAY()),MAX(0,Y7-N(J7)),0) | AL7: =IF(AND(Z7>0,DATE(Dashboard!$C$4,7,MIN(N(Units!$F7)+(N(Units!$F7)=0),DAY(EOMONTH(DATE(Dashboard!$C$4,7,1),0))))+N(Units!$G7)<TODAY()),MAX(0,Z7-N(K7)),0) | AM7: =IF(AND(AA7>0,DATE(Dashboard!$C$4,8,MIN(N(Units!$F7)+(N(Units!$F7)=0),DAY(EOMONTH(DATE(Dashboard!$C$4,8,1),0))))+N(Units!$G7)<TODAY()),MAX(0,AA7-N(L7)),0) | AN7: =IF(AND(AB7>0,DATE(Dashboard!$C$4,9,MIN(N(Units!$F7)+(N(Units!$F7)=0),DAY(EOMONTH(DATE(Dashboard!$C$4,9,1),0))))+N(Units!$G7)<TODAY()),MAX(0,AB7-N(M7)),0) | AO7: =IF(AND(AC7>0,DATE(Dashboard!$C$4,10,MIN(N(Units!$F7)+(N(Units!$F7)=0),DAY(EOMONTH(DATE(Dashboard!$C$4,10,1),0))))+N(Units!$G7)<TODAY()),MAX(0,AC7-N(N7)),0) | AP7: =IF(AND(AD7>0,DATE(Dashboard!$C$4,11,MIN(N(Units!$F7)+(N(Units!$F7)=0),DAY(EOMONTH(DATE(Dashboard!$C$4,11,1),0))))+N(Units!$G7)<TODAY()),MAX(0,AD7-N(O7)),0) | AQ7: =IF(AND(AE7>0,DATE(Dashboard!$C$4,12,MIN(N(Units!$F7)+(N(Units!$F7)=0),DAY(EOMONTH(DATE(Dashboard!$C$4,12,1),0))))+N(Units!$G7)<TODAY()),MAX(0,AE7-N(P7)),0) | AR7: =IF(B7="","",Units!C7)
B8: =IF(Units!B8="","",Units!B8) | C8: =IF(B8="","",Units!D8) | D8: =IF(B8="","",Units!E8) | E8: =IF($B8="","",IF(AND(SUMIFS('Rent log'!$D$6:$D$1005,'Rent log'!$C$6:$C$1005,$B8,'Rent log'!$H$6:$H$1005,">="&DATE(Dashboard!$C$4,1,1),'Rent log'!$H$6:$H$1005,"<="&EOMONTH(DATE(Dashboard!$C$4,1,1),0))=0,DATE(Dashboard!$C$4,1,1)>TODAY()),"",SUMIFS('Rent log'!$D$6:$D$1005,'Rent log'!$C$6:$C$1005,$B8,'Rent log'!$H$6:$H$1005,">="&DATE(Dashboard!$C$4,1,1),'Rent log'!$H$6:$H$1005,"<="&EOMONTH(DATE(Dashboard!$C$4,1,1),0)))) | F8: =IF($B8="","",IF(AND(SUMIFS('Rent log'!$D$6:$D$1005,'Rent log'!$C$6:$C$1005,$B8,'Rent log'!$H$6:$H$1005,">="&DATE(Dashboard!$C$4,2,1),'Rent log'!$H$6:$H$1005,"<="&EOMONTH(DATE(Dashboard!$C$4,2,1),0))=0,DATE(Dashboard!$C$4,2,1)>TODAY()),"",SUMIFS('Rent log'!$D$6:$D$1005,'Rent log'!$C$6:$C$1005,$B8,'Rent log'!$H$6:$H$1005,">="&DATE(Dashboard!$C$4,2,1),'Rent log'!$H$6:$H$1005,"<="&EOMONTH(DATE(Dashboard!$C$4,2,1),0)))) | G8: =IF($B8="","",IF(AND(SUMIFS('Rent log'!$D$6:$D$1005,'Rent log'!$C$6:$C$1005,$B8,'Rent log'!$H$6:$H$1005,">="&DATE(Dashboard!$C$4,3,1),'Rent log'!$H$6:$H$1005,"<="&EOMONTH(DATE(Dashboard!$C$4,3,1),0))=0,DATE(Dashboard!$C$4,3,1)>TODAY()),"",SUMIFS('Rent log'!$D$6:$D$1005,'Rent log'!$C$6:$C$1005,$B8,'Rent log'!$H$6:$H$1005,">="&DATE(Dashboard!$C$4,3,1),'Rent log'!$H$6:$H$1005,"<="&EOMONTH(DATE(Dashboard!$C$4,3,1),0)))) | H8: =IF($B8="","",IF(AND(SUMIFS('Rent log'!$D$6:$D$1005,'Rent log'!$C$6:$C$1005,$B8,'Rent log'!$H$6:$H$1005,">="&DATE(Dashboard!$C$4,4,1),'Rent log'!$H$6:$H$1005,"<="&EOMONTH(DATE(Dashboard!$C$4,4,1),0))=0,DATE(Dashboard!$C$4,4,1)>TODAY()),"",SUMIFS('Rent log'!$D$6:$D$1005,'Rent log'!$C$6:$C$1005,$B8,'Rent log'!$H$6:$H$1005,">="&DATE(Dashboard!$C$4,4,1),'Rent log'!$H$6:$H$1005,"<="&EOMONTH(DATE(Dashboard!$C$4,4,1),0)))) | I8: =IF($B8="","",IF(AND(SUMIFS('Rent log'!$D$6:$D$1005,'Rent log'!$C$6:$C$1005,$B8,'Rent log'!$H$6:$H$1005,">="&DATE(Dashboard!$C$4,5,1),'Rent log'!$H$6:$H$1005,"<="&EOMONTH(DATE(Dashboard!$C$4,5,1),0))=0,DATE(Dashboard!$C$4,5,1)>TODAY()),"",SUMIFS('Rent log'!$D$6:$D$1005,'Rent log'!$C$6:$C$1005,$B8,'Rent log'!$H$6:$H$1005,">="&DATE(Dashboard!$C$4,5,1),'Rent log'!$H$6:$H$1005,"<="&EOMONTH(DATE(Dashboard!$C$4,5,1),0)))) | J8: =IF($B8="","",IF(AND(SUMIFS('Rent log'!$D$6:$D$1005,'Rent log'!$C$6:$C$1005,$B8,'Rent log'!$H$6:$H$1005,">="&DATE(Dashboard!$C$4,6,1),'Rent log'!$H$6:$H$1005,"<="&EOMONTH(DATE(Dashboard!$C$4,6,1),0))=0,DATE(Dashboard!$C$4,6,1)>TODAY()),"",SUMIFS('Rent log'!$D$6:$D$1005,'Rent log'!$C$6:$C$1005,$B8,'Rent log'!$H$6:$H$1005,">="&DATE(Dashboard!$C$4,6,1),'Rent log'!$H$6:$H$1005,"<="&EOMONTH(DATE(Dashboard!$C$4,6,1),0)))) | K8: =IF($B8="","",IF(AND(SUMIFS('Rent log'!$D$6:$D$1005,'Rent log'!$C$6:$C$1005,$B8,'Rent log'!$H$6:$H$1005,">="&DATE(Dashboard!$C$4,7,1),'Rent log'!$H$6:$H$1005,"<="&EOMONTH(DATE(Dashboard!$C$4,7,1),0))=0,DATE(Dashboard!$C$4,7,1)>TODAY()),"",SUMIFS('Rent log'!$D$6:$D$1005,'Rent log'!$C$6:$C$1005,$B8,'Rent log'!$H$6:$H$1005,">="&DATE(Dashboard!$C$4,7,1),'Rent log'!$H$6:$H$1005,"<="&EOMONTH(DATE(Dashboard!$C$4,7,1),0)))) | L8: =IF($B8="","",IF(AND(SUMIFS('Rent log'!$D$6:$D$1005,'Rent log'!$C$6:$C$1005,$B8,'Rent log'!$H$6:$H$1005,">="&DATE(Dashboard!$C$4,8,1),'Rent log'!$H$6:$H$1005,"<="&EOMONTH(DATE(Dashboard!$C$4,8,1),0))=0,DATE(Dashboard!$C$4,8,1)>TODAY()),"",SUMIFS('Rent log'!$D$6:$D$1005,'Rent log'!$C$6:$C$1005,$B8,'Rent log'!$H$6:$H$1005,">="&DATE(Dashboard!$C$4,8,1),'Rent log'!$H$6:$H$1005,"<="&EOMONTH(DATE(Dashboard!$C$4,8,1),0)))) | M8: =IF($B8="","",IF(AND(SUMIFS('Rent log'!$D$6:$D$1005,'Rent log'!$C$6:$C$1005,$B8,'Rent log'!$H$6:$H$1005,">="&DATE(Dashboard!$C$4,9,1),'Rent log'!$H$6:$H$1005,"<="&EOMONTH(DATE(Dashboard!$C$4,9,1),0))=0,DATE(Dashboard!$C$4,9,1)>TODAY()),"",SUMIFS('Rent log'!$D$6:$D$1005,'Rent log'!$C$6:$C$1005,$B8,'Rent log'!$H$6:$H$1005,">="&DATE(Dashboard!$C$4,9,1),'Rent log'!$H$6:$H$1005,"<="&EOMONTH(DATE(Dashboard!$C$4,9,1),0)))) | N8: =IF($B8="","",IF(AND(SUMIFS('Rent log'!$D$6:$D$1005,'Rent log'!$C$6:$C$1005,$B8,'Rent log'!$H$6:$H$1005,">="&DATE(Dashboard!$C$4,10,1),'Rent log'!$H$6:$H$1005,"<="&EOMONTH(DATE(Dashboard!$C$4,10,1),0))=0,DATE(Dashboard!$C$4,10,1)>TODAY()),"",SUMIFS('Rent log'!$D$6:$D$1005,'Rent log'!$C$6:$C$1005,$B8,'Rent log'!$H$6:$H$1005,">="&DATE(Dashboard!$C$4,10,1),'Rent log'!$H$6:$H$1005,"<="&EOMONTH(DATE(Dashboard!$C$4,10,1),0)))) | O8: =IF($B8="","",IF(AND(SUMIFS('Rent log'!$D$6:$D$1005,'Rent log'!$C$6:$C$1005,$B8,'Rent log'!$H$6:$H$1005,">="&DATE(Dashboard!$C$4,11,1),'Rent log'!$H$6:$H$1005,"<="&EOMONTH(DATE(Dashboard!$C$4,11,1),0))=0,DATE(Dashboard!$C$4,11,1)>TODAY()),"",SUMIFS('Rent log'!$D$6:$D$1005,'Rent log'!$C$6:$C$1005,$B8,'Rent log'!$H$6:$H$1005,">="&DATE(Dashboard!$C$4,11,1),'Rent log'!$H$6:$H$1005,"<="&EOMONTH(DATE(Dashboard!$C$4,11,1),0)))) | P8: =IF($B8="","",IF(AND(SUMIFS('Rent log'!$D$6:$D$1005,'Rent log'!$C$6:$C$1005,$B8,'Rent log'!$H$6:$H$1005,">="&DATE(Dashboard!$C$4,12,1),'Rent log'!$H$6:$H$1005,"<="&EOMONTH(DATE(Dashboard!$C$4,12,1),0))=0,DATE(Dashboard!$C$4,12,1)>TODAY()),"",SUMIFS('Rent log'!$D$6:$D$1005,'Rent log'!$C$6:$C$1005,$B8,'Rent log'!$H$6:$H$1005,">="&DATE(Dashboard!$C$4,12,1),'Rent log'!$H$6:$H$1005,"<="&EOMONTH(DATE(Dashboard!$C$4,12,1),0)))) | Q8: =IF(B8="","",SUM(E8:P8)) | R8: =IF(B8="","",SUM(AF8:AQ8)) | S8: =IF(B8="","",IF(Dashboard!$C$4<>YEAR(TODAY()),"",IF(INDEX(T8:AE8,MONTH(TODAY()))=0,"No rent due",IF(N(INDEX(E8:P8,MONTH(TODAY())))>=INDEX(T8:AE8,MONTH(TODAY())),"Paid",IF(TODAY()>DATE(YEAR(TODAY()),MONTH(TODAY()),MIN(N(Units!$F8)+(N(Units!$F8)=0),DAY(EOMONTH(TODAY(),0))))+N(Units!$G8),"Late: "&FIXED(INDEX(T8:AE8,MONTH(TODAY()))-N(INDEX(E8:P8,MONTH(TODAY()))),2)&" owed",IF(N(INDEX(E8:P8,MONTH(TODAY())))>0,"Part paid: "&FIXED(INDEX(T8:AE8,MONTH(TODAY()))-N(INDEX(E8:P8,MONTH(TODAY()))),2)&" left","Due on the "&MIN(N(Units!$F8)+(N(Units!$F8)=0),DAY(EOMONTH(TODAY(),0)))&IF(AND(MIN(N(Units!$F8)+(N(Units!$F8)=0),DAY(EOMONTH(TODAY(),0)))>=11,MIN(N(Units!$F8)+(N(Units!$F8)=0),DAY(EOMONTH(TODAY(),0)))<=13),"th",IF(MOD(MIN(N(Units!$F8)+(N(Units!$F8)=0),DAY(EOMONTH(TODAY(),0))),10)=1,"st",IF(MOD(MIN(N(Units!$F8)+(N(Units!$F8)=0),DAY(EOMONTH(TODAY(),0))),10)=2,"nd",IF(MOD(MIN(N(Units!$F8)+(N(Units!$F8)=0),DAY(EOMONTH(TODAY(),0))),10)=3,"rd","th")))))))))) | T8: =IF($B8="",0,IF(AND(OR(Units!$H8="",Units!$H8<=EOMONTH(DATE(Dashboard!$C$4,1,1),0)),OR(Units!$I8="",Units!$I8>=DATE(Dashboard!$C$4,1,1))),N(Units!$E8),0)) | U8: =IF($B8="",0,IF(AND(OR(Units!$H8="",Units!$H8<=EOMONTH(DATE(Dashboard!$C$4,2,1),0)),OR(Units!$I8="",Units!$I8>=DATE(Dashboard!$C$4,2,1))),N(Units!$E8),0)) | V8: =IF($B8="",0,IF(AND(OR(Units!$H8="",Units!$H8<=EOMONTH(DATE(Dashboard!$C$4,3,1),0)),OR(Units!$I8="",Units!$I8>=DATE(Dashboard!$C$4,3,1))),N(Units!$E8),0)) | W8: =IF($B8="",0,IF(AND(OR(Units!$H8="",Units!$H8<=EOMONTH(DATE(Dashboard!$C$4,4,1),0)),OR(Units!$I8="",Units!$I8>=DATE(Dashboard!$C$4,4,1))),N(Units!$E8),0)) | X8: =IF($B8="",0,IF(AND(OR(Units!$H8="",Units!$H8<=EOMONTH(DATE(Dashboard!$C$4,5,1),0)),OR(Units!$I8="",Units!$I8>=DATE(Dashboard!$C$4,5,1))),N(Units!$E8),0)) | Y8: =IF($B8="",0,IF(AND(OR(Units!$H8="",Units!$H8<=EOMONTH(DATE(Dashboard!$C$4,6,1),0)),OR(Units!$I8="",Units!$I8>=DATE(Dashboard!$C$4,6,1))),N(Units!$E8),0)) | Z8: =IF($B8="",0,IF(AND(OR(Units!$H8="",Units!$H8<=EOMONTH(DATE(Dashboard!$C$4,7,1),0)),OR(Units!$I8="",Units!$I8>=DATE(Dashboard!$C$4,7,1))),N(Units!$E8),0)) | AA8: =IF($B8="",0,IF(AND(OR(Units!$H8="",Units!$H8<=EOMONTH(DATE(Dashboard!$C$4,8,1),0)),OR(Units!$I8="",Units!$I8>=DATE(Dashboard!$C$4,8,1))),N(Units!$E8),0)) | AB8: =IF($B8="",0,IF(AND(OR(Units!$H8="",Units!$H8<=EOMONTH(DATE(Dashboard!$C$4,9,1),0)),OR(Units!$I8="",Units!$I8>=DATE(Dashboard!$C$4,9,1))),N(Units!$E8),0)) | AC8: =IF($B8="",0,IF(AND(OR(Units!$H8="",Units!$H8<=EOMONTH(DATE(Dashboard!$C$4,10,1),0)),OR(Units!$I8="",Units!$I8>=DATE(Dashboard!$C$4,10,1))),N(Units!$E8),0)) | AD8: =IF($B8="",0,IF(AND(OR(Units!$H8="",Units!$H8<=EOMONTH(DATE(Dashboard!$C$4,11,1),0)),OR(Units!$I8="",Units!$I8>=DATE(Dashboard!$C$4,11,1))),N(Units!$E8),0)) | AE8: =IF($B8="",0,IF(AND(OR(Units!$H8="",Units!$H8<=EOMONTH(DATE(Dashboard!$C$4,12,1),0)),OR(Units!$I8="",Units!$I8>=DATE(Dashboard!$C$4,12,1))),N(Units!$E8),0)) | AF8: =IF(AND(T8>0,DATE(Dashboard!$C$4,1,MIN(N(Units!$F8)+(N(Units!$F8)=0),DAY(EOMONTH(DATE(Dashboard!$C$4,1,1),0))))+N(Units!$G8)<TODAY()),MAX(0,T8-N(E8)),0) | AG8: =IF(AND(U8>0,DATE(Dashboard!$C$4,2,MIN(N(Units!$F8)+(N(Units!$F8)=0),DAY(EOMONTH(DATE(Dashboard!$C$4,2,1),0))))+N(Units!$G8)<TODAY()),MAX(0,U8-N(F8)),0) | AH8: =IF(AND(V8>0,DATE(Dashboard!$C$4,3,MIN(N(Units!$F8)+(N(Units!$F8)=0),DAY(EOMONTH(DATE(Dashboard!$C$4,3,1),0))))+N(Units!$G8)<TODAY()),MAX(0,V8-N(G8)),0) | AI8: =IF(AND(W8>0,DATE(Dashboard!$C$4,4,MIN(N(Units!$F8)+(N(Units!$F8)=0),DAY(EOMONTH(DATE(Dashboard!$C$4,4,1),0))))+N(Units!$G8)<TODAY()),MAX(0,W8-N(H8)),0) | AJ8: =IF(AND(X8>0,DATE(Dashboard!$C$4,5,MIN(N(Units!$F8)+(N(Units!$F8)=0),DAY(EOMONTH(DATE(Dashboard!$C$4,5,1),0))))+N(Units!$G8)<TODAY()),MAX(0,X8-N(I8)),0) | AK8: =IF(AND(Y8>0,DATE(Dashboard!$C$4,6,MIN(N(Units!$F8)+(N(Units!$F8)=0),DAY(EOMONTH(DATE(Dashboard!$C$4,6,1),0))))+N(Units!$G8)<TODAY()),MAX(0,Y8-N(J8)),0) | AL8: =IF(AND(Z8>0,DATE(Dashboard!$C$4,7,MIN(N(Units!$F8)+(N(Units!$F8)=0),DAY(EOMONTH(DATE(Dashboard!$C$4,7,1),0))))+N(Units!$G8)<TODAY()),MAX(0,Z8-N(K8)),0) | AM8: =IF(AND(AA8>0,DATE(Dashboard!$C$4,8,MIN(N(Units!$F8)+(N(Units!$F8)=0),DAY(EOMONTH(DATE(Dashboard!$C$4,8,1),0))))+N(Units!$G8)<TODAY()),MAX(0,AA8-N(L8)),0) | AN8: =IF(AND(AB8>0,DATE(Dashboard!$C$4,9,MIN(N(Units!$F8)+(N(Units!$F8)=0),DAY(EOMONTH(DATE(Dashboard!$C$4,9,1),0))))+N(Units!$G8)<TODAY()),MAX(0,AB8-N(M8)),0) | AO8: =IF(AND(AC8>0,DATE(Dashboard!$C$4,10,MIN(N(Units!$F8)+(N(Units!$F8)=0),DAY(EOMONTH(DATE(Dashboard!$C$4,10,1),0))))+N(Units!$G8)<TODAY()),MAX(0,AC8-N(N8)),0) | AP8: =IF(AND(AD8>0,DATE(Dashboard!$C$4,11,MIN(N(Units!$F8)+(N(Units!$F8)=0),DAY(EOMONTH(DATE(Dashboard!$C$4,11,1),0))))+N(Units!$G8)<TODAY()),MAX(0,AD8-N(O8)),0) | AQ8: =IF(AND(AE8>0,DATE(Dashboard!$C$4,12,MIN(N(Units!$F8)+(N(Units!$F8)=0),DAY(EOMONTH(DATE(Dashboard!$C$4,12,1),0))))+N(Units!$G8)<TODAY()),MAX(0,AE8-N(P8)),0) | AR8: =IF(B8="","",Units!C8)
B9: =IF(Units!B9="","",Units!B9) | C9: =IF(B9="","",Units!D9) | D9: =IF(B9="","",Units!E9) | E9: =IF($B9="","",IF(AND(SUMIFS('Rent log'!$D$6:$D$1005,'Rent log'!$C$6:$C$1005,$B9,'Rent log'!$H$6:$H$1005,">="&DATE(Dashboard!$C$4,1,1),'Rent log'!$H$6:$H$1005,"<="&EOMONTH(DATE(Dashboard!$C$4,1,1),0))=0,DATE(Dashboard!$C$4,1,1)>TODAY()),"",SUMIFS('Rent log'!$D$6:$D$1005,'Rent log'!$C$6:$C$1005,$B9,'Rent log'!$H$6:$H$1005,">="&DATE(Dashboard!$C$4,1,1),'Rent log'!$H$6:$H$1005,"<="&EOMONTH(DATE(Dashboard!$C$4,1,1),0)))) | F9: =IF($B9="","",IF(AND(SUMIFS('Rent log'!$D$6:$D$1005,'Rent log'!$C$6:$C$1005,$B9,'Rent log'!$H$6:$H$1005,">="&DATE(Dashboard!$C$4,2,1),'Rent log'!$H$6:$H$1005,"<="&EOMONTH(DATE(Dashboard!$C$4,2,1),0))=0,DATE(Dashboard!$C$4,2,1)>TODAY()),"",SUMIFS('Rent log'!$D$6:$D$1005,'Rent log'!$C$6:$C$1005,$B9,'Rent log'!$H$6:$H$1005,">="&DATE(Dashboard!$C$4,2,1),'Rent log'!$H$6:$H$1005,"<="&EOMONTH(DATE(Dashboard!$C$4,2,1),0)))) | G9: =IF($B9="","",IF(AND(SUMIFS('Rent log'!$D$6:$D$1005,'Rent log'!$C$6:$C$1005,$B9,'Rent log'!$H$6:$H$1005,">="&DATE(Dashboard!$C$4,3,1),'Rent log'!$H$6:$H$1005,"<="&EOMONTH(DATE(Dashboard!$C$4,3,1),0))=0,DATE(Dashboard!$C$4,3,1)>TODAY()),"",SUMIFS('Rent log'!$D$6:$D$1005,'Rent log'!$C$6:$C$1005,$B9,'Rent log'!$H$6:$H$1005,">="&DATE(Dashboard!$C$4,3,1),'Rent log'!$H$6:$H$1005,"<="&EOMONTH(DATE(Dashboard!$C$4,3,1),0)))) | H9: =IF($B9="","",IF(AND(SUMIFS('Rent log'!$D$6:$D$1005,'Rent log'!$C$6:$C$1005,$B9,'Rent log'!$H$6:$H$1005,">="&DATE(Dashboard!$C$4,4,1),'Rent log'!$H$6:$H$1005,"<="&EOMONTH(DATE(Dashboard!$C$4,4,1),0))=0,DATE(Dashboard!$C$4,4,1)>TODAY()),"",SUMIFS('Rent log'!$D$6:$D$1005,'Rent log'!$C$6:$C$1005,$B9,'Rent log'!$H$6:$H$1005,">="&DATE(Dashboard!$C$4,4,1),'Rent log'!$H$6:$H$1005,"<="&EOMONTH(DATE(Dashboard!$C$4,4,1),0)))) | I9: =IF($B9="","",IF(AND(SUMIFS('Rent log'!$D$6:$D$1005,'Rent log'!$C$6:$C$1005,$B9,'Rent log'!$H$6:$H$1005,">="&DATE(Dashboard!$C$4,5,1),'Rent log'!$H$6:$H$1005,"<="&EOMONTH(DATE(Dashboard!$C$4,5,1),0))=0,DATE(Dashboard!$C$4,5,1)>TODAY()),"",SUMIFS('Rent log'!$D$6:$D$1005,'Rent log'!$C$6:$C$1005,$B9,'Rent log'!$H$6:$H$1005,">="&DATE(Dashboard!$C$4,5,1),'Rent log'!$H$6:$H$1005,"<="&EOMONTH(DATE(Dashboard!$C$4,5,1),0)))) | J9: =IF($B9="","",IF(AND(SUMIFS('Rent log'!$D$6:$D$1005,'Rent log'!$C$6:$C$1005,$B9,'Rent log'!$H$6:$H$1005,">="&DATE(Dashboard!$C$4,6,1),'Rent log'!$H$6:$H$1005,"<="&EOMONTH(DATE(Dashboard!$C$4,6,1),0))=0,DATE(Dashboard!$C$4,6,1)>TODAY()),"",SUMIFS('Rent log'!$D$6:$D$1005,'Rent log'!$C$6:$C$1005,$B9,'Rent log'!$H$6:$H$1005,">="&DATE(Dashboard!$C$4,6,1),'Rent log'!$H$6:$H$1005,"<="&EOMONTH(DATE(Dashboard!$C$4,6,1),0)))) | K9: =IF($B9="","",IF(AND(SUMIFS('Rent log'!$D$6:$D$1005,'Rent log'!$C$6:$C$1005,$B9,'Rent log'!$H$6:$H$1005,">="&DATE(Dashboard!$C$4,7,1),'Rent log'!$H$6:$H$1005,"<="&EOMONTH(DATE(Dashboard!$C$4,7,1),0))=0,DATE(Dashboard!$C$4,7,1)>TODAY()),"",SUMIFS('Rent log'!$D$6:$D$1005,'Rent log'!$C$6:$C$1005,$B9,'Rent log'!$H$6:$H$1005,">="&DATE(Dashboard!$C$4,7,1),'Rent log'!$H$6:$H$1005,"<="&EOMONTH(DATE(Dashboard!$C$4,7,1),0)))) | L9: =IF($B9="","",IF(AND(SUMIFS('Rent log'!$D$6:$D$1005,'Rent log'!$C$6:$C$1005,$B9,'Rent log'!$H$6:$H$1005,">="&DATE(Dashboard!$C$4,8,1),'Rent log'!$H$6:$H$1005,"<="&EOMONTH(DATE(Dashboard!$C$4,8,1),0))=0,DATE(Dashboard!$C$4,8,1)>TODAY()),"",SUMIFS('Rent log'!$D$6:$D$1005,'Rent log'!$C$6:$C$1005,$B9,'Rent log'!$H$6:$H$1005,">="&DATE(Dashboard!$C$4,8,1),'Rent log'!$H$6:$H$1005,"<="&EOMONTH(DATE(Dashboard!$C$4,8,1),0)))) | M9: =IF($B9="","",IF(AND(SUMIFS('Rent log'!$D$6:$D$1005,'Rent log'!$C$6:$C$1005,$B9,'Rent log'!$H$6:$H$1005,">="&DATE(Dashboard!$C$4,9,1),'Rent log'!$H$6:$H$1005,"<="&EOMONTH(DATE(Dashboard!$C$4,9,1),0))=0,DATE(Dashboard!$C$4,9,1)>TODAY()),"",SUMIFS('Rent log'!$D$6:$D$1005,'Rent log'!$C$6:$C$1005,$B9,'Rent log'!$H$6:$H$1005,">="&DATE(Dashboard!$C$4,9,1),'Rent log'!$H$6:$H$1005,"<="&EOMONTH(DATE(Dashboard!$C$4,9,1),0)))) | N9: =IF($B9="","",IF(AND(SUMIFS('Rent log'!$D$6:$D$1005,'Rent log'!$C$6:$C$1005,$B9,'Rent log'!$H$6:$H$1005,">="&DATE(Dashboard!$C$4,10,1),'Rent log'!$H$6:$H$1005,"<="&EOMONTH(DATE(Dashboard!$C$4,10,1),0))=0,DATE(Dashboard!$C$4,10,1)>TODAY()),"",SUMIFS('Rent log'!$D$6:$D$1005,'Rent log'!$C$6:$C$1005,$B9,'Rent log'!$H$6:$H$1005,">="&DATE(Dashboard!$C$4,10,1),'Rent log'!$H$6:$H$1005,"<="&EOMONTH(DATE(Dashboard!$C$4,10,1),0)))) | O9: =IF($B9="","",IF(AND(SUMIFS('Rent log'!$D$6:$D$1005,'Rent log'!$C$6:$C$1005,$B9,'Rent log'!$H$6:$H$1005,">="&DATE(Dashboard!$C$4,11,1),'Rent log'!$H$6:$H$1005,"<="&EOMONTH(DATE(Dashboard!$C$4,11,1),0))=0,DATE(Dashboard!$C$4,11,1)>TODAY()),"",SUMIFS('Rent log'!$D$6:$D$1005,'Rent log'!$C$6:$C$1005,$B9,'Rent log'!$H$6:$H$1005,">="&DATE(Dashboard!$C$4,11,1),'Rent log'!$H$6:$H$1005,"<="&EOMONTH(DATE(Dashboard!$C$4,11,1),0)))) | P9: =IF($B9="","",IF(AND(SUMIFS('Rent log'!$D$6:$D$1005,'Rent log'!$C$6:$C$1005,$B9,'Rent log'!$H$6:$H$1005,">="&DATE(Dashboard!$C$4,12,1),'Rent log'!$H$6:$H$1005,"<="&EOMONTH(DATE(Dashboard!$C$4,12,1),0))=0,DATE(Dashboard!$C$4,12,1)>TODAY()),"",SUMIFS('Rent log'!$D$6:$D$1005,'Rent log'!$C$6:$C$1005,$B9,'Rent log'!$H$6:$H$1005,">="&DATE(Dashboard!$C$4,12,1),'Rent log'!$H$6:$H$1005,"<="&EOMONTH(DATE(Dashboard!$C$4,12,1),0)))) | Q9: =IF(B9="","",SUM(E9:P9)) | R9: =IF(B9="","",SUM(AF9:AQ9)) | S9: =IF(B9="","",IF(Dashboard!$C$4<>YEAR(TODAY()),"",IF(INDEX(T9:AE9,MONTH(TODAY()))=0,"No rent due",IF(N(INDEX(E9:P9,MONTH(TODAY())))>=INDEX(T9:AE9,MONTH(TODAY())),"Paid",IF(TODAY()>DATE(YEAR(TODAY()),MONTH(TODAY()),MIN(N(Units!$F9)+(N(Units!$F9)=0),DAY(EOMONTH(TODAY(),0))))+N(Units!$G9),"Late: "&FIXED(INDEX(T9:AE9,MONTH(TODAY()))-N(INDEX(E9:P9,MONTH(TODAY()))),2)&" owed",IF(N(INDEX(E9:P9,MONTH(TODAY())))>0,"Part paid: "&FIXED(INDEX(T9:AE9,MONTH(TODAY()))-N(INDEX(E9:P9,MONTH(TODAY()))),2)&" left","Due on the "&MIN(N(Units!$F9)+(N(Units!$F9)=0),DAY(EOMONTH(TODAY(),0)))&IF(AND(MIN(N(Units!$F9)+(N(Units!$F9)=0),DAY(EOMONTH(TODAY(),0)))>=11,MIN(N(Units!$F9)+(N(Units!$F9)=0),DAY(EOMONTH(TODAY(),0)))<=13),"th",IF(MOD(MIN(N(Units!$F9)+(N(Units!$F9)=0),DAY(EOMONTH(TODAY(),0))),10)=1,"st",IF(MOD(MIN(N(Units!$F9)+(N(Units!$F9)=0),DAY(EOMONTH(TODAY(),0))),10)=2,"nd",IF(MOD(MIN(N(Units!$F9)+(N(Units!$F9)=0),DAY(EOMONTH(TODAY(),0))),10)=3,"rd","th")))))))))) | T9: =IF($B9="",0,IF(AND(OR(Units!$H9="",Units!$H9<=EOMONTH(DATE(Dashboard!$C$4,1,1),0)),OR(Units!$I9="",Units!$I9>=DATE(Dashboard!$C$4,1,1))),N(Units!$E9),0)) | U9: =IF($B9="",0,IF(AND(OR(Units!$H9="",Units!$H9<=EOMONTH(DATE(Dashboard!$C$4,2,1),0)),OR(Units!$I9="",Units!$I9>=DATE(Dashboard!$C$4,2,1))),N(Units!$E9),0)) | V9: =IF($B9="",0,IF(AND(OR(Units!$H9="",Units!$H9<=EOMONTH(DATE(Dashboard!$C$4,3,1),0)),OR(Units!$I9="",Units!$I9>=DATE(Dashboard!$C$4,3,1))),N(Units!$E9),0)) | W9: =IF($B9="",0,IF(AND(OR(Units!$H9="",Units!$H9<=EOMONTH(DATE(Dashboard!$C$4,4,1),0)),OR(Units!$I9="",Units!$I9>=DATE(Dashboard!$C$4,4,1))),N(Units!$E9),0)) | X9: =IF($B9="",0,IF(AND(OR(Units!$H9="",Units!$H9<=EOMONTH(DATE(Dashboard!$C$4,5,1),0)),OR(Units!$I9="",Units!$I9>=DATE(Dashboard!$C$4,5,1))),N(Units!$E9),0)) | Y9: =IF($B9="",0,IF(AND(OR(Units!$H9="",Units!$H9<=EOMONTH(DATE(Dashboard!$C$4,6,1),0)),OR(Units!$I9="",Units!$I9>=DATE(Dashboard!$C$4,6,1))),N(Units!$E9),0)) | Z9: =IF($B9="",0,IF(AND(OR(Units!$H9="",Units!$H9<=EOMONTH(DATE(Dashboard!$C$4,7,1),0)),OR(Units!$I9="",Units!$I9>=DATE(Dashboard!$C$4,7,1))),N(Units!$E9),0)) | AA9: =IF($B9="",0,IF(AND(OR(Units!$H9="",Units!$H9<=EOMONTH(DATE(Dashboard!$C$4,8,1),0)),OR(Units!$I9="",Units!$I9>=DATE(Dashboard!$C$4,8,1))),N(Units!$E9),0)) | AB9: =IF($B9="",0,IF(AND(OR(Units!$H9="",Units!$H9<=EOMONTH(DATE(Dashboard!$C$4,9,1),0)),OR(Units!$I9="",Units!$I9>=DATE(Dashboard!$C$4,9,1))),N(Units!$E9),0)) | AC9: =IF($B9="",0,IF(AND(OR(Units!$H9="",Units!$H9<=EOMONTH(DATE(Dashboard!$C$4,10,1),0)),OR(Units!$I9="",Units!$I9>=DATE(Dashboard!$C$4,10,1))),N(Units!$E9),0)) | AD9: =IF($B9="",0,IF(AND(OR(Units!$H9="",Units!$H9<=EOMONTH(DATE(Dashboard!$C$4,11,1),0)),OR(Units!$I9="",Units!$I9>=DATE(Dashboard!$C$4,11,1))),N(Units!$E9),0)) | AE9: =IF($B9="",0,IF(AND(OR(Units!$H9="",Units!$H9<=EOMONTH(DATE(Dashboard!$C$4,12,1),0)),OR(Units!$I9="",Units!$I9>=DATE(Dashboard!$C$4,12,1))),N(Units!$E9),0)) | AF9: =IF(AND(T9>0,DATE(Dashboard!$C$4,1,MIN(N(Units!$F9)+(N(Units!$F9)=0),DAY(EOMONTH(DATE(Dashboard!$C$4,1,1),0))))+N(Units!$G9)<TODAY()),MAX(0,T9-N(E9)),0) | AG9: =IF(AND(U9>0,DATE(Dashboard!$C$4,2,MIN(N(Units!$F9)+(N(Units!$F9)=0),DAY(EOMONTH(DATE(Dashboard!$C$4,2,1),0))))+N(Units!$G9)<TODAY()),MAX(0,U9-N(F9)),0) | AH9: =IF(AND(V9>0,DATE(Dashboard!$C$4,3,MIN(N(Units!$F9)+(N(Units!$F9)=0),DAY(EOMONTH(DATE(Dashboard!$C$4,3,1),0))))+N(Units!$G9)<TODAY()),MAX(0,V9-N(G9)),0) | AI9: =IF(AND(W9>0,DATE(Dashboard!$C$4,4,MIN(N(Units!$F9)+(N(Units!$F9)=0),DAY(EOMONTH(DATE(Dashboard!$C$4,4,1),0))))+N(Units!$G9)<TODAY()),MAX(0,W9-N(H9)),0) | AJ9: =IF(AND(X9>0,DATE(Dashboard!$C$4,5,MIN(N(Units!$F9)+(N(Units!$F9)=0),DAY(EOMONTH(DATE(Dashboard!$C$4,5,1),0))))+N(Units!$G9)<TODAY()),MAX(0,X9-N(I9)),0) | AK9: =IF(AND(Y9>0,DATE(Dashboard!$C$4,6,MIN(N(Units!$F9)+(N(Units!$F9)=0),DAY(EOMONTH(DATE(Dashboard!$C$4,6,1),0))))+N(Units!$G9)<TODAY()),MAX(0,Y9-N(J9)),0) | AL9: =IF(AND(Z9>0,DATE(Dashboard!$C$4,7,MIN(N(Units!$F9)+(N(Units!$F9)=0),DAY(EOMONTH(DATE(Dashboard!$C$4,7,1),0))))+N(Units!$G9)<TODAY()),MAX(0,Z9-N(K9)),0) | AM9: =IF(AND(AA9>0,DATE(Dashboard!$C$4,8,MIN(N(Units!$F9)+(N(Units!$F9)=0),DAY(EOMONTH(DATE(Dashboard!$C$4,8,1),0))))+N(Units!$G9)<TODAY()),MAX(0,AA9-N(L9)),0) | AN9: =IF(AND(AB9>0,DATE(Dashboard!$C$4,9,MIN(N(Units!$F9)+(N(Units!$F9)=0),DAY(EOMONTH(DATE(Dashboard!$C$4,9,1),0))))+N(Units!$G9)<TODAY()),MAX(0,AB9-N(M9)),0) | AO9: =IF(AND(AC9>0,DATE(Dashboard!$C$4,10,MIN(N(Units!$F9)+(N(Units!$F9)=0),DAY(EOMONTH(DATE(Dashboard!$C$4,10,1),0))))+N(Units!$G9)<TODAY()),MAX(0,AC9-N(N9)),0) | AP9: =IF(AND(AD9>0,DATE(Dashboard!$C$4,11,MIN(N(Units!$F9)+(N(Units!$F9)=0),DAY(EOMONTH(DATE(Dashboard!$C$4,11,1),0))))+N(Units!$G9)<TODAY()),MAX(0,AD9-N(O9)),0) | AQ9: =IF(AND(AE9>0,DATE(Dashboard!$C$4,12,MIN(N(Units!$F9)+(N(Units!$F9)=0),DAY(EOMONTH(DATE(Dashboard!$C$4,12,1),0))))+N(Units!$G9)<TODAY()),MAX(0,AE9-N(P9)),0) | AR9: =IF(B9="","",Units!C9)
B10: =IF(Units!B10="","",Units!B10) | C10: =IF(B10="","",Units!D10) | D10: =IF(B10="","",Units!E10) | E10: =IF($B10="","",IF(AND(SUMIFS('Rent log'!$D$6:$D$1005,'Rent log'!$C$6:$C$1005,$B10,'Rent log'!$H$6:$H$1005,">="&DATE(Dashboard!$C$4,1,1),'Rent log'!$H$6:$H$1005,"<="&EOMONTH(DATE(Dashboard!$C$4,1,1),0))=0,DATE(Dashboard!$C$4,1,1)>TODAY()),"",SUMIFS('Rent log'!$D$6:$D$1005,'Rent log'!$C$6:$C$1005,$B10,'Rent log'!$H$6:$H$1005,">="&DATE(Dashboard!$C$4,1,1),'Rent log'!$H$6:$H$1005,"<="&EOMONTH(DATE(Dashboard!$C$4,1,1),0)))) | F10: =IF($B10="","",IF(AND(SUMIFS('Rent log'!$D$6:$D$1005,'Rent log'!$C$6:$C$1005,$B10,'Rent log'!$H$6:$H$1005,">="&DATE(Dashboard!$C$4,2,1),'Rent log'!$H$6:$H$1005,"<="&EOMONTH(DATE(Dashboard!$C$4,2,1),0))=0,DATE(Dashboard!$C$4,2,1)>TODAY()),"",SUMIFS('Rent log'!$D$6:$D$1005,'Rent log'!$C$6:$C$1005,$B10,'Rent log'!$H$6:$H$1005,">="&DATE(Dashboard!$C$4,2,1),'Rent log'!$H$6:$H$1005,"<="&EOMONTH(DATE(Dashboard!$C$4,2,1),0)))) | G10: =IF($B10="","",IF(AND(SUMIFS('Rent log'!$D$6:$D$1005,'Rent log'!$C$6:$C$1005,$B10,'Rent log'!$H$6:$H$1005,">="&DATE(Dashboard!$C$4,3,1),'Rent log'!$H$6:$H$1005,"<="&EOMONTH(DATE(Dashboard!$C$4,3,1),0))=0,DATE(Dashboard!$C$4,3,1)>TODAY()),"",SUMIFS('Rent log'!$D$6:$D$1005,'Rent log'!$C$6:$C$1005,$B10,'Rent log'!$H$6:$H$1005,">="&DATE(Dashboard!$C$4,3,1),'Rent log'!$H$6:$H$1005,"<="&EOMONTH(DATE(Dashboard!$C$4,3,1),0)))) | H10: =IF($B10="","",IF(AND(SUMIFS('Rent log'!$D$6:$D$1005,'Rent log'!$C$6:$C$1005,$B10,'Rent log'!$H$6:$H$1005,">="&DATE(Dashboard!$C$4,4,1),'Rent log'!$H$6:$H$1005,"<="&EOMONTH(DATE(Dashboard!$C$4,4,1),0))=0,DATE(Dashboard!$C$4,4,1)>TODAY()),"",SUMIFS('Rent log'!$D$6:$D$1005,'Rent log'!$C$6:$C$1005,$B10,'Rent log'!$H$6:$H$1005,">="&DATE(Dashboard!$C$4,4,1),'Rent log'!$H$6:$H$1005,"<="&EOMONTH(DATE(Dashboard!$C$4,4,1),0)))) | I10: =IF($B10="","",IF(AND(SUMIFS('Rent log'!$D$6:$D$1005,'Rent log'!$C$6:$C$1005,$B10,'Rent log'!$H$6:$H$1005,">="&DATE(Dashboard!$C$4,5,1),'Rent log'!$H$6:$H$1005,"<="&EOMONTH(DATE(Dashboard!$C$4,5,1),0))=0,DATE(Dashboard!$C$4,5,1)>TODAY()),"",SUMIFS('Rent log'!$D$6:$D$1005,'Rent log'!$C$6:$C$1005,$B10,'Rent log'!$H$6:$H$1005,">="&DATE(Dashboard!$C$4,5,1),'Rent log'!$H$6:$H$1005,"<="&EOMONTH(DATE(Dashboard!$C$4,5,1),0)))) | J10: =IF($B10="","",IF(AND(SUMIFS('Rent log'!$D$6:$D$1005,'Rent log'!$C$6:$C$1005,$B10,'Rent log'!$H$6:$H$1005,">="&DATE(Dashboard!$C$4,6,1),'Rent log'!$H$6:$H$1005,"<="&EOMONTH(DATE(Dashboard!$C$4,6,1),0))=0,DATE(Dashboard!$C$4,6,1)>TODAY()),"",SUMIFS('Rent log'!$D$6:$D$1005,'Rent log'!$C$6:$C$1005,$B10,'Rent log'!$H$6:$H$1005,">="&DATE(Dashboard!$C$4,6,1),'Rent log'!$H$6:$H$1005,"<="&EOMONTH(DATE(Dashboard!$C$4,6,1),0)))) | K10: =IF($B10="","",IF(AND(SUMIFS('Rent log'!$D$6:$D$1005,'Rent log'!$C$6:$C$1005,$B10,'Rent log'!$H$6:$H$1005,">="&DATE(Dashboard!$C$4,7,1),'Rent log'!$H$6:$H$1005,"<="&EOMONTH(DATE(Dashboard!$C$4,7,1),0))=0,DATE(Dashboard!$C$4,7,1)>TODAY()),"",SUMIFS('Rent log'!$D$6:$D$1005,'Rent log'!$C$6:$C$1005,$B10,'Rent log'!$H$6:$H$1005,">="&DATE(Dashboard!$C$4,7,1),'Rent log'!$H$6:$H$1005,"<="&EOMONTH(DATE(Dashboard!$C$4,7,1),0)))) | L10: =IF($B10="","",IF(AND(SUMIFS('Rent log'!$D$6:$D$1005,'Rent log'!$C$6:$C$1005,$B10,'Rent log'!$H$6:$H$1005,">="&DATE(Dashboard!$C$4,8,1),'Rent log'!$H$6:$H$1005,"<="&EOMONTH(DATE(Dashboard!$C$4,8,1),0))=0,DATE(Dashboard!$C$4,8,1)>TODAY()),"",SUMIFS('Rent log'!$D$6:$D$1005,'Rent log'!$C$6:$C$1005,$B10,'Rent log'!$H$6:$H$1005,">="&DATE(Dashboard!$C$4,8,1),'Rent log'!$H$6:$H$1005,"<="&EOMONTH(DATE(Dashboard!$C$4,8,1),0)))) | M10: =IF($B10="","",IF(AND(SUMIFS('Rent log'!$D$6:$D$1005,'Rent log'!$C$6:$C$1005,$B10,'Rent log'!$H$6:$H$1005,">="&DATE(Dashboard!$C$4,9,1),'Rent log'!$H$6:$H$1005,"<="&EOMONTH(DATE(Dashboard!$C$4,9,1),0))=0,DATE(Dashboard!$C$4,9,1)>TODAY()),"",SUMIFS('Rent log'!$D$6:$D$1005,'Rent log'!$C$6:$C$1005,$B10,'Rent log'!$H$6:$H$1005,">="&DATE(Dashboard!$C$4,9,1),'Rent log'!$H$6:$H$1005,"<="&EOMONTH(DATE(Dashboard!$C$4,9,1),0)))) | N10: =IF($B10="","",IF(AND(SUMIFS('Rent log'!$D$6:$D$1005,'Rent log'!$C$6:$C$1005,$B10,'Rent log'!$H$6:$H$1005,">="&DATE(Dashboard!$C$4,10,1),'Rent log'!$H$6:$H$1005,"<="&EOMONTH(DATE(Dashboard!$C$4,10,1),0))=0,DATE(Dashboard!$C$4,10,1)>TODAY()),"",SUMIFS('Rent log'!$D$6:$D$1005,'Rent log'!$C$6:$C$1005,$B10,'Rent log'!$H$6:$H$1005,">="&DATE(Dashboard!$C$4,10,1),'Rent log'!$H$6:$H$1005,"<="&EOMONTH(DATE(Dashboard!$C$4,10,1),0)))) | O10: =IF($B10="","",IF(AND(SUMIFS('Rent log'!$D$6:$D$1005,'Rent log'!$C$6:$C$1005,$B10,'Rent log'!$H$6:$H$1005,">="&DATE(Dashboard!$C$4,11,1),'Rent log'!$H$6:$H$1005,"<="&EOMONTH(DATE(Dashboard!$C$4,11,1),0))=0,DATE(Dashboard!$C$4,11,1)>TODAY()),"",SUMIFS('Rent log'!$D$6:$D$1005,'Rent log'!$C$6:$C$1005,$B10,'Rent log'!$H$6:$H$1005,">="&DATE(Dashboard!$C$4,11,1),'Rent log'!$H$6:$H$1005,"<="&EOMONTH(DATE(Dashboard!$C$4,11,1),0)))) | P10: =IF($B10="","",IF(AND(SUMIFS('Rent log'!$D$6:$D$1005,'Rent log'!$C$6:$C$1005,$B10,'Rent log'!$H$6:$H$1005,">="&DATE(Dashboard!$C$4,12,1),'Rent log'!$H$6:$H$1005,"<="&EOMONTH(DATE(Dashboard!$C$4,12,1),0))=0,DATE(Dashboard!$C$4,12,1)>TODAY()),"",SUMIFS('Rent log'!$D$6:$D$1005,'Rent log'!$C$6:$C$1005,$B10,'Rent log'!$H$6:$H$1005,">="&DATE(Dashboard!$C$4,12,1),'Rent log'!$H$6:$H$1005,"<="&EOMONTH(DATE(Dashboard!$C$4,12,1),0)))) | Q10: =IF(B10="","",SUM(E10:P10)) | R10: =IF(B10="","",SUM(AF10:AQ10)) | S10: =IF(B10="","",IF(Dashboard!$C$4<>YEAR(TODAY()),"",IF(INDEX(T10:AE10,MONTH(TODAY()))=0,"No rent due",IF(N(INDEX(E10:P10,MONTH(TODAY())))>=INDEX(T10:AE10,MONTH(TODAY())),"Paid",IF(TODAY()>DATE(YEAR(TODAY()),MONTH(TODAY()),MIN(N(Units!$F10)+(N(Units!$F10)=0),DAY(EOMONTH(TODAY(),0))))+N(Units!$G10),"Late: "&FIXED(INDEX(T10:AE10,MONTH(TODAY()))-N(INDEX(E10:P10,MONTH(TODAY()))),2)&" owed",IF(N(INDEX(E10:P10,MONTH(TODAY())))>0,"Part paid: "&FIXED(INDEX(T10:AE10,MONTH(TODAY()))-N(INDEX(E10:P10,MONTH(TODAY()))),2)&" left","Due on the "&MIN(N(Units!$F10)+(N(Units!$F10)=0),DAY(EOMONTH(TODAY(),0)))&IF(AND(MIN(N(Units!$F10)+(N(Units!$F10)=0),DAY(EOMONTH(TODAY(),0)))>=11,MIN(N(Units!$F10)+(N(Units!$F10)=0),DAY(EOMONTH(TODAY(),0)))<=13),"th",IF(MOD(MIN(N(Units!$F10)+(N(Units!$F10)=0),DAY(EOMONTH(TODAY(),0))),10)=1,"st",IF(MOD(MIN(N(Units!$F10)+(N(Units!$F10)=0),DAY(EOMONTH(TODAY(),0))),10)=2,"nd",IF(MOD(MIN(N(Units!$F10)+(N(Units!$F10)=0),DAY(EOMONTH(TODAY(),0))),10)=3,"rd","th")))))))))) | T10: =IF($B10="",0,IF(AND(OR(Units!$H10="",Units!$H10<=EOMONTH(DATE(Dashboard!$C$4,1,1),0)),OR(Units!$I10="",Units!$I10>=DATE(Dashboard!$C$4,1,1))),N(Units!$E10),0)) | U10: =IF($B10="",0,IF(AND(OR(Units!$H10="",Units!$H10<=EOMONTH(DATE(Dashboard!$C$4,2,1),0)),OR(Units!$I10="",Units!$I10>=DATE(Dashboard!$C$4,2,1))),N(Units!$E10),0)) | V10: =IF($B10="",0,IF(AND(OR(Units!$H10="",Units!$H10<=EOMONTH(DATE(Dashboard!$C$4,3,1),0)),OR(Units!$I10="",Units!$I10>=DATE(Dashboard!$C$4,3,1))),N(Units!$E10),0)) | W10: =IF($B10="",0,IF(AND(OR(Units!$H10="",Units!$H10<=EOMONTH(DATE(Dashboard!$C$4,4,1),0)),OR(Units!$I10="",Units!$I10>=DATE(Dashboard!$C$4,4,1))),N(Units!$E10),0)) | X10: =IF($B10="",0,IF(AND(OR(Units!$H10="",Units!$H10<=EOMONTH(DATE(Dashboard!$C$4,5,1),0)),OR(Units!$I10="",Units!$I10>=DATE(Dashboard!$C$4,5,1))),N(Units!$E10),0)) | Y10: =IF($B10="",0,IF(AND(OR(Units!$H10="",Units!$H10<=EOMONTH(DATE(Dashboard!$C$4,6,1),0)),OR(Units!$I10="",Units!$I10>=DATE(Dashboard!$C$4,6,1))),N(Units!$E10),0)) | Z10: =IF($B10="",0,IF(AND(OR(Units!$H10="",Units!$H10<=EOMONTH(DATE(Dashboard!$C$4,7,1),0)),OR(Units!$I10="",Units!$I10>=DATE(Dashboard!$C$4,7,1))),N(Units!$E10),0)) | AA10: =IF($B10="",0,IF(AND(OR(Units!$H10="",Units!$H10<=EOMONTH(DATE(Dashboard!$C$4,8,1),0)),OR(Units!$I10="",Units!$I10>=DATE(Dashboard!$C$4,8,1))),N(Units!$E10),0)) | AB10: =IF($B10="",0,IF(AND(OR(Units!$H10="",Units!$H10<=EOMONTH(DATE(Dashboard!$C$4,9,1),0)),OR(Units!$I10="",Units!$I10>=DATE(Dashboard!$C$4,9,1))),N(Units!$E10),0)) | AC10: =IF($B10="",0,IF(AND(OR(Units!$H10="",Units!$H10<=EOMONTH(DATE(Dashboard!$C$4,10,1),0)),OR(Units!$I10="",Units!$I10>=DATE(Dashboard!$C$4,10,1))),N(Units!$E10),0)) | AD10: =IF($B10="",0,IF(AND(OR(Units!$H10="",Units!$H10<=EOMONTH(DATE(Dashboard!$C$4,11,1),0)),OR(Units!$I10="",Units!$I10>=DATE(Dashboard!$C$4,11,1))),N(Units!$E10),0)) | AE10: =IF($B10="",0,IF(AND(OR(Units!$H10="",Units!$H10<=EOMONTH(DATE(Dashboard!$C$4,12,1),0)),OR(Units!$I10="",Units!$I10>=DATE(Dashboard!$C$4,12,1))),N(Units!$E10),0)) | AF10: =IF(AND(T10>0,DATE(Dashboard!$C$4,1,MIN(N(Units!$F10)+(N(Units!$F10)=0),DAY(EOMONTH(DATE(Dashboard!$C$4,1,1),0))))+N(Units!$G10)<TODAY()),MAX(0,T10-N(E10)),0) | AG10: =IF(AND(U10>0,DATE(Dashboard!$C$4,2,MIN(N(Units!$F10)+(N(Units!$F10)=0),DAY(EOMONTH(DATE(Dashboard!$C$4,2,1),0))))+N(Units!$G10)<TODAY()),MAX(0,U10-N(F10)),0) | AH10: =IF(AND(V10>0,DATE(Dashboard!$C$4,3,MIN(N(Units!$F10)+(N(Units!$F10)=0),DAY(EOMONTH(DATE(Dashboard!$C$4,3,1),0))))+N(Units!$G10)<TODAY()),MAX(0,V10-N(G10)),0) | AI10: =IF(AND(W10>0,DATE(Dashboard!$C$4,4,MIN(N(Units!$F10)+(N(Units!$F10)=0),DAY(EOMONTH(DATE(Dashboard!$C$4,4,1),0))))+N(Units!$G10)<TODAY()),MAX(0,W10-N(H10)),0) | AJ10: =IF(AND(X10>0,DATE(Dashboard!$C$4,5,MIN(N(Units!$F10)+(N(Units!$F10)=0),DAY(EOMONTH(DATE(Dashboard!$C$4,5,1),0))))+N(Units!$G10)<TODAY()),MAX(0,X10-N(I10)),0) | AK10: =IF(AND(Y10>0,DATE(Dashboard!$C$4,6,MIN(N(Units!$F10)+(N(Units!$F10)=0),DAY(EOMONTH(DATE(Dashboard!$C$4,6,1),0))))+N(Units!$G10)<TODAY()),MAX(0,Y10-N(J10)),0) | AL10: =IF(AND(Z10>0,DATE(Dashboard!$C$4,7,MIN(N(Units!$F10)+(N(Units!$F10)=0),DAY(EOMONTH(DATE(Dashboard!$C$4,7,1),0))))+N(Units!$G10)<TODAY()),MAX(0,Z10-N(K10)),0) | AM10: =IF(AND(AA10>0,DATE(Dashboard!$C$4,8,MIN(N(Units!$F10)+(N(Units!$F10)=0),DAY(EOMONTH(DATE(Dashboard!$C$4,8,1),0))))+N(Units!$G10)<TODAY()),MAX(0,AA10-N(L10)),0) | AN10: =IF(AND(AB10>0,DATE(Dashboard!$C$4,9,MIN(N(Units!$F10)+(N(Units!$F10)=0),DAY(EOMONTH(DATE(Dashboard!$C$4,9,1),0))))+N(Units!$G10)<TODAY()),MAX(0,AB10-N(M10)),0) | AO10: =IF(AND(AC10>0,DATE(Dashboard!$C$4,10,MIN(N(Units!$F10)+(N(Units!$F10)=0),DAY(EOMONTH(DATE(Dashboard!$C$4,10,1),0))))+N(Units!$G10)<TODAY()),MAX(0,AC10-N(N10)),0) | AP10: =IF(AND(AD10>0,DATE(Dashboard!$C$4,11,MIN(N(Units!$F10)+(N(Units!$F10)=0),DAY(EOMONTH(DATE(Dashboard!$C$4,11,1),0))))+N(Units!$G10)<TODAY()),MAX(0,AD10-N(O10)),0) | AQ10: =IF(AND(AE10>0,DATE(Dashboard!$C$4,12,MIN(N(Units!$F10)+(N(Units!$F10)=0),DAY(EOMONTH(DATE(Dashboard!$C$4,12,1),0))))+N(Units!$G10)<TODAY()),MAX(0,AE10-N(P10)),0) | AR10: =IF(B10="","",Units!C10)
B11: =IF(Units!B11="","",Units!B11) | C11: =IF(B11="","",Units!D11) | D11: =IF(B11="","",Units!E11) | E11: =IF($B11="","",IF(AND(SUMIFS('Rent log'!$D$6:$D$1005,'Rent log'!$C$6:$C$1005,$B11,'Rent log'!$H$6:$H$1005,">="&DATE(Dashboard!$C$4,1,1),'Rent log'!$H$6:$H$1005,"<="&EOMONTH(DATE(Dashboard!$C$4,1,1),0))=0,DATE(Dashboard!$C$4,1,1)>TODAY()),"",SUMIFS('Rent log'!$D$6:$D$1005,'Rent log'!$C$6:$C$1005,$B11,'Rent log'!$H$6:$H$1005,">="&DATE(Dashboard!$C$4,1,1),'Rent log'!$H$6:$H$1005,"<="&EOMONTH(DATE(Dashboard!$C$4,1,1),0)))) | F11: =IF($B11="","",IF(AND(SUMIFS('Rent log'!$D$6:$D$1005,'Rent log'!$C$6:$C$1005,$B11,'Rent log'!$H$6:$H$1005,">="&DATE(Dashboard!$C$4,2,1),'Rent log'!$H$6:$H$1005,"<="&EOMONTH(DATE(Dashboard!$C$4,2,1),0))=0,DATE(Dashboard!$C$4,2,1)>TODAY()),"",SUMIFS('Rent log'!$D$6:$D$1005,'Rent log'!$C$6:$C$1005,$B11,'Rent log'!$H$6:$H$1005,">="&DATE(Dashboard!$C$4,2,1),'Rent log'!$H$6:$H$1005,"<="&EOMONTH(DATE(Dashboard!$C$4,2,1),0)))) | G11: =IF($B11="","",IF(AND(SUMIFS('Rent log'!$D$6:$D$1005,'Rent log'!$C$6:$C$1005,$B11,'Rent log'!$H$6:$H$1005,">="&DATE(Dashboard!$C$4,3,1),'Rent log'!$H$6:$H$1005,"<="&EOMONTH(DATE(Dashboard!$C$4,3,1),0))=0,DATE(Dashboard!$C$4,3,1)>TODAY()),"",SUMIFS('Rent log'!$D$6:$D$1005,'Rent log'!$C$6:$C$1005,$B11,'Rent log'!$H$6:$H$1005,">="&DATE(Dashboard!$C$4,3,1),'Rent log'!$H$6:$H$1005,"<="&EOMONTH(DATE(Dashboard!$C$4,3,1),0)))) | H11: =IF($B11="","",IF(AND(SUMIFS('Rent log'!$D$6:$D$1005,'Rent log'!$C$6:$C$1005,$B11,'Rent log'!$H$6:$H$1005,">="&DATE(Dashboard!$C$4,4,1),'Rent log'!$H$6:$H$1005,"<="&EOMONTH(DATE(Dashboard!$C$4,4,1),0))=0,DATE(Dashboard!$C$4,4,1)>TODAY()),"",SUMIFS('Rent log'!$D$6:$D$1005,'Rent log'!$C$6:$C$1005,$B11,'Rent log'!$H$6:$H$1005,">="&DATE(Dashboard!$C$4,4,1),'Rent log'!$H$6:$H$1005,"<="&EOMONTH(DATE(Dashboard!$C$4,4,1),0)))) | I11: =IF($B11="","",IF(AND(SUMIFS('Rent log'!$D$6:$D$1005,'Rent log'!$C$6:$C$1005,$B11,'Rent log'!$H$6:$H$1005,">="&DATE(Dashboard!$C$4,5,1),'Rent log'!$H$6:$H$1005,"<="&EOMONTH(DATE(Dashboard!$C$4,5,1),0))=0,DATE(Dashboard!$C$4,5,1)>TODAY()),"",SUMIFS('Rent log'!$D$6:$D$1005,'Rent log'!$C$6:$C$1005,$B11,'Rent log'!$H$6:$H$1005,">="&DATE(Dashboard!$C$4,5,1),'Rent log'!$H$6:$H$1005,"<="&EOMONTH(DATE(Dashboard!$C$4,5,1),0)))) | J11: =IF($B11="","",IF(AND(SUMIFS('Rent log'!$D$6:$D$1005,'Rent log'!$C$6:$C$1005,$B11,'Rent log'!$H$6:$H$1005,">="&DATE(Dashboard!$C$4,6,1),'Rent log'!$H$6:$H$1005,"<="&EOMONTH(DATE(Dashboard!$C$4,6,1),0))=0,DATE(Dashboard!$C$4,6,1)>TODAY()),"",SUMIFS('Rent log'!$D$6:$D$1005,'Rent log'!$C$6:$C$1005,$B11,'Rent log'!$H$6:$H$1005,">="&DATE(Dashboard!$C$4,6,1),'Rent log'!$H$6:$H$1005,"<="&EOMONTH(DATE(Dashboard!$C$4,6,1),0)))) | K11: =IF($B11="","",IF(AND(SUMIFS('Rent log'!$D$6:$D$1005,'Rent log'!$C$6:$C$1005,$B11,'Rent log'!$H$6:$H$1005,">="&DATE(Dashboard!$C$4,7,1),'Rent log'!$H$6:$H$1005,"<="&EOMONTH(DATE(Dashboard!$C$4,7,1),0))=0,DATE(Dashboard!$C$4,7,1)>TODAY()),"",SUMIFS('Rent log'!$D$6:$D$1005,'Rent log'!$C$6:$C$1005,$B11,'Rent log'!$H$6:$H$1005,">="&DATE(Dashboard!$C$4,7,1),'Rent log'!$H$6:$H$1005,"<="&EOMONTH(DATE(Dashboard!$C$4,7,1),0)))) | L11: =IF($B11="","",IF(AND(SUMIFS('Rent log'!$D$6:$D$1005,'Rent log'!$C$6:$C$1005,$B11,'Rent log'!$H$6:$H$1005,">="&DATE(Dashboard!$C$4,8,1),'Rent log'!$H$6:$H$1005,"<="&EOMONTH(DATE(Dashboard!$C$4,8,1),0))=0,DATE(Dashboard!$C$4,8,1)>TODAY()),"",SUMIFS('Rent log'!$D$6:$D$1005,'Rent log'!$C$6:$C$1005,$B11,'Rent log'!$H$6:$H$1005,">="&DATE(Dashboard!$C$4,8,1),'Rent log'!$H$6:$H$1005,"<="&EOMONTH(DATE(Dashboard!$C$4,8,1),0)))) | M11: =IF($B11="","",IF(AND(SUMIFS('Rent log'!$D$6:$D$1005,'Rent log'!$C$6:$C$1005,$B11,'Rent log'!$H$6:$H$1005,">="&DATE(Dashboard!$C$4,9,1),'Rent log'!$H$6:$H$1005,"<="&EOMONTH(DATE(Dashboard!$C$4,9,1),0))=0,DATE(Dashboard!$C$4,9,1)>TODAY()),"",SUMIFS('Rent log'!$D$6:$D$1005,'Rent log'!$C$6:$C$1005,$B11,'Rent log'!$H$6:$H$1005,">="&DATE(Dashboard!$C$4,9,1),'Rent log'!$H$6:$H$1005,"<="&EOMONTH(DATE(Dashboard!$C$4,9,1),0)))) | N11: =IF($B11="","",IF(AND(SUMIFS('Rent log'!$D$6:$D$1005,'Rent log'!$C$6:$C$1005,$B11,'Rent log'!$H$6:$H$1005,">="&DATE(Dashboard!$C$4,10,1),'Rent log'!$H$6:$H$1005,"<="&EOMONTH(DATE(Dashboard!$C$4,10,1),0))=0,DATE(Dashboard!$C$4,10,1)>TODAY()),"",SUMIFS('Rent log'!$D$6:$D$1005,'Rent log'!$C$6:$C$1005,$B11,'Rent log'!$H$6:$H$1005,">="&DATE(Dashboard!$C$4,10,1),'Rent log'!$H$6:$H$1005,"<="&EOMONTH(DATE(Dashboard!$C$4,10,1),0)))) | O11: =IF($B11="","",IF(AND(SUMIFS('Rent log'!$D$6:$D$1005,'Rent log'!$C$6:$C$1005,$B11,'Rent log'!$H$6:$H$1005,">="&DATE(Dashboard!$C$4,11,1),'Rent log'!$H$6:$H$1005,"<="&EOMONTH(DATE(Dashboard!$C$4,11,1),0))=0,DATE(Dashboard!$C$4,11,1)>TODAY()),"",SUMIFS('Rent log'!$D$6:$D$1005,'Rent log'!$C$6:$C$1005,$B11,'Rent log'!$H$6:$H$1005,">="&DATE(Dashboard!$C$4,11,1),'Rent log'!$H$6:$H$1005,"<="&EOMONTH(DATE(Dashboard!$C$4,11,1),0)))) | P11: =IF($B11="","",IF(AND(SUMIFS('Rent log'!$D$6:$D$1005,'Rent log'!$C$6:$C$1005,$B11,'Rent log'!$H$6:$H$1005,">="&DATE(Dashboard!$C$4,12,1),'Rent log'!$H$6:$H$1005,"<="&EOMONTH(DATE(Dashboard!$C$4,12,1),0))=0,DATE(Dashboard!$C$4,12,1)>TODAY()),"",SUMIFS('Rent log'!$D$6:$D$1005,'Rent log'!$C$6:$C$1005,$B11,'Rent log'!$H$6:$H$1005,">="&DATE(Dashboard!$C$4,12,1),'Rent log'!$H$6:$H$1005,"<="&EOMONTH(DATE(Dashboard!$C$4,12,1),0)))) | Q11: =IF(B11="","",SUM(E11:P11)) | R11: =IF(B11="","",SUM(AF11:AQ11)) | S11: =IF(B11="","",IF(Dashboard!$C$4<>YEAR(TODAY()),"",IF(INDEX(T11:AE11,MONTH(TODAY()))=0,"No rent due",IF(N(INDEX(E11:P11,MONTH(TODAY())))>=INDEX(T11:AE11,MONTH(TODAY())),"Paid",IF(TODAY()>DATE(YEAR(TODAY()),MONTH(TODAY()),MIN(N(Units!$F11)+(N(Units!$F11)=0),DAY(EOMONTH(TODAY(),0))))+N(Units!$G11),"Late: "&FIXED(INDEX(T11:AE11,MONTH(TODAY()))-N(INDEX(E11:P11,MONTH(TODAY()))),2)&" owed",IF(N(INDEX(E11:P11,MONTH(TODAY())))>0,"Part paid: "&FIXED(INDEX(T11:AE11,MONTH(TODAY()))-N(INDEX(E11:P11,MONTH(TODAY()))),2)&" left","Due on the "&MIN(N(Units!$F11)+(N(Units!$F11)=0),DAY(EOMONTH(TODAY(),0)))&IF(AND(MIN(N(Units!$F11)+(N(Units!$F11)=0),DAY(EOMONTH(TODAY(),0)))>=11,MIN(N(Units!$F11)+(N(Units!$F11)=0),DAY(EOMONTH(TODAY(),0)))<=13),"th",IF(MOD(MIN(N(Units!$F11)+(N(Units!$F11)=0),DAY(EOMONTH(TODAY(),0))),10)=1,"st",IF(MOD(MIN(N(Units!$F11)+(N(Units!$F11)=0),DAY(EOMONTH(TODAY(),0))),10)=2,"nd",IF(MOD(MIN(N(Units!$F11)+(N(Units!$F11)=0),DAY(EOMONTH(TODAY(),0))),10)=3,"rd","th")))))))))) | T11: =IF($B11="",0,IF(AND(OR(Units!$H11="",Units!$H11<=EOMONTH(DATE(Dashboard!$C$4,1,1),0)),OR(Units!$I11="",Units!$I11>=DATE(Dashboard!$C$4,1,1))),N(Units!$E11),0)) | U11: =IF($B11="",0,IF(AND(OR(Units!$H11="",Units!$H11<=EOMONTH(DATE(Dashboard!$C$4,2,1),0)),OR(Units!$I11="",Units!$I11>=DATE(Dashboard!$C$4,2,1))),N(Units!$E11),0)) | V11: =IF($B11="",0,IF(AND(OR(Units!$H11="",Units!$H11<=EOMONTH(DATE(Dashboard!$C$4,3,1),0)),OR(Units!$I11="",Units!$I11>=DATE(Dashboard!$C$4,3,1))),N(Units!$E11),0)) | W11: =IF($B11="",0,IF(AND(OR(Units!$H11="",Units!$H11<=EOMONTH(DATE(Dashboard!$C$4,4,1),0)),OR(Units!$I11="",Units!$I11>=DATE(Dashboard!$C$4,4,1))),N(Units!$E11),0)) | X11: =IF($B11="",0,IF(AND(OR(Units!$H11="",Units!$H11<=EOMONTH(DATE(Dashboard!$C$4,5,1),0)),OR(Units!$I11="",Units!$I11>=DATE(Dashboard!$C$4,5,1))),N(Units!$E11),0)) | Y11: =IF($B11="",0,IF(AND(OR(Units!$H11="",Units!$H11<=EOMONTH(DATE(Dashboard!$C$4,6,1),0)),OR(Units!$I11="",Units!$I11>=DATE(Dashboard!$C$4,6,1))),N(Units!$E11),0)) | Z11: =IF($B11="",0,IF(AND(OR(Units!$H11="",Units!$H11<=EOMONTH(DATE(Dashboard!$C$4,7,1),0)),OR(Units!$I11="",Units!$I11>=DATE(Dashboard!$C$4,7,1))),N(Units!$E11),0)) | AA11: =IF($B11="",0,IF(AND(OR(Units!$H11="",Units!$H11<=EOMONTH(DATE(Dashboard!$C$4,8,1),0)),OR(Units!$I11="",Units!$I11>=DATE(Dashboard!$C$4,8,1))),N(Units!$E11),0)) | AB11: =IF($B11="",0,IF(AND(OR(Units!$H11="",Units!$H11<=EOMONTH(DATE(Dashboard!$C$4,9,1),0)),OR(Units!$I11="",Units!$I11>=DATE(Dashboard!$C$4,9,1))),N(Units!$E11),0)) | AC11: =IF($B11="",0,IF(AND(OR(Units!$H11="",Units!$H11<=EOMONTH(DATE(Dashboard!$C$4,10,1),0)),OR(Units!$I11="",Units!$I11>=DATE(Dashboard!$C$4,10,1))),N(Units!$E11),0)) | AD11: =IF($B11="",0,IF(AND(OR(Units!$H11="",Units!$H11<=EOMONTH(DATE(Dashboard!$C$4,11,1),0)),OR(Units!$I11="",Units!$I11>=DATE(Dashboard!$C$4,11,1))),N(Units!$E11),0)) | AE11: =IF($B11="",0,IF(AND(OR(Units!$H11="",Units!$H11<=EOMONTH(DATE(Dashboard!$C$4,12,1),0)),OR(Units!$I11="",Units!$I11>=DATE(Dashboard!$C$4,12,1))),N(Units!$E11),0)) | AF11: =IF(AND(T11>0,DATE(Dashboard!$C$4,1,MIN(N(Units!$F11)+(N(Units!$F11)=0),DAY(EOMONTH(DATE(Dashboard!$C$4,1,1),0))))+N(Units!$G11)<TODAY()),MAX(0,T11-N(E11)),0) | AG11: =IF(AND(U11>0,DATE(Dashboard!$C$4,2,MIN(N(Units!$F11)+(N(Units!$F11)=0),DAY(EOMONTH(DATE(Dashboard!$C$4,2,1),0))))+N(Units!$G11)<TODAY()),MAX(0,U11-N(F11)),0) | AH11: =IF(AND(V11>0,DATE(Dashboard!$C$4,3,MIN(N(Units!$F11)+(N(Units!$F11)=0),DAY(EOMONTH(DATE(Dashboard!$C$4,3,1),0))))+N(Units!$G11)<TODAY()),MAX(0,V11-N(G11)),0) | AI11: =IF(AND(W11>0,DATE(Dashboard!$C$4,4,MIN(N(Units!$F11)+(N(Units!$F11)=0),DAY(EOMONTH(DATE(Dashboard!$C$4,4,1),0))))+N(Units!$G11)<TODAY()),MAX(0,W11-N(H11)),0) | AJ11: =IF(AND(X11>0,DATE(Dashboard!$C$4,5,MIN(N(Units!$F11)+(N(Units!$F11)=0),DAY(EOMONTH(DATE(Dashboard!$C$4,5,1),0))))+N(Units!$G11)<TODAY()),MAX(0,X11-N(I11)),0) | AK11: =IF(AND(Y11>0,DATE(Dashboard!$C$4,6,MIN(N(Units!$F11)+(N(Units!$F11)=0),DAY(EOMONTH(DATE(Dashboard!$C$4,6,1),0))))+N(Units!$G11)<TODAY()),MAX(0,Y11-N(J11)),0) | AL11: =IF(AND(Z11>0,DATE(Dashboard!$C$4,7,MIN(N(Units!$F11)+(N(Units!$F11)=0),DAY(EOMONTH(DATE(Dashboard!$C$4,7,1),0))))+N(Units!$G11)<TODAY()),MAX(0,Z11-N(K11)),0) | AM11: =IF(AND(AA11>0,DATE(Dashboard!$C$4,8,MIN(N(Units!$F11)+(N(Units!$F11)=0),DAY(EOMONTH(DATE(Dashboard!$C$4,8,1),0))))+N(Units!$G11)<TODAY()),MAX(0,AA11-N(L11)),0) | AN11: =IF(AND(AB11>0,DATE(Dashboard!$C$4,9,MIN(N(Units!$F11)+(N(Units!$F11)=0),DAY(EOMONTH(DATE(Dashboard!$C$4,9,1),0))))+N(Units!$G11)<TODAY()),MAX(0,AB11-N(M11)),0) | AO11: =IF(AND(AC11>0,DATE(Dashboard!$C$4,10,MIN(N(Units!$F11)+(N(Units!$F11)=0),DAY(EOMONTH(DATE(Dashboard!$C$4,10,1),0))))+N(Units!$G11)<TODAY()),MAX(0,AC11-N(N11)),0) | AP11: =IF(AND(AD11>0,DATE(Dashboard!$C$4,11,MIN(N(Units!$F11)+(N(Units!$F11)=0),DAY(EOMONTH(DATE(Dashboard!$C$4,11,1),0))))+N(Units!$G11)<TODAY()),MAX(0,AD11-N(O11)),0) | AQ11: =IF(AND(AE11>0,DATE(Dashboard!$C$4,12,MIN(N(Units!$F11)+(N(Units!$F11)=0),DAY(EOMONTH(DATE(Dashboard!$C$4,12,1),0))))+N(Units!$G11)<TODAY()),MAX(0,AE11-N(P11)),0) | AR11: =IF(B11="","",Units!C11)
B12: =IF(Units!B12="","",Units!B12) | C12: =IF(B12="","",Units!D12) | D12: =IF(B12="","",Units!E12) | E12: =IF($B12="","",IF(AND(SUMIFS('Rent log'!$D$6:$D$1005,'Rent log'!$C$6:$C$1005,$B12,'Rent log'!$H$6:$H$1005,">="&DATE(Dashboard!$C$4,1,1),'Rent log'!$H$6:$H$1005,"<="&EOMONTH(DATE(Dashboard!$C$4,1,1),0))=0,DATE(Dashboard!$C$4,1,1)>TODAY()),"",SUMIFS('Rent log'!$D$6:$D$1005,'Rent log'!$C$6:$C$1005,$B12,'Rent log'!$H$6:$H$1005,">="&DATE(Dashboard!$C$4,1,1),'Rent log'!$H$6:$H$1005,"<="&EOMONTH(DATE(Dashboard!$C$4,1,1),0)))) | F12: =IF($B12="","",IF(AND(SUMIFS('Rent log'!$D$6:$D$1005,'Rent log'!$C$6:$C$1005,$B12,'Rent log'!$H$6:$H$1005,">="&DATE(Dashboard!$C$4,2,1),'Rent log'!$H$6:$H$1005,"<="&EOMONTH(DATE(Dashboard!$C$4,2,1),0))=0,DATE(Dashboard!$C$4,2,1)>TODAY()),"",SUMIFS('Rent log'!$D$6:$D$1005,'Rent log'!$C$6:$C$1005,$B12,'Rent log'!$H$6:$H$1005,">="&DATE(Dashboard!$C$4,2,1),'Rent log'!$H$6:$H$1005,"<="&EOMONTH(DATE(Dashboard!$C$4,2,1),0)))) | G12: =IF($B12="","",IF(AND(SUMIFS('Rent log'!$D$6:$D$1005,'Rent log'!$C$6:$C$1005,$B12,'Rent log'!$H$6:$H$1005,">="&DATE(Dashboard!$C$4,3,1),'Rent log'!$H$6:$H$1005,"<="&EOMONTH(DATE(Dashboard!$C$4,3,1),0))=0,DATE(Dashboard!$C$4,3,1)>TODAY()),"",SUMIFS('Rent log'!$D$6:$D$1005,'Rent log'!$C$6:$C$1005,$B12,'Rent log'!$H$6:$H$1005,">="&DATE(Dashboard!$C$4,3,1),'Rent log'!$H$6:$H$1005,"<="&EOMONTH(DATE(Dashboard!$C$4,3,1),0)))) | H12: =IF($B12="","",IF(AND(SUMIFS('Rent log'!$D$6:$D$1005,'Rent log'!$C$6:$C$1005,$B12,'Rent log'!$H$6:$H$1005,">="&DATE(Dashboard!$C$4,4,1),'Rent log'!$H$6:$H$1005,"<="&EOMONTH(DATE(Dashboard!$C$4,4,1),0))=0,DATE(Dashboard!$C$4,4,1)>TODAY()),"",SUMIFS('Rent log'!$D$6:$D$1005,'Rent log'!$C$6:$C$1005,$B12,'Rent log'!$H$6:$H$1005,">="&DATE(Dashboard!$C$4,4,1),'Rent log'!$H$6:$H$1005,"<="&EOMONTH(DATE(Dashboard!$C$4,4,1),0)))) | I12: =IF($B12="","",IF(AND(SUMIFS('Rent log'!$D$6:$D$1005,'Rent log'!$C$6:$C$1005,$B12,'Rent log'!$H$6:$H$1005,">="&DATE(Dashboard!$C$4,5,1),'Rent log'!$H$6:$H$1005,"<="&EOMONTH(DATE(Dashboard!$C$4,5,1),0))=0,DATE(Dashboard!$C$4,5,1)>TODAY()),"",SUMIFS('Rent log'!$D$6:$D$1005,'Rent log'!$C$6:$C$1005,$B12,'Rent log'!$H$6:$H$1005,">="&DATE(Dashboard!$C$4,5,1),'Rent log'!$H$6:$H$1005,"<="&EOMONTH(DATE(Dashboard!$C$4,5,1),0)))) | J12: =IF($B12="","",IF(AND(SUMIFS('Rent log'!$D$6:$D$1005,'Rent log'!$C$6:$C$1005,$B12,'Rent log'!$H$6:$H$1005,">="&DATE(Dashboard!$C$4,6,1),'Rent log'!$H$6:$H$1005,"<="&EOMONTH(DATE(Dashboard!$C$4,6,1),0))=0,DATE(Dashboard!$C$4,6,1)>TODAY()),"",SUMIFS('Rent log'!$D$6:$D$1005,'Rent log'!$C$6:$C$1005,$B12,'Rent log'!$H$6:$H$1005,">="&DATE(Dashboard!$C$4,6,1),'Rent log'!$H$6:$H$1005,"<="&EOMONTH(DATE(Dashboard!$C$4,6,1),0)))) | K12: =IF($B12="","",IF(AND(SUMIFS('Rent log'!$D$6:$D$1005,'Rent log'!$C$6:$C$1005,$B12,'Rent log'!$H$6:$H$1005,">="&DATE(Dashboard!$C$4,7,1),'Rent log'!$H$6:$H$1005,"<="&EOMONTH(DATE(Dashboard!$C$4,7,1),0))=0,DATE(Dashboard!$C$4,7,1)>TODAY()),"",SUMIFS('Rent log'!$D$6:$D$1005,'Rent log'!$C$6:$C$1005,$B12,'Rent log'!$H$6:$H$1005,">="&DATE(Dashboard!$C$4,7,1),'Rent log'!$H$6:$H$1005,"<="&EOMONTH(DATE(Dashboard!$C$4,7,1),0)))) | L12: =IF($B12="","",IF(AND(SUMIFS('Rent log'!$D$6:$D$1005,'Rent log'!$C$6:$C$1005,$B12,'Rent log'!$H$6:$H$1005,">="&DATE(Dashboard!$C$4,8,1),'Rent log'!$H$6:$H$1005,"<="&EOMONTH(DATE(Dashboard!$C$4,8,1),0))=0,DATE(Dashboard!$C$4,8,1)>TODAY()),"",SUMIFS('Rent log'!$D$6:$D$1005,'Rent log'!$C$6:$C$1005,$B12,'Rent log'!$H$6:$H$1005,">="&DATE(Dashboard!$C$4,8,1),'Rent log'!$H$6:$H$1005,"<="&EOMONTH(DATE(Dashboard!$C$4,8,1),0)))) | M12: =IF($B12="","",IF(AND(SUMIFS('Rent log'!$D$6:$D$1005,'Rent log'!$C$6:$C$1005,$B12,'Rent log'!$H$6:$H$1005,">="&DATE(Dashboard!$C$4,9,1),'Rent log'!$H$6:$H$1005,"<="&EOMONTH(DATE(Dashboard!$C$4,9,1),0))=0,DATE(Dashboard!$C$4,9,1)>TODAY()),"",SUMIFS('Rent log'!$D$6:$D$1005,'Rent log'!$C$6:$C$1005,$B12,'Rent log'!$H$6:$H$1005,">="&DATE(Dashboard!$C$4,9,1),'Rent log'!$H$6:$H$1005,"<="&EOMONTH(DATE(Dashboard!$C$4,9,1),0)))) | N12: =IF($B12="","",IF(AND(SUMIFS('Rent log'!$D$6:$D$1005,'Rent log'!$C$6:$C$1005,$B12,'Rent log'!$H$6:$H$1005,">="&DATE(Dashboard!$C$4,10,1),'Rent log'!$H$6:$H$1005,"<="&EOMONTH(DATE(Dashboard!$C$4,10,1),0))=0,DATE(Dashboard!$C$4,10,1)>TODAY()),"",SUMIFS('Rent log'!$D$6:$D$1005,'Rent log'!$C$6:$C$1005,$B12,'Rent log'!$H$6:$H$1005,">="&DATE(Dashboard!$C$4,10,1),'Rent log'!$H$6:$H$1005,"<="&EOMONTH(DATE(Dashboard!$C$4,10,1),0)))) | O12: =IF($B12="","",IF(AND(SUMIFS('Rent log'!$D$6:$D$1005,'Rent log'!$C$6:$C$1005,$B12,'Rent log'!$H$6:$H$1005,">="&DATE(Dashboard!$C$4,11,1),'Rent log'!$H$6:$H$1005,"<="&EOMONTH(DATE(Dashboard!$C$4,11,1),0))=0,DATE(Dashboard!$C$4,11,1)>TODAY()),"",SUMIFS('Rent log'!$D$6:$D$1005,'Rent log'!$C$6:$C$1005,$B12,'Rent log'!$H$6:$H$1005,">="&DATE(Dashboard!$C$4,11,1),'Rent log'!$H$6:$H$1005,"<="&EOMONTH(DATE(Dashboard!$C$4,11,1),0)))) | P12: =IF($B12="","",IF(AND(SUMIFS('Rent log'!$D$6:$D$1005,'Rent log'!$C$6:$C$1005,$B12,'Rent log'!$H$6:$H$1005,">="&DATE(Dashboard!$C$4,12,1),'Rent log'!$H$6:$H$1005,"<="&EOMONTH(DATE(Dashboard!$C$4,12,1),0))=0,DATE(Dashboard!$C$4,12,1)>TODAY()),"",SUMIFS('Rent log'!$D$6:$D$1005,'Rent log'!$C$6:$C$1005,$B12,'Rent log'!$H$6:$H$1005,">="&DATE(Dashboard!$C$4,12,1),'Rent log'!$H$6:$H$1005,"<="&EOMONTH(DATE(Dashboard!$C$4,12,1),0)))) | Q12: =IF(B12="","",SUM(E12:P12)) | R12: =IF(B12="","",SUM(AF12:AQ12)) | S12: =IF(B12="","",IF(Dashboard!$C$4<>YEAR(TODAY()),"",IF(INDEX(T12:AE12,MONTH(TODAY()))=0,"No rent due",IF(N(INDEX(E12:P12,MONTH(TODAY())))>=INDEX(T12:AE12,MONTH(TODAY())),"Paid",IF(TODAY()>DATE(YEAR(TODAY()),MONTH(TODAY()),MIN(N(Units!$F12)+(N(Units!$F12)=0),DAY(EOMONTH(TODAY(),0))))+N(Units!$G12),"Late: "&FIXED(INDEX(T12:AE12,MONTH(TODAY()))-N(INDEX(E12:P12,MONTH(TODAY()))),2)&" owed",IF(N(INDEX(E12:P12,MONTH(TODAY())))>0,"Part paid: "&FIXED(INDEX(T12:AE12,MONTH(TODAY()))-N(INDEX(E12:P12,MONTH(TODAY()))),2)&" left","Due on the "&MIN(N(Units!$F12)+(N(Units!$F12)=0),DAY(EOMONTH(TODAY(),0)))&IF(AND(MIN(N(Units!$F12)+(N(Units!$F12)=0),DAY(EOMONTH(TODAY(),0)))>=11,MIN(N(Units!$F12)+(N(Units!$F12)=0),DAY(EOMONTH(TODAY(),0)))<=13),"th",IF(MOD(MIN(N(Units!$F12)+(N(Units!$F12)=0),DAY(EOMONTH(TODAY(),0))),10)=1,"st",IF(MOD(MIN(N(Units!$F12)+(N(Units!$F12)=0),DAY(EOMONTH(TODAY(),0))),10)=2,"nd",IF(MOD(MIN(N(Units!$F12)+(N(Units!$F12)=0),DAY(EOMONTH(TODAY(),0))),10)=3,"rd","th")))))))))) | T12: =IF($B12="",0,IF(AND(OR(Units!$H12="",Units!$H12<=EOMONTH(DATE(Dashboard!$C$4,1,1),0)),OR(Units!$I12="",Units!$I12>=DATE(Dashboard!$C$4,1,1))),N(Units!$E12),0)) | U12: =IF($B12="",0,IF(AND(OR(Units!$H12="",Units!$H12<=EOMONTH(DATE(Dashboard!$C$4,2,1),0)),OR(Units!$I12="",Units!$I12>=DATE(Dashboard!$C$4,2,1))),N(Units!$E12),0)) | V12: =IF($B12="",0,IF(AND(OR(Units!$H12="",Units!$H12<=EOMONTH(DATE(Dashboard!$C$4,3,1),0)),OR(Units!$I12="",Units!$I12>=DATE(Dashboard!$C$4,3,1))),N(Units!$E12),0)) | W12: =IF($B12="",0,IF(AND(OR(Units!$H12="",Units!$H12<=EOMONTH(DATE(Dashboard!$C$4,4,1),0)),OR(Units!$I12="",Units!$I12>=DATE(Dashboard!$C$4,4,1))),N(Units!$E12),0)) | X12: =IF($B12="",0,IF(AND(OR(Units!$H12="",Units!$H12<=EOMONTH(DATE(Dashboard!$C$4,5,1),0)),OR(Units!$I12="",Units!$I12>=DATE(Dashboard!$C$4,5,1))),N(Units!$E12),0)) | Y12: =IF($B12="",0,IF(AND(OR(Units!$H12="",Units!$H12<=EOMONTH(DATE(Dashboard!$C$4,6,1),0)),OR(Units!$I12="",Units!$I12>=DATE(Dashboard!$C$4,6,1))),N(Units!$E12),0)) | Z12: =IF($B12="",0,IF(AND(OR(Units!$H12="",Units!$H12<=EOMONTH(DATE(Dashboard!$C$4,7,1),0)),OR(Units!$I12="",Units!$I12>=DATE(Dashboard!$C$4,7,1))),N(Units!$E12),0)) | AA12: =IF($B12="",0,IF(AND(OR(Units!$H12="",Units!$H12<=EOMONTH(DATE(Dashboard!$C$4,8,1),0)),OR(Units!$I12="",Units!$I12>=DATE(Dashboard!$C$4,8,1))),N(Units!$E12),0)) | AB12: =IF($B12="",0,IF(AND(OR(Units!$H12="",Units!$H12<=EOMONTH(DATE(Dashboard!$C$4,9,1),0)),OR(Units!$I12="",Units!$I12>=DATE(Dashboard!$C$4,9,1))),N(Units!$E12),0)) | AC12: =IF($B12="",0,IF(AND(OR(Units!$H12="",Units!$H12<=EOMONTH(DATE(Dashboard!$C$4,10,1),0)),OR(Units!$I12="",Units!$I12>=DATE(Dashboard!$C$4,10,1))),N(Units!$E12),0)) | AD12: =IF($B12="",0,IF(AND(OR(Units!$H12="",Units!$H12<=EOMONTH(DATE(Dashboard!$C$4,11,1),0)),OR(Units!$I12="",Units!$I12>=DATE(Dashboard!$C$4,11,1))),N(Units!$E12),0)) | AE12: =IF($B12="",0,IF(AND(OR(Units!$H12="",Units!$H12<=EOMONTH(DATE(Dashboard!$C$4,12,1),0)),OR(Units!$I12="",Units!$I12>=DATE(Dashboard!$C$4,12,1))),N(Units!$E12),0)) | AF12: =IF(AND(T12>0,DATE(Dashboard!$C$4,1,MIN(N(Units!$F12)+(N(Units!$F12)=0),DAY(EOMONTH(DATE(Dashboard!$C$4,1,1),0))))+N(Units!$G12)<TODAY()),MAX(0,T12-N(E12)),0) | AG12: =IF(AND(U12>0,DATE(Dashboard!$C$4,2,MIN(N(Units!$F12)+(N(Units!$F12)=0),DAY(EOMONTH(DATE(Dashboard!$C$4,2,1),0))))+N(Units!$G12)<TODAY()),MAX(0,U12-N(F12)),0) | AH12: =IF(AND(V12>0,DATE(Dashboard!$C$4,3,MIN(N(Units!$F12)+(N(Units!$F12)=0),DAY(EOMONTH(DATE(Dashboard!$C$4,3,1),0))))+N(Units!$G12)<TODAY()),MAX(0,V12-N(G12)),0) | AI12: =IF(AND(W12>0,DATE(Dashboard!$C$4,4,MIN(N(Units!$F12)+(N(Units!$F12)=0),DAY(EOMONTH(DATE(Dashboard!$C$4,4,1),0))))+N(Units!$G12)<TODAY()),MAX(0,W12-N(H12)),0) | AJ12: =IF(AND(X12>0,DATE(Dashboard!$C$4,5,MIN(N(Units!$F12)+(N(Units!$F12)=0),DAY(EOMONTH(DATE(Dashboard!$C$4,5,1),0))))+N(Units!$G12)<TODAY()),MAX(0,X12-N(I12)),0) | AK12: =IF(AND(Y12>0,DATE(Dashboard!$C$4,6,MIN(N(Units!$F12)+(N(Units!$F12)=0),DAY(EOMONTH(DATE(Dashboard!$C$4,6,1),0))))+N(Units!$G12)<TODAY()),MAX(0,Y12-N(J12)),0) | AL12: =IF(AND(Z12>0,DATE(Dashboard!$C$4,7,MIN(N(Units!$F12)+(N(Units!$F12)=0),DAY(EOMONTH(DATE(Dashboard!$C$4,7,1),0))))+N(Units!$G12)<TODAY()),MAX(0,Z12-N(K12)),0) | AM12: =IF(AND(AA12>0,DATE(Dashboard!$C$4,8,MIN(N(Units!$F12)+(N(Units!$F12)=0),DAY(EOMONTH(DATE(Dashboard!$C$4,8,1),0))))+N(Units!$G12)<TODAY()),MAX(0,AA12-N(L12)),0) | AN12: =IF(AND(AB12>0,DATE(Dashboard!$C$4,9,MIN(N(Units!$F12)+(N(Units!$F12)=0),DAY(EOMONTH(DATE(Dashboard!$C$4,9,1),0))))+N(Units!$G12)<TODAY()),MAX(0,AB12-N(M12)),0) | AO12: =IF(AND(AC12>0,DATE(Dashboard!$C$4,10,MIN(N(Units!$F12)+(N(Units!$F12)=0),DAY(EOMONTH(DATE(Dashboard!$C$4,10,1),0))))+N(Units!$G12)<TODAY()),MAX(0,AC12-N(N12)),0) | AP12: =IF(AND(AD12>0,DATE(Dashboard!$C$4,11,MIN(N(Units!$F12)+(N(Units!$F12)=0),DAY(EOMONTH(DATE(Dashboard!$C$4,11,1),0))))+N(Units!$G12)<TODAY()),MAX(0,AD12-N(O12)),0) | AQ12: =IF(AND(AE12>0,DATE(Dashboard!$C$4,12,MIN(N(Units!$F12)+(N(Units!$F12)=0),DAY(EOMONTH(DATE(Dashboard!$C$4,12,1),0))))+N(Units!$G12)<TODAY()),MAX(0,AE12-N(P12)),0) | AR12: =IF(B12="","",Units!C12)
B13: =IF(Units!B13="","",Units!B13) | C13: =IF(B13="","",Units!D13) | D13: =IF(B13="","",Units!E13) | E13: =IF($B13="","",IF(AND(SUMIFS('Rent log'!$D$6:$D$1005,'Rent log'!$C$6:$C$1005,$B13,'Rent log'!$H$6:$H$1005,">="&DATE(Dashboard!$C$4,1,1),'Rent log'!$H$6:$H$1005,"<="&EOMONTH(DATE(Dashboard!$C$4,1,1),0))=0,DATE(Dashboard!$C$4,1,1)>TODAY()),"",SUMIFS('Rent log'!$D$6:$D$1005,'Rent log'!$C$6:$C$1005,$B13,'Rent log'!$H$6:$H$1005,">="&DATE(Dashboard!$C$4,1,1),'Rent log'!$H$6:$H$1005,"<="&EOMONTH(DATE(Dashboard!$C$4,1,1),0)))) | F13: =IF($B13="","",IF(AND(SUMIFS('Rent log'!$D$6:$D$1005,'Rent log'!$C$6:$C$1005,$B13,'Rent log'!$H$6:$H$1005,">="&DATE(Dashboard!$C$4,2,1),'Rent log'!$H$6:$H$1005,"<="&EOMONTH(DATE(Dashboard!$C$4,2,1),0))=0,DATE(Dashboard!$C$4,2,1)>TODAY()),"",SUMIFS('Rent log'!$D$6:$D$1005,'Rent log'!$C$6:$C$1005,$B13,'Rent log'!$H$6:$H$1005,">="&DATE(Dashboard!$C$4,2,1),'Rent log'!$H$6:$H$1005,"<="&EOMONTH(DATE(Dashboard!$C$4,2,1),0)))) | G13: =IF($B13="","",IF(AND(SUMIFS('Rent log'!$D$6:$D$1005,'Rent log'!$C$6:$C$1005,$B13,'Rent log'!$H$6:$H$1005,">="&DATE(Dashboard!$C$4,3,1),'Rent log'!$H$6:$H$1005,"<="&EOMONTH(DATE(Dashboard!$C$4,3,1),0))=0,DATE(Dashboard!$C$4,3,1)>TODAY()),"",SUMIFS('Rent log'!$D$6:$D$1005,'Rent log'!$C$6:$C$1005,$B13,'Rent log'!$H$6:$H$1005,">="&DATE(Dashboard!$C$4,3,1),'Rent log'!$H$6:$H$1005,"<="&EOMONTH(DATE(Dashboard!$C$4,3,1),0)))) | H13: =IF($B13="","",IF(AND(SUMIFS('Rent log'!$D$6:$D$1005,'Rent log'!$C$6:$C$1005,$B13,'Rent log'!$H$6:$H$1005,">="&DATE(Dashboard!$C$4,4,1),'Rent log'!$H$6:$H$1005,"<="&EOMONTH(DATE(Dashboard!$C$4,4,1),0))=0,DATE(Dashboard!$C$4,4,1)>TODAY()),"",SUMIFS('Rent log'!$D$6:$D$1005,'Rent log'!$C$6:$C$1005,$B13,'Rent log'!$H$6:$H$1005,">="&DATE(Dashboard!$C$4,4,1),'Rent log'!$H$6:$H$1005,"<="&EOMONTH(DATE(Dashboard!$C$4,4,1),0)))) | I13: =IF($B13="","",IF(AND(SUMIFS('Rent log'!$D$6:$D$1005,'Rent log'!$C$6:$C$1005,$B13,'Rent log'!$H$6:$H$1005,">="&DATE(Dashboard!$C$4,5,1),'Rent log'!$H$6:$H$1005,"<="&EOMONTH(DATE(Dashboard!$C$4,5,1),0))=0,DATE(Dashboard!$C$4,5,1)>TODAY()),"",SUMIFS('Rent log'!$D$6:$D$1005,'Rent log'!$C$6:$C$1005,$B13,'Rent log'!$H$6:$H$1005,">="&DATE(Dashboard!$C$4,5,1),'Rent log'!$H$6:$H$1005,"<="&EOMONTH(DATE(Dashboard!$C$4,5,1),0)))) | J13: =IF($B13="","",IF(AND(SUMIFS('Rent log'!$D$6:$D$1005,'Rent log'!$C$6:$C$1005,$B13,'Rent log'!$H$6:$H$1005,">="&DATE(Dashboard!$C$4,6,1),'Rent log'!$H$6:$H$1005,"<="&EOMONTH(DATE(Dashboard!$C$4,6,1),0))=0,DATE(Dashboard!$C$4,6,1)>TODAY()),"",SUMIFS('Rent log'!$D$6:$D$1005,'Rent log'!$C$6:$C$1005,$B13,'Rent log'!$H$6:$H$1005,">="&DATE(Dashboard!$C$4,6,1),'Rent log'!$H$6:$H$1005,"<="&EOMONTH(DATE(Dashboard!$C$4,6,1),0)))) | K13: =IF($B13="","",IF(AND(SUMIFS('Rent log'!$D$6:$D$1005,'Rent log'!$C$6:$C$1005,$B13,'Rent log'!$H$6:$H$1005,">="&DATE(Dashboard!$C$4,7,1),'Rent log'!$H$6:$H$1005,"<="&EOMONTH(DATE(Dashboard!$C$4,7,1),0))=0,DATE(Dashboard!$C$4,7,1)>TODAY()),"",SUMIFS('Rent log'!$D$6:$D$1005,'Rent log'!$C$6:$C$1005,$B13,'Rent log'!$H$6:$H$1005,">="&DATE(Dashboard!$C$4,7,1),'Rent log'!$H$6:$H$1005,"<="&EOMONTH(DATE(Dashboard!$C$4,7,1),0)))) | L13: =IF($B13="","",IF(AND(SUMIFS('Rent log'!$D$6:$D$1005,'Rent log'!$C$6:$C$1005,$B13,'Rent log'!$H$6:$H$1005,">="&DATE(Dashboard!$C$4,8,1),'Rent log'!$H$6:$H$1005,"<="&EOMONTH(DATE(Dashboard!$C$4,8,1),0))=0,DATE(Dashboard!$C$4,8,1)>TODAY()),"",SUMIFS('Rent log'!$D$6:$D$1005,'Rent log'!$C$6:$C$1005,$B13,'Rent log'!$H$6:$H$1005,">="&DATE(Dashboard!$C$4,8,1),'Rent log'!$H$6:$H$1005,"<="&EOMONTH(DATE(Dashboard!$C$4,8,1),0)))) | M13: =IF($B13="","",IF(AND(SUMIFS('Rent log'!$D$6:$D$1005,'Rent log'!$C$6:$C$1005,$B13,'Rent log'!$H$6:$H$1005,">="&DATE(Dashboard!$C$4,9,1),'Rent log'!$H$6:$H$1005,"<="&EOMONTH(DATE(Dashboard!$C$4,9,1),0))=0,DATE(Dashboard!$C$4,9,1)>TODAY()),"",SUMIFS('Rent log'!$D$6:$D$1005,'Rent log'!$C$6:$C$1005,$B13,'Rent log'!$H$6:$H$1005,">="&DATE(Dashboard!$C$4,9,1),'Rent log'!$H$6:$H$1005,"<="&EOMONTH(DATE(Dashboard!$C$4,9,1),0)))) | N13: =IF($B13="","",IF(AND(SUMIFS('Rent log'!$D$6:$D$1005,'Rent log'!$C$6:$C$1005,$B13,'Rent log'!$H$6:$H$1005,">="&DATE(Dashboard!$C$4,10,1),'Rent log'!$H$6:$H$1005,"<="&EOMONTH(DATE(Dashboard!$C$4,10,1),0))=0,DATE(Dashboard!$C$4,10,1)>TODAY()),"",SUMIFS('Rent log'!$D$6:$D$1005,'Rent log'!$C$6:$C$1005,$B13,'Rent log'!$H$6:$H$1005,">="&DATE(Dashboard!$C$4,10,1),'Rent log'!$H$6:$H$1005,"<="&EOMONTH(DATE(Dashboard!$C$4,10,1),0)))) | O13: =IF($B13="","",IF(AND(SUMIFS('Rent log'!$D$6:$D$1005,'Rent log'!$C$6:$C$1005,$B13,'Rent log'!$H$6:$H$1005,">="&DATE(Dashboard!$C$4,11,1),'Rent log'!$H$6:$H$1005,"<="&EOMONTH(DATE(Dashboard!$C$4,11,1),0))=0,DATE(Dashboard!$C$4,11,1)>TODAY()),"",SUMIFS('Rent log'!$D$6:$D$1005,'Rent log'!$C$6:$C$1005,$B13,'Rent log'!$H$6:$H$1005,">="&DATE(Dashboard!$C$4,11,1),'Rent log'!$H$6:$H$1005,"<="&EOMONTH(DATE(Dashboard!$C$4,11,1),0)))) | P13: =IF($B13="","",IF(AND(SUMIFS('Rent log'!$D$6:$D$1005,'Rent log'!$C$6:$C$1005,$B13,'Rent log'!$H$6:$H$1005,">="&DATE(Dashboard!$C$4,12,1),'Rent log'!$H$6:$H$1005,"<="&EOMONTH(DATE(Dashboard!$C$4,12,1),0))=0,DATE(Dashboard!$C$4,12,1)>TODAY()),"",SUMIFS('Rent log'!$D$6:$D$1005,'Rent log'!$C$6:$C$1005,$B13,'Rent log'!$H$6:$H$1005,">="&DATE(Dashboard!$C$4,12,1),'Rent log'!$H$6:$H$1005,"<="&EOMONTH(DATE(Dashboard!$C$4,12,1),0)))) | Q13: =IF(B13="","",SUM(E13:P13)) | R13: =IF(B13="","",SUM(AF13:AQ13)) | S13: =IF(B13="","",IF(Dashboard!$C$4<>YEAR(TODAY()),"",IF(INDEX(T13:AE13,MONTH(TODAY()))=0,"No rent due",IF(N(INDEX(E13:P13,MONTH(TODAY())))>=INDEX(T13:AE13,MONTH(TODAY())),"Paid",IF(TODAY()>DATE(YEAR(TODAY()),MONTH(TODAY()),MIN(N(Units!$F13)+(N(Units!$F13)=0),DAY(EOMONTH(TODAY(),0))))+N(Units!$G13),"Late: "&FIXED(INDEX(T13:AE13,MONTH(TODAY()))-N(INDEX(E13:P13,MONTH(TODAY()))),2)&" owed",IF(N(INDEX(E13:P13,MONTH(TODAY())))>0,"Part paid: "&FIXED(INDEX(T13:AE13,MONTH(TODAY()))-N(INDEX(E13:P13,MONTH(TODAY()))),2)&" left","Due on the "&MIN(N(Units!$F13)+(N(Units!$F13)=0),DAY(EOMONTH(TODAY(),0)))&IF(AND(MIN(N(Units!$F13)+(N(Units!$F13)=0),DAY(EOMONTH(TODAY(),0)))>=11,MIN(N(Units!$F13)+(N(Units!$F13)=0),DAY(EOMONTH(TODAY(),0)))<=13),"th",IF(MOD(MIN(N(Units!$F13)+(N(Units!$F13)=0),DAY(EOMONTH(TODAY(),0))),10)=1,"st",IF(MOD(MIN(N(Units!$F13)+(N(Units!$F13)=0),DAY(EOMONTH(TODAY(),0))),10)=2,"nd",IF(MOD(MIN(N(Units!$F13)+(N(Units!$F13)=0),DAY(EOMONTH(TODAY(),0))),10)=3,"rd","th")))))))))) | T13: =IF($B13="",0,IF(AND(OR(Units!$H13="",Units!$H13<=EOMONTH(DATE(Dashboard!$C$4,1,1),0)),OR(Units!$I13="",Units!$I13>=DATE(Dashboard!$C$4,1,1))),N(Units!$E13),0)) | U13: =IF($B13="",0,IF(AND(OR(Units!$H13="",Units!$H13<=EOMONTH(DATE(Dashboard!$C$4,2,1),0)),OR(Units!$I13="",Units!$I13>=DATE(Dashboard!$C$4,2,1))),N(Units!$E13),0)) | V13: =IF($B13="",0,IF(AND(OR(Units!$H13="",Units!$H13<=EOMONTH(DATE(Dashboard!$C$4,3,1),0)),OR(Units!$I13="",Units!$I13>=DATE(Dashboard!$C$4,3,1))),N(Units!$E13),0)) | W13: =IF($B13="",0,IF(AND(OR(Units!$H13="",Units!$H13<=EOMONTH(DATE(Dashboard!$C$4,4,1),0)),OR(Units!$I13="",Units!$I13>=DATE(Dashboard!$C$4,4,1))),N(Units!$E13),0)) | X13: =IF($B13="",0,IF(AND(OR(Units!$H13="",Units!$H13<=EOMONTH(DATE(Dashboard!$C$4,5,1),0)),OR(Units!$I13="",Units!$I13>=DATE(Dashboard!$C$4,5,1))),N(Units!$E13),0)) | Y13: =IF($B13="",0,IF(AND(OR(Units!$H13="",Units!$H13<=EOMONTH(DATE(Dashboard!$C$4,6,1),0)),OR(Units!$I13="",Units!$I13>=DATE(Dashboard!$C$4,6,1))),N(Units!$E13),0)) | Z13: =IF($B13="",0,IF(AND(OR(Units!$H13="",Units!$H13<=EOMONTH(DATE(Dashboard!$C$4,7,1),0)),OR(Units!$I13="",Units!$I13>=DATE(Dashboard!$C$4,7,1))),N(Units!$E13),0)) | AA13: =IF($B13="",0,IF(AND(OR(Units!$H13="",Units!$H13<=EOMONTH(DATE(Dashboard!$C$4,8,1),0)),OR(Units!$I13="",Units!$I13>=DATE(Dashboard!$C$4,8,1))),N(Units!$E13),0)) | AB13: =IF($B13="",0,IF(AND(OR(Units!$H13="",Units!$H13<=EOMONTH(DATE(Dashboard!$C$4,9,1),0)),OR(Units!$I13="",Units!$I13>=DATE(Dashboard!$C$4,9,1))),N(Units!$E13),0)) | AC13: =IF($B13="",0,IF(AND(OR(Units!$H13="",Units!$H13<=EOMONTH(DATE(Dashboard!$C$4,10,1),0)),OR(Units!$I13="",Units!$I13>=DATE(Dashboard!$C$4,10,1))),N(Units!$E13),0)) | AD13: =IF($B13="",0,IF(AND(OR(Units!$H13="",Units!$H13<=EOMONTH(DATE(Dashboard!$C$4,11,1),0)),OR(Units!$I13="",Units!$I13>=DATE(Dashboard!$C$4,11,1))),N(Units!$E13),0)) | AE13: =IF($B13="",0,IF(AND(OR(Units!$H13="",Units!$H13<=EOMONTH(DATE(Dashboard!$C$4,12,1),0)),OR(Units!$I13="",Units!$I13>=DATE(Dashboard!$C$4,12,1))),N(Units!$E13),0)) | AF13: =IF(AND(T13>0,DATE(Dashboard!$C$4,1,MIN(N(Units!$F13)+(N(Units!$F13)=0),DAY(EOMONTH(DATE(Dashboard!$C$4,1,1),0))))+N(Units!$G13)<TODAY()),MAX(0,T13-N(E13)),0) | AG13: =IF(AND(U13>0,DATE(Dashboard!$C$4,2,MIN(N(Units!$F13)+(N(Units!$F13)=0),DAY(EOMONTH(DATE(Dashboard!$C$4,2,1),0))))+N(Units!$G13)<TODAY()),MAX(0,U13-N(F13)),0) | AH13: =IF(AND(V13>0,DATE(Dashboard!$C$4,3,MIN(N(Units!$F13)+(N(Units!$F13)=0),DAY(EOMONTH(DATE(Dashboard!$C$4,3,1),0))))+N(Units!$G13)<TODAY()),MAX(0,V13-N(G13)),0) | AI13: =IF(AND(W13>0,DATE(Dashboard!$C$4,4,MIN(N(Units!$F13)+(N(Units!$F13)=0),DAY(EOMONTH(DATE(Dashboard!$C$4,4,1),0))))+N(Units!$G13)<TODAY()),MAX(0,W13-N(H13)),0) | AJ13: =IF(AND(X13>0,DATE(Dashboard!$C$4,5,MIN(N(Units!$F13)+(N(Units!$F13)=0),DAY(EOMONTH(DATE(Dashboard!$C$4,5,1),0))))+N(Units!$G13)<TODAY()),MAX(0,X13-N(I13)),0) | AK13: =IF(AND(Y13>0,DATE(Dashboard!$C$4,6,MIN(N(Units!$F13)+(N(Units!$F13)=0),DAY(EOMONTH(DATE(Dashboard!$C$4,6,1),0))))+N(Units!$G13)<TODAY()),MAX(0,Y13-N(J13)),0) | AL13: =IF(AND(Z13>0,DATE(Dashboard!$C$4,7,MIN(N(Units!$F13)+(N(Units!$F13)=0),DAY(EOMONTH(DATE(Dashboard!$C$4,7,1),0))))+N(Units!$G13)<TODAY()),MAX(0,Z13-N(K13)),0) | AM13: =IF(AND(AA13>0,DATE(Dashboard!$C$4,8,MIN(N(Units!$F13)+(N(Units!$F13)=0),DAY(EOMONTH(DATE(Dashboard!$C$4,8,1),0))))+N(Units!$G13)<TODAY()),MAX(0,AA13-N(L13)),0) | AN13: =IF(AND(AB13>0,DATE(Dashboard!$C$4,9,MIN(N(Units!$F13)+(N(Units!$F13)=0),DAY(EOMONTH(DATE(Dashboard!$C$4,9,1),0))))+N(Units!$G13)<TODAY()),MAX(0,AB13-N(M13)),0) | AO13: =IF(AND(AC13>0,DATE(Dashboard!$C$4,10,MIN(N(Units!$F13)+(N(Units!$F13)=0),DAY(EOMONTH(DATE(Dashboard!$C$4,10,1),0))))+N(Units!$G13)<TODAY()),MAX(0,AC13-N(N13)),0) | AP13: =IF(AND(AD13>0,DATE(Dashboard!$C$4,11,MIN(N(Units!$F13)+(N(Units!$F13)=0),DAY(EOMONTH(DATE(Dashboard!$C$4,11,1),0))))+N(Units!$G13)<TODAY()),MAX(0,AD13-N(O13)),0) | AQ13: =IF(AND(AE13>0,DATE(Dashboard!$C$4,12,MIN(N(Units!$F13)+(N(Units!$F13)=0),DAY(EOMONTH(DATE(Dashboard!$C$4,12,1),0))))+N(Units!$G13)<TODAY()),MAX(0,AE13-N(P13)),0) | AR13: =IF(B13="","",Units!C13)
B14: =IF(Units!B14="","",Units!B14) | C14: =IF(B14="","",Units!D14) | D14: =IF(B14="","",Units!E14) | E14: =IF($B14="","",IF(AND(SUMIFS('Rent log'!$D$6:$D$1005,'Rent log'!$C$6:$C$1005,$B14,'Rent log'!$H$6:$H$1005,">="&DATE(Dashboard!$C$4,1,1),'Rent log'!$H$6:$H$1005,"<="&EOMONTH(DATE(Dashboard!$C$4,1,1),0))=0,DATE(Dashboard!$C$4,1,1)>TODAY()),"",SUMIFS('Rent log'!$D$6:$D$1005,'Rent log'!$C$6:$C$1005,$B14,'Rent log'!$H$6:$H$1005,">="&DATE(Dashboard!$C$4,1,1),'Rent log'!$H$6:$H$1005,"<="&EOMONTH(DATE(Dashboard!$C$4,1,1),0)))) | F14: =IF($B14="","",IF(AND(SUMIFS('Rent log'!$D$6:$D$1005,'Rent log'!$C$6:$C$1005,$B14,'Rent log'!$H$6:$H$1005,">="&DATE(Dashboard!$C$4,2,1),'Rent log'!$H$6:$H$1005,"<="&EOMONTH(DATE(Dashboard!$C$4,2,1),0))=0,DATE(Dashboard!$C$4,2,1)>TODAY()),"",SUMIFS('Rent log'!$D$6:$D$1005,'Rent log'!$C$6:$C$1005,$B14,'Rent log'!$H$6:$H$1005,">="&DATE(Dashboard!$C$4,2,1),'Rent log'!$H$6:$H$1005,"<="&EOMONTH(DATE(Dashboard!$C$4,2,1),0)))) | G14: =IF($B14="","",IF(AND(SUMIFS('Rent log'!$D$6:$D$1005,'Rent log'!$C$6:$C$1005,$B14,'Rent log'!$H$6:$H$1005,">="&DATE(Dashboard!$C$4,3,1),'Rent log'!$H$6:$H$1005,"<="&EOMONTH(DATE(Dashboard!$C$4,3,1),0))=0,DATE(Dashboard!$C$4,3,1)>TODAY()),"",SUMIFS('Rent log'!$D$6:$D$1005,'Rent log'!$C$6:$C$1005,$B14,'Rent log'!$H$6:$H$1005,">="&DATE(Dashboard!$C$4,3,1),'Rent log'!$H$6:$H$1005,"<="&EOMONTH(DATE(Dashboard!$C$4,3,1),0)))) | H14: =IF($B14="","",IF(AND(SUMIFS('Rent log'!$D$6:$D$1005,'Rent log'!$C$6:$C$1005,$B14,'Rent log'!$H$6:$H$1005,">="&DATE(Dashboard!$C$4,4,1),'Rent log'!$H$6:$H$1005,"<="&EOMONTH(DATE(Dashboard!$C$4,4,1),0))=0,DATE(Dashboard!$C$4,4,1)>TODAY()),"",SUMIFS('Rent log'!$D$6:$D$1005,'Rent log'!$C$6:$C$1005,$B14,'Rent log'!$H$6:$H$1005,">="&DATE(Dashboard!$C$4,4,1),'Rent log'!$H$6:$H$1005,"<="&EOMONTH(DATE(Dashboard!$C$4,4,1),0)))) | I14: =IF($B14="","",IF(AND(SUMIFS('Rent log'!$D$6:$D$1005,'Rent log'!$C$6:$C$1005,$B14,'Rent log'!$H$6:$H$1005,">="&DATE(Dashboard!$C$4,5,1),'Rent log'!$H$6:$H$1005,"<="&EOMONTH(DATE(Dashboard!$C$4,5,1),0))=0,DATE(Dashboard!$C$4,5,1)>TODAY()),"",SUMIFS('Rent log'!$D$6:$D$1005,'Rent log'!$C$6:$C$1005,$B14,'Rent log'!$H$6:$H$1005,">="&DATE(Dashboard!$C$4,5,1),'Rent log'!$H$6:$H$1005,"<="&EOMONTH(DATE(Dashboard!$C$4,5,1),0)))) | J14: =IF($B14="","",IF(AND(SUMIFS('Rent log'!$D$6:$D$1005,'Rent log'!$C$6:$C$1005,$B14,'Rent log'!$H$6:$H$1005,">="&DATE(Dashboard!$C$4,6,1),'Rent log'!$H$6:$H$1005,"<="&EOMONTH(DATE(Dashboard!$C$4,6,1),0))=0,DATE(Dashboard!$C$4,6,1)>TODAY()),"",SUMIFS('Rent log'!$D$6:$D$1005,'Rent log'!$C$6:$C$1005,$B14,'Rent log'!$H$6:$H$1005,">="&DATE(Dashboard!$C$4,6,1),'Rent log'!$H$6:$H$1005,"<="&EOMONTH(DATE(Dashboard!$C$4,6,1),0)))) | K14: =IF($B14="","",IF(AND(SUMIFS('Rent log'!$D$6:$D$1005,'Rent log'!$C$6:$C$1005,$B14,'Rent log'!$H$6:$H$1005,">="&DATE(Dashboard!$C$4,7,1),'Rent log'!$H$6:$H$1005,"<="&EOMONTH(DATE(Dashboard!$C$4,7,1),0))=0,DATE(Dashboard!$C$4,7,1)>TODAY()),"",SUMIFS('Rent log'!$D$6:$D$1005,'Rent log'!$C$6:$C$1005,$B14,'Rent log'!$H$6:$H$1005,">="&DATE(Dashboard!$C$4,7,1),'Rent log'!$H$6:$H$1005,"<="&EOMONTH(DATE(Dashboard!$C$4,7,1),0)))) | L14: =IF($B14="","",IF(AND(SUMIFS('Rent log'!$D$6:$D$1005,'Rent log'!$C$6:$C$1005,$B14,'Rent log'!$H$6:$H$1005,">="&DATE(Dashboard!$C$4,8,1),'Rent log'!$H$6:$H$1005,"<="&EOMONTH(DATE(Dashboard!$C$4,8,1),0))=0,DATE(Dashboard!$C$4,8,1)>TODAY()),"",SUMIFS('Rent log'!$D$6:$D$1005,'Rent log'!$C$6:$C$1005,$B14,'Rent log'!$H$6:$H$1005,">="&DATE(Dashboard!$C$4,8,1),'Rent log'!$H$6:$H$1005,"<="&EOMONTH(DATE(Dashboard!$C$4,8,1),0)))) | M14: =IF($B14="","",IF(AND(SUMIFS('Rent log'!$D$6:$D$1005,'Rent log'!$C$6:$C$1005,$B14,'Rent log'!$H$6:$H$1005,">="&DATE(Dashboard!$C$4,9,1),'Rent log'!$H$6:$H$1005,"<="&EOMONTH(DATE(Dashboard!$C$4,9,1),0))=0,DATE(Dashboard!$C$4,9,1)>TODAY()),"",SUMIFS('Rent log'!$D$6:$D$1005,'Rent log'!$C$6:$C$1005,$B14,'Rent log'!$H$6:$H$1005,">="&DATE(Dashboard!$C$4,9,1),'Rent log'!$H$6:$H$1005,"<="&EOMONTH(DATE(Dashboard!$C$4,9,1),0)))) | N14: =IF($B14="","",IF(AND(SUMIFS('Rent log'!$D$6:$D$1005,'Rent log'!$C$6:$C$1005,$B14,'Rent log'!$H$6:$H$1005,">="&DATE(Dashboard!$C$4,10,1),'Rent log'!$H$6:$H$1005,"<="&EOMONTH(DATE(Dashboard!$C$4,10,1),0))=0,DATE(Dashboard!$C$4,10,1)>TODAY()),"",SUMIFS('Rent log'!$D$6:$D$1005,'Rent log'!$C$6:$C$1005,$B14,'Rent log'!$H$6:$H$1005,">="&DATE(Dashboard!$C$4,10,1),'Rent log'!$H$6:$H$1005,"<="&EOMONTH(DATE(Dashboard!$C$4,10,1),0)))) | O14: =IF($B14="","",IF(AND(SUMIFS('Rent log'!$D$6:$D$1005,'Rent log'!$C$6:$C$1005,$B14,'Rent log'!$H$6:$H$1005,">="&DATE(Dashboard!$C$4,11,1),'Rent log'!$H$6:$H$1005,"<="&EOMONTH(DATE(Dashboard!$C$4,11,1),0))=0,DATE(Dashboard!$C$4,11,1)>TODAY()),"",SUMIFS('Rent log'!$D$6:$D$1005,'Rent log'!$C$6:$C$1005,$B14,'Rent log'!$H$6:$H$1005,">="&DATE(Dashboard!$C$4,11,1),'Rent log'!$H$6:$H$1005,"<="&EOMONTH(DATE(Dashboard!$C$4,11,1),0)))) | P14: =IF($B14="","",IF(AND(SUMIFS('Rent log'!$D$6:$D$1005,'Rent log'!$C$6:$C$1005,$B14,'Rent log'!$H$6:$H$1005,">="&DATE(Dashboard!$C$4,12,1),'Rent log'!$H$6:$H$1005,"<="&EOMONTH(DATE(Dashboard!$C$4,12,1),0))=0,DATE(Dashboard!$C$4,12,1)>TODAY()),"",SUMIFS('Rent log'!$D$6:$D$1005,'Rent log'!$C$6:$C$1005,$B14,'Rent log'!$H$6:$H$1005,">="&DATE(Dashboard!$C$4,12,1),'Rent log'!$H$6:$H$1005,"<="&EOMONTH(DATE(Dashboard!$C$4,12,1),0)))) | Q14: =IF(B14="","",SUM(E14:P14)) | R14: =IF(B14="","",SUM(AF14:AQ14)) | S14: =IF(B14="","",IF(Dashboard!$C$4<>YEAR(TODAY()),"",IF(INDEX(T14:AE14,MONTH(TODAY()))=0,"No rent due",IF(N(INDEX(E14:P14,MONTH(TODAY())))>=INDEX(T14:AE14,MONTH(TODAY())),"Paid",IF(TODAY()>DATE(YEAR(TODAY()),MONTH(TODAY()),MIN(N(Units!$F14)+(N(Units!$F14)=0),DAY(EOMONTH(TODAY(),0))))+N(Units!$G14),"Late: "&FIXED(INDEX(T14:AE14,MONTH(TODAY()))-N(INDEX(E14:P14,MONTH(TODAY()))),2)&" owed",IF(N(INDEX(E14:P14,MONTH(TODAY())))>0,"Part paid: "&FIXED(INDEX(T14:AE14,MONTH(TODAY()))-N(INDEX(E14:P14,MONTH(TODAY()))),2)&" left","Due on the "&MIN(N(Units!$F14)+(N(Units!$F14)=0),DAY(EOMONTH(TODAY(),0)))&IF(AND(MIN(N(Units!$F14)+(N(Units!$F14)=0),DAY(EOMONTH(TODAY(),0)))>=11,MIN(N(Units!$F14)+(N(Units!$F14)=0),DAY(EOMONTH(TODAY(),0)))<=13),"th",IF(MOD(MIN(N(Units!$F14)+(N(Units!$F14)=0),DAY(EOMONTH(TODAY(),0))),10)=1,"st",IF(MOD(MIN(N(Units!$F14)+(N(Units!$F14)=0),DAY(EOMONTH(TODAY(),0))),10)=2,"nd",IF(MOD(MIN(N(Units!$F14)+(N(Units!$F14)=0),DAY(EOMONTH(TODAY(),0))),10)=3,"rd","th")))))))))) | T14: =IF($B14="",0,IF(AND(OR(Units!$H14="",Units!$H14<=EOMONTH(DATE(Dashboard!$C$4,1,1),0)),OR(Units!$I14="",Units!$I14>=DATE(Dashboard!$C$4,1,1))),N(Units!$E14),0)) | U14: =IF($B14="",0,IF(AND(OR(Units!$H14="",Units!$H14<=EOMONTH(DATE(Dashboard!$C$4,2,1),0)),OR(Units!$I14="",Units!$I14>=DATE(Dashboard!$C$4,2,1))),N(Units!$E14),0)) | V14: =IF($B14="",0,IF(AND(OR(Units!$H14="",Units!$H14<=EOMONTH(DATE(Dashboard!$C$4,3,1),0)),OR(Units!$I14="",Units!$I14>=DATE(Dashboard!$C$4,3,1))),N(Units!$E14),0)) | W14: =IF($B14="",0,IF(AND(OR(Units!$H14="",Units!$H14<=EOMONTH(DATE(Dashboard!$C$4,4,1),0)),OR(Units!$I14="",Units!$I14>=DATE(Dashboard!$C$4,4,1))),N(Units!$E14),0)) | X14: =IF($B14="",0,IF(AND(OR(Units!$H14="",Units!$H14<=EOMONTH(DATE(Dashboard!$C$4,5,1),0)),OR(Units!$I14="",Units!$I14>=DATE(Dashboard!$C$4,5,1))),N(Units!$E14),0)) | Y14: =IF($B14="",0,IF(AND(OR(Units!$H14="",Units!$H14<=EOMONTH(DATE(Dashboard!$C$4,6,1),0)),OR(Units!$I14="",Units!$I14>=DATE(Dashboard!$C$4,6,1))),N(Units!$E14),0)) | Z14: =IF($B14="",0,IF(AND(OR(Units!$H14="",Units!$H14<=EOMONTH(DATE(Dashboard!$C$4,7,1),0)),OR(Units!$I14="",Units!$I14>=DATE(Dashboard!$C$4,7,1))),N(Units!$E14),0)) | AA14: =IF($B14="",0,IF(AND(OR(Units!$H14="",Units!$H14<=EOMONTH(DATE(Dashboard!$C$4,8,1),0)),OR(Units!$I14="",Units!$I14>=DATE(Dashboard!$C$4,8,1))),N(Units!$E14),0)) | AB14: =IF($B14="",0,IF(AND(OR(Units!$H14="",Units!$H14<=EOMONTH(DATE(Dashboard!$C$4,9,1),0)),OR(Units!$I14="",Units!$I14>=DATE(Dashboard!$C$4,9,1))),N(Units!$E14),0)) | AC14: =IF($B14="",0,IF(AND(OR(Units!$H14="",Units!$H14<=EOMONTH(DATE(Dashboard!$C$4,10,1),0)),OR(Units!$I14="",Units!$I14>=DATE(Dashboard!$C$4,10,1))),N(Units!$E14),0)) | AD14: =IF($B14="",0,IF(AND(OR(Units!$H14="",Units!$H14<=EOMONTH(DATE(Dashboard!$C$4,11,1),0)),OR(Units!$I14="",Units!$I14>=DATE(Dashboard!$C$4,11,1))),N(Units!$E14),0)) | AE14: =IF($B14="",0,IF(AND(OR(Units!$H14="",Units!$H14<=EOMONTH(DATE(Dashboard!$C$4,12,1),0)),OR(Units!$I14="",Units!$I14>=DATE(Dashboard!$C$4,12,1))),N(Units!$E14),0)) | AF14: =IF(AND(T14>0,DATE(Dashboard!$C$4,1,MIN(N(Units!$F14)+(N(Units!$F14)=0),DAY(EOMONTH(DATE(Dashboard!$C$4,1,1),0))))+N(Units!$G14)<TODAY()),MAX(0,T14-N(E14)),0) | AG14: =IF(AND(U14>0,DATE(Dashboard!$C$4,2,MIN(N(Units!$F14)+(N(Units!$F14)=0),DAY(EOMONTH(DATE(Dashboard!$C$4,2,1),0))))+N(Units!$G14)<TODAY()),MAX(0,U14-N(F14)),0) | AH14: =IF(AND(V14>0,DATE(Dashboard!$C$4,3,MIN(N(Units!$F14)+(N(Units!$F14)=0),DAY(EOMONTH(DATE(Dashboard!$C$4,3,1),0))))+N(Units!$G14)<TODAY()),MAX(0,V14-N(G14)),0) | AI14: =IF(AND(W14>0,DATE(Dashboard!$C$4,4,MIN(N(Units!$F14)+(N(Units!$F14)=0),DAY(EOMONTH(DATE(Dashboard!$C$4,4,1),0))))+N(Units!$G14)<TODAY()),MAX(0,W14-N(H14)),0) | AJ14: =IF(AND(X14>0,DATE(Dashboard!$C$4,5,MIN(N(Units!$F14)+(N(Units!$F14)=0),DAY(EOMONTH(DATE(Dashboard!$C$4,5,1),0))))+N(Units!$G14)<TODAY()),MAX(0,X14-N(I14)),0) | AK14: =IF(AND(Y14>0,DATE(Dashboard!$C$4,6,MIN(N(Units!$F14)+(N(Units!$F14)=0),DAY(EOMONTH(DATE(Dashboard!$C$4,6,1),0))))+N(Units!$G14)<TODAY()),MAX(0,Y14-N(J14)),0) | AL14: =IF(AND(Z14>0,DATE(Dashboard!$C$4,7,MIN(N(Units!$F14)+(N(Units!$F14)=0),DAY(EOMONTH(DATE(Dashboard!$C$4,7,1),0))))+N(Units!$G14)<TODAY()),MAX(0,Z14-N(K14)),0) | AM14: =IF(AND(AA14>0,DATE(Dashboard!$C$4,8,MIN(N(Units!$F14)+(N(Units!$F14)=0),DAY(EOMONTH(DATE(Dashboard!$C$4,8,1),0))))+N(Units!$G14)<TODAY()),MAX(0,AA14-N(L14)),0) | AN14: =IF(AND(AB14>0,DATE(Dashboard!$C$4,9,MIN(N(Units!$F14)+(N(Units!$F14)=0),DAY(EOMONTH(DATE(Dashboard!$C$4,9,1),0))))+N(Units!$G14)<TODAY()),MAX(0,AB14-N(M14)),0) | AO14: =IF(AND(AC14>0,DATE(Dashboard!$C$4,10,MIN(N(Units!$F14)+(N(Units!$F14)=0),DAY(EOMONTH(DATE(Dashboard!$C$4,10,1),0))))+N(Units!$G14)<TODAY()),MAX(0,AC14-N(N14)),0) | AP14: =IF(AND(AD14>0,DATE(Dashboard!$C$4,11,MIN(N(Units!$F14)+(N(Units!$F14)=0),DAY(EOMONTH(DATE(Dashboard!$C$4,11,1),0))))+N(Units!$G14)<TODAY()),MAX(0,AD14-N(O14)),0) | AQ14: =IF(AND(AE14>0,DATE(Dashboard!$C$4,12,MIN(N(Units!$F14)+(N(Units!$F14)=0),DAY(EOMONTH(DATE(Dashboard!$C$4,12,1),0))))+N(Units!$G14)<TODAY()),MAX(0,AE14-N(P14)),0) | AR14: =IF(B14="","",Units!C14)
B15: =IF(Units!B15="","",Units!B15) | C15: =IF(B15="","",Units!D15) | D15: =IF(B15="","",Units!E15) | E15: =IF($B15="","",IF(AND(SUMIFS('Rent log'!$D$6:$D$1005,'Rent log'!$C$6:$C$1005,$B15,'Rent log'!$H$6:$H$1005,">="&DATE(Dashboard!$C$4,1,1),'Rent log'!$H$6:$H$1005,"<="&EOMONTH(DATE(Dashboard!$C$4,1,1),0))=0,DATE(Dashboard!$C$4,1,1)>TODAY()),"",SUMIFS('Rent log'!$D$6:$D$1005,'Rent log'!$C$6:$C$1005,$B15,'Rent log'!$H$6:$H$1005,">="&DATE(Dashboard!$C$4,1,1),'Rent log'!$H$6:$H$1005,"<="&EOMONTH(DATE(Dashboard!$C$4,1,1),0)))) | F15: =IF($B15="","",IF(AND(SUMIFS('Rent log'!$D$6:$D$1005,'Rent log'!$C$6:$C$1005,$B15,'Rent log'!$H$6:$H$1005,">="&DATE(Dashboard!$C$4,2,1),'Rent log'!$H$6:$H$1005,"<="&EOMONTH(DATE(Dashboard!$C$4,2,1),0))=0,DATE(Dashboard!$C$4,2,1)>TODAY()),"",SUMIFS('Rent log'!$D$6:$D$1005,'Rent log'!$C$6:$C$1005,$B15,'Rent log'!$H$6:$H$1005,">="&DATE(Dashboard!$C$4,2,1),'Rent log'!$H$6:$H$1005,"<="&EOMONTH(DATE(Dashboard!$C$4,2,1),0)))) | G15: =IF($B15="","",IF(AND(SUMIFS('Rent log'!$D$6:$D$1005,'Rent log'!$C$6:$C$1005,$B15,'Rent log'!$H$6:$H$1005,">="&DATE(Dashboard!$C$4,3,1),'Rent log'!$H$6:$H$1005,"<="&EOMONTH(DATE(Dashboard!$C$4,3,1),0))=0,DATE(Dashboard!$C$4,3,1)>TODAY()),"",SUMIFS('Rent log'!$D$6:$D$1005,'Rent log'!$C$6:$C$1005,$B15,'Rent log'!$H$6:$H$1005,">="&DATE(Dashboard!$C$4,3,1),'Rent log'!$H$6:$H$1005,"<="&EOMONTH(DATE(Dashboard!$C$4,3,1),0)))) | H15: =IF($B15="","",IF(AND(SUMIFS('Rent log'!$D$6:$D$1005,'Rent log'!$C$6:$C$1005,$B15,'Rent log'!$H$6:$H$1005,">="&DATE(Dashboard!$C$4,4,1),'Rent log'!$H$6:$H$1005,"<="&EOMONTH(DATE(Dashboard!$C$4,4,1),0))=0,DATE(Dashboard!$C$4,4,1)>TODAY()),"",SUMIFS('Rent log'!$D$6:$D$1005,'Rent log'!$C$6:$C$1005,$B15,'Rent log'!$H$6:$H$1005,">="&DATE(Dashboard!$C$4,4,1),'Rent log'!$H$6:$H$1005,"<="&EOMONTH(DATE(Dashboard!$C$4,4,1),0)))) | I15: =IF($B15="","",IF(AND(SUMIFS('Rent log'!$D$6:$D$1005,'Rent log'!$C$6:$C$1005,$B15,'Rent log'!$H$6:$H$1005,">="&DATE(Dashboard!$C$4,5,1),'Rent log'!$H$6:$H$1005,"<="&EOMONTH(DATE(Dashboard!$C$4,5,1),0))=0,DATE(Dashboard!$C$4,5,1)>TODAY()),"",SUMIFS('Rent log'!$D$6:$D$1005,'Rent log'!$C$6:$C$1005,$B15,'Rent log'!$H$6:$H$1005,">="&DATE(Dashboard!$C$4,5,1),'Rent log'!$H$6:$H$1005,"<="&EOMONTH(DATE(Dashboard!$C$4,5,1),0)))) | J15: =IF($B15="","",IF(AND(SUMIFS('Rent log'!$D$6:$D$1005,'Rent log'!$C$6:$C$1005,$B15,'Rent log'!$H$6:$H$1005,">="&DATE(Dashboard!$C$4,6,1),'Rent log'!$H$6:$H$1005,"<="&EOMONTH(DATE(Dashboard!$C$4,6,1),0))=0,DATE(Dashboard!$C$4,6,1)>TODAY()),"",SUMIFS('Rent log'!$D$6:$D$1005,'Rent log'!$C$6:$C$1005,$B15,'Rent log'!$H$6:$H$1005,">="&DATE(Dashboard!$C$4,6,1),'Rent log'!$H$6:$H$1005,"<="&EOMONTH(DATE(Dashboard!$C$4,6,1),0)))) | K15: =IF($B15="","",IF(AND(SUMIFS('Rent log'!$D$6:$D$1005,'Rent log'!$C$6:$C$1005,$B15,'Rent log'!$H$6:$H$1005,">="&DATE(Dashboard!$C$4,7,1),'Rent log'!$H$6:$H$1005,"<="&EOMONTH(DATE(Dashboard!$C$4,7,1),0))=0,DATE(Dashboard!$C$4,7,1)>TODAY()),"",SUMIFS('Rent log'!$D$6:$D$1005,'Rent log'!$C$6:$C$1005,$B15,'Rent log'!$H$6:$H$1005,">="&DATE(Dashboard!$C$4,7,1),'Rent log'!$H$6:$H$1005,"<="&EOMONTH(DATE(Dashboard!$C$4,7,1),0)))) | L15: =IF($B15="","",IF(AND(SUMIFS('Rent log'!$D$6:$D$1005,'Rent log'!$C$6:$C$1005,$B15,'Rent log'!$H$6:$H$1005,">="&DATE(Dashboard!$C$4,8,1),'Rent log'!$H$6:$H$1005,"<="&EOMONTH(DATE(Dashboard!$C$4,8,1),0))=0,DATE(Dashboard!$C$4,8,1)>TODAY()),"",SUMIFS('Rent log'!$D$6:$D$1005,'Rent log'!$C$6:$C$1005,$B15,'Rent log'!$H$6:$H$1005,">="&DATE(Dashboard!$C$4,8,1),'Rent log'!$H$6:$H$1005,"<="&EOMONTH(DATE(Dashboard!$C$4,8,1),0)))) | M15: =IF($B15="","",IF(AND(SUMIFS('Rent log'!$D$6:$D$1005,'Rent log'!$C$6:$C$1005,$B15,'Rent log'!$H$6:$H$1005,">="&DATE(Dashboard!$C$4,9,1),'Rent log'!$H$6:$H$1005,"<="&EOMONTH(DATE(Dashboard!$C$4,9,1),0))=0,DATE(Dashboard!$C$4,9,1)>TODAY()),"",SUMIFS('Rent log'!$D$6:$D$1005,'Rent log'!$C$6:$C$1005,$B15,'Rent log'!$H$6:$H$1005,">="&DATE(Dashboard!$C$4,9,1),'Rent log'!$H$6:$H$1005,"<="&EOMONTH(DATE(Dashboard!$C$4,9,1),0)))) | N15: =IF($B15="","",IF(AND(SUMIFS('Rent log'!$D$6:$D$1005,'Rent log'!$C$6:$C$1005,$B15,'Rent log'!$H$6:$H$1005,">="&DATE(Dashboard!$C$4,10,1),'Rent log'!$H$6:$H$1005,"<="&EOMONTH(DATE(Dashboard!$C$4,10,1),0))=0,DATE(Dashboard!$C$4,10,1)>TODAY()),"",SUMIFS('Rent log'!$D$6:$D$1005,'Rent log'!$C$6:$C$1005,$B15,'Rent log'!$H$6:$H$1005,">="&DATE(Dashboard!$C$4,10,1),'Rent log'!$H$6:$H$1005,"<="&EOMONTH(DATE(Dashboard!$C$4,10,1),0)))) | O15: =IF($B15="","",IF(AND(SUMIFS('Rent log'!$D$6:$D$1005,'Rent log'!$C$6:$C$1005,$B15,'Rent log'!$H$6:$H$1005,">="&DATE(Dashboard!$C$4,11,1),'Rent log'!$H$6:$H$1005,"<="&EOMONTH(DATE(Dashboard!$C$4,11,1),0))=0,DATE(Dashboard!$C$4,11,1)>TODAY()),"",SUMIFS('Rent log'!$D$6:$D$1005,'Rent log'!$C$6:$C$1005,$B15,'Rent log'!$H$6:$H$1005,">="&DATE(Dashboard!$C$4,11,1),'Rent log'!$H$6:$H$1005,"<="&EOMONTH(DATE(Dashboard!$C$4,11,1),0)))) | P15: =IF($B15="","",IF(AND(SUMIFS('Rent log'!$D$6:$D$1005,'Rent log'!$C$6:$C$1005,$B15,'Rent log'!$H$6:$H$1005,">="&DATE(Dashboard!$C$4,12,1),'Rent log'!$H$6:$H$1005,"<="&EOMONTH(DATE(Dashboard!$C$4,12,1),0))=0,DATE(Dashboard!$C$4,12,1)>TODAY()),"",SUMIFS('Rent log'!$D$6:$D$1005,'Rent log'!$C$6:$C$1005,$B15,'Rent log'!$H$6:$H$1005,">="&DATE(Dashboard!$C$4,12,1),'Rent log'!$H$6:$H$1005,"<="&EOMONTH(DATE(Dashboard!$C$4,12,1),0)))) | Q15: =IF(B15="","",SUM(E15:P15)) | R15: =IF(B15="","",SUM(AF15:AQ15)) | S15: =IF(B15="","",IF(Dashboard!$C$4<>YEAR(TODAY()),"",IF(INDEX(T15:AE15,MONTH(TODAY()))=0,"No rent due",IF(N(INDEX(E15:P15,MONTH(TODAY())))>=INDEX(T15:AE15,MONTH(TODAY())),"Paid",IF(TODAY()>DATE(YEAR(TODAY()),MONTH(TODAY()),MIN(N(Units!$F15)+(N(Units!$F15)=0),DAY(EOMONTH(TODAY(),0))))+N(Units!$G15),"Late: "&FIXED(INDEX(T15:AE15,MONTH(TODAY()))-N(INDEX(E15:P15,MONTH(TODAY()))),2)&" owed",IF(N(INDEX(E15:P15,MONTH(TODAY())))>0,"Part paid: "&FIXED(INDEX(T15:AE15,MONTH(TODAY()))-N(INDEX(E15:P15,MONTH(TODAY()))),2)&" left","Due on the "&MIN(N(Units!$F15)+(N(Units!$F15)=0),DAY(EOMONTH(TODAY(),0)))&IF(AND(MIN(N(Units!$F15)+(N(Units!$F15)=0),DAY(EOMONTH(TODAY(),0)))>=11,MIN(N(Units!$F15)+(N(Units!$F15)=0),DAY(EOMONTH(TODAY(),0)))<=13),"th",IF(MOD(MIN(N(Units!$F15)+(N(Units!$F15)=0),DAY(EOMONTH(TODAY(),0))),10)=1,"st",IF(MOD(MIN(N(Units!$F15)+(N(Units!$F15)=0),DAY(EOMONTH(TODAY(),0))),10)=2,"nd",IF(MOD(MIN(N(Units!$F15)+(N(Units!$F15)=0),DAY(EOMONTH(TODAY(),0))),10)=3,"rd","th")))))))))) | T15: =IF($B15="",0,IF(AND(OR(Units!$H15="",Units!$H15<=EOMONTH(DATE(Dashboard!$C$4,1,1),0)),OR(Units!$I15="",Units!$I15>=DATE(Dashboard!$C$4,1,1))),N(Units!$E15),0)) | U15: =IF($B15="",0,IF(AND(OR(Units!$H15="",Units!$H15<=EOMONTH(DATE(Dashboard!$C$4,2,1),0)),OR(Units!$I15="",Units!$I15>=DATE(Dashboard!$C$4,2,1))),N(Units!$E15),0)) | V15: =IF($B15="",0,IF(AND(OR(Units!$H15="",Units!$H15<=EOMONTH(DATE(Dashboard!$C$4,3,1),0)),OR(Units!$I15="",Units!$I15>=DATE(Dashboard!$C$4,3,1))),N(Units!$E15),0)) | W15: =IF($B15="",0,IF(AND(OR(Units!$H15="",Units!$H15<=EOMONTH(DATE(Dashboard!$C$4,4,1),0)),OR(Units!$I15="",Units!$I15>=DATE(Dashboard!$C$4,4,1))),N(Units!$E15),0)) | X15: =IF($B15="",0,IF(AND(OR(Units!$H15="",Units!$H15<=EOMONTH(DATE(Dashboard!$C$4,5,1),0)),OR(Units!$I15="",Units!$I15>=DATE(Dashboard!$C$4,5,1))),N(Units!$E15),0)) | Y15: =IF($B15="",0,IF(AND(OR(Units!$H15="",Units!$H15<=EOMONTH(DATE(Dashboard!$C$4,6,1),0)),OR(Units!$I15="",Units!$I15>=DATE(Dashboard!$C$4,6,1))),N(Units!$E15),0)) | Z15: =IF($B15="",0,IF(AND(OR(Units!$H15="",Units!$H15<=EOMONTH(DATE(Dashboard!$C$4,7,1),0)),OR(Units!$I15="",Units!$I15>=DATE(Dashboard!$C$4,7,1))),N(Units!$E15),0)) | AA15: =IF($B15="",0,IF(AND(OR(Units!$H15="",Units!$H15<=EOMONTH(DATE(Dashboard!$C$4,8,1),0)),OR(Units!$I15="",Units!$I15>=DATE(Dashboard!$C$4,8,1))),N(Units!$E15),0)) | AB15: =IF($B15="",0,IF(AND(OR(Units!$H15="",Units!$H15<=EOMONTH(DATE(Dashboard!$C$4,9,1),0)),OR(Units!$I15="",Units!$I15>=DATE(Dashboard!$C$4,9,1))),N(Units!$E15),0)) | AC15: =IF($B15="",0,IF(AND(OR(Units!$H15="",Units!$H15<=EOMONTH(DATE(Dashboard!$C$4,10,1),0)),OR(Units!$I15="",Units!$I15>=DATE(Dashboard!$C$4,10,1))),N(Units!$E15),0)) | AD15: =IF($B15="",0,IF(AND(OR(Units!$H15="",Units!$H15<=EOMONTH(DATE(Dashboard!$C$4,11,1),0)),OR(Units!$I15="",Units!$I15>=DATE(Dashboard!$C$4,11,1))),N(Units!$E15),0)) | AE15: =IF($B15="",0,IF(AND(OR(Units!$H15="",Units!$H15<=EOMONTH(DATE(Dashboard!$C$4,12,1),0)),OR(Units!$I15="",Units!$I15>=DATE(Dashboard!$C$4,12,1))),N(Units!$E15),0)) | AF15: =IF(AND(T15>0,DATE(Dashboard!$C$4,1,MIN(N(Units!$F15)+(N(Units!$F15)=0),DAY(EOMONTH(DATE(Dashboard!$C$4,1,1),0))))+N(Units!$G15)<TODAY()),MAX(0,T15-N(E15)),0) | AG15: =IF(AND(U15>0,DATE(Dashboard!$C$4,2,MIN(N(Units!$F15)+(N(Units!$F15)=0),DAY(EOMONTH(DATE(Dashboard!$C$4,2,1),0))))+N(Units!$G15)<TODAY()),MAX(0,U15-N(F15)),0) | AH15: =IF(AND(V15>0,DATE(Dashboard!$C$4,3,MIN(N(Units!$F15)+(N(Units!$F15)=0),DAY(EOMONTH(DATE(Dashboard!$C$4,3,1),0))))+N(Units!$G15)<TODAY()),MAX(0,V15-N(G15)),0) | AI15: =IF(AND(W15>0,DATE(Dashboard!$C$4,4,MIN(N(Units!$F15)+(N(Units!$F15)=0),DAY(EOMONTH(DATE(Dashboard!$C$4,4,1),0))))+N(Units!$G15)<TODAY()),MAX(0,W15-N(H15)),0) | AJ15: =IF(AND(X15>0,DATE(Dashboard!$C$4,5,MIN(N(Units!$F15)+(N(Units!$F15)=0),DAY(EOMONTH(DATE(Dashboard!$C$4,5,1),0))))+N(Units!$G15)<TODAY()),MAX(0,X15-N(I15)),0) | AK15: =IF(AND(Y15>0,DATE(Dashboard!$C$4,6,MIN(N(Units!$F15)+(N(Units!$F15)=0),DAY(EOMONTH(DATE(Dashboard!$C$4,6,1),0))))+N(Units!$G15)<TODAY()),MAX(0,Y15-N(J15)),0) | AL15: =IF(AND(Z15>0,DATE(Dashboard!$C$4,7,MIN(N(Units!$F15)+(N(Units!$F15)=0),DAY(EOMONTH(DATE(Dashboard!$C$4,7,1),0))))+N(Units!$G15)<TODAY()),MAX(0,Z15-N(K15)),0) | AM15: =IF(AND(AA15>0,DATE(Dashboard!$C$4,8,MIN(N(Units!$F15)+(N(Units!$F15)=0),DAY(EOMONTH(DATE(Dashboard!$C$4,8,1),0))))+N(Units!$G15)<TODAY()),MAX(0,AA15-N(L15)),0) | AN15: =IF(AND(AB15>0,DATE(Dashboard!$C$4,9,MIN(N(Units!$F15)+(N(Units!$F15)=0),DAY(EOMONTH(DATE(Dashboard!$C$4,9,1),0))))+N(Units!$G15)<TODAY()),MAX(0,AB15-N(M15)),0) | AO15: =IF(AND(AC15>0,DATE(Dashboard!$C$4,10,MIN(N(Units!$F15)+(N(Units!$F15)=0),DAY(EOMONTH(DATE(Dashboard!$C$4,10,1),0))))+N(Units!$G15)<TODAY()),MAX(0,AC15-N(N15)),0) | AP15: =IF(AND(AD15>0,DATE(Dashboard!$C$4,11,MIN(N(Units!$F15)+(N(Units!$F15)=0),DAY(EOMONTH(DATE(Dashboard!$C$4,11,1),0))))+N(Units!$G15)<TODAY()),MAX(0,AD15-N(O15)),0) | AQ15: =IF(AND(AE15>0,DATE(Dashboard!$C$4,12,MIN(N(Units!$F15)+(N(Units!$F15)=0),DAY(EOMONTH(DATE(Dashboard!$C$4,12,1),0))))+N(Units!$G15)<TODAY()),MAX(0,AE15-N(P15)),0) | AR15: =IF(B15="","",Units!C15)
B16: =IF(Units!B16="","",Units!B16) | C16: =IF(B16="","",Units!D16) | D16: =IF(B16="","",Units!E16) | E16: =IF($B16="","",IF(AND(SUMIFS('Rent log'!$D$6:$D$1005,'Rent log'!$C$6:$C$1005,$B16,'Rent log'!$H$6:$H$1005,">="&DATE(Dashboard!$C$4,1,1),'Rent log'!$H$6:$H$1005,"<="&EOMONTH(DATE(Dashboard!$C$4,1,1),0))=0,DATE(Dashboard!$C$4,1,1)>TODAY()),"",SUMIFS('Rent log'!$D$6:$D$1005,'Rent log'!$C$6:$C$1005,$B16,'Rent log'!$H$6:$H$1005,">="&DATE(Dashboard!$C$4,1,1),'Rent log'!$H$6:$H$1005,"<="&EOMONTH(DATE(Dashboard!$C$4,1,1),0)))) | F16: =IF($B16="","",IF(AND(SUMIFS('Rent log'!$D$6:$D$1005,'Rent log'!$C$6:$C$1005,$B16,'Rent log'!$H$6:$H$1005,">="&DATE(Dashboard!$C$4,2,1),'Rent log'!$H$6:$H$1005,"<="&EOMONTH(DATE(Dashboard!$C$4,2,1),0))=0,DATE(Dashboard!$C$4,2,1)>TODAY()),"",SUMIFS('Rent log'!$D$6:$D$1005,'Rent log'!$C$6:$C$1005,$B16,'Rent log'!$H$6:$H$1005,">="&DATE(Dashboard!$C$4,2,1),'Rent log'!$H$6:$H$1005,"<="&EOMONTH(DATE(Dashboard!$C$4,2,1),0)))) | G16: =IF($B16="","",IF(AND(SUMIFS('Rent log'!$D$6:$D$1005,'Rent log'!$C$6:$C$1005,$B16,'Rent log'!$H$6:$H$1005,">="&DATE(Dashboard!$C$4,3,1),'Rent log'!$H$6:$H$1005,"<="&EOMONTH(DATE(Dashboard!$C$4,3,1),0))=0,DATE(Dashboard!$C$4,3,1)>TODAY()),"",SUMIFS('Rent log'!$D$6:$D$1005,'Rent log'!$C$6:$C$1005,$B16,'Rent log'!$H$6:$H$1005,">="&DATE(Dashboard!$C$4,3,1),'Rent log'!$H$6:$H$1005,"<="&EOMONTH(DATE(Dashboard!$C$4,3,1),0)))) | H16: =IF($B16="","",IF(AND(SUMIFS('Rent log'!$D$6:$D$1005,'Rent log'!$C$6:$C$1005,$B16,'Rent log'!$H$6:$H$1005,">="&DATE(Dashboard!$C$4,4,1),'Rent log'!$H$6:$H$1005,"<="&EOMONTH(DATE(Dashboard!$C$4,4,1),0))=0,DATE(Dashboard!$C$4,4,1)>TODAY()),"",SUMIFS('Rent log'!$D$6:$D$1005,'Rent log'!$C$6:$C$1005,$B16,'Rent log'!$H$6:$H$1005,">="&DATE(Dashboard!$C$4,4,1),'Rent log'!$H$6:$H$1005,"<="&EOMONTH(DATE(Dashboard!$C$4,4,1),0)))) | I16: =IF($B16="","",IF(AND(SUMIFS('Rent log'!$D$6:$D$1005,'Rent log'!$C$6:$C$1005,$B16,'Rent log'!$H$6:$H$1005,">="&DATE(Dashboard!$C$4,5,1),'Rent log'!$H$6:$H$1005,"<="&EOMONTH(DATE(Dashboard!$C$4,5,1),0))=0,DATE(Dashboard!$C$4,5,1)>TODAY()),"",SUMIFS('Rent log'!$D$6:$D$1005,'Rent log'!$C$6:$C$1005,$B16,'Rent log'!$H$6:$H$1005,">="&DATE(Dashboard!$C$4,5,1),'Rent log'!$H$6:$H$1005,"<="&EOMONTH(DATE(Dashboard!$C$4,5,1),0)))) | J16: =IF($B16="","",IF(AND(SUMIFS('Rent log'!$D$6:$D$1005,'Rent log'!$C$6:$C$1005,$B16,'Rent log'!$H$6:$H$1005,">="&DATE(Dashboard!$C$4,6,1),'Rent log'!$H$6:$H$1005,"<="&EOMONTH(DATE(Dashboard!$C$4,6,1),0))=0,DATE(Dashboard!$C$4,6,1)>TODAY()),"",SUMIFS('Rent log'!$D$6:$D$1005,'Rent log'!$C$6:$C$1005,$B16,'Rent log'!$H$6:$H$1005,">="&DATE(Dashboard!$C$4,6,1),'Rent log'!$H$6:$H$1005,"<="&EOMONTH(DATE(Dashboard!$C$4,6,1),0)))) | K16: =IF($B16="","",IF(AND(SUMIFS('Rent log'!$D$6:$D$1005,'Rent log'!$C$6:$C$1005,$B16,'Rent log'!$H$6:$H$1005,">="&DATE(Dashboard!$C$4,7,1),'Rent log'!$H$6:$H$1005,"<="&EOMONTH(DATE(Dashboard!$C$4,7,1),0))=0,DATE(Dashboard!$C$4,7,1)>TODAY()),"",SUMIFS('Rent log'!$D$6:$D$1005,'Rent log'!$C$6:$C$1005,$B16,'Rent log'!$H$6:$H$1005,">="&DATE(Dashboard!$C$4,7,1),'Rent log'!$H$6:$H$1005,"<="&EOMONTH(DATE(Dashboard!$C$4,7,1),0)))) | L16: =IF($B16="","",IF(AND(SUMIFS('Rent log'!$D$6:$D$1005,'Rent log'!$C$6:$C$1005,$B16,'Rent log'!$H$6:$H$1005,">="&DATE(Dashboard!$C$4,8,1),'Rent log'!$H$6:$H$1005,"<="&EOMONTH(DATE(Dashboard!$C$4,8,1),0))=0,DATE(Dashboard!$C$4,8,1)>TODAY()),"",SUMIFS('Rent log'!$D$6:$D$1005,'Rent log'!$C$6:$C$1005,$B16,'Rent log'!$H$6:$H$1005,">="&DATE(Dashboard!$C$4,8,1),'Rent log'!$H$6:$H$1005,"<="&EOMONTH(DATE(Dashboard!$C$4,8,1),0)))) | M16: =IF($B16="","",IF(AND(SUMIFS('Rent log'!$D$6:$D$1005,'Rent log'!$C$6:$C$1005,$B16,'Rent log'!$H$6:$H$1005,">="&DATE(Dashboard!$C$4,9,1),'Rent log'!$H$6:$H$1005,"<="&EOMONTH(DATE(Dashboard!$C$4,9,1),0))=0,DATE(Dashboard!$C$4,9,1)>TODAY()),"",SUMIFS('Rent log'!$D$6:$D$1005,'Rent log'!$C$6:$C$1005,$B16,'Rent log'!$H$6:$H$1005,">="&DATE(Dashboard!$C$4,9,1),'Rent log'!$H$6:$H$1005,"<="&EOMONTH(DATE(Dashboard!$C$4,9,1),0)))) | N16: =IF($B16="","",IF(AND(SUMIFS('Rent log'!$D$6:$D$1005,'Rent log'!$C$6:$C$1005,$B16,'Rent log'!$H$6:$H$1005,">="&DATE(Dashboard!$C$4,10,1),'Rent log'!$H$6:$H$1005,"<="&EOMONTH(DATE(Dashboard!$C$4,10,1),0))=0,DATE(Dashboard!$C$4,10,1)>TODAY()),"",SUMIFS('Rent log'!$D$6:$D$1005,'Rent log'!$C$6:$C$1005,$B16,'Rent log'!$H$6:$H$1005,">="&DATE(Dashboard!$C$4,10,1),'Rent log'!$H$6:$H$1005,"<="&EOMONTH(DATE(Dashboard!$C$4,10,1),0)))) | O16: =IF($B16="","",IF(AND(SUMIFS('Rent log'!$D$6:$D$1005,'Rent log'!$C$6:$C$1005,$B16,'Rent log'!$H$6:$H$1005,">="&DATE(Dashboard!$C$4,11,1),'Rent log'!$H$6:$H$1005,"<="&EOMONTH(DATE(Dashboard!$C$4,11,1),0))=0,DATE(Dashboard!$C$4,11,1)>TODAY()),"",SUMIFS('Rent log'!$D$6:$D$1005,'Rent log'!$C$6:$C$1005,$B16,'Rent log'!$H$6:$H$1005,">="&DATE(Dashboard!$C$4,11,1),'Rent log'!$H$6:$H$1005,"<="&EOMONTH(DATE(Dashboard!$C$4,11,1),0)))) | P16: =IF($B16="","",IF(AND(SUMIFS('Rent log'!$D$6:$D$1005,'Rent log'!$C$6:$C$1005,$B16,'Rent log'!$H$6:$H$1005,">="&DATE(Dashboard!$C$4,12,1),'Rent log'!$H$6:$H$1005,"<="&EOMONTH(DATE(Dashboard!$C$4,12,1),0))=0,DATE(Dashboard!$C$4,12,1)>TODAY()),"",SUMIFS('Rent log'!$D$6:$D$1005,'Rent log'!$C$6:$C$1005,$B16,'Rent log'!$H$6:$H$1005,">="&DATE(Dashboard!$C$4,12,1),'Rent log'!$H$6:$H$1005,"<="&EOMONTH(DATE(Dashboard!$C$4,12,1),0)))) | Q16: =IF(B16="","",SUM(E16:P16)) | R16: =IF(B16="","",SUM(AF16:AQ16)) | S16: =IF(B16="","",IF(Dashboard!$C$4<>YEAR(TODAY()),"",IF(INDEX(T16:AE16,MONTH(TODAY()))=0,"No rent due",IF(N(INDEX(E16:P16,MONTH(TODAY())))>=INDEX(T16:AE16,MONTH(TODAY())),"Paid",IF(TODAY()>DATE(YEAR(TODAY()),MONTH(TODAY()),MIN(N(Units!$F16)+(N(Units!$F16)=0),DAY(EOMONTH(TODAY(),0))))+N(Units!$G16),"Late: "&FIXED(INDEX(T16:AE16,MONTH(TODAY()))-N(INDEX(E16:P16,MONTH(TODAY()))),2)&" owed",IF(N(INDEX(E16:P16,MONTH(TODAY())))>0,"Part paid: "&FIXED(INDEX(T16:AE16,MONTH(TODAY()))-N(INDEX(E16:P16,MONTH(TODAY()))),2)&" left","Due on the "&MIN(N(Units!$F16)+(N(Units!$F16)=0),DAY(EOMONTH(TODAY(),0)))&IF(AND(MIN(N(Units!$F16)+(N(Units!$F16)=0),DAY(EOMONTH(TODAY(),0)))>=11,MIN(N(Units!$F16)+(N(Units!$F16)=0),DAY(EOMONTH(TODAY(),0)))<=13),"th",IF(MOD(MIN(N(Units!$F16)+(N(Units!$F16)=0),DAY(EOMONTH(TODAY(),0))),10)=1,"st",IF(MOD(MIN(N(Units!$F16)+(N(Units!$F16)=0),DAY(EOMONTH(TODAY(),0))),10)=2,"nd",IF(MOD(MIN(N(Units!$F16)+(N(Units!$F16)=0),DAY(EOMONTH(TODAY(),0))),10)=3,"rd","th")))))))))) | T16: =IF($B16="",0,IF(AND(OR(Units!$H16="",Units!$H16<=EOMONTH(DATE(Dashboard!$C$4,1,1),0)),OR(Units!$I16="",Units!$I16>=DATE(Dashboard!$C$4,1,1))),N(Units!$E16),0)) | U16: =IF($B16="",0,IF(AND(OR(Units!$H16="",Units!$H16<=EOMONTH(DATE(Dashboard!$C$4,2,1),0)),OR(Units!$I16="",Units!$I16>=DATE(Dashboard!$C$4,2,1))),N(Units!$E16),0)) | V16: =IF($B16="",0,IF(AND(OR(Units!$H16="",Units!$H16<=EOMONTH(DATE(Dashboard!$C$4,3,1),0)),OR(Units!$I16="",Units!$I16>=DATE(Dashboard!$C$4,3,1))),N(Units!$E16),0)) | W16: =IF($B16="",0,IF(AND(OR(Units!$H16="",Units!$H16<=EOMONTH(DATE(Dashboard!$C$4,4,1),0)),OR(Units!$I16="",Units!$I16>=DATE(Dashboard!$C$4,4,1))),N(Units!$E16),0)) | X16: =IF($B16="",0,IF(AND(OR(Units!$H16="",Units!$H16<=EOMONTH(DATE(Dashboard!$C$4,5,1),0)),OR(Units!$I16="",Units!$I16>=DATE(Dashboard!$C$4,5,1))),N(Units!$E16),0)) | Y16: =IF($B16="",0,IF(AND(OR(Units!$H16="",Units!$H16<=EOMONTH(DATE(Dashboard!$C$4,6,1),0)),OR(Units!$I16="",Units!$I16>=DATE(Dashboard!$C$4,6,1))),N(Units!$E16),0)) | Z16: =IF($B16="",0,IF(AND(OR(Units!$H16="",Units!$H16<=EOMONTH(DATE(Dashboard!$C$4,7,1),0)),OR(Units!$I16="",Units!$I16>=DATE(Dashboard!$C$4,7,1))),N(Units!$E16),0)) | AA16: =IF($B16="",0,IF(AND(OR(Units!$H16="",Units!$H16<=EOMONTH(DATE(Dashboard!$C$4,8,1),0)),OR(Units!$I16="",Units!$I16>=DATE(Dashboard!$C$4,8,1))),N(Units!$E16),0)) | AB16: =IF($B16="",0,IF(AND(OR(Units!$H16="",Units!$H16<=EOMONTH(DATE(Dashboard!$C$4,9,1),0)),OR(Units!$I16="",Units!$I16>=DATE(Dashboard!$C$4,9,1))),N(Units!$E16),0)) | AC16: =IF($B16="",0,IF(AND(OR(Units!$H16="",Units!$H16<=EOMONTH(DATE(Dashboard!$C$4,10,1),0)),OR(Units!$I16="",Units!$I16>=DATE(Dashboard!$C$4,10,1))),N(Units!$E16),0)) | AD16: =IF($B16="",0,IF(AND(OR(Units!$H16="",Units!$H16<=EOMONTH(DATE(Dashboard!$C$4,11,1),0)),OR(Units!$I16="",Units!$I16>=DATE(Dashboard!$C$4,11,1))),N(Units!$E16),0)) | AE16: =IF($B16="",0,IF(AND(OR(Units!$H16="",Units!$H16<=EOMONTH(DATE(Dashboard!$C$4,12,1),0)),OR(Units!$I16="",Units!$I16>=DATE(Dashboard!$C$4,12,1))),N(Units!$E16),0)) | AF16: =IF(AND(T16>0,DATE(Dashboard!$C$4,1,MIN(N(Units!$F16)+(N(Units!$F16)=0),DAY(EOMONTH(DATE(Dashboard!$C$4,1,1),0))))+N(Units!$G16)<TODAY()),MAX(0,T16-N(E16)),0) | AG16: =IF(AND(U16>0,DATE(Dashboard!$C$4,2,MIN(N(Units!$F16)+(N(Units!$F16)=0),DAY(EOMONTH(DATE(Dashboard!$C$4,2,1),0))))+N(Units!$G16)<TODAY()),MAX(0,U16-N(F16)),0) | AH16: =IF(AND(V16>0,DATE(Dashboard!$C$4,3,MIN(N(Units!$F16)+(N(Units!$F16)=0),DAY(EOMONTH(DATE(Dashboard!$C$4,3,1),0))))+N(Units!$G16)<TODAY()),MAX(0,V16-N(G16)),0) | AI16: =IF(AND(W16>0,DATE(Dashboard!$C$4,4,MIN(N(Units!$F16)+(N(Units!$F16)=0),DAY(EOMONTH(DATE(Dashboard!$C$4,4,1),0))))+N(Units!$G16)<TODAY()),MAX(0,W16-N(H16)),0) | AJ16: =IF(AND(X16>0,DATE(Dashboard!$C$4,5,MIN(N(Units!$F16)+(N(Units!$F16)=0),DAY(EOMONTH(DATE(Dashboard!$C$4,5,1),0))))+N(Units!$G16)<TODAY()),MAX(0,X16-N(I16)),0) | AK16: =IF(AND(Y16>0,DATE(Dashboard!$C$4,6,MIN(N(Units!$F16)+(N(Units!$F16)=0),DAY(EOMONTH(DATE(Dashboard!$C$4,6,1),0))))+N(Units!$G16)<TODAY()),MAX(0,Y16-N(J16)),0) | AL16: =IF(AND(Z16>0,DATE(Dashboard!$C$4,7,MIN(N(Units!$F16)+(N(Units!$F16)=0),DAY(EOMONTH(DATE(Dashboard!$C$4,7,1),0))))+N(Units!$G16)<TODAY()),MAX(0,Z16-N(K16)),0) | AM16: =IF(AND(AA16>0,DATE(Dashboard!$C$4,8,MIN(N(Units!$F16)+(N(Units!$F16)=0),DAY(EOMONTH(DATE(Dashboard!$C$4,8,1),0))))+N(Units!$G16)<TODAY()),MAX(0,AA16-N(L16)),0) | AN16: =IF(AND(AB16>0,DATE(Dashboard!$C$4,9,MIN(N(Units!$F16)+(N(Units!$F16)=0),DAY(EOMONTH(DATE(Dashboard!$C$4,9,1),0))))+N(Units!$G16)<TODAY()),MAX(0,AB16-N(M16)),0) | AO16: =IF(AND(AC16>0,DATE(Dashboard!$C$4,10,MIN(N(Units!$F16)+(N(Units!$F16)=0),DAY(EOMONTH(DATE(Dashboard!$C$4,10,1),0))))+N(Units!$G16)<TODAY()),MAX(0,AC16-N(N16)),0) | AP16: =IF(AND(AD16>0,DATE(Dashboard!$C$4,11,MIN(N(Units!$F16)+(N(Units!$F16)=0),DAY(EOMONTH(DATE(Dashboard!$C$4,11,1),0))))+N(Units!$G16)<TODAY()),MAX(0,AD16-N(O16)),0) | AQ16: =IF(AND(AE16>0,DATE(Dashboard!$C$4,12,MIN(N(Units!$F16)+(N(Units!$F16)=0),DAY(EOMONTH(DATE(Dashboard!$C$4,12,1),0))))+N(Units!$G16)<TODAY()),MAX(0,AE16-N(P16)),0) | AR16: =IF(B16="","",Units!C16)
B17: =IF(Units!B17="","",Units!B17) | C17: =IF(B17="","",Units!D17) | D17: =IF(B17="","",Units!E17) | E17: =IF($B17="","",IF(AND(SUMIFS('Rent log'!$D$6:$D$1005,'Rent log'!$C$6:$C$1005,$B17,'Rent log'!$H$6:$H$1005,">="&DATE(Dashboard!$C$4,1,1),'Rent log'!$H$6:$H$1005,"<="&EOMONTH(DATE(Dashboard!$C$4,1,1),0))=0,DATE(Dashboard!$C$4,1,1)>TODAY()),"",SUMIFS('Rent log'!$D$6:$D$1005,'Rent log'!$C$6:$C$1005,$B17,'Rent log'!$H$6:$H$1005,">="&DATE(Dashboard!$C$4,1,1),'Rent log'!$H$6:$H$1005,"<="&EOMONTH(DATE(Dashboard!$C$4,1,1),0)))) | F17: =IF($B17="","",IF(AND(SUMIFS('Rent log'!$D$6:$D$1005,'Rent log'!$C$6:$C$1005,$B17,'Rent log'!$H$6:$H$1005,">="&DATE(Dashboard!$C$4,2,1),'Rent log'!$H$6:$H$1005,"<="&EOMONTH(DATE(Dashboard!$C$4,2,1),0))=0,DATE(Dashboard!$C$4,2,1)>TODAY()),"",SUMIFS('Rent log'!$D$6:$D$1005,'Rent log'!$C$6:$C$1005,$B17,'Rent log'!$H$6:$H$1005,">="&DATE(Dashboard!$C$4,2,1),'Rent log'!$H$6:$H$1005,"<="&EOMONTH(DATE(Dashboard!$C$4,2,1),0)))) | G17: =IF($B17="","",IF(AND(SUMIFS('Rent log'!$D$6:$D$1005,'Rent log'!$C$6:$C$1005,$B17,'Rent log'!$H$6:$H$1005,">="&DATE(Dashboard!$C$4,3,1),'Rent log'!$H$6:$H$1005,"<="&EOMONTH(DATE(Dashboard!$C$4,3,1),0))=0,DATE(Dashboard!$C$4,3,1)>TODAY()),"",SUMIFS('Rent log'!$D$6:$D$1005,'Rent log'!$C$6:$C$1005,$B17,'Rent log'!$H$6:$H$1005,">="&DATE(Dashboard!$C$4,3,1),'Rent log'!$H$6:$H$1005,"<="&EOMONTH(DATE(Dashboard!$C$4,3,1),0)))) | H17: =IF($B17="","",IF(AND(SUMIFS('Rent log'!$D$6:$D$1005,'Rent log'!$C$6:$C$1005,$B17,'Rent log'!$H$6:$H$1005,">="&DATE(Dashboard!$C$4,4,1),'Rent log'!$H$6:$H$1005,"<="&EOMONTH(DATE(Dashboard!$C$4,4,1),0))=0,DATE(Dashboard!$C$4,4,1)>TODAY()),"",SUMIFS('Rent log'!$D$6:$D$1005,'Rent log'!$C$6:$C$1005,$B17,'Rent log'!$H$6:$H$1005,">="&DATE(Dashboard!$C$4,4,1),'Rent log'!$H$6:$H$1005,"<="&EOMONTH(DATE(Dashboard!$C$4,4,1),0)))) | I17: =IF($B17="","",IF(AND(SUMIFS('Rent log'!$D$6:$D$1005,'Rent log'!$C$6:$C$1005,$B17,'Rent log'!$H$6:$H$1005,">="&DATE(Dashboard!$C$4,5,1),'Rent log'!$H$6:$H$1005,"<="&EOMONTH(DATE(Dashboard!$C$4,5,1),0))=0,DATE(Dashboard!$C$4,5,1)>TODAY()),"",SUMIFS('Rent log'!$D$6:$D$1005,'Rent log'!$C$6:$C$1005,$B17,'Rent log'!$H$6:$H$1005,">="&DATE(Dashboard!$C$4,5,1),'Rent log'!$H$6:$H$1005,"<="&EOMONTH(DATE(Dashboard!$C$4,5,1),0)))) | J17: =IF($B17="","",IF(AND(SUMIFS('Rent log'!$D$6:$D$1005,'Rent log'!$C$6:$C$1005,$B17,'Rent log'!$H$6:$H$1005,">="&DATE(Dashboard!$C$4,6,1),'Rent log'!$H$6:$H$1005,"<="&EOMONTH(DATE(Dashboard!$C$4,6,1),0))=0,DATE(Dashboard!$C$4,6,1)>TODAY()),"",SUMIFS('Rent log'!$D$6:$D$1005,'Rent log'!$C$6:$C$1005,$B17,'Rent log'!$H$6:$H$1005,">="&DATE(Dashboard!$C$4,6,1),'Rent log'!$H$6:$H$1005,"<="&EOMONTH(DATE(Dashboard!$C$4,6,1),0)))) | K17: =IF($B17="","",IF(AND(SUMIFS('Rent log'!$D$6:$D$1005,'Rent log'!$C$6:$C$1005,$B17,'Rent log'!$H$6:$H$1005,">="&DATE(Dashboard!$C$4,7,1),'Rent log'!$H$6:$H$1005,"<="&EOMONTH(DATE(Dashboard!$C$4,7,1),0))=0,DATE(Dashboard!$C$4,7,1)>TODAY()),"",SUMIFS('Rent log'!$D$6:$D$1005,'Rent log'!$C$6:$C$1005,$B17,'Rent log'!$H$6:$H$1005,">="&DATE(Dashboard!$C$4,7,1),'Rent log'!$H$6:$H$1005,"<="&EOMONTH(DATE(Dashboard!$C$4,7,1),0)))) | L17: =IF($B17="","",IF(AND(SUMIFS('Rent log'!$D$6:$D$1005,'Rent log'!$C$6:$C$1005,$B17,'Rent log'!$H$6:$H$1005,">="&DATE(Dashboard!$C$4,8,1),'Rent log'!$H$6:$H$1005,"<="&EOMONTH(DATE(Dashboard!$C$4,8,1),0))=0,DATE(Dashboard!$C$4,8,1)>TODAY()),"",SUMIFS('Rent log'!$D$6:$D$1005,'Rent log'!$C$6:$C$1005,$B17,'Rent log'!$H$6:$H$1005,">="&DATE(Dashboard!$C$4,8,1),'Rent log'!$H$6:$H$1005,"<="&EOMONTH(DATE(Dashboard!$C$4,8,1),0)))) | M17: =IF($B17="","",IF(AND(SUMIFS('Rent log'!$D$6:$D$1005,'Rent log'!$C$6:$C$1005,$B17,'Rent log'!$H$6:$H$1005,">="&DATE(Dashboard!$C$4,9,1),'Rent log'!$H$6:$H$1005,"<="&EOMONTH(DATE(Dashboard!$C$4,9,1),0))=0,DATE(Dashboard!$C$4,9,1)>TODAY()),"",SUMIFS('Rent log'!$D$6:$D$1005,'Rent log'!$C$6:$C$1005,$B17,'Rent log'!$H$6:$H$1005,">="&DATE(Dashboard!$C$4,9,1),'Rent log'!$H$6:$H$1005,"<="&EOMONTH(DATE(Dashboard!$C$4,9,1),0)))) | N17: =IF($B17="","",IF(AND(SUMIFS('Rent log'!$D$6:$D$1005,'Rent log'!$C$6:$C$1005,$B17,'Rent log'!$H$6:$H$1005,">="&DATE(Dashboard!$C$4,10,1),'Rent log'!$H$6:$H$1005,"<="&EOMONTH(DATE(Dashboard!$C$4,10,1),0))=0,DATE(Dashboard!$C$4,10,1)>TODAY()),"",SUMIFS('Rent log'!$D$6:$D$1005,'Rent log'!$C$6:$C$1005,$B17,'Rent log'!$H$6:$H$1005,">="&DATE(Dashboard!$C$4,10,1),'Rent log'!$H$6:$H$1005,"<="&EOMONTH(DATE(Dashboard!$C$4,10,1),0)))) | O17: =IF($B17="","",IF(AND(SUMIFS('Rent log'!$D$6:$D$1005,'Rent log'!$C$6:$C$1005,$B17,'Rent log'!$H$6:$H$1005,">="&DATE(Dashboard!$C$4,11,1),'Rent log'!$H$6:$H$1005,"<="&EOMONTH(DATE(Dashboard!$C$4,11,1),0))=0,DATE(Dashboard!$C$4,11,1)>TODAY()),"",SUMIFS('Rent log'!$D$6:$D$1005,'Rent log'!$C$6:$C$1005,$B17,'Rent log'!$H$6:$H$1005,">="&DATE(Dashboard!$C$4,11,1),'Rent log'!$H$6:$H$1005,"<="&EOMONTH(DATE(Dashboard!$C$4,11,1),0)))) | P17: =IF($B17="","",IF(AND(SUMIFS('Rent log'!$D$6:$D$1005,'Rent log'!$C$6:$C$1005,$B17,'Rent log'!$H$6:$H$1005,">="&DATE(Dashboard!$C$4,12,1),'Rent log'!$H$6:$H$1005,"<="&EOMONTH(DATE(Dashboard!$C$4,12,1),0))=0,DATE(Dashboard!$C$4,12,1)>TODAY()),"",SUMIFS('Rent log'!$D$6:$D$1005,'Rent log'!$C$6:$C$1005,$B17,'Rent log'!$H$6:$H$1005,">="&DATE(Dashboard!$C$4,12,1),'Rent log'!$H$6:$H$1005,"<="&EOMONTH(DATE(Dashboard!$C$4,12,1),0)))) | Q17: =IF(B17="","",SUM(E17:P17)) | R17: =IF(B17="","",SUM(AF17:AQ17)) | S17: =IF(B17="","",IF(Dashboard!$C$4<>YEAR(TODAY()),"",IF(INDEX(T17:AE17,MONTH(TODAY()))=0,"No rent due",IF(N(INDEX(E17:P17,MONTH(TODAY())))>=INDEX(T17:AE17,MONTH(TODAY())),"Paid",IF(TODAY()>DATE(YEAR(TODAY()),MONTH(TODAY()),MIN(N(Units!$F17)+(N(Units!$F17)=0),DAY(EOMONTH(TODAY(),0))))+N(Units!$G17),"Late: "&FIXED(INDEX(T17:AE17,MONTH(TODAY()))-N(INDEX(E17:P17,MONTH(TODAY()))),2)&" owed",IF(N(INDEX(E17:P17,MONTH(TODAY())))>0,"Part paid: "&FIXED(INDEX(T17:AE17,MONTH(TODAY()))-N(INDEX(E17:P17,MONTH(TODAY()))),2)&" left","Due on the "&MIN(N(Units!$F17)+(N(Units!$F17)=0),DAY(EOMONTH(TODAY(),0)))&IF(AND(MIN(N(Units!$F17)+(N(Units!$F17)=0),DAY(EOMONTH(TODAY(),0)))>=11,MIN(N(Units!$F17)+(N(Units!$F17)=0),DAY(EOMONTH(TODAY(),0)))<=13),"th",IF(MOD(MIN(N(Units!$F17)+(N(Units!$F17)=0),DAY(EOMONTH(TODAY(),0))),10)=1,"st",IF(MOD(MIN(N(Units!$F17)+(N(Units!$F17)=0),DAY(EOMONTH(TODAY(),0))),10)=2,"nd",IF(MOD(MIN(N(Units!$F17)+(N(Units!$F17)=0),DAY(EOMONTH(TODAY(),0))),10)=3,"rd","th")))))))))) | T17: =IF($B17="",0,IF(AND(OR(Units!$H17="",Units!$H17<=EOMONTH(DATE(Dashboard!$C$4,1,1),0)),OR(Units!$I17="",Units!$I17>=DATE(Dashboard!$C$4,1,1))),N(Units!$E17),0)) | U17: =IF($B17="",0,IF(AND(OR(Units!$H17="",Units!$H17<=EOMONTH(DATE(Dashboard!$C$4,2,1),0)),OR(Units!$I17="",Units!$I17>=DATE(Dashboard!$C$4,2,1))),N(Units!$E17),0)) | V17: =IF($B17="",0,IF(AND(OR(Units!$H17="",Units!$H17<=EOMONTH(DATE(Dashboard!$C$4,3,1),0)),OR(Units!$I17="",Units!$I17>=DATE(Dashboard!$C$4,3,1))),N(Units!$E17),0)) | W17: =IF($B17="",0,IF(AND(OR(Units!$H17="",Units!$H17<=EOMONTH(DATE(Dashboard!$C$4,4,1),0)),OR(Units!$I17="",Units!$I17>=DATE(Dashboard!$C$4,4,1))),N(Units!$E17),0)) | X17: =IF($B17="",0,IF(AND(OR(Units!$H17="",Units!$H17<=EOMONTH(DATE(Dashboard!$C$4,5,1),0)),OR(Units!$I17="",Units!$I17>=DATE(Dashboard!$C$4,5,1))),N(Units!$E17),0)) | Y17: =IF($B17="",0,IF(AND(OR(Units!$H17="",Units!$H17<=EOMONTH(DATE(Dashboard!$C$4,6,1),0)),OR(Units!$I17="",Units!$I17>=DATE(Dashboard!$C$4,6,1))),N(Units!$E17),0)) | Z17: =IF($B17="",0,IF(AND(OR(Units!$H17="",Units!$H17<=EOMONTH(DATE(Dashboard!$C$4,7,1),0)),OR(Units!$I17="",Units!$I17>=DATE(Dashboard!$C$4,7,1))),N(Units!$E17),0)) | AA17: =IF($B17="",0,IF(AND(OR(Units!$H17="",Units!$H17<=EOMONTH(DATE(Dashboard!$C$4,8,1),0)),OR(Units!$I17="",Units!$I17>=DATE(Dashboard!$C$4,8,1))),N(Units!$E17),0)) | AB17: =IF($B17="",0,IF(AND(OR(Units!$H17="",Units!$H17<=EOMONTH(DATE(Dashboard!$C$4,9,1),0)),OR(Units!$I17="",Units!$I17>=DATE(Dashboard!$C$4,9,1))),N(Units!$E17),0)) | AC17: =IF($B17="",0,IF(AND(OR(Units!$H17="",Units!$H17<=EOMONTH(DATE(Dashboard!$C$4,10,1),0)),OR(Units!$I17="",Units!$I17>=DATE(Dashboard!$C$4,10,1))),N(Units!$E17),0)) | AD17: =IF($B17="",0,IF(AND(OR(Units!$H17="",Units!$H17<=EOMONTH(DATE(Dashboard!$C$4,11,1),0)),OR(Units!$I17="",Units!$I17>=DATE(Dashboard!$C$4,11,1))),N(Units!$E17),0)) | AE17: =IF($B17="",0,IF(AND(OR(Units!$H17="",Units!$H17<=EOMONTH(DATE(Dashboard!$C$4,12,1),0)),OR(Units!$I17="",Units!$I17>=DATE(Dashboard!$C$4,12,1))),N(Units!$E17),0)) | AF17: =IF(AND(T17>0,DATE(Dashboard!$C$4,1,MIN(N(Units!$F17)+(N(Units!$F17)=0),DAY(EOMONTH(DATE(Dashboard!$C$4,1,1),0))))+N(Units!$G17)<TODAY()),MAX(0,T17-N(E17)),0) | AG17: =IF(AND(U17>0,DATE(Dashboard!$C$4,2,MIN(N(Units!$F17)+(N(Units!$F17)=0),DAY(EOMONTH(DATE(Dashboard!$C$4,2,1),0))))+N(Units!$G17)<TODAY()),MAX(0,U17-N(F17)),0) | AH17: =IF(AND(V17>0,DATE(Dashboard!$C$4,3,MIN(N(Units!$F17)+(N(Units!$F17)=0),DAY(EOMONTH(DATE(Dashboard!$C$4,3,1),0))))+N(Units!$G17)<TODAY()),MAX(0,V17-N(G17)),0) | AI17: =IF(AND(W17>0,DATE(Dashboard!$C$4,4,MIN(N(Units!$F17)+(N(Units!$F17)=0),DAY(EOMONTH(DATE(Dashboard!$C$4,4,1),0))))+N(Units!$G17)<TODAY()),MAX(0,W17-N(H17)),0) | AJ17: =IF(AND(X17>0,DATE(Dashboard!$C$4,5,MIN(N(Units!$F17)+(N(Units!$F17)=0),DAY(EOMONTH(DATE(Dashboard!$C$4,5,1),0))))+N(Units!$G17)<TODAY()),MAX(0,X17-N(I17)),0) | AK17: =IF(AND(Y17>0,DATE(Dashboard!$C$4,6,MIN(N(Units!$F17)+(N(Units!$F17)=0),DAY(EOMONTH(DATE(Dashboard!$C$4,6,1),0))))+N(Units!$G17)<TODAY()),MAX(0,Y17-N(J17)),0) | AL17: =IF(AND(Z17>0,DATE(Dashboard!$C$4,7,MIN(N(Units!$F17)+(N(Units!$F17)=0),DAY(EOMONTH(DATE(Dashboard!$C$4,7,1),0))))+N(Units!$G17)<TODAY()),MAX(0,Z17-N(K17)),0) | AM17: =IF(AND(AA17>0,DATE(Dashboard!$C$4,8,MIN(N(Units!$F17)+(N(Units!$F17)=0),DAY(EOMONTH(DATE(Dashboard!$C$4,8,1),0))))+N(Units!$G17)<TODAY()),MAX(0,AA17-N(L17)),0) | AN17: =IF(AND(AB17>0,DATE(Dashboard!$C$4,9,MIN(N(Units!$F17)+(N(Units!$F17)=0),DAY(EOMONTH(DATE(Dashboard!$C$4,9,1),0))))+N(Units!$G17)<TODAY()),MAX(0,AB17-N(M17)),0) | AO17: =IF(AND(AC17>0,DATE(Dashboard!$C$4,10,MIN(N(Units!$F17)+(N(Units!$F17)=0),DAY(EOMONTH(DATE(Dashboard!$C$4,10,1),0))))+N(Units!$G17)<TODAY()),MAX(0,AC17-N(N17)),0) | AP17: =IF(AND(AD17>0,DATE(Dashboard!$C$4,11,MIN(N(Units!$F17)+(N(Units!$F17)=0),DAY(EOMONTH(DATE(Dashboard!$C$4,11,1),0))))+N(Units!$G17)<TODAY()),MAX(0,AD17-N(O17)),0) | AQ17: =IF(AND(AE17>0,DATE(Dashboard!$C$4,12,MIN(N(Units!$F17)+(N(Units!$F17)=0),DAY(EOMONTH(DATE(Dashboard!$C$4,12,1),0))))+N(Units!$G17)<TODAY()),MAX(0,AE17-N(P17)),0) | AR17: =IF(B17="","",Units!C17)
... B25: =IF(Units!B25="","",Units!B25) | C25: =IF(B25="","",Units!D25) | D25: =IF(B25="","",Units!E25) | E25: =IF($B25="","",IF(AND(SUMIFS('Rent log'!$D$6:$D$1005,'Rent log'!$C$6:$C$1005,$B25,'Rent log'!$H$6:$H$1005,">="&DATE(Dashboard!$C$4,1,1),'Rent log'!$H$6:$H$1005,"<="&EOMONTH(DATE(Dashboard!$C$4,1,1),0))=0,DATE(Dashboard!$C$4,1,1)>TODAY()),"",SUMIFS('Rent log'!$D$6:$D$1005,'Rent log'!$C$6:$C$1005,$B25,'Rent log'!$H$6:$H$1005,">="&DATE(Dashboard!$C$4,1,1),'Rent log'!$H$6:$H$1005,"<="&EOMONTH(DATE(Dashboard!$C$4,1,1),0)))) | F25: =IF($B25="","",IF(AND(SUMIFS('Rent log'!$D$6:$D$1005,'Rent log'!$C$6:$C$1005,$B25,'Rent log'!$H$6:$H$1005,">="&DATE(Dashboard!$C$4,2,1),'Rent log'!$H$6:$H$1005,"<="&EOMONTH(DATE(Dashboard!$C$4,2,1),0))=0,DATE(Dashboard!$C$4,2,1)>TODAY()),"",SUMIFS('Rent log'!$D$6:$D$1005,'Rent log'!$C$6:$C$1005,$B25,'Rent log'!$H$6:$H$1005,">="&DATE(Dashboard!$C$4,2,1),'Rent log'!$H$6:$H$1005,"<="&EOMONTH(DATE(Dashboard!$C$4,2,1),0)))) | G25: =IF($B25="","",IF(AND(SUMIFS('Rent log'!$D$6:$D$1005,'Rent log'!$C$6:$C$1005,$B25,'Rent log'!$H$6:$H$1005,">="&DATE(Dashboard!$C$4,3,1),'Rent log'!$H$6:$H$1005,"<="&EOMONTH(DATE(Dashboard!$C$4,3,1),0))=0,DATE(Dashboard!$C$4,3,1)>TODAY()),"",SUMIFS('Rent log'!$D$6:$D$1005,'Rent log'!$C$6:$C$1005,$B25,'Rent log'!$H$6:$H$1005,">="&DATE(Dashboard!$C$4,3,1),'Rent log'!$H$6:$H$1005,"<="&EOMONTH(DATE(Dashboard!$C$4,3,1),0)))) | H25: =IF($B25="","",IF(AND(SUMIFS('Rent log'!$D$6:$D$1005,'Rent log'!$C$6:$C$1005,$B25,'Rent log'!$H$6:$H$1005,">="&DATE(Dashboard!$C$4,4,1),'Rent log'!$H$6:$H$1005,"<="&EOMONTH(DATE(Dashboard!$C$4,4,1),0))=0,DATE(Dashboard!$C$4,4,1)>TODAY()),"",SUMIFS('Rent log'!$D$6:$D$1005,'Rent log'!$C$6:$C$1005,$B25,'Rent log'!$H$6:$H$1005,">="&DATE(Dashboard!$C$4,4,1),'Rent log'!$H$6:$H$1005,"<="&EOMONTH(DATE(Dashboard!$C$4,4,1),0)))) | I25: =IF($B25="","",IF(AND(SUMIFS('Rent log'!$D$6:$D$1005,'Rent log'!$C$6:$C$1005,$B25,'Rent log'!$H$6:$H$1005,">="&DATE(Dashboard!$C$4,5,1),'Rent log'!$H$6:$H$1005,"<="&EOMONTH(DATE(Dashboard!$C$4,5,1),0))=0,DATE(Dashboard!$C$4,5,1)>TODAY()),"",SUMIFS('Rent log'!$D$6:$D$1005,'Rent log'!$C$6:$C$1005,$B25,'Rent log'!$H$6:$H$1005,">="&DATE(Dashboard!$C$4,5,1),'Rent log'!$H$6:$H$1005,"<="&EOMONTH(DATE(Dashboard!$C$4,5,1),0)))) | J25: =IF($B25="","",IF(AND(SUMIFS('Rent log'!$D$6:$D$1005,'Rent log'!$C$6:$C$1005,$B25,'Rent log'!$H$6:$H$1005,">="&DATE(Dashboard!$C$4,6,1),'Rent log'!$H$6:$H$1005,"<="&EOMONTH(DATE(Dashboard!$C$4,6,1),0))=0,DATE(Dashboard!$C$4,6,1)>TODAY()),"",SUMIFS('Rent log'!$D$6:$D$1005,'Rent log'!$C$6:$C$1005,$B25,'Rent log'!$H$6:$H$1005,">="&DATE(Dashboard!$C$4,6,1),'Rent log'!$H$6:$H$1005,"<="&EOMONTH(DATE(Dashboard!$C$4,6,1),0)))) | K25: =IF($B25="","",IF(AND(SUMIFS('Rent log'!$D$6:$D$1005,'Rent log'!$C$6:$C$1005,$B25,'Rent log'!$H$6:$H$1005,">="&DATE(Dashboard!$C$4,7,1),'Rent log'!$H$6:$H$1005,"<="&EOMONTH(DATE(Dashboard!$C$4,7,1),0))=0,DATE(Dashboard!$C$4,7,1)>TODAY()),"",SUMIFS('Rent log'!$D$6:$D$1005,'Rent log'!$C$6:$C$1005,$B25,'Rent log'!$H$6:$H$1005,">="&DATE(Dashboard!$C$4,7,1),'Rent log'!$H$6:$H$1005,"<="&EOMONTH(DATE(Dashboard!$C$4,7,1),0)))) | L25: =IF($B25="","",IF(AND(SUMIFS('Rent log'!$D$6:$D$1005,'Rent log'!$C$6:$C$1005,$B25,'Rent log'!$H$6:$H$1005,">="&DATE(Dashboard!$C$4,8,1),'Rent log'!$H$6:$H$1005,"<="&EOMONTH(DATE(Dashboard!$C$4,8,1),0))=0,DATE(Dashboard!$C$4,8,1)>TODAY()),"",SUMIFS('Rent log'!$D$6:$D$1005,'Rent log'!$C$6:$C$1005,$B25,'Rent log'!$H$6:$H$1005,">="&DATE(Dashboard!$C$4,8,1),'Rent log'!$H$6:$H$1005,"<="&EOMONTH(DATE(Dashboard!$C$4,8,1),0)))) | M25: =IF($B25="","",IF(AND(SUMIFS('Rent log'!$D$6:$D$1005,'Rent log'!$C$6:$C$1005,$B25,'Rent log'!$H$6:$H$1005,">="&DATE(Dashboard!$C$4,9,1),'Rent log'!$H$6:$H$1005,"<="&EOMONTH(DATE(Dashboard!$C$4,9,1),0))=0,DATE(Dashboard!$C$4,9,1)>TODAY()),"",SUMIFS('Rent log'!$D$6:$D$1005,'Rent log'!$C$6:$C$1005,$B25,'Rent log'!$H$6:$H$1005,">="&DATE(Dashboard!$C$4,9,1),'Rent log'!$H$6:$H$1005,"<="&EOMONTH(DATE(Dashboard!$C$4,9,1),0)))) | N25: =IF($B25="","",IF(AND(SUMIFS('Rent log'!$D$6:$D$1005,'Rent log'!$C$6:$C$1005,$B25,'Rent log'!$H$6:$H$1005,">="&DATE(Dashboard!$C$4,10,1),'Rent log'!$H$6:$H$1005,"<="&EOMONTH(DATE(Dashboard!$C$4,10,1),0))=0,DATE(Dashboard!$C$4,10,1)>TODAY()),"",SUMIFS('Rent log'!$D$6:$D$1005,'Rent log'!$C$6:$C$1005,$B25,'Rent log'!$H$6:$H$1005,">="&DATE(Dashboard!$C$4,10,1),'Rent log'!$H$6:$H$1005,"<="&EOMONTH(DATE(Dashboard!$C$4,10,1),0)))) | O25: =IF($B25="","",IF(AND(SUMIFS('Rent log'!$D$6:$D$1005,'Rent log'!$C$6:$C$1005,$B25,'Rent log'!$H$6:$H$1005,">="&DATE(Dashboard!$C$4,11,1),'Rent log'!$H$6:$H$1005,"<="&EOMONTH(DATE(Dashboard!$C$4,11,1),0))=0,DATE(Dashboard!$C$4,11,1)>TODAY()),"",SUMIFS('Rent log'!$D$6:$D$1005,'Rent log'!$C$6:$C$1005,$B25,'Rent log'!$H$6:$H$1005,">="&DATE(Dashboard!$C$4,11,1),'Rent log'!$H$6:$H$1005,"<="&EOMONTH(DATE(Dashboard!$C$4,11,1),0)))) | P25: =IF($B25="","",IF(AND(SUMIFS('Rent log'!$D$6:$D$1005,'Rent log'!$C$6:$C$1005,$B25,'Rent log'!$H$6:$H$1005,">="&DATE(Dashboard!$C$4,12,1),'Rent log'!$H$6:$H$1005,"<="&EOMONTH(DATE(Dashboard!$C$4,12,1),0))=0,DATE(Dashboard!$C$4,12,1)>TODAY()),"",SUMIFS('Rent log'!$D$6:$D$1005,'Rent log'!$C$6:$C$1005,$B25,'Rent log'!$H$6:$H$1005,">="&DATE(Dashboard!$C$4,12,1),'Rent log'!$H$6:$H$1005,"<="&EOMONTH(DATE(Dashboard!$C$4,12,1),0)))) | Q25: =IF(B25="","",SUM(E25:P25)) | R25: =IF(B25="","",SUM(AF25:AQ25)) | S25: =IF(B25="","",IF(Dashboard!$C$4<>YEAR(TODAY()),"",IF(INDEX(T25:AE25,MONTH(TODAY()))=0,"No rent due",IF(N(INDEX(E25:P25,MONTH(TODAY())))>=INDEX(T25:AE25,MONTH(TODAY())),"Paid",IF(TODAY()>DATE(YEAR(TODAY()),MONTH(TODAY()),MIN(N(Units!$F25)+(N(Units!$F25)=0),DAY(EOMONTH(TODAY(),0))))+N(Units!$G25),"Late: "&FIXED(INDEX(T25:AE25,MONTH(TODAY()))-N(INDEX(E25:P25,MONTH(TODAY()))),2)&" owed",IF(N(INDEX(E25:P25,MONTH(TODAY())))>0,"Part paid: "&FIXED(INDEX(T25:AE25,MONTH(TODAY()))-N(INDEX(E25:P25,MONTH(TODAY()))),2)&" left","Due on the "&MIN(N(Units!$F25)+(N(Units!$F25)=0),DAY(EOMONTH(TODAY(),0)))&IF(AND(MIN(N(Units!$F25)+(N(Units!$F25)=0),DAY(EOMONTH(TODAY(),0)))>=11,MIN(N(Units!$F25)+(N(Units!$F25)=0),DAY(EOMONTH(TODAY(),0)))<=13),"th",IF(MOD(MIN(N(Units!$F25)+(N(Units!$F25)=0),DAY(EOMONTH(TODAY(),0))),10)=1,"st",IF(MOD(MIN(N(Units!$F25)+(N(Units!$F25)=0),DAY(EOMONTH(TODAY(),0))),10)=2,"nd",IF(MOD(MIN(N(Units!$F25)+(N(Units!$F25)=0),DAY(EOMONTH(TODAY(),0))),10)=3,"rd","th")))))))))) | T25: =IF($B25="",0,IF(AND(OR(Units!$H25="",Units!$H25<=EOMONTH(DATE(Dashboard!$C$4,1,1),0)),OR(Units!$I25="",Units!$I25>=DATE(Dashboard!$C$4,1,1))),N(Units!$E25),0)) | U25: =IF($B25="",0,IF(AND(OR(Units!$H25="",Units!$H25<=EOMONTH(DATE(Dashboard!$C$4,2,1),0)),OR(Units!$I25="",Units!$I25>=DATE(Dashboard!$C$4,2,1))),N(Units!$E25),0)) | V25: =IF($B25="",0,IF(AND(OR(Units!$H25="",Units!$H25<=EOMONTH(DATE(Dashboard!$C$4,3,1),0)),OR(Units!$I25="",Units!$I25>=DATE(Dashboard!$C$4,3,1))),N(Units!$E25),0)) | W25: =IF($B25="",0,IF(AND(OR(Units!$H25="",Units!$H25<=EOMONTH(DATE(Dashboard!$C$4,4,1),0)),OR(Units!$I25="",Units!$I25>=DATE(Dashboard!$C$4,4,1))),N(Units!$E25),0)) | X25: =IF($B25="",0,IF(AND(OR(Units!$H25="",Units!$H25<=EOMONTH(DATE(Dashboard!$C$4,5,1),0)),OR(Units!$I25="",Units!$I25>=DATE(Dashboard!$C$4,5,1))),N(Units!$E25),0)) | Y25: =IF($B25="",0,IF(AND(OR(Units!$H25="",Units!$H25<=EOMONTH(DATE(Dashboard!$C$4,6,1),0)),OR(Units!$I25="",Units!$I25>=DATE(Dashboard!$C$4,6,1))),N(Units!$E25),0)) | Z25: =IF($B25="",0,IF(AND(OR(Units!$H25="",Units!$H25<=EOMONTH(DATE(Dashboard!$C$4,7,1),0)),OR(Units!$I25="",Units!$I25>=DATE(Dashboard!$C$4,7,1))),N(Units!$E25),0)) | AA25: =IF($B25="",0,IF(AND(OR(Units!$H25="",Units!$H25<=EOMONTH(DATE(Dashboard!$C$4,8,1),0)),OR(Units!$I25="",Units!$I25>=DATE(Dashboard!$C$4,8,1))),N(Units!$E25),0)) | AB25: =IF($B25="",0,IF(AND(OR(Units!$H25="",Units!$H25<=EOMONTH(DATE(Dashboard!$C$4,9,1),0)),OR(Units!$I25="",Units!$I25>=DATE(Dashboard!$C$4,9,1))),N(Units!$E25),0)) | AC25: =IF($B25="",0,IF(AND(OR(Units!$H25="",Units!$H25<=EOMONTH(DATE(Dashboard!$C$4,10,1),0)),OR(Units!$I25="",Units!$I25>=DATE(Dashboard!$C$4,10,1))),N(Units!$E25),0)) | AD25: =IF($B25="",0,IF(AND(OR(Units!$H25="",Units!$H25<=EOMONTH(DATE(Dashboard!$C$4,11,1),0)),OR(Units!$I25="",Units!$I25>=DATE(Dashboard!$C$4,11,1))),N(Units!$E25),0)) | AE25: =IF($B25="",0,IF(AND(OR(Units!$H25="",Units!$H25<=EOMONTH(DATE(Dashboard!$C$4,12,1),0)),OR(Units!$I25="",Units!$I25>=DATE(Dashboard!$C$4,12,1))),N(Units!$E25),0)) | AF25: =IF(AND(T25>0,DATE(Dashboard!$C$4,1,MIN(N(Units!$F25)+(N(Units!$F25)=0),DAY(EOMONTH(DATE(Dashboard!$C$4,1,1),0))))+N(Units!$G25)<TODAY()),MAX(0,T25-N(E25)),0) | AG25: =IF(AND(U25>0,DATE(Dashboard!$C$4,2,MIN(N(Units!$F25)+(N(Units!$F25)=0),DAY(EOMONTH(DATE(Dashboard!$C$4,2,1),0))))+N(Units!$G25)<TODAY()),MAX(0,U25-N(F25)),0) | AH25: =IF(AND(V25>0,DATE(Dashboard!$C$4,3,MIN(N(Units!$F25)+(N(Units!$F25)=0),DAY(EOMONTH(DATE(Dashboard!$C$4,3,1),0))))+N(Units!$G25)<TODAY()),MAX(0,V25-N(G25)),0) | AI25: =IF(AND(W25>0,DATE(Dashboard!$C$4,4,MIN(N(Units!$F25)+(N(Units!$F25)=0),DAY(EOMONTH(DATE(Dashboard!$C$4,4,1),0))))+N(Units!$G25)<TODAY()),MAX(0,W25-N(H25)),0) | AJ25: =IF(AND(X25>0,DATE(Dashboard!$C$4,5,MIN(N(Units!$F25)+(N(Units!$F25)=0),DAY(EOMONTH(DATE(Dashboard!$C$4,5,1),0))))+N(Units!$G25)<TODAY()),MAX(0,X25-N(I25)),0) | AK25: =IF(AND(Y25>0,DATE(Dashboard!$C$4,6,MIN(N(Units!$F25)+(N(Units!$F25)=0),DAY(EOMONTH(DATE(Dashboard!$C$4,6,1),0))))+N(Units!$G25)<TODAY()),MAX(0,Y25-N(J25)),0) | AL25: =IF(AND(Z25>0,DATE(Dashboard!$C$4,7,MIN(N(Units!$F25)+(N(Units!$F25)=0),DAY(EOMONTH(DATE(Dashboard!$C$4,7,1),0))))+N(Units!$G25)<TODAY()),MAX(0,Z25-N(K25)),0) | AM25: =IF(AND(AA25>0,DATE(Dashboard!$C$4,8,MIN(N(Units!$F25)+(N(Units!$F25)=0),DAY(EOMONTH(DATE(Dashboard!$C$4,8,1),0))))+N(Units!$G25)<TODAY()),MAX(0,AA25-N(L25)),0) | AN25: =IF(AND(AB25>0,DATE(Dashboard!$C$4,9,MIN(N(Units!$F25)+(N(Units!$F25)=0),DAY(EOMONTH(DATE(Dashboard!$C$4,9,1),0))))+N(Units!$G25)<TODAY()),MAX(0,AB25-N(M25)),0) | AO25: =IF(AND(AC25>0,DATE(Dashboard!$C$4,10,MIN(N(Units!$F25)+(N(Units!$F25)=0),DAY(EOMONTH(DATE(Dashboard!$C$4,10,1),0))))+N(Units!$G25)<TODAY()),MAX(0,AC25-N(N25)),0) | AP25: =IF(AND(AD25>0,DATE(Dashboard!$C$4,11,MIN(N(Units!$F25)+(N(Units!$F25)=0),DAY(EOMONTH(DATE(Dashboard!$C$4,11,1),0))))+N(Units!$G25)<TODAY()),MAX(0,AD25-N(O25)),0) | AQ25: =IF(AND(AE25>0,DATE(Dashboard!$C$4,12,MIN(N(Units!$F25)+(N(Units!$F25)=0),DAY(EOMONTH(DATE(Dashboard!$C$4,12,1),0))))+N(Units!$G25)<TODAY()),MAX(0,AE25-N(P25)),0) | AR25: =IF(B25="","",Units!C25)
B27: Colours: | C27: Paid in full | E27: Part paid | G27: Late | I27: No rent due

Sheet Start Here
B2: Start here
B3: Type only in the yellow cells. Everything else is calculated.
B5: 1 | C5: Settings: type the names of your properties. A building with several flats is one property.
B7: 2 | C7: Units: one line per unit, with the tenant, rent, due day, grace days, lease dates and deposit.
B9: 3 | C9: Rent log: one line each time rent arrives. Fill in 'For month' only for rent paid early or late.
B11: 4 | C11: Expenses: one line per cost, with its property and category.
B13: 5 | C13: Rent roll and Dashboard: every month shows paid, part paid or late, with what is owed and your net income.
C16: Rent counts as late once the due day and the grace days have passed.
C18: The example units, payments and expenses show how it works. Delete them and add your own.
C20: Works in Google Sheets and Microsoft Excel, in any currency. It does not give tax advice.
