Workbook

Sheet Dashboard
J1: =MATCH(C5,{"January","February","March","April","May","June","July","August","September","October","November","December"},0)
B2: Money at a glance | J2: =DATE(E5,J1,1)
B3: Pick a month. Everything below updates. | J3: =EOMONTH(J2,0)
B5: Month | C5: September | D5: Year | E5: 2026
B7: Money in | C7: Spent | D7: Bills not paid yet | E7: Left for the month | F7: Safe to spend per day
B8: =SUMIFS(Log!$C$6:$C$1000,Log!$D$6:$D$1000,"Income",Log!$B$6:$B$1000,">="&$J$2,Log!$B$6:$B$1000,"<="&$J$3) | C8: =SUMIFS(Log!$C$6:$C$1000,Log!$D$6:$D$1000,"Expense",Log!$B$6:$B$1000,">="&$J$2,Log!$B$6:$B$1000,"<="&$J$3) | D8: =SUM(Bills!$C$6:$C$30)-SUMIFS(Bills!$C$6:$C$30,Bills!$E$6:$E$30,TRUE) | E8: =B8-C8-D8-Budget!$E$8 | F8: =IF(AND(MONTH(TODAY())=$J$1,YEAR(TODAY())=$E$5),MAX(0,E8)/(J3-TODAY()+1),IF($J$3<TODAY(),"month closed","month not started"))
B10: Savings set aside this month (Budget tab): | E10: =Budget!$E$8
B12: Category | C12: Budget | D12: Spent | E12: Left | F12: Used | H12: Heads-up
B13: =Budget!B6 | C13: =Budget!C6 | D13: =SUMIFS(Log!$C$6:$C$1000,Log!$E$6:$E$1000,B13,Log!$D$6:$D$1000,"Expense",Log!$B$6:$B$1000,">="&$J$2,Log!$B$6:$B$1000,"<="&$J$3) | E13: =C13-D13 | F13: =IF(C13=0,"",REPT("█",MIN(20,ROUND(D13/C13*20,0)))&REPT("░",MAX(0,20-ROUND(D13/C13*20,0)))&" "&TEXT(D13/C13,"0%")) | H13: =COUNTIFS(Bills!$F$6:$F$30,"Due in*")&" bill(s) due in the next 3 days"
B14: =Budget!B7 | C14: =Budget!C7 | D14: =SUMIFS(Log!$C$6:$C$1000,Log!$E$6:$E$1000,B14,Log!$D$6:$D$1000,"Expense",Log!$B$6:$B$1000,">="&$J$2,Log!$B$6:$B$1000,"<="&$J$3) | E14: =C14-D14 | F14: =IF(C14=0,"",REPT("█",MIN(20,ROUND(D14/C14*20,0)))&REPT("░",MAX(0,20-ROUND(D14/C14*20,0)))&" "&TEXT(D14/C14,"0%"))
B15: =Budget!B8 | C15: =Budget!C8 | D15: =SUMIFS(Log!$C$6:$C$1000,Log!$E$6:$E$1000,B15,Log!$D$6:$D$1000,"Expense",Log!$B$6:$B$1000,">="&$J$2,Log!$B$6:$B$1000,"<="&$J$3) | E15: =C15-D15 | F15: =IF(C15=0,"",REPT("█",MIN(20,ROUND(D15/C15*20,0)))&REPT("░",MAX(0,20-ROUND(D15/C15*20,0)))&" "&TEXT(D15/C15,"0%")) | H15: =COUNTIFS(Bills!$F$6:$F$30,"⚠*")&" bill(s) overdue"
B16: =Budget!B9 | C16: =Budget!C9 | D16: =SUMIFS(Log!$C$6:$C$1000,Log!$E$6:$E$1000,B16,Log!$D$6:$D$1000,"Expense",Log!$B$6:$B$1000,">="&$J$2,Log!$B$6:$B$1000,"<="&$J$3) | E16: =C16-D16 | F16: =IF(C16=0,"",REPT("█",MIN(20,ROUND(D16/C16*20,0)))&REPT("░",MAX(0,20-ROUND(D16/C16*20,0)))&" "&TEXT(D16/C16,"0%"))
B17: =Budget!B10 | C17: =Budget!C10 | D17: =SUMIFS(Log!$C$6:$C$1000,Log!$E$6:$E$1000,B17,Log!$D$6:$D$1000,"Expense",Log!$B$6:$B$1000,">="&$J$2,Log!$B$6:$B$1000,"<="&$J$3) | E17: =C17-D17 | F17: =IF(C17=0,"",REPT("█",MIN(20,ROUND(D17/C17*20,0)))&REPT("░",MAX(0,20-ROUND(D17/C17*20,0)))&" "&TEXT(D17/C17,"0%")) | H17: =COUNTIFS('Impulse List'!$E$6:$E$30,"⏳*")&" item(s) cooling off on your Impulse List"
B18: =Budget!B11 | C18: =Budget!C11 | D18: =SUMIFS(Log!$C$6:$C$1000,Log!$E$6:$E$1000,B18,Log!$D$6:$D$1000,"Expense",Log!$B$6:$B$1000,">="&$J$2,Log!$B$6:$B$1000,"<="&$J$3) | E18: =C18-D18 | F18: =IF(C18=0,"",REPT("█",MIN(20,ROUND(D18/C18*20,0)))&REPT("░",MAX(0,20-ROUND(D18/C18*20,0)))&" "&TEXT(D18/C18,"0%"))
B19: =Budget!B12 | C19: =Budget!C12 | D19: =SUMIFS(Log!$C$6:$C$1000,Log!$E$6:$E$1000,B19,Log!$D$6:$D$1000,"Expense",Log!$B$6:$B$1000,">="&$J$2,Log!$B$6:$B$1000,"<="&$J$3) | E19: =C19-D19 | F19: =IF(C19=0,"",REPT("█",MIN(20,ROUND(D19/C19*20,0)))&REPT("░",MAX(0,20-ROUND(D19/C19*20,0)))&" "&TEXT(D19/C19,"0%")) | H19: ="Kept by skipping impulse buys: "&FIXED('Impulse List'!$H$6,2)
B20: =Budget!B13 | C20: =Budget!C13 | D20: =SUMIFS(Log!$C$6:$C$1000,Log!$E$6:$E$1000,B20,Log!$D$6:$D$1000,"Expense",Log!$B$6:$B$1000,">="&$J$2,Log!$B$6:$B$1000,"<="&$J$3) | E20: =C20-D20 | F20: =IF(C20=0,"",REPT("█",MIN(20,ROUND(D20/C20*20,0)))&REPT("░",MAX(0,20-ROUND(D20/C20*20,0)))&" "&TEXT(D20/C20,"0%"))
B21: =Budget!B14 | C21: =Budget!C14 | D21: =SUMIFS(Log!$C$6:$C$1000,Log!$E$6:$E$1000,B21,Log!$D$6:$D$1000,"Expense",Log!$B$6:$B$1000,">="&$J$2,Log!$B$6:$B$1000,"<="&$J$3) | E21: =C21-D21 | F21: =IF(C21=0,"",REPT("█",MIN(20,ROUND(D21/C21*20,0)))&REPT("░",MAX(0,20-ROUND(D21/C21*20,0)))&" "&TEXT(D21/C21,"0%"))

Sheet Start Here
B2: Start here: 3 steps, 5 minutes
B3: Only type in YELLOW cells. Everything else fills itself in.
B5: 1 | C5: Budget tab: type how much you want to spend per category each month.
B7: 2 | C7: Bills tab: list your bills once (amount + day of the month they are due).
B9: 3 | C9: Log tab: every time you spend or get paid, add ONE line: date, amount, category.
B13: ★ | C13: Dashboard: pick the month. The big number is what you can safely spend per day.
B15: ⏳ | C15: Impulse List: want to buy something? Park it here for 48 hours first.
B17: 🎯 | C17: Goals: watch your savings bars fill up.
C21: Tip: the example lines in Log, Bills and Goals are there to show how it works. Delete them and add yours.
C23: Works in Google Sheets (File → Import, or open the file in Drive) and in Microsoft Excel.

Sheet Budget
B2: Monthly budget
B3: How much you plan to spend per category, every month.
B5: Category | C5: Monthly budget
B6: Rent / Housing | C6: 900 | E6: Rename or add categories here: the Log dropdown and the Dashboard follow.
B7: Groceries | C7: 350 | E7: Monthly savings you want to set aside:
B8: Eating out | C8: 120 | E8: 150
B9: Transport | C9: 110
B10: Subscriptions | C10: 45
B11: Health | C11: 60
B12: Fun | C12: 90
B13: Shopping | C13: 80
B14: Other | C14: 60
B15: Total | C15: =SUM(C6:C14)

Sheet Log
B2: Log: one line per money moment
B3: Date · Amount · Type · Category · Note. That's it.
B5: Date | C5: Amount | D5: Type | E5: Category | F5: Note
B6: 46266 | C6: 2100 | D6: Income | F6: Salary
B7: 46266 | C7: 900 | D7: Expense | E7: Rent / Housing | F7: Rent
B8: 46267 | C8: 64.3 | D8: Expense | E8: Groceries | F8: Supermarket
B9: 46268 | C9: 12.5 | D9: Expense | E9: Eating out | F9: Lunch
B10: 46269 | C10: 9.99 | D10: Expense | E10: Subscriptions | F10: Music
B11: 46270 | C11: 38 | D11: Expense | E11: Transport | F11: Monthly pass
B12: 46271 | C12: 23.9 | D12: Expense | E12: Fun | F12: Cinema + snacks
B13: 46273 | C13: 71.2 | D13: Expense | E13: Groceries | F13: Weekly shop
B14: 46274 | C14: 18 | D14: Expense | E14: Eating out | F14: Pizza
B15: 46275 | C15: 45 | D15: Expense | E15: Shopping | F15: Shoes (was on the Impulse List!)
B16: 46277 | C16: 15.49 | D16: Expense | E16: Subscriptions | F16: Streaming
B17: 46278 | C17: 30 | D17: Expense | E17: Health | F17: Pharmacy

Sheet Bills
B2: Bills: list them once
B3: Tick 'Paid' each month. Colours warn you before the due date.
B5: Bill | C5: Amount | D5: Due day | E5: Paid? | F5: Status
B6: Rent | C6: 900 | D6: 1 | E6: TRUE | F6: =IF(B6="","",IF(E6=TRUE,"✓ Paid",IF(D6<DAY(TODAY()),"⚠ OVERDUE",IF(D6-DAY(TODAY())<=3,"Due in "&(D6-DAY(TODAY()))&" day(s)","Due on the "&D6))))
B7: Phone | C7: 19.99 | D7: 29 | E7: FALSE | F7: =IF(B7="","",IF(E7=TRUE,"✓ Paid",IF(D7<DAY(TODAY()),"⚠ OVERDUE",IF(D7-DAY(TODAY())<=3,"Due in "&(D7-DAY(TODAY()))&" day(s)","Due on the "&D7))))
B8: Internet | C8: 29.99 | D8: 15 | E8: TRUE | F8: =IF(B8="","",IF(E8=TRUE,"✓ Paid",IF(D8<DAY(TODAY()),"⚠ OVERDUE",IF(D8-DAY(TODAY())<=3,"Due in "&(D8-DAY(TODAY()))&" day(s)","Due on the "&D8))))
B9: Electricity | C9: 54 | D9: 30 | E9: FALSE | F9: =IF(B9="","",IF(E9=TRUE,"✓ Paid",IF(D9<DAY(TODAY()),"⚠ OVERDUE",IF(D9-DAY(TODAY())<=3,"Due in "&(D9-DAY(TODAY()))&" day(s)","Due on the "&D9))))
B10: Gym | C10: 24.9 | D10: 24 | E10: FALSE | F10: =IF(B10="","",IF(E10=TRUE,"✓ Paid",IF(D10<DAY(TODAY()),"⚠ OVERDUE",IF(D10-DAY(TODAY())<=3,"Due in "&(D10-DAY(TODAY()))&" day(s)","Due on the "&D10))))
B11: Insurance | C11: 32.5 | D11: 5 | E11: TRUE | F11: =IF(B11="","",IF(E11=TRUE,"✓ Paid",IF(D11<DAY(TODAY()),"⚠ OVERDUE",IF(D11-DAY(TODAY())<=3,"Due in "&(D11-DAY(TODAY()))&" day(s)","Due on the "&D11))))
F12: =IF(B12="","",IF(E12=TRUE,"✓ Paid",IF(D12<DAY(TODAY()),"⚠ OVERDUE",IF(D12-DAY(TODAY())<=3,"Due in "&(D12-DAY(TODAY()))&" day(s)","Due on the "&D12))))
F13: =IF(B13="","",IF(E13=TRUE,"✓ Paid",IF(D13<DAY(TODAY()),"⚠ OVERDUE",IF(D13-DAY(TODAY())<=3,"Due in "&(D13-DAY(TODAY()))&" day(s)","Due on the "&D13))))
F14: =IF(B14="","",IF(E14=TRUE,"✓ Paid",IF(D14<DAY(TODAY()),"⚠ OVERDUE",IF(D14-DAY(TODAY())<=3,"Due in "&(D14-DAY(TODAY()))&" day(s)","Due on the "&D14))))
F15: =IF(B15="","",IF(E15=TRUE,"✓ Paid",IF(D15<DAY(TODAY()),"⚠ OVERDUE",IF(D15-DAY(TODAY())<=3,"Due in "&(D15-DAY(TODAY()))&" day(s)","Due on the "&D15))))
F16: =IF(B16="","",IF(E16=TRUE,"✓ Paid",IF(D16<DAY(TODAY()),"⚠ OVERDUE",IF(D16-DAY(TODAY())<=3,"Due in "&(D16-DAY(TODAY()))&" day(s)","Due on the "&D16))))
F17: =IF(B17="","",IF(E17=TRUE,"✓ Paid",IF(D17<DAY(TODAY()),"⚠ OVERDUE",IF(D17-DAY(TODAY())<=3,"Due in "&(D17-DAY(TODAY()))&" day(s)","Due on the "&D17))))
F18: =IF(B18="","",IF(E18=TRUE,"✓ Paid",IF(D18<DAY(TODAY()),"⚠ OVERDUE",IF(D18-DAY(TODAY())<=3,"Due in "&(D18-DAY(TODAY()))&" day(s)","Due on the "&D18))))
F19: =IF(B19="","",IF(E19=TRUE,"✓ Paid",IF(D19<DAY(TODAY()),"⚠ OVERDUE",IF(D19-DAY(TODAY())<=3,"Due in "&(D19-DAY(TODAY()))&" day(s)","Due on the "&D19))))
F20: =IF(B20="","",IF(E20=TRUE,"✓ Paid",IF(D20<DAY(TODAY()),"⚠ OVERDUE",IF(D20-DAY(TODAY())<=3,"Due in "&(D20-DAY(TODAY()))&" day(s)","Due on the "&D20))))
F21: =IF(B21="","",IF(E21=TRUE,"✓ Paid",IF(D21<DAY(TODAY()),"⚠ OVERDUE",IF(D21-DAY(TODAY())<=3,"Due in "&(D21-DAY(TODAY()))&" day(s)","Due on the "&D21))))
F22: =IF(B22="","",IF(E22=TRUE,"✓ Paid",IF(D22<DAY(TODAY()),"⚠ OVERDUE",IF(D22-DAY(TODAY())<=3,"Due in "&(D22-DAY(TODAY()))&" day(s)","Due on the "&D22))))
F23: =IF(B23="","",IF(E23=TRUE,"✓ Paid",IF(D23<DAY(TODAY()),"⚠ OVERDUE",IF(D23-DAY(TODAY())<=3,"Due in "&(D23-DAY(TODAY()))&" day(s)","Due on the "&D23))))
... F30: =IF(B30="","",IF(E30=TRUE,"✓ Paid",IF(D30<DAY(TODAY()),"⚠ OVERDUE",IF(D30-DAY(TODAY())<=3,"Due in "&(D30-DAY(TODAY()))&" day(s)","Due on the "&D30))))

Sheet Impulse List
B2: Impulse List: the 48-hour rule
B3: Want it? Park it here. If you still want it in 48 hours, go ahead.
B5: Item | C5: Price | D5: Added on | E5: Verdict | F5: I decided | H5: Money kept by skipping:
B6: Wireless earbuds | C6: 79 | D6: 46290 | E6: =IF(B6="","",IF(F6<>"",F6,IF(TODAY()-D6>=2,"✓ 48h passed: buy only if you still want it","⏳ Wait "&(2-(TODAY()-D6))&" more day(s)"))) | H6: =SUMIFS(C6:C30,F6:F30,"Skipped")
B7: Standing desk | C7: 249 | D7: 46292 | E7: =IF(B7="","",IF(F7<>"",F7,IF(TODAY()-D7>=2,"✓ 48h passed: buy only if you still want it","⏳ Wait "&(2-(TODAY()-D7))&" more day(s)")))
B8: Shoes | C8: 45 | D8: 46287 | E8: =IF(B8="","",IF(F8<>"",F8,IF(TODAY()-D8>=2,"✓ 48h passed: buy only if you still want it","⏳ Wait "&(2-(TODAY()-D8))&" more day(s)"))) | F8: Bought
B9: Smart watch | C9: 199 | D9: 46284 | E9: =IF(B9="","",IF(F9<>"",F9,IF(TODAY()-D9>=2,"✓ 48h passed: buy only if you still want it","⏳ Wait "&(2-(TODAY()-D9))&" more day(s)"))) | F9: Skipped
B10: Board game | C10: 39 | D10: 46293 | E10: =IF(B10="","",IF(F10<>"",F10,IF(TODAY()-D10>=2,"✓ 48h passed: buy only if you still want it","⏳ Wait "&(2-(TODAY()-D10))&" more day(s)")))
E11: =IF(B11="","",IF(F11<>"",F11,IF(TODAY()-D11>=2,"✓ 48h passed: buy only if you still want it","⏳ Wait "&(2-(TODAY()-D11))&" more day(s)")))
E12: =IF(B12="","",IF(F12<>"",F12,IF(TODAY()-D12>=2,"✓ 48h passed: buy only if you still want it","⏳ Wait "&(2-(TODAY()-D12))&" more day(s)")))
E13: =IF(B13="","",IF(F13<>"",F13,IF(TODAY()-D13>=2,"✓ 48h passed: buy only if you still want it","⏳ Wait "&(2-(TODAY()-D13))&" more day(s)")))
E14: =IF(B14="","",IF(F14<>"",F14,IF(TODAY()-D14>=2,"✓ 48h passed: buy only if you still want it","⏳ Wait "&(2-(TODAY()-D14))&" more day(s)")))
E15: =IF(B15="","",IF(F15<>"",F15,IF(TODAY()-D15>=2,"✓ 48h passed: buy only if you still want it","⏳ Wait "&(2-(TODAY()-D15))&" more day(s)")))
E16: =IF(B16="","",IF(F16<>"",F16,IF(TODAY()-D16>=2,"✓ 48h passed: buy only if you still want it","⏳ Wait "&(2-(TODAY()-D16))&" more day(s)")))
E17: =IF(B17="","",IF(F17<>"",F17,IF(TODAY()-D17>=2,"✓ 48h passed: buy only if you still want it","⏳ Wait "&(2-(TODAY()-D17))&" more day(s)")))
E18: =IF(B18="","",IF(F18<>"",F18,IF(TODAY()-D18>=2,"✓ 48h passed: buy only if you still want it","⏳ Wait "&(2-(TODAY()-D18))&" more day(s)")))
E19: =IF(B19="","",IF(F19<>"",F19,IF(TODAY()-D19>=2,"✓ 48h passed: buy only if you still want it","⏳ Wait "&(2-(TODAY()-D19))&" more day(s)")))
E20: =IF(B20="","",IF(F20<>"",F20,IF(TODAY()-D20>=2,"✓ 48h passed: buy only if you still want it","⏳ Wait "&(2-(TODAY()-D20))&" more day(s)")))
E21: =IF(B21="","",IF(F21<>"",F21,IF(TODAY()-D21>=2,"✓ 48h passed: buy only if you still want it","⏳ Wait "&(2-(TODAY()-D21))&" more day(s)")))
E22: =IF(B22="","",IF(F22<>"",F22,IF(TODAY()-D22>=2,"✓ 48h passed: buy only if you still want it","⏳ Wait "&(2-(TODAY()-D22))&" more day(s)")))
... E30: =IF(B30="","",IF(F30<>"",F30,IF(TODAY()-D30>=2,"✓ 48h passed: buy only if you still want it","⏳ Wait "&(2-(TODAY()-D30))&" more day(s)")))

Sheet Goals
B2: Savings goals
B3: Update 'Saved so far' whenever you put money aside.
B5: Goal | C5: Target | D5: Saved so far | E5: Done | F5: Progress
B6: Emergency fund | C6: 3000 | D6: 1250 | E6: =IF(C6="","",MIN(1,D6/C6)) | F6: =IF(C6="","",REPT("█",ROUND(E6*20,0))&REPT("░",20-ROUND(E6*20,0)))
B7: Trip | C7: 1200 | D7: 400 | E7: =IF(C7="","",MIN(1,D7/C7)) | F7: =IF(C7="","",REPT("█",ROUND(E7*20,0))&REPT("░",20-ROUND(E7*20,0)))
B8: New laptop | C8: 900 | D8: 810 | E8: =IF(C8="","",MIN(1,D8/C8)) | F8: =IF(C8="","",REPT("█",ROUND(E8*20,0))&REPT("░",20-ROUND(E8*20,0)))
E9: =IF(C9="","",MIN(1,D9/C9)) | F9: =IF(C9="","",REPT("█",ROUND(E9*20,0))&REPT("░",20-ROUND(E9*20,0)))
E10: =IF(C10="","",MIN(1,D10/C10)) | F10: =IF(C10="","",REPT("█",ROUND(E10*20,0))&REPT("░",20-ROUND(E10*20,0)))
E11: =IF(C11="","",MIN(1,D11/C11)) | F11: =IF(C11="","",REPT("█",ROUND(E11*20,0))&REPT("░",20-ROUND(E11*20,0)))
E12: =IF(C12="","",MIN(1,D12/C12)) | F12: =IF(C12="","",REPT("█",ROUND(E12*20,0))&REPT("░",20-ROUND(E12*20,0)))
E13: =IF(C13="","",MIN(1,D13/C13)) | F13: =IF(C13="","",REPT("█",ROUND(E13*20,0))&REPT("░",20-ROUND(E13*20,0)))
E14: =IF(C14="","",MIN(1,D14/C14)) | F14: =IF(C14="","",REPT("█",ROUND(E14*20,0))&REPT("░",20-ROUND(E14*20,0)))
E15: =IF(C15="","",MIN(1,D15/C15)) | F15: =IF(C15="","",REPT("█",ROUND(E15*20,0))&REPT("░",20-ROUND(E15*20,0)))
