Workbook

Sheet Tableau de bord
J1: =MATCH(C5,{"Janvier","Février","Mars","Avril","Mai","Juin","Juillet","Août","Septembre","Octobre","Novembre","Décembre"},0)
B2: Vue d'ensemble | J2: =DATE(E5,J1,1)
B3: Choisissez un mois. Tout se met à jour. | J3: =EOMONTH(J2,0)
B5: Mois | C5: Septembre | D5: Année | E5: 2026
B7: Rentrées | C7: Dépensé | D7: Factures à payer | E7: Reste du mois | F7: À dépenser par jour
B8: =SUMIFS(Journal!$C$6:$C$1000,Journal!$D$6:$D$1000,"Revenu",Journal!$B$6:$B$1000,">="&$J$2,Journal!$B$6:$B$1000,"<="&$J$3) | C8: =SUMIFS(Journal!$C$6:$C$1000,Journal!$D$6:$D$1000,"Dépense",Journal!$B$6:$B$1000,">="&$J$2,Journal!$B$6:$B$1000,"<="&$J$3) | D8: =SUM(Factures!$C$6:$C$30)-SUMIFS(Factures!$C$6:$C$30,Factures!$E$6:$E$30,"Oui") | E8: =B8-C8-D8-Budget!$E$8 | F8: =IF(AND(MONTH(TODAY())=$J$1,YEAR(TODAY())=$E$5),MAX(0,E8)/(J3-TODAY()+1),IF($J$3<TODAY(),"mois terminé","mois pas commencé"))
B10: Épargne mise de côté ce mois-ci (onglet Budget) : | E10: =Budget!$E$8
B12: Catégorie | C12: Budget | D12: Dépensé | E12: Reste | F12: Utilisé | H12: À surveiller
B13: =Budget!B6 | C13: =Budget!C6 | D13: =SUMIFS(Journal!$C$6:$C$1000,Journal!$E$6:$E$1000,B13,Journal!$D$6:$D$1000,"Dépense",Journal!$B$6:$B$1000,">="&$J$2,Journal!$B$6:$B$1000,"<="&$J$3) | E13: =C13-D13 | F13: =IF(C13=0,"",REPT("█",MIN(20,ROUND(D13/C13*20,0)))&REPT("░",MAX(0,20-ROUND(D13/C13*20,0)))&" "&TEXT(D13/C13,"0%")) | H13: =IF((COUNTIFS(Factures!$F$6:$F$30,"Dans*")+COUNTIFS(Factures!$F$6:$F$30,"Aujourd'hui"))=0,"Aucune facture à payer dans les 3 jours",IF((COUNTIFS(Factures!$F$6:$F$30,"Dans*")+COUNTIFS(Factures!$F$6:$F$30,"Aujourd'hui"))=1,"1 facture",(COUNTIFS(Factures!$F$6:$F$30,"Dans*")+COUNTIFS(Factures!$F$6:$F$30,"Aujourd'hui"))&" factures")&" à payer dans les 3 jours")
B14: =Budget!B7 | C14: =Budget!C7 | D14: =SUMIFS(Journal!$C$6:$C$1000,Journal!$E$6:$E$1000,B14,Journal!$D$6:$D$1000,"Dépense",Journal!$B$6:$B$1000,">="&$J$2,Journal!$B$6:$B$1000,"<="&$J$3) | E14: =C14-D14 | F14: =IF(C14=0,"",REPT("█",MIN(20,ROUND(D14/C14*20,0)))&REPT("░",MAX(0,20-ROUND(D14/C14*20,0)))&" "&TEXT(D14/C14,"0%"))
B15: =Budget!B8 | C15: =Budget!C8 | D15: =SUMIFS(Journal!$C$6:$C$1000,Journal!$E$6:$E$1000,B15,Journal!$D$6:$D$1000,"Dépense",Journal!$B$6:$B$1000,">="&$J$2,Journal!$B$6:$B$1000,"<="&$J$3) | E15: =C15-D15 | F15: =IF(C15=0,"",REPT("█",MIN(20,ROUND(D15/C15*20,0)))&REPT("░",MAX(0,20-ROUND(D15/C15*20,0)))&" "&TEXT(D15/C15,"0%")) | H15: =IF(COUNTIFS(Factures!$F$6:$F$30,"En retard")=0,"Aucune facture en retard",IF(COUNTIFS(Factures!$F$6:$F$30,"En retard")=1,"1 facture en retard",COUNTIFS(Factures!$F$6:$F$30,"En retard")&" factures en retard"))
B16: =Budget!B9 | C16: =Budget!C9 | D16: =SUMIFS(Journal!$C$6:$C$1000,Journal!$E$6:$E$1000,B16,Journal!$D$6:$D$1000,"Dépense",Journal!$B$6:$B$1000,">="&$J$2,Journal!$B$6:$B$1000,"<="&$J$3) | E16: =C16-D16 | F16: =IF(C16=0,"",REPT("█",MIN(20,ROUND(D16/C16*20,0)))&REPT("░",MAX(0,20-ROUND(D16/C16*20,0)))&" "&TEXT(D16/C16,"0%"))
B17: =Budget!B10 | C17: =Budget!C10 | D17: =SUMIFS(Journal!$C$6:$C$1000,Journal!$E$6:$E$1000,B17,Journal!$D$6:$D$1000,"Dépense",Journal!$B$6:$B$1000,">="&$J$2,Journal!$B$6:$B$1000,"<="&$J$3) | E17: =C17-D17 | F17: =IF(C17=0,"",REPT("█",MIN(20,ROUND(D17/C17*20,0)))&REPT("░",MAX(0,20-ROUND(D17/C17*20,0)))&" "&TEXT(D17/C17,"0%")) | H17: =IF(COUNTIFS(Envies!$E$6:$E$30,"Encore*")=0,"Aucune envie en attente",IF(COUNTIFS(Envies!$E$6:$E$30,"Encore*")=1,"1 envie",COUNTIFS(Envies!$E$6:$E$30,"Encore*")&" envies")&" en attente sur votre liste")
B18: =Budget!B11 | C18: =Budget!C11 | D18: =SUMIFS(Journal!$C$6:$C$1000,Journal!$E$6:$E$1000,B18,Journal!$D$6:$D$1000,"Dépense",Journal!$B$6:$B$1000,">="&$J$2,Journal!$B$6:$B$1000,"<="&$J$3) | E18: =C18-D18 | F18: =IF(C18=0,"",REPT("█",MIN(20,ROUND(D18/C18*20,0)))&REPT("░",MAX(0,20-ROUND(D18/C18*20,0)))&" "&TEXT(D18/C18,"0%"))
B19: =Budget!B12 | C19: =Budget!C12 | D19: =SUMIFS(Journal!$C$6:$C$1000,Journal!$E$6:$E$1000,B19,Journal!$D$6:$D$1000,"Dépense",Journal!$B$6:$B$1000,">="&$J$2,Journal!$B$6:$B$1000,"<="&$J$3) | E19: =C19-D19 | F19: =IF(C19=0,"",REPT("█",MIN(20,ROUND(D19/C19*20,0)))&REPT("░",MAX(0,20-ROUND(D19/C19*20,0)))&" "&TEXT(D19/C19,"0%")) | H19: ="Gardé en renonçant aux achats impulsifs : "&FIXED(Envies!$H$6,2)
B20: =Budget!B13 | C20: =Budget!C13 | D20: =SUMIFS(Journal!$C$6:$C$1000,Journal!$E$6:$E$1000,B20,Journal!$D$6:$D$1000,"Dépense",Journal!$B$6:$B$1000,">="&$J$2,Journal!$B$6:$B$1000,"<="&$J$3) | E20: =C20-D20 | F20: =IF(C20=0,"",REPT("█",MIN(20,ROUND(D20/C20*20,0)))&REPT("░",MAX(0,20-ROUND(D20/C20*20,0)))&" "&TEXT(D20/C20,"0%"))
B21: =Budget!B14 | C21: =Budget!C14 | D21: =SUMIFS(Journal!$C$6:$C$1000,Journal!$E$6:$E$1000,B21,Journal!$D$6:$D$1000,"Dépense",Journal!$B$6:$B$1000,">="&$J$2,Journal!$B$6:$B$1000,"<="&$J$3) | E21: =C21-D21 | F21: =IF(C21=0,"",REPT("█",MIN(20,ROUND(D21/C21*20,0)))&REPT("░",MAX(0,20-ROUND(D21/C21*20,0)))&" "&TEXT(D21/C21,"0%"))

Sheet Commencer ici
B2: Commencer ici
B3: Tapez uniquement dans les cases jaunes. Tout le reste est calculé.
B5: 1 | C5: Onglet Budget : combien vous voulez dépenser par catégorie chaque mois.
B7: 2 | C7: Onglet Factures : listez vos factures une seule fois, avec le montant et le jour d'échéance.
B9: 3 | C9: Onglet Journal : à chaque dépense ou rentrée d'argent, ajoutez une ligne avec la date, le montant et la catégorie.
B13: 4 | C13: Tableau de bord : choisissez le mois. Le grand chiffre indique ce que vous pouvez dépenser par jour jusqu'à la fin du mois.
B15: 5 | C15: Envies : quand vous voulez acheter quelque chose, notez-le ici et attendez 48 heures.
B17: 6 | C17: Objectifs : mettez à jour ce que vous avez épargné et les barres se remplissent.
C21: Les lignes d'exemple du Journal, des Factures et des Objectifs montrent comment ça marche. Supprimez-les et ajoutez les vôtres.
C23: Fonctionne dans Google Sheets (Fichier > Importer, ou ouvrez le fichier depuis Drive) et dans Microsoft Excel.

Sheet Budget
B2: Budget mensuel
B3: Combien vous prévoyez de dépenser par catégorie, chaque mois.
B5: Catégorie | C5: Budget mensuel
B6: Loyer / Logement | C6: 900 | E6: Renommez ou ajoutez des catégories ici : la liste du Journal et le Tableau de bord suivent.
B7: Courses | C7: 350 | E7: Épargne à mettre de côté chaque mois :
B8: Restaurants | C8: 120 | E8: 150
B9: Transports | C9: 110
B10: Abonnements | C10: 45
B11: Santé | C11: 60
B12: Loisirs | C12: 90
B13: Shopping | C13: 80
B14: Autre | C14: 60
B15: Total | C15: =SUM(C6:C14)

Sheet Journal
B2: Journal : une ligne par achat ou rentrée d'argent
B3: Date, montant, type, catégorie, et une note si vous voulez.
B5: Date | C5: Montant | D5: Type | E5: Catégorie | F5: Note
B6: 46266 | C6: 2100 | D6: Revenu | F6: Salaire
B7: 46266 | C7: 900 | D7: Dépense | E7: Loyer / Logement | F7: Loyer
B8: 46267 | C8: 64.3 | D8: Dépense | E8: Courses | F8: Supermarché
B9: 46268 | C9: 12.5 | D9: Dépense | E9: Restaurants | F9: Déjeuner
B10: 46269 | C10: 9.99 | D10: Dépense | E10: Abonnements | F10: Musique
B11: 46270 | C11: 38 | D11: Dépense | E11: Transports | F11: Pass mensuel
B12: 46271 | C12: 23.9 | D12: Dépense | E12: Loisirs | F12: Cinéma + snacks
B13: 46273 | C13: 71.2 | D13: Dépense | E13: Courses | F13: Courses de la semaine
B14: 46274 | C14: 18 | D14: Dépense | E14: Restaurants | F14: Pizza
B15: 46275 | C15: 45 | D15: Dépense | E15: Shopping | F15: Chaussures, passées par la liste Envies
B16: 46277 | C16: 15.49 | D16: Dépense | E16: Abonnements | F16: Streaming
B17: 46278 | C17: 30 | D17: Dépense | E17: Santé | F17: Pharmacie

Sheet Factures
B2: Factures : à lister une seule fois
B3: Chaque mois, choisissez Oui quand une facture est payée. Les couleurs préviennent avant l'échéance.
B5: Facture | C5: Montant | D5: Jour d'échéance | E5: Payée ? | F5: Statut
B6: Loyer | C6: 900 | D6: 1 | E6: Oui | F6: =IF(B6="","",IF(E6="Oui","Payée",IF(D6<DAY(TODAY()),"En retard",IF((D6-DAY(TODAY()))=0,"Aujourd'hui",IF((D6-DAY(TODAY()))<=3,"Dans "&(D6-DAY(TODAY()))&IF((D6-DAY(TODAY()))<=1," jour"," jours"),"Le "&D6)))))
B7: Téléphone | C7: 19.99 | D7: 29 | E7: Non | F7: =IF(B7="","",IF(E7="Oui","Payée",IF(D7<DAY(TODAY()),"En retard",IF((D7-DAY(TODAY()))=0,"Aujourd'hui",IF((D7-DAY(TODAY()))<=3,"Dans "&(D7-DAY(TODAY()))&IF((D7-DAY(TODAY()))<=1," jour"," jours"),"Le "&D7)))))
B8: Internet | C8: 29.99 | D8: 15 | E8: Oui | F8: =IF(B8="","",IF(E8="Oui","Payée",IF(D8<DAY(TODAY()),"En retard",IF((D8-DAY(TODAY()))=0,"Aujourd'hui",IF((D8-DAY(TODAY()))<=3,"Dans "&(D8-DAY(TODAY()))&IF((D8-DAY(TODAY()))<=1," jour"," jours"),"Le "&D8)))))
B9: Électricité | C9: 54 | D9: 30 | E9: Non | F9: =IF(B9="","",IF(E9="Oui","Payée",IF(D9<DAY(TODAY()),"En retard",IF((D9-DAY(TODAY()))=0,"Aujourd'hui",IF((D9-DAY(TODAY()))<=3,"Dans "&(D9-DAY(TODAY()))&IF((D9-DAY(TODAY()))<=1," jour"," jours"),"Le "&D9)))))
B10: Salle de sport | C10: 24.9 | D10: 24 | E10: Non | F10: =IF(B10="","",IF(E10="Oui","Payée",IF(D10<DAY(TODAY()),"En retard",IF((D10-DAY(TODAY()))=0,"Aujourd'hui",IF((D10-DAY(TODAY()))<=3,"Dans "&(D10-DAY(TODAY()))&IF((D10-DAY(TODAY()))<=1," jour"," jours"),"Le "&D10)))))
B11: Assurance | C11: 32.5 | D11: 5 | E11: Oui | F11: =IF(B11="","",IF(E11="Oui","Payée",IF(D11<DAY(TODAY()),"En retard",IF((D11-DAY(TODAY()))=0,"Aujourd'hui",IF((D11-DAY(TODAY()))<=3,"Dans "&(D11-DAY(TODAY()))&IF((D11-DAY(TODAY()))<=1," jour"," jours"),"Le "&D11)))))
F12: =IF(B12="","",IF(E12="Oui","Payée",IF(D12<DAY(TODAY()),"En retard",IF((D12-DAY(TODAY()))=0,"Aujourd'hui",IF((D12-DAY(TODAY()))<=3,"Dans "&(D12-DAY(TODAY()))&IF((D12-DAY(TODAY()))<=1," jour"," jours"),"Le "&D12)))))
F13: =IF(B13="","",IF(E13="Oui","Payée",IF(D13<DAY(TODAY()),"En retard",IF((D13-DAY(TODAY()))=0,"Aujourd'hui",IF((D13-DAY(TODAY()))<=3,"Dans "&(D13-DAY(TODAY()))&IF((D13-DAY(TODAY()))<=1," jour"," jours"),"Le "&D13)))))
F14: =IF(B14="","",IF(E14="Oui","Payée",IF(D14<DAY(TODAY()),"En retard",IF((D14-DAY(TODAY()))=0,"Aujourd'hui",IF((D14-DAY(TODAY()))<=3,"Dans "&(D14-DAY(TODAY()))&IF((D14-DAY(TODAY()))<=1," jour"," jours"),"Le "&D14)))))
F15: =IF(B15="","",IF(E15="Oui","Payée",IF(D15<DAY(TODAY()),"En retard",IF((D15-DAY(TODAY()))=0,"Aujourd'hui",IF((D15-DAY(TODAY()))<=3,"Dans "&(D15-DAY(TODAY()))&IF((D15-DAY(TODAY()))<=1," jour"," jours"),"Le "&D15)))))
F16: =IF(B16="","",IF(E16="Oui","Payée",IF(D16<DAY(TODAY()),"En retard",IF((D16-DAY(TODAY()))=0,"Aujourd'hui",IF((D16-DAY(TODAY()))<=3,"Dans "&(D16-DAY(TODAY()))&IF((D16-DAY(TODAY()))<=1," jour"," jours"),"Le "&D16)))))
F17: =IF(B17="","",IF(E17="Oui","Payée",IF(D17<DAY(TODAY()),"En retard",IF((D17-DAY(TODAY()))=0,"Aujourd'hui",IF((D17-DAY(TODAY()))<=3,"Dans "&(D17-DAY(TODAY()))&IF((D17-DAY(TODAY()))<=1," jour"," jours"),"Le "&D17)))))
F18: =IF(B18="","",IF(E18="Oui","Payée",IF(D18<DAY(TODAY()),"En retard",IF((D18-DAY(TODAY()))=0,"Aujourd'hui",IF((D18-DAY(TODAY()))<=3,"Dans "&(D18-DAY(TODAY()))&IF((D18-DAY(TODAY()))<=1," jour"," jours"),"Le "&D18)))))
F19: =IF(B19="","",IF(E19="Oui","Payée",IF(D19<DAY(TODAY()),"En retard",IF((D19-DAY(TODAY()))=0,"Aujourd'hui",IF((D19-DAY(TODAY()))<=3,"Dans "&(D19-DAY(TODAY()))&IF((D19-DAY(TODAY()))<=1," jour"," jours"),"Le "&D19)))))
F20: =IF(B20="","",IF(E20="Oui","Payée",IF(D20<DAY(TODAY()),"En retard",IF((D20-DAY(TODAY()))=0,"Aujourd'hui",IF((D20-DAY(TODAY()))<=3,"Dans "&(D20-DAY(TODAY()))&IF((D20-DAY(TODAY()))<=1," jour"," jours"),"Le "&D20)))))
F21: =IF(B21="","",IF(E21="Oui","Payée",IF(D21<DAY(TODAY()),"En retard",IF((D21-DAY(TODAY()))=0,"Aujourd'hui",IF((D21-DAY(TODAY()))<=3,"Dans "&(D21-DAY(TODAY()))&IF((D21-DAY(TODAY()))<=1," jour"," jours"),"Le "&D21)))))
F22: =IF(B22="","",IF(E22="Oui","Payée",IF(D22<DAY(TODAY()),"En retard",IF((D22-DAY(TODAY()))=0,"Aujourd'hui",IF((D22-DAY(TODAY()))<=3,"Dans "&(D22-DAY(TODAY()))&IF((D22-DAY(TODAY()))<=1," jour"," jours"),"Le "&D22)))))
F23: =IF(B23="","",IF(E23="Oui","Payée",IF(D23<DAY(TODAY()),"En retard",IF((D23-DAY(TODAY()))=0,"Aujourd'hui",IF((D23-DAY(TODAY()))<=3,"Dans "&(D23-DAY(TODAY()))&IF((D23-DAY(TODAY()))<=1," jour"," jours"),"Le "&D23)))))
... F30: =IF(B30="","",IF(E30="Oui","Payée",IF(D30<DAY(TODAY()),"En retard",IF((D30-DAY(TODAY()))=0,"Aujourd'hui",IF((D30-DAY(TODAY()))<=3,"Dans "&(D30-DAY(TODAY()))&IF((D30-DAY(TODAY()))<=1," jour"," jours"),"Le "&D30)))))

Sheet Envies
B2: Envies : la règle des 48 heures
B3: Notez ce que vous voulez acheter. Si l'envie est toujours là 48 heures plus tard, allez-y.
B5: Article | C5: Prix | D5: Ajouté le | E5: Verdict | F5: Ma décision | H5: Argent gardé en renonçant :
B6: Écouteurs sans fil | C6: 79 | D6: 46290 | E6: =IF(B6="","",IF(F6<>"",F6,IF(TODAY()-D6>=2,"48 heures passées : achetez si l'envie est toujours là","Encore "&(2-(TODAY()-D6))&IF((2-(TODAY()-D6))<=1," jour"," jours")&" à attendre"))) | H6: =SUMIFS(C6:C30,F6:F30,"Renoncé")
B7: Bureau debout | C7: 249 | D7: 46292 | E7: =IF(B7="","",IF(F7<>"",F7,IF(TODAY()-D7>=2,"48 heures passées : achetez si l'envie est toujours là","Encore "&(2-(TODAY()-D7))&IF((2-(TODAY()-D7))<=1," jour"," jours")&" à attendre")))
B8: Chaussures | C8: 45 | D8: 46287 | E8: =IF(B8="","",IF(F8<>"",F8,IF(TODAY()-D8>=2,"48 heures passées : achetez si l'envie est toujours là","Encore "&(2-(TODAY()-D8))&IF((2-(TODAY()-D8))<=1," jour"," jours")&" à attendre"))) | F8: Acheté
B9: Montre connectée | C9: 199 | D9: 46284 | E9: =IF(B9="","",IF(F9<>"",F9,IF(TODAY()-D9>=2,"48 heures passées : achetez si l'envie est toujours là","Encore "&(2-(TODAY()-D9))&IF((2-(TODAY()-D9))<=1," jour"," jours")&" à attendre"))) | F9: Renoncé
B10: Jeu de société | C10: 39 | D10: 46293 | E10: =IF(B10="","",IF(F10<>"",F10,IF(TODAY()-D10>=2,"48 heures passées : achetez si l'envie est toujours là","Encore "&(2-(TODAY()-D10))&IF((2-(TODAY()-D10))<=1," jour"," jours")&" à attendre")))
E11: =IF(B11="","",IF(F11<>"",F11,IF(TODAY()-D11>=2,"48 heures passées : achetez si l'envie est toujours là","Encore "&(2-(TODAY()-D11))&IF((2-(TODAY()-D11))<=1," jour"," jours")&" à attendre")))
E12: =IF(B12="","",IF(F12<>"",F12,IF(TODAY()-D12>=2,"48 heures passées : achetez si l'envie est toujours là","Encore "&(2-(TODAY()-D12))&IF((2-(TODAY()-D12))<=1," jour"," jours")&" à attendre")))
E13: =IF(B13="","",IF(F13<>"",F13,IF(TODAY()-D13>=2,"48 heures passées : achetez si l'envie est toujours là","Encore "&(2-(TODAY()-D13))&IF((2-(TODAY()-D13))<=1," jour"," jours")&" à attendre")))
E14: =IF(B14="","",IF(F14<>"",F14,IF(TODAY()-D14>=2,"48 heures passées : achetez si l'envie est toujours là","Encore "&(2-(TODAY()-D14))&IF((2-(TODAY()-D14))<=1," jour"," jours")&" à attendre")))
E15: =IF(B15="","",IF(F15<>"",F15,IF(TODAY()-D15>=2,"48 heures passées : achetez si l'envie est toujours là","Encore "&(2-(TODAY()-D15))&IF((2-(TODAY()-D15))<=1," jour"," jours")&" à attendre")))
E16: =IF(B16="","",IF(F16<>"",F16,IF(TODAY()-D16>=2,"48 heures passées : achetez si l'envie est toujours là","Encore "&(2-(TODAY()-D16))&IF((2-(TODAY()-D16))<=1," jour"," jours")&" à attendre")))
E17: =IF(B17="","",IF(F17<>"",F17,IF(TODAY()-D17>=2,"48 heures passées : achetez si l'envie est toujours là","Encore "&(2-(TODAY()-D17))&IF((2-(TODAY()-D17))<=1," jour"," jours")&" à attendre")))
E18: =IF(B18="","",IF(F18<>"",F18,IF(TODAY()-D18>=2,"48 heures passées : achetez si l'envie est toujours là","Encore "&(2-(TODAY()-D18))&IF((2-(TODAY()-D18))<=1," jour"," jours")&" à attendre")))
E19: =IF(B19="","",IF(F19<>"",F19,IF(TODAY()-D19>=2,"48 heures passées : achetez si l'envie est toujours là","Encore "&(2-(TODAY()-D19))&IF((2-(TODAY()-D19))<=1," jour"," jours")&" à attendre")))
E20: =IF(B20="","",IF(F20<>"",F20,IF(TODAY()-D20>=2,"48 heures passées : achetez si l'envie est toujours là","Encore "&(2-(TODAY()-D20))&IF((2-(TODAY()-D20))<=1," jour"," jours")&" à attendre")))
E21: =IF(B21="","",IF(F21<>"",F21,IF(TODAY()-D21>=2,"48 heures passées : achetez si l'envie est toujours là","Encore "&(2-(TODAY()-D21))&IF((2-(TODAY()-D21))<=1," jour"," jours")&" à attendre")))
E22: =IF(B22="","",IF(F22<>"",F22,IF(TODAY()-D22>=2,"48 heures passées : achetez si l'envie est toujours là","Encore "&(2-(TODAY()-D22))&IF((2-(TODAY()-D22))<=1," jour"," jours")&" à attendre")))
... E30: =IF(B30="","",IF(F30<>"",F30,IF(TODAY()-D30>=2,"48 heures passées : achetez si l'envie est toujours là","Encore "&(2-(TODAY()-D30))&IF((2-(TODAY()-D30))<=1," jour"," jours")&" à attendre")))

Sheet Objectifs
B2: Objectifs d'épargne
B3: Mettez à jour la colonne Déjà épargné dès que vous mettez de l'argent de côté.
B5: Objectif | C5: Cible | D5: Déjà épargné | E5: Fait | F5: Progression
B6: Fonds d'urgence | C6: 3000 | D6: 1250 | E6: =IF(C6="","",MIN(1,D6/C6)) | F6: =IF(C6="","",REPT("█",ROUND(E6*20,0))&REPT("░",20-ROUND(E6*20,0)))
B7: Voyage | C7: 1200 | D7: 400 | E7: =IF(C7="","",MIN(1,D7/C7)) | F7: =IF(C7="","",REPT("█",ROUND(E7*20,0))&REPT("░",20-ROUND(E7*20,0)))
B8: Nouvel ordinateur | C8: 900 | D8: 810 | E8: =IF(C8="","",MIN(1,D8/C8)) | F8: =IF(C8="","",REPT("█",ROUND(E8*20,0))&REPT("░",20-ROUND(E8*20,0)))
E9: =IF(C9="","",MIN(1,D9/C9)) | F9: =IF(C9="","",REPT("█",ROUND(E9*20,0))&REPT("░",20-ROUND(E9*20,0)))
E10: =IF(C10="","",MIN(1,D10/C10)) | F10: =IF(C10="","",REPT("█",ROUND(E10*20,0))&REPT("░",20-ROUND(E10*20,0)))
E11: =IF(C11="","",MIN(1,D11/C11)) | F11: =IF(C11="","",REPT("█",ROUND(E11*20,0))&REPT("░",20-ROUND(E11*20,0)))
E12: =IF(C12="","",MIN(1,D12/C12)) | F12: =IF(C12="","",REPT("█",ROUND(E12*20,0))&REPT("░",20-ROUND(E12*20,0)))
E13: =IF(C13="","",MIN(1,D13/C13)) | F13: =IF(C13="","",REPT("█",ROUND(E13*20,0))&REPT("░",20-ROUND(E13*20,0)))
E14: =IF(C14="","",MIN(1,D14/C14)) | F14: =IF(C14="","",REPT("█",ROUND(E14*20,0))&REPT("░",20-ROUND(E14*20,0)))
E15: =IF(C15="","",MIN(1,D15/C15)) | F15: =IF(C15="","",REPT("█",ROUND(E15*20,0))&REPT("░",20-ROUND(E15*20,0)))
