Workbook

Sheet Dashboard
B2: ="Trip expenses: "&Setup!$D$4
B3: Who paid what, what everyone's share came to, and who pays whom to settle up.
B4: ="All amounts in "&Setup!$D$5
B6: Spent in total | C6: Per person | D6: Per day | E6: Days | F6: Expenses
B7: =SUMIFS(Expenses!$T$6:$T$505,Expenses!$D$6:$D$505,"<>Paying back") | C7: =IF(COUNTIF(Setup!$B$9:$B$20,"?*")=0,"",SUMIFS(Expenses!$T$6:$T$505,Expenses!$D$6:$D$505,"<>Paying back")/COUNTIF(Setup!$B$9:$B$20,"?*")) | D7: =IF(MIN(Expenses!$B$6:$B$505)=0,"",SUMIFS(Expenses!$T$6:$T$505,Expenses!$D$6:$D$505,"<>Paying back")/(MAX(Expenses!$B$6:$B$505)-MIN(Expenses!$B$6:$B$505)+1)) | E7: =IF(MIN(Expenses!$B$6:$B$505)=0,"",MAX(Expenses!$B$6:$B$505)-MIN(Expenses!$B$6:$B$505)+1) | F7: =COUNTIFS(Expenses!$T$6:$T$505,">0")
B9: Person | C9: Paid | D9: Share of costs | E9: Balance | F9: Status | H9: Settle up | I9: Amount
B10: =IF(Setup!B9="","",Setup!B9) | C10: =IF(B10="","",SUMIFS(Expenses!$T$6:$T$505,Expenses!$G$6:$G$505,B10)) | D10: =IF(B10="","",SUMIFS(Expenses!$W$6:$W$505,Expenses!$D$6:$D$505,"<>Paying back")) | E10: =IF(B10="","",ROUND(C10-SUM(Expenses!$W$6:$W$505),2)) | F10: =IF(B10="","",IF(ABS(E10)<0.005,"Settled",IF(E10>0,"Gets back "&FIXED(E10,2),"Owes "&FIXED(-E10,2)))) | H10: =IF(N(AA75)<0.01,"Everyone is settled",INDEX($B$10:$B$21,AA77)&" pays "&INDEX($B$10:$B$21,AA76)) | I10: =IF(N(AA75)<0.01,"",AA75)
B11: =IF(Setup!B10="","",Setup!B10) | C11: =IF(B11="","",SUMIFS(Expenses!$T$6:$T$505,Expenses!$G$6:$G$505,B11)) | D11: =IF(B11="","",SUMIFS(Expenses!$X$6:$X$505,Expenses!$D$6:$D$505,"<>Paying back")) | E11: =IF(B11="","",ROUND(C11-SUM(Expenses!$X$6:$X$505),2)) | F11: =IF(B11="","",IF(ABS(E11)<0.005,"Settled",IF(E11>0,"Gets back "&FIXED(E11,2),"Owes "&FIXED(-E11,2)))) | H11: =IF(N(AB75)<0.01,"",INDEX($B$10:$B$21,AB77)&" pays "&INDEX($B$10:$B$21,AB76)) | I11: =IF(N(AB75)<0.01,"",AB75)
B12: =IF(Setup!B11="","",Setup!B11) | C12: =IF(B12="","",SUMIFS(Expenses!$T$6:$T$505,Expenses!$G$6:$G$505,B12)) | D12: =IF(B12="","",SUMIFS(Expenses!$Y$6:$Y$505,Expenses!$D$6:$D$505,"<>Paying back")) | E12: =IF(B12="","",ROUND(C12-SUM(Expenses!$Y$6:$Y$505),2)) | F12: =IF(B12="","",IF(ABS(E12)<0.005,"Settled",IF(E12>0,"Gets back "&FIXED(E12,2),"Owes "&FIXED(-E12,2)))) | H12: =IF(N(AC75)<0.01,"",INDEX($B$10:$B$21,AC77)&" pays "&INDEX($B$10:$B$21,AC76)) | I12: =IF(N(AC75)<0.01,"",AC75)
B13: =IF(Setup!B12="","",Setup!B12) | C13: =IF(B13="","",SUMIFS(Expenses!$T$6:$T$505,Expenses!$G$6:$G$505,B13)) | D13: =IF(B13="","",SUMIFS(Expenses!$Z$6:$Z$505,Expenses!$D$6:$D$505,"<>Paying back")) | E13: =IF(B13="","",ROUND(C13-SUM(Expenses!$Z$6:$Z$505),2)) | F13: =IF(B13="","",IF(ABS(E13)<0.005,"Settled",IF(E13>0,"Gets back "&FIXED(E13,2),"Owes "&FIXED(-E13,2)))) | H13: =IF(N(AD75)<0.01,"",INDEX($B$10:$B$21,AD77)&" pays "&INDEX($B$10:$B$21,AD76)) | I13: =IF(N(AD75)<0.01,"",AD75)
B14: =IF(Setup!B13="","",Setup!B13) | C14: =IF(B14="","",SUMIFS(Expenses!$T$6:$T$505,Expenses!$G$6:$G$505,B14)) | D14: =IF(B14="","",SUMIFS(Expenses!$AA$6:$AA$505,Expenses!$D$6:$D$505,"<>Paying back")) | E14: =IF(B14="","",ROUND(C14-SUM(Expenses!$AA$6:$AA$505),2)) | F14: =IF(B14="","",IF(ABS(E14)<0.005,"Settled",IF(E14>0,"Gets back "&FIXED(E14,2),"Owes "&FIXED(-E14,2)))) | H14: =IF(N(AE75)<0.01,"",INDEX($B$10:$B$21,AE77)&" pays "&INDEX($B$10:$B$21,AE76)) | I14: =IF(N(AE75)<0.01,"",AE75)
B15: =IF(Setup!B14="","",Setup!B14) | C15: =IF(B15="","",SUMIFS(Expenses!$T$6:$T$505,Expenses!$G$6:$G$505,B15)) | D15: =IF(B15="","",SUMIFS(Expenses!$AB$6:$AB$505,Expenses!$D$6:$D$505,"<>Paying back")) | E15: =IF(B15="","",ROUND(C15-SUM(Expenses!$AB$6:$AB$505),2)) | F15: =IF(B15="","",IF(ABS(E15)<0.005,"Settled",IF(E15>0,"Gets back "&FIXED(E15,2),"Owes "&FIXED(-E15,2)))) | H15: =IF(N(AF75)<0.01,"",INDEX($B$10:$B$21,AF77)&" pays "&INDEX($B$10:$B$21,AF76)) | I15: =IF(N(AF75)<0.01,"",AF75)
B16: =IF(Setup!B15="","",Setup!B15) | C16: =IF(B16="","",SUMIFS(Expenses!$T$6:$T$505,Expenses!$G$6:$G$505,B16)) | D16: =IF(B16="","",SUMIFS(Expenses!$AC$6:$AC$505,Expenses!$D$6:$D$505,"<>Paying back")) | E16: =IF(B16="","",ROUND(C16-SUM(Expenses!$AC$6:$AC$505),2)) | F16: =IF(B16="","",IF(ABS(E16)<0.005,"Settled",IF(E16>0,"Gets back "&FIXED(E16,2),"Owes "&FIXED(-E16,2)))) | H16: =IF(N(AG75)<0.01,"",INDEX($B$10:$B$21,AG77)&" pays "&INDEX($B$10:$B$21,AG76)) | I16: =IF(N(AG75)<0.01,"",AG75)
B17: =IF(Setup!B16="","",Setup!B16) | C17: =IF(B17="","",SUMIFS(Expenses!$T$6:$T$505,Expenses!$G$6:$G$505,B17)) | D17: =IF(B17="","",SUMIFS(Expenses!$AD$6:$AD$505,Expenses!$D$6:$D$505,"<>Paying back")) | E17: =IF(B17="","",ROUND(C17-SUM(Expenses!$AD$6:$AD$505),2)) | F17: =IF(B17="","",IF(ABS(E17)<0.005,"Settled",IF(E17>0,"Gets back "&FIXED(E17,2),"Owes "&FIXED(-E17,2)))) | H17: =IF(N(AH75)<0.01,"",INDEX($B$10:$B$21,AH77)&" pays "&INDEX($B$10:$B$21,AH76)) | I17: =IF(N(AH75)<0.01,"",AH75)
B18: =IF(Setup!B17="","",Setup!B17) | C18: =IF(B18="","",SUMIFS(Expenses!$T$6:$T$505,Expenses!$G$6:$G$505,B18)) | D18: =IF(B18="","",SUMIFS(Expenses!$AE$6:$AE$505,Expenses!$D$6:$D$505,"<>Paying back")) | E18: =IF(B18="","",ROUND(C18-SUM(Expenses!$AE$6:$AE$505),2)) | F18: =IF(B18="","",IF(ABS(E18)<0.005,"Settled",IF(E18>0,"Gets back "&FIXED(E18,2),"Owes "&FIXED(-E18,2)))) | H18: =IF(N(AI75)<0.01,"",INDEX($B$10:$B$21,AI77)&" pays "&INDEX($B$10:$B$21,AI76)) | I18: =IF(N(AI75)<0.01,"",AI75)
B19: =IF(Setup!B18="","",Setup!B18) | C19: =IF(B19="","",SUMIFS(Expenses!$T$6:$T$505,Expenses!$G$6:$G$505,B19)) | D19: =IF(B19="","",SUMIFS(Expenses!$AF$6:$AF$505,Expenses!$D$6:$D$505,"<>Paying back")) | E19: =IF(B19="","",ROUND(C19-SUM(Expenses!$AF$6:$AF$505),2)) | F19: =IF(B19="","",IF(ABS(E19)<0.005,"Settled",IF(E19>0,"Gets back "&FIXED(E19,2),"Owes "&FIXED(-E19,2)))) | H19: =IF(N(AJ75)<0.01,"",INDEX($B$10:$B$21,AJ77)&" pays "&INDEX($B$10:$B$21,AJ76)) | I19: =IF(N(AJ75)<0.01,"",AJ75)
B20: =IF(Setup!B19="","",Setup!B19) | C20: =IF(B20="","",SUMIFS(Expenses!$T$6:$T$505,Expenses!$G$6:$G$505,B20)) | D20: =IF(B20="","",SUMIFS(Expenses!$AG$6:$AG$505,Expenses!$D$6:$D$505,"<>Paying back")) | E20: =IF(B20="","",ROUND(C20-SUM(Expenses!$AG$6:$AG$505),2)) | F20: =IF(B20="","",IF(ABS(E20)<0.005,"Settled",IF(E20>0,"Gets back "&FIXED(E20,2),"Owes "&FIXED(-E20,2)))) | H20: =IF(N(AK75)<0.01,"",INDEX($B$10:$B$21,AK77)&" pays "&INDEX($B$10:$B$21,AK76)) | I20: =IF(N(AK75)<0.01,"",AK75)
B21: =IF(Setup!B20="","",Setup!B20) | C21: =IF(B21="","",SUMIFS(Expenses!$T$6:$T$505,Expenses!$G$6:$G$505,B21)) | D21: =IF(B21="","",SUMIFS(Expenses!$AH$6:$AH$505,Expenses!$D$6:$D$505,"<>Paying back")) | E21: =IF(B21="","",ROUND(C21-SUM(Expenses!$AH$6:$AH$505),2)) | F21: =IF(B21="","",IF(ABS(E21)<0.005,"Settled",IF(E21>0,"Gets back "&FIXED(E21,2),"Owes "&FIXED(-E21,2))))
B22: Share of costs leaves out money paid back between you. Balance counts it. | H22: The fewest payments that bring every balance to zero.
B25: Category | C25: Spent | D25: Share | K25: Day | L25: Spent
B26: Lodging | C26: =SUMIFS(Expenses!$T$6:$T$505,Expenses!$D$6:$D$505,B26) | D26: =IF(N($B$7)=0,"",C26/$B$7) | K26: =IF(OR(MIN(Expenses!$B$6:$B$505)=0,(MIN(Expenses!$B$6:$B$505)+0)>MAX(Expenses!$B$6:$B$505)),"",(MIN(Expenses!$B$6:$B$505)+0)) | L26: =IF(K26="","",SUMIFS(Expenses!$T$6:$T$505,Expenses!$B$6:$B$505,K26,Expenses!$D$6:$D$505,"<>Paying back"))
B27: Food | C27: =SUMIFS(Expenses!$T$6:$T$505,Expenses!$D$6:$D$505,B27) | D27: =IF(N($B$7)=0,"",C27/$B$7) | K27: =IF(OR(MIN(Expenses!$B$6:$B$505)=0,(MIN(Expenses!$B$6:$B$505)+1)>MAX(Expenses!$B$6:$B$505)),"",(MIN(Expenses!$B$6:$B$505)+1)) | L27: =IF(K27="","",SUMIFS(Expenses!$T$6:$T$505,Expenses!$B$6:$B$505,K27,Expenses!$D$6:$D$505,"<>Paying back"))
B28: Transport | C28: =SUMIFS(Expenses!$T$6:$T$505,Expenses!$D$6:$D$505,B28) | D28: =IF(N($B$7)=0,"",C28/$B$7) | K28: =IF(OR(MIN(Expenses!$B$6:$B$505)=0,(MIN(Expenses!$B$6:$B$505)+2)>MAX(Expenses!$B$6:$B$505)),"",(MIN(Expenses!$B$6:$B$505)+2)) | L28: =IF(K28="","",SUMIFS(Expenses!$T$6:$T$505,Expenses!$B$6:$B$505,K28,Expenses!$D$6:$D$505,"<>Paying back"))
B29: Activities | C29: =SUMIFS(Expenses!$T$6:$T$505,Expenses!$D$6:$D$505,B29) | D29: =IF(N($B$7)=0,"",C29/$B$7) | K29: =IF(OR(MIN(Expenses!$B$6:$B$505)=0,(MIN(Expenses!$B$6:$B$505)+3)>MAX(Expenses!$B$6:$B$505)),"",(MIN(Expenses!$B$6:$B$505)+3)) | L29: =IF(K29="","",SUMIFS(Expenses!$T$6:$T$505,Expenses!$B$6:$B$505,K29,Expenses!$D$6:$D$505,"<>Paying back"))
B30: Groceries | C30: =SUMIFS(Expenses!$T$6:$T$505,Expenses!$D$6:$D$505,B30) | D30: =IF(N($B$7)=0,"",C30/$B$7) | K30: =IF(OR(MIN(Expenses!$B$6:$B$505)=0,(MIN(Expenses!$B$6:$B$505)+4)>MAX(Expenses!$B$6:$B$505)),"",(MIN(Expenses!$B$6:$B$505)+4)) | L30: =IF(K30="","",SUMIFS(Expenses!$T$6:$T$505,Expenses!$B$6:$B$505,K30,Expenses!$D$6:$D$505,"<>Paying back"))
B31: Other | C31: =SUMIFS(Expenses!$T$6:$T$505,Expenses!$D$6:$D$505,B31) | D31: =IF(N($B$7)=0,"",C31/$B$7) | K31: =IF(OR(MIN(Expenses!$B$6:$B$505)=0,(MIN(Expenses!$B$6:$B$505)+5)>MAX(Expenses!$B$6:$B$505)),"",(MIN(Expenses!$B$6:$B$505)+5)) | L31: =IF(K31="","",SUMIFS(Expenses!$T$6:$T$505,Expenses!$B$6:$B$505,K31,Expenses!$D$6:$D$505,"<>Paying back"))
K32: =IF(OR(MIN(Expenses!$B$6:$B$505)=0,(MIN(Expenses!$B$6:$B$505)+6)>MAX(Expenses!$B$6:$B$505)),"",(MIN(Expenses!$B$6:$B$505)+6)) | L32: =IF(K32="","",SUMIFS(Expenses!$T$6:$T$505,Expenses!$B$6:$B$505,K32,Expenses!$D$6:$D$505,"<>Paying back"))
K33: =IF(OR(MIN(Expenses!$B$6:$B$505)=0,(MIN(Expenses!$B$6:$B$505)+7)>MAX(Expenses!$B$6:$B$505)),"",(MIN(Expenses!$B$6:$B$505)+7)) | L33: =IF(K33="","",SUMIFS(Expenses!$T$6:$T$505,Expenses!$B$6:$B$505,K33,Expenses!$D$6:$D$505,"<>Paying back"))
K34: =IF(OR(MIN(Expenses!$B$6:$B$505)=0,(MIN(Expenses!$B$6:$B$505)+8)>MAX(Expenses!$B$6:$B$505)),"",(MIN(Expenses!$B$6:$B$505)+8)) | L34: =IF(K34="","",SUMIFS(Expenses!$T$6:$T$505,Expenses!$B$6:$B$505,K34,Expenses!$D$6:$D$505,"<>Paying back"))
K35: =IF(OR(MIN(Expenses!$B$6:$B$505)=0,(MIN(Expenses!$B$6:$B$505)+9)>MAX(Expenses!$B$6:$B$505)),"",(MIN(Expenses!$B$6:$B$505)+9)) | L35: =IF(K35="","",SUMIFS(Expenses!$T$6:$T$505,Expenses!$B$6:$B$505,K35,Expenses!$D$6:$D$505,"<>Paying back"))
K36: =IF(OR(MIN(Expenses!$B$6:$B$505)=0,(MIN(Expenses!$B$6:$B$505)+10)>MAX(Expenses!$B$6:$B$505)),"",(MIN(Expenses!$B$6:$B$505)+10)) | L36: =IF(K36="","",SUMIFS(Expenses!$T$6:$T$505,Expenses!$B$6:$B$505,K36,Expenses!$D$6:$D$505,"<>Paying back"))
K37: =IF(OR(MIN(Expenses!$B$6:$B$505)=0,(MIN(Expenses!$B$6:$B$505)+11)>MAX(Expenses!$B$6:$B$505)),"",(MIN(Expenses!$B$6:$B$505)+11)) | L37: =IF(K37="","",SUMIFS(Expenses!$T$6:$T$505,Expenses!$B$6:$B$505,K37,Expenses!$D$6:$D$505,"<>Paying back"))
K38: =IF(OR(MIN(Expenses!$B$6:$B$505)=0,(MIN(Expenses!$B$6:$B$505)+12)>MAX(Expenses!$B$6:$B$505)),"",(MIN(Expenses!$B$6:$B$505)+12)) | L38: =IF(K38="","",SUMIFS(Expenses!$T$6:$T$505,Expenses!$B$6:$B$505,K38,Expenses!$D$6:$D$505,"<>Paying back"))
K39: =IF(OR(MIN(Expenses!$B$6:$B$505)=0,(MIN(Expenses!$B$6:$B$505)+13)>MAX(Expenses!$B$6:$B$505)),"",(MIN(Expenses!$B$6:$B$505)+13)) | L39: =IF(K39="","",SUMIFS(Expenses!$T$6:$T$505,Expenses!$B$6:$B$505,K39,Expenses!$D$6:$D$505,"<>Paying back"))
K40: =IF(OR(MIN(Expenses!$B$6:$B$505)=0,(MIN(Expenses!$B$6:$B$505)+14)>MAX(Expenses!$B$6:$B$505)),"",(MIN(Expenses!$B$6:$B$505)+14)) | L40: =IF(K40="","",SUMIFS(Expenses!$T$6:$T$505,Expenses!$B$6:$B$505,K40,Expenses!$D$6:$D$505,"<>Paying back"))
K41: =IF(OR(MIN(Expenses!$B$6:$B$505)=0,(MIN(Expenses!$B$6:$B$505)+15)>MAX(Expenses!$B$6:$B$505)),"",(MIN(Expenses!$B$6:$B$505)+15)) | L41: =IF(K41="","",SUMIFS(Expenses!$T$6:$T$505,Expenses!$B$6:$B$505,K41,Expenses!$D$6:$D$505,"<>Paying back"))
K42: =IF(OR(MIN(Expenses!$B$6:$B$505)=0,(MIN(Expenses!$B$6:$B$505)+16)>MAX(Expenses!$B$6:$B$505)),"",(MIN(Expenses!$B$6:$B$505)+16)) | L42: =IF(K42="","",SUMIFS(Expenses!$T$6:$T$505,Expenses!$B$6:$B$505,K42,Expenses!$D$6:$D$505,"<>Paying back"))
K43: =IF(OR(MIN(Expenses!$B$6:$B$505)=0,(MIN(Expenses!$B$6:$B$505)+17)>MAX(Expenses!$B$6:$B$505)),"",(MIN(Expenses!$B$6:$B$505)+17)) | L43: =IF(K43="","",SUMIFS(Expenses!$T$6:$T$505,Expenses!$B$6:$B$505,K43,Expenses!$D$6:$D$505,"<>Paying back"))
K44: =IF(OR(MIN(Expenses!$B$6:$B$505)=0,(MIN(Expenses!$B$6:$B$505)+18)>MAX(Expenses!$B$6:$B$505)),"",(MIN(Expenses!$B$6:$B$505)+18)) | L44: =IF(K44="","",SUMIFS(Expenses!$T$6:$T$505,Expenses!$B$6:$B$505,K44,Expenses!$D$6:$D$505,"<>Paying back"))
K45: =IF(OR(MIN(Expenses!$B$6:$B$505)=0,(MIN(Expenses!$B$6:$B$505)+19)>MAX(Expenses!$B$6:$B$505)),"",(MIN(Expenses!$B$6:$B$505)+19)) | L45: =IF(K45="","",SUMIFS(Expenses!$T$6:$T$505,Expenses!$B$6:$B$505,K45,Expenses!$D$6:$D$505,"<>Paying back"))
K46: =IF(OR(MIN(Expenses!$B$6:$B$505)=0,(MIN(Expenses!$B$6:$B$505)+20)>MAX(Expenses!$B$6:$B$505)),"",(MIN(Expenses!$B$6:$B$505)+20)) | L46: =IF(K46="","",SUMIFS(Expenses!$T$6:$T$505,Expenses!$B$6:$B$505,K46,Expenses!$D$6:$D$505,"<>Paying back"))
AA60: =IF(B10="",0,E10) | AB60: =ROUND(AA60-IF(1=AA$76,AA$75,0)+IF(1=AA$77,AA$75,0),2) | AC60: =ROUND(AB60-IF(1=AB$76,AB$75,0)+IF(1=AB$77,AB$75,0),2) | AD60: =ROUND(AC60-IF(1=AC$76,AC$75,0)+IF(1=AC$77,AC$75,0),2) | AE60: =ROUND(AD60-IF(1=AD$76,AD$75,0)+IF(1=AD$77,AD$75,0),2) | AF60: =ROUND(AE60-IF(1=AE$76,AE$75,0)+IF(1=AE$77,AE$75,0),2) | AG60: =ROUND(AF60-IF(1=AF$76,AF$75,0)+IF(1=AF$77,AF$75,0),2) | AH60: =ROUND(AG60-IF(1=AG$76,AG$75,0)+IF(1=AG$77,AG$75,0),2) | AI60: =ROUND(AH60-IF(1=AH$76,AH$75,0)+IF(1=AH$77,AH$75,0),2) | ... AL60: =ROUND(AK60-IF(1=AK$76,AK$75,0)+IF(1=AK$77,AK$75,0),2)
AA61: =IF(B11="",0,E11) | AB61: =ROUND(AA61-IF(2=AA$76,AA$75,0)+IF(2=AA$77,AA$75,0),2) | AC61: =ROUND(AB61-IF(2=AB$76,AB$75,0)+IF(2=AB$77,AB$75,0),2) | AD61: =ROUND(AC61-IF(2=AC$76,AC$75,0)+IF(2=AC$77,AC$75,0),2) | AE61: =ROUND(AD61-IF(2=AD$76,AD$75,0)+IF(2=AD$77,AD$75,0),2) | AF61: =ROUND(AE61-IF(2=AE$76,AE$75,0)+IF(2=AE$77,AE$75,0),2) | AG61: =ROUND(AF61-IF(2=AF$76,AF$75,0)+IF(2=AF$77,AF$75,0),2) | AH61: =ROUND(AG61-IF(2=AG$76,AG$75,0)+IF(2=AG$77,AG$75,0),2) | AI61: =ROUND(AH61-IF(2=AH$76,AH$75,0)+IF(2=AH$77,AH$75,0),2) | ... AL61: =ROUND(AK61-IF(2=AK$76,AK$75,0)+IF(2=AK$77,AK$75,0),2)
AA62: =IF(B12="",0,E12) | AB62: =ROUND(AA62-IF(3=AA$76,AA$75,0)+IF(3=AA$77,AA$75,0),2) | AC62: =ROUND(AB62-IF(3=AB$76,AB$75,0)+IF(3=AB$77,AB$75,0),2) | AD62: =ROUND(AC62-IF(3=AC$76,AC$75,0)+IF(3=AC$77,AC$75,0),2) | AE62: =ROUND(AD62-IF(3=AD$76,AD$75,0)+IF(3=AD$77,AD$75,0),2) | AF62: =ROUND(AE62-IF(3=AE$76,AE$75,0)+IF(3=AE$77,AE$75,0),2) | AG62: =ROUND(AF62-IF(3=AF$76,AF$75,0)+IF(3=AF$77,AF$75,0),2) | AH62: =ROUND(AG62-IF(3=AG$76,AG$75,0)+IF(3=AG$77,AG$75,0),2) | AI62: =ROUND(AH62-IF(3=AH$76,AH$75,0)+IF(3=AH$77,AH$75,0),2) | ... AL62: =ROUND(AK62-IF(3=AK$76,AK$75,0)+IF(3=AK$77,AK$75,0),2)
AA63: =IF(B13="",0,E13) | AB63: =ROUND(AA63-IF(4=AA$76,AA$75,0)+IF(4=AA$77,AA$75,0),2) | AC63: =ROUND(AB63-IF(4=AB$76,AB$75,0)+IF(4=AB$77,AB$75,0),2) | AD63: =ROUND(AC63-IF(4=AC$76,AC$75,0)+IF(4=AC$77,AC$75,0),2) | AE63: =ROUND(AD63-IF(4=AD$76,AD$75,0)+IF(4=AD$77,AD$75,0),2) | AF63: =ROUND(AE63-IF(4=AE$76,AE$75,0)+IF(4=AE$77,AE$75,0),2) | AG63: =ROUND(AF63-IF(4=AF$76,AF$75,0)+IF(4=AF$77,AF$75,0),2) | AH63: =ROUND(AG63-IF(4=AG$76,AG$75,0)+IF(4=AG$77,AG$75,0),2) | AI63: =ROUND(AH63-IF(4=AH$76,AH$75,0)+IF(4=AH$77,AH$75,0),2) | ... AL63: =ROUND(AK63-IF(4=AK$76,AK$75,0)+IF(4=AK$77,AK$75,0),2)
AA64: =IF(B14="",0,E14) | AB64: =ROUND(AA64-IF(5=AA$76,AA$75,0)+IF(5=AA$77,AA$75,0),2) | AC64: =ROUND(AB64-IF(5=AB$76,AB$75,0)+IF(5=AB$77,AB$75,0),2) | AD64: =ROUND(AC64-IF(5=AC$76,AC$75,0)+IF(5=AC$77,AC$75,0),2) | AE64: =ROUND(AD64-IF(5=AD$76,AD$75,0)+IF(5=AD$77,AD$75,0),2) | AF64: =ROUND(AE64-IF(5=AE$76,AE$75,0)+IF(5=AE$77,AE$75,0),2) | AG64: =ROUND(AF64-IF(5=AF$76,AF$75,0)+IF(5=AF$77,AF$75,0),2) | AH64: =ROUND(AG64-IF(5=AG$76,AG$75,0)+IF(5=AG$77,AG$75,0),2) | AI64: =ROUND(AH64-IF(5=AH$76,AH$75,0)+IF(5=AH$77,AH$75,0),2) | ... AL64: =ROUND(AK64-IF(5=AK$76,AK$75,0)+IF(5=AK$77,AK$75,0),2)
AA65: =IF(B15="",0,E15) | AB65: =ROUND(AA65-IF(6=AA$76,AA$75,0)+IF(6=AA$77,AA$75,0),2) | AC65: =ROUND(AB65-IF(6=AB$76,AB$75,0)+IF(6=AB$77,AB$75,0),2) | AD65: =ROUND(AC65-IF(6=AC$76,AC$75,0)+IF(6=AC$77,AC$75,0),2) | AE65: =ROUND(AD65-IF(6=AD$76,AD$75,0)+IF(6=AD$77,AD$75,0),2) | AF65: =ROUND(AE65-IF(6=AE$76,AE$75,0)+IF(6=AE$77,AE$75,0),2) | AG65: =ROUND(AF65-IF(6=AF$76,AF$75,0)+IF(6=AF$77,AF$75,0),2) | AH65: =ROUND(AG65-IF(6=AG$76,AG$75,0)+IF(6=AG$77,AG$75,0),2) | AI65: =ROUND(AH65-IF(6=AH$76,AH$75,0)+IF(6=AH$77,AH$75,0),2) | ... AL65: =ROUND(AK65-IF(6=AK$76,AK$75,0)+IF(6=AK$77,AK$75,0),2)
AA66: =IF(B16="",0,E16) | AB66: =ROUND(AA66-IF(7=AA$76,AA$75,0)+IF(7=AA$77,AA$75,0),2) | AC66: =ROUND(AB66-IF(7=AB$76,AB$75,0)+IF(7=AB$77,AB$75,0),2) | AD66: =ROUND(AC66-IF(7=AC$76,AC$75,0)+IF(7=AC$77,AC$75,0),2) | AE66: =ROUND(AD66-IF(7=AD$76,AD$75,0)+IF(7=AD$77,AD$75,0),2) | AF66: =ROUND(AE66-IF(7=AE$76,AE$75,0)+IF(7=AE$77,AE$75,0),2) | AG66: =ROUND(AF66-IF(7=AF$76,AF$75,0)+IF(7=AF$77,AF$75,0),2) | AH66: =ROUND(AG66-IF(7=AG$76,AG$75,0)+IF(7=AG$77,AG$75,0),2) | AI66: =ROUND(AH66-IF(7=AH$76,AH$75,0)+IF(7=AH$77,AH$75,0),2) | ... AL66: =ROUND(AK66-IF(7=AK$76,AK$75,0)+IF(7=AK$77,AK$75,0),2)
AA67: =IF(B17="",0,E17) | AB67: =ROUND(AA67-IF(8=AA$76,AA$75,0)+IF(8=AA$77,AA$75,0),2) | AC67: =ROUND(AB67-IF(8=AB$76,AB$75,0)+IF(8=AB$77,AB$75,0),2) | AD67: =ROUND(AC67-IF(8=AC$76,AC$75,0)+IF(8=AC$77,AC$75,0),2) | AE67: =ROUND(AD67-IF(8=AD$76,AD$75,0)+IF(8=AD$77,AD$75,0),2) | AF67: =ROUND(AE67-IF(8=AE$76,AE$75,0)+IF(8=AE$77,AE$75,0),2) | AG67: =ROUND(AF67-IF(8=AF$76,AF$75,0)+IF(8=AF$77,AF$75,0),2) | AH67: =ROUND(AG67-IF(8=AG$76,AG$75,0)+IF(8=AG$77,AG$75,0),2) | AI67: =ROUND(AH67-IF(8=AH$76,AH$75,0)+IF(8=AH$77,AH$75,0),2) | ... AL67: =ROUND(AK67-IF(8=AK$76,AK$75,0)+IF(8=AK$77,AK$75,0),2)
AA68: =IF(B18="",0,E18) | AB68: =ROUND(AA68-IF(9=AA$76,AA$75,0)+IF(9=AA$77,AA$75,0),2) | AC68: =ROUND(AB68-IF(9=AB$76,AB$75,0)+IF(9=AB$77,AB$75,0),2) | AD68: =ROUND(AC68-IF(9=AC$76,AC$75,0)+IF(9=AC$77,AC$75,0),2) | AE68: =ROUND(AD68-IF(9=AD$76,AD$75,0)+IF(9=AD$77,AD$75,0),2) | AF68: =ROUND(AE68-IF(9=AE$76,AE$75,0)+IF(9=AE$77,AE$75,0),2) | AG68: =ROUND(AF68-IF(9=AF$76,AF$75,0)+IF(9=AF$77,AF$75,0),2) | AH68: =ROUND(AG68-IF(9=AG$76,AG$75,0)+IF(9=AG$77,AG$75,0),2) | AI68: =ROUND(AH68-IF(9=AH$76,AH$75,0)+IF(9=AH$77,AH$75,0),2) | ... AL68: =ROUND(AK68-IF(9=AK$76,AK$75,0)+IF(9=AK$77,AK$75,0),2)
AA69: =IF(B19="",0,E19) | AB69: =ROUND(AA69-IF(10=AA$76,AA$75,0)+IF(10=AA$77,AA$75,0),2) | AC69: =ROUND(AB69-IF(10=AB$76,AB$75,0)+IF(10=AB$77,AB$75,0),2) | AD69: =ROUND(AC69-IF(10=AC$76,AC$75,0)+IF(10=AC$77,AC$75,0),2) | AE69: =ROUND(AD69-IF(10=AD$76,AD$75,0)+IF(10=AD$77,AD$75,0),2) | AF69: =ROUND(AE69-IF(10=AE$76,AE$75,0)+IF(10=AE$77,AE$75,0),2) | AG69: =ROUND(AF69-IF(10=AF$76,AF$75,0)+IF(10=AF$77,AF$75,0),2) | AH69: =ROUND(AG69-IF(10=AG$76,AG$75,0)+IF(10=AG$77,AG$75,0),2) | AI69: =ROUND(AH69-IF(10=AH$76,AH$75,0)+IF(10=AH$77,AH$75,0),2) | ... AL69: =ROUND(AK69-IF(10=AK$76,AK$75,0)+IF(10=AK$77,AK$75,0),2)
AA70: =IF(B20="",0,E20) | AB70: =ROUND(AA70-IF(11=AA$76,AA$75,0)+IF(11=AA$77,AA$75,0),2) | AC70: =ROUND(AB70-IF(11=AB$76,AB$75,0)+IF(11=AB$77,AB$75,0),2) | AD70: =ROUND(AC70-IF(11=AC$76,AC$75,0)+IF(11=AC$77,AC$75,0),2) | AE70: =ROUND(AD70-IF(11=AD$76,AD$75,0)+IF(11=AD$77,AD$75,0),2) | AF70: =ROUND(AE70-IF(11=AE$76,AE$75,0)+IF(11=AE$77,AE$75,0),2) | AG70: =ROUND(AF70-IF(11=AF$76,AF$75,0)+IF(11=AF$77,AF$75,0),2) | AH70: =ROUND(AG70-IF(11=AG$76,AG$75,0)+IF(11=AG$77,AG$75,0),2) | AI70: =ROUND(AH70-IF(11=AH$76,AH$75,0)+IF(11=AH$77,AH$75,0),2) | ... AL70: =ROUND(AK70-IF(11=AK$76,AK$75,0)+IF(11=AK$77,AK$75,0),2)
AA71: =IF(B21="",0,E21) | AB71: =ROUND(AA71-IF(12=AA$76,AA$75,0)+IF(12=AA$77,AA$75,0),2) | AC71: =ROUND(AB71-IF(12=AB$76,AB$75,0)+IF(12=AB$77,AB$75,0),2) | AD71: =ROUND(AC71-IF(12=AC$76,AC$75,0)+IF(12=AC$77,AC$75,0),2) | AE71: =ROUND(AD71-IF(12=AD$76,AD$75,0)+IF(12=AD$77,AD$75,0),2) | AF71: =ROUND(AE71-IF(12=AE$76,AE$75,0)+IF(12=AE$77,AE$75,0),2) | AG71: =ROUND(AF71-IF(12=AF$76,AF$75,0)+IF(12=AF$77,AF$75,0),2) | AH71: =ROUND(AG71-IF(12=AG$76,AG$75,0)+IF(12=AG$77,AG$75,0),2) | AI71: =ROUND(AH71-IF(12=AH$76,AH$75,0)+IF(12=AH$77,AH$75,0),2) | ... AL71: =ROUND(AK71-IF(12=AK$76,AK$75,0)+IF(12=AK$77,AK$75,0),2)
AA73: =MAX(AA$60:AA$71) | AB73: =MAX(AB$60:AB$71) | AC73: =MAX(AC$60:AC$71) | AD73: =MAX(AD$60:AD$71) | AE73: =MAX(AE$60:AE$71) | AF73: =MAX(AF$60:AF$71) | AG73: =MAX(AG$60:AG$71) | AH73: =MAX(AH$60:AH$71) | ... AK73: =MAX(AK$60:AK$71)
AA74: =MIN(AA$60:AA$71) | AB74: =MIN(AB$60:AB$71) | AC74: =MIN(AC$60:AC$71) | AD74: =MIN(AD$60:AD$71) | AE74: =MIN(AE$60:AE$71) | AF74: =MIN(AF$60:AF$71) | AG74: =MIN(AG$60:AG$71) | AH74: =MIN(AH$60:AH$71) | ... AK74: =MIN(AK$60:AK$71)
AA75: =ROUND(MIN(AA73,-AA74),2) | AB75: =ROUND(MIN(AB73,-AB74),2) | AC75: =ROUND(MIN(AC73,-AC74),2) | AD75: =ROUND(MIN(AD73,-AD74),2) | AE75: =ROUND(MIN(AE73,-AE74),2) | AF75: =ROUND(MIN(AF73,-AF74),2) | AG75: =ROUND(MIN(AG73,-AG74),2) | AH75: =ROUND(MIN(AH73,-AH74),2) | ... AK75: =ROUND(MIN(AK73,-AK74),2)
AA76: =MATCH(AA73,AA$60:AA$71,0) | AB76: =MATCH(AB73,AB$60:AB$71,0) | AC76: =MATCH(AC73,AC$60:AC$71,0) | AD76: =MATCH(AD73,AD$60:AD$71,0) | AE76: =MATCH(AE73,AE$60:AE$71,0) | AF76: =MATCH(AF73,AF$60:AF$71,0) | AG76: =MATCH(AG73,AG$60:AG$71,0) | AH76: =MATCH(AH73,AH$60:AH$71,0) | ... AK76: =MATCH(AK73,AK$60:AK$71,0)
AA77: =MATCH(AA74,AA$60:AA$71,0) | AB77: =MATCH(AB74,AB$60:AB$71,0) | AC77: =MATCH(AC74,AC$60:AC$71,0) | AD77: =MATCH(AD74,AD$60:AD$71,0) | AE77: =MATCH(AE74,AE$60:AE$71,0) | AF77: =MATCH(AF74,AF$60:AF$71,0) | AG77: =MATCH(AG74,AG$60:AG$71,0) | AH77: =MATCH(AH74,AH$60:AH$71,0) | ... AK77: =MATCH(AK74,AK$60:AK$71,0)

Sheet Setup
B2: Setup
B3: The trip, the people on it, and the currencies you pay in.
B4: Trip | D4: Lisbon and Porto
B5: Home currency | D5: USD
B8: People | D8: Currency | E8: 1 unit is worth
B9: Ana | D9: =$D$5 | E9: 1 | G9: Up to 12 people. The Expenses tab gets one column for each.
B10: Ben | D10: EUR | E10: 1.08 | G10: Each currency's worth in your home currency, for example 1 EUR is worth 1.08 USD.
B11: Chloe | D11: GBP | E11: 1.27 | G11: Every total on the Dashboard is in the home currency.
B12: Dev | D12: CAD | E12: 0.74
B13: Emma

Sheet Expenses
B2: Expenses
B3: One line per expense. Leave the shares empty to split it between everyone, or put an x under the people who share it. A number gives someone more or less than one share.
B5: Date | C5: What | D5: Category | E5: Amount | F5: Currency | G5: Paid by | H5: =IF(Setup!B9="","",Setup!B9) | I5: =IF(Setup!B10="","",Setup!B10) | J5: =IF(Setup!B11="","",Setup!B11) | K5: =IF(Setup!B12="","",Setup!B12) | L5: =IF(Setup!B13="","",Setup!B13) | M5: =IF(Setup!B14="","",Setup!B14) | N5: =IF(Setup!B15="","",Setup!B15) | O5: =IF(Setup!B16="","",Setup!B16) | P5: =IF(Setup!B17="","",Setup!B17) | Q5: =IF(Setup!B18="","",Setup!B18) | R5: =IF(Setup!B19="","",Setup!B19) | S5: =IF(Setup!B20="","",Setup!B20) | T5: In home currency | U5: Shared by
B6: 46275 | C6: Taxi from the airport | D6: Transport | E6: 38 | F6: EUR | G6: Ana | T6: =IF(N(E6)=0,"",E6*IF(F6="",1,IFERROR(INDEX(Setup!$E$9:$E$18,MATCH(F6,Setup!$D$9:$D$18,0)),0))) | U6: =IF(T6="","",IF(V6=0,"Everyone",IF(COUNTIF(AI6:AT6,">0")=COUNTIF(Setup!$B$9:$B$20,"?*"),"Everyone",COUNTIF(AI6:AT6,">0")&IF(COUNTIF(AI6:AT6,">0")=1," person"," people")))) | V6: =SUM(AI6:AT6) | W6: =IF(OR(T6="",Setup!$B$9=""),0,IF(V6=0,T6/COUNTIF(Setup!$B$9:$B$20,"?*"),T6*AI6/V6)) | X6: =IF(OR(T6="",Setup!$B$10=""),0,IF(V6=0,T6/COUNTIF(Setup!$B$9:$B$20,"?*"),T6*AJ6/V6)) | Y6: =IF(OR(T6="",Setup!$B$11=""),0,IF(V6=0,T6/COUNTIF(Setup!$B$9:$B$20,"?*"),T6*AK6/V6)) | Z6: =IF(OR(T6="",Setup!$B$12=""),0,IF(V6=0,T6/COUNTIF(Setup!$B$9:$B$20,"?*"),T6*AL6/V6)) | AA6: =IF(OR(T6="",Setup!$B$13=""),0,IF(V6=0,T6/COUNTIF(Setup!$B$9:$B$20,"?*"),T6*AM6/V6)) | AB6: =IF(OR(T6="",Setup!$B$14=""),0,IF(V6=0,T6/COUNTIF(Setup!$B$9:$B$20,"?*"),T6*AN6/V6)) | AC6: =IF(OR(T6="",Setup!$B$15=""),0,IF(V6=0,T6/COUNTIF(Setup!$B$9:$B$20,"?*"),T6*AO6/V6)) | AD6: =IF(OR(T6="",Setup!$B$16=""),0,IF(V6=0,T6/COUNTIF(Setup!$B$9:$B$20,"?*"),T6*AP6/V6)) | AE6: =IF(OR(T6="",Setup!$B$17=""),0,IF(V6=0,T6/COUNTIF(Setup!$B$9:$B$20,"?*"),T6*AQ6/V6)) | AF6: =IF(OR(T6="",Setup!$B$18=""),0,IF(V6=0,T6/COUNTIF(Setup!$B$9:$B$20,"?*"),T6*AR6/V6)) | AG6: =IF(OR(T6="",Setup!$B$19=""),0,IF(V6=0,T6/COUNTIF(Setup!$B$9:$B$20,"?*"),T6*AS6/V6)) | AH6: =IF(OR(T6="",Setup!$B$20=""),0,IF(V6=0,T6/COUNTIF(Setup!$B$9:$B$20,"?*"),T6*AT6/V6)) | AI6: =IF(Setup!$B$9="",0,IF(H6="",0,IF(ISNUMBER(H6),H6,1))) | AJ6: =IF(Setup!$B$10="",0,IF(I6="",0,IF(ISNUMBER(I6),I6,1))) | AK6: =IF(Setup!$B$11="",0,IF(J6="",0,IF(ISNUMBER(J6),J6,1))) | AL6: =IF(Setup!$B$12="",0,IF(K6="",0,IF(ISNUMBER(K6),K6,1))) | AM6: =IF(Setup!$B$13="",0,IF(L6="",0,IF(ISNUMBER(L6),L6,1))) | AN6: =IF(Setup!$B$14="",0,IF(M6="",0,IF(ISNUMBER(M6),M6,1))) | AO6: =IF(Setup!$B$15="",0,IF(N6="",0,IF(ISNUMBER(N6),N6,1))) | AP6: =IF(Setup!$B$16="",0,IF(O6="",0,IF(ISNUMBER(O6),O6,1))) | AQ6: =IF(Setup!$B$17="",0,IF(P6="",0,IF(ISNUMBER(P6),P6,1))) | AR6: =IF(Setup!$B$18="",0,IF(Q6="",0,IF(ISNUMBER(Q6),Q6,1))) | AS6: =IF(Setup!$B$19="",0,IF(R6="",0,IF(ISNUMBER(R6),R6,1))) | AT6: =IF(Setup!$B$20="",0,IF(S6="",0,IF(ISNUMBER(S6),S6,1)))
B7: 46275 | C7: Flat in Lisbon, 4 nights | D7: Lodging | E7: 780 | F7: EUR | G7: Ben | T7: =IF(N(E7)=0,"",E7*IF(F7="",1,IFERROR(INDEX(Setup!$E$9:$E$18,MATCH(F7,Setup!$D$9:$D$18,0)),0))) | U7: =IF(T7="","",IF(V7=0,"Everyone",IF(COUNTIF(AI7:AT7,">0")=COUNTIF(Setup!$B$9:$B$20,"?*"),"Everyone",COUNTIF(AI7:AT7,">0")&IF(COUNTIF(AI7:AT7,">0")=1," person"," people")))) | V7: =SUM(AI7:AT7) | W7: =IF(OR(T7="",Setup!$B$9=""),0,IF(V7=0,T7/COUNTIF(Setup!$B$9:$B$20,"?*"),T7*AI7/V7)) | X7: =IF(OR(T7="",Setup!$B$10=""),0,IF(V7=0,T7/COUNTIF(Setup!$B$9:$B$20,"?*"),T7*AJ7/V7)) | Y7: =IF(OR(T7="",Setup!$B$11=""),0,IF(V7=0,T7/COUNTIF(Setup!$B$9:$B$20,"?*"),T7*AK7/V7)) | Z7: =IF(OR(T7="",Setup!$B$12=""),0,IF(V7=0,T7/COUNTIF(Setup!$B$9:$B$20,"?*"),T7*AL7/V7)) | AA7: =IF(OR(T7="",Setup!$B$13=""),0,IF(V7=0,T7/COUNTIF(Setup!$B$9:$B$20,"?*"),T7*AM7/V7)) | AB7: =IF(OR(T7="",Setup!$B$14=""),0,IF(V7=0,T7/COUNTIF(Setup!$B$9:$B$20,"?*"),T7*AN7/V7)) | AC7: =IF(OR(T7="",Setup!$B$15=""),0,IF(V7=0,T7/COUNTIF(Setup!$B$9:$B$20,"?*"),T7*AO7/V7)) | AD7: =IF(OR(T7="",Setup!$B$16=""),0,IF(V7=0,T7/COUNTIF(Setup!$B$9:$B$20,"?*"),T7*AP7/V7)) | AE7: =IF(OR(T7="",Setup!$B$17=""),0,IF(V7=0,T7/COUNTIF(Setup!$B$9:$B$20,"?*"),T7*AQ7/V7)) | AF7: =IF(OR(T7="",Setup!$B$18=""),0,IF(V7=0,T7/COUNTIF(Setup!$B$9:$B$20,"?*"),T7*AR7/V7)) | AG7: =IF(OR(T7="",Setup!$B$19=""),0,IF(V7=0,T7/COUNTIF(Setup!$B$9:$B$20,"?*"),T7*AS7/V7)) | AH7: =IF(OR(T7="",Setup!$B$20=""),0,IF(V7=0,T7/COUNTIF(Setup!$B$9:$B$20,"?*"),T7*AT7/V7)) | AI7: =IF(Setup!$B$9="",0,IF(H7="",0,IF(ISNUMBER(H7),H7,1))) | AJ7: =IF(Setup!$B$10="",0,IF(I7="",0,IF(ISNUMBER(I7),I7,1))) | AK7: =IF(Setup!$B$11="",0,IF(J7="",0,IF(ISNUMBER(J7),J7,1))) | AL7: =IF(Setup!$B$12="",0,IF(K7="",0,IF(ISNUMBER(K7),K7,1))) | AM7: =IF(Setup!$B$13="",0,IF(L7="",0,IF(ISNUMBER(L7),L7,1))) | AN7: =IF(Setup!$B$14="",0,IF(M7="",0,IF(ISNUMBER(M7),M7,1))) | AO7: =IF(Setup!$B$15="",0,IF(N7="",0,IF(ISNUMBER(N7),N7,1))) | AP7: =IF(Setup!$B$16="",0,IF(O7="",0,IF(ISNUMBER(O7),O7,1))) | AQ7: =IF(Setup!$B$17="",0,IF(P7="",0,IF(ISNUMBER(P7),P7,1))) | AR7: =IF(Setup!$B$18="",0,IF(Q7="",0,IF(ISNUMBER(Q7),Q7,1))) | AS7: =IF(Setup!$B$19="",0,IF(R7="",0,IF(ISNUMBER(R7),R7,1))) | AT7: =IF(Setup!$B$20="",0,IF(S7="",0,IF(ISNUMBER(S7),S7,1)))
B8: 46275 | C8: Groceries for the flat | D8: Groceries | E8: 64.3 | F8: EUR | G8: Chloe | T8: =IF(N(E8)=0,"",E8*IF(F8="",1,IFERROR(INDEX(Setup!$E$9:$E$18,MATCH(F8,Setup!$D$9:$D$18,0)),0))) | U8: =IF(T8="","",IF(V8=0,"Everyone",IF(COUNTIF(AI8:AT8,">0")=COUNTIF(Setup!$B$9:$B$20,"?*"),"Everyone",COUNTIF(AI8:AT8,">0")&IF(COUNTIF(AI8:AT8,">0")=1," person"," people")))) | V8: =SUM(AI8:AT8) | W8: =IF(OR(T8="",Setup!$B$9=""),0,IF(V8=0,T8/COUNTIF(Setup!$B$9:$B$20,"?*"),T8*AI8/V8)) | X8: =IF(OR(T8="",Setup!$B$10=""),0,IF(V8=0,T8/COUNTIF(Setup!$B$9:$B$20,"?*"),T8*AJ8/V8)) | Y8: =IF(OR(T8="",Setup!$B$11=""),0,IF(V8=0,T8/COUNTIF(Setup!$B$9:$B$20,"?*"),T8*AK8/V8)) | Z8: =IF(OR(T8="",Setup!$B$12=""),0,IF(V8=0,T8/COUNTIF(Setup!$B$9:$B$20,"?*"),T8*AL8/V8)) | AA8: =IF(OR(T8="",Setup!$B$13=""),0,IF(V8=0,T8/COUNTIF(Setup!$B$9:$B$20,"?*"),T8*AM8/V8)) | AB8: =IF(OR(T8="",Setup!$B$14=""),0,IF(V8=0,T8/COUNTIF(Setup!$B$9:$B$20,"?*"),T8*AN8/V8)) | AC8: =IF(OR(T8="",Setup!$B$15=""),0,IF(V8=0,T8/COUNTIF(Setup!$B$9:$B$20,"?*"),T8*AO8/V8)) | AD8: =IF(OR(T8="",Setup!$B$16=""),0,IF(V8=0,T8/COUNTIF(Setup!$B$9:$B$20,"?*"),T8*AP8/V8)) | AE8: =IF(OR(T8="",Setup!$B$17=""),0,IF(V8=0,T8/COUNTIF(Setup!$B$9:$B$20,"?*"),T8*AQ8/V8)) | AF8: =IF(OR(T8="",Setup!$B$18=""),0,IF(V8=0,T8/COUNTIF(Setup!$B$9:$B$20,"?*"),T8*AR8/V8)) | AG8: =IF(OR(T8="",Setup!$B$19=""),0,IF(V8=0,T8/COUNTIF(Setup!$B$9:$B$20,"?*"),T8*AS8/V8)) | AH8: =IF(OR(T8="",Setup!$B$20=""),0,IF(V8=0,T8/COUNTIF(Setup!$B$9:$B$20,"?*"),T8*AT8/V8)) | AI8: =IF(Setup!$B$9="",0,IF(H8="",0,IF(ISNUMBER(H8),H8,1))) | AJ8: =IF(Setup!$B$10="",0,IF(I8="",0,IF(ISNUMBER(I8),I8,1))) | AK8: =IF(Setup!$B$11="",0,IF(J8="",0,IF(ISNUMBER(J8),J8,1))) | AL8: =IF(Setup!$B$12="",0,IF(K8="",0,IF(ISNUMBER(K8),K8,1))) | AM8: =IF(Setup!$B$13="",0,IF(L8="",0,IF(ISNUMBER(L8),L8,1))) | AN8: =IF(Setup!$B$14="",0,IF(M8="",0,IF(ISNUMBER(M8),M8,1))) | AO8: =IF(Setup!$B$15="",0,IF(N8="",0,IF(ISNUMBER(N8),N8,1))) | AP8: =IF(Setup!$B$16="",0,IF(O8="",0,IF(ISNUMBER(O8),O8,1))) | AQ8: =IF(Setup!$B$17="",0,IF(P8="",0,IF(ISNUMBER(P8),P8,1))) | AR8: =IF(Setup!$B$18="",0,IF(Q8="",0,IF(ISNUMBER(Q8),Q8,1))) | AS8: =IF(Setup!$B$19="",0,IF(R8="",0,IF(ISNUMBER(R8),R8,1))) | AT8: =IF(Setup!$B$20="",0,IF(S8="",0,IF(ISNUMBER(S8),S8,1)))
B9: 46275 | C9: Dinner in Alfama | D9: Food | E9: 142 | F9: EUR | G9: Dev | T9: =IF(N(E9)=0,"",E9*IF(F9="",1,IFERROR(INDEX(Setup!$E$9:$E$18,MATCH(F9,Setup!$D$9:$D$18,0)),0))) | U9: =IF(T9="","",IF(V9=0,"Everyone",IF(COUNTIF(AI9:AT9,">0")=COUNTIF(Setup!$B$9:$B$20,"?*"),"Everyone",COUNTIF(AI9:AT9,">0")&IF(COUNTIF(AI9:AT9,">0")=1," person"," people")))) | V9: =SUM(AI9:AT9) | W9: =IF(OR(T9="",Setup!$B$9=""),0,IF(V9=0,T9/COUNTIF(Setup!$B$9:$B$20,"?*"),T9*AI9/V9)) | X9: =IF(OR(T9="",Setup!$B$10=""),0,IF(V9=0,T9/COUNTIF(Setup!$B$9:$B$20,"?*"),T9*AJ9/V9)) | Y9: =IF(OR(T9="",Setup!$B$11=""),0,IF(V9=0,T9/COUNTIF(Setup!$B$9:$B$20,"?*"),T9*AK9/V9)) | Z9: =IF(OR(T9="",Setup!$B$12=""),0,IF(V9=0,T9/COUNTIF(Setup!$B$9:$B$20,"?*"),T9*AL9/V9)) | AA9: =IF(OR(T9="",Setup!$B$13=""),0,IF(V9=0,T9/COUNTIF(Setup!$B$9:$B$20,"?*"),T9*AM9/V9)) | AB9: =IF(OR(T9="",Setup!$B$14=""),0,IF(V9=0,T9/COUNTIF(Setup!$B$9:$B$20,"?*"),T9*AN9/V9)) | AC9: =IF(OR(T9="",Setup!$B$15=""),0,IF(V9=0,T9/COUNTIF(Setup!$B$9:$B$20,"?*"),T9*AO9/V9)) | AD9: =IF(OR(T9="",Setup!$B$16=""),0,IF(V9=0,T9/COUNTIF(Setup!$B$9:$B$20,"?*"),T9*AP9/V9)) | AE9: =IF(OR(T9="",Setup!$B$17=""),0,IF(V9=0,T9/COUNTIF(Setup!$B$9:$B$20,"?*"),T9*AQ9/V9)) | AF9: =IF(OR(T9="",Setup!$B$18=""),0,IF(V9=0,T9/COUNTIF(Setup!$B$9:$B$20,"?*"),T9*AR9/V9)) | AG9: =IF(OR(T9="",Setup!$B$19=""),0,IF(V9=0,T9/COUNTIF(Setup!$B$9:$B$20,"?*"),T9*AS9/V9)) | AH9: =IF(OR(T9="",Setup!$B$20=""),0,IF(V9=0,T9/COUNTIF(Setup!$B$9:$B$20,"?*"),T9*AT9/V9)) | AI9: =IF(Setup!$B$9="",0,IF(H9="",0,IF(ISNUMBER(H9),H9,1))) | AJ9: =IF(Setup!$B$10="",0,IF(I9="",0,IF(ISNUMBER(I9),I9,1))) | AK9: =IF(Setup!$B$11="",0,IF(J9="",0,IF(ISNUMBER(J9),J9,1))) | AL9: =IF(Setup!$B$12="",0,IF(K9="",0,IF(ISNUMBER(K9),K9,1))) | AM9: =IF(Setup!$B$13="",0,IF(L9="",0,IF(ISNUMBER(L9),L9,1))) | AN9: =IF(Setup!$B$14="",0,IF(M9="",0,IF(ISNUMBER(M9),M9,1))) | AO9: =IF(Setup!$B$15="",0,IF(N9="",0,IF(ISNUMBER(N9),N9,1))) | AP9: =IF(Setup!$B$16="",0,IF(O9="",0,IF(ISNUMBER(O9),O9,1))) | AQ9: =IF(Setup!$B$17="",0,IF(P9="",0,IF(ISNUMBER(P9),P9,1))) | AR9: =IF(Setup!$B$18="",0,IF(Q9="",0,IF(ISNUMBER(Q9),Q9,1))) | AS9: =IF(Setup!$B$19="",0,IF(R9="",0,IF(ISNUMBER(R9),R9,1))) | AT9: =IF(Setup!$B$20="",0,IF(S9="",0,IF(ISNUMBER(S9),S9,1)))
B10: 46276 | C10: Tram day passes | D10: Transport | E10: 32 | F10: EUR | G10: Emma | T10: =IF(N(E10)=0,"",E10*IF(F10="",1,IFERROR(INDEX(Setup!$E$9:$E$18,MATCH(F10,Setup!$D$9:$D$18,0)),0))) | U10: =IF(T10="","",IF(V10=0,"Everyone",IF(COUNTIF(AI10:AT10,">0")=COUNTIF(Setup!$B$9:$B$20,"?*"),"Everyone",COUNTIF(AI10:AT10,">0")&IF(COUNTIF(AI10:AT10,">0")=1," person"," people")))) | V10: =SUM(AI10:AT10) | W10: =IF(OR(T10="",Setup!$B$9=""),0,IF(V10=0,T10/COUNTIF(Setup!$B$9:$B$20,"?*"),T10*AI10/V10)) | X10: =IF(OR(T10="",Setup!$B$10=""),0,IF(V10=0,T10/COUNTIF(Setup!$B$9:$B$20,"?*"),T10*AJ10/V10)) | Y10: =IF(OR(T10="",Setup!$B$11=""),0,IF(V10=0,T10/COUNTIF(Setup!$B$9:$B$20,"?*"),T10*AK10/V10)) | Z10: =IF(OR(T10="",Setup!$B$12=""),0,IF(V10=0,T10/COUNTIF(Setup!$B$9:$B$20,"?*"),T10*AL10/V10)) | AA10: =IF(OR(T10="",Setup!$B$13=""),0,IF(V10=0,T10/COUNTIF(Setup!$B$9:$B$20,"?*"),T10*AM10/V10)) | AB10: =IF(OR(T10="",Setup!$B$14=""),0,IF(V10=0,T10/COUNTIF(Setup!$B$9:$B$20,"?*"),T10*AN10/V10)) | AC10: =IF(OR(T10="",Setup!$B$15=""),0,IF(V10=0,T10/COUNTIF(Setup!$B$9:$B$20,"?*"),T10*AO10/V10)) | AD10: =IF(OR(T10="",Setup!$B$16=""),0,IF(V10=0,T10/COUNTIF(Setup!$B$9:$B$20,"?*"),T10*AP10/V10)) | AE10: =IF(OR(T10="",Setup!$B$17=""),0,IF(V10=0,T10/COUNTIF(Setup!$B$9:$B$20,"?*"),T10*AQ10/V10)) | AF10: =IF(OR(T10="",Setup!$B$18=""),0,IF(V10=0,T10/COUNTIF(Setup!$B$9:$B$20,"?*"),T10*AR10/V10)) | AG10: =IF(OR(T10="",Setup!$B$19=""),0,IF(V10=0,T10/COUNTIF(Setup!$B$9:$B$20,"?*"),T10*AS10/V10)) | AH10: =IF(OR(T10="",Setup!$B$20=""),0,IF(V10=0,T10/COUNTIF(Setup!$B$9:$B$20,"?*"),T10*AT10/V10)) | AI10: =IF(Setup!$B$9="",0,IF(H10="",0,IF(ISNUMBER(H10),H10,1))) | AJ10: =IF(Setup!$B$10="",0,IF(I10="",0,IF(ISNUMBER(I10),I10,1))) | AK10: =IF(Setup!$B$11="",0,IF(J10="",0,IF(ISNUMBER(J10),J10,1))) | AL10: =IF(Setup!$B$12="",0,IF(K10="",0,IF(ISNUMBER(K10),K10,1))) | AM10: =IF(Setup!$B$13="",0,IF(L10="",0,IF(ISNUMBER(L10),L10,1))) | AN10: =IF(Setup!$B$14="",0,IF(M10="",0,IF(ISNUMBER(M10),M10,1))) | AO10: =IF(Setup!$B$15="",0,IF(N10="",0,IF(ISNUMBER(N10),N10,1))) | AP10: =IF(Setup!$B$16="",0,IF(O10="",0,IF(ISNUMBER(O10),O10,1))) | AQ10: =IF(Setup!$B$17="",0,IF(P10="",0,IF(ISNUMBER(P10),P10,1))) | AR10: =IF(Setup!$B$18="",0,IF(Q10="",0,IF(ISNUMBER(Q10),Q10,1))) | AS10: =IF(Setup!$B$19="",0,IF(R10="",0,IF(ISNUMBER(R10),R10,1))) | AT10: =IF(Setup!$B$20="",0,IF(S10="",0,IF(ISNUMBER(S10),S10,1)))
B11: 46276 | C11: Lunch at the market | D11: Food | E11: 88.5 | F11: EUR | G11: Ana | T11: =IF(N(E11)=0,"",E11*IF(F11="",1,IFERROR(INDEX(Setup!$E$9:$E$18,MATCH(F11,Setup!$D$9:$D$18,0)),0))) | U11: =IF(T11="","",IF(V11=0,"Everyone",IF(COUNTIF(AI11:AT11,">0")=COUNTIF(Setup!$B$9:$B$20,"?*"),"Everyone",COUNTIF(AI11:AT11,">0")&IF(COUNTIF(AI11:AT11,">0")=1," person"," people")))) | V11: =SUM(AI11:AT11) | W11: =IF(OR(T11="",Setup!$B$9=""),0,IF(V11=0,T11/COUNTIF(Setup!$B$9:$B$20,"?*"),T11*AI11/V11)) | X11: =IF(OR(T11="",Setup!$B$10=""),0,IF(V11=0,T11/COUNTIF(Setup!$B$9:$B$20,"?*"),T11*AJ11/V11)) | Y11: =IF(OR(T11="",Setup!$B$11=""),0,IF(V11=0,T11/COUNTIF(Setup!$B$9:$B$20,"?*"),T11*AK11/V11)) | Z11: =IF(OR(T11="",Setup!$B$12=""),0,IF(V11=0,T11/COUNTIF(Setup!$B$9:$B$20,"?*"),T11*AL11/V11)) | AA11: =IF(OR(T11="",Setup!$B$13=""),0,IF(V11=0,T11/COUNTIF(Setup!$B$9:$B$20,"?*"),T11*AM11/V11)) | AB11: =IF(OR(T11="",Setup!$B$14=""),0,IF(V11=0,T11/COUNTIF(Setup!$B$9:$B$20,"?*"),T11*AN11/V11)) | AC11: =IF(OR(T11="",Setup!$B$15=""),0,IF(V11=0,T11/COUNTIF(Setup!$B$9:$B$20,"?*"),T11*AO11/V11)) | AD11: =IF(OR(T11="",Setup!$B$16=""),0,IF(V11=0,T11/COUNTIF(Setup!$B$9:$B$20,"?*"),T11*AP11/V11)) | AE11: =IF(OR(T11="",Setup!$B$17=""),0,IF(V11=0,T11/COUNTIF(Setup!$B$9:$B$20,"?*"),T11*AQ11/V11)) | AF11: =IF(OR(T11="",Setup!$B$18=""),0,IF(V11=0,T11/COUNTIF(Setup!$B$9:$B$20,"?*"),T11*AR11/V11)) | AG11: =IF(OR(T11="",Setup!$B$19=""),0,IF(V11=0,T11/COUNTIF(Setup!$B$9:$B$20,"?*"),T11*AS11/V11)) | AH11: =IF(OR(T11="",Setup!$B$20=""),0,IF(V11=0,T11/COUNTIF(Setup!$B$9:$B$20,"?*"),T11*AT11/V11)) | AI11: =IF(Setup!$B$9="",0,IF(H11="",0,IF(ISNUMBER(H11),H11,1))) | AJ11: =IF(Setup!$B$10="",0,IF(I11="",0,IF(ISNUMBER(I11),I11,1))) | AK11: =IF(Setup!$B$11="",0,IF(J11="",0,IF(ISNUMBER(J11),J11,1))) | AL11: =IF(Setup!$B$12="",0,IF(K11="",0,IF(ISNUMBER(K11),K11,1))) | AM11: =IF(Setup!$B$13="",0,IF(L11="",0,IF(ISNUMBER(L11),L11,1))) | AN11: =IF(Setup!$B$14="",0,IF(M11="",0,IF(ISNUMBER(M11),M11,1))) | AO11: =IF(Setup!$B$15="",0,IF(N11="",0,IF(ISNUMBER(N11),N11,1))) | AP11: =IF(Setup!$B$16="",0,IF(O11="",0,IF(ISNUMBER(O11),O11,1))) | AQ11: =IF(Setup!$B$17="",0,IF(P11="",0,IF(ISNUMBER(P11),P11,1))) | AR11: =IF(Setup!$B$18="",0,IF(Q11="",0,IF(ISNUMBER(Q11),Q11,1))) | AS11: =IF(Setup!$B$19="",0,IF(R11="",0,IF(ISNUMBER(R11),R11,1))) | AT11: =IF(Setup!$B$20="",0,IF(S11="",0,IF(ISNUMBER(S11),S11,1)))
B12: 46276 | C12: Castle tickets | D12: Activities | E12: 60 | F12: EUR | G12: Ben | H12: x | I12: x | J12: x | K12: x | T12: =IF(N(E12)=0,"",E12*IF(F12="",1,IFERROR(INDEX(Setup!$E$9:$E$18,MATCH(F12,Setup!$D$9:$D$18,0)),0))) | U12: =IF(T12="","",IF(V12=0,"Everyone",IF(COUNTIF(AI12:AT12,">0")=COUNTIF(Setup!$B$9:$B$20,"?*"),"Everyone",COUNTIF(AI12:AT12,">0")&IF(COUNTIF(AI12:AT12,">0")=1," person"," people")))) | V12: =SUM(AI12:AT12) | W12: =IF(OR(T12="",Setup!$B$9=""),0,IF(V12=0,T12/COUNTIF(Setup!$B$9:$B$20,"?*"),T12*AI12/V12)) | X12: =IF(OR(T12="",Setup!$B$10=""),0,IF(V12=0,T12/COUNTIF(Setup!$B$9:$B$20,"?*"),T12*AJ12/V12)) | Y12: =IF(OR(T12="",Setup!$B$11=""),0,IF(V12=0,T12/COUNTIF(Setup!$B$9:$B$20,"?*"),T12*AK12/V12)) | Z12: =IF(OR(T12="",Setup!$B$12=""),0,IF(V12=0,T12/COUNTIF(Setup!$B$9:$B$20,"?*"),T12*AL12/V12)) | AA12: =IF(OR(T12="",Setup!$B$13=""),0,IF(V12=0,T12/COUNTIF(Setup!$B$9:$B$20,"?*"),T12*AM12/V12)) | AB12: =IF(OR(T12="",Setup!$B$14=""),0,IF(V12=0,T12/COUNTIF(Setup!$B$9:$B$20,"?*"),T12*AN12/V12)) | AC12: =IF(OR(T12="",Setup!$B$15=""),0,IF(V12=0,T12/COUNTIF(Setup!$B$9:$B$20,"?*"),T12*AO12/V12)) | AD12: =IF(OR(T12="",Setup!$B$16=""),0,IF(V12=0,T12/COUNTIF(Setup!$B$9:$B$20,"?*"),T12*AP12/V12)) | AE12: =IF(OR(T12="",Setup!$B$17=""),0,IF(V12=0,T12/COUNTIF(Setup!$B$9:$B$20,"?*"),T12*AQ12/V12)) | AF12: =IF(OR(T12="",Setup!$B$18=""),0,IF(V12=0,T12/COUNTIF(Setup!$B$9:$B$20,"?*"),T12*AR12/V12)) | AG12: =IF(OR(T12="",Setup!$B$19=""),0,IF(V12=0,T12/COUNTIF(Setup!$B$9:$B$20,"?*"),T12*AS12/V12)) | AH12: =IF(OR(T12="",Setup!$B$20=""),0,IF(V12=0,T12/COUNTIF(Setup!$B$9:$B$20,"?*"),T12*AT12/V12)) | AI12: =IF(Setup!$B$9="",0,IF(H12="",0,IF(ISNUMBER(H12),H12,1))) | AJ12: =IF(Setup!$B$10="",0,IF(I12="",0,IF(ISNUMBER(I12),I12,1))) | AK12: =IF(Setup!$B$11="",0,IF(J12="",0,IF(ISNUMBER(J12),J12,1))) | AL12: =IF(Setup!$B$12="",0,IF(K12="",0,IF(ISNUMBER(K12),K12,1))) | AM12: =IF(Setup!$B$13="",0,IF(L12="",0,IF(ISNUMBER(L12),L12,1))) | AN12: =IF(Setup!$B$14="",0,IF(M12="",0,IF(ISNUMBER(M12),M12,1))) | AO12: =IF(Setup!$B$15="",0,IF(N12="",0,IF(ISNUMBER(N12),N12,1))) | AP12: =IF(Setup!$B$16="",0,IF(O12="",0,IF(ISNUMBER(O12),O12,1))) | AQ12: =IF(Setup!$B$17="",0,IF(P12="",0,IF(ISNUMBER(P12),P12,1))) | AR12: =IF(Setup!$B$18="",0,IF(Q12="",0,IF(ISNUMBER(Q12),Q12,1))) | AS12: =IF(Setup!$B$19="",0,IF(R12="",0,IF(ISNUMBER(R12),R12,1))) | AT12: =IF(Setup!$B$20="",0,IF(S12="",0,IF(ISNUMBER(S12),S12,1)))
B13: 46276 | C13: Dinner and fado | D13: Food | E13: 196 | F13: EUR | G13: Chloe | T13: =IF(N(E13)=0,"",E13*IF(F13="",1,IFERROR(INDEX(Setup!$E$9:$E$18,MATCH(F13,Setup!$D$9:$D$18,0)),0))) | U13: =IF(T13="","",IF(V13=0,"Everyone",IF(COUNTIF(AI13:AT13,">0")=COUNTIF(Setup!$B$9:$B$20,"?*"),"Everyone",COUNTIF(AI13:AT13,">0")&IF(COUNTIF(AI13:AT13,">0")=1," person"," people")))) | V13: =SUM(AI13:AT13) | W13: =IF(OR(T13="",Setup!$B$9=""),0,IF(V13=0,T13/COUNTIF(Setup!$B$9:$B$20,"?*"),T13*AI13/V13)) | X13: =IF(OR(T13="",Setup!$B$10=""),0,IF(V13=0,T13/COUNTIF(Setup!$B$9:$B$20,"?*"),T13*AJ13/V13)) | Y13: =IF(OR(T13="",Setup!$B$11=""),0,IF(V13=0,T13/COUNTIF(Setup!$B$9:$B$20,"?*"),T13*AK13/V13)) | Z13: =IF(OR(T13="",Setup!$B$12=""),0,IF(V13=0,T13/COUNTIF(Setup!$B$9:$B$20,"?*"),T13*AL13/V13)) | AA13: =IF(OR(T13="",Setup!$B$13=""),0,IF(V13=0,T13/COUNTIF(Setup!$B$9:$B$20,"?*"),T13*AM13/V13)) | AB13: =IF(OR(T13="",Setup!$B$14=""),0,IF(V13=0,T13/COUNTIF(Setup!$B$9:$B$20,"?*"),T13*AN13/V13)) | AC13: =IF(OR(T13="",Setup!$B$15=""),0,IF(V13=0,T13/COUNTIF(Setup!$B$9:$B$20,"?*"),T13*AO13/V13)) | AD13: =IF(OR(T13="",Setup!$B$16=""),0,IF(V13=0,T13/COUNTIF(Setup!$B$9:$B$20,"?*"),T13*AP13/V13)) | AE13: =IF(OR(T13="",Setup!$B$17=""),0,IF(V13=0,T13/COUNTIF(Setup!$B$9:$B$20,"?*"),T13*AQ13/V13)) | AF13: =IF(OR(T13="",Setup!$B$18=""),0,IF(V13=0,T13/COUNTIF(Setup!$B$9:$B$20,"?*"),T13*AR13/V13)) | AG13: =IF(OR(T13="",Setup!$B$19=""),0,IF(V13=0,T13/COUNTIF(Setup!$B$9:$B$20,"?*"),T13*AS13/V13)) | AH13: =IF(OR(T13="",Setup!$B$20=""),0,IF(V13=0,T13/COUNTIF(Setup!$B$9:$B$20,"?*"),T13*AT13/V13)) | AI13: =IF(Setup!$B$9="",0,IF(H13="",0,IF(ISNUMBER(H13),H13,1))) | AJ13: =IF(Setup!$B$10="",0,IF(I13="",0,IF(ISNUMBER(I13),I13,1))) | AK13: =IF(Setup!$B$11="",0,IF(J13="",0,IF(ISNUMBER(J13),J13,1))) | AL13: =IF(Setup!$B$12="",0,IF(K13="",0,IF(ISNUMBER(K13),K13,1))) | AM13: =IF(Setup!$B$13="",0,IF(L13="",0,IF(ISNUMBER(L13),L13,1))) | AN13: =IF(Setup!$B$14="",0,IF(M13="",0,IF(ISNUMBER(M13),M13,1))) | AO13: =IF(Setup!$B$15="",0,IF(N13="",0,IF(ISNUMBER(N13),N13,1))) | AP13: =IF(Setup!$B$16="",0,IF(O13="",0,IF(ISNUMBER(O13),O13,1))) | AQ13: =IF(Setup!$B$17="",0,IF(P13="",0,IF(ISNUMBER(P13),P13,1))) | AR13: =IF(Setup!$B$18="",0,IF(Q13="",0,IF(ISNUMBER(Q13),Q13,1))) | AS13: =IF(Setup!$B$19="",0,IF(R13="",0,IF(ISNUMBER(R13),R13,1))) | AT13: =IF(Setup!$B$20="",0,IF(S13="",0,IF(ISNUMBER(S13),S13,1)))
B14: 46277 | C14: Sintra train and palace | D14: Activities | E14: 115 | F14: EUR | G14: Dev | T14: =IF(N(E14)=0,"",E14*IF(F14="",1,IFERROR(INDEX(Setup!$E$9:$E$18,MATCH(F14,Setup!$D$9:$D$18,0)),0))) | U14: =IF(T14="","",IF(V14=0,"Everyone",IF(COUNTIF(AI14:AT14,">0")=COUNTIF(Setup!$B$9:$B$20,"?*"),"Everyone",COUNTIF(AI14:AT14,">0")&IF(COUNTIF(AI14:AT14,">0")=1," person"," people")))) | V14: =SUM(AI14:AT14) | W14: =IF(OR(T14="",Setup!$B$9=""),0,IF(V14=0,T14/COUNTIF(Setup!$B$9:$B$20,"?*"),T14*AI14/V14)) | X14: =IF(OR(T14="",Setup!$B$10=""),0,IF(V14=0,T14/COUNTIF(Setup!$B$9:$B$20,"?*"),T14*AJ14/V14)) | Y14: =IF(OR(T14="",Setup!$B$11=""),0,IF(V14=0,T14/COUNTIF(Setup!$B$9:$B$20,"?*"),T14*AK14/V14)) | Z14: =IF(OR(T14="",Setup!$B$12=""),0,IF(V14=0,T14/COUNTIF(Setup!$B$9:$B$20,"?*"),T14*AL14/V14)) | AA14: =IF(OR(T14="",Setup!$B$13=""),0,IF(V14=0,T14/COUNTIF(Setup!$B$9:$B$20,"?*"),T14*AM14/V14)) | AB14: =IF(OR(T14="",Setup!$B$14=""),0,IF(V14=0,T14/COUNTIF(Setup!$B$9:$B$20,"?*"),T14*AN14/V14)) | AC14: =IF(OR(T14="",Setup!$B$15=""),0,IF(V14=0,T14/COUNTIF(Setup!$B$9:$B$20,"?*"),T14*AO14/V14)) | AD14: =IF(OR(T14="",Setup!$B$16=""),0,IF(V14=0,T14/COUNTIF(Setup!$B$9:$B$20,"?*"),T14*AP14/V14)) | AE14: =IF(OR(T14="",Setup!$B$17=""),0,IF(V14=0,T14/COUNTIF(Setup!$B$9:$B$20,"?*"),T14*AQ14/V14)) | AF14: =IF(OR(T14="",Setup!$B$18=""),0,IF(V14=0,T14/COUNTIF(Setup!$B$9:$B$20,"?*"),T14*AR14/V14)) | AG14: =IF(OR(T14="",Setup!$B$19=""),0,IF(V14=0,T14/COUNTIF(Setup!$B$9:$B$20,"?*"),T14*AS14/V14)) | AH14: =IF(OR(T14="",Setup!$B$20=""),0,IF(V14=0,T14/COUNTIF(Setup!$B$9:$B$20,"?*"),T14*AT14/V14)) | AI14: =IF(Setup!$B$9="",0,IF(H14="",0,IF(ISNUMBER(H14),H14,1))) | AJ14: =IF(Setup!$B$10="",0,IF(I14="",0,IF(ISNUMBER(I14),I14,1))) | AK14: =IF(Setup!$B$11="",0,IF(J14="",0,IF(ISNUMBER(J14),J14,1))) | AL14: =IF(Setup!$B$12="",0,IF(K14="",0,IF(ISNUMBER(K14),K14,1))) | AM14: =IF(Setup!$B$13="",0,IF(L14="",0,IF(ISNUMBER(L14),L14,1))) | AN14: =IF(Setup!$B$14="",0,IF(M14="",0,IF(ISNUMBER(M14),M14,1))) | AO14: =IF(Setup!$B$15="",0,IF(N14="",0,IF(ISNUMBER(N14),N14,1))) | AP14: =IF(Setup!$B$16="",0,IF(O14="",0,IF(ISNUMBER(O14),O14,1))) | AQ14: =IF(Setup!$B$17="",0,IF(P14="",0,IF(ISNUMBER(P14),P14,1))) | AR14: =IF(Setup!$B$18="",0,IF(Q14="",0,IF(ISNUMBER(Q14),Q14,1))) | AS14: =IF(Setup!$B$19="",0,IF(R14="",0,IF(ISNUMBER(R14),R14,1))) | AT14: =IF(Setup!$B$20="",0,IF(S14="",0,IF(ISNUMBER(S14),S14,1)))
B15: 46277 | C15: Surf lesson | D15: Activities | E15: 90 | F15: EUR | G15: Ben | I15: x | K15: x | T15: =IF(N(E15)=0,"",E15*IF(F15="",1,IFERROR(INDEX(Setup!$E$9:$E$18,MATCH(F15,Setup!$D$9:$D$18,0)),0))) | U15: =IF(T15="","",IF(V15=0,"Everyone",IF(COUNTIF(AI15:AT15,">0")=COUNTIF(Setup!$B$9:$B$20,"?*"),"Everyone",COUNTIF(AI15:AT15,">0")&IF(COUNTIF(AI15:AT15,">0")=1," person"," people")))) | V15: =SUM(AI15:AT15) | W15: =IF(OR(T15="",Setup!$B$9=""),0,IF(V15=0,T15/COUNTIF(Setup!$B$9:$B$20,"?*"),T15*AI15/V15)) | X15: =IF(OR(T15="",Setup!$B$10=""),0,IF(V15=0,T15/COUNTIF(Setup!$B$9:$B$20,"?*"),T15*AJ15/V15)) | Y15: =IF(OR(T15="",Setup!$B$11=""),0,IF(V15=0,T15/COUNTIF(Setup!$B$9:$B$20,"?*"),T15*AK15/V15)) | Z15: =IF(OR(T15="",Setup!$B$12=""),0,IF(V15=0,T15/COUNTIF(Setup!$B$9:$B$20,"?*"),T15*AL15/V15)) | AA15: =IF(OR(T15="",Setup!$B$13=""),0,IF(V15=0,T15/COUNTIF(Setup!$B$9:$B$20,"?*"),T15*AM15/V15)) | AB15: =IF(OR(T15="",Setup!$B$14=""),0,IF(V15=0,T15/COUNTIF(Setup!$B$9:$B$20,"?*"),T15*AN15/V15)) | AC15: =IF(OR(T15="",Setup!$B$15=""),0,IF(V15=0,T15/COUNTIF(Setup!$B$9:$B$20,"?*"),T15*AO15/V15)) | AD15: =IF(OR(T15="",Setup!$B$16=""),0,IF(V15=0,T15/COUNTIF(Setup!$B$9:$B$20,"?*"),T15*AP15/V15)) | AE15: =IF(OR(T15="",Setup!$B$17=""),0,IF(V15=0,T15/COUNTIF(Setup!$B$9:$B$20,"?*"),T15*AQ15/V15)) | AF15: =IF(OR(T15="",Setup!$B$18=""),0,IF(V15=0,T15/COUNTIF(Setup!$B$9:$B$20,"?*"),T15*AR15/V15)) | AG15: =IF(OR(T15="",Setup!$B$19=""),0,IF(V15=0,T15/COUNTIF(Setup!$B$9:$B$20,"?*"),T15*AS15/V15)) | AH15: =IF(OR(T15="",Setup!$B$20=""),0,IF(V15=0,T15/COUNTIF(Setup!$B$9:$B$20,"?*"),T15*AT15/V15)) | AI15: =IF(Setup!$B$9="",0,IF(H15="",0,IF(ISNUMBER(H15),H15,1))) | AJ15: =IF(Setup!$B$10="",0,IF(I15="",0,IF(ISNUMBER(I15),I15,1))) | AK15: =IF(Setup!$B$11="",0,IF(J15="",0,IF(ISNUMBER(J15),J15,1))) | AL15: =IF(Setup!$B$12="",0,IF(K15="",0,IF(ISNUMBER(K15),K15,1))) | AM15: =IF(Setup!$B$13="",0,IF(L15="",0,IF(ISNUMBER(L15),L15,1))) | AN15: =IF(Setup!$B$14="",0,IF(M15="",0,IF(ISNUMBER(M15),M15,1))) | AO15: =IF(Setup!$B$15="",0,IF(N15="",0,IF(ISNUMBER(N15),N15,1))) | AP15: =IF(Setup!$B$16="",0,IF(O15="",0,IF(ISNUMBER(O15),O15,1))) | AQ15: =IF(Setup!$B$17="",0,IF(P15="",0,IF(ISNUMBER(P15),P15,1))) | AR15: =IF(Setup!$B$18="",0,IF(Q15="",0,IF(ISNUMBER(Q15),Q15,1))) | AS15: =IF(Setup!$B$19="",0,IF(R15="",0,IF(ISNUMBER(R15),R15,1))) | AT15: =IF(Setup!$B$20="",0,IF(S15="",0,IF(ISNUMBER(S15),S15,1)))
B16: 46277 | C16: Pastries in Belem | D16: Food | E16: 21.6 | F16: EUR | G16: Emma | T16: =IF(N(E16)=0,"",E16*IF(F16="",1,IFERROR(INDEX(Setup!$E$9:$E$18,MATCH(F16,Setup!$D$9:$D$18,0)),0))) | U16: =IF(T16="","",IF(V16=0,"Everyone",IF(COUNTIF(AI16:AT16,">0")=COUNTIF(Setup!$B$9:$B$20,"?*"),"Everyone",COUNTIF(AI16:AT16,">0")&IF(COUNTIF(AI16:AT16,">0")=1," person"," people")))) | V16: =SUM(AI16:AT16) | W16: =IF(OR(T16="",Setup!$B$9=""),0,IF(V16=0,T16/COUNTIF(Setup!$B$9:$B$20,"?*"),T16*AI16/V16)) | X16: =IF(OR(T16="",Setup!$B$10=""),0,IF(V16=0,T16/COUNTIF(Setup!$B$9:$B$20,"?*"),T16*AJ16/V16)) | Y16: =IF(OR(T16="",Setup!$B$11=""),0,IF(V16=0,T16/COUNTIF(Setup!$B$9:$B$20,"?*"),T16*AK16/V16)) | Z16: =IF(OR(T16="",Setup!$B$12=""),0,IF(V16=0,T16/COUNTIF(Setup!$B$9:$B$20,"?*"),T16*AL16/V16)) | AA16: =IF(OR(T16="",Setup!$B$13=""),0,IF(V16=0,T16/COUNTIF(Setup!$B$9:$B$20,"?*"),T16*AM16/V16)) | AB16: =IF(OR(T16="",Setup!$B$14=""),0,IF(V16=0,T16/COUNTIF(Setup!$B$9:$B$20,"?*"),T16*AN16/V16)) | AC16: =IF(OR(T16="",Setup!$B$15=""),0,IF(V16=0,T16/COUNTIF(Setup!$B$9:$B$20,"?*"),T16*AO16/V16)) | AD16: =IF(OR(T16="",Setup!$B$16=""),0,IF(V16=0,T16/COUNTIF(Setup!$B$9:$B$20,"?*"),T16*AP16/V16)) | AE16: =IF(OR(T16="",Setup!$B$17=""),0,IF(V16=0,T16/COUNTIF(Setup!$B$9:$B$20,"?*"),T16*AQ16/V16)) | AF16: =IF(OR(T16="",Setup!$B$18=""),0,IF(V16=0,T16/COUNTIF(Setup!$B$9:$B$20,"?*"),T16*AR16/V16)) | AG16: =IF(OR(T16="",Setup!$B$19=""),0,IF(V16=0,T16/COUNTIF(Setup!$B$9:$B$20,"?*"),T16*AS16/V16)) | AH16: =IF(OR(T16="",Setup!$B$20=""),0,IF(V16=0,T16/COUNTIF(Setup!$B$9:$B$20,"?*"),T16*AT16/V16)) | AI16: =IF(Setup!$B$9="",0,IF(H16="",0,IF(ISNUMBER(H16),H16,1))) | AJ16: =IF(Setup!$B$10="",0,IF(I16="",0,IF(ISNUMBER(I16),I16,1))) | AK16: =IF(Setup!$B$11="",0,IF(J16="",0,IF(ISNUMBER(J16),J16,1))) | AL16: =IF(Setup!$B$12="",0,IF(K16="",0,IF(ISNUMBER(K16),K16,1))) | AM16: =IF(Setup!$B$13="",0,IF(L16="",0,IF(ISNUMBER(L16),L16,1))) | AN16: =IF(Setup!$B$14="",0,IF(M16="",0,IF(ISNUMBER(M16),M16,1))) | AO16: =IF(Setup!$B$15="",0,IF(N16="",0,IF(ISNUMBER(N16),N16,1))) | AP16: =IF(Setup!$B$16="",0,IF(O16="",0,IF(ISNUMBER(O16),O16,1))) | AQ16: =IF(Setup!$B$17="",0,IF(P16="",0,IF(ISNUMBER(P16),P16,1))) | AR16: =IF(Setup!$B$18="",0,IF(Q16="",0,IF(ISNUMBER(Q16),Q16,1))) | AS16: =IF(Setup!$B$19="",0,IF(R16="",0,IF(ISNUMBER(R16),R16,1))) | AT16: =IF(Setup!$B$20="",0,IF(S16="",0,IF(ISNUMBER(S16),S16,1)))
B17: 46277 | C17: Dinner | D17: Food | E17: 128 | F17: EUR | G17: Ana | T17: =IF(N(E17)=0,"",E17*IF(F17="",1,IFERROR(INDEX(Setup!$E$9:$E$18,MATCH(F17,Setup!$D$9:$D$18,0)),0))) | U17: =IF(T17="","",IF(V17=0,"Everyone",IF(COUNTIF(AI17:AT17,">0")=COUNTIF(Setup!$B$9:$B$20,"?*"),"Everyone",COUNTIF(AI17:AT17,">0")&IF(COUNTIF(AI17:AT17,">0")=1," person"," people")))) | V17: =SUM(AI17:AT17) | W17: =IF(OR(T17="",Setup!$B$9=""),0,IF(V17=0,T17/COUNTIF(Setup!$B$9:$B$20,"?*"),T17*AI17/V17)) | X17: =IF(OR(T17="",Setup!$B$10=""),0,IF(V17=0,T17/COUNTIF(Setup!$B$9:$B$20,"?*"),T17*AJ17/V17)) | Y17: =IF(OR(T17="",Setup!$B$11=""),0,IF(V17=0,T17/COUNTIF(Setup!$B$9:$B$20,"?*"),T17*AK17/V17)) | Z17: =IF(OR(T17="",Setup!$B$12=""),0,IF(V17=0,T17/COUNTIF(Setup!$B$9:$B$20,"?*"),T17*AL17/V17)) | AA17: =IF(OR(T17="",Setup!$B$13=""),0,IF(V17=0,T17/COUNTIF(Setup!$B$9:$B$20,"?*"),T17*AM17/V17)) | AB17: =IF(OR(T17="",Setup!$B$14=""),0,IF(V17=0,T17/COUNTIF(Setup!$B$9:$B$20,"?*"),T17*AN17/V17)) | AC17: =IF(OR(T17="",Setup!$B$15=""),0,IF(V17=0,T17/COUNTIF(Setup!$B$9:$B$20,"?*"),T17*AO17/V17)) | AD17: =IF(OR(T17="",Setup!$B$16=""),0,IF(V17=0,T17/COUNTIF(Setup!$B$9:$B$20,"?*"),T17*AP17/V17)) | AE17: =IF(OR(T17="",Setup!$B$17=""),0,IF(V17=0,T17/COUNTIF(Setup!$B$9:$B$20,"?*"),T17*AQ17/V17)) | AF17: =IF(OR(T17="",Setup!$B$18=""),0,IF(V17=0,T17/COUNTIF(Setup!$B$9:$B$20,"?*"),T17*AR17/V17)) | AG17: =IF(OR(T17="",Setup!$B$19=""),0,IF(V17=0,T17/COUNTIF(Setup!$B$9:$B$20,"?*"),T17*AS17/V17)) | AH17: =IF(OR(T17="",Setup!$B$20=""),0,IF(V17=0,T17/COUNTIF(Setup!$B$9:$B$20,"?*"),T17*AT17/V17)) | AI17: =IF(Setup!$B$9="",0,IF(H17="",0,IF(ISNUMBER(H17),H17,1))) | AJ17: =IF(Setup!$B$10="",0,IF(I17="",0,IF(ISNUMBER(I17),I17,1))) | AK17: =IF(Setup!$B$11="",0,IF(J17="",0,IF(ISNUMBER(J17),J17,1))) | AL17: =IF(Setup!$B$12="",0,IF(K17="",0,IF(ISNUMBER(K17),K17,1))) | AM17: =IF(Setup!$B$13="",0,IF(L17="",0,IF(ISNUMBER(L17),L17,1))) | AN17: =IF(Setup!$B$14="",0,IF(M17="",0,IF(ISNUMBER(M17),M17,1))) | AO17: =IF(Setup!$B$15="",0,IF(N17="",0,IF(ISNUMBER(N17),N17,1))) | AP17: =IF(Setup!$B$16="",0,IF(O17="",0,IF(ISNUMBER(O17),O17,1))) | AQ17: =IF(Setup!$B$17="",0,IF(P17="",0,IF(ISNUMBER(P17),P17,1))) | AR17: =IF(Setup!$B$18="",0,IF(Q17="",0,IF(ISNUMBER(Q17),Q17,1))) | AS17: =IF(Setup!$B$19="",0,IF(R17="",0,IF(ISNUMBER(R17),R17,1))) | AT17: =IF(Setup!$B$20="",0,IF(S17="",0,IF(ISNUMBER(S17),S17,1)))
B18: 46277 | C18: Ana pays Ben back | D18: Paying back | E18: 100 | F18: EUR | G18: Ana | I18: x | T18: =IF(N(E18)=0,"",E18*IF(F18="",1,IFERROR(INDEX(Setup!$E$9:$E$18,MATCH(F18,Setup!$D$9:$D$18,0)),0))) | U18: =IF(T18="","",IF(V18=0,"Everyone",IF(COUNTIF(AI18:AT18,">0")=COUNTIF(Setup!$B$9:$B$20,"?*"),"Everyone",COUNTIF(AI18:AT18,">0")&IF(COUNTIF(AI18:AT18,">0")=1," person"," people")))) | V18: =SUM(AI18:AT18) | W18: =IF(OR(T18="",Setup!$B$9=""),0,IF(V18=0,T18/COUNTIF(Setup!$B$9:$B$20,"?*"),T18*AI18/V18)) | X18: =IF(OR(T18="",Setup!$B$10=""),0,IF(V18=0,T18/COUNTIF(Setup!$B$9:$B$20,"?*"),T18*AJ18/V18)) | Y18: =IF(OR(T18="",Setup!$B$11=""),0,IF(V18=0,T18/COUNTIF(Setup!$B$9:$B$20,"?*"),T18*AK18/V18)) | Z18: =IF(OR(T18="",Setup!$B$12=""),0,IF(V18=0,T18/COUNTIF(Setup!$B$9:$B$20,"?*"),T18*AL18/V18)) | AA18: =IF(OR(T18="",Setup!$B$13=""),0,IF(V18=0,T18/COUNTIF(Setup!$B$9:$B$20,"?*"),T18*AM18/V18)) | AB18: =IF(OR(T18="",Setup!$B$14=""),0,IF(V18=0,T18/COUNTIF(Setup!$B$9:$B$20,"?*"),T18*AN18/V18)) | AC18: =IF(OR(T18="",Setup!$B$15=""),0,IF(V18=0,T18/COUNTIF(Setup!$B$9:$B$20,"?*"),T18*AO18/V18)) | AD18: =IF(OR(T18="",Setup!$B$16=""),0,IF(V18=0,T18/COUNTIF(Setup!$B$9:$B$20,"?*"),T18*AP18/V18)) | AE18: =IF(OR(T18="",Setup!$B$17=""),0,IF(V18=0,T18/COUNTIF(Setup!$B$9:$B$20,"?*"),T18*AQ18/V18)) | AF18: =IF(OR(T18="",Setup!$B$18=""),0,IF(V18=0,T18/COUNTIF(Setup!$B$9:$B$20,"?*"),T18*AR18/V18)) | AG18: =IF(OR(T18="",Setup!$B$19=""),0,IF(V18=0,T18/COUNTIF(Setup!$B$9:$B$20,"?*"),T18*AS18/V18)) | AH18: =IF(OR(T18="",Setup!$B$20=""),0,IF(V18=0,T18/COUNTIF(Setup!$B$9:$B$20,"?*"),T18*AT18/V18)) | AI18: =IF(Setup!$B$9="",0,IF(H18="",0,IF(ISNUMBER(H18),H18,1))) | AJ18: =IF(Setup!$B$10="",0,IF(I18="",0,IF(ISNUMBER(I18),I18,1))) | AK18: =IF(Setup!$B$11="",0,IF(J18="",0,IF(ISNUMBER(J18),J18,1))) | AL18: =IF(Setup!$B$12="",0,IF(K18="",0,IF(ISNUMBER(K18),K18,1))) | AM18: =IF(Setup!$B$13="",0,IF(L18="",0,IF(ISNUMBER(L18),L18,1))) | AN18: =IF(Setup!$B$14="",0,IF(M18="",0,IF(ISNUMBER(M18),M18,1))) | AO18: =IF(Setup!$B$15="",0,IF(N18="",0,IF(ISNUMBER(N18),N18,1))) | AP18: =IF(Setup!$B$16="",0,IF(O18="",0,IF(ISNUMBER(O18),O18,1))) | AQ18: =IF(Setup!$B$17="",0,IF(P18="",0,IF(ISNUMBER(P18),P18,1))) | AR18: =IF(Setup!$B$18="",0,IF(Q18="",0,IF(ISNUMBER(Q18),Q18,1))) | AS18: =IF(Setup!$B$19="",0,IF(R18="",0,IF(ISNUMBER(R18),R18,1))) | AT18: =IF(Setup!$B$20="",0,IF(S18="",0,IF(ISNUMBER(S18),S18,1)))
B19: 46278 | C19: Train to Porto | D19: Transport | E19: 125 | F19: EUR | G19: Dev | T19: =IF(N(E19)=0,"",E19*IF(F19="",1,IFERROR(INDEX(Setup!$E$9:$E$18,MATCH(F19,Setup!$D$9:$D$18,0)),0))) | U19: =IF(T19="","",IF(V19=0,"Everyone",IF(COUNTIF(AI19:AT19,">0")=COUNTIF(Setup!$B$9:$B$20,"?*"),"Everyone",COUNTIF(AI19:AT19,">0")&IF(COUNTIF(AI19:AT19,">0")=1," person"," people")))) | V19: =SUM(AI19:AT19) | W19: =IF(OR(T19="",Setup!$B$9=""),0,IF(V19=0,T19/COUNTIF(Setup!$B$9:$B$20,"?*"),T19*AI19/V19)) | X19: =IF(OR(T19="",Setup!$B$10=""),0,IF(V19=0,T19/COUNTIF(Setup!$B$9:$B$20,"?*"),T19*AJ19/V19)) | Y19: =IF(OR(T19="",Setup!$B$11=""),0,IF(V19=0,T19/COUNTIF(Setup!$B$9:$B$20,"?*"),T19*AK19/V19)) | Z19: =IF(OR(T19="",Setup!$B$12=""),0,IF(V19=0,T19/COUNTIF(Setup!$B$9:$B$20,"?*"),T19*AL19/V19)) | AA19: =IF(OR(T19="",Setup!$B$13=""),0,IF(V19=0,T19/COUNTIF(Setup!$B$9:$B$20,"?*"),T19*AM19/V19)) | AB19: =IF(OR(T19="",Setup!$B$14=""),0,IF(V19=0,T19/COUNTIF(Setup!$B$9:$B$20,"?*"),T19*AN19/V19)) | AC19: =IF(OR(T19="",Setup!$B$15=""),0,IF(V19=0,T19/COUNTIF(Setup!$B$9:$B$20,"?*"),T19*AO19/V19)) | AD19: =IF(OR(T19="",Setup!$B$16=""),0,IF(V19=0,T19/COUNTIF(Setup!$B$9:$B$20,"?*"),T19*AP19/V19)) | AE19: =IF(OR(T19="",Setup!$B$17=""),0,IF(V19=0,T19/COUNTIF(Setup!$B$9:$B$20,"?*"),T19*AQ19/V19)) | AF19: =IF(OR(T19="",Setup!$B$18=""),0,IF(V19=0,T19/COUNTIF(Setup!$B$9:$B$20,"?*"),T19*AR19/V19)) | AG19: =IF(OR(T19="",Setup!$B$19=""),0,IF(V19=0,T19/COUNTIF(Setup!$B$9:$B$20,"?*"),T19*AS19/V19)) | AH19: =IF(OR(T19="",Setup!$B$20=""),0,IF(V19=0,T19/COUNTIF(Setup!$B$9:$B$20,"?*"),T19*AT19/V19)) | AI19: =IF(Setup!$B$9="",0,IF(H19="",0,IF(ISNUMBER(H19),H19,1))) | AJ19: =IF(Setup!$B$10="",0,IF(I19="",0,IF(ISNUMBER(I19),I19,1))) | AK19: =IF(Setup!$B$11="",0,IF(J19="",0,IF(ISNUMBER(J19),J19,1))) | AL19: =IF(Setup!$B$12="",0,IF(K19="",0,IF(ISNUMBER(K19),K19,1))) | AM19: =IF(Setup!$B$13="",0,IF(L19="",0,IF(ISNUMBER(L19),L19,1))) | AN19: =IF(Setup!$B$14="",0,IF(M19="",0,IF(ISNUMBER(M19),M19,1))) | AO19: =IF(Setup!$B$15="",0,IF(N19="",0,IF(ISNUMBER(N19),N19,1))) | AP19: =IF(Setup!$B$16="",0,IF(O19="",0,IF(ISNUMBER(O19),O19,1))) | AQ19: =IF(Setup!$B$17="",0,IF(P19="",0,IF(ISNUMBER(P19),P19,1))) | AR19: =IF(Setup!$B$18="",0,IF(Q19="",0,IF(ISNUMBER(Q19),Q19,1))) | AS19: =IF(Setup!$B$19="",0,IF(R19="",0,IF(ISNUMBER(R19),R19,1))) | AT19: =IF(Setup!$B$20="",0,IF(S19="",0,IF(ISNUMBER(S19),S19,1)))
B20: 46278 | C20: Hotel in Porto, 3 nights | D20: Lodging | E20: 540 | F20: EUR | G20: Chloe | T20: =IF(N(E20)=0,"",E20*IF(F20="",1,IFERROR(INDEX(Setup!$E$9:$E$18,MATCH(F20,Setup!$D$9:$D$18,0)),0))) | U20: =IF(T20="","",IF(V20=0,"Everyone",IF(COUNTIF(AI20:AT20,">0")=COUNTIF(Setup!$B$9:$B$20,"?*"),"Everyone",COUNTIF(AI20:AT20,">0")&IF(COUNTIF(AI20:AT20,">0")=1," person"," people")))) | V20: =SUM(AI20:AT20) | W20: =IF(OR(T20="",Setup!$B$9=""),0,IF(V20=0,T20/COUNTIF(Setup!$B$9:$B$20,"?*"),T20*AI20/V20)) | X20: =IF(OR(T20="",Setup!$B$10=""),0,IF(V20=0,T20/COUNTIF(Setup!$B$9:$B$20,"?*"),T20*AJ20/V20)) | Y20: =IF(OR(T20="",Setup!$B$11=""),0,IF(V20=0,T20/COUNTIF(Setup!$B$9:$B$20,"?*"),T20*AK20/V20)) | Z20: =IF(OR(T20="",Setup!$B$12=""),0,IF(V20=0,T20/COUNTIF(Setup!$B$9:$B$20,"?*"),T20*AL20/V20)) | AA20: =IF(OR(T20="",Setup!$B$13=""),0,IF(V20=0,T20/COUNTIF(Setup!$B$9:$B$20,"?*"),T20*AM20/V20)) | AB20: =IF(OR(T20="",Setup!$B$14=""),0,IF(V20=0,T20/COUNTIF(Setup!$B$9:$B$20,"?*"),T20*AN20/V20)) | AC20: =IF(OR(T20="",Setup!$B$15=""),0,IF(V20=0,T20/COUNTIF(Setup!$B$9:$B$20,"?*"),T20*AO20/V20)) | AD20: =IF(OR(T20="",Setup!$B$16=""),0,IF(V20=0,T20/COUNTIF(Setup!$B$9:$B$20,"?*"),T20*AP20/V20)) | AE20: =IF(OR(T20="",Setup!$B$17=""),0,IF(V20=0,T20/COUNTIF(Setup!$B$9:$B$20,"?*"),T20*AQ20/V20)) | AF20: =IF(OR(T20="",Setup!$B$18=""),0,IF(V20=0,T20/COUNTIF(Setup!$B$9:$B$20,"?*"),T20*AR20/V20)) | AG20: =IF(OR(T20="",Setup!$B$19=""),0,IF(V20=0,T20/COUNTIF(Setup!$B$9:$B$20,"?*"),T20*AS20/V20)) | AH20: =IF(OR(T20="",Setup!$B$20=""),0,IF(V20=0,T20/COUNTIF(Setup!$B$9:$B$20,"?*"),T20*AT20/V20)) | AI20: =IF(Setup!$B$9="",0,IF(H20="",0,IF(ISNUMBER(H20),H20,1))) | AJ20: =IF(Setup!$B$10="",0,IF(I20="",0,IF(ISNUMBER(I20),I20,1))) | AK20: =IF(Setup!$B$11="",0,IF(J20="",0,IF(ISNUMBER(J20),J20,1))) | AL20: =IF(Setup!$B$12="",0,IF(K20="",0,IF(ISNUMBER(K20),K20,1))) | AM20: =IF(Setup!$B$13="",0,IF(L20="",0,IF(ISNUMBER(L20),L20,1))) | AN20: =IF(Setup!$B$14="",0,IF(M20="",0,IF(ISNUMBER(M20),M20,1))) | AO20: =IF(Setup!$B$15="",0,IF(N20="",0,IF(ISNUMBER(N20),N20,1))) | AP20: =IF(Setup!$B$16="",0,IF(O20="",0,IF(ISNUMBER(O20),O20,1))) | AQ20: =IF(Setup!$B$17="",0,IF(P20="",0,IF(ISNUMBER(P20),P20,1))) | AR20: =IF(Setup!$B$18="",0,IF(Q20="",0,IF(ISNUMBER(Q20),Q20,1))) | AS20: =IF(Setup!$B$19="",0,IF(R20="",0,IF(ISNUMBER(R20),R20,1))) | AT20: =IF(Setup!$B$20="",0,IF(S20="",0,IF(ISNUMBER(S20),S20,1)))
B21: 46278 | C21: Dinner by the river | D21: Food | E21: 154 | F21: EUR | G21: Emma | T21: =IF(N(E21)=0,"",E21*IF(F21="",1,IFERROR(INDEX(Setup!$E$9:$E$18,MATCH(F21,Setup!$D$9:$D$18,0)),0))) | U21: =IF(T21="","",IF(V21=0,"Everyone",IF(COUNTIF(AI21:AT21,">0")=COUNTIF(Setup!$B$9:$B$20,"?*"),"Everyone",COUNTIF(AI21:AT21,">0")&IF(COUNTIF(AI21:AT21,">0")=1," person"," people")))) | V21: =SUM(AI21:AT21) | W21: =IF(OR(T21="",Setup!$B$9=""),0,IF(V21=0,T21/COUNTIF(Setup!$B$9:$B$20,"?*"),T21*AI21/V21)) | X21: =IF(OR(T21="",Setup!$B$10=""),0,IF(V21=0,T21/COUNTIF(Setup!$B$9:$B$20,"?*"),T21*AJ21/V21)) | Y21: =IF(OR(T21="",Setup!$B$11=""),0,IF(V21=0,T21/COUNTIF(Setup!$B$9:$B$20,"?*"),T21*AK21/V21)) | Z21: =IF(OR(T21="",Setup!$B$12=""),0,IF(V21=0,T21/COUNTIF(Setup!$B$9:$B$20,"?*"),T21*AL21/V21)) | AA21: =IF(OR(T21="",Setup!$B$13=""),0,IF(V21=0,T21/COUNTIF(Setup!$B$9:$B$20,"?*"),T21*AM21/V21)) | AB21: =IF(OR(T21="",Setup!$B$14=""),0,IF(V21=0,T21/COUNTIF(Setup!$B$9:$B$20,"?*"),T21*AN21/V21)) | AC21: =IF(OR(T21="",Setup!$B$15=""),0,IF(V21=0,T21/COUNTIF(Setup!$B$9:$B$20,"?*"),T21*AO21/V21)) | AD21: =IF(OR(T21="",Setup!$B$16=""),0,IF(V21=0,T21/COUNTIF(Setup!$B$9:$B$20,"?*"),T21*AP21/V21)) | AE21: =IF(OR(T21="",Setup!$B$17=""),0,IF(V21=0,T21/COUNTIF(Setup!$B$9:$B$20,"?*"),T21*AQ21/V21)) | AF21: =IF(OR(T21="",Setup!$B$18=""),0,IF(V21=0,T21/COUNTIF(Setup!$B$9:$B$20,"?*"),T21*AR21/V21)) | AG21: =IF(OR(T21="",Setup!$B$19=""),0,IF(V21=0,T21/COUNTIF(Setup!$B$9:$B$20,"?*"),T21*AS21/V21)) | AH21: =IF(OR(T21="",Setup!$B$20=""),0,IF(V21=0,T21/COUNTIF(Setup!$B$9:$B$20,"?*"),T21*AT21/V21)) | AI21: =IF(Setup!$B$9="",0,IF(H21="",0,IF(ISNUMBER(H21),H21,1))) | AJ21: =IF(Setup!$B$10="",0,IF(I21="",0,IF(ISNUMBER(I21),I21,1))) | AK21: =IF(Setup!$B$11="",0,IF(J21="",0,IF(ISNUMBER(J21),J21,1))) | AL21: =IF(Setup!$B$12="",0,IF(K21="",0,IF(ISNUMBER(K21),K21,1))) | AM21: =IF(Setup!$B$13="",0,IF(L21="",0,IF(ISNUMBER(L21),L21,1))) | AN21: =IF(Setup!$B$14="",0,IF(M21="",0,IF(ISNUMBER(M21),M21,1))) | AO21: =IF(Setup!$B$15="",0,IF(N21="",0,IF(ISNUMBER(N21),N21,1))) | AP21: =IF(Setup!$B$16="",0,IF(O21="",0,IF(ISNUMBER(O21),O21,1))) | AQ21: =IF(Setup!$B$17="",0,IF(P21="",0,IF(ISNUMBER(P21),P21,1))) | AR21: =IF(Setup!$B$18="",0,IF(Q21="",0,IF(ISNUMBER(Q21),Q21,1))) | AS21: =IF(Setup!$B$19="",0,IF(R21="",0,IF(ISNUMBER(R21),R21,1))) | AT21: =IF(Setup!$B$20="",0,IF(S21="",0,IF(ISNUMBER(S21),S21,1)))
B22: 46279 | C22: Port wine tasting | D22: Activities | E22: 75 | F22: EUR | G22: Ben | T22: =IF(N(E22)=0,"",E22*IF(F22="",1,IFERROR(INDEX(Setup!$E$9:$E$18,MATCH(F22,Setup!$D$9:$D$18,0)),0))) | U22: =IF(T22="","",IF(V22=0,"Everyone",IF(COUNTIF(AI22:AT22,">0")=COUNTIF(Setup!$B$9:$B$20,"?*"),"Everyone",COUNTIF(AI22:AT22,">0")&IF(COUNTIF(AI22:AT22,">0")=1," person"," people")))) | V22: =SUM(AI22:AT22) | W22: =IF(OR(T22="",Setup!$B$9=""),0,IF(V22=0,T22/COUNTIF(Setup!$B$9:$B$20,"?*"),T22*AI22/V22)) | X22: =IF(OR(T22="",Setup!$B$10=""),0,IF(V22=0,T22/COUNTIF(Setup!$B$9:$B$20,"?*"),T22*AJ22/V22)) | Y22: =IF(OR(T22="",Setup!$B$11=""),0,IF(V22=0,T22/COUNTIF(Setup!$B$9:$B$20,"?*"),T22*AK22/V22)) | Z22: =IF(OR(T22="",Setup!$B$12=""),0,IF(V22=0,T22/COUNTIF(Setup!$B$9:$B$20,"?*"),T22*AL22/V22)) | AA22: =IF(OR(T22="",Setup!$B$13=""),0,IF(V22=0,T22/COUNTIF(Setup!$B$9:$B$20,"?*"),T22*AM22/V22)) | AB22: =IF(OR(T22="",Setup!$B$14=""),0,IF(V22=0,T22/COUNTIF(Setup!$B$9:$B$20,"?*"),T22*AN22/V22)) | AC22: =IF(OR(T22="",Setup!$B$15=""),0,IF(V22=0,T22/COUNTIF(Setup!$B$9:$B$20,"?*"),T22*AO22/V22)) | AD22: =IF(OR(T22="",Setup!$B$16=""),0,IF(V22=0,T22/COUNTIF(Setup!$B$9:$B$20,"?*"),T22*AP22/V22)) | AE22: =IF(OR(T22="",Setup!$B$17=""),0,IF(V22=0,T22/COUNTIF(Setup!$B$9:$B$20,"?*"),T22*AQ22/V22)) | AF22: =IF(OR(T22="",Setup!$B$18=""),0,IF(V22=0,T22/COUNTIF(Setup!$B$9:$B$20,"?*"),T22*AR22/V22)) | AG22: =IF(OR(T22="",Setup!$B$19=""),0,IF(V22=0,T22/COUNTIF(Setup!$B$9:$B$20,"?*"),T22*AS22/V22)) | AH22: =IF(OR(T22="",Setup!$B$20=""),0,IF(V22=0,T22/COUNTIF(Setup!$B$9:$B$20,"?*"),T22*AT22/V22)) | AI22: =IF(Setup!$B$9="",0,IF(H22="",0,IF(ISNUMBER(H22),H22,1))) | AJ22: =IF(Setup!$B$10="",0,IF(I22="",0,IF(ISNUMBER(I22),I22,1))) | AK22: =IF(Setup!$B$11="",0,IF(J22="",0,IF(ISNUMBER(J22),J22,1))) | AL22: =IF(Setup!$B$12="",0,IF(K22="",0,IF(ISNUMBER(K22),K22,1))) | AM22: =IF(Setup!$B$13="",0,IF(L22="",0,IF(ISNUMBER(L22),L22,1))) | AN22: =IF(Setup!$B$14="",0,IF(M22="",0,IF(ISNUMBER(M22),M22,1))) | AO22: =IF(Setup!$B$15="",0,IF(N22="",0,IF(ISNUMBER(N22),N22,1))) | AP22: =IF(Setup!$B$16="",0,IF(O22="",0,IF(ISNUMBER(O22),O22,1))) | AQ22: =IF(Setup!$B$17="",0,IF(P22="",0,IF(ISNUMBER(P22),P22,1))) | AR22: =IF(Setup!$B$18="",0,IF(Q22="",0,IF(ISNUMBER(Q22),Q22,1))) | AS22: =IF(Setup!$B$19="",0,IF(R22="",0,IF(ISNUMBER(R22),R22,1))) | AT22: =IF(Setup!$B$20="",0,IF(S22="",0,IF(ISNUMBER(S22),S22,1)))
B23: 46279 | C23: Wine to take home | D23: Other | E23: 72 | F23: EUR | G23: Chloe | H23: 2 | J23: 1 | L23: 1 | T23: =IF(N(E23)=0,"",E23*IF(F23="",1,IFERROR(INDEX(Setup!$E$9:$E$18,MATCH(F23,Setup!$D$9:$D$18,0)),0))) | U23: =IF(T23="","",IF(V23=0,"Everyone",IF(COUNTIF(AI23:AT23,">0")=COUNTIF(Setup!$B$9:$B$20,"?*"),"Everyone",COUNTIF(AI23:AT23,">0")&IF(COUNTIF(AI23:AT23,">0")=1," person"," people")))) | V23: =SUM(AI23:AT23) | W23: =IF(OR(T23="",Setup!$B$9=""),0,IF(V23=0,T23/COUNTIF(Setup!$B$9:$B$20,"?*"),T23*AI23/V23)) | X23: =IF(OR(T23="",Setup!$B$10=""),0,IF(V23=0,T23/COUNTIF(Setup!$B$9:$B$20,"?*"),T23*AJ23/V23)) | Y23: =IF(OR(T23="",Setup!$B$11=""),0,IF(V23=0,T23/COUNTIF(Setup!$B$9:$B$20,"?*"),T23*AK23/V23)) | Z23: =IF(OR(T23="",Setup!$B$12=""),0,IF(V23=0,T23/COUNTIF(Setup!$B$9:$B$20,"?*"),T23*AL23/V23)) | AA23: =IF(OR(T23="",Setup!$B$13=""),0,IF(V23=0,T23/COUNTIF(Setup!$B$9:$B$20,"?*"),T23*AM23/V23)) | AB23: =IF(OR(T23="",Setup!$B$14=""),0,IF(V23=0,T23/COUNTIF(Setup!$B$9:$B$20,"?*"),T23*AN23/V23)) | AC23: =IF(OR(T23="",Setup!$B$15=""),0,IF(V23=0,T23/COUNTIF(Setup!$B$9:$B$20,"?*"),T23*AO23/V23)) | AD23: =IF(OR(T23="",Setup!$B$16=""),0,IF(V23=0,T23/COUNTIF(Setup!$B$9:$B$20,"?*"),T23*AP23/V23)) | AE23: =IF(OR(T23="",Setup!$B$17=""),0,IF(V23=0,T23/COUNTIF(Setup!$B$9:$B$20,"?*"),T23*AQ23/V23)) | AF23: =IF(OR(T23="",Setup!$B$18=""),0,IF(V23=0,T23/COUNTIF(Setup!$B$9:$B$20,"?*"),T23*AR23/V23)) | AG23: =IF(OR(T23="",Setup!$B$19=""),0,IF(V23=0,T23/COUNTIF(Setup!$B$9:$B$20,"?*"),T23*AS23/V23)) | AH23: =IF(OR(T23="",Setup!$B$20=""),0,IF(V23=0,T23/COUNTIF(Setup!$B$9:$B$20,"?*"),T23*AT23/V23)) | AI23: =IF(Setup!$B$9="",0,IF(H23="",0,IF(ISNUMBER(H23),H23,1))) | AJ23: =IF(Setup!$B$10="",0,IF(I23="",0,IF(ISNUMBER(I23),I23,1))) | AK23: =IF(Setup!$B$11="",0,IF(J23="",0,IF(ISNUMBER(J23),J23,1))) | AL23: =IF(Setup!$B$12="",0,IF(K23="",0,IF(ISNUMBER(K23),K23,1))) | AM23: =IF(Setup!$B$13="",0,IF(L23="",0,IF(ISNUMBER(L23),L23,1))) | AN23: =IF(Setup!$B$14="",0,IF(M23="",0,IF(ISNUMBER(M23),M23,1))) | AO23: =IF(Setup!$B$15="",0,IF(N23="",0,IF(ISNUMBER(N23),N23,1))) | AP23: =IF(Setup!$B$16="",0,IF(O23="",0,IF(ISNUMBER(O23),O23,1))) | AQ23: =IF(Setup!$B$17="",0,IF(P23="",0,IF(ISNUMBER(P23),P23,1))) | AR23: =IF(Setup!$B$18="",0,IF(Q23="",0,IF(ISNUMBER(Q23),Q23,1))) | AS23: =IF(Setup!$B$19="",0,IF(R23="",0,IF(ISNUMBER(R23),R23,1))) | AT23: =IF(Setup!$B$20="",0,IF(S23="",0,IF(ISNUMBER(S23),S23,1)))
B24: 46279 | C24: Bookshop tickets | D24: Activities | E24: 50 | F24: EUR | G24: Emma | T24: =IF(N(E24)=0,"",E24*IF(F24="",1,IFERROR(INDEX(Setup!$E$9:$E$18,MATCH(F24,Setup!$D$9:$D$18,0)),0))) | U24: =IF(T24="","",IF(V24=0,"Everyone",IF(COUNTIF(AI24:AT24,">0")=COUNTIF(Setup!$B$9:$B$20,"?*"),"Everyone",COUNTIF(AI24:AT24,">0")&IF(COUNTIF(AI24:AT24,">0")=1," person"," people")))) | V24: =SUM(AI24:AT24) | W24: =IF(OR(T24="",Setup!$B$9=""),0,IF(V24=0,T24/COUNTIF(Setup!$B$9:$B$20,"?*"),T24*AI24/V24)) | X24: =IF(OR(T24="",Setup!$B$10=""),0,IF(V24=0,T24/COUNTIF(Setup!$B$9:$B$20,"?*"),T24*AJ24/V24)) | Y24: =IF(OR(T24="",Setup!$B$11=""),0,IF(V24=0,T24/COUNTIF(Setup!$B$9:$B$20,"?*"),T24*AK24/V24)) | Z24: =IF(OR(T24="",Setup!$B$12=""),0,IF(V24=0,T24/COUNTIF(Setup!$B$9:$B$20,"?*"),T24*AL24/V24)) | AA24: =IF(OR(T24="",Setup!$B$13=""),0,IF(V24=0,T24/COUNTIF(Setup!$B$9:$B$20,"?*"),T24*AM24/V24)) | AB24: =IF(OR(T24="",Setup!$B$14=""),0,IF(V24=0,T24/COUNTIF(Setup!$B$9:$B$20,"?*"),T24*AN24/V24)) | AC24: =IF(OR(T24="",Setup!$B$15=""),0,IF(V24=0,T24/COUNTIF(Setup!$B$9:$B$20,"?*"),T24*AO24/V24)) | AD24: =IF(OR(T24="",Setup!$B$16=""),0,IF(V24=0,T24/COUNTIF(Setup!$B$9:$B$20,"?*"),T24*AP24/V24)) | AE24: =IF(OR(T24="",Setup!$B$17=""),0,IF(V24=0,T24/COUNTIF(Setup!$B$9:$B$20,"?*"),T24*AQ24/V24)) | AF24: =IF(OR(T24="",Setup!$B$18=""),0,IF(V24=0,T24/COUNTIF(Setup!$B$9:$B$20,"?*"),T24*AR24/V24)) | AG24: =IF(OR(T24="",Setup!$B$19=""),0,IF(V24=0,T24/COUNTIF(Setup!$B$9:$B$20,"?*"),T24*AS24/V24)) | AH24: =IF(OR(T24="",Setup!$B$20=""),0,IF(V24=0,T24/COUNTIF(Setup!$B$9:$B$20,"?*"),T24*AT24/V24)) | AI24: =IF(Setup!$B$9="",0,IF(H24="",0,IF(ISNUMBER(H24),H24,1))) | AJ24: =IF(Setup!$B$10="",0,IF(I24="",0,IF(ISNUMBER(I24),I24,1))) | AK24: =IF(Setup!$B$11="",0,IF(J24="",0,IF(ISNUMBER(J24),J24,1))) | AL24: =IF(Setup!$B$12="",0,IF(K24="",0,IF(ISNUMBER(K24),K24,1))) | AM24: =IF(Setup!$B$13="",0,IF(L24="",0,IF(ISNUMBER(L24),L24,1))) | AN24: =IF(Setup!$B$14="",0,IF(M24="",0,IF(ISNUMBER(M24),M24,1))) | AO24: =IF(Setup!$B$15="",0,IF(N24="",0,IF(ISNUMBER(N24),N24,1))) | AP24: =IF(Setup!$B$16="",0,IF(O24="",0,IF(ISNUMBER(O24),O24,1))) | AQ24: =IF(Setup!$B$17="",0,IF(P24="",0,IF(ISNUMBER(P24),P24,1))) | AR24: =IF(Setup!$B$18="",0,IF(Q24="",0,IF(ISNUMBER(Q24),Q24,1))) | AS24: =IF(Setup!$B$19="",0,IF(R24="",0,IF(ISNUMBER(R24),R24,1))) | AT24: =IF(Setup!$B$20="",0,IF(S24="",0,IF(ISNUMBER(S24),S24,1)))
B25: 46279 | C25: Lunch | D25: Food | E25: 67 | F25: EUR | G25: Dev | T25: =IF(N(E25)=0,"",E25*IF(F25="",1,IFERROR(INDEX(Setup!$E$9:$E$18,MATCH(F25,Setup!$D$9:$D$18,0)),0))) | U25: =IF(T25="","",IF(V25=0,"Everyone",IF(COUNTIF(AI25:AT25,">0")=COUNTIF(Setup!$B$9:$B$20,"?*"),"Everyone",COUNTIF(AI25:AT25,">0")&IF(COUNTIF(AI25:AT25,">0")=1," person"," people")))) | V25: =SUM(AI25:AT25) | W25: =IF(OR(T25="",Setup!$B$9=""),0,IF(V25=0,T25/COUNTIF(Setup!$B$9:$B$20,"?*"),T25*AI25/V25)) | X25: =IF(OR(T25="",Setup!$B$10=""),0,IF(V25=0,T25/COUNTIF(Setup!$B$9:$B$20,"?*"),T25*AJ25/V25)) | Y25: =IF(OR(T25="",Setup!$B$11=""),0,IF(V25=0,T25/COUNTIF(Setup!$B$9:$B$20,"?*"),T25*AK25/V25)) | Z25: =IF(OR(T25="",Setup!$B$12=""),0,IF(V25=0,T25/COUNTIF(Setup!$B$9:$B$20,"?*"),T25*AL25/V25)) | AA25: =IF(OR(T25="",Setup!$B$13=""),0,IF(V25=0,T25/COUNTIF(Setup!$B$9:$B$20,"?*"),T25*AM25/V25)) | AB25: =IF(OR(T25="",Setup!$B$14=""),0,IF(V25=0,T25/COUNTIF(Setup!$B$9:$B$20,"?*"),T25*AN25/V25)) | AC25: =IF(OR(T25="",Setup!$B$15=""),0,IF(V25=0,T25/COUNTIF(Setup!$B$9:$B$20,"?*"),T25*AO25/V25)) | AD25: =IF(OR(T25="",Setup!$B$16=""),0,IF(V25=0,T25/COUNTIF(Setup!$B$9:$B$20,"?*"),T25*AP25/V25)) | AE25: =IF(OR(T25="",Setup!$B$17=""),0,IF(V25=0,T25/COUNTIF(Setup!$B$9:$B$20,"?*"),T25*AQ25/V25)) | AF25: =IF(OR(T25="",Setup!$B$18=""),0,IF(V25=0,T25/COUNTIF(Setup!$B$9:$B$20,"?*"),T25*AR25/V25)) | AG25: =IF(OR(T25="",Setup!$B$19=""),0,IF(V25=0,T25/COUNTIF(Setup!$B$9:$B$20,"?*"),T25*AS25/V25)) | AH25: =IF(OR(T25="",Setup!$B$20=""),0,IF(V25=0,T25/COUNTIF(Setup!$B$9:$B$20,"?*"),T25*AT25/V25)) | AI25: =IF(Setup!$B$9="",0,IF(H25="",0,IF(ISNUMBER(H25),H25,1))) | AJ25: =IF(Setup!$B$10="",0,IF(I25="",0,IF(ISNUMBER(I25),I25,1))) | AK25: =IF(Setup!$B$11="",0,IF(J25="",0,IF(ISNUMBER(J25),J25,1))) | AL25: =IF(Setup!$B$12="",0,IF(K25="",0,IF(ISNUMBER(K25),K25,1))) | AM25: =IF(Setup!$B$13="",0,IF(L25="",0,IF(ISNUMBER(L25),L25,1))) | AN25: =IF(Setup!$B$14="",0,IF(M25="",0,IF(ISNUMBER(M25),M25,1))) | AO25: =IF(Setup!$B$15="",0,IF(N25="",0,IF(ISNUMBER(N25),N25,1))) | AP25: =IF(Setup!$B$16="",0,IF(O25="",0,IF(ISNUMBER(O25),O25,1))) | AQ25: =IF(Setup!$B$17="",0,IF(P25="",0,IF(ISNUMBER(P25),P25,1))) | AR25: =IF(Setup!$B$18="",0,IF(Q25="",0,IF(ISNUMBER(Q25),Q25,1))) | AS25: =IF(Setup!$B$19="",0,IF(R25="",0,IF(ISNUMBER(R25),R25,1))) | AT25: =IF(Setup!$B$20="",0,IF(S25="",0,IF(ISNUMBER(S25),S25,1)))
B26: 46279 | C26: Dinner | D26: Food | E26: 139 | F26: EUR | G26: Ben | T26: =IF(N(E26)=0,"",E26*IF(F26="",1,IFERROR(INDEX(Setup!$E$9:$E$18,MATCH(F26,Setup!$D$9:$D$18,0)),0))) | U26: =IF(T26="","",IF(V26=0,"Everyone",IF(COUNTIF(AI26:AT26,">0")=COUNTIF(Setup!$B$9:$B$20,"?*"),"Everyone",COUNTIF(AI26:AT26,">0")&IF(COUNTIF(AI26:AT26,">0")=1," person"," people")))) | V26: =SUM(AI26:AT26) | W26: =IF(OR(T26="",Setup!$B$9=""),0,IF(V26=0,T26/COUNTIF(Setup!$B$9:$B$20,"?*"),T26*AI26/V26)) | X26: =IF(OR(T26="",Setup!$B$10=""),0,IF(V26=0,T26/COUNTIF(Setup!$B$9:$B$20,"?*"),T26*AJ26/V26)) | Y26: =IF(OR(T26="",Setup!$B$11=""),0,IF(V26=0,T26/COUNTIF(Setup!$B$9:$B$20,"?*"),T26*AK26/V26)) | Z26: =IF(OR(T26="",Setup!$B$12=""),0,IF(V26=0,T26/COUNTIF(Setup!$B$9:$B$20,"?*"),T26*AL26/V26)) | AA26: =IF(OR(T26="",Setup!$B$13=""),0,IF(V26=0,T26/COUNTIF(Setup!$B$9:$B$20,"?*"),T26*AM26/V26)) | AB26: =IF(OR(T26="",Setup!$B$14=""),0,IF(V26=0,T26/COUNTIF(Setup!$B$9:$B$20,"?*"),T26*AN26/V26)) | AC26: =IF(OR(T26="",Setup!$B$15=""),0,IF(V26=0,T26/COUNTIF(Setup!$B$9:$B$20,"?*"),T26*AO26/V26)) | AD26: =IF(OR(T26="",Setup!$B$16=""),0,IF(V26=0,T26/COUNTIF(Setup!$B$9:$B$20,"?*"),T26*AP26/V26)) | AE26: =IF(OR(T26="",Setup!$B$17=""),0,IF(V26=0,T26/COUNTIF(Setup!$B$9:$B$20,"?*"),T26*AQ26/V26)) | AF26: =IF(OR(T26="",Setup!$B$18=""),0,IF(V26=0,T26/COUNTIF(Setup!$B$9:$B$20,"?*"),T26*AR26/V26)) | AG26: =IF(OR(T26="",Setup!$B$19=""),0,IF(V26=0,T26/COUNTIF(Setup!$B$9:$B$20,"?*"),T26*AS26/V26)) | AH26: =IF(OR(T26="",Setup!$B$20=""),0,IF(V26=0,T26/COUNTIF(Setup!$B$9:$B$20,"?*"),T26*AT26/V26)) | AI26: =IF(Setup!$B$9="",0,IF(H26="",0,IF(ISNUMBER(H26),H26,1))) | AJ26: =IF(Setup!$B$10="",0,IF(I26="",0,IF(ISNUMBER(I26),I26,1))) | AK26: =IF(Setup!$B$11="",0,IF(J26="",0,IF(ISNUMBER(J26),J26,1))) | AL26: =IF(Setup!$B$12="",0,IF(K26="",0,IF(ISNUMBER(K26),K26,1))) | AM26: =IF(Setup!$B$13="",0,IF(L26="",0,IF(ISNUMBER(L26),L26,1))) | AN26: =IF(Setup!$B$14="",0,IF(M26="",0,IF(ISNUMBER(M26),M26,1))) | AO26: =IF(Setup!$B$15="",0,IF(N26="",0,IF(ISNUMBER(N26),N26,1))) | AP26: =IF(Setup!$B$16="",0,IF(O26="",0,IF(ISNUMBER(O26),O26,1))) | AQ26: =IF(Setup!$B$17="",0,IF(P26="",0,IF(ISNUMBER(P26),P26,1))) | AR26: =IF(Setup!$B$18="",0,IF(Q26="",0,IF(ISNUMBER(Q26),Q26,1))) | AS26: =IF(Setup!$B$19="",0,IF(R26="",0,IF(ISNUMBER(R26),R26,1))) | AT26: =IF(Setup!$B$20="",0,IF(S26="",0,IF(ISNUMBER(S26),S26,1)))
B27: 46280 | C27: Boat tour on the Douro | D27: Activities | E27: 95 | F27: EUR | G27: Ana | T27: =IF(N(E27)=0,"",E27*IF(F27="",1,IFERROR(INDEX(Setup!$E$9:$E$18,MATCH(F27,Setup!$D$9:$D$18,0)),0))) | U27: =IF(T27="","",IF(V27=0,"Everyone",IF(COUNTIF(AI27:AT27,">0")=COUNTIF(Setup!$B$9:$B$20,"?*"),"Everyone",COUNTIF(AI27:AT27,">0")&IF(COUNTIF(AI27:AT27,">0")=1," person"," people")))) | V27: =SUM(AI27:AT27) | W27: =IF(OR(T27="",Setup!$B$9=""),0,IF(V27=0,T27/COUNTIF(Setup!$B$9:$B$20,"?*"),T27*AI27/V27)) | X27: =IF(OR(T27="",Setup!$B$10=""),0,IF(V27=0,T27/COUNTIF(Setup!$B$9:$B$20,"?*"),T27*AJ27/V27)) | Y27: =IF(OR(T27="",Setup!$B$11=""),0,IF(V27=0,T27/COUNTIF(Setup!$B$9:$B$20,"?*"),T27*AK27/V27)) | Z27: =IF(OR(T27="",Setup!$B$12=""),0,IF(V27=0,T27/COUNTIF(Setup!$B$9:$B$20,"?*"),T27*AL27/V27)) | AA27: =IF(OR(T27="",Setup!$B$13=""),0,IF(V27=0,T27/COUNTIF(Setup!$B$9:$B$20,"?*"),T27*AM27/V27)) | AB27: =IF(OR(T27="",Setup!$B$14=""),0,IF(V27=0,T27/COUNTIF(Setup!$B$9:$B$20,"?*"),T27*AN27/V27)) | AC27: =IF(OR(T27="",Setup!$B$15=""),0,IF(V27=0,T27/COUNTIF(Setup!$B$9:$B$20,"?*"),T27*AO27/V27)) | AD27: =IF(OR(T27="",Setup!$B$16=""),0,IF(V27=0,T27/COUNTIF(Setup!$B$9:$B$20,"?*"),T27*AP27/V27)) | AE27: =IF(OR(T27="",Setup!$B$17=""),0,IF(V27=0,T27/COUNTIF(Setup!$B$9:$B$20,"?*"),T27*AQ27/V27)) | AF27: =IF(OR(T27="",Setup!$B$18=""),0,IF(V27=0,T27/COUNTIF(Setup!$B$9:$B$20,"?*"),T27*AR27/V27)) | AG27: =IF(OR(T27="",Setup!$B$19=""),0,IF(V27=0,T27/COUNTIF(Setup!$B$9:$B$20,"?*"),T27*AS27/V27)) | AH27: =IF(OR(T27="",Setup!$B$20=""),0,IF(V27=0,T27/COUNTIF(Setup!$B$9:$B$20,"?*"),T27*AT27/V27)) | AI27: =IF(Setup!$B$9="",0,IF(H27="",0,IF(ISNUMBER(H27),H27,1))) | AJ27: =IF(Setup!$B$10="",0,IF(I27="",0,IF(ISNUMBER(I27),I27,1))) | AK27: =IF(Setup!$B$11="",0,IF(J27="",0,IF(ISNUMBER(J27),J27,1))) | AL27: =IF(Setup!$B$12="",0,IF(K27="",0,IF(ISNUMBER(K27),K27,1))) | AM27: =IF(Setup!$B$13="",0,IF(L27="",0,IF(ISNUMBER(L27),L27,1))) | AN27: =IF(Setup!$B$14="",0,IF(M27="",0,IF(ISNUMBER(M27),M27,1))) | AO27: =IF(Setup!$B$15="",0,IF(N27="",0,IF(ISNUMBER(N27),N27,1))) | AP27: =IF(Setup!$B$16="",0,IF(O27="",0,IF(ISNUMBER(O27),O27,1))) | AQ27: =IF(Setup!$B$17="",0,IF(P27="",0,IF(ISNUMBER(P27),P27,1))) | AR27: =IF(Setup!$B$18="",0,IF(Q27="",0,IF(ISNUMBER(Q27),Q27,1))) | AS27: =IF(Setup!$B$19="",0,IF(R27="",0,IF(ISNUMBER(R27),R27,1))) | AT27: =IF(Setup!$B$20="",0,IF(S27="",0,IF(ISNUMBER(S27),S27,1)))
B28: 46280 | C28: Groceries | D28: Groceries | E28: 38.2 | F28: EUR | G28: Emma | T28: =IF(N(E28)=0,"",E28*IF(F28="",1,IFERROR(INDEX(Setup!$E$9:$E$18,MATCH(F28,Setup!$D$9:$D$18,0)),0))) | U28: =IF(T28="","",IF(V28=0,"Everyone",IF(COUNTIF(AI28:AT28,">0")=COUNTIF(Setup!$B$9:$B$20,"?*"),"Everyone",COUNTIF(AI28:AT28,">0")&IF(COUNTIF(AI28:AT28,">0")=1," person"," people")))) | V28: =SUM(AI28:AT28) | W28: =IF(OR(T28="",Setup!$B$9=""),0,IF(V28=0,T28/COUNTIF(Setup!$B$9:$B$20,"?*"),T28*AI28/V28)) | X28: =IF(OR(T28="",Setup!$B$10=""),0,IF(V28=0,T28/COUNTIF(Setup!$B$9:$B$20,"?*"),T28*AJ28/V28)) | Y28: =IF(OR(T28="",Setup!$B$11=""),0,IF(V28=0,T28/COUNTIF(Setup!$B$9:$B$20,"?*"),T28*AK28/V28)) | Z28: =IF(OR(T28="",Setup!$B$12=""),0,IF(V28=0,T28/COUNTIF(Setup!$B$9:$B$20,"?*"),T28*AL28/V28)) | AA28: =IF(OR(T28="",Setup!$B$13=""),0,IF(V28=0,T28/COUNTIF(Setup!$B$9:$B$20,"?*"),T28*AM28/V28)) | AB28: =IF(OR(T28="",Setup!$B$14=""),0,IF(V28=0,T28/COUNTIF(Setup!$B$9:$B$20,"?*"),T28*AN28/V28)) | AC28: =IF(OR(T28="",Setup!$B$15=""),0,IF(V28=0,T28/COUNTIF(Setup!$B$9:$B$20,"?*"),T28*AO28/V28)) | AD28: =IF(OR(T28="",Setup!$B$16=""),0,IF(V28=0,T28/COUNTIF(Setup!$B$9:$B$20,"?*"),T28*AP28/V28)) | AE28: =IF(OR(T28="",Setup!$B$17=""),0,IF(V28=0,T28/COUNTIF(Setup!$B$9:$B$20,"?*"),T28*AQ28/V28)) | AF28: =IF(OR(T28="",Setup!$B$18=""),0,IF(V28=0,T28/COUNTIF(Setup!$B$9:$B$20,"?*"),T28*AR28/V28)) | AG28: =IF(OR(T28="",Setup!$B$19=""),0,IF(V28=0,T28/COUNTIF(Setup!$B$9:$B$20,"?*"),T28*AS28/V28)) | AH28: =IF(OR(T28="",Setup!$B$20=""),0,IF(V28=0,T28/COUNTIF(Setup!$B$9:$B$20,"?*"),T28*AT28/V28)) | AI28: =IF(Setup!$B$9="",0,IF(H28="",0,IF(ISNUMBER(H28),H28,1))) | AJ28: =IF(Setup!$B$10="",0,IF(I28="",0,IF(ISNUMBER(I28),I28,1))) | AK28: =IF(Setup!$B$11="",0,IF(J28="",0,IF(ISNUMBER(J28),J28,1))) | AL28: =IF(Setup!$B$12="",0,IF(K28="",0,IF(ISNUMBER(K28),K28,1))) | AM28: =IF(Setup!$B$13="",0,IF(L28="",0,IF(ISNUMBER(L28),L28,1))) | AN28: =IF(Setup!$B$14="",0,IF(M28="",0,IF(ISNUMBER(M28),M28,1))) | AO28: =IF(Setup!$B$15="",0,IF(N28="",0,IF(ISNUMBER(N28),N28,1))) | AP28: =IF(Setup!$B$16="",0,IF(O28="",0,IF(ISNUMBER(O28),O28,1))) | AQ28: =IF(Setup!$B$17="",0,IF(P28="",0,IF(ISNUMBER(P28),P28,1))) | AR28: =IF(Setup!$B$18="",0,IF(Q28="",0,IF(ISNUMBER(Q28),Q28,1))) | AS28: =IF(Setup!$B$19="",0,IF(R28="",0,IF(ISNUMBER(R28),R28,1))) | AT28: =IF(Setup!$B$20="",0,IF(S28="",0,IF(ISNUMBER(S28),S28,1)))
B29: 46280 | C29: Farewell dinner | D29: Food | E29: 210 | F29: EUR | G29: Chloe | T29: =IF(N(E29)=0,"",E29*IF(F29="",1,IFERROR(INDEX(Setup!$E$9:$E$18,MATCH(F29,Setup!$D$9:$D$18,0)),0))) | U29: =IF(T29="","",IF(V29=0,"Everyone",IF(COUNTIF(AI29:AT29,">0")=COUNTIF(Setup!$B$9:$B$20,"?*"),"Everyone",COUNTIF(AI29:AT29,">0")&IF(COUNTIF(AI29:AT29,">0")=1," person"," people")))) | V29: =SUM(AI29:AT29) | W29: =IF(OR(T29="",Setup!$B$9=""),0,IF(V29=0,T29/COUNTIF(Setup!$B$9:$B$20,"?*"),T29*AI29/V29)) | X29: =IF(OR(T29="",Setup!$B$10=""),0,IF(V29=0,T29/COUNTIF(Setup!$B$9:$B$20,"?*"),T29*AJ29/V29)) | Y29: =IF(OR(T29="",Setup!$B$11=""),0,IF(V29=0,T29/COUNTIF(Setup!$B$9:$B$20,"?*"),T29*AK29/V29)) | Z29: =IF(OR(T29="",Setup!$B$12=""),0,IF(V29=0,T29/COUNTIF(Setup!$B$9:$B$20,"?*"),T29*AL29/V29)) | AA29: =IF(OR(T29="",Setup!$B$13=""),0,IF(V29=0,T29/COUNTIF(Setup!$B$9:$B$20,"?*"),T29*AM29/V29)) | AB29: =IF(OR(T29="",Setup!$B$14=""),0,IF(V29=0,T29/COUNTIF(Setup!$B$9:$B$20,"?*"),T29*AN29/V29)) | AC29: =IF(OR(T29="",Setup!$B$15=""),0,IF(V29=0,T29/COUNTIF(Setup!$B$9:$B$20,"?*"),T29*AO29/V29)) | AD29: =IF(OR(T29="",Setup!$B$16=""),0,IF(V29=0,T29/COUNTIF(Setup!$B$9:$B$20,"?*"),T29*AP29/V29)) | AE29: =IF(OR(T29="",Setup!$B$17=""),0,IF(V29=0,T29/COUNTIF(Setup!$B$9:$B$20,"?*"),T29*AQ29/V29)) | AF29: =IF(OR(T29="",Setup!$B$18=""),0,IF(V29=0,T29/COUNTIF(Setup!$B$9:$B$20,"?*"),T29*AR29/V29)) | AG29: =IF(OR(T29="",Setup!$B$19=""),0,IF(V29=0,T29/COUNTIF(Setup!$B$9:$B$20,"?*"),T29*AS29/V29)) | AH29: =IF(OR(T29="",Setup!$B$20=""),0,IF(V29=0,T29/COUNTIF(Setup!$B$9:$B$20,"?*"),T29*AT29/V29)) | AI29: =IF(Setup!$B$9="",0,IF(H29="",0,IF(ISNUMBER(H29),H29,1))) | AJ29: =IF(Setup!$B$10="",0,IF(I29="",0,IF(ISNUMBER(I29),I29,1))) | AK29: =IF(Setup!$B$11="",0,IF(J29="",0,IF(ISNUMBER(J29),J29,1))) | AL29: =IF(Setup!$B$12="",0,IF(K29="",0,IF(ISNUMBER(K29),K29,1))) | AM29: =IF(Setup!$B$13="",0,IF(L29="",0,IF(ISNUMBER(L29),L29,1))) | AN29: =IF(Setup!$B$14="",0,IF(M29="",0,IF(ISNUMBER(M29),M29,1))) | AO29: =IF(Setup!$B$15="",0,IF(N29="",0,IF(ISNUMBER(N29),N29,1))) | AP29: =IF(Setup!$B$16="",0,IF(O29="",0,IF(ISNUMBER(O29),O29,1))) | AQ29: =IF(Setup!$B$17="",0,IF(P29="",0,IF(ISNUMBER(P29),P29,1))) | AR29: =IF(Setup!$B$18="",0,IF(Q29="",0,IF(ISNUMBER(Q29),Q29,1))) | AS29: =IF(Setup!$B$19="",0,IF(R29="",0,IF(ISNUMBER(R29),R29,1))) | AT29: =IF(Setup!$B$20="",0,IF(S29="",0,IF(ISNUMBER(S29),S29,1)))
B30: 46281 | C30: Taxi to the airport | D30: Transport | E30: 34 | F30: EUR | G30: Dev | T30: =IF(N(E30)=0,"",E30*IF(F30="",1,IFERROR(INDEX(Setup!$E$9:$E$18,MATCH(F30,Setup!$D$9:$D$18,0)),0))) | U30: =IF(T30="","",IF(V30=0,"Everyone",IF(COUNTIF(AI30:AT30,">0")=COUNTIF(Setup!$B$9:$B$20,"?*"),"Everyone",COUNTIF(AI30:AT30,">0")&IF(COUNTIF(AI30:AT30,">0")=1," person"," people")))) | V30: =SUM(AI30:AT30) | W30: =IF(OR(T30="",Setup!$B$9=""),0,IF(V30=0,T30/COUNTIF(Setup!$B$9:$B$20,"?*"),T30*AI30/V30)) | X30: =IF(OR(T30="",Setup!$B$10=""),0,IF(V30=0,T30/COUNTIF(Setup!$B$9:$B$20,"?*"),T30*AJ30/V30)) | Y30: =IF(OR(T30="",Setup!$B$11=""),0,IF(V30=0,T30/COUNTIF(Setup!$B$9:$B$20,"?*"),T30*AK30/V30)) | Z30: =IF(OR(T30="",Setup!$B$12=""),0,IF(V30=0,T30/COUNTIF(Setup!$B$9:$B$20,"?*"),T30*AL30/V30)) | AA30: =IF(OR(T30="",Setup!$B$13=""),0,IF(V30=0,T30/COUNTIF(Setup!$B$9:$B$20,"?*"),T30*AM30/V30)) | AB30: =IF(OR(T30="",Setup!$B$14=""),0,IF(V30=0,T30/COUNTIF(Setup!$B$9:$B$20,"?*"),T30*AN30/V30)) | AC30: =IF(OR(T30="",Setup!$B$15=""),0,IF(V30=0,T30/COUNTIF(Setup!$B$9:$B$20,"?*"),T30*AO30/V30)) | AD30: =IF(OR(T30="",Setup!$B$16=""),0,IF(V30=0,T30/COUNTIF(Setup!$B$9:$B$20,"?*"),T30*AP30/V30)) | AE30: =IF(OR(T30="",Setup!$B$17=""),0,IF(V30=0,T30/COUNTIF(Setup!$B$9:$B$20,"?*"),T30*AQ30/V30)) | AF30: =IF(OR(T30="",Setup!$B$18=""),0,IF(V30=0,T30/COUNTIF(Setup!$B$9:$B$20,"?*"),T30*AR30/V30)) | AG30: =IF(OR(T30="",Setup!$B$19=""),0,IF(V30=0,T30/COUNTIF(Setup!$B$9:$B$20,"?*"),T30*AS30/V30)) | AH30: =IF(OR(T30="",Setup!$B$20=""),0,IF(V30=0,T30/COUNTIF(Setup!$B$9:$B$20,"?*"),T30*AT30/V30)) | AI30: =IF(Setup!$B$9="",0,IF(H30="",0,IF(ISNUMBER(H30),H30,1))) | AJ30: =IF(Setup!$B$10="",0,IF(I30="",0,IF(ISNUMBER(I30),I30,1))) | AK30: =IF(Setup!$B$11="",0,IF(J30="",0,IF(ISNUMBER(J30),J30,1))) | AL30: =IF(Setup!$B$12="",0,IF(K30="",0,IF(ISNUMBER(K30),K30,1))) | AM30: =IF(Setup!$B$13="",0,IF(L30="",0,IF(ISNUMBER(L30),L30,1))) | AN30: =IF(Setup!$B$14="",0,IF(M30="",0,IF(ISNUMBER(M30),M30,1))) | AO30: =IF(Setup!$B$15="",0,IF(N30="",0,IF(ISNUMBER(N30),N30,1))) | AP30: =IF(Setup!$B$16="",0,IF(O30="",0,IF(ISNUMBER(O30),O30,1))) | AQ30: =IF(Setup!$B$17="",0,IF(P30="",0,IF(ISNUMBER(P30),P30,1))) | AR30: =IF(Setup!$B$18="",0,IF(Q30="",0,IF(ISNUMBER(Q30),Q30,1))) | AS30: =IF(Setup!$B$19="",0,IF(R30="",0,IF(ISNUMBER(R30),R30,1))) | AT30: =IF(Setup!$B$20="",0,IF(S30="",0,IF(ISNUMBER(S30),S30,1)))
B31: 46281 | C31: Airport snacks | D31: Food | E31: 22.4 | F31: EUR | G31: Ben | T31: =IF(N(E31)=0,"",E31*IF(F31="",1,IFERROR(INDEX(Setup!$E$9:$E$18,MATCH(F31,Setup!$D$9:$D$18,0)),0))) | U31: =IF(T31="","",IF(V31=0,"Everyone",IF(COUNTIF(AI31:AT31,">0")=COUNTIF(Setup!$B$9:$B$20,"?*"),"Everyone",COUNTIF(AI31:AT31,">0")&IF(COUNTIF(AI31:AT31,">0")=1," person"," people")))) | V31: =SUM(AI31:AT31) | W31: =IF(OR(T31="",Setup!$B$9=""),0,IF(V31=0,T31/COUNTIF(Setup!$B$9:$B$20,"?*"),T31*AI31/V31)) | X31: =IF(OR(T31="",Setup!$B$10=""),0,IF(V31=0,T31/COUNTIF(Setup!$B$9:$B$20,"?*"),T31*AJ31/V31)) | Y31: =IF(OR(T31="",Setup!$B$11=""),0,IF(V31=0,T31/COUNTIF(Setup!$B$9:$B$20,"?*"),T31*AK31/V31)) | Z31: =IF(OR(T31="",Setup!$B$12=""),0,IF(V31=0,T31/COUNTIF(Setup!$B$9:$B$20,"?*"),T31*AL31/V31)) | AA31: =IF(OR(T31="",Setup!$B$13=""),0,IF(V31=0,T31/COUNTIF(Setup!$B$9:$B$20,"?*"),T31*AM31/V31)) | AB31: =IF(OR(T31="",Setup!$B$14=""),0,IF(V31=0,T31/COUNTIF(Setup!$B$9:$B$20,"?*"),T31*AN31/V31)) | AC31: =IF(OR(T31="",Setup!$B$15=""),0,IF(V31=0,T31/COUNTIF(Setup!$B$9:$B$20,"?*"),T31*AO31/V31)) | AD31: =IF(OR(T31="",Setup!$B$16=""),0,IF(V31=0,T31/COUNTIF(Setup!$B$9:$B$20,"?*"),T31*AP31/V31)) | AE31: =IF(OR(T31="",Setup!$B$17=""),0,IF(V31=0,T31/COUNTIF(Setup!$B$9:$B$20,"?*"),T31*AQ31/V31)) | AF31: =IF(OR(T31="",Setup!$B$18=""),0,IF(V31=0,T31/COUNTIF(Setup!$B$9:$B$20,"?*"),T31*AR31/V31)) | AG31: =IF(OR(T31="",Setup!$B$19=""),0,IF(V31=0,T31/COUNTIF(Setup!$B$9:$B$20,"?*"),T31*AS31/V31)) | AH31: =IF(OR(T31="",Setup!$B$20=""),0,IF(V31=0,T31/COUNTIF(Setup!$B$9:$B$20,"?*"),T31*AT31/V31)) | AI31: =IF(Setup!$B$9="",0,IF(H31="",0,IF(ISNUMBER(H31),H31,1))) | AJ31: =IF(Setup!$B$10="",0,IF(I31="",0,IF(ISNUMBER(I31),I31,1))) | AK31: =IF(Setup!$B$11="",0,IF(J31="",0,IF(ISNUMBER(J31),J31,1))) | AL31: =IF(Setup!$B$12="",0,IF(K31="",0,IF(ISNUMBER(K31),K31,1))) | AM31: =IF(Setup!$B$13="",0,IF(L31="",0,IF(ISNUMBER(L31),L31,1))) | AN31: =IF(Setup!$B$14="",0,IF(M31="",0,IF(ISNUMBER(M31),M31,1))) | AO31: =IF(Setup!$B$15="",0,IF(N31="",0,IF(ISNUMBER(N31),N31,1))) | AP31: =IF(Setup!$B$16="",0,IF(O31="",0,IF(ISNUMBER(O31),O31,1))) | AQ31: =IF(Setup!$B$17="",0,IF(P31="",0,IF(ISNUMBER(P31),P31,1))) | AR31: =IF(Setup!$B$18="",0,IF(Q31="",0,IF(ISNUMBER(Q31),Q31,1))) | AS31: =IF(Setup!$B$19="",0,IF(R31="",0,IF(ISNUMBER(R31),R31,1))) | AT31: =IF(Setup!$B$20="",0,IF(S31="",0,IF(ISNUMBER(S31),S31,1)))
B32: 46281 | C32: Car home from the airport | D32: Transport | E32: 58 | F32: USD | G32: Emma | H32: x | L32: x | T32: =IF(N(E32)=0,"",E32*IF(F32="",1,IFERROR(INDEX(Setup!$E$9:$E$18,MATCH(F32,Setup!$D$9:$D$18,0)),0))) | U32: =IF(T32="","",IF(V32=0,"Everyone",IF(COUNTIF(AI32:AT32,">0")=COUNTIF(Setup!$B$9:$B$20,"?*"),"Everyone",COUNTIF(AI32:AT32,">0")&IF(COUNTIF(AI32:AT32,">0")=1," person"," people")))) | V32: =SUM(AI32:AT32) | W32: =IF(OR(T32="",Setup!$B$9=""),0,IF(V32=0,T32/COUNTIF(Setup!$B$9:$B$20,"?*"),T32*AI32/V32)) | X32: =IF(OR(T32="",Setup!$B$10=""),0,IF(V32=0,T32/COUNTIF(Setup!$B$9:$B$20,"?*"),T32*AJ32/V32)) | Y32: =IF(OR(T32="",Setup!$B$11=""),0,IF(V32=0,T32/COUNTIF(Setup!$B$9:$B$20,"?*"),T32*AK32/V32)) | Z32: =IF(OR(T32="",Setup!$B$12=""),0,IF(V32=0,T32/COUNTIF(Setup!$B$9:$B$20,"?*"),T32*AL32/V32)) | AA32: =IF(OR(T32="",Setup!$B$13=""),0,IF(V32=0,T32/COUNTIF(Setup!$B$9:$B$20,"?*"),T32*AM32/V32)) | AB32: =IF(OR(T32="",Setup!$B$14=""),0,IF(V32=0,T32/COUNTIF(Setup!$B$9:$B$20,"?*"),T32*AN32/V32)) | AC32: =IF(OR(T32="",Setup!$B$15=""),0,IF(V32=0,T32/COUNTIF(Setup!$B$9:$B$20,"?*"),T32*AO32/V32)) | AD32: =IF(OR(T32="",Setup!$B$16=""),0,IF(V32=0,T32/COUNTIF(Setup!$B$9:$B$20,"?*"),T32*AP32/V32)) | AE32: =IF(OR(T32="",Setup!$B$17=""),0,IF(V32=0,T32/COUNTIF(Setup!$B$9:$B$20,"?*"),T32*AQ32/V32)) | AF32: =IF(OR(T32="",Setup!$B$18=""),0,IF(V32=0,T32/COUNTIF(Setup!$B$9:$B$20,"?*"),T32*AR32/V32)) | AG32: =IF(OR(T32="",Setup!$B$19=""),0,IF(V32=0,T32/COUNTIF(Setup!$B$9:$B$20,"?*"),T32*AS32/V32)) | AH32: =IF(OR(T32="",Setup!$B$20=""),0,IF(V32=0,T32/COUNTIF(Setup!$B$9:$B$20,"?*"),T32*AT32/V32)) | AI32: =IF(Setup!$B$9="",0,IF(H32="",0,IF(ISNUMBER(H32),H32,1))) | AJ32: =IF(Setup!$B$10="",0,IF(I32="",0,IF(ISNUMBER(I32),I32,1))) | AK32: =IF(Setup!$B$11="",0,IF(J32="",0,IF(ISNUMBER(J32),J32,1))) | AL32: =IF(Setup!$B$12="",0,IF(K32="",0,IF(ISNUMBER(K32),K32,1))) | AM32: =IF(Setup!$B$13="",0,IF(L32="",0,IF(ISNUMBER(L32),L32,1))) | AN32: =IF(Setup!$B$14="",0,IF(M32="",0,IF(ISNUMBER(M32),M32,1))) | AO32: =IF(Setup!$B$15="",0,IF(N32="",0,IF(ISNUMBER(N32),N32,1))) | AP32: =IF(Setup!$B$16="",0,IF(O32="",0,IF(ISNUMBER(O32),O32,1))) | AQ32: =IF(Setup!$B$17="",0,IF(P32="",0,IF(ISNUMBER(P32),P32,1))) | AR32: =IF(Setup!$B$18="",0,IF(Q32="",0,IF(ISNUMBER(Q32),Q32,1))) | AS32: =IF(Setup!$B$19="",0,IF(R32="",0,IF(ISNUMBER(R32),R32,1))) | AT32: =IF(Setup!$B$20="",0,IF(S32="",0,IF(ISNUMBER(S32),S32,1)))
T33: =IF(N(E33)=0,"",E33*IF(F33="",1,IFERROR(INDEX(Setup!$E$9:$E$18,MATCH(F33,Setup!$D$9:$D$18,0)),0))) | U33: =IF(T33="","",IF(V33=0,"Everyone",IF(COUNTIF(AI33:AT33,">0")=COUNTIF(Setup!$B$9:$B$20,"?*"),"Everyone",COUNTIF(AI33:AT33,">0")&IF(COUNTIF(AI33:AT33,">0")=1," person"," people")))) | V33: =SUM(AI33:AT33) | W33: =IF(OR(T33="",Setup!$B$9=""),0,IF(V33=0,T33/COUNTIF(Setup!$B$9:$B$20,"?*"),T33*AI33/V33)) | X33: =IF(OR(T33="",Setup!$B$10=""),0,IF(V33=0,T33/COUNTIF(Setup!$B$9:$B$20,"?*"),T33*AJ33/V33)) | Y33: =IF(OR(T33="",Setup!$B$11=""),0,IF(V33=0,T33/COUNTIF(Setup!$B$9:$B$20,"?*"),T33*AK33/V33)) | Z33: =IF(OR(T33="",Setup!$B$12=""),0,IF(V33=0,T33/COUNTIF(Setup!$B$9:$B$20,"?*"),T33*AL33/V33)) | AA33: =IF(OR(T33="",Setup!$B$13=""),0,IF(V33=0,T33/COUNTIF(Setup!$B$9:$B$20,"?*"),T33*AM33/V33)) | AB33: =IF(OR(T33="",Setup!$B$14=""),0,IF(V33=0,T33/COUNTIF(Setup!$B$9:$B$20,"?*"),T33*AN33/V33)) | AC33: =IF(OR(T33="",Setup!$B$15=""),0,IF(V33=0,T33/COUNTIF(Setup!$B$9:$B$20,"?*"),T33*AO33/V33)) | AD33: =IF(OR(T33="",Setup!$B$16=""),0,IF(V33=0,T33/COUNTIF(Setup!$B$9:$B$20,"?*"),T33*AP33/V33)) | AE33: =IF(OR(T33="",Setup!$B$17=""),0,IF(V33=0,T33/COUNTIF(Setup!$B$9:$B$20,"?*"),T33*AQ33/V33)) | AF33: =IF(OR(T33="",Setup!$B$18=""),0,IF(V33=0,T33/COUNTIF(Setup!$B$9:$B$20,"?*"),T33*AR33/V33)) | AG33: =IF(OR(T33="",Setup!$B$19=""),0,IF(V33=0,T33/COUNTIF(Setup!$B$9:$B$20,"?*"),T33*AS33/V33)) | AH33: =IF(OR(T33="",Setup!$B$20=""),0,IF(V33=0,T33/COUNTIF(Setup!$B$9:$B$20,"?*"),T33*AT33/V33)) | AI33: =IF(Setup!$B$9="",0,IF(H33="",0,IF(ISNUMBER(H33),H33,1))) | AJ33: =IF(Setup!$B$10="",0,IF(I33="",0,IF(ISNUMBER(I33),I33,1))) | AK33: =IF(Setup!$B$11="",0,IF(J33="",0,IF(ISNUMBER(J33),J33,1))) | AL33: =IF(Setup!$B$12="",0,IF(K33="",0,IF(ISNUMBER(K33),K33,1))) | AM33: =IF(Setup!$B$13="",0,IF(L33="",0,IF(ISNUMBER(L33),L33,1))) | AN33: =IF(Setup!$B$14="",0,IF(M33="",0,IF(ISNUMBER(M33),M33,1))) | AO33: =IF(Setup!$B$15="",0,IF(N33="",0,IF(ISNUMBER(N33),N33,1))) | AP33: =IF(Setup!$B$16="",0,IF(O33="",0,IF(ISNUMBER(O33),O33,1))) | AQ33: =IF(Setup!$B$17="",0,IF(P33="",0,IF(ISNUMBER(P33),P33,1))) | AR33: =IF(Setup!$B$18="",0,IF(Q33="",0,IF(ISNUMBER(Q33),Q33,1))) | AS33: =IF(Setup!$B$19="",0,IF(R33="",0,IF(ISNUMBER(R33),R33,1))) | AT33: =IF(Setup!$B$20="",0,IF(S33="",0,IF(ISNUMBER(S33),S33,1)))
T34: =IF(N(E34)=0,"",E34*IF(F34="",1,IFERROR(INDEX(Setup!$E$9:$E$18,MATCH(F34,Setup!$D$9:$D$18,0)),0))) | U34: =IF(T34="","",IF(V34=0,"Everyone",IF(COUNTIF(AI34:AT34,">0")=COUNTIF(Setup!$B$9:$B$20,"?*"),"Everyone",COUNTIF(AI34:AT34,">0")&IF(COUNTIF(AI34:AT34,">0")=1," person"," people")))) | V34: =SUM(AI34:AT34) | W34: =IF(OR(T34="",Setup!$B$9=""),0,IF(V34=0,T34/COUNTIF(Setup!$B$9:$B$20,"?*"),T34*AI34/V34)) | X34: =IF(OR(T34="",Setup!$B$10=""),0,IF(V34=0,T34/COUNTIF(Setup!$B$9:$B$20,"?*"),T34*AJ34/V34)) | Y34: =IF(OR(T34="",Setup!$B$11=""),0,IF(V34=0,T34/COUNTIF(Setup!$B$9:$B$20,"?*"),T34*AK34/V34)) | Z34: =IF(OR(T34="",Setup!$B$12=""),0,IF(V34=0,T34/COUNTIF(Setup!$B$9:$B$20,"?*"),T34*AL34/V34)) | AA34: =IF(OR(T34="",Setup!$B$13=""),0,IF(V34=0,T34/COUNTIF(Setup!$B$9:$B$20,"?*"),T34*AM34/V34)) | AB34: =IF(OR(T34="",Setup!$B$14=""),0,IF(V34=0,T34/COUNTIF(Setup!$B$9:$B$20,"?*"),T34*AN34/V34)) | AC34: =IF(OR(T34="",Setup!$B$15=""),0,IF(V34=0,T34/COUNTIF(Setup!$B$9:$B$20,"?*"),T34*AO34/V34)) | AD34: =IF(OR(T34="",Setup!$B$16=""),0,IF(V34=0,T34/COUNTIF(Setup!$B$9:$B$20,"?*"),T34*AP34/V34)) | AE34: =IF(OR(T34="",Setup!$B$17=""),0,IF(V34=0,T34/COUNTIF(Setup!$B$9:$B$20,"?*"),T34*AQ34/V34)) | AF34: =IF(OR(T34="",Setup!$B$18=""),0,IF(V34=0,T34/COUNTIF(Setup!$B$9:$B$20,"?*"),T34*AR34/V34)) | AG34: =IF(OR(T34="",Setup!$B$19=""),0,IF(V34=0,T34/COUNTIF(Setup!$B$9:$B$20,"?*"),T34*AS34/V34)) | AH34: =IF(OR(T34="",Setup!$B$20=""),0,IF(V34=0,T34/COUNTIF(Setup!$B$9:$B$20,"?*"),T34*AT34/V34)) | AI34: =IF(Setup!$B$9="",0,IF(H34="",0,IF(ISNUMBER(H34),H34,1))) | AJ34: =IF(Setup!$B$10="",0,IF(I34="",0,IF(ISNUMBER(I34),I34,1))) | AK34: =IF(Setup!$B$11="",0,IF(J34="",0,IF(ISNUMBER(J34),J34,1))) | AL34: =IF(Setup!$B$12="",0,IF(K34="",0,IF(ISNUMBER(K34),K34,1))) | AM34: =IF(Setup!$B$13="",0,IF(L34="",0,IF(ISNUMBER(L34),L34,1))) | AN34: =IF(Setup!$B$14="",0,IF(M34="",0,IF(ISNUMBER(M34),M34,1))) | AO34: =IF(Setup!$B$15="",0,IF(N34="",0,IF(ISNUMBER(N34),N34,1))) | AP34: =IF(Setup!$B$16="",0,IF(O34="",0,IF(ISNUMBER(O34),O34,1))) | AQ34: =IF(Setup!$B$17="",0,IF(P34="",0,IF(ISNUMBER(P34),P34,1))) | AR34: =IF(Setup!$B$18="",0,IF(Q34="",0,IF(ISNUMBER(Q34),Q34,1))) | AS34: =IF(Setup!$B$19="",0,IF(R34="",0,IF(ISNUMBER(R34),R34,1))) | AT34: =IF(Setup!$B$20="",0,IF(S34="",0,IF(ISNUMBER(S34),S34,1)))
T35: =IF(N(E35)=0,"",E35*IF(F35="",1,IFERROR(INDEX(Setup!$E$9:$E$18,MATCH(F35,Setup!$D$9:$D$18,0)),0))) | U35: =IF(T35="","",IF(V35=0,"Everyone",IF(COUNTIF(AI35:AT35,">0")=COUNTIF(Setup!$B$9:$B$20,"?*"),"Everyone",COUNTIF(AI35:AT35,">0")&IF(COUNTIF(AI35:AT35,">0")=1," person"," people")))) | V35: =SUM(AI35:AT35) | W35: =IF(OR(T35="",Setup!$B$9=""),0,IF(V35=0,T35/COUNTIF(Setup!$B$9:$B$20,"?*"),T35*AI35/V35)) | X35: =IF(OR(T35="",Setup!$B$10=""),0,IF(V35=0,T35/COUNTIF(Setup!$B$9:$B$20,"?*"),T35*AJ35/V35)) | Y35: =IF(OR(T35="",Setup!$B$11=""),0,IF(V35=0,T35/COUNTIF(Setup!$B$9:$B$20,"?*"),T35*AK35/V35)) | Z35: =IF(OR(T35="",Setup!$B$12=""),0,IF(V35=0,T35/COUNTIF(Setup!$B$9:$B$20,"?*"),T35*AL35/V35)) | AA35: =IF(OR(T35="",Setup!$B$13=""),0,IF(V35=0,T35/COUNTIF(Setup!$B$9:$B$20,"?*"),T35*AM35/V35)) | AB35: =IF(OR(T35="",Setup!$B$14=""),0,IF(V35=0,T35/COUNTIF(Setup!$B$9:$B$20,"?*"),T35*AN35/V35)) | AC35: =IF(OR(T35="",Setup!$B$15=""),0,IF(V35=0,T35/COUNTIF(Setup!$B$9:$B$20,"?*"),T35*AO35/V35)) | AD35: =IF(OR(T35="",Setup!$B$16=""),0,IF(V35=0,T35/COUNTIF(Setup!$B$9:$B$20,"?*"),T35*AP35/V35)) | AE35: =IF(OR(T35="",Setup!$B$17=""),0,IF(V35=0,T35/COUNTIF(Setup!$B$9:$B$20,"?*"),T35*AQ35/V35)) | AF35: =IF(OR(T35="",Setup!$B$18=""),0,IF(V35=0,T35/COUNTIF(Setup!$B$9:$B$20,"?*"),T35*AR35/V35)) | AG35: =IF(OR(T35="",Setup!$B$19=""),0,IF(V35=0,T35/COUNTIF(Setup!$B$9:$B$20,"?*"),T35*AS35/V35)) | AH35: =IF(OR(T35="",Setup!$B$20=""),0,IF(V35=0,T35/COUNTIF(Setup!$B$9:$B$20,"?*"),T35*AT35/V35)) | AI35: =IF(Setup!$B$9="",0,IF(H35="",0,IF(ISNUMBER(H35),H35,1))) | AJ35: =IF(Setup!$B$10="",0,IF(I35="",0,IF(ISNUMBER(I35),I35,1))) | AK35: =IF(Setup!$B$11="",0,IF(J35="",0,IF(ISNUMBER(J35),J35,1))) | AL35: =IF(Setup!$B$12="",0,IF(K35="",0,IF(ISNUMBER(K35),K35,1))) | AM35: =IF(Setup!$B$13="",0,IF(L35="",0,IF(ISNUMBER(L35),L35,1))) | AN35: =IF(Setup!$B$14="",0,IF(M35="",0,IF(ISNUMBER(M35),M35,1))) | AO35: =IF(Setup!$B$15="",0,IF(N35="",0,IF(ISNUMBER(N35),N35,1))) | AP35: =IF(Setup!$B$16="",0,IF(O35="",0,IF(ISNUMBER(O35),O35,1))) | AQ35: =IF(Setup!$B$17="",0,IF(P35="",0,IF(ISNUMBER(P35),P35,1))) | AR35: =IF(Setup!$B$18="",0,IF(Q35="",0,IF(ISNUMBER(Q35),Q35,1))) | AS35: =IF(Setup!$B$19="",0,IF(R35="",0,IF(ISNUMBER(R35),R35,1))) | AT35: =IF(Setup!$B$20="",0,IF(S35="",0,IF(ISNUMBER(S35),S35,1)))
T36: =IF(N(E36)=0,"",E36*IF(F36="",1,IFERROR(INDEX(Setup!$E$9:$E$18,MATCH(F36,Setup!$D$9:$D$18,0)),0))) | U36: =IF(T36="","",IF(V36=0,"Everyone",IF(COUNTIF(AI36:AT36,">0")=COUNTIF(Setup!$B$9:$B$20,"?*"),"Everyone",COUNTIF(AI36:AT36,">0")&IF(COUNTIF(AI36:AT36,">0")=1," person"," people")))) | V36: =SUM(AI36:AT36) | W36: =IF(OR(T36="",Setup!$B$9=""),0,IF(V36=0,T36/COUNTIF(Setup!$B$9:$B$20,"?*"),T36*AI36/V36)) | X36: =IF(OR(T36="",Setup!$B$10=""),0,IF(V36=0,T36/COUNTIF(Setup!$B$9:$B$20,"?*"),T36*AJ36/V36)) | Y36: =IF(OR(T36="",Setup!$B$11=""),0,IF(V36=0,T36/COUNTIF(Setup!$B$9:$B$20,"?*"),T36*AK36/V36)) | Z36: =IF(OR(T36="",Setup!$B$12=""),0,IF(V36=0,T36/COUNTIF(Setup!$B$9:$B$20,"?*"),T36*AL36/V36)) | AA36: =IF(OR(T36="",Setup!$B$13=""),0,IF(V36=0,T36/COUNTIF(Setup!$B$9:$B$20,"?*"),T36*AM36/V36)) | AB36: =IF(OR(T36="",Setup!$B$14=""),0,IF(V36=0,T36/COUNTIF(Setup!$B$9:$B$20,"?*"),T36*AN36/V36)) | AC36: =IF(OR(T36="",Setup!$B$15=""),0,IF(V36=0,T36/COUNTIF(Setup!$B$9:$B$20,"?*"),T36*AO36/V36)) | AD36: =IF(OR(T36="",Setup!$B$16=""),0,IF(V36=0,T36/COUNTIF(Setup!$B$9:$B$20,"?*"),T36*AP36/V36)) | AE36: =IF(OR(T36="",Setup!$B$17=""),0,IF(V36=0,T36/COUNTIF(Setup!$B$9:$B$20,"?*"),T36*AQ36/V36)) | AF36: =IF(OR(T36="",Setup!$B$18=""),0,IF(V36=0,T36/COUNTIF(Setup!$B$9:$B$20,"?*"),T36*AR36/V36)) | AG36: =IF(OR(T36="",Setup!$B$19=""),0,IF(V36=0,T36/COUNTIF(Setup!$B$9:$B$20,"?*"),T36*AS36/V36)) | AH36: =IF(OR(T36="",Setup!$B$20=""),0,IF(V36=0,T36/COUNTIF(Setup!$B$9:$B$20,"?*"),T36*AT36/V36)) | AI36: =IF(Setup!$B$9="",0,IF(H36="",0,IF(ISNUMBER(H36),H36,1))) | AJ36: =IF(Setup!$B$10="",0,IF(I36="",0,IF(ISNUMBER(I36),I36,1))) | AK36: =IF(Setup!$B$11="",0,IF(J36="",0,IF(ISNUMBER(J36),J36,1))) | AL36: =IF(Setup!$B$12="",0,IF(K36="",0,IF(ISNUMBER(K36),K36,1))) | AM36: =IF(Setup!$B$13="",0,IF(L36="",0,IF(ISNUMBER(L36),L36,1))) | AN36: =IF(Setup!$B$14="",0,IF(M36="",0,IF(ISNUMBER(M36),M36,1))) | AO36: =IF(Setup!$B$15="",0,IF(N36="",0,IF(ISNUMBER(N36),N36,1))) | AP36: =IF(Setup!$B$16="",0,IF(O36="",0,IF(ISNUMBER(O36),O36,1))) | AQ36: =IF(Setup!$B$17="",0,IF(P36="",0,IF(ISNUMBER(P36),P36,1))) | AR36: =IF(Setup!$B$18="",0,IF(Q36="",0,IF(ISNUMBER(Q36),Q36,1))) | AS36: =IF(Setup!$B$19="",0,IF(R36="",0,IF(ISNUMBER(R36),R36,1))) | AT36: =IF(Setup!$B$20="",0,IF(S36="",0,IF(ISNUMBER(S36),S36,1)))
T37: =IF(N(E37)=0,"",E37*IF(F37="",1,IFERROR(INDEX(Setup!$E$9:$E$18,MATCH(F37,Setup!$D$9:$D$18,0)),0))) | U37: =IF(T37="","",IF(V37=0,"Everyone",IF(COUNTIF(AI37:AT37,">0")=COUNTIF(Setup!$B$9:$B$20,"?*"),"Everyone",COUNTIF(AI37:AT37,">0")&IF(COUNTIF(AI37:AT37,">0")=1," person"," people")))) | V37: =SUM(AI37:AT37) | W37: =IF(OR(T37="",Setup!$B$9=""),0,IF(V37=0,T37/COUNTIF(Setup!$B$9:$B$20,"?*"),T37*AI37/V37)) | X37: =IF(OR(T37="",Setup!$B$10=""),0,IF(V37=0,T37/COUNTIF(Setup!$B$9:$B$20,"?*"),T37*AJ37/V37)) | Y37: =IF(OR(T37="",Setup!$B$11=""),0,IF(V37=0,T37/COUNTIF(Setup!$B$9:$B$20,"?*"),T37*AK37/V37)) | Z37: =IF(OR(T37="",Setup!$B$12=""),0,IF(V37=0,T37/COUNTIF(Setup!$B$9:$B$20,"?*"),T37*AL37/V37)) | AA37: =IF(OR(T37="",Setup!$B$13=""),0,IF(V37=0,T37/COUNTIF(Setup!$B$9:$B$20,"?*"),T37*AM37/V37)) | AB37: =IF(OR(T37="",Setup!$B$14=""),0,IF(V37=0,T37/COUNTIF(Setup!$B$9:$B$20,"?*"),T37*AN37/V37)) | AC37: =IF(OR(T37="",Setup!$B$15=""),0,IF(V37=0,T37/COUNTIF(Setup!$B$9:$B$20,"?*"),T37*AO37/V37)) | AD37: =IF(OR(T37="",Setup!$B$16=""),0,IF(V37=0,T37/COUNTIF(Setup!$B$9:$B$20,"?*"),T37*AP37/V37)) | AE37: =IF(OR(T37="",Setup!$B$17=""),0,IF(V37=0,T37/COUNTIF(Setup!$B$9:$B$20,"?*"),T37*AQ37/V37)) | AF37: =IF(OR(T37="",Setup!$B$18=""),0,IF(V37=0,T37/COUNTIF(Setup!$B$9:$B$20,"?*"),T37*AR37/V37)) | AG37: =IF(OR(T37="",Setup!$B$19=""),0,IF(V37=0,T37/COUNTIF(Setup!$B$9:$B$20,"?*"),T37*AS37/V37)) | AH37: =IF(OR(T37="",Setup!$B$20=""),0,IF(V37=0,T37/COUNTIF(Setup!$B$9:$B$20,"?*"),T37*AT37/V37)) | AI37: =IF(Setup!$B$9="",0,IF(H37="",0,IF(ISNUMBER(H37),H37,1))) | AJ37: =IF(Setup!$B$10="",0,IF(I37="",0,IF(ISNUMBER(I37),I37,1))) | AK37: =IF(Setup!$B$11="",0,IF(J37="",0,IF(ISNUMBER(J37),J37,1))) | AL37: =IF(Setup!$B$12="",0,IF(K37="",0,IF(ISNUMBER(K37),K37,1))) | AM37: =IF(Setup!$B$13="",0,IF(L37="",0,IF(ISNUMBER(L37),L37,1))) | AN37: =IF(Setup!$B$14="",0,IF(M37="",0,IF(ISNUMBER(M37),M37,1))) | AO37: =IF(Setup!$B$15="",0,IF(N37="",0,IF(ISNUMBER(N37),N37,1))) | AP37: =IF(Setup!$B$16="",0,IF(O37="",0,IF(ISNUMBER(O37),O37,1))) | AQ37: =IF(Setup!$B$17="",0,IF(P37="",0,IF(ISNUMBER(P37),P37,1))) | AR37: =IF(Setup!$B$18="",0,IF(Q37="",0,IF(ISNUMBER(Q37),Q37,1))) | AS37: =IF(Setup!$B$19="",0,IF(R37="",0,IF(ISNUMBER(R37),R37,1))) | AT37: =IF(Setup!$B$20="",0,IF(S37="",0,IF(ISNUMBER(S37),S37,1)))
T38: =IF(N(E38)=0,"",E38*IF(F38="",1,IFERROR(INDEX(Setup!$E$9:$E$18,MATCH(F38,Setup!$D$9:$D$18,0)),0))) | U38: =IF(T38="","",IF(V38=0,"Everyone",IF(COUNTIF(AI38:AT38,">0")=COUNTIF(Setup!$B$9:$B$20,"?*"),"Everyone",COUNTIF(AI38:AT38,">0")&IF(COUNTIF(AI38:AT38,">0")=1," person"," people")))) | V38: =SUM(AI38:AT38) | W38: =IF(OR(T38="",Setup!$B$9=""),0,IF(V38=0,T38/COUNTIF(Setup!$B$9:$B$20,"?*"),T38*AI38/V38)) | X38: =IF(OR(T38="",Setup!$B$10=""),0,IF(V38=0,T38/COUNTIF(Setup!$B$9:$B$20,"?*"),T38*AJ38/V38)) | Y38: =IF(OR(T38="",Setup!$B$11=""),0,IF(V38=0,T38/COUNTIF(Setup!$B$9:$B$20,"?*"),T38*AK38/V38)) | Z38: =IF(OR(T38="",Setup!$B$12=""),0,IF(V38=0,T38/COUNTIF(Setup!$B$9:$B$20,"?*"),T38*AL38/V38)) | AA38: =IF(OR(T38="",Setup!$B$13=""),0,IF(V38=0,T38/COUNTIF(Setup!$B$9:$B$20,"?*"),T38*AM38/V38)) | AB38: =IF(OR(T38="",Setup!$B$14=""),0,IF(V38=0,T38/COUNTIF(Setup!$B$9:$B$20,"?*"),T38*AN38/V38)) | AC38: =IF(OR(T38="",Setup!$B$15=""),0,IF(V38=0,T38/COUNTIF(Setup!$B$9:$B$20,"?*"),T38*AO38/V38)) | AD38: =IF(OR(T38="",Setup!$B$16=""),0,IF(V38=0,T38/COUNTIF(Setup!$B$9:$B$20,"?*"),T38*AP38/V38)) | AE38: =IF(OR(T38="",Setup!$B$17=""),0,IF(V38=0,T38/COUNTIF(Setup!$B$9:$B$20,"?*"),T38*AQ38/V38)) | AF38: =IF(OR(T38="",Setup!$B$18=""),0,IF(V38=0,T38/COUNTIF(Setup!$B$9:$B$20,"?*"),T38*AR38/V38)) | AG38: =IF(OR(T38="",Setup!$B$19=""),0,IF(V38=0,T38/COUNTIF(Setup!$B$9:$B$20,"?*"),T38*AS38/V38)) | AH38: =IF(OR(T38="",Setup!$B$20=""),0,IF(V38=0,T38/COUNTIF(Setup!$B$9:$B$20,"?*"),T38*AT38/V38)) | AI38: =IF(Setup!$B$9="",0,IF(H38="",0,IF(ISNUMBER(H38),H38,1))) | AJ38: =IF(Setup!$B$10="",0,IF(I38="",0,IF(ISNUMBER(I38),I38,1))) | AK38: =IF(Setup!$B$11="",0,IF(J38="",0,IF(ISNUMBER(J38),J38,1))) | AL38: =IF(Setup!$B$12="",0,IF(K38="",0,IF(ISNUMBER(K38),K38,1))) | AM38: =IF(Setup!$B$13="",0,IF(L38="",0,IF(ISNUMBER(L38),L38,1))) | AN38: =IF(Setup!$B$14="",0,IF(M38="",0,IF(ISNUMBER(M38),M38,1))) | AO38: =IF(Setup!$B$15="",0,IF(N38="",0,IF(ISNUMBER(N38),N38,1))) | AP38: =IF(Setup!$B$16="",0,IF(O38="",0,IF(ISNUMBER(O38),O38,1))) | AQ38: =IF(Setup!$B$17="",0,IF(P38="",0,IF(ISNUMBER(P38),P38,1))) | AR38: =IF(Setup!$B$18="",0,IF(Q38="",0,IF(ISNUMBER(Q38),Q38,1))) | AS38: =IF(Setup!$B$19="",0,IF(R38="",0,IF(ISNUMBER(R38),R38,1))) | AT38: =IF(Setup!$B$20="",0,IF(S38="",0,IF(ISNUMBER(S38),S38,1)))
T39: =IF(N(E39)=0,"",E39*IF(F39="",1,IFERROR(INDEX(Setup!$E$9:$E$18,MATCH(F39,Setup!$D$9:$D$18,0)),0))) | U39: =IF(T39="","",IF(V39=0,"Everyone",IF(COUNTIF(AI39:AT39,">0")=COUNTIF(Setup!$B$9:$B$20,"?*"),"Everyone",COUNTIF(AI39:AT39,">0")&IF(COUNTIF(AI39:AT39,">0")=1," person"," people")))) | V39: =SUM(AI39:AT39) | W39: =IF(OR(T39="",Setup!$B$9=""),0,IF(V39=0,T39/COUNTIF(Setup!$B$9:$B$20,"?*"),T39*AI39/V39)) | X39: =IF(OR(T39="",Setup!$B$10=""),0,IF(V39=0,T39/COUNTIF(Setup!$B$9:$B$20,"?*"),T39*AJ39/V39)) | Y39: =IF(OR(T39="",Setup!$B$11=""),0,IF(V39=0,T39/COUNTIF(Setup!$B$9:$B$20,"?*"),T39*AK39/V39)) | Z39: =IF(OR(T39="",Setup!$B$12=""),0,IF(V39=0,T39/COUNTIF(Setup!$B$9:$B$20,"?*"),T39*AL39/V39)) | AA39: =IF(OR(T39="",Setup!$B$13=""),0,IF(V39=0,T39/COUNTIF(Setup!$B$9:$B$20,"?*"),T39*AM39/V39)) | AB39: =IF(OR(T39="",Setup!$B$14=""),0,IF(V39=0,T39/COUNTIF(Setup!$B$9:$B$20,"?*"),T39*AN39/V39)) | AC39: =IF(OR(T39="",Setup!$B$15=""),0,IF(V39=0,T39/COUNTIF(Setup!$B$9:$B$20,"?*"),T39*AO39/V39)) | AD39: =IF(OR(T39="",Setup!$B$16=""),0,IF(V39=0,T39/COUNTIF(Setup!$B$9:$B$20,"?*"),T39*AP39/V39)) | AE39: =IF(OR(T39="",Setup!$B$17=""),0,IF(V39=0,T39/COUNTIF(Setup!$B$9:$B$20,"?*"),T39*AQ39/V39)) | AF39: =IF(OR(T39="",Setup!$B$18=""),0,IF(V39=0,T39/COUNTIF(Setup!$B$9:$B$20,"?*"),T39*AR39/V39)) | AG39: =IF(OR(T39="",Setup!$B$19=""),0,IF(V39=0,T39/COUNTIF(Setup!$B$9:$B$20,"?*"),T39*AS39/V39)) | AH39: =IF(OR(T39="",Setup!$B$20=""),0,IF(V39=0,T39/COUNTIF(Setup!$B$9:$B$20,"?*"),T39*AT39/V39)) | AI39: =IF(Setup!$B$9="",0,IF(H39="",0,IF(ISNUMBER(H39),H39,1))) | AJ39: =IF(Setup!$B$10="",0,IF(I39="",0,IF(ISNUMBER(I39),I39,1))) | AK39: =IF(Setup!$B$11="",0,IF(J39="",0,IF(ISNUMBER(J39),J39,1))) | AL39: =IF(Setup!$B$12="",0,IF(K39="",0,IF(ISNUMBER(K39),K39,1))) | AM39: =IF(Setup!$B$13="",0,IF(L39="",0,IF(ISNUMBER(L39),L39,1))) | AN39: =IF(Setup!$B$14="",0,IF(M39="",0,IF(ISNUMBER(M39),M39,1))) | AO39: =IF(Setup!$B$15="",0,IF(N39="",0,IF(ISNUMBER(N39),N39,1))) | AP39: =IF(Setup!$B$16="",0,IF(O39="",0,IF(ISNUMBER(O39),O39,1))) | AQ39: =IF(Setup!$B$17="",0,IF(P39="",0,IF(ISNUMBER(P39),P39,1))) | AR39: =IF(Setup!$B$18="",0,IF(Q39="",0,IF(ISNUMBER(Q39),Q39,1))) | AS39: =IF(Setup!$B$19="",0,IF(R39="",0,IF(ISNUMBER(R39),R39,1))) | AT39: =IF(Setup!$B$20="",0,IF(S39="",0,IF(ISNUMBER(S39),S39,1)))
T40: =IF(N(E40)=0,"",E40*IF(F40="",1,IFERROR(INDEX(Setup!$E$9:$E$18,MATCH(F40,Setup!$D$9:$D$18,0)),0))) | U40: =IF(T40="","",IF(V40=0,"Everyone",IF(COUNTIF(AI40:AT40,">0")=COUNTIF(Setup!$B$9:$B$20,"?*"),"Everyone",COUNTIF(AI40:AT40,">0")&IF(COUNTIF(AI40:AT40,">0")=1," person"," people")))) | V40: =SUM(AI40:AT40) | W40: =IF(OR(T40="",Setup!$B$9=""),0,IF(V40=0,T40/COUNTIF(Setup!$B$9:$B$20,"?*"),T40*AI40/V40)) | X40: =IF(OR(T40="",Setup!$B$10=""),0,IF(V40=0,T40/COUNTIF(Setup!$B$9:$B$20,"?*"),T40*AJ40/V40)) | Y40: =IF(OR(T40="",Setup!$B$11=""),0,IF(V40=0,T40/COUNTIF(Setup!$B$9:$B$20,"?*"),T40*AK40/V40)) | Z40: =IF(OR(T40="",Setup!$B$12=""),0,IF(V40=0,T40/COUNTIF(Setup!$B$9:$B$20,"?*"),T40*AL40/V40)) | AA40: =IF(OR(T40="",Setup!$B$13=""),0,IF(V40=0,T40/COUNTIF(Setup!$B$9:$B$20,"?*"),T40*AM40/V40)) | AB40: =IF(OR(T40="",Setup!$B$14=""),0,IF(V40=0,T40/COUNTIF(Setup!$B$9:$B$20,"?*"),T40*AN40/V40)) | AC40: =IF(OR(T40="",Setup!$B$15=""),0,IF(V40=0,T40/COUNTIF(Setup!$B$9:$B$20,"?*"),T40*AO40/V40)) | AD40: =IF(OR(T40="",Setup!$B$16=""),0,IF(V40=0,T40/COUNTIF(Setup!$B$9:$B$20,"?*"),T40*AP40/V40)) | AE40: =IF(OR(T40="",Setup!$B$17=""),0,IF(V40=0,T40/COUNTIF(Setup!$B$9:$B$20,"?*"),T40*AQ40/V40)) | AF40: =IF(OR(T40="",Setup!$B$18=""),0,IF(V40=0,T40/COUNTIF(Setup!$B$9:$B$20,"?*"),T40*AR40/V40)) | AG40: =IF(OR(T40="",Setup!$B$19=""),0,IF(V40=0,T40/COUNTIF(Setup!$B$9:$B$20,"?*"),T40*AS40/V40)) | AH40: =IF(OR(T40="",Setup!$B$20=""),0,IF(V40=0,T40/COUNTIF(Setup!$B$9:$B$20,"?*"),T40*AT40/V40)) | AI40: =IF(Setup!$B$9="",0,IF(H40="",0,IF(ISNUMBER(H40),H40,1))) | AJ40: =IF(Setup!$B$10="",0,IF(I40="",0,IF(ISNUMBER(I40),I40,1))) | AK40: =IF(Setup!$B$11="",0,IF(J40="",0,IF(ISNUMBER(J40),J40,1))) | AL40: =IF(Setup!$B$12="",0,IF(K40="",0,IF(ISNUMBER(K40),K40,1))) | AM40: =IF(Setup!$B$13="",0,IF(L40="",0,IF(ISNUMBER(L40),L40,1))) | AN40: =IF(Setup!$B$14="",0,IF(M40="",0,IF(ISNUMBER(M40),M40,1))) | AO40: =IF(Setup!$B$15="",0,IF(N40="",0,IF(ISNUMBER(N40),N40,1))) | AP40: =IF(Setup!$B$16="",0,IF(O40="",0,IF(ISNUMBER(O40),O40,1))) | AQ40: =IF(Setup!$B$17="",0,IF(P40="",0,IF(ISNUMBER(P40),P40,1))) | AR40: =IF(Setup!$B$18="",0,IF(Q40="",0,IF(ISNUMBER(Q40),Q40,1))) | AS40: =IF(Setup!$B$19="",0,IF(R40="",0,IF(ISNUMBER(R40),R40,1))) | AT40: =IF(Setup!$B$20="",0,IF(S40="",0,IF(ISNUMBER(S40),S40,1)))
T41: =IF(N(E41)=0,"",E41*IF(F41="",1,IFERROR(INDEX(Setup!$E$9:$E$18,MATCH(F41,Setup!$D$9:$D$18,0)),0))) | U41: =IF(T41="","",IF(V41=0,"Everyone",IF(COUNTIF(AI41:AT41,">0")=COUNTIF(Setup!$B$9:$B$20,"?*"),"Everyone",COUNTIF(AI41:AT41,">0")&IF(COUNTIF(AI41:AT41,">0")=1," person"," people")))) | V41: =SUM(AI41:AT41) | W41: =IF(OR(T41="",Setup!$B$9=""),0,IF(V41=0,T41/COUNTIF(Setup!$B$9:$B$20,"?*"),T41*AI41/V41)) | X41: =IF(OR(T41="",Setup!$B$10=""),0,IF(V41=0,T41/COUNTIF(Setup!$B$9:$B$20,"?*"),T41*AJ41/V41)) | Y41: =IF(OR(T41="",Setup!$B$11=""),0,IF(V41=0,T41/COUNTIF(Setup!$B$9:$B$20,"?*"),T41*AK41/V41)) | Z41: =IF(OR(T41="",Setup!$B$12=""),0,IF(V41=0,T41/COUNTIF(Setup!$B$9:$B$20,"?*"),T41*AL41/V41)) | AA41: =IF(OR(T41="",Setup!$B$13=""),0,IF(V41=0,T41/COUNTIF(Setup!$B$9:$B$20,"?*"),T41*AM41/V41)) | AB41: =IF(OR(T41="",Setup!$B$14=""),0,IF(V41=0,T41/COUNTIF(Setup!$B$9:$B$20,"?*"),T41*AN41/V41)) | AC41: =IF(OR(T41="",Setup!$B$15=""),0,IF(V41=0,T41/COUNTIF(Setup!$B$9:$B$20,"?*"),T41*AO41/V41)) | AD41: =IF(OR(T41="",Setup!$B$16=""),0,IF(V41=0,T41/COUNTIF(Setup!$B$9:$B$20,"?*"),T41*AP41/V41)) | AE41: =IF(OR(T41="",Setup!$B$17=""),0,IF(V41=0,T41/COUNTIF(Setup!$B$9:$B$20,"?*"),T41*AQ41/V41)) | AF41: =IF(OR(T41="",Setup!$B$18=""),0,IF(V41=0,T41/COUNTIF(Setup!$B$9:$B$20,"?*"),T41*AR41/V41)) | AG41: =IF(OR(T41="",Setup!$B$19=""),0,IF(V41=0,T41/COUNTIF(Setup!$B$9:$B$20,"?*"),T41*AS41/V41)) | AH41: =IF(OR(T41="",Setup!$B$20=""),0,IF(V41=0,T41/COUNTIF(Setup!$B$9:$B$20,"?*"),T41*AT41/V41)) | AI41: =IF(Setup!$B$9="",0,IF(H41="",0,IF(ISNUMBER(H41),H41,1))) | AJ41: =IF(Setup!$B$10="",0,IF(I41="",0,IF(ISNUMBER(I41),I41,1))) | AK41: =IF(Setup!$B$11="",0,IF(J41="",0,IF(ISNUMBER(J41),J41,1))) | AL41: =IF(Setup!$B$12="",0,IF(K41="",0,IF(ISNUMBER(K41),K41,1))) | AM41: =IF(Setup!$B$13="",0,IF(L41="",0,IF(ISNUMBER(L41),L41,1))) | AN41: =IF(Setup!$B$14="",0,IF(M41="",0,IF(ISNUMBER(M41),M41,1))) | AO41: =IF(Setup!$B$15="",0,IF(N41="",0,IF(ISNUMBER(N41),N41,1))) | AP41: =IF(Setup!$B$16="",0,IF(O41="",0,IF(ISNUMBER(O41),O41,1))) | AQ41: =IF(Setup!$B$17="",0,IF(P41="",0,IF(ISNUMBER(P41),P41,1))) | AR41: =IF(Setup!$B$18="",0,IF(Q41="",0,IF(ISNUMBER(Q41),Q41,1))) | AS41: =IF(Setup!$B$19="",0,IF(R41="",0,IF(ISNUMBER(R41),R41,1))) | AT41: =IF(Setup!$B$20="",0,IF(S41="",0,IF(ISNUMBER(S41),S41,1)))
T42: =IF(N(E42)=0,"",E42*IF(F42="",1,IFERROR(INDEX(Setup!$E$9:$E$18,MATCH(F42,Setup!$D$9:$D$18,0)),0))) | U42: =IF(T42="","",IF(V42=0,"Everyone",IF(COUNTIF(AI42:AT42,">0")=COUNTIF(Setup!$B$9:$B$20,"?*"),"Everyone",COUNTIF(AI42:AT42,">0")&IF(COUNTIF(AI42:AT42,">0")=1," person"," people")))) | V42: =SUM(AI42:AT42) | W42: =IF(OR(T42="",Setup!$B$9=""),0,IF(V42=0,T42/COUNTIF(Setup!$B$9:$B$20,"?*"),T42*AI42/V42)) | X42: =IF(OR(T42="",Setup!$B$10=""),0,IF(V42=0,T42/COUNTIF(Setup!$B$9:$B$20,"?*"),T42*AJ42/V42)) | Y42: =IF(OR(T42="",Setup!$B$11=""),0,IF(V42=0,T42/COUNTIF(Setup!$B$9:$B$20,"?*"),T42*AK42/V42)) | Z42: =IF(OR(T42="",Setup!$B$12=""),0,IF(V42=0,T42/COUNTIF(Setup!$B$9:$B$20,"?*"),T42*AL42/V42)) | AA42: =IF(OR(T42="",Setup!$B$13=""),0,IF(V42=0,T42/COUNTIF(Setup!$B$9:$B$20,"?*"),T42*AM42/V42)) | AB42: =IF(OR(T42="",Setup!$B$14=""),0,IF(V42=0,T42/COUNTIF(Setup!$B$9:$B$20,"?*"),T42*AN42/V42)) | AC42: =IF(OR(T42="",Setup!$B$15=""),0,IF(V42=0,T42/COUNTIF(Setup!$B$9:$B$20,"?*"),T42*AO42/V42)) | AD42: =IF(OR(T42="",Setup!$B$16=""),0,IF(V42=0,T42/COUNTIF(Setup!$B$9:$B$20,"?*"),T42*AP42/V42)) | AE42: =IF(OR(T42="",Setup!$B$17=""),0,IF(V42=0,T42/COUNTIF(Setup!$B$9:$B$20,"?*"),T42*AQ42/V42)) | AF42: =IF(OR(T42="",Setup!$B$18=""),0,IF(V42=0,T42/COUNTIF(Setup!$B$9:$B$20,"?*"),T42*AR42/V42)) | AG42: =IF(OR(T42="",Setup!$B$19=""),0,IF(V42=0,T42/COUNTIF(Setup!$B$9:$B$20,"?*"),T42*AS42/V42)) | AH42: =IF(OR(T42="",Setup!$B$20=""),0,IF(V42=0,T42/COUNTIF(Setup!$B$9:$B$20,"?*"),T42*AT42/V42)) | AI42: =IF(Setup!$B$9="",0,IF(H42="",0,IF(ISNUMBER(H42),H42,1))) | AJ42: =IF(Setup!$B$10="",0,IF(I42="",0,IF(ISNUMBER(I42),I42,1))) | AK42: =IF(Setup!$B$11="",0,IF(J42="",0,IF(ISNUMBER(J42),J42,1))) | AL42: =IF(Setup!$B$12="",0,IF(K42="",0,IF(ISNUMBER(K42),K42,1))) | AM42: =IF(Setup!$B$13="",0,IF(L42="",0,IF(ISNUMBER(L42),L42,1))) | AN42: =IF(Setup!$B$14="",0,IF(M42="",0,IF(ISNUMBER(M42),M42,1))) | AO42: =IF(Setup!$B$15="",0,IF(N42="",0,IF(ISNUMBER(N42),N42,1))) | AP42: =IF(Setup!$B$16="",0,IF(O42="",0,IF(ISNUMBER(O42),O42,1))) | AQ42: =IF(Setup!$B$17="",0,IF(P42="",0,IF(ISNUMBER(P42),P42,1))) | AR42: =IF(Setup!$B$18="",0,IF(Q42="",0,IF(ISNUMBER(Q42),Q42,1))) | AS42: =IF(Setup!$B$19="",0,IF(R42="",0,IF(ISNUMBER(R42),R42,1))) | AT42: =IF(Setup!$B$20="",0,IF(S42="",0,IF(ISNUMBER(S42),S42,1)))
T43: =IF(N(E43)=0,"",E43*IF(F43="",1,IFERROR(INDEX(Setup!$E$9:$E$18,MATCH(F43,Setup!$D$9:$D$18,0)),0))) | U43: =IF(T43="","",IF(V43=0,"Everyone",IF(COUNTIF(AI43:AT43,">0")=COUNTIF(Setup!$B$9:$B$20,"?*"),"Everyone",COUNTIF(AI43:AT43,">0")&IF(COUNTIF(AI43:AT43,">0")=1," person"," people")))) | V43: =SUM(AI43:AT43) | W43: =IF(OR(T43="",Setup!$B$9=""),0,IF(V43=0,T43/COUNTIF(Setup!$B$9:$B$20,"?*"),T43*AI43/V43)) | X43: =IF(OR(T43="",Setup!$B$10=""),0,IF(V43=0,T43/COUNTIF(Setup!$B$9:$B$20,"?*"),T43*AJ43/V43)) | Y43: =IF(OR(T43="",Setup!$B$11=""),0,IF(V43=0,T43/COUNTIF(Setup!$B$9:$B$20,"?*"),T43*AK43/V43)) | Z43: =IF(OR(T43="",Setup!$B$12=""),0,IF(V43=0,T43/COUNTIF(Setup!$B$9:$B$20,"?*"),T43*AL43/V43)) | AA43: =IF(OR(T43="",Setup!$B$13=""),0,IF(V43=0,T43/COUNTIF(Setup!$B$9:$B$20,"?*"),T43*AM43/V43)) | AB43: =IF(OR(T43="",Setup!$B$14=""),0,IF(V43=0,T43/COUNTIF(Setup!$B$9:$B$20,"?*"),T43*AN43/V43)) | AC43: =IF(OR(T43="",Setup!$B$15=""),0,IF(V43=0,T43/COUNTIF(Setup!$B$9:$B$20,"?*"),T43*AO43/V43)) | AD43: =IF(OR(T43="",Setup!$B$16=""),0,IF(V43=0,T43/COUNTIF(Setup!$B$9:$B$20,"?*"),T43*AP43/V43)) | AE43: =IF(OR(T43="",Setup!$B$17=""),0,IF(V43=0,T43/COUNTIF(Setup!$B$9:$B$20,"?*"),T43*AQ43/V43)) | AF43: =IF(OR(T43="",Setup!$B$18=""),0,IF(V43=0,T43/COUNTIF(Setup!$B$9:$B$20,"?*"),T43*AR43/V43)) | AG43: =IF(OR(T43="",Setup!$B$19=""),0,IF(V43=0,T43/COUNTIF(Setup!$B$9:$B$20,"?*"),T43*AS43/V43)) | AH43: =IF(OR(T43="",Setup!$B$20=""),0,IF(V43=0,T43/COUNTIF(Setup!$B$9:$B$20,"?*"),T43*AT43/V43)) | AI43: =IF(Setup!$B$9="",0,IF(H43="",0,IF(ISNUMBER(H43),H43,1))) | AJ43: =IF(Setup!$B$10="",0,IF(I43="",0,IF(ISNUMBER(I43),I43,1))) | AK43: =IF(Setup!$B$11="",0,IF(J43="",0,IF(ISNUMBER(J43),J43,1))) | AL43: =IF(Setup!$B$12="",0,IF(K43="",0,IF(ISNUMBER(K43),K43,1))) | AM43: =IF(Setup!$B$13="",0,IF(L43="",0,IF(ISNUMBER(L43),L43,1))) | AN43: =IF(Setup!$B$14="",0,IF(M43="",0,IF(ISNUMBER(M43),M43,1))) | AO43: =IF(Setup!$B$15="",0,IF(N43="",0,IF(ISNUMBER(N43),N43,1))) | AP43: =IF(Setup!$B$16="",0,IF(O43="",0,IF(ISNUMBER(O43),O43,1))) | AQ43: =IF(Setup!$B$17="",0,IF(P43="",0,IF(ISNUMBER(P43),P43,1))) | AR43: =IF(Setup!$B$18="",0,IF(Q43="",0,IF(ISNUMBER(Q43),Q43,1))) | AS43: =IF(Setup!$B$19="",0,IF(R43="",0,IF(ISNUMBER(R43),R43,1))) | AT43: =IF(Setup!$B$20="",0,IF(S43="",0,IF(ISNUMBER(S43),S43,1)))
T44: =IF(N(E44)=0,"",E44*IF(F44="",1,IFERROR(INDEX(Setup!$E$9:$E$18,MATCH(F44,Setup!$D$9:$D$18,0)),0))) | U44: =IF(T44="","",IF(V44=0,"Everyone",IF(COUNTIF(AI44:AT44,">0")=COUNTIF(Setup!$B$9:$B$20,"?*"),"Everyone",COUNTIF(AI44:AT44,">0")&IF(COUNTIF(AI44:AT44,">0")=1," person"," people")))) | V44: =SUM(AI44:AT44) | W44: =IF(OR(T44="",Setup!$B$9=""),0,IF(V44=0,T44/COUNTIF(Setup!$B$9:$B$20,"?*"),T44*AI44/V44)) | X44: =IF(OR(T44="",Setup!$B$10=""),0,IF(V44=0,T44/COUNTIF(Setup!$B$9:$B$20,"?*"),T44*AJ44/V44)) | Y44: =IF(OR(T44="",Setup!$B$11=""),0,IF(V44=0,T44/COUNTIF(Setup!$B$9:$B$20,"?*"),T44*AK44/V44)) | Z44: =IF(OR(T44="",Setup!$B$12=""),0,IF(V44=0,T44/COUNTIF(Setup!$B$9:$B$20,"?*"),T44*AL44/V44)) | AA44: =IF(OR(T44="",Setup!$B$13=""),0,IF(V44=0,T44/COUNTIF(Setup!$B$9:$B$20,"?*"),T44*AM44/V44)) | AB44: =IF(OR(T44="",Setup!$B$14=""),0,IF(V44=0,T44/COUNTIF(Setup!$B$9:$B$20,"?*"),T44*AN44/V44)) | AC44: =IF(OR(T44="",Setup!$B$15=""),0,IF(V44=0,T44/COUNTIF(Setup!$B$9:$B$20,"?*"),T44*AO44/V44)) | AD44: =IF(OR(T44="",Setup!$B$16=""),0,IF(V44=0,T44/COUNTIF(Setup!$B$9:$B$20,"?*"),T44*AP44/V44)) | AE44: =IF(OR(T44="",Setup!$B$17=""),0,IF(V44=0,T44/COUNTIF(Setup!$B$9:$B$20,"?*"),T44*AQ44/V44)) | AF44: =IF(OR(T44="",Setup!$B$18=""),0,IF(V44=0,T44/COUNTIF(Setup!$B$9:$B$20,"?*"),T44*AR44/V44)) | AG44: =IF(OR(T44="",Setup!$B$19=""),0,IF(V44=0,T44/COUNTIF(Setup!$B$9:$B$20,"?*"),T44*AS44/V44)) | AH44: =IF(OR(T44="",Setup!$B$20=""),0,IF(V44=0,T44/COUNTIF(Setup!$B$9:$B$20,"?*"),T44*AT44/V44)) | AI44: =IF(Setup!$B$9="",0,IF(H44="",0,IF(ISNUMBER(H44),H44,1))) | AJ44: =IF(Setup!$B$10="",0,IF(I44="",0,IF(ISNUMBER(I44),I44,1))) | AK44: =IF(Setup!$B$11="",0,IF(J44="",0,IF(ISNUMBER(J44),J44,1))) | AL44: =IF(Setup!$B$12="",0,IF(K44="",0,IF(ISNUMBER(K44),K44,1))) | AM44: =IF(Setup!$B$13="",0,IF(L44="",0,IF(ISNUMBER(L44),L44,1))) | AN44: =IF(Setup!$B$14="",0,IF(M44="",0,IF(ISNUMBER(M44),M44,1))) | AO44: =IF(Setup!$B$15="",0,IF(N44="",0,IF(ISNUMBER(N44),N44,1))) | AP44: =IF(Setup!$B$16="",0,IF(O44="",0,IF(ISNUMBER(O44),O44,1))) | AQ44: =IF(Setup!$B$17="",0,IF(P44="",0,IF(ISNUMBER(P44),P44,1))) | AR44: =IF(Setup!$B$18="",0,IF(Q44="",0,IF(ISNUMBER(Q44),Q44,1))) | AS44: =IF(Setup!$B$19="",0,IF(R44="",0,IF(ISNUMBER(R44),R44,1))) | AT44: =IF(Setup!$B$20="",0,IF(S44="",0,IF(ISNUMBER(S44),S44,1)))
... T505: =IF(N(E505)=0,"",E505*IF(F505="",1,IFERROR(INDEX(Setup!$E$9:$E$18,MATCH(F505,Setup!$D$9:$D$18,0)),0))) | U505: =IF(T505="","",IF(V505=0,"Everyone",IF(COUNTIF(AI505:AT505,">0")=COUNTIF(Setup!$B$9:$B$20,"?*"),"Everyone",COUNTIF(AI505:AT505,">0")&IF(COUNTIF(AI505:AT505,">0")=1," person"," people")))) | V505: =SUM(AI505:AT505) | W505: =IF(OR(T505="",Setup!$B$9=""),0,IF(V505=0,T505/COUNTIF(Setup!$B$9:$B$20,"?*"),T505*AI505/V505)) | X505: =IF(OR(T505="",Setup!$B$10=""),0,IF(V505=0,T505/COUNTIF(Setup!$B$9:$B$20,"?*"),T505*AJ505/V505)) | Y505: =IF(OR(T505="",Setup!$B$11=""),0,IF(V505=0,T505/COUNTIF(Setup!$B$9:$B$20,"?*"),T505*AK505/V505)) | Z505: =IF(OR(T505="",Setup!$B$12=""),0,IF(V505=0,T505/COUNTIF(Setup!$B$9:$B$20,"?*"),T505*AL505/V505)) | AA505: =IF(OR(T505="",Setup!$B$13=""),0,IF(V505=0,T505/COUNTIF(Setup!$B$9:$B$20,"?*"),T505*AM505/V505)) | AB505: =IF(OR(T505="",Setup!$B$14=""),0,IF(V505=0,T505/COUNTIF(Setup!$B$9:$B$20,"?*"),T505*AN505/V505)) | AC505: =IF(OR(T505="",Setup!$B$15=""),0,IF(V505=0,T505/COUNTIF(Setup!$B$9:$B$20,"?*"),T505*AO505/V505)) | AD505: =IF(OR(T505="",Setup!$B$16=""),0,IF(V505=0,T505/COUNTIF(Setup!$B$9:$B$20,"?*"),T505*AP505/V505)) | AE505: =IF(OR(T505="",Setup!$B$17=""),0,IF(V505=0,T505/COUNTIF(Setup!$B$9:$B$20,"?*"),T505*AQ505/V505)) | AF505: =IF(OR(T505="",Setup!$B$18=""),0,IF(V505=0,T505/COUNTIF(Setup!$B$9:$B$20,"?*"),T505*AR505/V505)) | AG505: =IF(OR(T505="",Setup!$B$19=""),0,IF(V505=0,T505/COUNTIF(Setup!$B$9:$B$20,"?*"),T505*AS505/V505)) | AH505: =IF(OR(T505="",Setup!$B$20=""),0,IF(V505=0,T505/COUNTIF(Setup!$B$9:$B$20,"?*"),T505*AT505/V505)) | AI505: =IF(Setup!$B$9="",0,IF(H505="",0,IF(ISNUMBER(H505),H505,1))) | AJ505: =IF(Setup!$B$10="",0,IF(I505="",0,IF(ISNUMBER(I505),I505,1))) | AK505: =IF(Setup!$B$11="",0,IF(J505="",0,IF(ISNUMBER(J505),J505,1))) | AL505: =IF(Setup!$B$12="",0,IF(K505="",0,IF(ISNUMBER(K505),K505,1))) | AM505: =IF(Setup!$B$13="",0,IF(L505="",0,IF(ISNUMBER(L505),L505,1))) | AN505: =IF(Setup!$B$14="",0,IF(M505="",0,IF(ISNUMBER(M505),M505,1))) | AO505: =IF(Setup!$B$15="",0,IF(N505="",0,IF(ISNUMBER(N505),N505,1))) | AP505: =IF(Setup!$B$16="",0,IF(O505="",0,IF(ISNUMBER(O505),O505,1))) | AQ505: =IF(Setup!$B$17="",0,IF(P505="",0,IF(ISNUMBER(P505),P505,1))) | AR505: =IF(Setup!$B$18="",0,IF(Q505="",0,IF(ISNUMBER(Q505),Q505,1))) | AS505: =IF(Setup!$B$19="",0,IF(R505="",0,IF(ISNUMBER(R505),R505,1))) | AT505: =IF(Setup!$B$20="",0,IF(S505="",0,IF(ISNUMBER(S505),S505,1)))

Sheet Start Here
B2: Start here
B3: Type only in the yellow cells. Everything else is calculated.
B5: 1 | C5: Setup: the trip's name, your home currency, the people on the trip and what other currencies are worth.
B7: 2 | C7: Expenses: one line per expense, with the amount, currency and who paid.
B9: 3 | C9: Leave the shares empty to split an expense between everyone. Or put an x under the people who share it.
B11: 4 | C11: A number instead of an x gives someone more shares, for example 2 for someone who had two tickets.
B13: 5 | C13: Dashboard: what each person paid, their share, their balance, and who pays whom to settle up.
C16: When someone pays another person back, add it as an expense in the category Paying back, paid by the one who pays, with an x under the one who gets the money.
C18: The example trip shows how it works. Delete it and start with your own.
C20: Works in Google Sheets and Microsoft Excel, with any currencies.
