Workbook

Sheet Dashboard
B2: Client dashboard
B3: This month, what is coming up, and who needs a message.
B5: Paid this month | D5: Done this month | E5: Booked ahead | F5: No-shows | G5: Owed to you | I5: Clients | J5: Visits this year | K5: Paid this year
B6: =SUMIFS(Appointments!$I$6:$I$2005,Appointments!$B$6:$B$2005,">="&DATE(YEAR(TODAY()),MONTH(TODAY()),1),Appointments!$B$6:$B$2005,"<="&EOMONTH(TODAY(),0))+SUMIFS(Packages!$F$6:$F$305,Packages!$B$6:$B$305,">="&DATE(YEAR(TODAY()),MONTH(TODAY()),1),Packages!$B$6:$B$305,"<="&EOMONTH(TODAY(),0)) | D6: =COUNTIFS(Appointments!$F$6:$F$2005,"Done",Appointments!$B$6:$B$2005,">="&DATE(YEAR(TODAY()),MONTH(TODAY()),1),Appointments!$B$6:$B$2005,"<="&EOMONTH(TODAY(),0)) | E6: =COUNTIFS(Appointments!$F$6:$F$2005,"Booked",Appointments!$B$6:$B$2005,">="&TODAY()) | F6: =COUNTIFS(Appointments!$F$6:$F$2005,"No-show",Appointments!$B$6:$B$2005,">="&DATE(YEAR(TODAY()),MONTH(TODAY()),1),Appointments!$B$6:$B$2005,"<="&EOMONTH(TODAY(),0)) | G6: =SUM(Appointments!$K$6:$K$2005) | I6: =COUNTIF(Clients!$B$6:$B$305,"?*") | J6: =COUNTIFS(Appointments!$F$6:$F$2005,"Done",Appointments!$B$6:$B$2005,">="&DATE(YEAR(TODAY()),1,1)) | K6: =SUMIFS(Appointments!$I$6:$I$2005,Appointments!$B$6:$B$2005,">="&DATE(YEAR(TODAY()),1,1))+SUMIFS(Packages!$F$6:$F$305,Packages!$B$6:$B$305,">="&DATE(YEAR(TODAY()),1,1))
B8: Coming up
B9: Date | C9: Time | D9: Client | E9: Service | I9: Needs attention
B10: =IF(O10="","",INT(O10)) | C10: =IF(O10="","",INDEX(Appointments!$C$6:$C$2005,MATCH(O10,Appointments!$M$6:$M$2005,0))) | D10: =IF(O10="","",INDEX(Appointments!$D$6:$D$2005,MATCH(O10,Appointments!$M$6:$M$2005,0))) | E10: =IF(O10="","",INDEX(Appointments!$E$6:$E$2005,MATCH(O10,Appointments!$M$6:$M$2005,0))) | I10: =IF(COUNTIFS(Appointments!$F$6:$F$2005,"Booked",Appointments!$B$6:$B$2005,"<"&TODAY())=0,"Every past appointment has its status",IF(COUNTIFS(Appointments!$F$6:$F$2005,"Booked",Appointments!$B$6:$B$2005,"<"&TODAY())=1,"1 past appointment is",COUNTIFS(Appointments!$F$6:$F$2005,"Booked",Appointments!$B$6:$B$2005,"<"&TODAY())&" past appointments are")&" still marked Booked") | O10: =IFERROR(SMALL(Appointments!$M$6:$M$2005,COUNTIF(Appointments!$M$6:$M$2005,"<"&NOW())+1),"")
B11: =IF(O11="","",INT(O11)) | C11: =IF(O11="","",INDEX(Appointments!$C$6:$C$2005,MATCH(O11,Appointments!$M$6:$M$2005,0))) | D11: =IF(O11="","",INDEX(Appointments!$D$6:$D$2005,MATCH(O11,Appointments!$M$6:$M$2005,0))) | E11: =IF(O11="","",INDEX(Appointments!$E$6:$E$2005,MATCH(O11,Appointments!$M$6:$M$2005,0))) | I11: =IF(COUNTIFS(Clients!$L$6:$L$305,">0")=0,"Nobody owes you money",IF(COUNTIFS(Clients!$L$6:$L$305,">0")=1,"1 client owes you ",COUNTIFS(Clients!$L$6:$L$305,">0")&" clients owe you ")&FIXED(SUM(Clients!$L$6:$L$305),2)) | O11: =IFERROR(SMALL(Appointments!$M$6:$M$2005,COUNTIF(Appointments!$M$6:$M$2005,"<"&NOW())+2),"")
B12: =IF(O12="","",INT(O12)) | C12: =IF(O12="","",INDEX(Appointments!$C$6:$C$2005,MATCH(O12,Appointments!$M$6:$M$2005,0))) | D12: =IF(O12="","",INDEX(Appointments!$D$6:$D$2005,MATCH(O12,Appointments!$M$6:$M$2005,0))) | E12: =IF(O12="","",INDEX(Appointments!$E$6:$E$2005,MATCH(O12,Appointments!$M$6:$M$2005,0))) | I12: =IF(COUNTIFS(Clients!$M$6:$M$305,"<=1")=0,"No package is running out",IF(COUNTIFS(Clients!$M$6:$M$305,"<=1")=1,"1 client has",COUNTIFS(Clients!$M$6:$M$305,"<=1")&" clients have")&" 1 package session left or none") | O12: =IFERROR(SMALL(Appointments!$M$6:$M$2005,COUNTIF(Appointments!$M$6:$M$2005,"<"&NOW())+3),"")
B13: =IF(O13="","",INT(O13)) | C13: =IF(O13="","",INDEX(Appointments!$C$6:$C$2005,MATCH(O13,Appointments!$M$6:$M$2005,0))) | D13: =IF(O13="","",INDEX(Appointments!$D$6:$D$2005,MATCH(O13,Appointments!$M$6:$M$2005,0))) | E13: =IF(O13="","",INDEX(Appointments!$E$6:$E$2005,MATCH(O13,Appointments!$M$6:$M$2005,0))) | I13: =IF(COUNTIFS(Clients!$N$6:$N$305,"Not seen*")=0,"Every regular client has been back lately",IF(COUNTIFS(Clients!$N$6:$N$305,"Not seen*")=1,"1 client has not",COUNTIFS(Clients!$N$6:$N$305,"Not seen*")&" clients have not")&" been back in "&Services!$I$7&" days") | O13: =IFERROR(SMALL(Appointments!$M$6:$M$2005,COUNTIF(Appointments!$M$6:$M$2005,"<"&NOW())+4),"")
B14: =IF(O14="","",INT(O14)) | C14: =IF(O14="","",INDEX(Appointments!$C$6:$C$2005,MATCH(O14,Appointments!$M$6:$M$2005,0))) | D14: =IF(O14="","",INDEX(Appointments!$D$6:$D$2005,MATCH(O14,Appointments!$M$6:$M$2005,0))) | E14: =IF(O14="","",INDEX(Appointments!$E$6:$E$2005,MATCH(O14,Appointments!$M$6:$M$2005,0))) | I14: =IF(COUNTIFS(Clients!$O$6:$O$305,MONTH(TODAY()))=0,"No birthdays this month",IF(COUNTIFS(Clients!$O$6:$O$305,MONTH(TODAY()))=1,"1 client has a birthday",COUNTIFS(Clients!$O$6:$O$305,MONTH(TODAY()))&" clients have a birthday")&" this month") | O14: =IFERROR(SMALL(Appointments!$M$6:$M$2005,COUNTIF(Appointments!$M$6:$M$2005,"<"&NOW())+5),"")
B15: =IF(O15="","",INT(O15)) | C15: =IF(O15="","",INDEX(Appointments!$C$6:$C$2005,MATCH(O15,Appointments!$M$6:$M$2005,0))) | D15: =IF(O15="","",INDEX(Appointments!$D$6:$D$2005,MATCH(O15,Appointments!$M$6:$M$2005,0))) | E15: =IF(O15="","",INDEX(Appointments!$E$6:$E$2005,MATCH(O15,Appointments!$M$6:$M$2005,0))) | O15: =IFERROR(SMALL(Appointments!$M$6:$M$2005,COUNTIF(Appointments!$M$6:$M$2005,"<"&NOW())+6),"")
B16: =IF(O16="","",INT(O16)) | C16: =IF(O16="","",INDEX(Appointments!$C$6:$C$2005,MATCH(O16,Appointments!$M$6:$M$2005,0))) | D16: =IF(O16="","",INDEX(Appointments!$D$6:$D$2005,MATCH(O16,Appointments!$M$6:$M$2005,0))) | E16: =IF(O16="","",INDEX(Appointments!$E$6:$E$2005,MATCH(O16,Appointments!$M$6:$M$2005,0))) | O16: =IFERROR(SMALL(Appointments!$M$6:$M$2005,COUNTIF(Appointments!$M$6:$M$2005,"<"&NOW())+7),"")
B17: =IF(O17="","",INT(O17)) | C17: =IF(O17="","",INDEX(Appointments!$C$6:$C$2005,MATCH(O17,Appointments!$M$6:$M$2005,0))) | D17: =IF(O17="","",INDEX(Appointments!$D$6:$D$2005,MATCH(O17,Appointments!$M$6:$M$2005,0))) | E17: =IF(O17="","",INDEX(Appointments!$E$6:$E$2005,MATCH(O17,Appointments!$M$6:$M$2005,0))) | O17: =IFERROR(SMALL(Appointments!$M$6:$M$2005,COUNTIF(Appointments!$M$6:$M$2005,"<"&NOW())+8),"")
B18: =IF(O18="","",INT(O18)) | C18: =IF(O18="","",INDEX(Appointments!$C$6:$C$2005,MATCH(O18,Appointments!$M$6:$M$2005,0))) | D18: =IF(O18="","",INDEX(Appointments!$D$6:$D$2005,MATCH(O18,Appointments!$M$6:$M$2005,0))) | E18: =IF(O18="","",INDEX(Appointments!$E$6:$E$2005,MATCH(O18,Appointments!$M$6:$M$2005,0))) | O18: =IFERROR(SMALL(Appointments!$M$6:$M$2005,COUNTIF(Appointments!$M$6:$M$2005,"<"&NOW())+9),"")
B19: =IF(O19="","",INT(O19)) | C19: =IF(O19="","",INDEX(Appointments!$C$6:$C$2005,MATCH(O19,Appointments!$M$6:$M$2005,0))) | D19: =IF(O19="","",INDEX(Appointments!$D$6:$D$2005,MATCH(O19,Appointments!$M$6:$M$2005,0))) | E19: =IF(O19="","",INDEX(Appointments!$E$6:$E$2005,MATCH(O19,Appointments!$M$6:$M$2005,0))) | O19: =IFERROR(SMALL(Appointments!$M$6:$M$2005,COUNTIF(Appointments!$M$6:$M$2005,"<"&NOW())+10),"")
B22: Year | C22: 2026
B24: Month | C24: Done | D24: No-shows | E24: Appointments paid | F24: Packages sold | G24: Total
B25: Jan | C25: =COUNTIFS(Appointments!$F$6:$F$2005,"Done",Appointments!$B$6:$B$2005,">="&DATE($C$22,1,1),Appointments!$B$6:$B$2005,"<="&EOMONTH(DATE($C$22,1,1),0)) | D25: =COUNTIFS(Appointments!$F$6:$F$2005,"No-show",Appointments!$B$6:$B$2005,">="&DATE($C$22,1,1),Appointments!$B$6:$B$2005,"<="&EOMONTH(DATE($C$22,1,1),0)) | E25: =SUMIFS(Appointments!$I$6:$I$2005,Appointments!$B$6:$B$2005,">="&DATE($C$22,1,1),Appointments!$B$6:$B$2005,"<="&EOMONTH(DATE($C$22,1,1),0)) | F25: =SUMIFS(Packages!$F$6:$F$305,Packages!$B$6:$B$305,">="&DATE($C$22,1,1),Packages!$B$6:$B$305,"<="&EOMONTH(DATE($C$22,1,1),0)) | G25: =E25+F25
B26: Feb | C26: =COUNTIFS(Appointments!$F$6:$F$2005,"Done",Appointments!$B$6:$B$2005,">="&DATE($C$22,2,1),Appointments!$B$6:$B$2005,"<="&EOMONTH(DATE($C$22,2,1),0)) | D26: =COUNTIFS(Appointments!$F$6:$F$2005,"No-show",Appointments!$B$6:$B$2005,">="&DATE($C$22,2,1),Appointments!$B$6:$B$2005,"<="&EOMONTH(DATE($C$22,2,1),0)) | E26: =SUMIFS(Appointments!$I$6:$I$2005,Appointments!$B$6:$B$2005,">="&DATE($C$22,2,1),Appointments!$B$6:$B$2005,"<="&EOMONTH(DATE($C$22,2,1),0)) | F26: =SUMIFS(Packages!$F$6:$F$305,Packages!$B$6:$B$305,">="&DATE($C$22,2,1),Packages!$B$6:$B$305,"<="&EOMONTH(DATE($C$22,2,1),0)) | G26: =E26+F26
B27: Mar | C27: =COUNTIFS(Appointments!$F$6:$F$2005,"Done",Appointments!$B$6:$B$2005,">="&DATE($C$22,3,1),Appointments!$B$6:$B$2005,"<="&EOMONTH(DATE($C$22,3,1),0)) | D27: =COUNTIFS(Appointments!$F$6:$F$2005,"No-show",Appointments!$B$6:$B$2005,">="&DATE($C$22,3,1),Appointments!$B$6:$B$2005,"<="&EOMONTH(DATE($C$22,3,1),0)) | E27: =SUMIFS(Appointments!$I$6:$I$2005,Appointments!$B$6:$B$2005,">="&DATE($C$22,3,1),Appointments!$B$6:$B$2005,"<="&EOMONTH(DATE($C$22,3,1),0)) | F27: =SUMIFS(Packages!$F$6:$F$305,Packages!$B$6:$B$305,">="&DATE($C$22,3,1),Packages!$B$6:$B$305,"<="&EOMONTH(DATE($C$22,3,1),0)) | G27: =E27+F27
B28: Apr | C28: =COUNTIFS(Appointments!$F$6:$F$2005,"Done",Appointments!$B$6:$B$2005,">="&DATE($C$22,4,1),Appointments!$B$6:$B$2005,"<="&EOMONTH(DATE($C$22,4,1),0)) | D28: =COUNTIFS(Appointments!$F$6:$F$2005,"No-show",Appointments!$B$6:$B$2005,">="&DATE($C$22,4,1),Appointments!$B$6:$B$2005,"<="&EOMONTH(DATE($C$22,4,1),0)) | E28: =SUMIFS(Appointments!$I$6:$I$2005,Appointments!$B$6:$B$2005,">="&DATE($C$22,4,1),Appointments!$B$6:$B$2005,"<="&EOMONTH(DATE($C$22,4,1),0)) | F28: =SUMIFS(Packages!$F$6:$F$305,Packages!$B$6:$B$305,">="&DATE($C$22,4,1),Packages!$B$6:$B$305,"<="&EOMONTH(DATE($C$22,4,1),0)) | G28: =E28+F28
B29: May | C29: =COUNTIFS(Appointments!$F$6:$F$2005,"Done",Appointments!$B$6:$B$2005,">="&DATE($C$22,5,1),Appointments!$B$6:$B$2005,"<="&EOMONTH(DATE($C$22,5,1),0)) | D29: =COUNTIFS(Appointments!$F$6:$F$2005,"No-show",Appointments!$B$6:$B$2005,">="&DATE($C$22,5,1),Appointments!$B$6:$B$2005,"<="&EOMONTH(DATE($C$22,5,1),0)) | E29: =SUMIFS(Appointments!$I$6:$I$2005,Appointments!$B$6:$B$2005,">="&DATE($C$22,5,1),Appointments!$B$6:$B$2005,"<="&EOMONTH(DATE($C$22,5,1),0)) | F29: =SUMIFS(Packages!$F$6:$F$305,Packages!$B$6:$B$305,">="&DATE($C$22,5,1),Packages!$B$6:$B$305,"<="&EOMONTH(DATE($C$22,5,1),0)) | G29: =E29+F29
B30: Jun | C30: =COUNTIFS(Appointments!$F$6:$F$2005,"Done",Appointments!$B$6:$B$2005,">="&DATE($C$22,6,1),Appointments!$B$6:$B$2005,"<="&EOMONTH(DATE($C$22,6,1),0)) | D30: =COUNTIFS(Appointments!$F$6:$F$2005,"No-show",Appointments!$B$6:$B$2005,">="&DATE($C$22,6,1),Appointments!$B$6:$B$2005,"<="&EOMONTH(DATE($C$22,6,1),0)) | E30: =SUMIFS(Appointments!$I$6:$I$2005,Appointments!$B$6:$B$2005,">="&DATE($C$22,6,1),Appointments!$B$6:$B$2005,"<="&EOMONTH(DATE($C$22,6,1),0)) | F30: =SUMIFS(Packages!$F$6:$F$305,Packages!$B$6:$B$305,">="&DATE($C$22,6,1),Packages!$B$6:$B$305,"<="&EOMONTH(DATE($C$22,6,1),0)) | G30: =E30+F30
B31: Jul | C31: =COUNTIFS(Appointments!$F$6:$F$2005,"Done",Appointments!$B$6:$B$2005,">="&DATE($C$22,7,1),Appointments!$B$6:$B$2005,"<="&EOMONTH(DATE($C$22,7,1),0)) | D31: =COUNTIFS(Appointments!$F$6:$F$2005,"No-show",Appointments!$B$6:$B$2005,">="&DATE($C$22,7,1),Appointments!$B$6:$B$2005,"<="&EOMONTH(DATE($C$22,7,1),0)) | E31: =SUMIFS(Appointments!$I$6:$I$2005,Appointments!$B$6:$B$2005,">="&DATE($C$22,7,1),Appointments!$B$6:$B$2005,"<="&EOMONTH(DATE($C$22,7,1),0)) | F31: =SUMIFS(Packages!$F$6:$F$305,Packages!$B$6:$B$305,">="&DATE($C$22,7,1),Packages!$B$6:$B$305,"<="&EOMONTH(DATE($C$22,7,1),0)) | G31: =E31+F31
B32: Aug | C32: =COUNTIFS(Appointments!$F$6:$F$2005,"Done",Appointments!$B$6:$B$2005,">="&DATE($C$22,8,1),Appointments!$B$6:$B$2005,"<="&EOMONTH(DATE($C$22,8,1),0)) | D32: =COUNTIFS(Appointments!$F$6:$F$2005,"No-show",Appointments!$B$6:$B$2005,">="&DATE($C$22,8,1),Appointments!$B$6:$B$2005,"<="&EOMONTH(DATE($C$22,8,1),0)) | E32: =SUMIFS(Appointments!$I$6:$I$2005,Appointments!$B$6:$B$2005,">="&DATE($C$22,8,1),Appointments!$B$6:$B$2005,"<="&EOMONTH(DATE($C$22,8,1),0)) | F32: =SUMIFS(Packages!$F$6:$F$305,Packages!$B$6:$B$305,">="&DATE($C$22,8,1),Packages!$B$6:$B$305,"<="&EOMONTH(DATE($C$22,8,1),0)) | G32: =E32+F32
B33: Sep | C33: =COUNTIFS(Appointments!$F$6:$F$2005,"Done",Appointments!$B$6:$B$2005,">="&DATE($C$22,9,1),Appointments!$B$6:$B$2005,"<="&EOMONTH(DATE($C$22,9,1),0)) | D33: =COUNTIFS(Appointments!$F$6:$F$2005,"No-show",Appointments!$B$6:$B$2005,">="&DATE($C$22,9,1),Appointments!$B$6:$B$2005,"<="&EOMONTH(DATE($C$22,9,1),0)) | E33: =SUMIFS(Appointments!$I$6:$I$2005,Appointments!$B$6:$B$2005,">="&DATE($C$22,9,1),Appointments!$B$6:$B$2005,"<="&EOMONTH(DATE($C$22,9,1),0)) | F33: =SUMIFS(Packages!$F$6:$F$305,Packages!$B$6:$B$305,">="&DATE($C$22,9,1),Packages!$B$6:$B$305,"<="&EOMONTH(DATE($C$22,9,1),0)) | G33: =E33+F33
B34: Oct | C34: =COUNTIFS(Appointments!$F$6:$F$2005,"Done",Appointments!$B$6:$B$2005,">="&DATE($C$22,10,1),Appointments!$B$6:$B$2005,"<="&EOMONTH(DATE($C$22,10,1),0)) | D34: =COUNTIFS(Appointments!$F$6:$F$2005,"No-show",Appointments!$B$6:$B$2005,">="&DATE($C$22,10,1),Appointments!$B$6:$B$2005,"<="&EOMONTH(DATE($C$22,10,1),0)) | E34: =SUMIFS(Appointments!$I$6:$I$2005,Appointments!$B$6:$B$2005,">="&DATE($C$22,10,1),Appointments!$B$6:$B$2005,"<="&EOMONTH(DATE($C$22,10,1),0)) | F34: =SUMIFS(Packages!$F$6:$F$305,Packages!$B$6:$B$305,">="&DATE($C$22,10,1),Packages!$B$6:$B$305,"<="&EOMONTH(DATE($C$22,10,1),0)) | G34: =E34+F34
B35: Nov | C35: =COUNTIFS(Appointments!$F$6:$F$2005,"Done",Appointments!$B$6:$B$2005,">="&DATE($C$22,11,1),Appointments!$B$6:$B$2005,"<="&EOMONTH(DATE($C$22,11,1),0)) | D35: =COUNTIFS(Appointments!$F$6:$F$2005,"No-show",Appointments!$B$6:$B$2005,">="&DATE($C$22,11,1),Appointments!$B$6:$B$2005,"<="&EOMONTH(DATE($C$22,11,1),0)) | E35: =SUMIFS(Appointments!$I$6:$I$2005,Appointments!$B$6:$B$2005,">="&DATE($C$22,11,1),Appointments!$B$6:$B$2005,"<="&EOMONTH(DATE($C$22,11,1),0)) | F35: =SUMIFS(Packages!$F$6:$F$305,Packages!$B$6:$B$305,">="&DATE($C$22,11,1),Packages!$B$6:$B$305,"<="&EOMONTH(DATE($C$22,11,1),0)) | G35: =E35+F35
B36: Dec | C36: =COUNTIFS(Appointments!$F$6:$F$2005,"Done",Appointments!$B$6:$B$2005,">="&DATE($C$22,12,1),Appointments!$B$6:$B$2005,"<="&EOMONTH(DATE($C$22,12,1),0)) | D36: =COUNTIFS(Appointments!$F$6:$F$2005,"No-show",Appointments!$B$6:$B$2005,">="&DATE($C$22,12,1),Appointments!$B$6:$B$2005,"<="&EOMONTH(DATE($C$22,12,1),0)) | E36: =SUMIFS(Appointments!$I$6:$I$2005,Appointments!$B$6:$B$2005,">="&DATE($C$22,12,1),Appointments!$B$6:$B$2005,"<="&EOMONTH(DATE($C$22,12,1),0)) | F36: =SUMIFS(Packages!$F$6:$F$305,Packages!$B$6:$B$305,">="&DATE($C$22,12,1),Packages!$B$6:$B$305,"<="&EOMONTH(DATE($C$22,12,1),0)) | G36: =E36+F36
B37: Year | C37: =SUM(C25:C36) | D37: =SUM(D25:D36) | E37: =SUM(E25:E36) | F37: =SUM(F25:F36) | G37: =SUM(G25:G36)

Sheet Appointments
B2: Appointments
B3: One line per appointment. Change the status to Done after the visit and type what was paid.
B5: Date | C5: Time | D5: Client | E5: Service | F5: Status | G5: Price | H5: Discount | I5: Paid | J5: Paid with | K5: Still to pay | L5: Note
B6: 46028 | C6: 0.375 | D6: Anna Rossi | E6: Colour | F6: Done | G6: =IF(E6="","",MAX(0,IFERROR(INDEX(Services!$C$6:$C$35,MATCH(E6,Services!$B$6:$B$35,0)),0)-N(H6))) | I6: 95 | J6: App | K6: =IF(OR(B6="",F6<>"Done",J6="Package"),"",IF(N(G6)-N(I6)>0,N(G6)-N(I6),"")) | M6: =IF(OR(B6="",D6="",F6="Cancelled"),"",B6+N(C6)+ROW()/10000000) | N6: =IF(AND(F6="Done",M6<>""),IF(COUNTIFS(Appointments!$D$6:$D$2005,D6,Appointments!$F$6:$F$2005,"Done",Appointments!$M$6:$M$2005,">"&M6)=0,1,0),0) | O6: =IF(AND(F6="Booked",M6<>"",N(B6)>=TODAY()),IF(COUNTIFS(Appointments!$D$6:$D$2005,D6,Appointments!$F$6:$F$2005,"Booked",Appointments!$B$6:$B$2005,">="&TODAY(),Appointments!$M$6:$M$2005,"<"&M6)=0,1,0),0)
B7: 46028 | C7: 0.46527778 | D7: Finn Cook | E7: Men's haircut | F7: Done | G7: =IF(E7="","",MAX(0,IFERROR(INDEX(Services!$C$6:$C$35,MATCH(E7,Services!$B$6:$B$35,0)),0)-N(H7))) | I7: 30 | J7: Card | K7: =IF(OR(B7="",F7<>"Done",J7="Package"),"",IF(N(G7)-N(I7)>0,N(G7)-N(I7),"")) | M7: =IF(OR(B7="",D7="",F7="Cancelled"),"",B7+N(C7)+ROW()/10000000) | N7: =IF(AND(F7="Done",M7<>""),IF(COUNTIFS(Appointments!$D$6:$D$2005,D7,Appointments!$F$6:$F$2005,"Done",Appointments!$M$6:$M$2005,">"&M7)=0,1,0),0) | O7: =IF(AND(F7="Booked",M7<>"",N(B7)>=TODAY()),IF(COUNTIFS(Appointments!$D$6:$D$2005,D7,Appointments!$F$6:$F$2005,"Booked",Appointments!$B$6:$B$2005,">="&TODAY(),Appointments!$M$6:$M$2005,"<"&M7)=0,1,0),0)
B8: 46029 | C8: 0.375 | D8: Ava Reed | E8: Highlights | F8: Done | G8: =IF(E8="","",MAX(0,IFERROR(INDEX(Services!$C$6:$C$35,MATCH(E8,Services!$B$6:$B$35,0)),0)-N(H8))) | I8: 140 | J8: Cash | K8: =IF(OR(B8="",F8<>"Done",J8="Package"),"",IF(N(G8)-N(I8)>0,N(G8)-N(I8),"")) | M8: =IF(OR(B8="",D8="",F8="Cancelled"),"",B8+N(C8)+ROW()/10000000) | N8: =IF(AND(F8="Done",M8<>""),IF(COUNTIFS(Appointments!$D$6:$D$2005,D8,Appointments!$F$6:$F$2005,"Done",Appointments!$M$6:$M$2005,">"&M8)=0,1,0),0) | O8: =IF(AND(F8="Booked",M8<>"",N(B8)>=TODAY()),IF(COUNTIFS(Appointments!$D$6:$D$2005,D8,Appointments!$F$6:$F$2005,"Booked",Appointments!$B$6:$B$2005,">="&TODAY(),Appointments!$M$6:$M$2005,"<"&M8)=0,1,0),0)
B9: 46029 | C9: 0.48611111 | D9: Eli James | E9: Men's haircut | F9: Done | G9: =IF(E9="","",MAX(0,IFERROR(INDEX(Services!$C$6:$C$35,MATCH(E9,Services!$B$6:$B$35,0)),0)-N(H9))) | I9: 30 | J9: Card | K9: =IF(OR(B9="",F9<>"Done",J9="Package"),"",IF(N(G9)-N(I9)>0,N(G9)-N(I9),"")) | M9: =IF(OR(B9="",D9="",F9="Cancelled"),"",B9+N(C9)+ROW()/10000000) | N9: =IF(AND(F9="Done",M9<>""),IF(COUNTIFS(Appointments!$D$6:$D$2005,D9,Appointments!$F$6:$F$2005,"Done",Appointments!$M$6:$M$2005,">"&M9)=0,1,0),0) | O9: =IF(AND(F9="Booked",M9<>"",N(B9)>=TODAY()),IF(COUNTIFS(Appointments!$D$6:$D$2005,D9,Appointments!$F$6:$F$2005,"Booked",Appointments!$B$6:$B$2005,">="&TODAY(),Appointments!$M$6:$M$2005,"<"&M9)=0,1,0),0)
B10: 46029 | C10: 0.51388889 | D10: Kara Adams | E10: Women's haircut | F10: No-show | G10: =IF(E10="","",MAX(0,IFERROR(INDEX(Services!$C$6:$C$35,MATCH(E10,Services!$B$6:$B$35,0)),0)-N(H10))) | K10: =IF(OR(B10="",F10<>"Done",J10="Package"),"",IF(N(G10)-N(I10)>0,N(G10)-N(I10),"")) | M10: =IF(OR(B10="",D10="",F10="Cancelled"),"",B10+N(C10)+ROW()/10000000) | N10: =IF(AND(F10="Done",M10<>""),IF(COUNTIFS(Appointments!$D$6:$D$2005,D10,Appointments!$F$6:$F$2005,"Done",Appointments!$M$6:$M$2005,">"&M10)=0,1,0),0) | O10: =IF(AND(F10="Booked",M10<>"",N(B10)>=TODAY()),IF(COUNTIFS(Appointments!$D$6:$D$2005,D10,Appointments!$F$6:$F$2005,"Booked",Appointments!$B$6:$B$2005,">="&TODAY(),Appointments!$M$6:$M$2005,"<"&M10)=0,1,0),0)
B11: 46030 | C11: 0.375 | D11: Julia Hughes | E11: Women's haircut | F11: Done | G11: =IF(E11="","",MAX(0,IFERROR(INDEX(Services!$C$6:$C$35,MATCH(E11,Services!$B$6:$B$35,0)),0)-N(H11))) | H11: 10 | I11: 45 | J11: Card | K11: =IF(OR(B11="",F11<>"Done",J11="Package"),"",IF(N(G11)-N(I11)>0,N(G11)-N(I11),"")) | L11: Friends and family | M11: =IF(OR(B11="",D11="",F11="Cancelled"),"",B11+N(C11)+ROW()/10000000) | N11: =IF(AND(F11="Done",M11<>""),IF(COUNTIFS(Appointments!$D$6:$D$2005,D11,Appointments!$F$6:$F$2005,"Done",Appointments!$M$6:$M$2005,">"&M11)=0,1,0),0) | O11: =IF(AND(F11="Booked",M11<>"",N(B11)>=TODAY()),IF(COUNTIFS(Appointments!$D$6:$D$2005,D11,Appointments!$F$6:$F$2005,"Booked",Appointments!$B$6:$B$2005,">="&TODAY(),Appointments!$M$6:$M$2005,"<"&M11)=0,1,0),0)
B12: 46030 | C12: 0.42361111 | D12: Owen Walsh | E12: Men's haircut | F12: Done | G12: =IF(E12="","",MAX(0,IFERROR(INDEX(Services!$C$6:$C$35,MATCH(E12,Services!$B$6:$B$35,0)),0)-N(H12))) | I12: 30 | J12: Card | K12: =IF(OR(B12="",F12<>"Done",J12="Package"),"",IF(N(G12)-N(I12)>0,N(G12)-N(I12),"")) | M12: =IF(OR(B12="",D12="",F12="Cancelled"),"",B12+N(C12)+ROW()/10000000) | N12: =IF(AND(F12="Done",M12<>""),IF(COUNTIFS(Appointments!$D$6:$D$2005,D12,Appointments!$F$6:$F$2005,"Done",Appointments!$M$6:$M$2005,">"&M12)=0,1,0),0) | O12: =IF(AND(F12="Booked",M12<>"",N(B12)>=TODAY()),IF(COUNTIFS(Appointments!$D$6:$D$2005,D12,Appointments!$F$6:$F$2005,"Booked",Appointments!$B$6:$B$2005,">="&TODAY(),Appointments!$M$6:$M$2005,"<"&M12)=0,1,0),0)
B13: 46030 | C13: 0.45138889 | D13: Sara Stone | E13: Blow dry | F13: Done | G13: =IF(E13="","",MAX(0,IFERROR(INDEX(Services!$C$6:$C$35,MATCH(E13,Services!$B$6:$B$35,0)),0)-N(H13))) | I13: 35 | J13: Card | K13: =IF(OR(B13="",F13<>"Done",J13="Package"),"",IF(N(G13)-N(I13)>0,N(G13)-N(I13),"")) | M13: =IF(OR(B13="",D13="",F13="Cancelled"),"",B13+N(C13)+ROW()/10000000) | N13: =IF(AND(F13="Done",M13<>""),IF(COUNTIFS(Appointments!$D$6:$D$2005,D13,Appointments!$F$6:$F$2005,"Done",Appointments!$M$6:$M$2005,">"&M13)=0,1,0),0) | O13: =IF(AND(F13="Booked",M13<>"",N(B13)>=TODAY()),IF(COUNTIFS(Appointments!$D$6:$D$2005,D13,Appointments!$F$6:$F$2005,"Booked",Appointments!$B$6:$B$2005,">="&TODAY(),Appointments!$M$6:$M$2005,"<"&M13)=0,1,0),0)
B14: 46030 | C14: 0.48958333 | D14: Sophie Ellis | E14: Treatment | F14: Done | G14: =IF(E14="","",MAX(0,IFERROR(INDEX(Services!$C$6:$C$35,MATCH(E14,Services!$B$6:$B$35,0)),0)-N(H14))) | I14: 30 | J14: Card | K14: =IF(OR(B14="",F14<>"Done",J14="Package"),"",IF(N(G14)-N(I14)>0,N(G14)-N(I14),"")) | M14: =IF(OR(B14="",D14="",F14="Cancelled"),"",B14+N(C14)+ROW()/10000000) | N14: =IF(AND(F14="Done",M14<>""),IF(COUNTIFS(Appointments!$D$6:$D$2005,D14,Appointments!$F$6:$F$2005,"Done",Appointments!$M$6:$M$2005,">"&M14)=0,1,0),0) | O14: =IF(AND(F14="Booked",M14<>"",N(B14)>=TODAY()),IF(COUNTIFS(Appointments!$D$6:$D$2005,D14,Appointments!$F$6:$F$2005,"Booked",Appointments!$B$6:$B$2005,">="&TODAY(),Appointments!$M$6:$M$2005,"<"&M14)=0,1,0),0)
B15: 46030 | C15: 0.51736111 | D15: Zoe Turner | E15: Women's haircut | F15: Done | G15: =IF(E15="","",MAX(0,IFERROR(INDEX(Services!$C$6:$C$35,MATCH(E15,Services!$B$6:$B$35,0)),0)-N(H15))) | I15: 55 | J15: Cash | K15: =IF(OR(B15="",F15<>"Done",J15="Package"),"",IF(N(G15)-N(I15)>0,N(G15)-N(I15),"")) | M15: =IF(OR(B15="",D15="",F15="Cancelled"),"",B15+N(C15)+ROW()/10000000) | N15: =IF(AND(F15="Done",M15<>""),IF(COUNTIFS(Appointments!$D$6:$D$2005,D15,Appointments!$F$6:$F$2005,"Done",Appointments!$M$6:$M$2005,">"&M15)=0,1,0),0) | O15: =IF(AND(F15="Booked",M15<>"",N(B15)>=TODAY()),IF(COUNTIFS(Appointments!$D$6:$D$2005,D15,Appointments!$F$6:$F$2005,"Booked",Appointments!$B$6:$B$2005,">="&TODAY(),Appointments!$M$6:$M$2005,"<"&M15)=0,1,0),0)
B16: 46031 | C16: 0.375 | D16: Ella James | E16: Treatment | F16: No-show | G16: =IF(E16="","",MAX(0,IFERROR(INDEX(Services!$C$6:$C$35,MATCH(E16,Services!$B$6:$B$35,0)),0)-N(H16))) | K16: =IF(OR(B16="",F16<>"Done",J16="Package"),"",IF(N(G16)-N(I16)>0,N(G16)-N(I16),"")) | M16: =IF(OR(B16="",D16="",F16="Cancelled"),"",B16+N(C16)+ROW()/10000000) | N16: =IF(AND(F16="Done",M16<>""),IF(COUNTIFS(Appointments!$D$6:$D$2005,D16,Appointments!$F$6:$F$2005,"Done",Appointments!$M$6:$M$2005,">"&M16)=0,1,0),0) | O16: =IF(AND(F16="Booked",M16<>"",N(B16)>=TODAY()),IF(COUNTIFS(Appointments!$D$6:$D$2005,D16,Appointments!$F$6:$F$2005,"Booked",Appointments!$B$6:$B$2005,">="&TODAY(),Appointments!$M$6:$M$2005,"<"&M16)=0,1,0),0)
B17: 46031 | C17: 0.40277778 | D17: Hannah Ellis | E17: Colour | F17: Done | G17: =IF(E17="","",MAX(0,IFERROR(INDEX(Services!$C$6:$C$35,MATCH(E17,Services!$B$6:$B$35,0)),0)-N(H17))) | I17: 95 | J17: Card | K17: =IF(OR(B17="",F17<>"Done",J17="Package"),"",IF(N(G17)-N(I17)>0,N(G17)-N(I17),"")) | M17: =IF(OR(B17="",D17="",F17="Cancelled"),"",B17+N(C17)+ROW()/10000000) | N17: =IF(AND(F17="Done",M17<>""),IF(COUNTIFS(Appointments!$D$6:$D$2005,D17,Appointments!$F$6:$F$2005,"Done",Appointments!$M$6:$M$2005,">"&M17)=0,1,0),0) | O17: =IF(AND(F17="Booked",M17<>"",N(B17)>=TODAY()),IF(COUNTIFS(Appointments!$D$6:$D$2005,D17,Appointments!$F$6:$F$2005,"Booked",Appointments!$B$6:$B$2005,">="&TODAY(),Appointments!$M$6:$M$2005,"<"&M17)=0,1,0),0)
B18: 46031 | C18: 0.49305556 | D18: Hannah Kelly | E18: Women's haircut | F18: No-show | G18: =IF(E18="","",MAX(0,IFERROR(INDEX(Services!$C$6:$C$35,MATCH(E18,Services!$B$6:$B$35,0)),0)-N(H18))) | K18: =IF(OR(B18="",F18<>"Done",J18="Package"),"",IF(N(G18)-N(I18)>0,N(G18)-N(I18),"")) | M18: =IF(OR(B18="",D18="",F18="Cancelled"),"",B18+N(C18)+ROW()/10000000) | N18: =IF(AND(F18="Done",M18<>""),IF(COUNTIFS(Appointments!$D$6:$D$2005,D18,Appointments!$F$6:$F$2005,"Done",Appointments!$M$6:$M$2005,">"&M18)=0,1,0),0) | O18: =IF(AND(F18="Booked",M18<>"",N(B18)>=TODAY()),IF(COUNTIFS(Appointments!$D$6:$D$2005,D18,Appointments!$F$6:$F$2005,"Booked",Appointments!$B$6:$B$2005,">="&TODAY(),Appointments!$M$6:$M$2005,"<"&M18)=0,1,0),0)
B19: 46031 | C19: 0.54166667 | D19: Harry Adams | E19: Men's haircut | F19: Done | G19: =IF(E19="","",MAX(0,IFERROR(INDEX(Services!$C$6:$C$35,MATCH(E19,Services!$B$6:$B$35,0)),0)-N(H19))) | I19: 30 | J19: Cash | K19: =IF(OR(B19="",F19<>"Done",J19="Package"),"",IF(N(G19)-N(I19)>0,N(G19)-N(I19),"")) | M19: =IF(OR(B19="",D19="",F19="Cancelled"),"",B19+N(C19)+ROW()/10000000) | N19: =IF(AND(F19="Done",M19<>""),IF(COUNTIFS(Appointments!$D$6:$D$2005,D19,Appointments!$F$6:$F$2005,"Done",Appointments!$M$6:$M$2005,">"&M19)=0,1,0),0) | O19: =IF(AND(F19="Booked",M19<>"",N(B19)>=TODAY()),IF(COUNTIFS(Appointments!$D$6:$D$2005,D19,Appointments!$F$6:$F$2005,"Booked",Appointments!$B$6:$B$2005,">="&TODAY(),Appointments!$M$6:$M$2005,"<"&M19)=0,1,0),0)
B20: 46031 | C20: 0.56944444 | D20: Isla Brown | E20: Women's haircut | F20: Done | G20: =IF(E20="","",MAX(0,IFERROR(INDEX(Services!$C$6:$C$35,MATCH(E20,Services!$B$6:$B$35,0)),0)-N(H20))) | I20: 55 | J20: Card | K20: =IF(OR(B20="",F20<>"Done",J20="Package"),"",IF(N(G20)-N(I20)>0,N(G20)-N(I20),"")) | M20: =IF(OR(B20="",D20="",F20="Cancelled"),"",B20+N(C20)+ROW()/10000000) | N20: =IF(AND(F20="Done",M20<>""),IF(COUNTIFS(Appointments!$D$6:$D$2005,D20,Appointments!$F$6:$F$2005,"Done",Appointments!$M$6:$M$2005,">"&M20)=0,1,0),0) | O20: =IF(AND(F20="Booked",M20<>"",N(B20)>=TODAY()),IF(COUNTIFS(Appointments!$D$6:$D$2005,D20,Appointments!$F$6:$F$2005,"Booked",Appointments!$B$6:$B$2005,">="&TODAY(),Appointments!$M$6:$M$2005,"<"&M20)=0,1,0),0)
B21: 46031 | C21: 0.61805556 | D21: Nina Ellis | E21: Women's haircut | F21: Done | G21: =IF(E21="","",MAX(0,IFERROR(INDEX(Services!$C$6:$C$35,MATCH(E21,Services!$B$6:$B$35,0)),0)-N(H21))) | I21: 55 | J21: Cash | K21: =IF(OR(B21="",F21<>"Done",J21="Package"),"",IF(N(G21)-N(I21)>0,N(G21)-N(I21),"")) | M21: =IF(OR(B21="",D21="",F21="Cancelled"),"",B21+N(C21)+ROW()/10000000) | N21: =IF(AND(F21="Done",M21<>""),IF(COUNTIFS(Appointments!$D$6:$D$2005,D21,Appointments!$F$6:$F$2005,"Done",Appointments!$M$6:$M$2005,">"&M21)=0,1,0),0) | O21: =IF(AND(F21="Booked",M21<>"",N(B21)>=TODAY()),IF(COUNTIFS(Appointments!$D$6:$D$2005,D21,Appointments!$F$6:$F$2005,"Booked",Appointments!$B$6:$B$2005,">="&TODAY(),Appointments!$M$6:$M$2005,"<"&M21)=0,1,0),0)
B22: 46031 | C22: 0.66666667 | D22: Ruby Webb | E22: Women's haircut | F22: No-show | G22: =IF(E22="","",MAX(0,IFERROR(INDEX(Services!$C$6:$C$35,MATCH(E22,Services!$B$6:$B$35,0)),0)-N(H22))) | K22: =IF(OR(B22="",F22<>"Done",J22="Package"),"",IF(N(G22)-N(I22)>0,N(G22)-N(I22),"")) | M22: =IF(OR(B22="",D22="",F22="Cancelled"),"",B22+N(C22)+ROW()/10000000) | N22: =IF(AND(F22="Done",M22<>""),IF(COUNTIFS(Appointments!$D$6:$D$2005,D22,Appointments!$F$6:$F$2005,"Done",Appointments!$M$6:$M$2005,">"&M22)=0,1,0),0) | O22: =IF(AND(F22="Booked",M22<>"",N(B22)>=TODAY()),IF(COUNTIFS(Appointments!$D$6:$D$2005,D22,Appointments!$F$6:$F$2005,"Booked",Appointments!$B$6:$B$2005,">="&TODAY(),Appointments!$M$6:$M$2005,"<"&M22)=0,1,0),0)
B23: 46032 | C23: 0.375 | D23: Chris Cox | E23: Men's haircut | F23: Done | G23: =IF(E23="","",MAX(0,IFERROR(INDEX(Services!$C$6:$C$35,MATCH(E23,Services!$B$6:$B$35,0)),0)-N(H23))) | I23: 30 | J23: Card | K23: =IF(OR(B23="",F23<>"Done",J23="Package"),"",IF(N(G23)-N(I23)>0,N(G23)-N(I23),"")) | M23: =IF(OR(B23="",D23="",F23="Cancelled"),"",B23+N(C23)+ROW()/10000000) | N23: =IF(AND(F23="Done",M23<>""),IF(COUNTIFS(Appointments!$D$6:$D$2005,D23,Appointments!$F$6:$F$2005,"Done",Appointments!$M$6:$M$2005,">"&M23)=0,1,0),0) | O23: =IF(AND(F23="Booked",M23<>"",N(B23)>=TODAY()),IF(COUNTIFS(Appointments!$D$6:$D$2005,D23,Appointments!$F$6:$F$2005,"Booked",Appointments!$B$6:$B$2005,">="&TODAY(),Appointments!$M$6:$M$2005,"<"&M23)=0,1,0),0)
B24: 46032 | C24: 0.40277778 | D24: Chris Ellis | E24: Men's haircut | F24: Done | G24: =IF(E24="","",MAX(0,IFERROR(INDEX(Services!$C$6:$C$35,MATCH(E24,Services!$B$6:$B$35,0)),0)-N(H24))) | I24: 30 | J24: Cash | K24: =IF(OR(B24="",F24<>"Done",J24="Package"),"",IF(N(G24)-N(I24)>0,N(G24)-N(I24),"")) | M24: =IF(OR(B24="",D24="",F24="Cancelled"),"",B24+N(C24)+ROW()/10000000) | N24: =IF(AND(F24="Done",M24<>""),IF(COUNTIFS(Appointments!$D$6:$D$2005,D24,Appointments!$F$6:$F$2005,"Done",Appointments!$M$6:$M$2005,">"&M24)=0,1,0),0) | O24: =IF(AND(F24="Booked",M24<>"",N(B24)>=TODAY()),IF(COUNTIFS(Appointments!$D$6:$D$2005,D24,Appointments!$F$6:$F$2005,"Booked",Appointments!$B$6:$B$2005,">="&TODAY(),Appointments!$M$6:$M$2005,"<"&M24)=0,1,0),0)
B25: 46032 | C25: 0.43055556 | D25: Holly Shaw | E25: Women's haircut | F25: Done | G25: =IF(E25="","",MAX(0,IFERROR(INDEX(Services!$C$6:$C$35,MATCH(E25,Services!$B$6:$B$35,0)),0)-N(H25))) | I25: 55 | J25: Cash | K25: =IF(OR(B25="",F25<>"Done",J25="Package"),"",IF(N(G25)-N(I25)>0,N(G25)-N(I25),"")) | M25: =IF(OR(B25="",D25="",F25="Cancelled"),"",B25+N(C25)+ROW()/10000000) | N25: =IF(AND(F25="Done",M25<>""),IF(COUNTIFS(Appointments!$D$6:$D$2005,D25,Appointments!$F$6:$F$2005,"Done",Appointments!$M$6:$M$2005,">"&M25)=0,1,0),0) | O25: =IF(AND(F25="Booked",M25<>"",N(B25)>=TODAY()),IF(COUNTIFS(Appointments!$D$6:$D$2005,D25,Appointments!$F$6:$F$2005,"Booked",Appointments!$B$6:$B$2005,">="&TODAY(),Appointments!$M$6:$M$2005,"<"&M25)=0,1,0),0)
B26: 46032 | C26: 0.47916667 | D26: Lily Lewis | E26: Blow dry | F26: Done | G26: =IF(E26="","",MAX(0,IFERROR(INDEX(Services!$C$6:$C$35,MATCH(E26,Services!$B$6:$B$35,0)),0)-N(H26))) | I26: 35 | J26: Card | K26: =IF(OR(B26="",F26<>"Done",J26="Package"),"",IF(N(G26)-N(I26)>0,N(G26)-N(I26),"")) | M26: =IF(OR(B26="",D26="",F26="Cancelled"),"",B26+N(C26)+ROW()/10000000) | N26: =IF(AND(F26="Done",M26<>""),IF(COUNTIFS(Appointments!$D$6:$D$2005,D26,Appointments!$F$6:$F$2005,"Done",Appointments!$M$6:$M$2005,">"&M26)=0,1,0),0) | O26: =IF(AND(F26="Booked",M26<>"",N(B26)>=TODAY()),IF(COUNTIFS(Appointments!$D$6:$D$2005,D26,Appointments!$F$6:$F$2005,"Booked",Appointments!$B$6:$B$2005,">="&TODAY(),Appointments!$M$6:$M$2005,"<"&M26)=0,1,0),0)
B27: 46032 | C27: 0.51736111 | D27: Nina Baker | E27: Women's haircut | F27: Done | G27: =IF(E27="","",MAX(0,IFERROR(INDEX(Services!$C$6:$C$35,MATCH(E27,Services!$B$6:$B$35,0)),0)-N(H27))) | I27: 55 | J27: Card | K27: =IF(OR(B27="",F27<>"Done",J27="Package"),"",IF(N(G27)-N(I27)>0,N(G27)-N(I27),"")) | M27: =IF(OR(B27="",D27="",F27="Cancelled"),"",B27+N(C27)+ROW()/10000000) | N27: =IF(AND(F27="Done",M27<>""),IF(COUNTIFS(Appointments!$D$6:$D$2005,D27,Appointments!$F$6:$F$2005,"Done",Appointments!$M$6:$M$2005,">"&M27)=0,1,0),0) | O27: =IF(AND(F27="Booked",M27<>"",N(B27)>=TODAY()),IF(COUNTIFS(Appointments!$D$6:$D$2005,D27,Appointments!$F$6:$F$2005,"Booked",Appointments!$B$6:$B$2005,">="&TODAY(),Appointments!$M$6:$M$2005,"<"&M27)=0,1,0),0)
B28: 46032 | C28: 0.56597222 | D28: Nina Young | E28: Women's haircut | F28: Done | G28: =IF(E28="","",MAX(0,IFERROR(INDEX(Services!$C$6:$C$35,MATCH(E28,Services!$B$6:$B$35,0)),0)-N(H28))) | I28: 55 | J28: Card | K28: =IF(OR(B28="",F28<>"Done",J28="Package"),"",IF(N(G28)-N(I28)>0,N(G28)-N(I28),"")) | M28: =IF(OR(B28="",D28="",F28="Cancelled"),"",B28+N(C28)+ROW()/10000000) | N28: =IF(AND(F28="Done",M28<>""),IF(COUNTIFS(Appointments!$D$6:$D$2005,D28,Appointments!$F$6:$F$2005,"Done",Appointments!$M$6:$M$2005,">"&M28)=0,1,0),0) | O28: =IF(AND(F28="Booked",M28<>"",N(B28)>=TODAY()),IF(COUNTIFS(Appointments!$D$6:$D$2005,D28,Appointments!$F$6:$F$2005,"Booked",Appointments!$B$6:$B$2005,">="&TODAY(),Appointments!$M$6:$M$2005,"<"&M28)=0,1,0),0)
B29: 46032 | C29: 0.61458333 | D29: Tom Ellis | E29: Men's haircut | F29: Done | G29: =IF(E29="","",MAX(0,IFERROR(INDEX(Services!$C$6:$C$35,MATCH(E29,Services!$B$6:$B$35,0)),0)-N(H29))) | I29: 30 | J29: Transfer | K29: =IF(OR(B29="",F29<>"Done",J29="Package"),"",IF(N(G29)-N(I29)>0,N(G29)-N(I29),"")) | M29: =IF(OR(B29="",D29="",F29="Cancelled"),"",B29+N(C29)+ROW()/10000000) | N29: =IF(AND(F29="Done",M29<>""),IF(COUNTIFS(Appointments!$D$6:$D$2005,D29,Appointments!$F$6:$F$2005,"Done",Appointments!$M$6:$M$2005,">"&M29)=0,1,0),0) | O29: =IF(AND(F29="Booked",M29<>"",N(B29)>=TODAY()),IF(COUNTIFS(Appointments!$D$6:$D$2005,D29,Appointments!$F$6:$F$2005,"Booked",Appointments!$B$6:$B$2005,">="&TODAY(),Appointments!$M$6:$M$2005,"<"&M29)=0,1,0),0)
B30: 46035 | C30: 0.375 | D30: Finn Price | E30: Men's haircut | F30: Done | G30: =IF(E30="","",MAX(0,IFERROR(INDEX(Services!$C$6:$C$35,MATCH(E30,Services!$B$6:$B$35,0)),0)-N(H30))) | H30: 10 | I30: 20 | J30: Transfer | K30: =IF(OR(B30="",F30<>"Done",J30="Package"),"",IF(N(G30)-N(I30)>0,N(G30)-N(I30),"")) | L30: Friends and family | M30: =IF(OR(B30="",D30="",F30="Cancelled"),"",B30+N(C30)+ROW()/10000000) | N30: =IF(AND(F30="Done",M30<>""),IF(COUNTIFS(Appointments!$D$6:$D$2005,D30,Appointments!$F$6:$F$2005,"Done",Appointments!$M$6:$M$2005,">"&M30)=0,1,0),0) | O30: =IF(AND(F30="Booked",M30<>"",N(B30)>=TODAY()),IF(COUNTIFS(Appointments!$D$6:$D$2005,D30,Appointments!$F$6:$F$2005,"Booked",Appointments!$B$6:$B$2005,">="&TODAY(),Appointments!$M$6:$M$2005,"<"&M30)=0,1,0),0)
B31: 46035 | C31: 0.40277778 | D31: Harry Cox | E31: Men's haircut | F31: Done | G31: =IF(E31="","",MAX(0,IFERROR(INDEX(Services!$C$6:$C$35,MATCH(E31,Services!$B$6:$B$35,0)),0)-N(H31))) | I31: 30 | J31: Cash | K31: =IF(OR(B31="",F31<>"Done",J31="Package"),"",IF(N(G31)-N(I31)>0,N(G31)-N(I31),"")) | M31: =IF(OR(B31="",D31="",F31="Cancelled"),"",B31+N(C31)+ROW()/10000000) | N31: =IF(AND(F31="Done",M31<>""),IF(COUNTIFS(Appointments!$D$6:$D$2005,D31,Appointments!$F$6:$F$2005,"Done",Appointments!$M$6:$M$2005,">"&M31)=0,1,0),0) | O31: =IF(AND(F31="Booked",M31<>"",N(B31)>=TODAY()),IF(COUNTIFS(Appointments!$D$6:$D$2005,D31,Appointments!$F$6:$F$2005,"Booked",Appointments!$B$6:$B$2005,">="&TODAY(),Appointments!$M$6:$M$2005,"<"&M31)=0,1,0),0)
B32: 46035 | C32: 0.43055556 | D32: Kyle Hughes | E32: Men's haircut | F32: Done | G32: =IF(E32="","",MAX(0,IFERROR(INDEX(Services!$C$6:$C$35,MATCH(E32,Services!$B$6:$B$35,0)),0)-N(H32))) | I32: 30 | J32: Cash | K32: =IF(OR(B32="",F32<>"Done",J32="Package"),"",IF(N(G32)-N(I32)>0,N(G32)-N(I32),"")) | M32: =IF(OR(B32="",D32="",F32="Cancelled"),"",B32+N(C32)+ROW()/10000000) | N32: =IF(AND(F32="Done",M32<>""),IF(COUNTIFS(Appointments!$D$6:$D$2005,D32,Appointments!$F$6:$F$2005,"Done",Appointments!$M$6:$M$2005,">"&M32)=0,1,0),0) | O32: =IF(AND(F32="Booked",M32<>"",N(B32)>=TODAY()),IF(COUNTIFS(Appointments!$D$6:$D$2005,D32,Appointments!$F$6:$F$2005,"Booked",Appointments!$B$6:$B$2005,">="&TODAY(),Appointments!$M$6:$M$2005,"<"&M32)=0,1,0),0)
B33: 46035 | C33: 0.45833333 | D33: Luke Hall | E33: Men's haircut | F33: Done | G33: =IF(E33="","",MAX(0,IFERROR(INDEX(Services!$C$6:$C$35,MATCH(E33,Services!$B$6:$B$35,0)),0)-N(H33))) | I33: 30 | J33: Card | K33: =IF(OR(B33="",F33<>"Done",J33="Package"),"",IF(N(G33)-N(I33)>0,N(G33)-N(I33),"")) | M33: =IF(OR(B33="",D33="",F33="Cancelled"),"",B33+N(C33)+ROW()/10000000) | N33: =IF(AND(F33="Done",M33<>""),IF(COUNTIFS(Appointments!$D$6:$D$2005,D33,Appointments!$F$6:$F$2005,"Done",Appointments!$M$6:$M$2005,">"&M33)=0,1,0),0) | O33: =IF(AND(F33="Booked",M33<>"",N(B33)>=TODAY()),IF(COUNTIFS(Appointments!$D$6:$D$2005,D33,Appointments!$F$6:$F$2005,"Booked",Appointments!$B$6:$B$2005,">="&TODAY(),Appointments!$M$6:$M$2005,"<"&M33)=0,1,0),0)
B34: 46035 | C34: 0.48611111 | D34: Owen Morgan | E34: Men's haircut | F34: Done | G34: =IF(E34="","",MAX(0,IFERROR(INDEX(Services!$C$6:$C$35,MATCH(E34,Services!$B$6:$B$35,0)),0)-N(H34))) | I34: 30 | J34: Card | K34: =IF(OR(B34="",F34<>"Done",J34="Package"),"",IF(N(G34)-N(I34)>0,N(G34)-N(I34),"")) | M34: =IF(OR(B34="",D34="",F34="Cancelled"),"",B34+N(C34)+ROW()/10000000) | N34: =IF(AND(F34="Done",M34<>""),IF(COUNTIFS(Appointments!$D$6:$D$2005,D34,Appointments!$F$6:$F$2005,"Done",Appointments!$M$6:$M$2005,">"&M34)=0,1,0),0) | O34: =IF(AND(F34="Booked",M34<>"",N(B34)>=TODAY()),IF(COUNTIFS(Appointments!$D$6:$D$2005,D34,Appointments!$F$6:$F$2005,"Booked",Appointments!$B$6:$B$2005,">="&TODAY(),Appointments!$M$6:$M$2005,"<"&M34)=0,1,0),0)
B35: 46035 | C35: 0.51388889 | D35: Pete Young | E35: Men's haircut | F35: Cancelled | G35: =IF(E35="","",MAX(0,IFERROR(INDEX(Services!$C$6:$C$35,MATCH(E35,Services!$B$6:$B$35,0)),0)-N(H35))) | K35: =IF(OR(B35="",F35<>"Done",J35="Package"),"",IF(N(G35)-N(I35)>0,N(G35)-N(I35),"")) | M35: =IF(OR(B35="",D35="",F35="Cancelled"),"",B35+N(C35)+ROW()/10000000) | N35: =IF(AND(F35="Done",M35<>""),IF(COUNTIFS(Appointments!$D$6:$D$2005,D35,Appointments!$F$6:$F$2005,"Done",Appointments!$M$6:$M$2005,">"&M35)=0,1,0),0) | O35: =IF(AND(F35="Booked",M35<>"",N(B35)>=TODAY()),IF(COUNTIFS(Appointments!$D$6:$D$2005,D35,Appointments!$F$6:$F$2005,"Booked",Appointments!$B$6:$B$2005,">="&TODAY(),Appointments!$M$6:$M$2005,"<"&M35)=0,1,0),0)
B36: 46035 | C36: 0.54166667 | D36: Uma Nair | E36: Women's haircut | F36: Cancelled | G36: =IF(E36="","",MAX(0,IFERROR(INDEX(Services!$C$6:$C$35,MATCH(E36,Services!$B$6:$B$35,0)),0)-N(H36))) | K36: =IF(OR(B36="",F36<>"Done",J36="Package"),"",IF(N(G36)-N(I36)>0,N(G36)-N(I36),"")) | M36: =IF(OR(B36="",D36="",F36="Cancelled"),"",B36+N(C36)+ROW()/10000000) | N36: =IF(AND(F36="Done",M36<>""),IF(COUNTIFS(Appointments!$D$6:$D$2005,D36,Appointments!$F$6:$F$2005,"Done",Appointments!$M$6:$M$2005,">"&M36)=0,1,0),0) | O36: =IF(AND(F36="Booked",M36<>"",N(B36)>=TODAY()),IF(COUNTIFS(Appointments!$D$6:$D$2005,D36,Appointments!$F$6:$F$2005,"Booked",Appointments!$B$6:$B$2005,">="&TODAY(),Appointments!$M$6:$M$2005,"<"&M36)=0,1,0),0)
B37: 46036 | C37: 0.375 | D37: Ben Carter | E37: Men's haircut | F37: Done | G37: =IF(E37="","",MAX(0,IFERROR(INDEX(Services!$C$6:$C$35,MATCH(E37,Services!$B$6:$B$35,0)),0)-N(H37))) | I37: 30 | J37: Card | K37: =IF(OR(B37="",F37<>"Done",J37="Package"),"",IF(N(G37)-N(I37)>0,N(G37)-N(I37),"")) | M37: =IF(OR(B37="",D37="",F37="Cancelled"),"",B37+N(C37)+ROW()/10000000) | N37: =IF(AND(F37="Done",M37<>""),IF(COUNTIFS(Appointments!$D$6:$D$2005,D37,Appointments!$F$6:$F$2005,"Done",Appointments!$M$6:$M$2005,">"&M37)=0,1,0),0) | O37: =IF(AND(F37="Booked",M37<>"",N(B37)>=TODAY()),IF(COUNTIFS(Appointments!$D$6:$D$2005,D37,Appointments!$F$6:$F$2005,"Booked",Appointments!$B$6:$B$2005,">="&TODAY(),Appointments!$M$6:$M$2005,"<"&M37)=0,1,0),0)
B38: 46036 | C38: 0.40277778 | D38: Dina Baker | E38: Women's haircut | F38: Done | G38: =IF(E38="","",MAX(0,IFERROR(INDEX(Services!$C$6:$C$35,MATCH(E38,Services!$B$6:$B$35,0)),0)-N(H38))) | I38: 55 | J38: Card | K38: =IF(OR(B38="",F38<>"Done",J38="Package"),"",IF(N(G38)-N(I38)>0,N(G38)-N(I38),"")) | M38: =IF(OR(B38="",D38="",F38="Cancelled"),"",B38+N(C38)+ROW()/10000000) | N38: =IF(AND(F38="Done",M38<>""),IF(COUNTIFS(Appointments!$D$6:$D$2005,D38,Appointments!$F$6:$F$2005,"Done",Appointments!$M$6:$M$2005,">"&M38)=0,1,0),0) | O38: =IF(AND(F38="Booked",M38<>"",N(B38)>=TODAY()),IF(COUNTIFS(Appointments!$D$6:$D$2005,D38,Appointments!$F$6:$F$2005,"Booked",Appointments!$B$6:$B$2005,">="&TODAY(),Appointments!$M$6:$M$2005,"<"&M38)=0,1,0),0)
B39: 46036 | C39: 0.45138889 | D39: Eli Hughes | E39: Men's haircut | F39: Done | G39: =IF(E39="","",MAX(0,IFERROR(INDEX(Services!$C$6:$C$35,MATCH(E39,Services!$B$6:$B$35,0)),0)-N(H39))) | I39: 30 | J39: Card | K39: =IF(OR(B39="",F39<>"Done",J39="Package"),"",IF(N(G39)-N(I39)>0,N(G39)-N(I39),"")) | M39: =IF(OR(B39="",D39="",F39="Cancelled"),"",B39+N(C39)+ROW()/10000000) | N39: =IF(AND(F39="Done",M39<>""),IF(COUNTIFS(Appointments!$D$6:$D$2005,D39,Appointments!$F$6:$F$2005,"Done",Appointments!$M$6:$M$2005,">"&M39)=0,1,0),0) | O39: =IF(AND(F39="Booked",M39<>"",N(B39)>=TODAY()),IF(COUNTIFS(Appointments!$D$6:$D$2005,D39,Appointments!$F$6:$F$2005,"Booked",Appointments!$B$6:$B$2005,">="&TODAY(),Appointments!$M$6:$M$2005,"<"&M39)=0,1,0),0)
B40: 46036 | C40: 0.47916667 | D40: Jade Hill | E40: Women's haircut | F40: Done | G40: =IF(E40="","",MAX(0,IFERROR(INDEX(Services!$C$6:$C$35,MATCH(E40,Services!$B$6:$B$35,0)),0)-N(H40))) | I40: 55 | J40: Cash | K40: =IF(OR(B40="",F40<>"Done",J40="Package"),"",IF(N(G40)-N(I40)>0,N(G40)-N(I40),"")) | M40: =IF(OR(B40="",D40="",F40="Cancelled"),"",B40+N(C40)+ROW()/10000000) | N40: =IF(AND(F40="Done",M40<>""),IF(COUNTIFS(Appointments!$D$6:$D$2005,D40,Appointments!$F$6:$F$2005,"Done",Appointments!$M$6:$M$2005,">"&M40)=0,1,0),0) | O40: =IF(AND(F40="Booked",M40<>"",N(B40)>=TODAY()),IF(COUNTIFS(Appointments!$D$6:$D$2005,D40,Appointments!$F$6:$F$2005,"Booked",Appointments!$B$6:$B$2005,">="&TODAY(),Appointments!$M$6:$M$2005,"<"&M40)=0,1,0),0)
B41: 46036 | C41: 0.52777778 | D41: Jon Reid | E41: Men's haircut | F41: Done | G41: =IF(E41="","",MAX(0,IFERROR(INDEX(Services!$C$6:$C$35,MATCH(E41,Services!$B$6:$B$35,0)),0)-N(H41))) | I41: 30 | J41: Cash | K41: =IF(OR(B41="",F41<>"Done",J41="Package"),"",IF(N(G41)-N(I41)>0,N(G41)-N(I41),"")) | M41: =IF(OR(B41="",D41="",F41="Cancelled"),"",B41+N(C41)+ROW()/10000000) | N41: =IF(AND(F41="Done",M41<>""),IF(COUNTIFS(Appointments!$D$6:$D$2005,D41,Appointments!$F$6:$F$2005,"Done",Appointments!$M$6:$M$2005,">"&M41)=0,1,0),0) | O41: =IF(AND(F41="Booked",M41<>"",N(B41)>=TODAY()),IF(COUNTIFS(Appointments!$D$6:$D$2005,D41,Appointments!$F$6:$F$2005,"Booked",Appointments!$B$6:$B$2005,">="&TODAY(),Appointments!$M$6:$M$2005,"<"&M41)=0,1,0),0)
B42: 46036 | C42: 0.55555556 | D42: Sam Clarke | E42: Men's haircut | F42: Done | G42: =IF(E42="","",MAX(0,IFERROR(INDEX(Services!$C$6:$C$35,MATCH(E42,Services!$B$6:$B$35,0)),0)-N(H42))) | I42: 30 | J42: Card | K42: =IF(OR(B42="",F42<>"Done",J42="Package"),"",IF(N(G42)-N(I42)>0,N(G42)-N(I42),"")) | M42: =IF(OR(B42="",D42="",F42="Cancelled"),"",B42+N(C42)+ROW()/10000000) | N42: =IF(AND(F42="Done",M42<>""),IF(COUNTIFS(Appointments!$D$6:$D$2005,D42,Appointments!$F$6:$F$2005,"Done",Appointments!$M$6:$M$2005,">"&M42)=0,1,0),0) | O42: =IF(AND(F42="Booked",M42<>"",N(B42)>=TODAY()),IF(COUNTIFS(Appointments!$D$6:$D$2005,D42,Appointments!$F$6:$F$2005,"Booked",Appointments!$B$6:$B$2005,">="&TODAY(),Appointments!$M$6:$M$2005,"<"&M42)=0,1,0),0)
B43: 46036 | C43: 0.58333333 | D43: Sophie Cox | E43: Women's haircut | F43: Done | G43: =IF(E43="","",MAX(0,IFERROR(INDEX(Services!$C$6:$C$35,MATCH(E43,Services!$B$6:$B$35,0)),0)-N(H43))) | I43: 55 | J43: Card | K43: =IF(OR(B43="",F43<>"Done",J43="Package"),"",IF(N(G43)-N(I43)>0,N(G43)-N(I43),"")) | M43: =IF(OR(B43="",D43="",F43="Cancelled"),"",B43+N(C43)+ROW()/10000000) | N43: =IF(AND(F43="Done",M43<>""),IF(COUNTIFS(Appointments!$D$6:$D$2005,D43,Appointments!$F$6:$F$2005,"Done",Appointments!$M$6:$M$2005,">"&M43)=0,1,0),0) | O43: =IF(AND(F43="Booked",M43<>"",N(B43)>=TODAY()),IF(COUNTIFS(Appointments!$D$6:$D$2005,D43,Appointments!$F$6:$F$2005,"Booked",Appointments!$B$6:$B$2005,">="&TODAY(),Appointments!$M$6:$M$2005,"<"&M43)=0,1,0),0)
B44: 46037 | C44: 0.375 | D44: Adam Gray | E44: Men's haircut | F44: Done | G44: =IF(E44="","",MAX(0,IFERROR(INDEX(Services!$C$6:$C$35,MATCH(E44,Services!$B$6:$B$35,0)),0)-N(H44))) | I44: 30 | J44: Card | K44: =IF(OR(B44="",F44<>"Done",J44="Package"),"",IF(N(G44)-N(I44)>0,N(G44)-N(I44),"")) | M44: =IF(OR(B44="",D44="",F44="Cancelled"),"",B44+N(C44)+ROW()/10000000) | N44: =IF(AND(F44="Done",M44<>""),IF(COUNTIFS(Appointments!$D$6:$D$2005,D44,Appointments!$F$6:$F$2005,"Done",Appointments!$M$6:$M$2005,">"&M44)=0,1,0),0) | O44: =IF(AND(F44="Booked",M44<>"",N(B44)>=TODAY()),IF(COUNTIFS(Appointments!$D$6:$D$2005,D44,Appointments!$F$6:$F$2005,"Booked",Appointments!$B$6:$B$2005,">="&TODAY(),Appointments!$M$6:$M$2005,"<"&M44)=0,1,0),0)
B45: 46037 | C45: 0.40277778 | D45: Holly Gray | E45: Women's haircut | F45: Done | G45: =IF(E45="","",MAX(0,IFERROR(INDEX(Services!$C$6:$C$35,MATCH(E45,Services!$B$6:$B$35,0)),0)-N(H45))) | I45: 55 | J45: Transfer | K45: =IF(OR(B45="",F45<>"Done",J45="Package"),"",IF(N(G45)-N(I45)>0,N(G45)-N(I45),"")) | M45: =IF(OR(B45="",D45="",F45="Cancelled"),"",B45+N(C45)+ROW()/10000000) | N45: =IF(AND(F45="Done",M45<>""),IF(COUNTIFS(Appointments!$D$6:$D$2005,D45,Appointments!$F$6:$F$2005,"Done",Appointments!$M$6:$M$2005,">"&M45)=0,1,0),0) | O45: =IF(AND(F45="Booked",M45<>"",N(B45)>=TODAY()),IF(COUNTIFS(Appointments!$D$6:$D$2005,D45,Appointments!$F$6:$F$2005,"Booked",Appointments!$B$6:$B$2005,">="&TODAY(),Appointments!$M$6:$M$2005,"<"&M45)=0,1,0),0)
B46: 46037 | C46: 0.45138889 | D46: Ian Bell | E46: Men's haircut | F46: Done | G46: =IF(E46="","",MAX(0,IFERROR(INDEX(Services!$C$6:$C$35,MATCH(E46,Services!$B$6:$B$35,0)),0)-N(H46))) | I46: 30 | J46: Transfer | K46: =IF(OR(B46="",F46<>"Done",J46="Package"),"",IF(N(G46)-N(I46)>0,N(G46)-N(I46),"")) | M46: =IF(OR(B46="",D46="",F46="Cancelled"),"",B46+N(C46)+ROW()/10000000) | N46: =IF(AND(F46="Done",M46<>""),IF(COUNTIFS(Appointments!$D$6:$D$2005,D46,Appointments!$F$6:$F$2005,"Done",Appointments!$M$6:$M$2005,">"&M46)=0,1,0),0) | O46: =IF(AND(F46="Booked",M46<>"",N(B46)>=TODAY()),IF(COUNTIFS(Appointments!$D$6:$D$2005,D46,Appointments!$F$6:$F$2005,"Booked",Appointments!$B$6:$B$2005,">="&TODAY(),Appointments!$M$6:$M$2005,"<"&M46)=0,1,0),0)
B47: 46037 | C47: 0.47916667 | D47: Kara Young | E47: Toner | F47: Done | G47: =IF(E47="","",MAX(0,IFERROR(INDEX(Services!$C$6:$C$35,MATCH(E47,Services!$B$6:$B$35,0)),0)-N(H47))) | I47: 40 | J47: Card | K47: =IF(OR(B47="",F47<>"Done",J47="Package"),"",IF(N(G47)-N(I47)>0,N(G47)-N(I47),"")) | M47: =IF(OR(B47="",D47="",F47="Cancelled"),"",B47+N(C47)+ROW()/10000000) | N47: =IF(AND(F47="Done",M47<>""),IF(COUNTIFS(Appointments!$D$6:$D$2005,D47,Appointments!$F$6:$F$2005,"Done",Appointments!$M$6:$M$2005,">"&M47)=0,1,0),0) | O47: =IF(AND(F47="Booked",M47<>"",N(B47)>=TODAY()),IF(COUNTIFS(Appointments!$D$6:$D$2005,D47,Appointments!$F$6:$F$2005,"Booked",Appointments!$B$6:$B$2005,">="&TODAY(),Appointments!$M$6:$M$2005,"<"&M47)=0,1,0),0)
B48: 46037 | C48: 0.50694444 | D48: Luke Lewis | E48: Men's haircut | F48: Done | G48: =IF(E48="","",MAX(0,IFERROR(INDEX(Services!$C$6:$C$35,MATCH(E48,Services!$B$6:$B$35,0)),0)-N(H48))) | I48: 30 | J48: Card | K48: =IF(OR(B48="",F48<>"Done",J48="Package"),"",IF(N(G48)-N(I48)>0,N(G48)-N(I48),"")) | M48: =IF(OR(B48="",D48="",F48="Cancelled"),"",B48+N(C48)+ROW()/10000000) | N48: =IF(AND(F48="Done",M48<>""),IF(COUNTIFS(Appointments!$D$6:$D$2005,D48,Appointments!$F$6:$F$2005,"Done",Appointments!$M$6:$M$2005,">"&M48)=0,1,0),0) | O48: =IF(AND(F48="Booked",M48<>"",N(B48)>=TODAY()),IF(COUNTIFS(Appointments!$D$6:$D$2005,D48,Appointments!$F$6:$F$2005,"Booked",Appointments!$B$6:$B$2005,">="&TODAY(),Appointments!$M$6:$M$2005,"<"&M48)=0,1,0),0)
B49: 46037 | C49: 0.53472222 | D49: Quinn Harris | E49: Highlights | F49: Done | G49: =IF(E49="","",MAX(0,IFERROR(INDEX(Services!$C$6:$C$35,MATCH(E49,Services!$B$6:$B$35,0)),0)-N(H49))) | H49: 10 | I49: 130 | J49: Card | K49: =IF(OR(B49="",F49<>"Done",J49="Package"),"",IF(N(G49)-N(I49)>0,N(G49)-N(I49),"")) | L49: Friends and family | M49: =IF(OR(B49="",D49="",F49="Cancelled"),"",B49+N(C49)+ROW()/10000000) | N49: =IF(AND(F49="Done",M49<>""),IF(COUNTIFS(Appointments!$D$6:$D$2005,D49,Appointments!$F$6:$F$2005,"Done",Appointments!$M$6:$M$2005,">"&M49)=0,1,0),0) | O49: =IF(AND(F49="Booked",M49<>"",N(B49)>=TODAY()),IF(COUNTIFS(Appointments!$D$6:$D$2005,D49,Appointments!$F$6:$F$2005,"Booked",Appointments!$B$6:$B$2005,">="&TODAY(),Appointments!$M$6:$M$2005,"<"&M49)=0,1,0),0)
B50: 46037 | C50: 0.64583333 | D50: Tom Gray | E50: Men's haircut | F50: Done | G50: =IF(E50="","",MAX(0,IFERROR(INDEX(Services!$C$6:$C$35,MATCH(E50,Services!$B$6:$B$35,0)),0)-N(H50))) | I50: 30 | J50: App | K50: =IF(OR(B50="",F50<>"Done",J50="Package"),"",IF(N(G50)-N(I50)>0,N(G50)-N(I50),"")) | M50: =IF(OR(B50="",D50="",F50="Cancelled"),"",B50+N(C50)+ROW()/10000000) | N50: =IF(AND(F50="Done",M50<>""),IF(COUNTIFS(Appointments!$D$6:$D$2005,D50,Appointments!$F$6:$F$2005,"Done",Appointments!$M$6:$M$2005,">"&M50)=0,1,0),0) | O50: =IF(AND(F50="Booked",M50<>"",N(B50)>=TODAY()),IF(COUNTIFS(Appointments!$D$6:$D$2005,D50,Appointments!$F$6:$F$2005,"Booked",Appointments!$B$6:$B$2005,">="&TODAY(),Appointments!$M$6:$M$2005,"<"&M50)=0,1,0),0)
B51: 46038 | C51: 0.375 | D51: Dina Adams | E51: Women's haircut | F51: Done | G51: =IF(E51="","",MAX(0,IFERROR(INDEX(Services!$C$6:$C$35,MATCH(E51,Services!$B$6:$B$35,0)),0)-N(H51))) | I51: 55 | J51: Cash | K51: =IF(OR(B51="",F51<>"Done",J51="Package"),"",IF(N(G51)-N(I51)>0,N(G51)-N(I51),"")) | M51: =IF(OR(B51="",D51="",F51="Cancelled"),"",B51+N(C51)+ROW()/10000000) | N51: =IF(AND(F51="Done",M51<>""),IF(COUNTIFS(Appointments!$D$6:$D$2005,D51,Appointments!$F$6:$F$2005,"Done",Appointments!$M$6:$M$2005,">"&M51)=0,1,0),0) | O51: =IF(AND(F51="Booked",M51<>"",N(B51)>=TODAY()),IF(COUNTIFS(Appointments!$D$6:$D$2005,D51,Appointments!$F$6:$F$2005,"Booked",Appointments!$B$6:$B$2005,">="&TODAY(),Appointments!$M$6:$M$2005,"<"&M51)=0,1,0),0)
B52: 46038 | C52: 0.42361111 | D52: Finn Gray | E52: Men's haircut | F52: Done | G52: =IF(E52="","",MAX(0,IFERROR(INDEX(Services!$C$6:$C$35,MATCH(E52,Services!$B$6:$B$35,0)),0)-N(H52))) | I52: 30 | J52: App | K52: =IF(OR(B52="",F52<>"Done",J52="Package"),"",IF(N(G52)-N(I52)>0,N(G52)-N(I52),"")) | M52: =IF(OR(B52="",D52="",F52="Cancelled"),"",B52+N(C52)+ROW()/10000000) | N52: =IF(AND(F52="Done",M52<>""),IF(COUNTIFS(Appointments!$D$6:$D$2005,D52,Appointments!$F$6:$F$2005,"Done",Appointments!$M$6:$M$2005,">"&M52)=0,1,0),0) | O52: =IF(AND(F52="Booked",M52<>"",N(B52)>=TODAY()),IF(COUNTIFS(Appointments!$D$6:$D$2005,D52,Appointments!$F$6:$F$2005,"Booked",Appointments!$B$6:$B$2005,">="&TODAY(),Appointments!$M$6:$M$2005,"<"&M52)=0,1,0),0)
B53: 46038 | C53: 0.45138889 | D53: George Kelly | E53: Men's haircut | F53: Done | G53: =IF(E53="","",MAX(0,IFERROR(INDEX(Services!$C$6:$C$35,MATCH(E53,Services!$B$6:$B$35,0)),0)-N(H53))) | I53: 30 | J53: Card | K53: =IF(OR(B53="",F53<>"Done",J53="Package"),"",IF(N(G53)-N(I53)>0,N(G53)-N(I53),"")) | M53: =IF(OR(B53="",D53="",F53="Cancelled"),"",B53+N(C53)+ROW()/10000000) | N53: =IF(AND(F53="Done",M53<>""),IF(COUNTIFS(Appointments!$D$6:$D$2005,D53,Appointments!$F$6:$F$2005,"Done",Appointments!$M$6:$M$2005,">"&M53)=0,1,0),0) | O53: =IF(AND(F53="Booked",M53<>"",N(B53)>=TODAY()),IF(COUNTIFS(Appointments!$D$6:$D$2005,D53,Appointments!$F$6:$F$2005,"Booked",Appointments!$B$6:$B$2005,">="&TODAY(),Appointments!$M$6:$M$2005,"<"&M53)=0,1,0),0)
B54: 46038 | C54: 0.47916667 | D54: Grace Lee | E54: Women's haircut | F54: Done | G54: =IF(E54="","",MAX(0,IFERROR(INDEX(Services!$C$6:$C$35,MATCH(E54,Services!$B$6:$B$35,0)),0)-N(H54))) | I54: 55 | J54: Card | K54: =IF(OR(B54="",F54<>"Done",J54="Package"),"",IF(N(G54)-N(I54)>0,N(G54)-N(I54),"")) | M54: =IF(OR(B54="",D54="",F54="Cancelled"),"",B54+N(C54)+ROW()/10000000) | N54: =IF(AND(F54="Done",M54<>""),IF(COUNTIFS(Appointments!$D$6:$D$2005,D54,Appointments!$F$6:$F$2005,"Done",Appointments!$M$6:$M$2005,">"&M54)=0,1,0),0) | O54: =IF(AND(F54="Booked",M54<>"",N(B54)>=TODAY()),IF(COUNTIFS(Appointments!$D$6:$D$2005,D54,Appointments!$F$6:$F$2005,"Booked",Appointments!$B$6:$B$2005,">="&TODAY(),Appointments!$M$6:$M$2005,"<"&M54)=0,1,0),0)
B55: 46038 | C55: 0.52777778 | D55: Harry Ellis | E55: Men's haircut | F55: Done | G55: =IF(E55="","",MAX(0,IFERROR(INDEX(Services!$C$6:$C$35,MATCH(E55,Services!$B$6:$B$35,0)),0)-N(H55))) | I55: 30 | J55: Cash | K55: =IF(OR(B55="",F55<>"Done",J55="Package"),"",IF(N(G55)-N(I55)>0,N(G55)-N(I55),"")) | M55: =IF(OR(B55="",D55="",F55="Cancelled"),"",B55+N(C55)+ROW()/10000000) | N55: =IF(AND(F55="Done",M55<>""),IF(COUNTIFS(Appointments!$D$6:$D$2005,D55,Appointments!$F$6:$F$2005,"Done",Appointments!$M$6:$M$2005,">"&M55)=0,1,0),0) | O55: =IF(AND(F55="Booked",M55<>"",N(B55)>=TODAY()),IF(COUNTIFS(Appointments!$D$6:$D$2005,D55,Appointments!$F$6:$F$2005,"Booked",Appointments!$B$6:$B$2005,">="&TODAY(),Appointments!$M$6:$M$2005,"<"&M55)=0,1,0),0)
B56: 46038 | C56: 0.55555556 | D56: Ian Reed | E56: Men's haircut | F56: Done | G56: =IF(E56="","",MAX(0,IFERROR(INDEX(Services!$C$6:$C$35,MATCH(E56,Services!$B$6:$B$35,0)),0)-N(H56))) | I56: 30 | J56: Card | K56: =IF(OR(B56="",F56<>"Done",J56="Package"),"",IF(N(G56)-N(I56)>0,N(G56)-N(I56),"")) | M56: =IF(OR(B56="",D56="",F56="Cancelled"),"",B56+N(C56)+ROW()/10000000) | N56: =IF(AND(F56="Done",M56<>""),IF(COUNTIFS(Appointments!$D$6:$D$2005,D56,Appointments!$F$6:$F$2005,"Done",Appointments!$M$6:$M$2005,">"&M56)=0,1,0),0) | O56: =IF(AND(F56="Booked",M56<>"",N(B56)>=TODAY()),IF(COUNTIFS(Appointments!$D$6:$D$2005,D56,Appointments!$F$6:$F$2005,"Booked",Appointments!$B$6:$B$2005,">="&TODAY(),Appointments!$M$6:$M$2005,"<"&M56)=0,1,0),0)
B57: 46038 | C57: 0.58333333 | D57: Tina Walsh | E57: Blow dry | F57: Done | G57: =IF(E57="","",MAX(0,IFERROR(INDEX(Services!$C$6:$C$35,MATCH(E57,Services!$B$6:$B$35,0)),0)-N(H57))) | I57: 35 | J57: Card | K57: =IF(OR(B57="",F57<>"Done",J57="Package"),"",IF(N(G57)-N(I57)>0,N(G57)-N(I57),"")) | M57: =IF(OR(B57="",D57="",F57="Cancelled"),"",B57+N(C57)+ROW()/10000000) | N57: =IF(AND(F57="Done",M57<>""),IF(COUNTIFS(Appointments!$D$6:$D$2005,D57,Appointments!$F$6:$F$2005,"Done",Appointments!$M$6:$M$2005,">"&M57)=0,1,0),0) | O57: =IF(AND(F57="Booked",M57<>"",N(B57)>=TODAY()),IF(COUNTIFS(Appointments!$D$6:$D$2005,D57,Appointments!$F$6:$F$2005,"Booked",Appointments!$B$6:$B$2005,">="&TODAY(),Appointments!$M$6:$M$2005,"<"&M57)=0,1,0),0)
B58: 46039 | C58: 0.375 | D58: Adam King | E58: Men's haircut | F58: Done | G58: =IF(E58="","",MAX(0,IFERROR(INDEX(Services!$C$6:$C$35,MATCH(E58,Services!$B$6:$B$35,0)),0)-N(H58))) | I58: 30 | J58: Card | K58: =IF(OR(B58="",F58<>"Done",J58="Package"),"",IF(N(G58)-N(I58)>0,N(G58)-N(I58),"")) | M58: =IF(OR(B58="",D58="",F58="Cancelled"),"",B58+N(C58)+ROW()/10000000) | N58: =IF(AND(F58="Done",M58<>""),IF(COUNTIFS(Appointments!$D$6:$D$2005,D58,Appointments!$F$6:$F$2005,"Done",Appointments!$M$6:$M$2005,">"&M58)=0,1,0),0) | O58: =IF(AND(F58="Booked",M58<>"",N(B58)>=TODAY()),IF(COUNTIFS(Appointments!$D$6:$D$2005,D58,Appointments!$F$6:$F$2005,"Booked",Appointments!$B$6:$B$2005,">="&TODAY(),Appointments!$M$6:$M$2005,"<"&M58)=0,1,0),0)
B59: 46039 | C59: 0.40277778 | D59: Eli Brooks | E59: Men's haircut | F59: Done | G59: =IF(E59="","",MAX(0,IFERROR(INDEX(Services!$C$6:$C$35,MATCH(E59,Services!$B$6:$B$35,0)),0)-N(H59))) | I59: 30 | J59: Cash | K59: =IF(OR(B59="",F59<>"Done",J59="Package"),"",IF(N(G59)-N(I59)>0,N(G59)-N(I59),"")) | M59: =IF(OR(B59="",D59="",F59="Cancelled"),"",B59+N(C59)+ROW()/10000000) | N59: =IF(AND(F59="Done",M59<>""),IF(COUNTIFS(Appointments!$D$6:$D$2005,D59,Appointments!$F$6:$F$2005,"Done",Appointments!$M$6:$M$2005,">"&M59)=0,1,0),0) | O59: =IF(AND(F59="Booked",M59<>"",N(B59)>=TODAY()),IF(COUNTIFS(Appointments!$D$6:$D$2005,D59,Appointments!$F$6:$F$2005,"Booked",Appointments!$B$6:$B$2005,">="&TODAY(),Appointments!$M$6:$M$2005,"<"&M59)=0,1,0),0)
B60: 46039 | C60: 0.43055556 | D60: Finn Wood | E60: Men's haircut | F60: Done | G60: =IF(E60="","",MAX(0,IFERROR(INDEX(Services!$C$6:$C$35,MATCH(E60,Services!$B$6:$B$35,0)),0)-N(H60))) | I60: 30 | J60: Cash | K60: =IF(OR(B60="",F60<>"Done",J60="Package"),"",IF(N(G60)-N(I60)>0,N(G60)-N(I60),"")) | M60: =IF(OR(B60="",D60="",F60="Cancelled"),"",B60+N(C60)+ROW()/10000000) | N60: =IF(AND(F60="Done",M60<>""),IF(COUNTIFS(Appointments!$D$6:$D$2005,D60,Appointments!$F$6:$F$2005,"Done",Appointments!$M$6:$M$2005,">"&M60)=0,1,0),0) | O60: =IF(AND(F60="Booked",M60<>"",N(B60)>=TODAY()),IF(COUNTIFS(Appointments!$D$6:$D$2005,D60,Appointments!$F$6:$F$2005,"Booked",Appointments!$B$6:$B$2005,">="&TODAY(),Appointments!$M$6:$M$2005,"<"&M60)=0,1,0),0)
B61: 46039 | C61: 0.45833333 | D61: Jon Gray | E61: Men's haircut | F61: Done | G61: =IF(E61="","",MAX(0,IFERROR(INDEX(Services!$C$6:$C$35,MATCH(E61,Services!$B$6:$B$35,0)),0)-N(H61))) | I61: 30 | J61: Cash | K61: =IF(OR(B61="",F61<>"Done",J61="Package"),"",IF(N(G61)-N(I61)>0,N(G61)-N(I61),"")) | M61: =IF(OR(B61="",D61="",F61="Cancelled"),"",B61+N(C61)+ROW()/10000000) | N61: =IF(AND(F61="Done",M61<>""),IF(COUNTIFS(Appointments!$D$6:$D$2005,D61,Appointments!$F$6:$F$2005,"Done",Appointments!$M$6:$M$2005,">"&M61)=0,1,0),0) | O61: =IF(AND(F61="Booked",M61<>"",N(B61)>=TODAY()),IF(COUNTIFS(Appointments!$D$6:$D$2005,D61,Appointments!$F$6:$F$2005,"Booked",Appointments!$B$6:$B$2005,">="&TODAY(),Appointments!$M$6:$M$2005,"<"&M61)=0,1,0),0)
B62: 46039 | C62: 0.48611111 | D62: Luke Reed | E62: Men's haircut | F62: Done | G62: =IF(E62="","",MAX(0,IFERROR(INDEX(Services!$C$6:$C$35,MATCH(E62,Services!$B$6:$B$35,0)),0)-N(H62))) | I62: 30 | J62: Cash | K62: =IF(OR(B62="",F62<>"Done",J62="Package"),"",IF(N(G62)-N(I62)>0,N(G62)-N(I62),"")) | M62: =IF(OR(B62="",D62="",F62="Cancelled"),"",B62+N(C62)+ROW()/10000000) | N62: =IF(AND(F62="Done",M62<>""),IF(COUNTIFS(Appointments!$D$6:$D$2005,D62,Appointments!$F$6:$F$2005,"Done",Appointments!$M$6:$M$2005,">"&M62)=0,1,0),0) | O62: =IF(AND(F62="Booked",M62<>"",N(B62)>=TODAY()),IF(COUNTIFS(Appointments!$D$6:$D$2005,D62,Appointments!$F$6:$F$2005,"Booked",Appointments!$B$6:$B$2005,">="&TODAY(),Appointments!$M$6:$M$2005,"<"&M62)=0,1,0),0)
B63: 46039 | C63: 0.51388889 | D63: Ryan Adams | E63: Men's haircut | F63: Done | G63: =IF(E63="","",MAX(0,IFERROR(INDEX(Services!$C$6:$C$35,MATCH(E63,Services!$B$6:$B$35,0)),0)-N(H63))) | H63: 10 | I63: 20 | J63: Card | K63: =IF(OR(B63="",F63<>"Done",J63="Package"),"",IF(N(G63)-N(I63)>0,N(G63)-N(I63),"")) | L63: Friends and family | M63: =IF(OR(B63="",D63="",F63="Cancelled"),"",B63+N(C63)+ROW()/10000000) | N63: =IF(AND(F63="Done",M63<>""),IF(COUNTIFS(Appointments!$D$6:$D$2005,D63,Appointments!$F$6:$F$2005,"Done",Appointments!$M$6:$M$2005,">"&M63)=0,1,0),0) | O63: =IF(AND(F63="Booked",M63<>"",N(B63)>=TODAY()),IF(COUNTIFS(Appointments!$D$6:$D$2005,D63,Appointments!$F$6:$F$2005,"Booked",Appointments!$B$6:$B$2005,">="&TODAY(),Appointments!$M$6:$M$2005,"<"&M63)=0,1,0),0)
B64: 46039 | C64: 0.54166667 | D64: Sara Ward | E64: Women's haircut | F64: Done | G64: =IF(E64="","",MAX(0,IFERROR(INDEX(Services!$C$6:$C$35,MATCH(E64,Services!$B$6:$B$35,0)),0)-N(H64))) | I64: 55 | J64: Card | K64: =IF(OR(B64="",F64<>"Done",J64="Package"),"",IF(N(G64)-N(I64)>0,N(G64)-N(I64),"")) | M64: =IF(OR(B64="",D64="",F64="Cancelled"),"",B64+N(C64)+ROW()/10000000) | N64: =IF(AND(F64="Done",M64<>""),IF(COUNTIFS(Appointments!$D$6:$D$2005,D64,Appointments!$F$6:$F$2005,"Done",Appointments!$M$6:$M$2005,">"&M64)=0,1,0),0) | O64: =IF(AND(F64="Booked",M64<>"",N(B64)>=TODAY()),IF(COUNTIFS(Appointments!$D$6:$D$2005,D64,Appointments!$F$6:$F$2005,"Booked",Appointments!$B$6:$B$2005,">="&TODAY(),Appointments!$M$6:$M$2005,"<"&M64)=0,1,0),0)
B65: 46042 | C65: 0.375 | D65: Chloe Martin | E65: Highlights | F65: Done | G65: =IF(E65="","",MAX(0,IFERROR(INDEX(Services!$C$6:$C$35,MATCH(E65,Services!$B$6:$B$35,0)),0)-N(H65))) | I65: 140 | J65: Cash | K65: =IF(OR(B65="",F65<>"Done",J65="Package"),"",IF(N(G65)-N(I65)>0,N(G65)-N(I65),"")) | M65: =IF(OR(B65="",D65="",F65="Cancelled"),"",B65+N(C65)+ROW()/10000000) | N65: =IF(AND(F65="Done",M65<>""),IF(COUNTIFS(Appointments!$D$6:$D$2005,D65,Appointments!$F$6:$F$2005,"Done",Appointments!$M$6:$M$2005,">"&M65)=0,1,0),0) | O65: =IF(AND(F65="Booked",M65<>"",N(B65)>=TODAY()),IF(COUNTIFS(Appointments!$D$6:$D$2005,D65,Appointments!$F$6:$F$2005,"Booked",Appointments!$B$6:$B$2005,">="&TODAY(),Appointments!$M$6:$M$2005,"<"&M65)=0,1,0),0)
B66: 46042 | C66: 0.48611111 | D66: Daniel Kim | E66: Men's haircut | F66: Done | G66: =IF(E66="","",MAX(0,IFERROR(INDEX(Services!$C$6:$C$35,MATCH(E66,Services!$B$6:$B$35,0)),0)-N(H66))) | I66: 30 | J66: Card | K66: =IF(OR(B66="",F66<>"Done",J66="Package"),"",IF(N(G66)-N(I66)>0,N(G66)-N(I66),"")) | M66: =IF(OR(B66="",D66="",F66="Cancelled"),"",B66+N(C66)+ROW()/10000000) | N66: =IF(AND(F66="Done",M66<>""),IF(COUNTIFS(Appointments!$D$6:$D$2005,D66,Appointments!$F$6:$F$2005,"Done",Appointments!$M$6:$M$2005,">"&M66)=0,1,0),0) | O66: =IF(AND(F66="Booked",M66<>"",N(B66)>=TODAY()),IF(COUNTIFS(Appointments!$D$6:$D$2005,D66,Appointments!$F$6:$F$2005,"Booked",Appointments!$B$6:$B$2005,">="&TODAY(),Appointments!$M$6:$M$2005,"<"&M66)=0,1,0),0)
B67: 46042 | C67: 0.51388889 | D67: Finn Davies | E67: Men's haircut | F67: Done | G67: =IF(E67="","",MAX(0,IFERROR(INDEX(Services!$C$6:$C$35,MATCH(E67,Services!$B$6:$B$35,0)),0)-N(H67))) | I67: 30 | J67: Card | K67: =IF(OR(B67="",F67<>"Done",J67="Package"),"",IF(N(G67)-N(I67)>0,N(G67)-N(I67),"")) | M67: =IF(OR(B67="",D67="",F67="Cancelled"),"",B67+N(C67)+ROW()/10000000) | N67: =IF(AND(F67="Done",M67<>""),IF(COUNTIFS(Appointments!$D$6:$D$2005,D67,Appointments!$F$6:$F$2005,"Done",Appointments!$M$6:$M$2005,">"&M67)=0,1,0),0) | O67: =IF(AND(F67="Booked",M67<>"",N(B67)>=TODAY()),IF(COUNTIFS(Appointments!$D$6:$D$2005,D67,Appointments!$F$6:$F$2005,"Booked",Appointments!$B$6:$B$2005,">="&TODAY(),Appointments!$M$6:$M$2005,"<"&M67)=0,1,0),0)
B68: 46042 | C68: 0.54166667 | D68: Jack Wilson | E68: Men's haircut | F68: Done | G68: =IF(E68="","",MAX(0,IFERROR(INDEX(Services!$C$6:$C$35,MATCH(E68,Services!$B$6:$B$35,0)),0)-N(H68))) | I68: 30 | J68: Cash | K68: =IF(OR(B68="",F68<>"Done",J68="Package"),"",IF(N(G68)-N(I68)>0,N(G68)-N(I68),"")) | M68: =IF(OR(B68="",D68="",F68="Cancelled"),"",B68+N(C68)+ROW()/10000000) | N68: =IF(AND(F68="Done",M68<>""),IF(COUNTIFS(Appointments!$D$6:$D$2005,D68,Appointments!$F$6:$F$2005,"Done",Appointments!$M$6:$M$2005,">"&M68)=0,1,0),0) | O68: =IF(AND(F68="Booked",M68<>"",N(B68)>=TODAY()),IF(COUNTIFS(Appointments!$D$6:$D$2005,D68,Appointments!$F$6:$F$2005,"Booked",Appointments!$B$6:$B$2005,">="&TODAY(),Appointments!$M$6:$M$2005,"<"&M68)=0,1,0),0)
B69: 46042 | C69: 0.56944444 | D69: Matt Ellis | E69: Men's haircut | F69: Done | G69: =IF(E69="","",MAX(0,IFERROR(INDEX(Services!$C$6:$C$35,MATCH(E69,Services!$B$6:$B$35,0)),0)-N(H69))) | I69: 30 | J69: Cash | K69: =IF(OR(B69="",F69<>"Done",J69="Package"),"",IF(N(G69)-N(I69)>0,N(G69)-N(I69),"")) | M69: =IF(OR(B69="",D69="",F69="Cancelled"),"",B69+N(C69)+ROW()/10000000) | N69: =IF(AND(F69="Done",M69<>""),IF(COUNTIFS(Appointments!$D$6:$D$2005,D69,Appointments!$F$6:$F$2005,"Done",Appointments!$M$6:$M$2005,">"&M69)=0,1,0),0) | O69: =IF(AND(F69="Booked",M69<>"",N(B69)>=TODAY()),IF(COUNTIFS(Appointments!$D$6:$D$2005,D69,Appointments!$F$6:$F$2005,"Booked",Appointments!$B$6:$B$2005,">="&TODAY(),Appointments!$M$6:$M$2005,"<"&M69)=0,1,0),0)
B70: 46042 | C70: 0.59722222 | D70: Olivia Green | E70: Women's haircut | F70: Cancelled | G70: =IF(E70="","",MAX(0,IFERROR(INDEX(Services!$C$6:$C$35,MATCH(E70,Services!$B$6:$B$35,0)),0)-N(H70))) | K70: =IF(OR(B70="",F70<>"Done",J70="Package"),"",IF(N(G70)-N(I70)>0,N(G70)-N(I70),"")) | M70: =IF(OR(B70="",D70="",F70="Cancelled"),"",B70+N(C70)+ROW()/10000000) | N70: =IF(AND(F70="Done",M70<>""),IF(COUNTIFS(Appointments!$D$6:$D$2005,D70,Appointments!$F$6:$F$2005,"Done",Appointments!$M$6:$M$2005,">"&M70)=0,1,0),0) | O70: =IF(AND(F70="Booked",M70<>"",N(B70)>=TODAY()),IF(COUNTIFS(Appointments!$D$6:$D$2005,D70,Appointments!$F$6:$F$2005,"Booked",Appointments!$B$6:$B$2005,">="&TODAY(),Appointments!$M$6:$M$2005,"<"&M70)=0,1,0),0)
B71: 46042 | C71: 0.64583333 | D71: Rosa Diaz | E71: Colour | F71: Done | G71: =IF(E71="","",MAX(0,IFERROR(INDEX(Services!$C$6:$C$35,MATCH(E71,Services!$B$6:$B$35,0)),0)-N(H71))) | I71: 95 | J71: Card | K71: =IF(OR(B71="",F71<>"Done",J71="Package"),"",IF(N(G71)-N(I71)>0,N(G71)-N(I71),"")) | M71: =IF(OR(B71="",D71="",F71="Cancelled"),"",B71+N(C71)+ROW()/10000000) | N71: =IF(AND(F71="Done",M71<>""),IF(COUNTIFS(Appointments!$D$6:$D$2005,D71,Appointments!$F$6:$F$2005,"Done",Appointments!$M$6:$M$2005,">"&M71)=0,1,0),0) | O71: =IF(AND(F71="Booked",M71<>"",N(B71)>=TODAY()),IF(COUNTIFS(Appointments!$D$6:$D$2005,D71,Appointments!$F$6:$F$2005,"Booked",Appointments!$B$6:$B$2005,">="&TODAY(),Appointments!$M$6:$M$2005,"<"&M71)=0,1,0),0)
B72: 46043 | C72: 0.375 | D72: George Mason | E72: Men's haircut | F72: Done | G72: =IF(E72="","",MAX(0,IFERROR(INDEX(Services!$C$6:$C$35,MATCH(E72,Services!$B$6:$B$35,0)),0)-N(H72))) | I72: 30 | J72: Cash | K72: =IF(OR(B72="",F72<>"Done",J72="Package"),"",IF(N(G72)-N(I72)>0,N(G72)-N(I72),"")) | M72: =IF(OR(B72="",D72="",F72="Cancelled"),"",B72+N(C72)+ROW()/10000000) | N72: =IF(AND(F72="Done",M72<>""),IF(COUNTIFS(Appointments!$D$6:$D$2005,D72,Appointments!$F$6:$F$2005,"Done",Appointments!$M$6:$M$2005,">"&M72)=0,1,0),0) | O72: =IF(AND(F72="Booked",M72<>"",N(B72)>=TODAY()),IF(COUNTIFS(Appointments!$D$6:$D$2005,D72,Appointments!$F$6:$F$2005,"Booked",Appointments!$B$6:$B$2005,">="&TODAY(),Appointments!$M$6:$M$2005,"<"&M72)=0,1,0),0)
B73: 46043 | C73: 0.40277778 | D73: Harry Hill | E73: Men's haircut | F73: Done | G73: =IF(E73="","",MAX(0,IFERROR(INDEX(Services!$C$6:$C$35,MATCH(E73,Services!$B$6:$B$35,0)),0)-N(H73))) | I73: 30 | J73: Cash | K73: =IF(OR(B73="",F73<>"Done",J73="Package"),"",IF(N(G73)-N(I73)>0,N(G73)-N(I73),"")) | M73: =IF(OR(B73="",D73="",F73="Cancelled"),"",B73+N(C73)+ROW()/10000000) | N73: =IF(AND(F73="Done",M73<>""),IF(COUNTIFS(Appointments!$D$6:$D$2005,D73,Appointments!$F$6:$F$2005,"Done",Appointments!$M$6:$M$2005,">"&M73)=0,1,0),0) | O73: =IF(AND(F73="Booked",M73<>"",N(B73)>=TODAY()),IF(COUNTIFS(Appointments!$D$6:$D$2005,D73,Appointments!$F$6:$F$2005,"Booked",Appointments!$B$6:$B$2005,">="&TODAY(),Appointments!$M$6:$M$2005,"<"&M73)=0,1,0),0)
B74: 46043 | C74: 0.43055556 | D74: Helen Mason | E74: Women's haircut | F74: Cancelled | G74: =IF(E74="","",MAX(0,IFERROR(INDEX(Services!$C$6:$C$35,MATCH(E74,Services!$B$6:$B$35,0)),0)-N(H74))) | K74: =IF(OR(B74="",F74<>"Done",J74="Package"),"",IF(N(G74)-N(I74)>0,N(G74)-N(I74),"")) | M74: =IF(OR(B74="",D74="",F74="Cancelled"),"",B74+N(C74)+ROW()/10000000) | N74: =IF(AND(F74="Done",M74<>""),IF(COUNTIFS(Appointments!$D$6:$D$2005,D74,Appointments!$F$6:$F$2005,"Done",Appointments!$M$6:$M$2005,">"&M74)=0,1,0),0) | O74: =IF(AND(F74="Booked",M74<>"",N(B74)>=TODAY()),IF(COUNTIFS(Appointments!$D$6:$D$2005,D74,Appointments!$F$6:$F$2005,"Booked",Appointments!$B$6:$B$2005,">="&TODAY(),Appointments!$M$6:$M$2005,"<"&M74)=0,1,0),0)
B75: 46043 | C75: 0.47916667 | D75: Ian Hall | E75: Men's haircut | F75: Done | G75: =IF(E75="","",MAX(0,IFERROR(INDEX(Services!$C$6:$C$35,MATCH(E75,Services!$B$6:$B$35,0)),0)-N(H75))) | I75: 30 | J75: Cash | K75: =IF(OR(B75="",F75<>"Done",J75="Package"),"",IF(N(G75)-N(I75)>0,N(G75)-N(I75),"")) | M75: =IF(OR(B75="",D75="",F75="Cancelled"),"",B75+N(C75)+ROW()/10000000) | N75: =IF(AND(F75="Done",M75<>""),IF(COUNTIFS(Appointments!$D$6:$D$2005,D75,Appointments!$F$6:$F$2005,"Done",Appointments!$M$6:$M$2005,">"&M75)=0,1,0),0) | O75: =IF(AND(F75="Booked",M75<>"",N(B75)>=TODAY()),IF(COUNTIFS(Appointments!$D$6:$D$2005,D75,Appointments!$F$6:$F$2005,"Booked",Appointments!$B$6:$B$2005,">="&TODAY(),Appointments!$M$6:$M$2005,"<"&M75)=0,1,0),0)
B76: 46043 | C76: 0.50694444 | D76: Iris West | E76: Women's haircut | F76: Done | G76: =IF(E76="","",MAX(0,IFERROR(INDEX(Services!$C$6:$C$35,MATCH(E76,Services!$B$6:$B$35,0)),0)-N(H76))) | I76: 55 | J76: Card | K76: =IF(OR(B76="",F76<>"Done",J76="Package"),"",IF(N(G76)-N(I76)>0,N(G76)-N(I76),"")) | M76: =IF(OR(B76="",D76="",F76="Cancelled"),"",B76+N(C76)+ROW()/10000000) | N76: =IF(AND(F76="Done",M76<>""),IF(COUNTIFS(Appointments!$D$6:$D$2005,D76,Appointments!$F$6:$F$2005,"Done",Appointments!$M$6:$M$2005,">"&M76)=0,1,0),0) | O76: =IF(AND(F76="Booked",M76<>"",N(B76)>=TODAY()),IF(COUNTIFS(Appointments!$D$6:$D$2005,D76,Appointments!$F$6:$F$2005,"Booked",Appointments!$B$6:$B$2005,">="&TODAY(),Appointments!$M$6:$M$2005,"<"&M76)=0,1,0),0)
B77: 46043 | C77: 0.55555556 | D77: Leah Hill | E77: Women's haircut | F77: Done | G77: =IF(E77="","",MAX(0,IFERROR(INDEX(Services!$C$6:$C$35,MATCH(E77,Services!$B$6:$B$35,0)),0)-N(H77))) | I77: 55 | J77: Card | K77: =IF(OR(B77="",F77<>"Done",J77="Package"),"",IF(N(G77)-N(I77)>0,N(G77)-N(I77),"")) | M77: =IF(OR(B77="",D77="",F77="Cancelled"),"",B77+N(C77)+ROW()/10000000) | N77: =IF(AND(F77="Done",M77<>""),IF(COUNTIFS(Appointments!$D$6:$D$2005,D77,Appointments!$F$6:$F$2005,"Done",Appointments!$M$6:$M$2005,">"&M77)=0,1,0),0) | O77: =IF(AND(F77="Booked",M77<>"",N(B77)>=TODAY()),IF(COUNTIFS(Appointments!$D$6:$D$2005,D77,Appointments!$F$6:$F$2005,"Booked",Appointments!$B$6:$B$2005,">="&TODAY(),Appointments!$M$6:$M$2005,"<"&M77)=0,1,0),0)
B78: 46043 | C78: 0.60416667 | D78: Paula Mason | E78: Toner | F78: Done | G78: =IF(E78="","",MAX(0,IFERROR(INDEX(Services!$C$6:$C$35,MATCH(E78,Services!$B$6:$B$35,0)),0)-N(H78))) | I78: 40 | J78: Card | K78: =IF(OR(B78="",F78<>"Done",J78="Package"),"",IF(N(G78)-N(I78)>0,N(G78)-N(I78),"")) | M78: =IF(OR(B78="",D78="",F78="Cancelled"),"",B78+N(C78)+ROW()/10000000) | N78: =IF(AND(F78="Done",M78<>""),IF(COUNTIFS(Appointments!$D$6:$D$2005,D78,Appointments!$F$6:$F$2005,"Done",Appointments!$M$6:$M$2005,">"&M78)=0,1,0),0) | O78: =IF(AND(F78="Booked",M78<>"",N(B78)>=TODAY()),IF(COUNTIFS(Appointments!$D$6:$D$2005,D78,Appointments!$F$6:$F$2005,"Booked",Appointments!$B$6:$B$2005,">="&TODAY(),Appointments!$M$6:$M$2005,"<"&M78)=0,1,0),0)
B79: 46044 | C79: 0.375 | D79: Clara Morgan | E79: Women's haircut | F79: Done | G79: =IF(E79="","",MAX(0,IFERROR(INDEX(Services!$C$6:$C$35,MATCH(E79,Services!$B$6:$B$35,0)),0)-N(H79))) | I79: 55 | J79: Card | K79: =IF(OR(B79="",F79<>"Done",J79="Package"),"",IF(N(G79)-N(I79)>0,N(G79)-N(I79),"")) | M79: =IF(OR(B79="",D79="",F79="Cancelled"),"",B79+N(C79)+ROW()/10000000) | N79: =IF(AND(F79="Done",M79<>""),IF(COUNTIFS(Appointments!$D$6:$D$2005,D79,Appointments!$F$6:$F$2005,"Done",Appointments!$M$6:$M$2005,">"&M79)=0,1,0),0) | O79: =IF(AND(F79="Booked",M79<>"",N(B79)>=TODAY()),IF(COUNTIFS(Appointments!$D$6:$D$2005,D79,Appointments!$F$6:$F$2005,"Booked",Appointments!$B$6:$B$2005,">="&TODAY(),Appointments!$M$6:$M$2005,"<"&M79)=0,1,0),0)
B80: 46044 | C80: 0.42361111 | D80: Hugo Silva | E80: Men's haircut | F80: Done | G80: =IF(E80="","",MAX(0,IFERROR(INDEX(Services!$C$6:$C$35,MATCH(E80,Services!$B$6:$B$35,0)),0)-N(H80))) | I80: 30 | J80: Cash | K80: =IF(OR(B80="",F80<>"Done",J80="Package"),"",IF(N(G80)-N(I80)>0,N(G80)-N(I80),"")) | M80: =IF(OR(B80="",D80="",F80="Cancelled"),"",B80+N(C80)+ROW()/10000000) | N80: =IF(AND(F80="Done",M80<>""),IF(COUNTIFS(Appointments!$D$6:$D$2005,D80,Appointments!$F$6:$F$2005,"Done",Appointments!$M$6:$M$2005,">"&M80)=0,1,0),0) | O80: =IF(AND(F80="Booked",M80<>"",N(B80)>=TODAY()),IF(COUNTIFS(Appointments!$D$6:$D$2005,D80,Appointments!$F$6:$F$2005,"Booked",Appointments!$B$6:$B$2005,">="&TODAY(),Appointments!$M$6:$M$2005,"<"&M80)=0,1,0),0)
B81: 46044 | C81: 0.45138889 | D81: Mia Cole | E81: Women's haircut | F81: Done | G81: =IF(E81="","",MAX(0,IFERROR(INDEX(Services!$C$6:$C$35,MATCH(E81,Services!$B$6:$B$35,0)),0)-N(H81))) | I81: 55 | J81: Card | K81: =IF(OR(B81="",F81<>"Done",J81="Package"),"",IF(N(G81)-N(I81)>0,N(G81)-N(I81),"")) | M81: =IF(OR(B81="",D81="",F81="Cancelled"),"",B81+N(C81)+ROW()/10000000) | N81: =IF(AND(F81="Done",M81<>""),IF(COUNTIFS(Appointments!$D$6:$D$2005,D81,Appointments!$F$6:$F$2005,"Done",Appointments!$M$6:$M$2005,">"&M81)=0,1,0),0) | O81: =IF(AND(F81="Booked",M81<>"",N(B81)>=TODAY()),IF(COUNTIFS(Appointments!$D$6:$D$2005,D81,Appointments!$F$6:$F$2005,"Booked",Appointments!$B$6:$B$2005,">="&TODAY(),Appointments!$M$6:$M$2005,"<"&M81)=0,1,0),0)
B82: 46044 | C82: 0.5 | D82: Nick Young | E82: Men's haircut | F82: Done | G82: =IF(E82="","",MAX(0,IFERROR(INDEX(Services!$C$6:$C$35,MATCH(E82,Services!$B$6:$B$35,0)),0)-N(H82))) | I82: 30 | J82: Card | K82: =IF(OR(B82="",F82<>"Done",J82="Package"),"",IF(N(G82)-N(I82)>0,N(G82)-N(I82),"")) | M82: =IF(OR(B82="",D82="",F82="Cancelled"),"",B82+N(C82)+ROW()/10000000) | N82: =IF(AND(F82="Done",M82<>""),IF(COUNTIFS(Appointments!$D$6:$D$2005,D82,Appointments!$F$6:$F$2005,"Done",Appointments!$M$6:$M$2005,">"&M82)=0,1,0),0) | O82: =IF(AND(F82="Booked",M82<>"",N(B82)>=TODAY()),IF(COUNTIFS(Appointments!$D$6:$D$2005,D82,Appointments!$F$6:$F$2005,"Booked",Appointments!$B$6:$B$2005,">="&TODAY(),Appointments!$M$6:$M$2005,"<"&M82)=0,1,0),0)
B83: 46044 | C83: 0.52777778 | D83: Paula Cook | E83: Blow dry | F83: Done | G83: =IF(E83="","",MAX(0,IFERROR(INDEX(Services!$C$6:$C$35,MATCH(E83,Services!$B$6:$B$35,0)),0)-N(H83))) | I83: 35 | J83: Card | K83: =IF(OR(B83="",F83<>"Done",J83="Package"),"",IF(N(G83)-N(I83)>0,N(G83)-N(I83),"")) | M83: =IF(OR(B83="",D83="",F83="Cancelled"),"",B83+N(C83)+ROW()/10000000) | N83: =IF(AND(F83="Done",M83<>""),IF(COUNTIFS(Appointments!$D$6:$D$2005,D83,Appointments!$F$6:$F$2005,"Done",Appointments!$M$6:$M$2005,">"&M83)=0,1,0),0) | O83: =IF(AND(F83="Booked",M83<>"",N(B83)>=TODAY()),IF(COUNTIFS(Appointments!$D$6:$D$2005,D83,Appointments!$F$6:$F$2005,"Booked",Appointments!$B$6:$B$2005,">="&TODAY(),Appointments!$M$6:$M$2005,"<"&M83)=0,1,0),0)
B84: 46044 | C84: 0.56597222 | D84: Ruby Cook | E84: Women's haircut | F84: Done | G84: =IF(E84="","",MAX(0,IFERROR(INDEX(Services!$C$6:$C$35,MATCH(E84,Services!$B$6:$B$35,0)),0)-N(H84))) | I84: 55 | J84: Cash | K84: =IF(OR(B84="",F84<>"Done",J84="Package"),"",IF(N(G84)-N(I84)>0,N(G84)-N(I84),"")) | M84: =IF(OR(B84="",D84="",F84="Cancelled"),"",B84+N(C84)+ROW()/10000000) | N84: =IF(AND(F84="Done",M84<>""),IF(COUNTIFS(Appointments!$D$6:$D$2005,D84,Appointments!$F$6:$F$2005,"Done",Appointments!$M$6:$M$2005,">"&M84)=0,1,0),0) | O84: =IF(AND(F84="Booked",M84<>"",N(B84)>=TODAY()),IF(COUNTIFS(Appointments!$D$6:$D$2005,D84,Appointments!$F$6:$F$2005,"Booked",Appointments!$B$6:$B$2005,">="&TODAY(),Appointments!$M$6:$M$2005,"<"&M84)=0,1,0),0)
B85: 46044 | C85: 0.61458333 | D85: Tom Davies | E85: Men's haircut | F85: Done | G85: =IF(E85="","",MAX(0,IFERROR(INDEX(Services!$C$6:$C$35,MATCH(E85,Services!$B$6:$B$35,0)),0)-N(H85))) | H85: 10 | I85: 20 | J85: Card | K85: =IF(OR(B85="",F85<>"Done",J85="Package"),"",IF(N(G85)-N(I85)>0,N(G85)-N(I85),"")) | L85: Friends and family | M85: =IF(OR(B85="",D85="",F85="Cancelled"),"",B85+N(C85)+ROW()/10000000) | N85: =IF(AND(F85="Done",M85<>""),IF(COUNTIFS(Appointments!$D$6:$D$2005,D85,Appointments!$F$6:$F$2005,"Done",Appointments!$M$6:$M$2005,">"&M85)=0,1,0),0) | O85: =IF(AND(F85="Booked",M85<>"",N(B85)>=TODAY()),IF(COUNTIFS(Appointments!$D$6:$D$2005,D85,Appointments!$F$6:$F$2005,"Booked",Appointments!$B$6:$B$2005,">="&TODAY(),Appointments!$M$6:$M$2005,"<"&M85)=0,1,0),0)
B86: 46045 | C86: 0.375 | D86: Chris West | E86: Men's haircut | F86: Done | G86: =IF(E86="","",MAX(0,IFERROR(INDEX(Services!$C$6:$C$35,MATCH(E86,Services!$B$6:$B$35,0)),0)-N(H86))) | I86: 30 | J86: Card | K86: =IF(OR(B86="",F86<>"Done",J86="Package"),"",IF(N(G86)-N(I86)>0,N(G86)-N(I86),"")) | M86: =IF(OR(B86="",D86="",F86="Cancelled"),"",B86+N(C86)+ROW()/10000000) | N86: =IF(AND(F86="Done",M86<>""),IF(COUNTIFS(Appointments!$D$6:$D$2005,D86,Appointments!$F$6:$F$2005,"Done",Appointments!$M$6:$M$2005,">"&M86)=0,1,0),0) | O86: =IF(AND(F86="Booked",M86<>"",N(B86)>=TODAY()),IF(COUNTIFS(Appointments!$D$6:$D$2005,D86,Appointments!$F$6:$F$2005,"Booked",Appointments!$B$6:$B$2005,">="&TODAY(),Appointments!$M$6:$M$2005,"<"&M86)=0,1,0),0)
B87: 46045 | C87: 0.40277778 | D87: Dina West | E87: Treatment | F87: Done | G87: =IF(E87="","",MAX(0,IFERROR(INDEX(Services!$C$6:$C$35,MATCH(E87,Services!$B$6:$B$35,0)),0)-N(H87))) | I87: 30 | J87: Cash | K87: =IF(OR(B87="",F87<>"Done",J87="Package"),"",IF(N(G87)-N(I87)>0,N(G87)-N(I87),"")) | M87: =IF(OR(B87="",D87="",F87="Cancelled"),"",B87+N(C87)+ROW()/10000000) | N87: =IF(AND(F87="Done",M87<>""),IF(COUNTIFS(Appointments!$D$6:$D$2005,D87,Appointments!$F$6:$F$2005,"Done",Appointments!$M$6:$M$2005,">"&M87)=0,1,0),0) | O87: =IF(AND(F87="Booked",M87<>"",N(B87)>=TODAY()),IF(COUNTIFS(Appointments!$D$6:$D$2005,D87,Appointments!$F$6:$F$2005,"Booked",Appointments!$B$6:$B$2005,">="&TODAY(),Appointments!$M$6:$M$2005,"<"&M87)=0,1,0),0)
B88: 46045 | C88: 0.43055556 | D88: Ella Morgan | E88: Colour | F88: Done | G88: =IF(E88="","",MAX(0,IFERROR(INDEX(Services!$C$6:$C$35,MATCH(E88,Services!$B$6:$B$35,0)),0)-N(H88))) | I88: 95 | J88: Cash | K88: =IF(OR(B88="",F88<>"Done",J88="Package"),"",IF(N(G88)-N(I88)>0,N(G88)-N(I88),"")) | M88: =IF(OR(B88="",D88="",F88="Cancelled"),"",B88+N(C88)+ROW()/10000000) | N88: =IF(AND(F88="Done",M88<>""),IF(COUNTIFS(Appointments!$D$6:$D$2005,D88,Appointments!$F$6:$F$2005,"Done",Appointments!$M$6:$M$2005,">"&M88)=0,1,0),0) | O88: =IF(AND(F88="Booked",M88<>"",N(B88)>=TODAY()),IF(COUNTIFS(Appointments!$D$6:$D$2005,D88,Appointments!$F$6:$F$2005,"Booked",Appointments!$B$6:$B$2005,">="&TODAY(),Appointments!$M$6:$M$2005,"<"&M88)=0,1,0),0)
B89: 46045 | C89: 0.52083333 | D89: Jade Davies | E89: Treatment | F89: Done | G89: =IF(E89="","",MAX(0,IFERROR(INDEX(Services!$C$6:$C$35,MATCH(E89,Services!$B$6:$B$35,0)),0)-N(H89))) | I89: 30 | J89: Transfer | K89: =IF(OR(B89="",F89<>"Done",J89="Package"),"",IF(N(G89)-N(I89)>0,N(G89)-N(I89),"")) | M89: =IF(OR(B89="",D89="",F89="Cancelled"),"",B89+N(C89)+ROW()/10000000) | N89: =IF(AND(F89="Done",M89<>""),IF(COUNTIFS(Appointments!$D$6:$D$2005,D89,Appointments!$F$6:$F$2005,"Done",Appointments!$M$6:$M$2005,">"&M89)=0,1,0),0) | O89: =IF(AND(F89="Booked",M89<>"",N(B89)>=TODAY()),IF(COUNTIFS(Appointments!$D$6:$D$2005,D89,Appointments!$F$6:$F$2005,"Booked",Appointments!$B$6:$B$2005,">="&TODAY(),Appointments!$M$6:$M$2005,"<"&M89)=0,1,0),0)
B90: 46045 | C90: 0.54861111 | D90: Jade Hughes | E90: Blow dry | F90: Done | G90: =IF(E90="","",MAX(0,IFERROR(INDEX(Services!$C$6:$C$35,MATCH(E90,Services!$B$6:$B$35,0)),0)-N(H90))) | I90: 35 | J90: Card | K90: =IF(OR(B90="",F90<>"Done",J90="Package"),"",IF(N(G90)-N(I90)>0,N(G90)-N(I90),"")) | M90: =IF(OR(B90="",D90="",F90="Cancelled"),"",B90+N(C90)+ROW()/10000000) | N90: =IF(AND(F90="Done",M90<>""),IF(COUNTIFS(Appointments!$D$6:$D$2005,D90,Appointments!$F$6:$F$2005,"Done",Appointments!$M$6:$M$2005,">"&M90)=0,1,0),0) | O90: =IF(AND(F90="Booked",M90<>"",N(B90)>=TODAY()),IF(COUNTIFS(Appointments!$D$6:$D$2005,D90,Appointments!$F$6:$F$2005,"Booked",Appointments!$B$6:$B$2005,">="&TODAY(),Appointments!$M$6:$M$2005,"<"&M90)=0,1,0),0)
B91: 46045 | C91: 0.58680556 | D91: Sara Hughes | E91: Highlights | F91: Done | G91: =IF(E91="","",MAX(0,IFERROR(INDEX(Services!$C$6:$C$35,MATCH(E91,Services!$B$6:$B$35,0)),0)-N(H91))) | I91: 140 | J91: Cash | K91: =IF(OR(B91="",F91<>"Done",J91="Package"),"",IF(N(G91)-N(I91)>0,N(G91)-N(I91),"")) | M91: =IF(OR(B91="",D91="",F91="Cancelled"),"",B91+N(C91)+ROW()/10000000) | N91: =IF(AND(F91="Done",M91<>""),IF(COUNTIFS(Appointments!$D$6:$D$2005,D91,Appointments!$F$6:$F$2005,"Done",Appointments!$M$6:$M$2005,">"&M91)=0,1,0),0) | O91: =IF(AND(F91="Booked",M91<>"",N(B91)>=TODAY()),IF(COUNTIFS(Appointments!$D$6:$D$2005,D91,Appointments!$F$6:$F$2005,"Booked",Appointments!$B$6:$B$2005,">="&TODAY(),Appointments!$M$6:$M$2005,"<"&M91)=0,1,0),0)
B92: 46045 | C92: 0.69791667 | D92: Tina Baker | E92: Colour | F92: Done | G92: =IF(E92="","",MAX(0,IFERROR(INDEX(Services!$C$6:$C$35,MATCH(E92,Services!$B$6:$B$35,0)),0)-N(H92))) | I92: 95 | J92: Card | K92: =IF(OR(B92="",F92<>"Done",J92="Package"),"",IF(N(G92)-N(I92)>0,N(G92)-N(I92),"")) | M92: =IF(OR(B92="",D92="",F92="Cancelled"),"",B92+N(C92)+ROW()/10000000) | N92: =IF(AND(F92="Done",M92<>""),IF(COUNTIFS(Appointments!$D$6:$D$2005,D92,Appointments!$F$6:$F$2005,"Done",Appointments!$M$6:$M$2005,">"&M92)=0,1,0),0) | O92: =IF(AND(F92="Booked",M92<>"",N(B92)>=TODAY()),IF(COUNTIFS(Appointments!$D$6:$D$2005,D92,Appointments!$F$6:$F$2005,"Booked",Appointments!$B$6:$B$2005,">="&TODAY(),Appointments!$M$6:$M$2005,"<"&M92)=0,1,0),0)
B93: 46046 | C93: 0.375 | D93: Gina Reid | E93: Toner | F93: Done | G93: =IF(E93="","",MAX(0,IFERROR(INDEX(Services!$C$6:$C$35,MATCH(E93,Services!$B$6:$B$35,0)),0)-N(H93))) | I93: 40 | J93: Card | K93: =IF(OR(B93="",F93<>"Done",J93="Package"),"",IF(N(G93)-N(I93)>0,N(G93)-N(I93),"")) | M93: =IF(OR(B93="",D93="",F93="Cancelled"),"",B93+N(C93)+ROW()/10000000) | N93: =IF(AND(F93="Done",M93<>""),IF(COUNTIFS(Appointments!$D$6:$D$2005,D93,Appointments!$F$6:$F$2005,"Done",Appointments!$M$6:$M$2005,">"&M93)=0,1,0),0) | O93: =IF(AND(F93="Booked",M93<>"",N(B93)>=TODAY()),IF(COUNTIFS(Appointments!$D$6:$D$2005,D93,Appointments!$F$6:$F$2005,"Booked",Appointments!$B$6:$B$2005,">="&TODAY(),Appointments!$M$6:$M$2005,"<"&M93)=0,1,0),0)
B94: 46046 | C94: 0.40277778 | D94: Harry Hall | E94: Men's haircut | F94: Done | G94: =IF(E94="","",MAX(0,IFERROR(INDEX(Services!$C$6:$C$35,MATCH(E94,Services!$B$6:$B$35,0)),0)-N(H94))) | I94: 30 | J94: Card | K94: =IF(OR(B94="",F94<>"Done",J94="Package"),"",IF(N(G94)-N(I94)>0,N(G94)-N(I94),"")) | M94: =IF(OR(B94="",D94="",F94="Cancelled"),"",B94+N(C94)+ROW()/10000000) | N94: =IF(AND(F94="Done",M94<>""),IF(COUNTIFS(Appointments!$D$6:$D$2005,D94,Appointments!$F$6:$F$2005,"Done",Appointments!$M$6:$M$2005,">"&M94)=0,1,0),0) | O94: =IF(AND(F94="Booked",M94<>"",N(B94)>=TODAY()),IF(COUNTIFS(Appointments!$D$6:$D$2005,D94,Appointments!$F$6:$F$2005,"Booked",Appointments!$B$6:$B$2005,">="&TODAY(),Appointments!$M$6:$M$2005,"<"&M94)=0,1,0),0)
B95: 46046 | C95: 0.43055556 | D95: Katie Moore | E95: Women's haircut | F95: Done | G95: =IF(E95="","",MAX(0,IFERROR(INDEX(Services!$C$6:$C$35,MATCH(E95,Services!$B$6:$B$35,0)),0)-N(H95))) | I95: 55 | J95: Card | K95: =IF(OR(B95="",F95<>"Done",J95="Package"),"",IF(N(G95)-N(I95)>0,N(G95)-N(I95),"")) | M95: =IF(OR(B95="",D95="",F95="Cancelled"),"",B95+N(C95)+ROW()/10000000) | N95: =IF(AND(F95="Done",M95<>""),IF(COUNTIFS(Appointments!$D$6:$D$2005,D95,Appointments!$F$6:$F$2005,"Done",Appointments!$M$6:$M$2005,">"&M95)=0,1,0),0) | O95: =IF(AND(F95="Booked",M95<>"",N(B95)>=TODAY()),IF(COUNTIFS(Appointments!$D$6:$D$2005,D95,Appointments!$F$6:$F$2005,"Booked",Appointments!$B$6:$B$2005,">="&TODAY(),Appointments!$M$6:$M$2005,"<"&M95)=0,1,0),0)
B96: 46046 | C96: 0.47916667 | D96: Kyle Fox | E96: Men's haircut | F96: Done | G96: =IF(E96="","",MAX(0,IFERROR(INDEX(Services!$C$6:$C$35,MATCH(E96,Services!$B$6:$B$35,0)),0)-N(H96))) | I96: 30 | J96: Card | K96: =IF(OR(B96="",F96<>"Done",J96="Package"),"",IF(N(G96)-N(I96)>0,N(G96)-N(I96),"")) | M96: =IF(OR(B96="",D96="",F96="Cancelled"),"",B96+N(C96)+ROW()/10000000) | N96: =IF(AND(F96="Done",M96<>""),IF(COUNTIFS(Appointments!$D$6:$D$2005,D96,Appointments!$F$6:$F$2005,"Done",Appointments!$M$6:$M$2005,">"&M96)=0,1,0),0) | O96: =IF(AND(F96="Booked",M96<>"",N(B96)>=TODAY()),IF(COUNTIFS(Appointments!$D$6:$D$2005,D96,Appointments!$F$6:$F$2005,"Booked",Appointments!$B$6:$B$2005,">="&TODAY(),Appointments!$M$6:$M$2005,"<"&M96)=0,1,0),0)
B97: 46046 | C97: 0.50694444 | D97: Ryan Davies | E97: Men's haircut | F97: Done | G97: =IF(E97="","",MAX(0,IFERROR(INDEX(Services!$C$6:$C$35,MATCH(E97,Services!$B$6:$B$35,0)),0)-N(H97))) | I97: 30 | J97: Cash | K97: =IF(OR(B97="",F97<>"Done",J97="Package"),"",IF(N(G97)-N(I97)>0,N(G97)-N(I97),"")) | M97: =IF(OR(B97="",D97="",F97="Cancelled"),"",B97+N(C97)+ROW()/10000000) | N97: =IF(AND(F97="Done",M97<>""),IF(COUNTIFS(Appointments!$D$6:$D$2005,D97,Appointments!$F$6:$F$2005,"Done",Appointments!$M$6:$M$2005,">"&M97)=0,1,0),0) | O97: =IF(AND(F97="Booked",M97<>"",N(B97)>=TODAY()),IF(COUNTIFS(Appointments!$D$6:$D$2005,D97,Appointments!$F$6:$F$2005,"Booked",Appointments!$B$6:$B$2005,">="&TODAY(),Appointments!$M$6:$M$2005,"<"&M97)=0,1,0),0)
B98: 46046 | C98: 0.53472222 | D98: Sara Reed | E98: Women's haircut | F98: Done | G98: =IF(E98="","",MAX(0,IFERROR(INDEX(Services!$C$6:$C$35,MATCH(E98,Services!$B$6:$B$35,0)),0)-N(H98))) | I98: 55 | J98: App | K98: =IF(OR(B98="",F98<>"Done",J98="Package"),"",IF(N(G98)-N(I98)>0,N(G98)-N(I98),"")) | M98: =IF(OR(B98="",D98="",F98="Cancelled"),"",B98+N(C98)+ROW()/10000000) | N98: =IF(AND(F98="Done",M98<>""),IF(COUNTIFS(Appointments!$D$6:$D$2005,D98,Appointments!$F$6:$F$2005,"Done",Appointments!$M$6:$M$2005,">"&M98)=0,1,0),0) | O98: =IF(AND(F98="Booked",M98<>"",N(B98)>=TODAY()),IF(COUNTIFS(Appointments!$D$6:$D$2005,D98,Appointments!$F$6:$F$2005,"Booked",Appointments!$B$6:$B$2005,">="&TODAY(),Appointments!$M$6:$M$2005,"<"&M98)=0,1,0),0)
B99: 46046 | C99: 0.58333333 | D99: Will Baker | E99: Men's haircut | F99: Done | G99: =IF(E99="","",MAX(0,IFERROR(INDEX(Services!$C$6:$C$35,MATCH(E99,Services!$B$6:$B$35,0)),0)-N(H99))) | H99: 10 | I99: 20 | J99: Transfer | K99: =IF(OR(B99="",F99<>"Done",J99="Package"),"",IF(N(G99)-N(I99)>0,N(G99)-N(I99),"")) | L99: Friends and family | M99: =IF(OR(B99="",D99="",F99="Cancelled"),"",B99+N(C99)+ROW()/10000000) | N99: =IF(AND(F99="Done",M99<>""),IF(COUNTIFS(Appointments!$D$6:$D$2005,D99,Appointments!$F$6:$F$2005,"Done",Appointments!$M$6:$M$2005,">"&M99)=0,1,0),0) | O99: =IF(AND(F99="Booked",M99<>"",N(B99)>=TODAY()),IF(COUNTIFS(Appointments!$D$6:$D$2005,D99,Appointments!$F$6:$F$2005,"Booked",Appointments!$B$6:$B$2005,">="&TODAY(),Appointments!$M$6:$M$2005,"<"&M99)=0,1,0),0)
B100: 46049 | C100: 0.375 | D100: Chris Cook | E100: Men's haircut | F100: Done | G100: =IF(E100="","",MAX(0,IFERROR(INDEX(Services!$C$6:$C$35,MATCH(E100,Services!$B$6:$B$35,0)),0)-N(H100))) | I100: 30 | J100: Cash | K100: =IF(OR(B100="",F100<>"Done",J100="Package"),"",IF(N(G100)-N(I100)>0,N(G100)-N(I100),"")) | M100: =IF(OR(B100="",D100="",F100="Cancelled"),"",B100+N(C100)+ROW()/10000000) | N100: =IF(AND(F100="Done",M100<>""),IF(COUNTIFS(Appointments!$D$6:$D$2005,D100,Appointments!$F$6:$F$2005,"Done",Appointments!$M$6:$M$2005,">"&M100)=0,1,0),0) | O100: =IF(AND(F100="Booked",M100<>"",N(B100)>=TODAY()),IF(COUNTIFS(Appointments!$D$6:$D$2005,D100,Appointments!$F$6:$F$2005,"Booked",Appointments!$B$6:$B$2005,">="&TODAY(),Appointments!$M$6:$M$2005,"<"&M100)=0,1,0),0)
B101: 46049 | C101: 0.40277778 | D101: Eva Brooks | E101: Women's haircut | F101: Done | G101: =IF(E101="","",MAX(0,IFERROR(INDEX(Services!$C$6:$C$35,MATCH(E101,Services!$B$6:$B$35,0)),0)-N(H101))) | I101: 55 | J101: Cash | K101: =IF(OR(B101="",F101<>"Done",J101="Package"),"",IF(N(G101)-N(I101)>0,N(G101)-N(I101),"")) | M101: =IF(OR(B101="",D101="",F101="Cancelled"),"",B101+N(C101)+ROW()/10000000) | N101: =IF(AND(F101="Done",M101<>""),IF(COUNTIFS(Appointments!$D$6:$D$2005,D101,Appointments!$F$6:$F$2005,"Done",Appointments!$M$6:$M$2005,">"&M101)=0,1,0),0) | O101: =IF(AND(F101="Booked",M101<>"",N(B101)>=TODAY()),IF(COUNTIFS(Appointments!$D$6:$D$2005,D101,Appointments!$F$6:$F$2005,"Booked",Appointments!$B$6:$B$2005,">="&TODAY(),Appointments!$M$6:$M$2005,"<"&M101)=0,1,0),0)
B102: 46049 | C102: 0.45138889 | D102: Eva Mills | E102: Women's haircut | F102: Done | G102: =IF(E102="","",MAX(0,IFERROR(INDEX(Services!$C$6:$C$35,MATCH(E102,Services!$B$6:$B$35,0)),0)-N(H102))) | I102: 55 | J102: Cash | K102: =IF(OR(B102="",F102<>"Done",J102="Package"),"",IF(N(G102)-N(I102)>0,N(G102)-N(I102),"")) | M102: =IF(OR(B102="",D102="",F102="Cancelled"),"",B102+N(C102)+ROW()/10000000) | N102: =IF(AND(F102="Done",M102<>""),IF(COUNTIFS(Appointments!$D$6:$D$2005,D102,Appointments!$F$6:$F$2005,"Done",Appointments!$M$6:$M$2005,">"&M102)=0,1,0),0) | O102: =IF(AND(F102="Booked",M102<>"",N(B102)>=TODAY()),IF(COUNTIFS(Appointments!$D$6:$D$2005,D102,Appointments!$F$6:$F$2005,"Booked",Appointments!$B$6:$B$2005,">="&TODAY(),Appointments!$M$6:$M$2005,"<"&M102)=0,1,0),0)
...

Sheet Clients
B2: Clients
B3: One line per client. Visits, payments and package sessions come from the other tabs.
B5: Client | C5: Phone | D5: Email | E5: Birthday | F5: Client since | G5: Notes | H5: Visits | I5: Last visit | J5: Next booking | K5: Paid in total | L5: Owes | M5: Sessions left | N5: Follow up
B6: Anna Rossi | C6: 555 0101 | D6: anna.r@example.com | E6: 32400 | F6: 45353 | G6: Likes it shorter at the back | H6: =IF(B6="","",COUNTIFS(Appointments!$D$6:$D$2005,B6,Appointments!$F$6:$F$2005,"Done")) | I6: =IF(OR(B6="",N(H6)=0),"",INT(SUMIFS(Appointments!$M$6:$M$2005,Appointments!$D$6:$D$2005,B6,Appointments!$N$6:$N$2005,1))) | J6: =IF(B6="","",IF(SUMIFS(Appointments!$M$6:$M$2005,Appointments!$D$6:$D$2005,B6,Appointments!$O$6:$O$2005,1)=0,"",INT(SUMIFS(Appointments!$M$6:$M$2005,Appointments!$D$6:$D$2005,B6,Appointments!$O$6:$O$2005,1)))) | K6: =IF(B6="","",SUMIFS(Appointments!$I$6:$I$2005,Appointments!$D$6:$D$2005,B6)+SUMIFS(Packages!$F$6:$F$305,Packages!$C$6:$C$305,B6)) | L6: =IF(B6="","",IF(SUMIFS(Appointments!$K$6:$K$2005,Appointments!$D$6:$D$2005,B6)=0,"",SUMIFS(Appointments!$K$6:$K$2005,Appointments!$D$6:$D$2005,B6))) | M6: =IF(OR(B6="",SUMIFS(Packages!$E$6:$E$305,Packages!$C$6:$C$305,B6)=0),"",SUMIFS(Packages!$E$6:$E$305,Packages!$C$6:$C$305,B6)-COUNTIFS(Appointments!$D$6:$D$2005,B6,Appointments!$J$6:$J$2005,"Package",Appointments!$F$6:$F$2005,"Done")+IF(Services!$I$6="Yes",COUNTIFS(Appointments!$D$6:$D$2005,B6,Appointments!$J$6:$J$2005,"Package",Appointments!$F$6:$F$2005,"No-show"),0)) | N6: =IF(OR(B6="",I6=""),"",IF(AND(J6="",TODAY()-I6>=N(Services!$I$7)),"Not seen for "&(TODAY()-I6)&" days","")) | O6: =IF(N(E6)=0,"",MONTH(E6))
B7: Ben Carter | C7: 555 0102 | F7: 45250 | H7: =IF(B7="","",COUNTIFS(Appointments!$D$6:$D$2005,B7,Appointments!$F$6:$F$2005,"Done")) | I7: =IF(OR(B7="",N(H7)=0),"",INT(SUMIFS(Appointments!$M$6:$M$2005,Appointments!$D$6:$D$2005,B7,Appointments!$N$6:$N$2005,1))) | J7: =IF(B7="","",IF(SUMIFS(Appointments!$M$6:$M$2005,Appointments!$D$6:$D$2005,B7,Appointments!$O$6:$O$2005,1)=0,"",INT(SUMIFS(Appointments!$M$6:$M$2005,Appointments!$D$6:$D$2005,B7,Appointments!$O$6:$O$2005,1)))) | K7: =IF(B7="","",SUMIFS(Appointments!$I$6:$I$2005,Appointments!$D$6:$D$2005,B7)+SUMIFS(Packages!$F$6:$F$305,Packages!$C$6:$C$305,B7)) | L7: =IF(B7="","",IF(SUMIFS(Appointments!$K$6:$K$2005,Appointments!$D$6:$D$2005,B7)=0,"",SUMIFS(Appointments!$K$6:$K$2005,Appointments!$D$6:$D$2005,B7))) | M7: =IF(OR(B7="",SUMIFS(Packages!$E$6:$E$305,Packages!$C$6:$C$305,B7)=0),"",SUMIFS(Packages!$E$6:$E$305,Packages!$C$6:$C$305,B7)-COUNTIFS(Appointments!$D$6:$D$2005,B7,Appointments!$J$6:$J$2005,"Package",Appointments!$F$6:$F$2005,"Done")+IF(Services!$I$6="Yes",COUNTIFS(Appointments!$D$6:$D$2005,B7,Appointments!$J$6:$J$2005,"Package",Appointments!$F$6:$F$2005,"No-show"),0)) | N7: =IF(OR(B7="",I7=""),"",IF(AND(J7="",TODAY()-I7>=N(Services!$I$7)),"Not seen for "&(TODAY()-I7)&" days","")) | O7: =IF(N(E7)=0,"",MONTH(E7))
B8: Chloe Martin | C8: 555 0103 | D8: chloe.m@example.com | E8: 33637 | F8: 44723 | G8: Blow dry card since September | H8: =IF(B8="","",COUNTIFS(Appointments!$D$6:$D$2005,B8,Appointments!$F$6:$F$2005,"Done")) | I8: =IF(OR(B8="",N(H8)=0),"",INT(SUMIFS(Appointments!$M$6:$M$2005,Appointments!$D$6:$D$2005,B8,Appointments!$N$6:$N$2005,1))) | J8: =IF(B8="","",IF(SUMIFS(Appointments!$M$6:$M$2005,Appointments!$D$6:$D$2005,B8,Appointments!$O$6:$O$2005,1)=0,"",INT(SUMIFS(Appointments!$M$6:$M$2005,Appointments!$D$6:$D$2005,B8,Appointments!$O$6:$O$2005,1)))) | K8: =IF(B8="","",SUMIFS(Appointments!$I$6:$I$2005,Appointments!$D$6:$D$2005,B8)+SUMIFS(Packages!$F$6:$F$305,Packages!$C$6:$C$305,B8)) | L8: =IF(B8="","",IF(SUMIFS(Appointments!$K$6:$K$2005,Appointments!$D$6:$D$2005,B8)=0,"",SUMIFS(Appointments!$K$6:$K$2005,Appointments!$D$6:$D$2005,B8))) | M8: =IF(OR(B8="",SUMIFS(Packages!$E$6:$E$305,Packages!$C$6:$C$305,B8)=0),"",SUMIFS(Packages!$E$6:$E$305,Packages!$C$6:$C$305,B8)-COUNTIFS(Appointments!$D$6:$D$2005,B8,Appointments!$J$6:$J$2005,"Package",Appointments!$F$6:$F$2005,"Done")+IF(Services!$I$6="Yes",COUNTIFS(Appointments!$D$6:$D$2005,B8,Appointments!$J$6:$J$2005,"Package",Appointments!$F$6:$F$2005,"No-show"),0)) | N8: =IF(OR(B8="",I8=""),"",IF(AND(J8="",TODAY()-I8>=N(Services!$I$7)),"Not seen for "&(TODAY()-I8)&" days","")) | O8: =IF(N(E8)=0,"",MONTH(E8))
B9: Daniel Kim | C9: 555 0104 | E9: 33208 | F9: 45306 | H9: =IF(B9="","",COUNTIFS(Appointments!$D$6:$D$2005,B9,Appointments!$F$6:$F$2005,"Done")) | I9: =IF(OR(B9="",N(H9)=0),"",INT(SUMIFS(Appointments!$M$6:$M$2005,Appointments!$D$6:$D$2005,B9,Appointments!$N$6:$N$2005,1))) | J9: =IF(B9="","",IF(SUMIFS(Appointments!$M$6:$M$2005,Appointments!$D$6:$D$2005,B9,Appointments!$O$6:$O$2005,1)=0,"",INT(SUMIFS(Appointments!$M$6:$M$2005,Appointments!$D$6:$D$2005,B9,Appointments!$O$6:$O$2005,1)))) | K9: =IF(B9="","",SUMIFS(Appointments!$I$6:$I$2005,Appointments!$D$6:$D$2005,B9)+SUMIFS(Packages!$F$6:$F$305,Packages!$C$6:$C$305,B9)) | L9: =IF(B9="","",IF(SUMIFS(Appointments!$K$6:$K$2005,Appointments!$D$6:$D$2005,B9)=0,"",SUMIFS(Appointments!$K$6:$K$2005,Appointments!$D$6:$D$2005,B9))) | M9: =IF(OR(B9="",SUMIFS(Packages!$E$6:$E$305,Packages!$C$6:$C$305,B9)=0),"",SUMIFS(Packages!$E$6:$E$305,Packages!$C$6:$C$305,B9)-COUNTIFS(Appointments!$D$6:$D$2005,B9,Appointments!$J$6:$J$2005,"Package",Appointments!$F$6:$F$2005,"Done")+IF(Services!$I$6="Yes",COUNTIFS(Appointments!$D$6:$D$2005,B9,Appointments!$J$6:$J$2005,"Package",Appointments!$F$6:$F$2005,"No-show"),0)) | N9: =IF(OR(B9="",I9=""),"",IF(AND(J9="",TODAY()-I9>=N(Services!$I$7)),"Not seen for "&(TODAY()-I9)&" days","")) | O9: =IF(N(E9)=0,"",MONTH(E9))
B10: Emma Johnson | C10: 555 0105 | D10: emma.j@example.com | E10: 34811 | F10: 45051 | G10: Blow dry card | H10: =IF(B10="","",COUNTIFS(Appointments!$D$6:$D$2005,B10,Appointments!$F$6:$F$2005,"Done")) | I10: =IF(OR(B10="",N(H10)=0),"",INT(SUMIFS(Appointments!$M$6:$M$2005,Appointments!$D$6:$D$2005,B10,Appointments!$N$6:$N$2005,1))) | J10: =IF(B10="","",IF(SUMIFS(Appointments!$M$6:$M$2005,Appointments!$D$6:$D$2005,B10,Appointments!$O$6:$O$2005,1)=0,"",INT(SUMIFS(Appointments!$M$6:$M$2005,Appointments!$D$6:$D$2005,B10,Appointments!$O$6:$O$2005,1)))) | K10: =IF(B10="","",SUMIFS(Appointments!$I$6:$I$2005,Appointments!$D$6:$D$2005,B10)+SUMIFS(Packages!$F$6:$F$305,Packages!$C$6:$C$305,B10)) | L10: =IF(B10="","",IF(SUMIFS(Appointments!$K$6:$K$2005,Appointments!$D$6:$D$2005,B10)=0,"",SUMIFS(Appointments!$K$6:$K$2005,Appointments!$D$6:$D$2005,B10))) | M10: =IF(OR(B10="",SUMIFS(Packages!$E$6:$E$305,Packages!$C$6:$C$305,B10)=0),"",SUMIFS(Packages!$E$6:$E$305,Packages!$C$6:$C$305,B10)-COUNTIFS(Appointments!$D$6:$D$2005,B10,Appointments!$J$6:$J$2005,"Package",Appointments!$F$6:$F$2005,"Done")+IF(Services!$I$6="Yes",COUNTIFS(Appointments!$D$6:$D$2005,B10,Appointments!$J$6:$J$2005,"Package",Appointments!$F$6:$F$2005,"No-show"),0)) | N10: =IF(OR(B10="",I10=""),"",IF(AND(J10="",TODAY()-I10>=N(Services!$I$7)),"Not seen for "&(TODAY()-I10)&" days","")) | O10: =IF(N(E10)=0,"",MONTH(E10))
B11: Farah Ali | C11: 555 0106 | E11: 31237 | F11: 44469 | G11: Patch test before colour | H11: =IF(B11="","",COUNTIFS(Appointments!$D$6:$D$2005,B11,Appointments!$F$6:$F$2005,"Done")) | I11: =IF(OR(B11="",N(H11)=0),"",INT(SUMIFS(Appointments!$M$6:$M$2005,Appointments!$D$6:$D$2005,B11,Appointments!$N$6:$N$2005,1))) | J11: =IF(B11="","",IF(SUMIFS(Appointments!$M$6:$M$2005,Appointments!$D$6:$D$2005,B11,Appointments!$O$6:$O$2005,1)=0,"",INT(SUMIFS(Appointments!$M$6:$M$2005,Appointments!$D$6:$D$2005,B11,Appointments!$O$6:$O$2005,1)))) | K11: =IF(B11="","",SUMIFS(Appointments!$I$6:$I$2005,Appointments!$D$6:$D$2005,B11)+SUMIFS(Packages!$F$6:$F$305,Packages!$C$6:$C$305,B11)) | L11: =IF(B11="","",IF(SUMIFS(Appointments!$K$6:$K$2005,Appointments!$D$6:$D$2005,B11)=0,"",SUMIFS(Appointments!$K$6:$K$2005,Appointments!$D$6:$D$2005,B11))) | M11: =IF(OR(B11="",SUMIFS(Packages!$E$6:$E$305,Packages!$C$6:$C$305,B11)=0),"",SUMIFS(Packages!$E$6:$E$305,Packages!$C$6:$C$305,B11)-COUNTIFS(Appointments!$D$6:$D$2005,B11,Appointments!$J$6:$J$2005,"Package",Appointments!$F$6:$F$2005,"Done")+IF(Services!$I$6="Yes",COUNTIFS(Appointments!$D$6:$D$2005,B11,Appointments!$J$6:$J$2005,"Package",Appointments!$F$6:$F$2005,"No-show"),0)) | N11: =IF(OR(B11="",I11=""),"",IF(AND(J11="",TODAY()-I11>=N(Services!$I$7)),"Not seen for "&(TODAY()-I11)&" days","")) | O11: =IF(N(E11)=0,"",MONTH(E11))
B12: Grace Lee | C12: 555 0107 | D12: grace.l@example.com | F12: 45512 | H12: =IF(B12="","",COUNTIFS(Appointments!$D$6:$D$2005,B12,Appointments!$F$6:$F$2005,"Done")) | I12: =IF(OR(B12="",N(H12)=0),"",INT(SUMIFS(Appointments!$M$6:$M$2005,Appointments!$D$6:$D$2005,B12,Appointments!$N$6:$N$2005,1))) | J12: =IF(B12="","",IF(SUMIFS(Appointments!$M$6:$M$2005,Appointments!$D$6:$D$2005,B12,Appointments!$O$6:$O$2005,1)=0,"",INT(SUMIFS(Appointments!$M$6:$M$2005,Appointments!$D$6:$D$2005,B12,Appointments!$O$6:$O$2005,1)))) | K12: =IF(B12="","",SUMIFS(Appointments!$I$6:$I$2005,Appointments!$D$6:$D$2005,B12)+SUMIFS(Packages!$F$6:$F$305,Packages!$C$6:$C$305,B12)) | L12: =IF(B12="","",IF(SUMIFS(Appointments!$K$6:$K$2005,Appointments!$D$6:$D$2005,B12)=0,"",SUMIFS(Appointments!$K$6:$K$2005,Appointments!$D$6:$D$2005,B12))) | M12: =IF(OR(B12="",SUMIFS(Packages!$E$6:$E$305,Packages!$C$6:$C$305,B12)=0),"",SUMIFS(Packages!$E$6:$E$305,Packages!$C$6:$C$305,B12)-COUNTIFS(Appointments!$D$6:$D$2005,B12,Appointments!$J$6:$J$2005,"Package",Appointments!$F$6:$F$2005,"Done")+IF(Services!$I$6="Yes",COUNTIFS(Appointments!$D$6:$D$2005,B12,Appointments!$J$6:$J$2005,"Package",Appointments!$F$6:$F$2005,"No-show"),0)) | N12: =IF(OR(B12="",I12=""),"",IF(AND(J12="",TODAY()-I12>=N(Services!$I$7)),"Not seen for "&(TODAY()-I12)&" days","")) | O12: =IF(N(E12)=0,"",MONTH(E12))
B13: Hugo Silva | C13: 555 0108 | E13: 31853 | F13: 44958 | H13: =IF(B13="","",COUNTIFS(Appointments!$D$6:$D$2005,B13,Appointments!$F$6:$F$2005,"Done")) | I13: =IF(OR(B13="",N(H13)=0),"",INT(SUMIFS(Appointments!$M$6:$M$2005,Appointments!$D$6:$D$2005,B13,Appointments!$N$6:$N$2005,1))) | J13: =IF(B13="","",IF(SUMIFS(Appointments!$M$6:$M$2005,Appointments!$D$6:$D$2005,B13,Appointments!$O$6:$O$2005,1)=0,"",INT(SUMIFS(Appointments!$M$6:$M$2005,Appointments!$D$6:$D$2005,B13,Appointments!$O$6:$O$2005,1)))) | K13: =IF(B13="","",SUMIFS(Appointments!$I$6:$I$2005,Appointments!$D$6:$D$2005,B13)+SUMIFS(Packages!$F$6:$F$305,Packages!$C$6:$C$305,B13)) | L13: =IF(B13="","",IF(SUMIFS(Appointments!$K$6:$K$2005,Appointments!$D$6:$D$2005,B13)=0,"",SUMIFS(Appointments!$K$6:$K$2005,Appointments!$D$6:$D$2005,B13))) | M13: =IF(OR(B13="",SUMIFS(Packages!$E$6:$E$305,Packages!$C$6:$C$305,B13)=0),"",SUMIFS(Packages!$E$6:$E$305,Packages!$C$6:$C$305,B13)-COUNTIFS(Appointments!$D$6:$D$2005,B13,Appointments!$J$6:$J$2005,"Package",Appointments!$F$6:$F$2005,"Done")+IF(Services!$I$6="Yes",COUNTIFS(Appointments!$D$6:$D$2005,B13,Appointments!$J$6:$J$2005,"Package",Appointments!$F$6:$F$2005,"No-show"),0)) | N13: =IF(OR(B13="",I13=""),"",IF(AND(J13="",TODAY()-I13>=N(Services!$I$7)),"Not seen for "&(TODAY()-I13)&" days","")) | O13: =IF(N(E13)=0,"",MONTH(E13))
B14: Isla Brown | C14: 555 0109 | F14: 44838 | G14: Sensitive scalp | H14: =IF(B14="","",COUNTIFS(Appointments!$D$6:$D$2005,B14,Appointments!$F$6:$F$2005,"Done")) | I14: =IF(OR(B14="",N(H14)=0),"",INT(SUMIFS(Appointments!$M$6:$M$2005,Appointments!$D$6:$D$2005,B14,Appointments!$N$6:$N$2005,1))) | J14: =IF(B14="","",IF(SUMIFS(Appointments!$M$6:$M$2005,Appointments!$D$6:$D$2005,B14,Appointments!$O$6:$O$2005,1)=0,"",INT(SUMIFS(Appointments!$M$6:$M$2005,Appointments!$D$6:$D$2005,B14,Appointments!$O$6:$O$2005,1)))) | K14: =IF(B14="","",SUMIFS(Appointments!$I$6:$I$2005,Appointments!$D$6:$D$2005,B14)+SUMIFS(Packages!$F$6:$F$305,Packages!$C$6:$C$305,B14)) | L14: =IF(B14="","",IF(SUMIFS(Appointments!$K$6:$K$2005,Appointments!$D$6:$D$2005,B14)=0,"",SUMIFS(Appointments!$K$6:$K$2005,Appointments!$D$6:$D$2005,B14))) | M14: =IF(OR(B14="",SUMIFS(Packages!$E$6:$E$305,Packages!$C$6:$C$305,B14)=0),"",SUMIFS(Packages!$E$6:$E$305,Packages!$C$6:$C$305,B14)-COUNTIFS(Appointments!$D$6:$D$2005,B14,Appointments!$J$6:$J$2005,"Package",Appointments!$F$6:$F$2005,"Done")+IF(Services!$I$6="Yes",COUNTIFS(Appointments!$D$6:$D$2005,B14,Appointments!$J$6:$J$2005,"Package",Appointments!$F$6:$F$2005,"No-show"),0)) | N14: =IF(OR(B14="",I14=""),"",IF(AND(J14="",TODAY()-I14>=N(Services!$I$7)),"Not seen for "&(TODAY()-I14)&" days","")) | O14: =IF(N(E14)=0,"",MONTH(E14))
B15: Jack Wilson | C15: 555 0110 | F15: 45433 | H15: =IF(B15="","",COUNTIFS(Appointments!$D$6:$D$2005,B15,Appointments!$F$6:$F$2005,"Done")) | I15: =IF(OR(B15="",N(H15)=0),"",INT(SUMIFS(Appointments!$M$6:$M$2005,Appointments!$D$6:$D$2005,B15,Appointments!$N$6:$N$2005,1))) | J15: =IF(B15="","",IF(SUMIFS(Appointments!$M$6:$M$2005,Appointments!$D$6:$D$2005,B15,Appointments!$O$6:$O$2005,1)=0,"",INT(SUMIFS(Appointments!$M$6:$M$2005,Appointments!$D$6:$D$2005,B15,Appointments!$O$6:$O$2005,1)))) | K15: =IF(B15="","",SUMIFS(Appointments!$I$6:$I$2005,Appointments!$D$6:$D$2005,B15)+SUMIFS(Packages!$F$6:$F$305,Packages!$C$6:$C$305,B15)) | L15: =IF(B15="","",IF(SUMIFS(Appointments!$K$6:$K$2005,Appointments!$D$6:$D$2005,B15)=0,"",SUMIFS(Appointments!$K$6:$K$2005,Appointments!$D$6:$D$2005,B15))) | M15: =IF(OR(B15="",SUMIFS(Packages!$E$6:$E$305,Packages!$C$6:$C$305,B15)=0),"",SUMIFS(Packages!$E$6:$E$305,Packages!$C$6:$C$305,B15)-COUNTIFS(Appointments!$D$6:$D$2005,B15,Appointments!$J$6:$J$2005,"Package",Appointments!$F$6:$F$2005,"Done")+IF(Services!$I$6="Yes",COUNTIFS(Appointments!$D$6:$D$2005,B15,Appointments!$J$6:$J$2005,"Package",Appointments!$F$6:$F$2005,"No-show"),0)) | N15: =IF(OR(B15="",I15=""),"",IF(AND(J15="",TODAY()-I15>=N(Services!$I$7)),"Not seen for "&(TODAY()-I15)&" days","")) | O15: =IF(N(E15)=0,"",MONTH(E15))
B16: Katie Moore | C16: 555 0111 | D16: katie.m@example.com | E16: 34281 | F16: 45114 | H16: =IF(B16="","",COUNTIFS(Appointments!$D$6:$D$2005,B16,Appointments!$F$6:$F$2005,"Done")) | I16: =IF(OR(B16="",N(H16)=0),"",INT(SUMIFS(Appointments!$M$6:$M$2005,Appointments!$D$6:$D$2005,B16,Appointments!$N$6:$N$2005,1))) | J16: =IF(B16="","",IF(SUMIFS(Appointments!$M$6:$M$2005,Appointments!$D$6:$D$2005,B16,Appointments!$O$6:$O$2005,1)=0,"",INT(SUMIFS(Appointments!$M$6:$M$2005,Appointments!$D$6:$D$2005,B16,Appointments!$O$6:$O$2005,1)))) | K16: =IF(B16="","",SUMIFS(Appointments!$I$6:$I$2005,Appointments!$D$6:$D$2005,B16)+SUMIFS(Packages!$F$6:$F$305,Packages!$C$6:$C$305,B16)) | L16: =IF(B16="","",IF(SUMIFS(Appointments!$K$6:$K$2005,Appointments!$D$6:$D$2005,B16)=0,"",SUMIFS(Appointments!$K$6:$K$2005,Appointments!$D$6:$D$2005,B16))) | M16: =IF(OR(B16="",SUMIFS(Packages!$E$6:$E$305,Packages!$C$6:$C$305,B16)=0),"",SUMIFS(Packages!$E$6:$E$305,Packages!$C$6:$C$305,B16)-COUNTIFS(Appointments!$D$6:$D$2005,B16,Appointments!$J$6:$J$2005,"Package",Appointments!$F$6:$F$2005,"Done")+IF(Services!$I$6="Yes",COUNTIFS(Appointments!$D$6:$D$2005,B16,Appointments!$J$6:$J$2005,"Package",Appointments!$F$6:$F$2005,"No-show"),0)) | N16: =IF(OR(B16="",I16=""),"",IF(AND(J16="",TODAY()-I16>=N(Services!$I$7)),"Not seen for "&(TODAY()-I16)&" days","")) | O16: =IF(N(E16)=0,"",MONTH(E16))
B17: Liam Evans | C17: 555 0112 | F17: 45667 | H17: =IF(B17="","",COUNTIFS(Appointments!$D$6:$D$2005,B17,Appointments!$F$6:$F$2005,"Done")) | I17: =IF(OR(B17="",N(H17)=0),"",INT(SUMIFS(Appointments!$M$6:$M$2005,Appointments!$D$6:$D$2005,B17,Appointments!$N$6:$N$2005,1))) | J17: =IF(B17="","",IF(SUMIFS(Appointments!$M$6:$M$2005,Appointments!$D$6:$D$2005,B17,Appointments!$O$6:$O$2005,1)=0,"",INT(SUMIFS(Appointments!$M$6:$M$2005,Appointments!$D$6:$D$2005,B17,Appointments!$O$6:$O$2005,1)))) | K17: =IF(B17="","",SUMIFS(Appointments!$I$6:$I$2005,Appointments!$D$6:$D$2005,B17)+SUMIFS(Packages!$F$6:$F$305,Packages!$C$6:$C$305,B17)) | L17: =IF(B17="","",IF(SUMIFS(Appointments!$K$6:$K$2005,Appointments!$D$6:$D$2005,B17)=0,"",SUMIFS(Appointments!$K$6:$K$2005,Appointments!$D$6:$D$2005,B17))) | M17: =IF(OR(B17="",SUMIFS(Packages!$E$6:$E$305,Packages!$C$6:$C$305,B17)=0),"",SUMIFS(Packages!$E$6:$E$305,Packages!$C$6:$C$305,B17)-COUNTIFS(Appointments!$D$6:$D$2005,B17,Appointments!$J$6:$J$2005,"Package",Appointments!$F$6:$F$2005,"Done")+IF(Services!$I$6="Yes",COUNTIFS(Appointments!$D$6:$D$2005,B17,Appointments!$J$6:$J$2005,"Package",Appointments!$F$6:$F$2005,"No-show"),0)) | N17: =IF(OR(B17="",I17=""),"",IF(AND(J17="",TODAY()-I17>=N(Services!$I$7)),"Not seen for "&(TODAY()-I17)&" days","")) | O17: =IF(N(E17)=0,"",MONTH(E17))
B18: Maya Patel | C18: 555 0113 | D18: maya.p@example.com | E18: 33414 | F18: 45336 | G18: Treatment card | H18: =IF(B18="","",COUNTIFS(Appointments!$D$6:$D$2005,B18,Appointments!$F$6:$F$2005,"Done")) | I18: =IF(OR(B18="",N(H18)=0),"",INT(SUMIFS(Appointments!$M$6:$M$2005,Appointments!$D$6:$D$2005,B18,Appointments!$N$6:$N$2005,1))) | J18: =IF(B18="","",IF(SUMIFS(Appointments!$M$6:$M$2005,Appointments!$D$6:$D$2005,B18,Appointments!$O$6:$O$2005,1)=0,"",INT(SUMIFS(Appointments!$M$6:$M$2005,Appointments!$D$6:$D$2005,B18,Appointments!$O$6:$O$2005,1)))) | K18: =IF(B18="","",SUMIFS(Appointments!$I$6:$I$2005,Appointments!$D$6:$D$2005,B18)+SUMIFS(Packages!$F$6:$F$305,Packages!$C$6:$C$305,B18)) | L18: =IF(B18="","",IF(SUMIFS(Appointments!$K$6:$K$2005,Appointments!$D$6:$D$2005,B18)=0,"",SUMIFS(Appointments!$K$6:$K$2005,Appointments!$D$6:$D$2005,B18))) | M18: =IF(OR(B18="",SUMIFS(Packages!$E$6:$E$305,Packages!$C$6:$C$305,B18)=0),"",SUMIFS(Packages!$E$6:$E$305,Packages!$C$6:$C$305,B18)-COUNTIFS(Appointments!$D$6:$D$2005,B18,Appointments!$J$6:$J$2005,"Package",Appointments!$F$6:$F$2005,"Done")+IF(Services!$I$6="Yes",COUNTIFS(Appointments!$D$6:$D$2005,B18,Appointments!$J$6:$J$2005,"Package",Appointments!$F$6:$F$2005,"No-show"),0)) | N18: =IF(OR(B18="",I18=""),"",IF(AND(J18="",TODAY()-I18>=N(Services!$I$7)),"Not seen for "&(TODAY()-I18)&" days","")) | O18: =IF(N(E18)=0,"",MONTH(E18))
B19: Noah Taylor | C19: 555 0114 | F19: 45538 | G19: Brings his son Leo | H19: =IF(B19="","",COUNTIFS(Appointments!$D$6:$D$2005,B19,Appointments!$F$6:$F$2005,"Done")) | I19: =IF(OR(B19="",N(H19)=0),"",INT(SUMIFS(Appointments!$M$6:$M$2005,Appointments!$D$6:$D$2005,B19,Appointments!$N$6:$N$2005,1))) | J19: =IF(B19="","",IF(SUMIFS(Appointments!$M$6:$M$2005,Appointments!$D$6:$D$2005,B19,Appointments!$O$6:$O$2005,1)=0,"",INT(SUMIFS(Appointments!$M$6:$M$2005,Appointments!$D$6:$D$2005,B19,Appointments!$O$6:$O$2005,1)))) | K19: =IF(B19="","",SUMIFS(Appointments!$I$6:$I$2005,Appointments!$D$6:$D$2005,B19)+SUMIFS(Packages!$F$6:$F$305,Packages!$C$6:$C$305,B19)) | L19: =IF(B19="","",IF(SUMIFS(Appointments!$K$6:$K$2005,Appointments!$D$6:$D$2005,B19)=0,"",SUMIFS(Appointments!$K$6:$K$2005,Appointments!$D$6:$D$2005,B19))) | M19: =IF(OR(B19="",SUMIFS(Packages!$E$6:$E$305,Packages!$C$6:$C$305,B19)=0),"",SUMIFS(Packages!$E$6:$E$305,Packages!$C$6:$C$305,B19)-COUNTIFS(Appointments!$D$6:$D$2005,B19,Appointments!$J$6:$J$2005,"Package",Appointments!$F$6:$F$2005,"Done")+IF(Services!$I$6="Yes",COUNTIFS(Appointments!$D$6:$D$2005,B19,Appointments!$J$6:$J$2005,"Package",Appointments!$F$6:$F$2005,"No-show"),0)) | N19: =IF(OR(B19="",I19=""),"",IF(AND(J19="",TODAY()-I19>=N(Services!$I$7)),"Not seen for "&(TODAY()-I19)&" days","")) | O19: =IF(N(E19)=0,"",MONTH(E19))
B20: Olivia Green | C20: 555 0115 | D20: olivia.g@example.com | E20: 32781 | F20: 44632 | H20: =IF(B20="","",COUNTIFS(Appointments!$D$6:$D$2005,B20,Appointments!$F$6:$F$2005,"Done")) | I20: =IF(OR(B20="",N(H20)=0),"",INT(SUMIFS(Appointments!$M$6:$M$2005,Appointments!$D$6:$D$2005,B20,Appointments!$N$6:$N$2005,1))) | J20: =IF(B20="","",IF(SUMIFS(Appointments!$M$6:$M$2005,Appointments!$D$6:$D$2005,B20,Appointments!$O$6:$O$2005,1)=0,"",INT(SUMIFS(Appointments!$M$6:$M$2005,Appointments!$D$6:$D$2005,B20,Appointments!$O$6:$O$2005,1)))) | K20: =IF(B20="","",SUMIFS(Appointments!$I$6:$I$2005,Appointments!$D$6:$D$2005,B20)+SUMIFS(Packages!$F$6:$F$305,Packages!$C$6:$C$305,B20)) | L20: =IF(B20="","",IF(SUMIFS(Appointments!$K$6:$K$2005,Appointments!$D$6:$D$2005,B20)=0,"",SUMIFS(Appointments!$K$6:$K$2005,Appointments!$D$6:$D$2005,B20))) | M20: =IF(OR(B20="",SUMIFS(Packages!$E$6:$E$305,Packages!$C$6:$C$305,B20)=0),"",SUMIFS(Packages!$E$6:$E$305,Packages!$C$6:$C$305,B20)-COUNTIFS(Appointments!$D$6:$D$2005,B20,Appointments!$J$6:$J$2005,"Package",Appointments!$F$6:$F$2005,"Done")+IF(Services!$I$6="Yes",COUNTIFS(Appointments!$D$6:$D$2005,B20,Appointments!$J$6:$J$2005,"Package",Appointments!$F$6:$F$2005,"No-show"),0)) | N20: =IF(OR(B20="",I20=""),"",IF(AND(J20="",TODAY()-I20>=N(Services!$I$7)),"Not seen for "&(TODAY()-I20)&" days","")) | O20: =IF(N(E20)=0,"",MONTH(E20))
B21: Paul Wright | C21: 555 0116 | F21: 45034 | H21: =IF(B21="","",COUNTIFS(Appointments!$D$6:$D$2005,B21,Appointments!$F$6:$F$2005,"Done")) | I21: =IF(OR(B21="",N(H21)=0),"",INT(SUMIFS(Appointments!$M$6:$M$2005,Appointments!$D$6:$D$2005,B21,Appointments!$N$6:$N$2005,1))) | J21: =IF(B21="","",IF(SUMIFS(Appointments!$M$6:$M$2005,Appointments!$D$6:$D$2005,B21,Appointments!$O$6:$O$2005,1)=0,"",INT(SUMIFS(Appointments!$M$6:$M$2005,Appointments!$D$6:$D$2005,B21,Appointments!$O$6:$O$2005,1)))) | K21: =IF(B21="","",SUMIFS(Appointments!$I$6:$I$2005,Appointments!$D$6:$D$2005,B21)+SUMIFS(Packages!$F$6:$F$305,Packages!$C$6:$C$305,B21)) | L21: =IF(B21="","",IF(SUMIFS(Appointments!$K$6:$K$2005,Appointments!$D$6:$D$2005,B21)=0,"",SUMIFS(Appointments!$K$6:$K$2005,Appointments!$D$6:$D$2005,B21))) | M21: =IF(OR(B21="",SUMIFS(Packages!$E$6:$E$305,Packages!$C$6:$C$305,B21)=0),"",SUMIFS(Packages!$E$6:$E$305,Packages!$C$6:$C$305,B21)-COUNTIFS(Appointments!$D$6:$D$2005,B21,Appointments!$J$6:$J$2005,"Package",Appointments!$F$6:$F$2005,"Done")+IF(Services!$I$6="Yes",COUNTIFS(Appointments!$D$6:$D$2005,B21,Appointments!$J$6:$J$2005,"Package",Appointments!$F$6:$F$2005,"No-show"),0)) | N21: =IF(OR(B21="",I21=""),"",IF(AND(J21="",TODAY()-I21>=N(Services!$I$7)),"Not seen for "&(TODAY()-I21)&" days","")) | O21: =IF(N(E21)=0,"",MONTH(E21))
B22: Quinn Harris | C22: 555 0117 | F22: 45719 | H22: =IF(B22="","",COUNTIFS(Appointments!$D$6:$D$2005,B22,Appointments!$F$6:$F$2005,"Done")) | I22: =IF(OR(B22="",N(H22)=0),"",INT(SUMIFS(Appointments!$M$6:$M$2005,Appointments!$D$6:$D$2005,B22,Appointments!$N$6:$N$2005,1))) | J22: =IF(B22="","",IF(SUMIFS(Appointments!$M$6:$M$2005,Appointments!$D$6:$D$2005,B22,Appointments!$O$6:$O$2005,1)=0,"",INT(SUMIFS(Appointments!$M$6:$M$2005,Appointments!$D$6:$D$2005,B22,Appointments!$O$6:$O$2005,1)))) | K22: =IF(B22="","",SUMIFS(Appointments!$I$6:$I$2005,Appointments!$D$6:$D$2005,B22)+SUMIFS(Packages!$F$6:$F$305,Packages!$C$6:$C$305,B22)) | L22: =IF(B22="","",IF(SUMIFS(Appointments!$K$6:$K$2005,Appointments!$D$6:$D$2005,B22)=0,"",SUMIFS(Appointments!$K$6:$K$2005,Appointments!$D$6:$D$2005,B22))) | M22: =IF(OR(B22="",SUMIFS(Packages!$E$6:$E$305,Packages!$C$6:$C$305,B22)=0),"",SUMIFS(Packages!$E$6:$E$305,Packages!$C$6:$C$305,B22)-COUNTIFS(Appointments!$D$6:$D$2005,B22,Appointments!$J$6:$J$2005,"Package",Appointments!$F$6:$F$2005,"Done")+IF(Services!$I$6="Yes",COUNTIFS(Appointments!$D$6:$D$2005,B22,Appointments!$J$6:$J$2005,"Package",Appointments!$F$6:$F$2005,"No-show"),0)) | N22: =IF(OR(B22="",I22=""),"",IF(AND(J22="",TODAY()-I22>=N(Services!$I$7)),"Not seen for "&(TODAY()-I22)&" days","")) | O22: =IF(N(E22)=0,"",MONTH(E22))
B23: Rosa Diaz | C23: 555 0118 | D23: rosa.d@example.com | E23: 30710 | F23: 44341 | H23: =IF(B23="","",COUNTIFS(Appointments!$D$6:$D$2005,B23,Appointments!$F$6:$F$2005,"Done")) | I23: =IF(OR(B23="",N(H23)=0),"",INT(SUMIFS(Appointments!$M$6:$M$2005,Appointments!$D$6:$D$2005,B23,Appointments!$N$6:$N$2005,1))) | J23: =IF(B23="","",IF(SUMIFS(Appointments!$M$6:$M$2005,Appointments!$D$6:$D$2005,B23,Appointments!$O$6:$O$2005,1)=0,"",INT(SUMIFS(Appointments!$M$6:$M$2005,Appointments!$D$6:$D$2005,B23,Appointments!$O$6:$O$2005,1)))) | K23: =IF(B23="","",SUMIFS(Appointments!$I$6:$I$2005,Appointments!$D$6:$D$2005,B23)+SUMIFS(Packages!$F$6:$F$305,Packages!$C$6:$C$305,B23)) | L23: =IF(B23="","",IF(SUMIFS(Appointments!$K$6:$K$2005,Appointments!$D$6:$D$2005,B23)=0,"",SUMIFS(Appointments!$K$6:$K$2005,Appointments!$D$6:$D$2005,B23))) | M23: =IF(OR(B23="",SUMIFS(Packages!$E$6:$E$305,Packages!$C$6:$C$305,B23)=0),"",SUMIFS(Packages!$E$6:$E$305,Packages!$C$6:$C$305,B23)-COUNTIFS(Appointments!$D$6:$D$2005,B23,Appointments!$J$6:$J$2005,"Package",Appointments!$F$6:$F$2005,"Done")+IF(Services!$I$6="Yes",COUNTIFS(Appointments!$D$6:$D$2005,B23,Appointments!$J$6:$J$2005,"Package",Appointments!$F$6:$F$2005,"No-show"),0)) | N23: =IF(OR(B23="",I23=""),"",IF(AND(J23="",TODAY()-I23>=N(Services!$I$7)),"Not seen for "&(TODAY()-I23)&" days","")) | O23: =IF(N(E23)=0,"",MONTH(E23))
B24: Sam Clarke | C24: 555 0119 | F24: 45575 | H24: =IF(B24="","",COUNTIFS(Appointments!$D$6:$D$2005,B24,Appointments!$F$6:$F$2005,"Done")) | I24: =IF(OR(B24="",N(H24)=0),"",INT(SUMIFS(Appointments!$M$6:$M$2005,Appointments!$D$6:$D$2005,B24,Appointments!$N$6:$N$2005,1))) | J24: =IF(B24="","",IF(SUMIFS(Appointments!$M$6:$M$2005,Appointments!$D$6:$D$2005,B24,Appointments!$O$6:$O$2005,1)=0,"",INT(SUMIFS(Appointments!$M$6:$M$2005,Appointments!$D$6:$D$2005,B24,Appointments!$O$6:$O$2005,1)))) | K24: =IF(B24="","",SUMIFS(Appointments!$I$6:$I$2005,Appointments!$D$6:$D$2005,B24)+SUMIFS(Packages!$F$6:$F$305,Packages!$C$6:$C$305,B24)) | L24: =IF(B24="","",IF(SUMIFS(Appointments!$K$6:$K$2005,Appointments!$D$6:$D$2005,B24)=0,"",SUMIFS(Appointments!$K$6:$K$2005,Appointments!$D$6:$D$2005,B24))) | M24: =IF(OR(B24="",SUMIFS(Packages!$E$6:$E$305,Packages!$C$6:$C$305,B24)=0),"",SUMIFS(Packages!$E$6:$E$305,Packages!$C$6:$C$305,B24)-COUNTIFS(Appointments!$D$6:$D$2005,B24,Appointments!$J$6:$J$2005,"Package",Appointments!$F$6:$F$2005,"Done")+IF(Services!$I$6="Yes",COUNTIFS(Appointments!$D$6:$D$2005,B24,Appointments!$J$6:$J$2005,"Package",Appointments!$F$6:$F$2005,"No-show"),0)) | N24: =IF(OR(B24="",I24=""),"",IF(AND(J24="",TODAY()-I24>=N(Services!$I$7)),"Not seen for "&(TODAY()-I24)&" days","")) | O24: =IF(N(E24)=0,"",MONTH(E24))
B25: Tara Singh | C25: 555 0120 | E25: 35289 | F25: 45157 | H25: =IF(B25="","",COUNTIFS(Appointments!$D$6:$D$2005,B25,Appointments!$F$6:$F$2005,"Done")) | I25: =IF(OR(B25="",N(H25)=0),"",INT(SUMIFS(Appointments!$M$6:$M$2005,Appointments!$D$6:$D$2005,B25,Appointments!$N$6:$N$2005,1))) | J25: =IF(B25="","",IF(SUMIFS(Appointments!$M$6:$M$2005,Appointments!$D$6:$D$2005,B25,Appointments!$O$6:$O$2005,1)=0,"",INT(SUMIFS(Appointments!$M$6:$M$2005,Appointments!$D$6:$D$2005,B25,Appointments!$O$6:$O$2005,1)))) | K25: =IF(B25="","",SUMIFS(Appointments!$I$6:$I$2005,Appointments!$D$6:$D$2005,B25)+SUMIFS(Packages!$F$6:$F$305,Packages!$C$6:$C$305,B25)) | L25: =IF(B25="","",IF(SUMIFS(Appointments!$K$6:$K$2005,Appointments!$D$6:$D$2005,B25)=0,"",SUMIFS(Appointments!$K$6:$K$2005,Appointments!$D$6:$D$2005,B25))) | M25: =IF(OR(B25="",SUMIFS(Packages!$E$6:$E$305,Packages!$C$6:$C$305,B25)=0),"",SUMIFS(Packages!$E$6:$E$305,Packages!$C$6:$C$305,B25)-COUNTIFS(Appointments!$D$6:$D$2005,B25,Appointments!$J$6:$J$2005,"Package",Appointments!$F$6:$F$2005,"Done")+IF(Services!$I$6="Yes",COUNTIFS(Appointments!$D$6:$D$2005,B25,Appointments!$J$6:$J$2005,"Package",Appointments!$F$6:$F$2005,"No-show"),0)) | N25: =IF(OR(B25="",I25=""),"",IF(AND(J25="",TODAY()-I25>=N(Services!$I$7)),"Not seen for "&(TODAY()-I25)&" days","")) | O25: =IF(N(E25)=0,"",MONTH(E25))
B26: Uma Nair | C26: 555 0121 | F26: 45386 | H26: =IF(B26="","",COUNTIFS(Appointments!$D$6:$D$2005,B26,Appointments!$F$6:$F$2005,"Done")) | I26: =IF(OR(B26="",N(H26)=0),"",INT(SUMIFS(Appointments!$M$6:$M$2005,Appointments!$D$6:$D$2005,B26,Appointments!$N$6:$N$2005,1))) | J26: =IF(B26="","",IF(SUMIFS(Appointments!$M$6:$M$2005,Appointments!$D$6:$D$2005,B26,Appointments!$O$6:$O$2005,1)=0,"",INT(SUMIFS(Appointments!$M$6:$M$2005,Appointments!$D$6:$D$2005,B26,Appointments!$O$6:$O$2005,1)))) | K26: =IF(B26="","",SUMIFS(Appointments!$I$6:$I$2005,Appointments!$D$6:$D$2005,B26)+SUMIFS(Packages!$F$6:$F$305,Packages!$C$6:$C$305,B26)) | L26: =IF(B26="","",IF(SUMIFS(Appointments!$K$6:$K$2005,Appointments!$D$6:$D$2005,B26)=0,"",SUMIFS(Appointments!$K$6:$K$2005,Appointments!$D$6:$D$2005,B26))) | M26: =IF(OR(B26="",SUMIFS(Packages!$E$6:$E$305,Packages!$C$6:$C$305,B26)=0),"",SUMIFS(Packages!$E$6:$E$305,Packages!$C$6:$C$305,B26)-COUNTIFS(Appointments!$D$6:$D$2005,B26,Appointments!$J$6:$J$2005,"Package",Appointments!$F$6:$F$2005,"Done")+IF(Services!$I$6="Yes",COUNTIFS(Appointments!$D$6:$D$2005,B26,Appointments!$J$6:$J$2005,"Package",Appointments!$F$6:$F$2005,"No-show"),0)) | N26: =IF(OR(B26="",I26=""),"",IF(AND(J26="",TODAY()-I26>=N(Services!$I$7)),"Not seen for "&(TODAY()-I26)&" days","")) | O26: =IF(N(E26)=0,"",MONTH(E26))
B27: Victor Lane | C27: 555 0122 | F27: 45690 | H27: =IF(B27="","",COUNTIFS(Appointments!$D$6:$D$2005,B27,Appointments!$F$6:$F$2005,"Done")) | I27: =IF(OR(B27="",N(H27)=0),"",INT(SUMIFS(Appointments!$M$6:$M$2005,Appointments!$D$6:$D$2005,B27,Appointments!$N$6:$N$2005,1))) | J27: =IF(B27="","",IF(SUMIFS(Appointments!$M$6:$M$2005,Appointments!$D$6:$D$2005,B27,Appointments!$O$6:$O$2005,1)=0,"",INT(SUMIFS(Appointments!$M$6:$M$2005,Appointments!$D$6:$D$2005,B27,Appointments!$O$6:$O$2005,1)))) | K27: =IF(B27="","",SUMIFS(Appointments!$I$6:$I$2005,Appointments!$D$6:$D$2005,B27)+SUMIFS(Packages!$F$6:$F$305,Packages!$C$6:$C$305,B27)) | L27: =IF(B27="","",IF(SUMIFS(Appointments!$K$6:$K$2005,Appointments!$D$6:$D$2005,B27)=0,"",SUMIFS(Appointments!$K$6:$K$2005,Appointments!$D$6:$D$2005,B27))) | M27: =IF(OR(B27="",SUMIFS(Packages!$E$6:$E$305,Packages!$C$6:$C$305,B27)=0),"",SUMIFS(Packages!$E$6:$E$305,Packages!$C$6:$C$305,B27)-COUNTIFS(Appointments!$D$6:$D$2005,B27,Appointments!$J$6:$J$2005,"Package",Appointments!$F$6:$F$2005,"Done")+IF(Services!$I$6="Yes",COUNTIFS(Appointments!$D$6:$D$2005,B27,Appointments!$J$6:$J$2005,"Package",Appointments!$F$6:$F$2005,"No-show"),0)) | N27: =IF(OR(B27="",I27=""),"",IF(AND(J27="",TODAY()-I27>=N(Services!$I$7)),"Not seen for "&(TODAY()-I27)&" days","")) | O27: =IF(N(E27)=0,"",MONTH(E27))
B28: Wendy Scott | C28: 555 0123 | D28: wendy.s@example.com | F28: 44896 | H28: =IF(B28="","",COUNTIFS(Appointments!$D$6:$D$2005,B28,Appointments!$F$6:$F$2005,"Done")) | I28: =IF(OR(B28="",N(H28)=0),"",INT(SUMIFS(Appointments!$M$6:$M$2005,Appointments!$D$6:$D$2005,B28,Appointments!$N$6:$N$2005,1))) | J28: =IF(B28="","",IF(SUMIFS(Appointments!$M$6:$M$2005,Appointments!$D$6:$D$2005,B28,Appointments!$O$6:$O$2005,1)=0,"",INT(SUMIFS(Appointments!$M$6:$M$2005,Appointments!$D$6:$D$2005,B28,Appointments!$O$6:$O$2005,1)))) | K28: =IF(B28="","",SUMIFS(Appointments!$I$6:$I$2005,Appointments!$D$6:$D$2005,B28)+SUMIFS(Packages!$F$6:$F$305,Packages!$C$6:$C$305,B28)) | L28: =IF(B28="","",IF(SUMIFS(Appointments!$K$6:$K$2005,Appointments!$D$6:$D$2005,B28)=0,"",SUMIFS(Appointments!$K$6:$K$2005,Appointments!$D$6:$D$2005,B28))) | M28: =IF(OR(B28="",SUMIFS(Packages!$E$6:$E$305,Packages!$C$6:$C$305,B28)=0),"",SUMIFS(Packages!$E$6:$E$305,Packages!$C$6:$C$305,B28)-COUNTIFS(Appointments!$D$6:$D$2005,B28,Appointments!$J$6:$J$2005,"Package",Appointments!$F$6:$F$2005,"Done")+IF(Services!$I$6="Yes",COUNTIFS(Appointments!$D$6:$D$2005,B28,Appointments!$J$6:$J$2005,"Package",Appointments!$F$6:$F$2005,"No-show"),0)) | N28: =IF(OR(B28="",I28=""),"",IF(AND(J28="",TODAY()-I28>=N(Services!$I$7)),"Not seen for "&(TODAY()-I28)&" days","")) | O28: =IF(N(E28)=0,"",MONTH(E28))
B29: Yara Haddad | C29: 555 0124 | D29: yara.h@example.com | F29: 46270 | G29: New client, found us online | H29: =IF(B29="","",COUNTIFS(Appointments!$D$6:$D$2005,B29,Appointments!$F$6:$F$2005,"Done")) | I29: =IF(OR(B29="",N(H29)=0),"",INT(SUMIFS(Appointments!$M$6:$M$2005,Appointments!$D$6:$D$2005,B29,Appointments!$N$6:$N$2005,1))) | J29: =IF(B29="","",IF(SUMIFS(Appointments!$M$6:$M$2005,Appointments!$D$6:$D$2005,B29,Appointments!$O$6:$O$2005,1)=0,"",INT(SUMIFS(Appointments!$M$6:$M$2005,Appointments!$D$6:$D$2005,B29,Appointments!$O$6:$O$2005,1)))) | K29: =IF(B29="","",SUMIFS(Appointments!$I$6:$I$2005,Appointments!$D$6:$D$2005,B29)+SUMIFS(Packages!$F$6:$F$305,Packages!$C$6:$C$305,B29)) | L29: =IF(B29="","",IF(SUMIFS(Appointments!$K$6:$K$2005,Appointments!$D$6:$D$2005,B29)=0,"",SUMIFS(Appointments!$K$6:$K$2005,Appointments!$D$6:$D$2005,B29))) | M29: =IF(OR(B29="",SUMIFS(Packages!$E$6:$E$305,Packages!$C$6:$C$305,B29)=0),"",SUMIFS(Packages!$E$6:$E$305,Packages!$C$6:$C$305,B29)-COUNTIFS(Appointments!$D$6:$D$2005,B29,Appointments!$J$6:$J$2005,"Package",Appointments!$F$6:$F$2005,"Done")+IF(Services!$I$6="Yes",COUNTIFS(Appointments!$D$6:$D$2005,B29,Appointments!$J$6:$J$2005,"Package",Appointments!$F$6:$F$2005,"No-show"),0)) | N29: =IF(OR(B29="",I29=""),"",IF(AND(J29="",TODAY()-I29>=N(Services!$I$7)),"Not seen for "&(TODAY()-I29)&" days","")) | O29: =IF(N(E29)=0,"",MONTH(E29))
B30: Zoe Turner | C30: 555 0125 | E30: 35920 | F30: 45473 | H30: =IF(B30="","",COUNTIFS(Appointments!$D$6:$D$2005,B30,Appointments!$F$6:$F$2005,"Done")) | I30: =IF(OR(B30="",N(H30)=0),"",INT(SUMIFS(Appointments!$M$6:$M$2005,Appointments!$D$6:$D$2005,B30,Appointments!$N$6:$N$2005,1))) | J30: =IF(B30="","",IF(SUMIFS(Appointments!$M$6:$M$2005,Appointments!$D$6:$D$2005,B30,Appointments!$O$6:$O$2005,1)=0,"",INT(SUMIFS(Appointments!$M$6:$M$2005,Appointments!$D$6:$D$2005,B30,Appointments!$O$6:$O$2005,1)))) | K30: =IF(B30="","",SUMIFS(Appointments!$I$6:$I$2005,Appointments!$D$6:$D$2005,B30)+SUMIFS(Packages!$F$6:$F$305,Packages!$C$6:$C$305,B30)) | L30: =IF(B30="","",IF(SUMIFS(Appointments!$K$6:$K$2005,Appointments!$D$6:$D$2005,B30)=0,"",SUMIFS(Appointments!$K$6:$K$2005,Appointments!$D$6:$D$2005,B30))) | M30: =IF(OR(B30="",SUMIFS(Packages!$E$6:$E$305,Packages!$C$6:$C$305,B30)=0),"",SUMIFS(Packages!$E$6:$E$305,Packages!$C$6:$C$305,B30)-COUNTIFS(Appointments!$D$6:$D$2005,B30,Appointments!$J$6:$J$2005,"Package",Appointments!$F$6:$F$2005,"Done")+IF(Services!$I$6="Yes",COUNTIFS(Appointments!$D$6:$D$2005,B30,Appointments!$J$6:$J$2005,"Package",Appointments!$F$6:$F$2005,"No-show"),0)) | N30: =IF(OR(B30="",I30=""),"",IF(AND(J30="",TODAY()-I30>=N(Services!$I$7)),"Not seen for "&(TODAY()-I30)&" days","")) | O30: =IF(N(E30)=0,"",MONTH(E30))
B31: Sara Ward | C31: 555 0225 | F31: 44646 | H31: =IF(B31="","",COUNTIFS(Appointments!$D$6:$D$2005,B31,Appointments!$F$6:$F$2005,"Done")) | I31: =IF(OR(B31="",N(H31)=0),"",INT(SUMIFS(Appointments!$M$6:$M$2005,Appointments!$D$6:$D$2005,B31,Appointments!$N$6:$N$2005,1))) | J31: =IF(B31="","",IF(SUMIFS(Appointments!$M$6:$M$2005,Appointments!$D$6:$D$2005,B31,Appointments!$O$6:$O$2005,1)=0,"",INT(SUMIFS(Appointments!$M$6:$M$2005,Appointments!$D$6:$D$2005,B31,Appointments!$O$6:$O$2005,1)))) | K31: =IF(B31="","",SUMIFS(Appointments!$I$6:$I$2005,Appointments!$D$6:$D$2005,B31)+SUMIFS(Packages!$F$6:$F$305,Packages!$C$6:$C$305,B31)) | L31: =IF(B31="","",IF(SUMIFS(Appointments!$K$6:$K$2005,Appointments!$D$6:$D$2005,B31)=0,"",SUMIFS(Appointments!$K$6:$K$2005,Appointments!$D$6:$D$2005,B31))) | M31: =IF(OR(B31="",SUMIFS(Packages!$E$6:$E$305,Packages!$C$6:$C$305,B31)=0),"",SUMIFS(Packages!$E$6:$E$305,Packages!$C$6:$C$305,B31)-COUNTIFS(Appointments!$D$6:$D$2005,B31,Appointments!$J$6:$J$2005,"Package",Appointments!$F$6:$F$2005,"Done")+IF(Services!$I$6="Yes",COUNTIFS(Appointments!$D$6:$D$2005,B31,Appointments!$J$6:$J$2005,"Package",Appointments!$F$6:$F$2005,"No-show"),0)) | N31: =IF(OR(B31="",I31=""),"",IF(AND(J31="",TODAY()-I31>=N(Services!$I$7)),"Not seen for "&(TODAY()-I31)&" days","")) | O31: =IF(N(E31)=0,"",MONTH(E31))
B32: Luke Hall | C32: 555 0226 | D32: luke.h@example.com | F32: 44465 | H32: =IF(B32="","",COUNTIFS(Appointments!$D$6:$D$2005,B32,Appointments!$F$6:$F$2005,"Done")) | I32: =IF(OR(B32="",N(H32)=0),"",INT(SUMIFS(Appointments!$M$6:$M$2005,Appointments!$D$6:$D$2005,B32,Appointments!$N$6:$N$2005,1))) | J32: =IF(B32="","",IF(SUMIFS(Appointments!$M$6:$M$2005,Appointments!$D$6:$D$2005,B32,Appointments!$O$6:$O$2005,1)=0,"",INT(SUMIFS(Appointments!$M$6:$M$2005,Appointments!$D$6:$D$2005,B32,Appointments!$O$6:$O$2005,1)))) | K32: =IF(B32="","",SUMIFS(Appointments!$I$6:$I$2005,Appointments!$D$6:$D$2005,B32)+SUMIFS(Packages!$F$6:$F$305,Packages!$C$6:$C$305,B32)) | L32: =IF(B32="","",IF(SUMIFS(Appointments!$K$6:$K$2005,Appointments!$D$6:$D$2005,B32)=0,"",SUMIFS(Appointments!$K$6:$K$2005,Appointments!$D$6:$D$2005,B32))) | M32: =IF(OR(B32="",SUMIFS(Packages!$E$6:$E$305,Packages!$C$6:$C$305,B32)=0),"",SUMIFS(Packages!$E$6:$E$305,Packages!$C$6:$C$305,B32)-COUNTIFS(Appointments!$D$6:$D$2005,B32,Appointments!$J$6:$J$2005,"Package",Appointments!$F$6:$F$2005,"Done")+IF(Services!$I$6="Yes",COUNTIFS(Appointments!$D$6:$D$2005,B32,Appointments!$J$6:$J$2005,"Package",Appointments!$F$6:$F$2005,"No-show"),0)) | N32: =IF(OR(B32="",I32=""),"",IF(AND(J32="",TODAY()-I32>=N(Services!$I$7)),"Not seen for "&(TODAY()-I32)&" days","")) | O32: =IF(N(E32)=0,"",MONTH(E32))
B33: Jon Reid | C33: 555 0227 | F33: 45967 | H33: =IF(B33="","",COUNTIFS(Appointments!$D$6:$D$2005,B33,Appointments!$F$6:$F$2005,"Done")) | I33: =IF(OR(B33="",N(H33)=0),"",INT(SUMIFS(Appointments!$M$6:$M$2005,Appointments!$D$6:$D$2005,B33,Appointments!$N$6:$N$2005,1))) | J33: =IF(B33="","",IF(SUMIFS(Appointments!$M$6:$M$2005,Appointments!$D$6:$D$2005,B33,Appointments!$O$6:$O$2005,1)=0,"",INT(SUMIFS(Appointments!$M$6:$M$2005,Appointments!$D$6:$D$2005,B33,Appointments!$O$6:$O$2005,1)))) | K33: =IF(B33="","",SUMIFS(Appointments!$I$6:$I$2005,Appointments!$D$6:$D$2005,B33)+SUMIFS(Packages!$F$6:$F$305,Packages!$C$6:$C$305,B33)) | L33: =IF(B33="","",IF(SUMIFS(Appointments!$K$6:$K$2005,Appointments!$D$6:$D$2005,B33)=0,"",SUMIFS(Appointments!$K$6:$K$2005,Appointments!$D$6:$D$2005,B33))) | M33: =IF(OR(B33="",SUMIFS(Packages!$E$6:$E$305,Packages!$C$6:$C$305,B33)=0),"",SUMIFS(Packages!$E$6:$E$305,Packages!$C$6:$C$305,B33)-COUNTIFS(Appointments!$D$6:$D$2005,B33,Appointments!$J$6:$J$2005,"Package",Appointments!$F$6:$F$2005,"Done")+IF(Services!$I$6="Yes",COUNTIFS(Appointments!$D$6:$D$2005,B33,Appointments!$J$6:$J$2005,"Package",Appointments!$F$6:$F$2005,"No-show"),0)) | N33: =IF(OR(B33="",I33=""),"",IF(AND(J33="",TODAY()-I33>=N(Services!$I$7)),"Not seen for "&(TODAY()-I33)&" days","")) | O33: =IF(N(E33)=0,"",MONTH(E33))
B34: Eli Cole | C34: 555 0228 | D34: eli.c@example.com | E34: 29495 | F34: 45458 | H34: =IF(B34="","",COUNTIFS(Appointments!$D$6:$D$2005,B34,Appointments!$F$6:$F$2005,"Done")) | I34: =IF(OR(B34="",N(H34)=0),"",INT(SUMIFS(Appointments!$M$6:$M$2005,Appointments!$D$6:$D$2005,B34,Appointments!$N$6:$N$2005,1))) | J34: =IF(B34="","",IF(SUMIFS(Appointments!$M$6:$M$2005,Appointments!$D$6:$D$2005,B34,Appointments!$O$6:$O$2005,1)=0,"",INT(SUMIFS(Appointments!$M$6:$M$2005,Appointments!$D$6:$D$2005,B34,Appointments!$O$6:$O$2005,1)))) | K34: =IF(B34="","",SUMIFS(Appointments!$I$6:$I$2005,Appointments!$D$6:$D$2005,B34)+SUMIFS(Packages!$F$6:$F$305,Packages!$C$6:$C$305,B34)) | L34: =IF(B34="","",IF(SUMIFS(Appointments!$K$6:$K$2005,Appointments!$D$6:$D$2005,B34)=0,"",SUMIFS(Appointments!$K$6:$K$2005,Appointments!$D$6:$D$2005,B34))) | M34: =IF(OR(B34="",SUMIFS(Packages!$E$6:$E$305,Packages!$C$6:$C$305,B34)=0),"",SUMIFS(Packages!$E$6:$E$305,Packages!$C$6:$C$305,B34)-COUNTIFS(Appointments!$D$6:$D$2005,B34,Appointments!$J$6:$J$2005,"Package",Appointments!$F$6:$F$2005,"Done")+IF(Services!$I$6="Yes",COUNTIFS(Appointments!$D$6:$D$2005,B34,Appointments!$J$6:$J$2005,"Package",Appointments!$F$6:$F$2005,"No-show"),0)) | N34: =IF(OR(B34="",I34=""),"",IF(AND(J34="",TODAY()-I34>=N(Services!$I$7)),"Not seen for "&(TODAY()-I34)&" days","")) | O34: =IF(N(E34)=0,"",MONTH(E34))
B35: Eli James | C35: 555 0229 | F35: 44429 | H35: =IF(B35="","",COUNTIFS(Appointments!$D$6:$D$2005,B35,Appointments!$F$6:$F$2005,"Done")) | I35: =IF(OR(B35="",N(H35)=0),"",INT(SUMIFS(Appointments!$M$6:$M$2005,Appointments!$D$6:$D$2005,B35,Appointments!$N$6:$N$2005,1))) | J35: =IF(B35="","",IF(SUMIFS(Appointments!$M$6:$M$2005,Appointments!$D$6:$D$2005,B35,Appointments!$O$6:$O$2005,1)=0,"",INT(SUMIFS(Appointments!$M$6:$M$2005,Appointments!$D$6:$D$2005,B35,Appointments!$O$6:$O$2005,1)))) | K35: =IF(B35="","",SUMIFS(Appointments!$I$6:$I$2005,Appointments!$D$6:$D$2005,B35)+SUMIFS(Packages!$F$6:$F$305,Packages!$C$6:$C$305,B35)) | L35: =IF(B35="","",IF(SUMIFS(Appointments!$K$6:$K$2005,Appointments!$D$6:$D$2005,B35)=0,"",SUMIFS(Appointments!$K$6:$K$2005,Appointments!$D$6:$D$2005,B35))) | M35: =IF(OR(B35="",SUMIFS(Packages!$E$6:$E$305,Packages!$C$6:$C$305,B35)=0),"",SUMIFS(Packages!$E$6:$E$305,Packages!$C$6:$C$305,B35)-COUNTIFS(Appointments!$D$6:$D$2005,B35,Appointments!$J$6:$J$2005,"Package",Appointments!$F$6:$F$2005,"Done")+IF(Services!$I$6="Yes",COUNTIFS(Appointments!$D$6:$D$2005,B35,Appointments!$J$6:$J$2005,"Package",Appointments!$F$6:$F$2005,"No-show"),0)) | N35: =IF(OR(B35="",I35=""),"",IF(AND(J35="",TODAY()-I35>=N(Services!$I$7)),"Not seen for "&(TODAY()-I35)&" days","")) | O35: =IF(N(E35)=0,"",MONTH(E35))
B36: Paula Cook | C36: 555 0230 | F36: 44814 | H36: =IF(B36="","",COUNTIFS(Appointments!$D$6:$D$2005,B36,Appointments!$F$6:$F$2005,"Done")) | I36: =IF(OR(B36="",N(H36)=0),"",INT(SUMIFS(Appointments!$M$6:$M$2005,Appointments!$D$6:$D$2005,B36,Appointments!$N$6:$N$2005,1))) | J36: =IF(B36="","",IF(SUMIFS(Appointments!$M$6:$M$2005,Appointments!$D$6:$D$2005,B36,Appointments!$O$6:$O$2005,1)=0,"",INT(SUMIFS(Appointments!$M$6:$M$2005,Appointments!$D$6:$D$2005,B36,Appointments!$O$6:$O$2005,1)))) | K36: =IF(B36="","",SUMIFS(Appointments!$I$6:$I$2005,Appointments!$D$6:$D$2005,B36)+SUMIFS(Packages!$F$6:$F$305,Packages!$C$6:$C$305,B36)) | L36: =IF(B36="","",IF(SUMIFS(Appointments!$K$6:$K$2005,Appointments!$D$6:$D$2005,B36)=0,"",SUMIFS(Appointments!$K$6:$K$2005,Appointments!$D$6:$D$2005,B36))) | M36: =IF(OR(B36="",SUMIFS(Packages!$E$6:$E$305,Packages!$C$6:$C$305,B36)=0),"",SUMIFS(Packages!$E$6:$E$305,Packages!$C$6:$C$305,B36)-COUNTIFS(Appointments!$D$6:$D$2005,B36,Appointments!$J$6:$J$2005,"Package",Appointments!$F$6:$F$2005,"Done")+IF(Services!$I$6="Yes",COUNTIFS(Appointments!$D$6:$D$2005,B36,Appointments!$J$6:$J$2005,"Package",Appointments!$F$6:$F$2005,"No-show"),0)) | N36: =IF(OR(B36="",I36=""),"",IF(AND(J36="",TODAY()-I36>=N(Services!$I$7)),"Not seen for "&(TODAY()-I36)&" days","")) | O36: =IF(N(E36)=0,"",MONTH(E36))
B37: Harry Cox | C37: 555 0231 | F37: 45323 | H37: =IF(B37="","",COUNTIFS(Appointments!$D$6:$D$2005,B37,Appointments!$F$6:$F$2005,"Done")) | I37: =IF(OR(B37="",N(H37)=0),"",INT(SUMIFS(Appointments!$M$6:$M$2005,Appointments!$D$6:$D$2005,B37,Appointments!$N$6:$N$2005,1))) | J37: =IF(B37="","",IF(SUMIFS(Appointments!$M$6:$M$2005,Appointments!$D$6:$D$2005,B37,Appointments!$O$6:$O$2005,1)=0,"",INT(SUMIFS(Appointments!$M$6:$M$2005,Appointments!$D$6:$D$2005,B37,Appointments!$O$6:$O$2005,1)))) | K37: =IF(B37="","",SUMIFS(Appointments!$I$6:$I$2005,Appointments!$D$6:$D$2005,B37)+SUMIFS(Packages!$F$6:$F$305,Packages!$C$6:$C$305,B37)) | L37: =IF(B37="","",IF(SUMIFS(Appointments!$K$6:$K$2005,Appointments!$D$6:$D$2005,B37)=0,"",SUMIFS(Appointments!$K$6:$K$2005,Appointments!$D$6:$D$2005,B37))) | M37: =IF(OR(B37="",SUMIFS(Packages!$E$6:$E$305,Packages!$C$6:$C$305,B37)=0),"",SUMIFS(Packages!$E$6:$E$305,Packages!$C$6:$C$305,B37)-COUNTIFS(Appointments!$D$6:$D$2005,B37,Appointments!$J$6:$J$2005,"Package",Appointments!$F$6:$F$2005,"Done")+IF(Services!$I$6="Yes",COUNTIFS(Appointments!$D$6:$D$2005,B37,Appointments!$J$6:$J$2005,"Package",Appointments!$F$6:$F$2005,"No-show"),0)) | N37: =IF(OR(B37="",I37=""),"",IF(AND(J37="",TODAY()-I37>=N(Services!$I$7)),"Not seen for "&(TODAY()-I37)&" days","")) | O37: =IF(N(E37)=0,"",MONTH(E37))
B38: Amy Hughes | C38: 555 0232 | E38: 32855 | F38: 45341 | H38: =IF(B38="","",COUNTIFS(Appointments!$D$6:$D$2005,B38,Appointments!$F$6:$F$2005,"Done")) | I38: =IF(OR(B38="",N(H38)=0),"",INT(SUMIFS(Appointments!$M$6:$M$2005,Appointments!$D$6:$D$2005,B38,Appointments!$N$6:$N$2005,1))) | J38: =IF(B38="","",IF(SUMIFS(Appointments!$M$6:$M$2005,Appointments!$D$6:$D$2005,B38,Appointments!$O$6:$O$2005,1)=0,"",INT(SUMIFS(Appointments!$M$6:$M$2005,Appointments!$D$6:$D$2005,B38,Appointments!$O$6:$O$2005,1)))) | K38: =IF(B38="","",SUMIFS(Appointments!$I$6:$I$2005,Appointments!$D$6:$D$2005,B38)+SUMIFS(Packages!$F$6:$F$305,Packages!$C$6:$C$305,B38)) | L38: =IF(B38="","",IF(SUMIFS(Appointments!$K$6:$K$2005,Appointments!$D$6:$D$2005,B38)=0,"",SUMIFS(Appointments!$K$6:$K$2005,Appointments!$D$6:$D$2005,B38))) | M38: =IF(OR(B38="",SUMIFS(Packages!$E$6:$E$305,Packages!$C$6:$C$305,B38)=0),"",SUMIFS(Packages!$E$6:$E$305,Packages!$C$6:$C$305,B38)-COUNTIFS(Appointments!$D$6:$D$2005,B38,Appointments!$J$6:$J$2005,"Package",Appointments!$F$6:$F$2005,"Done")+IF(Services!$I$6="Yes",COUNTIFS(Appointments!$D$6:$D$2005,B38,Appointments!$J$6:$J$2005,"Package",Appointments!$F$6:$F$2005,"No-show"),0)) | N38: =IF(OR(B38="",I38=""),"",IF(AND(J38="",TODAY()-I38>=N(Services!$I$7)),"Not seen for "&(TODAY()-I38)&" days","")) | O38: =IF(N(E38)=0,"",MONTH(E38))
B39: Owen Lewis | C39: 555 0233 | D39: owen.l@example.com | F39: 44402 | H39: =IF(B39="","",COUNTIFS(Appointments!$D$6:$D$2005,B39,Appointments!$F$6:$F$2005,"Done")) | I39: =IF(OR(B39="",N(H39)=0),"",INT(SUMIFS(Appointments!$M$6:$M$2005,Appointments!$D$6:$D$2005,B39,Appointments!$N$6:$N$2005,1))) | J39: =IF(B39="","",IF(SUMIFS(Appointments!$M$6:$M$2005,Appointments!$D$6:$D$2005,B39,Appointments!$O$6:$O$2005,1)=0,"",INT(SUMIFS(Appointments!$M$6:$M$2005,Appointments!$D$6:$D$2005,B39,Appointments!$O$6:$O$2005,1)))) | K39: =IF(B39="","",SUMIFS(Appointments!$I$6:$I$2005,Appointments!$D$6:$D$2005,B39)+SUMIFS(Packages!$F$6:$F$305,Packages!$C$6:$C$305,B39)) | L39: =IF(B39="","",IF(SUMIFS(Appointments!$K$6:$K$2005,Appointments!$D$6:$D$2005,B39)=0,"",SUMIFS(Appointments!$K$6:$K$2005,Appointments!$D$6:$D$2005,B39))) | M39: =IF(OR(B39="",SUMIFS(Packages!$E$6:$E$305,Packages!$C$6:$C$305,B39)=0),"",SUMIFS(Packages!$E$6:$E$305,Packages!$C$6:$C$305,B39)-COUNTIFS(Appointments!$D$6:$D$2005,B39,Appointments!$J$6:$J$2005,"Package",Appointments!$F$6:$F$2005,"Done")+IF(Services!$I$6="Yes",COUNTIFS(Appointments!$D$6:$D$2005,B39,Appointments!$J$6:$J$2005,"Package",Appointments!$F$6:$F$2005,"No-show"),0)) | N39: =IF(OR(B39="",I39=""),"",IF(AND(J39="",TODAY()-I39>=N(Services!$I$7)),"Not seen for "&(TODAY()-I39)&" days","")) | O39: =IF(N(E39)=0,"",MONTH(E39))
B40: Hannah Kelly | C40: 555 0234 | E40: 34552 | F40: 45762 | H40: =IF(B40="","",COUNTIFS(Appointments!$D$6:$D$2005,B40,Appointments!$F$6:$F$2005,"Done")) | I40: =IF(OR(B40="",N(H40)=0),"",INT(SUMIFS(Appointments!$M$6:$M$2005,Appointments!$D$6:$D$2005,B40,Appointments!$N$6:$N$2005,1))) | J40: =IF(B40="","",IF(SUMIFS(Appointments!$M$6:$M$2005,Appointments!$D$6:$D$2005,B40,Appointments!$O$6:$O$2005,1)=0,"",INT(SUMIFS(Appointments!$M$6:$M$2005,Appointments!$D$6:$D$2005,B40,Appointments!$O$6:$O$2005,1)))) | K40: =IF(B40="","",SUMIFS(Appointments!$I$6:$I$2005,Appointments!$D$6:$D$2005,B40)+SUMIFS(Packages!$F$6:$F$305,Packages!$C$6:$C$305,B40)) | L40: =IF(B40="","",IF(SUMIFS(Appointments!$K$6:$K$2005,Appointments!$D$6:$D$2005,B40)=0,"",SUMIFS(Appointments!$K$6:$K$2005,Appointments!$D$6:$D$2005,B40))) | M40: =IF(OR(B40="",SUMIFS(Packages!$E$6:$E$305,Packages!$C$6:$C$305,B40)=0),"",SUMIFS(Packages!$E$6:$E$305,Packages!$C$6:$C$305,B40)-COUNTIFS(Appointments!$D$6:$D$2005,B40,Appointments!$J$6:$J$2005,"Package",Appointments!$F$6:$F$2005,"Done")+IF(Services!$I$6="Yes",COUNTIFS(Appointments!$D$6:$D$2005,B40,Appointments!$J$6:$J$2005,"Package",Appointments!$F$6:$F$2005,"No-show"),0)) | N40: =IF(OR(B40="",I40=""),"",IF(AND(J40="",TODAY()-I40>=N(Services!$I$7)),"Not seen for "&(TODAY()-I40)&" days","")) | O40: =IF(N(E40)=0,"",MONTH(E40))
B41: Tom Ellis | C41: 555 0235 | F41: 45480 | H41: =IF(B41="","",COUNTIFS(Appointments!$D$6:$D$2005,B41,Appointments!$F$6:$F$2005,"Done")) | I41: =IF(OR(B41="",N(H41)=0),"",INT(SUMIFS(Appointments!$M$6:$M$2005,Appointments!$D$6:$D$2005,B41,Appointments!$N$6:$N$2005,1))) | J41: =IF(B41="","",IF(SUMIFS(Appointments!$M$6:$M$2005,Appointments!$D$6:$D$2005,B41,Appointments!$O$6:$O$2005,1)=0,"",INT(SUMIFS(Appointments!$M$6:$M$2005,Appointments!$D$6:$D$2005,B41,Appointments!$O$6:$O$2005,1)))) | K41: =IF(B41="","",SUMIFS(Appointments!$I$6:$I$2005,Appointments!$D$6:$D$2005,B41)+SUMIFS(Packages!$F$6:$F$305,Packages!$C$6:$C$305,B41)) | L41: =IF(B41="","",IF(SUMIFS(Appointments!$K$6:$K$2005,Appointments!$D$6:$D$2005,B41)=0,"",SUMIFS(Appointments!$K$6:$K$2005,Appointments!$D$6:$D$2005,B41))) | M41: =IF(OR(B41="",SUMIFS(Packages!$E$6:$E$305,Packages!$C$6:$C$305,B41)=0),"",SUMIFS(Packages!$E$6:$E$305,Packages!$C$6:$C$305,B41)-COUNTIFS(Appointments!$D$6:$D$2005,B41,Appointments!$J$6:$J$2005,"Package",Appointments!$F$6:$F$2005,"Done")+IF(Services!$I$6="Yes",COUNTIFS(Appointments!$D$6:$D$2005,B41,Appointments!$J$6:$J$2005,"Package",Appointments!$F$6:$F$2005,"No-show"),0)) | N41: =IF(OR(B41="",I41=""),"",IF(AND(J41="",TODAY()-I41>=N(Services!$I$7)),"Not seen for "&(TODAY()-I41)&" days","")) | O41: =IF(N(E41)=0,"",MONTH(E41))
B42: Eva Mills | C42: 555 0236 | E42: 27969 | F42: 45980 | H42: =IF(B42="","",COUNTIFS(Appointments!$D$6:$D$2005,B42,Appointments!$F$6:$F$2005,"Done")) | I42: =IF(OR(B42="",N(H42)=0),"",INT(SUMIFS(Appointments!$M$6:$M$2005,Appointments!$D$6:$D$2005,B42,Appointments!$N$6:$N$2005,1))) | J42: =IF(B42="","",IF(SUMIFS(Appointments!$M$6:$M$2005,Appointments!$D$6:$D$2005,B42,Appointments!$O$6:$O$2005,1)=0,"",INT(SUMIFS(Appointments!$M$6:$M$2005,Appointments!$D$6:$D$2005,B42,Appointments!$O$6:$O$2005,1)))) | K42: =IF(B42="","",SUMIFS(Appointments!$I$6:$I$2005,Appointments!$D$6:$D$2005,B42)+SUMIFS(Packages!$F$6:$F$305,Packages!$C$6:$C$305,B42)) | L42: =IF(B42="","",IF(SUMIFS(Appointments!$K$6:$K$2005,Appointments!$D$6:$D$2005,B42)=0,"",SUMIFS(Appointments!$K$6:$K$2005,Appointments!$D$6:$D$2005,B42))) | M42: =IF(OR(B42="",SUMIFS(Packages!$E$6:$E$305,Packages!$C$6:$C$305,B42)=0),"",SUMIFS(Packages!$E$6:$E$305,Packages!$C$6:$C$305,B42)-COUNTIFS(Appointments!$D$6:$D$2005,B42,Appointments!$J$6:$J$2005,"Package",Appointments!$F$6:$F$2005,"Done")+IF(Services!$I$6="Yes",COUNTIFS(Appointments!$D$6:$D$2005,B42,Appointments!$J$6:$J$2005,"Package",Appointments!$F$6:$F$2005,"No-show"),0)) | N42: =IF(OR(B42="",I42=""),"",IF(AND(J42="",TODAY()-I42>=N(Services!$I$7)),"Not seen for "&(TODAY()-I42)&" days","")) | O42: =IF(N(E42)=0,"",MONTH(E42))
B43: Jade Hughes | C43: 555 0237 | E43: 38165 | F43: 45110 | H43: =IF(B43="","",COUNTIFS(Appointments!$D$6:$D$2005,B43,Appointments!$F$6:$F$2005,"Done")) | I43: =IF(OR(B43="",N(H43)=0),"",INT(SUMIFS(Appointments!$M$6:$M$2005,Appointments!$D$6:$D$2005,B43,Appointments!$N$6:$N$2005,1))) | J43: =IF(B43="","",IF(SUMIFS(Appointments!$M$6:$M$2005,Appointments!$D$6:$D$2005,B43,Appointments!$O$6:$O$2005,1)=0,"",INT(SUMIFS(Appointments!$M$6:$M$2005,Appointments!$D$6:$D$2005,B43,Appointments!$O$6:$O$2005,1)))) | K43: =IF(B43="","",SUMIFS(Appointments!$I$6:$I$2005,Appointments!$D$6:$D$2005,B43)+SUMIFS(Packages!$F$6:$F$305,Packages!$C$6:$C$305,B43)) | L43: =IF(B43="","",IF(SUMIFS(Appointments!$K$6:$K$2005,Appointments!$D$6:$D$2005,B43)=0,"",SUMIFS(Appointments!$K$6:$K$2005,Appointments!$D$6:$D$2005,B43))) | M43: =IF(OR(B43="",SUMIFS(Packages!$E$6:$E$305,Packages!$C$6:$C$305,B43)=0),"",SUMIFS(Packages!$E$6:$E$305,Packages!$C$6:$C$305,B43)-COUNTIFS(Appointments!$D$6:$D$2005,B43,Appointments!$J$6:$J$2005,"Package",Appointments!$F$6:$F$2005,"Done")+IF(Services!$I$6="Yes",COUNTIFS(Appointments!$D$6:$D$2005,B43,Appointments!$J$6:$J$2005,"Package",Appointments!$F$6:$F$2005,"No-show"),0)) | N43: =IF(OR(B43="",I43=""),"",IF(AND(J43="",TODAY()-I43>=N(Services!$I$7)),"Not seen for "&(TODAY()-I43)&" days","")) | O43: =IF(N(E43)=0,"",MONTH(E43))
B44: Amy Kelly | C44: 555 0238 | D44: amy.k@example.com | F44: 45874 | H44: =IF(B44="","",COUNTIFS(Appointments!$D$6:$D$2005,B44,Appointments!$F$6:$F$2005,"Done")) | I44: =IF(OR(B44="",N(H44)=0),"",INT(SUMIFS(Appointments!$M$6:$M$2005,Appointments!$D$6:$D$2005,B44,Appointments!$N$6:$N$2005,1))) | J44: =IF(B44="","",IF(SUMIFS(Appointments!$M$6:$M$2005,Appointments!$D$6:$D$2005,B44,Appointments!$O$6:$O$2005,1)=0,"",INT(SUMIFS(Appointments!$M$6:$M$2005,Appointments!$D$6:$D$2005,B44,Appointments!$O$6:$O$2005,1)))) | K44: =IF(B44="","",SUMIFS(Appointments!$I$6:$I$2005,Appointments!$D$6:$D$2005,B44)+SUMIFS(Packages!$F$6:$F$305,Packages!$C$6:$C$305,B44)) | L44: =IF(B44="","",IF(SUMIFS(Appointments!$K$6:$K$2005,Appointments!$D$6:$D$2005,B44)=0,"",SUMIFS(Appointments!$K$6:$K$2005,Appointments!$D$6:$D$2005,B44))) | M44: =IF(OR(B44="",SUMIFS(Packages!$E$6:$E$305,Packages!$C$6:$C$305,B44)=0),"",SUMIFS(Packages!$E$6:$E$305,Packages!$C$6:$C$305,B44)-COUNTIFS(Appointments!$D$6:$D$2005,B44,Appointments!$J$6:$J$2005,"Package",Appointments!$F$6:$F$2005,"Done")+IF(Services!$I$6="Yes",COUNTIFS(Appointments!$D$6:$D$2005,B44,Appointments!$J$6:$J$2005,"Package",Appointments!$F$6:$F$2005,"No-show"),0)) | N44: =IF(OR(B44="",I44=""),"",IF(AND(J44="",TODAY()-I44>=N(Services!$I$7)),"Not seen for "&(TODAY()-I44)&" days","")) | O44: =IF(N(E44)=0,"",MONTH(E44))
B45: Harry Ellis | C45: 555 0239 | E45: 27157 | F45: 45771 | H45: =IF(B45="","",COUNTIFS(Appointments!$D$6:$D$2005,B45,Appointments!$F$6:$F$2005,"Done")) | I45: =IF(OR(B45="",N(H45)=0),"",INT(SUMIFS(Appointments!$M$6:$M$2005,Appointments!$D$6:$D$2005,B45,Appointments!$N$6:$N$2005,1))) | J45: =IF(B45="","",IF(SUMIFS(Appointments!$M$6:$M$2005,Appointments!$D$6:$D$2005,B45,Appointments!$O$6:$O$2005,1)=0,"",INT(SUMIFS(Appointments!$M$6:$M$2005,Appointments!$D$6:$D$2005,B45,Appointments!$O$6:$O$2005,1)))) | K45: =IF(B45="","",SUMIFS(Appointments!$I$6:$I$2005,Appointments!$D$6:$D$2005,B45)+SUMIFS(Packages!$F$6:$F$305,Packages!$C$6:$C$305,B45)) | L45: =IF(B45="","",IF(SUMIFS(Appointments!$K$6:$K$2005,Appointments!$D$6:$D$2005,B45)=0,"",SUMIFS(Appointments!$K$6:$K$2005,Appointments!$D$6:$D$2005,B45))) | M45: =IF(OR(B45="",SUMIFS(Packages!$E$6:$E$305,Packages!$C$6:$C$305,B45)=0),"",SUMIFS(Packages!$E$6:$E$305,Packages!$C$6:$C$305,B45)-COUNTIFS(Appointments!$D$6:$D$2005,B45,Appointments!$J$6:$J$2005,"Package",Appointments!$F$6:$F$2005,"Done")+IF(Services!$I$6="Yes",COUNTIFS(Appointments!$D$6:$D$2005,B45,Appointments!$J$6:$J$2005,"Package",Appointments!$F$6:$F$2005,"No-show"),0)) | N45: =IF(OR(B45="",I45=""),"",IF(AND(J45="",TODAY()-I45>=N(Services!$I$7)),"Not seen for "&(TODAY()-I45)&" days","")) | O45: =IF(N(E45)=0,"",MONTH(E45))
B46: Leah Hill | C46: 555 0240 | F46: 45568 | H46: =IF(B46="","",COUNTIFS(Appointments!$D$6:$D$2005,B46,Appointments!$F$6:$F$2005,"Done")) | I46: =IF(OR(B46="",N(H46)=0),"",INT(SUMIFS(Appointments!$M$6:$M$2005,Appointments!$D$6:$D$2005,B46,Appointments!$N$6:$N$2005,1))) | J46: =IF(B46="","",IF(SUMIFS(Appointments!$M$6:$M$2005,Appointments!$D$6:$D$2005,B46,Appointments!$O$6:$O$2005,1)=0,"",INT(SUMIFS(Appointments!$M$6:$M$2005,Appointments!$D$6:$D$2005,B46,Appointments!$O$6:$O$2005,1)))) | K46: =IF(B46="","",SUMIFS(Appointments!$I$6:$I$2005,Appointments!$D$6:$D$2005,B46)+SUMIFS(Packages!$F$6:$F$305,Packages!$C$6:$C$305,B46)) | L46: =IF(B46="","",IF(SUMIFS(Appointments!$K$6:$K$2005,Appointments!$D$6:$D$2005,B46)=0,"",SUMIFS(Appointments!$K$6:$K$2005,Appointments!$D$6:$D$2005,B46))) | M46: =IF(OR(B46="",SUMIFS(Packages!$E$6:$E$305,Packages!$C$6:$C$305,B46)=0),"",SUMIFS(Packages!$E$6:$E$305,Packages!$C$6:$C$305,B46)-COUNTIFS(Appointments!$D$6:$D$2005,B46,Appointments!$J$6:$J$2005,"Package",Appointments!$F$6:$F$2005,"Done")+IF(Services!$I$6="Yes",COUNTIFS(Appointments!$D$6:$D$2005,B46,Appointments!$J$6:$J$2005,"Package",Appointments!$F$6:$F$2005,"No-show"),0)) | N46: =IF(OR(B46="",I46=""),"",IF(AND(J46="",TODAY()-I46>=N(Services!$I$7)),"Not seen for "&(TODAY()-I46)&" days","")) | O46: =IF(N(E46)=0,"",MONTH(E46))
B47: Lily Wood | C47: 555 0241 | E47: 33007 | F47: 45879 | H47: =IF(B47="","",COUNTIFS(Appointments!$D$6:$D$2005,B47,Appointments!$F$6:$F$2005,"Done")) | I47: =IF(OR(B47="",N(H47)=0),"",INT(SUMIFS(Appointments!$M$6:$M$2005,Appointments!$D$6:$D$2005,B47,Appointments!$N$6:$N$2005,1))) | J47: =IF(B47="","",IF(SUMIFS(Appointments!$M$6:$M$2005,Appointments!$D$6:$D$2005,B47,Appointments!$O$6:$O$2005,1)=0,"",INT(SUMIFS(Appointments!$M$6:$M$2005,Appointments!$D$6:$D$2005,B47,Appointments!$O$6:$O$2005,1)))) | K47: =IF(B47="","",SUMIFS(Appointments!$I$6:$I$2005,Appointments!$D$6:$D$2005,B47)+SUMIFS(Packages!$F$6:$F$305,Packages!$C$6:$C$305,B47)) | L47: =IF(B47="","",IF(SUMIFS(Appointments!$K$6:$K$2005,Appointments!$D$6:$D$2005,B47)=0,"",SUMIFS(Appointments!$K$6:$K$2005,Appointments!$D$6:$D$2005,B47))) | M47: =IF(OR(B47="",SUMIFS(Packages!$E$6:$E$305,Packages!$C$6:$C$305,B47)=0),"",SUMIFS(Packages!$E$6:$E$305,Packages!$C$6:$C$305,B47)-COUNTIFS(Appointments!$D$6:$D$2005,B47,Appointments!$J$6:$J$2005,"Package",Appointments!$F$6:$F$2005,"Done")+IF(Services!$I$6="Yes",COUNTIFS(Appointments!$D$6:$D$2005,B47,Appointments!$J$6:$J$2005,"Package",Appointments!$F$6:$F$2005,"No-show"),0)) | N47: =IF(OR(B47="",I47=""),"",IF(AND(J47="",TODAY()-I47>=N(Services!$I$7)),"Not seen for "&(TODAY()-I47)&" days","")) | O47: =IF(N(E47)=0,"",MONTH(E47))
B48: Tom Cole | C48: 555 0242 | D48: tom.c@example.com | F48: 45933 | H48: =IF(B48="","",COUNTIFS(Appointments!$D$6:$D$2005,B48,Appointments!$F$6:$F$2005,"Done")) | I48: =IF(OR(B48="",N(H48)=0),"",INT(SUMIFS(Appointments!$M$6:$M$2005,Appointments!$D$6:$D$2005,B48,Appointments!$N$6:$N$2005,1))) | J48: =IF(B48="","",IF(SUMIFS(Appointments!$M$6:$M$2005,Appointments!$D$6:$D$2005,B48,Appointments!$O$6:$O$2005,1)=0,"",INT(SUMIFS(Appointments!$M$6:$M$2005,Appointments!$D$6:$D$2005,B48,Appointments!$O$6:$O$2005,1)))) | K48: =IF(B48="","",SUMIFS(Appointments!$I$6:$I$2005,Appointments!$D$6:$D$2005,B48)+SUMIFS(Packages!$F$6:$F$305,Packages!$C$6:$C$305,B48)) | L48: =IF(B48="","",IF(SUMIFS(Appointments!$K$6:$K$2005,Appointments!$D$6:$D$2005,B48)=0,"",SUMIFS(Appointments!$K$6:$K$2005,Appointments!$D$6:$D$2005,B48))) | M48: =IF(OR(B48="",SUMIFS(Packages!$E$6:$E$305,Packages!$C$6:$C$305,B48)=0),"",SUMIFS(Packages!$E$6:$E$305,Packages!$C$6:$C$305,B48)-COUNTIFS(Appointments!$D$6:$D$2005,B48,Appointments!$J$6:$J$2005,"Package",Appointments!$F$6:$F$2005,"Done")+IF(Services!$I$6="Yes",COUNTIFS(Appointments!$D$6:$D$2005,B48,Appointments!$J$6:$J$2005,"Package",Appointments!$F$6:$F$2005,"No-show"),0)) | N48: =IF(OR(B48="",I48=""),"",IF(AND(J48="",TODAY()-I48>=N(Services!$I$7)),"Not seen for "&(TODAY()-I48)&" days","")) | O48: =IF(N(E48)=0,"",MONTH(E48))
B49: Will Baker | C49: 555 0243 | D49: will.b@example.com | F49: 44563 | H49: =IF(B49="","",COUNTIFS(Appointments!$D$6:$D$2005,B49,Appointments!$F$6:$F$2005,"Done")) | I49: =IF(OR(B49="",N(H49)=0),"",INT(SUMIFS(Appointments!$M$6:$M$2005,Appointments!$D$6:$D$2005,B49,Appointments!$N$6:$N$2005,1))) | J49: =IF(B49="","",IF(SUMIFS(Appointments!$M$6:$M$2005,Appointments!$D$6:$D$2005,B49,Appointments!$O$6:$O$2005,1)=0,"",INT(SUMIFS(Appointments!$M$6:$M$2005,Appointments!$D$6:$D$2005,B49,Appointments!$O$6:$O$2005,1)))) | K49: =IF(B49="","",SUMIFS(Appointments!$I$6:$I$2005,Appointments!$D$6:$D$2005,B49)+SUMIFS(Packages!$F$6:$F$305,Packages!$C$6:$C$305,B49)) | L49: =IF(B49="","",IF(SUMIFS(Appointments!$K$6:$K$2005,Appointments!$D$6:$D$2005,B49)=0,"",SUMIFS(Appointments!$K$6:$K$2005,Appointments!$D$6:$D$2005,B49))) | M49: =IF(OR(B49="",SUMIFS(Packages!$E$6:$E$305,Packages!$C$6:$C$305,B49)=0),"",SUMIFS(Packages!$E$6:$E$305,Packages!$C$6:$C$305,B49)-COUNTIFS(Appointments!$D$6:$D$2005,B49,Appointments!$J$6:$J$2005,"Package",Appointments!$F$6:$F$2005,"Done")+IF(Services!$I$6="Yes",COUNTIFS(Appointments!$D$6:$D$2005,B49,Appointments!$J$6:$J$2005,"Package",Appointments!$F$6:$F$2005,"No-show"),0)) | N49: =IF(OR(B49="",I49=""),"",IF(AND(J49="",TODAY()-I49>=N(Services!$I$7)),"Not seen for "&(TODAY()-I49)&" days","")) | O49: =IF(N(E49)=0,"",MONTH(E49))
B50: Fiona Price | C50: 555 0244 | F50: 44352 | H50: =IF(B50="","",COUNTIFS(Appointments!$D$6:$D$2005,B50,Appointments!$F$6:$F$2005,"Done")) | I50: =IF(OR(B50="",N(H50)=0),"",INT(SUMIFS(Appointments!$M$6:$M$2005,Appointments!$D$6:$D$2005,B50,Appointments!$N$6:$N$2005,1))) | J50: =IF(B50="","",IF(SUMIFS(Appointments!$M$6:$M$2005,Appointments!$D$6:$D$2005,B50,Appointments!$O$6:$O$2005,1)=0,"",INT(SUMIFS(Appointments!$M$6:$M$2005,Appointments!$D$6:$D$2005,B50,Appointments!$O$6:$O$2005,1)))) | K50: =IF(B50="","",SUMIFS(Appointments!$I$6:$I$2005,Appointments!$D$6:$D$2005,B50)+SUMIFS(Packages!$F$6:$F$305,Packages!$C$6:$C$305,B50)) | L50: =IF(B50="","",IF(SUMIFS(Appointments!$K$6:$K$2005,Appointments!$D$6:$D$2005,B50)=0,"",SUMIFS(Appointments!$K$6:$K$2005,Appointments!$D$6:$D$2005,B50))) | M50: =IF(OR(B50="",SUMIFS(Packages!$E$6:$E$305,Packages!$C$6:$C$305,B50)=0),"",SUMIFS(Packages!$E$6:$E$305,Packages!$C$6:$C$305,B50)-COUNTIFS(Appointments!$D$6:$D$2005,B50,Appointments!$J$6:$J$2005,"Package",Appointments!$F$6:$F$2005,"Done")+IF(Services!$I$6="Yes",COUNTIFS(Appointments!$D$6:$D$2005,B50,Appointments!$J$6:$J$2005,"Package",Appointments!$F$6:$F$2005,"No-show"),0)) | N50: =IF(OR(B50="",I50=""),"",IF(AND(J50="",TODAY()-I50>=N(Services!$I$7)),"Not seen for "&(TODAY()-I50)&" days","")) | O50: =IF(N(E50)=0,"",MONTH(E50))
B51: Nick Young | C51: 555 0245 | E51: 24488 | F51: 45270 | H51: =IF(B51="","",COUNTIFS(Appointments!$D$6:$D$2005,B51,Appointments!$F$6:$F$2005,"Done")) | I51: =IF(OR(B51="",N(H51)=0),"",INT(SUMIFS(Appointments!$M$6:$M$2005,Appointments!$D$6:$D$2005,B51,Appointments!$N$6:$N$2005,1))) | J51: =IF(B51="","",IF(SUMIFS(Appointments!$M$6:$M$2005,Appointments!$D$6:$D$2005,B51,Appointments!$O$6:$O$2005,1)=0,"",INT(SUMIFS(Appointments!$M$6:$M$2005,Appointments!$D$6:$D$2005,B51,Appointments!$O$6:$O$2005,1)))) | K51: =IF(B51="","",SUMIFS(Appointments!$I$6:$I$2005,Appointments!$D$6:$D$2005,B51)+SUMIFS(Packages!$F$6:$F$305,Packages!$C$6:$C$305,B51)) | L51: =IF(B51="","",IF(SUMIFS(Appointments!$K$6:$K$2005,Appointments!$D$6:$D$2005,B51)=0,"",SUMIFS(Appointments!$K$6:$K$2005,Appointments!$D$6:$D$2005,B51))) | M51: =IF(OR(B51="",SUMIFS(Packages!$E$6:$E$305,Packages!$C$6:$C$305,B51)=0),"",SUMIFS(Packages!$E$6:$E$305,Packages!$C$6:$C$305,B51)-COUNTIFS(Appointments!$D$6:$D$2005,B51,Appointments!$J$6:$J$2005,"Package",Appointments!$F$6:$F$2005,"Done")+IF(Services!$I$6="Yes",COUNTIFS(Appointments!$D$6:$D$2005,B51,Appointments!$J$6:$J$2005,"Package",Appointments!$F$6:$F$2005,"No-show"),0)) | N51: =IF(OR(B51="",I51=""),"",IF(AND(J51="",TODAY()-I51>=N(Services!$I$7)),"Not seen for "&(TODAY()-I51)&" days","")) | O51: =IF(N(E51)=0,"",MONTH(E51))
B52: Mia Cole | C52: 555 0246 | F52: 44988 | H52: =IF(B52="","",COUNTIFS(Appointments!$D$6:$D$2005,B52,Appointments!$F$6:$F$2005,"Done")) | I52: =IF(OR(B52="",N(H52)=0),"",INT(SUMIFS(Appointments!$M$6:$M$2005,Appointments!$D$6:$D$2005,B52,Appointments!$N$6:$N$2005,1))) | J52: =IF(B52="","",IF(SUMIFS(Appointments!$M$6:$M$2005,Appointments!$D$6:$D$2005,B52,Appointments!$O$6:$O$2005,1)=0,"",INT(SUMIFS(Appointments!$M$6:$M$2005,Appointments!$D$6:$D$2005,B52,Appointments!$O$6:$O$2005,1)))) | K52: =IF(B52="","",SUMIFS(Appointments!$I$6:$I$2005,Appointments!$D$6:$D$2005,B52)+SUMIFS(Packages!$F$6:$F$305,Packages!$C$6:$C$305,B52)) | L52: =IF(B52="","",IF(SUMIFS(Appointments!$K$6:$K$2005,Appointments!$D$6:$D$2005,B52)=0,"",SUMIFS(Appointments!$K$6:$K$2005,Appointments!$D$6:$D$2005,B52))) | M52: =IF(OR(B52="",SUMIFS(Packages!$E$6:$E$305,Packages!$C$6:$C$305,B52)=0),"",SUMIFS(Packages!$E$6:$E$305,Packages!$C$6:$C$305,B52)-COUNTIFS(Appointments!$D$6:$D$2005,B52,Appointments!$J$6:$J$2005,"Package",Appointments!$F$6:$F$2005,"Done")+IF(Services!$I$6="Yes",COUNTIFS(Appointments!$D$6:$D$2005,B52,Appointments!$J$6:$J$2005,"Package",Appointments!$F$6:$F$2005,"No-show"),0)) | N52: =IF(OR(B52="",I52=""),"",IF(AND(J52="",TODAY()-I52>=N(Services!$I$7)),"Not seen for "&(TODAY()-I52)&" days","")) | O52: =IF(N(E52)=0,"",MONTH(E52))
B53: Finn Price | C53: 555 0247 | F53: 44724 | H53: =IF(B53="","",COUNTIFS(Appointments!$D$6:$D$2005,B53,Appointments!$F$6:$F$2005,"Done")) | I53: =IF(OR(B53="",N(H53)=0),"",INT(SUMIFS(Appointments!$M$6:$M$2005,Appointments!$D$6:$D$2005,B53,Appointments!$N$6:$N$2005,1))) | J53: =IF(B53="","",IF(SUMIFS(Appointments!$M$6:$M$2005,Appointments!$D$6:$D$2005,B53,Appointments!$O$6:$O$2005,1)=0,"",INT(SUMIFS(Appointments!$M$6:$M$2005,Appointments!$D$6:$D$2005,B53,Appointments!$O$6:$O$2005,1)))) | K53: =IF(B53="","",SUMIFS(Appointments!$I$6:$I$2005,Appointments!$D$6:$D$2005,B53)+SUMIFS(Packages!$F$6:$F$305,Packages!$C$6:$C$305,B53)) | L53: =IF(B53="","",IF(SUMIFS(Appointments!$K$6:$K$2005,Appointments!$D$6:$D$2005,B53)=0,"",SUMIFS(Appointments!$K$6:$K$2005,Appointments!$D$6:$D$2005,B53))) | M53: =IF(OR(B53="",SUMIFS(Packages!$E$6:$E$305,Packages!$C$6:$C$305,B53)=0),"",SUMIFS(Packages!$E$6:$E$305,Packages!$C$6:$C$305,B53)-COUNTIFS(Appointments!$D$6:$D$2005,B53,Appointments!$J$6:$J$2005,"Package",Appointments!$F$6:$F$2005,"Done")+IF(Services!$I$6="Yes",COUNTIFS(Appointments!$D$6:$D$2005,B53,Appointments!$J$6:$J$2005,"Package",Appointments!$F$6:$F$2005,"No-show"),0)) | N53: =IF(OR(B53="",I53=""),"",IF(AND(J53="",TODAY()-I53>=N(Services!$I$7)),"Not seen for "&(TODAY()-I53)&" days","")) | O53: =IF(N(E53)=0,"",MONTH(E53))
B54: Owen Webb | C54: 555 0248 | F54: 45319 | H54: =IF(B54="","",COUNTIFS(Appointments!$D$6:$D$2005,B54,Appointments!$F$6:$F$2005,"Done")) | I54: =IF(OR(B54="",N(H54)=0),"",INT(SUMIFS(Appointments!$M$6:$M$2005,Appointments!$D$6:$D$2005,B54,Appointments!$N$6:$N$2005,1))) | J54: =IF(B54="","",IF(SUMIFS(Appointments!$M$6:$M$2005,Appointments!$D$6:$D$2005,B54,Appointments!$O$6:$O$2005,1)=0,"",INT(SUMIFS(Appointments!$M$6:$M$2005,Appointments!$D$6:$D$2005,B54,Appointments!$O$6:$O$2005,1)))) | K54: =IF(B54="","",SUMIFS(Appointments!$I$6:$I$2005,Appointments!$D$6:$D$2005,B54)+SUMIFS(Packages!$F$6:$F$305,Packages!$C$6:$C$305,B54)) | L54: =IF(B54="","",IF(SUMIFS(Appointments!$K$6:$K$2005,Appointments!$D$6:$D$2005,B54)=0,"",SUMIFS(Appointments!$K$6:$K$2005,Appointments!$D$6:$D$2005,B54))) | M54: =IF(OR(B54="",SUMIFS(Packages!$E$6:$E$305,Packages!$C$6:$C$305,B54)=0),"",SUMIFS(Packages!$E$6:$E$305,Packages!$C$6:$C$305,B54)-COUNTIFS(Appointments!$D$6:$D$2005,B54,Appointments!$J$6:$J$2005,"Package",Appointments!$F$6:$F$2005,"Done")+IF(Services!$I$6="Yes",COUNTIFS(Appointments!$D$6:$D$2005,B54,Appointments!$J$6:$J$2005,"Package",Appointments!$F$6:$F$2005,"No-show"),0)) | N54: =IF(OR(B54="",I54=""),"",IF(AND(J54="",TODAY()-I54>=N(Services!$I$7)),"Not seen for "&(TODAY()-I54)&" days","")) | O54: =IF(N(E54)=0,"",MONTH(E54))
B55: Harry Adams | C55: 555 0249 | F55: 45677 | H55: =IF(B55="","",COUNTIFS(Appointments!$D$6:$D$2005,B55,Appointments!$F$6:$F$2005,"Done")) | I55: =IF(OR(B55="",N(H55)=0),"",INT(SUMIFS(Appointments!$M$6:$M$2005,Appointments!$D$6:$D$2005,B55,Appointments!$N$6:$N$2005,1))) | J55: =IF(B55="","",IF(SUMIFS(Appointments!$M$6:$M$2005,Appointments!$D$6:$D$2005,B55,Appointments!$O$6:$O$2005,1)=0,"",INT(SUMIFS(Appointments!$M$6:$M$2005,Appointments!$D$6:$D$2005,B55,Appointments!$O$6:$O$2005,1)))) | K55: =IF(B55="","",SUMIFS(Appointments!$I$6:$I$2005,Appointments!$D$6:$D$2005,B55)+SUMIFS(Packages!$F$6:$F$305,Packages!$C$6:$C$305,B55)) | L55: =IF(B55="","",IF(SUMIFS(Appointments!$K$6:$K$2005,Appointments!$D$6:$D$2005,B55)=0,"",SUMIFS(Appointments!$K$6:$K$2005,Appointments!$D$6:$D$2005,B55))) | M55: =IF(OR(B55="",SUMIFS(Packages!$E$6:$E$305,Packages!$C$6:$C$305,B55)=0),"",SUMIFS(Packages!$E$6:$E$305,Packages!$C$6:$C$305,B55)-COUNTIFS(Appointments!$D$6:$D$2005,B55,Appointments!$J$6:$J$2005,"Package",Appointments!$F$6:$F$2005,"Done")+IF(Services!$I$6="Yes",COUNTIFS(Appointments!$D$6:$D$2005,B55,Appointments!$J$6:$J$2005,"Package",Appointments!$F$6:$F$2005,"No-show"),0)) | N55: =IF(OR(B55="",I55=""),"",IF(AND(J55="",TODAY()-I55>=N(Services!$I$7)),"Not seen for "&(TODAY()-I55)&" days","")) | O55: =IF(N(E55)=0,"",MONTH(E55))
B56: Ruby Cook | C56: 555 0250 | F56: 45637 | H56: =IF(B56="","",COUNTIFS(Appointments!$D$6:$D$2005,B56,Appointments!$F$6:$F$2005,"Done")) | I56: =IF(OR(B56="",N(H56)=0),"",INT(SUMIFS(Appointments!$M$6:$M$2005,Appointments!$D$6:$D$2005,B56,Appointments!$N$6:$N$2005,1))) | J56: =IF(B56="","",IF(SUMIFS(Appointments!$M$6:$M$2005,Appointments!$D$6:$D$2005,B56,Appointments!$O$6:$O$2005,1)=0,"",INT(SUMIFS(Appointments!$M$6:$M$2005,Appointments!$D$6:$D$2005,B56,Appointments!$O$6:$O$2005,1)))) | K56: =IF(B56="","",SUMIFS(Appointments!$I$6:$I$2005,Appointments!$D$6:$D$2005,B56)+SUMIFS(Packages!$F$6:$F$305,Packages!$C$6:$C$305,B56)) | L56: =IF(B56="","",IF(SUMIFS(Appointments!$K$6:$K$2005,Appointments!$D$6:$D$2005,B56)=0,"",SUMIFS(Appointments!$K$6:$K$2005,Appointments!$D$6:$D$2005,B56))) | M56: =IF(OR(B56="",SUMIFS(Packages!$E$6:$E$305,Packages!$C$6:$C$305,B56)=0),"",SUMIFS(Packages!$E$6:$E$305,Packages!$C$6:$C$305,B56)-COUNTIFS(Appointments!$D$6:$D$2005,B56,Appointments!$J$6:$J$2005,"Package",Appointments!$F$6:$F$2005,"Done")+IF(Services!$I$6="Yes",COUNTIFS(Appointments!$D$6:$D$2005,B56,Appointments!$J$6:$J$2005,"Package",Appointments!$F$6:$F$2005,"No-show"),0)) | N56: =IF(OR(B56="",I56=""),"",IF(AND(J56="",TODAY()-I56>=N(Services!$I$7)),"Not seen for "&(TODAY()-I56)&" days","")) | O56: =IF(N(E56)=0,"",MONTH(E56))
B57: Tina Walsh | C57: 555 0251 | F57: 45901 | H57: =IF(B57="","",COUNTIFS(Appointments!$D$6:$D$2005,B57,Appointments!$F$6:$F$2005,"Done")) | I57: =IF(OR(B57="",N(H57)=0),"",INT(SUMIFS(Appointments!$M$6:$M$2005,Appointments!$D$6:$D$2005,B57,Appointments!$N$6:$N$2005,1))) | J57: =IF(B57="","",IF(SUMIFS(Appointments!$M$6:$M$2005,Appointments!$D$6:$D$2005,B57,Appointments!$O$6:$O$2005,1)=0,"",INT(SUMIFS(Appointments!$M$6:$M$2005,Appointments!$D$6:$D$2005,B57,Appointments!$O$6:$O$2005,1)))) | K57: =IF(B57="","",SUMIFS(Appointments!$I$6:$I$2005,Appointments!$D$6:$D$2005,B57)+SUMIFS(Packages!$F$6:$F$305,Packages!$C$6:$C$305,B57)) | L57: =IF(B57="","",IF(SUMIFS(Appointments!$K$6:$K$2005,Appointments!$D$6:$D$2005,B57)=0,"",SUMIFS(Appointments!$K$6:$K$2005,Appointments!$D$6:$D$2005,B57))) | M57: =IF(OR(B57="",SUMIFS(Packages!$E$6:$E$305,Packages!$C$6:$C$305,B57)=0),"",SUMIFS(Packages!$E$6:$E$305,Packages!$C$6:$C$305,B57)-COUNTIFS(Appointments!$D$6:$D$2005,B57,Appointments!$J$6:$J$2005,"Package",Appointments!$F$6:$F$2005,"Done")+IF(Services!$I$6="Yes",COUNTIFS(Appointments!$D$6:$D$2005,B57,Appointments!$J$6:$J$2005,"Package",Appointments!$F$6:$F$2005,"No-show"),0)) | N57: =IF(OR(B57="",I57=""),"",IF(AND(J57="",TODAY()-I57>=N(Services!$I$7)),"Not seen for "&(TODAY()-I57)&" days","")) | O57: =IF(N(E57)=0,"",MONTH(E57))
B58: Ruby Webb | C58: 555 0252 | D58: ruby.w@example.com | F58: 44433 | H58: =IF(B58="","",COUNTIFS(Appointments!$D$6:$D$2005,B58,Appointments!$F$6:$F$2005,"Done")) | I58: =IF(OR(B58="",N(H58)=0),"",INT(SUMIFS(Appointments!$M$6:$M$2005,Appointments!$D$6:$D$2005,B58,Appointments!$N$6:$N$2005,1))) | J58: =IF(B58="","",IF(SUMIFS(Appointments!$M$6:$M$2005,Appointments!$D$6:$D$2005,B58,Appointments!$O$6:$O$2005,1)=0,"",INT(SUMIFS(Appointments!$M$6:$M$2005,Appointments!$D$6:$D$2005,B58,Appointments!$O$6:$O$2005,1)))) | K58: =IF(B58="","",SUMIFS(Appointments!$I$6:$I$2005,Appointments!$D$6:$D$2005,B58)+SUMIFS(Packages!$F$6:$F$305,Packages!$C$6:$C$305,B58)) | L58: =IF(B58="","",IF(SUMIFS(Appointments!$K$6:$K$2005,Appointments!$D$6:$D$2005,B58)=0,"",SUMIFS(Appointments!$K$6:$K$2005,Appointments!$D$6:$D$2005,B58))) | M58: =IF(OR(B58="",SUMIFS(Packages!$E$6:$E$305,Packages!$C$6:$C$305,B58)=0),"",SUMIFS(Packages!$E$6:$E$305,Packages!$C$6:$C$305,B58)-COUNTIFS(Appointments!$D$6:$D$2005,B58,Appointments!$J$6:$J$2005,"Package",Appointments!$F$6:$F$2005,"Done")+IF(Services!$I$6="Yes",COUNTIFS(Appointments!$D$6:$D$2005,B58,Appointments!$J$6:$J$2005,"Package",Appointments!$F$6:$F$2005,"No-show"),0)) | N58: =IF(OR(B58="",I58=""),"",IF(AND(J58="",TODAY()-I58>=N(Services!$I$7)),"Not seen for "&(TODAY()-I58)&" days","")) | O58: =IF(N(E58)=0,"",MONTH(E58))
B59: Dina Adams | C59: 555 0253 | D59: dina.a@example.com | E59: 38094 | F59: 44734 | H59: =IF(B59="","",COUNTIFS(Appointments!$D$6:$D$2005,B59,Appointments!$F$6:$F$2005,"Done")) | I59: =IF(OR(B59="",N(H59)=0),"",INT(SUMIFS(Appointments!$M$6:$M$2005,Appointments!$D$6:$D$2005,B59,Appointments!$N$6:$N$2005,1))) | J59: =IF(B59="","",IF(SUMIFS(Appointments!$M$6:$M$2005,Appointments!$D$6:$D$2005,B59,Appointments!$O$6:$O$2005,1)=0,"",INT(SUMIFS(Appointments!$M$6:$M$2005,Appointments!$D$6:$D$2005,B59,Appointments!$O$6:$O$2005,1)))) | K59: =IF(B59="","",SUMIFS(Appointments!$I$6:$I$2005,Appointments!$D$6:$D$2005,B59)+SUMIFS(Packages!$F$6:$F$305,Packages!$C$6:$C$305,B59)) | L59: =IF(B59="","",IF(SUMIFS(Appointments!$K$6:$K$2005,Appointments!$D$6:$D$2005,B59)=0,"",SUMIFS(Appointments!$K$6:$K$2005,Appointments!$D$6:$D$2005,B59))) | M59: =IF(OR(B59="",SUMIFS(Packages!$E$6:$E$305,Packages!$C$6:$C$305,B59)=0),"",SUMIFS(Packages!$E$6:$E$305,Packages!$C$6:$C$305,B59)-COUNTIFS(Appointments!$D$6:$D$2005,B59,Appointments!$J$6:$J$2005,"Package",Appointments!$F$6:$F$2005,"Done")+IF(Services!$I$6="Yes",COUNTIFS(Appointments!$D$6:$D$2005,B59,Appointments!$J$6:$J$2005,"Package",Appointments!$F$6:$F$2005,"No-show"),0)) | N59: =IF(OR(B59="",I59=""),"",IF(AND(J59="",TODAY()-I59>=N(Services!$I$7)),"Not seen for "&(TODAY()-I59)&" days","")) | O59: =IF(N(E59)=0,"",MONTH(E59))
B60: Clara Morgan | C60: 555 0254 | E60: 33701 | F60: 45401 | H60: =IF(B60="","",COUNTIFS(Appointments!$D$6:$D$2005,B60,Appointments!$F$6:$F$2005,"Done")) | I60: =IF(OR(B60="",N(H60)=0),"",INT(SUMIFS(Appointments!$M$6:$M$2005,Appointments!$D$6:$D$2005,B60,Appointments!$N$6:$N$2005,1))) | J60: =IF(B60="","",IF(SUMIFS(Appointments!$M$6:$M$2005,Appointments!$D$6:$D$2005,B60,Appointments!$O$6:$O$2005,1)=0,"",INT(SUMIFS(Appointments!$M$6:$M$2005,Appointments!$D$6:$D$2005,B60,Appointments!$O$6:$O$2005,1)))) | K60: =IF(B60="","",SUMIFS(Appointments!$I$6:$I$2005,Appointments!$D$6:$D$2005,B60)+SUMIFS(Packages!$F$6:$F$305,Packages!$C$6:$C$305,B60)) | L60: =IF(B60="","",IF(SUMIFS(Appointments!$K$6:$K$2005,Appointments!$D$6:$D$2005,B60)=0,"",SUMIFS(Appointments!$K$6:$K$2005,Appointments!$D$6:$D$2005,B60))) | M60: =IF(OR(B60="",SUMIFS(Packages!$E$6:$E$305,Packages!$C$6:$C$305,B60)=0),"",SUMIFS(Packages!$E$6:$E$305,Packages!$C$6:$C$305,B60)-COUNTIFS(Appointments!$D$6:$D$2005,B60,Appointments!$J$6:$J$2005,"Package",Appointments!$F$6:$F$2005,"Done")+IF(Services!$I$6="Yes",COUNTIFS(Appointments!$D$6:$D$2005,B60,Appointments!$J$6:$J$2005,"Package",Appointments!$F$6:$F$2005,"No-show"),0)) | N60: =IF(OR(B60="",I60=""),"",IF(AND(J60="",TODAY()-I60>=N(Services!$I$7)),"Not seen for "&(TODAY()-I60)&" days","")) | O60: =IF(N(E60)=0,"",MONTH(E60))
B61: Hannah Ellis | C61: 555 0255 | F61: 44533 | H61: =IF(B61="","",COUNTIFS(Appointments!$D$6:$D$2005,B61,Appointments!$F$6:$F$2005,"Done")) | I61: =IF(OR(B61="",N(H61)=0),"",INT(SUMIFS(Appointments!$M$6:$M$2005,Appointments!$D$6:$D$2005,B61,Appointments!$N$6:$N$2005,1))) | J61: =IF(B61="","",IF(SUMIFS(Appointments!$M$6:$M$2005,Appointments!$D$6:$D$2005,B61,Appointments!$O$6:$O$2005,1)=0,"",INT(SUMIFS(Appointments!$M$6:$M$2005,Appointments!$D$6:$D$2005,B61,Appointments!$O$6:$O$2005,1)))) | K61: =IF(B61="","",SUMIFS(Appointments!$I$6:$I$2005,Appointments!$D$6:$D$2005,B61)+SUMIFS(Packages!$F$6:$F$305,Packages!$C$6:$C$305,B61)) | L61: =IF(B61="","",IF(SUMIFS(Appointments!$K$6:$K$2005,Appointments!$D$6:$D$2005,B61)=0,"",SUMIFS(Appointments!$K$6:$K$2005,Appointments!$D$6:$D$2005,B61))) | M61: =IF(OR(B61="",SUMIFS(Packages!$E$6:$E$305,Packages!$C$6:$C$305,B61)=0),"",SUMIFS(Packages!$E$6:$E$305,Packages!$C$6:$C$305,B61)-COUNTIFS(Appointments!$D$6:$D$2005,B61,Appointments!$J$6:$J$2005,"Package",Appointments!$F$6:$F$2005,"Done")+IF(Services!$I$6="Yes",COUNTIFS(Appointments!$D$6:$D$2005,B61,Appointments!$J$6:$J$2005,"Package",Appointments!$F$6:$F$2005,"No-show"),0)) | N61: =IF(OR(B61="",I61=""),"",IF(AND(J61="",TODAY()-I61>=N(Services!$I$7)),"Not seen for "&(TODAY()-I61)&" days","")) | O61: =IF(N(E61)=0,"",MONTH(E61))
B62: Nora Walsh | C62: 555 0256 | F62: 45494 | H62: =IF(B62="","",COUNTIFS(Appointments!$D$6:$D$2005,B62,Appointments!$F$6:$F$2005,"Done")) | I62: =IF(OR(B62="",N(H62)=0),"",INT(SUMIFS(Appointments!$M$6:$M$2005,Appointments!$D$6:$D$2005,B62,Appointments!$N$6:$N$2005,1))) | J62: =IF(B62="","",IF(SUMIFS(Appointments!$M$6:$M$2005,Appointments!$D$6:$D$2005,B62,Appointments!$O$6:$O$2005,1)=0,"",INT(SUMIFS(Appointments!$M$6:$M$2005,Appointments!$D$6:$D$2005,B62,Appointments!$O$6:$O$2005,1)))) | K62: =IF(B62="","",SUMIFS(Appointments!$I$6:$I$2005,Appointments!$D$6:$D$2005,B62)+SUMIFS(Packages!$F$6:$F$305,Packages!$C$6:$C$305,B62)) | L62: =IF(B62="","",IF(SUMIFS(Appointments!$K$6:$K$2005,Appointments!$D$6:$D$2005,B62)=0,"",SUMIFS(Appointments!$K$6:$K$2005,Appointments!$D$6:$D$2005,B62))) | M62: =IF(OR(B62="",SUMIFS(Packages!$E$6:$E$305,Packages!$C$6:$C$305,B62)=0),"",SUMIFS(Packages!$E$6:$E$305,Packages!$C$6:$C$305,B62)-COUNTIFS(Appointments!$D$6:$D$2005,B62,Appointments!$J$6:$J$2005,"Package",Appointments!$F$6:$F$2005,"Done")+IF(Services!$I$6="Yes",COUNTIFS(Appointments!$D$6:$D$2005,B62,Appointments!$J$6:$J$2005,"Package",Appointments!$F$6:$F$2005,"No-show"),0)) | N62: =IF(OR(B62="",I62=""),"",IF(AND(J62="",TODAY()-I62>=N(Services!$I$7)),"Not seen for "&(TODAY()-I62)&" days","")) | O62: =IF(N(E62)=0,"",MONTH(E62))
B63: Owen Morgan | C63: 555 0257 | F63: 45880 | H63: =IF(B63="","",COUNTIFS(Appointments!$D$6:$D$2005,B63,Appointments!$F$6:$F$2005,"Done")) | I63: =IF(OR(B63="",N(H63)=0),"",INT(SUMIFS(Appointments!$M$6:$M$2005,Appointments!$D$6:$D$2005,B63,Appointments!$N$6:$N$2005,1))) | J63: =IF(B63="","",IF(SUMIFS(Appointments!$M$6:$M$2005,Appointments!$D$6:$D$2005,B63,Appointments!$O$6:$O$2005,1)=0,"",INT(SUMIFS(Appointments!$M$6:$M$2005,Appointments!$D$6:$D$2005,B63,Appointments!$O$6:$O$2005,1)))) | K63: =IF(B63="","",SUMIFS(Appointments!$I$6:$I$2005,Appointments!$D$6:$D$2005,B63)+SUMIFS(Packages!$F$6:$F$305,Packages!$C$6:$C$305,B63)) | L63: =IF(B63="","",IF(SUMIFS(Appointments!$K$6:$K$2005,Appointments!$D$6:$D$2005,B63)=0,"",SUMIFS(Appointments!$K$6:$K$2005,Appointments!$D$6:$D$2005,B63))) | M63: =IF(OR(B63="",SUMIFS(Packages!$E$6:$E$305,Packages!$C$6:$C$305,B63)=0),"",SUMIFS(Packages!$E$6:$E$305,Packages!$C$6:$C$305,B63)-COUNTIFS(Appointments!$D$6:$D$2005,B63,Appointments!$J$6:$J$2005,"Package",Appointments!$F$6:$F$2005,"Done")+IF(Services!$I$6="Yes",COUNTIFS(Appointments!$D$6:$D$2005,B63,Appointments!$J$6:$J$2005,"Package",Appointments!$F$6:$F$2005,"No-show"),0)) | N63: =IF(OR(B63="",I63=""),"",IF(AND(J63="",TODAY()-I63>=N(Services!$I$7)),"Not seen for "&(TODAY()-I63)&" days","")) | O63: =IF(N(E63)=0,"",MONTH(E63))
B64: Lily Lewis | C64: 555 0258 | E64: 30236 | F64: 45256 | H64: =IF(B64="","",COUNTIFS(Appointments!$D$6:$D$2005,B64,Appointments!$F$6:$F$2005,"Done")) | I64: =IF(OR(B64="",N(H64)=0),"",INT(SUMIFS(Appointments!$M$6:$M$2005,Appointments!$D$6:$D$2005,B64,Appointments!$N$6:$N$2005,1))) | J64: =IF(B64="","",IF(SUMIFS(Appointments!$M$6:$M$2005,Appointments!$D$6:$D$2005,B64,Appointments!$O$6:$O$2005,1)=0,"",INT(SUMIFS(Appointments!$M$6:$M$2005,Appointments!$D$6:$D$2005,B64,Appointments!$O$6:$O$2005,1)))) | K64: =IF(B64="","",SUMIFS(Appointments!$I$6:$I$2005,Appointments!$D$6:$D$2005,B64)+SUMIFS(Packages!$F$6:$F$305,Packages!$C$6:$C$305,B64)) | L64: =IF(B64="","",IF(SUMIFS(Appointments!$K$6:$K$2005,Appointments!$D$6:$D$2005,B64)=0,"",SUMIFS(Appointments!$K$6:$K$2005,Appointments!$D$6:$D$2005,B64))) | M64: =IF(OR(B64="",SUMIFS(Packages!$E$6:$E$305,Packages!$C$6:$C$305,B64)=0),"",SUMIFS(Packages!$E$6:$E$305,Packages!$C$6:$C$305,B64)-COUNTIFS(Appointments!$D$6:$D$2005,B64,Appointments!$J$6:$J$2005,"Package",Appointments!$F$6:$F$2005,"Done")+IF(Services!$I$6="Yes",COUNTIFS(Appointments!$D$6:$D$2005,B64,Appointments!$J$6:$J$2005,"Package",Appointments!$F$6:$F$2005,"No-show"),0)) | N64: =IF(OR(B64="",I64=""),"",IF(AND(J64="",TODAY()-I64>=N(Services!$I$7)),"Not seen for "&(TODAY()-I64)&" days","")) | O64: =IF(N(E64)=0,"",MONTH(E64))
B65: Matt Ellis | C65: 555 0259 | E65: 30066 | F65: 44582 | H65: =IF(B65="","",COUNTIFS(Appointments!$D$6:$D$2005,B65,Appointments!$F$6:$F$2005,"Done")) | I65: =IF(OR(B65="",N(H65)=0),"",INT(SUMIFS(Appointments!$M$6:$M$2005,Appointments!$D$6:$D$2005,B65,Appointments!$N$6:$N$2005,1))) | J65: =IF(B65="","",IF(SUMIFS(Appointments!$M$6:$M$2005,Appointments!$D$6:$D$2005,B65,Appointments!$O$6:$O$2005,1)=0,"",INT(SUMIFS(Appointments!$M$6:$M$2005,Appointments!$D$6:$D$2005,B65,Appointments!$O$6:$O$2005,1)))) | K65: =IF(B65="","",SUMIFS(Appointments!$I$6:$I$2005,Appointments!$D$6:$D$2005,B65)+SUMIFS(Packages!$F$6:$F$305,Packages!$C$6:$C$305,B65)) | L65: =IF(B65="","",IF(SUMIFS(Appointments!$K$6:$K$2005,Appointments!$D$6:$D$2005,B65)=0,"",SUMIFS(Appointments!$K$6:$K$2005,Appointments!$D$6:$D$2005,B65))) | M65: =IF(OR(B65="",SUMIFS(Packages!$E$6:$E$305,Packages!$C$6:$C$305,B65)=0),"",SUMIFS(Packages!$E$6:$E$305,Packages!$C$6:$C$305,B65)-COUNTIFS(Appointments!$D$6:$D$2005,B65,Appointments!$J$6:$J$2005,"Package",Appointments!$F$6:$F$2005,"Done")+IF(Services!$I$6="Yes",COUNTIFS(Appointments!$D$6:$D$2005,B65,Appointments!$J$6:$J$2005,"Package",Appointments!$F$6:$F$2005,"No-show"),0)) | N65: =IF(OR(B65="",I65=""),"",IF(AND(J65="",TODAY()-I65>=N(Services!$I$7)),"Not seen for "&(TODAY()-I65)&" days","")) | O65: =IF(N(E65)=0,"",MONTH(E65))
B66: Sara Cox | C66: 555 0260 | F66: 44979 | H66: =IF(B66="","",COUNTIFS(Appointments!$D$6:$D$2005,B66,Appointments!$F$6:$F$2005,"Done")) | I66: =IF(OR(B66="",N(H66)=0),"",INT(SUMIFS(Appointments!$M$6:$M$2005,Appointments!$D$6:$D$2005,B66,Appointments!$N$6:$N$2005,1))) | J66: =IF(B66="","",IF(SUMIFS(Appointments!$M$6:$M$2005,Appointments!$D$6:$D$2005,B66,Appointments!$O$6:$O$2005,1)=0,"",INT(SUMIFS(Appointments!$M$6:$M$2005,Appointments!$D$6:$D$2005,B66,Appointments!$O$6:$O$2005,1)))) | K66: =IF(B66="","",SUMIFS(Appointments!$I$6:$I$2005,Appointments!$D$6:$D$2005,B66)+SUMIFS(Packages!$F$6:$F$305,Packages!$C$6:$C$305,B66)) | L66: =IF(B66="","",IF(SUMIFS(Appointments!$K$6:$K$2005,Appointments!$D$6:$D$2005,B66)=0,"",SUMIFS(Appointments!$K$6:$K$2005,Appointments!$D$6:$D$2005,B66))) | M66: =IF(OR(B66="",SUMIFS(Packages!$E$6:$E$305,Packages!$C$6:$C$305,B66)=0),"",SUMIFS(Packages!$E$6:$E$305,Packages!$C$6:$C$305,B66)-COUNTIFS(Appointments!$D$6:$D$2005,B66,Appointments!$J$6:$J$2005,"Package",Appointments!$F$6:$F$2005,"Done")+IF(Services!$I$6="Yes",COUNTIFS(Appointments!$D$6:$D$2005,B66,Appointments!$J$6:$J$2005,"Package",Appointments!$F$6:$F$2005,"No-show"),0)) | N66: =IF(OR(B66="",I66=""),"",IF(AND(J66="",TODAY()-I66>=N(Services!$I$7)),"Not seen for "&(TODAY()-I66)&" days","")) | O66: =IF(N(E66)=0,"",MONTH(E66))
B67: Adam King | C67: 555 0261 | D67: adam.k@example.com | E67: 34965 | F67: 44263 | H67: =IF(B67="","",COUNTIFS(Appointments!$D$6:$D$2005,B67,Appointments!$F$6:$F$2005,"Done")) | I67: =IF(OR(B67="",N(H67)=0),"",INT(SUMIFS(Appointments!$M$6:$M$2005,Appointments!$D$6:$D$2005,B67,Appointments!$N$6:$N$2005,1))) | J67: =IF(B67="","",IF(SUMIFS(Appointments!$M$6:$M$2005,Appointments!$D$6:$D$2005,B67,Appointments!$O$6:$O$2005,1)=0,"",INT(SUMIFS(Appointments!$M$6:$M$2005,Appointments!$D$6:$D$2005,B67,Appointments!$O$6:$O$2005,1)))) | K67: =IF(B67="","",SUMIFS(Appointments!$I$6:$I$2005,Appointments!$D$6:$D$2005,B67)+SUMIFS(Packages!$F$6:$F$305,Packages!$C$6:$C$305,B67)) | L67: =IF(B67="","",IF(SUMIFS(Appointments!$K$6:$K$2005,Appointments!$D$6:$D$2005,B67)=0,"",SUMIFS(Appointments!$K$6:$K$2005,Appointments!$D$6:$D$2005,B67))) | M67: =IF(OR(B67="",SUMIFS(Packages!$E$6:$E$305,Packages!$C$6:$C$305,B67)=0),"",SUMIFS(Packages!$E$6:$E$305,Packages!$C$6:$C$305,B67)-COUNTIFS(Appointments!$D$6:$D$2005,B67,Appointments!$J$6:$J$2005,"Package",Appointments!$F$6:$F$2005,"Done")+IF(Services!$I$6="Yes",COUNTIFS(Appointments!$D$6:$D$2005,B67,Appointments!$J$6:$J$2005,"Package",Appointments!$F$6:$F$2005,"No-show"),0)) | N67: =IF(OR(B67="",I67=""),"",IF(AND(J67="",TODAY()-I67>=N(Services!$I$7)),"Not seen for "&(TODAY()-I67)&" days","")) | O67: =IF(N(E67)=0,"",MONTH(E67))
B68: Julia Young | C68: 555 0262 | F68: 44770 | H68: =IF(B68="","",COUNTIFS(Appointments!$D$6:$D$2005,B68,Appointments!$F$6:$F$2005,"Done")) | I68: =IF(OR(B68="",N(H68)=0),"",INT(SUMIFS(Appointments!$M$6:$M$2005,Appointments!$D$6:$D$2005,B68,Appointments!$N$6:$N$2005,1))) | J68: =IF(B68="","",IF(SUMIFS(Appointments!$M$6:$M$2005,Appointments!$D$6:$D$2005,B68,Appointments!$O$6:$O$2005,1)=0,"",INT(SUMIFS(Appointments!$M$6:$M$2005,Appointments!$D$6:$D$2005,B68,Appointments!$O$6:$O$2005,1)))) | K68: =IF(B68="","",SUMIFS(Appointments!$I$6:$I$2005,Appointments!$D$6:$D$2005,B68)+SUMIFS(Packages!$F$6:$F$305,Packages!$C$6:$C$305,B68)) | L68: =IF(B68="","",IF(SUMIFS(Appointments!$K$6:$K$2005,Appointments!$D$6:$D$2005,B68)=0,"",SUMIFS(Appointments!$K$6:$K$2005,Appointments!$D$6:$D$2005,B68))) | M68: =IF(OR(B68="",SUMIFS(Packages!$E$6:$E$305,Packages!$C$6:$C$305,B68)=0),"",SUMIFS(Packages!$E$6:$E$305,Packages!$C$6:$C$305,B68)-COUNTIFS(Appointments!$D$6:$D$2005,B68,Appointments!$J$6:$J$2005,"Package",Appointments!$F$6:$F$2005,"Done")+IF(Services!$I$6="Yes",COUNTIFS(Appointments!$D$6:$D$2005,B68,Appointments!$J$6:$J$2005,"Package",Appointments!$F$6:$F$2005,"No-show"),0)) | N68: =IF(OR(B68="",I68=""),"",IF(AND(J68="",TODAY()-I68>=N(Services!$I$7)),"Not seen for "&(TODAY()-I68)&" days","")) | O68: =IF(N(E68)=0,"",MONTH(E68))
B69: Ruby Shaw | C69: 555 0263 | F69: 44788 | H69: =IF(B69="","",COUNTIFS(Appointments!$D$6:$D$2005,B69,Appointments!$F$6:$F$2005,"Done")) | I69: =IF(OR(B69="",N(H69)=0),"",INT(SUMIFS(Appointments!$M$6:$M$2005,Appointments!$D$6:$D$2005,B69,Appointments!$N$6:$N$2005,1))) | J69: =IF(B69="","",IF(SUMIFS(Appointments!$M$6:$M$2005,Appointments!$D$6:$D$2005,B69,Appointments!$O$6:$O$2005,1)=0,"",INT(SUMIFS(Appointments!$M$6:$M$2005,Appointments!$D$6:$D$2005,B69,Appointments!$O$6:$O$2005,1)))) | K69: =IF(B69="","",SUMIFS(Appointments!$I$6:$I$2005,Appointments!$D$6:$D$2005,B69)+SUMIFS(Packages!$F$6:$F$305,Packages!$C$6:$C$305,B69)) | L69: =IF(B69="","",IF(SUMIFS(Appointments!$K$6:$K$2005,Appointments!$D$6:$D$2005,B69)=0,"",SUMIFS(Appointments!$K$6:$K$2005,Appointments!$D$6:$D$2005,B69))) | M69: =IF(OR(B69="",SUMIFS(Packages!$E$6:$E$305,Packages!$C$6:$C$305,B69)=0),"",SUMIFS(Packages!$E$6:$E$305,Packages!$C$6:$C$305,B69)-COUNTIFS(Appointments!$D$6:$D$2005,B69,Appointments!$J$6:$J$2005,"Package",Appointments!$F$6:$F$2005,"Done")+IF(Services!$I$6="Yes",COUNTIFS(Appointments!$D$6:$D$2005,B69,Appointments!$J$6:$J$2005,"Package",Appointments!$F$6:$F$2005,"No-show"),0)) | N69: =IF(OR(B69="",I69=""),"",IF(AND(J69="",TODAY()-I69>=N(Services!$I$7)),"Not seen for "&(TODAY()-I69)&" days","")) | O69: =IF(N(E69)=0,"",MONTH(E69))
B70: Lucy Wood | C70: 555 0264 | F70: 45464 | H70: =IF(B70="","",COUNTIFS(Appointments!$D$6:$D$2005,B70,Appointments!$F$6:$F$2005,"Done")) | I70: =IF(OR(B70="",N(H70)=0),"",INT(SUMIFS(Appointments!$M$6:$M$2005,Appointments!$D$6:$D$2005,B70,Appointments!$N$6:$N$2005,1))) | J70: =IF(B70="","",IF(SUMIFS(Appointments!$M$6:$M$2005,Appointments!$D$6:$D$2005,B70,Appointments!$O$6:$O$2005,1)=0,"",INT(SUMIFS(Appointments!$M$6:$M$2005,Appointments!$D$6:$D$2005,B70,Appointments!$O$6:$O$2005,1)))) | K70: =IF(B70="","",SUMIFS(Appointments!$I$6:$I$2005,Appointments!$D$6:$D$2005,B70)+SUMIFS(Packages!$F$6:$F$305,Packages!$C$6:$C$305,B70)) | L70: =IF(B70="","",IF(SUMIFS(Appointments!$K$6:$K$2005,Appointments!$D$6:$D$2005,B70)=0,"",SUMIFS(Appointments!$K$6:$K$2005,Appointments!$D$6:$D$2005,B70))) | M70: =IF(OR(B70="",SUMIFS(Packages!$E$6:$E$305,Packages!$C$6:$C$305,B70)=0),"",SUMIFS(Packages!$E$6:$E$305,Packages!$C$6:$C$305,B70)-COUNTIFS(Appointments!$D$6:$D$2005,B70,Appointments!$J$6:$J$2005,"Package",Appointments!$F$6:$F$2005,"Done")+IF(Services!$I$6="Yes",COUNTIFS(Appointments!$D$6:$D$2005,B70,Appointments!$J$6:$J$2005,"Package",Appointments!$F$6:$F$2005,"No-show"),0)) | N70: =IF(OR(B70="",I70=""),"",IF(AND(J70="",TODAY()-I70>=N(Services!$I$7)),"Not seen for "&(TODAY()-I70)&" days","")) | O70: =IF(N(E70)=0,"",MONTH(E70))
B71: Tom Davies | C71: 555 0265 | D71: tom.d@example.com | F71: 44334 | H71: =IF(B71="","",COUNTIFS(Appointments!$D$6:$D$2005,B71,Appointments!$F$6:$F$2005,"Done")) | I71: =IF(OR(B71="",N(H71)=0),"",INT(SUMIFS(Appointments!$M$6:$M$2005,Appointments!$D$6:$D$2005,B71,Appointments!$N$6:$N$2005,1))) | J71: =IF(B71="","",IF(SUMIFS(Appointments!$M$6:$M$2005,Appointments!$D$6:$D$2005,B71,Appointments!$O$6:$O$2005,1)=0,"",INT(SUMIFS(Appointments!$M$6:$M$2005,Appointments!$D$6:$D$2005,B71,Appointments!$O$6:$O$2005,1)))) | K71: =IF(B71="","",SUMIFS(Appointments!$I$6:$I$2005,Appointments!$D$6:$D$2005,B71)+SUMIFS(Packages!$F$6:$F$305,Packages!$C$6:$C$305,B71)) | L71: =IF(B71="","",IF(SUMIFS(Appointments!$K$6:$K$2005,Appointments!$D$6:$D$2005,B71)=0,"",SUMIFS(Appointments!$K$6:$K$2005,Appointments!$D$6:$D$2005,B71))) | M71: =IF(OR(B71="",SUMIFS(Packages!$E$6:$E$305,Packages!$C$6:$C$305,B71)=0),"",SUMIFS(Packages!$E$6:$E$305,Packages!$C$6:$C$305,B71)-COUNTIFS(Appointments!$D$6:$D$2005,B71,Appointments!$J$6:$J$2005,"Package",Appointments!$F$6:$F$2005,"Done")+IF(Services!$I$6="Yes",COUNTIFS(Appointments!$D$6:$D$2005,B71,Appointments!$J$6:$J$2005,"Package",Appointments!$F$6:$F$2005,"No-show"),0)) | N71: =IF(OR(B71="",I71=""),"",IF(AND(J71="",TODAY()-I71>=N(Services!$I$7)),"Not seen for "&(TODAY()-I71)&" days","")) | O71: =IF(N(E71)=0,"",MONTH(E71))
B72: Dina Baker | C72: 555 0266 | D72: dina.b@example.com | E72: 34138 | F72: 45428 | H72: =IF(B72="","",COUNTIFS(Appointments!$D$6:$D$2005,B72,Appointments!$F$6:$F$2005,"Done")) | I72: =IF(OR(B72="",N(H72)=0),"",INT(SUMIFS(Appointments!$M$6:$M$2005,Appointments!$D$6:$D$2005,B72,Appointments!$N$6:$N$2005,1))) | J72: =IF(B72="","",IF(SUMIFS(Appointments!$M$6:$M$2005,Appointments!$D$6:$D$2005,B72,Appointments!$O$6:$O$2005,1)=0,"",INT(SUMIFS(Appointments!$M$6:$M$2005,Appointments!$D$6:$D$2005,B72,Appointments!$O$6:$O$2005,1)))) | K72: =IF(B72="","",SUMIFS(Appointments!$I$6:$I$2005,Appointments!$D$6:$D$2005,B72)+SUMIFS(Packages!$F$6:$F$305,Packages!$C$6:$C$305,B72)) | L72: =IF(B72="","",IF(SUMIFS(Appointments!$K$6:$K$2005,Appointments!$D$6:$D$2005,B72)=0,"",SUMIFS(Appointments!$K$6:$K$2005,Appointments!$D$6:$D$2005,B72))) | M72: =IF(OR(B72="",SUMIFS(Packages!$E$6:$E$305,Packages!$C$6:$C$305,B72)=0),"",SUMIFS(Packages!$E$6:$E$305,Packages!$C$6:$C$305,B72)-COUNTIFS(Appointments!$D$6:$D$2005,B72,Appointments!$J$6:$J$2005,"Package",Appointments!$F$6:$F$2005,"Done")+IF(Services!$I$6="Yes",COUNTIFS(Appointments!$D$6:$D$2005,B72,Appointments!$J$6:$J$2005,"Package",Appointments!$F$6:$F$2005,"No-show"),0)) | N72: =IF(OR(B72="",I72=""),"",IF(AND(J72="",TODAY()-I72>=N(Services!$I$7)),"Not seen for "&(TODAY()-I72)&" days","")) | O72: =IF(N(E72)=0,"",MONTH(E72))
B73: Sophie Stone | C73: 555 0267 | E73: 31742 | F73: 44778 | H73: =IF(B73="","",COUNTIFS(Appointments!$D$6:$D$2005,B73,Appointments!$F$6:$F$2005,"Done")) | I73: =IF(OR(B73="",N(H73)=0),"",INT(SUMIFS(Appointments!$M$6:$M$2005,Appointments!$D$6:$D$2005,B73,Appointments!$N$6:$N$2005,1))) | J73: =IF(B73="","",IF(SUMIFS(Appointments!$M$6:$M$2005,Appointments!$D$6:$D$2005,B73,Appointments!$O$6:$O$2005,1)=0,"",INT(SUMIFS(Appointments!$M$6:$M$2005,Appointments!$D$6:$D$2005,B73,Appointments!$O$6:$O$2005,1)))) | K73: =IF(B73="","",SUMIFS(Appointments!$I$6:$I$2005,Appointments!$D$6:$D$2005,B73)+SUMIFS(Packages!$F$6:$F$305,Packages!$C$6:$C$305,B73)) | L73: =IF(B73="","",IF(SUMIFS(Appointments!$K$6:$K$2005,Appointments!$D$6:$D$2005,B73)=0,"",SUMIFS(Appointments!$K$6:$K$2005,Appointments!$D$6:$D$2005,B73))) | M73: =IF(OR(B73="",SUMIFS(Packages!$E$6:$E$305,Packages!$C$6:$C$305,B73)=0),"",SUMIFS(Packages!$E$6:$E$305,Packages!$C$6:$C$305,B73)-COUNTIFS(Appointments!$D$6:$D$2005,B73,Appointments!$J$6:$J$2005,"Package",Appointments!$F$6:$F$2005,"Done")+IF(Services!$I$6="Yes",COUNTIFS(Appointments!$D$6:$D$2005,B73,Appointments!$J$6:$J$2005,"Package",Appointments!$F$6:$F$2005,"No-show"),0)) | N73: =IF(OR(B73="",I73=""),"",IF(AND(J73="",TODAY()-I73>=N(Services!$I$7)),"Not seen for "&(TODAY()-I73)&" days","")) | O73: =IF(N(E73)=0,"",MONTH(E73))
B74: Owen Walsh | C74: 555 0268 | F74: 44301 | H74: =IF(B74="","",COUNTIFS(Appointments!$D$6:$D$2005,B74,Appointments!$F$6:$F$2005,"Done")) | I74: =IF(OR(B74="",N(H74)=0),"",INT(SUMIFS(Appointments!$M$6:$M$2005,Appointments!$D$6:$D$2005,B74,Appointments!$N$6:$N$2005,1))) | J74: =IF(B74="","",IF(SUMIFS(Appointments!$M$6:$M$2005,Appointments!$D$6:$D$2005,B74,Appointments!$O$6:$O$2005,1)=0,"",INT(SUMIFS(Appointments!$M$6:$M$2005,Appointments!$D$6:$D$2005,B74,Appointments!$O$6:$O$2005,1)))) | K74: =IF(B74="","",SUMIFS(Appointments!$I$6:$I$2005,Appointments!$D$6:$D$2005,B74)+SUMIFS(Packages!$F$6:$F$305,Packages!$C$6:$C$305,B74)) | L74: =IF(B74="","",IF(SUMIFS(Appointments!$K$6:$K$2005,Appointments!$D$6:$D$2005,B74)=0,"",SUMIFS(Appointments!$K$6:$K$2005,Appointments!$D$6:$D$2005,B74))) | M74: =IF(OR(B74="",SUMIFS(Packages!$E$6:$E$305,Packages!$C$6:$C$305,B74)=0),"",SUMIFS(Packages!$E$6:$E$305,Packages!$C$6:$C$305,B74)-COUNTIFS(Appointments!$D$6:$D$2005,B74,Appointments!$J$6:$J$2005,"Package",Appointments!$F$6:$F$2005,"Done")+IF(Services!$I$6="Yes",COUNTIFS(Appointments!$D$6:$D$2005,B74,Appointments!$J$6:$J$2005,"Package",Appointments!$F$6:$F$2005,"No-show"),0)) | N74: =IF(OR(B74="",I74=""),"",IF(AND(J74="",TODAY()-I74>=N(Services!$I$7)),"Not seen for "&(TODAY()-I74)&" days","")) | O74: =IF(N(E74)=0,"",MONTH(E74))
B75: Tom Gray | C75: 555 0269 | F75: 45787 | H75: =IF(B75="","",COUNTIFS(Appointments!$D$6:$D$2005,B75,Appointments!$F$6:$F$2005,"Done")) | I75: =IF(OR(B75="",N(H75)=0),"",INT(SUMIFS(Appointments!$M$6:$M$2005,Appointments!$D$6:$D$2005,B75,Appointments!$N$6:$N$2005,1))) | J75: =IF(B75="","",IF(SUMIFS(Appointments!$M$6:$M$2005,Appointments!$D$6:$D$2005,B75,Appointments!$O$6:$O$2005,1)=0,"",INT(SUMIFS(Appointments!$M$6:$M$2005,Appointments!$D$6:$D$2005,B75,Appointments!$O$6:$O$2005,1)))) | K75: =IF(B75="","",SUMIFS(Appointments!$I$6:$I$2005,Appointments!$D$6:$D$2005,B75)+SUMIFS(Packages!$F$6:$F$305,Packages!$C$6:$C$305,B75)) | L75: =IF(B75="","",IF(SUMIFS(Appointments!$K$6:$K$2005,Appointments!$D$6:$D$2005,B75)=0,"",SUMIFS(Appointments!$K$6:$K$2005,Appointments!$D$6:$D$2005,B75))) | M75: =IF(OR(B75="",SUMIFS(Packages!$E$6:$E$305,Packages!$C$6:$C$305,B75)=0),"",SUMIFS(Packages!$E$6:$E$305,Packages!$C$6:$C$305,B75)-COUNTIFS(Appointments!$D$6:$D$2005,B75,Appointments!$J$6:$J$2005,"Package",Appointments!$F$6:$F$2005,"Done")+IF(Services!$I$6="Yes",COUNTIFS(Appointments!$D$6:$D$2005,B75,Appointments!$J$6:$J$2005,"Package",Appointments!$F$6:$F$2005,"No-show"),0)) | N75: =IF(OR(B75="",I75=""),"",IF(AND(J75="",TODAY()-I75>=N(Services!$I$7)),"Not seen for "&(TODAY()-I75)&" days","")) | O75: =IF(N(E75)=0,"",MONTH(E75))
B76: Kyle Hughes | C76: 555 0270 | D76: kyle.h@example.com | E76: 36412 | F76: 45876 | H76: =IF(B76="","",COUNTIFS(Appointments!$D$6:$D$2005,B76,Appointments!$F$6:$F$2005,"Done")) | I76: =IF(OR(B76="",N(H76)=0),"",INT(SUMIFS(Appointments!$M$6:$M$2005,Appointments!$D$6:$D$2005,B76,Appointments!$N$6:$N$2005,1))) | J76: =IF(B76="","",IF(SUMIFS(Appointments!$M$6:$M$2005,Appointments!$D$6:$D$2005,B76,Appointments!$O$6:$O$2005,1)=0,"",INT(SUMIFS(Appointments!$M$6:$M$2005,Appointments!$D$6:$D$2005,B76,Appointments!$O$6:$O$2005,1)))) | K76: =IF(B76="","",SUMIFS(Appointments!$I$6:$I$2005,Appointments!$D$6:$D$2005,B76)+SUMIFS(Packages!$F$6:$F$305,Packages!$C$6:$C$305,B76)) | L76: =IF(B76="","",IF(SUMIFS(Appointments!$K$6:$K$2005,Appointments!$D$6:$D$2005,B76)=0,"",SUMIFS(Appointments!$K$6:$K$2005,Appointments!$D$6:$D$2005,B76))) | M76: =IF(OR(B76="",SUMIFS(Packages!$E$6:$E$305,Packages!$C$6:$C$305,B76)=0),"",SUMIFS(Packages!$E$6:$E$305,Packages!$C$6:$C$305,B76)-COUNTIFS(Appointments!$D$6:$D$2005,B76,Appointments!$J$6:$J$2005,"Package",Appointments!$F$6:$F$2005,"Done")+IF(Services!$I$6="Yes",COUNTIFS(Appointments!$D$6:$D$2005,B76,Appointments!$J$6:$J$2005,"Package",Appointments!$F$6:$F$2005,"No-show"),0)) | N76: =IF(OR(B76="",I76=""),"",IF(AND(J76="",TODAY()-I76>=N(Services!$I$7)),"Not seen for "&(TODAY()-I76)&" days","")) | O76: =IF(N(E76)=0,"",MONTH(E76))
B77: Finn Davies | C77: 555 0271 | F77: 44441 | H77: =IF(B77="","",COUNTIFS(Appointments!$D$6:$D$2005,B77,Appointments!$F$6:$F$2005,"Done")) | I77: =IF(OR(B77="",N(H77)=0),"",INT(SUMIFS(Appointments!$M$6:$M$2005,Appointments!$D$6:$D$2005,B77,Appointments!$N$6:$N$2005,1))) | J77: =IF(B77="","",IF(SUMIFS(Appointments!$M$6:$M$2005,Appointments!$D$6:$D$2005,B77,Appointments!$O$6:$O$2005,1)=0,"",INT(SUMIFS(Appointments!$M$6:$M$2005,Appointments!$D$6:$D$2005,B77,Appointments!$O$6:$O$2005,1)))) | K77: =IF(B77="","",SUMIFS(Appointments!$I$6:$I$2005,Appointments!$D$6:$D$2005,B77)+SUMIFS(Packages!$F$6:$F$305,Packages!$C$6:$C$305,B77)) | L77: =IF(B77="","",IF(SUMIFS(Appointments!$K$6:$K$2005,Appointments!$D$6:$D$2005,B77)=0,"",SUMIFS(Appointments!$K$6:$K$2005,Appointments!$D$6:$D$2005,B77))) | M77: =IF(OR(B77="",SUMIFS(Packages!$E$6:$E$305,Packages!$C$6:$C$305,B77)=0),"",SUMIFS(Packages!$E$6:$E$305,Packages!$C$6:$C$305,B77)-COUNTIFS(Appointments!$D$6:$D$2005,B77,Appointments!$J$6:$J$2005,"Package",Appointments!$F$6:$F$2005,"Done")+IF(Services!$I$6="Yes",COUNTIFS(Appointments!$D$6:$D$2005,B77,Appointments!$J$6:$J$2005,"Package",Appointments!$F$6:$F$2005,"No-show"),0)) | N77: =IF(OR(B77="",I77=""),"",IF(AND(J77="",TODAY()-I77>=N(Services!$I$7)),"Not seen for "&(TODAY()-I77)&" days","")) | O77: =IF(N(E77)=0,"",MONTH(E77))
B78: Chris Cook | C78: 555 0272 | E78: 36386 | F78: 45420 | H78: =IF(B78="","",COUNTIFS(Appointments!$D$6:$D$2005,B78,Appointments!$F$6:$F$2005,"Done")) | I78: =IF(OR(B78="",N(H78)=0),"",INT(SUMIFS(Appointments!$M$6:$M$2005,Appointments!$D$6:$D$2005,B78,Appointments!$N$6:$N$2005,1))) | J78: =IF(B78="","",IF(SUMIFS(Appointments!$M$6:$M$2005,Appointments!$D$6:$D$2005,B78,Appointments!$O$6:$O$2005,1)=0,"",INT(SUMIFS(Appointments!$M$6:$M$2005,Appointments!$D$6:$D$2005,B78,Appointments!$O$6:$O$2005,1)))) | K78: =IF(B78="","",SUMIFS(Appointments!$I$6:$I$2005,Appointments!$D$6:$D$2005,B78)+SUMIFS(Packages!$F$6:$F$305,Packages!$C$6:$C$305,B78)) | L78: =IF(B78="","",IF(SUMIFS(Appointments!$K$6:$K$2005,Appointments!$D$6:$D$2005,B78)=0,"",SUMIFS(Appointments!$K$6:$K$2005,Appointments!$D$6:$D$2005,B78))) | M78: =IF(OR(B78="",SUMIFS(Packages!$E$6:$E$305,Packages!$C$6:$C$305,B78)=0),"",SUMIFS(Packages!$E$6:$E$305,Packages!$C$6:$C$305,B78)-COUNTIFS(Appointments!$D$6:$D$2005,B78,Appointments!$J$6:$J$2005,"Package",Appointments!$F$6:$F$2005,"Done")+IF(Services!$I$6="Yes",COUNTIFS(Appointments!$D$6:$D$2005,B78,Appointments!$J$6:$J$2005,"Package",Appointments!$F$6:$F$2005,"No-show"),0)) | N78: =IF(OR(B78="",I78=""),"",IF(AND(J78="",TODAY()-I78>=N(Services!$I$7)),"Not seen for "&(TODAY()-I78)&" days","")) | O78: =IF(N(E78)=0,"",MONTH(E78))
B79: Chris Ellis | C79: 555 0273 | D79: chris.e@example.com | F79: 45546 | H79: =IF(B79="","",COUNTIFS(Appointments!$D$6:$D$2005,B79,Appointments!$F$6:$F$2005,"Done")) | I79: =IF(OR(B79="",N(H79)=0),"",INT(SUMIFS(Appointments!$M$6:$M$2005,Appointments!$D$6:$D$2005,B79,Appointments!$N$6:$N$2005,1))) | J79: =IF(B79="","",IF(SUMIFS(Appointments!$M$6:$M$2005,Appointments!$D$6:$D$2005,B79,Appointments!$O$6:$O$2005,1)=0,"",INT(SUMIFS(Appointments!$M$6:$M$2005,Appointments!$D$6:$D$2005,B79,Appointments!$O$6:$O$2005,1)))) | K79: =IF(B79="","",SUMIFS(Appointments!$I$6:$I$2005,Appointments!$D$6:$D$2005,B79)+SUMIFS(Packages!$F$6:$F$305,Packages!$C$6:$C$305,B79)) | L79: =IF(B79="","",IF(SUMIFS(Appointments!$K$6:$K$2005,Appointments!$D$6:$D$2005,B79)=0,"",SUMIFS(Appointments!$K$6:$K$2005,Appointments!$D$6:$D$2005,B79))) | M79: =IF(OR(B79="",SUMIFS(Packages!$E$6:$E$305,Packages!$C$6:$C$305,B79)=0),"",SUMIFS(Packages!$E$6:$E$305,Packages!$C$6:$C$305,B79)-COUNTIFS(Appointments!$D$6:$D$2005,B79,Appointments!$J$6:$J$2005,"Package",Appointments!$F$6:$F$2005,"Done")+IF(Services!$I$6="Yes",COUNTIFS(Appointments!$D$6:$D$2005,B79,Appointments!$J$6:$J$2005,"Package",Appointments!$F$6:$F$2005,"No-show"),0)) | N79: =IF(OR(B79="",I79=""),"",IF(AND(J79="",TODAY()-I79>=N(Services!$I$7)),"Not seen for "&(TODAY()-I79)&" days","")) | O79: =IF(N(E79)=0,"",MONTH(E79))
B80: Holly Shaw | C80: 555 0274 | F80: 44920 | H80: =IF(B80="","",COUNTIFS(Appointments!$D$6:$D$2005,B80,Appointments!$F$6:$F$2005,"Done")) | I80: =IF(OR(B80="",N(H80)=0),"",INT(SUMIFS(Appointments!$M$6:$M$2005,Appointments!$D$6:$D$2005,B80,Appointments!$N$6:$N$2005,1))) | J80: =IF(B80="","",IF(SUMIFS(Appointments!$M$6:$M$2005,Appointments!$D$6:$D$2005,B80,Appointments!$O$6:$O$2005,1)=0,"",INT(SUMIFS(Appointments!$M$6:$M$2005,Appointments!$D$6:$D$2005,B80,Appointments!$O$6:$O$2005,1)))) | K80: =IF(B80="","",SUMIFS(Appointments!$I$6:$I$2005,Appointments!$D$6:$D$2005,B80)+SUMIFS(Packages!$F$6:$F$305,Packages!$C$6:$C$305,B80)) | L80: =IF(B80="","",IF(SUMIFS(Appointments!$K$6:$K$2005,Appointments!$D$6:$D$2005,B80)=0,"",SUMIFS(Appointments!$K$6:$K$2005,Appointments!$D$6:$D$2005,B80))) | M80: =IF(OR(B80="",SUMIFS(Packages!$E$6:$E$305,Packages!$C$6:$C$305,B80)=0),"",SUMIFS(Packages!$E$6:$E$305,Packages!$C$6:$C$305,B80)-COUNTIFS(Appointments!$D$6:$D$2005,B80,Appointments!$J$6:$J$2005,"Package",Appointments!$F$6:$F$2005,"Done")+IF(Services!$I$6="Yes",COUNTIFS(Appointments!$D$6:$D$2005,B80,Appointments!$J$6:$J$2005,"Package",Appointments!$F$6:$F$2005,"No-show"),0)) | N80: =IF(OR(B80="",I80=""),"",IF(AND(J80="",TODAY()-I80>=N(Services!$I$7)),"Not seen for "&(TODAY()-I80)&" days","")) | O80: =IF(N(E80)=0,"",MONTH(E80))
B81: Holly Fox | C81: 555 0275 | D81: holly.f@example.com | F81: 45272 | H81: =IF(B81="","",COUNTIFS(Appointments!$D$6:$D$2005,B81,Appointments!$F$6:$F$2005,"Done")) | I81: =IF(OR(B81="",N(H81)=0),"",INT(SUMIFS(Appointments!$M$6:$M$2005,Appointments!$D$6:$D$2005,B81,Appointments!$N$6:$N$2005,1))) | J81: =IF(B81="","",IF(SUMIFS(Appointments!$M$6:$M$2005,Appointments!$D$6:$D$2005,B81,Appointments!$O$6:$O$2005,1)=0,"",INT(SUMIFS(Appointments!$M$6:$M$2005,Appointments!$D$6:$D$2005,B81,Appointments!$O$6:$O$2005,1)))) | K81: =IF(B81="","",SUMIFS(Appointments!$I$6:$I$2005,Appointments!$D$6:$D$2005,B81)+SUMIFS(Packages!$F$6:$F$305,Packages!$C$6:$C$305,B81)) | L81: =IF(B81="","",IF(SUMIFS(Appointments!$K$6:$K$2005,Appointments!$D$6:$D$2005,B81)=0,"",SUMIFS(Appointments!$K$6:$K$2005,Appointments!$D$6:$D$2005,B81))) | M81: =IF(OR(B81="",SUMIFS(Packages!$E$6:$E$305,Packages!$C$6:$C$305,B81)=0),"",SUMIFS(Packages!$E$6:$E$305,Packages!$C$6:$C$305,B81)-COUNTIFS(Appointments!$D$6:$D$2005,B81,Appointments!$J$6:$J$2005,"Package",Appointments!$F$6:$F$2005,"Done")+IF(Services!$I$6="Yes",COUNTIFS(Appointments!$D$6:$D$2005,B81,Appointments!$J$6:$J$2005,"Package",Appointments!$F$6:$F$2005,"No-show"),0)) | N81: =IF(OR(B81="",I81=""),"",IF(AND(J81="",TODAY()-I81>=N(Services!$I$7)),"Not seen for "&(TODAY()-I81)&" days","")) | O81: =IF(N(E81)=0,"",MONTH(E81))
B82: Chris Cox | C82: 555 0276 | F82: 45939 | H82: =IF(B82="","",COUNTIFS(Appointments!$D$6:$D$2005,B82,Appointments!$F$6:$F$2005,"Done")) | I82: =IF(OR(B82="",N(H82)=0),"",INT(SUMIFS(Appointments!$M$6:$M$2005,Appointments!$D$6:$D$2005,B82,Appointments!$N$6:$N$2005,1))) | J82: =IF(B82="","",IF(SUMIFS(Appointments!$M$6:$M$2005,Appointments!$D$6:$D$2005,B82,Appointments!$O$6:$O$2005,1)=0,"",INT(SUMIFS(Appointments!$M$6:$M$2005,Appointments!$D$6:$D$2005,B82,Appointments!$O$6:$O$2005,1)))) | K82: =IF(B82="","",SUMIFS(Appointments!$I$6:$I$2005,Appointments!$D$6:$D$2005,B82)+SUMIFS(Packages!$F$6:$F$305,Packages!$C$6:$C$305,B82)) | L82: =IF(B82="","",IF(SUMIFS(Appointments!$K$6:$K$2005,Appointments!$D$6:$D$2005,B82)=0,"",SUMIFS(Appointments!$K$6:$K$2005,Appointments!$D$6:$D$2005,B82))) | M82: =IF(OR(B82="",SUMIFS(Packages!$E$6:$E$305,Packages!$C$6:$C$305,B82)=0),"",SUMIFS(Packages!$E$6:$E$305,Packages!$C$6:$C$305,B82)-COUNTIFS(Appointments!$D$6:$D$2005,B82,Appointments!$J$6:$J$2005,"Package",Appointments!$F$6:$F$2005,"Done")+IF(Services!$I$6="Yes",COUNTIFS(Appointments!$D$6:$D$2005,B82,Appointments!$J$6:$J$2005,"Package",Appointments!$F$6:$F$2005,"No-show"),0)) | N82: =IF(OR(B82="",I82=""),"",IF(AND(J82="",TODAY()-I82>=N(Services!$I$7)),"Not seen for "&(TODAY()-I82)&" days","")) | O82: =IF(N(E82)=0,"",MONTH(E82))
B83: Pete Young | C83: 555 0277 | E83: 33501 | F83: 44811 | H83: =IF(B83="","",COUNTIFS(Appointments!$D$6:$D$2005,B83,Appointments!$F$6:$F$2005,"Done")) | I83: =IF(OR(B83="",N(H83)=0),"",INT(SUMIFS(Appointments!$M$6:$M$2005,Appointments!$D$6:$D$2005,B83,Appointments!$N$6:$N$2005,1))) | J83: =IF(B83="","",IF(SUMIFS(Appointments!$M$6:$M$2005,Appointments!$D$6:$D$2005,B83,Appointments!$O$6:$O$2005,1)=0,"",INT(SUMIFS(Appointments!$M$6:$M$2005,Appointments!$D$6:$D$2005,B83,Appointments!$O$6:$O$2005,1)))) | K83: =IF(B83="","",SUMIFS(Appointments!$I$6:$I$2005,Appointments!$D$6:$D$2005,B83)+SUMIFS(Packages!$F$6:$F$305,Packages!$C$6:$C$305,B83)) | L83: =IF(B83="","",IF(SUMIFS(Appointments!$K$6:$K$2005,Appointments!$D$6:$D$2005,B83)=0,"",SUMIFS(Appointments!$K$6:$K$2005,Appointments!$D$6:$D$2005,B83))) | M83: =IF(OR(B83="",SUMIFS(Packages!$E$6:$E$305,Packages!$C$6:$C$305,B83)=0),"",SUMIFS(Packages!$E$6:$E$305,Packages!$C$6:$C$305,B83)-COUNTIFS(Appointments!$D$6:$D$2005,B83,Appointments!$J$6:$J$2005,"Package",Appointments!$F$6:$F$2005,"Done")+IF(Services!$I$6="Yes",COUNTIFS(Appointments!$D$6:$D$2005,B83,Appointments!$J$6:$J$2005,"Package",Appointments!$F$6:$F$2005,"No-show"),0)) | N83: =IF(OR(B83="",I83=""),"",IF(AND(J83="",TODAY()-I83>=N(Services!$I$7)),"Not seen for "&(TODAY()-I83)&" days","")) | O83: =IF(N(E83)=0,"",MONTH(E83))
B84: Eli Hughes | C84: 555 0278 | F84: 44675 | H84: =IF(B84="","",COUNTIFS(Appointments!$D$6:$D$2005,B84,Appointments!$F$6:$F$2005,"Done")) | I84: =IF(OR(B84="",N(H84)=0),"",INT(SUMIFS(Appointments!$M$6:$M$2005,Appointments!$D$6:$D$2005,B84,Appointments!$N$6:$N$2005,1))) | J84: =IF(B84="","",IF(SUMIFS(Appointments!$M$6:$M$2005,Appointments!$D$6:$D$2005,B84,Appointments!$O$6:$O$2005,1)=0,"",INT(SUMIFS(Appointments!$M$6:$M$2005,Appointments!$D$6:$D$2005,B84,Appointments!$O$6:$O$2005,1)))) | K84: =IF(B84="","",SUMIFS(Appointments!$I$6:$I$2005,Appointments!$D$6:$D$2005,B84)+SUMIFS(Packages!$F$6:$F$305,Packages!$C$6:$C$305,B84)) | L84: =IF(B84="","",IF(SUMIFS(Appointments!$K$6:$K$2005,Appointments!$D$6:$D$2005,B84)=0,"",SUMIFS(Appointments!$K$6:$K$2005,Appointments!$D$6:$D$2005,B84))) | M84: =IF(OR(B84="",SUMIFS(Packages!$E$6:$E$305,Packages!$C$6:$C$305,B84)=0),"",SUMIFS(Packages!$E$6:$E$305,Packages!$C$6:$C$305,B84)-COUNTIFS(Appointments!$D$6:$D$2005,B84,Appointments!$J$6:$J$2005,"Package",Appointments!$F$6:$F$2005,"Done")+IF(Services!$I$6="Yes",COUNTIFS(Appointments!$D$6:$D$2005,B84,Appointments!$J$6:$J$2005,"Package",Appointments!$F$6:$F$2005,"No-show"),0)) | N84: =IF(OR(B84="",I84=""),"",IF(AND(J84="",TODAY()-I84>=N(Services!$I$7)),"Not seen for "&(TODAY()-I84)&" days","")) | O84: =IF(N(E84)=0,"",MONTH(E84))
B85: Megan Morgan | C85: 555 0279 | F85: 44676 | H85: =IF(B85="","",COUNTIFS(Appointments!$D$6:$D$2005,B85,Appointments!$F$6:$F$2005,"Done")) | I85: =IF(OR(B85="",N(H85)=0),"",INT(SUMIFS(Appointments!$M$6:$M$2005,Appointments!$D$6:$D$2005,B85,Appointments!$N$6:$N$2005,1))) | J85: =IF(B85="","",IF(SUMIFS(Appointments!$M$6:$M$2005,Appointments!$D$6:$D$2005,B85,Appointments!$O$6:$O$2005,1)=0,"",INT(SUMIFS(Appointments!$M$6:$M$2005,Appointments!$D$6:$D$2005,B85,Appointments!$O$6:$O$2005,1)))) | K85: =IF(B85="","",SUMIFS(Appointments!$I$6:$I$2005,Appointments!$D$6:$D$2005,B85)+SUMIFS(Packages!$F$6:$F$305,Packages!$C$6:$C$305,B85)) | L85: =IF(B85="","",IF(SUMIFS(Appointments!$K$6:$K$2005,Appointments!$D$6:$D$2005,B85)=0,"",SUMIFS(Appointments!$K$6:$K$2005,Appointments!$D$6:$D$2005,B85))) | M85: =IF(OR(B85="",SUMIFS(Packages!$E$6:$E$305,Packages!$C$6:$C$305,B85)=0),"",SUMIFS(Packages!$E$6:$E$305,Packages!$C$6:$C$305,B85)-COUNTIFS(Appointments!$D$6:$D$2005,B85,Appointments!$J$6:$J$2005,"Package",Appointments!$F$6:$F$2005,"Done")+IF(Services!$I$6="Yes",COUNTIFS(Appointments!$D$6:$D$2005,B85,Appointments!$J$6:$J$2005,"Package",Appointments!$F$6:$F$2005,"No-show"),0)) | N85: =IF(OR(B85="",I85=""),"",IF(AND(J85="",TODAY()-I85>=N(Services!$I$7)),"Not seen for "&(TODAY()-I85)&" days","")) | O85: =IF(N(E85)=0,"",MONTH(E85))
B86: Hannah Cook | C86: 555 0280 | D86: hannah.c@example.com | E86: 33507 | F86: 44664 | H86: =IF(B86="","",COUNTIFS(Appointments!$D$6:$D$2005,B86,Appointments!$F$6:$F$2005,"Done")) | I86: =IF(OR(B86="",N(H86)=0),"",INT(SUMIFS(Appointments!$M$6:$M$2005,Appointments!$D$6:$D$2005,B86,Appointments!$N$6:$N$2005,1))) | J86: =IF(B86="","",IF(SUMIFS(Appointments!$M$6:$M$2005,Appointments!$D$6:$D$2005,B86,Appointments!$O$6:$O$2005,1)=0,"",INT(SUMIFS(Appointments!$M$6:$M$2005,Appointments!$D$6:$D$2005,B86,Appointments!$O$6:$O$2005,1)))) | K86: =IF(B86="","",SUMIFS(Appointments!$I$6:$I$2005,Appointments!$D$6:$D$2005,B86)+SUMIFS(Packages!$F$6:$F$305,Packages!$C$6:$C$305,B86)) | L86: =IF(B86="","",IF(SUMIFS(Appointments!$K$6:$K$2005,Appointments!$D$6:$D$2005,B86)=0,"",SUMIFS(Appointments!$K$6:$K$2005,Appointments!$D$6:$D$2005,B86))) | M86: =IF(OR(B86="",SUMIFS(Packages!$E$6:$E$305,Packages!$C$6:$C$305,B86)=0),"",SUMIFS(Packages!$E$6:$E$305,Packages!$C$6:$C$305,B86)-COUNTIFS(Appointments!$D$6:$D$2005,B86,Appointments!$J$6:$J$2005,"Package",Appointments!$F$6:$F$2005,"Done")+IF(Services!$I$6="Yes",COUNTIFS(Appointments!$D$6:$D$2005,B86,Appointments!$J$6:$J$2005,"Package",Appointments!$F$6:$F$2005,"No-show"),0)) | N86: =IF(OR(B86="",I86=""),"",IF(AND(J86="",TODAY()-I86>=N(Services!$I$7)),"Not seen for "&(TODAY()-I86)&" days","")) | O86: =IF(N(E86)=0,"",MONTH(E86))
B87: Harry Owens | C87: 555 0281 | F87: 44547 | H87: =IF(B87="","",COUNTIFS(Appointments!$D$6:$D$2005,B87,Appointments!$F$6:$F$2005,"Done")) | I87: =IF(OR(B87="",N(H87)=0),"",INT(SUMIFS(Appointments!$M$6:$M$2005,Appointments!$D$6:$D$2005,B87,Appointments!$N$6:$N$2005,1))) | J87: =IF(B87="","",IF(SUMIFS(Appointments!$M$6:$M$2005,Appointments!$D$6:$D$2005,B87,Appointments!$O$6:$O$2005,1)=0,"",INT(SUMIFS(Appointments!$M$6:$M$2005,Appointments!$D$6:$D$2005,B87,Appointments!$O$6:$O$2005,1)))) | K87: =IF(B87="","",SUMIFS(Appointments!$I$6:$I$2005,Appointments!$D$6:$D$2005,B87)+SUMIFS(Packages!$F$6:$F$305,Packages!$C$6:$C$305,B87)) | L87: =IF(B87="","",IF(SUMIFS(Appointments!$K$6:$K$2005,Appointments!$D$6:$D$2005,B87)=0,"",SUMIFS(Appointments!$K$6:$K$2005,Appointments!$D$6:$D$2005,B87))) | M87: =IF(OR(B87="",SUMIFS(Packages!$E$6:$E$305,Packages!$C$6:$C$305,B87)=0),"",SUMIFS(Packages!$E$6:$E$305,Packages!$C$6:$C$305,B87)-COUNTIFS(Appointments!$D$6:$D$2005,B87,Appointments!$J$6:$J$2005,"Package",Appointments!$F$6:$F$2005,"Done")+IF(Services!$I$6="Yes",COUNTIFS(Appointments!$D$6:$D$2005,B87,Appointments!$J$6:$J$2005,"Package",Appointments!$F$6:$F$2005,"No-show"),0)) | N87: =IF(OR(B87="",I87=""),"",IF(AND(J87="",TODAY()-I87>=N(Services!$I$7)),"Not seen for "&(TODAY()-I87)&" days","")) | O87: =IF(N(E87)=0,"",MONTH(E87))
B88: Dan Hill | C88: 555 0282 | F88: 44221 | H88: =IF(B88="","",COUNTIFS(Appointments!$D$6:$D$2005,B88,Appointments!$F$6:$F$2005,"Done")) | I88: =IF(OR(B88="",N(H88)=0),"",INT(SUMIFS(Appointments!$M$6:$M$2005,Appointments!$D$6:$D$2005,B88,Appointments!$N$6:$N$2005,1))) | J88: =IF(B88="","",IF(SUMIFS(Appointments!$M$6:$M$2005,Appointments!$D$6:$D$2005,B88,Appointments!$O$6:$O$2005,1)=0,"",INT(SUMIFS(Appointments!$M$6:$M$2005,Appointments!$D$6:$D$2005,B88,Appointments!$O$6:$O$2005,1)))) | K88: =IF(B88="","",SUMIFS(Appointments!$I$6:$I$2005,Appointments!$D$6:$D$2005,B88)+SUMIFS(Packages!$F$6:$F$305,Packages!$C$6:$C$305,B88)) | L88: =IF(B88="","",IF(SUMIFS(Appointments!$K$6:$K$2005,Appointments!$D$6:$D$2005,B88)=0,"",SUMIFS(Appointments!$K$6:$K$2005,Appointments!$D$6:$D$2005,B88))) | M88: =IF(OR(B88="",SUMIFS(Packages!$E$6:$E$305,Packages!$C$6:$C$305,B88)=0),"",SUMIFS(Packages!$E$6:$E$305,Packages!$C$6:$C$305,B88)-COUNTIFS(Appointments!$D$6:$D$2005,B88,Appointments!$J$6:$J$2005,"Package",Appointments!$F$6:$F$2005,"Done")+IF(Services!$I$6="Yes",COUNTIFS(Appointments!$D$6:$D$2005,B88,Appointments!$J$6:$J$2005,"Package",Appointments!$F$6:$F$2005,"No-show"),0)) | N88: =IF(OR(B88="",I88=""),"",IF(AND(J88="",TODAY()-I88>=N(Services!$I$7)),"Not seen for "&(TODAY()-I88)&" days","")) | O88: =IF(N(E88)=0,"",MONTH(E88))
B89: Jade Hill | C89: 555 0283 | D89: jade.h@example.com | E89: 27536 | F89: 44471 | H89: =IF(B89="","",COUNTIFS(Appointments!$D$6:$D$2005,B89,Appointments!$F$6:$F$2005,"Done")) | I89: =IF(OR(B89="",N(H89)=0),"",INT(SUMIFS(Appointments!$M$6:$M$2005,Appointments!$D$6:$D$2005,B89,Appointments!$N$6:$N$2005,1))) | J89: =IF(B89="","",IF(SUMIFS(Appointments!$M$6:$M$2005,Appointments!$D$6:$D$2005,B89,Appointments!$O$6:$O$2005,1)=0,"",INT(SUMIFS(Appointments!$M$6:$M$2005,Appointments!$D$6:$D$2005,B89,Appointments!$O$6:$O$2005,1)))) | K89: =IF(B89="","",SUMIFS(Appointments!$I$6:$I$2005,Appointments!$D$6:$D$2005,B89)+SUMIFS(Packages!$F$6:$F$305,Packages!$C$6:$C$305,B89)) | L89: =IF(B89="","",IF(SUMIFS(Appointments!$K$6:$K$2005,Appointments!$D$6:$D$2005,B89)=0,"",SUMIFS(Appointments!$K$6:$K$2005,Appointments!$D$6:$D$2005,B89))) | M89: =IF(OR(B89="",SUMIFS(Packages!$E$6:$E$305,Packages!$C$6:$C$305,B89)=0),"",SUMIFS(Packages!$E$6:$E$305,Packages!$C$6:$C$305,B89)-COUNTIFS(Appointments!$D$6:$D$2005,B89,Appointments!$J$6:$J$2005,"Package",Appointments!$F$6:$F$2005,"Done")+IF(Services!$I$6="Yes",COUNTIFS(Appointments!$D$6:$D$2005,B89,Appointments!$J$6:$J$2005,"Package",Appointments!$F$6:$F$2005,"No-show"),0)) | N89: =IF(OR(B89="",I89=""),"",IF(AND(J89="",TODAY()-I89>=N(Services!$I$7)),"Not seen for "&(TODAY()-I89)&" days","")) | O89: =IF(N(E89)=0,"",MONTH(E89))
