Workbook

Sheet Dashboard
B2: =IF(C4="","Party planner",C4)
B3: The countdown, the guests, the checklist and the money for the party.
B4: Party | C4: Mia turns 7
B5: Date | C5: 46319 | D5: Starts | E5: 0.58333333
B6: Budget | C6: 1100
B8: Countdown | C8: Coming | D8: No answer yet | E8: Tasks done | F8: Late tasks | G8: Budget left
B9: =IF($C$5="","",IF($C$5-TODAY()>1,($C$5-TODAY())&" days",IF($C$5-TODAY()=1,"Tomorrow",IF($C$5=TODAY(),"Today","Done")))) | C9: =SUMIFS(Guests!$M$6:$M$305,Guests!$D$6:$D$305,"Yes")+SUMIFS(Guests!$N$6:$N$305,Guests!$D$6:$D$305,"Yes") | D9: =SUMIFS(Guests!$M$6:$M$305,Guests!$O$6:$O$305,"No answer")+SUMIFS(Guests!$N$6:$N$305,Guests!$O$6:$O$305,"No answer") | E9: =COUNTIFS(Tasks!$B$6:$B$65,"<>",Tasks!$F$6:$F$65,"<>")&" of "&COUNTIF(Tasks!$B$6:$B$65,"?*") | F9: =COUNTIF(Tasks!$G$6:$G$65,"Late") | G9: =IF(N($C$6)=0,"",$C$6-(SUM(Budget!$M$6:$M$55)+SUM('Food and drinks'!$K$8:$K$47)))
B11: Next up | E11: Date | F11: Who | G11: Status | I11: Guests | J11: Adults | K11: Kids | L11: Total
B12: =IF(O12="",IF($C$5="","Type the date of the party first","Nothing left to do"),INDEX(Tasks!$B$6:$B$65,MATCH(O12,Tasks!$J$6:$J$65,0))) | E12: =IF(O12="","",INT(O12)) | F12: =IF(O12="","",INDEX(Tasks!$E$6:$E$65,MATCH(O12,Tasks!$J$6:$J$65,0))) | G12: =IF(O12="","",INDEX(Tasks!$G$6:$G$65,MATCH(O12,Tasks!$J$6:$J$65,0))) | I12: Coming | J12: =SUMIFS(Guests!$M$6:$M$305,Guests!$O$6:$O$305,"Yes") | K12: =SUMIFS(Guests!$N$6:$N$305,Guests!$O$6:$O$305,"Yes") | L12: =J12+K12 | O12: =IFERROR(SMALL(Tasks!$J$6:$J$65,1),"")
B13: =IF(O13="","",INDEX(Tasks!$B$6:$B$65,MATCH(O13,Tasks!$J$6:$J$65,0))) | E13: =IF(O13="","",INT(O13)) | F13: =IF(O13="","",INDEX(Tasks!$E$6:$E$65,MATCH(O13,Tasks!$J$6:$J$65,0))) | G13: =IF(O13="","",INDEX(Tasks!$G$6:$G$65,MATCH(O13,Tasks!$J$6:$J$65,0))) | I13: Maybe | J13: =SUMIFS(Guests!$M$6:$M$305,Guests!$O$6:$O$305,"Maybe") | K13: =SUMIFS(Guests!$N$6:$N$305,Guests!$O$6:$O$305,"Maybe") | L13: =J13+K13 | O13: =IFERROR(SMALL(Tasks!$J$6:$J$65,2),"")
B14: =IF(O14="","",INDEX(Tasks!$B$6:$B$65,MATCH(O14,Tasks!$J$6:$J$65,0))) | E14: =IF(O14="","",INT(O14)) | F14: =IF(O14="","",INDEX(Tasks!$E$6:$E$65,MATCH(O14,Tasks!$J$6:$J$65,0))) | G14: =IF(O14="","",INDEX(Tasks!$G$6:$G$65,MATCH(O14,Tasks!$J$6:$J$65,0))) | I14: No answer yet | J14: =SUMIFS(Guests!$M$6:$M$305,Guests!$O$6:$O$305,"No answer") | K14: =SUMIFS(Guests!$N$6:$N$305,Guests!$O$6:$O$305,"No answer") | L14: =J14+K14 | O14: =IFERROR(SMALL(Tasks!$J$6:$J$65,3),"")
B15: =IF(O15="","",INDEX(Tasks!$B$6:$B$65,MATCH(O15,Tasks!$J$6:$J$65,0))) | E15: =IF(O15="","",INT(O15)) | F15: =IF(O15="","",INDEX(Tasks!$E$6:$E$65,MATCH(O15,Tasks!$J$6:$J$65,0))) | G15: =IF(O15="","",INDEX(Tasks!$G$6:$G$65,MATCH(O15,Tasks!$J$6:$J$65,0))) | I15: Can't come | J15: =SUMIFS(Guests!$M$6:$M$305,Guests!$O$6:$O$305,"No") | K15: =SUMIFS(Guests!$N$6:$N$305,Guests!$O$6:$O$305,"No") | L15: =J15+K15 | O15: =IFERROR(SMALL(Tasks!$J$6:$J$65,4),"")
B16: =IF(O16="","",INDEX(Tasks!$B$6:$B$65,MATCH(O16,Tasks!$J$6:$J$65,0))) | E16: =IF(O16="","",INT(O16)) | F16: =IF(O16="","",INDEX(Tasks!$E$6:$E$65,MATCH(O16,Tasks!$J$6:$J$65,0))) | G16: =IF(O16="","",INDEX(Tasks!$G$6:$G$65,MATCH(O16,Tasks!$J$6:$J$65,0))) | I16: Invited | J16: =SUM(J12:J15) | K16: =SUM(K12:K15) | L16: =SUM(L12:L15) | O16: =IFERROR(SMALL(Tasks!$J$6:$J$65,5),"")
B17: =IF(O17="","",INDEX(Tasks!$B$6:$B$65,MATCH(O17,Tasks!$J$6:$J$65,0))) | E17: =IF(O17="","",INT(O17)) | F17: =IF(O17="","",INDEX(Tasks!$E$6:$E$65,MATCH(O17,Tasks!$J$6:$J$65,0))) | G17: =IF(O17="","",INDEX(Tasks!$G$6:$G$65,MATCH(O17,Tasks!$J$6:$J$65,0))) | I17: ="Thank-you notes to send: "&COUNTIF(Guests!$J$6:$J$305,"To send") | O17: =IFERROR(SMALL(Tasks!$J$6:$J$65,6),"")
B18: =IF(O18="","",INDEX(Tasks!$B$6:$B$65,MATCH(O18,Tasks!$J$6:$J$65,0))) | E18: =IF(O18="","",INT(O18)) | F18: =IF(O18="","",INDEX(Tasks!$E$6:$E$65,MATCH(O18,Tasks!$J$6:$J$65,0))) | G18: =IF(O18="","",INDEX(Tasks!$G$6:$G$65,MATCH(O18,Tasks!$J$6:$J$65,0))) | O18: =IFERROR(SMALL(Tasks!$J$6:$J$65,7),"")
B19: =IF(O19="","",INDEX(Tasks!$B$6:$B$65,MATCH(O19,Tasks!$J$6:$J$65,0))) | E19: =IF(O19="","",INT(O19)) | F19: =IF(O19="","",INDEX(Tasks!$E$6:$E$65,MATCH(O19,Tasks!$J$6:$J$65,0))) | G19: =IF(O19="","",INDEX(Tasks!$G$6:$G$65,MATCH(O19,Tasks!$J$6:$J$65,0))) | O19: =IFERROR(SMALL(Tasks!$J$6:$J$65,8),"")
B21: Money | C21: Planned | D21: Paid | E21: Still to pay | I21: Dietary needs of guests coming | J21: Guests
B22: Venue | C22: =SUMIFS(Budget!$M$6:$M$55,Budget!$C$6:$C$55,B22) | D22: =SUMIFS(Budget!$G$6:$G$55,Budget!$C$6:$C$55,B22) | E22: =SUMIFS(Budget!$H$6:$H$55,Budget!$C$6:$C$55,B22) | I22: Vegetarian | J22: =COUNTIFS(Guests!$G$6:$G$305,I22,Guests!$D$6:$D$305,"Yes")
B23: Cake | C23: =SUMIFS(Budget!$M$6:$M$55,Budget!$C$6:$C$55,B23) | D23: =SUMIFS(Budget!$G$6:$G$55,Budget!$C$6:$C$55,B23) | E23: =SUMIFS(Budget!$H$6:$H$55,Budget!$C$6:$C$55,B23) | I23: Vegan | J23: =COUNTIFS(Guests!$G$6:$G$305,I23,Guests!$D$6:$D$305,"Yes")
B24: Decorations | C24: =SUMIFS(Budget!$M$6:$M$55,Budget!$C$6:$C$55,B24) | D24: =SUMIFS(Budget!$G$6:$G$55,Budget!$C$6:$C$55,B24) | E24: =SUMIFS(Budget!$H$6:$H$55,Budget!$C$6:$C$55,B24) | I24: Gluten free | J24: =COUNTIFS(Guests!$G$6:$G$305,I24,Guests!$D$6:$D$305,"Yes")
B25: Entertainment | C25: =SUMIFS(Budget!$M$6:$M$55,Budget!$C$6:$C$55,B25) | D25: =SUMIFS(Budget!$G$6:$G$55,Budget!$C$6:$C$55,B25) | E25: =SUMIFS(Budget!$H$6:$H$55,Budget!$C$6:$C$55,B25) | I25: Dairy free | J25: =COUNTIFS(Guests!$G$6:$G$305,I25,Guests!$D$6:$D$305,"Yes")
B26: Rentals | C26: =SUMIFS(Budget!$M$6:$M$55,Budget!$C$6:$C$55,B26) | D26: =SUMIFS(Budget!$G$6:$G$55,Budget!$C$6:$C$55,B26) | E26: =SUMIFS(Budget!$H$6:$H$55,Budget!$C$6:$C$55,B26) | I26: Nut allergy | J26: =COUNTIFS(Guests!$G$6:$G$305,I26,Guests!$D$6:$D$305,"Yes")
B27: Invitations | C27: =SUMIFS(Budget!$M$6:$M$55,Budget!$C$6:$C$55,B27) | D27: =SUMIFS(Budget!$G$6:$G$55,Budget!$C$6:$C$55,B27) | E27: =SUMIFS(Budget!$H$6:$H$55,Budget!$C$6:$C$55,B27) | I27: Halal | J27: =COUNTIFS(Guests!$G$6:$G$305,I27,Guests!$D$6:$D$305,"Yes")
B28: Favours | C28: =SUMIFS(Budget!$M$6:$M$55,Budget!$C$6:$C$55,B28) | D28: =SUMIFS(Budget!$G$6:$G$55,Budget!$C$6:$C$55,B28) | E28: =SUMIFS(Budget!$H$6:$H$55,Budget!$C$6:$C$55,B28) | I28: Kosher | J28: =COUNTIFS(Guests!$G$6:$G$305,I28,Guests!$D$6:$D$305,"Yes")
B29: Photos | C29: =SUMIFS(Budget!$M$6:$M$55,Budget!$C$6:$C$55,B29) | D29: =SUMIFS(Budget!$G$6:$G$55,Budget!$C$6:$C$55,B29) | E29: =SUMIFS(Budget!$H$6:$H$55,Budget!$C$6:$C$55,B29) | I29: Other | J29: =COUNTIFS(Guests!$G$6:$G$305,I29,Guests!$D$6:$D$305,"Yes")
B30: Outfits | C30: =SUMIFS(Budget!$M$6:$M$55,Budget!$C$6:$C$55,B30) | D30: =SUMIFS(Budget!$G$6:$G$55,Budget!$C$6:$C$55,B30) | E30: =SUMIFS(Budget!$H$6:$H$55,Budget!$C$6:$C$55,B30)
B31: Other | C31: =SUMIFS(Budget!$M$6:$M$55,Budget!$C$6:$C$55,B31) | D31: =SUMIFS(Budget!$G$6:$G$55,Budget!$C$6:$C$55,B31) | E31: =SUMIFS(Budget!$H$6:$H$55,Budget!$C$6:$C$55,B31)
B32: Food and drinks | C32: =SUM('Food and drinks'!$K$8:$K$47) | D32: =SUMIFS('Food and drinks'!$K$8:$K$47,'Food and drinks'!$L$8:$L$47,"<>") | E32: =C32-D32
B33: Total | C33: =SUM(Budget!$M$6:$M$55)+SUM('Food and drinks'!$K$8:$K$47) | D33: =SUM(Budget!$G$6:$G$55)+SUMIFS('Food and drinks'!$K$8:$K$47,'Food and drinks'!$L$8:$L$47,"<>") | E33: =SUM(Budget!$H$6:$H$55)+SUM('Food and drinks'!$K$8:$K$47)-SUMIFS('Food and drinks'!$K$8:$K$47,'Food and drinks'!$L$8:$L$47,"<>")
B34: =IF(N($C$6)=0,"",REPT("█",MIN(24,MAX(0,ROUND((MIN(1,C33/$C$6))*24,0))))&REPT("░",24-MIN(24,MAX(0,ROUND((MIN(1,C33/$C$6))*24,0))))) | E34: =IF(N($C$6)=0,"",IF(C33>$C$6,"Over by "&FIXED(C33-$C$6,2),FIXED(C33/$C$6*100,0)&"% of the budget"))

Sheet Guests
B2: Guests
B3: One line per guest or family. The answers, head counts and dietary needs add up on the Dashboard.
B5: Name | C5: Group | D5: Answer | E5: Adults | F5: Kids | G5: Dietary needs | H5: Gift | I5: Card sent | J5: Thank you | K5: Notes
B6: Grandma Rosa and Grandpa Joe | C6: Family | D6: Yes | E6: 2 | F6: 0 | J6: =IF(H6="","",IF(I6="","To send","Sent")) | K6: Bringing the photo album | M6: =IF(B6="",0,IF(E6="",1,N(E6))) | N6: =IF(B6="",0,N(F6)) | O6: =IF(B6="","",IF(D6="","No answer",D6))
B7: Aunt Clara and Ben | C7: Family | D7: Yes | E7: 2 | F7: 2 | G7: Vegetarian | J7: =IF(H7="","",IF(I7="","To send","Sent")) | M7: =IF(B7="",0,IF(E7="",1,N(E7))) | N7: =IF(B7="",0,N(F7)) | O7: =IF(B7="","",IF(D7="","No answer",D7))
B8: Uncle Dan | C8: Family | D8: No | E8: 1 | F8: 0 | H8: Book and card by post | I8: x | J8: =IF(H8="","",IF(I8="","To send","Sent")) | K8: Away that weekend | M8: =IF(B8="",0,IF(E8="",1,N(E8))) | N8: =IF(B8="",0,N(F8)) | O8: =IF(B8="","",IF(D8="","No answer",D8))
B9: The Okafor family | C9: School | D9: Yes | E9: 2 | F9: 2 | J9: =IF(H9="","",IF(I9="","To send","Sent")) | M9: =IF(B9="",0,IF(E9="",1,N(E9))) | N9: =IF(B9="",0,N(F9)) | O9: =IF(B9="","",IF(D9="","No answer",D9))
B10: The Lindqvist family | C10: School | D10: Yes | E10: 1 | F10: 1 | G10: Nut allergy | J10: =IF(H10="","",IF(I10="","To send","Sent")) | K10: Ask about the cake | M10: =IF(B10="",0,IF(E10="",1,N(E10))) | N10: =IF(B10="",0,N(F10)) | O10: =IF(B10="","",IF(D10="","No answer",D10))
B11: The Brandt family | C11: School | D11: Maybe | E11: 2 | F11: 1 | J11: =IF(H11="","",IF(I11="","To send","Sent")) | M11: =IF(B11="",0,IF(E11="",1,N(E11))) | N11: =IF(B11="",0,N(F11)) | O11: =IF(B11="","",IF(D11="","No answer",D11))
B12: The Varga family | C12: School | D12: Yes | E12: 2 | F12: 1 | J12: =IF(H12="","",IF(I12="","To send","Sent")) | M12: =IF(B12="",0,IF(E12="",1,N(E12))) | N12: =IF(B12="",0,N(F12)) | O12: =IF(B12="","",IF(D12="","No answer",D12))
B13: The Castell family | C13: School | D13: Yes | E13: 1 | F13: 2 | G13: Gluten free | J13: =IF(H13="","",IF(I13="","To send","Sent")) | M13: =IF(B13="",0,IF(E13="",1,N(E13))) | N13: =IF(B13="",0,N(F13)) | O13: =IF(B13="","",IF(D13="","No answer",D13))
B14: The Holloway family | C14: School | D14: No | E14: 2 | F14: 1 | H14: Gift card | J14: =IF(H14="","",IF(I14="","To send","Sent")) | M14: =IF(B14="",0,IF(E14="",1,N(E14))) | N14: =IF(B14="",0,N(F14)) | O14: =IF(B14="","",IF(D14="","No answer",D14))
B15: The Quill family | C15: School | E15: 2 | F15: 1 | J15: =IF(H15="","",IF(I15="","To send","Sent")) | M15: =IF(B15="",0,IF(E15="",1,N(E15))) | N15: =IF(B15="",0,N(F15)) | O15: =IF(B15="","",IF(D15="","No answer",D15))
B16: The Rook family | C16: School | D16: Yes | E16: 2 | F16: 1 | J16: =IF(H16="","",IF(I16="","To send","Sent")) | M16: =IF(B16="",0,IF(E16="",1,N(E16))) | N16: =IF(B16="",0,N(F16)) | O16: =IF(B16="","",IF(D16="","No answer",D16))
B17: The Ashby family | C17: School | E17: 1 | F17: 1 | J17: =IF(H17="","",IF(I17="","To send","Sent")) | M17: =IF(B17="",0,IF(E17="",1,N(E17))) | N17: =IF(B17="",0,N(F17)) | O17: =IF(B17="","",IF(D17="","No answer",D17))
B18: Nadia and Sam | C18: Friends | D18: Yes | E18: 2 | F18: 0 | G18: Vegan | J18: =IF(H18="","",IF(I18="","To send","Sent")) | M18: =IF(B18="",0,IF(E18="",1,N(E18))) | N18: =IF(B18="",0,N(F18)) | O18: =IF(B18="","",IF(D18="","No answer",D18))
B19: Iris | C19: Friends | D19: Yes | E19: 1 | F19: 0 | J19: =IF(H19="","",IF(I19="","To send","Sent")) | K19: Can help with the games | M19: =IF(B19="",0,IF(E19="",1,N(E19))) | N19: =IF(B19="",0,N(F19)) | O19: =IF(B19="","",IF(D19="","No answer",D19))
B20: Tomas and Ines | C20: Friends | D20: Maybe | E20: 2 | F20: 1 | J20: =IF(H20="","",IF(I20="","To send","Sent")) | M20: =IF(B20="",0,IF(E20="",1,N(E20))) | N20: =IF(B20="",0,N(F20)) | O20: =IF(B20="","",IF(D20="","No answer",D20))
B21: The Marlowe family | C21: Neighbours | D21: Yes | E21: 2 | F21: 2 | J21: =IF(H21="","",IF(I21="","To send","Sent")) | M21: =IF(B21="",0,IF(E21="",1,N(E21))) | N21: =IF(B21="",0,N(F21)) | O21: =IF(B21="","",IF(D21="","No answer",D21))
B22: Mr and Mrs Thorne | C22: Neighbours | E22: 2 | F22: 0 | J22: =IF(H22="","",IF(I22="","To send","Sent")) | M22: =IF(B22="",0,IF(E22="",1,N(E22))) | N22: =IF(B22="",0,N(F22)) | O22: =IF(B22="","",IF(D22="","No answer",D22))
B23: Coach Wren | C23: Other | D23: Yes | E23: 1 | F23: 0 | G23: Dairy free | J23: =IF(H23="","",IF(I23="","To send","Sent")) | M23: =IF(B23="",0,IF(E23="",1,N(E23))) | N23: =IF(B23="",0,N(F23)) | O23: =IF(B23="","",IF(D23="","No answer",D23))
B24: The Fennimore family | C24: School | D24: Yes | E24: 2 | F24: 1 | J24: =IF(H24="","",IF(I24="","To send","Sent")) | M24: =IF(B24="",0,IF(E24="",1,N(E24))) | N24: =IF(B24="",0,N(F24)) | O24: =IF(B24="","",IF(D24="","No answer",D24))
B25: Jude | C25: Friends | E25: 1 | F25: 0 | J25: =IF(H25="","",IF(I25="","To send","Sent")) | M25: =IF(B25="",0,IF(E25="",1,N(E25))) | N25: =IF(B25="",0,N(F25)) | O25: =IF(B25="","",IF(D25="","No answer",D25))
J26: =IF(H26="","",IF(I26="","To send","Sent")) | M26: =IF(B26="",0,IF(E26="",1,N(E26))) | N26: =IF(B26="",0,N(F26)) | O26: =IF(B26="","",IF(D26="","No answer",D26))
J27: =IF(H27="","",IF(I27="","To send","Sent")) | M27: =IF(B27="",0,IF(E27="",1,N(E27))) | N27: =IF(B27="",0,N(F27)) | O27: =IF(B27="","",IF(D27="","No answer",D27))
J28: =IF(H28="","",IF(I28="","To send","Sent")) | M28: =IF(B28="",0,IF(E28="",1,N(E28))) | N28: =IF(B28="",0,N(F28)) | O28: =IF(B28="","",IF(D28="","No answer",D28))
J29: =IF(H29="","",IF(I29="","To send","Sent")) | M29: =IF(B29="",0,IF(E29="",1,N(E29))) | N29: =IF(B29="",0,N(F29)) | O29: =IF(B29="","",IF(D29="","No answer",D29))
J30: =IF(H30="","",IF(I30="","To send","Sent")) | M30: =IF(B30="",0,IF(E30="",1,N(E30))) | N30: =IF(B30="",0,N(F30)) | O30: =IF(B30="","",IF(D30="","No answer",D30))
J31: =IF(H31="","",IF(I31="","To send","Sent")) | M31: =IF(B31="",0,IF(E31="",1,N(E31))) | N31: =IF(B31="",0,N(F31)) | O31: =IF(B31="","",IF(D31="","No answer",D31))
J32: =IF(H32="","",IF(I32="","To send","Sent")) | M32: =IF(B32="",0,IF(E32="",1,N(E32))) | N32: =IF(B32="",0,N(F32)) | O32: =IF(B32="","",IF(D32="","No answer",D32))
J33: =IF(H33="","",IF(I33="","To send","Sent")) | M33: =IF(B33="",0,IF(E33="",1,N(E33))) | N33: =IF(B33="",0,N(F33)) | O33: =IF(B33="","",IF(D33="","No answer",D33))
J34: =IF(H34="","",IF(I34="","To send","Sent")) | M34: =IF(B34="",0,IF(E34="",1,N(E34))) | N34: =IF(B34="",0,N(F34)) | O34: =IF(B34="","",IF(D34="","No answer",D34))
J35: =IF(H35="","",IF(I35="","To send","Sent")) | M35: =IF(B35="",0,IF(E35="",1,N(E35))) | N35: =IF(B35="",0,N(F35)) | O35: =IF(B35="","",IF(D35="","No answer",D35))
J36: =IF(H36="","",IF(I36="","To send","Sent")) | M36: =IF(B36="",0,IF(E36="",1,N(E36))) | N36: =IF(B36="",0,N(F36)) | O36: =IF(B36="","",IF(D36="","No answer",D36))
J37: =IF(H37="","",IF(I37="","To send","Sent")) | M37: =IF(B37="",0,IF(E37="",1,N(E37))) | N37: =IF(B37="",0,N(F37)) | O37: =IF(B37="","",IF(D37="","No answer",D37))
... J305: =IF(H305="","",IF(I305="","To send","Sent")) | M305: =IF(B305="",0,IF(E305="",1,N(E305))) | N305: =IF(B305="",0,N(F305)) | O305: =IF(B305="","",IF(D305="","No answer",D305))

Sheet Tasks
B2: Tasks
B3: The checklist, counted back from the day of the party. Change the days before and the dates follow. 0 is the day itself, and a minus number is after it.
B5: Task | C5: Days before | D5: Date | E5: Who | F5: Done | G5: Status | H5: Notes
B6: Set the date, the time and the budget | C6: 56 | D6: =IF(OR(B6="",C6="",Dashboard!$C$5=""),"",Dashboard!$C$5-C6) | E6: Mum | F6: x | G6: =IF(B6="","",IF(F6<>"","Done",IF(D6="","",IF(D6<TODAY(),"Late",IF(D6-TODAY()<=7,"This week","Coming"))))) | J6: =IF(AND(B6<>"",F6="",D6<>""),D6+ROW()/10000000,"")
B7: Book the venue | C7: 56 | D7: =IF(OR(B7="",C7="",Dashboard!$C$5=""),"",Dashboard!$C$5-C7) | E7: Mum | F7: x | G7: =IF(B7="","",IF(F7<>"","Done",IF(D7="","",IF(D7<TODAY(),"Late",IF(D7-TODAY()<=7,"This week","Coming"))))) | J7: =IF(AND(B7<>"",F7="",D7<>""),D7+ROW()/10000000,"")
B8: Make the guest list | C8: 49 | D8: =IF(OR(B8="",C8="",Dashboard!$C$5=""),"",Dashboard!$C$5-C8) | E8: Mum and Dad | F8: x | G8: =IF(B8="","",IF(F8<>"","Done",IF(D8="","",IF(D8<TODAY(),"Late",IF(D8-TODAY()<=7,"This week","Coming"))))) | J8: =IF(AND(B8<>"",F8="",D8<>""),D8+ROW()/10000000,"")
B9: Send the invitations | C9: 42 | D9: =IF(OR(B9="",C9="",Dashboard!$C$5=""),"",Dashboard!$C$5-C9) | E9: Dad | F9: x | G9: =IF(B9="","",IF(F9<>"","Done",IF(D9="","",IF(D9<TODAY(),"Late",IF(D9-TODAY()<=7,"This week","Coming"))))) | J9: =IF(AND(B9<>"",F9="",D9<>""),D9+ROW()/10000000,"")
B10: Book the entertainment | C10: 42 | D10: =IF(OR(B10="",C10="",Dashboard!$C$5=""),"",Dashboard!$C$5-C10) | E10: Dad | F10: x | G10: =IF(B10="","",IF(F10<>"","Done",IF(D10="","",IF(D10<TODAY(),"Late",IF(D10-TODAY()<=7,"This week","Coming"))))) | J10: =IF(AND(B10<>"",F10="",D10<>""),D10+ROW()/10000000,"")
B11: Order the cake | C11: 35 | D11: =IF(OR(B11="",C11="",Dashboard!$C$5=""),"",Dashboard!$C$5-C11) | E11: Mum | F11: x | G11: =IF(B11="","",IF(F11<>"","Done",IF(D11="","",IF(D11<TODAY(),"Late",IF(D11-TODAY()<=7,"This week","Coming"))))) | J11: =IF(AND(B11<>"",F11="",D11<>""),D11+ROW()/10000000,"")
B12: Choose a theme and decorations | C12: 35 | D12: =IF(OR(B12="",C12="",Dashboard!$C$5=""),"",Dashboard!$C$5-C12) | E12: Mia and Mum | F12: x | G12: =IF(B12="","",IF(F12<>"","Done",IF(D12="","",IF(D12<TODAY(),"Late",IF(D12-TODAY()<=7,"This week","Coming"))))) | J12: =IF(AND(B12<>"",F12="",D12<>""),D12+ROW()/10000000,"")
B13: Plan the menu | C13: 30 | D13: =IF(OR(B13="",C13="",Dashboard!$C$5=""),"",Dashboard!$C$5-C13) | E13: Dad | F13: x | G13: =IF(B13="","",IF(F13<>"","Done",IF(D13="","",IF(D13<TODAY(),"Late",IF(D13-TODAY()<=7,"This week","Coming"))))) | J13: =IF(AND(B13<>"",F13="",D13<>""),D13+ROW()/10000000,"")
B14: Order the party bags | C14: 35 | D14: =IF(OR(B14="",C14="",Dashboard!$C$5=""),"",Dashboard!$C$5-C14) | E14: Mum | G14: =IF(B14="","",IF(F14<>"","Done",IF(D14="","",IF(D14<TODAY(),"Late",IF(D14-TODAY()<=7,"This week","Coming"))))) | J14: =IF(AND(B14<>"",F14="",D14<>""),D14+ROW()/10000000,"")
B15: Book a face painter | C15: 28 | D15: =IF(OR(B15="",C15="",Dashboard!$C$5=""),"",Dashboard!$C$5-C15) | E15: Mum | F15: x | G15: =IF(B15="","",IF(F15<>"","Done",IF(D15="","",IF(D15<TODAY(),"Late",IF(D15-TODAY()<=7,"This week","Coming"))))) | J15: =IF(AND(B15<>"",F15="",D15<>""),D15+ROW()/10000000,"")
B16: Rent extra tables and chairs | C16: 21 | D16: =IF(OR(B16="",C16="",Dashboard!$C$5=""),"",Dashboard!$C$5-C16) | E16: Dad | G16: =IF(B16="","",IF(F16<>"","Done",IF(D16="","",IF(D16<TODAY(),"Late",IF(D16-TODAY()<=7,"This week","Coming"))))) | J16: =IF(AND(B16<>"",F16="",D16<>""),D16+ROW()/10000000,"")
B17: Follow up on the answers | C17: 21 | D17: =IF(OR(B17="",C17="",Dashboard!$C$5=""),"",Dashboard!$C$5-C17) | E17: Mum | G17: =IF(B17="","",IF(F17<>"","Done",IF(D17="","",IF(D17<TODAY(),"Late",IF(D17-TODAY()<=7,"This week","Coming"))))) | J17: =IF(AND(B17<>"",F17="",D17<>""),D17+ROW()/10000000,"")
B18: Plan the games and the music | C18: 18 | D18: =IF(OR(B18="",C18="",Dashboard!$C$5=""),"",Dashboard!$C$5-C18) | E18: Iris | G18: =IF(B18="","",IF(F18<>"","Done",IF(D18="","",IF(D18<TODAY(),"Late",IF(D18-TODAY()<=7,"This week","Coming"))))) | J18: =IF(AND(B18<>"",F18="",D18<>""),D18+ROW()/10000000,"")
B19: Buy balloons and a banner | C19: 14 | D19: =IF(OR(B19="",C19="",Dashboard!$C$5=""),"",Dashboard!$C$5-C19) | E19: Dad | G19: =IF(B19="","",IF(F19<>"","Done",IF(D19="","",IF(D19<TODAY(),"Late",IF(D19-TODAY()<=7,"This week","Coming"))))) | J19: =IF(AND(B19<>"",F19="",D19<>""),D19+ROW()/10000000,"")
B20: Confirm the entertainment | C20: 14 | D20: =IF(OR(B20="",C20="",Dashboard!$C$5=""),"",Dashboard!$C$5-C20) | E20: Dad | G20: =IF(B20="","",IF(F20<>"","Done",IF(D20="","",IF(D20<TODAY(),"Late",IF(D20-TODAY()<=7,"This week","Coming"))))) | J20: =IF(AND(B20<>"",F20="",D20<>""),D20+ROW()/10000000,"")
B21: Make the plan for the day | C21: 12 | D21: =IF(OR(B21="",C21="",Dashboard!$C$5=""),"",Dashboard!$C$5-C21) | E21: Mum | G21: =IF(B21="","",IF(F21<>"","Done",IF(D21="","",IF(D21<TODAY(),"Late",IF(D21-TODAY()<=7,"This week","Coming"))))) | J21: =IF(AND(B21<>"",F21="",D21<>""),D21+ROW()/10000000,"")
B22: Final guest count for the food | C22: 10 | D22: =IF(OR(B22="",C22="",Dashboard!$C$5=""),"",Dashboard!$C$5-C22) | E22: Mum | G22: =IF(B22="","",IF(F22<>"","Done",IF(D22="","",IF(D22<TODAY(),"Late",IF(D22-TODAY()<=7,"This week","Coming"))))) | J22: =IF(AND(B22<>"",F22="",D22<>""),D22+ROW()/10000000,"")
B23: Shop for drinks and snacks | C23: 7 | D23: =IF(OR(B23="",C23="",Dashboard!$C$5=""),"",Dashboard!$C$5-C23) | E23: Dad | G23: =IF(B23="","",IF(F23<>"","Done",IF(D23="","",IF(D23<TODAY(),"Late",IF(D23-TODAY()<=7,"This week","Coming"))))) | J23: =IF(AND(B23<>"",F23="",D23<>""),D23+ROW()/10000000,"")
B24: Confirm the venue and the cake | C24: 7 | D24: =IF(OR(B24="",C24="",Dashboard!$C$5=""),"",Dashboard!$C$5-C24) | E24: Mum | G24: =IF(B24="","",IF(F24<>"","Done",IF(D24="","",IF(D24<TODAY(),"Late",IF(D24-TODAY()<=7,"This week","Coming"))))) | J24: =IF(AND(B24<>"",F24="",D24<>""),D24+ROW()/10000000,"")
B25: Ask helpers for a job each | C25: 5 | D25: =IF(OR(B25="",C25="",Dashboard!$C$5=""),"",Dashboard!$C$5-C25) | E25: Mum | G25: =IF(B25="","",IF(F25<>"","Done",IF(D25="","",IF(D25<TODAY(),"Late",IF(D25-TODAY()<=7,"This week","Coming"))))) | J25: =IF(AND(B25<>"",F25="",D25<>""),D25+ROW()/10000000,"")
B26: Charge the camera and the speaker | C26: 2 | D26: =IF(OR(B26="",C26="",Dashboard!$C$5=""),"",Dashboard!$C$5-C26) | E26: Dad | G26: =IF(B26="","",IF(F26<>"","Done",IF(D26="","",IF(D26<TODAY(),"Late",IF(D26-TODAY()<=7,"This week","Coming"))))) | J26: =IF(AND(B26<>"",F26="",D26<>""),D26+ROW()/10000000,"")
B27: Buy fresh food and ice | C27: 1 | D27: =IF(OR(B27="",C27="",Dashboard!$C$5=""),"",Dashboard!$C$5-C27) | E27: Dad | G27: =IF(B27="","",IF(F27<>"","Done",IF(D27="","",IF(D27<TODAY(),"Late",IF(D27-TODAY()<=7,"This week","Coming"))))) | J27: =IF(AND(B27<>"",F27="",D27<>""),D27+ROW()/10000000,"")
... B32: Share the photos | C32: -4 | D32: =IF(OR(B32="",C32="",Dashboard!$C$5=""),"",Dashboard!$C$5-C32) | E32: Mum | G32: =IF(B32="","",IF(F32<>"","Done",IF(D32="","",IF(D32<TODAY(),"Late",IF(D32-TODAY()<=7,"This week","Coming"))))) | J32: =IF(AND(B32<>"",F32="",D32<>""),D32+ROW()/10000000,"")
D33: =IF(OR(B33="",C33="",Dashboard!$C$5=""),"",Dashboard!$C$5-C33) | G33: =IF(B33="","",IF(F33<>"","Done",IF(D33="","",IF(D33<TODAY(),"Late",IF(D33-TODAY()<=7,"This week","Coming"))))) | J33: =IF(AND(B33<>"",F33="",D33<>""),D33+ROW()/10000000,"")
D34: =IF(OR(B34="",C34="",Dashboard!$C$5=""),"",Dashboard!$C$5-C34) | G34: =IF(B34="","",IF(F34<>"","Done",IF(D34="","",IF(D34<TODAY(),"Late",IF(D34-TODAY()<=7,"This week","Coming"))))) | J34: =IF(AND(B34<>"",F34="",D34<>""),D34+ROW()/10000000,"")
D35: =IF(OR(B35="",C35="",Dashboard!$C$5=""),"",Dashboard!$C$5-C35) | G35: =IF(B35="","",IF(F35<>"","Done",IF(D35="","",IF(D35<TODAY(),"Late",IF(D35-TODAY()<=7,"This week","Coming"))))) | J35: =IF(AND(B35<>"",F35="",D35<>""),D35+ROW()/10000000,"")
D36: =IF(OR(B36="",C36="",Dashboard!$C$5=""),"",Dashboard!$C$5-C36) | G36: =IF(B36="","",IF(F36<>"","Done",IF(D36="","",IF(D36<TODAY(),"Late",IF(D36-TODAY()<=7,"This week","Coming"))))) | J36: =IF(AND(B36<>"",F36="",D36<>""),D36+ROW()/10000000,"")
D37: =IF(OR(B37="",C37="",Dashboard!$C$5=""),"",Dashboard!$C$5-C37) | G37: =IF(B37="","",IF(F37<>"","Done",IF(D37="","",IF(D37<TODAY(),"Late",IF(D37-TODAY()<=7,"This week","Coming"))))) | J37: =IF(AND(B37<>"",F37="",D37<>""),D37+ROW()/10000000,"")
D38: =IF(OR(B38="",C38="",Dashboard!$C$5=""),"",Dashboard!$C$5-C38) | G38: =IF(B38="","",IF(F38<>"","Done",IF(D38="","",IF(D38<TODAY(),"Late",IF(D38-TODAY()<=7,"This week","Coming"))))) | J38: =IF(AND(B38<>"",F38="",D38<>""),D38+ROW()/10000000,"")
D39: =IF(OR(B39="",C39="",Dashboard!$C$5=""),"",Dashboard!$C$5-C39) | G39: =IF(B39="","",IF(F39<>"","Done",IF(D39="","",IF(D39<TODAY(),"Late",IF(D39-TODAY()<=7,"This week","Coming"))))) | J39: =IF(AND(B39<>"",F39="",D39<>""),D39+ROW()/10000000,"")
D40: =IF(OR(B40="",C40="",Dashboard!$C$5=""),"",Dashboard!$C$5-C40) | G40: =IF(B40="","",IF(F40<>"","Done",IF(D40="","",IF(D40<TODAY(),"Late",IF(D40-TODAY()<=7,"This week","Coming"))))) | J40: =IF(AND(B40<>"",F40="",D40<>""),D40+ROW()/10000000,"")
D41: =IF(OR(B41="",C41="",Dashboard!$C$5=""),"",Dashboard!$C$5-C41) | G41: =IF(B41="","",IF(F41<>"","Done",IF(D41="","",IF(D41<TODAY(),"Late",IF(D41-TODAY()<=7,"This week","Coming"))))) | J41: =IF(AND(B41<>"",F41="",D41<>""),D41+ROW()/10000000,"")
D42: =IF(OR(B42="",C42="",Dashboard!$C$5=""),"",Dashboard!$C$5-C42) | G42: =IF(B42="","",IF(F42<>"","Done",IF(D42="","",IF(D42<TODAY(),"Late",IF(D42-TODAY()<=7,"This week","Coming"))))) | J42: =IF(AND(B42<>"",F42="",D42<>""),D42+ROW()/10000000,"")
D43: =IF(OR(B43="",C43="",Dashboard!$C$5=""),"",Dashboard!$C$5-C43) | G43: =IF(B43="","",IF(F43<>"","Done",IF(D43="","",IF(D43<TODAY(),"Late",IF(D43-TODAY()<=7,"This week","Coming"))))) | J43: =IF(AND(B43<>"",F43="",D43<>""),D43+ROW()/10000000,"")
D44: =IF(OR(B44="",C44="",Dashboard!$C$5=""),"",Dashboard!$C$5-C44) | G44: =IF(B44="","",IF(F44<>"","Done",IF(D44="","",IF(D44<TODAY(),"Late",IF(D44-TODAY()<=7,"This week","Coming"))))) | J44: =IF(AND(B44<>"",F44="",D44<>""),D44+ROW()/10000000,"")
... D65: =IF(OR(B65="",C65="",Dashboard!$C$5=""),"",Dashboard!$C$5-C65) | G65: =IF(B65="","",IF(F65<>"","Done",IF(D65="","",IF(D65<TODAY(),"Late",IF(D65-TODAY()<=7,"This week","Coming"))))) | J65: =IF(AND(B65<>"",F65="",D65<>""),D65+ROW()/10000000,"")

Sheet Food and drinks
B2: Food and drinks
B3: How much to buy, for everyone who may come: the yes, the maybe and those who have not answered. Amounts per person are for the whole party.
B4: Adults | C4: =SUMIFS(Guests!$M$6:$M$305,Guests!$D$6:$D$305,"<>No") | E4: Extra, to be safe | G4: 0.1 | I4: A common rule for drinks: one per guest for each hour, and one more.
B5: Kids | C5: =SUMIFS(Guests!$N$6:$N$305,Guests!$D$6:$D$305,"<>No") | I5: Needed and packs round up, so there is always enough.
B7: Item | C7: Kind | D7: Per adult | E7: Per kid | F7: Unit | G7: Needed | H7: Pack of | I7: Packs | J7: Price a pack | K7: Cost | L7: Bought | M7: Where
B8: Pizza | C8: Food | D8: 2 | E8: 2 | F8: slices | G8: =IF(B8="","",ROUNDUP(ROUND((N(D8)*$C$4+N(E8)*$C$5)*(1+N($G$4)),6),0)) | H8: 8 | I8: =IF(OR(G8="",N(H8)=0),"",ROUNDUP(ROUND(G8/H8,6),0)) | J8: 11 | K8: =IF(OR(I8="",J8=""),"",I8*J8)
B9: Wraps and sandwiches | C9: Food | D9: 1 | E9: 0.5 | F9: pieces | G9: =IF(B9="","",ROUNDUP(ROUND((N(D9)*$C$4+N(E9)*$C$5)*(1+N($G$4)),6),0)) | H9: 12 | I9: =IF(OR(G9="",N(H9)=0),"",ROUNDUP(ROUND(G9/H9,6),0)) | J9: 12 | K9: =IF(OR(I9="",J9=""),"",I9*J9)
B10: Crisps and snacks | C10: Food | D10: 0.5 | E10: 0.5 | F10: bags | G10: =IF(B10="","",ROUNDUP(ROUND((N(D10)*$C$4+N(E10)*$C$5)*(1+N($G$4)),6),0)) | H10: 6 | I10: =IF(OR(G10="",N(H10)=0),"",ROUNDUP(ROUND(G10/H10,6),0)) | J10: 3.2 | K10: =IF(OR(I10="",J10=""),"",I10*J10) | L10: x
B11: Fruit platter | C11: Food | D11: 0.5 | E11: 1 | F11: portions | G11: =IF(B11="","",ROUNDUP(ROUND((N(D11)*$C$4+N(E11)*$C$5)*(1+N($G$4)),6),0)) | H11: 12 | I11: =IF(OR(G11="",N(H11)=0),"",ROUNDUP(ROUND(G11/H11,6),0)) | J11: 10 | K11: =IF(OR(I11="",J11=""),"",I11*J11)
B12: Veggies and dip | C12: Food | D12: 0.3 | E12: 0.2 | F12: portions | G12: =IF(B12="","",ROUNDUP(ROUND((N(D12)*$C$4+N(E12)*$C$5)*(1+N($G$4)),6),0)) | H12: 10 | I12: =IF(OR(G12="",N(H12)=0),"",ROUNDUP(ROUND(G12/H12,6),0)) | J12: 9.5 | K12: =IF(OR(I12="",J12=""),"",I12*J12)
B13: Soft drinks | C13: Drinks | D13: 2 | E13: 1 | F13: cans | G13: =IF(B13="","",ROUNDUP(ROUND((N(D13)*$C$4+N(E13)*$C$5)*(1+N($G$4)),6),0)) | H13: 24 | I13: =IF(OR(G13="",N(H13)=0),"",ROUNDUP(ROUND(G13/H13,6),0)) | J13: 11 | K13: =IF(OR(I13="",J13=""),"",I13*J13) | L13: x
B14: Juice boxes | C14: Drinks | D14: 0 | E14: 2 | F14: boxes | G14: =IF(B14="","",ROUNDUP(ROUND((N(D14)*$C$4+N(E14)*$C$5)*(1+N($G$4)),6),0)) | H14: 10 | I14: =IF(OR(G14="",N(H14)=0),"",ROUNDUP(ROUND(G14/H14,6),0)) | J14: 4.5 | K14: =IF(OR(I14="",J14=""),"",I14*J14) | L14: x
B15: Water | C15: Drinks | D15: 1 | E15: 1 | F15: bottles | G15: =IF(B15="","",ROUNDUP(ROUND((N(D15)*$C$4+N(E15)*$C$5)*(1+N($G$4)),6),0)) | H15: 24 | I15: =IF(OR(G15="",N(H15)=0),"",ROUNDUP(ROUND(G15/H15,6),0)) | J15: 5 | K15: =IF(OR(I15="",J15=""),"",I15*J15)
B16: Coffee and tea | C16: Drinks | D16: 1 | E16: 0 | F16: cups | G16: =IF(B16="","",ROUNDUP(ROUND((N(D16)*$C$4+N(E16)*$C$5)*(1+N($G$4)),6),0)) | H16: 40 | I16: =IF(OR(G16="",N(H16)=0),"",ROUNDUP(ROUND(G16/H16,6),0)) | J16: 7.5 | K16: =IF(OR(I16="",J16=""),"",I16*J16)
B17: Ice | C17: Drinks | D17: 0.05 | E17: 0.05 | F17: bags | G17: =IF(B17="","",ROUNDUP(ROUND((N(D17)*$C$4+N(E17)*$C$5)*(1+N($G$4)),6),0)) | H17: 1 | I17: =IF(OR(G17="",N(H17)=0),"",ROUNDUP(ROUND(G17/H17,6),0)) | J17: 2.5 | K17: =IF(OR(I17="",J17=""),"",I17*J17)
B18: Plates | C18: Supplies | D18: 2 | E18: 2 | F18: plates | G18: =IF(B18="","",ROUNDUP(ROUND((N(D18)*$C$4+N(E18)*$C$5)*(1+N($G$4)),6),0)) | H18: 50 | I18: =IF(OR(G18="",N(H18)=0),"",ROUNDUP(ROUND(G18/H18,6),0)) | J18: 4 | K18: =IF(OR(I18="",J18=""),"",I18*J18) | L18: x
B19: Cups | C19: Supplies | D19: 3 | E19: 3 | F19: cups | G19: =IF(B19="","",ROUNDUP(ROUND((N(D19)*$C$4+N(E19)*$C$5)*(1+N($G$4)),6),0)) | H19: 50 | I19: =IF(OR(G19="",N(H19)=0),"",ROUNDUP(ROUND(G19/H19,6),0)) | J19: 3.5 | K19: =IF(OR(I19="",J19=""),"",I19*J19) | L19: x
B20: Napkins | C20: Supplies | D20: 3 | E20: 3 | F20: napkins | G20: =IF(B20="","",ROUNDUP(ROUND((N(D20)*$C$4+N(E20)*$C$5)*(1+N($G$4)),6),0)) | H20: 100 | I20: =IF(OR(G20="",N(H20)=0),"",ROUNDUP(ROUND(G20/H20,6),0)) | J20: 2.5 | K20: =IF(OR(I20="",J20=""),"",I20*J20) | L20: x
G21: =IF(B21="","",ROUNDUP(ROUND((N(D21)*$C$4+N(E21)*$C$5)*(1+N($G$4)),6),0)) | I21: =IF(OR(G21="",N(H21)=0),"",ROUNDUP(ROUND(G21/H21,6),0)) | K21: =IF(OR(I21="",J21=""),"",I21*J21)
G22: =IF(B22="","",ROUNDUP(ROUND((N(D22)*$C$4+N(E22)*$C$5)*(1+N($G$4)),6),0)) | I22: =IF(OR(G22="",N(H22)=0),"",ROUNDUP(ROUND(G22/H22,6),0)) | K22: =IF(OR(I22="",J22=""),"",I22*J22)
G23: =IF(B23="","",ROUNDUP(ROUND((N(D23)*$C$4+N(E23)*$C$5)*(1+N($G$4)),6),0)) | I23: =IF(OR(G23="",N(H23)=0),"",ROUNDUP(ROUND(G23/H23,6),0)) | K23: =IF(OR(I23="",J23=""),"",I23*J23)
G24: =IF(B24="","",ROUNDUP(ROUND((N(D24)*$C$4+N(E24)*$C$5)*(1+N($G$4)),6),0)) | I24: =IF(OR(G24="",N(H24)=0),"",ROUNDUP(ROUND(G24/H24,6),0)) | K24: =IF(OR(I24="",J24=""),"",I24*J24)
G25: =IF(B25="","",ROUNDUP(ROUND((N(D25)*$C$4+N(E25)*$C$5)*(1+N($G$4)),6),0)) | I25: =IF(OR(G25="",N(H25)=0),"",ROUNDUP(ROUND(G25/H25,6),0)) | K25: =IF(OR(I25="",J25=""),"",I25*J25)
G26: =IF(B26="","",ROUNDUP(ROUND((N(D26)*$C$4+N(E26)*$C$5)*(1+N($G$4)),6),0)) | I26: =IF(OR(G26="",N(H26)=0),"",ROUNDUP(ROUND(G26/H26,6),0)) | K26: =IF(OR(I26="",J26=""),"",I26*J26)
G27: =IF(B27="","",ROUNDUP(ROUND((N(D27)*$C$4+N(E27)*$C$5)*(1+N($G$4)),6),0)) | I27: =IF(OR(G27="",N(H27)=0),"",ROUNDUP(ROUND(G27/H27,6),0)) | K27: =IF(OR(I27="",J27=""),"",I27*J27)
G28: =IF(B28="","",ROUNDUP(ROUND((N(D28)*$C$4+N(E28)*$C$5)*(1+N($G$4)),6),0)) | I28: =IF(OR(G28="",N(H28)=0),"",ROUNDUP(ROUND(G28/H28,6),0)) | K28: =IF(OR(I28="",J28=""),"",I28*J28)
G29: =IF(B29="","",ROUNDUP(ROUND((N(D29)*$C$4+N(E29)*$C$5)*(1+N($G$4)),6),0)) | I29: =IF(OR(G29="",N(H29)=0),"",ROUNDUP(ROUND(G29/H29,6),0)) | K29: =IF(OR(I29="",J29=""),"",I29*J29)
G30: =IF(B30="","",ROUNDUP(ROUND((N(D30)*$C$4+N(E30)*$C$5)*(1+N($G$4)),6),0)) | I30: =IF(OR(G30="",N(H30)=0),"",ROUNDUP(ROUND(G30/H30,6),0)) | K30: =IF(OR(I30="",J30=""),"",I30*J30)
G31: =IF(B31="","",ROUNDUP(ROUND((N(D31)*$C$4+N(E31)*$C$5)*(1+N($G$4)),6),0)) | I31: =IF(OR(G31="",N(H31)=0),"",ROUNDUP(ROUND(G31/H31,6),0)) | K31: =IF(OR(I31="",J31=""),"",I31*J31)
G32: =IF(B32="","",ROUNDUP(ROUND((N(D32)*$C$4+N(E32)*$C$5)*(1+N($G$4)),6),0)) | I32: =IF(OR(G32="",N(H32)=0),"",ROUNDUP(ROUND(G32/H32,6),0)) | K32: =IF(OR(I32="",J32=""),"",I32*J32)
... G47: =IF(B47="","",ROUNDUP(ROUND((N(D47)*$C$4+N(E47)*$C$5)*(1+N($G$4)),6),0)) | I47: =IF(OR(G47="",N(H47)=0),"",ROUNDUP(ROUND(G47/H47,6),0)) | K47: =IF(OR(I47="",J47=""),"",I47*J47)
B48: Total | K48: =SUM(K8:K47)

Sheet Budget
B2: Budget
B3: Everything you book or buy besides the food: what it costs, what you paid and when the rest is due.
B5: Item | C5: Category | D5: Shop or vendor | E5: Estimate | F5: Final price | G5: Paid | H5: Still to pay | I5: Pay by | J5: Status | K5: Notes
B6: Community hall, 3 hours | C6: Venue | D6: Rowan Street hall | E6: 180 | F6: 180 | G6: 50 | H6: =IF(B6="","",MAX(0,IF(F6<>"",F6,N(E6))-N(G6))) | I6: 46312 | J6: =IF(B6="","",IF(H6<=0,"Paid",IF(I6="","To pay",IF(I6<TODAY(),"Late",IF(I6-TODAY()<=7,"Due soon","To pay"))))) | M6: =IF(B6="",0,IF(F6<>"",F6,N(E6)))
B7: Unicorn cake, 24 slices | C7: Cake | D7: Corner bakery | E7: 60 | F7: 55 | G7: 20 | H7: =IF(B7="","",MAX(0,IF(F7<>"",F7,N(E7))-N(G7))) | I7: 46318 | J7: =IF(B7="","",IF(H7<=0,"Paid",IF(I7="","To pay",IF(I7<TODAY(),"Late",IF(I7-TODAY()<=7,"Due soon","To pay"))))) | M7: =IF(B7="",0,IF(F7<>"",F7,N(E7)))
B8: Balloons and a banner | C8: Decorations | D8: Party shop | E8: 45 | F8: 38.6 | G8: 38.6 | H8: =IF(B8="","",MAX(0,IF(F8<>"",F8,N(E8))-N(G8))) | J8: =IF(B8="","",IF(H8<=0,"Paid",IF(I8="","To pay",IF(I8<TODAY(),"Late",IF(I8-TODAY()<=7,"Due soon","To pay"))))) | M8: =IF(B8="",0,IF(F8<>"",F8,N(E8)))
B9: Magician, 45 minutes | C9: Entertainment | D9: Magic Max | E9: 150 | F9: 150 | G9: 0 | H9: =IF(B9="","",MAX(0,IF(F9<>"",F9,N(E9))-N(G9))) | I9: 46319 | J9: =IF(B9="","",IF(H9<=0,"Paid",IF(I9="","To pay",IF(I9<TODAY(),"Late",IF(I9-TODAY()<=7,"Due soon","To pay"))))) | M9: =IF(B9="",0,IF(F9<>"",F9,N(E9)))
B10: Face painting | C10: Entertainment | D10: Painted Faces | E10: 90 | F10: 90 | G10: 20 | H10: =IF(B10="","",MAX(0,IF(F10<>"",F10,N(E10))-N(G10))) | I10: 46319 | J10: =IF(B10="","",IF(H10<=0,"Paid",IF(I10="","To pay",IF(I10<TODAY(),"Late",IF(I10-TODAY()<=7,"Due soon","To pay"))))) | M10: =IF(B10="",0,IF(F10<>"",F10,N(E10)))
B11: Extra tables and chairs | C11: Rentals | D11: Hire shop | E11: 35 | G11: 0 | H11: =IF(B11="","",MAX(0,IF(F11<>"",F11,N(E11))-N(G11))) | I11: 46317 | J11: =IF(B11="","",IF(H11<=0,"Paid",IF(I11="","To pay",IF(I11<TODAY(),"Late",IF(I11-TODAY()<=7,"Due soon","To pay"))))) | M11: =IF(B11="",0,IF(F11<>"",F11,N(E11)))
B12: Printed invitations | C12: Invitations | D12: Print shop | E12: 18 | F12: 16.5 | G12: 16.5 | H12: =IF(B12="","",MAX(0,IF(F12<>"",F12,N(E12))-N(G12))) | J12: =IF(B12="","",IF(H12<=0,"Paid",IF(I12="","To pay",IF(I12<TODAY(),"Late",IF(I12-TODAY()<=7,"Due soon","To pay"))))) | M12: =IF(B12="",0,IF(F12<>"",F12,N(E12)))
B13: Party bags | C13: Favours | E13: 40 | G13: 0 | H13: =IF(B13="","",MAX(0,IF(F13<>"",F13,N(E13))-N(G13))) | I13: 46298 | J13: =IF(B13="","",IF(H13<=0,"Paid",IF(I13="","To pay",IF(I13<TODAY(),"Late",IF(I13-TODAY()<=7,"Due soon","To pay"))))) | M13: =IF(B13="",0,IF(F13<>"",F13,N(E13)))
H14: =IF(B14="","",MAX(0,IF(F14<>"",F14,N(E14))-N(G14))) | J14: =IF(B14="","",IF(H14<=0,"Paid",IF(I14="","To pay",IF(I14<TODAY(),"Late",IF(I14-TODAY()<=7,"Due soon","To pay"))))) | M14: =IF(B14="",0,IF(F14<>"",F14,N(E14)))
H15: =IF(B15="","",MAX(0,IF(F15<>"",F15,N(E15))-N(G15))) | J15: =IF(B15="","",IF(H15<=0,"Paid",IF(I15="","To pay",IF(I15<TODAY(),"Late",IF(I15-TODAY()<=7,"Due soon","To pay"))))) | M15: =IF(B15="",0,IF(F15<>"",F15,N(E15)))
H16: =IF(B16="","",MAX(0,IF(F16<>"",F16,N(E16))-N(G16))) | J16: =IF(B16="","",IF(H16<=0,"Paid",IF(I16="","To pay",IF(I16<TODAY(),"Late",IF(I16-TODAY()<=7,"Due soon","To pay"))))) | M16: =IF(B16="",0,IF(F16<>"",F16,N(E16)))
H17: =IF(B17="","",MAX(0,IF(F17<>"",F17,N(E17))-N(G17))) | J17: =IF(B17="","",IF(H17<=0,"Paid",IF(I17="","To pay",IF(I17<TODAY(),"Late",IF(I17-TODAY()<=7,"Due soon","To pay"))))) | M17: =IF(B17="",0,IF(F17<>"",F17,N(E17)))
H18: =IF(B18="","",MAX(0,IF(F18<>"",F18,N(E18))-N(G18))) | J18: =IF(B18="","",IF(H18<=0,"Paid",IF(I18="","To pay",IF(I18<TODAY(),"Late",IF(I18-TODAY()<=7,"Due soon","To pay"))))) | M18: =IF(B18="",0,IF(F18<>"",F18,N(E18)))
H19: =IF(B19="","",MAX(0,IF(F19<>"",F19,N(E19))-N(G19))) | J19: =IF(B19="","",IF(H19<=0,"Paid",IF(I19="","To pay",IF(I19<TODAY(),"Late",IF(I19-TODAY()<=7,"Due soon","To pay"))))) | M19: =IF(B19="",0,IF(F19<>"",F19,N(E19)))
H20: =IF(B20="","",MAX(0,IF(F20<>"",F20,N(E20))-N(G20))) | J20: =IF(B20="","",IF(H20<=0,"Paid",IF(I20="","To pay",IF(I20<TODAY(),"Late",IF(I20-TODAY()<=7,"Due soon","To pay"))))) | M20: =IF(B20="",0,IF(F20<>"",F20,N(E20)))
H21: =IF(B21="","",MAX(0,IF(F21<>"",F21,N(E21))-N(G21))) | J21: =IF(B21="","",IF(H21<=0,"Paid",IF(I21="","To pay",IF(I21<TODAY(),"Late",IF(I21-TODAY()<=7,"Due soon","To pay"))))) | M21: =IF(B21="",0,IF(F21<>"",F21,N(E21)))
H22: =IF(B22="","",MAX(0,IF(F22<>"",F22,N(E22))-N(G22))) | J22: =IF(B22="","",IF(H22<=0,"Paid",IF(I22="","To pay",IF(I22<TODAY(),"Late",IF(I22-TODAY()<=7,"Due soon","To pay"))))) | M22: =IF(B22="",0,IF(F22<>"",F22,N(E22)))
H23: =IF(B23="","",MAX(0,IF(F23<>"",F23,N(E23))-N(G23))) | J23: =IF(B23="","",IF(H23<=0,"Paid",IF(I23="","To pay",IF(I23<TODAY(),"Late",IF(I23-TODAY()<=7,"Due soon","To pay"))))) | M23: =IF(B23="",0,IF(F23<>"",F23,N(E23)))
H24: =IF(B24="","",MAX(0,IF(F24<>"",F24,N(E24))-N(G24))) | J24: =IF(B24="","",IF(H24<=0,"Paid",IF(I24="","To pay",IF(I24<TODAY(),"Late",IF(I24-TODAY()<=7,"Due soon","To pay"))))) | M24: =IF(B24="",0,IF(F24<>"",F24,N(E24)))
H25: =IF(B25="","",MAX(0,IF(F25<>"",F25,N(E25))-N(G25))) | J25: =IF(B25="","",IF(H25<=0,"Paid",IF(I25="","To pay",IF(I25<TODAY(),"Late",IF(I25-TODAY()<=7,"Due soon","To pay"))))) | M25: =IF(B25="",0,IF(F25<>"",F25,N(E25)))
... H55: =IF(B55="","",MAX(0,IF(F55<>"",F55,N(E55))-N(G55))) | J55: =IF(B55="","",IF(H55<=0,"Paid",IF(I55="","To pay",IF(I55<TODAY(),"Late",IF(I55-TODAY()<=7,"Due soon","To pay"))))) | M55: =IF(B55="",0,IF(F55<>"",F55,N(E55)))
B56: The final price counts once you know it. Until then the estimate does.

Sheet The day
B2: The day
B3: The plan for the party itself, hour by hour, and who looks after what.
B5: Time | C5: What happens | D5: Who | E5: Notes
B6: 0.52083333 | C6: Set up the room, balloons and tables | D6: Dad and Iris
B7: 0.5625 | C7: Food and drinks out, music on | D7: Dad
B8: 0.58333333 | C8: Guests arrive, face painting starts | D8: Mum
B9: 0.61458333 | C9: Games in the hall | D9: Iris
B10: 0.64583333 | C10: Magician | D10: Magic Max
B11: 0.67708333 | C11: Pizza and snacks | D11: Everyone
B12: 0.69791667 | C12: Cake and singing | D12: Mum
B13: 0.71875 | C13: Party bags and goodbyes | D13: Mia
B14: 0.72916667 | C14: Tidy up and return the hall key | D14: Dad

Sheet Start Here
B2: Start here
B3: Type only in the yellow cells. Everything else is calculated.
B5: 1 | C5: Dashboard: the name of the party, the date, the time it starts and your budget.
B7: 2 | C7: Guests: one line per guest or family, with their answer and how many adults and kids.
B9: 3 | C9: Tasks: a checklist is ready, counted back from the date. Put an x under Done as you go.
B11: 4 | C11: Food and drinks: how much each person eats or drinks, and the size and price of a pack. It says what to buy.
B13: 5 | C13: Budget and The day: what you book or buy, what you paid, and the plan for the party hour by hour.
C16: The example party, its guests and its shops are made up. Delete them and add your own.
C18: Change the date and every task date moves with it.
C20: Works in Google Sheets and Microsoft Excel, in any currency.
